Workbook
Name DataRef: Listas!$A$3
Name dem_q4_conclusao: LBE_Modelo!$B$54
Name dem_q4_melhoria: LBE_Modelo!$B$52
Name dom_x1_max: LBE_Modelo!$F$33
Name dom_x1_min: LBE_Modelo!$E$33
Name dom_x2_max: LBE_Modelo!$F$34
Name dom_x2_min: LBE_Modelo!$E$34
Name lbe_a: LBE_Modelo!$B$5
Name lbe_b1: LBE_Modelo!$B$6
Name lbe_b2: LBE_Modelo!$B$7
Name lbe_base_pct: LBE_Modelo!$B$20
Name lbe_cv: LBE_Modelo!$B$16
Name lbe_df: LBE_Modelo!$B$13
Name lbe_f: LBE_Modelo!$B$12
Name lbe_limite: LBE_Modelo!$B$19
Name lbe_nmbe: LBE_Modelo!$B$17
Name lbe_pf: LBE_Modelo!$B$14
Name lbe_r2: LBE_Modelo!$B$10
Name lbe_sey: LBE_Modelo!$B$11
Name lbe_t: LBE_Modelo!$B$18
Name lbe_ymed: LBE_Modelo!$B$15
Name lst_DataReferencia: Listas!$A$3:$A$3
Name lst_EstadoLBE: Listas!$F$3:$F$5
Name lst_EstadoPlano: Listas!$E$3:$E$7
Name lst_Funcao: Listas!$B$3:$B$24
Name lst_Periodo: Listas!$D$3:$D$4
Name lst_Polaridade: Listas!$C$3:$C$4
Name lst_TipoIDE: Listas!$G$3:$G$12
Name preco_medio: Parametros!$B$5

Sheet 00_LEIA-ME
A1: RG-SGE-05 — IDE, Linhas de Base Energéticas, Normalização, Objetivos, Metas e Planos de Ação
A2: Sistema de Gestão da Energia NP EN ISO 50001:2019 (ISO 50001:2018 + Amd 1:2024) · Plasticom — Unidade 1 (Marinha Grande, Portugal) · Registo do SGE (fábrica simulada)
A4: CONTROLO DO DOCUMENTO (7.5 — informação documentada)
A5: Código do registo | B5: RG-SGE-05
A6: Título | B6: IDE, Linhas de Base Energéticas, Normalização, Objetivos, Metas e Planos de Ação
A7: Versão / Revisão | B7: 01
A8: Data de emissão | B8: 46387
A9: Elaborado por | B9: Gestor(a) de Energia
A10: Aprovado por | B10: Diretor Geral
A11: Estado | B11: Em vigor
A12: Retenção | B12: 5 anos após substituição
A13: Localização | B13: Repositório controlado do SGE > Registos_SGE_Plasticom (a versão eletrónica é a controlada; cópias impressas são não controladas). Controlo da informação documentada comum ao SGI: PR-SGA-08 (7.5.3 — distribuição, acesso, versão, retenção).
A15: FINALIDADE E ÂMBITO
A16: Finalidade | B16: Base mensal de energia 2025-03 a 2026-12 (fonte única RG-SGA-13) com as variáveis relevantes; modelo estatístico da LBE-01 calculado por LINEST sobre 2025-03–2026-02 com testes de validade; IDE mensais por fórmula (esperado, diferença, CUSUM, domínio de validade); catálogo de IDE; registo das LBE e das suas alterações; fatores estáticos; objetivos, metas energéticas e planos de ação ligados aos IDE.
A17: Utilização / atividades | B17: Definir os indicadores de desempenho energético e as linhas de base; normalizar pelas variáveis relevantes; comparar os IDE com as LBE todos os meses; demonstrar (ou não) a melhoria do desempenho energético; estabelecer objetivos, metas energéticas e planos de ação.
A18: Requisitos ISO 50001:2018 | B18: 6.2.1 objetivos e metas energéticas; 6.2.2 a)–h) (reter); 6.2.3 planos de ação (o quê, recursos, quem, quando, como avaliar, método de verificação — reter); 6.4 IDE (metodologia mantida; valores retidos; considerar variáveis relevantes); 6.5 LBE (normalização; revisão nos casos a)–c); reter LBE, variáveis e modificações); 9.1.1 (melhoria avaliada comparando IDE com LBE); 5.1 l) (IDE representam o desempenho); 10.2 (demonstrar melhoria contínua do desempenho energético).
A20: NORMAS DE ORIENTAÇÃO E REFERÊNCIAS APLICADAS (orientação — não são requisitos auditáveis da ISO 50001)
A21: ISO 50006:2023 §5.2–5.3 e tabela 1 | B21: Utilizadores e fronteira de cada IDE (colunas Utilizadores e Fronteira do tbl_kpi).
A22: ISO 50006:2023 §6.2 (tipos de IDE) | B22: Valor medido (IDE-09), rácio (IDE-02 a 04, 06 a 08, 10) e modelo estatístico (IDE-01, IDE-05).
A23: ISO 50006:2023 §7.2 (período de referência) | B23: 12 meses (mar/2025–fev/2026) para cobrir o ciclo completo da temperatura; termina antes dos compressores VSD.
A24: ISO 50006:2023 §8 e anexos D–F (normalização) | B24: Energia esperada = modelo da LBE aplicado às variáveis do mês; comparação sob condições equivalentes.
A25: ISO 50006:2023 §9.2 (fatores estáticos) | B25: Ajuste não rotineiro ALE-01 (4 máquinas novas em 07/2026) e tbl_fatores_estaticos.
A26: ISO 50006:2023 §10.3 (demonstrar melhoria) | B26: Soma do período de reporte dentro do domínio, comparada com a incerteza do modelo.
A27: LBNL — EnPI Lite 'Valid model requirements' / 50001 Ready M&V Protocol | B27: R² ≥ 0,5; p < 0,2 em todas as variáveis e < 0,1 em pelo menos uma; teste F com p < 0,1 (folha LBE_Modelo).
A28: ASHRAE Guideline 14 (dados mensais) | B28: CV(RMSE) ≤ 15% e NMBE ±5%; R² recomendado > 0,75; incerteza da poupança a 95%.
A29: EVO — IPMVP Core Concepts (opções A–D) | B29: Método de verificação de cada plano de ação (6.2.3) e ajustes não rotineiros.
A30: Kent, R. — Energy Management in Plastics Processing (BPF/Tangram) | B30: 'Impressão digital' energética: carga de base (IDE-05, típico 20–40%) + consumo proporcional à produção; o SEC mensal engana quando a produção varia.
A32: REQUISITOS LEGAIS E OUTROS REQUISITOS APLICADOS (4.2, 9.1.2 — lista completa no RG-SGE-11)
A33: DL 71/2008 (SGCIE) — LEG-08 | B33: Consumo específico e intensidade energética são indicadores do PREn (RG-SGE-10); o IDE-02 e o IDE-09 alimentam-nos.
A35: ESTRUTURA DO FICHEIRO
A36: Base_Mensal | B36: Base mensal de energia e variáveis relevantes (RG-SGA-13, dataset, RG-SGA-19).
A37: IDE_Mensal | B37: IDE mensais calculados por fórmula: energia esperada pela LBE, diferença, CUSUM, melhoria normalizada, domínio de validade e rácios.
A38: LBE_Modelo | B38: Modelo estatístico da LBE-01 calculado por LINEST, testes de validade, domínio e demonstração da melhoria no período de reporte.
A39: Variaveis_Relevantes | B39: Seleção das variáveis relevantes (6.4, 6.5; ISO 50006 §5.5 e anexo D).
A40: Catalogo_IDE | B40: Catálogo de IDE e KPI do SGE: tipo, fronteira, variáveis, normalização, LBE, dono e utilizadores (6.4; ISO 50006 §5–6).
A41: Registo_LBE | B41: Registo das LBE (6.5 — reter as LBE, os dados das variáveis relevantes e as modificações).
A42: Alteracoes_LBE | B42: Modificações às LBE e ajustes não rotineiros (6.5 — reter).
A43: Fatores_Estaticos | B43: Fatores estáticos monitorizados para decidir revisões da LBE (6.5 b).
A44: Parametros | B44: Parâmetros usados nos cálculos deste registo (mesma estrutura do RG-SGA-13 tbl_parametros).
A45: Objetivos_Energeticos | B45: Objetivos energéticos e do SGE (6.2.1, 6.2.2 a–h) — mesmas colunas do RG-SGA-05 tbl_objetivos.
A46: Metas_Energeticas | B46: Metas energéticas quantificadas por IDE (6.2.1 — 'a organização deve estabelecer metas energéticas').
A47: Planos_Acao | B47: Planos de ação energéticos (6.2.3 — reter).
... A50: Dicionario_Dados | B50: Descrição de cada coluna de cada tabela: tipo, origem (entrada/calculado), domínio, obrigatoriedade e chaves.
A52: CONVENÇÕES (prontas para análise de dados e machine learning)
A53: Tabelas | B53: Cada registo é uma Tabela Excel com nome próprio (tbl_*): uma linha = um registo, cabeçalho único, sem células mescladas. Ler com pandas (pd.read_excel(ficheiro, sheet_name=folha, header=<linha do cabeçalho - 1>)) ou Power BI (Obter Dados > Tabela).
A54: Cabeçalho cinzento | B54: Coluna CALCULADA por fórmula — não escrever por cima. As restantes colunas são de entrada.
A55: Validação | B55: Colunas com lista controlada só aceitam valores da folha Listas (evita categorias duplicadas por grafia diferente).
A56: Chaves | B56: IDs estáveis e únicos (PK) e referências a IDs de outros registos (FK) permitem juntar tabelas entre ficheiros do SGE, do SGA e do SGQ — ver SGE-00_Indice_Modelo_Dados.xlsx.
A57: Datas e unidades | B57: Datas em formato data (aaaa-mm-dd); energia em kWh (MWh quando indicado); a unidade está no nome da coluna ou no dicionário. Data de referência do SGE: 2026-12-31.
A58: Dados | B58: Fábrica simulada Plasticom. Eletricidade mensal por uso: fonte única RG-SGA-13 (tbl_dados_ambientais, mar/2025 a dez/2026, já com o efeito das ações de energia de out–dez/2026). Produção e horas de marcha por máquina: dataset do projeto (datasets/silver). Dados que o dataset não tem (campanha de medição por máquina, faturas por período tarifário, gasóleo, compressores, SGCIE) são simulação didática coerente com esses dados e estão marcados como tal.
A60: LIGAÇÕES A OUTROS REGISTOS
A61: RG-SGA-13 | B61: Fonte única da eletricidade mensal por uso (tbl_dados_ambientais) — alterar lá, não aqui.
A62: RG-SGA-05 | B62: OBJ-01 e KPI-01 (SEC) — o SGE mede o mesmo desempenho normalizado (IDE-01) e em rácio (IDE-02).
A63: RG-SGE-04 | B63: USE e oportunidades (OPE-xx) que originam os objetivos e planos.
A64: RG-SGE-06 | B64: Plano de recolha de dados (DAD-xx) que alimenta os IDE.
A65: RG-SGE-11 | B65: Desvios significativos (9.1.1) e M&V das poupanças por ação (ISO 50015 / IPMVP).
A66: RG-SGE-02 | B66: Compromissos da política energética (POL-E-xx) a que os objetivos dão corpo.

Sheet Base_Mensal
A1: BASE MENSAL DE ENERGIA E VARIÁVEIS RELEVANTES
A2: 2025-03-01 a 2026-12-31 · Eletricidade: RG-SGA-13 (fonte única, mar/2025–dez/2026) · Referência = 12 primeiros meses · Reporte = mar–dez/2026
A4: Mes | B4: Periodo | C4: Qualidade_Producao | D4: Fonte_Energia | E4: Dias_Calendario | F4: Dias_Uteis | G4: Temp_Media_C | H4: CDD_15 | I4: kWh_Total | J4: kWh_SOP | K4: kWh_INJ | L4: kWh_UTL_AR | M4: kWh_UTL_FRIO | N4: kWh_GER | O4: kWh_SER | P4: kWh_HFS | Q4: Unid_INJ | R4: Unid_SOP | S4: Unid_SER | T4: Unid_HFS | U4: Horas_INJ | V4: Horas_SOP | W4: Horas_SER | X4: Horas_HFS | Y4: Unid_Maquinas_Novas | Z4: kWh_Maquinas_Novas | AA4: L_Gasoleo_Frota | AB4: L_Gasoleo_Gerador | AC4: Verif_Soma_Usos | AD4: Energia_Final_MWh
A5: 45717 | B5: Referência (LBE) | C5: Reconstruído (pré-dataset) | D5: RG-SGA-13 (fatura) | E5: 31 | F5: 21 | G5: 13.2 | H5: 0 | I5: 568941 | J5: 233780 | K5: 150493 | L5: 78797 | M5: 34765 | N5: 45887 | O5: 12915 | P5: 12304 | Q5: 3127150 | R5: 2074828 | S5: 373701 | T5: 622911 | U5: 3398.2 | V5: 4230.2 | W5: 745.8 | X5: 1330 | Y5: 0 | Z5: 0 | AA5: 255.2 | AB5: 20.9 | AC5: =IF(A5="","",J5+K5+L5+M5+N5+O5+P5-I5) -> 0 | AD5: =IF(A5="","",(I5+(AA5+AB5)*10)/1000) -> 571.702
A6: 45748 | B6: Referência (LBE) | C6: Reconstruído (pré-dataset) | D6: RG-SGA-13 (fatura) | E6: 30 | F6: 20 | G6: 15.2 | H6: 6 | I6: 545354 | J6: 218570 | K6: 148146 | L6: 75062 | M6: 36654 | N6: 43909 | O6: 12953 | P6: 10060 | Q6: 2949838 | R6: 1917166 | S6: 352528 | T6: 532950 | U6: 3205.5 | V6: 3908.8 | W6: 703.6 | X6: 1137.9 | Y6: 0 | Z6: 0 | AA6: 270.5 | AB6: 20.4 | AC6: =IF(A6="","",J6+K6+L6+M6+N6+O6+P6-I6) -> 0 | AD6: =IF(A6="","",(I6+(AA6+AB6)*10)/1000) -> 548.263
A7: 45778 | B7: Referência (LBE) | C7: Reconstruído (pré-dataset) | D7: RG-SGA-13 (fatura) | E7: 31 | F7: 21 | G7: 16.8 | H7: 55.8 | I7: 538026 | J7: 212282 | K7: 147778 | L7: 72249 | M7: 39448 | N7: 41507 | O7: 13269 | P7: 11493 | Q7: 3081721 | R7: 1948876 | S7: 376251 | T7: 583006 | U7: 3348.8 | V7: 3973.4 | W7: 750.9 | X7: 1244.8 | Y7: 0 | Z7: 0 | AA7: 254.1 | AB7: 19.6 | AC7: =IF(A7="","",J7+K7+L7+M7+N7+O7+P7-I7) -> 0 | AD7: =IF(A7="","",(I7+(AA7+AB7)*10)/1000) -> 540.763
A8: 45809 | B8: Referência (LBE) | C8: Reconstruído (pré-dataset) | D8: RG-SGA-13 (fatura) | E8: 30 | F8: 19 | G8: 21.2 | H8: 186 | I8: 515423 | J8: 209893 | K8: 127528 | L8: 68734 | M8: 43262 | N8: 43471 | O8: 12590 | P8: 9946 | Q8: 2676526 | R8: 1867421 | S8: 336762 | T8: 521560 | U8: 2908.5 | V8: 3807.3 | W8: 672.1 | X8: 1113.6 | Y8: 0 | Z8: 0 | AA8: 227.4 | AB8: 19.2 | AC8: =IF(A8="","",J8+K8+L8+M8+N8+O8+P8-I8) -> 1 | AD8: =IF(A8="","",(I8+(AA8+AB8)*10)/1000) -> 517.889
A9: 45839 | B9: Referência (LBE) | C9: Dataset | D9: RG-SGA-13 (fatura) | E9: 31 | F9: 23 | G9: 22.2 | H9: 223.2 | I9: 620886 | J9: 255934 | K9: 155542 | L9: 83129 | M9: 54774 | N9: 42982 | O9: 15942 | P9: 12584 | Q9: 3036460 | R9: 2236614 | S9: 443480 | T9: 634114 | U9: 3407.4 | V9: 4527.4 | W9: 881.9 | X9: 1354.2 | Y9: 0 | Z9: 0 | AA9: 244.8 | AB9: 16.9 | AC9: =IF(A9="","",J9+K9+L9+M9+N9+O9+P9-I9) -> 1 | AD9: =IF(A9="","",(I9+(AA9+AB9)*10)/1000) -> 623.503
A10: 45870 | B10: Referência (LBE) | C10: Dataset | D10: RG-SGA-13 (fatura) | E10: 31 | F10: 20 | G10: 23.1 | H10: 251.1 | I10: 586901 | J10: 232060 | K10: 150415 | L10: 77888 | M10: 54405 | N10: 50669 | O10: 8255 | P10: 13210 | Q10: 3305389 | R10: 2138267 | S10: 237760 | T10: 681799 | U10: 3440.7 | V10: 4257.9 | W10: 480.2 | X10: 1453.3 | Y10: 0 | Z10: 0 | AA10: 263.4 | AB10: 17.3 | AC10: =IF(A10="","",J10+K10+L10+M10+N10+O10+P10-I10) -> 1 | AD10: =IF(A10="","",(I10+(AA10+AB10)*10)/1000) -> 589.708
A11: 45901 | B11: Referência (LBE) | C11: Dataset | D11: RG-SGA-13 (fatura) | E11: 30 | F11: 22 | G11: 20.9 | H11: 177 | I11: 569448 | J11: 224732 | K11: 151543 | L11: 76055 | M11: 48367 | N11: 45651 | O11: 11963 | P11: 11136 | Q11: 3070042 | R11: 1992851 | S11: 372292 | T11: 572466 | U11: 3317.5 | V11: 4102.8 | W11: 718.5 | X11: 1223.7 | Y11: 0 | Z11: 0 | AA11: 290.2 | AB11: 15.8 | AC11: =IF(A11="","",J11+K11+L11+M11+N11+O11+P11-I11) -> -1 | AD11: =IF(A11="","",(I11+(AA11+AB11)*10)/1000) -> 572.508
A12: 45931 | B12: Referência (LBE) | C12: Dataset | D12: RG-SGA-13 (fatura) | E12: 31 | F12: 22 | G12: 18.1 | H12: 96.1 | I12: 568762 | J12: 231621 | K12: 150121 | L12: 76437 | M12: 43597 | N12: 41407 | O12: 15408 | P12: 10171 | Q12: 3063889 | R12: 2094836 | S12: 431440 | T12: 550527 | U12: 3377.9 | V12: 4346.1 | W12: 875.3 | X12: 1166 | Y12: 0 | Z12: 0 | AA12: 231.1 | AB12: 20.2 | AC12: =IF(A12="","",J12+K12+L12+M12+N12+O12+P12-I12) -> 0 | AD12: =IF(A12="","",(I12+(AA12+AB12)*10)/1000) -> 571.275
A13: 45962 | B13: Referência (LBE) | C13: Dataset | D13: RG-SGA-13 (fatura) | E13: 30 | F13: 19 | G13: 13.3 | H13: 0 | I13: 561643 | J13: 230406 | K13: 147075 | L13: 76392 | M13: 34544 | N13: 46470 | O13: 16262 | P13: 10494 | Q13: 2975801 | R13: 1998289 | S13: 448497 | T13: 548163 | U13: 3276.5 | V13: 4159.3 | W13: 886.9 | X13: 1168.5 | Y13: 0 | Z13: 0 | AA13: 231.2 | AB13: 16.6 | AC13: =IF(A13="","",J13+K13+L13+M13+N13+O13+P13-I13) -> 0 | AD13: =IF(A13="","",(I13+(AA13+AB13)*10)/1000) -> 564.121
A14: 45992 | B14: Referência (LBE) | C14: Dataset | D14: RG-SGA-13 (fatura) | E14: 31 | F14: 20 | G14: 11.4 | H14: 0 | I14: 582602 | J14: 246048 | K14: 151639 | L14: 77790 | M14: 34150 | N14: 49348 | O14: 12466 | P14: 11162 | Q14: 3058510 | R14: 2163430 | S14: 338785 | T14: 572203 | U14: 3294.6 | V14: 4345.2 | W14: 692.1 | X14: 1233.9 | Y14: 0 | Z14: 0 | AA14: 229.3 | AB14: 17.1 | AC14: =IF(A14="","",J14+K14+L14+M14+N14+O14+P14-I14) -> 1 | AD14: =IF(A14="","",(I14+(AA14+AB14)*10)/1000) -> 585.066
A15: 46023 | B15: Referência (LBE) | C15: Dataset | D15: RG-SGA-13 (fatura) | E15: 31 | F15: 21 | G15: 9.6 | H15: 0 | I15: 567251 | J15: 238387 | K15: 154580 | L15: 78622 | M15: 28266 | N15: 48208 | O15: 10220 | P15: 8969 | Q15: 3226809 | R15: 2045475 | S15: 296927 | T15: 469263 | U15: 3454.1 | V15: 4280.6 | W15: 578.5 | X15: 998.2 | Y15: 0 | Z15: 0 | AA15: 283.3 | AB15: 18.1 | AC15: =IF(A15="","",J15+K15+L15+M15+N15+O15+P15-I15) -> 1 | AD15: =IF(A15="","",(I15+(AA15+AB15)*10)/1000) -> 570.265
A16: 46054 | B16: Referência (LBE) | C16: Dataset | D16: RG-SGA-13 (fatura) | E16: 28 | F16: 20 | G16: 11.9 | H16: 0 | I16: 527749 | J16: 219236 | K16: 138364 | L16: 71532 | M16: 30720 | N16: 47297 | O16: 10672 | P16: 9929 | Q16: 2776640 | R16: 1980694 | S16: 295268 | T16: 526979 | U16: 3055.7 | V16: 3951 | W16: 587.8 | X16: 1110.5 | Y16: 0 | Z16: 0 | AA16: 288.8 | AB16: 17.9 | AC16: =IF(A16="","",J16+K16+L16+M16+N16+O16+P16-I16) -> 1 | AD16: =IF(A16="","",(I16+(AA16+AB16)*10)/1000) -> 530.816
... A26: 46357 | B26: Reporte | C26: Dataset | D26: RG-SGA-13 (fatura) | E26: 31 | F26: 20 | G26: 11.1 | H26: 0 | I26: 675973 | J26: 286521 | K26: 197345 | L26: 79474 | M26: 38953 | N26: 49119 | O26: 13206 | P26: 11356 | Q26: 4306092 | R26: 2608256 | S26: 359103 | T26: 589367 | U26: 4791.1 | V26: 5342.6 | W26: 729.8 | X26: 1245.6 | Y26: 1847309 | Z26: 162411 | AA26: 234.8 | AB26: 18.9 | AC26: =IF(A26="","",J26+K26+L26+M26+N26+O26+P26-I26) -> 1 | AD26: =IF(A26="","",(I26+(AA26+AB26)*10)/1000) -> 678.51

Sheet IDE_Mensal
A1: IDE MENSAIS — COMPARAÇÃO COM A LBE (ISO 50001 9.1.1; ISO 50006 §8 e §10)
A2: Tudo calculado · kWh_Esperado = LBE-01 aplicada às variáveis do mês · Fora do domínio = variáveis fora do intervalo da referência (não usar para demonstrar melhoria)
A4: Mes | B4: Periodo | C4: Y_kWh_Ajustado | D4: X1_Unid_mil | E4: X2_CDD | F4: kWh_Esperado | G4: Diferenca_kWh | H4: CUSUM_kWh | I4: Melhoria_Pct | J4: Dentro_Dominio | K4: Estado_IDE01 | L4: SEC_Real | M4: SEC_SOP | N4: SEC_INJ | O4: Carga_Base_Pct | P4: Racio_Frio | Q4: Racio_Ar | R4: Energia_Final_MWh
A5: 45717 | B5: =IF(A5="","",INDEX(tbl_base_energia[Periodo],MATCH(A5,tbl_base_energia[Mes],0))) -> Referência (LBE) | C5: =IF(A5="","",INDEX(tbl_base_energia[kWh_Total],MATCH(A5,tbl_base_energia[Mes],0))-INDEX(tbl_base_energia[kWh_Maquinas_Novas],MATCH(A5,tbl_base_energia[Mes],0))) -> 568941 | D5: =IF(A5="","",(INDEX(tbl_base_energia[Unid_INJ],MATCH(A5,tbl_base_energia[Mes],0))+INDEX(tbl_base_energia[Unid_SOP],MATCH(A5,tbl_base_energia[Mes],0))-INDEX(tbl_base_energia[Unid_Maquinas_Novas],MATCH(A5,tbl_base_energia[Mes],0)))/1000) -> 5201.978 | E5: =IF(A5="","",INDEX(tbl_base_energia[CDD_15],MATCH(A5,tbl_base_energia[Mes],0))) -> 0 | F5: =IF(A5="","",lbe_a+lbe_b1*D5+lbe_b2*E5) -> 570403.97 | G5: =IF(A5="","",C5-F5) -> -1462.974 | H5: =IF(A5="","",SUM($G$5:G5)) -> -1462.974 | I5: =IF(A5="","",-G5/F5) -> 0.0025648033 | J5: =IF(A5="","",IF(AND(D5>=dom_x1_min,D5<=dom_x1_max,E5>=dom_x2_min,E5<=dom_x2_max),"Sim","Não")) -> Sim | K5: =IF(A5="","",IF(B5="Referência (LBE)","Referência",IF(J5="Não","Fora do domínio",IF(G5>lbe_limite,"Desvio significativo",IF(G5<-lbe_limite,"Melhoria significativa","Dentro da incerteza"))))) -> Referência | L5: =IF(A5="","",INDEX(tbl_base_energia[kWh_Total],MATCH(A5,tbl_base_energia[Mes],0))/(INDEX(tbl_base_energia[Unid_INJ],MATCH(A5,tbl_base_energia[Mes],0))+INDEX(tbl_base_energia[Unid_SOP],MATCH(A5,tbl_base_energia[Mes],0)))*1000) -> 109.37013 | M5: =IF(A5="","",INDEX(tbl_base_energia[kWh_SOP],MATCH(A5,tbl_base_energia[Mes],0))/INDEX(tbl_base_energia[Unid_SOP],MATCH(A5,tbl_base_energia[Mes],0))*1000) -> 112.6744 | N5: =IF(A5="","",INDEX(tbl_base_energia[kWh_INJ],MATCH(A5,tbl_base_energia[Mes],0))/INDEX(tbl_base_energia[Unid_INJ],MATCH(A5,tbl_base_energia[Mes],0))*1000) -> 48.12465 | O5: =IF(A5="","",lbe_a/C5) -> 0.16499257 | P5: =IF(A5="","",INDEX(tbl_base_energia[kWh_UTL_FRIO],MATCH(A5,tbl_base_energia[Mes],0))/(INDEX(tbl_base_energia[kWh_INJ],MATCH(A5,tbl_base_energia[Mes],0))+INDEX(tbl_base_energia[kWh_SOP],MATCH(A5,tbl_base_energia[Mes],0)))) -> 0.090469536 | Q5: =IF(A5="","",INDEX(tbl_base_energia[kWh_UTL_AR],MATCH(A5,tbl_base_energia[Mes],0))/(INDEX(tbl_base_energia[kWh_INJ],MATCH(A5,tbl_base_energia[Mes],0))+INDEX(tbl_base_energia[kWh_SOP],MATCH(A5,tbl_base_energia[Mes],0))+INDEX(tbl_base_energia[kWh_SER],MATCH(A5,tbl_base_energia[Mes],0))+INDEX(tbl_base_energia[kWh_HFS],MATCH(A5,tbl_base_energia[Mes],0)))) -> 0.19242623 | R5: =IF(A5="","",INDEX(tbl_base_energia[Energia_Final_MWh],MATCH(A5,tbl_base_energia[Mes],0))) -> 571.702
A6: 45748 | B6: =IF(A6="","",INDEX(tbl_base_energia[Periodo],MATCH(A6,tbl_base_energia[Mes],0))) -> Referência (LBE) | C6: =IF(A6="","",INDEX(tbl_base_energia[kWh_Total],MATCH(A6,tbl_base_energia[Mes],0))-INDEX(tbl_base_energia[kWh_Maquinas_Novas],MATCH(A6,tbl_base_energia[Mes],0))) -> 545354 | D6: =IF(A6="","",(INDEX(tbl_base_energia[Unid_INJ],MATCH(A6,tbl_base_energia[Mes],0))+INDEX(tbl_base_energia[Unid_SOP],MATCH(A6,tbl_base_energia[Mes],0))-INDEX(tbl_base_energia[Unid_Maquinas_Novas],MATCH(A6,tbl_base_energia[Mes],0)))/1000) -> 4867.004 | E6: =IF(A6="","",INDEX(tbl_base_energia[CDD_15],MATCH(A6,tbl_base_energia[Mes],0))) -> 6 | F6: =IF(A6="","",lbe_a+lbe_b1*D6+lbe_b2*E6) -> 540057.1 | G6: =IF(A6="","",C6-F6) -> 5296.9026 | H6: =IF(A6="","",SUM($G$5:G6)) -> 3833.9287 | I6: =IF(A6="","",-G6/F6) -> -0.0098080419 | J6: =IF(A6="","",IF(AND(D6>=dom_x1_min,D6<=dom_x1_max,E6>=dom_x2_min,E6<=dom_x2_max),"Sim","Não")) -> Sim | K6: =IF(A6="","",IF(B6="Referência (LBE)","Referência",IF(J6="Não","Fora do domínio",IF(G6>lbe_limite,"Desvio significativo",IF(G6<-lbe_limite,"Melhoria significativa","Dentro da incerteza"))))) -> Referência | L6: =IF(A6="","",INDEX(tbl_base_energia[kWh_Total],MATCH(A6,tbl_base_energia[Mes],0))/(INDEX(tbl_base_energia[Unid_INJ],MATCH(A6,tbl_base_energia[Mes],0))+INDEX(tbl_base_energia[Unid_SOP],MATCH(A6,tbl_base_energia[Mes],0)))*1000) -> 112.05127 | M6: =IF(A6="","",INDEX(tbl_base_energia[kWh_SOP],MATCH(A6,tbl_base_energia[Mes],0))/INDEX(tbl_base_energia[Unid_SOP],MATCH(A6,tbl_base_energia[Mes],0))*1000) -> 114.00682 | N6: =IF(A6="","",INDEX(tbl_base_energia[kWh_INJ],MATCH(A6,tbl_base_energia[Mes],0))/INDEX(tbl_base_energia[Unid_INJ],MATCH(A6,tbl_base_energia[Mes],0))*1000) -> 50.221741 | O6: =IF(A6="","",lbe_a/C6) -> 0.17212863 | P6: =IF(A6="","",INDEX(tbl_base_energia[kWh_UTL_FRIO],MATCH(A6,tbl_base_energia[Mes],0))/(INDEX(tbl_base_energia[kWh_INJ],MATCH(A6,tbl_base_energia[Mes],0))+INDEX(tbl_base_energia[kWh_SOP],MATCH(A6,tbl_base_energia[Mes],0)))) -> 0.099952006 | Q6: =IF(A6="","",INDEX(tbl_base_energia[kWh_UTL_AR],MATCH(A6,tbl_base_energia[Mes],0))/(INDEX(tbl_base_energia[kWh_INJ],MATCH(A6,tbl_base_energia[Mes],0))+INDEX(tbl_base_energia[kWh_SOP],MATCH(A6,tbl_base_energia[Mes],0))+INDEX(tbl_base_energia[kWh_SER],MATCH(A6,tbl_base_energia[Mes],0))+INDEX(tbl_base_energia[kWh_HFS],MATCH(A6,tbl_base_energia[Mes],0)))) -> 0.1926005 | R6: =IF(A6="","",INDEX(tbl_base_energia[Energia_Final_MWh],MATCH(A6,tbl_base_energia[Mes],0))) -> 548.263
A7: 45778 | B7: =IF(A7="","",INDEX(tbl_base_energia[Periodo],MATCH(A7,tbl_base_energia[Mes],0))) -> Referência (LBE) | C7: =IF(A7="","",INDEX(tbl_base_energia[kWh_Total],MATCH(A7,tbl_base_energia[Mes],0))-INDEX(tbl_base_energia[kWh_Maquinas_Novas],MATCH(A7,tbl_base_energia[Mes],0))) -> 538026 | D7: =IF(A7="","",(INDEX(tbl_base_energia[Unid_INJ],MATCH(A7,tbl_base_energia[Mes],0))+INDEX(tbl_base_energia[Unid_SOP],MATCH(A7,tbl_base_energia[Mes],0))-INDEX(tbl_base_energia[Unid_Maquinas_Novas],MATCH(A7,tbl_base_energia[Mes],0)))/1000) -> 5030.597 | E7: =IF(A7="","",INDEX(tbl_base_energia[CDD_15],MATCH(A7,tbl_base_energia[Mes],0))) -> 55.8 | F7: =IF(A7="","",lbe_a+lbe_b1*D7+lbe_b2*E7) -> 557855.14 | G7: =IF(A7="","",C7-F7) -> -19829.142 | H7: =IF(A7="","",SUM($G$5:G7)) -> -15995.214 | I7: =IF(A7="","",-G7/F7) -> 0.035545325 | J7: =IF(A7="","",IF(AND(D7>=dom_x1_min,D7<=dom_x1_max,E7>=dom_x2_min,E7<=dom_x2_max),"Sim","Não")) -> Sim | K7: =IF(A7="","",IF(B7="Referência (LBE)","Referência",IF(J7="Não","Fora do domínio",IF(G7>lbe_limite,"Desvio significativo",IF(G7<-lbe_limite,"Melhoria significativa","Dentro da incerteza"))))) -> Referência | L7: =IF(A7="","",INDEX(tbl_base_energia[kWh_Total],MATCH(A7,tbl_base_energia[Mes],0))/(INDEX(tbl_base_energia[Unid_INJ],MATCH(A7,tbl_base_energia[Mes],0))+INDEX(tbl_base_energia[Unid_SOP],MATCH(A7,tbl_base_energia[Mes],0)))*1000) -> 106.95073 | M7: =IF(A7="","",INDEX(tbl_base_energia[kWh_SOP],MATCH(A7,tbl_base_energia[Mes],0))/INDEX(tbl_base_energia[Unid_SOP],MATCH(A7,tbl_base_energia[Mes],0))*1000) -> 108.92535 | N7: =IF(A7="","",INDEX(tbl_base_energia[kWh_INJ],MATCH(A7,tbl_base_energia[Mes],0))/INDEX(tbl_base_energia[Unid_INJ],MATCH(A7,tbl_base_energia[Mes],0))*1000) -> 47.953076 | O7: =IF(A7="","",lbe_a/C7) -> 0.17447305 | P7: =IF(A7="","",INDEX(tbl_base_energia[kWh_UTL_FRIO],MATCH(A7,tbl_base_energia[Mes],0))/(INDEX(tbl_base_energia[kWh_INJ],MATCH(A7,tbl_base_energia[Mes],0))+INDEX(tbl_base_energia[kWh_SOP],MATCH(A7,tbl_base_energia[Mes],0)))) -> 0.10955952 | Q7: =IF(A7="","",INDEX(tbl_base_energia[kWh_UTL_AR],MATCH(A7,tbl_base_energia[Mes],0))/(INDEX(tbl_base_energia[kWh_INJ],MATCH(A7,tbl_base_energia[Mes],0))+INDEX(tbl_base_energia[kWh_SOP],MATCH(A7,tbl_base_energia[Mes],0))+INDEX(tbl_base_energia[kWh_SER],MATCH(A7,tbl_base_energia[Mes],0))+INDEX(tbl_base_energia[kWh_HFS],MATCH(A7,tbl_base_energia[Mes],0)))) -> 0.18774654 | R7: =IF(A7="","",INDEX(tbl_base_energia[Energia_Final_MWh],MATCH(A7,tbl_base_energia[Mes],0))) -> 540.763
A8: 45809 | B8: =IF(A8="","",INDEX(tbl_base_energia[Periodo],MATCH(A8,tbl_base_energia[Mes],0))) -> Referência (LBE) | C8: =IF(A8="","",INDEX(tbl_base_energia[kWh_Total],MATCH(A8,tbl_base_energia[Mes],0))-INDEX(tbl_base_energia[kWh_Maquinas_Novas],MATCH(A8,tbl_base_energia[Mes],0))) -> 515423 | D8: =IF(A8="","",(INDEX(tbl_base_energia[Unid_INJ],MATCH(A8,tbl_base_energia[Mes],0))+INDEX(tbl_base_energia[Unid_SOP],MATCH(A8,tbl_base_energia[Mes],0))-INDEX(tbl_base_energia[Unid_Maquinas_Novas],MATCH(A8,tbl_base_energia[Mes],0)))/1000) -> 4543.947 | E8: =IF(A8="","",INDEX(tbl_base_energia[CDD_15],MATCH(A8,tbl_base_energia[Mes],0))) -> 186 | F8: =IF(A8="","",lbe_a+lbe_b1*D8+lbe_b2*E8) -> 520626.7 | G8: =IF(A8="","",C8-F8) -> -5203.6979 | H8: =IF(A8="","",SUM($G$5:G8)) -> -21198.912 | I8: =IF(A8="","",-G8/F8) -> 0.0099950654 | J8: =IF(A8="","",IF(AND(D8>=dom_x1_min,D8<=dom_x1_max,E8>=dom_x2_min,E8<=dom_x2_max),"Sim","Não")) -> Sim | K8: =IF(A8="","",IF(B8="Referência (LBE)","Referência",IF(J8="Não","Fora do domínio",IF(G8>lbe_limite,"Desvio significativo",IF(G8<-lbe_limite,"Melhoria significativa","Dentro da incerteza"))))) -> Referência | L8: =IF(A8="","",INDEX(tbl_base_energia[kWh_Total],MATCH(A8,tbl_base_energia[Mes],0))/(INDEX(tbl_base_energia[Unid_INJ],MATCH(A8,tbl_base_energia[Mes],0))+INDEX(tbl_base_energia[Unid_SOP],MATCH(A8,tbl_base_energia[Mes],0)))*1000) -> 113.43068 | M8: =IF(A8="","",INDEX(tbl_base_energia[kWh_SOP],MATCH(A8,tbl_base_energia[Mes],0))/INDEX(tbl_base_energia[Unid_SOP],MATCH(A8,tbl_base_energia[Mes],0))*1000) -> 112.39726 | N8: =IF(A8="","",INDEX(tbl_base_energia[kWh_INJ],MATCH(A8,tbl_base_energia[Mes],0))/INDEX(tbl_base_energia[Unid_INJ],MATCH(A8,tbl_base_energia[Mes],0))*1000) -> 47.646838 | O8: =IF(A8="","",lbe_a/C8) -> 0.18212427 | P8: =IF(A8="","",INDEX(tbl_base_energia[kWh_UTL_FRIO],MATCH(A8,tbl_base_energia[Mes],0))/(INDEX(tbl_base_energia[kWh_INJ],MATCH(A8,tbl_base_energia[Mes],0))+INDEX(tbl_base_energia[kWh_SOP],MATCH(A8,tbl_base_energia[Mes],0)))) -> 0.12821372 | Q8: =IF(A8="","",INDEX(tbl_base_energia[kWh_UTL_AR],MATCH(A8,tbl_base_energia[Mes],0))/(INDEX(tbl_base_energia[kWh_INJ],MATCH(A8,tbl_base_energia[Mes],0))+INDEX(tbl_base_energia[kWh_SOP],MATCH(A8,tbl_base_energia[Mes],0))+INDEX(tbl_base_energia[kWh_SER],MATCH(A8,tbl_base_energia[Mes],0))+INDEX(tbl_base_energia[kWh_HFS],MATCH(A8,tbl_base_energia[Mes],0)))) -> 0.19095059 | R8: =IF(A8="","",INDEX(tbl_base_energia[Energia_Final_MWh],MATCH(A8,tbl_base_energia[Mes],0))) -> 517.889
A9: 45839 | B9: =IF(A9="","",INDEX(tbl_base_energia[Periodo],MATCH(A9,tbl_base_energia[Mes],0))) -> Referência (LBE) | C9: =IF(A9="","",INDEX(tbl_base_energia[kWh_Total],MATCH(A9,tbl_base_energia[Mes],0))-INDEX(tbl_base_energia[kWh_Maquinas_Novas],MATCH(A9,tbl_base_energia[Mes],0))) -> 620886 | D9: =IF(A9="","",(INDEX(tbl_base_energia[Unid_INJ],MATCH(A9,tbl_base_energia[Mes],0))+INDEX(tbl_base_energia[Unid_SOP],MATCH(A9,tbl_base_energia[Mes],0))-INDEX(tbl_base_energia[Unid_Maquinas_Novas],MATCH(A9,tbl_base_energia[Mes],0)))/1000) -> 5273.074 | E9: =IF(A9="","",INDEX(tbl_base_energia[CDD_15],MATCH(A9,tbl_base_energia[Mes],0))) -> 223.2 | F9: =IF(A9="","",lbe_a+lbe_b1*D9+lbe_b2*E9) -> 589519.66 | G9: =IF(A9="","",C9-F9) -> 31366.342 | H9: =IF(A9="","",SUM($G$5:G9)) -> 10167.431 | I9: =IF(A9="","",-G9/F9) -> -0.05320661 | J9: =IF(A9="","",IF(AND(D9>=dom_x1_min,D9<=dom_x1_max,E9>=dom_x2_min,E9<=dom_x2_max),"Sim","Não")) -> Sim | K9: =IF(A9="","",IF(B9="Referência (LBE)","Referência",IF(J9="Não","Fora do domínio",IF(G9>lbe_limite,"Desvio significativo",IF(G9<-lbe_limite,"Melhoria significativa","Dentro da incerteza"))))) -> Referência | L9: =IF(A9="","",INDEX(tbl_base_energia[kWh_Total],MATCH(A9,tbl_base_energia[Mes],0))/(INDEX(tbl_base_energia[Unid_INJ],MATCH(A9,tbl_base_energia[Mes],0))+INDEX(tbl_base_energia[Unid_SOP],MATCH(A9,tbl_base_energia[Mes],0)))*1000) -> 117.7465 | M9: =IF(A9="","",INDEX(tbl_base_energia[kWh_SOP],MATCH(A9,tbl_base_energia[Mes],0))/INDEX(tbl_base_energia[Unid_SOP],MATCH(A9,tbl_base_energia[Mes],0))*1000) -> 114.42922 | N9: =IF(A9="","",INDEX(tbl_base_energia[kWh_INJ],MATCH(A9,tbl_base_energia[Mes],0))/INDEX(tbl_base_energia[Unid_INJ],MATCH(A9,tbl_base_energia[Mes],0))*1000) -> 51.224781 | O9: =IF(A9="","",lbe_a/C9) -> 0.15118884 | P9: =IF(A9="","",INDEX(tbl_base_energia[kWh_UTL_FRIO],MATCH(A9,tbl_base_energia[Mes],0))/(INDEX(tbl_base_energia[kWh_INJ],MATCH(A9,tbl_base_energia[Mes],0))+INDEX(tbl_base_energia[kWh_SOP],MATCH(A9,tbl_base_energia[Mes],0)))) -> 0.1331159 | Q9: =IF(A9="","",INDEX(tbl_base_energia[kWh_UTL_AR],MATCH(A9,tbl_base_energia[Mes],0))/(INDEX(tbl_base_energia[kWh_INJ],MATCH(A9,tbl_base_energia[Mes],0))+INDEX(tbl_base_energia[kWh_SOP],MATCH(A9,tbl_base_energia[Mes],0))+INDEX(tbl_base_energia[kWh_SER],MATCH(A9,tbl_base_energia[Mes],0))+INDEX(tbl_base_energia[kWh_HFS],MATCH(A9,tbl_base_energia[Mes],0)))) -> 0.18892869 | R9: =IF(A9="","",INDEX(tbl_base_energia[Energia_Final_MWh],MATCH(A9,tbl_base_energia[Mes],0))) -> 623.503
A10: 45870 | B10: =IF(A10="","",INDEX(tbl_base_energia[Periodo],MATCH(A10,tbl_base_energia[Mes],0))) -> Referência (LBE) | C10: =IF(A10="","",INDEX(tbl_base_energia[kWh_Total],MATCH(A10,tbl_base_energia[Mes],0))-INDEX(tbl_base_energia[kWh_Maquinas_Novas],MATCH(A10,tbl_base_energia[Mes],0))) -> 586901 | D10: =IF(A10="","",(INDEX(tbl_base_energia[Unid_INJ],MATCH(A10,tbl_base_energia[Mes],0))+INDEX(tbl_base_energia[Unid_SOP],MATCH(A10,tbl_base_energia[Mes],0))-INDEX(tbl_base_energia[Unid_Maquinas_Novas],MATCH(A10,tbl_base_energia[Mes],0)))/1000) -> 5443.656 | E10: =IF(A10="","",INDEX(tbl_base_energia[CDD_15],MATCH(A10,tbl_base_energia[Mes],0))) -> 251.1 | F10: =IF(A10="","",lbe_a+lbe_b1*D10+lbe_b2*E10) -> 606721.37 | G10: =IF(A10="","",C10-F10) -> -19820.367 | H10: =IF(A10="","",SUM($G$5:G10)) -> -9652.9363 | I10: =IF(A10="","",-G10/F10) -> 0.032667989 | J10: =IF(A10="","",IF(AND(D10>=dom_x1_min,D10<=dom_x1_max,E10>=dom_x2_min,E10<=dom_x2_max),"Sim","Não")) -> Sim | K10: =IF(A10="","",IF(B10="Referência (LBE)","Referência",IF(J10="Não","Fora do domínio",IF(G10>lbe_limite,"Desvio significativo",IF(G10<-lbe_limite,"Melhoria significativa","Dentro da incerteza"))))) -> Referência | L10: =IF(A10="","",INDEX(tbl_base_energia[kWh_Total],MATCH(A10,tbl_base_energia[Mes],0))/(INDEX(tbl_base_energia[Unid_INJ],MATCH(A10,tbl_base_energia[Mes],0))+INDEX(tbl_base_energia[Unid_SOP],MATCH(A10,tbl_base_energia[Mes],0)))*1000) -> 107.81376 | M10: =IF(A10="","",INDEX(tbl_base_energia[kWh_SOP],MATCH(A10,tbl_base_energia[Mes],0))/INDEX(tbl_base_energia[Unid_SOP],MATCH(A10,tbl_base_energia[Mes],0))*1000) -> 108.52714 | N10: =IF(A10="","",INDEX(tbl_base_energia[kWh_INJ],MATCH(A10,tbl_base_energia[Mes],0))/INDEX(tbl_base_energia[Unid_INJ],MATCH(A10,tbl_base_energia[Mes],0))*1000) -> 45.50599 | O10: =IF(A10="","",lbe_a/C10) -> 0.15994356 | P10: =IF(A10="","",INDEX(tbl_base_energia[kWh_UTL_FRIO],MATCH(A10,tbl_base_energia[Mes],0))/(INDEX(tbl_base_energia[kWh_INJ],MATCH(A10,tbl_base_energia[Mes],0))+INDEX(tbl_base_energia[kWh_SOP],MATCH(A10,tbl_base_energia[Mes],0)))) -> 0.14224459 | Q10: =IF(A10="","",INDEX(tbl_base_energia[kWh_UTL_AR],MATCH(A10,tbl_base_energia[Mes],0))/(INDEX(tbl_base_energia[kWh_INJ],MATCH(A10,tbl_base_energia[Mes],0))+INDEX(tbl_base_energia[kWh_SOP],MATCH(A10,tbl_base_energia[Mes],0))+INDEX(tbl_base_energia[kWh_SER],MATCH(A10,tbl_base_energia[Mes],0))+INDEX(tbl_base_energia[kWh_HFS],MATCH(A10,tbl_base_energia[Mes],0)))) -> 0.19282072 | R10: =IF(A10="","",INDEX(tbl_base_energia[Energia_Final_MWh],MATCH(A10,tbl_base_energia[Mes],0))) -> 589.708
A11: 45901 | B11: =IF(A11="","",INDEX(tbl_base_energia[Periodo],MATCH(A11,tbl_base_energia[Mes],0))) -> Referência (LBE) | C11: =IF(A11="","",INDEX(tbl_base_energia[kWh_Total],MATCH(A11,tbl_base_energia[Mes],0))-INDEX(tbl_base_energia[kWh_Maquinas_Novas],MATCH(A11,tbl_base_energia[Mes],0))) -> 569448 | D11: =IF(A11="","",(INDEX(tbl_base_energia[Unid_INJ],MATCH(A11,tbl_base_energia[Mes],0))+INDEX(tbl_base_energia[Unid_SOP],MATCH(A11,tbl_base_energia[Mes],0))-INDEX(tbl_base_energia[Unid_Maquinas_Novas],MATCH(A11,tbl_base_energia[Mes],0)))/1000) -> 5062.893 | E11: =IF(A11="","",INDEX(tbl_base_energia[CDD_15],MATCH(A11,tbl_base_energia[Mes],0))) -> 177 | F11: =IF(A11="","",lbe_a+lbe_b1*D11+lbe_b2*E11) -> 567657.14 | G11: =IF(A11="","",C11-F11) -> 1790.8606 | H11: =IF(A11="","",SUM($G$5:G11)) -> -7862.0757 | I11: =IF(A11="","",-G11/F11) -> -0.0031548279 | J11: =IF(A11="","",IF(AND(D11>=dom_x1_min,D11<=dom_x1_max,E11>=dom_x2_min,E11<=dom_x2_max),"Sim","Não")) -> Sim | K11: =IF(A11="","",IF(B11="Referência (LBE)","Referência",IF(J11="Não","Fora do domínio",IF(G11>lbe_limite,"Desvio significativo",IF(G11<-lbe_limite,"Melhoria significativa","Dentro da incerteza"))))) -> Referência | L11: =IF(A11="","",INDEX(tbl_base_energia[kWh_Total],MATCH(A11,tbl_base_energia[Mes],0))/(INDEX(tbl_base_energia[Unid_INJ],MATCH(A11,tbl_base_energia[Mes],0))+INDEX(tbl_base_energia[Unid_SOP],MATCH(A11,tbl_base_energia[Mes],0)))*1000) -> 112.47482 | M11: =IF(A11="","",INDEX(tbl_base_energia[kWh_SOP],MATCH(A11,tbl_base_energia[Mes],0))/INDEX(tbl_base_energia[Unid_SOP],MATCH(A11,tbl_base_energia[Mes],0))*1000) -> 112.76909 | N11: =IF(A11="","",INDEX(tbl_base_energia[kWh_INJ],MATCH(A11,tbl_base_energia[Mes],0))/INDEX(tbl_base_energia[Unid_INJ],MATCH(A11,tbl_base_energia[Mes],0))*1000) -> 49.361865 | O11: =IF(A11="","",lbe_a/C11) -> 0.16484567 | P11: =IF(A11="","",INDEX(tbl_base_energia[kWh_UTL_FRIO],MATCH(A11,tbl_base_energia[Mes],0))/(INDEX(tbl_base_energia[kWh_INJ],MATCH(A11,tbl_base_energia[Mes],0))+INDEX(tbl_base_energia[kWh_SOP],MATCH(A11,tbl_base_energia[Mes],0)))) -> 0.12854163 | Q11: =IF(A11="","",INDEX(tbl_base_energia[kWh_UTL_AR],MATCH(A11,tbl_base_energia[Mes],0))/(INDEX(tbl_base_energia[kWh_INJ],MATCH(A11,tbl_base_energia[Mes],0))+INDEX(tbl_base_energia[kWh_SOP],MATCH(A11,tbl_base_energia[Mes],0))+INDEX(tbl_base_energia[kWh_SER],MATCH(A11,tbl_base_energia[Mes],0))+INDEX(tbl_base_energia[kWh_HFS],MATCH(A11,tbl_base_energia[Mes],0)))) -> 0.19043553 | R11: =IF(A11="","",INDEX(tbl_base_energia[Energia_Final_MWh],MATCH(A11,tbl_base_energia[Mes],0))) -> 572.508
A12: 45931 | B12: =IF(A12="","",INDEX(tbl_base_energia[Periodo],MATCH(A12,tbl_base_energia[Mes],0))) -> Referência (LBE) | C12: =IF(A12="","",INDEX(tbl_base_energia[kWh_Total],MATCH(A12,tbl_base_energia[Mes],0))-INDEX(tbl_base_energia[kWh_Maquinas_Novas],MATCH(A12,tbl_base_energia[Mes],0))) -> 568762 | D12: =IF(A12="","",(INDEX(tbl_base_energia[Unid_INJ],MATCH(A12,tbl_base_energia[Mes],0))+INDEX(tbl_base_energia[Unid_SOP],MATCH(A12,tbl_base_energia[Mes],0))-INDEX(tbl_base_energia[Unid_Maquinas_Novas],MATCH(A12,tbl_base_energia[Mes],0)))/1000) -> 5158.725 | E12: =IF(A12="","",INDEX(tbl_base_energia[CDD_15],MATCH(A12,tbl_base_energia[Mes],0))) -> 96.1 | F12: =IF(A12="","",lbe_a+lbe_b1*D12+lbe_b2*E12) -> 571867.96 | G12: =IF(A12="","",C12-F12) -> -3105.9649 | H12: =IF(A12="","",SUM($G$5:G12)) -> -10968.041 | I12: =IF(A12="","",-G12/F12) -> 0.0054312622 | J12: =IF(A12="","",IF(AND(D12>=dom_x1_min,D12<=dom_x1_max,E12>=dom_x2_min,E12<=dom_x2_max),"Sim","Não")) -> Sim | K12: =IF(A12="","",IF(B12="Referência (LBE)","Referência",IF(J12="Não","Fora do domínio",IF(G12>lbe_limite,"Desvio significativo",IF(G12<-lbe_limite,"Melhoria significativa","Dentro da incerteza"))))) -> Referência | L12: =IF(A12="","",INDEX(tbl_base_energia[kWh_Total],MATCH(A12,tbl_base_energia[Mes],0))/(INDEX(tbl_base_energia[Unid_INJ],MATCH(A12,tbl_base_energia[Mes],0))+INDEX(tbl_base_energia[Unid_SOP],MATCH(A12,tbl_base_energia[Mes],0)))*1000) -> 110.25244 | M12: =IF(A12="","",INDEX(tbl_base_energia[kWh_SOP],MATCH(A12,tbl_base_energia[Mes],0))/INDEX(tbl_base_energia[Unid_SOP],MATCH(A12,tbl_base_energia[Mes],0))*1000) -> 110.56761 | N12: =IF(A12="","",INDEX(tbl_base_energia[kWh_INJ],MATCH(A12,tbl_base_energia[Mes],0))/INDEX(tbl_base_energia[Unid_INJ],MATCH(A12,tbl_base_energia[Mes],0))*1000) -> 48.996879 | O12: =IF(A12="","",lbe_a/C12) -> 0.16504449 | P12: =IF(A12="","",INDEX(tbl_base_energia[kWh_UTL_FRIO],MATCH(A12,tbl_base_energia[Mes],0))/(INDEX(tbl_base_energia[kWh_INJ],MATCH(A12,tbl_base_energia[Mes],0))+INDEX(tbl_base_energia[kWh_SOP],MATCH(A12,tbl_base_energia[Mes],0)))) -> 0.11420541 | Q12: =IF(A12="","",INDEX(tbl_base_energia[kWh_UTL_AR],MATCH(A12,tbl_base_energia[Mes],0))/(INDEX(tbl_base_energia[kWh_INJ],MATCH(A12,tbl_base_energia[Mes],0))+INDEX(tbl_base_energia[kWh_SOP],MATCH(A12,tbl_base_energia[Mes],0))+INDEX(tbl_base_energia[kWh_SER],MATCH(A12,tbl_base_energia[Mes],0))+INDEX(tbl_base_energia[kWh_HFS],MATCH(A12,tbl_base_energia[Mes],0)))) -> 0.18765789 | R12: =IF(A12="","",INDEX(tbl_base_energia[Energia_Final_MWh],MATCH(A12,tbl_base_energia[Mes],0))) -> 571.275
A13: 45962 | B13: =IF(A13="","",INDEX(tbl_base_energia[Periodo],MATCH(A13,tbl_base_energia[Mes],0))) -> Referência (LBE) | C13: =IF(A13="","",INDEX(tbl_base_energia[kWh_Total],MATCH(A13,tbl_base_energia[Mes],0))-INDEX(tbl_base_energia[kWh_Maquinas_Novas],MATCH(A13,tbl_base_energia[Mes],0))) -> 561643 | D13: =IF(A13="","",(INDEX(tbl_base_energia[Unid_INJ],MATCH(A13,tbl_base_energia[Mes],0))+INDEX(tbl_base_energia[Unid_SOP],MATCH(A13,tbl_base_energia[Mes],0))-INDEX(tbl_base_energia[Unid_Maquinas_Novas],MATCH(A13,tbl_base_energia[Mes],0)))/1000) -> 4974.09 | E13: =IF(A13="","",INDEX(tbl_base_energia[CDD_15],MATCH(A13,tbl_base_energia[Mes],0))) -> 0 | F13: =IF(A13="","",lbe_a+lbe_b1*D13+lbe_b2*E13) -> 549528.04 | G13: =IF(A13="","",C13-F13) -> 12114.958 | H13: =IF(A13="","",SUM($G$5:G13)) -> 1146.9172 | I13: =IF(A13="","",-G13/F13) -> -0.022046114 | J13: =IF(A13="","",IF(AND(D13>=dom_x1_min,D13<=dom_x1_max,E13>=dom_x2_min,E13<=dom_x2_max),"Sim","Não")) -> Sim | K13: =IF(A13="","",IF(B13="Referência (LBE)","Referência",IF(J13="Não","Fora do domínio",IF(G13>lbe_limite,"Desvio significativo",IF(G13<-lbe_limite,"Melhoria significativa","Dentro da incerteza"))))) -> Referência | L13: =IF(A13="","",INDEX(tbl_base_energia[kWh_Total],MATCH(A13,tbl_base_energia[Mes],0))/(INDEX(tbl_base_energia[Unid_INJ],MATCH(A13,tbl_base_energia[Mes],0))+INDEX(tbl_base_energia[Unid_SOP],MATCH(A13,tbl_base_energia[Mes],0)))*1000) -> 112.91372 | M13: =IF(A13="","",INDEX(tbl_base_energia[kWh_SOP],MATCH(A13,tbl_base_energia[Mes],0))/INDEX(tbl_base_energia[Unid_SOP],MATCH(A13,tbl_base_energia[Mes],0))*1000) -> 115.30164 | N13: =IF(A13="","",INDEX(tbl_base_energia[kWh_INJ],MATCH(A13,tbl_base_energia[Mes],0))/INDEX(tbl_base_energia[Unid_INJ],MATCH(A13,tbl_base_energia[Mes],0))*1000) -> 49.423668 | O13: =IF(A13="","",lbe_a/C13) -> 0.16713648 | P13: =IF(A13="","",INDEX(tbl_base_energia[kWh_UTL_FRIO],MATCH(A13,tbl_base_energia[Mes],0))/(INDEX(tbl_base_energia[kWh_INJ],MATCH(A13,tbl_base_energia[Mes],0))+INDEX(tbl_base_energia[kWh_SOP],MATCH(A13,tbl_base_energia[Mes],0)))) -> 0.091511891 | Q13: =IF(A13="","",INDEX(tbl_base_energia[kWh_UTL_AR],MATCH(A13,tbl_base_energia[Mes],0))/(INDEX(tbl_base_energia[kWh_INJ],MATCH(A13,tbl_base_energia[Mes],0))+INDEX(tbl_base_energia[kWh_SOP],MATCH(A13,tbl_base_energia[Mes],0))+INDEX(tbl_base_energia[kWh_SER],MATCH(A13,tbl_base_energia[Mes],0))+INDEX(tbl_base_energia[kWh_HFS],MATCH(A13,tbl_base_energia[Mes],0)))) -> 0.18897825 | R13: =IF(A13="","",INDEX(tbl_base_energia[Energia_Final_MWh],MATCH(A13,tbl_base_energia[Mes],0))) -> 564.121
A14: 45992 | B14: =IF(A14="","",INDEX(tbl_base_energia[Periodo],MATCH(A14,tbl_base_energia[Mes],0))) -> Referência (LBE) | C14: =IF(A14="","",INDEX(tbl_base_energia[kWh_Total],MATCH(A14,tbl_base_energia[Mes],0))-INDEX(tbl_base_energia[kWh_Maquinas_Novas],MATCH(A14,tbl_base_energia[Mes],0))) -> 582602 | D14: =IF(A14="","",(INDEX(tbl_base_energia[Unid_INJ],MATCH(A14,tbl_base_energia[Mes],0))+INDEX(tbl_base_energia[Unid_SOP],MATCH(A14,tbl_base_energia[Mes],0))-INDEX(tbl_base_energia[Unid_Maquinas_Novas],MATCH(A14,tbl_base_energia[Mes],0)))/1000) -> 5221.94 | E14: =IF(A14="","",INDEX(tbl_base_energia[CDD_15],MATCH(A14,tbl_base_energia[Mes],0))) -> 0 | F14: =IF(A14="","",lbe_a+lbe_b1*D14+lbe_b2*E14) -> 572232.62 | G14: =IF(A14="","",C14-F14) -> 10369.385 | H14: =IF(A14="","",SUM($G$5:G14)) -> 11516.302 | I14: =IF(A14="","",-G14/F14) -> -0.018120926 | J14: =IF(A14="","",IF(AND(D14>=dom_x1_min,D14<=dom_x1_max,E14>=dom_x2_min,E14<=dom_x2_max),"Sim","Não")) -> Sim | K14: =IF(A14="","",IF(B14="Referência (LBE)","Referência",IF(J14="Não","Fora do domínio",IF(G14>lbe_limite,"Desvio significativo",IF(G14<-lbe_limite,"Melhoria significativa","Dentro da incerteza"))))) -> Referência | L14: =IF(A14="","",INDEX(tbl_base_energia[kWh_Total],MATCH(A14,tbl_base_energia[Mes],0))/(INDEX(tbl_base_energia[Unid_INJ],MATCH(A14,tbl_base_energia[Mes],0))+INDEX(tbl_base_energia[Unid_SOP],MATCH(A14,tbl_base_energia[Mes],0)))*1000) -> 111.56811 | M14: =IF(A14="","",INDEX(tbl_base_energia[kWh_SOP],MATCH(A14,tbl_base_energia[Mes],0))/INDEX(tbl_base_energia[Unid_SOP],MATCH(A14,tbl_base_energia[Mes],0))*1000) -> 113.73051 | N14: =IF(A14="","",INDEX(tbl_base_energia[kWh_INJ],MATCH(A14,tbl_base_energia[Mes],0))/INDEX(tbl_base_energia[Unid_INJ],MATCH(A14,tbl_base_energia[Mes],0))*1000) -> 49.57937 | O14: =IF(A14="","",lbe_a/C14) -> 0.16112378 | P14: =IF(A14="","",INDEX(tbl_base_energia[kWh_UTL_FRIO],MATCH(A14,tbl_base_energia[Mes],0))/(INDEX(tbl_base_energia[kWh_INJ],MATCH(A14,tbl_base_energia[Mes],0))+INDEX(tbl_base_energia[kWh_SOP],MATCH(A14,tbl_base_energia[Mes],0)))) -> 0.085871552 | Q14: =IF(A14="","",INDEX(tbl_base_energia[kWh_UTL_AR],MATCH(A14,tbl_base_energia[Mes],0))/(INDEX(tbl_base_energia[kWh_INJ],MATCH(A14,tbl_base_energia[Mes],0))+INDEX(tbl_base_energia[kWh_SOP],MATCH(A14,tbl_base_energia[Mes],0))+INDEX(tbl_base_energia[kWh_SER],MATCH(A14,tbl_base_energia[Mes],0))+INDEX(tbl_base_energia[kWh_HFS],MATCH(A14,tbl_base_energia[Mes],0)))) -> 0.1846362 | R14: =IF(A14="","",INDEX(tbl_base_energia[Energia_Final_MWh],MATCH(A14,tbl_base_energia[Mes],0))) -> 585.066
A15: 46023 | B15: =IF(A15="","",INDEX(tbl_base_energia[Periodo],MATCH(A15,tbl_base_energia[Mes],0))) -> Referência (LBE) | C15: =IF(A15="","",INDEX(tbl_base_energia[kWh_Total],MATCH(A15,tbl_base_energia[Mes],0))-INDEX(tbl_base_energia[kWh_Maquinas_Novas],MATCH(A15,tbl_base_energia[Mes],0))) -> 567251 | D15: =IF(A15="","",(INDEX(tbl_base_energia[Unid_INJ],MATCH(A15,tbl_base_energia[Mes],0))+INDEX(tbl_base_energia[Unid_SOP],MATCH(A15,tbl_base_energia[Mes],0))-INDEX(tbl_base_energia[Unid_Maquinas_Novas],MATCH(A15,tbl_base_energia[Mes],0)))/1000) -> 5272.284 | E15: =IF(A15="","",INDEX(tbl_base_energia[CDD_15],MATCH(A15,tbl_base_energia[Mes],0))) -> 0 | F15: =IF(A15="","",lbe_a+lbe_b1*D15+lbe_b2*E15) -> 576844.43 | G15: =IF(A15="","",C15-F15) -> -9593.4327 | H15: =IF(A15="","",SUM($G$5:G15)) -> 1922.8695 | I15: =IF(A15="","",-G15/F15) -> 0.016630884 | J15: =IF(A15="","",IF(AND(D15>=dom_x1_min,D15<=dom_x1_max,E15>=dom_x2_min,E15<=dom_x2_max),"Sim","Não")) -> Sim | K15: =IF(A15="","",IF(B15="Referência (LBE)","Referência",IF(J15="Não","Fora do domínio",IF(G15>lbe_limite,"Desvio significativo",IF(G15<-lbe_limite,"Melhoria significativa","Dentro da incerteza"))))) -> Referência | L15: =IF(A15="","",INDEX(tbl_base_energia[kWh_Total],MATCH(A15,tbl_base_energia[Mes],0))/(INDEX(tbl_base_energia[Unid_INJ],MATCH(A15,tbl_base_energia[Mes],0))+INDEX(tbl_base_energia[Unid_SOP],MATCH(A15,tbl_base_energia[Mes],0)))*1000) -> 107.59113 | M15: =IF(A15="","",INDEX(tbl_base_energia[kWh_SOP],MATCH(A15,tbl_base_energia[Mes],0))/INDEX(tbl_base_energia[Unid_SOP],MATCH(A15,tbl_base_energia[Mes],0))*1000) -> 116.54359 | N15: =IF(A15="","",INDEX(tbl_base_energia[kWh_INJ],MATCH(A15,tbl_base_energia[Mes],0))/INDEX(tbl_base_energia[Unid_INJ],MATCH(A15,tbl_base_energia[Mes],0))*1000) -> 47.904912 | O15: =IF(A15="","",lbe_a/C15) -> 0.16548413 | P15: =IF(A15="","",INDEX(tbl_base_energia[kWh_UTL_FRIO],MATCH(A15,tbl_base_energia[Mes],0))/(INDEX(tbl_base_energia[kWh_INJ],MATCH(A15,tbl_base_energia[Mes],0))+INDEX(tbl_base_energia[kWh_SOP],MATCH(A15,tbl_base_energia[Mes],0)))) -> 0.071929704 | Q15: =IF(A15="","",INDEX(tbl_base_energia[kWh_UTL_AR],MATCH(A15,tbl_base_energia[Mes],0))/(INDEX(tbl_base_energia[kWh_INJ],MATCH(A15,tbl_base_energia[Mes],0))+INDEX(tbl_base_energia[kWh_SOP],MATCH(A15,tbl_base_energia[Mes],0))+INDEX(tbl_base_energia[kWh_SER],MATCH(A15,tbl_base_energia[Mes],0))+INDEX(tbl_base_energia[kWh_HFS],MATCH(A15,tbl_base_energia[Mes],0)))) -> 0.19075787 | R15: =IF(A15="","",INDEX(tbl_base_energia[Energia_Final_MWh],MATCH(A15,tbl_base_energia[Mes],0))) -> 570.265
A16: 46054 | B16: =IF(A16="","",INDEX(tbl_base_energia[Periodo],MATCH(A16,tbl_base_energia[Mes],0))) -> Referência (LBE) | C16: =IF(A16="","",INDEX(tbl_base_energia[kWh_Total],MATCH(A16,tbl_base_energia[Mes],0))-INDEX(tbl_base_energia[kWh_Maquinas_Novas],MATCH(A16,tbl_base_energia[Mes],0))) -> 527749 | D16: =IF(A16="","",(INDEX(tbl_base_energia[Unid_INJ],MATCH(A16,tbl_base_energia[Mes],0))+INDEX(tbl_base_energia[Unid_SOP],MATCH(A16,tbl_base_energia[Mes],0))-INDEX(tbl_base_energia[Unid_Maquinas_Novas],MATCH(A16,tbl_base_energia[Mes],0)))/1000) -> 4757.334 | E16: =IF(A16="","",INDEX(tbl_base_energia[CDD_15],MATCH(A16,tbl_base_energia[Mes],0))) -> 0 | F16: =IF(A16="","",lbe_a+lbe_b1*D16+lbe_b2*E16) -> 529671.87 | G16: =IF(A16="","",C16-F16) -> -1922.8695 | H16: =IF(A16="","",SUM($G$5:G16)) -> -2.910383e-10 | I16: =IF(A16="","",-G16/F16) -> 0.0036303032 | J16: =IF(A16="","",IF(AND(D16>=dom_x1_min,D16<=dom_x1_max,E16>=dom_x2_min,E16<=dom_x2_max),"Sim","Não")) -> Sim | K16: =IF(A16="","",IF(B16="Referência (LBE)","Referência",IF(J16="Não","Fora do domínio",IF(G16>lbe_limite,"Desvio significativo",IF(G16<-lbe_limite,"Melhoria significativa","Dentro da incerteza"))))) -> Referência | L16: =IF(A16="","",INDEX(tbl_base_energia[kWh_Total],MATCH(A16,tbl_base_energia[Mes],0))/(INDEX(tbl_base_energia[Unid_INJ],MATCH(A16,tbl_base_energia[Mes],0))+INDEX(tbl_base_energia[Unid_SOP],MATCH(A16,tbl_base_energia[Mes],0)))*1000) -> 110.93377 | M16: =IF(A16="","",INDEX(tbl_base_energia[kWh_SOP],MATCH(A16,tbl_base_energia[Mes],0))/INDEX(tbl_base_energia[Unid_SOP],MATCH(A16,tbl_base_energia[Mes],0))*1000) -> 110.68646 | N16: =IF(A16="","",INDEX(tbl_base_energia[kWh_INJ],MATCH(A16,tbl_base_energia[Mes],0))/INDEX(tbl_base_energia[Unid_INJ],MATCH(A16,tbl_base_energia[Mes],0))*1000) -> 49.831451 | O16: =IF(A16="","",lbe_a/C16) -> 0.17787061 | P16: =IF(A16="","",INDEX(tbl_base_energia[kWh_UTL_FRIO],MATCH(A16,tbl_base_energia[Mes],0))/(INDEX(tbl_base_energia[kWh_INJ],MATCH(A16,tbl_base_energia[Mes],0))+INDEX(tbl_base_energia[kWh_SOP],MATCH(A16,tbl_base_energia[Mes],0)))) -> 0.08590604 | Q16: =IF(A16="","",INDEX(tbl_base_energia[kWh_UTL_AR],MATCH(A16,tbl_base_energia[Mes],0))/(INDEX(tbl_base_energia[kWh_INJ],MATCH(A16,tbl_base_energia[Mes],0))+INDEX(tbl_base_energia[kWh_SOP],MATCH(A16,tbl_base_energia[Mes],0))+INDEX(tbl_base_energia[kWh_SER],MATCH(A16,tbl_base_energia[Mes],0))+INDEX(tbl_base_energia[kWh_HFS],MATCH(A16,tbl_base_energia[Mes],0)))) -> 0.18913752 | R16: =IF(A16="","",INDEX(tbl_base_energia[Energia_Final_MWh],MATCH(A16,tbl_base_energia[Mes],0))) -> 530.816
... A26: 46357 | B26: =IF(A26="","",INDEX(tbl_base_energia[Periodo],MATCH(A26,tbl_base_energia[Mes],0))) -> Reporte | C26: =IF(A26="","",INDEX(tbl_base_energia[kWh_Total],MATCH(A26,tbl_base_energia[Mes],0))-INDEX(tbl_base_energia[kWh_Maquinas_Novas],MATCH(A26,tbl_base_energia[Mes],0))) -> 513562 | D26: =IF(A26="","",(INDEX(tbl_base_energia[Unid_INJ],MATCH(A26,tbl_base_energia[Mes],0))+INDEX(tbl_base_energia[Unid_SOP],MATCH(A26,tbl_base_energia[Mes],0))-INDEX(tbl_base_energia[Unid_Maquinas_Novas],MATCH(A26,tbl_base_energia[Mes],0)))/1000) -> 5067.039 | E26: =IF(A26="","",INDEX(tbl_base_energia[CDD_15],MATCH(A26,tbl_base_energia[Mes],0))) -> 0 | F26: =IF(A26="","",lbe_a+lbe_b1*D26+lbe_b2*E26) -> 558042.74 | G26: =IF(A26="","",C26-F26) -> -44480.738 | H26: =IF(A26="","",SUM($G$5:G26)) -> -81639.974 | I26: =IF(A26="","",-G26/F26) -> 0.079708479 | J26: =IF(A26="","",IF(AND(D26>=dom_x1_min,D26<=dom_x1_max,E26>=dom_x2_min,E26<=dom_x2_max),"Sim","Não")) -> Sim | K26: =IF(A26="","",IF(B26="Referência (LBE)","Referência",IF(J26="Não","Fora do domínio",IF(G26>lbe_limite,"Desvio significativo",IF(G26<-lbe_limite,"Melhoria significativa","Dentro da incerteza"))))) -> Melhoria significativa | L26: =IF(A26="","",INDEX(tbl_base_energia[kWh_Total],MATCH(A26,tbl_base_energia[Mes],0))/(INDEX(tbl_base_energia[Unid_INJ],MATCH(A26,tbl_base_energia[Mes],0))+INDEX(tbl_base_energia[Unid_SOP],MATCH(A26,tbl_base_energia[Mes],0)))*1000) -> 97.763809 | M26: =IF(A26="","",INDEX(tbl_base_energia[kWh_SOP],MATCH(A26,tbl_base_energia[Mes],0))/INDEX(tbl_base_energia[Unid_SOP],MATCH(A26,tbl_base_energia[Mes],0))*1000) -> 109.85156 | N26: =IF(A26="","",INDEX(tbl_base_energia[kWh_INJ],MATCH(A26,tbl_base_energia[Mes],0))/INDEX(tbl_base_energia[Unid_INJ],MATCH(A26,tbl_base_energia[Mes],0))*1000) -> 45.829258 | O26: =IF(A26="","",lbe_a/C26) -> 0.18278423 | P26: =IF(A26="","",INDEX(tbl_base_energia[kWh_UTL_FRIO],MATCH(A26,tbl_base_energia[Mes],0))/(INDEX(tbl_base_energia[kWh_INJ],MATCH(A26,tbl_base_energia[Mes],0))+INDEX(tbl_base_energia[kWh_SOP],MATCH(A26,tbl_base_energia[Mes],0)))) -> 0.080503693 | Q26: =IF(A26="","",INDEX(tbl_base_energia[kWh_UTL_AR],MATCH(A26,tbl_base_energia[Mes],0))/(INDEX(tbl_base_energia[kWh_INJ],MATCH(A26,tbl_base_energia[Mes],0))+INDEX(tbl_base_energia[kWh_SOP],MATCH(A26,tbl_base_energia[Mes],0))+INDEX(tbl_base_energia[kWh_SER],MATCH(A26,tbl_base_energia[Mes],0))+INDEX(tbl_base_energia[kWh_HFS],MATCH(A26,tbl_base_energia[Mes],0)))) -> 0.15631318 | R26: =IF(A26="","",INDEX(tbl_base_energia[Energia_Final_MWh],MATCH(A26,tbl_base_energia[Mes],0))) -> 678.51

Sheet LBE_Modelo
A1: LBE-01 — MODELO ESTATÍSTICO, VALIDADE E DEMONSTRAÇÃO DA MELHORIA — calculado
A2: kWh ajustado = a + b1 × (mil unidades INJ+SOP) + b2 × CDD₁₅ · Referência 2025-03-01 a 2026-02-28 (12 meses) · LINEST sobre IDE_Mensal
A4: Termo | B4: Coeficiente | C4: Erro-padrão | D4: t | E4: p-valor | F4: Cumpre p < 0,2? | G4: Interpretação
A5: a — carga de base (kWh/mês) | B5: =INDEX(LINEST(IDE_Mensal!$C$5:$C$16,IDE_Mensal!$D$5:$E$16,TRUE,TRUE),1,3) -> 93871.037 | C5: =INDEX(LINEST(IDE_Mensal!$C$5:$C$16,IDE_Mensal!$D$5:$E$16,TRUE,TRUE),2,3) -> 95670.531 | D5: =IFERROR(B5/C5,"") -> 0.98119072 | E5: =IFERROR(TDIST(ABS(D5),lbe_df,2),"") -> 0.35213713 | F5: =IF(E5="","",IF(E5<0.2,"Sim","Não")) -> Não | G5: Energia consumida sem produção nem calor: iluminação, AVAC, utilidades em vazio, máquinas em espera (≈ 'base load' de Kent).
A6: b1 — kWh por mil unidades (INJ+SOP) | B6: =INDEX(LINEST(IDE_Mensal!$C$5:$C$16,IDE_Mensal!$D$5:$E$16,TRUE,TRUE),1,2) -> 91.606104 | C6: =INDEX(LINEST(IDE_Mensal!$C$5:$C$16,IDE_Mensal!$D$5:$E$16,TRUE,TRUE),2,2) -> 18.979981 | D6: =IFERROR(B6/C6,"") -> 4.8264592 | E6: =IFERROR(TDIST(ABS(D6),lbe_df,2),"") -> 0.00093851091 | F6: =IF(E6="","",IF(E6<0.2,"Sim","Não")) -> Sim | G6: Consumo marginal de produção: cada mil unidades adicionais custam b1 kWh.
A7: b2 — kWh por grau-dia de arrefecimento | B7: =INDEX(LINEST(IDE_Mensal!$C$5:$C$16,IDE_Mensal!$D$5:$E$16,TRUE,TRUE),1,1) -> 56.464409 | C7: =INDEX(LINEST(IDE_Mensal!$C$5:$C$16,IDE_Mensal!$D$5:$E$16,TRUE,TRUE),2,1) -> 48.058908 | D7: =IFERROR(B7/C7,"") -> 1.1749 | E7: =IFERROR(TDIST(ABS(D7),lbe_df,2),"") -> 0.27018198 | F7: =IF(E7="","",IF(E7<0.2,"Sim","Não")) -> Não | G7: Efeito do calor no arrefecimento de moldes e no AVAC.
A9: Estatística do modelo | B9: Valor
A10: R² | B10: =INDEX(LINEST(IDE_Mensal!$C$5:$C$16,IDE_Mensal!$D$5:$E$16,TRUE,TRUE),3,1) -> 0.75328415
A11: Erro-padrão da estimativa (kWh) | B11: =INDEX(LINEST(IDE_Mensal!$C$5:$C$16,IDE_Mensal!$D$5:$E$16,TRUE,TRUE),3,2) -> 15599.313
A12: Estatística F | B12: =INDEX(LINEST(IDE_Mensal!$C$5:$C$16,IDE_Mensal!$D$5:$E$16,TRUE,TRUE),4,1) -> 13.739606
A13: Graus de liberdade (n − p − 1) | B13: =INDEX(LINEST(IDE_Mensal!$C$5:$C$16,IDE_Mensal!$D$5:$E$16,TRUE,TRUE),4,2) -> 9
A14: p-valor do teste F | B14: =FDIST(lbe_f,2,lbe_df) -> 0.0018402921
A15: Média de Y na referência (kWh) | B15: =AVERAGE(IDE_Mensal!$C$5:$C$16) -> 562748.83
A16: CV(RMSE) | B16: =lbe_sey/lbe_ymed -> 0.02771985
A17: NMBE | B17: =SUM(IDE_Mensal!$G$5:$G$16)/((COUNT(IDE_Mensal!$C$5:$C$16)-3)*lbe_ymed) -> -5.7463628e-17
A18: t(95%; gl) | B18: =TINV(0.05,lbe_df) -> 2.2621572
A19: Limite de desvio significativo mensal (kWh) = t × erro-padrão | B19: =lbe_t*lbe_sey -> 35288.098
A20: Carga de base em % do consumo médio | B20: =lbe_a/lbe_ymed -> 0.16680805
A22: Teste de validade | B22: Valor | C22: Critério | D22: Resultado | F22: Fonte do critério | G22: Leitura
A23: R² (EnPI Lite) | B23: =lbe_r2 -> 0.75328415 | C23: ≥ 0,50 | D23: =IF(lbe_r2>=0.5,"Cumpre","Não cumpre") -> Cumpre | F23: LBNL EnPI Lite / 50001 Ready M&V | G23: Fração da variação mensal explicada pelas variáveis.
A24: R² (ASHRAE 14, recomendado) | B24: =lbe_r2 -> 0.75328415 | C24: > 0,75 | D24: =IF(lbe_r2>0.75,"Cumpre","Não cumpre") -> Cumpre | F24: ASHRAE Guideline 14 | G24: Recomendação para modelos mensais; valores perto do limite pedem mais dados medidos.
A25: p-valor de todas as variáveis | B25: =MAX(E6:E7) -> 0.27018198 | C25: < 0,20 | D25: =IF(MAX(E6:E7)<0.2,"Cumpre","Não cumpre") -> Não cumpre | F25: LBNL EnPI Lite | G25: Cada variável relevante tem efeito estatisticamente distinguível.
A26: p-valor de pelo menos uma variável | B26: =MIN(E6:E7) -> 0.00093851091 | C26: < 0,10 | D26: =IF(MIN(E6:E7)<0.1,"Cumpre","Não cumpre") -> Cumpre | F26: LBNL EnPI Lite
A27: p-valor do teste F | B27: =lbe_pf -> 0.0018402921 | C27: < 0,10 | D27: =IF(lbe_pf<0.1,"Cumpre","Não cumpre") -> Cumpre | F27: LBNL EnPI Lite | G27: O modelo no seu conjunto é significativo.
A28: CV(RMSE) | B28: =lbe_cv -> 0.02771985 | C28: ≤ 15% | D28: =IF(lbe_cv<=0.15,"Cumpre","Não cumpre") -> Cumpre | F28: ASHRAE Guideline 14 (mensal) | G28: Dispersão do modelo face à média — base da incerteza da poupança.
A29: NMBE | B29: =lbe_nmbe -> -5.7463628e-17 | C29: entre −5% e +5% | D29: =IF(ABS(lbe_nmbe)<=0.05,"Cumpre","Não cumpre") -> Cumpre | F29: ASHRAE Guideline 14 | G29: Sem enviesamento sistemático (≈ 0 por construção em mínimos quadrados).
A30: Modelo válido para a LBE-01? | B30: =IF(COUNTIF(D23:D29,"Não cumpre")=0,"Válido",IF(COUNTIF(D23:D29,"Não cumpre")=1,"Válido com reserva","Não válido")) -> Válido com reserva
A32: Domínio de validade (ISO 50006 §8.2) | B32: Mínimo | C32: Máximo | D32: Tolerância | E32: Mín. aceite | F32: Máx. aceite | G32: Nota
A33: X1 — mil unidades INJ+SOP | B33: =MIN(IDE_Mensal!$D$5:$D$16) -> 4543.947 | C33: =MAX(IDE_Mensal!$D$5:$D$16) -> 5443.656 | D33: 0.1 | E33: =B33*(1-D33) -> 4089.5523 | F33: =C33*(1+D33) -> 5988.0216 | G33: Fora destes limites o modelo extrapola: o mês não entra na demonstração da melhoria.
A34: X2 — CDD₁₅ | B34: =MIN(IDE_Mensal!$E$5:$E$16) -> 0 | C34: =MAX(IDE_Mensal!$E$5:$E$16) -> 251.1 | D34: 0.1 | E34: =B34*(1-D34) -> 0 | F34: =C34*(1+D34) -> 276.21 | G34: Com CDD = 0 no inverno, o mínimo aceite é 0.
A37: Demonstração da melhoria (ISO 50001 9.1.1 e 10.2; ISO 50006 §10.3) | B37: Valor | G37: Leitura
A38: Meses de reporte | B38: =COUNTIF(tbl_ide_mensal[Periodo],"Reporte") -> 10
A39: Meses de reporte dentro do domínio (m) | B39: =COUNTIFS(tbl_ide_mensal[Periodo],"Reporte",tbl_ide_mensal[Dentro_Dominio],"Sim") -> 9 | G39: Só estes meses servem para demonstrar melhoria.
A40: Σ kWh esperado (dentro do domínio) | B40: =SUMIFS(tbl_ide_mensal[kWh_Esperado],tbl_ide_mensal[Periodo],"Reporte",tbl_ide_mensal[Dentro_Dominio],"Sim") -> 5146702.1
A41: Σ kWh real ajustado (dentro do domínio) | B41: =SUMIFS(tbl_ide_mensal[Y_kWh_Ajustado],tbl_ide_mensal[Periodo],"Reporte",tbl_ide_mensal[Dentro_Dominio],"Sim") -> 5047066
A42: Poupança normalizada (kWh) = esperado − real | B42: =B40-B41 -> 99636.085 | G42: Positivo = melhoria; negativo = piorou.
A43: Melhoria do desempenho energético (%) | B43: =IFERROR(B42/B40,"") -> 0.01935921 | G43: IDE-01 agregado no período de reporte.
A44: Incerteza a 95% (kWh) ≈ t × erro-padrão × √m | B44: =lbe_t*lbe_sey*SQRT(B39) -> 105864.29 | G44: Aproximação da ASHRAE 14 sem termos de alavancagem (conservadora para m pequeno).
A45: Conclusão | B45: =IF(B39=0,"Sem meses válidos",IF(B42>B44,"Melhoria DEMONSTRADA (estatisticamente significativa)",IF(B42<-B44,"Piorou (desvio significativo)","Melhoria NÃO demonstrada: diferença dentro da incerteza do modelo"))) -> Melhoria NÃO demonstrada: diferença dentro da incerteza do modelo | G45: Para a certificação (ISO 50003:2021) a melhoria tem de ser demonstrada; ver RG-SGE-11 (M&V por ação) e PA-E-01 (submedição).
A47: Após as ações de standby e ar comprimido (out–dez/2026) | B47: Valor | G47: Leitura
A48: Meses dentro do domínio (m) | B48: =COUNTIFS(tbl_ide_mensal[Mes],">="&DATE(2026,10,1),tbl_ide_mensal[Dentro_Dominio],"Sim") -> 3
A49: Σ kWh esperado | B49: =SUMIFS(tbl_ide_mensal[kWh_Esperado],tbl_ide_mensal[Mes],">="&DATE(2026,10,1),tbl_ide_mensal[Dentro_Dominio],"Sim") -> 1694240.7
A50: Σ kWh real ajustado | B50: =SUMIFS(tbl_ide_mensal[Y_kWh_Ajustado],tbl_ide_mensal[Mes],">="&DATE(2026,10,1),tbl_ide_mensal[Dentro_Dominio],"Sim") -> 1602311
A51: Poupança normalizada (kWh) | B51: =B49-B50 -> 91929.714 | G51: Comparar com a poupança verificada por ação (RG-SGE-11).
A52: Melhoria (%) | B52: =IFERROR(B51/B49,"") -> 0.054260126
A53: Incerteza a 95% (kWh) | B53: =lbe_t*lbe_sey*SQRT(B48) -> 61120.779
A54: Conclusão | B54: =IF(B48=0,"Sem meses válidos",IF(B51>B53,"Melhoria DEMONSTRADA (estatisticamente significativa)",IF(B51<-B53,"Piorou (desvio significativo)","Melhoria NÃO demonstrada: diferença dentro da incerteza do modelo"))) -> Melhoria DEMONSTRADA (estatisticamente significativa) | G54: Evidência para a ISO 50003: melhoria demonstrada depois da implementação das ações (ISO 50006 §10.3).

Sheet Variaveis_Relevantes
A1: VARIÁVEIS RELEVANTES CANDIDATAS — SELEÇÃO (ISO 50006 §5.5)
A2: Correlação calculada nos 12 meses de referência · Critério de relevância: significativa no modelo (p < 0,2) e com explicação física
A4: ID_Variavel | B4: Variavel | C4: Coluna_Base | D4: Fonte | E4: Unidade | F4: Correlacao_com_kWh | G4: R2_Simples | H4: Decisao | I4: Justificacao
A5: VAR-01 | B5: Unidades produzidas INJ + SOP | C5: Unid_INJ | D5: Dataset (MES) | E5: un | F5: =SUMPRODUCT((Base_Mensal!$Q$5:$Q$16+Base_Mensal!$R$5:$R$16-AVERAGE(Base_Mensal!$Q$5:$Q$16)-AVERAGE(Base_Mensal!$R$5:$R$16))*(Base_Mensal!$I$5:$I$16-AVERAGE(Base_Mensal!$I$5:$I$16)))/SQRT(SUMPRODUCT((Base_Mensal!$Q$5:$Q$16+Base_Mensal!$R$5:$R$16-AVERAGE(Base_Mensal!$Q$5:$Q$16)-AVERAGE(Base_Mensal!$R$5:$R$16))^2)*SUMPRODUCT((Base_Mensal!$I$5:$I$16-AVERAGE(Base_Mensal!$I$5:$I$16))^2)) -> 0.84583905 | G5: =IF(A5="","",IFERROR(F5^2,"")) -> 0.71544369 | H5: Relevante | I5: Maior correlação com sentido físico; variável de negócio que a produção controla. Entra como X1 (soma INJ+SOP, milhares).
A6: VAR-02 | B6: Graus-dia de arrefecimento (base 15 °C) | C6: CDD_15 | D6: IPMA (via RG-SGA-13) | E6: °C·dia | F6: =CORREL(Base_Mensal!$I$5:$I$16,Base_Mensal!$H$5:$H$16) -> 0.33868759 | G6: =IF(A6="","",IFERROR(F6^2,"")) -> 0.11470929 | H6: Relevante (com reserva) | I6: Explica fisicamente o arrefecimento e o AVAC no verão e reduz o erro nos meses quentes, mas p ≈ 0,27 (> 0,2) com 12 meses de rateio. Mantida com reserva registada (LBE válida com reserva); reavaliar com os dados medidos dos analisadores (ALE-03).
A7: VAR-03 | B7: Horas de marcha da injeção | C7: Horas_INJ | D7: Dataset (MES) | E7: h | F7: =CORREL(Base_Mensal!$I$5:$I$16,Base_Mensal!$U$5:$U$16) -> 0.76162037 | G7: =IF(A7="","",IFERROR(F7^2,"")) -> 0.58006558 | H7: Redundante | I7: Muito correlacionada com as unidades (a energia do rateio é horas × kW). Não se usam as duas: preferidas as unidades (saída útil).
A8: VAR-04 | B8: Horas de marcha do sopro | C8: Horas_SOP | D8: Dataset (MES) | E8: h | F8: =CORREL(Base_Mensal!$I$5:$I$16,Base_Mensal!$V$5:$V$16) -> 0.93019174 | G8: =IF(A8="","",IFERROR(F8^2,"")) -> 0.86525667 | H8: Redundante | I8: Correlação mais alta que as unidades (a energia do rateio é horas × kW) e um modelo horas + CDD teria R² ≈ 0,86 — rejeitado: normalizar por horas esconderia as perdas de produtividade (marcha lenta, microparagens) que são desperdício de energia. A ISO 50006 recomenda variáveis de saída útil quando possível.
A9: VAR-05 | B9: Dias úteis | C9: Dias_Uteis | D9: Calendário | E9: dias | F9: =CORREL(Base_Mensal!$I$5:$I$16,Base_Mensal!$F$5:$F$16) -> 0.60898591 | G9: =IF(A9="","",IFERROR(F9^2,"")) -> 0.37086384 | H9: Excluída | I9: Efeito já captado pelas unidades produzidas; correlação fraca isoladamente.
A10: VAR-06 | B10: Temperatura média exterior | C10: Temp_Media_C | D10: IPMA | E10: °C | F10: =CORREL(Base_Mensal!$I$5:$I$16,Base_Mensal!$G$5:$G$16) -> 0.23025918 | G10: =IF(A10="","",IFERROR(F10^2,"")) -> 0.053019289 | H10: Redundante | I10: Substituída pelos graus-dia (relação não linear: só acima de 15 °C há carga de arrefecimento).

Sheet Catalogo_IDE
A1: CATÁLOGO DE INDICADORES DE DESEMPENHO ENERGÉTICO (6.4) — ISO 50006
A2: Mesmas colunas do RG-SGA-05 tbl_kpi nas primeiras 12 posições · Baseline e valor de reporte calculados a partir de IDE_Mensal
A4: ID_KPI | B4: Nome | C4: Formula_Calculo | D4: Unidade | E4: Polaridade | F4: Tipo_IDE_ISO50006 | G4: Frequencia | H4: Fonte_Dados | I4: Responsavel | J4: Baseline | K4: ID_OBJ | L4: ID_MED | M4: Fronteira | N4: ID_USE | O4: Variaveis_Relevantes | P4: Fatores_Estaticos | Q4: Normalizacao | R4: ID_LBE | S4: Utilizadores | T4: Coluna_Mensal | U4: Meta | V4: Valor_LBE_Externo | W4: Valor_Reporte_Externo | X4: Valor_Reporte | Y4: Variacao_vs_LBE | Z4: Estado | AA4: Ligacao_SGI | AB4: Qualidade_Dados
A5: IDE-01 | B5: Melhoria do desempenho energético da instalação (consumo normalizado) | C5: (kWh esperado pelo modelo da LBE − kWh real ajustado) ÷ kWh esperado | D5: % | E5: Maior | F5: Modelo estatístico (regressão linear múltipla) | G5: Mensal | H5: RG-SGA-13 (fatura) + dataset de produção + IPMA | I5: Gestor(a) de Energia (líder da equipa de gestão de energia) | J5: =IF(OR(A5="",T5="—"),V5,IFERROR(AVERAGE(INDEX(IDE_Mensal!$A$5:$R$16,0,MATCH(T5,IDE_Mensal!$A$4:$R$4,0))),"")) -> 0 | K5: OBJ-E-01 | L5: DAD-01; DAD-02; DAD-06 | M5: Instalação da Unidade 1 sem as 4 máquinas novas de 07/2026 (ajuste não rotineiro ALE-01) | N5: Todos | O5: Unidades INJ+SOP (mil); graus-dia de arrefecimento base 15 °C | P5: N.º de máquinas; turnos 3×8 em 5 dias; mix de produto; área; tipo de energia | Q5: Sim — modelo da LBE aplicado às condições do mês (ISO 50006 §8) | R5: LBE-01 | S5: Gestão de topo; equipa de gestão de energia; auditores do SGE; certificação ISO 50003 | T5: — | U5: 0.05 | V5: 0 | W5: =LBE_Modelo!$B$43 -> 0.01935921 | X5: =IF(A5="","",IF(T5="—",W5,IFERROR(AVERAGE(INDEX(IDE_Mensal!$A$17:$R$26,0,MATCH(T5,IDE_Mensal!$A$4:$R$4,0))),""))) -> 0.01935921 | Y5: =IF(OR(A5="",NOT(ISNUMBER(X5)),NOT(ISNUMBER(J5))),"",IF(ABS(J5)<0.000001,"",(X5-J5)/ABS(J5))) | Z5: =IF(A5="","",IF(OR(U5="",NOT(ISNUMBER(X5))),"Sem meta / sem dado",IF(E5="Maior",IF(X5>=U5,"Cumpre","Não cumpre"),IF(X5<=U5,"Cumpre","Não cumpre")))) -> Não cumpre | AA5: SGA OBJ-01 (mesma intenção; SGE mede normalizado) | AB5: Medido (fatura) + variáveis medidas
A6: IDE-02 | B6: Consumo específico de eletricidade da instalação (SEC) | C6: kWh total ÷ unidades INJ + SOP × 1 000 | D6: kWh/1.000 un | E6: Menor | F6: Rácio de valores medidos | G6: Mensal | H6: RG-SGA-13 + dataset | I6: Gerente de Manutenção | J6: =IF(OR(A6="",T6="—"),V6,IFERROR(AVERAGE(INDEX(IDE_Mensal!$A$5:$R$16,0,MATCH(T6,IDE_Mensal!$A$4:$R$4,0))),"")) -> 111.09142 | K6: OBJ-E-01 | L6: DAD-01; DAD-02 | M6: Instalação completa | N6: Todos | O6: — (rácio simples; não corrige a carga de base nem o clima) | P6: Idem IDE-01 | Q6: Não — rácio; a comparação exige cautela (Kent: o SEC mensal engana quando a produção varia) | R6: LBE-02 | S6: Relato externo (SGA KPI-01, ESRS E1-5, EMAS); SGCIE (consumo específico) | T6: SEC_Real | U6: 101 | X6: =IF(A6="","",IF(T6="—",W6,IFERROR(AVERAGE(INDEX(IDE_Mensal!$A$17:$R$26,0,MATCH(T6,IDE_Mensal!$A$4:$R$4,0))),""))) -> 106.61392 | Y6: =IF(OR(A6="",NOT(ISNUMBER(X6)),NOT(ISNUMBER(J6))),"",IF(ABS(J6)<0.000001,"",(X6-J6)/ABS(J6))) -> -0.040304671 | Z6: =IF(A6="","",IF(OR(U6="",NOT(ISNUMBER(X6))),"Sem meta / sem dado",IF(E6="Maior",IF(X6>=U6,"Cumpre","Não cumpre"),IF(X6<=U6,"Cumpre","Não cumpre")))) -> Não cumpre | AA6: SGA KPI-01 (mesmo cálculo) | AB6: Medido
A7: IDE-03 | B7: Consumo específico do sopro (ISBM) | C7: kWh do sopro ÷ frascos × 1 000 | D7: kWh/1.000 frascos | E7: Menor | F7: Rácio (numerador estimado) | G7: Mensal | H7: RG-SGA-13 (rateio por horas) + dataset; analisador QGBT-SOP a partir de 12/2026 | I7: Gerente de Produção | J7: =IF(OR(A7="",T7="—"),V7,IFERROR(AVERAGE(INDEX(IDE_Mensal!$A$5:$R$16,0,MATCH(T7,IDE_Mensal!$A$4:$R$4,0))),"")) -> 112.54659 | K7: OBJ-E-01 | L7: DAD-03 | M7: Máquinas ISBM-001 a 010 | N7: SOP | O7: Frascos produzidos; horas de marcha | P7: Tecnologia das máquinas; massa média do frasco | Q7: Não (até haver submedição) | R7: LBE-03 | S7: Produção; engenharia de processo | T7: SEC_SOP | X7: =IF(A7="","",IF(T7="—",W7,IFERROR(AVERAGE(INDEX(IDE_Mensal!$A$17:$R$26,0,MATCH(T7,IDE_Mensal!$A$4:$R$4,0))),""))) -> 115.25237 | Y7: =IF(OR(A7="",NOT(ISNUMBER(X7)),NOT(ISNUMBER(J7))),"",IF(ABS(J7)<0.000001,"",(X7-J7)/ABS(J7))) -> 0.024041406 | Z7: =IF(A7="","",IF(OR(U7="",NOT(ISNUMBER(X7))),"Sem meta / sem dado",IF(E7="Maior",IF(X7>=U7,"Cumpre","Não cumpre"),IF(X7<=U7,"Cumpre","Não cumpre")))) -> Sem meta / sem dado | AA7: — | AB7: Estimado (rateio)
A8: IDE-04 | B8: Consumo específico da injeção | C8: kWh da injeção ÷ tampas e potes × 1 000 | D8: kWh/1.000 un | E8: Menor | F8: Rácio (numerador estimado) | G8: Mensal | H8: RG-SGA-13 (rateio por horas) + dataset; analisador QGBT-INJ a partir de 12/2026 | I8: Gerente de Produção | J8: =IF(OR(A8="",T8="—"),V8,IFERROR(AVERAGE(INDEX(IDE_Mensal!$A$5:$R$16,0,MATCH(T8,IDE_Mensal!$A$4:$R$4,0))),"")) -> 48.814602 | K8: OBJ-E-01 | L8: DAD-03 | M8: Máquinas IM-001 a 008 | N8: INJ | O8: Peças produzidas; horas de marcha | P8: Tecnologia das máquinas; mix tampas/potes | Q8: Não (até haver submedição) | R8: LBE-04 | S8: Produção; engenharia de processo | T8: SEC_INJ | X8: =IF(A8="","",IF(T8="—",W8,IFERROR(AVERAGE(INDEX(IDE_Mensal!$A$17:$R$26,0,MATCH(T8,IDE_Mensal!$A$4:$R$4,0))),""))) -> 47.689961 | Y8: =IF(OR(A8="",NOT(ISNUMBER(X8)),NOT(ISNUMBER(J8))),"",IF(ABS(J8)<0.000001,"",(X8-J8)/ABS(J8))) -> -0.023039024 | Z8: =IF(A8="","",IF(OR(U8="",NOT(ISNUMBER(X8))),"Sem meta / sem dado",IF(E8="Maior",IF(X8>=U8,"Cumpre","Não cumpre"),IF(X8<=U8,"Cumpre","Não cumpre")))) -> Sem meta / sem dado | AA8: — | AB8: Estimado (rateio)
A9: IDE-05 | B9: Carga de base (energia não associada à produção) | C9: Coeficiente independente do modelo da LBE ÷ kWh real do mês | D9: % | E9: Menor | F9: Modelo estatístico (termo independente) | G9: Mensal | H9: Modelo LBE-01 | I9: Gestor(a) de Energia (líder da equipa de gestão de energia) | J9: =IF(OR(A9="",T9="—"),V9,IFERROR(AVERAGE(INDEX(IDE_Mensal!$A$5:$R$16,0,MATCH(T9,IDE_Mensal!$A$4:$R$4,0))),"")) -> 0.16719634 | K9: OBJ-E-03 | L9: DAD-01 | M9: Instalação | N9: Todos | O9: — | P9: Idem IDE-01 | Q9: Derivado do modelo | R9: LBE-01 | S9: Gestão; operação e manutenção | T9: Carga_Base_Pct | U9: 0.14 | X9: =IF(A9="","",IF(T9="—",W9,IFERROR(AVERAGE(INDEX(IDE_Mensal!$A$17:$R$26,0,MATCH(T9,IDE_Mensal!$A$4:$R$4,0))),""))) -> 0.16615393 | Y9: =IF(OR(A9="",NOT(ISNUMBER(X9)),NOT(ISNUMBER(J9))),"",IF(ABS(J9)<0.000001,"",(X9-J9)/ABS(J9))) -> -0.0062346332 | Z9: =IF(A9="","",IF(OR(U9="",NOT(ISNUMBER(X9))),"Sem meta / sem dado",IF(E9="Maior",IF(X9>=U9,"Cumpre","Não cumpre"),IF(X9<=U9,"Cumpre","Não cumpre")))) -> Não cumpre | AA9: — | AB9: Calculado
A10: IDE-06 | B10: Rácio de arrefecimento (frio ÷ energia de injeção + sopro) | C10: kWh chiller/torre ÷ (kWh INJ + kWh SOP) | D10: fração | E10: Menor | F10: Rácio (estimado) | G10: Mensal | H10: RG-SGA-13 (rateio com fator de temperatura) | I10: Técnico de Utilidades | J10: =IF(OR(A10="",T10="—"),V10,IFERROR(AVERAGE(INDEX(IDE_Mensal!$A$5:$R$16,0,MATCH(T10,IDE_Mensal!$A$4:$R$4,0))),"")) -> 0.10679346 | K10: OBJ-E-04 | L10: DAD-04 | M10: Sistema de arrefecimento CH-01/TR-01 | N10: UTL-FRIO | O10: Temperatura exterior; carga térmica | P10: Setpoint da água gelada; n.º de moldes | Q10: Não — rácio sazonal: comparar o mesmo mês do ano ou normalizar por graus-dia (ISO 50006 §8); o reporte mar–ago contra a média anual penaliza o IDE | R10: LBE-05 | S10: Utilidades; manutenção | T10: Racio_Frio | U10: 0.095 | X10: =IF(A10="","",IF(T10="—",W10,IFERROR(AVERAGE(INDEX(IDE_Mensal!$A$17:$R$26,0,MATCH(T10,IDE_Mensal!$A$4:$R$4,0))),""))) -> 0.11425928 | Y10: =IF(OR(A10="",NOT(ISNUMBER(X10)),NOT(ISNUMBER(J10))),"",IF(ABS(J10)<0.000001,"",(X10-J10)/ABS(J10))) -> 0.069908987 | Z10: =IF(A10="","",IF(OR(U10="",NOT(ISNUMBER(X10))),"Sem meta / sem dado",IF(E10="Maior",IF(X10>=U10,"Cumpre","Não cumpre"),IF(X10<=U10,"Cumpre","Não cumpre")))) -> Não cumpre | AA10: — | AB10: Estimado
A11: IDE-07 | B11: Rácio de ar comprimido (ar ÷ energia dos processos) | C11: kWh ar comprimido ÷ kWh (INJ+SOP+SER+HFS) | D11: fração | E11: Menor | F11: Rácio (estimado — fator fixo) | G11: Mensal | H11: RG-SGA-13 (AR_FRAC = 0,19 fixo) | I11: Técnico de Utilidades | J11: =IF(OR(A11="",T11="—"),V11,IFERROR(AVERAGE(INDEX(IDE_Mensal!$A$5:$R$16,0,MATCH(T11,IDE_Mensal!$A$4:$R$4,0))),"")) -> 0.18975638 | K11: OBJ-E-02 | L11: DAD-05 | M11: Central de ar comprimido | N11: UTL-AR | O11: — | P11: — | Q11: Não — o valor é constante por construção: NÃO serve para demonstrar melhoria (substituído pelo IDE-08) | R11: — | S11: Utilidades | T11: Racio_Ar | X11: =IF(A11="","",IF(T11="—",W11,IFERROR(AVERAGE(INDEX(IDE_Mensal!$A$17:$R$26,0,MATCH(T11,IDE_Mensal!$A$4:$R$4,0))),""))) -> 0.18421752 | Y11: =IF(OR(A11="",NOT(ISNUMBER(X11)),NOT(ISNUMBER(J11))),"",IF(ABS(J11)<0.000001,"",(X11-J11)/ABS(J11))) -> -0.029189324 | Z11: =IF(A11="","",IF(OR(U11="",NOT(ISNUMBER(X11))),"Sem meta / sem dado",IF(E11="Maior",IF(X11>=U11,"Cumpre","Não cumpre"),IF(X11<=U11,"Cumpre","Não cumpre")))) -> Sem meta / sem dado | AA11: — | AB11: Estimado (fator fixo)
A12: IDE-08 | B12: Potência específica da central de ar comprimido | C12: kWh dos compressores ÷ Nm³ de ar produzido (semana de medição) | D12: kWh/Nm³ | E12: Menor | F12: Rácio de valores medidos (fronteira de medida) | G12: Mensal a partir de 12/2026; antes, campanhas | H12: RG-SGE-11 tbl_ar_mv (PA-01 + caudalímetro EQP-04) | I12: Técnico de Utilidades | J12: =IF(OR(A12="",T12="—"),V12,IFERROR(AVERAGE(INDEX(IDE_Mensal!$A$5:$R$16,0,MATCH(T12,IDE_Mensal!$A$4:$R$4,0))),"")) -> 0.1337 | K12: OBJ-E-02 | L12: DAD-05 | M12: Compressores CMP-01/02 + secadores | N12: UTL-AR | O12: Nm³ produzidos; pressão | P12: Pressão de serviço; n.º de compressores | Q12: Sim — mesma semana-tipo com produção (ISO 50015 / IPMVP opção B) | R12: LBE-06 | S12: Utilidades; engenheiros (M&V) | T12: — | U12: 0.105 | V12: 0.1337 | W12: 0.1064 | X12: =IF(A12="","",IF(T12="—",W12,IFERROR(AVERAGE(INDEX(IDE_Mensal!$A$17:$R$26,0,MATCH(T12,IDE_Mensal!$A$4:$R$4,0))),""))) -> 0.1064 | Y12: =IF(OR(A12="",NOT(ISNUMBER(X12)),NOT(ISNUMBER(J12))),"",IF(ABS(J12)<0.000001,"",(X12-J12)/ABS(J12))) -> -0.20418848 | Z12: =IF(A12="","",IF(OR(U12="",NOT(ISNUMBER(X12))),"Sem meta / sem dado",IF(E12="Maior",IF(X12>=U12,"Cumpre","Não cumpre"),IF(X12<=U12,"Cumpre","Não cumpre")))) -> Não cumpre | AA12: SGA-10 OT-2026-02 (instalação dos VSD) | AB12: Medido (campanha)
A13: IDE-09 | B13: Consumo de energia final (eletricidade + gasóleo) | C13: kWh elétricos + L gasóleo × 10 kWh/L | D13: MWh | E13: Menor | F13: Valor de energia medido | G13: Mensal | H13: RG-SGA-13 + RG-SGA-19 (gasóleo) | I13: Gestor(a) de Energia (líder da equipa de gestão de energia) | J13: =IF(OR(A13="",T13="—"),V13,IFERROR(AVERAGE(INDEX(IDE_Mensal!$A$5:$R$16,0,MATCH(T13,IDE_Mensal!$A$4:$R$4,0))),"")) -> 565.48992 | K13: OBJ-E-05 | L13: DAD-01; DAD-07 | M13: Instalação + frota | N13: Todos | O13: — | P13: — | Q13: Não (valor absoluto) | R13: LBE-07 | S13: SGCIE; ESRS E1-5; EMAS; gestão de topo | T13: Energia_Final_MWh | X13: =IF(A13="","",IF(T13="—",W13,IFERROR(AVERAGE(INDEX(IDE_Mensal!$A$17:$R$26,0,MATCH(T13,IDE_Mensal!$A$4:$R$4,0))),""))) -> 671.456 | Y13: =IF(OR(A13="",NOT(ISNUMBER(X13)),NOT(ISNUMBER(J13))),"",IF(ABS(J13)<0.000001,"",(X13-J13)/ABS(J13))) -> 0.1873881 | Z13: =IF(A13="","",IF(OR(U13="",NOT(ISNUMBER(X13))),"Sem meta / sem dado",IF(E13="Maior",IF(X13>=U13,"Cumpre","Não cumpre"),IF(X13<=U13,"Cumpre","Não cumpre")))) -> Sem meta / sem dado | AA13: SGA ESG-E01; EMAS-01 | AB13: Medido
A14: IDE-10 | B14: Quota de eletricidade renovável (garantias de origem + autoconsumo) | C14: kWh renováveis ÷ kWh totais | D14: % | E14: Maior | F14: Rácio de valores medidos | G14: Anual | H14: Rótulo de energia do comercializador; UPAC (2027) | I14: Diretor Financeiro | J14: =IF(OR(A14="",T14="—"),V14,IFERROR(AVERAGE(INDEX(IDE_Mensal!$A$5:$R$16,0,MATCH(T14,IDE_Mensal!$A$4:$R$4,0))),"")) -> 0.55 | K14: OBJ-E-05 | L14: DAD-08 | M14: Instalação | N14: Todos | O14: — | P14: — | Q14: Não | R14: LBE-08 | S14: Gestão de topo; clientes; ESG | T14: — | U14: 0.8 | V14: 0.55 | W14: 0.55 | X14: =IF(A14="","",IF(T14="—",W14,IFERROR(AVERAGE(INDEX(IDE_Mensal!$A$17:$R$26,0,MATCH(T14,IDE_Mensal!$A$4:$R$4,0))),""))) -> 0.55 | Y14: =IF(OR(A14="",NOT(ISNUMBER(X14)),NOT(ISNUMBER(J14))),"",IF(ABS(J14)<0.000001,"",(X14-J14)/ABS(J14))) -> 0 | Z14: =IF(A14="","",IF(OR(U14="",NOT(ISNUMBER(X14))),"Sem meta / sem dado",IF(E14="Maior",IF(X14>=U14,"Cumpre","Não cumpre"),IF(X14<=U14,"Cumpre","Não cumpre")))) -> Não cumpre | AA14: SGA KPI-09; MET-03 | AB14: Medido
A15: KPI-E-01 | B15: Consumo de eletricidade medido por submedição (não estimado) | C15: kWh medidos por analisador fixo ÷ kWh totais | D15: % | E15: Maior | F15: KPI do sistema (não é IDE) | G15: Mensal | H15: RG-SGE-06 tbl_contadores | I15: Gestor(a) de Energia (líder da equipa de gestão de energia) | J15: =IF(OR(A15="",T15="—"),V15,IFERROR(AVERAGE(INDEX(IDE_Mensal!$A$5:$R$16,0,MATCH(T15,IDE_Mensal!$A$4:$R$4,0))),"")) -> 0 | K15: OBJ-E-06 | L15: DAD-01 | M15: Instalação | N15: — | O15: — | P15: — | Q15: — | R15: — | S15: Equipa de gestão de energia | T15: — | U15: 0.9 | V15: 0 | W15: 0.954 | X15: =IF(A15="","",IF(T15="—",W15,IFERROR(AVERAGE(INDEX(IDE_Mensal!$A$17:$R$26,0,MATCH(T15,IDE_Mensal!$A$4:$R$4,0))),""))) -> 0.954 | Y15: =IF(OR(A15="",NOT(ISNUMBER(X15)),NOT(ISNUMBER(J15))),"",IF(ABS(J15)<0.000001,"",(X15-J15)/ABS(J15))) | Z15: =IF(A15="","",IF(OR(U15="",NOT(ISNUMBER(X15))),"Sem meta / sem dado",IF(E15="Maior",IF(X15>=U15,"Cumpre","Não cumpre"),IF(X15<=U15,"Cumpre","Não cumpre")))) -> Cumpre | AA15: SGA R35 / PAM-26-02 | AB15: Medido
A16: KPI-E-02 | B16: Desvios significativos investigados em ≤ 30 dias | C16: Desvios investigados no prazo ÷ desvios detetados | D16: % | E16: Maior | F16: KPI do sistema (não é IDE) | G16: Mensal | H16: RG-SGE-11 tbl_desvios | I16: Gestor(a) de Energia (líder da equipa de gestão de energia) | J16: =IF(OR(A16="",T16="—"),V16,IFERROR(AVERAGE(INDEX(IDE_Mensal!$A$5:$R$16,0,MATCH(T16,IDE_Mensal!$A$4:$R$4,0))),"")) -> 0 | K16: OBJ-E-06 | L16: — | M16: — | N16: — | O16: — | P16: — | Q16: — | R16: — | S16: Equipa de gestão de energia | T16: — | U16: 1 | W16: 1 | X16: =IF(A16="","",IF(T16="—",W16,IFERROR(AVERAGE(INDEX(IDE_Mensal!$A$17:$R$26,0,MATCH(T16,IDE_Mensal!$A$4:$R$4,0))),""))) -> 1 | Y16: =IF(OR(A16="",NOT(ISNUMBER(X16)),NOT(ISNUMBER(J16))),"",IF(ABS(J16)<0.000001,"",(X16-J16)/ABS(J16))) | Z16: =IF(A16="","",IF(OR(U16="",NOT(ISNUMBER(X16))),"Sem meta / sem dado",IF(E16="Maior",IF(X16>=U16,"Cumpre","Não cumpre"),IF(X16<=U16,"Cumpre","Não cumpre")))) -> Cumpre | AA16: — | AB16: Registo
A17: KPI-E-03 | B17: Ações dos planos de ação energéticos no prazo | C17: Ações no prazo ÷ ações com prazo vencido ou concluídas | D17: % | E17: Maior | F17: KPI do sistema (não é IDE) | G17: Mensal | H17: RG-SGE-05 tbl_planos_acao | I17: Gestor(a) de Energia (líder da equipa de gestão de energia) | J17: =IF(OR(A17="",T17="—"),V17,IFERROR(AVERAGE(INDEX(IDE_Mensal!$A$5:$R$16,0,MATCH(T17,IDE_Mensal!$A$4:$R$4,0))),"")) -> 0 | K17: OBJ-E-06 | L17: — | M17: — | N17: — | O17: — | P17: — | Q17: — | R17: — | S17: Gestão de topo | T17: — | U17: 0.85 | W17: 0.86 | X17: =IF(A17="","",IF(T17="—",W17,IFERROR(AVERAGE(INDEX(IDE_Mensal!$A$17:$R$26,0,MATCH(T17,IDE_Mensal!$A$4:$R$4,0))),""))) -> 0.86 | Y17: =IF(OR(A17="",NOT(ISNUMBER(X17)),NOT(ISNUMBER(J17))),"",IF(ABS(J17)<0.000001,"",(X17-J17)/ABS(J17))) | Z17: =IF(A17="","",IF(OR(U17="",NOT(ISNUMBER(X17))),"Sem meta / sem dado",IF(E17="Maior",IF(X17>=U17,"Cumpre","Não cumpre"),IF(X17<=U17,"Cumpre","Não cumpre")))) -> Cumpre | AA17: — | AB17: Registo

Sheet Registo_LBE
A1: REGISTO DAS LINHAS DE BASE ENERGÉTICAS (6.5)
A4: ID_LBE | B4: ID_KPI | C4: Descricao | D4: Periodo_Inicio | E4: Periodo_Fim | F4: N_Meses | G4: Metodo | H4: Valor_LBE | I4: R2 | J4: Validade_Estatistica | K4: Estado | L4: Data_Aprovacao | M4: Criterios_Revisao | N4: Proxima_Revisao
A5: LBE-01 | B5: IDE-01 | C5: Modelo de regressão da eletricidade da instalação (sem máquinas novas) | D5: 45717 | E5: 46081 | F5: =IF(A5="","",IF(ISNUMBER(E5),DATEDIF(D5,E5,"m")+1,"")) -> 12 | G5: kWh = a + b1·mil un + b2·CDD₁₅ (LINEST) | H5: =IF(A5="","",IFERROR(INDEX(tbl_kpi[Baseline],MATCH(B5,tbl_kpi[ID_KPI],0)),"")) -> 0 | I5: =lbe_r2 -> 0.75328415 | J5: =LBE_Modelo!B30 -> Válido com reserva | K5: Em vigor | L5: 46280 | M5: a) IDE deixa de refletir o desempenho (ex.: submedição); b) alteração significativa de fatores estáticos (tbl_fatores_estaticos); c) revisão anual com a revisão energética | N5: 46599
A6: LBE-02 | B6: IDE-02 | C6: SEC médio da instalação | D6: 45717 | E6: 46081 | F6: =IF(A6="","",IF(ISNUMBER(E6),DATEDIF(D6,E6,"m")+1,"")) -> 12 | G6: Média dos rácios mensais | H6: =IF(A6="","",IFERROR(INDEX(tbl_kpi[Baseline],MATCH(B6,tbl_kpi[ID_KPI],0)),"")) -> 111.09142 | K6: Em vigor | L6: 46280 | M6: a) IDE deixa de refletir o desempenho (ex.: submedição); b) alteração significativa de fatores estáticos (tbl_fatores_estaticos); c) revisão anual com a revisão energética | N6: 46599
A7: LBE-03 | B7: IDE-03 | C7: SEC do sopro (estimado) | D7: 45717 | E7: 46081 | F7: =IF(A7="","",IF(ISNUMBER(E7),DATEDIF(D7,E7,"m")+1,"")) -> 12 | G7: Média dos rácios mensais | H7: =IF(A7="","",IFERROR(INDEX(tbl_kpi[Baseline],MATCH(B7,tbl_kpi[ID_KPI],0)),"")) -> 112.54659 | K7: Em vigor | L7: 46280 | M7: a) IDE deixa de refletir o desempenho (ex.: submedição); b) alteração significativa de fatores estáticos (tbl_fatores_estaticos); c) revisão anual com a revisão energética | N7: 46752
A8: LBE-04 | B8: IDE-04 | C8: SEC da injeção (estimado) | D8: 45717 | E8: 46081 | F8: =IF(A8="","",IF(ISNUMBER(E8),DATEDIF(D8,E8,"m")+1,"")) -> 12 | G8: Média dos rácios mensais | H8: =IF(A8="","",IFERROR(INDEX(tbl_kpi[Baseline],MATCH(B8,tbl_kpi[ID_KPI],0)),"")) -> 48.814602 | K8: Em vigor | L8: 46280 | M8: a) IDE deixa de refletir o desempenho (ex.: submedição); b) alteração significativa de fatores estáticos (tbl_fatores_estaticos); c) revisão anual com a revisão energética | N8: 46752
A9: LBE-05 | B9: IDE-06 | C9: Rácio de arrefecimento (estimado) | D9: 45717 | E9: 46081 | F9: =IF(A9="","",IF(ISNUMBER(E9),DATEDIF(D9,E9,"m")+1,"")) -> 12 | G9: Média dos rácios mensais | H9: =IF(A9="","",IFERROR(INDEX(tbl_kpi[Baseline],MATCH(B9,tbl_kpi[ID_KPI],0)),"")) -> 0.10679346 | K9: Em vigor | L9: 46280 | M9: a) IDE deixa de refletir o desempenho (ex.: submedição); b) alteração significativa de fatores estáticos (tbl_fatores_estaticos); c) revisão anual com a revisão energética | N9: 46752
A10: LBE-06 | B10: IDE-08 | C10: Potência específica do ar comprimido — compressores antigos | D10: 46034 | E10: 46040 | F10: =IF(A10="","",IF(ISNUMBER(E10),DATEDIF(D10,E10,"m")+1,"")) -> 1 | G10: Semana de registo PA-01 + EQP-04 (RG-SGE-11) | H10: =IF(A10="","",IFERROR(INDEX(tbl_kpi[Baseline],MATCH(B10,tbl_kpi[ID_KPI],0)),"")) -> 0.1337 | K10: Em vigor | L10: 46280 | M10: a) IDE deixa de refletir o desempenho (ex.: submedição); b) alteração significativa de fatores estáticos (tbl_fatores_estaticos); c) revisão anual com a revisão energética | N10: 46568
A11: LBE-07 | B11: IDE-09 | C11: Energia final mensal média | D11: 45717 | E11: 46081 | F11: =IF(A11="","",IF(ISNUMBER(E11),DATEDIF(D11,E11,"m")+1,"")) -> 12 | G11: Média mensal | H11: =IF(A11="","",IFERROR(INDEX(tbl_kpi[Baseline],MATCH(B11,tbl_kpi[ID_KPI],0)),"")) -> 565.48992 | K11: Em vigor | L11: 46280 | M11: a) IDE deixa de refletir o desempenho (ex.: submedição); b) alteração significativa de fatores estáticos (tbl_fatores_estaticos); c) revisão anual com a revisão energética | N11: 46599
A12: LBE-08 | B12: IDE-10 | C12: Quota renovável 2025/26 (rótulo de energia) | D12: 45658 | E12: 46022 | F12: =IF(A12="","",IF(ISNUMBER(E12),DATEDIF(D12,E12,"m")+1,"")) -> 12 | G12: Rótulo do comercializador | H12: =IF(A12="","",IFERROR(INDEX(tbl_kpi[Baseline],MATCH(B12,tbl_kpi[ID_KPI],0)),"")) -> 0.55 | K12: Em vigor | L12: 46280 | M12: a) IDE deixa de refletir o desempenho (ex.: submedição); b) alteração significativa de fatores estáticos (tbl_fatores_estaticos); c) revisão anual com a revisão energética | N12: 46568

Sheet Alteracoes_LBE
A1: ALTERAÇÕES ÀS LBE E AJUSTES NÃO ROTINEIROS (6.5; ISO 50006 §9)
A4: ID_Alteracao_LBE | B4: Data_Efeito | C4: Tipo | D4: Descricao | E4: LBE_Afetadas | F4: Tratamento | G4: Acao_Futura | H4: Estado | I4: Responsavel | J4: Data_Aprovacao
A5: ALE-01 | B5: 46204 | C5: Fator estático | D5: Entrada em produção de 4 máquinas novas (IM-007, IM-008, ISBM-009, ISBM-010) — ALT-2026-03 (linhas alimentar e farmacêutica). | E5: LBE-01 | F5: Ajuste não rotineiro (ISO 50006 §9.2): a energia atribuível às máquinas novas (horas × kW do RG-SGA-13 + quota de ar e frio) é retirada do real e as suas unidades das variáveis; fronteira do IDE-01 = instalação existente. | G5: Criar LBE-01b com 12 meses após a estabilização (07/2027) incluindo as máquinas novas. | H5: Aprovado | I5: Gestor(a) de Energia (líder da equipa de gestão de energia) | J5: 46280
A6: ALE-02 | B6: 46054 | C6: Ação de melhoria (não é fator estático) | D6: Substituição dos compressores CMP-01/02 por unidades de velocidade variável (ALT-2026-01). | E6: LBE-01; LBE-06 | F6: Sem ajuste: é uma melhoria a demonstrar. A LBE-01 termina em fev/2026 para que o reporte (mar–dez/2026) inclua o efeito dos VSD. | G6: — | H6: Aprovado | I6: Gestor(a) de Energia (líder da equipa de gestão de energia) | J6: 46280
A7: ALE-03 | B7: 46371 | C7: Método de medição | D7: Início da submedição por 6 analisadores (PA-E-01, em serviço desde 15/12/2026): os consumos por USE deixam de ser rateio. | E7: LBE-03; LBE-04; LBE-05 | F7: Revisão da LBE decidida (6.5 a): os IDE por USE estimados deixam de representar o desempenho; LBE atuais mantidas até haver 12 meses medidos. | G7: Nova LBE por USE com 12 meses medidos (01–12/2027). | H7: Aprovado | I7: Gestor(a) de Energia (líder da equipa de gestão de energia) | J7: 46374
A8: ALE-04 | B8: 46568 | C8: Tipo de energia | D8: Entrada em serviço da UPAC ≈ 1 MWp (ALT-2026-07). | E8: LBE-07; LBE-08 | F8: Sem ajuste ao IDE-01 (mede consumo, não a origem); o IDE-10 passa a incluir autoconsumo. | G8: — | H8: Planeado | I8: Diretor Financeiro

Sheet Fatores_Estaticos
A1: FATORES ESTÁTICOS MONITORIZADOS (6.5 b; ISO 50006 §9.2)
A4: ID_Fator | B4: Fator_Estatico | C4: Condicao_Na_LBE | D4: Condicao_Atual | E4: Situacao | F4: ID_Alteracao_LBE
A5: FEST-01 | B5: N.º de máquinas produtivas | C5: 18 (8 ISBM, 6 IM, 2 SS, 2 HF) | D5: 22 desde 07/2026 | E5: Alterado | F5: ALE-01
A6: FEST-02 | B6: Regime de trabalho | C6: 3 turnos × 8 h, 5 dias/semana; fins de semana só em picos | D6: Igual | E6: Sem alteração | F6: —
A7: FEST-03 | B7: Mix de produto (famílias) | C7: Cosmética + alimentar (frascos, tampas) | D7: Acrescentados potes e tampas alimentar/farma (17 SKU) | E7: Alterado | F7: ALE-01
A8: FEST-04 | B8: Área e edifícios | C8: Terreno 45 000 m², naves de produção e armazéns | D8: Igual | E8: Sem alteração | F8: —
A9: FEST-05 | B9: Tipos de energia | C9: Eletricidade da rede; gasóleo (frota, gerador) | D9: Igual (UPAC prevista 2027) | E9: Sem alteração | F9: ALE-04
A10: FEST-06 | B10: Central de ar comprimido | C10: 2 compressores de velocidade fixa (carga/vazio) | D10: 2 compressores VSD desde 02/2026 | E10: Alteração = ação de melhoria | F10: ALE-02
A11: FEST-07 | B11: Setpoint da água gelada | C11: 7 °C | D11: Igual | E11: Sem alteração | F11: —

Sheet Parametros
A1: PARÂMETROS DE CÁLCULO
A4: Codigo | B4: Valor | C4: Unidade | D4: Descricao | E4: Fonte
A5: PRECO_MEDIO | B5: 0.1335 | C5: €/kWh | D5: Preço médio da eletricidade (energia + redes, sem potência) nos 12 meses set/2025–ago/2026 | E5: RG-SGE-09 tbl_faturas (simulado)
A6: KWH_POR_L_GASOLEO | B6: 10 | C6: kWh/L | D6: Poder calorífico inferior do gasóleo ≈ 35,9 MJ/L | E6: Despacho 17313/2008 / DGEG — confirmar
A7: TOL_DOMINIO | B7: 0.1 | C7: fração | D7: Tolerância do domínio de validade do modelo da LBE-01 | E7: Decisão da equipa de gestão de energia (ISO 50006 §8.2)
A8: T_BASE_CDD | B8: 15 | C8: °C | D8: Temperatura base dos graus-dia de arrefecimento | E8: Mesma base do FRIO_TEMP do RG-SGA-13

Sheet Objetivos_Energeticos
A1: OBJETIVOS ENERGÉTICOS 2026–2028 (6.2)
A2: Retidos como informação documentada (6.2.2) · Valor atual calculado a partir dos IDE e da LBE_Modelo
A4: ID_OBJ | B4: ID_Politica | C4: Origem_Tipo | D4: Origem_IDs | E4: Origem_Descricao | F4: Declaracao_Objetivo | G4: ID_KPI | H4: Indicador_KPI | I4: Baseline | J4: Meta_Tipo | K4: Meta_Valor | L4: Meta_Numerica | M4: Prazo | N4: Recursos_Humanos | O4: Recursos_Materiais | P4: Recursos_Financeiros_EUR | Q4: Responsavel | R4: Acoes_PAM | S4: Estado | T4: Valor_Atual | U4: Progresso | V4: Dias_ate_Prazo | W4: S_Especifico | X4: M_Mensuravel | Y4: A_Atingivel | Z4: R_Relevante | AA4: T_Temporal | AB4: Validacao_SMART | AC4: Data_Aprovacao | AD4: Considera_USE | AE4: Oportunidades_Revisao | AF4: Requisitos_Aplicaveis | AG4: Comunicado | AH4: Ligacao_SGA | AI4: Polaridade
A5: OBJ-E-01 | B5: POL-E-01 | C5: Revisão energética | D5: USE-01; USE-02; USE-03; OPE-01; OPE-03; OPE-05; OPE-06 | E5: Injeção, sopro e ar comprimido somam 81% da eletricidade; melhoria só demonstrada após as ações de out–dez/2026. | F5: Melhorar em 5% o desempenho energético normalizado da instalação (IDE-01) até 31/12/2027, face à LBE-01 (mar/2025–fev/2026). | G5: IDE-01 | H5: =IFERROR(INDEX(tbl_kpi[Nome],MATCH(G5,tbl_kpi[ID_KPI],0))&" ("&INDEX(tbl_kpi[Unidade],MATCH(G5,tbl_kpi[ID_KPI],0))&")","") -> Melhoria do desempenho energético da instalação (consumo normalizado) (%) | I5: =IF(A5="","",IFERROR(INDEX(tbl_kpi[Baseline],MATCH(G5,tbl_kpi[ID_KPI],0)),"")) -> 0 | J5: Relativa | K5: +5% vs LBE-01 | L5: 0.05 | M5: 46752 | N5: Equipa de gestão de energia (6 pessoas, 10% do tempo) | O5: Analisadores (PAM-26-02), detetor de fugas | P5: 185000 | Q5: Gestor(a) de Energia (líder da equipa de gestão de energia) | R5: PA-E-01; PA-E-02; PA-E-03; PA-E-04 | S5: =IF(A5="","",IF(NOT(ISNUMBER(T5)),"Sem dado",IF(AI5="Maior",IF(T5>=L5,"Atingido","Em curso"),IF(T5<=L5,"Atingido","Em curso")))) -> Em curso | T5: =IF(A5="","",IF(G5="IDE-01",IFERROR(LBE_Modelo!$B$43,""),IFERROR(INDEX(tbl_kpi[Valor_Reporte],MATCH(G5,tbl_kpi[ID_KPI],0)),""))) -> 0.01935921 | U5: =IF(A5="","",IF(OR(NOT(ISNUMBER(T5)),NOT(ISNUMBER(I5))),"",IF(L5=I5,"",MAX(-1,MIN(1,(T5-I5)/(L5-I5)))))) -> 0.3871842 | V5: =IF(A5="","",M5-DataRef) -> 365 | W5: =IF(A5="","",IF(AND(LEN(F5)>40,G5<>""),"✔","✘")) -> ✔ | X5: =IF(A5="","",IF(ISNUMBER(L5),"✔","✘")) -> ✔ | Y5: =IF(A5="","",IF(AND(N5<>"",Q5<>"",R5<>""),"✔","✘")) -> ✔ | Z5: =IF(A5="","",IF(AND(B5<>"",D5<>""),"✔","✘")) -> ✔ | AA5: =IF(A5="","",IF(ISNUMBER(M5),"✔","✘")) -> ✔ | AB5: =IF(A5="","",IF((W5="✔")+(X5="✔")+(Y5="✔")+(Z5="✔")+(AA5="✔")=5,"SMART","Rever")) -> SMART | AC5: 46294 | AD5: USE-01, USE-02, USE-03 | AE5: OPE-01 a OPE-07 | AF5: LEG-08 SGCIE (−6% CEE até 2030); ISO 50003 (melhoria demonstrada) | AG5: Quadro de energia + reunião mensal de desempenho | AH5: OBJ-01 (−8% kWh/1.000 un até 12/2027) | AI5: =IF(A5="","",IFERROR(INDEX(tbl_kpi[Polaridade],MATCH(G5,tbl_kpi[ID_KPI],0)),"")) -> Maior
A6: OBJ-E-02 | B6: POL-E-02 | C6: Revisão energética | D6: USE-03; OPE-01; OPE-02; OPE-04 | E6: Ar comprimido com fugas ≈ 25% e pressão de 7,4 bar; compressores VSD desde 02/2026. | F6: Reduzir a potência específica da central de ar comprimido para ≤ 0,105 kWh/Nm³ e as fugas para ≤ 10% até 30/06/2027. | G6: IDE-08 | H6: =IFERROR(INDEX(tbl_kpi[Nome],MATCH(G6,tbl_kpi[ID_KPI],0))&" ("&INDEX(tbl_kpi[Unidade],MATCH(G6,tbl_kpi[ID_KPI],0))&")","") -> Potência específica da central de ar comprimido (kWh/Nm³) | I6: =IF(A6="","",IFERROR(INDEX(tbl_kpi[Baseline],MATCH(G6,tbl_kpi[ID_KPI],0)),"")) -> 0.1337 | J6: Absoluta | K6: ≤ 0,105 kWh/Nm³ | L6: 0.105 | M6: 46568 | N6: Técnico de Utilidades + manutenção (2 h/semana) | O6: Detetor ultrassónico EQP-05; etiquetas de fugas | P6: 18000 | Q6: Técnico de Utilidades | R6: PA-E-02; PA-E-05 | S6: =IF(A6="","",IF(NOT(ISNUMBER(T6)),"Sem dado",IF(AI6="Maior",IF(T6>=L6,"Atingido","Em curso"),IF(T6<=L6,"Atingido","Em curso")))) -> Em curso | T6: =IF(A6="","",IF(G6="IDE-01",IFERROR(LBE_Modelo!$B$43,""),IFERROR(INDEX(tbl_kpi[Valor_Reporte],MATCH(G6,tbl_kpi[ID_KPI],0)),""))) -> 0.1064 | U6: =IF(A6="","",IF(OR(NOT(ISNUMBER(T6)),NOT(ISNUMBER(I6))),"",IF(L6=I6,"",MAX(-1,MIN(1,(T6-I6)/(L6-I6)))))) -> 0.95121951 | V6: =IF(A6="","",M6-DataRef) -> 181 | W6: =IF(A6="","",IF(AND(LEN(F6)>40,G6<>""),"✔","✘")) -> ✔ | X6: =IF(A6="","",IF(ISNUMBER(L6),"✔","✘")) -> ✔ | Y6: =IF(A6="","",IF(AND(N6<>"",Q6<>"",R6<>""),"✔","✘")) -> ✔ | Z6: =IF(A6="","",IF(AND(B6<>"",D6<>""),"✔","✘")) -> ✔ | AA6: =IF(A6="","",IF(ISNUMBER(M6),"✔","✘")) -> ✔ | AB6: =IF(A6="","",IF((W6="✔")+(X6="✔")+(Y6="✔")+(Z6="✔")+(AA6="✔")=5,"SMART","Rever")) -> SMART | AC6: 46294 | AD6: USE-03 | AE6: OPE-01; OPE-02; OPE-04 | AF6: — | AG6: Ronda de fugas mensal + quadro da manutenção | AH6: SGA KZ-04; PAM-26-01 | AI6: =IF(A6="","",IFERROR(INDEX(tbl_kpi[Polaridade],MATCH(G6,tbl_kpi[ID_KPI],0)),"")) -> Menor
A7: OBJ-E-03 | B7: POL-E-01 | C7: Revisão energética | D7: OPE-03; KZ-01 | E7: Máquinas em espera aquecida nas pausas e paragens; carga de base 16% do consumo. | F7: Reduzir a carga de base (IDE-05) para ≤ 14% até 31/03/2027 com o modo standby nas pausas e paragens > 30 min. | G7: IDE-05 | H7: =IFERROR(INDEX(tbl_kpi[Nome],MATCH(G7,tbl_kpi[ID_KPI],0))&" ("&INDEX(tbl_kpi[Unidade],MATCH(G7,tbl_kpi[ID_KPI],0))&")","") -> Carga de base (energia não associada à produção) (%) | I7: =IF(A7="","",IFERROR(INDEX(tbl_kpi[Baseline],MATCH(G7,tbl_kpi[ID_KPI],0)),"")) -> 0.16719634 | J7: Absoluta | K7: ≤ 14% | L7: 0.14 | M7: 46477 | N7: Chefes de turno; operadores | O7: Etiquetas e checklist de pausa | P7: 0 | Q7: Gerente de Produção | R7: PA-E-03 | S7: =IF(A7="","",IF(NOT(ISNUMBER(T7)),"Sem dado",IF(AI7="Maior",IF(T7>=L7,"Atingido","Em curso"),IF(T7<=L7,"Atingido","Em curso")))) -> Em curso | T7: =IF(A7="","",IF(G7="IDE-01",IFERROR(LBE_Modelo!$B$43,""),IFERROR(INDEX(tbl_kpi[Valor_Reporte],MATCH(G7,tbl_kpi[ID_KPI],0)),""))) -> 0.16615393 | U7: =IF(A7="","",IF(OR(NOT(ISNUMBER(T7)),NOT(ISNUMBER(I7))),"",IF(L7=I7,"",MAX(-1,MIN(1,(T7-I7)/(L7-I7)))))) -> 0.038328975 | V7: =IF(A7="","",M7-DataRef) -> 90 | W7: =IF(A7="","",IF(AND(LEN(F7)>40,G7<>""),"✔","✘")) -> ✔ | X7: =IF(A7="","",IF(ISNUMBER(L7),"✔","✘")) -> ✔ | Y7: =IF(A7="","",IF(AND(N7<>"",Q7<>"",R7<>""),"✔","✘")) -> ✔ | Z7: =IF(A7="","",IF(AND(B7<>"",D7<>""),"✔","✘")) -> ✔ | AA7: =IF(A7="","",IF(ISNUMBER(M7),"✔","✘")) -> ✔ | AB7: =IF(A7="","",IF((W7="✔")+(X7="✔")+(Y7="✔")+(Z7="✔")+(AA7="✔")=5,"SMART","Rever")) -> SMART | AC7: 46294 | AD7: USE-01; USE-02 | AE7: OPE-03 | AF7: — | AG7: Formação no posto + checklist do chefe de turno | AH7: SGA PAM-26-06 (KZ-01) | AI7: =IF(A7="","",IFERROR(INDEX(tbl_kpi[Polaridade],MATCH(G7,tbl_kpi[ID_KPI],0)),"")) -> Menor
A8: OBJ-E-04 | B8: POL-E-01 | C8: Revisão energética | D8: USE-04; OPE-08; OPE-09 | E8: Chiller com setpoint de 7 °C e sem free-cooling; verões mais quentes (PES-08). | F8: Reduzir o rácio de arrefecimento (IDE-06) para ≤ 0,095 até 31/12/2027 (setpoint 10–12 °C e free-cooling). | G8: IDE-06 | H8: =IFERROR(INDEX(tbl_kpi[Nome],MATCH(G8,tbl_kpi[ID_KPI],0))&" ("&INDEX(tbl_kpi[Unidade],MATCH(G8,tbl_kpi[ID_KPI],0))&")","") -> Rácio de arrefecimento (frio ÷ energia de injeção + sopro) (fração) | I8: =IF(A8="","",IFERROR(INDEX(tbl_kpi[Baseline],MATCH(G8,tbl_kpi[ID_KPI],0)),"")) -> 0.10679346 | J8: Absoluta | K8: ≤ 0,095 | L8: 0.095 | M8: 46752 | N8: Técnico de Utilidades; engenharia de processo | O8: Permutador de free-cooling | P8: 42000 | Q8: Técnico de Utilidades | R8: PA-E-06 | S8: =IF(A8="","",IF(NOT(ISNUMBER(T8)),"Sem dado",IF(AI8="Maior",IF(T8>=L8,"Atingido","Em curso"),IF(T8<=L8,"Atingido","Em curso")))) -> Em curso | T8: =IF(A8="","",IF(G8="IDE-01",IFERROR(LBE_Modelo!$B$43,""),IFERROR(INDEX(tbl_kpi[Valor_Reporte],MATCH(G8,tbl_kpi[ID_KPI],0)),""))) -> 0.11425928 | U8: =IF(A8="","",IF(OR(NOT(ISNUMBER(T8)),NOT(ISNUMBER(I8))),"",IF(L8=I8,"",MAX(-1,MIN(1,(T8-I8)/(L8-I8)))))) -> -0.63304781 | V8: =IF(A8="","",M8-DataRef) -> 365 | W8: =IF(A8="","",IF(AND(LEN(F8)>40,G8<>""),"✔","✘")) -> ✔ | X8: =IF(A8="","",IF(ISNUMBER(L8),"✔","✘")) -> ✔ | Y8: =IF(A8="","",IF(AND(N8<>"",Q8<>"",R8<>""),"✔","✘")) -> ✔ | Z8: =IF(A8="","",IF(AND(B8<>"",D8<>""),"✔","✘")) -> ✔ | AA8: =IF(A8="","",IF(ISNUMBER(M8),"✔","✘")) -> ✔ | AB8: =IF(A8="","",IF((W8="✔")+(X8="✔")+(Y8="✔")+(Z8="✔")+(AA8="✔")=5,"SMART","Rever")) -> SMART | AC8: 46294 | AD8: USE-04 | AE8: OPE-08; OPE-09 | AF8: Reg. (UE) 2024/573 (gases fluorados — manutenção do chiller) | AG8: Quadro das utilidades | AH8: SGA OBJ-05 (água do arrefecimento) | AI8: =IF(A8="","",IFERROR(INDEX(tbl_kpi[Polaridade],MATCH(G8,tbl_kpi[ID_KPI],0)),"")) -> Menor
A9: OBJ-E-05 | B9: POL-E-03 | C9: Contexto / partes interessadas | D9: PES-01; O15; ALT-2026-07 | E9: Clientes e PL-SGA-01 pedem eletricidade renovável; UPAC ≈ 1 MWp aprovada para estudo. | F9: Atingir ≥ 80% de eletricidade renovável (garantias de origem + autoconsumo) em 2028. | G9: IDE-10 | H9: =IFERROR(INDEX(tbl_kpi[Nome],MATCH(G9,tbl_kpi[ID_KPI],0))&" ("&INDEX(tbl_kpi[Unidade],MATCH(G9,tbl_kpi[ID_KPI],0))&")","") -> Quota de eletricidade renovável (garantias de origem + autoconsumo) (%) | I9: =IF(A9="","",IFERROR(INDEX(tbl_kpi[Baseline],MATCH(G9,tbl_kpi[ID_KPI],0)),"")) -> 0.55 | J9: Absoluta | K9: ≥ 80% | L9: 0.8 | M9: 47118 | N9: Diretor Financeiro; Gestor(a) de Energia | O9: UPAC ≈ 1 MWp | P9: 850000 | Q9: Diretor Financeiro | R9: PA-E-07 | S9: =IF(A9="","",IF(NOT(ISNUMBER(T9)),"Sem dado",IF(AI9="Maior",IF(T9>=L9,"Atingido","Em curso"),IF(T9<=L9,"Atingido","Em curso")))) -> Em curso | T9: =IF(A9="","",IF(G9="IDE-01",IFERROR(LBE_Modelo!$B$43,""),IFERROR(INDEX(tbl_kpi[Valor_Reporte],MATCH(G9,tbl_kpi[ID_KPI],0)),""))) -> 0.55 | U9: =IF(A9="","",IF(OR(NOT(ISNUMBER(T9)),NOT(ISNUMBER(I9))),"",IF(L9=I9,"",MAX(-1,MIN(1,(T9-I9)/(L9-I9)))))) -> 0 | V9: =IF(A9="","",M9-DataRef) -> 731 | W9: =IF(A9="","",IF(AND(LEN(F9)>40,G9<>""),"✔","✘")) -> ✔ | X9: =IF(A9="","",IF(ISNUMBER(L9),"✔","✘")) -> ✔ | Y9: =IF(A9="","",IF(AND(N9<>"",Q9<>"",R9<>""),"✔","✘")) -> ✔ | Z9: =IF(A9="","",IF(AND(B9<>"",D9<>""),"✔","✘")) -> ✔ | AA9: =IF(A9="","",IF(ISNUMBER(M9),"✔","✘")) -> ✔ | AB9: =IF(A9="","",IF((W9="✔")+(X9="✔")+(Y9="✔")+(Z9="✔")+(AA9="✔")=5,"SMART","Rever")) -> SMART | AC9: 46294 | AD9: — | AE9: OPE-12 | AF9: DL 15/2022 alterado pelo DL 130/2026 (autoconsumo) | AG9: Relatório de sustentabilidade; site | AH9: SGA MET-03; PL-SGA-01 | AI9: =IF(A9="","",IFERROR(INDEX(tbl_kpi[Polaridade],MATCH(G9,tbl_kpi[ID_KPI],0)),"")) -> Maior
A10: OBJ-E-06 | B10: POL-E-04 | C10: Requisito do SGE | D10: R35; ALE-03 | E10: Consumos por uso são estimados (rateio); sem submedição não há IDE por USE nem prova de melhoria (ISO 50003). | F10: Medir por analisador fixo ≥ 90% da eletricidade (KPI-E-01) até 31/03/2027 e investigar 100% dos desvios significativos em ≤ 30 dias. | G10: KPI-E-01 | H10: =IFERROR(INDEX(tbl_kpi[Nome],MATCH(G10,tbl_kpi[ID_KPI],0))&" ("&INDEX(tbl_kpi[Unidade],MATCH(G10,tbl_kpi[ID_KPI],0))&")","") -> Consumo de eletricidade medido por submedição (não estimado) (%) | I10: =IF(A10="","",IFERROR(INDEX(tbl_kpi[Baseline],MATCH(G10,tbl_kpi[ID_KPI],0)),"")) -> 0 | J10: Absoluta | K10: ≥ 90% | L10: 0.9 | M10: 46477 | N10: Gerente de Dados / TI; instalador | O10: 6 analisadores + integração no BI | P10: 38000 | Q10: Gerente de Dados / TI | R10: PA-E-01 | S10: =IF(A10="","",IF(NOT(ISNUMBER(T10)),"Sem dado",IF(AI10="Maior",IF(T10>=L10,"Atingido","Em curso"),IF(T10<=L10,"Atingido","Em curso")))) -> Atingido | T10: =IF(A10="","",IF(G10="IDE-01",IFERROR(LBE_Modelo!$B$43,""),IFERROR(INDEX(tbl_kpi[Valor_Reporte],MATCH(G10,tbl_kpi[ID_KPI],0)),""))) -> 0.954 | U10: =IF(A10="","",IF(OR(NOT(ISNUMBER(T10)),NOT(ISNUMBER(I10))),"",IF(L10=I10,"",MAX(-1,MIN(1,(T10-I10)/(L10-I10)))))) -> 1 | V10: =IF(A10="","",M10-DataRef) -> 90 | W10: =IF(A10="","",IF(AND(LEN(F10)>40,G10<>""),"✔","✘")) -> ✔ | X10: =IF(A10="","",IF(ISNUMBER(L10),"✔","✘")) -> ✔ | Y10: =IF(A10="","",IF(AND(N10<>"",Q10<>"",R10<>""),"✔","✘")) -> ✔ | Z10: =IF(A10="","",IF(AND(B10<>"",D10<>""),"✔","✘")) -> ✔ | AA10: =IF(A10="","",IF(ISNUMBER(M10),"✔","✘")) -> ✔ | AB10: =IF(A10="","",IF((W10="✔")+(X10="✔")+(Y10="✔")+(Z10="✔")+(AA10="✔")=5,"SMART","Rever")) -> SMART | AC10: 46294 | AD10: Todos | AE10: — | AF10: ISO 50001 6.6 (exatidão e repetibilidade); ISO 50003 | AG10: Reunião da equipa de gestão de energia | AH10: SGA R35; PAM-26-02; RG-26-D03 | AI10: =IF(A10="","",IFERROR(INDEX(tbl_kpi[Polaridade],MATCH(G10,tbl_kpi[ID_KPI],0)),"")) -> Maior

Sheet Metas_Energeticas
A1: METAS ENERGÉTICAS (6.2.1)
A4: ID_Meta | B4: ID_OBJ | C4: ID_KPI | D4: Descricao | E4: Meta_Numerica | F4: Prazo | G4: Valor_LBE | H4: Valor_Atual | I4: Unidade
A5: MET-E-01 | B5: OBJ-E-01 | C5: IDE-01 | D5: Melhoria normalizada da instalação — etapa 2026 | E5: 0.02 | F5: 46387 | G5: =IF(A5="","",IFERROR(INDEX(tbl_kpi[Baseline],MATCH(C5,tbl_kpi[ID_KPI],0)),"")) -> 0 | H5: =IF(A5="","",IFERROR(INDEX(tbl_objetivos[Valor_Atual],MATCH(B5,tbl_objetivos[ID_OBJ],0)),"")) -> 0.01935921 | I5: =IF(A5="","",IFERROR(INDEX(tbl_kpi[Unidade],MATCH(C5,tbl_kpi[ID_KPI],0)),"")) -> %
A6: MET-E-02 | B6: OBJ-E-01 | C6: IDE-01 | D6: Melhoria normalizada da instalação — meta 2027 | E6: 0.05 | F6: 46752 | G6: =IF(A6="","",IFERROR(INDEX(tbl_kpi[Baseline],MATCH(C6,tbl_kpi[ID_KPI],0)),"")) -> 0 | H6: =IF(A6="","",IFERROR(INDEX(tbl_objetivos[Valor_Atual],MATCH(B6,tbl_objetivos[ID_OBJ],0)),"")) -> 0.01935921 | I6: =IF(A6="","",IFERROR(INDEX(tbl_kpi[Unidade],MATCH(C6,tbl_kpi[ID_KPI],0)),"")) -> %
A7: MET-E-03 | B7: OBJ-E-01 | C7: IDE-02 | D7: SEC da instalação (alinhado com SGA OBJ-01: −8%) | E7: 101 | F7: 46752 | G7: =IF(A7="","",IFERROR(INDEX(tbl_kpi[Baseline],MATCH(C7,tbl_kpi[ID_KPI],0)),"")) -> 111.09142 | H7: =IF(A7="","",IFERROR(INDEX(tbl_objetivos[Valor_Atual],MATCH(B7,tbl_objetivos[ID_OBJ],0)),"")) -> 0.01935921 | I7: =IF(A7="","",IFERROR(INDEX(tbl_kpi[Unidade],MATCH(C7,tbl_kpi[ID_KPI],0)),"")) -> kWh/1.000 un
A8: MET-E-04 | B8: OBJ-E-02 | C8: IDE-08 | D8: Potência específica do ar comprimido | E8: 0.105 | F8: 46568 | G8: =IF(A8="","",IFERROR(INDEX(tbl_kpi[Baseline],MATCH(C8,tbl_kpi[ID_KPI],0)),"")) -> 0.1337 | H8: =IF(A8="","",IFERROR(INDEX(tbl_objetivos[Valor_Atual],MATCH(B8,tbl_objetivos[ID_OBJ],0)),"")) -> 0.1064 | I8: =IF(A8="","",IFERROR(INDEX(tbl_kpi[Unidade],MATCH(C8,tbl_kpi[ID_KPI],0)),"")) -> kWh/Nm³
A9: MET-E-05 | B9: OBJ-E-03 | C9: IDE-05 | D9: Carga de base | E9: 0.14 | F9: 46477 | G9: =IF(A9="","",IFERROR(INDEX(tbl_kpi[Baseline],MATCH(C9,tbl_kpi[ID_KPI],0)),"")) -> 0.16719634 | H9: =IF(A9="","",IFERROR(INDEX(tbl_objetivos[Valor_Atual],MATCH(B9,tbl_objetivos[ID_OBJ],0)),"")) -> 0.16615393 | I9: =IF(A9="","",IFERROR(INDEX(tbl_kpi[Unidade],MATCH(C9,tbl_kpi[ID_KPI],0)),"")) -> %
A10: MET-E-06 | B10: OBJ-E-04 | C10: IDE-06 | D10: Rácio de arrefecimento | E10: 0.095 | F10: 46752 | G10: =IF(A10="","",IFERROR(INDEX(tbl_kpi[Baseline],MATCH(C10,tbl_kpi[ID_KPI],0)),"")) -> 0.10679346 | H10: =IF(A10="","",IFERROR(INDEX(tbl_objetivos[Valor_Atual],MATCH(B10,tbl_objetivos[ID_OBJ],0)),"")) -> 0.11425928 | I10: =IF(A10="","",IFERROR(INDEX(tbl_kpi[Unidade],MATCH(C10,tbl_kpi[ID_KPI],0)),"")) -> fração
A11: MET-E-07 | B11: OBJ-E-05 | C11: IDE-10 | D11: Eletricidade renovável | E11: 0.8 | F11: 47118 | G11: =IF(A11="","",IFERROR(INDEX(tbl_kpi[Baseline],MATCH(C11,tbl_kpi[ID_KPI],0)),"")) -> 0.55 | H11: =IF(A11="","",IFERROR(INDEX(tbl_objetivos[Valor_Atual],MATCH(B11,tbl_objetivos[ID_OBJ],0)),"")) -> 0.55 | I11: =IF(A11="","",IFERROR(INDEX(tbl_kpi[Unidade],MATCH(C11,tbl_kpi[ID_KPI],0)),"")) -> %
A12: MET-E-08 | B12: OBJ-E-06 | C12: KPI-E-01 | D12: Eletricidade medida por submedição | E12: 0.9 | F12: 46477 | G12: =IF(A12="","",IFERROR(INDEX(tbl_kpi[Baseline],MATCH(C12,tbl_kpi[ID_KPI],0)),"")) -> 0 | H12: =IF(A12="","",IFERROR(INDEX(tbl_objetivos[Valor_Atual],MATCH(B12,tbl_objetivos[ID_OBJ],0)),"")) -> 0.954 | I12: =IF(A12="","",IFERROR(INDEX(tbl_kpi[Unidade],MATCH(C12,tbl_kpi[ID_KPI],0)),"")) -> %

Sheet Planos_Acao
A1: PLANOS DE AÇÃO ENERGÉTICOS (6.2.3)
A2: Cada plano diz como a melhoria será verificada (9.1) · Preço médio da eletricidade: célula preco_medio (RG-SGE-09, média das faturas de 12 meses)
A4: ID_Plano | B4: ID_OBJ | C4: O_Que_Fazer | D4: Recursos | E4: Custo_EUR | F4: Responsavel | G4: Inicio | H4: Prazo | I4: Como_Avaliar | J4: Metodo_Verificacao | K4: Poupanca_Prevista_MWh | L4: Estado | M4: Integracao_Negocio | N4: ID_PAM_SGA | O4: ID_Oportunidade | P4: Dias_ate_Prazo | Q4: Poupanca_Prevista_EUR | R4: Payback_Anos
A5: PA-E-01 | B5: OBJ-E-06 | C5: Instalar 6 analisadores de energia (QGBT-INJ, QGBT-SOP, QGBT-DEC, Q-AR, Q-FRIO, Q-SERV) e ligar ao BI; rever a LBE por USE com 12 meses medidos. | D5: Analisadores classe 0,5S, TI de medida, integração BI | E5: 38000 | F5: Gerente de Dados / TI | G5: 46296 | H5: 46371 | I5: Cobertura medida ≥ 90% (KPI-E-01) e reconciliação mensal com a fatura (±2%) | J5: Reconciliação Σ analisadores vs contador geral EQP-01 | K5: 0 | L5: Concluído | M5: Orçamento CAPEX 2026 (RG-26-D03) | N5: PAM-26-02 | O5: — | P5: =IF(A5="","",H5-DataRef) -> -16 | Q5: =IF(A5="","",K5*1000*preco_medio) -> 0 | R5: =IF(OR(A5="",Q5=0),"",E5/Q5)
A6: PA-E-02 | B6: OBJ-E-02 | C6: Campanha de fugas com ultrassom (mensal), reparação em ≤ 5 dias, teste de vazio ao domingo e redução da pressão para 6,8 bar. | D6: Detetor EQP-05; 2 h/semana do Técnico de Utilidades; peças | E6: 6000 | F6: Técnico de Utilidades | G6: 46296 | H6: 46568 | I6: Fugas ≤ 10% no teste de vazio; IDE-08 ≤ 0,105 kWh/Nm³ | J6: IPMVP opção B na fronteira da central (PA-01 + EQP-04), semana-tipo | K6: 145 | L6: Em curso | M6: Plano de manutenção preventiva (SAP PM) | N6: — | O6: OPE-01; OPE-02 | P6: =IF(A6="","",H6-DataRef) -> 181 | Q6: =IF(A6="","",K6*1000*preco_medio) -> 19357.5 | R6: =IF(OR(A6="",Q6=0),"",E6/Q6) -> 0.30995738
A7: PA-E-03 | B7: OBJ-E-03 | C7: Modo standby nas pausas do 3.º turno e nas paragens > 30 min (resistências a 60%, bomba desligada); checklist do chefe de turno. | D7: Formação no posto (30 min/operador); etiquetas | E7: 0 | F7: Gerente de Produção | G7: 46300 | H7: 46387 | I7: IDE-05 ≤ 14%; poupança medida por analisador no QGBT-INJ/SOP | J7: IPMVP opção A (kW medido em espera × horas registadas) até haver analisadores | K7: 190 | L7: Concluído | M7: Standard work do turno (SQDC) | N7: PAM-26-06 | O7: OPE-03 | P7: =IF(A7="","",H7-DataRef) -> 0 | Q7: =IF(A7="","",K7*1000*preco_medio) -> 25365 | R7: =IF(OR(A7="",Q7=0),"",E7/Q7) -> 0
A8: PA-E-04 | B8: OBJ-E-01 | C8: Servo-bomba nas injetoras hidráulicas IM-002 e IM-004 e isolamento térmico dos canhões de todas as injetoras. | D8: Retrofit servo (2 × €28 000); mantas (8 × €900) | E8: 63200 | F8: Gerente de Manutenção | G8: 46402 | H8: 46568 | I8: SEC por máquina (analisador) −30% nas IM-002/004 | J8: IPMVP opção B por máquina (analisador portátil antes/depois, mesmo molde) | K8: 210 | L8: Planeado | M8: Plano de investimento 2027 | N8: — | O8: OPE-05; OPE-06 | P8: =IF(A8="","",H8-DataRef) -> 181 | Q8: =IF(A8="","",K8*1000*preco_medio) -> 28035 | R8: =IF(OR(A8="",Q8=0),"",E8/Q8) -> 2.254325
A9: PA-E-05 | B9: OBJ-E-02 | C9: Recuperação de calor dos compressores para pré-aquecimento de águas sanitárias e AVAC dos balneários. | D9: Permutador e tubagem | E9: 14000 | F9: Técnico de Utilidades | G9: 46447 | H9: 46660 | I9: kWh térmicos recuperados (contador de energia térmica) | J9: Medição direta (contador de entalpia) — ISO 50015 | K9: 60 | L9: Planeado | M9: Plano de investimento 2027 | N9: — | O9: OPE-13 | P9: =IF(A9="","",H9-DataRef) -> 273 | Q9: =IF(A9="","",K9*1000*preco_medio) -> 8010 | R9: =IF(OR(A9="",Q9=0),"",E9/Q9) -> 1.7478152
A10: PA-E-06 | B10: OBJ-E-04 | C10: Subir o setpoint da água gelada de 7 °C para 11 °C (validado com a qualidade dos moldes) e instalar free-cooling na torre. | D10: Ensaio DOE com a engenharia de processo; permutador | E10: 42000 | F10: Técnico de Utilidades | G10: 46327 | H10: 46691 | I10: IDE-06 ≤ 0,095 normalizado pela temperatura | J10: IPMVP opção B (analisador Q-FRIO) com ajuste por graus-dia | K10: 120 | L10: Em curso | M10: Validação de processo (RG-SGQ-13) | N10: — | O10: OPE-08; OPE-09 | P10: =IF(A10="","",H10-DataRef) -> 304 | Q10: =IF(A10="","",K10*1000*preco_medio) -> 16020 | R10: =IF(OR(A10="",Q10=0),"",E10/Q10) -> 2.6217228
A11: PA-E-07 | B11: OBJ-E-05 | C11: UPAC ≈ 1 MWp na cobertura (≈ 1 400 MWh/ano) e contrato de garantias de origem para o restante. | D11: EPC fotovoltaico; licenciamento DGEG | E11: 850000 | F11: Diretor Financeiro | G11: 46388 | H11: 46752 | I11: IDE-10 ≥ 80% em 2028; produção UPAC medida | J11: Contador da UPAC + rótulo de energia (não é poupança: substitui a origem) | K11: 0 | L11: Em estudo | M11: Plano de transição climática PL-SGA-01 | N11: — | O11: OPE-12 | P11: =IF(A11="","",H11-DataRef) -> 365 | Q11: =IF(A11="","",K11*1000*preco_medio) -> 0 | R11: =IF(OR(A11="",Q11=0),"",E11/Q11)

Sheet Metodologia_IDE_LBE
A1: METODOLOGIA DOS IDE E DAS LBE (6.4 e 6.5 — informação documentada mantida; detalhe no PR-SGE-03)
A3: 1. Fronteiras | B3: ISO 50006 §5.3: instalação (IDE-01/02/05/09), USE (IDE-03/04/06/07), fronteira de medida da central de ar (IDE-08). A fronteira do IDE-01 exclui as 4 máquinas novas até haver 12 meses (ALE-01).
A4: 2. Variáveis relevantes | B4: ISO 50006 §5.5: candidatas em tbl_variaveis; entram no modelo se forem significativas (p < 0,2) e tiverem explicação física. Escolhidas: unidades INJ+SOP e graus-dia base 15 °C.
A5: 3. Tipo de IDE | B5: ISO 50006 §6.2: modelo estatístico quando há variáveis relevantes (IDE-01); rácio quando há uma entrada e uma saída e poucas variáveis (IDE-02 a 08); valor medido para relato (IDE-09).
A6: 4. Período de referência | B6: ISO 50006 §7.2: 2025-03-01 a 2026-02-28 — 12 meses para cobrir o ciclo anual de temperatura; termina antes dos compressores VSD para que o efeito apareça no reporte. Meses mar–jun/2025 têm produção reconstruída (qualidade inferior, RG-SGA-13).
A7: 5. Normalização | B7: ISO 50006 §8: energia esperada = modelo aplicado às variáveis do mês; melhoria = (esperado − real) ÷ esperado. Não se normaliza fora do domínio (±10% do intervalo de referência).
A8: 6. Validade estatística | B8: R² ≥ 0,5 e p-valores (EnPI Lite/LBNL); CV(RMSE) ≤ 15% e NMBE ±5% (ASHRAE 14). O resultado está em LBE_Modelo e em tbl_lbe.
A9: 7. Desvio significativo (9.1.1) | B9: Mês com |real − esperado| > t(95%) × erro-padrão do modelo: investigar e responder, com registo no RG-SGE-11 tbl_desvios.
A10: 8. Demonstração da melhoria | B10: ISO 50006 §10.3: soma do reporte dentro do domínio; a melhoria só é declarada se exceder a incerteza a 95%. A ISO 50003:2021 exige melhoria demonstrada para certificar.
A11: 9. Revisão das LBE (6.5) | B11: a) IDE deixa de representar (submedição 12/2026); b) fatores estáticos (tbl_fatores_estaticos); c) anualmente com a revisão energética. Cada alteração fica em tbl_alteracoes_lbe.
A12: 10. Limitações conhecidas | B12: O consumo por uso é rateio (horas × kW) até 12/2026: os IDE por USE não mostram ganhos de eficiência das máquinas — por isso a melhoria dos compressores é verificada por medição dedicada (RG-SGE-11, IPMVP opção B).

Sheet Listas
A1: LISTAS CONTROLADAS (domínios de validação de dados) — editar aqui para alterar opções
A2: DataReferencia | B2: Funcao | C2: Polaridade | D2: Periodo | E2: EstadoPlano | F2: EstadoLBE | G2: TipoIDE
A3: 46387 | B3: Diretor Geral (Gestão de Topo) | C3: Maior | D3: Referência (LBE) | E3: Em estudo | F3: Em vigor | G3: Valor de energia medido
B4: Diretor Industrial | C4: Menor | D4: Reporte | E4: Planeado | F4: Planeado | G4: Rácio de valores medidos
B5: Gestor(a) de Energia (líder da equipa de gestão de energia) | E5: Em curso | F5: Substituída | G5: Rácio (numerador estimado)
B6: Gerente de Manutenção | E6: Concluído | G6: Rácio (estimado)
B7: Gerente de Produção | E7: Cancelado | G7: Rácio (estimado — fator fixo)
B8: Técnico de Utilidades | G8: Rácio de valores medidos (fronteira de medida)
B9: Gestor do SGA / EHS (Responsável Ambiental) | G9: Modelo estatístico (regressão linear múltipla)
B10: Gerente da Qualidade | G10: Modelo estatístico (termo independente)
B11: Diretor Financeiro | G11: Modelo de engenharia
B12: Responsável de Compras | G12: KPI do sistema (não é IDE)
B13: Responsável de R&D
B14: Responsável de Recursos Humanos
B15: Gerente de Dados / TI
B16: Engenheiro(a) de Processo
B17: Chefe de Turno
B18: Operador de Injeção
B19: Operador de Sopro (ISBM)
B20: Operador de Serigrafia
B21: Operador de Hot Foil
B22: Técnico de Manutenção
B23: Auditor(a) Interno(a) do SGE
B24: Responsável de Armazém e Logística

Sheet Dicionario_Dados
A1: Folha | B1: Tabela | C1: Coluna | D1: Tipo | E1: Origem | F1: Descricao | G1: Dominio_Unidade | H1: Obrigatorio | I1: Chave
A2: Base_Mensal | B2: tbl_base_energia | C2: Mes | D2: Data (aaaa-mm-dd) | E2: Entrada | F2: Mês (1.º dia). | H2: Sim | I2: PK
A3: Base_Mensal | B3: tbl_base_energia | C3: Periodo | D3: Texto | E3: Entrada | F3: Referência (LBE) = mar/2025–fev/2026; Reporte = mar–ago/2026. | H3: Sim
A4: Base_Mensal | B4: tbl_base_energia | C4: Qualidade_Producao | D4: Texto | E4: Entrada | F4: Dataset = produção real do dataset; Reconstruído = mar–jun/2025, anterior ao dataset (RG-SGA-13). | H4: Sim
A5: Base_Mensal | B5: tbl_base_energia | C5: Fonte_Energia | D5: Texto | E5: Entrada | F5: RG-SGA-13 (fatura), fonte única mar/2025–dez/2026, já com o efeito das ações de out–dez/2026. | H5: Sim
A6: Base_Mensal | B6: tbl_base_energia | C6: Dias_Calendario | D6: Inteiro | E6: Entrada | F6: Dias do mês. | H6: Sim
A7: Base_Mensal | B7: tbl_base_energia | C7: Dias_Uteis | D7: Inteiro | E7: Entrada | F7: Dias úteis (RG-SGA-13). | H7: Sim
A8: Base_Mensal | B8: tbl_base_energia | C8: Temp_Media_C | D8: Decimal | E8: Entrada | F8: Temperatura média exterior (°C) — RG-SGA-13 (IPMA). | H8: Sim
A9: Base_Mensal | B9: tbl_base_energia | C9: CDD_15 | D9: Decimal | E9: Entrada | F9: Graus-dia de arrefecimento base 15 °C = max(0; T − 15) × dias. | H9: Sim
A10: Base_Mensal | B10: tbl_base_energia | C10: kWh_Total | D10: kwh | E10: Entrada | F10: Eletricidade total da fatura (RG-SGA-13, medido). | H10: Sim
A11: Base_Mensal | B11: tbl_base_energia | C11: kWh_SOP | D11: kwh | E11: Entrada | F11: Eletricidade do sopro (rateio RG-SGA-13). | H11: Sim
A12: Base_Mensal | B12: tbl_base_energia | C12: kWh_INJ | D12: kwh | E12: Entrada | F12: Eletricidade da injeção (rateio). | H12: Sim
A13: Base_Mensal | B13: tbl_base_energia | C13: kWh_UTL_AR | D13: kwh | E13: Entrada | F13: Ar comprimido (rateio: 19% dos processos). | H13: Sim
A14: Base_Mensal | B14: tbl_base_energia | C14: kWh_UTL_FRIO | D14: kwh | E14: Entrada | F14: Arrefecimento (rateio com fator de temperatura). | H14: Sim
... A31: Base_Mensal | B31: tbl_base_energia | C31: Energia_Final_MWh | D31: Decimal | E31: Calculado (fórmula) | F31: Energia final: eletricidade + gasóleo × 10 kWh/L (PCI ≈ 35,9 MJ/L). | H31: Sim
A32: IDE_Mensal | B32: tbl_ide_mensal | C32: Mes | D32: Data (aaaa-mm-dd) | E32: Entrada | F32: Mês. | H32: Sim | I32: PK / FK → tbl_base_energia
A33: IDE_Mensal | B33: tbl_ide_mensal | C33: Periodo | D33: Texto | E33: Calculado (fórmula) | F33: Referência (LBE) ou Reporte. | H33: Sim
A34: IDE_Mensal | B34: tbl_ide_mensal | C34: Y_kWh_Ajustado | D34: kwh | E34: Calculado (fórmula) | F34: Variável dependente: eletricidade real sem as máquinas novas (ALE-01). | H34: Sim
A35: IDE_Mensal | B35: tbl_ide_mensal | C35: X1_Unid_mil | D35: Decimal | E35: Calculado (fórmula) | F35: Variável relevante 1: milhares de unidades INJ + SOP (sem máquinas novas). | H35: Sim
A36: IDE_Mensal | B36: tbl_ide_mensal | C36: X2_CDD | D36: Decimal | E36: Calculado (fórmula) | F36: Variável relevante 2: graus-dia de arrefecimento base 15 °C. | H36: Sim
A37: IDE_Mensal | B37: tbl_ide_mensal | C37: kWh_Esperado | D37: kwh | E37: Calculado (fórmula) | F37: Energia esperada pelo modelo da LBE-01 nas condições do mês (normalização). | H37: Sim
A38: IDE_Mensal | B38: tbl_ide_mensal | C38: Diferenca_kWh | D38: kwh | E38: Calculado (fórmula) | F38: Real − esperado (negativo = poupança). | H38: Sim
A39: IDE_Mensal | B39: tbl_ide_mensal | C39: CUSUM_kWh | D39: kwh | E39: Calculado (fórmula) | F39: Soma acumulada das diferenças desde o início da LBE (tendência). | H39: Sim
A40: IDE_Mensal | B40: tbl_ide_mensal | C40: Melhoria_Pct | D40: Percentagem (fração 0-1) | E40: Calculado (fórmula) | F40: IDE-01: (esperado − real) ÷ esperado. | H40: Sim
A41: IDE_Mensal | B41: tbl_ide_mensal | C41: Dentro_Dominio | D41: Texto | E41: Calculado (fórmula) | F41: As variáveis do mês estão dentro do intervalo da LBE (± tolerância)? Fora do domínio o modelo extrapola (ISO 50006 §8.2). | H41: Sim
A42: IDE_Mensal | B42: tbl_ide_mensal | C42: Estado_IDE01 | D42: Texto | E42: Calculado (fórmula) | F42: Classificação do mês: limite = t(95%) × erro-padrão do modelo (9.1.1 — investigar desvios significativos). | H42: Sim
A43: IDE_Mensal | B43: tbl_ide_mensal | C43: SEC_Real | D43: Decimal | E43: Calculado (fórmula) | F43: IDE-02: kWh por 1.000 unidades (rácio, instalação completa). | H43: Sim
A44: IDE_Mensal | B44: tbl_ide_mensal | C44: SEC_SOP | D44: Decimal | E44: Calculado (fórmula) | F44: IDE-03 (estimado). | H44: Sim
... A49: IDE_Mensal | B49: tbl_ide_mensal | C49: Energia_Final_MWh | D49: Decimal | E49: Calculado (fórmula) | F49: IDE-09. | H49: Sim
A50: Variaveis_Relevantes | B50: tbl_variaveis | C50: ID_Variavel | D50: Texto | E50: Entrada | F50: Variável candidata. | H50: Sim | I50: PK
A51: Variaveis_Relevantes | B51: tbl_variaveis | C51: Variavel | D51: Texto | E51: Entrada | F51: Descrição. | H51: Sim
A52: Variaveis_Relevantes | B52: tbl_variaveis | C52: Coluna_Base | D52: Texto | E52: Entrada | F52: Coluna em tbl_base_energia. | H52: Sim
A53: Variaveis_Relevantes | B53: tbl_variaveis | C53: Fonte | D53: Texto | E53: Entrada | F53: Origem do dado. | H53: Sim
A54: Variaveis_Relevantes | B54: tbl_variaveis | C54: Unidade | D54: Texto | E54: Entrada | F54: Unidade. | H54: Sim
A55: Variaveis_Relevantes | B55: tbl_variaveis | C55: Correlacao_com_kWh | D55: Decimal | E55: Calculado (fórmula) | F55: Coeficiente de correlação (Pearson) com o kWh total nos 12 meses de referência. | H55: Sim
A56: Variaveis_Relevantes | B56: tbl_variaveis | C56: R2_Simples | D56: Decimal | E56: Calculado (fórmula) | F56: R² da regressão simples. | H56: Sim
A57: Variaveis_Relevantes | B57: tbl_variaveis | C57: Decisao | D57: Texto | E57: Entrada | F57: Relevante (entra no modelo) / Não relevante / Redundante. | H57: Sim
A58: Variaveis_Relevantes | B58: tbl_variaveis | C58: Justificacao | D58: Texto | E58: Entrada | F58: Porquê (critério: significância estatística e sentido físico). | H58: Sim
A59: Catalogo_IDE | B59: tbl_kpi | C59: ID_KPI | D59: Texto | E59: Entrada | F59: IDE-xx = indicador de desempenho energético; KPI-E-xx = indicador do sistema. | H59: Sim | I59: PK
A60: Catalogo_IDE | B60: tbl_kpi | C60: Nome | D60: Texto | E60: Entrada | F60: Nome do indicador. | H60: Sim
A61: Catalogo_IDE | B61: tbl_kpi | C61: Formula_Calculo | D61: Texto | E61: Entrada | F61: Definição operacional. | H61: Sim
A62: Catalogo_IDE | B62: tbl_kpi | C62: Unidade | D62: Texto | E62: Entrada | F62: Unidade. | H62: Sim
A63: Catalogo_IDE | B63: tbl_kpi | C63: Polaridade | D63: Texto | E63: Entrada | F63: Maior ou menor é melhor. | G63: Lista lst_Polaridade | H63: Sim
A64: Catalogo_IDE | B64: tbl_kpi | C64: Tipo_IDE_ISO50006 | D64: Texto | E64: Entrada | F64: Tipo de IDE (ISO 50006 §6.2) — posição equivalente ao Tipo_ISO14031 do RG-SGA-05. | G64: Lista lst_TipoIDE | H64: Sim
A65: Catalogo_IDE | B65: tbl_kpi | C65: Frequencia | D65: Texto | E65: Entrada | F65: Frequência de cálculo. | H65: Sim
A66: Catalogo_IDE | B66: tbl_kpi | C66: Fonte_Dados | D66: Texto | E66: Entrada | F66: Origem dos dados. | H66: Sim
A67: Catalogo_IDE | B67: tbl_kpi | C67: Responsavel | D67: Texto | E67: Entrada | F67: Dono do IDE (ISO 50006 tab. 1 — 'EnPI owner'). | G67: Lista lst_Funcao | H67: Sim
A68: Catalogo_IDE | B68: tbl_kpi | C68: Baseline | D68: Decimal | E68: Calculado (fórmula) | F68: Valor da LBE: média dos 12 meses de referência (ou valor externo quando o IDE vem de outro registo). | H68: Sim
A69: Catalogo_IDE | B69: tbl_kpi | C69: ID_OBJ | D69: Texto | E69: Entrada | F69: Objetivo que o indicador mede. | H69: Sim | I69: FK → tbl_objetivos
A70: Catalogo_IDE | B70: tbl_kpi | C70: ID_MED | D70: Texto | E70: Entrada | F70: Linhas do plano de recolha de dados (RG-SGE-06). | H70: Sim | I70: FK → RG-SGE-06 tbl_plano_recolha
A71: Catalogo_IDE | B71: tbl_kpi | C71: Fronteira | D71: Texto | E71: Entrada | F71: [Só SGE] Fronteira do IDE (ISO 50006 §5.3). | H71: Sim
A72: Catalogo_IDE | B72: tbl_kpi | C72: ID_USE | D72: Texto | E72: Entrada | F72: [Só SGE] Uso significativo abrangido. | H72: Sim
A73: Catalogo_IDE | B73: tbl_kpi | C73: Variaveis_Relevantes | D73: Texto | E73: Entrada | F73: [Só SGE] Variáveis relevantes consideradas (6.4). | H73: Sim
A74: Catalogo_IDE | B74: tbl_kpi | C74: Fatores_Estaticos | D74: Texto | E74: Entrada | F74: [Só SGE] Fatores estáticos monitorizados. | H74: Sim
A75: Catalogo_IDE | B75: tbl_kpi | C75: Normalizacao | D75: Texto | E75: Entrada | F75: [Só SGE] Se e como é normalizado (6.5; ISO 50006 §8). | H75: Sim
A76: Catalogo_IDE | B76: tbl_kpi | C76: ID_LBE | D76: Texto | E76: Entrada | F76: [Só SGE] LBE correspondente. | H76: Sim | I76: FK → tbl_lbe
A77: Catalogo_IDE | B77: tbl_kpi | C77: Utilizadores | D77: Texto | E77: Entrada | F77: [Só SGE] Utilizadores do IDE (ISO 50006 §5.2). | H77: Sim
A78: Catalogo_IDE | B78: tbl_kpi | C78: Coluna_Mensal | D78: Texto | E78: Entrada | F78: [Só SGE] Coluna em tbl_ide_mensal ('—' se vem de outro registo). | H78: Sim
A79: Catalogo_IDE | B79: tbl_kpi | C79: Meta | D79: Decimal | E79: Entrada | F79: [Só SGE] Meta energética associada (percentagens como fração). | H79: Não
A80: Catalogo_IDE | B80: tbl_kpi | C80: Valor_LBE_Externo | D80: Decimal | E80: Entrada | F80: [Só SGE] Valor da LBE quando o IDE é calculado noutro registo (à data de referência). | H80: Não
A81: Catalogo_IDE | B81: tbl_kpi | C81: Valor_Reporte_Externo | D81: Decimal | E81: Entrada | F81: [Só SGE] Valor atual quando o IDE é calculado noutro registo. | H81: Não
A82: Catalogo_IDE | B82: tbl_kpi | C82: Valor_Reporte | D82: Decimal | E82: Calculado (fórmula) | F82: [Só SGE] Média dos meses de reporte mar–dez/2026 (IDE-01: agregado oficial da LBE_Modelo; IDE-08 e KPI-E-01: valor de dez/2026). | H82: Sim
A83: Catalogo_IDE | B83: tbl_kpi | C83: Variacao_vs_LBE | D83: Percentagem (fração 0-1) | E83: Calculado (fórmula) | F83: [Só SGE] Variação relativa do reporte face à LBE. | H83: Sim
A84: Catalogo_IDE | B84: tbl_kpi | C84: Estado | D84: Texto | E84: Calculado (fórmula) | F84: [Só SGE] Estado face à meta. | H84: Sim
A85: Catalogo_IDE | B85: tbl_kpi | C85: Ligacao_SGI | D85: Texto | E85: Entrada | F85: [Só SGE] Indicador equivalente no SGA/SGQ. | H85: Não
A86: Catalogo_IDE | B86: tbl_kpi | C86: Qualidade_Dados | D86: Texto | E86: Entrada | F86: [Só SGE] Medido / estimado / calculado (EN 17267). | H86: Sim
A87: Registo_LBE | B87: tbl_lbe | C87: ID_LBE | D87: Texto | E87: Entrada | F87: Linha de base energética. | H87: Sim | I87: PK
A88: Registo_LBE | B88: tbl_lbe | C88: ID_KPI | D88: Texto | E88: Entrada | F88: IDE que a usa. | H88: Sim | I88: FK → tbl_kpi
A89: Registo_LBE | B89: tbl_lbe | C89: Descricao | D89: Texto | E89: Entrada | F89: O que é a LBE. | H89: Sim
A90: Registo_LBE | B90: tbl_lbe | C90: Periodo_Inicio | D90: Data (aaaa-mm-dd) | E90: Entrada | F90: Início do período de referência. | H90: Sim
A91: Registo_LBE | B91: tbl_lbe | C91: Periodo_Fim | D91: Data (aaaa-mm-dd) | E91: Entrada | F91: Fim do período de referência. | H91: Sim
A92: Registo_LBE | B92: tbl_lbe | C92: N_Meses | D92: Inteiro | E92: Calculado (fórmula) | F92: Duração (meses). | H92: Sim
A93: Registo_LBE | B93: tbl_lbe | C93: Metodo | D93: Texto | E93: Entrada | F93: Modelo / cálculo. | H93: Sim
A94: Registo_LBE | B94: tbl_lbe | C94: Valor_LBE | D94: Decimal | E94: Calculado (fórmula) | F94: Valor da LBE (do catálogo). | H94: Sim
A95: Registo_LBE | B95: tbl_lbe | C95: R2 | D95: Decimal | E95: Entrada | F95: R² (só modelos). | H95: Não
A96: Registo_LBE | B96: tbl_lbe | C96: Validade_Estatistica | D96: Texto | E96: Entrada | F96: Resultado dos testes (LBE_Modelo). | H96: Não
A97: Registo_LBE | B97: tbl_lbe | C97: Estado | D97: Texto | E97: Entrada | F97: Em vigor / planeado / substituída. | G97: Lista lst_EstadoLBE | H97: Sim
A98: Registo_LBE | B98: tbl_lbe | C98: Data_Aprovacao | D98: Data (aaaa-mm-dd) | E98: Entrada | F98: Aprovação pela equipa de gestão de energia. | H98: Não
A99: Registo_LBE | B99: tbl_lbe | C99: Criterios_Revisao | D99: Texto | E99: Entrada | F99: Quando rever (6.5 a) IDE deixa de representar; b) fatores estáticos; c) método predeterminado). | H99: Sim
A100: Registo_LBE | B100: tbl_lbe | C100: Proxima_Revisao | D100: Data (aaaa-mm-dd) | E100: Entrada | F100: Revisão prevista. | H100: Não
A101: Alteracoes_LBE | B101: tbl_alteracoes_lbe | C101: ID_Alteracao_LBE | D101: Texto | E101: Entrada | F101: Alteração/ajuste. | H101: Sim | I101: PK
A102: Alteracoes_LBE | B102: tbl_alteracoes_lbe | C102: Data_Efeito | D102: Data (aaaa-mm-dd) | E102: Entrada | F102: Data a partir da qual tem efeito. | H102: Sim
A103: Alteracoes_LBE | B103: tbl_alteracoes_lbe | C103: Tipo | D103: Texto | E103: Entrada | F103: Fator estático / ação de melhoria / método de medição / tipo de energia. | H103: Sim
A104: Alteracoes_LBE | B104: tbl_alteracoes_lbe | C104: Descricao | D104: Texto | E104: Entrada | F104: O que mudou. | H104: Sim
A105: Alteracoes_LBE | B105: tbl_alteracoes_lbe | C105: LBE_Afetadas | D105: Texto | E105: Entrada | F105: LBE afetadas. | H105: Sim
A106: Alteracoes_LBE | B106: tbl_alteracoes_lbe | C106: Tratamento | D106: Texto | E106: Entrada | F106: Ajuste aplicado e justificação (ISO 50006 §9). | H106: Sim
A107: Alteracoes_LBE | B107: tbl_alteracoes_lbe | C107: Acao_Futura | D107: Texto | E107: Entrada | F107: O que falta fazer. | H107: Não
A108: Alteracoes_LBE | B108: tbl_alteracoes_lbe | C108: Estado | D108: Texto | E108: Entrada | F108: Aprovado / planeado. | H108: Sim
A109: Alteracoes_LBE | B109: tbl_alteracoes_lbe | C109: Responsavel | D109: Texto | E109: Entrada | F109: Responsável. | G109: Lista lst_Funcao | H109: Sim
A110: Alteracoes_LBE | B110: tbl_alteracoes_lbe | C110: Data_Aprovacao | D110: Data (aaaa-mm-dd) | E110: Entrada | F110: Aprovação. | H110: Não
A111: Fatores_Estaticos | B111: tbl_fatores_estaticos | C111: ID_Fator | D111: Texto | E111: Entrada | F111: Fator estático. | H111: Sim | I111: PK
A112: Fatores_Estaticos | B112: tbl_fatores_estaticos | C112: Fator_Estatico | D112: Texto | E112: Entrada | F112: Fator que não varia rotineiramente mas afeta o desempenho (ISO 50006 3.1.18). | H112: Sim
A113: Fatores_Estaticos | B113: tbl_fatores_estaticos | C113: Condicao_Na_LBE | D113: Texto | E113: Entrada | F113: Condição no período de referência. | H113: Sim
A114: Fatores_Estaticos | B114: tbl_fatores_estaticos | C114: Condicao_Atual | D114: Texto | E114: Entrada | F114: Condição à data de referência. | H114: Sim
A115: Fatores_Estaticos | B115: tbl_fatores_estaticos | C115: Situacao | D115: Texto | E115: Entrada | F115: Sem alteração / alterado. | H115: Sim
A116: Fatores_Estaticos | B116: tbl_fatores_estaticos | C116: ID_Alteracao_LBE | D116: Texto | E116: Entrada | F116: Tratamento. | H116: Não | I116: FK → tbl_alteracoes_lbe
A117: Parametros | B117: tbl_parametros | C117: Codigo | D117: Texto | E117: Entrada | F117: Parâmetro. | H117: Sim | I117: PK
A118: Parametros | B118: tbl_parametros | C118: Valor | D118: Decimal | E118: Entrada | F118: Valor. | H118: Sim
A119: Parametros | B119: tbl_parametros | C119: Unidade | D119: Texto | E119: Entrada | F119: Unidade. | H119: Sim
A120: Parametros | B120: tbl_parametros | C120: Descricao | D120: Texto | E120: Entrada | F120: Descrição. | H120: Sim
...
