Workbook
Name DataRef: Listas!$A$3
Name lst_DataReferencia: Listas!$A$3:$A$3
Name lst_Entrada932: Listas!$C$3:$C$10
Name lst_Funcao: Listas!$E$3:$E$24
Name lst_Presenca: Listas!$B$3:$B$5
Name lst_Saida933: Listas!$D$3:$D$9

Sheet 00_LEIA-ME
A1: RG-SGA-15 — Revisão pela Gestão 2026 — Ordem de Trabalhos, Participantes e Ata de Decisões
A2: Sistema de Gestão Ambiental NP EN ISO 14001:2026 · Plasticom — Unidade 1 (Marinha Grande, Portugal) · Registo do SGA (fábrica simulada)
A4: CONTROLO DO DOCUMENTO (7.5 — informação documentada)
A5: Código do registo | B5: RG-SGA-15
A6: Título | B6: Revisão pela Gestão 2026 — Ordem de Trabalhos, Participantes e Ata de Decisões
A7: Versão / Revisão | B7: 01
A8: Data de emissão | B8: 46387
A9: Elaborado por | B9: Gestor(a) do SGA / EHS
A10: Aprovado por | B10: Diretor Geral
A11: Estado | B11: Em vigor
A12: Retenção | B12: 5 anos após substituição
A13: Localização | B13: Repositório controlado do SGA > Registos_SGA_Plasticom (versão eletrónica é a versão controlada; cópias impressas são não controladas)
A15: FINALIDADE E ÂMBITO
A16: Finalidade | B16: Registar a convocatória, os participantes, a ordem de trabalhos ligada às entradas obrigatórias da 9.3.2 e às fontes de dados de cada ponto, as conclusões sobre adequação/suficiência/eficácia e as decisões com problema, decisão, recursos, responsável, prazo e ação no PAM.
A17: Atividades do curso | B17: Atividade 5.4 — Parte I: Ordem de Trabalhos (inputs da cláusula 9.3). Parte II: excerto da Ata com as decisões (reunião de 23/09/2026).
A18: Requisitos ISO 14001:2026 | B18: 9.3.1 Generalidades; 9.3.2 Entradas; 9.3.3 Resultados (estrutura da ISO 14001:2026)
A20: ESTRUTURA DO FICHEIRO
A21: Participantes | B21: Participantes convocados e presença.
A22: Ordem_Trabalhos | B22: Ordem de trabalhos: 1 linha por ponto, ligada à alínea da 9.3.2 e à fonte de dados.
A23: Ata_Decisoes | B23: Decisões da revisão pela gestão (saídas 9.3.3) com recursos, responsável e prazo.
A24: Conclusoes | B24: Conclusões sobre adequação, suficiência e eficácia (9.3.3).
A25: Convocatoria_Impressao | B25: Parte I — Convocatória/Ordem de trabalhos em formato de impressão (fórum), calculada a partir das tabelas.
A26: Ata_Impressao | B26: Parte II — Excerto da ata com as decisões (formato para auditor externo), calculado a partir de tbl_decisoes.
A27: Listas | B27: Domínios (listas de valores) usados na validação de dados das tabelas.
A28: Dicionario_Dados | B28: Descrição de cada coluna de cada tabela: tipo, origem (entrada/calculado), domínio, obrigatoriedade e chaves.
A30: CONVENÇÕES (prontas para análise de dados e machine learning)
A31: Tabelas | B31: Cada registo é uma Tabela Excel com nome próprio (tbl_*): uma linha = um registo, cabeçalho único, sem células mescladas. Ler com pandas (pd.read_excel(ficheiro, sheet_name=folha, header=<linha do cabeçalho - 1>)) ou Power BI (Obter Dados > Tabela).
A32: Cabeçalho cinzento | B32: Coluna CALCULADA por fórmula — não escrever por cima. As restantes colunas são de entrada.
A33: Validação | B33: Colunas com lista controlada só aceitam valores da folha Listas (evita categorias duplicadas por grafia diferente).
A34: Chaves | B34: IDs estáveis e únicos (PK) e referências a IDs de outros registos (FK) permitem juntar tabelas entre ficheiros — ver SGA-00_Indice_Modelo_Dados.xlsx.
A35: Datas e unidades | B35: Datas em formato data (aaaa-mm-dd); números como números; a unidade está no nome da coluna ou no dicionário. Data de referência do SGA: 2026-12-31 (fecho do ano).
A36: Dados simulados | B36: Fábrica simulada Plasticom. Dados operacionais derivados do dataset do projeto (datasets/silver); dados ambientais e de conformidade são simulação didática — confirmar aplicabilidade legal e números antes de uso real.
A38: LIGAÇÕES A OUTROS REGISTOS
A39: RG-SGA-06 PAM | B39: Cada decisão gera ação(ões) no PAM.
A40: Todos os registos | B40: A coluna Fonte_Dados indica o registo que alimenta cada ponto.

Sheet Participantes
A1: ID_Reuniao | B1: Funcao | C1: Papel | D1: Presenca
A2: RG-2026 | B2: Diretor Geral (Gestão de Topo) | C2: Preside e decide | D2: Presente
A3: RG-2026 | B3: Diretor Industrial | C3: Participante | D3: Presente
A4: RG-2026 | B4: Diretor Financeiro | C4: Participante (recursos) | D4: Presente
A5: RG-2026 | B5: Gestor do SGA / EHS (Responsável Ambiental) | C5: Apresenta e secretaria a ata | D5: Presente
A6: RG-2026 | B6: Gerente de Produção | C6: Participante | D6: Presente
A7: RG-2026 | B7: Gerente de Manutenção | C7: Participante | D7: Presente
A8: RG-2026 | B8: Gerente da Qualidade | C8: Participante (auditorias) | D8: Presente
A9: RG-2026 | B9: Responsável de Compras | C9: Participante | D9: Presente
A10: RG-2026 | B10: Responsável de R&D | C10: Participante (PPWR) | D10: Presente
A11: RG-2026 | B11: Responsável de Armazém e Logística | C11: Convidado (pontos 6 e 7) | D11: Presente
A12: RG-2026 | B12: Responsável de Recursos Humanos | C12: Participante (competências) | D12: Ausente justificado
A13: RG-2026 | B13: Representante dos Trabalhadores (SST/Ambiente) | C13: Participante (consulta e participação) | D13: Presente

Sheet Ordem_Trabalhos
A1: ORDEM DE TRABALHOS — REVISÃO PELA GESTÃO 2026
A2: 23/09/2026, 14:30–17:30 · Sala de Reuniões da Administração, Plasticom Unidade 1 · Convocatória enviada a 09/09/2026
A4: ID_Reuniao | B4: Ponto | C4: Entrada_9_3_2 | D4: Topico | E4: Fonte_Dados | F4: Apresentador | G4: Duracao_min | H4: Hora_Inicio | I4: N_Decisoes
A5: RG-2026 | B5: 1 | C5: 9.3.2 a) | D5: Abertura; estado das ações da revisão pela gestão de 2025 (4 decisões: 3 concluídas, 1 em curso). | E5: Atas RG-2025; RG-SGA-06 | F5: Diretor Geral | G5: 10 | H5: =TIME(14,30,0)+SUMIFS($G$5:$G$14,$B$5:$B$14,"<"&B5)/1440 -> 0.60416667 | I5: =COUNTIF(tbl_decisoes[Ponto_Agenda],B5) -> 0
A6: RG-2026 | B6: 2 | C6: 9.3.2 b) | D6: Alterações nas questões externas e internas relevantes, incluindo as condições ambientais: verão de 2026 mais quente (+2 °C), risco de seca, risco de incêndio florestal, preço da energia e mercado de PCR. | E6: RG-SGA-01 (PESTEL/SWOT) | F6: Gestor do SGA / EHS (Responsável Ambiental) | G6: 15 | H6: =TIME(14,30,0)+SUMIFS($G$5:$G$14,$B$5:$B$14,"<"&B6)/1440 -> 0.61111111 | I6: =COUNTIF(tbl_decisoes[Ponto_Agenda],B6) -> 0
A7: RG-2026 | B7: 3 | C7: 9.3.2 b) | D7: Necessidades e expectativas das partes interessadas e obrigações de conformidade: PPWR aplicável desde 12/08/2026, regulamento europeu de granulados, reclamação de ruído da vizinhança, pedidos ESG de clientes. | E7: RG-SGA-04; registo de reclamações | F7: Gestor do SGA / EHS (Responsável Ambiental) | G7: 15 | H7: =TIME(14,30,0)+SUMIFS($G$5:$G$14,$B$5:$B$14,"<"&B7)/1440 -> 0.62152778 | I7: =COUNTIF(tbl_decisoes[Ponto_Agenda],B7) -> 1
A8: RG-2026 | B8: 4 | C8: 9.3.2 b) | D8: Aspetos ambientais significativos (COV da serigrafia, ruído dos compressores, embalagens sem declaração PPWR) e riscos e oportunidades significativos (6 riscos, 1 oportunidade). | E8: RG-SGA-03; RG-SGA-02 | F8: Gestor do SGA / EHS (Responsável Ambiental) | G8: 15 | H8: =TIME(14,30,0)+SUMIFS($G$5:$G$14,$B$5:$B$14,"<"&B8)/1440 -> 0.63194444 | I8: =COUNTIF(tbl_decisoes[Ponto_Agenda],B8) -> 0
A9: RG-2026 | B9: 5 | C9: 9.3.2 c) | D9: Grau de cumprimento dos objetivos ambientais OBJ-01 a OBJ-06 (energia, scrap, solvente, PPWR, água, granulado). | E9: RG-SGA-05 | F9: Diretor Industrial | G9: 15 | H9: =TIME(14,30,0)+SUMIFS($G$5:$G$14,$B$5:$B$14,"<"&B9)/1440 -> 0.64236111 | I9: =COUNTIF(tbl_decisoes[Ponto_Agenda],B9) -> 0
A10: RG-2026 | B10: 6 | C10: 9.3.2 d) | D10: Desempenho ambiental: tendências de 18 meses dos KPI; desvio de +15% no solvente; não conformidades e ações corretivas (9 NC em 2026); avaliação da conformidade legal (82%, 2 NC); auditoria interna AUD-2026-01 (6 NC, 4 OM). | E10: RG-SGA-13; RG-SGA-07; RG-SGA-04; RG-SGA-14 | F10: Gestor do SGA / EHS (Responsável Ambiental) | G10: 35 | H10: =TIME(14,30,0)+SUMIFS($G$5:$G$14,$B$5:$B$14,"<"&B10)/1440 -> 0.65277778 | I10: =COUNTIF(tbl_decisoes[Ponto_Agenda],B10) -> 2
A11: RG-2026 | B11: 7 | C11: 9.3.2 e) | D11: Adequação dos recursos: submedição, recursos para o PPWR, formação de temporários, equipamento de recuperação de solvente. | E11: RG-SGA-06; RG-SGA-08 | F11: Diretor Financeiro | G11: 15 | H11: =TIME(14,30,0)+SUMIFS($G$5:$G$14,$B$5:$B$14,"<"&B11)/1440 -> 0.67708333 | I11: =COUNTIF(tbl_decisoes[Ponto_Agenda],B11) -> 1
A12: RG-2026 | B12: 8 | C12: 9.3.2 f) | D12: Comunicações relevantes das partes interessadas, incluindo reclamações (ruído) e sugestões dos trabalhadores (caixa Kaizen). | E12: RG-SGA-09; RG-SGA-16 | F12: Representante dos Trabalhadores (SST/Ambiente) | G12: 10 | H12: =TIME(14,30,0)+SUMIFS($G$5:$G$14,$B$5:$B$14,"<"&B12)/1440 -> 0.6875 | I12: =COUNTIF(tbl_decisoes[Ponto_Agenda],B12) -> 0
A13: RG-2026 | B13: 9 | C13: 9.3.2 g) | D13: Oportunidades de melhoria contínua: Kaizen do turno 3, fotovoltaico, preparação do registo EMAS. | E13: RG-SGA-16; RG-SGA-02 | F13: Gestor do SGA / EHS (Responsável Ambiental) | G13: 15 | H13: =TIME(14,30,0)+SUMIFS($G$5:$G$14,$B$5:$B$14,"<"&B13)/1440 -> 0.69444444 | I13: =COUNTIF(tbl_decisoes[Ponto_Agenda],B13) -> 1
A14: RG-2026 | B14: 10 | C14: 9.3.3 | D14: Conclusões sobre a adequação, suficiência e eficácia do SGA; decisões, recursos e alterações ao SGA; encerramento. | E14: — | F14: Diretor Geral | G14: 20 | H14: =TIME(14,30,0)+SUMIFS($G$5:$G$14,$B$5:$B$14,"<"&B14)/1440 -> 0.70486111 | I14: =COUNTIF(tbl_decisoes[Ponto_Agenda],B14) -> 0

Sheet Ata_Decisoes
A1: ID_Decisao | B1: Ponto_Agenda | C1: Tipo_Saida_9_3_3 | D1: Problema_Analise | E1: Decisao_Tomada | F1: Recursos_EUR | G1: Recursos_Pessoas | H1: Responsavel | I1: Prazo | J1: IDs_PAM | K1: Dias_ate_Prazo
A2: RG-26-D01 | B2: 6 | C2: Oportunidades de melhoria contínua | D2: O consumo específico de solvente de limpeza na serigrafia subiu 15% em jun–ago/2026 com a produção estável; o aspeto (COV) é significativo (IRA 40) e o solvente usado é enviado como resíduo perigoso. As causas confirmadas são recipientes abertos, a SS-001 após o overhaul e um operador temporário sem formação. | E2: Aprovar a compra de uma unidade de recuperação de solvente (destilador de 60 L) e de 4 dispensadores de segurança, e tornar obrigatória a formação FOR-02 antes de qualquer temporário trabalhar na serigrafia. | F2: 14100 | G2: Gestor do SGA (0,1 ETI); chefe de serigrafia; fornecedor do destilador | H2: Gestor do SGA / EHS (Responsável Ambiental) | I2: 46477 | J2: PAM-26-13; PAM-26-08 | K2: =I2-DataRef -> 90
A3: RG-26-D02 | B3: 3 | C3: Implicações para a direção estratégica | D3: O PPWR aplica-se desde 12/08/2026 e só 9 de 22 famílias (41%) têm documentação técnica e declaração UE de conformidade (NC legal); os clientes alimentares e farmacêuticos já pedem as declarações. | E3: Contratar consultoria especializada em PPWR, afetar um técnico de qualidade/ambiente a 50% durante 6 meses e priorizar as famílias por volume de vendas; o incumprimento passa a ser risco estratégico acompanhado mensalmente pela gestão. | F3: 26000 | G3: Responsável de R&D; técnico Q/A (0,5 ETI, 6 meses); consultor externo | H3: Responsável de R&D | I3: 46387 | J3: PAM-26-10 | K3: =I3-DataRef -> 0
A4: RG-26-D03 | B4: 7 | C4: Recursos | D4: Sem submedição não é possível demonstrar o desempenho de energia e água (RO-02, nível -6) nem medir o efeito das ações; o ar comprimido tem ≈ 25% de fugas. | E4: Aprovar o CAPEX de submedição (6 analisadores + 3 contadores) e do variador de velocidade do compressor, e submeter candidatura ao Portugal 2030 para cofinanciamento. | F4: 38000 | G4: Gerente de Manutenção; técnico de utilidades; instalador | H4: Gerente de Manutenção | I4: 46387 | J4: PAM-26-01; PAM-26-02 | K4: =I4-DataRef -> 0
A5: RG-26-D04 | B5: 9 | C5: Oportunidades de melhoria contínua | D5: Oportunidade RO-09: fotovoltaico em ≈ 9.000 m² de cobertura; clientes pedem dados de carbono; o registo EMAS daria acesso a clientes públicos e a menos inspeções. | E5: Encomendar o estudo de viabilidade de uma UPAC de ≈ 1 MWp e preparar o diagnóstico para o registo EMAS em 2027 (declaração ambiental com os 6 indicadores principais). | F5: 4000 | G5: Diretor Financeiro; Gestor do SGA | H5: Diretor Financeiro | I5: 46477 | J5: PAM-26-18 | K5: =I5-DataRef -> 90
A6: RG-26-D05 | B6: 6 | C6: Necessidade de alterações ao SGA | D6: A auditoria AUD-2026-01 detetou que a substituição dos compressores não passou por avaliação ambiental (requisito novo 6.3 da ISO 14001:2026), o que originou a NC legal de ruído. | E6: Aprovar o procedimento PR-SGA-06 'Planeamento de alterações' com checklist ambiental/legal obrigatória antes de qualquer investimento em equipamento, processo, layout ou material. | F6: 0 | G6: Gestor do SGA; Diretor Industrial | H6: Gestor do SGA / EHS (Responsável Ambiental) | I6: 46356 | J6: PAM-26-17 | K6: =I6-DataRef -> -31

Sheet Conclusoes
A1: Tema | B1: Conclusao
A2: Adequação | B2: O SGA continua adequado ao contexto da Plasticom, mas tem de integrar o PPWR, o regulamento de granulados e a gestão de alterações (6.3).
A3: Suficiência | B3: Recursos insuficientes em medição e em conformidade de produto: reforçados pelas decisões D02 e D03.
A4: Eficácia | B4: Eficácia parcial: 2 de 6 objetivos no caminho previsto (energia, scrap); solvente e água com desvio; 1 de 2 ações de NC verificadas como eficazes.
A5: Política Ambiental | B5: Rev. 02 (junho/2026) mantém-se adequada; não é necessária alteração.

Sheet Convocatoria_Impressao
A1: PLASTICOM | B1: CONVOCATÓRIA — REVISÃO PELA GESTÃO DO SGA 2026 | E1: RG-SGA-15
B2: Plasticom — Unidade 1 (Marinha Grande, Portugal) · NP EN ISO 14001:2026 | E2: Rev. 01 · 31/12/2026
A5: Data e hora | C5: 23/09/2026, 14:30–17:30
A6: Local | C6: Sala de Reuniões da Administração — Plasticom, Unidade 1 (Marinha Grande)
A7: Convocada por | C7: Diretor Geral, sob proposta do Gestor do SGA/EHS
A8: Participantes | C8: =INDEX(Participantes!$B$2:$B$13,1)&", "&INDEX(Participantes!$B$2:$B$13,2)&", "&INDEX(Participantes!$B$2:$B$13,3)&", "&INDEX(Participantes!$B$2:$B$13,4)&", "&INDEX(Participantes!$B$2:$B$13,5)&", "&INDEX(Participantes!$B$2:$B$13,6)&", "&INDEX(Participantes!$B$2:$B$13,7)&", "&INDEX(Participantes!$B$2:$B$13,8)&", "&INDEX(Participantes!$B$2:$B$13,9)&", "&INDEX(Participantes!$B$2:$B$13,10)&", "&INDEX(Participantes!$B$2:$B$13,11)&", "&INDEX(Participantes!$B$2:$B$13,12) -> Diretor Geral (Gestão de Topo), Diretor Industrial, Diretor Financeiro, Gestor do SGA / EHS (Responsável Ambiental), Gerente de Produção, Gerente de Manutenção, Gerente da Qualidade, Responsável de Compras, Responsável de R&D, Responsável de Armazém e Logística, Responsável de Recursos Humanos, Representante dos Trabalhadores (SST/Ambiente)
A9: Documentos de apoio | C9: Registos RG-SGA-01 a RG-SGA-16 e painel ambiental (enviados a 16/09/2026)
A11: Ponto | B11: Hora | C11: Tópico (entrada da 9.3.2) | D11: Apresentador | E11: Min
A12: =INDEX(Ordem_Trabalhos!$B$5:$B$14,1) -> 1 | B12: =INDEX(Ordem_Trabalhos!$H$5:$H$14,1) -> 0.60416667 | C12: =INDEX(Ordem_Trabalhos!$D$5:$D$14,1)&" ["&INDEX(Ordem_Trabalhos!$C$5:$C$14,1)&"]" -> Abertura; estado das ações da revisão pela gestão de 2025 (4 decisões: 3 concluídas, 1 em curso). [9.3.2 a)] | D12: =INDEX(Ordem_Trabalhos!$F$5:$F$14,1) -> Diretor Geral | E12: =INDEX(Ordem_Trabalhos!$G$5:$G$14,1) -> 10
A13: =INDEX(Ordem_Trabalhos!$B$5:$B$14,2) -> 2 | B13: =INDEX(Ordem_Trabalhos!$H$5:$H$14,2) -> 0.61111111 | C13: =INDEX(Ordem_Trabalhos!$D$5:$D$14,2)&" ["&INDEX(Ordem_Trabalhos!$C$5:$C$14,2)&"]" -> Alterações nas questões externas e internas relevantes, incluindo as condições ambientais: verão de 2026 mais quente (+2 °C), risco de seca, risco de incêndio florestal, preço da energia e mercado de PCR. [9.3.2 b)] | D13: =INDEX(Ordem_Trabalhos!$F$5:$F$14,2) -> Gestor do SGA / EHS (Responsável Ambiental) | E13: =INDEX(Ordem_Trabalhos!$G$5:$G$14,2) -> 15
A14: =INDEX(Ordem_Trabalhos!$B$5:$B$14,3) -> 3 | B14: =INDEX(Ordem_Trabalhos!$H$5:$H$14,3) -> 0.62152778 | C14: =INDEX(Ordem_Trabalhos!$D$5:$D$14,3)&" ["&INDEX(Ordem_Trabalhos!$C$5:$C$14,3)&"]" -> Necessidades e expectativas das partes interessadas e obrigações de conformidade: PPWR aplicável desde 12/08/2026, regulamento europeu de granulados, reclamação de ruído da vizinhança, pedidos ESG de clientes. [9.3.2 b)] | D14: =INDEX(Ordem_Trabalhos!$F$5:$F$14,3) -> Gestor do SGA / EHS (Responsável Ambiental) | E14: =INDEX(Ordem_Trabalhos!$G$5:$G$14,3) -> 15
A15: =INDEX(Ordem_Trabalhos!$B$5:$B$14,4) -> 4 | B15: =INDEX(Ordem_Trabalhos!$H$5:$H$14,4) -> 0.63194444 | C15: =INDEX(Ordem_Trabalhos!$D$5:$D$14,4)&" ["&INDEX(Ordem_Trabalhos!$C$5:$C$14,4)&"]" -> Aspetos ambientais significativos (COV da serigrafia, ruído dos compressores, embalagens sem declaração PPWR) e riscos e oportunidades significativos (6 riscos, 1 oportunidade). [9.3.2 b)] | D15: =INDEX(Ordem_Trabalhos!$F$5:$F$14,4) -> Gestor do SGA / EHS (Responsável Ambiental) | E15: =INDEX(Ordem_Trabalhos!$G$5:$G$14,4) -> 15
A16: =INDEX(Ordem_Trabalhos!$B$5:$B$14,5) -> 5 | B16: =INDEX(Ordem_Trabalhos!$H$5:$H$14,5) -> 0.64236111 | C16: =INDEX(Ordem_Trabalhos!$D$5:$D$14,5)&" ["&INDEX(Ordem_Trabalhos!$C$5:$C$14,5)&"]" -> Grau de cumprimento dos objetivos ambientais OBJ-01 a OBJ-06 (energia, scrap, solvente, PPWR, água, granulado). [9.3.2 c)] | D16: =INDEX(Ordem_Trabalhos!$F$5:$F$14,5) -> Diretor Industrial | E16: =INDEX(Ordem_Trabalhos!$G$5:$G$14,5) -> 15
A17: =INDEX(Ordem_Trabalhos!$B$5:$B$14,6) -> 6 | B17: =INDEX(Ordem_Trabalhos!$H$5:$H$14,6) -> 0.65277778 | C17: =INDEX(Ordem_Trabalhos!$D$5:$D$14,6)&" ["&INDEX(Ordem_Trabalhos!$C$5:$C$14,6)&"]" -> Desempenho ambiental: tendências de 18 meses dos KPI; desvio de +15% no solvente; não conformidades e ações corretivas (9 NC em 2026); avaliação da conformidade legal (82%, 2 NC); auditoria interna AUD-2026-01 (6 NC, 4 OM). [9.3.2 d)] | D17: =INDEX(Ordem_Trabalhos!$F$5:$F$14,6) -> Gestor do SGA / EHS (Responsável Ambiental) | E17: =INDEX(Ordem_Trabalhos!$G$5:$G$14,6) -> 35
A18: =INDEX(Ordem_Trabalhos!$B$5:$B$14,7) -> 7 | B18: =INDEX(Ordem_Trabalhos!$H$5:$H$14,7) -> 0.67708333 | C18: =INDEX(Ordem_Trabalhos!$D$5:$D$14,7)&" ["&INDEX(Ordem_Trabalhos!$C$5:$C$14,7)&"]" -> Adequação dos recursos: submedição, recursos para o PPWR, formação de temporários, equipamento de recuperação de solvente. [9.3.2 e)] | D18: =INDEX(Ordem_Trabalhos!$F$5:$F$14,7) -> Diretor Financeiro | E18: =INDEX(Ordem_Trabalhos!$G$5:$G$14,7) -> 15
A19: =INDEX(Ordem_Trabalhos!$B$5:$B$14,8) -> 8 | B19: =INDEX(Ordem_Trabalhos!$H$5:$H$14,8) -> 0.6875 | C19: =INDEX(Ordem_Trabalhos!$D$5:$D$14,8)&" ["&INDEX(Ordem_Trabalhos!$C$5:$C$14,8)&"]" -> Comunicações relevantes das partes interessadas, incluindo reclamações (ruído) e sugestões dos trabalhadores (caixa Kaizen). [9.3.2 f)] | D19: =INDEX(Ordem_Trabalhos!$F$5:$F$14,8) -> Representante dos Trabalhadores (SST/Ambiente) | E19: =INDEX(Ordem_Trabalhos!$G$5:$G$14,8) -> 10
A20: =INDEX(Ordem_Trabalhos!$B$5:$B$14,9) -> 9 | B20: =INDEX(Ordem_Trabalhos!$H$5:$H$14,9) -> 0.69444444 | C20: =INDEX(Ordem_Trabalhos!$D$5:$D$14,9)&" ["&INDEX(Ordem_Trabalhos!$C$5:$C$14,9)&"]" -> Oportunidades de melhoria contínua: Kaizen do turno 3, fotovoltaico, preparação do registo EMAS. [9.3.2 g)] | D20: =INDEX(Ordem_Trabalhos!$F$5:$F$14,9) -> Gestor do SGA / EHS (Responsável Ambiental) | E20: =INDEX(Ordem_Trabalhos!$G$5:$G$14,9) -> 15
A21: =INDEX(Ordem_Trabalhos!$B$5:$B$14,10) -> 10 | B21: =INDEX(Ordem_Trabalhos!$H$5:$H$14,10) -> 0.70486111 | C21: =INDEX(Ordem_Trabalhos!$D$5:$D$14,10)&" ["&INDEX(Ordem_Trabalhos!$C$5:$C$14,10)&"]" -> Conclusões sobre a adequação, suficiência e eficácia do SGA; decisões, recursos e alterações ao SGA; encerramento. [9.3.3] | D21: =INDEX(Ordem_Trabalhos!$F$5:$F$14,10) -> Diretor Geral | E21: =INDEX(Ordem_Trabalhos!$G$5:$G$14,10) -> 20

Sheet Ata_Impressao
A1: PLASTICOM | B1: RG-SGA-15
B2: Plasticom — Unidade 1 (Marinha Grande, Portugal) · NP EN ISO 14001:2026
A5: Reunião | B5: 23/09/2026, 14:30–17:30, Sala de Reuniões da Administração. Presidida pelo Diretor Geral; secretariada pelo Gestor do SGA/EHS.
A6: Presenças | B6: =COUNTIF(Participantes!$D$2:$D$13,"Presente")&" de "&COUNTA(Participantes!$B$2:$B$13)&" convocados presentes" -> 11 de 12 convocados presentes
A8: ="DECISÃO "&INDEX(Ata_Decisoes!$A$2:$A$6,1)&" (ponto "&INDEX(Ata_Decisoes!$B$2:$B$6,1)&")" -> DECISÃO RG-26-D01 (ponto 6)
A9: Problema / Análise | B9: =INDEX(Ata_Decisoes!$D$2:$D$6,1) -> O consumo específico de solvente de limpeza na serigrafia subiu 15% em jun–ago/2026 com a produção estável; o aspeto (COV) é significativo (IRA 40) e o solvente usado é enviado como resíduo perigoso. As causas confirmadas são recipientes abertos, a SS-001 após o overhaul e um operador temporário sem formação.
A10: Decisão tomada | B10: =INDEX(Ata_Decisoes!$E$2:$E$6,1) -> Aprovar a compra de uma unidade de recuperação de solvente (destilador de 60 L) e de 4 dispensadores de segurança, e tornar obrigatória a formação FOR-02 antes de qualquer temporário trabalhar na serigrafia.
A11: Recursos alocados | B11: =FIXED(INDEX(Ata_Decisoes!$F$2:$F$6,1),0)&" € — "&INDEX(Ata_Decisoes!$G$2:$G$6,1) -> 14 100 € — Gestor do SGA (0,1 ETI); chefe de serigrafia; fornecedor do destilador
A12: Responsável e prazo | B12: =INDEX(Ata_Decisoes!$H$2:$H$6,1)&" — até "&TEXT(DAY(INDEX(Ata_Decisoes!$I$2:$I$6,1)),"00")&"/"&TEXT(MONTH(INDEX(Ata_Decisoes!$I$2:$I$6,1)),"00")&"/"&YEAR(INDEX(Ata_Decisoes!$I$2:$I$6,1)) -> Gestor do SGA / EHS (Responsável Ambiental) — até 31/03/2027
A13: Ações no PAM | B13: =INDEX(Ata_Decisoes!$J$2:$J$6,1) -> PAM-26-13; PAM-26-08
A15: ="DECISÃO "&INDEX(Ata_Decisoes!$A$2:$A$6,2)&" (ponto "&INDEX(Ata_Decisoes!$B$2:$B$6,2)&")" -> DECISÃO RG-26-D02 (ponto 3)
A16: Problema / Análise | B16: =INDEX(Ata_Decisoes!$D$2:$D$6,2) -> O PPWR aplica-se desde 12/08/2026 e só 9 de 22 famílias (41%) têm documentação técnica e declaração UE de conformidade (NC legal); os clientes alimentares e farmacêuticos já pedem as declarações.
A17: Decisão tomada | B17: =INDEX(Ata_Decisoes!$E$2:$E$6,2) -> Contratar consultoria especializada em PPWR, afetar um técnico de qualidade/ambiente a 50% durante 6 meses e priorizar as famílias por volume de vendas; o incumprimento passa a ser risco estratégico acompanhado mensalmente pela gestão.
A18: Recursos alocados | B18: =FIXED(INDEX(Ata_Decisoes!$F$2:$F$6,2),0)&" € — "&INDEX(Ata_Decisoes!$G$2:$G$6,2) -> 26 000 € — Responsável de R&D; técnico Q/A (0,5 ETI, 6 meses); consultor externo
A19: Responsável e prazo | B19: =INDEX(Ata_Decisoes!$H$2:$H$6,2)&" — até "&TEXT(DAY(INDEX(Ata_Decisoes!$I$2:$I$6,2)),"00")&"/"&TEXT(MONTH(INDEX(Ata_Decisoes!$I$2:$I$6,2)),"00")&"/"&YEAR(INDEX(Ata_Decisoes!$I$2:$I$6,2)) -> Responsável de R&D — até 31/12/2026
A20: Ações no PAM | B20: =INDEX(Ata_Decisoes!$J$2:$J$6,2) -> PAM-26-10
A22: ="DECISÃO "&INDEX(Ata_Decisoes!$A$2:$A$6,3)&" (ponto "&INDEX(Ata_Decisoes!$B$2:$B$6,3)&")" -> DECISÃO RG-26-D03 (ponto 7)
A23: Problema / Análise | B23: =INDEX(Ata_Decisoes!$D$2:$D$6,3) -> Sem submedição não é possível demonstrar o desempenho de energia e água (RO-02, nível -6) nem medir o efeito das ações; o ar comprimido tem ≈ 25% de fugas.
A24: Decisão tomada | B24: =INDEX(Ata_Decisoes!$E$2:$E$6,3) -> Aprovar o CAPEX de submedição (6 analisadores + 3 contadores) e do variador de velocidade do compressor, e submeter candidatura ao Portugal 2030 para cofinanciamento.
A25: Recursos alocados | B25: =FIXED(INDEX(Ata_Decisoes!$F$2:$F$6,3),0)&" € — "&INDEX(Ata_Decisoes!$G$2:$G$6,3) -> 38 000 € — Gerente de Manutenção; técnico de utilidades; instalador
A26: Responsável e prazo | B26: =INDEX(Ata_Decisoes!$H$2:$H$6,3)&" — até "&TEXT(DAY(INDEX(Ata_Decisoes!$I$2:$I$6,3)),"00")&"/"&TEXT(MONTH(INDEX(Ata_Decisoes!$I$2:$I$6,3)),"00")&"/"&YEAR(INDEX(Ata_Decisoes!$I$2:$I$6,3)) -> Gerente de Manutenção — até 31/12/2026
A27: Ações no PAM | B27: =INDEX(Ata_Decisoes!$J$2:$J$6,3) -> PAM-26-01; PAM-26-02
A29: ="DECISÃO "&INDEX(Ata_Decisoes!$A$2:$A$6,4)&" (ponto "&INDEX(Ata_Decisoes!$B$2:$B$6,4)&")" -> DECISÃO RG-26-D04 (ponto 9)
A30: Problema / Análise | B30: =INDEX(Ata_Decisoes!$D$2:$D$6,4) -> Oportunidade RO-09: fotovoltaico em ≈ 9.000 m² de cobertura; clientes pedem dados de carbono; o registo EMAS daria acesso a clientes públicos e a menos inspeções.
A31: Decisão tomada | B31: =INDEX(Ata_Decisoes!$E$2:$E$6,4) -> Encomendar o estudo de viabilidade de uma UPAC de ≈ 1 MWp e preparar o diagnóstico para o registo EMAS em 2027 (declaração ambiental com os 6 indicadores principais).
A32: Recursos alocados | B32: =FIXED(INDEX(Ata_Decisoes!$F$2:$F$6,4),0)&" € — "&INDEX(Ata_Decisoes!$G$2:$G$6,4) -> 4 000 € — Diretor Financeiro; Gestor do SGA
A33: Responsável e prazo | B33: =INDEX(Ata_Decisoes!$H$2:$H$6,4)&" — até "&TEXT(DAY(INDEX(Ata_Decisoes!$I$2:$I$6,4)),"00")&"/"&TEXT(MONTH(INDEX(Ata_Decisoes!$I$2:$I$6,4)),"00")&"/"&YEAR(INDEX(Ata_Decisoes!$I$2:$I$6,4)) -> Diretor Financeiro — até 31/03/2027
A34: Ações no PAM | B34: =INDEX(Ata_Decisoes!$J$2:$J$6,4) -> PAM-26-18
A36: ="DECISÃO "&INDEX(Ata_Decisoes!$A$2:$A$6,5)&" (ponto "&INDEX(Ata_Decisoes!$B$2:$B$6,5)&")" -> DECISÃO RG-26-D05 (ponto 6)
A37: Problema / Análise | B37: =INDEX(Ata_Decisoes!$D$2:$D$6,5) -> A auditoria AUD-2026-01 detetou que a substituição dos compressores não passou por avaliação ambiental (requisito novo 6.3 da ISO 14001:2026), o que originou a NC legal de ruído.
A38: Decisão tomada | B38: =INDEX(Ata_Decisoes!$E$2:$E$6,5) -> Aprovar o procedimento PR-SGA-06 'Planeamento de alterações' com checklist ambiental/legal obrigatória antes de qualquer investimento em equipamento, processo, layout ou material.
A39: Recursos alocados | B39: =FIXED(INDEX(Ata_Decisoes!$F$2:$F$6,5),0)&" € — "&INDEX(Ata_Decisoes!$G$2:$G$6,5) -> 0 € — Gestor do SGA; Diretor Industrial
A40: Responsável e prazo | B40: =INDEX(Ata_Decisoes!$H$2:$H$6,5)&" — até "&TEXT(DAY(INDEX(Ata_Decisoes!$I$2:$I$6,5)),"00")&"/"&TEXT(MONTH(INDEX(Ata_Decisoes!$I$2:$I$6,5)),"00")&"/"&YEAR(INDEX(Ata_Decisoes!$I$2:$I$6,5)) -> Gestor do SGA / EHS (Responsável Ambiental) — até 30/11/2026
A41: Ações no PAM | B41: =INDEX(Ata_Decisoes!$J$2:$J$6,5) -> PAM-26-17
A43: Conclusões (9.3.3)
A44: =INDEX(Conclusoes!$A$2:$A$5,1) -> Adequação | B44: =INDEX(Conclusoes!$B$2:$B$5,1) -> O SGA continua adequado ao contexto da Plasticom, mas tem de integrar o PPWR, o regulamento de granulados e a gestão de alterações (6.3).
A45: =INDEX(Conclusoes!$A$2:$A$5,2) -> Suficiência | B45: =INDEX(Conclusoes!$B$2:$B$5,2) -> Recursos insuficientes em medição e em conformidade de produto: reforçados pelas decisões D02 e D03.
A46: =INDEX(Conclusoes!$A$2:$A$5,3) -> Eficácia | B46: =INDEX(Conclusoes!$B$2:$B$5,3) -> Eficácia parcial: 2 de 6 objetivos no caminho previsto (energia, scrap); solvente e água com desvio; 1 de 2 ações de NC verificadas como eficazes.
A47: =INDEX(Conclusoes!$A$2:$A$5,4) -> Política Ambiental | B47: =INDEX(Conclusoes!$B$2:$B$5,4) -> Rev. 02 (junho/2026) mantém-se adequada; não é necessária alteração.
A49: Assinaturas: Diretor Geral ________________ Gestor do SGA/EHS ________________

Sheet Listas
A1: LISTAS CONTROLADAS (domínios de validação de dados) — editar aqui para alterar opções
A2: DataReferencia | B2: Presenca | C2: Entrada932 | D2: Saida933 | E2: Funcao
A3: 46387 | B3: Presente | C3: 9.3.2 a) | D3: Conclusões sobre adequação, suficiência e eficácia | E3: Diretor Geral (Gestão de Topo)
B4: Ausente justificado | C4: 9.3.2 b) | D4: Oportunidades de melhoria contínua | E4: Diretor Industrial
B5: Ausente | C5: 9.3.2 c) | D5: Necessidade de alterações ao SGA | E5: Gestor do SGA / EHS (Responsável Ambiental)
C6: 9.3.2 d) | D6: Recursos | E6: Gerente de Produção
C7: 9.3.2 e) | D7: Ações quando os objetivos não foram atingidos | E7: Gerente de Manutenção
C8: 9.3.2 f) | D8: Integração nos processos de negócio | E8: Gerente da Qualidade
C9: 9.3.2 g) | D9: Implicações para a direção estratégica | E9: Responsável de Armazém e Logística
C10: 9.3.3 | E10: Responsável de Compras
E11: Responsável de R&D
E12: Responsável de Recursos Humanos
E13: Diretor Financeiro
E14: Operador de Serigrafia
E15: Operador de Injeção
E16: Operador de Sopro (ISBM)
E17: Operador de Hot Foil
E18: Técnico de Manutenção
E19: Técnico de Utilidades
E20: Operador de Armazém / Empilhador
E21: Chefe de Turno
E22: Auditor Interno do SGA
... E24: Técnico de Qualidade/Ambiente

Sheet Dicionario_Dados
A1: Folha | B1: Tabela | C1: Coluna | D1: Tipo | E1: Origem | F1: Descricao | G1: Dominio_Unidade | H1: Obrigatorio | I1: Chave
A2: Participantes | B2: tbl_participantes | C2: ID_Reuniao | D2: Texto | E2: Entrada | F2: Reunião. | H2: Sim | I2: FK
A3: Participantes | B3: tbl_participantes | C3: Funcao | D3: Texto | E3: Entrada | F3: Cargo convocado. | G3: Lista lst_Funcao | H3: Sim
A4: Participantes | B4: tbl_participantes | C4: Papel | D4: Texto | E4: Entrada | F4: Papel na reunião. | H4: Sim
A5: Participantes | B5: tbl_participantes | C5: Presenca | D5: Texto | E5: Entrada | F5: Presença. | G5: Lista lst_Presenca | H5: Sim
A6: Ordem_Trabalhos | B6: tbl_agenda | C6: ID_Reuniao | D6: Texto | E6: Entrada | F6: Reunião. | H6: Sim | I6: FK
A7: Ordem_Trabalhos | B7: tbl_agenda | C7: Ponto | D7: Inteiro | E7: Entrada | F7: N.º do ponto. | H7: Sim
A8: Ordem_Trabalhos | B8: tbl_agenda | C8: Entrada_9_3_2 | D8: Texto | E8: Entrada | F8: Alínea da 9.3.2. | G8: Lista lst_Entrada932 | H8: Sim
A9: Ordem_Trabalhos | B9: tbl_agenda | C9: Topico | D9: Texto | E9: Entrada | F9: Tópico adaptado à Plasticom. | H9: Sim
A10: Ordem_Trabalhos | B10: tbl_agenda | C10: Fonte_Dados | D10: Texto | E10: Entrada | F10: Registo que suporta o ponto. | H10: Sim
A11: Ordem_Trabalhos | B11: tbl_agenda | C11: Apresentador | D11: Texto | E11: Entrada | F11: Quem apresenta. | G11: Lista lst_Funcao | H11: Sim
A12: Ordem_Trabalhos | B12: tbl_agenda | C12: Duracao_min | D12: Inteiro | E12: Entrada | F12: Duração (min). | H12: Sim
A13: Ordem_Trabalhos | B13: tbl_agenda | C13: Hora_Inicio | D13: Texto | E13: Calculado (fórmula) | F13: Hora de início do ponto (reunião às 14:30). | H13: Sim
A14: Ordem_Trabalhos | B14: tbl_agenda | C14: N_Decisoes | D14: Inteiro | E14: Calculado (fórmula) | F14: Decisões tomadas neste ponto. | H14: Sim
A15: Ata_Decisoes | B15: tbl_decisoes | C15: ID_Decisao | D15: Texto | E15: Entrada | F15: Decisão. | H15: Sim | I15: PK
A16: Ata_Decisoes | B16: tbl_decisoes | C16: Ponto_Agenda | D16: Inteiro | E16: Entrada | F16: Ponto da agenda. | H16: Sim
A17: Ata_Decisoes | B17: tbl_decisoes | C17: Tipo_Saida_9_3_3 | D17: Texto | E17: Entrada | F17: Tipo de resultado exigido pela 9.3.3. | G17: Lista lst_Saida933 | H17: Sim
A18: Ata_Decisoes | B18: tbl_decisoes | C18: Problema_Analise | D18: Texto | E18: Entrada | F18: O que motivou a decisão. | H18: Sim
A19: Ata_Decisoes | B19: tbl_decisoes | C19: Decisao_Tomada | D19: Texto | E19: Entrada | F19: O que se vai comprar, alterar ou implementar. | H19: Sim
A20: Ata_Decisoes | B20: tbl_decisoes | C20: Recursos_EUR | D20: Moeda (EUR) | E20: Entrada | F20: Orçamento alocado. | H20: Sim
A21: Ata_Decisoes | B21: tbl_decisoes | C21: Recursos_Pessoas | D21: Texto | E21: Entrada | F21: Pessoas envolvidas. | H21: Sim
A22: Ata_Decisoes | B22: tbl_decisoes | C22: Responsavel | D22: Texto | E22: Entrada | F22: Quem executa. | G22: Lista lst_Funcao | H22: Sim
A23: Ata_Decisoes | B23: tbl_decisoes | C23: Prazo | D23: Data (aaaa-mm-dd) | E23: Entrada | F23: Até quando. | H23: Sim
A24: Ata_Decisoes | B24: tbl_decisoes | C24: IDs_PAM | D24: Texto | E24: Entrada | F24: Ações no PAM. | H24: Sim | I24: FK → RG-SGA-06
A25: Ata_Decisoes | B25: tbl_decisoes | C25: Dias_ate_Prazo | D25: Inteiro | E25: Calculado (fórmula) | F25: Dias até ao prazo. | H25: Sim
A26: Conclusoes | B26: tbl_conclusoes | C26: Tema | D26: Texto | E26: Entrada | F26: Conclusão exigida. | H26: Sim
A27: Conclusoes | B27: tbl_conclusoes | C27: Conclusao | D27: Texto | E27: Entrada | F27: Conclusão da gestão. | H27: Sim
