Workbook
Name DataRef: Listas!$A$3
Name esc_Fin_Limite: Listas!$E$49:$E$53
Name esc_Prob_Media: Listas!$F$44:$F$48
Name lst_DataReferencia: Listas!$A$3:$A$3
Name lst_Escala: Listas!$I$3:$I$7
Name lst_EstadoValidacao: Listas!$M$3:$M$5
Name lst_Etapa: Listas!$F$3:$F$7
Name lst_FEtapa: Listas!$U$3:$U$8
Name lst_FHorizonte: Listas!$V$3:$V$6
Name lst_FPilar: Listas!$S$3:$S$6
Name lst_FTipo: Listas!$W$3:$W$7
Name lst_FTopico: Listas!$T$3:$T$14
Name lst_Funcao: Listas!$R$3:$R$24
Name lst_Horizonte: Listas!$G$3:$G$5
Name lst_Metodo: Listas!$P$3:$P$8
Name lst_Natureza: Listas!$E$3:$E$4
Name lst_Parte: Listas!$O$3:$O$10
Name lst_Pilar: Listas!$B$3:$B$5
Name lst_Qualidade: Listas!$K$3:$K$5
Name lst_RelevanciaSetorial: Listas!$N$3:$N$5
Name lst_Rubrica: Listas!$J$3:$J$8
Name lst_SimNao: Listas!$H$3:$H$4
Name lst_TipoContributo: Listas!$Q$3:$Q$4
Name lst_TipoDado: Listas!$L$3:$L$6
Name lst_TipoIRO: Listas!$D$3:$D$6
Name lst_TopicoESRS: Listas!$C$3:$C$13
Name prm_Faturacao_EUR: Listas!$B$66
Name prm_Grav_DH: Listas!$B$62
Name prm_Limiar_Alto: Listas!$B$60
Name prm_Limiar_Baixo: Listas!$B$61
Name prm_Limiar_Financeiro: Listas!$B$59
Name prm_Limiar_Impacto: Listas!$B$58
Name prm_Meses_Rev_Material: Listas!$B$64
Name prm_Meses_Rev_Outros: Listas!$B$65
Name prm_Preco_Eletricidade: Listas!$B$67
Name prm_Preco_Polimero: Listas!$B$68
Name prm_Relev_Alerta: Listas!$B$63
Name prm_Trabalhadores: Listas!$B$69
Name SegmentaçãoDeDados_Etapa_Cadeia_Valor: #N/A
Name SegmentaçãoDeDados_Horizonte: #N/A
Name SegmentaçãoDeDados_Material: #N/A
Name SegmentaçãoDeDados_Pilar: #N/A
Name SegmentaçãoDeDados_Qualidade_Evidencia: #N/A
Name SegmentaçãoDeDados_Tipo_IRO: #N/A

Sheet 00_LEIA-ME
A1: RG-SGA-17 — Análise de Dupla Materialidade (DMA) — Plasticom
A2: Sistema de Gestão Ambiental NP EN ISO 14001:2026 · Plasticom — Unidade 1 (Marinha Grande, Portugal) · Registo do SGA (fábrica simulada)
A4: CONTROLO DO DOCUMENTO (7.5 — informação documentada)
A5: Código do registo | B5: RG-SGA-17
A6: Título | B6: Análise de Dupla Materialidade (DMA) — Plasticom
A7: Versão / Revisão | B7: 02
A8: Data de emissão | B8: 46289
A9: Elaborado por | B9: Gestor(a) do SGA / EHS
A10: Aprovado por | B10: Diretor Geral
A11: Estado | B11: Em vigor
A12: Retenção | B12: 5 anos após substituição
A13: Localização | B13: Repositório controlado do SGA > Registos_SGA_Plasticom (versão eletrónica é a versão controlada; cópias impressas são não controladas)
A15: FINALIDADE E ÂMBITO
A16: Finalidade | B16: Identificar e avaliar os temas de sustentabilidade materiais para a Plasticom nas duas perspetivas — impacto (efeitos da empresa sobre pessoas e ambiente, de dentro para fora) e financeira (efeitos dos temas sobre o desempenho e a posição financeira, de fora para dentro) — ao nível de cada impacto, risco e oportunidade (IRO), com critérios parametrizados, evidências rastreáveis, contributos das partes interessadas e ligação às decisões do SGA. Revisão 02: substitui a folha única 28_Dupla_Materialidade (12 temas, sem IRO nem evidências).
A17: Atividades do curso | B17: Complemento ESG do SGA (não é atividade do curso): dupla materialidade para priorizar temas, riscos e oportunidades de sustentabilidade.
A18: Requisitos ISO 14001:2026 | B18: 4.1 Contexto; 4.2 Partes interessadas; 6.1.1–6.1.4 Aspetos, obrigações, riscos e oportunidades (integração)
A20: ESTRUTURA DO FICHEIRO
A21: Painel | B21: Painel interativo: filtros, indicadores, matriz de dupla materialidade, gráfico dinâmico, ranking, resumo por tópico ESRS e tabela dinâmica com segmentações de dados.
A22: Temas | B22: Temas de sustentabilidade com a materialidade agregada a partir dos IRO (1 linha por tema).
A23: IRO | B23: Impactos, riscos e oportunidades (IRO) — unidade de avaliação da dupla materialidade (1 linha por IRO).
A24: Evidencias | B24: Evidências quantitativas e qualitativas que sustentam cada IRO (instantâneo dos registos do SGA à data da avaliação).
A25: Consultas | B25: Contributos das partes interessadas por tema (1 linha por contributo; formato longo para análise).
A26: Listas | B26: Domínios de validação e, abaixo, as tabelas de critérios (tbl_dma_escalas) e de parâmetros (tbl_dma_parametros) com os limiares lidos pelas fórmulas — alterar aqui recalcula toda a análise.
A27: Dicionario_Dados | B27: Descrição de cada coluna de cada tabela: tipo, origem (entrada/calculado), domínio, obrigatoriedade e chaves.
A29: CONVENÇÕES (prontas para análise de dados e machine learning)
A30: Tabelas | B30: Cada registo é uma Tabela Excel com nome próprio (tbl_*): uma linha = um registo, cabeçalho único, sem células mescladas. Ler com pandas (pd.read_excel(ficheiro, sheet_name=folha, header=<linha do cabeçalho - 1>)) ou Power BI (Obter Dados > Tabela).
A31: Cabeçalho cinzento | B31: Coluna CALCULADA por fórmula — não escrever por cima. As restantes colunas são de entrada.
A32: Validação | B32: Colunas com lista controlada só aceitam valores da folha Listas (evita categorias duplicadas por grafia diferente).
A33: Chaves | B33: IDs estáveis e únicos (PK) e referências a IDs de outros registos (FK) permitem juntar tabelas entre ficheiros — ver SGA-00_Indice_Modelo_Dados.xlsx.
A34: Datas e unidades | B34: Datas em formato data (aaaa-mm-dd); números como números; a unidade está no nome da coluna ou no dicionário. Data de referência do SGA: 2026-12-31 (fecho do ano).
A35: Dados simulados | B35: Fábrica simulada Plasticom. Dados operacionais derivados do dataset do projeto (datasets/silver); dados ambientais e de conformidade são simulação didática — confirmar aplicabilidade legal e números antes de uso real.
A37: LIGAÇÕES A OUTROS REGISTOS
A38: RG-SGA-01 Contexto | B38: IDs_Contexto → SWOT (SWT-*) e PESTEL (PES-*).
A39: RG-SGA-02 Riscos e oportunidades | B39: ID_RO → coluna 'ID RO (SGA)' e ID_Registo_Corporativo → coluna 'ID' de tbRiscos / tbOportunidades.
A40: RG-SGA-03 Aspetos | B40: IDs_Aspetos → tbl_aspetos (significância ISO 14001).
A41: RG-SGA-04 Legal | B41: ID_Legal → tbl_legal.
A42: RG-SGA-05 Objetivos e KPI | B42: ID_OBJ → tbl_objetivos; ID_KPI → tbl_kpi.
A43: RG-SGA-06 PAM | B43: ID_PAM → tbl_pam.
A44: RG-SGA-16 EMAS | B44: Evidências quantitativas (EMAS-*) — instantâneo à data da avaliação.
A45: RG-SGA-02 — avaliação corporativa | B45: Linha equivalente em tbRiscos / tbOportunidades: avaliação 5×5, inerente, BowTie e KRI.
A47: METODOLOGIA (EFRAG IG 1 — processo em 4 passos, adaptado ao SGA)
A48: 1. Contexto e âmbito | B48: Operações próprias da Unidade 1 e cadeia de valor (fornecedores de polímero, transporte, clientes de cosmética, alimentar e farmacêutica, fim de vida). Período de referência: set/2025 a ago/2026. Finalidade: gestão (SGA, riscos, pedidos ESG de clientes), não reporte obrigatório.
A49: 2. Identificação | B49: Lista de temas a partir dos tópicos ESRS (ESRS 1 AR 16) + temas específicos da entidade, cruzada com o contexto (RG-SGA-01), aspetos ambientais (RG-SGA-03), requisitos legais (RG-SGA-04), riscos e oportunidades (RG-SGA-02 e registo corporativo) e consulta às partes interessadas.
A50: 3. Avaliação | B50: Cada IRO é avaliado numa só dimensão. Impacto: Gravidade = média de Magnitude, Alcance e Irremediabilidade (esta só nos negativos); Score_Impacto = Gravidade × Probabilidade efetiva (real = 5; direitos humanos com gravidade ≥ prm_Grav_DH = 5). Financeira: Magnitude pelas bandas em € (tbl_dma_escalas); Score_Financeiro = Magnitude × Probabilidade. Material se o score ≥ limiar (prm_Limiar_*).
A51: 4. Consolidação | B51: Um tema é material se pelo menos um IRO for material: Dupla materialidade (ambas), Material — impacto, Material — financeira ou Não material. As partes interessadas informam a avaliação mas não entram na fórmula; divergências geram alerta (Alerta_Consistencia).
A52: Aplicabilidade legal | B52: Com ≈ 150 trabalhadores e ≈ 3,7 M€ de faturação, a Plasticom está fora do âmbito obrigatório da CSRD/ESRS; a DMA é voluntária e pode alimentar a norma voluntária para PME (VSME) e os pedidos ESG de clientes. O âmbito da CSRD está a ser alterado pelo processo de simplificação europeu (Omnibus): confirmar a legislação em vigor à data de uso.
A53: ISO 14001 ≠ DMA | B53: A significância dos aspetos ambientais (IRA) e a materialidade de impacto usam critérios e âmbitos diferentes: ex. o ruído dos compressores é aspeto significativo no SGA mas não material na DMA. Os dados são partilhados pelas chaves (IDs_Aspetos, ID_RO, ID_Legal, ID_OBJ, ID_PAM).
A54: Referências | B54: EFRAG IG 1 Materiality Assessment (2024); EFRAG IG 2 Value Chain (2024); ESRS 1 §43–51 e AR 16; GRI 3 Material Topics (2021); IFRS S1 (materialidade financeira); ISO 14001:2026 cláusulas 4.1, 4.2, 6.1.
A55: Limitações | B55: Avaliação simulada da fábrica fictícia Plasticom: pontuações, estimativas em € e contributos das partes interessadas são hipóteses didáticas a validar. Emissões do âmbito 3 estimadas por fator médio. Lacunas de dados sinalizadas com Qualidade_Evidencia = Baixa.
A56: Uso em análise de dados | B56: Juntar tbl_dma_iro a tbl_dma_temas por ID_Tema; tbl_dma_evidencias por ID_IRO; tbl_dma_consultas por ID_Tema. Chaves externas: ID_RO e ID_Registo_Corporativo → RG-SGA-02 (tbRiscos/tbOportunidades); IDs_Aspetos → RG-SGA-03; ID_Legal → RG-SGA-04; ID_OBJ/ID_KPI → RG-SGA-05; ID_PAM → RG-SGA-06. Campos com vários IDs usam ';'.

Sheet Painel
A1: PAINEL DE DUPLA MATERIALIDADE — PLASTICOM
A2: Escolha os filtros nas células amarelas (lista pendente). Indicadores, matriz, resumo e gráfico recalculam-se. A tabela dinâmica no fim tem segmentações de dados (Dados > Atualizar tudo após editar as tabelas).
Z3: Dados auxiliares do gráfico (não editar)
A4: FILTROS ('(Todos)' = sem filtro · Pilar e Tópico aplicam-se a temas e IRO; Etapa, Horizonte e Tipo só aos IRO) | Z4: ID | AA4: Financeira (x) | AB4: Dupla materialidade | AC4: Material — impacto | AD4: Material — financeira | AE4: Não material
A5: Pilar | B5: Tópico ESRS | C5: Etapa da cadeia de valor | D5: Horizonte temporal | E5: Tipo de IRO | Z5: =IF(AND(INDEX(Temas!$A$5:$A$40,1)<>"",OR($A$6="(Todos)",INDEX(Temas!$B$5:$B$40,1)=$A$6),OR($B$6="(Todos)",INDEX(Temas!$C$5:$C$40,1)=$B$6)),INDEX(Temas!$A$5:$A$40,1),"") -> DM-01 | AA5: =IF(AND(INDEX(Temas!$A$5:$A$40,1)<>"",OR($A$6="(Todos)",INDEX(Temas!$B$5:$B$40,1)=$A$6),OR($B$6="(Todos)",INDEX(Temas!$C$5:$C$40,1)=$B$6)),N(INDEX(Temas!$Q$5:$Q$40,1)),NA()) -> 12 | AB5: =IF(AND(AND(INDEX(Temas!$A$5:$A$40,1)<>"",OR($A$6="(Todos)",INDEX(Temas!$B$5:$B$40,1)=$A$6),OR($B$6="(Todos)",INDEX(Temas!$C$5:$C$40,1)=$B$6)),INDEX(Temas!$T$5:$T$40,1)="Dupla materialidade"),N(INDEX(Temas!$P$5:$P$40,1)),NA()) -> 20 | AC5: =IF(AND(AND(INDEX(Temas!$A$5:$A$40,1)<>"",OR($A$6="(Todos)",INDEX(Temas!$B$5:$B$40,1)=$A$6),OR($B$6="(Todos)",INDEX(Temas!$C$5:$C$40,1)=$B$6)),INDEX(Temas!$T$5:$T$40,1)="Material — impacto"),N(INDEX(Temas!$P$5:$P$40,1)),NA()) -> #N/A | AD5: =IF(AND(AND(INDEX(Temas!$A$5:$A$40,1)<>"",OR($A$6="(Todos)",INDEX(Temas!$B$5:$B$40,1)=$A$6),OR($B$6="(Todos)",INDEX(Temas!$C$5:$C$40,1)=$B$6)),INDEX(Temas!$T$5:$T$40,1)="Material — financeira"),N(INDEX(Temas!$P$5:$P$40,1)),NA()) -> #N/A | AE5: =IF(AND(AND(INDEX(Temas!$A$5:$A$40,1)<>"",OR($A$6="(Todos)",INDEX(Temas!$B$5:$B$40,1)=$A$6),OR($B$6="(Todos)",INDEX(Temas!$C$5:$C$40,1)=$B$6)),INDEX(Temas!$T$5:$T$40,1)="Não material"),N(INDEX(Temas!$P$5:$P$40,1)),NA()) -> #N/A
A6: (Todos) | B6: (Todos) | C6: (Todos) | D6: (Todos) | E6: (Todos) | Z6: =IF(AND(INDEX(Temas!$A$5:$A$40,2)<>"",OR($A$6="(Todos)",INDEX(Temas!$B$5:$B$40,2)=$A$6),OR($B$6="(Todos)",INDEX(Temas!$C$5:$C$40,2)=$B$6)),INDEX(Temas!$A$5:$A$40,2),"") -> DM-02 | AA6: =IF(AND(INDEX(Temas!$A$5:$A$40,2)<>"",OR($A$6="(Todos)",INDEX(Temas!$B$5:$B$40,2)=$A$6),OR($B$6="(Todos)",INDEX(Temas!$C$5:$C$40,2)=$B$6)),N(INDEX(Temas!$Q$5:$Q$40,2)),NA()) -> 16 | AB6: =IF(AND(AND(INDEX(Temas!$A$5:$A$40,2)<>"",OR($A$6="(Todos)",INDEX(Temas!$B$5:$B$40,2)=$A$6),OR($B$6="(Todos)",INDEX(Temas!$C$5:$C$40,2)=$B$6)),INDEX(Temas!$T$5:$T$40,2)="Dupla materialidade"),N(INDEX(Temas!$P$5:$P$40,2)),NA()) -> 15 | AC6: =IF(AND(AND(INDEX(Temas!$A$5:$A$40,2)<>"",OR($A$6="(Todos)",INDEX(Temas!$B$5:$B$40,2)=$A$6),OR($B$6="(Todos)",INDEX(Temas!$C$5:$C$40,2)=$B$6)),INDEX(Temas!$T$5:$T$40,2)="Material — impacto"),N(INDEX(Temas!$P$5:$P$40,2)),NA()) -> #N/A | AD6: =IF(AND(AND(INDEX(Temas!$A$5:$A$40,2)<>"",OR($A$6="(Todos)",INDEX(Temas!$B$5:$B$40,2)=$A$6),OR($B$6="(Todos)",INDEX(Temas!$C$5:$C$40,2)=$B$6)),INDEX(Temas!$T$5:$T$40,2)="Material — financeira"),N(INDEX(Temas!$P$5:$P$40,2)),NA()) -> #N/A | AE6: =IF(AND(AND(INDEX(Temas!$A$5:$A$40,2)<>"",OR($A$6="(Todos)",INDEX(Temas!$B$5:$B$40,2)=$A$6),OR($B$6="(Todos)",INDEX(Temas!$C$5:$C$40,2)=$B$6)),INDEX(Temas!$T$5:$T$40,2)="Não material"),N(INDEX(Temas!$P$5:$P$40,2)),NA()) -> #N/A
A7: =IF(A6="(Todos)","*",A6) -> * | B7: =IF(B6="(Todos)","*",B6) -> * | C7: =IF(C6="(Todos)","*",C6) -> * | D7: =IF(D6="(Todos)","*",D6) -> * | E7: =IF(E6="(Todos)","*",E6) -> * | F7: ← critérios usados nas fórmulas | Z7: =IF(AND(INDEX(Temas!$A$5:$A$40,3)<>"",OR($A$6="(Todos)",INDEX(Temas!$B$5:$B$40,3)=$A$6),OR($B$6="(Todos)",INDEX(Temas!$C$5:$C$40,3)=$B$6)),INDEX(Temas!$A$5:$A$40,3),"") -> DM-03 | AA7: =IF(AND(INDEX(Temas!$A$5:$A$40,3)<>"",OR($A$6="(Todos)",INDEX(Temas!$B$5:$B$40,3)=$A$6),OR($B$6="(Todos)",INDEX(Temas!$C$5:$C$40,3)=$B$6)),N(INDEX(Temas!$Q$5:$Q$40,3)),NA()) -> 12 | AB7: =IF(AND(AND(INDEX(Temas!$A$5:$A$40,3)<>"",OR($A$6="(Todos)",INDEX(Temas!$B$5:$B$40,3)=$A$6),OR($B$6="(Todos)",INDEX(Temas!$C$5:$C$40,3)=$B$6)),INDEX(Temas!$T$5:$T$40,3)="Dupla materialidade"),N(INDEX(Temas!$P$5:$P$40,3)),NA()) -> #N/A | AC7: =IF(AND(AND(INDEX(Temas!$A$5:$A$40,3)<>"",OR($A$6="(Todos)",INDEX(Temas!$B$5:$B$40,3)=$A$6),OR($B$6="(Todos)",INDEX(Temas!$C$5:$C$40,3)=$B$6)),INDEX(Temas!$T$5:$T$40,3)="Material — impacto"),N(INDEX(Temas!$P$5:$P$40,3)),NA()) -> #N/A | AD7: =IF(AND(AND(INDEX(Temas!$A$5:$A$40,3)<>"",OR($A$6="(Todos)",INDEX(Temas!$B$5:$B$40,3)=$A$6),OR($B$6="(Todos)",INDEX(Temas!$C$5:$C$40,3)=$B$6)),INDEX(Temas!$T$5:$T$40,3)="Material — financeira"),N(INDEX(Temas!$P$5:$P$40,3)),NA()) -> 0 | AE7: =IF(AND(AND(INDEX(Temas!$A$5:$A$40,3)<>"",OR($A$6="(Todos)",INDEX(Temas!$B$5:$B$40,3)=$A$6),OR($B$6="(Todos)",INDEX(Temas!$C$5:$C$40,3)=$B$6)),INDEX(Temas!$T$5:$T$40,3)="Não material"),N(INDEX(Temas!$P$5:$P$40,3)),NA()) -> #N/A
Z8: =IF(AND(INDEX(Temas!$A$5:$A$40,4)<>"",OR($A$6="(Todos)",INDEX(Temas!$B$5:$B$40,4)=$A$6),OR($B$6="(Todos)",INDEX(Temas!$C$5:$C$40,4)=$B$6)),INDEX(Temas!$A$5:$A$40,4),"") -> DM-04 | AA8: =IF(AND(INDEX(Temas!$A$5:$A$40,4)<>"",OR($A$6="(Todos)",INDEX(Temas!$B$5:$B$40,4)=$A$6),OR($B$6="(Todos)",INDEX(Temas!$C$5:$C$40,4)=$B$6)),N(INDEX(Temas!$Q$5:$Q$40,4)),NA()) -> 4 | AB8: =IF(AND(AND(INDEX(Temas!$A$5:$A$40,4)<>"",OR($A$6="(Todos)",INDEX(Temas!$B$5:$B$40,4)=$A$6),OR($B$6="(Todos)",INDEX(Temas!$C$5:$C$40,4)=$B$6)),INDEX(Temas!$T$5:$T$40,4)="Dupla materialidade"),N(INDEX(Temas!$P$5:$P$40,4)),NA()) -> #N/A | AC8: =IF(AND(AND(INDEX(Temas!$A$5:$A$40,4)<>"",OR($A$6="(Todos)",INDEX(Temas!$B$5:$B$40,4)=$A$6),OR($B$6="(Todos)",INDEX(Temas!$C$5:$C$40,4)=$B$6)),INDEX(Temas!$T$5:$T$40,4)="Material — impacto"),N(INDEX(Temas!$P$5:$P$40,4)),NA()) -> 13.4 | AD8: =IF(AND(AND(INDEX(Temas!$A$5:$A$40,4)<>"",OR($A$6="(Todos)",INDEX(Temas!$B$5:$B$40,4)=$A$6),OR($B$6="(Todos)",INDEX(Temas!$C$5:$C$40,4)=$B$6)),INDEX(Temas!$T$5:$T$40,4)="Material — financeira"),N(INDEX(Temas!$P$5:$P$40,4)),NA()) -> #N/A | AE8: =IF(AND(AND(INDEX(Temas!$A$5:$A$40,4)<>"",OR($A$6="(Todos)",INDEX(Temas!$B$5:$B$40,4)=$A$6),OR($B$6="(Todos)",INDEX(Temas!$C$5:$C$40,4)=$B$6)),INDEX(Temas!$T$5:$T$40,4)="Não material"),N(INDEX(Temas!$P$5:$P$40,4)),NA()) -> #N/A
A9: INDICADORES (com filtros) | Z9: =IF(AND(INDEX(Temas!$A$5:$A$40,5)<>"",OR($A$6="(Todos)",INDEX(Temas!$B$5:$B$40,5)=$A$6),OR($B$6="(Todos)",INDEX(Temas!$C$5:$C$40,5)=$B$6)),INDEX(Temas!$A$5:$A$40,5),"") -> DM-05 | AA9: =IF(AND(INDEX(Temas!$A$5:$A$40,5)<>"",OR($A$6="(Todos)",INDEX(Temas!$B$5:$B$40,5)=$A$6),OR($B$6="(Todos)",INDEX(Temas!$C$5:$C$40,5)=$B$6)),N(INDEX(Temas!$Q$5:$Q$40,5)),NA()) -> 4 | AB9: =IF(AND(AND(INDEX(Temas!$A$5:$A$40,5)<>"",OR($A$6="(Todos)",INDEX(Temas!$B$5:$B$40,5)=$A$6),OR($B$6="(Todos)",INDEX(Temas!$C$5:$C$40,5)=$B$6)),INDEX(Temas!$T$5:$T$40,5)="Dupla materialidade"),N(INDEX(Temas!$P$5:$P$40,5)),NA()) -> #N/A | AC9: =IF(AND(AND(INDEX(Temas!$A$5:$A$40,5)<>"",OR($A$6="(Todos)",INDEX(Temas!$B$5:$B$40,5)=$A$6),OR($B$6="(Todos)",INDEX(Temas!$C$5:$C$40,5)=$B$6)),INDEX(Temas!$T$5:$T$40,5)="Material — impacto"),N(INDEX(Temas!$P$5:$P$40,5)),NA()) -> #N/A | AD9: =IF(AND(AND(INDEX(Temas!$A$5:$A$40,5)<>"",OR($A$6="(Todos)",INDEX(Temas!$B$5:$B$40,5)=$A$6),OR($B$6="(Todos)",INDEX(Temas!$C$5:$C$40,5)=$B$6)),INDEX(Temas!$T$5:$T$40,5)="Material — financeira"),N(INDEX(Temas!$P$5:$P$40,5)),NA()) -> #N/A | AE9: =IF(AND(AND(INDEX(Temas!$A$5:$A$40,5)<>"",OR($A$6="(Todos)",INDEX(Temas!$B$5:$B$40,5)=$A$6),OR($B$6="(Todos)",INDEX(Temas!$C$5:$C$40,5)=$B$6)),INDEX(Temas!$T$5:$T$40,5)="Não material"),N(INDEX(Temas!$P$5:$P$40,5)),NA()) -> 10
A10: Temas avaliados | B10: Dupla materialidade | C10: Material — impacto | D10: Material — financeira | E10: Não material | F10: IRO avaliados | G10: IRO materiais | H10: Efeito financeiro ponderado líquido (€/ano) | I10: IRO com evidência de qualidade Alta | J10: IRO aprovados pela Direção | Z10: =IF(AND(INDEX(Temas!$A$5:$A$40,6)<>"",OR($A$6="(Todos)",INDEX(Temas!$B$5:$B$40,6)=$A$6),OR($B$6="(Todos)",INDEX(Temas!$C$5:$C$40,6)=$B$6)),INDEX(Temas!$A$5:$A$40,6),"") -> DM-06 | AA10: =IF(AND(INDEX(Temas!$A$5:$A$40,6)<>"",OR($A$6="(Todos)",INDEX(Temas!$B$5:$B$40,6)=$A$6),OR($B$6="(Todos)",INDEX(Temas!$C$5:$C$40,6)=$B$6)),N(INDEX(Temas!$Q$5:$Q$40,6)),NA()) -> 12 | AB10: =IF(AND(AND(INDEX(Temas!$A$5:$A$40,6)<>"",OR($A$6="(Todos)",INDEX(Temas!$B$5:$B$40,6)=$A$6),OR($B$6="(Todos)",INDEX(Temas!$C$5:$C$40,6)=$B$6)),INDEX(Temas!$T$5:$T$40,6)="Dupla materialidade"),N(INDEX(Temas!$P$5:$P$40,6)),NA()) -> 18.4 | AC10: =IF(AND(AND(INDEX(Temas!$A$5:$A$40,6)<>"",OR($A$6="(Todos)",INDEX(Temas!$B$5:$B$40,6)=$A$6),OR($B$6="(Todos)",INDEX(Temas!$C$5:$C$40,6)=$B$6)),INDEX(Temas!$T$5:$T$40,6)="Material — impacto"),N(INDEX(Temas!$P$5:$P$40,6)),NA()) -> #N/A | AD10: =IF(AND(AND(INDEX(Temas!$A$5:$A$40,6)<>"",OR($A$6="(Todos)",INDEX(Temas!$B$5:$B$40,6)=$A$6),OR($B$6="(Todos)",INDEX(Temas!$C$5:$C$40,6)=$B$6)),INDEX(Temas!$T$5:$T$40,6)="Material — financeira"),N(INDEX(Temas!$P$5:$P$40,6)),NA()) -> #N/A | AE10: =IF(AND(AND(INDEX(Temas!$A$5:$A$40,6)<>"",OR($A$6="(Todos)",INDEX(Temas!$B$5:$B$40,6)=$A$6),OR($B$6="(Todos)",INDEX(Temas!$C$5:$C$40,6)=$B$6)),INDEX(Temas!$T$5:$T$40,6)="Não material"),N(INDEX(Temas!$P$5:$P$40,6)),NA()) -> #N/A
A11: =COUNTIFS(Temas!$B$5:$B$40,$A$7,Temas!$C$5:$C$40,$B$7) -> 24 | B11: =COUNTIFS(Temas!$B$5:$B$40,$A$7,Temas!$C$5:$C$40,$B$7,Temas!$T$5:$T$40,"Dupla materialidade") -> 6 | C11: =COUNTIFS(Temas!$B$5:$B$40,$A$7,Temas!$C$5:$C$40,$B$7,Temas!$T$5:$T$40,"Material — impacto") -> 4 | D11: =COUNTIFS(Temas!$B$5:$B$40,$A$7,Temas!$C$5:$C$40,$B$7,Temas!$T$5:$T$40,"Material — financeira") -> 6 | E11: =COUNTIFS(Temas!$B$5:$B$40,$A$7,Temas!$C$5:$C$40,$B$7,Temas!$T$5:$T$40,"Não material") -> 8 | F11: =COUNTIFS(IRO!$D$5:$D$91,$A$7,IRO!$E$5:$E$91,$B$7,IRO!$J$5:$J$91,$C$7,IRO!$K$5:$K$91,$D$7,IRO!$F$5:$F$91,$E$7) -> 57 | G11: =COUNTIFS(IRO!$D$5:$D$91,$A$7,IRO!$E$5:$E$91,$B$7,IRO!$J$5:$J$91,$C$7,IRO!$K$5:$K$91,$D$7,IRO!$F$5:$F$91,$E$7,IRO!$AC$5:$AC$91,"Sim") -> 27 | H11: =SUMIFS(IRO!$AA$5:$AA$91,IRO!$D$5:$D$91,$A$7,IRO!$E$5:$E$91,$B$7,IRO!$J$5:$J$91,$C$7,IRO!$K$5:$K$91,$D$7,IRO!$F$5:$F$91,$E$7) -> -863000 | I11: =IFERROR(COUNTIFS(IRO!$D$5:$D$91,$A$7,IRO!$E$5:$E$91,$B$7,IRO!$J$5:$J$91,$C$7,IRO!$K$5:$K$91,$D$7,IRO!$F$5:$F$91,$E$7,IRO!$AG$5:$AG$91,"Alta")/COUNTIFS(IRO!$D$5:$D$91,$A$7,IRO!$E$5:$E$91,$B$7,IRO!$J$5:$J$91,$C$7,IRO!$K$5:$K$91,$D$7,IRO!$F$5:$F$91,$E$7),0) -> 0.33333333 | J11: =IFERROR(COUNTIFS(IRO!$D$5:$D$91,$A$7,IRO!$E$5:$E$91,$B$7,IRO!$J$5:$J$91,$C$7,IRO!$K$5:$K$91,$D$7,IRO!$F$5:$F$91,$E$7,IRO!$AT$5:$AT$91,"Aprovado pela Direção")/COUNTIFS(IRO!$D$5:$D$91,$A$7,IRO!$E$5:$E$91,$B$7,IRO!$J$5:$J$91,$C$7,IRO!$K$5:$K$91,$D$7,IRO!$F$5:$F$91,$E$7),0) -> 0 | Z11: =IF(AND(INDEX(Temas!$A$5:$A$40,7)<>"",OR($A$6="(Todos)",INDEX(Temas!$B$5:$B$40,7)=$A$6),OR($B$6="(Todos)",INDEX(Temas!$C$5:$C$40,7)=$B$6)),INDEX(Temas!$A$5:$A$40,7),"") -> DM-07 | AA11: =IF(AND(INDEX(Temas!$A$5:$A$40,7)<>"",OR($A$6="(Todos)",INDEX(Temas!$B$5:$B$40,7)=$A$6),OR($B$6="(Todos)",INDEX(Temas!$C$5:$C$40,7)=$B$6)),N(INDEX(Temas!$Q$5:$Q$40,7)),NA()) -> 9 | AB11: =IF(AND(AND(INDEX(Temas!$A$5:$A$40,7)<>"",OR($A$6="(Todos)",INDEX(Temas!$B$5:$B$40,7)=$A$6),OR($B$6="(Todos)",INDEX(Temas!$C$5:$C$40,7)=$B$6)),INDEX(Temas!$T$5:$T$40,7)="Dupla materialidade"),N(INDEX(Temas!$P$5:$P$40,7)),NA()) -> #N/A | AC11: =IF(AND(AND(INDEX(Temas!$A$5:$A$40,7)<>"",OR($A$6="(Todos)",INDEX(Temas!$B$5:$B$40,7)=$A$6),OR($B$6="(Todos)",INDEX(Temas!$C$5:$C$40,7)=$B$6)),INDEX(Temas!$T$5:$T$40,7)="Material — impacto"),N(INDEX(Temas!$P$5:$P$40,7)),NA()) -> #N/A | AD11: =IF(AND(AND(INDEX(Temas!$A$5:$A$40,7)<>"",OR($A$6="(Todos)",INDEX(Temas!$B$5:$B$40,7)=$A$6),OR($B$6="(Todos)",INDEX(Temas!$C$5:$C$40,7)=$B$6)),INDEX(Temas!$T$5:$T$40,7)="Material — financeira"),N(INDEX(Temas!$P$5:$P$40,7)),NA()) -> #N/A | AE11: =IF(AND(AND(INDEX(Temas!$A$5:$A$40,7)<>"",OR($A$6="(Todos)",INDEX(Temas!$B$5:$B$40,7)=$A$6),OR($B$6="(Todos)",INDEX(Temas!$C$5:$C$40,7)=$B$6)),INDEX(Temas!$T$5:$T$40,7)="Não material"),N(INDEX(Temas!$P$5:$P$40,7)),NA()) -> 8
Z12: =IF(AND(INDEX(Temas!$A$5:$A$40,8)<>"",OR($A$6="(Todos)",INDEX(Temas!$B$5:$B$40,8)=$A$6),OR($B$6="(Todos)",INDEX(Temas!$C$5:$C$40,8)=$B$6)),INDEX(Temas!$A$5:$A$40,8),"") -> DM-08 | AA12: =IF(AND(INDEX(Temas!$A$5:$A$40,8)<>"",OR($A$6="(Todos)",INDEX(Temas!$B$5:$B$40,8)=$A$6),OR($B$6="(Todos)",INDEX(Temas!$C$5:$C$40,8)=$B$6)),N(INDEX(Temas!$Q$5:$Q$40,8)),NA()) -> 6 | AB12: =IF(AND(AND(INDEX(Temas!$A$5:$A$40,8)<>"",OR($A$6="(Todos)",INDEX(Temas!$B$5:$B$40,8)=$A$6),OR($B$6="(Todos)",INDEX(Temas!$C$5:$C$40,8)=$B$6)),INDEX(Temas!$T$5:$T$40,8)="Dupla materialidade"),N(INDEX(Temas!$P$5:$P$40,8)),NA()) -> #N/A | AC12: =IF(AND(AND(INDEX(Temas!$A$5:$A$40,8)<>"",OR($A$6="(Todos)",INDEX(Temas!$B$5:$B$40,8)=$A$6),OR($B$6="(Todos)",INDEX(Temas!$C$5:$C$40,8)=$B$6)),INDEX(Temas!$T$5:$T$40,8)="Material — impacto"),N(INDEX(Temas!$P$5:$P$40,8)),NA()) -> #N/A | AD12: =IF(AND(AND(INDEX(Temas!$A$5:$A$40,8)<>"",OR($A$6="(Todos)",INDEX(Temas!$B$5:$B$40,8)=$A$6),OR($B$6="(Todos)",INDEX(Temas!$C$5:$C$40,8)=$B$6)),INDEX(Temas!$T$5:$T$40,8)="Material — financeira"),N(INDEX(Temas!$P$5:$P$40,8)),NA()) -> #N/A | AE12: =IF(AND(AND(INDEX(Temas!$A$5:$A$40,8)<>"",OR($A$6="(Todos)",INDEX(Temas!$B$5:$B$40,8)=$A$6),OR($B$6="(Todos)",INDEX(Temas!$C$5:$C$40,8)=$B$6)),INDEX(Temas!$T$5:$T$40,8)="Não material"),N(INDEX(Temas!$P$5:$P$40,8)),NA()) -> 11.7
A13: MATRIZ DE DUPLA MATERIALIDADE — n.º de temas por banda (filtros Pilar e Tópico) | Z13: =IF(AND(INDEX(Temas!$A$5:$A$40,9)<>"",OR($A$6="(Todos)",INDEX(Temas!$B$5:$B$40,9)=$A$6),OR($B$6="(Todos)",INDEX(Temas!$C$5:$C$40,9)=$B$6)),INDEX(Temas!$A$5:$A$40,9),"") -> DM-09 | AA13: =IF(AND(INDEX(Temas!$A$5:$A$40,9)<>"",OR($A$6="(Todos)",INDEX(Temas!$B$5:$B$40,9)=$A$6),OR($B$6="(Todos)",INDEX(Temas!$C$5:$C$40,9)=$B$6)),N(INDEX(Temas!$Q$5:$Q$40,9)),NA()) -> 0 | AB13: =IF(AND(AND(INDEX(Temas!$A$5:$A$40,9)<>"",OR($A$6="(Todos)",INDEX(Temas!$B$5:$B$40,9)=$A$6),OR($B$6="(Todos)",INDEX(Temas!$C$5:$C$40,9)=$B$6)),INDEX(Temas!$T$5:$T$40,9)="Dupla materialidade"),N(INDEX(Temas!$P$5:$P$40,9)),NA()) -> #N/A | AC13: =IF(AND(AND(INDEX(Temas!$A$5:$A$40,9)<>"",OR($A$6="(Todos)",INDEX(Temas!$B$5:$B$40,9)=$A$6),OR($B$6="(Todos)",INDEX(Temas!$C$5:$C$40,9)=$B$6)),INDEX(Temas!$T$5:$T$40,9)="Material — impacto"),N(INDEX(Temas!$P$5:$P$40,9)),NA()) -> 14 | AD13: =IF(AND(AND(INDEX(Temas!$A$5:$A$40,9)<>"",OR($A$6="(Todos)",INDEX(Temas!$B$5:$B$40,9)=$A$6),OR($B$6="(Todos)",INDEX(Temas!$C$5:$C$40,9)=$B$6)),INDEX(Temas!$T$5:$T$40,9)="Material — financeira"),N(INDEX(Temas!$P$5:$P$40,9)),NA()) -> #N/A | AE13: =IF(AND(AND(INDEX(Temas!$A$5:$A$40,9)<>"",OR($A$6="(Todos)",INDEX(Temas!$B$5:$B$40,9)=$A$6),OR($B$6="(Todos)",INDEX(Temas!$C$5:$C$40,9)=$B$6)),INDEX(Temas!$T$5:$T$40,9)="Não material"),N(INDEX(Temas!$P$5:$P$40,9)),NA()) -> #N/A
A14: Impacto ↓ · Financeira → | B14: ="Sem IRO" -> Sem IRO | C14: ="Baixa (<"&prm_Limiar_Baixo&")" -> Baixa (<6) | D14: ="Monitorizar ("&prm_Limiar_Baixo&"–<"&prm_Limiar_Financeiro&")" -> Monitorizar (6–<12) | E14: ="Material ("&prm_Limiar_Financeiro&"–<"&prm_Limiar_Alto&")" -> Material (12–<18) | F14: ="Alta (≥"&prm_Limiar_Alto&")" -> Alta (≥18) | Z14: =IF(AND(INDEX(Temas!$A$5:$A$40,10)<>"",OR($A$6="(Todos)",INDEX(Temas!$B$5:$B$40,10)=$A$6),OR($B$6="(Todos)",INDEX(Temas!$C$5:$C$40,10)=$B$6)),INDEX(Temas!$A$5:$A$40,10),"") -> DM-10 | AA14: =IF(AND(INDEX(Temas!$A$5:$A$40,10)<>"",OR($A$6="(Todos)",INDEX(Temas!$B$5:$B$40,10)=$A$6),OR($B$6="(Todos)",INDEX(Temas!$C$5:$C$40,10)=$B$6)),N(INDEX(Temas!$Q$5:$Q$40,10)),NA()) -> 12 | AB14: =IF(AND(AND(INDEX(Temas!$A$5:$A$40,10)<>"",OR($A$6="(Todos)",INDEX(Temas!$B$5:$B$40,10)=$A$6),OR($B$6="(Todos)",INDEX(Temas!$C$5:$C$40,10)=$B$6)),INDEX(Temas!$T$5:$T$40,10)="Dupla materialidade"),N(INDEX(Temas!$P$5:$P$40,10)),NA()) -> 18.4 | AC14: =IF(AND(AND(INDEX(Temas!$A$5:$A$40,10)<>"",OR($A$6="(Todos)",INDEX(Temas!$B$5:$B$40,10)=$A$6),OR($B$6="(Todos)",INDEX(Temas!$C$5:$C$40,10)=$B$6)),INDEX(Temas!$T$5:$T$40,10)="Material — impacto"),N(INDEX(Temas!$P$5:$P$40,10)),NA()) -> #N/A | AD14: =IF(AND(AND(INDEX(Temas!$A$5:$A$40,10)<>"",OR($A$6="(Todos)",INDEX(Temas!$B$5:$B$40,10)=$A$6),OR($B$6="(Todos)",INDEX(Temas!$C$5:$C$40,10)=$B$6)),INDEX(Temas!$T$5:$T$40,10)="Material — financeira"),N(INDEX(Temas!$P$5:$P$40,10)),NA()) -> #N/A | AE14: =IF(AND(AND(INDEX(Temas!$A$5:$A$40,10)<>"",OR($A$6="(Todos)",INDEX(Temas!$B$5:$B$40,10)=$A$6),OR($B$6="(Todos)",INDEX(Temas!$C$5:$C$40,10)=$B$6)),INDEX(Temas!$T$5:$T$40,10)="Não material"),N(INDEX(Temas!$P$5:$P$40,10)),NA()) -> #N/A
A15: ="Alta (≥"&prm_Limiar_Alto&")" -> Alta (≥18) | B15: =COUNTIFS(Temas!$U$5:$U$40,4,Temas!$V$5:$V$40,0,Temas!$B$5:$B$40,$A$7,Temas!$C$5:$C$40,$B$7) -> 0 | C15: =COUNTIFS(Temas!$U$5:$U$40,4,Temas!$V$5:$V$40,1,Temas!$B$5:$B$40,$A$7,Temas!$C$5:$C$40,$B$7) -> 0 | D15: =COUNTIFS(Temas!$U$5:$U$40,4,Temas!$V$5:$V$40,2,Temas!$B$5:$B$40,$A$7,Temas!$C$5:$C$40,$B$7) -> 1 | E15: =COUNTIFS(Temas!$U$5:$U$40,4,Temas!$V$5:$V$40,3,Temas!$B$5:$B$40,$A$7,Temas!$C$5:$C$40,$B$7) -> 4 | F15: =COUNTIFS(Temas!$U$5:$U$40,4,Temas!$V$5:$V$40,4,Temas!$B$5:$B$40,$A$7,Temas!$C$5:$C$40,$B$7) -> 0 | G15: Vermelho = dupla materialidade · laranja = material numa dimensão · amarelo = monitorizar · verde = baixa · cinzento = sem IRO nessa dimensão | Z15: =IF(AND(INDEX(Temas!$A$5:$A$40,11)<>"",OR($A$6="(Todos)",INDEX(Temas!$B$5:$B$40,11)=$A$6),OR($B$6="(Todos)",INDEX(Temas!$C$5:$C$40,11)=$B$6)),INDEX(Temas!$A$5:$A$40,11),"") -> DM-11 | AA15: =IF(AND(INDEX(Temas!$A$5:$A$40,11)<>"",OR($A$6="(Todos)",INDEX(Temas!$B$5:$B$40,11)=$A$6),OR($B$6="(Todos)",INDEX(Temas!$C$5:$C$40,11)=$B$6)),N(INDEX(Temas!$Q$5:$Q$40,11)),NA()) -> 20 | AB15: =IF(AND(AND(INDEX(Temas!$A$5:$A$40,11)<>"",OR($A$6="(Todos)",INDEX(Temas!$B$5:$B$40,11)=$A$6),OR($B$6="(Todos)",INDEX(Temas!$C$5:$C$40,11)=$B$6)),INDEX(Temas!$T$5:$T$40,11)="Dupla materialidade"),N(INDEX(Temas!$P$5:$P$40,11)),NA()) -> 16.7 | AC15: =IF(AND(AND(INDEX(Temas!$A$5:$A$40,11)<>"",OR($A$6="(Todos)",INDEX(Temas!$B$5:$B$40,11)=$A$6),OR($B$6="(Todos)",INDEX(Temas!$C$5:$C$40,11)=$B$6)),INDEX(Temas!$T$5:$T$40,11)="Material — impacto"),N(INDEX(Temas!$P$5:$P$40,11)),NA()) -> #N/A | AD15: =IF(AND(AND(INDEX(Temas!$A$5:$A$40,11)<>"",OR($A$6="(Todos)",INDEX(Temas!$B$5:$B$40,11)=$A$6),OR($B$6="(Todos)",INDEX(Temas!$C$5:$C$40,11)=$B$6)),INDEX(Temas!$T$5:$T$40,11)="Material — financeira"),N(INDEX(Temas!$P$5:$P$40,11)),NA()) -> #N/A | AE15: =IF(AND(AND(INDEX(Temas!$A$5:$A$40,11)<>"",OR($A$6="(Todos)",INDEX(Temas!$B$5:$B$40,11)=$A$6),OR($B$6="(Todos)",INDEX(Temas!$C$5:$C$40,11)=$B$6)),INDEX(Temas!$T$5:$T$40,11)="Não material"),N(INDEX(Temas!$P$5:$P$40,11)),NA()) -> #N/A
A16: ="Material ("&prm_Limiar_Impacto&"–<"&prm_Limiar_Alto&")" -> Material (12–<18) | B16: =COUNTIFS(Temas!$U$5:$U$40,3,Temas!$V$5:$V$40,0,Temas!$B$5:$B$40,$A$7,Temas!$C$5:$C$40,$B$7) -> 2 | C16: =COUNTIFS(Temas!$U$5:$U$40,3,Temas!$V$5:$V$40,1,Temas!$B$5:$B$40,$A$7,Temas!$C$5:$C$40,$B$7) -> 1 | D16: =COUNTIFS(Temas!$U$5:$U$40,3,Temas!$V$5:$V$40,2,Temas!$B$5:$B$40,$A$7,Temas!$C$5:$C$40,$B$7) -> 0 | E16: =COUNTIFS(Temas!$U$5:$U$40,3,Temas!$V$5:$V$40,3,Temas!$B$5:$B$40,$A$7,Temas!$C$5:$C$40,$B$7) -> 1 | F16: =COUNTIFS(Temas!$U$5:$U$40,3,Temas!$V$5:$V$40,4,Temas!$B$5:$B$40,$A$7,Temas!$C$5:$C$40,$B$7) -> 1 | Z16: =IF(AND(INDEX(Temas!$A$5:$A$40,12)<>"",OR($A$6="(Todos)",INDEX(Temas!$B$5:$B$40,12)=$A$6),OR($B$6="(Todos)",INDEX(Temas!$C$5:$C$40,12)=$B$6)),INDEX(Temas!$A$5:$A$40,12),"") -> DM-12 | AA16: =IF(AND(INDEX(Temas!$A$5:$A$40,12)<>"",OR($A$6="(Todos)",INDEX(Temas!$B$5:$B$40,12)=$A$6),OR($B$6="(Todos)",INDEX(Temas!$C$5:$C$40,12)=$B$6)),N(INDEX(Temas!$Q$5:$Q$40,12)),NA()) -> 8 | AB16: =IF(AND(AND(INDEX(Temas!$A$5:$A$40,12)<>"",OR($A$6="(Todos)",INDEX(Temas!$B$5:$B$40,12)=$A$6),OR($B$6="(Todos)",INDEX(Temas!$C$5:$C$40,12)=$B$6)),INDEX(Temas!$T$5:$T$40,12)="Dupla materialidade"),N(INDEX(Temas!$P$5:$P$40,12)),NA()) -> #N/A | AC16: =IF(AND(AND(INDEX(Temas!$A$5:$A$40,12)<>"",OR($A$6="(Todos)",INDEX(Temas!$B$5:$B$40,12)=$A$6),OR($B$6="(Todos)",INDEX(Temas!$C$5:$C$40,12)=$B$6)),INDEX(Temas!$T$5:$T$40,12)="Material — impacto"),N(INDEX(Temas!$P$5:$P$40,12)),NA()) -> #N/A | AD16: =IF(AND(AND(INDEX(Temas!$A$5:$A$40,12)<>"",OR($A$6="(Todos)",INDEX(Temas!$B$5:$B$40,12)=$A$6),OR($B$6="(Todos)",INDEX(Temas!$C$5:$C$40,12)=$B$6)),INDEX(Temas!$T$5:$T$40,12)="Material — financeira"),N(INDEX(Temas!$P$5:$P$40,12)),NA()) -> #N/A | AE16: =IF(AND(AND(INDEX(Temas!$A$5:$A$40,12)<>"",OR($A$6="(Todos)",INDEX(Temas!$B$5:$B$40,12)=$A$6),OR($B$6="(Todos)",INDEX(Temas!$C$5:$C$40,12)=$B$6)),INDEX(Temas!$T$5:$T$40,12)="Não material"),N(INDEX(Temas!$P$5:$P$40,12)),NA()) -> 10
A17: ="Monitorizar ("&prm_Limiar_Baixo&"–<"&prm_Limiar_Impacto&")" -> Monitorizar (6–<12) | B17: =COUNTIFS(Temas!$U$5:$U$40,2,Temas!$V$5:$V$40,0,Temas!$B$5:$B$40,$A$7,Temas!$C$5:$C$40,$B$7) -> 1 | C17: =COUNTIFS(Temas!$U$5:$U$40,2,Temas!$V$5:$V$40,1,Temas!$B$5:$B$40,$A$7,Temas!$C$5:$C$40,$B$7) -> 1 | D17: =COUNTIFS(Temas!$U$5:$U$40,2,Temas!$V$5:$V$40,2,Temas!$B$5:$B$40,$A$7,Temas!$C$5:$C$40,$B$7) -> 5 | E17: =COUNTIFS(Temas!$U$5:$U$40,2,Temas!$V$5:$V$40,3,Temas!$B$5:$B$40,$A$7,Temas!$C$5:$C$40,$B$7) -> 2 | F17: =COUNTIFS(Temas!$U$5:$U$40,2,Temas!$V$5:$V$40,4,Temas!$B$5:$B$40,$A$7,Temas!$C$5:$C$40,$B$7) -> 1 | Z17: =IF(AND(INDEX(Temas!$A$5:$A$40,13)<>"",OR($A$6="(Todos)",INDEX(Temas!$B$5:$B$40,13)=$A$6),OR($B$6="(Todos)",INDEX(Temas!$C$5:$C$40,13)=$B$6)),INDEX(Temas!$A$5:$A$40,13),"") -> DM-13 | AA17: =IF(AND(INDEX(Temas!$A$5:$A$40,13)<>"",OR($A$6="(Todos)",INDEX(Temas!$B$5:$B$40,13)=$A$6),OR($B$6="(Todos)",INDEX(Temas!$C$5:$C$40,13)=$B$6)),N(INDEX(Temas!$Q$5:$Q$40,13)),NA()) -> 6 | AB17: =IF(AND(AND(INDEX(Temas!$A$5:$A$40,13)<>"",OR($A$6="(Todos)",INDEX(Temas!$B$5:$B$40,13)=$A$6),OR($B$6="(Todos)",INDEX(Temas!$C$5:$C$40,13)=$B$6)),INDEX(Temas!$T$5:$T$40,13)="Dupla materialidade"),N(INDEX(Temas!$P$5:$P$40,13)),NA()) -> #N/A | AC17: =IF(AND(AND(INDEX(Temas!$A$5:$A$40,13)<>"",OR($A$6="(Todos)",INDEX(Temas!$B$5:$B$40,13)=$A$6),OR($B$6="(Todos)",INDEX(Temas!$C$5:$C$40,13)=$B$6)),INDEX(Temas!$T$5:$T$40,13)="Material — impacto"),N(INDEX(Temas!$P$5:$P$40,13)),NA()) -> 20 | AD17: =IF(AND(AND(INDEX(Temas!$A$5:$A$40,13)<>"",OR($A$6="(Todos)",INDEX(Temas!$B$5:$B$40,13)=$A$6),OR($B$6="(Todos)",INDEX(Temas!$C$5:$C$40,13)=$B$6)),INDEX(Temas!$T$5:$T$40,13)="Material — financeira"),N(INDEX(Temas!$P$5:$P$40,13)),NA()) -> #N/A | AE17: =IF(AND(AND(INDEX(Temas!$A$5:$A$40,13)<>"",OR($A$6="(Todos)",INDEX(Temas!$B$5:$B$40,13)=$A$6),OR($B$6="(Todos)",INDEX(Temas!$C$5:$C$40,13)=$B$6)),INDEX(Temas!$T$5:$T$40,13)="Não material"),N(INDEX(Temas!$P$5:$P$40,13)),NA()) -> #N/A
A18: ="Baixa (<"&prm_Limiar_Baixo&")" -> Baixa (<6) | B18: =COUNTIFS(Temas!$U$5:$U$40,1,Temas!$V$5:$V$40,0,Temas!$B$5:$B$40,$A$7,Temas!$C$5:$C$40,$B$7) -> 1 | C18: =COUNTIFS(Temas!$U$5:$U$40,1,Temas!$V$5:$V$40,1,Temas!$B$5:$B$40,$A$7,Temas!$C$5:$C$40,$B$7) -> 0 | D18: =COUNTIFS(Temas!$U$5:$U$40,1,Temas!$V$5:$V$40,2,Temas!$B$5:$B$40,$A$7,Temas!$C$5:$C$40,$B$7) -> 0 | E18: =COUNTIFS(Temas!$U$5:$U$40,1,Temas!$V$5:$V$40,3,Temas!$B$5:$B$40,$A$7,Temas!$C$5:$C$40,$B$7) -> 1 | F18: =COUNTIFS(Temas!$U$5:$U$40,1,Temas!$V$5:$V$40,4,Temas!$B$5:$B$40,$A$7,Temas!$C$5:$C$40,$B$7) -> 0 | Z18: =IF(AND(INDEX(Temas!$A$5:$A$40,14)<>"",OR($A$6="(Todos)",INDEX(Temas!$B$5:$B$40,14)=$A$6),OR($B$6="(Todos)",INDEX(Temas!$C$5:$C$40,14)=$B$6)),INDEX(Temas!$A$5:$A$40,14),"") -> DM-14 | AA18: =IF(AND(INDEX(Temas!$A$5:$A$40,14)<>"",OR($A$6="(Todos)",INDEX(Temas!$B$5:$B$40,14)=$A$6),OR($B$6="(Todos)",INDEX(Temas!$C$5:$C$40,14)=$B$6)),N(INDEX(Temas!$Q$5:$Q$40,14)),NA()) -> 16 | AB18: =IF(AND(AND(INDEX(Temas!$A$5:$A$40,14)<>"",OR($A$6="(Todos)",INDEX(Temas!$B$5:$B$40,14)=$A$6),OR($B$6="(Todos)",INDEX(Temas!$C$5:$C$40,14)=$B$6)),INDEX(Temas!$T$5:$T$40,14)="Dupla materialidade"),N(INDEX(Temas!$P$5:$P$40,14)),NA()) -> #N/A | AC18: =IF(AND(AND(INDEX(Temas!$A$5:$A$40,14)<>"",OR($A$6="(Todos)",INDEX(Temas!$B$5:$B$40,14)=$A$6),OR($B$6="(Todos)",INDEX(Temas!$C$5:$C$40,14)=$B$6)),INDEX(Temas!$T$5:$T$40,14)="Material — impacto"),N(INDEX(Temas!$P$5:$P$40,14)),NA()) -> #N/A | AD18: =IF(AND(AND(INDEX(Temas!$A$5:$A$40,14)<>"",OR($A$6="(Todos)",INDEX(Temas!$B$5:$B$40,14)=$A$6),OR($B$6="(Todos)",INDEX(Temas!$C$5:$C$40,14)=$B$6)),INDEX(Temas!$T$5:$T$40,14)="Material — financeira"),N(INDEX(Temas!$P$5:$P$40,14)),NA()) -> 11.7 | AE18: =IF(AND(AND(INDEX(Temas!$A$5:$A$40,14)<>"",OR($A$6="(Todos)",INDEX(Temas!$B$5:$B$40,14)=$A$6),OR($B$6="(Todos)",INDEX(Temas!$C$5:$C$40,14)=$B$6)),INDEX(Temas!$T$5:$T$40,14)="Não material"),N(INDEX(Temas!$P$5:$P$40,14)),NA()) -> #N/A
A19: Sem IRO de impacto | B19: =COUNTIFS(Temas!$U$5:$U$40,0,Temas!$V$5:$V$40,0,Temas!$B$5:$B$40,$A$7,Temas!$C$5:$C$40,$B$7) -> 0 | C19: =COUNTIFS(Temas!$U$5:$U$40,0,Temas!$V$5:$V$40,1,Temas!$B$5:$B$40,$A$7,Temas!$C$5:$C$40,$B$7) -> 0 | D19: =COUNTIFS(Temas!$U$5:$U$40,0,Temas!$V$5:$V$40,2,Temas!$B$5:$B$40,$A$7,Temas!$C$5:$C$40,$B$7) -> 0 | E19: =COUNTIFS(Temas!$U$5:$U$40,0,Temas!$V$5:$V$40,3,Temas!$B$5:$B$40,$A$7,Temas!$C$5:$C$40,$B$7) -> 2 | F19: =COUNTIFS(Temas!$U$5:$U$40,0,Temas!$V$5:$V$40,4,Temas!$B$5:$B$40,$A$7,Temas!$C$5:$C$40,$B$7) -> 0 | Z19: =IF(AND(INDEX(Temas!$A$5:$A$40,15)<>"",OR($A$6="(Todos)",INDEX(Temas!$B$5:$B$40,15)=$A$6),OR($B$6="(Todos)",INDEX(Temas!$C$5:$C$40,15)=$B$6)),INDEX(Temas!$A$5:$A$40,15),"") -> DM-15 | AA19: =IF(AND(INDEX(Temas!$A$5:$A$40,15)<>"",OR($A$6="(Todos)",INDEX(Temas!$B$5:$B$40,15)=$A$6),OR($B$6="(Todos)",INDEX(Temas!$C$5:$C$40,15)=$B$6)),N(INDEX(Temas!$Q$5:$Q$40,15)),NA()) -> 9 | AB19: =IF(AND(AND(INDEX(Temas!$A$5:$A$40,15)<>"",OR($A$6="(Todos)",INDEX(Temas!$B$5:$B$40,15)=$A$6),OR($B$6="(Todos)",INDEX(Temas!$C$5:$C$40,15)=$B$6)),INDEX(Temas!$T$5:$T$40,15)="Dupla materialidade"),N(INDEX(Temas!$P$5:$P$40,15)),NA()) -> #N/A | AC19: =IF(AND(AND(INDEX(Temas!$A$5:$A$40,15)<>"",OR($A$6="(Todos)",INDEX(Temas!$B$5:$B$40,15)=$A$6),OR($B$6="(Todos)",INDEX(Temas!$C$5:$C$40,15)=$B$6)),INDEX(Temas!$T$5:$T$40,15)="Material — impacto"),N(INDEX(Temas!$P$5:$P$40,15)),NA()) -> #N/A | AD19: =IF(AND(AND(INDEX(Temas!$A$5:$A$40,15)<>"",OR($A$6="(Todos)",INDEX(Temas!$B$5:$B$40,15)=$A$6),OR($B$6="(Todos)",INDEX(Temas!$C$5:$C$40,15)=$B$6)),INDEX(Temas!$T$5:$T$40,15)="Material — financeira"),N(INDEX(Temas!$P$5:$P$40,15)),NA()) -> #N/A | AE19: =IF(AND(AND(INDEX(Temas!$A$5:$A$40,15)<>"",OR($A$6="(Todos)",INDEX(Temas!$B$5:$B$40,15)=$A$6),OR($B$6="(Todos)",INDEX(Temas!$C$5:$C$40,15)=$B$6)),INDEX(Temas!$T$5:$T$40,15)="Não material"),N(INDEX(Temas!$P$5:$P$40,15)),NA()) -> 10
Z20: =IF(AND(INDEX(Temas!$A$5:$A$40,16)<>"",OR($A$6="(Todos)",INDEX(Temas!$B$5:$B$40,16)=$A$6),OR($B$6="(Todos)",INDEX(Temas!$C$5:$C$40,16)=$B$6)),INDEX(Temas!$A$5:$A$40,16),"") -> DM-16 | AA20: =IF(AND(INDEX(Temas!$A$5:$A$40,16)<>"",OR($A$6="(Todos)",INDEX(Temas!$B$5:$B$40,16)=$A$6),OR($B$6="(Todos)",INDEX(Temas!$C$5:$C$40,16)=$B$6)),N(INDEX(Temas!$Q$5:$Q$40,16)),NA()) -> 0 | AB20: =IF(AND(AND(INDEX(Temas!$A$5:$A$40,16)<>"",OR($A$6="(Todos)",INDEX(Temas!$B$5:$B$40,16)=$A$6),OR($B$6="(Todos)",INDEX(Temas!$C$5:$C$40,16)=$B$6)),INDEX(Temas!$T$5:$T$40,16)="Dupla materialidade"),N(INDEX(Temas!$P$5:$P$40,16)),NA()) -> #N/A | AC20: =IF(AND(AND(INDEX(Temas!$A$5:$A$40,16)<>"",OR($A$6="(Todos)",INDEX(Temas!$B$5:$B$40,16)=$A$6),OR($B$6="(Todos)",INDEX(Temas!$C$5:$C$40,16)=$B$6)),INDEX(Temas!$T$5:$T$40,16)="Material — impacto"),N(INDEX(Temas!$P$5:$P$40,16)),NA()) -> #N/A | AD20: =IF(AND(AND(INDEX(Temas!$A$5:$A$40,16)<>"",OR($A$6="(Todos)",INDEX(Temas!$B$5:$B$40,16)=$A$6),OR($B$6="(Todos)",INDEX(Temas!$C$5:$C$40,16)=$B$6)),INDEX(Temas!$T$5:$T$40,16)="Material — financeira"),N(INDEX(Temas!$P$5:$P$40,16)),NA()) -> #N/A | AE20: =IF(AND(AND(INDEX(Temas!$A$5:$A$40,16)<>"",OR($A$6="(Todos)",INDEX(Temas!$B$5:$B$40,16)=$A$6),OR($B$6="(Todos)",INDEX(Temas!$C$5:$C$40,16)=$B$6)),INDEX(Temas!$T$5:$T$40,16)="Não material"),N(INDEX(Temas!$P$5:$P$40,16)),NA()) -> 4
A21: GRÁFICO — MATRIZ DE DUPLA MATERIALIDADE POR TEMA (dinâmico com os filtros Pilar e Tópico; rótulo = ID do tema) | Z21: =IF(AND(INDEX(Temas!$A$5:$A$40,17)<>"",OR($A$6="(Todos)",INDEX(Temas!$B$5:$B$40,17)=$A$6),OR($B$6="(Todos)",INDEX(Temas!$C$5:$C$40,17)=$B$6)),INDEX(Temas!$A$5:$A$40,17),"") -> DM-17 | AA21: =IF(AND(INDEX(Temas!$A$5:$A$40,17)<>"",OR($A$6="(Todos)",INDEX(Temas!$B$5:$B$40,17)=$A$6),OR($B$6="(Todos)",INDEX(Temas!$C$5:$C$40,17)=$B$6)),N(INDEX(Temas!$Q$5:$Q$40,17)),NA()) -> 0 | AB21: =IF(AND(AND(INDEX(Temas!$A$5:$A$40,17)<>"",OR($A$6="(Todos)",INDEX(Temas!$B$5:$B$40,17)=$A$6),OR($B$6="(Todos)",INDEX(Temas!$C$5:$C$40,17)=$B$6)),INDEX(Temas!$T$5:$T$40,17)="Dupla materialidade"),N(INDEX(Temas!$P$5:$P$40,17)),NA()) -> #N/A | AC21: =IF(AND(AND(INDEX(Temas!$A$5:$A$40,17)<>"",OR($A$6="(Todos)",INDEX(Temas!$B$5:$B$40,17)=$A$6),OR($B$6="(Todos)",INDEX(Temas!$C$5:$C$40,17)=$B$6)),INDEX(Temas!$T$5:$T$40,17)="Material — impacto"),N(INDEX(Temas!$P$5:$P$40,17)),NA()) -> #N/A | AD21: =IF(AND(AND(INDEX(Temas!$A$5:$A$40,17)<>"",OR($A$6="(Todos)",INDEX(Temas!$B$5:$B$40,17)=$A$6),OR($B$6="(Todos)",INDEX(Temas!$C$5:$C$40,17)=$B$6)),INDEX(Temas!$T$5:$T$40,17)="Material — financeira"),N(INDEX(Temas!$P$5:$P$40,17)),NA()) -> #N/A | AE21: =IF(AND(AND(INDEX(Temas!$A$5:$A$40,17)<>"",OR($A$6="(Todos)",INDEX(Temas!$B$5:$B$40,17)=$A$6),OR($B$6="(Todos)",INDEX(Temas!$C$5:$C$40,17)=$B$6)),INDEX(Temas!$T$5:$T$40,17)="Não material"),N(INDEX(Temas!$P$5:$P$40,17)),NA()) -> 6.7
Z22: =IF(AND(INDEX(Temas!$A$5:$A$40,18)<>"",OR($A$6="(Todos)",INDEX(Temas!$B$5:$B$40,18)=$A$6),OR($B$6="(Todos)",INDEX(Temas!$C$5:$C$40,18)=$B$6)),INDEX(Temas!$A$5:$A$40,18),"") -> DM-18 | AA22: =IF(AND(INDEX(Temas!$A$5:$A$40,18)<>"",OR($A$6="(Todos)",INDEX(Temas!$B$5:$B$40,18)=$A$6),OR($B$6="(Todos)",INDEX(Temas!$C$5:$C$40,18)=$B$6)),N(INDEX(Temas!$Q$5:$Q$40,18)),NA()) -> 0 | AB22: =IF(AND(AND(INDEX(Temas!$A$5:$A$40,18)<>"",OR($A$6="(Todos)",INDEX(Temas!$B$5:$B$40,18)=$A$6),OR($B$6="(Todos)",INDEX(Temas!$C$5:$C$40,18)=$B$6)),INDEX(Temas!$T$5:$T$40,18)="Dupla materialidade"),N(INDEX(Temas!$P$5:$P$40,18)),NA()) -> #N/A | AC22: =IF(AND(AND(INDEX(Temas!$A$5:$A$40,18)<>"",OR($A$6="(Todos)",INDEX(Temas!$B$5:$B$40,18)=$A$6),OR($B$6="(Todos)",INDEX(Temas!$C$5:$C$40,18)=$B$6)),INDEX(Temas!$T$5:$T$40,18)="Material — impacto"),N(INDEX(Temas!$P$5:$P$40,18)),NA()) -> 12.5 | AD22: =IF(AND(AND(INDEX(Temas!$A$5:$A$40,18)<>"",OR($A$6="(Todos)",INDEX(Temas!$B$5:$B$40,18)=$A$6),OR($B$6="(Todos)",INDEX(Temas!$C$5:$C$40,18)=$B$6)),INDEX(Temas!$T$5:$T$40,18)="Material — financeira"),N(INDEX(Temas!$P$5:$P$40,18)),NA()) -> #N/A | AE22: =IF(AND(AND(INDEX(Temas!$A$5:$A$40,18)<>"",OR($A$6="(Todos)",INDEX(Temas!$B$5:$B$40,18)=$A$6),OR($B$6="(Todos)",INDEX(Temas!$C$5:$C$40,18)=$B$6)),INDEX(Temas!$T$5:$T$40,18)="Não material"),N(INDEX(Temas!$P$5:$P$40,18)),NA()) -> #N/A
Z23: =IF(AND(INDEX(Temas!$A$5:$A$40,19)<>"",OR($A$6="(Todos)",INDEX(Temas!$B$5:$B$40,19)=$A$6),OR($B$6="(Todos)",INDEX(Temas!$C$5:$C$40,19)=$B$6)),INDEX(Temas!$A$5:$A$40,19),"") -> DM-19 | AA23: =IF(AND(INDEX(Temas!$A$5:$A$40,19)<>"",OR($A$6="(Todos)",INDEX(Temas!$B$5:$B$40,19)=$A$6),OR($B$6="(Todos)",INDEX(Temas!$C$5:$C$40,19)=$B$6)),N(INDEX(Temas!$Q$5:$Q$40,19)),NA()) -> 15 | AB23: =IF(AND(AND(INDEX(Temas!$A$5:$A$40,19)<>"",OR($A$6="(Todos)",INDEX(Temas!$B$5:$B$40,19)=$A$6),OR($B$6="(Todos)",INDEX(Temas!$C$5:$C$40,19)=$B$6)),INDEX(Temas!$T$5:$T$40,19)="Dupla materialidade"),N(INDEX(Temas!$P$5:$P$40,19)),NA()) -> 20 | AC23: =IF(AND(AND(INDEX(Temas!$A$5:$A$40,19)<>"",OR($A$6="(Todos)",INDEX(Temas!$B$5:$B$40,19)=$A$6),OR($B$6="(Todos)",INDEX(Temas!$C$5:$C$40,19)=$B$6)),INDEX(Temas!$T$5:$T$40,19)="Material — impacto"),N(INDEX(Temas!$P$5:$P$40,19)),NA()) -> #N/A | AD23: =IF(AND(AND(INDEX(Temas!$A$5:$A$40,19)<>"",OR($A$6="(Todos)",INDEX(Temas!$B$5:$B$40,19)=$A$6),OR($B$6="(Todos)",INDEX(Temas!$C$5:$C$40,19)=$B$6)),INDEX(Temas!$T$5:$T$40,19)="Material — financeira"),N(INDEX(Temas!$P$5:$P$40,19)),NA()) -> #N/A | AE23: =IF(AND(AND(INDEX(Temas!$A$5:$A$40,19)<>"",OR($A$6="(Todos)",INDEX(Temas!$B$5:$B$40,19)=$A$6),OR($B$6="(Todos)",INDEX(Temas!$C$5:$C$40,19)=$B$6)),INDEX(Temas!$T$5:$T$40,19)="Não material"),N(INDEX(Temas!$P$5:$P$40,19)),NA()) -> #N/A
Z24: =IF(AND(INDEX(Temas!$A$5:$A$40,20)<>"",OR($A$6="(Todos)",INDEX(Temas!$B$5:$B$40,20)=$A$6),OR($B$6="(Todos)",INDEX(Temas!$C$5:$C$40,20)=$B$6)),INDEX(Temas!$A$5:$A$40,20),"") -> DM-20 | AA24: =IF(AND(INDEX(Temas!$A$5:$A$40,20)<>"",OR($A$6="(Todos)",INDEX(Temas!$B$5:$B$40,20)=$A$6),OR($B$6="(Todos)",INDEX(Temas!$C$5:$C$40,20)=$B$6)),N(INDEX(Temas!$Q$5:$Q$40,20)),NA()) -> 9 | AB24: =IF(AND(AND(INDEX(Temas!$A$5:$A$40,20)<>"",OR($A$6="(Todos)",INDEX(Temas!$B$5:$B$40,20)=$A$6),OR($B$6="(Todos)",INDEX(Temas!$C$5:$C$40,20)=$B$6)),INDEX(Temas!$T$5:$T$40,20)="Dupla materialidade"),N(INDEX(Temas!$P$5:$P$40,20)),NA()) -> #N/A | AC24: =IF(AND(AND(INDEX(Temas!$A$5:$A$40,20)<>"",OR($A$6="(Todos)",INDEX(Temas!$B$5:$B$40,20)=$A$6),OR($B$6="(Todos)",INDEX(Temas!$C$5:$C$40,20)=$B$6)),INDEX(Temas!$T$5:$T$40,20)="Material — impacto"),N(INDEX(Temas!$P$5:$P$40,20)),NA()) -> #N/A | AD24: =IF(AND(AND(INDEX(Temas!$A$5:$A$40,20)<>"",OR($A$6="(Todos)",INDEX(Temas!$B$5:$B$40,20)=$A$6),OR($B$6="(Todos)",INDEX(Temas!$C$5:$C$40,20)=$B$6)),INDEX(Temas!$T$5:$T$40,20)="Material — financeira"),N(INDEX(Temas!$P$5:$P$40,20)),NA()) -> #N/A | AE24: =IF(AND(AND(INDEX(Temas!$A$5:$A$40,20)<>"",OR($A$6="(Todos)",INDEX(Temas!$B$5:$B$40,20)=$A$6),OR($B$6="(Todos)",INDEX(Temas!$C$5:$C$40,20)=$B$6)),INDEX(Temas!$T$5:$T$40,20)="Não material"),N(INDEX(Temas!$P$5:$P$40,20)),NA()) -> 7
Z25: =IF(AND(INDEX(Temas!$A$5:$A$40,21)<>"",OR($A$6="(Todos)",INDEX(Temas!$B$5:$B$40,21)=$A$6),OR($B$6="(Todos)",INDEX(Temas!$C$5:$C$40,21)=$B$6)),INDEX(Temas!$A$5:$A$40,21),"") -> DM-21 | AA25: =IF(AND(INDEX(Temas!$A$5:$A$40,21)<>"",OR($A$6="(Todos)",INDEX(Temas!$B$5:$B$40,21)=$A$6),OR($B$6="(Todos)",INDEX(Temas!$C$5:$C$40,21)=$B$6)),N(INDEX(Temas!$Q$5:$Q$40,21)),NA()) -> 12 | AB25: =IF(AND(AND(INDEX(Temas!$A$5:$A$40,21)<>"",OR($A$6="(Todos)",INDEX(Temas!$B$5:$B$40,21)=$A$6),OR($B$6="(Todos)",INDEX(Temas!$C$5:$C$40,21)=$B$6)),INDEX(Temas!$T$5:$T$40,21)="Dupla materialidade"),N(INDEX(Temas!$P$5:$P$40,21)),NA()) -> #N/A | AC25: =IF(AND(AND(INDEX(Temas!$A$5:$A$40,21)<>"",OR($A$6="(Todos)",INDEX(Temas!$B$5:$B$40,21)=$A$6),OR($B$6="(Todos)",INDEX(Temas!$C$5:$C$40,21)=$B$6)),INDEX(Temas!$T$5:$T$40,21)="Material — impacto"),N(INDEX(Temas!$P$5:$P$40,21)),NA()) -> #N/A | AD25: =IF(AND(AND(INDEX(Temas!$A$5:$A$40,21)<>"",OR($A$6="(Todos)",INDEX(Temas!$B$5:$B$40,21)=$A$6),OR($B$6="(Todos)",INDEX(Temas!$C$5:$C$40,21)=$B$6)),INDEX(Temas!$T$5:$T$40,21)="Material — financeira"),N(INDEX(Temas!$P$5:$P$40,21)),NA()) -> 2 | AE25: =IF(AND(AND(INDEX(Temas!$A$5:$A$40,21)<>"",OR($A$6="(Todos)",INDEX(Temas!$B$5:$B$40,21)=$A$6),OR($B$6="(Todos)",INDEX(Temas!$C$5:$C$40,21)=$B$6)),INDEX(Temas!$T$5:$T$40,21)="Não material"),N(INDEX(Temas!$P$5:$P$40,21)),NA()) -> #N/A
Z26: =IF(AND(INDEX(Temas!$A$5:$A$40,22)<>"",OR($A$6="(Todos)",INDEX(Temas!$B$5:$B$40,22)=$A$6),OR($B$6="(Todos)",INDEX(Temas!$C$5:$C$40,22)=$B$6)),INDEX(Temas!$A$5:$A$40,22),"") -> DM-22 | AA26: =IF(AND(INDEX(Temas!$A$5:$A$40,22)<>"",OR($A$6="(Todos)",INDEX(Temas!$B$5:$B$40,22)=$A$6),OR($B$6="(Todos)",INDEX(Temas!$C$5:$C$40,22)=$B$6)),N(INDEX(Temas!$Q$5:$Q$40,22)),NA()) -> 12 | AB26: =IF(AND(AND(INDEX(Temas!$A$5:$A$40,22)<>"",OR($A$6="(Todos)",INDEX(Temas!$B$5:$B$40,22)=$A$6),OR($B$6="(Todos)",INDEX(Temas!$C$5:$C$40,22)=$B$6)),INDEX(Temas!$T$5:$T$40,22)="Dupla materialidade"),N(INDEX(Temas!$P$5:$P$40,22)),NA()) -> #N/A | AC26: =IF(AND(AND(INDEX(Temas!$A$5:$A$40,22)<>"",OR($A$6="(Todos)",INDEX(Temas!$B$5:$B$40,22)=$A$6),OR($B$6="(Todos)",INDEX(Temas!$C$5:$C$40,22)=$B$6)),INDEX(Temas!$T$5:$T$40,22)="Material — impacto"),N(INDEX(Temas!$P$5:$P$40,22)),NA()) -> #N/A | AD26: =IF(AND(AND(INDEX(Temas!$A$5:$A$40,22)<>"",OR($A$6="(Todos)",INDEX(Temas!$B$5:$B$40,22)=$A$6),OR($B$6="(Todos)",INDEX(Temas!$C$5:$C$40,22)=$B$6)),INDEX(Temas!$T$5:$T$40,22)="Material — financeira"),N(INDEX(Temas!$P$5:$P$40,22)),NA()) -> 7.5 | AE26: =IF(AND(AND(INDEX(Temas!$A$5:$A$40,22)<>"",OR($A$6="(Todos)",INDEX(Temas!$B$5:$B$40,22)=$A$6),OR($B$6="(Todos)",INDEX(Temas!$C$5:$C$40,22)=$B$6)),INDEX(Temas!$T$5:$T$40,22)="Não material"),N(INDEX(Temas!$P$5:$P$40,22)),NA()) -> #N/A
Z27: =IF(AND(INDEX(Temas!$A$5:$A$40,23)<>"",OR($A$6="(Todos)",INDEX(Temas!$B$5:$B$40,23)=$A$6),OR($B$6="(Todos)",INDEX(Temas!$C$5:$C$40,23)=$B$6)),INDEX(Temas!$A$5:$A$40,23),"") -> DM-23 | AA27: =IF(AND(INDEX(Temas!$A$5:$A$40,23)<>"",OR($A$6="(Todos)",INDEX(Temas!$B$5:$B$40,23)=$A$6),OR($B$6="(Todos)",INDEX(Temas!$C$5:$C$40,23)=$B$6)),N(INDEX(Temas!$Q$5:$Q$40,23)),NA()) -> 20 | AB27: =IF(AND(AND(INDEX(Temas!$A$5:$A$40,23)<>"",OR($A$6="(Todos)",INDEX(Temas!$B$5:$B$40,23)=$A$6),OR($B$6="(Todos)",INDEX(Temas!$C$5:$C$40,23)=$B$6)),INDEX(Temas!$T$5:$T$40,23)="Dupla materialidade"),N(INDEX(Temas!$P$5:$P$40,23)),NA()) -> #N/A | AC27: =IF(AND(AND(INDEX(Temas!$A$5:$A$40,23)<>"",OR($A$6="(Todos)",INDEX(Temas!$B$5:$B$40,23)=$A$6),OR($B$6="(Todos)",INDEX(Temas!$C$5:$C$40,23)=$B$6)),INDEX(Temas!$T$5:$T$40,23)="Material — impacto"),N(INDEX(Temas!$P$5:$P$40,23)),NA()) -> #N/A | AD27: =IF(AND(AND(INDEX(Temas!$A$5:$A$40,23)<>"",OR($A$6="(Todos)",INDEX(Temas!$B$5:$B$40,23)=$A$6),OR($B$6="(Todos)",INDEX(Temas!$C$5:$C$40,23)=$B$6)),INDEX(Temas!$T$5:$T$40,23)="Material — financeira"),N(INDEX(Temas!$P$5:$P$40,23)),NA()) -> 10 | AE27: =IF(AND(AND(INDEX(Temas!$A$5:$A$40,23)<>"",OR($A$6="(Todos)",INDEX(Temas!$B$5:$B$40,23)=$A$6),OR($B$6="(Todos)",INDEX(Temas!$C$5:$C$40,23)=$B$6)),INDEX(Temas!$T$5:$T$40,23)="Não material"),N(INDEX(Temas!$P$5:$P$40,23)),NA()) -> #N/A
Z28: =IF(AND(INDEX(Temas!$A$5:$A$40,24)<>"",OR($A$6="(Todos)",INDEX(Temas!$B$5:$B$40,24)=$A$6),OR($B$6="(Todos)",INDEX(Temas!$C$5:$C$40,24)=$B$6)),INDEX(Temas!$A$5:$A$40,24),"") -> DM-24 | AA28: =IF(AND(INDEX(Temas!$A$5:$A$40,24)<>"",OR($A$6="(Todos)",INDEX(Temas!$B$5:$B$40,24)=$A$6),OR($B$6="(Todos)",INDEX(Temas!$C$5:$C$40,24)=$B$6)),N(INDEX(Temas!$Q$5:$Q$40,24)),NA()) -> 12 | AB28: =IF(AND(AND(INDEX(Temas!$A$5:$A$40,24)<>"",OR($A$6="(Todos)",INDEX(Temas!$B$5:$B$40,24)=$A$6),OR($B$6="(Todos)",INDEX(Temas!$C$5:$C$40,24)=$B$6)),INDEX(Temas!$T$5:$T$40,24)="Dupla materialidade"),N(INDEX(Temas!$P$5:$P$40,24)),NA()) -> #N/A | AC28: =IF(AND(AND(INDEX(Temas!$A$5:$A$40,24)<>"",OR($A$6="(Todos)",INDEX(Temas!$B$5:$B$40,24)=$A$6),OR($B$6="(Todos)",INDEX(Temas!$C$5:$C$40,24)=$B$6)),INDEX(Temas!$T$5:$T$40,24)="Material — impacto"),N(INDEX(Temas!$P$5:$P$40,24)),NA()) -> #N/A | AD28: =IF(AND(AND(INDEX(Temas!$A$5:$A$40,24)<>"",OR($A$6="(Todos)",INDEX(Temas!$B$5:$B$40,24)=$A$6),OR($B$6="(Todos)",INDEX(Temas!$C$5:$C$40,24)=$B$6)),INDEX(Temas!$T$5:$T$40,24)="Material — financeira"),N(INDEX(Temas!$P$5:$P$40,24)),NA()) -> 0 | AE28: =IF(AND(AND(INDEX(Temas!$A$5:$A$40,24)<>"",OR($A$6="(Todos)",INDEX(Temas!$B$5:$B$40,24)=$A$6),OR($B$6="(Todos)",INDEX(Temas!$C$5:$C$40,24)=$B$6)),INDEX(Temas!$T$5:$T$40,24)="Não material"),N(INDEX(Temas!$P$5:$P$40,24)),NA()) -> #N/A
Z29: =IF(AND(INDEX(Temas!$A$5:$A$40,25)<>"",OR($A$6="(Todos)",INDEX(Temas!$B$5:$B$40,25)=$A$6),OR($B$6="(Todos)",INDEX(Temas!$C$5:$C$40,25)=$B$6)),INDEX(Temas!$A$5:$A$40,25),"") | AA29: =IF(AND(INDEX(Temas!$A$5:$A$40,25)<>"",OR($A$6="(Todos)",INDEX(Temas!$B$5:$B$40,25)=$A$6),OR($B$6="(Todos)",INDEX(Temas!$C$5:$C$40,25)=$B$6)),N(INDEX(Temas!$Q$5:$Q$40,25)),NA()) -> #N/A | AB29: =IF(AND(AND(INDEX(Temas!$A$5:$A$40,25)<>"",OR($A$6="(Todos)",INDEX(Temas!$B$5:$B$40,25)=$A$6),OR($B$6="(Todos)",INDEX(Temas!$C$5:$C$40,25)=$B$6)),INDEX(Temas!$T$5:$T$40,25)="Dupla materialidade"),N(INDEX(Temas!$P$5:$P$40,25)),NA()) -> #N/A | AC29: =IF(AND(AND(INDEX(Temas!$A$5:$A$40,25)<>"",OR($A$6="(Todos)",INDEX(Temas!$B$5:$B$40,25)=$A$6),OR($B$6="(Todos)",INDEX(Temas!$C$5:$C$40,25)=$B$6)),INDEX(Temas!$T$5:$T$40,25)="Material — impacto"),N(INDEX(Temas!$P$5:$P$40,25)),NA()) -> #N/A | AD29: =IF(AND(AND(INDEX(Temas!$A$5:$A$40,25)<>"",OR($A$6="(Todos)",INDEX(Temas!$B$5:$B$40,25)=$A$6),OR($B$6="(Todos)",INDEX(Temas!$C$5:$C$40,25)=$B$6)),INDEX(Temas!$T$5:$T$40,25)="Material — financeira"),N(INDEX(Temas!$P$5:$P$40,25)),NA()) -> #N/A | AE29: =IF(AND(AND(INDEX(Temas!$A$5:$A$40,25)<>"",OR($A$6="(Todos)",INDEX(Temas!$B$5:$B$40,25)=$A$6),OR($B$6="(Todos)",INDEX(Temas!$C$5:$C$40,25)=$B$6)),INDEX(Temas!$T$5:$T$40,25)="Não material"),N(INDEX(Temas!$P$5:$P$40,25)),NA()) -> #N/A
Z30: =IF(AND(INDEX(Temas!$A$5:$A$40,26)<>"",OR($A$6="(Todos)",INDEX(Temas!$B$5:$B$40,26)=$A$6),OR($B$6="(Todos)",INDEX(Temas!$C$5:$C$40,26)=$B$6)),INDEX(Temas!$A$5:$A$40,26),"") | AA30: =IF(AND(INDEX(Temas!$A$5:$A$40,26)<>"",OR($A$6="(Todos)",INDEX(Temas!$B$5:$B$40,26)=$A$6),OR($B$6="(Todos)",INDEX(Temas!$C$5:$C$40,26)=$B$6)),N(INDEX(Temas!$Q$5:$Q$40,26)),NA()) -> #N/A | AB30: =IF(AND(AND(INDEX(Temas!$A$5:$A$40,26)<>"",OR($A$6="(Todos)",INDEX(Temas!$B$5:$B$40,26)=$A$6),OR($B$6="(Todos)",INDEX(Temas!$C$5:$C$40,26)=$B$6)),INDEX(Temas!$T$5:$T$40,26)="Dupla materialidade"),N(INDEX(Temas!$P$5:$P$40,26)),NA()) -> #N/A | AC30: =IF(AND(AND(INDEX(Temas!$A$5:$A$40,26)<>"",OR($A$6="(Todos)",INDEX(Temas!$B$5:$B$40,26)=$A$6),OR($B$6="(Todos)",INDEX(Temas!$C$5:$C$40,26)=$B$6)),INDEX(Temas!$T$5:$T$40,26)="Material — impacto"),N(INDEX(Temas!$P$5:$P$40,26)),NA()) -> #N/A | AD30: =IF(AND(AND(INDEX(Temas!$A$5:$A$40,26)<>"",OR($A$6="(Todos)",INDEX(Temas!$B$5:$B$40,26)=$A$6),OR($B$6="(Todos)",INDEX(Temas!$C$5:$C$40,26)=$B$6)),INDEX(Temas!$T$5:$T$40,26)="Material — financeira"),N(INDEX(Temas!$P$5:$P$40,26)),NA()) -> #N/A | AE30: =IF(AND(AND(INDEX(Temas!$A$5:$A$40,26)<>"",OR($A$6="(Todos)",INDEX(Temas!$B$5:$B$40,26)=$A$6),OR($B$6="(Todos)",INDEX(Temas!$C$5:$C$40,26)=$B$6)),INDEX(Temas!$T$5:$T$40,26)="Não material"),N(INDEX(Temas!$P$5:$P$40,26)),NA()) -> #N/A
Z31: =IF(AND(INDEX(Temas!$A$5:$A$40,27)<>"",OR($A$6="(Todos)",INDEX(Temas!$B$5:$B$40,27)=$A$6),OR($B$6="(Todos)",INDEX(Temas!$C$5:$C$40,27)=$B$6)),INDEX(Temas!$A$5:$A$40,27),"") | AA31: =IF(AND(INDEX(Temas!$A$5:$A$40,27)<>"",OR($A$6="(Todos)",INDEX(Temas!$B$5:$B$40,27)=$A$6),OR($B$6="(Todos)",INDEX(Temas!$C$5:$C$40,27)=$B$6)),N(INDEX(Temas!$Q$5:$Q$40,27)),NA()) -> #N/A | AB31: =IF(AND(AND(INDEX(Temas!$A$5:$A$40,27)<>"",OR($A$6="(Todos)",INDEX(Temas!$B$5:$B$40,27)=$A$6),OR($B$6="(Todos)",INDEX(Temas!$C$5:$C$40,27)=$B$6)),INDEX(Temas!$T$5:$T$40,27)="Dupla materialidade"),N(INDEX(Temas!$P$5:$P$40,27)),NA()) -> #N/A | AC31: =IF(AND(AND(INDEX(Temas!$A$5:$A$40,27)<>"",OR($A$6="(Todos)",INDEX(Temas!$B$5:$B$40,27)=$A$6),OR($B$6="(Todos)",INDEX(Temas!$C$5:$C$40,27)=$B$6)),INDEX(Temas!$T$5:$T$40,27)="Material — impacto"),N(INDEX(Temas!$P$5:$P$40,27)),NA()) -> #N/A | AD31: =IF(AND(AND(INDEX(Temas!$A$5:$A$40,27)<>"",OR($A$6="(Todos)",INDEX(Temas!$B$5:$B$40,27)=$A$6),OR($B$6="(Todos)",INDEX(Temas!$C$5:$C$40,27)=$B$6)),INDEX(Temas!$T$5:$T$40,27)="Material — financeira"),N(INDEX(Temas!$P$5:$P$40,27)),NA()) -> #N/A | AE31: =IF(AND(AND(INDEX(Temas!$A$5:$A$40,27)<>"",OR($A$6="(Todos)",INDEX(Temas!$B$5:$B$40,27)=$A$6),OR($B$6="(Todos)",INDEX(Temas!$C$5:$C$40,27)=$B$6)),INDEX(Temas!$T$5:$T$40,27)="Não material"),N(INDEX(Temas!$P$5:$P$40,27)),NA()) -> #N/A
Z32: =IF(AND(INDEX(Temas!$A$5:$A$40,28)<>"",OR($A$6="(Todos)",INDEX(Temas!$B$5:$B$40,28)=$A$6),OR($B$6="(Todos)",INDEX(Temas!$C$5:$C$40,28)=$B$6)),INDEX(Temas!$A$5:$A$40,28),"") | AA32: =IF(AND(INDEX(Temas!$A$5:$A$40,28)<>"",OR($A$6="(Todos)",INDEX(Temas!$B$5:$B$40,28)=$A$6),OR($B$6="(Todos)",INDEX(Temas!$C$5:$C$40,28)=$B$6)),N(INDEX(Temas!$Q$5:$Q$40,28)),NA()) -> #N/A | AB32: =IF(AND(AND(INDEX(Temas!$A$5:$A$40,28)<>"",OR($A$6="(Todos)",INDEX(Temas!$B$5:$B$40,28)=$A$6),OR($B$6="(Todos)",INDEX(Temas!$C$5:$C$40,28)=$B$6)),INDEX(Temas!$T$5:$T$40,28)="Dupla materialidade"),N(INDEX(Temas!$P$5:$P$40,28)),NA()) -> #N/A | AC32: =IF(AND(AND(INDEX(Temas!$A$5:$A$40,28)<>"",OR($A$6="(Todos)",INDEX(Temas!$B$5:$B$40,28)=$A$6),OR($B$6="(Todos)",INDEX(Temas!$C$5:$C$40,28)=$B$6)),INDEX(Temas!$T$5:$T$40,28)="Material — impacto"),N(INDEX(Temas!$P$5:$P$40,28)),NA()) -> #N/A | AD32: =IF(AND(AND(INDEX(Temas!$A$5:$A$40,28)<>"",OR($A$6="(Todos)",INDEX(Temas!$B$5:$B$40,28)=$A$6),OR($B$6="(Todos)",INDEX(Temas!$C$5:$C$40,28)=$B$6)),INDEX(Temas!$T$5:$T$40,28)="Material — financeira"),N(INDEX(Temas!$P$5:$P$40,28)),NA()) -> #N/A | AE32: =IF(AND(AND(INDEX(Temas!$A$5:$A$40,28)<>"",OR($A$6="(Todos)",INDEX(Temas!$B$5:$B$40,28)=$A$6),OR($B$6="(Todos)",INDEX(Temas!$C$5:$C$40,28)=$B$6)),INDEX(Temas!$T$5:$T$40,28)="Não material"),N(INDEX(Temas!$P$5:$P$40,28)),NA()) -> #N/A
Z33: =IF(AND(INDEX(Temas!$A$5:$A$40,29)<>"",OR($A$6="(Todos)",INDEX(Temas!$B$5:$B$40,29)=$A$6),OR($B$6="(Todos)",INDEX(Temas!$C$5:$C$40,29)=$B$6)),INDEX(Temas!$A$5:$A$40,29),"") | AA33: =IF(AND(INDEX(Temas!$A$5:$A$40,29)<>"",OR($A$6="(Todos)",INDEX(Temas!$B$5:$B$40,29)=$A$6),OR($B$6="(Todos)",INDEX(Temas!$C$5:$C$40,29)=$B$6)),N(INDEX(Temas!$Q$5:$Q$40,29)),NA()) -> #N/A | AB33: =IF(AND(AND(INDEX(Temas!$A$5:$A$40,29)<>"",OR($A$6="(Todos)",INDEX(Temas!$B$5:$B$40,29)=$A$6),OR($B$6="(Todos)",INDEX(Temas!$C$5:$C$40,29)=$B$6)),INDEX(Temas!$T$5:$T$40,29)="Dupla materialidade"),N(INDEX(Temas!$P$5:$P$40,29)),NA()) -> #N/A | AC33: =IF(AND(AND(INDEX(Temas!$A$5:$A$40,29)<>"",OR($A$6="(Todos)",INDEX(Temas!$B$5:$B$40,29)=$A$6),OR($B$6="(Todos)",INDEX(Temas!$C$5:$C$40,29)=$B$6)),INDEX(Temas!$T$5:$T$40,29)="Material — impacto"),N(INDEX(Temas!$P$5:$P$40,29)),NA()) -> #N/A | AD33: =IF(AND(AND(INDEX(Temas!$A$5:$A$40,29)<>"",OR($A$6="(Todos)",INDEX(Temas!$B$5:$B$40,29)=$A$6),OR($B$6="(Todos)",INDEX(Temas!$C$5:$C$40,29)=$B$6)),INDEX(Temas!$T$5:$T$40,29)="Material — financeira"),N(INDEX(Temas!$P$5:$P$40,29)),NA()) -> #N/A | AE33: =IF(AND(AND(INDEX(Temas!$A$5:$A$40,29)<>"",OR($A$6="(Todos)",INDEX(Temas!$B$5:$B$40,29)=$A$6),OR($B$6="(Todos)",INDEX(Temas!$C$5:$C$40,29)=$B$6)),INDEX(Temas!$T$5:$T$40,29)="Não material"),N(INDEX(Temas!$P$5:$P$40,29)),NA()) -> #N/A
Z34: =IF(AND(INDEX(Temas!$A$5:$A$40,30)<>"",OR($A$6="(Todos)",INDEX(Temas!$B$5:$B$40,30)=$A$6),OR($B$6="(Todos)",INDEX(Temas!$C$5:$C$40,30)=$B$6)),INDEX(Temas!$A$5:$A$40,30),"") | AA34: =IF(AND(INDEX(Temas!$A$5:$A$40,30)<>"",OR($A$6="(Todos)",INDEX(Temas!$B$5:$B$40,30)=$A$6),OR($B$6="(Todos)",INDEX(Temas!$C$5:$C$40,30)=$B$6)),N(INDEX(Temas!$Q$5:$Q$40,30)),NA()) -> #N/A | AB34: =IF(AND(AND(INDEX(Temas!$A$5:$A$40,30)<>"",OR($A$6="(Todos)",INDEX(Temas!$B$5:$B$40,30)=$A$6),OR($B$6="(Todos)",INDEX(Temas!$C$5:$C$40,30)=$B$6)),INDEX(Temas!$T$5:$T$40,30)="Dupla materialidade"),N(INDEX(Temas!$P$5:$P$40,30)),NA()) -> #N/A | AC34: =IF(AND(AND(INDEX(Temas!$A$5:$A$40,30)<>"",OR($A$6="(Todos)",INDEX(Temas!$B$5:$B$40,30)=$A$6),OR($B$6="(Todos)",INDEX(Temas!$C$5:$C$40,30)=$B$6)),INDEX(Temas!$T$5:$T$40,30)="Material — impacto"),N(INDEX(Temas!$P$5:$P$40,30)),NA()) -> #N/A | AD34: =IF(AND(AND(INDEX(Temas!$A$5:$A$40,30)<>"",OR($A$6="(Todos)",INDEX(Temas!$B$5:$B$40,30)=$A$6),OR($B$6="(Todos)",INDEX(Temas!$C$5:$C$40,30)=$B$6)),INDEX(Temas!$T$5:$T$40,30)="Material — financeira"),N(INDEX(Temas!$P$5:$P$40,30)),NA()) -> #N/A | AE34: =IF(AND(AND(INDEX(Temas!$A$5:$A$40,30)<>"",OR($A$6="(Todos)",INDEX(Temas!$B$5:$B$40,30)=$A$6),OR($B$6="(Todos)",INDEX(Temas!$C$5:$C$40,30)=$B$6)),INDEX(Temas!$T$5:$T$40,30)="Não material"),N(INDEX(Temas!$P$5:$P$40,30)),NA()) -> #N/A
Z35: =IF(AND(INDEX(Temas!$A$5:$A$40,31)<>"",OR($A$6="(Todos)",INDEX(Temas!$B$5:$B$40,31)=$A$6),OR($B$6="(Todos)",INDEX(Temas!$C$5:$C$40,31)=$B$6)),INDEX(Temas!$A$5:$A$40,31),"") | AA35: =IF(AND(INDEX(Temas!$A$5:$A$40,31)<>"",OR($A$6="(Todos)",INDEX(Temas!$B$5:$B$40,31)=$A$6),OR($B$6="(Todos)",INDEX(Temas!$C$5:$C$40,31)=$B$6)),N(INDEX(Temas!$Q$5:$Q$40,31)),NA()) -> #N/A | AB35: =IF(AND(AND(INDEX(Temas!$A$5:$A$40,31)<>"",OR($A$6="(Todos)",INDEX(Temas!$B$5:$B$40,31)=$A$6),OR($B$6="(Todos)",INDEX(Temas!$C$5:$C$40,31)=$B$6)),INDEX(Temas!$T$5:$T$40,31)="Dupla materialidade"),N(INDEX(Temas!$P$5:$P$40,31)),NA()) -> #N/A | AC35: =IF(AND(AND(INDEX(Temas!$A$5:$A$40,31)<>"",OR($A$6="(Todos)",INDEX(Temas!$B$5:$B$40,31)=$A$6),OR($B$6="(Todos)",INDEX(Temas!$C$5:$C$40,31)=$B$6)),INDEX(Temas!$T$5:$T$40,31)="Material — impacto"),N(INDEX(Temas!$P$5:$P$40,31)),NA()) -> #N/A | AD35: =IF(AND(AND(INDEX(Temas!$A$5:$A$40,31)<>"",OR($A$6="(Todos)",INDEX(Temas!$B$5:$B$40,31)=$A$6),OR($B$6="(Todos)",INDEX(Temas!$C$5:$C$40,31)=$B$6)),INDEX(Temas!$T$5:$T$40,31)="Material — financeira"),N(INDEX(Temas!$P$5:$P$40,31)),NA()) -> #N/A | AE35: =IF(AND(AND(INDEX(Temas!$A$5:$A$40,31)<>"",OR($A$6="(Todos)",INDEX(Temas!$B$5:$B$40,31)=$A$6),OR($B$6="(Todos)",INDEX(Temas!$C$5:$C$40,31)=$B$6)),INDEX(Temas!$T$5:$T$40,31)="Não material"),N(INDEX(Temas!$P$5:$P$40,31)),NA()) -> #N/A
Z36: =IF(AND(INDEX(Temas!$A$5:$A$40,32)<>"",OR($A$6="(Todos)",INDEX(Temas!$B$5:$B$40,32)=$A$6),OR($B$6="(Todos)",INDEX(Temas!$C$5:$C$40,32)=$B$6)),INDEX(Temas!$A$5:$A$40,32),"") | AA36: =IF(AND(INDEX(Temas!$A$5:$A$40,32)<>"",OR($A$6="(Todos)",INDEX(Temas!$B$5:$B$40,32)=$A$6),OR($B$6="(Todos)",INDEX(Temas!$C$5:$C$40,32)=$B$6)),N(INDEX(Temas!$Q$5:$Q$40,32)),NA()) -> #N/A | AB36: =IF(AND(AND(INDEX(Temas!$A$5:$A$40,32)<>"",OR($A$6="(Todos)",INDEX(Temas!$B$5:$B$40,32)=$A$6),OR($B$6="(Todos)",INDEX(Temas!$C$5:$C$40,32)=$B$6)),INDEX(Temas!$T$5:$T$40,32)="Dupla materialidade"),N(INDEX(Temas!$P$5:$P$40,32)),NA()) -> #N/A | AC36: =IF(AND(AND(INDEX(Temas!$A$5:$A$40,32)<>"",OR($A$6="(Todos)",INDEX(Temas!$B$5:$B$40,32)=$A$6),OR($B$6="(Todos)",INDEX(Temas!$C$5:$C$40,32)=$B$6)),INDEX(Temas!$T$5:$T$40,32)="Material — impacto"),N(INDEX(Temas!$P$5:$P$40,32)),NA()) -> #N/A | AD36: =IF(AND(AND(INDEX(Temas!$A$5:$A$40,32)<>"",OR($A$6="(Todos)",INDEX(Temas!$B$5:$B$40,32)=$A$6),OR($B$6="(Todos)",INDEX(Temas!$C$5:$C$40,32)=$B$6)),INDEX(Temas!$T$5:$T$40,32)="Material — financeira"),N(INDEX(Temas!$P$5:$P$40,32)),NA()) -> #N/A | AE36: =IF(AND(AND(INDEX(Temas!$A$5:$A$40,32)<>"",OR($A$6="(Todos)",INDEX(Temas!$B$5:$B$40,32)=$A$6),OR($B$6="(Todos)",INDEX(Temas!$C$5:$C$40,32)=$B$6)),INDEX(Temas!$T$5:$T$40,32)="Não material"),N(INDEX(Temas!$P$5:$P$40,32)),NA()) -> #N/A
Z37: =IF(AND(INDEX(Temas!$A$5:$A$40,33)<>"",OR($A$6="(Todos)",INDEX(Temas!$B$5:$B$40,33)=$A$6),OR($B$6="(Todos)",INDEX(Temas!$C$5:$C$40,33)=$B$6)),INDEX(Temas!$A$5:$A$40,33),"") | AA37: =IF(AND(INDEX(Temas!$A$5:$A$40,33)<>"",OR($A$6="(Todos)",INDEX(Temas!$B$5:$B$40,33)=$A$6),OR($B$6="(Todos)",INDEX(Temas!$C$5:$C$40,33)=$B$6)),N(INDEX(Temas!$Q$5:$Q$40,33)),NA()) -> #N/A | AB37: =IF(AND(AND(INDEX(Temas!$A$5:$A$40,33)<>"",OR($A$6="(Todos)",INDEX(Temas!$B$5:$B$40,33)=$A$6),OR($B$6="(Todos)",INDEX(Temas!$C$5:$C$40,33)=$B$6)),INDEX(Temas!$T$5:$T$40,33)="Dupla materialidade"),N(INDEX(Temas!$P$5:$P$40,33)),NA()) -> #N/A | AC37: =IF(AND(AND(INDEX(Temas!$A$5:$A$40,33)<>"",OR($A$6="(Todos)",INDEX(Temas!$B$5:$B$40,33)=$A$6),OR($B$6="(Todos)",INDEX(Temas!$C$5:$C$40,33)=$B$6)),INDEX(Temas!$T$5:$T$40,33)="Material — impacto"),N(INDEX(Temas!$P$5:$P$40,33)),NA()) -> #N/A | AD37: =IF(AND(AND(INDEX(Temas!$A$5:$A$40,33)<>"",OR($A$6="(Todos)",INDEX(Temas!$B$5:$B$40,33)=$A$6),OR($B$6="(Todos)",INDEX(Temas!$C$5:$C$40,33)=$B$6)),INDEX(Temas!$T$5:$T$40,33)="Material — financeira"),N(INDEX(Temas!$P$5:$P$40,33)),NA()) -> #N/A | AE37: =IF(AND(AND(INDEX(Temas!$A$5:$A$40,33)<>"",OR($A$6="(Todos)",INDEX(Temas!$B$5:$B$40,33)=$A$6),OR($B$6="(Todos)",INDEX(Temas!$C$5:$C$40,33)=$B$6)),INDEX(Temas!$T$5:$T$40,33)="Não material"),N(INDEX(Temas!$P$5:$P$40,33)),NA()) -> #N/A
Z38: =IF(AND(INDEX(Temas!$A$5:$A$40,34)<>"",OR($A$6="(Todos)",INDEX(Temas!$B$5:$B$40,34)=$A$6),OR($B$6="(Todos)",INDEX(Temas!$C$5:$C$40,34)=$B$6)),INDEX(Temas!$A$5:$A$40,34),"") | AA38: =IF(AND(INDEX(Temas!$A$5:$A$40,34)<>"",OR($A$6="(Todos)",INDEX(Temas!$B$5:$B$40,34)=$A$6),OR($B$6="(Todos)",INDEX(Temas!$C$5:$C$40,34)=$B$6)),N(INDEX(Temas!$Q$5:$Q$40,34)),NA()) -> #N/A | AB38: =IF(AND(AND(INDEX(Temas!$A$5:$A$40,34)<>"",OR($A$6="(Todos)",INDEX(Temas!$B$5:$B$40,34)=$A$6),OR($B$6="(Todos)",INDEX(Temas!$C$5:$C$40,34)=$B$6)),INDEX(Temas!$T$5:$T$40,34)="Dupla materialidade"),N(INDEX(Temas!$P$5:$P$40,34)),NA()) -> #N/A | AC38: =IF(AND(AND(INDEX(Temas!$A$5:$A$40,34)<>"",OR($A$6="(Todos)",INDEX(Temas!$B$5:$B$40,34)=$A$6),OR($B$6="(Todos)",INDEX(Temas!$C$5:$C$40,34)=$B$6)),INDEX(Temas!$T$5:$T$40,34)="Material — impacto"),N(INDEX(Temas!$P$5:$P$40,34)),NA()) -> #N/A | AD38: =IF(AND(AND(INDEX(Temas!$A$5:$A$40,34)<>"",OR($A$6="(Todos)",INDEX(Temas!$B$5:$B$40,34)=$A$6),OR($B$6="(Todos)",INDEX(Temas!$C$5:$C$40,34)=$B$6)),INDEX(Temas!$T$5:$T$40,34)="Material — financeira"),N(INDEX(Temas!$P$5:$P$40,34)),NA()) -> #N/A | AE38: =IF(AND(AND(INDEX(Temas!$A$5:$A$40,34)<>"",OR($A$6="(Todos)",INDEX(Temas!$B$5:$B$40,34)=$A$6),OR($B$6="(Todos)",INDEX(Temas!$C$5:$C$40,34)=$B$6)),INDEX(Temas!$T$5:$T$40,34)="Não material"),N(INDEX(Temas!$P$5:$P$40,34)),NA()) -> #N/A
Z39: =IF(AND(INDEX(Temas!$A$5:$A$40,35)<>"",OR($A$6="(Todos)",INDEX(Temas!$B$5:$B$40,35)=$A$6),OR($B$6="(Todos)",INDEX(Temas!$C$5:$C$40,35)=$B$6)),INDEX(Temas!$A$5:$A$40,35),"") | AA39: =IF(AND(INDEX(Temas!$A$5:$A$40,35)<>"",OR($A$6="(Todos)",INDEX(Temas!$B$5:$B$40,35)=$A$6),OR($B$6="(Todos)",INDEX(Temas!$C$5:$C$40,35)=$B$6)),N(INDEX(Temas!$Q$5:$Q$40,35)),NA()) -> #N/A | AB39: =IF(AND(AND(INDEX(Temas!$A$5:$A$40,35)<>"",OR($A$6="(Todos)",INDEX(Temas!$B$5:$B$40,35)=$A$6),OR($B$6="(Todos)",INDEX(Temas!$C$5:$C$40,35)=$B$6)),INDEX(Temas!$T$5:$T$40,35)="Dupla materialidade"),N(INDEX(Temas!$P$5:$P$40,35)),NA()) -> #N/A | AC39: =IF(AND(AND(INDEX(Temas!$A$5:$A$40,35)<>"",OR($A$6="(Todos)",INDEX(Temas!$B$5:$B$40,35)=$A$6),OR($B$6="(Todos)",INDEX(Temas!$C$5:$C$40,35)=$B$6)),INDEX(Temas!$T$5:$T$40,35)="Material — impacto"),N(INDEX(Temas!$P$5:$P$40,35)),NA()) -> #N/A | AD39: =IF(AND(AND(INDEX(Temas!$A$5:$A$40,35)<>"",OR($A$6="(Todos)",INDEX(Temas!$B$5:$B$40,35)=$A$6),OR($B$6="(Todos)",INDEX(Temas!$C$5:$C$40,35)=$B$6)),INDEX(Temas!$T$5:$T$40,35)="Material — financeira"),N(INDEX(Temas!$P$5:$P$40,35)),NA()) -> #N/A | AE39: =IF(AND(AND(INDEX(Temas!$A$5:$A$40,35)<>"",OR($A$6="(Todos)",INDEX(Temas!$B$5:$B$40,35)=$A$6),OR($B$6="(Todos)",INDEX(Temas!$C$5:$C$40,35)=$B$6)),INDEX(Temas!$T$5:$T$40,35)="Não material"),N(INDEX(Temas!$P$5:$P$40,35)),NA()) -> #N/A
Z40: =IF(AND(INDEX(Temas!$A$5:$A$40,36)<>"",OR($A$6="(Todos)",INDEX(Temas!$B$5:$B$40,36)=$A$6),OR($B$6="(Todos)",INDEX(Temas!$C$5:$C$40,36)=$B$6)),INDEX(Temas!$A$5:$A$40,36),"") | AA40: =IF(AND(INDEX(Temas!$A$5:$A$40,36)<>"",OR($A$6="(Todos)",INDEX(Temas!$B$5:$B$40,36)=$A$6),OR($B$6="(Todos)",INDEX(Temas!$C$5:$C$40,36)=$B$6)),N(INDEX(Temas!$Q$5:$Q$40,36)),NA()) -> #N/A | AB40: =IF(AND(AND(INDEX(Temas!$A$5:$A$40,36)<>"",OR($A$6="(Todos)",INDEX(Temas!$B$5:$B$40,36)=$A$6),OR($B$6="(Todos)",INDEX(Temas!$C$5:$C$40,36)=$B$6)),INDEX(Temas!$T$5:$T$40,36)="Dupla materialidade"),N(INDEX(Temas!$P$5:$P$40,36)),NA()) -> #N/A | AC40: =IF(AND(AND(INDEX(Temas!$A$5:$A$40,36)<>"",OR($A$6="(Todos)",INDEX(Temas!$B$5:$B$40,36)=$A$6),OR($B$6="(Todos)",INDEX(Temas!$C$5:$C$40,36)=$B$6)),INDEX(Temas!$T$5:$T$40,36)="Material — impacto"),N(INDEX(Temas!$P$5:$P$40,36)),NA()) -> #N/A | AD40: =IF(AND(AND(INDEX(Temas!$A$5:$A$40,36)<>"",OR($A$6="(Todos)",INDEX(Temas!$B$5:$B$40,36)=$A$6),OR($B$6="(Todos)",INDEX(Temas!$C$5:$C$40,36)=$B$6)),INDEX(Temas!$T$5:$T$40,36)="Material — financeira"),N(INDEX(Temas!$P$5:$P$40,36)),NA()) -> #N/A | AE40: =IF(AND(AND(INDEX(Temas!$A$5:$A$40,36)<>"",OR($A$6="(Todos)",INDEX(Temas!$B$5:$B$40,36)=$A$6),OR($B$6="(Todos)",INDEX(Temas!$C$5:$C$40,36)=$B$6)),INDEX(Temas!$T$5:$T$40,36)="Não material"),N(INDEX(Temas!$P$5:$P$40,36)),NA()) -> #N/A
Z42: Limiares
Z43: =prm_Limiar_Financeiro -> 12 | AA43: 0
Z44: =prm_Limiar_Financeiro -> 12 | AA44: 25
Z45: 0 | AA45: =prm_Limiar_Impacto -> 12
Z46: 25 | AA46: =prm_Limiar_Impacto -> 12
A49: RESUMO POR TÓPICO ESRS
A50: Tópico ESRS | B50: Temas | C50: Temas materiais | D50: Dupla materialidade | E50: Impacto máx. | F50: Financeiro máx. | G50: IRO | H50: Exposição a riscos (€/ano) | I50: Oportunidades (€/ano) | J50: Relevância média p/ partes interessadas
A51: E1 Alterações climáticas | B51: =COUNTIFS(Temas!$C$5:$C$40,"E1 Alterações climáticas") -> 3 | C51: =COUNTIFS(Temas!$C$5:$C$40,"E1 Alterações climáticas",Temas!$T$5:$T$40,"<>Não material") -> 3 | D51: =COUNTIFS(Temas!$C$5:$C$40,"E1 Alterações climáticas",Temas!$T$5:$T$40,"Dupla materialidade") -> 2 | E51: =_xlfn.MAXIFS(Temas!$P$5:$P$40,Temas!$C$5:$C$40,"E1 Alterações climáticas") -> 20 | F51: =_xlfn.MAXIFS(Temas!$Q$5:$Q$40,Temas!$C$5:$C$40,"E1 Alterações climáticas") -> 16 | G51: =SUMIFS(Temas!$M$5:$M$40,Temas!$C$5:$C$40,"E1 Alterações climáticas") -> 10 | H51: =SUMIFS(Temas!$Y$5:$Y$40,Temas!$C$5:$C$40,"E1 Alterações climáticas") -> 258750 | I51: =SUMIFS(Temas!$Z$5:$Z$40,Temas!$C$5:$C$40,"E1 Alterações climáticas") -> 120750 | J51: =IFERROR(AVERAGEIFS(Temas!$AA$5:$AA$40,Temas!$C$5:$C$40,"E1 Alterações climáticas"),"—") -> 4
A52: E2 Poluição | B52: =COUNTIFS(Temas!$C$5:$C$40,"E2 Poluição") -> 4 | C52: =COUNTIFS(Temas!$C$5:$C$40,"E2 Poluição",Temas!$T$5:$T$40,"<>Não material") -> 2 | D52: =COUNTIFS(Temas!$C$5:$C$40,"E2 Poluição",Temas!$T$5:$T$40,"Dupla materialidade") -> 1 | E52: =_xlfn.MAXIFS(Temas!$P$5:$P$40,Temas!$C$5:$C$40,"E2 Poluição") -> 18.4 | F52: =_xlfn.MAXIFS(Temas!$Q$5:$Q$40,Temas!$C$5:$C$40,"E2 Poluição") -> 12 | G52: =SUMIFS(Temas!$M$5:$M$40,Temas!$C$5:$C$40,"E2 Poluição") -> 9 | H52: =SUMIFS(Temas!$Y$5:$Y$40,Temas!$C$5:$C$40,"E2 Poluição") -> 51000 | I52: =SUMIFS(Temas!$Z$5:$Z$40,Temas!$C$5:$C$40,"E2 Poluição") -> 0 | J52: =IFERROR(AVERAGEIFS(Temas!$AA$5:$AA$40,Temas!$C$5:$C$40,"E2 Poluição"),"—") -> 3.1666667
A53: E3 Água e recursos marinhos | B53: =COUNTIFS(Temas!$C$5:$C$40,"E3 Água e recursos marinhos") -> 1 | C53: =COUNTIFS(Temas!$C$5:$C$40,"E3 Água e recursos marinhos",Temas!$T$5:$T$40,"<>Não material") -> 0 | D53: =COUNTIFS(Temas!$C$5:$C$40,"E3 Água e recursos marinhos",Temas!$T$5:$T$40,"Dupla materialidade") -> 0 | E53: =_xlfn.MAXIFS(Temas!$P$5:$P$40,Temas!$C$5:$C$40,"E3 Água e recursos marinhos") -> 11.7 | F53: =_xlfn.MAXIFS(Temas!$Q$5:$Q$40,Temas!$C$5:$C$40,"E3 Água e recursos marinhos") -> 6 | G53: =SUMIFS(Temas!$M$5:$M$40,Temas!$C$5:$C$40,"E3 Água e recursos marinhos") -> 2 | H53: =SUMIFS(Temas!$Y$5:$Y$40,Temas!$C$5:$C$40,"E3 Água e recursos marinhos") -> 8000 | I53: =SUMIFS(Temas!$Z$5:$Z$40,Temas!$C$5:$C$40,"E3 Água e recursos marinhos") -> 0 | J53: =IFERROR(AVERAGEIFS(Temas!$AA$5:$AA$40,Temas!$C$5:$C$40,"E3 Água e recursos marinhos"),"—") -> 3
A54: E4 Biodiversidade e ecossistemas | B54: =COUNTIFS(Temas!$C$5:$C$40,"E4 Biodiversidade e ecossistemas") -> 1 | C54: =COUNTIFS(Temas!$C$5:$C$40,"E4 Biodiversidade e ecossistemas",Temas!$T$5:$T$40,"<>Não material") -> 1 | D54: =COUNTIFS(Temas!$C$5:$C$40,"E4 Biodiversidade e ecossistemas",Temas!$T$5:$T$40,"Dupla materialidade") -> 0 | E54: =_xlfn.MAXIFS(Temas!$P$5:$P$40,Temas!$C$5:$C$40,"E4 Biodiversidade e ecossistemas") -> 14 | F54: =_xlfn.MAXIFS(Temas!$Q$5:$Q$40,Temas!$C$5:$C$40,"E4 Biodiversidade e ecossistemas") -> 0 | G54: =SUMIFS(Temas!$M$5:$M$40,Temas!$C$5:$C$40,"E4 Biodiversidade e ecossistemas") -> 2 | H54: =SUMIFS(Temas!$Y$5:$Y$40,Temas!$C$5:$C$40,"E4 Biodiversidade e ecossistemas") -> 0 | I54: =SUMIFS(Temas!$Z$5:$Z$40,Temas!$C$5:$C$40,"E4 Biodiversidade e ecossistemas") -> 0 | J54: =IFERROR(AVERAGEIFS(Temas!$AA$5:$AA$40,Temas!$C$5:$C$40,"E4 Biodiversidade e ecossistemas"),"—") -> —
A55: E5 Uso de recursos e economia circular | B55: =COUNTIFS(Temas!$C$5:$C$40,"E5 Uso de recursos e economia circular") -> 3 | C55: =COUNTIFS(Temas!$C$5:$C$40,"E5 Uso de recursos e economia circular",Temas!$T$5:$T$40,"<>Não material") -> 2 | D55: =COUNTIFS(Temas!$C$5:$C$40,"E5 Uso de recursos e economia circular",Temas!$T$5:$T$40,"Dupla materialidade") -> 2 | E55: =_xlfn.MAXIFS(Temas!$P$5:$P$40,Temas!$C$5:$C$40,"E5 Uso de recursos e economia circular") -> 18.4 | F55: =_xlfn.MAXIFS(Temas!$Q$5:$Q$40,Temas!$C$5:$C$40,"E5 Uso de recursos e economia circular") -> 20 | G55: =SUMIFS(Temas!$M$5:$M$40,Temas!$C$5:$C$40,"E5 Uso de recursos e economia circular") -> 10 | H55: =SUMIFS(Temas!$Y$5:$Y$40,Temas!$C$5:$C$40,"E5 Uso de recursos e economia circular") -> 292000 | I55: =SUMIFS(Temas!$Z$5:$Z$40,Temas!$C$5:$C$40,"E5 Uso de recursos e economia circular") -> 93000 | J55: =IFERROR(AVERAGEIFS(Temas!$AA$5:$AA$40,Temas!$C$5:$C$40,"E5 Uso de recursos e economia circular"),"—") -> 4.2233333
A56: S1 Trabalhadores próprios | B56: =COUNTIFS(Temas!$C$5:$C$40,"S1 Trabalhadores próprios") -> 4 | C56: =COUNTIFS(Temas!$C$5:$C$40,"S1 Trabalhadores próprios",Temas!$T$5:$T$40,"<>Não material") -> 2 | D56: =COUNTIFS(Temas!$C$5:$C$40,"S1 Trabalhadores próprios",Temas!$T$5:$T$40,"Dupla materialidade") -> 0 | E56: =_xlfn.MAXIFS(Temas!$P$5:$P$40,Temas!$C$5:$C$40,"S1 Trabalhadores próprios") -> 20 | F56: =_xlfn.MAXIFS(Temas!$Q$5:$Q$40,Temas!$C$5:$C$40,"S1 Trabalhadores próprios") -> 16 | G56: =SUMIFS(Temas!$M$5:$M$40,Temas!$C$5:$C$40,"S1 Trabalhadores próprios") -> 8 | H56: =SUMIFS(Temas!$Y$5:$Y$40,Temas!$C$5:$C$40,"S1 Trabalhadores próprios") -> 113500 | I56: =SUMIFS(Temas!$Z$5:$Z$40,Temas!$C$5:$C$40,"S1 Trabalhadores próprios") -> 16000 | J56: =IFERROR(AVERAGEIFS(Temas!$AA$5:$AA$40,Temas!$C$5:$C$40,"S1 Trabalhadores próprios"),"—") -> 3.625
A57: S2 Trabalhadores da cadeia de valor | B57: =COUNTIFS(Temas!$C$5:$C$40,"S2 Trabalhadores da cadeia de valor") -> 1 | C57: =COUNTIFS(Temas!$C$5:$C$40,"S2 Trabalhadores da cadeia de valor",Temas!$T$5:$T$40,"<>Não material") -> 0 | D57: =COUNTIFS(Temas!$C$5:$C$40,"S2 Trabalhadores da cadeia de valor",Temas!$T$5:$T$40,"Dupla materialidade") -> 0 | E57: =_xlfn.MAXIFS(Temas!$P$5:$P$40,Temas!$C$5:$C$40,"S2 Trabalhadores da cadeia de valor") -> 6.7 | F57: =_xlfn.MAXIFS(Temas!$Q$5:$Q$40,Temas!$C$5:$C$40,"S2 Trabalhadores da cadeia de valor") -> 0 | G57: =SUMIFS(Temas!$M$5:$M$40,Temas!$C$5:$C$40,"S2 Trabalhadores da cadeia de valor") -> 1 | H57: =SUMIFS(Temas!$Y$5:$Y$40,Temas!$C$5:$C$40,"S2 Trabalhadores da cadeia de valor") -> 0 | I57: =SUMIFS(Temas!$Z$5:$Z$40,Temas!$C$5:$C$40,"S2 Trabalhadores da cadeia de valor") -> 0 | J57: =IFERROR(AVERAGEIFS(Temas!$AA$5:$AA$40,Temas!$C$5:$C$40,"S2 Trabalhadores da cadeia de valor"),"—") -> 3
A58: S3 Comunidades afetadas | B58: =COUNTIFS(Temas!$C$5:$C$40,"S3 Comunidades afetadas") -> 1 | C58: =COUNTIFS(Temas!$C$5:$C$40,"S3 Comunidades afetadas",Temas!$T$5:$T$40,"<>Não material") -> 1 | D58: =COUNTIFS(Temas!$C$5:$C$40,"S3 Comunidades afetadas",Temas!$T$5:$T$40,"Dupla materialidade") -> 0 | E58: =_xlfn.MAXIFS(Temas!$P$5:$P$40,Temas!$C$5:$C$40,"S3 Comunidades afetadas") -> 12.5 | F58: =_xlfn.MAXIFS(Temas!$Q$5:$Q$40,Temas!$C$5:$C$40,"S3 Comunidades afetadas") -> 0 | G58: =SUMIFS(Temas!$M$5:$M$40,Temas!$C$5:$C$40,"S3 Comunidades afetadas") -> 3 | H58: =SUMIFS(Temas!$Y$5:$Y$40,Temas!$C$5:$C$40,"S3 Comunidades afetadas") -> 0 | I58: =SUMIFS(Temas!$Z$5:$Z$40,Temas!$C$5:$C$40,"S3 Comunidades afetadas") -> 0 | J58: =IFERROR(AVERAGEIFS(Temas!$AA$5:$AA$40,Temas!$C$5:$C$40,"S3 Comunidades afetadas"),"—") -> 4
A59: S4 Consumidores e utilizadores finais | B59: =COUNTIFS(Temas!$C$5:$C$40,"S4 Consumidores e utilizadores finais") -> 2 | C59: =COUNTIFS(Temas!$C$5:$C$40,"S4 Consumidores e utilizadores finais",Temas!$T$5:$T$40,"<>Não material") -> 1 | D59: =COUNTIFS(Temas!$C$5:$C$40,"S4 Consumidores e utilizadores finais",Temas!$T$5:$T$40,"Dupla materialidade") -> 1 | E59: =_xlfn.MAXIFS(Temas!$P$5:$P$40,Temas!$C$5:$C$40,"S4 Consumidores e utilizadores finais") -> 20 | F59: =_xlfn.MAXIFS(Temas!$Q$5:$Q$40,Temas!$C$5:$C$40,"S4 Consumidores e utilizadores finais") -> 15 | G59: =SUMIFS(Temas!$M$5:$M$40,Temas!$C$5:$C$40,"S4 Consumidores e utilizadores finais") -> 4 | H59: =SUMIFS(Temas!$Y$5:$Y$40,Temas!$C$5:$C$40,"S4 Consumidores e utilizadores finais") -> 140000 | I59: =SUMIFS(Temas!$Z$5:$Z$40,Temas!$C$5:$C$40,"S4 Consumidores e utilizadores finais") -> 0 | J59: =IFERROR(AVERAGEIFS(Temas!$AA$5:$AA$40,Temas!$C$5:$C$40,"S4 Consumidores e utilizadores finais"),"—") -> 4.5
A60: G1 Conduta empresarial | B60: =COUNTIFS(Temas!$C$5:$C$40,"G1 Conduta empresarial") -> 2 | C60: =COUNTIFS(Temas!$C$5:$C$40,"G1 Conduta empresarial",Temas!$T$5:$T$40,"<>Não material") -> 2 | D60: =COUNTIFS(Temas!$C$5:$C$40,"G1 Conduta empresarial",Temas!$T$5:$T$40,"Dupla materialidade") -> 0 | E60: =_xlfn.MAXIFS(Temas!$P$5:$P$40,Temas!$C$5:$C$40,"G1 Conduta empresarial") -> 7.5 | F60: =_xlfn.MAXIFS(Temas!$Q$5:$Q$40,Temas!$C$5:$C$40,"G1 Conduta empresarial") -> 12 | G60: =SUMIFS(Temas!$M$5:$M$40,Temas!$C$5:$C$40,"G1 Conduta empresarial") -> 4 | H60: =SUMIFS(Temas!$Y$5:$Y$40,Temas!$C$5:$C$40,"G1 Conduta empresarial") -> 88000 | I60: =SUMIFS(Temas!$Z$5:$Z$40,Temas!$C$5:$C$40,"G1 Conduta empresarial") -> 0 | J60: =IFERROR(AVERAGEIFS(Temas!$AA$5:$AA$40,Temas!$C$5:$C$40,"G1 Conduta empresarial"),"—") -> 3.5
A61: Específico da entidade | B61: =COUNTIFS(Temas!$C$5:$C$40,"Específico da entidade") -> 2 | C61: =COUNTIFS(Temas!$C$5:$C$40,"Específico da entidade",Temas!$T$5:$T$40,"<>Não material") -> 2 | D61: =COUNTIFS(Temas!$C$5:$C$40,"Específico da entidade",Temas!$T$5:$T$40,"Dupla materialidade") -> 0 | E61: =_xlfn.MAXIFS(Temas!$P$5:$P$40,Temas!$C$5:$C$40,"Específico da entidade") -> 10 | F61: =_xlfn.MAXIFS(Temas!$Q$5:$Q$40,Temas!$C$5:$C$40,"Específico da entidade") -> 20 | G61: =SUMIFS(Temas!$M$5:$M$40,Temas!$C$5:$C$40,"Específico da entidade") -> 4 | H61: =SUMIFS(Temas!$Y$5:$Y$40,Temas!$C$5:$C$40,"Específico da entidade") -> 174000 | I61: =SUMIFS(Temas!$Z$5:$Z$40,Temas!$C$5:$C$40,"Específico da entidade") -> 32500 | J61: =IFERROR(AVERAGEIFS(Temas!$AA$5:$AA$40,Temas!$C$5:$C$40,"Específico da entidade"),"—") -> 4.5
A62: Total | B62: =SUM(B51:B61) -> 24 | C62: =SUM(C51:C61) -> 16 | D62: =SUM(D51:D61) -> 6 | G62: =SUM(G51:G61) -> 57 | H62: =SUM(H51:H61) -> 1125250 | I62: =SUM(I51:I61) -> 262250
A64: TOP 15 TEMAS POR PRIORIDADE (impacto máx. + financeiro máx.; sem filtros)
A65: Tema | B65: ID | C65: Tópico ESRS | D65: Pilar | E65: Impacto máx. | F65: Financeiro máx. | G65: Classificação | H65: Relevância p/ partes | I65: Exposição a riscos (€/ano) | J65: Alerta de consistência
A66: =IFERROR(1&". "&INDEX(Temas!$E$5:$E$40,MATCH(1,Temas!$X$5:$X$40,0)),"") -> 1. Reciclabilidade e conformidade PPWR das embalagens | B66: =IFERROR(INDEX(Temas!$A$5:$A$40,MATCH(1,Temas!$X$5:$X$40,0))&"","") -> DM-11 | C66: =IFERROR(INDEX(Temas!$C$5:$C$40,MATCH(1,Temas!$X$5:$X$40,0))&"","") -> E5 Uso de recursos e economia circular | D66: =IFERROR(INDEX(Temas!$B$5:$B$40,MATCH(1,Temas!$X$5:$X$40,0))&"","") -> Ambiental | E66: =IFERROR(INDEX(Temas!$P$5:$P$40,MATCH(1,Temas!$X$5:$X$40,0)),"") -> 16.7 | F66: =IFERROR(INDEX(Temas!$Q$5:$Q$40,MATCH(1,Temas!$X$5:$X$40,0)),"") -> 20 | G66: =IFERROR(INDEX(Temas!$T$5:$T$40,MATCH(1,Temas!$X$5:$X$40,0))&"","") -> Dupla materialidade | H66: =IFERROR(INDEX(Temas!$AA$5:$AA$40,MATCH(1,Temas!$X$5:$X$40,0)),"") -> 4.67 | I66: =IFERROR(INDEX(Temas!$Y$5:$Y$40,MATCH(1,Temas!$X$5:$X$40,0)),"") -> 227500 | J66: =IFERROR(INDEX(Temas!$AD$5:$AD$40,MATCH(1,Temas!$X$5:$X$40,0))&"","") -> OK
A67: =IFERROR(2&". "&INDEX(Temas!$E$5:$E$40,MATCH(2,Temas!$X$5:$X$40,0)),"") -> 2. Segurança do produto (contacto alimentar, farmacêutico e cosmético) | B67: =IFERROR(INDEX(Temas!$A$5:$A$40,MATCH(2,Temas!$X$5:$X$40,0))&"","") -> DM-19 | C67: =IFERROR(INDEX(Temas!$C$5:$C$40,MATCH(2,Temas!$X$5:$X$40,0))&"","") -> S4 Consumidores e utilizadores finais | D67: =IFERROR(INDEX(Temas!$B$5:$B$40,MATCH(2,Temas!$X$5:$X$40,0))&"","") -> Social | E67: =IFERROR(INDEX(Temas!$P$5:$P$40,MATCH(2,Temas!$X$5:$X$40,0)),"") -> 20 | F67: =IFERROR(INDEX(Temas!$Q$5:$Q$40,MATCH(2,Temas!$X$5:$X$40,0)),"") -> 15 | G67: =IFERROR(INDEX(Temas!$T$5:$T$40,MATCH(2,Temas!$X$5:$X$40,0))&"","") -> Dupla materialidade | H67: =IFERROR(INDEX(Temas!$AA$5:$AA$40,MATCH(2,Temas!$X$5:$X$40,0)),"") -> 5 | I67: =IFERROR(INDEX(Temas!$Y$5:$Y$40,MATCH(2,Temas!$X$5:$X$40,0)),"") -> 120000 | J67: =IFERROR(INDEX(Temas!$AD$5:$AD$40,MATCH(2,Temas!$X$5:$X$40,0))&"","") -> OK
A68: =IFERROR(3&". "&INDEX(Temas!$E$5:$E$40,MATCH(3,Temas!$X$5:$X$40,0)),"") -> 3. Emissões de GEE (âmbitos 1, 2 e 3) | B68: =IFERROR(INDEX(Temas!$A$5:$A$40,MATCH(3,Temas!$X$5:$X$40,0))&"","") -> DM-01 | C68: =IFERROR(INDEX(Temas!$C$5:$C$40,MATCH(3,Temas!$X$5:$X$40,0))&"","") -> E1 Alterações climáticas | D68: =IFERROR(INDEX(Temas!$B$5:$B$40,MATCH(3,Temas!$X$5:$X$40,0))&"","") -> Ambiental | E68: =IFERROR(INDEX(Temas!$P$5:$P$40,MATCH(3,Temas!$X$5:$X$40,0)),"") -> 20 | F68: =IFERROR(INDEX(Temas!$Q$5:$Q$40,MATCH(3,Temas!$X$5:$X$40,0)),"") -> 12 | G68: =IFERROR(INDEX(Temas!$T$5:$T$40,MATCH(3,Temas!$X$5:$X$40,0))&"","") -> Dupla materialidade | H68: =IFERROR(INDEX(Temas!$AA$5:$AA$40,MATCH(3,Temas!$X$5:$X$40,0)),"") -> 4 | I68: =IFERROR(INDEX(Temas!$Y$5:$Y$40,MATCH(3,Temas!$X$5:$X$40,0)),"") -> 60000 | J68: =IFERROR(INDEX(Temas!$AD$5:$AD$40,MATCH(3,Temas!$X$5:$X$40,0))&"","") -> OK
A69: =IFERROR(4&". "&INDEX(Temas!$E$5:$E$40,MATCH(4,Temas!$X$5:$X$40,0)),"") -> 4. Consumo e eficiência energética | B69: =IFERROR(INDEX(Temas!$A$5:$A$40,MATCH(4,Temas!$X$5:$X$40,0))&"","") -> DM-02 | C69: =IFERROR(INDEX(Temas!$C$5:$C$40,MATCH(4,Temas!$X$5:$X$40,0))&"","") -> E1 Alterações climáticas | D69: =IFERROR(INDEX(Temas!$B$5:$B$40,MATCH(4,Temas!$X$5:$X$40,0))&"","") -> Ambiental | E69: =IFERROR(INDEX(Temas!$P$5:$P$40,MATCH(4,Temas!$X$5:$X$40,0)),"") -> 15 | F69: =IFERROR(INDEX(Temas!$Q$5:$Q$40,MATCH(4,Temas!$X$5:$X$40,0)),"") -> 16 | G69: =IFERROR(INDEX(Temas!$T$5:$T$40,MATCH(4,Temas!$X$5:$X$40,0))&"","") -> Dupla materialidade | H69: =IFERROR(INDEX(Temas!$AA$5:$AA$40,MATCH(4,Temas!$X$5:$X$40,0)),"") -> 4.5 | I69: =IFERROR(INDEX(Temas!$Y$5:$Y$40,MATCH(4,Temas!$X$5:$X$40,0)),"") -> 139750 | J69: =IFERROR(INDEX(Temas!$AD$5:$AD$40,MATCH(4,Temas!$X$5:$X$40,0))&"","") -> OK
A70: =IFERROR(5&". "&INDEX(Temas!$E$5:$E$40,MATCH(5,Temas!$X$5:$X$40,0)),"") -> 5. Perdas de granulado de plástico | B70: =IFERROR(INDEX(Temas!$A$5:$A$40,MATCH(5,Temas!$X$5:$X$40,0))&"","") -> DM-06 | C70: =IFERROR(INDEX(Temas!$C$5:$C$40,MATCH(5,Temas!$X$5:$X$40,0))&"","") -> E2 Poluição | D70: =IFERROR(INDEX(Temas!$B$5:$B$40,MATCH(5,Temas!$X$5:$X$40,0))&"","") -> Ambiental | E70: =IFERROR(INDEX(Temas!$P$5:$P$40,MATCH(5,Temas!$X$5:$X$40,0)),"") -> 18.4 | F70: =IFERROR(INDEX(Temas!$Q$5:$Q$40,MATCH(5,Temas!$X$5:$X$40,0)),"") -> 12 | G70: =IFERROR(INDEX(Temas!$T$5:$T$40,MATCH(5,Temas!$X$5:$X$40,0))&"","") -> Dupla materialidade | H70: =IFERROR(INDEX(Temas!$AA$5:$AA$40,MATCH(5,Temas!$X$5:$X$40,0)),"") -> 3.5 | I70: =IFERROR(INDEX(Temas!$Y$5:$Y$40,MATCH(5,Temas!$X$5:$X$40,0)),"") -> 19500 | J70: =IFERROR(INDEX(Temas!$AD$5:$AD$40,MATCH(5,Temas!$X$5:$X$40,0))&"","") -> OK
A71: =IFERROR(6&". "&INDEX(Temas!$E$5:$E$40,MATCH(6,Temas!$X$5:$X$40,0)),"") -> 6. Polímeros virgens e conteúdo reciclado | B71: =IFERROR(INDEX(Temas!$A$5:$A$40,MATCH(6,Temas!$X$5:$X$40,0))&"","") -> DM-10 | C71: =IFERROR(INDEX(Temas!$C$5:$C$40,MATCH(6,Temas!$X$5:$X$40,0))&"","") -> E5 Uso de recursos e economia circular | D71: =IFERROR(INDEX(Temas!$B$5:$B$40,MATCH(6,Temas!$X$5:$X$40,0))&"","") -> Ambiental | E71: =IFERROR(INDEX(Temas!$P$5:$P$40,MATCH(6,Temas!$X$5:$X$40,0)),"") -> 18.4 | F71: =IFERROR(INDEX(Temas!$Q$5:$Q$40,MATCH(6,Temas!$X$5:$X$40,0)),"") -> 12 | G71: =IFERROR(INDEX(Temas!$T$5:$T$40,MATCH(6,Temas!$X$5:$X$40,0))&"","") -> Dupla materialidade | H71: =IFERROR(INDEX(Temas!$AA$5:$AA$40,MATCH(6,Temas!$X$5:$X$40,0)),"") -> 4.5 | I71: =IFERROR(INDEX(Temas!$Y$5:$Y$40,MATCH(6,Temas!$X$5:$X$40,0)),"") -> 58500 | J71: =IFERROR(INDEX(Temas!$AD$5:$AD$40,MATCH(6,Temas!$X$5:$X$40,0))&"","") -> OK
A72: =IFERROR(7&". "&INDEX(Temas!$E$5:$E$40,MATCH(7,Temas!$X$5:$X$40,0)),"") -> 7. Qualidade do produto e custo da não-qualidade | B72: =IFERROR(INDEX(Temas!$A$5:$A$40,MATCH(7,Temas!$X$5:$X$40,0))&"","") -> DM-23 | C72: =IFERROR(INDEX(Temas!$C$5:$C$40,MATCH(7,Temas!$X$5:$X$40,0))&"","") -> Específico da entidade | D72: =IFERROR(INDEX(Temas!$B$5:$B$40,MATCH(7,Temas!$X$5:$X$40,0))&"","") -> Governança | E72: =IFERROR(INDEX(Temas!$P$5:$P$40,MATCH(7,Temas!$X$5:$X$40,0)),"") -> 10 | F72: =IFERROR(INDEX(Temas!$Q$5:$Q$40,MATCH(7,Temas!$X$5:$X$40,0)),"") -> 20 | G72: =IFERROR(INDEX(Temas!$T$5:$T$40,MATCH(7,Temas!$X$5:$X$40,0))&"","") -> Material — financeira | H72: =IFERROR(INDEX(Temas!$AA$5:$AA$40,MATCH(7,Temas!$X$5:$X$40,0)),"") -> 5 | I72: =IFERROR(INDEX(Temas!$Y$5:$Y$40,MATCH(7,Temas!$X$5:$X$40,0)),"") -> 162000 | J72: =IFERROR(INDEX(Temas!$AD$5:$AD$40,MATCH(7,Temas!$X$5:$X$40,0))&"","") -> OK
A73: =IFERROR(8&". "&INDEX(Temas!$E$5:$E$40,MATCH(8,Temas!$X$5:$X$40,0)),"") -> 8. Condições de trabalho e disponibilidade de pessoas | B73: =IFERROR(INDEX(Temas!$A$5:$A$40,MATCH(8,Temas!$X$5:$X$40,0))&"","") -> DM-14 | C73: =IFERROR(INDEX(Temas!$C$5:$C$40,MATCH(8,Temas!$X$5:$X$40,0))&"","") -> S1 Trabalhadores próprios | D73: =IFERROR(INDEX(Temas!$B$5:$B$40,MATCH(8,Temas!$X$5:$X$40,0))&"","") -> Social | E73: =IFERROR(INDEX(Temas!$P$5:$P$40,MATCH(8,Temas!$X$5:$X$40,0)),"") -> 11.7 | F73: =IFERROR(INDEX(Temas!$Q$5:$Q$40,MATCH(8,Temas!$X$5:$X$40,0)),"") -> 16 | G73: =IFERROR(INDEX(Temas!$T$5:$T$40,MATCH(8,Temas!$X$5:$X$40,0))&"","") -> Material — financeira | H73: =IFERROR(INDEX(Temas!$AA$5:$AA$40,MATCH(8,Temas!$X$5:$X$40,0)),"") -> 4 | I73: =IFERROR(INDEX(Temas!$Y$5:$Y$40,MATCH(8,Temas!$X$5:$X$40,0)),"") -> 97500 | J73: =IFERROR(INDEX(Temas!$AD$5:$AD$40,MATCH(8,Temas!$X$5:$X$40,0))&"","") -> OK
A74: =IFERROR(9&". "&INDEX(Temas!$E$5:$E$40,MATCH(9,Temas!$X$5:$X$40,0)),"") -> 9. Saúde e segurança no trabalho | B74: =IFERROR(INDEX(Temas!$A$5:$A$40,MATCH(9,Temas!$X$5:$X$40,0))&"","") -> DM-13 | C74: =IFERROR(INDEX(Temas!$C$5:$C$40,MATCH(9,Temas!$X$5:$X$40,0))&"","") -> S1 Trabalhadores próprios | D74: =IFERROR(INDEX(Temas!$B$5:$B$40,MATCH(9,Temas!$X$5:$X$40,0))&"","") -> Social | E74: =IFERROR(INDEX(Temas!$P$5:$P$40,MATCH(9,Temas!$X$5:$X$40,0)),"") -> 20 | F74: =IFERROR(INDEX(Temas!$Q$5:$Q$40,MATCH(9,Temas!$X$5:$X$40,0)),"") -> 6 | G74: =IFERROR(INDEX(Temas!$T$5:$T$40,MATCH(9,Temas!$X$5:$X$40,0))&"","") -> Material — impacto | H74: =IFERROR(INDEX(Temas!$AA$5:$AA$40,MATCH(9,Temas!$X$5:$X$40,0)),"") -> 4.5 | I74: =IFERROR(INDEX(Temas!$Y$5:$Y$40,MATCH(9,Temas!$X$5:$X$40,0)),"") -> 16000 | J74: =IFERROR(INDEX(Temas!$AD$5:$AD$40,MATCH(9,Temas!$X$5:$X$40,0))&"","") -> OK
A75: =IFERROR(10&". "&INDEX(Temas!$E$5:$E$40,MATCH(10,Temas!$X$5:$X$40,0)),"") -> 10. Gestão e avaliação de fornecedores | B75: =IFERROR(INDEX(Temas!$A$5:$A$40,MATCH(10,Temas!$X$5:$X$40,0))&"","") -> DM-22 | C75: =IFERROR(INDEX(Temas!$C$5:$C$40,MATCH(10,Temas!$X$5:$X$40,0))&"","") -> G1 Conduta empresarial | D75: =IFERROR(INDEX(Temas!$B$5:$B$40,MATCH(10,Temas!$X$5:$X$40,0))&"","") -> Governança | E75: =IFERROR(INDEX(Temas!$P$5:$P$40,MATCH(10,Temas!$X$5:$X$40,0)),"") -> 7.5 | F75: =IFERROR(INDEX(Temas!$Q$5:$Q$40,MATCH(10,Temas!$X$5:$X$40,0)),"") -> 12 | G75: =IFERROR(INDEX(Temas!$T$5:$T$40,MATCH(10,Temas!$X$5:$X$40,0))&"","") -> Material — financeira | H75: =IFERROR(INDEX(Temas!$AA$5:$AA$40,MATCH(10,Temas!$X$5:$X$40,0)),"") -> 3 | I75: =IFERROR(INDEX(Temas!$Y$5:$Y$40,MATCH(10,Temas!$X$5:$X$40,0)),"") -> 40000 | J75: =IFERROR(INDEX(Temas!$AD$5:$AD$40,MATCH(10,Temas!$X$5:$X$40,0))&"","") -> OK
A76: =IFERROR(11&". "&INDEX(Temas!$E$5:$E$40,MATCH(11,Temas!$X$5:$X$40,0)),"") -> 11. Formação e competências | B76: =IFERROR(INDEX(Temas!$A$5:$A$40,MATCH(11,Temas!$X$5:$X$40,0))&"","") -> DM-15 | C76: =IFERROR(INDEX(Temas!$C$5:$C$40,MATCH(11,Temas!$X$5:$X$40,0))&"","") -> S1 Trabalhadores próprios | D76: =IFERROR(INDEX(Temas!$B$5:$B$40,MATCH(11,Temas!$X$5:$X$40,0))&"","") -> Social | E76: =IFERROR(INDEX(Temas!$P$5:$P$40,MATCH(11,Temas!$X$5:$X$40,0)),"") -> 10 | F76: =IFERROR(INDEX(Temas!$Q$5:$Q$40,MATCH(11,Temas!$X$5:$X$40,0)),"") -> 9 | G76: =IFERROR(INDEX(Temas!$T$5:$T$40,MATCH(11,Temas!$X$5:$X$40,0))&"","") -> Não material | H76: =IFERROR(INDEX(Temas!$AA$5:$AA$40,MATCH(11,Temas!$X$5:$X$40,0)),"") -> 4 | I76: =IFERROR(INDEX(Temas!$Y$5:$Y$40,MATCH(11,Temas!$X$5:$X$40,0)),"") -> 0 | J76: =IFERROR(INDEX(Temas!$AD$5:$AD$40,MATCH(11,Temas!$X$5:$X$40,0))&"","") -> Rever: relevância alta para as partes interessadas
A77: =IFERROR(12&". "&INDEX(Temas!$E$5:$E$40,MATCH(12,Temas!$X$5:$X$40,0)),"") -> 12. Resíduos da produção | B77: =IFERROR(INDEX(Temas!$A$5:$A$40,MATCH(12,Temas!$X$5:$X$40,0))&"","") -> DM-12 | C77: =IFERROR(INDEX(Temas!$C$5:$C$40,MATCH(12,Temas!$X$5:$X$40,0))&"","") -> E5 Uso de recursos e economia circular | D77: =IFERROR(INDEX(Temas!$B$5:$B$40,MATCH(12,Temas!$X$5:$X$40,0))&"","") -> Ambiental | E77: =IFERROR(INDEX(Temas!$P$5:$P$40,MATCH(12,Temas!$X$5:$X$40,0)),"") -> 10 | F77: =IFERROR(INDEX(Temas!$Q$5:$Q$40,MATCH(12,Temas!$X$5:$X$40,0)),"") -> 8 | G77: =IFERROR(INDEX(Temas!$T$5:$T$40,MATCH(12,Temas!$X$5:$X$40,0))&"","") -> Não material | H77: =IFERROR(INDEX(Temas!$AA$5:$AA$40,MATCH(12,Temas!$X$5:$X$40,0)),"") -> 3.5 | I77: =IFERROR(INDEX(Temas!$Y$5:$Y$40,MATCH(12,Temas!$X$5:$X$40,0)),"") -> 6000 | J77: =IFERROR(INDEX(Temas!$AD$5:$AD$40,MATCH(12,Temas!$X$5:$X$40,0))&"","") -> OK
A78: =IFERROR(13&". "&INDEX(Temas!$E$5:$E$40,MATCH(13,Temas!$X$5:$X$40,0)),"") -> 13. Consumo de água | B78: =IFERROR(INDEX(Temas!$A$5:$A$40,MATCH(13,Temas!$X$5:$X$40,0))&"","") -> DM-08 | C78: =IFERROR(INDEX(Temas!$C$5:$C$40,MATCH(13,Temas!$X$5:$X$40,0))&"","") -> E3 Água e recursos marinhos | D78: =IFERROR(INDEX(Temas!$B$5:$B$40,MATCH(13,Temas!$X$5:$X$40,0))&"","") -> Ambiental | E78: =IFERROR(INDEX(Temas!$P$5:$P$40,MATCH(13,Temas!$X$5:$X$40,0)),"") -> 11.7 | F78: =IFERROR(INDEX(Temas!$Q$5:$Q$40,MATCH(13,Temas!$X$5:$X$40,0)),"") -> 6 | G78: =IFERROR(INDEX(Temas!$T$5:$T$40,MATCH(13,Temas!$X$5:$X$40,0))&"","") -> Não material | H78: =IFERROR(INDEX(Temas!$AA$5:$AA$40,MATCH(13,Temas!$X$5:$X$40,0)),"") -> 3 | I78: =IFERROR(INDEX(Temas!$Y$5:$Y$40,MATCH(13,Temas!$X$5:$X$40,0)),"") -> 8000 | J78: =IFERROR(INDEX(Temas!$AD$5:$AD$40,MATCH(13,Temas!$X$5:$X$40,0))&"","") -> OK
A79: =IFERROR(14&". "&INDEX(Temas!$E$5:$E$40,MATCH(14,Temas!$X$5:$X$40,0)),"") -> 14. Emissões de COV da serigrafia | B79: =IFERROR(INDEX(Temas!$A$5:$A$40,MATCH(14,Temas!$X$5:$X$40,0))&"","") -> DM-04 | C79: =IFERROR(INDEX(Temas!$C$5:$C$40,MATCH(14,Temas!$X$5:$X$40,0))&"","") -> E2 Poluição | D79: =IFERROR(INDEX(Temas!$B$5:$B$40,MATCH(14,Temas!$X$5:$X$40,0))&"","") -> Ambiental | E79: =IFERROR(INDEX(Temas!$P$5:$P$40,MATCH(14,Temas!$X$5:$X$40,0)),"") -> 13.4 | F79: =IFERROR(INDEX(Temas!$Q$5:$Q$40,MATCH(14,Temas!$X$5:$X$40,0)),"") -> 4 | G79: =IFERROR(INDEX(Temas!$T$5:$T$40,MATCH(14,Temas!$X$5:$X$40,0))&"","") -> Material — impacto | H79: =IFERROR(INDEX(Temas!$AA$5:$AA$40,MATCH(14,Temas!$X$5:$X$40,0)),"") -> 3 | I79: =IFERROR(INDEX(Temas!$Y$5:$Y$40,MATCH(14,Temas!$X$5:$X$40,0)),"") -> 3000 | J79: =IFERROR(INDEX(Temas!$AD$5:$AD$40,MATCH(14,Temas!$X$5:$X$40,0))&"","") -> OK
A80: =IFERROR(15&". "&INDEX(Temas!$E$5:$E$40,MATCH(15,Temas!$X$5:$X$40,0)),"") -> 15. Substâncias perigosas em tintas e aditivos | B80: =IFERROR(INDEX(Temas!$A$5:$A$40,MATCH(15,Temas!$X$5:$X$40,0))&"","") -> DM-07 | C80: =IFERROR(INDEX(Temas!$C$5:$C$40,MATCH(15,Temas!$X$5:$X$40,0))&"","") -> E2 Poluição | D80: =IFERROR(INDEX(Temas!$B$5:$B$40,MATCH(15,Temas!$X$5:$X$40,0))&"","") -> Ambiental | E80: =IFERROR(INDEX(Temas!$P$5:$P$40,MATCH(15,Temas!$X$5:$X$40,0)),"") -> 8 | F80: =IFERROR(INDEX(Temas!$Q$5:$Q$40,MATCH(15,Temas!$X$5:$X$40,0)),"") -> 9 | G80: =IFERROR(INDEX(Temas!$T$5:$T$40,MATCH(15,Temas!$X$5:$X$40,0))&"","") -> Não material | H80: =IFERROR(INDEX(Temas!$AA$5:$AA$40,MATCH(15,Temas!$X$5:$X$40,0)),"") | I80: =IFERROR(INDEX(Temas!$Y$5:$Y$40,MATCH(15,Temas!$X$5:$X$40,0)),"") -> 16000 | J80: =IFERROR(INDEX(Temas!$AD$5:$AD$40,MATCH(15,Temas!$X$5:$X$40,0))&"","") -> OK
A82: IRO MATERIAIS POR ETAPA DA CADEIA DE VALOR × HORIZONTE (filtros Pilar, Tópico e Tipo)
A83: Etapa da cadeia de valor | B83: Curto prazo (≤ 1 ano) | C83: Médio prazo (1–5 anos) | D83: Longo prazo (> 5 anos) | E83: IRO materiais | F83: IRO avaliados | G83: % materiais
A84: Upstream — fornecedores | B84: =COUNTIFS(IRO!$D$5:$D$91,$A$7,IRO!$E$5:$E$91,$B$7,IRO!$F$5:$F$91,$E$7,IRO!$J$5:$J$91,$A84,IRO!$K$5:$K$91,"Curto prazo (≤ 1 ano)",IRO!$AC$5:$AC$91,"Sim") -> 3 | C84: =COUNTIFS(IRO!$D$5:$D$91,$A$7,IRO!$E$5:$E$91,$B$7,IRO!$F$5:$F$91,$E$7,IRO!$J$5:$J$91,$A84,IRO!$K$5:$K$91,"Médio prazo (1–5 anos)",IRO!$AC$5:$AC$91,"Sim") -> 1 | D84: =COUNTIFS(IRO!$D$5:$D$91,$A$7,IRO!$E$5:$E$91,$B$7,IRO!$F$5:$F$91,$E$7,IRO!$J$5:$J$91,$A84,IRO!$K$5:$K$91,"Longo prazo (> 5 anos)",IRO!$AC$5:$AC$91,"Sim") -> 0 | E84: =SUM(B84:D84) -> 4 | F84: =COUNTIFS(IRO!$D$5:$D$91,$A$7,IRO!$E$5:$E$91,$B$7,IRO!$F$5:$F$91,$E$7,IRO!$J$5:$J$91,$A84) -> 7 | G84: =IFERROR(E84/F84,0) -> 0.57142857
A85: Operações próprias | B85: =COUNTIFS(IRO!$D$5:$D$91,$A$7,IRO!$E$5:$E$91,$B$7,IRO!$F$5:$F$91,$E$7,IRO!$J$5:$J$91,$A85,IRO!$K$5:$K$91,"Curto prazo (≤ 1 ano)",IRO!$AC$5:$AC$91,"Sim") -> 13 | C85: =COUNTIFS(IRO!$D$5:$D$91,$A$7,IRO!$E$5:$E$91,$B$7,IRO!$F$5:$F$91,$E$7,IRO!$J$5:$J$91,$A85,IRO!$K$5:$K$91,"Médio prazo (1–5 anos)",IRO!$AC$5:$AC$91,"Sim") -> 3 | D85: =COUNTIFS(IRO!$D$5:$D$91,$A$7,IRO!$E$5:$E$91,$B$7,IRO!$F$5:$F$91,$E$7,IRO!$J$5:$J$91,$A85,IRO!$K$5:$K$91,"Longo prazo (> 5 anos)",IRO!$AC$5:$AC$91,"Sim") -> 0 | E85: =SUM(B85:D85) -> 16 | F85: =COUNTIFS(IRO!$D$5:$D$91,$A$7,IRO!$E$5:$E$91,$B$7,IRO!$F$5:$F$91,$E$7,IRO!$J$5:$J$91,$A85) -> 37 | G85: =IFERROR(E85/F85,0) -> 0.43243243
A86: Downstream — distribuição | B86: =COUNTIFS(IRO!$D$5:$D$91,$A$7,IRO!$E$5:$E$91,$B$7,IRO!$F$5:$F$91,$E$7,IRO!$J$5:$J$91,$A86,IRO!$K$5:$K$91,"Curto prazo (≤ 1 ano)",IRO!$AC$5:$AC$91,"Sim") -> 0 | C86: =COUNTIFS(IRO!$D$5:$D$91,$A$7,IRO!$E$5:$E$91,$B$7,IRO!$F$5:$F$91,$E$7,IRO!$J$5:$J$91,$A86,IRO!$K$5:$K$91,"Médio prazo (1–5 anos)",IRO!$AC$5:$AC$91,"Sim") -> 1 | D86: =COUNTIFS(IRO!$D$5:$D$91,$A$7,IRO!$E$5:$E$91,$B$7,IRO!$F$5:$F$91,$E$7,IRO!$J$5:$J$91,$A86,IRO!$K$5:$K$91,"Longo prazo (> 5 anos)",IRO!$AC$5:$AC$91,"Sim") -> 0 | E86: =SUM(B86:D86) -> 1 | F86: =COUNTIFS(IRO!$D$5:$D$91,$A$7,IRO!$E$5:$E$91,$B$7,IRO!$F$5:$F$91,$E$7,IRO!$J$5:$J$91,$A86) -> 2 | G86: =IFERROR(E86/F86,0) -> 0.5
A87: Downstream — utilização | B87: =COUNTIFS(IRO!$D$5:$D$91,$A$7,IRO!$E$5:$E$91,$B$7,IRO!$F$5:$F$91,$E$7,IRO!$J$5:$J$91,$A87,IRO!$K$5:$K$91,"Curto prazo (≤ 1 ano)",IRO!$AC$5:$AC$91,"Sim") -> 3 | C87: =COUNTIFS(IRO!$D$5:$D$91,$A$7,IRO!$E$5:$E$91,$B$7,IRO!$F$5:$F$91,$E$7,IRO!$J$5:$J$91,$A87,IRO!$K$5:$K$91,"Médio prazo (1–5 anos)",IRO!$AC$5:$AC$91,"Sim") -> 1 | D87: =COUNTIFS(IRO!$D$5:$D$91,$A$7,IRO!$E$5:$E$91,$B$7,IRO!$F$5:$F$91,$E$7,IRO!$J$5:$J$91,$A87,IRO!$K$5:$K$91,"Longo prazo (> 5 anos)",IRO!$AC$5:$AC$91,"Sim") -> 0 | E87: =SUM(B87:D87) -> 4 | F87: =COUNTIFS(IRO!$D$5:$D$91,$A$7,IRO!$E$5:$E$91,$B$7,IRO!$F$5:$F$91,$E$7,IRO!$J$5:$J$91,$A87) -> 7 | G87: =IFERROR(E87/F87,0) -> 0.57142857
A88: Downstream — fim de vida | B88: =COUNTIFS(IRO!$D$5:$D$91,$A$7,IRO!$E$5:$E$91,$B$7,IRO!$F$5:$F$91,$E$7,IRO!$J$5:$J$91,$A88,IRO!$K$5:$K$91,"Curto prazo (≤ 1 ano)",IRO!$AC$5:$AC$91,"Sim") -> 0 | C88: =COUNTIFS(IRO!$D$5:$D$91,$A$7,IRO!$E$5:$E$91,$B$7,IRO!$F$5:$F$91,$E$7,IRO!$J$5:$J$91,$A88,IRO!$K$5:$K$91,"Médio prazo (1–5 anos)",IRO!$AC$5:$AC$91,"Sim") -> 1 | D88: =COUNTIFS(IRO!$D$5:$D$91,$A$7,IRO!$E$5:$E$91,$B$7,IRO!$F$5:$F$91,$E$7,IRO!$J$5:$J$91,$A88,IRO!$K$5:$K$91,"Longo prazo (> 5 anos)",IRO!$AC$5:$AC$91,"Sim") -> 1 | E88: =SUM(B88:D88) -> 2 | F88: =COUNTIFS(IRO!$D$5:$D$91,$A$7,IRO!$E$5:$E$91,$B$7,IRO!$F$5:$F$91,$E$7,IRO!$J$5:$J$91,$A88) -> 4 | G88: =IFERROR(E88/F88,0) -> 0.5
A91: ANÁLISE DINÂMICA — tabela dinâmica de tbl_dma_iro com segmentações de dados (clique nos botões para filtrar)
A92: Criada no pós-processamento do Excel; se não aparecer, execute: python build_17_dupla_materialidade.py <ficheiro>.
C94: Classificacao_IRO | D94: Valores
C95: Material — financeiro | E95: Material — impacto | G95: Não material | I95: Total N.º de IRO | J95: Total Efeito ponderado (€/ano)
A96: ESRS_Topico | B96: Tema | C96: N.º de IRO | D96: Efeito ponderado (€/ano) | E96: N.º de IRO | F96: Efeito ponderado (€/ano) | G96: N.º de IRO | H96: Efeito ponderado (€/ano)
A97: E1 Alterações climáticas | B97: Consumo e eficiência energética | C97: 3 | D97: -19000 | E97: 1 | F97: 0 | I97: 4 | J97: -19000
B98: Emissões de GEE (âmbitos 1, 2 e 3) | C98: 1 | D98: -60000 | E98: 2 | F98: 0 | G98: 1 | H98: 0 | I98: 4 | J98: -60000
B99: Resiliência a ondas de calor, seca e incêndio | C99: 1 | D99: -39000 | G99: 1 | H99: -20000 | I99: 2 | J99: -59000
A100: E1 Alterações climáticas Total | C100: 5 | D100: -118000 | E100: 3 | F100: 0 | G100: 2 | H100: -20000 | I100: 10 | J100: -138000
A101: E2 Poluição | B101: Derrames e descargas | G101: 3 | H101: -12500 | I101: 3 | J101: -12500
B102: Emissões de COV da serigrafia | E102: 1 | F102: 0 | G102: 1 | H102: -3000 | I102: 2 | J102: -3000
B103: Perdas de granulado de plástico | C103: 1 | D103: -19500 | E103: 1 | F103: 0 | I103: 2 | J103: -19500
B104: Substâncias perigosas em tintas e aditivos | G104: 2 | H104: -16000 | I104: 2 | J104: -16000
A105: E2 Poluição Total | C105: 1 | D105: -19500 | E105: 2 | F105: 0 | G105: 6 | H105: -31500 | I105: 9 | J105: -51000
A106: E3 Água e recursos marinhos | B106: Consumo de água | G106: 2 | H106: -8000 | I106: 2 | J106: -8000
A107: E3 Água e recursos marinhos Total | G107: 2 | H107: -8000 | I107: 2 | J107: -8000
A108: E4 Biodiversidade e ecossistemas | B108: Ocupação do solo e plástico no meio natural | E108: 1 | F108: 0 | G108: 1 | H108: 0 | I108: 2 | J108: 0
...

Sheet Temas
A1: TEMAS DE SUSTENTABILIDADE — MATERIALIDADE AGREGADA
A2: Um tema é material se pelo menos um IRO for material · Cabeçalho cinzento = calculado · Linhas vazias no fim = reserva para novos temas
A4: ID_Tema | B4: Pilar | C4: ESRS_Topico | D4: Subtopico_ESRS | E4: Tema | F4: Descricao | G4: Referencia_GRI | H4: Relevancia_Setorial | I4: Fonte_Identificacao | J4: Dono | K4: Justificacao_Avaliacao | L4: Data_Avaliacao | M4: N_IRO | N4: N_Impactos | O4: N_Riscos_Oportunidades | P4: Score_Impacto_Max | Q4: Score_Financeiro_Max | R4: Material_Impacto | S4: Material_Financeiro | T4: Classificacao | U4: Banda_Impacto | V4: Banda_Financeira | W4: Indice_Prioridade | X4: Ranking | Y4: Exposicao_Risco_EUR | Z4: Potencial_Oportunidade_EUR | AA4: Relevancia_Partes_Interessadas | AB4: N_Contributos | AC4: Cobertura_Evidencia | AD4: Alerta_Consistencia | AE4: Decisao_Gestao
A5: DM-01 | B5: Ambiental | C5: E1 Alterações climáticas | D5: Mitigação das alterações climáticas | E5: Emissões de GEE (âmbitos 1, 2 e 3) | F5: Emissões diretas e indiretas de gases com efeito de estufa na operação e na cadeia de valor (polímeros, transporte). | G5: GRI 305 | H5: Alta | I5: RG-SGA-03 (AA-002, AA-007, AA-010, AA-040); PES-01; tbl_emas EMAS-06 | J5: Gestor do SGA / EHS (Responsável Ambiental) | K5: Processo 100% elétrico (≈ 7,8 GWh/ano) e 712 t/ano de polímero virgem: as emissões do âmbito 3 a montante superam as do âmbito 2; clientes europeus começam a pedir pegada de carbono. | L5: 46289 | M5: =IF(A5="","",COUNTIF(IRO!$B$5:$B$91,A5)) -> 4 | N5: =IF(A5="","",COUNTIFS(IRO!$B$5:$B$91,A5,IRO!$G$5:$G$91,"Impacto")) -> 3 | O5: =IF(A5="","",COUNTIFS(IRO!$B$5:$B$91,A5,IRO!$G$5:$G$91,"Financeira")) -> 1 | P5: =IF(OR(A5="",N5=0),"",_xlfn.MAXIFS(IRO!$T$5:$T$91,IRO!$B$5:$B$91,A5)) -> 20 | Q5: =IF(OR(A5="",O5=0),"",_xlfn.MAXIFS(IRO!$Z$5:$Z$91,IRO!$B$5:$B$91,A5)) -> 12 | R5: =IF(A5="","",IF(P5="","Não",IF(P5>=prm_Limiar_Impacto,"Sim","Não"))) -> Sim | S5: =IF(A5="","",IF(Q5="","Não",IF(Q5>=prm_Limiar_Financeiro,"Sim","Não"))) -> Sim | T5: =IF(A5="","",IF(AND(R5="Sim",S5="Sim"),"Dupla materialidade",IF(R5="Sim","Material — impacto",IF(S5="Sim","Material — financeira","Não material")))) -> Dupla materialidade | U5: =IF(A5="","",IF(P5="",0,IF(P5>=prm_Limiar_Alto,4,IF(P5>=prm_Limiar_Impacto,3,IF(P5>=prm_Limiar_Baixo,2,1))))) -> 4 | V5: =IF(A5="","",IF(Q5="",0,IF(Q5>=prm_Limiar_Alto,4,IF(Q5>=prm_Limiar_Financeiro,3,IF(Q5>=prm_Limiar_Baixo,2,1))))) -> 3 | W5: =IF(A5="","",N(P5)+N(Q5)) -> 32 | X5: =IF(A5="","",RANK(W5,$W$5:$W$40,0)+COUNTIFS($W$5:$W$40,W5,$A$5:$A$40,"<"&A5)) -> 3 | Y5: =IF(A5="","",-SUMIFS(IRO!$AA$5:$AA$91,IRO!$B$5:$B$91,A5,IRO!$F$5:$F$91,"Risco")) -> 60000 | Z5: =IF(A5="","",SUMIFS(IRO!$AA$5:$AA$91,IRO!$B$5:$B$91,A5,IRO!$F$5:$F$91,"Oportunidade")) -> 0 | AA5: =IF(A5="","",IFERROR(ROUND(AVERAGEIFS(Consultas!$H$5:$H$76,Consultas!$F$5:$F$76,A5),2),"")) -> 4 | AB5: =IF(A5="","",COUNTIF(Consultas!$F$5:$F$76,A5)) -> 2 | AC5: =IF(OR(A5="",N(M5)=0),"",(COUNTIFS(IRO!$B$5:$B$91,A5,IRO!$AG$5:$AG$91,"Alta")+COUNTIFS(IRO!$B$5:$B$91,A5,IRO!$AG$5:$AG$91,"Média"))/M5) -> 0.5 | AD5: =IF(A5="","",IF(AND(AA5<>"",N(AA5)>=prm_Relev_Alerta,T5="Não material"),"Rever: relevância alta para as partes interessadas",IF(AND(T5<>"Não material",AC5<>"",N(AC5)<0.5),"Material com evidência fraca","OK"))) -> OK | AE5: =IF(A5="","",IF(T5="Não material","Monitorizar e reavaliar na próxima DMA","Gerir: política, ações, meta e KPI; divulgar (VSME / ESRS voluntário)")) -> Gerir: política, ações, meta e KPI; divulgar (VSME / ESRS voluntário)
A6: DM-02 | B6: Ambiental | C6: E1 Alterações climáticas | D6: Energia | E6: Consumo e eficiência energética | F6: Consumo de eletricidade da injeção, sopro, compressores e utilidades; quota renovável e autoconsumo. | G6: GRI 302 | H6: Alta | I6: RG-SGA-03 (AA-007, AA-010, AA-021, AA-030); PES-02; SWT-F02; SWT-W01 | J6: Diretor Industrial | K6: A eletricidade é o 2.º maior custo variável; sem submedição por processo, a eficiência não é demonstrável. | L6: 46289 | M6: =IF(A6="","",COUNTIF(IRO!$B$5:$B$91,A6)) -> 4 | N6: =IF(A6="","",COUNTIFS(IRO!$B$5:$B$91,A6,IRO!$G$5:$G$91,"Impacto")) -> 1 | O6: =IF(A6="","",COUNTIFS(IRO!$B$5:$B$91,A6,IRO!$G$5:$G$91,"Financeira")) -> 3 | P6: =IF(OR(A6="",N6=0),"",_xlfn.MAXIFS(IRO!$T$5:$T$91,IRO!$B$5:$B$91,A6)) -> 15 | Q6: =IF(OR(A6="",O6=0),"",_xlfn.MAXIFS(IRO!$Z$5:$Z$91,IRO!$B$5:$B$91,A6)) -> 16 | R6: =IF(A6="","",IF(P6="","Não",IF(P6>=prm_Limiar_Impacto,"Sim","Não"))) -> Sim | S6: =IF(A6="","",IF(Q6="","Não",IF(Q6>=prm_Limiar_Financeiro,"Sim","Não"))) -> Sim | T6: =IF(A6="","",IF(AND(R6="Sim",S6="Sim"),"Dupla materialidade",IF(R6="Sim","Material — impacto",IF(S6="Sim","Material — financeira","Não material")))) -> Dupla materialidade | U6: =IF(A6="","",IF(P6="",0,IF(P6>=prm_Limiar_Alto,4,IF(P6>=prm_Limiar_Impacto,3,IF(P6>=prm_Limiar_Baixo,2,1))))) -> 3 | V6: =IF(A6="","",IF(Q6="",0,IF(Q6>=prm_Limiar_Alto,4,IF(Q6>=prm_Limiar_Financeiro,3,IF(Q6>=prm_Limiar_Baixo,2,1))))) -> 3 | W6: =IF(A6="","",N(P6)+N(Q6)) -> 31 | X6: =IF(A6="","",RANK(W6,$W$5:$W$40,0)+COUNTIFS($W$5:$W$40,W6,$A$5:$A$40,"<"&A6)) -> 4 | Y6: =IF(A6="","",-SUMIFS(IRO!$AA$5:$AA$91,IRO!$B$5:$B$91,A6,IRO!$F$5:$F$91,"Risco")) -> 139750 | Z6: =IF(A6="","",SUMIFS(IRO!$AA$5:$AA$91,IRO!$B$5:$B$91,A6,IRO!$F$5:$F$91,"Oportunidade")) -> 120750 | AA6: =IF(A6="","",IFERROR(ROUND(AVERAGEIFS(Consultas!$H$5:$H$76,Consultas!$F$5:$F$76,A6),2),"")) -> 4.5 | AB6: =IF(A6="","",COUNTIF(Consultas!$F$5:$F$76,A6)) -> 2 | AC6: =IF(OR(A6="",N(M6)=0),"",(COUNTIFS(IRO!$B$5:$B$91,A6,IRO!$AG$5:$AG$91,"Alta")+COUNTIFS(IRO!$B$5:$B$91,A6,IRO!$AG$5:$AG$91,"Média"))/M6) -> 1 | AD6: =IF(A6="","",IF(AND(AA6<>"",N(AA6)>=prm_Relev_Alerta,T6="Não material"),"Rever: relevância alta para as partes interessadas",IF(AND(T6<>"Não material",AC6<>"",N(AC6)<0.5),"Material com evidência fraca","OK"))) -> OK | AE6: =IF(A6="","",IF(T6="Não material","Monitorizar e reavaliar na próxima DMA","Gerir: política, ações, meta e KPI; divulgar (VSME / ESRS voluntário)")) -> Gerir: política, ações, meta e KPI; divulgar (VSME / ESRS voluntário)
A7: DM-03 | B7: Ambiental | C7: E1 Alterações climáticas | D7: Adaptação às alterações climáticas | E7: Resiliência a ondas de calor, seca e incêndio | F7: Riscos físicos agudos e crónicos sobre a operação: carga térmica, água de arrefecimento, incêndio rural. | G7: GRI 201-2 | H7: Média | I7: PES-08; PES-09; PES-10; SWT-T01; RO-04; RO-08 | J7: Diretor Industrial | K7: Verões de 2025 e 2026 com anomalia de +1,6 a +2,2 °C; proximidade ao Pinhal de Leiria. | L7: 46289 | M7: =IF(A7="","",COUNTIF(IRO!$B$5:$B$91,A7)) -> 2 | N7: =IF(A7="","",COUNTIFS(IRO!$B$5:$B$91,A7,IRO!$G$5:$G$91,"Impacto")) -> 0 | O7: =IF(A7="","",COUNTIFS(IRO!$B$5:$B$91,A7,IRO!$G$5:$G$91,"Financeira")) -> 2 | P7: =IF(OR(A7="",N7=0),"",_xlfn.MAXIFS(IRO!$T$5:$T$91,IRO!$B$5:$B$91,A7)) | Q7: =IF(OR(A7="",O7=0),"",_xlfn.MAXIFS(IRO!$Z$5:$Z$91,IRO!$B$5:$B$91,A7)) -> 12 | R7: =IF(A7="","",IF(P7="","Não",IF(P7>=prm_Limiar_Impacto,"Sim","Não"))) -> Não | S7: =IF(A7="","",IF(Q7="","Não",IF(Q7>=prm_Limiar_Financeiro,"Sim","Não"))) -> Sim | T7: =IF(A7="","",IF(AND(R7="Sim",S7="Sim"),"Dupla materialidade",IF(R7="Sim","Material — impacto",IF(S7="Sim","Material — financeira","Não material")))) -> Material — financeira | U7: =IF(A7="","",IF(P7="",0,IF(P7>=prm_Limiar_Alto,4,IF(P7>=prm_Limiar_Impacto,3,IF(P7>=prm_Limiar_Baixo,2,1))))) -> 0 | V7: =IF(A7="","",IF(Q7="",0,IF(Q7>=prm_Limiar_Alto,4,IF(Q7>=prm_Limiar_Financeiro,3,IF(Q7>=prm_Limiar_Baixo,2,1))))) -> 3 | W7: =IF(A7="","",N(P7)+N(Q7)) -> 12 | X7: =IF(A7="","",RANK(W7,$W$5:$W$40,0)+COUNTIFS($W$5:$W$40,W7,$A$5:$A$40,"<"&A7)) -> 21 | Y7: =IF(A7="","",-SUMIFS(IRO!$AA$5:$AA$91,IRO!$B$5:$B$91,A7,IRO!$F$5:$F$91,"Risco")) -> 59000 | Z7: =IF(A7="","",SUMIFS(IRO!$AA$5:$AA$91,IRO!$B$5:$B$91,A7,IRO!$F$5:$F$91,"Oportunidade")) -> 0 | AA7: =IF(A7="","",IFERROR(ROUND(AVERAGEIFS(Consultas!$H$5:$H$76,Consultas!$F$5:$F$76,A7),2),"")) -> 3.5 | AB7: =IF(A7="","",COUNTIF(Consultas!$F$5:$F$76,A7)) -> 2 | AC7: =IF(OR(A7="",N(M7)=0),"",(COUNTIFS(IRO!$B$5:$B$91,A7,IRO!$AG$5:$AG$91,"Alta")+COUNTIFS(IRO!$B$5:$B$91,A7,IRO!$AG$5:$AG$91,"Média"))/M7) -> 1 | AD7: =IF(A7="","",IF(AND(AA7<>"",N(AA7)>=prm_Relev_Alerta,T7="Não material"),"Rever: relevância alta para as partes interessadas",IF(AND(T7<>"Não material",AC7<>"",N(AC7)<0.5),"Material com evidência fraca","OK"))) -> OK | AE7: =IF(A7="","",IF(T7="Não material","Monitorizar e reavaliar na próxima DMA","Gerir: política, ações, meta e KPI; divulgar (VSME / ESRS voluntário)")) -> Gerir: política, ações, meta e KPI; divulgar (VSME / ESRS voluntário)
A8: DM-04 | B8: Ambiental | C8: E2 Poluição | D8: Poluição do ar | E8: Emissões de COV da serigrafia | F8: Emissão difusa de compostos orgânicos voláteis na limpeza de ecrãs e na impressão serigráfica. | G8: GRI 305-7 | H8: Média | I8: RG-SGA-03 (AA-014 — AAS, AA-006); LEG-04; OBJ-03 | J8: Gestor do SGA / EHS (Responsável Ambiental) | K8: Único aspeto ambiental significativo de processo (IRA 40); 1,95 t de COV/ano (balanço do RG-SGA-21). | L8: 46289 | M8: =IF(A8="","",COUNTIF(IRO!$B$5:$B$91,A8)) -> 2 | N8: =IF(A8="","",COUNTIFS(IRO!$B$5:$B$91,A8,IRO!$G$5:$G$91,"Impacto")) -> 1 | O8: =IF(A8="","",COUNTIFS(IRO!$B$5:$B$91,A8,IRO!$G$5:$G$91,"Financeira")) -> 1 | P8: =IF(OR(A8="",N8=0),"",_xlfn.MAXIFS(IRO!$T$5:$T$91,IRO!$B$5:$B$91,A8)) -> 13.4 | Q8: =IF(OR(A8="",O8=0),"",_xlfn.MAXIFS(IRO!$Z$5:$Z$91,IRO!$B$5:$B$91,A8)) -> 4 | R8: =IF(A8="","",IF(P8="","Não",IF(P8>=prm_Limiar_Impacto,"Sim","Não"))) -> Sim | S8: =IF(A8="","",IF(Q8="","Não",IF(Q8>=prm_Limiar_Financeiro,"Sim","Não"))) -> Não | T8: =IF(A8="","",IF(AND(R8="Sim",S8="Sim"),"Dupla materialidade",IF(R8="Sim","Material — impacto",IF(S8="Sim","Material — financeira","Não material")))) -> Material — impacto | U8: =IF(A8="","",IF(P8="",0,IF(P8>=prm_Limiar_Alto,4,IF(P8>=prm_Limiar_Impacto,3,IF(P8>=prm_Limiar_Baixo,2,1))))) -> 3 | V8: =IF(A8="","",IF(Q8="",0,IF(Q8>=prm_Limiar_Alto,4,IF(Q8>=prm_Limiar_Financeiro,3,IF(Q8>=prm_Limiar_Baixo,2,1))))) -> 1 | W8: =IF(A8="","",N(P8)+N(Q8)) -> 17.4 | X8: =IF(A8="","",RANK(W8,$W$5:$W$40,0)+COUNTIFS($W$5:$W$40,W8,$A$5:$A$40,"<"&A8)) -> 14 | Y8: =IF(A8="","",-SUMIFS(IRO!$AA$5:$AA$91,IRO!$B$5:$B$91,A8,IRO!$F$5:$F$91,"Risco")) -> 3000 | Z8: =IF(A8="","",SUMIFS(IRO!$AA$5:$AA$91,IRO!$B$5:$B$91,A8,IRO!$F$5:$F$91,"Oportunidade")) -> 0 | AA8: =IF(A8="","",IFERROR(ROUND(AVERAGEIFS(Consultas!$H$5:$H$76,Consultas!$F$5:$F$76,A8),2),"")) -> 3 | AB8: =IF(A8="","",COUNTIF(Consultas!$F$5:$F$76,A8)) -> 1 | AC8: =IF(OR(A8="",N(M8)=0),"",(COUNTIFS(IRO!$B$5:$B$91,A8,IRO!$AG$5:$AG$91,"Alta")+COUNTIFS(IRO!$B$5:$B$91,A8,IRO!$AG$5:$AG$91,"Média"))/M8) -> 1 | AD8: =IF(A8="","",IF(AND(AA8<>"",N(AA8)>=prm_Relev_Alerta,T8="Não material"),"Rever: relevância alta para as partes interessadas",IF(AND(T8<>"Não material",AC8<>"",N(AC8)<0.5),"Material com evidência fraca","OK"))) -> OK | AE8: =IF(A8="","",IF(T8="Não material","Monitorizar e reavaliar na próxima DMA","Gerir: política, ações, meta e KPI; divulgar (VSME / ESRS voluntário)")) -> Gerir: política, ações, meta e KPI; divulgar (VSME / ESRS voluntário)
A9: DM-05 | B9: Ambiental | C9: E2 Poluição | D9: Poluição da água e do solo | E9: Derrames e descargas | F9: Derrames de tintas, solventes e óleos; purga da torre de arrefecimento; águas de combate a incêndio. | G9: GRI 303-4; GRI 306-3 | H9: Média | I9: RG-SGA-03 (AA-005, AA-009, AA-013, AA-024); RO-10; NC-SGA-26-03 | J9: Gestor do SGA / EHS (Responsável Ambiental) | K9: NC do kit antipoluição em 2026 mostra fragilidade de controlo, mas os volumes em causa são pequenos e contidos. | L9: 46289 | M9: =IF(A9="","",COUNTIF(IRO!$B$5:$B$91,A9)) -> 3 | N9: =IF(A9="","",COUNTIFS(IRO!$B$5:$B$91,A9,IRO!$G$5:$G$91,"Impacto")) -> 2 | O9: =IF(A9="","",COUNTIFS(IRO!$B$5:$B$91,A9,IRO!$G$5:$G$91,"Financeira")) -> 1 | P9: =IF(OR(A9="",N9=0),"",_xlfn.MAXIFS(IRO!$T$5:$T$91,IRO!$B$5:$B$91,A9)) -> 10 | Q9: =IF(OR(A9="",O9=0),"",_xlfn.MAXIFS(IRO!$Z$5:$Z$91,IRO!$B$5:$B$91,A9)) -> 4 | R9: =IF(A9="","",IF(P9="","Não",IF(P9>=prm_Limiar_Impacto,"Sim","Não"))) -> Não | S9: =IF(A9="","",IF(Q9="","Não",IF(Q9>=prm_Limiar_Financeiro,"Sim","Não"))) -> Não | T9: =IF(A9="","",IF(AND(R9="Sim",S9="Sim"),"Dupla materialidade",IF(R9="Sim","Material — impacto",IF(S9="Sim","Material — financeira","Não material")))) -> Não material | U9: =IF(A9="","",IF(P9="",0,IF(P9>=prm_Limiar_Alto,4,IF(P9>=prm_Limiar_Impacto,3,IF(P9>=prm_Limiar_Baixo,2,1))))) -> 2 | V9: =IF(A9="","",IF(Q9="",0,IF(Q9>=prm_Limiar_Alto,4,IF(Q9>=prm_Limiar_Financeiro,3,IF(Q9>=prm_Limiar_Baixo,2,1))))) -> 1 | W9: =IF(A9="","",N(P9)+N(Q9)) -> 14 | X9: =IF(A9="","",RANK(W9,$W$5:$W$40,0)+COUNTIFS($W$5:$W$40,W9,$A$5:$A$40,"<"&A9)) -> 17 | Y9: =IF(A9="","",-SUMIFS(IRO!$AA$5:$AA$91,IRO!$B$5:$B$91,A9,IRO!$F$5:$F$91,"Risco")) -> 12500 | Z9: =IF(A9="","",SUMIFS(IRO!$AA$5:$AA$91,IRO!$B$5:$B$91,A9,IRO!$F$5:$F$91,"Oportunidade")) -> 0 | AA9: =IF(A9="","",IFERROR(ROUND(AVERAGEIFS(Consultas!$H$5:$H$76,Consultas!$F$5:$F$76,A9),2),"")) -> 3 | AB9: =IF(A9="","",COUNTIF(Consultas!$F$5:$F$76,A9)) -> 1 | AC9: =IF(OR(A9="",N(M9)=0),"",(COUNTIFS(IRO!$B$5:$B$91,A9,IRO!$AG$5:$AG$91,"Alta")+COUNTIFS(IRO!$B$5:$B$91,A9,IRO!$AG$5:$AG$91,"Média"))/M9) -> 0.66666667 | AD9: =IF(A9="","",IF(AND(AA9<>"",N(AA9)>=prm_Relev_Alerta,T9="Não material"),"Rever: relevância alta para as partes interessadas",IF(AND(T9<>"Não material",AC9<>"",N(AC9)<0.5),"Material com evidência fraca","OK"))) -> OK | AE9: =IF(A9="","",IF(T9="Não material","Monitorizar e reavaliar na próxima DMA","Gerir: política, ações, meta e KPI; divulgar (VSME / ESRS voluntário)")) -> Monitorizar e reavaliar na próxima DMA
A10: DM-06 | B10: Ambiental | C10: E2 Poluição | D10: Microplásticos | E10: Perdas de granulado de plástico | F10: Perdas de pellets na descarga de silos e big bags que podem chegar à rede pluvial e ao meio aquático. | G10: GRI 306 | H10: Alta | I10: RG-SGA-03 (AA-003); PES-11; PES-13; RO-07; OBJ-06 | J10: Gestor do SGA / EHS (Responsável Ambiental) | K10: Impacto persistente e novo regulamento europeu de perdas de granulado; só 43% dos pontos críticos têm contenção. | L10: 46289 | M10: =IF(A10="","",COUNTIF(IRO!$B$5:$B$91,A10)) -> 2 | N10: =IF(A10="","",COUNTIFS(IRO!$B$5:$B$91,A10,IRO!$G$5:$G$91,"Impacto")) -> 1 | O10: =IF(A10="","",COUNTIFS(IRO!$B$5:$B$91,A10,IRO!$G$5:$G$91,"Financeira")) -> 1 | P10: =IF(OR(A10="",N10=0),"",_xlfn.MAXIFS(IRO!$T$5:$T$91,IRO!$B$5:$B$91,A10)) -> 18.4 | Q10: =IF(OR(A10="",O10=0),"",_xlfn.MAXIFS(IRO!$Z$5:$Z$91,IRO!$B$5:$B$91,A10)) -> 12 | R10: =IF(A10="","",IF(P10="","Não",IF(P10>=prm_Limiar_Impacto,"Sim","Não"))) -> Sim | S10: =IF(A10="","",IF(Q10="","Não",IF(Q10>=prm_Limiar_Financeiro,"Sim","Não"))) -> Sim | T10: =IF(A10="","",IF(AND(R10="Sim",S10="Sim"),"Dupla materialidade",IF(R10="Sim","Material — impacto",IF(S10="Sim","Material — financeira","Não material")))) -> Dupla materialidade | U10: =IF(A10="","",IF(P10="",0,IF(P10>=prm_Limiar_Alto,4,IF(P10>=prm_Limiar_Impacto,3,IF(P10>=prm_Limiar_Baixo,2,1))))) -> 4 | V10: =IF(A10="","",IF(Q10="",0,IF(Q10>=prm_Limiar_Alto,4,IF(Q10>=prm_Limiar_Financeiro,3,IF(Q10>=prm_Limiar_Baixo,2,1))))) -> 3 | W10: =IF(A10="","",N(P10)+N(Q10)) -> 30.4 | X10: =IF(A10="","",RANK(W10,$W$5:$W$40,0)+COUNTIFS($W$5:$W$40,W10,$A$5:$A$40,"<"&A10)) -> 5 | Y10: =IF(A10="","",-SUMIFS(IRO!$AA$5:$AA$91,IRO!$B$5:$B$91,A10,IRO!$F$5:$F$91,"Risco")) -> 19500 | Z10: =IF(A10="","",SUMIFS(IRO!$AA$5:$AA$91,IRO!$B$5:$B$91,A10,IRO!$F$5:$F$91,"Oportunidade")) -> 0 | AA10: =IF(A10="","",IFERROR(ROUND(AVERAGEIFS(Consultas!$H$5:$H$76,Consultas!$F$5:$F$76,A10),2),"")) -> 3.5 | AB10: =IF(A10="","",COUNTIF(Consultas!$F$5:$F$76,A10)) -> 2 | AC10: =IF(OR(A10="",N(M10)=0),"",(COUNTIFS(IRO!$B$5:$B$91,A10,IRO!$AG$5:$AG$91,"Alta")+COUNTIFS(IRO!$B$5:$B$91,A10,IRO!$AG$5:$AG$91,"Média"))/M10) -> 1 | AD10: =IF(A10="","",IF(AND(AA10<>"",N(AA10)>=prm_Relev_Alerta,T10="Não material"),"Rever: relevância alta para as partes interessadas",IF(AND(T10<>"Não material",AC10<>"",N(AC10)<0.5),"Material com evidência fraca","OK"))) -> OK | AE10: =IF(A10="","",IF(T10="Não material","Monitorizar e reavaliar na próxima DMA","Gerir: política, ações, meta e KPI; divulgar (VSME / ESRS voluntário)")) -> Gerir: política, ações, meta e KPI; divulgar (VSME / ESRS voluntário)
A11: DM-07 | B11: Ambiental | C11: E2 Poluição | D11: Substâncias que suscitam preocupação | E11: Substâncias perigosas em tintas e aditivos | F11: Uso de tintas, solventes e aditivos classificados (CLP) e restrições a substâncias em embalagens (PPWR, REACH). | G11: GRI 416 | H11: Média | I11: RG-SGA-03 (AA-015); LEG-06; LEG-09; PES-12 | J11: Responsável de R&D | K11: Quantidades baixas (≈ 1,1 t de tinta/ano) e FDS disponíveis; vigiar restrições PFAS em contacto alimentar. | L11: 46289 | M11: =IF(A11="","",COUNTIF(IRO!$B$5:$B$91,A11)) -> 2 | N11: =IF(A11="","",COUNTIFS(IRO!$B$5:$B$91,A11,IRO!$G$5:$G$91,"Impacto")) -> 1 | O11: =IF(A11="","",COUNTIFS(IRO!$B$5:$B$91,A11,IRO!$G$5:$G$91,"Financeira")) -> 1 | P11: =IF(OR(A11="",N11=0),"",_xlfn.MAXIFS(IRO!$T$5:$T$91,IRO!$B$5:$B$91,A11)) -> 8 | Q11: =IF(OR(A11="",O11=0),"",_xlfn.MAXIFS(IRO!$Z$5:$Z$91,IRO!$B$5:$B$91,A11)) -> 9 | R11: =IF(A11="","",IF(P11="","Não",IF(P11>=prm_Limiar_Impacto,"Sim","Não"))) -> Não | S11: =IF(A11="","",IF(Q11="","Não",IF(Q11>=prm_Limiar_Financeiro,"Sim","Não"))) -> Não | T11: =IF(A11="","",IF(AND(R11="Sim",S11="Sim"),"Dupla materialidade",IF(R11="Sim","Material — impacto",IF(S11="Sim","Material — financeira","Não material")))) -> Não material | U11: =IF(A11="","",IF(P11="",0,IF(P11>=prm_Limiar_Alto,4,IF(P11>=prm_Limiar_Impacto,3,IF(P11>=prm_Limiar_Baixo,2,1))))) -> 2 | V11: =IF(A11="","",IF(Q11="",0,IF(Q11>=prm_Limiar_Alto,4,IF(Q11>=prm_Limiar_Financeiro,3,IF(Q11>=prm_Limiar_Baixo,2,1))))) -> 2 | W11: =IF(A11="","",N(P11)+N(Q11)) -> 17 | X11: =IF(A11="","",RANK(W11,$W$5:$W$40,0)+COUNTIFS($W$5:$W$40,W11,$A$5:$A$40,"<"&A11)) -> 15 | Y11: =IF(A11="","",-SUMIFS(IRO!$AA$5:$AA$91,IRO!$B$5:$B$91,A11,IRO!$F$5:$F$91,"Risco")) -> 16000 | Z11: =IF(A11="","",SUMIFS(IRO!$AA$5:$AA$91,IRO!$B$5:$B$91,A11,IRO!$F$5:$F$91,"Oportunidade")) -> 0 | AA11: =IF(A11="","",IFERROR(ROUND(AVERAGEIFS(Consultas!$H$5:$H$76,Consultas!$F$5:$F$76,A11),2),"")) | AB11: =IF(A11="","",COUNTIF(Consultas!$F$5:$F$76,A11)) -> 0 | AC11: =IF(OR(A11="",N(M11)=0),"",(COUNTIFS(IRO!$B$5:$B$91,A11,IRO!$AG$5:$AG$91,"Alta")+COUNTIFS(IRO!$B$5:$B$91,A11,IRO!$AG$5:$AG$91,"Média"))/M11) -> 1 | AD11: =IF(A11="","",IF(AND(AA11<>"",N(AA11)>=prm_Relev_Alerta,T11="Não material"),"Rever: relevância alta para as partes interessadas",IF(AND(T11<>"Não material",AC11<>"",N(AC11)<0.5),"Material com evidência fraca","OK"))) -> OK | AE11: =IF(A11="","",IF(T11="Não material","Monitorizar e reavaliar na próxima DMA","Gerir: política, ações, meta e KPI; divulgar (VSME / ESRS voluntário)")) -> Monitorizar e reavaliar na próxima DMA
A12: DM-08 | B12: Ambiental | C12: E3 Água e recursos marinhos | D12: Água | E12: Consumo de água | F12: Água de rede para reposição da torre de arrefecimento e uso sanitário, numa região com seca sazonal. | G12: GRI 303 | H12: Média | I12: RG-SGA-03 (AA-023, AA-035); PES-09; OBJ-05; tbl_emas EMAS-03 | J12: Gerente de Manutenção | K12: 9.384 m³/ano, dos quais 81% na torre; consumo cresce com a temperatura. | L12: 46289 | M12: =IF(A12="","",COUNTIF(IRO!$B$5:$B$91,A12)) -> 2 | N12: =IF(A12="","",COUNTIFS(IRO!$B$5:$B$91,A12,IRO!$G$5:$G$91,"Impacto")) -> 1 | O12: =IF(A12="","",COUNTIFS(IRO!$B$5:$B$91,A12,IRO!$G$5:$G$91,"Financeira")) -> 1 | P12: =IF(OR(A12="",N12=0),"",_xlfn.MAXIFS(IRO!$T$5:$T$91,IRO!$B$5:$B$91,A12)) -> 11.7 | Q12: =IF(OR(A12="",O12=0),"",_xlfn.MAXIFS(IRO!$Z$5:$Z$91,IRO!$B$5:$B$91,A12)) -> 6 | R12: =IF(A12="","",IF(P12="","Não",IF(P12>=prm_Limiar_Impacto,"Sim","Não"))) -> Não | S12: =IF(A12="","",IF(Q12="","Não",IF(Q12>=prm_Limiar_Financeiro,"Sim","Não"))) -> Não | T12: =IF(A12="","",IF(AND(R12="Sim",S12="Sim"),"Dupla materialidade",IF(R12="Sim","Material — impacto",IF(S12="Sim","Material — financeira","Não material")))) -> Não material | U12: =IF(A12="","",IF(P12="",0,IF(P12>=prm_Limiar_Alto,4,IF(P12>=prm_Limiar_Impacto,3,IF(P12>=prm_Limiar_Baixo,2,1))))) -> 2 | V12: =IF(A12="","",IF(Q12="",0,IF(Q12>=prm_Limiar_Alto,4,IF(Q12>=prm_Limiar_Financeiro,3,IF(Q12>=prm_Limiar_Baixo,2,1))))) -> 2 | W12: =IF(A12="","",N(P12)+N(Q12)) -> 17.7 | X12: =IF(A12="","",RANK(W12,$W$5:$W$40,0)+COUNTIFS($W$5:$W$40,W12,$A$5:$A$40,"<"&A12)) -> 13 | Y12: =IF(A12="","",-SUMIFS(IRO!$AA$5:$AA$91,IRO!$B$5:$B$91,A12,IRO!$F$5:$F$91,"Risco")) -> 8000 | Z12: =IF(A12="","",SUMIFS(IRO!$AA$5:$AA$91,IRO!$B$5:$B$91,A12,IRO!$F$5:$F$91,"Oportunidade")) -> 0 | AA12: =IF(A12="","",IFERROR(ROUND(AVERAGEIFS(Consultas!$H$5:$H$76,Consultas!$F$5:$F$76,A12),2),"")) -> 3 | AB12: =IF(A12="","",COUNTIF(Consultas!$F$5:$F$76,A12)) -> 1 | AC12: =IF(OR(A12="",N(M12)=0),"",(COUNTIFS(IRO!$B$5:$B$91,A12,IRO!$AG$5:$AG$91,"Alta")+COUNTIFS(IRO!$B$5:$B$91,A12,IRO!$AG$5:$AG$91,"Média"))/M12) -> 0.5 | AD12: =IF(A12="","",IF(AND(AA12<>"",N(AA12)>=prm_Relev_Alerta,T12="Não material"),"Rever: relevância alta para as partes interessadas",IF(AND(T12<>"Não material",AC12<>"",N(AC12)<0.5),"Material com evidência fraca","OK"))) -> OK | AE12: =IF(A12="","",IF(T12="Não material","Monitorizar e reavaliar na próxima DMA","Gerir: política, ações, meta e KPI; divulgar (VSME / ESRS voluntário)")) -> Monitorizar e reavaliar na próxima DMA
A13: DM-09 | B13: Ambiental | C13: E4 Biodiversidade e ecossistemas | D13: Biodiversidade e ecossistemas | E13: Ocupação do solo e plástico no meio natural | F13: Impermeabilização do terreno e escape de embalagens para o meio natural e marinho no fim de vida. | G13: GRI 304 | H13: Média | I13: RG-SGA-03 (AA-033, AA-043); PES-10; tbl_emas EMAS-05 | J13: Gestor do SGA / EHS (Responsável Ambiental) | K13: O impacto relevante está a jusante (lixo plástico), não no local. | L13: 46289 | M13: =IF(A13="","",COUNTIF(IRO!$B$5:$B$91,A13)) -> 2 | N13: =IF(A13="","",COUNTIFS(IRO!$B$5:$B$91,A13,IRO!$G$5:$G$91,"Impacto")) -> 2 | O13: =IF(A13="","",COUNTIFS(IRO!$B$5:$B$91,A13,IRO!$G$5:$G$91,"Financeira")) -> 0 | P13: =IF(OR(A13="",N13=0),"",_xlfn.MAXIFS(IRO!$T$5:$T$91,IRO!$B$5:$B$91,A13)) -> 14 | Q13: =IF(OR(A13="",O13=0),"",_xlfn.MAXIFS(IRO!$Z$5:$Z$91,IRO!$B$5:$B$91,A13)) | R13: =IF(A13="","",IF(P13="","Não",IF(P13>=prm_Limiar_Impacto,"Sim","Não"))) -> Sim | S13: =IF(A13="","",IF(Q13="","Não",IF(Q13>=prm_Limiar_Financeiro,"Sim","Não"))) -> Não | T13: =IF(A13="","",IF(AND(R13="Sim",S13="Sim"),"Dupla materialidade",IF(R13="Sim","Material — impacto",IF(S13="Sim","Material — financeira","Não material")))) -> Material — impacto | U13: =IF(A13="","",IF(P13="",0,IF(P13>=prm_Limiar_Alto,4,IF(P13>=prm_Limiar_Impacto,3,IF(P13>=prm_Limiar_Baixo,2,1))))) -> 3 | V13: =IF(A13="","",IF(Q13="",0,IF(Q13>=prm_Limiar_Alto,4,IF(Q13>=prm_Limiar_Financeiro,3,IF(Q13>=prm_Limiar_Baixo,2,1))))) -> 0 | W13: =IF(A13="","",N(P13)+N(Q13)) -> 14 | X13: =IF(A13="","",RANK(W13,$W$5:$W$40,0)+COUNTIFS($W$5:$W$40,W13,$A$5:$A$40,"<"&A13)) -> 18 | Y13: =IF(A13="","",-SUMIFS(IRO!$AA$5:$AA$91,IRO!$B$5:$B$91,A13,IRO!$F$5:$F$91,"Risco")) -> 0 | Z13: =IF(A13="","",SUMIFS(IRO!$AA$5:$AA$91,IRO!$B$5:$B$91,A13,IRO!$F$5:$F$91,"Oportunidade")) -> 0 | AA13: =IF(A13="","",IFERROR(ROUND(AVERAGEIFS(Consultas!$H$5:$H$76,Consultas!$F$5:$F$76,A13),2),"")) | AB13: =IF(A13="","",COUNTIF(Consultas!$F$5:$F$76,A13)) -> 0 | AC13: =IF(OR(A13="",N(M13)=0),"",(COUNTIFS(IRO!$B$5:$B$91,A13,IRO!$AG$5:$AG$91,"Alta")+COUNTIFS(IRO!$B$5:$B$91,A13,IRO!$AG$5:$AG$91,"Média"))/M13) -> 0.5 | AD13: =IF(A13="","",IF(AND(AA13<>"",N(AA13)>=prm_Relev_Alerta,T13="Não material"),"Rever: relevância alta para as partes interessadas",IF(AND(T13<>"Não material",AC13<>"",N(AC13)<0.5),"Material com evidência fraca","OK"))) -> OK | AE13: =IF(A13="","",IF(T13="Não material","Monitorizar e reavaliar na próxima DMA","Gerir: política, ações, meta e KPI; divulgar (VSME / ESRS voluntário)")) -> Gerir: política, ações, meta e KPI; divulgar (VSME / ESRS voluntário)
A14: DM-10 | B14: Ambiental | C14: E5 Uso de recursos e economia circular | D14: Entradas de recursos | E14: Polímeros virgens e conteúdo reciclado | F14: Dependência de polímeros de origem fóssil; acesso a PCR/rPET de qualidade; reintegração de scrap. | G14: GRI 301 | H14: Alta | I14: RG-SGA-03 (AA-001, AA-020); SWT-W02; SWT-T02; PES-03; RO-05; RO-11 | J14: Responsável de Compras | K14: 88% do polímero é virgem; metas de conteúdo reciclado do PPWR para 2030. | L14: 46289 | M14: =IF(A14="","",COUNTIF(IRO!$B$5:$B$91,A14)) -> 3 | N14: =IF(A14="","",COUNTIFS(IRO!$B$5:$B$91,A14,IRO!$G$5:$G$91,"Impacto")) -> 1 | O14: =IF(A14="","",COUNTIFS(IRO!$B$5:$B$91,A14,IRO!$G$5:$G$91,"Financeira")) -> 2 | P14: =IF(OR(A14="",N14=0),"",_xlfn.MAXIFS(IRO!$T$5:$T$91,IRO!$B$5:$B$91,A14)) -> 18.4 | Q14: =IF(OR(A14="",O14=0),"",_xlfn.MAXIFS(IRO!$Z$5:$Z$91,IRO!$B$5:$B$91,A14)) -> 12 | R14: =IF(A14="","",IF(P14="","Não",IF(P14>=prm_Limiar_Impacto,"Sim","Não"))) -> Sim | S14: =IF(A14="","",IF(Q14="","Não",IF(Q14>=prm_Limiar_Financeiro,"Sim","Não"))) -> Sim | T14: =IF(A14="","",IF(AND(R14="Sim",S14="Sim"),"Dupla materialidade",IF(R14="Sim","Material — impacto",IF(S14="Sim","Material — financeira","Não material")))) -> Dupla materialidade | U14: =IF(A14="","",IF(P14="",0,IF(P14>=prm_Limiar_Alto,4,IF(P14>=prm_Limiar_Impacto,3,IF(P14>=prm_Limiar_Baixo,2,1))))) -> 4 | V14: =IF(A14="","",IF(Q14="",0,IF(Q14>=prm_Limiar_Alto,4,IF(Q14>=prm_Limiar_Financeiro,3,IF(Q14>=prm_Limiar_Baixo,2,1))))) -> 3 | W14: =IF(A14="","",N(P14)+N(Q14)) -> 30.4 | X14: =IF(A14="","",RANK(W14,$W$5:$W$40,0)+COUNTIFS($W$5:$W$40,W14,$A$5:$A$40,"<"&A14)) -> 6 | Y14: =IF(A14="","",-SUMIFS(IRO!$AA$5:$AA$91,IRO!$B$5:$B$91,A14,IRO!$F$5:$F$91,"Risco")) -> 58500 | Z14: =IF(A14="","",SUMIFS(IRO!$AA$5:$AA$91,IRO!$B$5:$B$91,A14,IRO!$F$5:$F$91,"Oportunidade")) -> 7800 | AA14: =IF(A14="","",IFERROR(ROUND(AVERAGEIFS(Consultas!$H$5:$H$76,Consultas!$F$5:$F$76,A14),2),"")) -> 4.5 | AB14: =IF(A14="","",COUNTIF(Consultas!$F$5:$F$76,A14)) -> 2 | AC14: =IF(OR(A14="",N(M14)=0),"",(COUNTIFS(IRO!$B$5:$B$91,A14,IRO!$AG$5:$AG$91,"Alta")+COUNTIFS(IRO!$B$5:$B$91,A14,IRO!$AG$5:$AG$91,"Média"))/M14) -> 1 | AD14: =IF(A14="","",IF(AND(AA14<>"",N(AA14)>=prm_Relev_Alerta,T14="Não material"),"Rever: relevância alta para as partes interessadas",IF(AND(T14<>"Não material",AC14<>"",N(AC14)<0.5),"Material com evidência fraca","OK"))) -> OK | AE14: =IF(A14="","",IF(T14="Não material","Monitorizar e reavaliar na próxima DMA","Gerir: política, ações, meta e KPI; divulgar (VSME / ESRS voluntário)")) -> Gerir: política, ações, meta e KPI; divulgar (VSME / ESRS voluntário)
A15: DM-11 | B15: Ambiental | C15: E5 Uso de recursos e economia circular | D15: Saídas de recursos — produtos e embalagens | E15: Reciclabilidade e conformidade PPWR das embalagens | F15: Design for recycling, reciclabilidade, documentação técnica e declaração UE de conformidade das embalagens. | G15: GRI 301-3 | H15: Alta | I15: RG-SGA-03 (AA-037, AA-038 — AAS, AA-043); PES-04; PES-07; PES-12; SWT-O01; RO-03; RO-06 | J15: Responsável de R&D | K15: Aspeto de maior IRA do SGA (60); só 41% das famílias com documentação PPWR. | L15: 46289 | M15: =IF(A15="","",COUNTIF(IRO!$B$5:$B$91,A15)) -> 4 | N15: =IF(A15="","",COUNTIFS(IRO!$B$5:$B$91,A15,IRO!$G$5:$G$91,"Impacto")) -> 2 | O15: =IF(A15="","",COUNTIFS(IRO!$B$5:$B$91,A15,IRO!$G$5:$G$91,"Financeira")) -> 2 | P15: =IF(OR(A15="",N15=0),"",_xlfn.MAXIFS(IRO!$T$5:$T$91,IRO!$B$5:$B$91,A15)) -> 16.7 | Q15: =IF(OR(A15="",O15=0),"",_xlfn.MAXIFS(IRO!$Z$5:$Z$91,IRO!$B$5:$B$91,A15)) -> 20 | R15: =IF(A15="","",IF(P15="","Não",IF(P15>=prm_Limiar_Impacto,"Sim","Não"))) -> Sim | S15: =IF(A15="","",IF(Q15="","Não",IF(Q15>=prm_Limiar_Financeiro,"Sim","Não"))) -> Sim | T15: =IF(A15="","",IF(AND(R15="Sim",S15="Sim"),"Dupla materialidade",IF(R15="Sim","Material — impacto",IF(S15="Sim","Material — financeira","Não material")))) -> Dupla materialidade | U15: =IF(A15="","",IF(P15="",0,IF(P15>=prm_Limiar_Alto,4,IF(P15>=prm_Limiar_Impacto,3,IF(P15>=prm_Limiar_Baixo,2,1))))) -> 3 | V15: =IF(A15="","",IF(Q15="",0,IF(Q15>=prm_Limiar_Alto,4,IF(Q15>=prm_Limiar_Financeiro,3,IF(Q15>=prm_Limiar_Baixo,2,1))))) -> 4 | W15: =IF(A15="","",N(P15)+N(Q15)) -> 36.7 | X15: =IF(A15="","",RANK(W15,$W$5:$W$40,0)+COUNTIFS($W$5:$W$40,W15,$A$5:$A$40,"<"&A15)) -> 1 | Y15: =IF(A15="","",-SUMIFS(IRO!$AA$5:$AA$91,IRO!$B$5:$B$91,A15,IRO!$F$5:$F$91,"Risco")) -> 227500 | Z15: =IF(A15="","",SUMIFS(IRO!$AA$5:$AA$91,IRO!$B$5:$B$91,A15,IRO!$F$5:$F$91,"Oportunidade")) -> 80000 | AA15: =IF(A15="","",IFERROR(ROUND(AVERAGEIFS(Consultas!$H$5:$H$76,Consultas!$F$5:$F$76,A15),2),"")) -> 4.67 | AB15: =IF(A15="","",COUNTIF(Consultas!$F$5:$F$76,A15)) -> 3 | AC15: =IF(OR(A15="",N(M15)=0),"",(COUNTIFS(IRO!$B$5:$B$91,A15,IRO!$AG$5:$AG$91,"Alta")+COUNTIFS(IRO!$B$5:$B$91,A15,IRO!$AG$5:$AG$91,"Média"))/M15) -> 1 | AD15: =IF(A15="","",IF(AND(AA15<>"",N(AA15)>=prm_Relev_Alerta,T15="Não material"),"Rever: relevância alta para as partes interessadas",IF(AND(T15<>"Não material",AC15<>"",N(AC15)<0.5),"Material com evidência fraca","OK"))) -> OK | AE15: =IF(A15="","",IF(T15="Não material","Monitorizar e reavaliar na próxima DMA","Gerir: política, ações, meta e KPI; divulgar (VSME / ESRS voluntário)")) -> Gerir: política, ações, meta e KPI; divulgar (VSME / ESRS voluntário)
A16: DM-12 | B16: Ambiental | C16: E5 Uso de recursos e economia circular | D16: Resíduos | E16: Resíduos da produção | F16: Scrap, embalagens de matérias-primas, resíduos perigosos (tintas, óleos) e indiferenciados. | G16: GRI 306 | H16: Média | I16: RG-SGA-03 (AA-004, AA-008, AA-011, AA-016, AA-026, AA-028, AA-029); PES-14 | J16: Gestor do SGA / EHS (Responsável Ambiental) | K16: 130,6 t/ano com valorização elevada; 2,1 t de perigosos. | L16: 46289 | M16: =IF(A16="","",COUNTIF(IRO!$B$5:$B$91,A16)) -> 3 | N16: =IF(A16="","",COUNTIFS(IRO!$B$5:$B$91,A16,IRO!$G$5:$G$91,"Impacto")) -> 1 | O16: =IF(A16="","",COUNTIFS(IRO!$B$5:$B$91,A16,IRO!$G$5:$G$91,"Financeira")) -> 2 | P16: =IF(OR(A16="",N16=0),"",_xlfn.MAXIFS(IRO!$T$5:$T$91,IRO!$B$5:$B$91,A16)) -> 10 | Q16: =IF(OR(A16="",O16=0),"",_xlfn.MAXIFS(IRO!$Z$5:$Z$91,IRO!$B$5:$B$91,A16)) -> 8 | R16: =IF(A16="","",IF(P16="","Não",IF(P16>=prm_Limiar_Impacto,"Sim","Não"))) -> Não | S16: =IF(A16="","",IF(Q16="","Não",IF(Q16>=prm_Limiar_Financeiro,"Sim","Não"))) -> Não | T16: =IF(A16="","",IF(AND(R16="Sim",S16="Sim"),"Dupla materialidade",IF(R16="Sim","Material — impacto",IF(S16="Sim","Material — financeira","Não material")))) -> Não material | U16: =IF(A16="","",IF(P16="",0,IF(P16>=prm_Limiar_Alto,4,IF(P16>=prm_Limiar_Impacto,3,IF(P16>=prm_Limiar_Baixo,2,1))))) -> 2 | V16: =IF(A16="","",IF(Q16="",0,IF(Q16>=prm_Limiar_Alto,4,IF(Q16>=prm_Limiar_Financeiro,3,IF(Q16>=prm_Limiar_Baixo,2,1))))) -> 2 | W16: =IF(A16="","",N(P16)+N(Q16)) -> 18 | X16: =IF(A16="","",RANK(W16,$W$5:$W$40,0)+COUNTIFS($W$5:$W$40,W16,$A$5:$A$40,"<"&A16)) -> 12 | Y16: =IF(A16="","",-SUMIFS(IRO!$AA$5:$AA$91,IRO!$B$5:$B$91,A16,IRO!$F$5:$F$91,"Risco")) -> 6000 | Z16: =IF(A16="","",SUMIFS(IRO!$AA$5:$AA$91,IRO!$B$5:$B$91,A16,IRO!$F$5:$F$91,"Oportunidade")) -> 5200 | AA16: =IF(A16="","",IFERROR(ROUND(AVERAGEIFS(Consultas!$H$5:$H$76,Consultas!$F$5:$F$76,A16),2),"")) -> 3.5 | AB16: =IF(A16="","",COUNTIF(Consultas!$F$5:$F$76,A16)) -> 2 | AC16: =IF(OR(A16="",N(M16)=0),"",(COUNTIFS(IRO!$B$5:$B$91,A16,IRO!$AG$5:$AG$91,"Alta")+COUNTIFS(IRO!$B$5:$B$91,A16,IRO!$AG$5:$AG$91,"Média"))/M16) -> 1 | AD16: =IF(A16="","",IF(AND(AA16<>"",N(AA16)>=prm_Relev_Alerta,T16="Não material"),"Rever: relevância alta para as partes interessadas",IF(AND(T16<>"Não material",AC16<>"",N(AC16)<0.5),"Material com evidência fraca","OK"))) -> OK | AE16: =IF(A16="","",IF(T16="Não material","Monitorizar e reavaliar na próxima DMA","Gerir: política, ações, meta e KPI; divulgar (VSME / ESRS voluntário)")) -> Monitorizar e reavaliar na próxima DMA
... A28: DM-24 | B28: Governança | C28: Específico da entidade | D28: Dados, digitalização e cibersegurança | E28: Dados industriais e cibersegurança | F28: Disponibilidade e integridade do warehouse de dados, sistemas OT e uso de dados para decisões ESG. | G28: GRI 418 | H28: Média | I28: SWT-F01; RO-01; registo corporativo R26, O3 | J28: Diretor Geral (Gestão de Topo) | K28: Força de dados industriais; dependência crescente do pipeline de dados. | L28: 46289 | M28: =IF(A28="","",COUNTIF(IRO!$B$5:$B$91,A28)) -> 2 | N28: =IF(A28="","",COUNTIFS(IRO!$B$5:$B$91,A28,IRO!$G$5:$G$91,"Impacto")) -> 0 | O28: =IF(A28="","",COUNTIFS(IRO!$B$5:$B$91,A28,IRO!$G$5:$G$91,"Financeira")) -> 2 | P28: =IF(OR(A28="",N28=0),"",_xlfn.MAXIFS(IRO!$T$5:$T$91,IRO!$B$5:$B$91,A28)) | Q28: =IF(OR(A28="",O28=0),"",_xlfn.MAXIFS(IRO!$Z$5:$Z$91,IRO!$B$5:$B$91,A28)) -> 12 | R28: =IF(A28="","",IF(P28="","Não",IF(P28>=prm_Limiar_Impacto,"Sim","Não"))) -> Não | S28: =IF(A28="","",IF(Q28="","Não",IF(Q28>=prm_Limiar_Financeiro,"Sim","Não"))) -> Sim | T28: =IF(A28="","",IF(AND(R28="Sim",S28="Sim"),"Dupla materialidade",IF(R28="Sim","Material — impacto",IF(S28="Sim","Material — financeira","Não material")))) -> Material — financeira | U28: =IF(A28="","",IF(P28="",0,IF(P28>=prm_Limiar_Alto,4,IF(P28>=prm_Limiar_Impacto,3,IF(P28>=prm_Limiar_Baixo,2,1))))) -> 0 | V28: =IF(A28="","",IF(Q28="",0,IF(Q28>=prm_Limiar_Alto,4,IF(Q28>=prm_Limiar_Financeiro,3,IF(Q28>=prm_Limiar_Baixo,2,1))))) -> 3 | W28: =IF(A28="","",N(P28)+N(Q28)) -> 12 | X28: =IF(A28="","",RANK(W28,$W$5:$W$40,0)+COUNTIFS($W$5:$W$40,W28,$A$5:$A$40,"<"&A28)) -> 22 | Y28: =IF(A28="","",-SUMIFS(IRO!$AA$5:$AA$91,IRO!$B$5:$B$91,A28,IRO!$F$5:$F$91,"Risco")) -> 12000 | Z28: =IF(A28="","",SUMIFS(IRO!$AA$5:$AA$91,IRO!$B$5:$B$91,A28,IRO!$F$5:$F$91,"Oportunidade")) -> 32500 | AA28: =IF(A28="","",IFERROR(ROUND(AVERAGEIFS(Consultas!$H$5:$H$76,Consultas!$F$5:$F$76,A28),2),"")) -> 4 | AB28: =IF(A28="","",COUNTIF(Consultas!$F$5:$F$76,A28)) -> 1 | AC28: =IF(OR(A28="",N(M28)=0),"",(COUNTIFS(IRO!$B$5:$B$91,A28,IRO!$AG$5:$AG$91,"Alta")+COUNTIFS(IRO!$B$5:$B$91,A28,IRO!$AG$5:$AG$91,"Média"))/M28) -> 1 | AD28: =IF(A28="","",IF(AND(AA28<>"",N(AA28)>=prm_Relev_Alerta,T28="Não material"),"Rever: relevância alta para as partes interessadas",IF(AND(T28<>"Não material",AC28<>"",N(AC28)<0.5),"Material com evidência fraca","OK"))) -> OK | AE28: =IF(A28="","",IF(T28="Não material","Monitorizar e reavaliar na próxima DMA","Gerir: política, ações, meta e KPI; divulgar (VSME / ESRS voluntário)")) -> Gerir: política, ações, meta e KPI; divulgar (VSME / ESRS voluntário)
M29: =IF(A29="","",COUNTIF(IRO!$B$5:$B$91,A29)) | N29: =IF(A29="","",COUNTIFS(IRO!$B$5:$B$91,A29,IRO!$G$5:$G$91,"Impacto")) | O29: =IF(A29="","",COUNTIFS(IRO!$B$5:$B$91,A29,IRO!$G$5:$G$91,"Financeira")) | P29: =IF(OR(A29="",N29=0),"",_xlfn.MAXIFS(IRO!$T$5:$T$91,IRO!$B$5:$B$91,A29)) | Q29: =IF(OR(A29="",O29=0),"",_xlfn.MAXIFS(IRO!$Z$5:$Z$91,IRO!$B$5:$B$91,A29)) | R29: =IF(A29="","",IF(P29="","Não",IF(P29>=prm_Limiar_Impacto,"Sim","Não"))) | S29: =IF(A29="","",IF(Q29="","Não",IF(Q29>=prm_Limiar_Financeiro,"Sim","Não"))) | T29: =IF(A29="","",IF(AND(R29="Sim",S29="Sim"),"Dupla materialidade",IF(R29="Sim","Material — impacto",IF(S29="Sim","Material — financeira","Não material")))) | U29: =IF(A29="","",IF(P29="",0,IF(P29>=prm_Limiar_Alto,4,IF(P29>=prm_Limiar_Impacto,3,IF(P29>=prm_Limiar_Baixo,2,1))))) | V29: =IF(A29="","",IF(Q29="",0,IF(Q29>=prm_Limiar_Alto,4,IF(Q29>=prm_Limiar_Financeiro,3,IF(Q29>=prm_Limiar_Baixo,2,1))))) | W29: =IF(A29="","",N(P29)+N(Q29)) | X29: =IF(A29="","",RANK(W29,$W$5:$W$40,0)+COUNTIFS($W$5:$W$40,W29,$A$5:$A$40,"<"&A29)) | Y29: =IF(A29="","",-SUMIFS(IRO!$AA$5:$AA$91,IRO!$B$5:$B$91,A29,IRO!$F$5:$F$91,"Risco")) | Z29: =IF(A29="","",SUMIFS(IRO!$AA$5:$AA$91,IRO!$B$5:$B$91,A29,IRO!$F$5:$F$91,"Oportunidade")) | AA29: =IF(A29="","",IFERROR(ROUND(AVERAGEIFS(Consultas!$H$5:$H$76,Consultas!$F$5:$F$76,A29),2),"")) | AB29: =IF(A29="","",COUNTIF(Consultas!$F$5:$F$76,A29)) | AC29: =IF(OR(A29="",N(M29)=0),"",(COUNTIFS(IRO!$B$5:$B$91,A29,IRO!$AG$5:$AG$91,"Alta")+COUNTIFS(IRO!$B$5:$B$91,A29,IRO!$AG$5:$AG$91,"Média"))/M29) | AD29: =IF(A29="","",IF(AND(AA29<>"",N(AA29)>=prm_Relev_Alerta,T29="Não material"),"Rever: relevância alta para as partes interessadas",IF(AND(T29<>"Não material",AC29<>"",N(AC29)<0.5),"Material com evidência fraca","OK"))) | AE29: =IF(A29="","",IF(T29="Não material","Monitorizar e reavaliar na próxima DMA","Gerir: política, ações, meta e KPI; divulgar (VSME / ESRS voluntário)"))
M30: =IF(A30="","",COUNTIF(IRO!$B$5:$B$91,A30)) | N30: =IF(A30="","",COUNTIFS(IRO!$B$5:$B$91,A30,IRO!$G$5:$G$91,"Impacto")) | O30: =IF(A30="","",COUNTIFS(IRO!$B$5:$B$91,A30,IRO!$G$5:$G$91,"Financeira")) | P30: =IF(OR(A30="",N30=0),"",_xlfn.MAXIFS(IRO!$T$5:$T$91,IRO!$B$5:$B$91,A30)) | Q30: =IF(OR(A30="",O30=0),"",_xlfn.MAXIFS(IRO!$Z$5:$Z$91,IRO!$B$5:$B$91,A30)) | R30: =IF(A30="","",IF(P30="","Não",IF(P30>=prm_Limiar_Impacto,"Sim","Não"))) | S30: =IF(A30="","",IF(Q30="","Não",IF(Q30>=prm_Limiar_Financeiro,"Sim","Não"))) | T30: =IF(A30="","",IF(AND(R30="Sim",S30="Sim"),"Dupla materialidade",IF(R30="Sim","Material — impacto",IF(S30="Sim","Material — financeira","Não material")))) | U30: =IF(A30="","",IF(P30="",0,IF(P30>=prm_Limiar_Alto,4,IF(P30>=prm_Limiar_Impacto,3,IF(P30>=prm_Limiar_Baixo,2,1))))) | V30: =IF(A30="","",IF(Q30="",0,IF(Q30>=prm_Limiar_Alto,4,IF(Q30>=prm_Limiar_Financeiro,3,IF(Q30>=prm_Limiar_Baixo,2,1))))) | W30: =IF(A30="","",N(P30)+N(Q30)) | X30: =IF(A30="","",RANK(W30,$W$5:$W$40,0)+COUNTIFS($W$5:$W$40,W30,$A$5:$A$40,"<"&A30)) | Y30: =IF(A30="","",-SUMIFS(IRO!$AA$5:$AA$91,IRO!$B$5:$B$91,A30,IRO!$F$5:$F$91,"Risco")) | Z30: =IF(A30="","",SUMIFS(IRO!$AA$5:$AA$91,IRO!$B$5:$B$91,A30,IRO!$F$5:$F$91,"Oportunidade")) | AA30: =IF(A30="","",IFERROR(ROUND(AVERAGEIFS(Consultas!$H$5:$H$76,Consultas!$F$5:$F$76,A30),2),"")) | AB30: =IF(A30="","",COUNTIF(Consultas!$F$5:$F$76,A30)) | AC30: =IF(OR(A30="",N(M30)=0),"",(COUNTIFS(IRO!$B$5:$B$91,A30,IRO!$AG$5:$AG$91,"Alta")+COUNTIFS(IRO!$B$5:$B$91,A30,IRO!$AG$5:$AG$91,"Média"))/M30) | AD30: =IF(A30="","",IF(AND(AA30<>"",N(AA30)>=prm_Relev_Alerta,T30="Não material"),"Rever: relevância alta para as partes interessadas",IF(AND(T30<>"Não material",AC30<>"",N(AC30)<0.5),"Material com evidência fraca","OK"))) | AE30: =IF(A30="","",IF(T30="Não material","Monitorizar e reavaliar na próxima DMA","Gerir: política, ações, meta e KPI; divulgar (VSME / ESRS voluntário)"))
M31: =IF(A31="","",COUNTIF(IRO!$B$5:$B$91,A31)) | N31: =IF(A31="","",COUNTIFS(IRO!$B$5:$B$91,A31,IRO!$G$5:$G$91,"Impacto")) | O31: =IF(A31="","",COUNTIFS(IRO!$B$5:$B$91,A31,IRO!$G$5:$G$91,"Financeira")) | P31: =IF(OR(A31="",N31=0),"",_xlfn.MAXIFS(IRO!$T$5:$T$91,IRO!$B$5:$B$91,A31)) | Q31: =IF(OR(A31="",O31=0),"",_xlfn.MAXIFS(IRO!$Z$5:$Z$91,IRO!$B$5:$B$91,A31)) | R31: =IF(A31="","",IF(P31="","Não",IF(P31>=prm_Limiar_Impacto,"Sim","Não"))) | S31: =IF(A31="","",IF(Q31="","Não",IF(Q31>=prm_Limiar_Financeiro,"Sim","Não"))) | T31: =IF(A31="","",IF(AND(R31="Sim",S31="Sim"),"Dupla materialidade",IF(R31="Sim","Material — impacto",IF(S31="Sim","Material — financeira","Não material")))) | U31: =IF(A31="","",IF(P31="",0,IF(P31>=prm_Limiar_Alto,4,IF(P31>=prm_Limiar_Impacto,3,IF(P31>=prm_Limiar_Baixo,2,1))))) | V31: =IF(A31="","",IF(Q31="",0,IF(Q31>=prm_Limiar_Alto,4,IF(Q31>=prm_Limiar_Financeiro,3,IF(Q31>=prm_Limiar_Baixo,2,1))))) | W31: =IF(A31="","",N(P31)+N(Q31)) | X31: =IF(A31="","",RANK(W31,$W$5:$W$40,0)+COUNTIFS($W$5:$W$40,W31,$A$5:$A$40,"<"&A31)) | Y31: =IF(A31="","",-SUMIFS(IRO!$AA$5:$AA$91,IRO!$B$5:$B$91,A31,IRO!$F$5:$F$91,"Risco")) | Z31: =IF(A31="","",SUMIFS(IRO!$AA$5:$AA$91,IRO!$B$5:$B$91,A31,IRO!$F$5:$F$91,"Oportunidade")) | AA31: =IF(A31="","",IFERROR(ROUND(AVERAGEIFS(Consultas!$H$5:$H$76,Consultas!$F$5:$F$76,A31),2),"")) | AB31: =IF(A31="","",COUNTIF(Consultas!$F$5:$F$76,A31)) | AC31: =IF(OR(A31="",N(M31)=0),"",(COUNTIFS(IRO!$B$5:$B$91,A31,IRO!$AG$5:$AG$91,"Alta")+COUNTIFS(IRO!$B$5:$B$91,A31,IRO!$AG$5:$AG$91,"Média"))/M31) | AD31: =IF(A31="","",IF(AND(AA31<>"",N(AA31)>=prm_Relev_Alerta,T31="Não material"),"Rever: relevância alta para as partes interessadas",IF(AND(T31<>"Não material",AC31<>"",N(AC31)<0.5),"Material com evidência fraca","OK"))) | AE31: =IF(A31="","",IF(T31="Não material","Monitorizar e reavaliar na próxima DMA","Gerir: política, ações, meta e KPI; divulgar (VSME / ESRS voluntário)"))
M32: =IF(A32="","",COUNTIF(IRO!$B$5:$B$91,A32)) | N32: =IF(A32="","",COUNTIFS(IRO!$B$5:$B$91,A32,IRO!$G$5:$G$91,"Impacto")) | O32: =IF(A32="","",COUNTIFS(IRO!$B$5:$B$91,A32,IRO!$G$5:$G$91,"Financeira")) | P32: =IF(OR(A32="",N32=0),"",_xlfn.MAXIFS(IRO!$T$5:$T$91,IRO!$B$5:$B$91,A32)) | Q32: =IF(OR(A32="",O32=0),"",_xlfn.MAXIFS(IRO!$Z$5:$Z$91,IRO!$B$5:$B$91,A32)) | R32: =IF(A32="","",IF(P32="","Não",IF(P32>=prm_Limiar_Impacto,"Sim","Não"))) | S32: =IF(A32="","",IF(Q32="","Não",IF(Q32>=prm_Limiar_Financeiro,"Sim","Não"))) | T32: =IF(A32="","",IF(AND(R32="Sim",S32="Sim"),"Dupla materialidade",IF(R32="Sim","Material — impacto",IF(S32="Sim","Material — financeira","Não material")))) | U32: =IF(A32="","",IF(P32="",0,IF(P32>=prm_Limiar_Alto,4,IF(P32>=prm_Limiar_Impacto,3,IF(P32>=prm_Limiar_Baixo,2,1))))) | V32: =IF(A32="","",IF(Q32="",0,IF(Q32>=prm_Limiar_Alto,4,IF(Q32>=prm_Limiar_Financeiro,3,IF(Q32>=prm_Limiar_Baixo,2,1))))) | W32: =IF(A32="","",N(P32)+N(Q32)) | X32: =IF(A32="","",RANK(W32,$W$5:$W$40,0)+COUNTIFS($W$5:$W$40,W32,$A$5:$A$40,"<"&A32)) | Y32: =IF(A32="","",-SUMIFS(IRO!$AA$5:$AA$91,IRO!$B$5:$B$91,A32,IRO!$F$5:$F$91,"Risco")) | Z32: =IF(A32="","",SUMIFS(IRO!$AA$5:$AA$91,IRO!$B$5:$B$91,A32,IRO!$F$5:$F$91,"Oportunidade")) | AA32: =IF(A32="","",IFERROR(ROUND(AVERAGEIFS(Consultas!$H$5:$H$76,Consultas!$F$5:$F$76,A32),2),"")) | AB32: =IF(A32="","",COUNTIF(Consultas!$F$5:$F$76,A32)) | AC32: =IF(OR(A32="",N(M32)=0),"",(COUNTIFS(IRO!$B$5:$B$91,A32,IRO!$AG$5:$AG$91,"Alta")+COUNTIFS(IRO!$B$5:$B$91,A32,IRO!$AG$5:$AG$91,"Média"))/M32) | AD32: =IF(A32="","",IF(AND(AA32<>"",N(AA32)>=prm_Relev_Alerta,T32="Não material"),"Rever: relevância alta para as partes interessadas",IF(AND(T32<>"Não material",AC32<>"",N(AC32)<0.5),"Material com evidência fraca","OK"))) | AE32: =IF(A32="","",IF(T32="Não material","Monitorizar e reavaliar na próxima DMA","Gerir: política, ações, meta e KPI; divulgar (VSME / ESRS voluntário)"))
M33: =IF(A33="","",COUNTIF(IRO!$B$5:$B$91,A33)) | N33: =IF(A33="","",COUNTIFS(IRO!$B$5:$B$91,A33,IRO!$G$5:$G$91,"Impacto")) | O33: =IF(A33="","",COUNTIFS(IRO!$B$5:$B$91,A33,IRO!$G$5:$G$91,"Financeira")) | P33: =IF(OR(A33="",N33=0),"",_xlfn.MAXIFS(IRO!$T$5:$T$91,IRO!$B$5:$B$91,A33)) | Q33: =IF(OR(A33="",O33=0),"",_xlfn.MAXIFS(IRO!$Z$5:$Z$91,IRO!$B$5:$B$91,A33)) | R33: =IF(A33="","",IF(P33="","Não",IF(P33>=prm_Limiar_Impacto,"Sim","Não"))) | S33: =IF(A33="","",IF(Q33="","Não",IF(Q33>=prm_Limiar_Financeiro,"Sim","Não"))) | T33: =IF(A33="","",IF(AND(R33="Sim",S33="Sim"),"Dupla materialidade",IF(R33="Sim","Material — impacto",IF(S33="Sim","Material — financeira","Não material")))) | U33: =IF(A33="","",IF(P33="",0,IF(P33>=prm_Limiar_Alto,4,IF(P33>=prm_Limiar_Impacto,3,IF(P33>=prm_Limiar_Baixo,2,1))))) | V33: =IF(A33="","",IF(Q33="",0,IF(Q33>=prm_Limiar_Alto,4,IF(Q33>=prm_Limiar_Financeiro,3,IF(Q33>=prm_Limiar_Baixo,2,1))))) | W33: =IF(A33="","",N(P33)+N(Q33)) | X33: =IF(A33="","",RANK(W33,$W$5:$W$40,0)+COUNTIFS($W$5:$W$40,W33,$A$5:$A$40,"<"&A33)) | Y33: =IF(A33="","",-SUMIFS(IRO!$AA$5:$AA$91,IRO!$B$5:$B$91,A33,IRO!$F$5:$F$91,"Risco")) | Z33: =IF(A33="","",SUMIFS(IRO!$AA$5:$AA$91,IRO!$B$5:$B$91,A33,IRO!$F$5:$F$91,"Oportunidade")) | AA33: =IF(A33="","",IFERROR(ROUND(AVERAGEIFS(Consultas!$H$5:$H$76,Consultas!$F$5:$F$76,A33),2),"")) | AB33: =IF(A33="","",COUNTIF(Consultas!$F$5:$F$76,A33)) | AC33: =IF(OR(A33="",N(M33)=0),"",(COUNTIFS(IRO!$B$5:$B$91,A33,IRO!$AG$5:$AG$91,"Alta")+COUNTIFS(IRO!$B$5:$B$91,A33,IRO!$AG$5:$AG$91,"Média"))/M33) | AD33: =IF(A33="","",IF(AND(AA33<>"",N(AA33)>=prm_Relev_Alerta,T33="Não material"),"Rever: relevância alta para as partes interessadas",IF(AND(T33<>"Não material",AC33<>"",N(AC33)<0.5),"Material com evidência fraca","OK"))) | AE33: =IF(A33="","",IF(T33="Não material","Monitorizar e reavaliar na próxima DMA","Gerir: política, ações, meta e KPI; divulgar (VSME / ESRS voluntário)"))
M34: =IF(A34="","",COUNTIF(IRO!$B$5:$B$91,A34)) | N34: =IF(A34="","",COUNTIFS(IRO!$B$5:$B$91,A34,IRO!$G$5:$G$91,"Impacto")) | O34: =IF(A34="","",COUNTIFS(IRO!$B$5:$B$91,A34,IRO!$G$5:$G$91,"Financeira")) | P34: =IF(OR(A34="",N34=0),"",_xlfn.MAXIFS(IRO!$T$5:$T$91,IRO!$B$5:$B$91,A34)) | Q34: =IF(OR(A34="",O34=0),"",_xlfn.MAXIFS(IRO!$Z$5:$Z$91,IRO!$B$5:$B$91,A34)) | R34: =IF(A34="","",IF(P34="","Não",IF(P34>=prm_Limiar_Impacto,"Sim","Não"))) | S34: =IF(A34="","",IF(Q34="","Não",IF(Q34>=prm_Limiar_Financeiro,"Sim","Não"))) | T34: =IF(A34="","",IF(AND(R34="Sim",S34="Sim"),"Dupla materialidade",IF(R34="Sim","Material — impacto",IF(S34="Sim","Material — financeira","Não material")))) | U34: =IF(A34="","",IF(P34="",0,IF(P34>=prm_Limiar_Alto,4,IF(P34>=prm_Limiar_Impacto,3,IF(P34>=prm_Limiar_Baixo,2,1))))) | V34: =IF(A34="","",IF(Q34="",0,IF(Q34>=prm_Limiar_Alto,4,IF(Q34>=prm_Limiar_Financeiro,3,IF(Q34>=prm_Limiar_Baixo,2,1))))) | W34: =IF(A34="","",N(P34)+N(Q34)) | X34: =IF(A34="","",RANK(W34,$W$5:$W$40,0)+COUNTIFS($W$5:$W$40,W34,$A$5:$A$40,"<"&A34)) | Y34: =IF(A34="","",-SUMIFS(IRO!$AA$5:$AA$91,IRO!$B$5:$B$91,A34,IRO!$F$5:$F$91,"Risco")) | Z34: =IF(A34="","",SUMIFS(IRO!$AA$5:$AA$91,IRO!$B$5:$B$91,A34,IRO!$F$5:$F$91,"Oportunidade")) | AA34: =IF(A34="","",IFERROR(ROUND(AVERAGEIFS(Consultas!$H$5:$H$76,Consultas!$F$5:$F$76,A34),2),"")) | AB34: =IF(A34="","",COUNTIF(Consultas!$F$5:$F$76,A34)) | AC34: =IF(OR(A34="",N(M34)=0),"",(COUNTIFS(IRO!$B$5:$B$91,A34,IRO!$AG$5:$AG$91,"Alta")+COUNTIFS(IRO!$B$5:$B$91,A34,IRO!$AG$5:$AG$91,"Média"))/M34) | AD34: =IF(A34="","",IF(AND(AA34<>"",N(AA34)>=prm_Relev_Alerta,T34="Não material"),"Rever: relevância alta para as partes interessadas",IF(AND(T34<>"Não material",AC34<>"",N(AC34)<0.5),"Material com evidência fraca","OK"))) | AE34: =IF(A34="","",IF(T34="Não material","Monitorizar e reavaliar na próxima DMA","Gerir: política, ações, meta e KPI; divulgar (VSME / ESRS voluntário)"))
M35: =IF(A35="","",COUNTIF(IRO!$B$5:$B$91,A35)) | N35: =IF(A35="","",COUNTIFS(IRO!$B$5:$B$91,A35,IRO!$G$5:$G$91,"Impacto")) | O35: =IF(A35="","",COUNTIFS(IRO!$B$5:$B$91,A35,IRO!$G$5:$G$91,"Financeira")) | P35: =IF(OR(A35="",N35=0),"",_xlfn.MAXIFS(IRO!$T$5:$T$91,IRO!$B$5:$B$91,A35)) | Q35: =IF(OR(A35="",O35=0),"",_xlfn.MAXIFS(IRO!$Z$5:$Z$91,IRO!$B$5:$B$91,A35)) | R35: =IF(A35="","",IF(P35="","Não",IF(P35>=prm_Limiar_Impacto,"Sim","Não"))) | S35: =IF(A35="","",IF(Q35="","Não",IF(Q35>=prm_Limiar_Financeiro,"Sim","Não"))) | T35: =IF(A35="","",IF(AND(R35="Sim",S35="Sim"),"Dupla materialidade",IF(R35="Sim","Material — impacto",IF(S35="Sim","Material — financeira","Não material")))) | U35: =IF(A35="","",IF(P35="",0,IF(P35>=prm_Limiar_Alto,4,IF(P35>=prm_Limiar_Impacto,3,IF(P35>=prm_Limiar_Baixo,2,1))))) | V35: =IF(A35="","",IF(Q35="",0,IF(Q35>=prm_Limiar_Alto,4,IF(Q35>=prm_Limiar_Financeiro,3,IF(Q35>=prm_Limiar_Baixo,2,1))))) | W35: =IF(A35="","",N(P35)+N(Q35)) | X35: =IF(A35="","",RANK(W35,$W$5:$W$40,0)+COUNTIFS($W$5:$W$40,W35,$A$5:$A$40,"<"&A35)) | Y35: =IF(A35="","",-SUMIFS(IRO!$AA$5:$AA$91,IRO!$B$5:$B$91,A35,IRO!$F$5:$F$91,"Risco")) | Z35: =IF(A35="","",SUMIFS(IRO!$AA$5:$AA$91,IRO!$B$5:$B$91,A35,IRO!$F$5:$F$91,"Oportunidade")) | AA35: =IF(A35="","",IFERROR(ROUND(AVERAGEIFS(Consultas!$H$5:$H$76,Consultas!$F$5:$F$76,A35),2),"")) | AB35: =IF(A35="","",COUNTIF(Consultas!$F$5:$F$76,A35)) | AC35: =IF(OR(A35="",N(M35)=0),"",(COUNTIFS(IRO!$B$5:$B$91,A35,IRO!$AG$5:$AG$91,"Alta")+COUNTIFS(IRO!$B$5:$B$91,A35,IRO!$AG$5:$AG$91,"Média"))/M35) | AD35: =IF(A35="","",IF(AND(AA35<>"",N(AA35)>=prm_Relev_Alerta,T35="Não material"),"Rever: relevância alta para as partes interessadas",IF(AND(T35<>"Não material",AC35<>"",N(AC35)<0.5),"Material com evidência fraca","OK"))) | AE35: =IF(A35="","",IF(T35="Não material","Monitorizar e reavaliar na próxima DMA","Gerir: política, ações, meta e KPI; divulgar (VSME / ESRS voluntário)"))
M36: =IF(A36="","",COUNTIF(IRO!$B$5:$B$91,A36)) | N36: =IF(A36="","",COUNTIFS(IRO!$B$5:$B$91,A36,IRO!$G$5:$G$91,"Impacto")) | O36: =IF(A36="","",COUNTIFS(IRO!$B$5:$B$91,A36,IRO!$G$5:$G$91,"Financeira")) | P36: =IF(OR(A36="",N36=0),"",_xlfn.MAXIFS(IRO!$T$5:$T$91,IRO!$B$5:$B$91,A36)) | Q36: =IF(OR(A36="",O36=0),"",_xlfn.MAXIFS(IRO!$Z$5:$Z$91,IRO!$B$5:$B$91,A36)) | R36: =IF(A36="","",IF(P36="","Não",IF(P36>=prm_Limiar_Impacto,"Sim","Não"))) | S36: =IF(A36="","",IF(Q36="","Não",IF(Q36>=prm_Limiar_Financeiro,"Sim","Não"))) | T36: =IF(A36="","",IF(AND(R36="Sim",S36="Sim"),"Dupla materialidade",IF(R36="Sim","Material — impacto",IF(S36="Sim","Material — financeira","Não material")))) | U36: =IF(A36="","",IF(P36="",0,IF(P36>=prm_Limiar_Alto,4,IF(P36>=prm_Limiar_Impacto,3,IF(P36>=prm_Limiar_Baixo,2,1))))) | V36: =IF(A36="","",IF(Q36="",0,IF(Q36>=prm_Limiar_Alto,4,IF(Q36>=prm_Limiar_Financeiro,3,IF(Q36>=prm_Limiar_Baixo,2,1))))) | W36: =IF(A36="","",N(P36)+N(Q36)) | X36: =IF(A36="","",RANK(W36,$W$5:$W$40,0)+COUNTIFS($W$5:$W$40,W36,$A$5:$A$40,"<"&A36)) | Y36: =IF(A36="","",-SUMIFS(IRO!$AA$5:$AA$91,IRO!$B$5:$B$91,A36,IRO!$F$5:$F$91,"Risco")) | Z36: =IF(A36="","",SUMIFS(IRO!$AA$5:$AA$91,IRO!$B$5:$B$91,A36,IRO!$F$5:$F$91,"Oportunidade")) | AA36: =IF(A36="","",IFERROR(ROUND(AVERAGEIFS(Consultas!$H$5:$H$76,Consultas!$F$5:$F$76,A36),2),"")) | AB36: =IF(A36="","",COUNTIF(Consultas!$F$5:$F$76,A36)) | AC36: =IF(OR(A36="",N(M36)=0),"",(COUNTIFS(IRO!$B$5:$B$91,A36,IRO!$AG$5:$AG$91,"Alta")+COUNTIFS(IRO!$B$5:$B$91,A36,IRO!$AG$5:$AG$91,"Média"))/M36) | AD36: =IF(A36="","",IF(AND(AA36<>"",N(AA36)>=prm_Relev_Alerta,T36="Não material"),"Rever: relevância alta para as partes interessadas",IF(AND(T36<>"Não material",AC36<>"",N(AC36)<0.5),"Material com evidência fraca","OK"))) | AE36: =IF(A36="","",IF(T36="Não material","Monitorizar e reavaliar na próxima DMA","Gerir: política, ações, meta e KPI; divulgar (VSME / ESRS voluntário)"))
M37: =IF(A37="","",COUNTIF(IRO!$B$5:$B$91,A37)) | N37: =IF(A37="","",COUNTIFS(IRO!$B$5:$B$91,A37,IRO!$G$5:$G$91,"Impacto")) | O37: =IF(A37="","",COUNTIFS(IRO!$B$5:$B$91,A37,IRO!$G$5:$G$91,"Financeira")) | P37: =IF(OR(A37="",N37=0),"",_xlfn.MAXIFS(IRO!$T$5:$T$91,IRO!$B$5:$B$91,A37)) | Q37: =IF(OR(A37="",O37=0),"",_xlfn.MAXIFS(IRO!$Z$5:$Z$91,IRO!$B$5:$B$91,A37)) | R37: =IF(A37="","",IF(P37="","Não",IF(P37>=prm_Limiar_Impacto,"Sim","Não"))) | S37: =IF(A37="","",IF(Q37="","Não",IF(Q37>=prm_Limiar_Financeiro,"Sim","Não"))) | T37: =IF(A37="","",IF(AND(R37="Sim",S37="Sim"),"Dupla materialidade",IF(R37="Sim","Material — impacto",IF(S37="Sim","Material — financeira","Não material")))) | U37: =IF(A37="","",IF(P37="",0,IF(P37>=prm_Limiar_Alto,4,IF(P37>=prm_Limiar_Impacto,3,IF(P37>=prm_Limiar_Baixo,2,1))))) | V37: =IF(A37="","",IF(Q37="",0,IF(Q37>=prm_Limiar_Alto,4,IF(Q37>=prm_Limiar_Financeiro,3,IF(Q37>=prm_Limiar_Baixo,2,1))))) | W37: =IF(A37="","",N(P37)+N(Q37)) | X37: =IF(A37="","",RANK(W37,$W$5:$W$40,0)+COUNTIFS($W$5:$W$40,W37,$A$5:$A$40,"<"&A37)) | Y37: =IF(A37="","",-SUMIFS(IRO!$AA$5:$AA$91,IRO!$B$5:$B$91,A37,IRO!$F$5:$F$91,"Risco")) | Z37: =IF(A37="","",SUMIFS(IRO!$AA$5:$AA$91,IRO!$B$5:$B$91,A37,IRO!$F$5:$F$91,"Oportunidade")) | AA37: =IF(A37="","",IFERROR(ROUND(AVERAGEIFS(Consultas!$H$5:$H$76,Consultas!$F$5:$F$76,A37),2),"")) | AB37: =IF(A37="","",COUNTIF(Consultas!$F$5:$F$76,A37)) | AC37: =IF(OR(A37="",N(M37)=0),"",(COUNTIFS(IRO!$B$5:$B$91,A37,IRO!$AG$5:$AG$91,"Alta")+COUNTIFS(IRO!$B$5:$B$91,A37,IRO!$AG$5:$AG$91,"Média"))/M37) | AD37: =IF(A37="","",IF(AND(AA37<>"",N(AA37)>=prm_Relev_Alerta,T37="Não material"),"Rever: relevância alta para as partes interessadas",IF(AND(T37<>"Não material",AC37<>"",N(AC37)<0.5),"Material com evidência fraca","OK"))) | AE37: =IF(A37="","",IF(T37="Não material","Monitorizar e reavaliar na próxima DMA","Gerir: política, ações, meta e KPI; divulgar (VSME / ESRS voluntário)"))
M38: =IF(A38="","",COUNTIF(IRO!$B$5:$B$91,A38)) | N38: =IF(A38="","",COUNTIFS(IRO!$B$5:$B$91,A38,IRO!$G$5:$G$91,"Impacto")) | O38: =IF(A38="","",COUNTIFS(IRO!$B$5:$B$91,A38,IRO!$G$5:$G$91,"Financeira")) | P38: =IF(OR(A38="",N38=0),"",_xlfn.MAXIFS(IRO!$T$5:$T$91,IRO!$B$5:$B$91,A38)) | Q38: =IF(OR(A38="",O38=0),"",_xlfn.MAXIFS(IRO!$Z$5:$Z$91,IRO!$B$5:$B$91,A38)) | R38: =IF(A38="","",IF(P38="","Não",IF(P38>=prm_Limiar_Impacto,"Sim","Não"))) | S38: =IF(A38="","",IF(Q38="","Não",IF(Q38>=prm_Limiar_Financeiro,"Sim","Não"))) | T38: =IF(A38="","",IF(AND(R38="Sim",S38="Sim"),"Dupla materialidade",IF(R38="Sim","Material — impacto",IF(S38="Sim","Material — financeira","Não material")))) | U38: =IF(A38="","",IF(P38="",0,IF(P38>=prm_Limiar_Alto,4,IF(P38>=prm_Limiar_Impacto,3,IF(P38>=prm_Limiar_Baixo,2,1))))) | V38: =IF(A38="","",IF(Q38="",0,IF(Q38>=prm_Limiar_Alto,4,IF(Q38>=prm_Limiar_Financeiro,3,IF(Q38>=prm_Limiar_Baixo,2,1))))) | W38: =IF(A38="","",N(P38)+N(Q38)) | X38: =IF(A38="","",RANK(W38,$W$5:$W$40,0)+COUNTIFS($W$5:$W$40,W38,$A$5:$A$40,"<"&A38)) | Y38: =IF(A38="","",-SUMIFS(IRO!$AA$5:$AA$91,IRO!$B$5:$B$91,A38,IRO!$F$5:$F$91,"Risco")) | Z38: =IF(A38="","",SUMIFS(IRO!$AA$5:$AA$91,IRO!$B$5:$B$91,A38,IRO!$F$5:$F$91,"Oportunidade")) | AA38: =IF(A38="","",IFERROR(ROUND(AVERAGEIFS(Consultas!$H$5:$H$76,Consultas!$F$5:$F$76,A38),2),"")) | AB38: =IF(A38="","",COUNTIF(Consultas!$F$5:$F$76,A38)) | AC38: =IF(OR(A38="",N(M38)=0),"",(COUNTIFS(IRO!$B$5:$B$91,A38,IRO!$AG$5:$AG$91,"Alta")+COUNTIFS(IRO!$B$5:$B$91,A38,IRO!$AG$5:$AG$91,"Média"))/M38) | AD38: =IF(A38="","",IF(AND(AA38<>"",N(AA38)>=prm_Relev_Alerta,T38="Não material"),"Rever: relevância alta para as partes interessadas",IF(AND(T38<>"Não material",AC38<>"",N(AC38)<0.5),"Material com evidência fraca","OK"))) | AE38: =IF(A38="","",IF(T38="Não material","Monitorizar e reavaliar na próxima DMA","Gerir: política, ações, meta e KPI; divulgar (VSME / ESRS voluntário)"))
M39: =IF(A39="","",COUNTIF(IRO!$B$5:$B$91,A39)) | N39: =IF(A39="","",COUNTIFS(IRO!$B$5:$B$91,A39,IRO!$G$5:$G$91,"Impacto")) | O39: =IF(A39="","",COUNTIFS(IRO!$B$5:$B$91,A39,IRO!$G$5:$G$91,"Financeira")) | P39: =IF(OR(A39="",N39=0),"",_xlfn.MAXIFS(IRO!$T$5:$T$91,IRO!$B$5:$B$91,A39)) | Q39: =IF(OR(A39="",O39=0),"",_xlfn.MAXIFS(IRO!$Z$5:$Z$91,IRO!$B$5:$B$91,A39)) | R39: =IF(A39="","",IF(P39="","Não",IF(P39>=prm_Limiar_Impacto,"Sim","Não"))) | S39: =IF(A39="","",IF(Q39="","Não",IF(Q39>=prm_Limiar_Financeiro,"Sim","Não"))) | T39: =IF(A39="","",IF(AND(R39="Sim",S39="Sim"),"Dupla materialidade",IF(R39="Sim","Material — impacto",IF(S39="Sim","Material — financeira","Não material")))) | U39: =IF(A39="","",IF(P39="",0,IF(P39>=prm_Limiar_Alto,4,IF(P39>=prm_Limiar_Impacto,3,IF(P39>=prm_Limiar_Baixo,2,1))))) | V39: =IF(A39="","",IF(Q39="",0,IF(Q39>=prm_Limiar_Alto,4,IF(Q39>=prm_Limiar_Financeiro,3,IF(Q39>=prm_Limiar_Baixo,2,1))))) | W39: =IF(A39="","",N(P39)+N(Q39)) | X39: =IF(A39="","",RANK(W39,$W$5:$W$40,0)+COUNTIFS($W$5:$W$40,W39,$A$5:$A$40,"<"&A39)) | Y39: =IF(A39="","",-SUMIFS(IRO!$AA$5:$AA$91,IRO!$B$5:$B$91,A39,IRO!$F$5:$F$91,"Risco")) | Z39: =IF(A39="","",SUMIFS(IRO!$AA$5:$AA$91,IRO!$B$5:$B$91,A39,IRO!$F$5:$F$91,"Oportunidade")) | AA39: =IF(A39="","",IFERROR(ROUND(AVERAGEIFS(Consultas!$H$5:$H$76,Consultas!$F$5:$F$76,A39),2),"")) | AB39: =IF(A39="","",COUNTIF(Consultas!$F$5:$F$76,A39)) | AC39: =IF(OR(A39="",N(M39)=0),"",(COUNTIFS(IRO!$B$5:$B$91,A39,IRO!$AG$5:$AG$91,"Alta")+COUNTIFS(IRO!$B$5:$B$91,A39,IRO!$AG$5:$AG$91,"Média"))/M39) | AD39: =IF(A39="","",IF(AND(AA39<>"",N(AA39)>=prm_Relev_Alerta,T39="Não material"),"Rever: relevância alta para as partes interessadas",IF(AND(T39<>"Não material",AC39<>"",N(AC39)<0.5),"Material com evidência fraca","OK"))) | AE39: =IF(A39="","",IF(T39="Não material","Monitorizar e reavaliar na próxima DMA","Gerir: política, ações, meta e KPI; divulgar (VSME / ESRS voluntário)"))
M40: =IF(A40="","",COUNTIF(IRO!$B$5:$B$91,A40)) | N40: =IF(A40="","",COUNTIFS(IRO!$B$5:$B$91,A40,IRO!$G$5:$G$91,"Impacto")) | O40: =IF(A40="","",COUNTIFS(IRO!$B$5:$B$91,A40,IRO!$G$5:$G$91,"Financeira")) | P40: =IF(OR(A40="",N40=0),"",_xlfn.MAXIFS(IRO!$T$5:$T$91,IRO!$B$5:$B$91,A40)) | Q40: =IF(OR(A40="",O40=0),"",_xlfn.MAXIFS(IRO!$Z$5:$Z$91,IRO!$B$5:$B$91,A40)) | R40: =IF(A40="","",IF(P40="","Não",IF(P40>=prm_Limiar_Impacto,"Sim","Não"))) | S40: =IF(A40="","",IF(Q40="","Não",IF(Q40>=prm_Limiar_Financeiro,"Sim","Não"))) | T40: =IF(A40="","",IF(AND(R40="Sim",S40="Sim"),"Dupla materialidade",IF(R40="Sim","Material — impacto",IF(S40="Sim","Material — financeira","Não material")))) | U40: =IF(A40="","",IF(P40="",0,IF(P40>=prm_Limiar_Alto,4,IF(P40>=prm_Limiar_Impacto,3,IF(P40>=prm_Limiar_Baixo,2,1))))) | V40: =IF(A40="","",IF(Q40="",0,IF(Q40>=prm_Limiar_Alto,4,IF(Q40>=prm_Limiar_Financeiro,3,IF(Q40>=prm_Limiar_Baixo,2,1))))) | W40: =IF(A40="","",N(P40)+N(Q40)) | X40: =IF(A40="","",RANK(W40,$W$5:$W$40,0)+COUNTIFS($W$5:$W$40,W40,$A$5:$A$40,"<"&A40)) | Y40: =IF(A40="","",-SUMIFS(IRO!$AA$5:$AA$91,IRO!$B$5:$B$91,A40,IRO!$F$5:$F$91,"Risco")) | Z40: =IF(A40="","",SUMIFS(IRO!$AA$5:$AA$91,IRO!$B$5:$B$91,A40,IRO!$F$5:$F$91,"Oportunidade")) | AA40: =IF(A40="","",IFERROR(ROUND(AVERAGEIFS(Consultas!$H$5:$H$76,Consultas!$F$5:$F$76,A40),2),"")) | AB40: =IF(A40="","",COUNTIF(Consultas!$F$5:$F$76,A40)) | AC40: =IF(OR(A40="",N(M40)=0),"",(COUNTIFS(IRO!$B$5:$B$91,A40,IRO!$AG$5:$AG$91,"Alta")+COUNTIFS(IRO!$B$5:$B$91,A40,IRO!$AG$5:$AG$91,"Média"))/M40) | AD40: =IF(A40="","",IF(AND(AA40<>"",N(AA40)>=prm_Relev_Alerta,T40="Não material"),"Rever: relevância alta para as partes interessadas",IF(AND(T40<>"Não material",AC40<>"",N(AC40)<0.5),"Material com evidência fraca","OK"))) | AE40: =IF(A40="","",IF(T40="Não material","Monitorizar e reavaliar na próxima DMA","Gerir: política, ações, meta e KPI; divulgar (VSME / ESRS voluntário)"))

Sheet IRO
A1: IMPACTOS, RISCOS E OPORTUNIDADES (IRO) — AVALIAÇÃO DE DUPLA MATERIALIDADE
A2: Impacto: Gravidade × Probabilidade efetiva · Financeira: Magnitude (€) × Probabilidade · Material se ≥ limiar (folha Listas) · Cinzento = calculado
A4: ID_IRO | B4: ID_Tema | C4: Tema | D4: Pilar | E4: ESRS_Topico | F4: Tipo_IRO | G4: Dimensao | H4: Descricao | I4: Natureza | J4: Etapa_Cadeia_Valor | K4: Horizonte | L4: Afetados | M4: Direitos_Humanos | N4: Magnitude | O4: Alcance | P4: Irremediabilidade | Q4: Probabilidade | R4: Gravidade | S4: Probabilidade_Efetiva | T4: Score_Impacto | U4: Mecanismo_Financeiro | V4: Rubrica_Financeira | W4: Efeito_Financeiro_EUR_Ano | X4: Probabilidade_Financeira | Y4: Magnitude_Financeira | Z4: Score_Financeiro | AA4: Efeito_Ponderado_EUR | AB4: Score | AC4: Material | AD4: Classificacao_IRO | AE4: Ranking_IRO | AF4: Evidencia_Resumo | AG4: Qualidade_Evidencia | AH4: N_Evidencias | AI4: Controlo_Qualidade | AJ4: IDs_Contexto | AK4: ID_RO | AL4: ID_Registo_Corporativo | AM4: IDs_Aspetos | AN4: ID_Legal | AO4: ID_OBJ | AP4: ID_KPI | AQ4: ID_PAM | AR4: Resposta_Gestao | AS4: Responsavel | AT4: Estado_Validacao | AU4: Data_Avaliacao | AV4: Proxima_Revisao | AW4: Notas
A5: IRO-001 | B5: DM-01 | C5: =IF(B5="","",IFERROR(INDEX(Temas!$E$5:$E$40,MATCH(B5,Temas!$A$5:$A$40,0)),"ID_Tema não encontrado")) -> Emissões de GEE (âmbitos 1, 2 e 3) | D5: =IF(B5="","",IFERROR(INDEX(Temas!$B$5:$B$40,MATCH(B5,Temas!$A$5:$A$40,0)),"")) -> Ambiental | E5: =IF(B5="","",IFERROR(INDEX(Temas!$C$5:$C$40,MATCH(B5,Temas!$A$5:$A$40,0)),"")) -> E1 Alterações climáticas | F5: Impacto negativo | G5: =IF(F5="","",IF(LEFT(F5,7)="Impacto","Impacto","Financeira")) -> Impacto | H5: Emissões de GEE do âmbito 2 (≈ 860 tCO2e em 2026, location-based) associadas ao consumo de 7,8 GWh de eletricidade e fugas de R410A. | I5: Real | J5: Operações próprias | K5: Curto prazo (≤ 1 ano) | L5: Clima global; sociedade | M5: Não | N5: 3 | O5: 4 | P5: 4 | R5: =IF(G5<>"Impacto","",IF(F5="Impacto negativo",IF(COUNT(N5,O5,P5)=3,ROUND(AVERAGE(N5,O5,P5),2),""),IF(COUNT(N5,O5)=2,ROUND(AVERAGE(N5,O5),2),""))) -> 3.67 | S5: =IF(OR(G5<>"Impacto",R5=""),"",IF(I5="Real",5,IF(AND(M5="Sim",R5>=prm_Grav_DH),5,IF(Q5="","",Q5)))) -> 5 | T5: =IF(OR(R5="",S5=""),"",ROUND(R5*S5,1)) -> 18.4 | Y5: =IF(OR(G5<>"Financeira",W5=""),"",MATCH(W5,esc_Fin_Limite,1)) | Z5: =IF(OR(Y5="",X5=""),"",Y5*X5) | AA5: =IF(Z5="","",ROUND(W5*INDEX(esc_Prob_Media,X5),0)*IF(F5="Risco",-1,1)) | AB5: =IF(G5="","",IF(G5="Impacto",T5,Z5)) -> 18.4 | AC5: =IF(OR(G5="",AB5=""),"",IF(AB5>=IF(G5="Impacto",prm_Limiar_Impacto,prm_Limiar_Financeiro),"Sim","Não")) -> Sim | AD5: =IF(AC5="","",IF(AC5="Sim",IF(G5="Impacto","Material — impacto","Material — financeiro"),"Não material")) -> Material — impacto | AE5: =IF(AB5="","",RANK(AB5,$AB$5:$AB$91,0)+COUNTIFS($AB$5:$AB$91,AB5,$A$5:$A$91,"<"&A5)) -> 6 | AF5: EMAS-06 (865 tCO2e, âmbitos 1 + 2 LB); fator 0,110 kgCO2e/kWh; fuga de 3,2 kg de R410A | AG5: Alta | AH5: =IF(A5="","",COUNTIF(Evidencias!$B$5:$B$115,A5)) -> 2 | AI5: =IF(A5="","",IF(G5="","FALTA tipo de IRO",IF(AB5="",IF(G5="Impacto","FALTA pontuação de impacto","FALTA estimativa financeira"),IF(AH5=0,"Sem evidência registada","OK")))) -> OK | AJ5: PES-01 | AM5: AA-007; AA-010; AA-021; AA-025 | AN5: LEG-08; LEG-07 | AO5: OBJ-01 | AP5: KPI-08 | AQ5: PAM-26-01 | AR5: Eficiência energética (OBJ-01), garantias de origem renováveis e autoconsumo fotovoltaico. | AS5: Gestor do SGA / EHS (Responsável Ambiental) | AT5: Validado pelo responsável | AU5: 46289 | AV5: =IF(AU5="","",EDATE(AU5,IF(AC5="Sim",prm_Meses_Rev_Material,prm_Meses_Rev_Outros))) -> 46470
A6: IRO-002 | B6: DM-01 | C6: =IF(B6="","",IFERROR(INDEX(Temas!$E$5:$E$40,MATCH(B6,Temas!$A$5:$A$40,0)),"ID_Tema não encontrado")) -> Emissões de GEE (âmbitos 1, 2 e 3) | D6: =IF(B6="","",IFERROR(INDEX(Temas!$B$5:$B$40,MATCH(B6,Temas!$A$5:$A$40,0)),"")) -> Ambiental | E6: =IF(B6="","",IFERROR(INDEX(Temas!$C$5:$C$40,MATCH(B6,Temas!$A$5:$A$40,0)),"")) -> E1 Alterações climáticas | F6: Impacto negativo | G6: =IF(F6="","",IF(LEFT(F6,7)="Impacto","Impacto","Financeira")) -> Impacto | H6: Emissões do âmbito 3 a montante na produção de ≈ 712 t/ano de polímeros virgens (≈ 1.350 tCO2e/ano, estimativa por fator médio 1,9 kgCO2e/kg). | I6: Real | J6: Upstream — fornecedores | K6: Curto prazo (≤ 1 ano) | L6: Clima global | M6: Não | N6: 4 | O6: 4 | P6: 4 | R6: =IF(G6<>"Impacto","",IF(F6="Impacto negativo",IF(COUNT(N6,O6,P6)=3,ROUND(AVERAGE(N6,O6,P6),2),""),IF(COUNT(N6,O6)=2,ROUND(AVERAGE(N6,O6),2),""))) -> 4 | S6: =IF(OR(G6<>"Impacto",R6=""),"",IF(I6="Real",5,IF(AND(M6="Sim",R6>=prm_Grav_DH),5,IF(Q6="","",Q6)))) -> 5 | T6: =IF(OR(R6="",S6=""),"",ROUND(R6*S6,1)) -> 20 | Y6: =IF(OR(G6<>"Financeira",W6=""),"",MATCH(W6,esc_Fin_Limite,1)) | Z6: =IF(OR(Y6="",X6=""),"",Y6*X6) | AA6: =IF(Z6="","",ROUND(W6*INDEX(esc_Prob_Media,X6),0)*IF(F6="Risco",-1,1)) | AB6: =IF(G6="","",IF(G6="Impacto",T6,Z6)) -> 20 | AC6: =IF(OR(G6="",AB6=""),"",IF(AB6>=IF(G6="Impacto",prm_Limiar_Impacto,prm_Limiar_Financeiro),"Sim","Não")) -> Sim | AD6: =IF(AC6="","",IF(AC6="Sim",IF(G6="Impacto","Material — impacto","Material — financeiro"),"Não material")) -> Material — impacto | AE6: =IF(AB6="","",RANK(AB6,$AB$5:$AB$91,0)+COUNTIFS($AB$5:$AB$91,AB6,$A$5:$A$91,"<"&A6)) -> 1 | AF6: AA-001 (712,4 t/ano); fator médio de literatura — estimativa não verificada | AG6: Baixa | AH6: =IF(A6="","",COUNTIF(Evidencias!$B$5:$B$115,A6)) -> 2 | AI6: =IF(A6="","",IF(G6="","FALTA tipo de IRO",IF(AB6="",IF(G6="Impacto","FALTA pontuação de impacto","FALTA estimativa financeira"),IF(AH6=0,"Sem evidência registada","OK")))) -> OK | AJ6: PES-01; SWT-T02 | AM6: AA-001 | AR6: Inventário do âmbito 3 (categoria 1) com fatores de fornecedores; aumentar PCR e lightweighting. | AS6: Gestor do SGA / EHS (Responsável Ambiental) | AT6: Validado pelo responsável | AU6: 46289 | AV6: =IF(AU6="","",EDATE(AU6,IF(AC6="Sim",prm_Meses_Rev_Material,prm_Meses_Rev_Outros))) -> 46470 | AW6: Principal fonte de emissões da cadeia de valor; exige dados primários de fornecedores.
A7: IRO-003 | B7: DM-01 | C7: =IF(B7="","",IFERROR(INDEX(Temas!$E$5:$E$40,MATCH(B7,Temas!$A$5:$A$40,0)),"ID_Tema não encontrado")) -> Emissões de GEE (âmbitos 1, 2 e 3) | D7: =IF(B7="","",IFERROR(INDEX(Temas!$B$5:$B$40,MATCH(B7,Temas!$A$5:$A$40,0)),"")) -> Ambiental | E7: =IF(B7="","",IFERROR(INDEX(Temas!$C$5:$C$40,MATCH(B7,Temas!$A$5:$A$40,0)),"")) -> E1 Alterações climáticas | F7: Impacto negativo | G7: =IF(F7="","",IF(LEFT(F7,7)="Impacto","Impacto","Financeira")) -> Impacto | H7: Emissões do transporte rodoviário de matérias-primas e de produto acabado a clientes. | I7: Real | J7: Downstream — distribuição | K7: Curto prazo (≤ 1 ano) | L7: Clima global; qualidade do ar local | M7: Não | N7: 2 | O7: 2 | P7: 3 | R7: =IF(G7<>"Impacto","",IF(F7="Impacto negativo",IF(COUNT(N7,O7,P7)=3,ROUND(AVERAGE(N7,O7,P7),2),""),IF(COUNT(N7,O7)=2,ROUND(AVERAGE(N7,O7),2),""))) -> 2.33 | S7: =IF(OR(G7<>"Impacto",R7=""),"",IF(I7="Real",5,IF(AND(M7="Sim",R7>=prm_Grav_DH),5,IF(Q7="","",Q7)))) -> 5 | T7: =IF(OR(R7="",S7=""),"",ROUND(R7*S7,1)) -> 11.7 | Y7: =IF(OR(G7<>"Financeira",W7=""),"",MATCH(W7,esc_Fin_Limite,1)) | Z7: =IF(OR(Y7="",X7=""),"",Y7*X7) | AA7: =IF(Z7="","",ROUND(W7*INDEX(esc_Prob_Media,X7),0)*IF(F7="Risco",-1,1)) | AB7: =IF(G7="","",IF(G7="Impacto",T7,Z7)) -> 11.7 | AC7: =IF(OR(G7="",AB7=""),"",IF(AB7>=IF(G7="Impacto",prm_Limiar_Impacto,prm_Limiar_Financeiro),"Sim","Não")) -> Não | AD7: =IF(AC7="","",IF(AC7="Sim",IF(G7="Impacto","Material — impacto","Material — financeiro"),"Não material")) -> Não material | AE7: =IF(AB7="","",RANK(AB7,$AB$5:$AB$91,0)+COUNTIFS($AB$5:$AB$91,AB7,$A$5:$A$91,"<"&A7)) -> 28 | AF7: AA-002, AA-040 (sem quantificação de t.km) | AG7: Baixa | AH7: =IF(A7="","",COUNTIF(Evidencias!$B$5:$B$115,A7)) -> 1 | AI7: =IF(A7="","",IF(G7="","FALTA tipo de IRO",IF(AB7="",IF(G7="Impacto","FALTA pontuação de impacto","FALTA estimativa financeira"),IF(AH7=0,"Sem evidência registada","OK")))) -> OK | AM7: AA-002; AA-040 | AR7: Recolher t.km por cliente/fornecedor e otimizar cargas. | AS7: Responsável de Armazém e Logística | AT7: Validado pelo responsável | AU7: 46289 | AV7: =IF(AU7="","",EDATE(AU7,IF(AC7="Sim",prm_Meses_Rev_Material,prm_Meses_Rev_Outros))) -> 46654
A8: IRO-004 | B8: DM-01 | C8: =IF(B8="","",IFERROR(INDEX(Temas!$E$5:$E$40,MATCH(B8,Temas!$A$5:$A$40,0)),"ID_Tema não encontrado")) -> Emissões de GEE (âmbitos 1, 2 e 3) | D8: =IF(B8="","",IFERROR(INDEX(Temas!$B$5:$B$40,MATCH(B8,Temas!$A$5:$A$40,0)),"")) -> Ambiental | E8: =IF(B8="","",IFERROR(INDEX(Temas!$C$5:$C$40,MATCH(B8,Temas!$A$5:$A$40,0)),"")) -> E1 Alterações climáticas | F8: Risco | G8: =IF(F8="","",IF(LEFT(F8,7)="Impacto","Impacto","Financeira")) -> Financeira | H8: Perda ou redução de contratos com marcas europeias que exigem pegada de carbono do produto e metas de redução aos fornecedores. | J8: Downstream — distribuição | K8: Médio prazo (1–5 anos) | R8: =IF(G8<>"Impacto","",IF(F8="Impacto negativo",IF(COUNT(N8,O8,P8)=3,ROUND(AVERAGE(N8,O8,P8),2),""),IF(COUNT(N8,O8)=2,ROUND(AVERAGE(N8,O8),2),""))) | S8: =IF(OR(G8<>"Impacto",R8=""),"",IF(I8="Real",5,IF(AND(M8="Sim",R8>=prm_Grav_DH),5,IF(Q8="","",Q8)))) | T8: =IF(OR(R8="",S8=""),"",ROUND(R8*S8,1)) | U8: Receitas: ≈ 4% da faturação (3,68 M€) em clientes com requisitos climáticos em 2027; pressuposto interno. | V8: Receitas | W8: 150000 | X8: 3 | Y8: =IF(OR(G8<>"Financeira",W8=""),"",MATCH(W8,esc_Fin_Limite,1)) -> 4 | Z8: =IF(OR(Y8="",X8=""),"",Y8*X8) -> 12 | AA8: =IF(Z8="","",ROUND(W8*INDEX(esc_Prob_Media,X8),0)*IF(F8="Risco",-1,1)) -> -60000 | AB8: =IF(G8="","",IF(G8="Impacto",T8,Z8)) -> 12 | AC8: =IF(OR(G8="",AB8=""),"",IF(AB8>=IF(G8="Impacto",prm_Limiar_Impacto,prm_Limiar_Financeiro),"Sim","Não")) -> Sim | AD8: =IF(AC8="","",IF(AC8="Sim",IF(G8="Impacto","Material — impacto","Material — financeiro"),"Não material")) -> Material — financeiro | AE8: =IF(AB8="","",RANK(AB8,$AB$5:$AB$91,0)+COUNTIFS($AB$5:$AB$91,AB8,$A$5:$A$91,"<"&A8)) -> 18 | AF8: PES-04 (clientes pedem dados ambientais); questionários ESG recebidos | AG8: Média | AH8: =IF(A8="","",COUNTIF(Evidencias!$B$5:$B$115,A8)) -> 1 | AI8: =IF(A8="","",IF(G8="","FALTA tipo de IRO",IF(AB8="",IF(G8="Impacto","FALTA pontuação de impacto","FALTA estimativa financeira"),IF(AH8=0,"Sem evidência registada","OK")))) -> OK | AJ8: PES-04; PES-01 | AL8: O3 | AR8: Cálculo de pegada por família de produto e resposta estruturada a questionários ESG. | AS8: Diretor Geral (Gestão de Topo) | AT8: Validado pelo responsável | AU8: 46289 | AV8: =IF(AU8="","",EDATE(AU8,IF(AC8="Sim",prm_Meses_Rev_Material,prm_Meses_Rev_Outros))) -> 46470
A9: IRO-005 | B9: DM-02 | C9: =IF(B9="","",IFERROR(INDEX(Temas!$E$5:$E$40,MATCH(B9,Temas!$A$5:$A$40,0)),"ID_Tema não encontrado")) -> Consumo e eficiência energética | D9: =IF(B9="","",IFERROR(INDEX(Temas!$B$5:$B$40,MATCH(B9,Temas!$A$5:$A$40,0)),"")) -> Ambiental | E9: =IF(B9="","",IFERROR(INDEX(Temas!$C$5:$C$40,MATCH(B9,Temas!$A$5:$A$40,0)),"")) -> E1 Alterações climáticas | F9: Impacto negativo | G9: =IF(F9="","",IF(LEFT(F9,7)="Impacto","Impacto","Financeira")) -> Impacto | H9: Consumo de 7.174 MWh/ano de eletricidade, 45% de origem não renovável, com intensidade de 110 kWh por 1.000 unidades. | I9: Real | J9: Operações próprias | K9: Curto prazo (≤ 1 ano) | L9: Recursos energéticos; clima | M9: Não | N9: 3 | O9: 3 | P9: 3 | R9: =IF(G9<>"Impacto","",IF(F9="Impacto negativo",IF(COUNT(N9,O9,P9)=3,ROUND(AVERAGE(N9,O9,P9),2),""),IF(COUNT(N9,O9)=2,ROUND(AVERAGE(N9,O9),2),""))) -> 3 | S9: =IF(OR(G9<>"Impacto",R9=""),"",IF(I9="Real",5,IF(AND(M9="Sim",R9>=prm_Grav_DH),5,IF(Q9="","",Q9)))) -> 5 | T9: =IF(OR(R9="",S9=""),"",ROUND(R9*S9,1)) -> 15 | Y9: =IF(OR(G9<>"Financeira",W9=""),"",MATCH(W9,esc_Fin_Limite,1)) | Z9: =IF(OR(Y9="",X9=""),"",Y9*X9) | AA9: =IF(Z9="","",ROUND(W9*INDEX(esc_Prob_Media,X9),0)*IF(F9="Risco",-1,1)) | AB9: =IF(G9="","",IF(G9="Impacto",T9,Z9)) -> 15 | AC9: =IF(OR(G9="",AB9=""),"",IF(AB9>=IF(G9="Impacto",prm_Limiar_Impacto,prm_Limiar_Financeiro),"Sim","Não")) -> Sim | AD9: =IF(AC9="","",IF(AC9="Sim",IF(G9="Impacto","Material — impacto","Material — financeiro"),"Não material")) -> Material — impacto | AE9: =IF(AB9="","",RANK(AB9,$AB$5:$AB$91,0)+COUNTIFS($AB$5:$AB$91,AB9,$A$5:$A$91,"<"&A9)) -> 12 | AF9: EMAS-01 (7.173,6 MWh); EMAS-01b (3.945,5 MWh renováveis); KPI-01 | AG9: Alta | AH9: =IF(A9="","",COUNTIF(Evidencias!$B$5:$B$115,A9)) -> 3 | AI9: =IF(A9="","",IF(G9="","FALTA tipo de IRO",IF(AB9="",IF(G9="Impacto","FALTA pontuação de impacto","FALTA estimativa financeira"),IF(AH9=0,"Sem evidência registada","OK")))) -> OK | AJ9: SWT-F02; SWT-W01 | AK9: RO-02 | AL9: R35 | AM9: AA-007; AA-010; AA-019; AA-021; AA-030 | AN9: LEG-08 | AO9: OBJ-01 | AP9: KPI-01; KPI-09 | AQ9: PAM-26-01; PAM-26-02 | AR9: Submedição por processo (PAM-26-02) e plano de eficiência (OBJ-01). | AS9: Diretor Industrial | AT9: Validado pelo responsável | AU9: 46289 | AV9: =IF(AU9="","",EDATE(AU9,IF(AC9="Sim",prm_Meses_Rev_Material,prm_Meses_Rev_Outros))) -> 46470
A10: IRO-006 | B10: DM-02 | C10: =IF(B10="","",IFERROR(INDEX(Temas!$E$5:$E$40,MATCH(B10,Temas!$A$5:$A$40,0)),"ID_Tema não encontrado")) -> Consumo e eficiência energética | D10: =IF(B10="","",IFERROR(INDEX(Temas!$B$5:$B$40,MATCH(B10,Temas!$A$5:$A$40,0)),"")) -> Ambiental | E10: =IF(B10="","",IFERROR(INDEX(Temas!$C$5:$C$40,MATCH(B10,Temas!$A$5:$A$40,0)),"")) -> E1 Alterações climáticas | F10: Risco | G10: =IF(F10="","",IF(LEFT(F10,7)="Impacto","Impacto","Financeira")) -> Financeira | H10: Volatilidade do preço da eletricidade num processo eletrointensivo (≈ 7,8 GWh/ano). | J10: Operações próprias | K10: Curto prazo (≤ 1 ano) | R10: =IF(G10<>"Impacto","",IF(F10="Impacto negativo",IF(COUNT(N10,O10,P10)=3,ROUND(AVERAGE(N10,O10,P10),2),""),IF(COUNT(N10,O10)=2,ROUND(AVERAGE(N10,O10),2),""))) | S10: =IF(OR(G10<>"Impacto",R10=""),"",IF(I10="Real",5,IF(AND(M10="Sim",R10>=prm_Grav_DH),5,IF(Q10="","",Q10)))) | T10: =IF(OR(R10="",S10=""),"",ROUND(R10*S10,1)) | U10: Custos: +0,03 €/kWh × 7,17 GWh ≈ 215 k€/ano de custo adicional, sem repercussão imediata no preço de venda. | V10: Custos de energia e matérias-primas | W10: 215000 | X10: 4 | Y10: =IF(OR(G10<>"Financeira",W10=""),"",MATCH(W10,esc_Fin_Limite,1)) -> 4 | Z10: =IF(OR(Y10="",X10=""),"",Y10*X10) -> 16 | AA10: =IF(Z10="","",ROUND(W10*INDEX(esc_Prob_Media,X10),0)*IF(F10="Risco",-1,1)) -> -139750 | AB10: =IF(G10="","",IF(G10="Impacto",T10,Z10)) -> 16 | AC10: =IF(OR(G10="",AB10=""),"",IF(AB10>=IF(G10="Impacto",prm_Limiar_Impacto,prm_Limiar_Financeiro),"Sim","Não")) -> Sim | AD10: =IF(AC10="","",IF(AC10="Sim",IF(G10="Impacto","Material — impacto","Material — financeiro"),"Não material")) -> Material — financeiro | AE10: =IF(AB10="","",RANK(AB10,$AB$5:$AB$91,0)+COUNTIFS($AB$5:$AB$91,AB10,$A$5:$A$91,"<"&A10)) -> 10 | AF10: EMAS-01; PES-02; faturas de eletricidade | AG10: Alta | AH10: =IF(A10="","",COUNTIF(Evidencias!$B$5:$B$115,A10)) -> 1 | AI10: =IF(A10="","",IF(G10="","FALTA tipo de IRO",IF(AB10="",IF(G10="Impacto","FALTA pontuação de impacto","FALTA estimativa financeira"),IF(AH10=0,"Sem evidência registada","OK")))) -> OK | AJ10: PES-02 | AL10: R25 | AP10: KPI-01 | AR10: Contrato com preço indexado limitado, eficiência e autoconsumo. | AS10: Diretor Financeiro | AT10: Validado pelo responsável | AU10: 46289 | AV10: =IF(AU10="","",EDATE(AU10,IF(AC10="Sim",prm_Meses_Rev_Material,prm_Meses_Rev_Outros))) -> 46470
A11: IRO-007 | B11: DM-02 | C11: =IF(B11="","",IFERROR(INDEX(Temas!$E$5:$E$40,MATCH(B11,Temas!$A$5:$A$40,0)),"ID_Tema não encontrado")) -> Consumo e eficiência energética | D11: =IF(B11="","",IFERROR(INDEX(Temas!$B$5:$B$40,MATCH(B11,Temas!$A$5:$A$40,0)),"")) -> Ambiental | E11: =IF(B11="","",IFERROR(INDEX(Temas!$C$5:$C$40,MATCH(B11,Temas!$A$5:$A$40,0)),"")) -> E1 Alterações climáticas | F11: Oportunidade | G11: =IF(F11="","",IF(LEFT(F11,7)="Impacto","Impacto","Financeira")) -> Financeira | H11: Autoconsumo fotovoltaico (UPAC ≈ 1 MWp, ≈ 1.400 MWh/ano) na cobertura de ≈ 9.000 m². | J11: Operações próprias | K11: Médio prazo (1–5 anos) | R11: =IF(G11<>"Impacto","",IF(F11="Impacto negativo",IF(COUNT(N11,O11,P11)=3,ROUND(AVERAGE(N11,O11,P11),2),""),IF(COUNT(N11,O11)=2,ROUND(AVERAGE(N11,O11),2),""))) | S11: =IF(OR(G11<>"Impacto",R11=""),"",IF(I11="Real",5,IF(AND(M11="Sim",R11>=prm_Grav_DH),5,IF(Q11="","",Q11)))) | T11: =IF(OR(R11="",S11=""),"",ROUND(R11*S11,1)) | U11: Custos evitados: 1.400 MWh × 0,13 €/kWh ≈ 182 k€/ano; investimento a financiar com apoio público (SWT-O03). | V11: Custos de energia e matérias-primas | W11: 180000 | X11: 3 | Y11: =IF(OR(G11<>"Financeira",W11=""),"",MATCH(W11,esc_Fin_Limite,1)) -> 4 | Z11: =IF(OR(Y11="",X11=""),"",Y11*X11) -> 12 | AA11: =IF(Z11="","",ROUND(W11*INDEX(esc_Prob_Media,X11),0)*IF(F11="Risco",-1,1)) -> 72000 | AB11: =IF(G11="","",IF(G11="Impacto",T11,Z11)) -> 12 | AC11: =IF(OR(G11="",AB11=""),"",IF(AB11>=IF(G11="Impacto",prm_Limiar_Impacto,prm_Limiar_Financeiro),"Sim","Não")) -> Sim | AD11: =IF(AC11="","",IF(AC11="Sim",IF(G11="Impacto","Material — impacto","Material — financeiro"),"Não material")) -> Material — financeiro | AE11: =IF(AB11="","",RANK(AB11,$AB$5:$AB$91,0)+COUNTIFS($AB$5:$AB$91,AB11,$A$5:$A$91,"<"&A11)) -> 19 | AF11: AA-032 (1.400 MWh/ano, estimativa); estudo de viabilidade em curso | AG11: Média | AH11: =IF(A11="","",COUNTIF(Evidencias!$B$5:$B$115,A11)) -> 1 | AI11: =IF(A11="","",IF(G11="","FALTA tipo de IRO",IF(AB11="",IF(G11="Impacto","FALTA pontuação de impacto","FALTA estimativa financeira"),IF(AH11=0,"Sem evidência registada","OK")))) -> OK | AJ11: SWT-O02; SWT-O03 | AK11: RO-09 | AL11: O15 | AM11: AA-031; AA-032 | AR11: Estudo de viabilidade e candidatura a financiamento (RO-09). | AS11: Diretor Financeiro | AT11: Validado pelo responsável | AU11: 46289 | AV11: =IF(AU11="","",EDATE(AU11,IF(AC11="Sim",prm_Meses_Rev_Material,prm_Meses_Rev_Outros))) -> 46470
A12: IRO-008 | B12: DM-02 | C12: =IF(B12="","",IFERROR(INDEX(Temas!$E$5:$E$40,MATCH(B12,Temas!$A$5:$A$40,0)),"ID_Tema não encontrado")) -> Consumo e eficiência energética | D12: =IF(B12="","",IFERROR(INDEX(Temas!$B$5:$B$40,MATCH(B12,Temas!$A$5:$A$40,0)),"")) -> Ambiental | E12: =IF(B12="","",IFERROR(INDEX(Temas!$C$5:$C$40,MATCH(B12,Temas!$A$5:$A$40,0)),"")) -> E1 Alterações climáticas | F12: Oportunidade | G12: =IF(F12="","",IF(LEFT(F12,7)="Impacto","Impacto","Financeira")) -> Financeira | H12: Redução de 8% do consumo específico (OBJ-01) e das fugas de ar comprimido com submedição por processo. | J12: Operações próprias | K12: Curto prazo (≤ 1 ano) | R12: =IF(G12<>"Impacto","",IF(F12="Impacto negativo",IF(COUNT(N12,O12,P12)=3,ROUND(AVERAGE(N12,O12,P12),2),""),IF(COUNT(N12,O12)=2,ROUND(AVERAGE(N12,O12),2),""))) | S12: =IF(OR(G12<>"Impacto",R12=""),"",IF(I12="Real",5,IF(AND(M12="Sim",R12>=prm_Grav_DH),5,IF(Q12="","",Q12)))) | T12: =IF(OR(R12="",S12=""),"",ROUND(R12*S12,1)) | U12: Custos evitados: 8% × 7,17 GWh ≈ 574 MWh × 0,13 €/kWh ≈ 75 k€/ano. | V12: Custos de energia e matérias-primas | W12: 75000 | X12: 4 | Y12: =IF(OR(G12<>"Financeira",W12=""),"",MATCH(W12,esc_Fin_Limite,1)) -> 3 | Z12: =IF(OR(Y12="",X12=""),"",Y12*X12) -> 12 | AA12: =IF(Z12="","",ROUND(W12*INDEX(esc_Prob_Media,X12),0)*IF(F12="Risco",-1,1)) -> 48750 | AB12: =IF(G12="","",IF(G12="Impacto",T12,Z12)) -> 12 | AC12: =IF(OR(G12="",AB12=""),"",IF(AB12>=IF(G12="Impacto",prm_Limiar_Impacto,prm_Limiar_Financeiro),"Sim","Não")) -> Sim | AD12: =IF(AC12="","",IF(AC12="Sim",IF(G12="Impacto","Material — impacto","Material — financeiro"),"Não material")) -> Material — financeiro | AE12: =IF(AB12="","",RANK(AB12,$AB$5:$AB$91,0)+COUNTIFS($AB$5:$AB$91,AB12,$A$5:$A$91,"<"&A12)) -> 20 | AF12: KPI-01 (baseline 109,9 kWh/1.000 un); AA-021 (975 MWh/ano em compressores) | AG12: Alta | AH12: =IF(A12="","",COUNTIF(Evidencias!$B$5:$B$115,A12)) -> 1 | AI12: =IF(A12="","",IF(G12="","FALTA tipo de IRO",IF(AB12="",IF(G12="Impacto","FALTA pontuação de impacto","FALTA estimativa financeira"),IF(AH12=0,"Sem evidência registada","OK")))) -> OK | AK12: RO-02 | AL12: O6 | AM12: AA-021 | AO12: OBJ-01 | AP12: KPI-01 | AQ12: PAM-26-01; PAM-26-02 | AR12: Plano de eficiência energética e deteção de fugas. | AS12: Gerente de Manutenção | AT12: Validado pelo responsável | AU12: 46289 | AV12: =IF(AU12="","",EDATE(AU12,IF(AC12="Sim",prm_Meses_Rev_Material,prm_Meses_Rev_Outros))) -> 46470
A13: IRO-009 | B13: DM-03 | C13: =IF(B13="","",IFERROR(INDEX(Temas!$E$5:$E$40,MATCH(B13,Temas!$A$5:$A$40,0)),"ID_Tema não encontrado")) -> Resiliência a ondas de calor, seca e incêndio | D13: =IF(B13="","",IFERROR(INDEX(Temas!$B$5:$B$40,MATCH(B13,Temas!$A$5:$A$40,0)),"")) -> Ambiental | E13: =IF(B13="","",IFERROR(INDEX(Temas!$C$5:$C$40,MATCH(B13,Temas!$A$5:$A$40,0)),"")) -> E1 Alterações climáticas | F13: Risco | G13: =IF(F13="","",IF(LEFT(F13,7)="Impacto","Impacto","Financeira")) -> Financeira | H13: Ondas de calor e seca aumentam o consumo de água e energia do arrefecimento, os defeitos e o risco de restrição de água. | J13: Operações próprias | K13: Médio prazo (1–5 anos) | R13: =IF(G13<>"Impacto","",IF(F13="Impacto negativo",IF(COUNT(N13,O13,P13)=3,ROUND(AVERAGE(N13,O13,P13),2),""),IF(COUNT(N13,O13)=2,ROUND(AVERAGE(N13,O13),2),""))) | S13: =IF(OR(G13<>"Impacto",R13=""),"",IF(I13="Real",5,IF(AND(M13="Sim",R13>=prm_Grav_DH),5,IF(Q13="","",Q13)))) | T13: =IF(OR(R13="",S13=""),"",ROUND(R13*S13,1)) | U13: Custos: +5% de energia de arrefecimento por °C acima de 15 °C, refugo e horas de paragem no verão ≈ 60 k€/ano. | V13: Outros custos operacionais | W13: 60000 | X13: 4 | Y13: =IF(OR(G13<>"Financeira",W13=""),"",MATCH(W13,esc_Fin_Limite,1)) -> 3 | Z13: =IF(OR(Y13="",X13=""),"",Y13*X13) -> 12 | AA13: =IF(Z13="","",ROUND(W13*INDEX(esc_Prob_Media,X13),0)*IF(F13="Risco",-1,1)) -> -39000 | AB13: =IF(G13="","",IF(G13="Impacto",T13,Z13)) -> 12 | AC13: =IF(OR(G13="",AB13=""),"",IF(AB13>=IF(G13="Impacto",prm_Limiar_Impacto,prm_Limiar_Financeiro),"Sim","Não")) -> Sim | AD13: =IF(AC13="","",IF(AC13="Sim",IF(G13="Impacto","Material — impacto","Material — financeiro"),"Não material")) -> Material — financeiro | AE13: =IF(AB13="","",RANK(AB13,$AB$5:$AB$91,0)+COUNTIFS($AB$5:$AB$91,AB13,$A$5:$A$91,"<"&A13)) -> 21 | AF13: Anomalia térmica de +2,2 °C em ago/2026; KPI-16; AA-023 | AG13: Média | AH13: =IF(A13="","",COUNTIF(Evidencias!$B$5:$B$115,A13)) -> 2 | AI13: =IF(A13="","",IF(G13="","FALTA tipo de IRO",IF(AB13="",IF(G13="Impacto","FALTA pontuação de impacto","FALTA estimativa financeira"),IF(AH13=0,"Sem evidência registada","OK")))) -> OK | AJ13: PES-08; PES-09; SWT-T01 | AK13: RO-04 | AL13: R34 | AM13: AA-023 | AO13: OBJ-05 | AP13: KPI-02; KPI-16 | AR13: Avaliação de cenários climáticos e circuito fechado de arrefecimento (OBJ-05). | AS13: Diretor Industrial | AT13: Validado pelo responsável | AU13: 46289 | AV13: =IF(AU13="","",EDATE(AU13,IF(AC13="Sim",prm_Meses_Rev_Material,prm_Meses_Rev_Outros))) -> 46470
A14: IRO-010 | B14: DM-03 | C14: =IF(B14="","",IFERROR(INDEX(Temas!$E$5:$E$40,MATCH(B14,Temas!$A$5:$A$40,0)),"ID_Tema não encontrado")) -> Resiliência a ondas de calor, seca e incêndio | D14: =IF(B14="","",IFERROR(INDEX(Temas!$B$5:$B$40,MATCH(B14,Temas!$A$5:$A$40,0)),"")) -> Ambiental | E14: =IF(B14="","",IFERROR(INDEX(Temas!$C$5:$C$40,MATCH(B14,Temas!$A$5:$A$40,0)),"")) -> E1 Alterações climáticas | F14: Risco | G14: =IF(F14="","",IF(LEFT(F14,7)="Impacto","Impacto","Financeira")) -> Financeira | H14: Incêndio rural na envolvente florestal que atinge o armazém de matérias-primas. | J14: Operações próprias | K14: Longo prazo (> 5 anos) | R14: =IF(G14<>"Impacto","",IF(F14="Impacto negativo",IF(COUNT(N14,O14,P14)=3,ROUND(AVERAGE(N14,O14,P14),2),""),IF(COUNT(N14,O14)=2,ROUND(AVERAGE(N14,O14),2),""))) | S14: =IF(OR(G14<>"Impacto",R14=""),"",IF(I14="Real",5,IF(AND(M14="Sim",R14>=prm_Grav_DH),5,IF(Q14="","",Q14)))) | T14: =IF(OR(R14="",S14=""),"",ROUND(R14*S14,1)) | U14: Ativos e paragem: dano estimado ≈ 400 k€; parcialmente transferido para o seguro multirriscos. | V14: CAPEX / ativos | W14: 400000 | X14: 1 | Y14: =IF(OR(G14<>"Financeira",W14=""),"",MATCH(W14,esc_Fin_Limite,1)) -> 5 | Z14: =IF(OR(Y14="",X14=""),"",Y14*X14) -> 5 | AA14: =IF(Z14="","",ROUND(W14*INDEX(esc_Prob_Media,X14),0)*IF(F14="Risco",-1,1)) -> -20000 | AB14: =IF(G14="","",IF(G14="Impacto",T14,Z14)) -> 5 | AC14: =IF(OR(G14="",AB14=""),"",IF(AB14>=IF(G14="Impacto",prm_Limiar_Impacto,prm_Limiar_Financeiro),"Sim","Não")) -> Não | AD14: =IF(AC14="","",IF(AC14="Sim",IF(G14="Impacto","Material — impacto","Material — financeiro"),"Não material")) -> Não material | AE14: =IF(AB14="","",RANK(AB14,$AB$5:$AB$91,0)+COUNTIFS($AB$5:$AB$91,AB14,$A$5:$A$91,"<"&A14)) -> 53 | AF14: PES-10; plano de emergência (RG-SGA-12) | AG14: Média | AH14: =IF(A14="","",COUNTIF(Evidencias!$B$5:$B$115,A14)) -> 1 | AI14: =IF(A14="","",IF(G14="","FALTA tipo de IRO",IF(AB14="",IF(G14="Impacto","FALTA pontuação de impacto","FALTA estimativa financeira"),IF(AH14=0,"Sem evidência registada","OK")))) -> OK | AJ14: PES-10 | AK14: RO-08 | AL14: R38 | AM14: AA-034 | AN14: LEG-11 | AR14: Faixa de gestão de combustível, seguro e simulacro anual. | AS14: Diretor Industrial | AT14: Validado pelo responsável | AU14: 46289 | AV14: =IF(AU14="","",EDATE(AU14,IF(AC14="Sim",prm_Meses_Rev_Material,prm_Meses_Rev_Outros))) -> 46654
A15: IRO-011 | B15: DM-04 | C15: =IF(B15="","",IFERROR(INDEX(Temas!$E$5:$E$40,MATCH(B15,Temas!$A$5:$A$40,0)),"ID_Tema não encontrado")) -> Emissões de COV da serigrafia | D15: =IF(B15="","",IFERROR(INDEX(Temas!$B$5:$B$40,MATCH(B15,Temas!$A$5:$A$40,0)),"")) -> Ambiental | E15: =IF(B15="","",IFERROR(INDEX(Temas!$C$5:$C$40,MATCH(B15,Temas!$A$5:$A$40,0)),"")) -> E2 Poluição | F15: Impacto negativo | G15: =IF(F15="","",IF(LEFT(F15,7)="Impacto","Impacto","Financeira")) -> Impacto | H15: Emissão difusa de ≈ 1,95 t/ano de COV na serigrafia e manutenção (precursores de ozono troposférico). | I15: Real | J15: Operações próprias | K15: Curto prazo (≤ 1 ano) | L15: Trabalhadores da serigrafia; qualidade do ar local | M15: Não | N15: 3 | O15: 3 | P15: 2 | R15: =IF(G15<>"Impacto","",IF(F15="Impacto negativo",IF(COUNT(N15,O15,P15)=3,ROUND(AVERAGE(N15,O15,P15),2),""),IF(COUNT(N15,O15)=2,ROUND(AVERAGE(N15,O15),2),""))) -> 2.67 | S15: =IF(OR(G15<>"Impacto",R15=""),"",IF(I15="Real",5,IF(AND(M15="Sim",R15>=prm_Grav_DH),5,IF(Q15="","",Q15)))) -> 5 | T15: =IF(OR(R15="",S15=""),"",ROUND(R15*S15,1)) -> 13.4 | Y15: =IF(OR(G15<>"Financeira",W15=""),"",MATCH(W15,esc_Fin_Limite,1)) | Z15: =IF(OR(Y15="",X15=""),"",Y15*X15) | AA15: =IF(Z15="","",ROUND(W15*INDEX(esc_Prob_Media,X15),0)*IF(F15="Risco",-1,1)) | AB15: =IF(G15="","",IF(G15="Impacto",T15,Z15)) -> 13.4 | AC15: =IF(OR(G15="",AB15=""),"",IF(AB15>=IF(G15="Impacto",prm_Limiar_Impacto,prm_Limiar_Financeiro),"Sim","Não")) -> Sim | AD15: =IF(AC15="","",IF(AC15="Sim",IF(G15="Impacto","Material — impacto","Material — financeiro"),"Não material")) -> Material — impacto | AE15: =IF(AB15="","",RANK(AB15,$AB$5:$AB$91,0)+COUNTIFS($AB$5:$AB$91,AB15,$A$5:$A$91,"<"&A15)) -> 15 | AF15: EMAS-06b (1,95 t COV); AA-014 (759 kg de solvente/ano); KPI-06 | AG15: Alta | AH15: =IF(A15="","",COUNTIF(Evidencias!$B$5:$B$115,A15)) -> 3 | AI15: =IF(A15="","",IF(G15="","FALTA tipo de IRO",IF(AB15="",IF(G15="Impacto","FALTA pontuação de impacto","FALTA estimativa financeira"),IF(AH15=0,"Sem evidência registada","OK")))) -> OK | AM15: AA-014; AA-006 | AN15: LEG-04; LEG-12 | AO15: OBJ-03 | AP15: KPI-06 | AQ15: PAM-26-07 | AR15: Reduzir 20% do solvente por peça (OBJ-03); recipientes fechados; avaliar tintas UV sem solvente. | AS15: Gerente de Produção | AT15: Validado pelo responsável | AU15: 46289 | AV15: =IF(AU15="","",EDATE(AU15,IF(AC15="Sim",prm_Meses_Rev_Material,prm_Meses_Rev_Outros))) -> 46470
A16: IRO-012 | B16: DM-04 | C16: =IF(B16="","",IFERROR(INDEX(Temas!$E$5:$E$40,MATCH(B16,Temas!$A$5:$A$40,0)),"ID_Tema não encontrado")) -> Emissões de COV da serigrafia | D16: =IF(B16="","",IFERROR(INDEX(Temas!$B$5:$B$40,MATCH(B16,Temas!$A$5:$A$40,0)),"")) -> Ambiental | E16: =IF(B16="","",IFERROR(INDEX(Temas!$C$5:$C$40,MATCH(B16,Temas!$A$5:$A$40,0)),"")) -> E2 Poluição | F16: Risco | G16: =IF(F16="","",IF(LEFT(F16,7)="Impacto","Impacto","Financeira")) -> Financeira | H16: Incumprimento do regime de COV (limiar de consumo de solventes e plano de gestão de solventes). | J16: Operações próprias | K16: Curto prazo (≤ 1 ano) | R16: =IF(G16<>"Impacto","",IF(F16="Impacto negativo",IF(COUNT(N16,O16,P16)=3,ROUND(AVERAGE(N16,O16,P16),2),""),IF(COUNT(N16,O16)=2,ROUND(AVERAGE(N16,O16),2),""))) | S16: =IF(OR(G16<>"Impacto",R16=""),"",IF(I16="Real",5,IF(AND(M16="Sim",R16>=prm_Grav_DH),5,IF(Q16="","",Q16)))) | T16: =IF(OR(R16="",S16=""),"",ROUND(R16*S16,1)) | U16: Multas e custos de adaptação: coima e medições adicionais ≈ 15 k€. | V16: Multas, passivos e litígios | W16: 15000 | X16: 2 | Y16: =IF(OR(G16<>"Financeira",W16=""),"",MATCH(W16,esc_Fin_Limite,1)) -> 2 | Z16: =IF(OR(Y16="",X16=""),"",Y16*X16) -> 4 | AA16: =IF(Z16="","",ROUND(W16*INDEX(esc_Prob_Media,X16),0)*IF(F16="Risco",-1,1)) -> -3000 | AB16: =IF(G16="","",IF(G16="Impacto",T16,Z16)) -> 4 | AC16: =IF(OR(G16="",AB16=""),"",IF(AB16>=IF(G16="Impacto",prm_Limiar_Impacto,prm_Limiar_Financeiro),"Sim","Não")) -> Não | AD16: =IF(AC16="","",IF(AC16="Sim",IF(G16="Impacto","Material — impacto","Material — financeiro"),"Não material")) -> Não material | AE16: =IF(AB16="","",RANK(AB16,$AB$5:$AB$91,0)+COUNTIFS($AB$5:$AB$91,AB16,$A$5:$A$91,"<"&A16)) -> 54 | AF16: LEG-04 (avaliação de conformidade) | AG16: Média | AH16: =IF(A16="","",COUNTIF(Evidencias!$B$5:$B$115,A16)) -> 1 | AI16: =IF(A16="","",IF(G16="","FALTA tipo de IRO",IF(AB16="",IF(G16="Impacto","FALTA pontuação de impacto","FALTA estimativa financeira"),IF(AH16=0,"Sem evidência registada","OK")))) -> OK | AN16: LEG-04 | AS16: Gestor do SGA / EHS (Responsável Ambiental) | AT16: Validado pelo responsável | AU16: 46289 | AV16: =IF(AU16="","",EDATE(AU16,IF(AC16="Sim",prm_Meses_Rev_Material,prm_Meses_Rev_Outros))) -> 46654
A17: IRO-013 | B17: DM-05 | C17: =IF(B17="","",IFERROR(INDEX(Temas!$E$5:$E$40,MATCH(B17,Temas!$A$5:$A$40,0)),"ID_Tema não encontrado")) -> Derrames e descargas | D17: =IF(B17="","",IFERROR(INDEX(Temas!$B$5:$B$40,MATCH(B17,Temas!$A$5:$A$40,0)),"")) -> Ambiental | E17: =IF(B17="","",IFERROR(INDEX(Temas!$C$5:$C$40,MATCH(B17,Temas!$A$5:$A$40,0)),"")) -> E2 Poluição | F17: Impacto negativo | G17: =IF(F17="","",IF(LEFT(F17,7)="Impacto","Impacto","Financeira")) -> Impacto | H17: Derrame de tintas, solventes ou óleos não contido que contamina o solo ou a rede pluvial. | I17: Potencial | J17: Operações próprias | K17: Curto prazo (≤ 1 ano) | L17: Solo; águas superficiais | M17: Não | N17: 4 | O17: 2 | P17: 3 | Q17: 3 | R17: =IF(G17<>"Impacto","",IF(F17="Impacto negativo",IF(COUNT(N17,O17,P17)=3,ROUND(AVERAGE(N17,O17,P17),2),""),IF(COUNT(N17,O17)=2,ROUND(AVERAGE(N17,O17),2),""))) -> 3 | S17: =IF(OR(G17<>"Impacto",R17=""),"",IF(I17="Real",5,IF(AND(M17="Sim",R17>=prm_Grav_DH),5,IF(Q17="","",Q17)))) -> 3 | T17: =IF(OR(R17="",S17=""),"",ROUND(R17*S17,1)) -> 9 | Y17: =IF(OR(G17<>"Financeira",W17=""),"",MATCH(W17,esc_Fin_Limite,1)) | Z17: =IF(OR(Y17="",X17=""),"",Y17*X17) | AA17: =IF(Z17="","",ROUND(W17*INDEX(esc_Prob_Media,X17),0)*IF(F17="Risco",-1,1)) | AB17: =IF(G17="","",IF(G17="Impacto",T17,Z17)) -> 9 | AC17: =IF(OR(G17="",AB17=""),"",IF(AB17>=IF(G17="Impacto",prm_Limiar_Impacto,prm_Limiar_Financeiro),"Sim","Não")) -> Não | AD17: =IF(AC17="","",IF(AC17="Sim",IF(G17="Impacto","Material — impacto","Material — financeiro"),"Não material")) -> Não material | AE17: =IF(AB17="","",RANK(AB17,$AB$5:$AB$91,0)+COUNTIFS($AB$5:$AB$91,AB17,$A$5:$A$91,"<"&A17)) -> 36 | AF17: NC-SGA-26-03 (kit antipoluição incompleto); AA-005, AA-013 | AG17: Média | AH17: =IF(A17="","",COUNTIF(Evidencias!$B$5:$B$115,A17)) -> 1 | AI17: =IF(A17="","",IF(G17="","FALTA tipo de IRO",IF(AB17="",IF(G17="Impacto","FALTA pontuação de impacto","FALTA estimativa financeira"),IF(AH17=0,"Sem evidência registada","OK")))) -> OK | AJ17: SWT-W04 | AK17: RO-10 | AL17: R30 | AM17: AA-005; AA-009; AA-013; AA-016; AA-017 | AN17: LEG-06 | AQ17: PAM-26-04; PAM-26-05 | AR17: Bacias de retenção, kits selados e verificação semanal. | AS17: Gestor do SGA / EHS (Responsável Ambiental) | AT17: Validado pelo responsável | AU17: 46289 | AV17: =IF(AU17="","",EDATE(AU17,IF(AC17="Sim",prm_Meses_Rev_Material,prm_Meses_Rev_Outros))) -> 46654
A18: IRO-014 | B18: DM-05 | C18: =IF(B18="","",IFERROR(INDEX(Temas!$E$5:$E$40,MATCH(B18,Temas!$A$5:$A$40,0)),"ID_Tema não encontrado")) -> Derrames e descargas | D18: =IF(B18="","",IFERROR(INDEX(Temas!$B$5:$B$40,MATCH(B18,Temas!$A$5:$A$40,0)),"")) -> Ambiental | E18: =IF(B18="","",IFERROR(INDEX(Temas!$C$5:$C$40,MATCH(B18,Temas!$A$5:$A$40,0)),"")) -> E2 Poluição | F18: Impacto negativo | G18: =IF(F18="","",IF(LEFT(F18,7)="Impacto","Impacto","Financeira")) -> Impacto | H18: Descarga da purga da torre de arrefecimento com biocida e anti-incrustante no coletor. | I18: Real | J18: Operações próprias | K18: Curto prazo (≤ 1 ano) | L18: Meio recetor | M18: Não | N18: 2 | O18: 2 | P18: 2 | R18: =IF(G18<>"Impacto","",IF(F18="Impacto negativo",IF(COUNT(N18,O18,P18)=3,ROUND(AVERAGE(N18,O18,P18),2),""),IF(COUNT(N18,O18)=2,ROUND(AVERAGE(N18,O18),2),""))) -> 2 | S18: =IF(OR(G18<>"Impacto",R18=""),"",IF(I18="Real",5,IF(AND(M18="Sim",R18>=prm_Grav_DH),5,IF(Q18="","",Q18)))) -> 5 | T18: =IF(OR(R18="",S18=""),"",ROUND(R18*S18,1)) -> 10 | Y18: =IF(OR(G18<>"Financeira",W18=""),"",MATCH(W18,esc_Fin_Limite,1)) | Z18: =IF(OR(Y18="",X18=""),"",Y18*X18) | AA18: =IF(Z18="","",ROUND(W18*INDEX(esc_Prob_Media,X18),0)*IF(F18="Risco",-1,1)) | AB18: =IF(G18="","",IF(G18="Impacto",T18,Z18)) -> 10 | AC18: =IF(OR(G18="",AB18=""),"",IF(AB18>=IF(G18="Impacto",prm_Limiar_Impacto,prm_Limiar_Financeiro),"Sim","Não")) -> Não | AD18: =IF(AC18="","",IF(AC18="Sim",IF(G18="Impacto","Material — impacto","Material — financeiro"),"Não material")) -> Não material | AE18: =IF(AB18="","",RANK(AB18,$AB$5:$AB$91,0)+COUNTIFS($AB$5:$AB$91,AB18,$A$5:$A$91,"<"&A18)) -> 31 | AF18: AA-024; LEG-03 | AG18: Média | AH18: =IF(A18="","",COUNTIF(Evidencias!$B$5:$B$115,A18)) -> 1 | AI18: =IF(A18="","",IF(G18="","FALTA tipo de IRO",IF(AB18="",IF(G18="Impacto","FALTA pontuação de impacto","FALTA estimativa financeira"),IF(AH18=0,"Sem evidência registada","OK")))) -> OK | AM18: AA-024 | AN18: LEG-03 | AR18: Controlo analítico da purga e dosagem otimizada. | AS18: Gerente de Manutenção | AT18: Validado pelo responsável | AU18: 46289 | AV18: =IF(AU18="","",EDATE(AU18,IF(AC18="Sim",prm_Meses_Rev_Material,prm_Meses_Rev_Outros))) -> 46654
A19: IRO-015 | B19: DM-05 | C19: =IF(B19="","",IFERROR(INDEX(Temas!$E$5:$E$40,MATCH(B19,Temas!$A$5:$A$40,0)),"ID_Tema não encontrado")) -> Derrames e descargas | D19: =IF(B19="","",IFERROR(INDEX(Temas!$B$5:$B$40,MATCH(B19,Temas!$A$5:$A$40,0)),"")) -> Ambiental | E19: =IF(B19="","",IFERROR(INDEX(Temas!$C$5:$C$40,MATCH(B19,Temas!$A$5:$A$40,0)),"")) -> E2 Poluição | F19: Risco | G19: =IF(F19="","",IF(LEFT(F19,7)="Impacto","Impacto","Financeira")) -> Financeira | H19: Responsabilidade ambiental e custos de remediação após contaminação do solo. | J19: Operações próprias | K19: Médio prazo (1–5 anos) | R19: =IF(G19<>"Impacto","",IF(F19="Impacto negativo",IF(COUNT(N19,O19,P19)=3,ROUND(AVERAGE(N19,O19,P19),2),""),IF(COUNT(N19,O19)=2,ROUND(AVERAGE(N19,O19),2),""))) | S19: =IF(OR(G19<>"Impacto",R19=""),"",IF(I19="Real",5,IF(AND(M19="Sim",R19>=prm_Grav_DH),5,IF(Q19="","",Q19)))) | T19: =IF(OR(R19="",S19=""),"",ROUND(R19*S19,1)) | U19: Passivos: remediação e garantia financeira ≈ 250 k€ num evento grave. | V19: Multas, passivos e litígios | W19: 250000 | X19: 1 | Y19: =IF(OR(G19<>"Financeira",W19=""),"",MATCH(W19,esc_Fin_Limite,1)) -> 4 | Z19: =IF(OR(Y19="",X19=""),"",Y19*X19) -> 4 | AA19: =IF(Z19="","",ROUND(W19*INDEX(esc_Prob_Media,X19),0)*IF(F19="Risco",-1,1)) -> -12500 | AB19: =IF(G19="","",IF(G19="Impacto",T19,Z19)) -> 4 | AC19: =IF(OR(G19="",AB19=""),"",IF(AB19>=IF(G19="Impacto",prm_Limiar_Impacto,prm_Limiar_Financeiro),"Sim","Não")) -> Não | AD19: =IF(AC19="","",IF(AC19="Sim",IF(G19="Impacto","Material — impacto","Material — financeiro"),"Não material")) -> Não material | AE19: =IF(AB19="","",RANK(AB19,$AB$5:$AB$91,0)+COUNTIFS($AB$5:$AB$91,AB19,$A$5:$A$91,"<"&A19)) -> 55 | AF19: LEG-14 | AG19: Baixa | AH19: =IF(A19="","",COUNTIF(Evidencias!$B$5:$B$115,A19)) -> 1 | AI19: =IF(A19="","",IF(G19="","FALTA tipo de IRO",IF(AB19="",IF(G19="Impacto","FALTA pontuação de impacto","FALTA estimativa financeira"),IF(AH19=0,"Sem evidência registada","OK")))) -> OK | AN19: LEG-14 | AS19: Diretor Financeiro | AT19: Validado pelo responsável | AU19: 46289 | AV19: =IF(AU19="","",EDATE(AU19,IF(AC19="Sim",prm_Meses_Rev_Material,prm_Meses_Rev_Outros))) -> 46654
A20: IRO-016 | B20: DM-06 | C20: =IF(B20="","",IFERROR(INDEX(Temas!$E$5:$E$40,MATCH(B20,Temas!$A$5:$A$40,0)),"ID_Tema não encontrado")) -> Perdas de granulado de plástico | D20: =IF(B20="","",IFERROR(INDEX(Temas!$B$5:$B$40,MATCH(B20,Temas!$A$5:$A$40,0)),"")) -> Ambiental | E20: =IF(B20="","",IFERROR(INDEX(Temas!$C$5:$C$40,MATCH(B20,Temas!$A$5:$A$40,0)),"")) -> E2 Poluição | F20: Impacto negativo | G20: =IF(F20="","",IF(LEFT(F20,7)="Impacto","Impacto","Financeira")) -> Impacto | H20: Perda de granulado de plástico na descarga de silos e big bags para o pavimento e a rede pluvial (persistente no meio aquático). | I20: Real | J20: Operações próprias | K20: Curto prazo (≤ 1 ano) | L20: Ecossistemas aquáticos; comunidade | M20: Não | N20: 3 | O20: 3 | P20: 5 | R20: =IF(G20<>"Impacto","",IF(F20="Impacto negativo",IF(COUNT(N20,O20,P20)=3,ROUND(AVERAGE(N20,O20,P20),2),""),IF(COUNT(N20,O20)=2,ROUND(AVERAGE(N20,O20),2),""))) -> 3.67 | S20: =IF(OR(G20<>"Impacto",R20=""),"",IF(I20="Real",5,IF(AND(M20="Sim",R20>=prm_Grav_DH),5,IF(Q20="","",Q20)))) -> 5 | T20: =IF(OR(R20="",S20=""),"",ROUND(R20*S20,1)) -> 18.4 | Y20: =IF(OR(G20<>"Financeira",W20=""),"",MATCH(W20,esc_Fin_Limite,1)) | Z20: =IF(OR(Y20="",X20=""),"",Y20*X20) | AA20: =IF(Z20="","",ROUND(W20*INDEX(esc_Prob_Media,X20),0)*IF(F20="Risco",-1,1)) | AB20: =IF(G20="","",IF(G20="Impacto",T20,Z20)) -> 18.4 | AC20: =IF(OR(G20="",AB20=""),"",IF(AB20>=IF(G20="Impacto",prm_Limiar_Impacto,prm_Limiar_Financeiro),"Sim","Não")) -> Sim | AD20: =IF(AC20="","",IF(AC20="Sim",IF(G20="Impacto","Material — impacto","Material — financeiro"),"Não material")) -> Material — impacto | AE20: =IF(AB20="","",RANK(AB20,$AB$5:$AB$91,0)+COUNTIFS($AB$5:$AB$91,AB20,$A$5:$A$91,"<"&A20)) -> 7 | AF20: AA-003 (≈ 100 kg/ano recolhidos; perdas totais não medidas); KPI-13 (43% dos pontos com contenção) | AG20: Média | AH20: =IF(A20="","",COUNTIF(Evidencias!$B$5:$B$115,A20)) -> 2 | AI20: =IF(A20="","",IF(G20="","FALTA tipo de IRO",IF(AB20="",IF(G20="Impacto","FALTA pontuação de impacto","FALTA estimativa financeira"),IF(AH20=0,"Sem evidência registada","OK")))) -> OK | AJ20: PES-11; SWT-W04 | AK20: RO-07 | AL20: R37 | AM20: AA-003 | AN20: LEG-10 | AO20: OBJ-06 | AP20: KPI-13 | AQ20: PAM-26-11 | AR20: Operation Clean Sweep: filtros nas sarjetas, bacias e inspeção semanal. | AS20: Gestor do SGA / EHS (Responsável Ambiental) | AT20: Validado pelo responsável | AU20: 46289 | AV20: =IF(AU20="","",EDATE(AU20,IF(AC20="Sim",prm_Meses_Rev_Material,prm_Meses_Rev_Outros))) -> 46470
A21: IRO-017 | B21: DM-06 | C21: =IF(B21="","",IFERROR(INDEX(Temas!$E$5:$E$40,MATCH(B21,Temas!$A$5:$A$40,0)),"ID_Tema não encontrado")) -> Perdas de granulado de plástico | D21: =IF(B21="","",IFERROR(INDEX(Temas!$B$5:$B$40,MATCH(B21,Temas!$A$5:$A$40,0)),"")) -> Ambiental | E21: =IF(B21="","",IFERROR(INDEX(Temas!$C$5:$C$40,MATCH(B21,Temas!$A$5:$A$40,0)),"")) -> E2 Poluição | F21: Risco | G21: =IF(F21="","",IF(LEFT(F21,7)="Impacto","Impacto","Financeira")) -> Financeira | H21: Obrigações do regulamento europeu de prevenção de perdas de granulados (avaliação de risco, plano, registos). | J21: Operações próprias | K21: Médio prazo (1–5 anos) | R21: =IF(G21<>"Impacto","",IF(F21="Impacto negativo",IF(COUNT(N21,O21,P21)=3,ROUND(AVERAGE(N21,O21,P21),2),""),IF(COUNT(N21,O21)=2,ROUND(AVERAGE(N21,O21),2),""))) | S21: =IF(OR(G21<>"Impacto",R21=""),"",IF(I21="Real",5,IF(AND(M21="Sim",R21>=prm_Grav_DH),5,IF(Q21="","",Q21)))) | T21: =IF(OR(R21="",S21=""),"",ROUND(R21*S21,1)) | U21: Custos de conformidade: equipamento de contenção, formação e registos ≈ 30 k€. | V21: Outros custos operacionais | W21: 30000 | X21: 4 | Y21: =IF(OR(G21<>"Financeira",W21=""),"",MATCH(W21,esc_Fin_Limite,1)) -> 3 | Z21: =IF(OR(Y21="",X21=""),"",Y21*X21) -> 12 | AA21: =IF(Z21="","",ROUND(W21*INDEX(esc_Prob_Media,X21),0)*IF(F21="Risco",-1,1)) -> -19500 | AB21: =IF(G21="","",IF(G21="Impacto",T21,Z21)) -> 12 | AC21: =IF(OR(G21="",AB21=""),"",IF(AB21>=IF(G21="Impacto",prm_Limiar_Impacto,prm_Limiar_Financeiro),"Sim","Não")) -> Sim | AD21: =IF(AC21="","",IF(AC21="Sim",IF(G21="Impacto","Material — impacto","Material — financeiro"),"Não material")) -> Material — financeiro | AE21: =IF(AB21="","",RANK(AB21,$AB$5:$AB$91,0)+COUNTIFS($AB$5:$AB$91,AB21,$A$5:$A$91,"<"&A21)) -> 22 | AF21: PES-13; LEG-10 | AG21: Média | AH21: =IF(A21="","",COUNTIF(Evidencias!$B$5:$B$115,A21)) -> 1 | AI21: =IF(A21="","",IF(G21="","FALTA tipo de IRO",IF(AB21="",IF(G21="Impacto","FALTA pontuação de impacto","FALTA estimativa financeira"),IF(AH21=0,"Sem evidência registada","OK")))) -> OK | AJ21: PES-13 | AN21: LEG-10 | AO21: OBJ-06 | AQ21: PAM-26-11 | AR21: Plano de prevenção de perdas integrado no OBJ-06. | AS21: Gestor do SGA / EHS (Responsável Ambiental) | AT21: Validado pelo responsável | AU21: 46289 | AV21: =IF(AU21="","",EDATE(AU21,IF(AC21="Sim",prm_Meses_Rev_Material,prm_Meses_Rev_Outros))) -> 46470
A22: IRO-018 | B22: DM-07 | C22: =IF(B22="","",IFERROR(INDEX(Temas!$E$5:$E$40,MATCH(B22,Temas!$A$5:$A$40,0)),"ID_Tema não encontrado")) -> Substâncias perigosas em tintas e aditivos | D22: =IF(B22="","",IFERROR(INDEX(Temas!$B$5:$B$40,MATCH(B22,Temas!$A$5:$A$40,0)),"")) -> Ambiental | E22: =IF(B22="","",IFERROR(INDEX(Temas!$C$5:$C$40,MATCH(B22,Temas!$A$5:$A$40,0)),"")) -> E2 Poluição | F22: Impacto negativo | G22: =IF(F22="","",IF(LEFT(F22,7)="Impacto","Impacto","Financeira")) -> Impacto | H22: Uso de tintas, solventes e aditivos classificados (CLP) que podem chegar ao ambiente por derrame ou resíduo. | I22: Potencial | J22: Operações próprias | K22: Médio prazo (1–5 anos) | L22: Ambiente; trabalhadores | M22: Não | N22: 3 | O22: 2 | P22: 3 | Q22: 3 | R22: =IF(G22<>"Impacto","",IF(F22="Impacto negativo",IF(COUNT(N22,O22,P22)=3,ROUND(AVERAGE(N22,O22,P22),2),""),IF(COUNT(N22,O22)=2,ROUND(AVERAGE(N22,O22),2),""))) -> 2.67 | S22: =IF(OR(G22<>"Impacto",R22=""),"",IF(I22="Real",5,IF(AND(M22="Sim",R22>=prm_Grav_DH),5,IF(Q22="","",Q22)))) -> 3 | T22: =IF(OR(R22="",S22=""),"",ROUND(R22*S22,1)) -> 8 | Y22: =IF(OR(G22<>"Financeira",W22=""),"",MATCH(W22,esc_Fin_Limite,1)) | Z22: =IF(OR(Y22="",X22=""),"",Y22*X22) | AA22: =IF(Z22="","",ROUND(W22*INDEX(esc_Prob_Media,X22),0)*IF(F22="Risco",-1,1)) | AB22: =IF(G22="","",IF(G22="Impacto",T22,Z22)) -> 8 | AC22: =IF(OR(G22="",AB22=""),"",IF(AB22>=IF(G22="Impacto",prm_Limiar_Impacto,prm_Limiar_Financeiro),"Sim","Não")) -> Não | AD22: =IF(AC22="","",IF(AC22="Sim",IF(G22="Impacto","Material — impacto","Material — financeiro"),"Não material")) -> Não material | AE22: =IF(AB22="","",RANK(AB22,$AB$5:$AB$91,0)+COUNTIFS($AB$5:$AB$91,AB22,$A$5:$A$91,"<"&A22)) -> 42 | AF22: AA-015 (1.082 kg de tinta/ano); FDS | AG22: Média | AH22: =IF(A22="","",COUNTIF(Evidencias!$B$5:$B$115,A22)) -> 1 | AI22: =IF(A22="","",IF(G22="","FALTA tipo de IRO",IF(AB22="",IF(G22="Impacto","FALTA pontuação de impacto","FALTA estimativa financeira"),IF(AH22=0,"Sem evidência registada","OK")))) -> OK | AM22: AA-015 | AN22: LEG-06 | AR22: Inventário de substâncias e substituição progressiva. | AS22: Responsável de R&D | AT22: Validado pelo responsável | AU22: 46289 | AV22: =IF(AU22="","",EDATE(AU22,IF(AC22="Sim",prm_Meses_Rev_Material,prm_Meses_Rev_Outros))) -> 46654
A23: IRO-019 | B23: DM-07 | C23: =IF(B23="","",IFERROR(INDEX(Temas!$E$5:$E$40,MATCH(B23,Temas!$A$5:$A$40,0)),"ID_Tema não encontrado")) -> Substâncias perigosas em tintas e aditivos | D23: =IF(B23="","",IFERROR(INDEX(Temas!$B$5:$B$40,MATCH(B23,Temas!$A$5:$A$40,0)),"")) -> Ambiental | E23: =IF(B23="","",IFERROR(INDEX(Temas!$C$5:$C$40,MATCH(B23,Temas!$A$5:$A$40,0)),"")) -> E2 Poluição | F23: Risco | G23: =IF(F23="","",IF(LEFT(F23,7)="Impacto","Impacto","Financeira")) -> Financeira | H23: Restrições a substâncias em embalagens (PFAS em contacto alimentar — PPWR; REACH) obrigam a reformular tintas e aditivos. | J23: Downstream — utilização | K23: Médio prazo (1–5 anos) | R23: =IF(G23<>"Impacto","",IF(F23="Impacto negativo",IF(COUNT(N23,O23,P23)=3,ROUND(AVERAGE(N23,O23,P23),2),""),IF(COUNT(N23,O23)=2,ROUND(AVERAGE(N23,O23),2),""))) | S23: =IF(OR(G23<>"Impacto",R23=""),"",IF(I23="Real",5,IF(AND(M23="Sim",R23>=prm_Grav_DH),5,IF(Q23="","",Q23)))) | T23: =IF(OR(R23="",S23=""),"",ROUND(R23*S23,1)) | U23: Custos: requalificação de materiais e ensaios ≈ 40 k€. | V23: Outros custos operacionais | W23: 40000 | X23: 3 | Y23: =IF(OR(G23<>"Financeira",W23=""),"",MATCH(W23,esc_Fin_Limite,1)) -> 3 | Z23: =IF(OR(Y23="",X23=""),"",Y23*X23) -> 9 | AA23: =IF(Z23="","",ROUND(W23*INDEX(esc_Prob_Media,X23),0)*IF(F23="Risco",-1,1)) -> -16000 | AB23: =IF(G23="","",IF(G23="Impacto",T23,Z23)) -> 9 | AC23: =IF(OR(G23="",AB23=""),"",IF(AB23>=IF(G23="Impacto",prm_Limiar_Impacto,prm_Limiar_Financeiro),"Sim","Não")) -> Não | AD23: =IF(AC23="","",IF(AC23="Sim",IF(G23="Impacto","Material — impacto","Material — financeiro"),"Não material")) -> Não material | AE23: =IF(AB23="","",RANK(AB23,$AB$5:$AB$91,0)+COUNTIFS($AB$5:$AB$91,AB23,$A$5:$A$91,"<"&A23)) -> 37 | AF23: PES-12; LEG-09 | AG23: Média | AH23: =IF(A23="","",COUNTIF(Evidencias!$B$5:$B$115,A23)) -> 1 | AI23: =IF(A23="","",IF(G23="","FALTA tipo de IRO",IF(AB23="",IF(G23="Impacto","FALTA pontuação de impacto","FALTA estimativa financeira"),IF(AH23=0,"Sem evidência registada","OK")))) -> OK | AJ23: PES-12 | AN23: LEG-06; LEG-09 | AS23: Responsável de R&D | AT23: Validado pelo responsável | AU23: 46289 | AV23: =IF(AU23="","",EDATE(AU23,IF(AC23="Sim",prm_Meses_Rev_Material,prm_Meses_Rev_Outros))) -> 46654
