Workbook
Name AcaoOport: Critérios!$E$25:$E$28
Name AcaoRisco: Critérios!$D$25:$D$28
Name ApetIdx: Critérios!$I$50:$I$56
Name AudArea: Maturidade_Auditoria!$C$73:$C$80
Name AudData: Maturidade_Auditoria!$B$73:$B$80
Name AudIds: Maturidade_Auditoria!$A$73:$A$80
Name AudPct: Maturidade_Auditoria!$M$73:$M$80
Name BtEf: BowTie!$G$7:$G$86
Name BtId: BowTie!$A$7:$A$86
Name BtSit: BowTie!$N$7:$N$86
Name Ciclo_Atual: Maturidade_Auditoria!$B$5
Name CovMin: Maturidade_Auditoria!$B$9
Name DiasAlerta: Critérios!$C$17
Name FreqDias: Critérios!$N$71:$N$79
Name GrauAud: Maturidade_Auditoria!$C$152:$C$156
Name GrauMin: Maturidade_Auditoria!$E$152:$E$156
Name GrauNome: Maturidade_Auditoria!$A$152:$A$156
Name IdxExige: Critérios!$C$21
Name KriChaves: KRI!$A$7:$A$66
Name KriHoriz: KRI!$E$3
Name KriId: KRI!$B$7:$B$66
Name KriSit: KRI!$R$7:$R$66
Name Limites: Critérios!$C$25:$C$28
Name ListaAcaoOport: Critérios!$E$71:$E$78
Name ListaAcaoRisco: Critérios!$D$71:$D$76
Name ListaAlinh: Critérios!$L$71:$L$73
Name ListaAreas: Critérios!$B$71:$B$90
Name ListaCatOport: Critérios!$B$61:$B$67
Name ListaCatRisco: Critérios!$B$50:$B$56
Name ListaConf: Critérios!$I$71:$I$73
Name ListaEficacia: Critérios!$C$71:$C$74
Name ListaFacil: Critérios!$J$71:$J$73
Name ListaFreq: Critérios!$M$71:$M$79
Name ListaOrigem: Critérios!L71C6:L90C6
Name ListaPartes: Critérios!L71C20:L86C20
Name ListaReducao: Critérios!$K$71:$K$73
Name ListaStatus: Critérios!$G$71:$G$74
Name ListaTipoCtrl: Critérios!$Q$71:$Q$75
Name ListaTipoRisco: Critérios!$H$71:$H$74
Name ListaVeloc: Critérios!$O$71:$O$74
Name ListaVolat: Critérios!$P$71:$P$73
Name LstCrit: Maturidade_Auditoria!$B$175:$B$177
Name LstEficacia: Maturidade_Auditoria!$E$175:$E$178
Name LstMetodo: Maturidade_Auditoria!$D$175:$D$179
Name LstResultado: Maturidade_Auditoria!$C$175:$C$178
Name LstTeste: Maturidade_Auditoria!$A$175:$A$177
Name MatGrau: Maturidade_Auditoria!$B$13
Name MesesRev: Critérios!$H$25:$H$28
Name MetaGrau: Maturidade_Auditoria!$B$8
Name MinIdx: Critérios!$C$20
Name MonSit: Monitoramento!$L$5:$L$64
Name Niveis: Critérios!$B$25:$B$28
Name OportId: Oportunidades!$A$5:$A$154
Name PlanosAbertura: Planos!$I$7:$I$296
Name PlanosCod: Planos!$A$7:$A$296
Name PlanosIdRef: Planos!$B$7:$B$296
Name PlanosPrazo: Planos!$F$7:$F$296
Name PlanosStatus: Planos!$G$7:$G$296
Name PlanoUrl: Critérios!$C$18
Name ProbMedia: Critérios!$R$71:$R$75

Sheet 00_LEIA-ME
A1: RG-SGA-02 — Gestão de Riscos e Oportunidades — registo corporativo multiárea com a matriz do SGA
A2: Sistema de Gestão Ambiental NP EN ISO 14001:2026 · Plasticom — Unidade 1 (Marinha Grande, Portugal) · ficheiro gestao-riscos-oportunidades-v3.6-Plasticom.xlsx (fábrica simulada)
A4: CONTROLO DO DOCUMENTO (7.5 — informação documentada)
A5: Código do registo | B5: RG-SGA-02 (registo corporativo: REG-RISCOS-01 / REG-OPORT-01)
A6: Título | B6: Gestão de Riscos e Oportunidades — Identificação, Avaliação, Tratamento e Monitorização
A7: Versão / Revisão | B7: 02 — integra a Matriz_RO e os critérios do SGA (antes aba própria) e consolida abas
A8: Data de emissão | B8: 46289
A9: Elaborado por | B9: Gestor(a) do SGA / EHS
A10: Aprovado por | B10: Diretor Geral
A11: Estado | B11: Em vigor
A12: Retenção | B12: 5 anos após substituição
A13: Localização | B13: Repositório controlado do SGA > SGA_Sistema-de-gestao-ambiental (versão eletrónica é a versão controlada; cópias impressas são não controladas)
A15: FINALIDADE E ÂMBITO
A16: Finalidade | B16: Registo único de riscos (ameaças) e oportunidades da Plasticom — qualidade, SST, ambiente e negócio. Todos os itens usam a escala 5×5 (probabilidade × impacto/benefício). Os itens do SGA (ISO 14001) têm ainda a avaliação do curso no grupo de colunas 'METODOLOGIA SGA' (Nível = P × S; P 1 a 3; S −1 a −3 para riscos e 1 a 3 para oportunidades), com a decisão e a ação de tratamento.
A17: Atividades do curso | B17: Atividade 3.1 — Aplicação da Matriz de Riscos e Planeamento de Ações: filtrar 'Selecionado Atividade 3.1' = Sim (4 itens da SWOT: RO-01 a RO-04).
A18: Requisitos ISO 14001:2026 | B18: 6.1.1; 6.1.4 Riscos e oportunidades; 6.1.5 Planeamento de ações (numeração ISO 14001:2026)
A19: Itens do SGA migrados | B19: Riscos: RO-02 = R35; RO-05 = R36; RO-07 = R37; RO-08 = R38; RO-12 = R39; consolidados em riscos já existentes: RO-04 = R34; RO-06 = R33; RO-10 = R30. Oportunidades: RO-09 = O15; consolidadas em oportunidades já existentes: RO-01 = O3; RO-03 = O5; RO-11 = O10. O ID original fica na coluna 'ID RO (SGA)'. O risco inerente dos itens novos é simulado (validar).
A21: ESTRUTURA DO FICHEIRO (16 abas)
A22: Riscos | B22: tbRiscos — registo de riscos: identificação, inerente, controlos, risco atual, tratamento, plano, eficácia, residual, monitorização, custo-benefício e, à direita, o grupo METODOLOGIA SGA.
A23: Oportunidades | B23: tbOportunidades — registo de oportunidades: potencial, portfólio, decisão, plano, resultado, retorno e o grupo METODOLOGIA SGA.
A24: Painel | B24: Visão consolidada (calculada): mapas de calor, alertas, planos, KRI e BowTie.
A25: Planos | B25: tbPlanos — espelho dos planos de ação / RNC (PAC ou RNC + nº) ligados por código aos riscos e oportunidades.
A26: KRI | B26: tbKRI — cadastro dos indicadores de risco: limite, sentido, tendência e situação (calculada).
A27: KRI_Coletas | B27: tbKRIColetas — medições dos KRI em formato longo (1 linha = 1 medição).
A28: BowTie | B28: tbBowTie — barreiras preventivas e reativas por risco, eficácia e fatores de intensificação.
A29: Monitoramento | B29: tbMonitoramento — rotinas de monitorização, comunicação e consulta por nível.
A30: Politica_Apetite | B30: Política de gestão de riscos e apetite ao risco (§1). O contexto (PESTEL, SWOT, partes interessadas, 5 forças, TOWS) regista-se só no RG-SGA-01 desde 24/09/2026. Ações ambientais: só no PAM (RG-SGA-06), ligadas pela coluna 'Cód. PAM (RG-SGA-06)'.
A31: Maturidade_Auditoria | B31: Avaliação do processo de gestão de riscos (calculada): A) Maturidade (linha 1), B) Auditoria — tbAuditorias (linha 68), C) Plano ABR — tbPlanoABR (linha 104), D) Guia de avaliação (linha 139). Substitui as abas Maturidade, Auditoria, Plano ABR e Guia_Avaliação.
A32: Maturidade_Registro | B32: tbMat — avaliação de maturidade por critério e ciclo (4 testes de evidência).
A33: Auditoria_Registro | B33: tbAud — constatações de auditoria (1 linha = 1 pergunta avaliada).
... A36: Dicionário_Dados | B36: tbDicionario — uma linha por campo de cada tabela: tipo, formato, valores permitidos e descrição.
A38: CONVENÇÕES (prontas para análise de dados e machine learning)
A39: Tabelas | B39: Cada registo é uma Tabela Excel com nome próprio (tb*): uma linha = um registo, cabeçalho único. Ler com Power BI/Power Query (Obter Dados > Tabela) ou com pandas: Riscos e Oportunidades têm o cabeçalho na linha 4 (pd.read_excel(ficheiro, sheet_name='Riscos', header=3)). As tabelas têm linhas de reserva vazias: filtrar pelo ID não vazio.
A40: Texto azul / fundo cinzento | B40: Azul = entrada; cabeçalho laranja e fundo cinzento = coluna CALCULADA por fórmula (não escrever por cima).
A41: Validação | B41: Colunas com lista controlada só aceitam valores das listas em Critérios (evita categorias duplicadas por grafia diferente).
A42: Chaves | B42: ID (R1…, O1…) é a chave primária; 'ID RO (SGA)' liga ao SGA (RG-SGA-01 contexto, RG-SGA-06 PAM); campos com vários IDs usam ';' — ver SGA-00_Indice_Modelo_Dados.xlsx.
A43: Segmentação | B43: Para filtrar só o SGA: filtro ou segmentação de dados (Tabela > Inserir Segmentação) em 'ID RO (SGA)' não vazio, 'Significância SGA' ou 'Selecionado Atividade 3.1'.
A44: Datas e unidades | B44: Datas em formato data (aaaa-mm-dd); números como números; a unidade está no nome da coluna ou no dicionário.
A45: Dados simulados | B45: Fábrica simulada Plasticom. Dados operacionais derivados do dataset do projeto (datasets/silver); dados ambientais e de conformidade são simulação didática — confirmar aplicabilidade legal e números antes de uso real.
A47: LIGAÇÕES A OUTROS REGISTOS
A48: RG-SGA-01 Contexto | B48: A coluna 'ID de origem (contexto SGA)' aponta para o item SWOT/PESTEL de origem.
A49: RG-SGA-04 Requisitos legais | B49: A coluna 'ID de origem (contexto SGA)' = LEG-xx aponta para a obrigação de conformidade.
A50: RG-SGA-06 PAM | B50: A coluna 'Cód. PAM (RG-SGA-06)' aponta para a ação no Plano de Ações de Melhoria (Mod.G.10.00); o PAM usa o 'ID RO (SGA)'.
A51: Registos_SGA_Plasticom/SGA-02_Gestao_Riscos_Oportunidades.xlsx | B51: Registo do SGA RG-SGA-02, revisão 02 (24/09/2026): só os itens do SGA, com a mesma estrutura deste ficheiro — abas Riscos (tbl_riscos) e Oportunidades (tbl_oportunidades), critérios P×S na folha Listas. Chave comum: ID_RO = 'ID RO (SGA)'; a coluna ID_Registo_Corporativo do SGA-02 aponta para o ID deste ficheiro (R30, R33–R39; O3, O5, O10, O15). A avaliação 5×5, o inerente, o critério de eficácia e o BowTie ficam aqui.

Sheet Riscos
A1: REGISTRO DE RISCOS (AMEAÇAS) — FÁBRICA, USO MULTIÁREA | L1: Registros da Plasticom (fábrica simulada; dados do raio-X analítico) | Texto AZUL = preencher | Fundo CINZA = fórmula (não editar) | Código do plano: PAC 202601 ou RNC 202601 | Passe o mouse nos cabeçalhos: instruções por coluna | Use os botões [–] acima das colunas para recolher blocos
A2: Unidade / fábrica | D2: Plasticom — Unidade 1 (Portugal) | E2: Escopo / período | G2: Todas as áreas — jul/2025 a dez/2026 | I2: Responsável | J2: Coordenação do SGI | L2: Versão | N2: 1/2026 | P2: Atualizado em | R2: 46387 | U2: Cód. documento | W2: REG-RISCOS-01 | Y2: Aprovado por / em | AA2: Direção — 22/12/2026
A3: IDENTIFICAÇÃO | N3: INERENTE (sem considerar controles) | R3: CONTROLES EXISTENTES | T3: RISCO ATUAL (com os controles existentes) | Y3: TRATAMENTO | AI3: VÍNCULO PLANO / RNC | AM3: EFICÁCIA | AP3: RESIDUAL (após o tratamento) | AU3: MONITORAMENTO, REVISÃO E ALERTA | BA3: OUTROS | BD3: COMPLEMENTOS (velocidade, controle, custo-benefício e continuidade) | BM3: METODOLOGIA SGA — ISO 14001:2026 (curso UC00557 · Nível = P × S, escala 3×3; critérios em Critérios › Metodologia do SGA)
A4: ID | B4: Área / processo responsável | C4: Descrição do risco | D4: Origem | E4: Tipo de risco | F4: Nível de análise | G4: Objetivo afetado | H4: Situação vs. análise anterior | I4: Parte interessada afetada | J4: Causa | K4: Causa (6M) | L4: Consequência (impacto) | M4: Categoria de impacto | N4: Prob. inerente | O4: Imp. inerente | P4: Score inerente | Q4: Nível inerente | R4: Controles existentes | S4: Eficácia dos controles | T4: Prob. atual | U4: Imp. atual | V4: Score atual | W4: Nível atual | X4: Confiança da estimativa | Y4: Ação recomendada | Z4: Ação adotada | AA4: Hierarquia do controle principal | AB4: Aceite válido até | AC4: Resumo da ação | AD4: Dono do risco | AE4: Resp. da ação | AF4: Prazo (ação simples) | AG4: Status (ação simples) | AH4: Critério de eficácia (meta) | AI4: Cód. plano de ação / RNC | AJ4: Abrir plano (link) | AK4: Status atual | AL4: Prazo atual | AM4: Verificar eficácia em | AN4: Eficácia do tratamento | AO4: Data aval. eficácia | AP4: Prob. residual | AQ4: Imp. residual | AR4: Score residual | AS4: Nível residual | AT4: Residual aceitável? | AU4: Indicador (KRI) / gatilho de reavaliação | AV4: Ocorrências (últimos 12 meses) | AW4: Avaliado em | AX4: Avaliado por (equipe) | AY4: Próx. revisão | AZ4: Alerta | BA4: Justificativa / evidências / notas | BB4: Riscos / oport. relacionados (IDs) | BC4: Ordem (ranking) | BD4: Velocidade de impacto | BE4: Volatilidade da probabilidade | BF4: Tipo do controle principal | BG4: Custo estimado do tratamento (€) | BH4: Perda potencial se ocorrer (€) | BI4: Perda esperada (€) | BJ4: Leitura custo-benefício | BK4: MAO: parada máx. aceitável (horas) | BL4: Plano de contingência / continuidade (cód. ou link) | BM4: ID RO (SGA) | BN4: Data de identificação (SGA) | BO4: ID de origem (contexto SGA) | BP4: Selecionado Atividade 3.1 | BQ4: Área de gestão (SGA) | BR4: Processo (código SGA) | BS4: Tema (SGA) | BT4: Partes interessadas (SGA) | BU4: Probabilidade SGA | BV4: Severidade SGA | BW4: P (valor SGA) | BX4: S (valor SGA) | BY4: Nível SGA (P×S) | BZ4: Significância SGA | CA4: Aceitabilidade SGA | CB4: Decisão SGA | CC4: Tipo de ação SGA | CD4: Cód. PAM (RG-SGA-06) | CE4: Probabilidade SGA residual | CF4: Severidade SGA residual | CG4: Nível SGA residual | CH4: Significância SGA residual | CI4: Simulação forçada (Atv 3.1)
A5: R1 | B5: Sopro (ISBM) | C5: Instabilidade da espessura de parede na ISBM-003 gera frascos fora de especificação e lotes rejeitados/refeitos | D5: Análise de dados / raio-X analítico | E5: Técnico | F5: Operacional | G5: Cpk ≥ 1,33 nas características críticas | H5: Novo | I5: Clientes de cosmética (marcas UE) | J5: Programação do parison instável: dispersão de espessura (RangeR ≈ 3,0× as demais ISBM) com viés para ombro fino | K5: Máquina | L5: Rejeição e refação de lote (NC-01319), reclamações de frasco deformado/colapsado, custo de refugo e retrabalho | M5: Qualidade / Cliente | N5: 4 | O5: 4 | P5: =IF(COUNT($N5:$O5)=2,$N5*$O5,"") -> 16 | Q5: =IF($P5="","",INDEX(Niveis,MAX(IFERROR(MATCH($P5,Limites,1),1),IF($O5=5,MinIdx,1)))) -> Crítico | R5: Cartas X-barra/R por subgrupo; AQL por lote; inspeção de espessura por turno | S5: Média | T5: 4 | U5: 3 | V5: =IF(COUNT($T5:$U5)=2,$T5*$U5,"") -> 12 | W5: =IF($V5="","",INDEX(Niveis,MAX(IFERROR(MATCH($V5,Limites,1),1),IF($U5=5,MinIdx,1)))) -> Alto | X5: Alta | Y5: =IF(IF($W5<>"",$W5,$Q5)="","",INDEX(AcaoRisco,MATCH(IF($W5<>"",$W5,$Q5),Niveis,0))) -> Mitigar | Z5: Mitigar | AA5: Controle de engenharia | AC5: Verificar programação do parison, atuadores/sensores e cabeçote; comparar Cpk e RangeR antes/depois (RC-01) | AD5: Gerente de Produção | AE5: Eng. de Processo | AH5: RangeR ISBM-003 ≤ 1,3× a média das demais ISBM e Cpk ≥ 1,33 por 3 meses | AI5: PAC 202601 | AJ5: =IF(OR($AI5="",PlanoUrl=""),"",HYPERLINK(SUBSTITUTE(PlanoUrl,"{COD}",SUBSTITUTE($AI5," ","%20")),"↗")) | AK5: =IF($C5="","",IF($AI5="",$AG5&"",IFERROR(IF(INDEX(PlanosStatus,MATCH($AI5,PlanosCod,0))="",$AG5&"",INDEX(PlanosStatus,MATCH($AI5,PlanosCod,0))),$AG5&""))) -> Em andamento | AL5: =IF($C5="","",IF($AI5="",IF($AF5="","",$AF5),IFERROR(IF(INDEX(PlanosPrazo,MATCH($AI5,PlanosCod,0))="",IF($AF5="","",$AF5),INDEX(PlanosPrazo,MATCH($AI5,PlanosCod,0))),IF($AF5="","",$AF5)))) -> 46444 | AM5: 46538 | AP5: 2 | AQ5: 3 | AR5: =IF(COUNT($AP5:$AQ5)=2,$AP5*$AQ5,"") -> 6 | AS5: =IF($AR5="","",INDEX(Niveis,MAX(IFERROR(MATCH($AR5,Limites,1),1),IF($AQ5=5,MinIdx,1)))) -> Baixo | AT5: Sim | AU5: Razão RangeR espessura ISBM-003 ÷ demais ISBM (aba KRI) | AV5: 52 | AW5: 46371 | AX5: Comitê da Qualidade | AY5: =IF(OR($AW5="",IF(AND($AN5="Eficaz",$AS5<>""),$AS5,IF($W5<>"",$W5,$Q5))=""),"",EDATE($AW5,INDEX(MesesRev,MATCH(IF(AND($AN5="Eficaz",$AS5<>""),$AS5,IF($W5<>"",$W5,$Q5)),Niveis,0)))) -> 46461 | AZ5: =IF($C5="","",IF($AD5="","Sem dono",IF($W5="","Falta avaliação",IF(AND($AI5<>"",COUNTIF(PlanosCod,$AI5)=0),"Código não encontrado",IF(AND($AI5<>"",IFERROR(INDEX(PlanosIdRef,MATCH($AI5,PlanosCod,0))&"","")<>"",ISERROR(SEARCH(";"&$A5&";",";"&SUBSTITUTE(SUBSTITUTE(IFERROR(INDEX(PlanosIdRef,MATCH($AI5,PlanosCod,0))&"","")," ",""),",",";")&";"))),"Vínculo divergente",IF(AND(ISNUMBER($P5),ISNUMBER($V5),$V5<$P5,OR($S5="",$S5="Inexistente")),"Redução s/ controle",IF(AND(ISNUMBER($AR5),ISNUMBER($V5),$AR5<$V5,NOT(OR($Z5="Prevenir",$Z5="Mitigar",$Z5="Transferir / compartilhar")),$AC5="",$AI5=""),"Residual s/ tratamento",IF(AND(LEFT($AI5,3)="RNC",N(IFERROR(INDEX(PlanosAbertura,MATCH($AI5,PlanosCod,0)),0))>N($AW5)),"Reavaliar após RNC",IF(AND(N($AV5)>=1,ISNUMBER($T5),$T5<=2),"Recalibrar probabilidade",IF(AND($Z5="Aceitar",$BA5=""),"Aceite sem justificativa",IF(AND($Z5="Aceitar",ISNUMBER($AB5),$AB5<TODAY()),"Aceite vencido",IF(AND(OR($Z5="Aceitar",$Z5="Monitorar"),$Y5<>"Monitorar",$Y5<>""),"Aprovar aceite",IF(AND($Z5<>"Aceitar",$Z5<>"Monitorar",$Z5<>"Aprofundar análise",$AC5="",$AI5="",IFERROR(MATCH(IF($W5<>"",$W5,$Q5),Niveis,0),0)>IF(N(IFERROR(INDEX(ApetIdx,MATCH($M5,ListaCatRisco,0)),0))=0,IdxExige-1,INDEX(ApetIdx,MATCH($M5,ListaCatRisco,0)))),"Sem ação",IF($Z5="Aprofundar análise","Aprofundar análise",IF(AND(OR($Z5="Prevenir",$Z5="Mitigar",$Z5="Transferir / compartilhar"),$AH5=""),"Definir critério de eficácia",IF(AND(OR($Z5="Prevenir",$Z5="Mitigar",$Z5="Transferir / compartilhar"),OR($AA5="Controle administrativo",$AA5="EPI"),IFERROR(MATCH(IF($W5<>"",$W5,$Q5),Niveis,0),0)>=3),"Rever hierarquia de controle",IF(COUNTIFS(KriId,$A5,KriSit,"Estourou")+COUNTIFS(KriId,$A5,KriSit,"Atenção")>0,"KRI em alerta",IF(COUNTIFS(BtId,$A5,BtEf,"Baixa")+COUNTIFS(BtId,$A5,BtEf,"Inexistente")>0,"Barreira fraca",IF($AN5="Não eficaz","Ação ineficaz",IF(AND($AL5<>"",$AL5<TODAY(),$AK5<>"Concluído",$AK5<>"Cancelado"),"Ação vencida",IF(AND($AN5<>"Eficaz",OR($AK5="Concluído",AND(ISNUMBER($AM5),$AM5<TODAY()))),"Avaliar eficácia",IF(AND($AN5="Eficaz",OR($AS5="",$AT5="")),"Concluir residual",IF($AT5="Não","Tratamento adicional",IF(AND($AT5="Sim",$AS5<>"",IFERROR(MATCH($AS5,Niveis,0),0)>IF(N(IFERROR(INDEX(ApetIdx,MATCH($M5,ListaCatRisco,0)),0))=0,IdxExige-1,INDEX(ApetIdx,MATCH($M5,ListaCatRisco,0)))),"Aceite fora do apetite",IF(AND(COUNTIF(BtId,$A5)=0,OR(IFERROR(MATCH(IF($W5<>"",$W5,$Q5),Niveis,0),0)>=3,AND(OR($S5="Baixa",$S5="Inexistente"),IFERROR(MATCH(IF($W5<>"",$W5,$Q5),Niveis,0),0)>=2))),"Sem BowTie",IF(AND($AY5<>"",$AY5<TODAY()),"Revisão vencida",IF(AND($AL5<>"",N($AL5)-TODAY()<=DiasAlerta,$AK5<>"Concluído",$AK5<>"Cancelado"),"Vence em breve","OK"))))))))))))))))))))))))))) -> KRI em alerta | BA5: Evidência: RangeR ISBM-003 ≈ 3,0× pares (18 meses); rejeição da máquina 3,94% vs 2,4% da planta. Causa física a confirmar em campo (RC-01). | BB5: R2;R16 | BC5: =IF($V5="","",1+COUNTIF($V$5:$V$154,">"&$V5)+COUNTIFS($V$5:$V$154,$V5,$U$5:$U$154,">"&$U5)+COUNTIFS($V$4:$V4,$V5,$U$4:$U4,$U5)) -> 7 | BD5: Média — semanas | BE5: Moderada | BF5: Detectivo | BG5: 18000 | BH5: 45000 | BI5: =IF(OR($BH5="",$T5=""),"",IFERROR($BH5*INDEX(ProbMedia,$T5),"")) -> 31500 | BJ5: =IF(OR($BG5="",$BI5=""),"",IF(OR(LEFT($M5,3)="SST",LEFT($M5,5)="Legal",LEFT($M5,8)="Ambienta"),"SST/Ambiental/Legal: custo não justifica aceitar (apetite e ALARP)",IF($BG5>$BI5,"Custo maior que a perda esperada: reter/aceitar é defensável, com justificativa","Custo menor ou igual à perda esperada: tratar compensa"))) -> Custo menor ou igual à perda esperada: tratar compensa | BW5: =IF($BU5="","",IFERROR(INDEX(SgaProbValor,MATCH($BU5,SgaProbNivel,0)),"")) | BX5: =IF($BV5="","",IFERROR(INDEX(SgaSevRiValor,MATCH($BV5,SgaSevRiNivel,0)),"")) | BY5: =IF(COUNT($BW5:$BX5)=2,$BW5*$BX5,"") | BZ5: =IF($BY5="","",IF($BY5<=SgaLimRiSig,"SIGNIFICATIVO",IF($BY5<=SgaLimRiTol,"TOLERÁVEL","BAIXO"))) | CA5: =IF($BZ5="","",IF($BZ5="SIGNIFICATIVO","NÃO ACEITÁVEL","ACEITÁVEL")) | CG5: =IF(OR($CE5="",$CF5=""),"",IFERROR(INDEX(SgaProbValor,MATCH($CE5,SgaProbNivel,0))*INDEX(SgaSevRiValor,MATCH($CF5,SgaSevRiNivel,0)),"")) | CH5: =IF($CG5="","",IF($CG5<=SgaLimRiSig,"SIGNIFICATIVO",IF($CG5<=SgaLimRiTol,"TOLERÁVEL","BAIXO")))
A6: R2 | B6: Sopro (ISBM) | C6: Desgaste acumulado do molde M-SOP-007 (ISBM-001) eleva Flash/Leakage até a reforma | D6: Análise de dados / raio-X analítico | E6: Técnico | F6: Operacional | G6: Taxa de rejeição ≤ 2,0% (baseline 2,39%) | H6: Mantido | I6: Clientes de cosmética (marcas UE) | J6: Desgaste do molde cresce com as unidades acumuladas; sem contador de ciclos desde a reforma, a ação ocorre só após o lote falhar | K6: Máquina | L6: Lote rejeitado/refeito (NC-01321), Flash e vazamento em frascos e reclamações | M6: Qualidade / Cliente | N6: 4 | O6: 4 | P6: =IF(COUNT($N6:$O6)=2,$N6*$O6,"") -> 16 | Q6: =IF($P6="","",INDEX(Niveis,MAX(IFERROR(MATCH($P6,Limites,1),1),IF($O6=5,MinIdx,1)))) -> Crítico | R6: Reforma do molde em 15/06/2026 (PAC 202604); inspeção AQL de Flash/Leakage por lote | S6: Média | T6: 3 | U6: 3 | V6: =IF(COUNT($T6:$U6)=2,$T6*$U6,"") -> 9 | W6: =IF($V6="","",INDEX(Niveis,MAX(IFERROR(MATCH($V6,Limites,1),1),IF($U6=5,MinIdx,1)))) -> Médio | X6: Alta | Y6: =IF(IF($W6<>"",$W6,$Q6)="","",INDEX(AcaoRisco,MATCH(IF($W6<>"",$W6,$Q6),Niveis,0))) -> Mitigar | Z6: Mitigar | AA6: Controle de engenharia | AC6: Criar contador CiclosDesdeReforma com limite de alerta/ação e inspeção por condição (RC-12) | AD6: Gerente de Manutenção | AE6: Eng. de Manutenção | AH6: Nenhum lote rejeitado por Flash/Leakage no M-SOP-007 por 6 meses; reforma acionada por condição | AI6: PAC 202605 | AJ6: =IF(OR($AI6="",PlanoUrl=""),"",HYPERLINK(SUBSTITUTE(PlanoUrl,"{COD}",SUBSTITUTE($AI6," ","%20")),"↗")) | AK6: =IF($C6="","",IF($AI6="",$AG6&"",IFERROR(IF(INDEX(PlanosStatus,MATCH($AI6,PlanosCod,0))="",$AG6&"",INDEX(PlanosStatus,MATCH($AI6,PlanosCod,0))),$AG6&""))) -> Aberto | AL6: =IF($C6="","",IF($AI6="",IF($AF6="","",$AF6),IFERROR(IF(INDEX(PlanosPrazo,MATCH($AI6,PlanosCod,0))="",IF($AF6="","",$AF6),INDEX(PlanosPrazo,MATCH($AI6,PlanosCod,0))),IF($AF6="","",$AF6)))) -> 46477 | AM6: 46568 | AP6: 2 | AQ6: 3 | AR6: =IF(COUNT($AP6:$AQ6)=2,$AP6*$AQ6,"") -> 6 | AS6: =IF($AR6="","",INDEX(Niveis,MAX(IFERROR(MATCH($AR6,Limites,1),1),IF($AQ6=5,MinIdx,1)))) -> Baixo | AT6: Sim | AU6: Unidades desde a reforma e defeitos Flash+Leakage por lote (aba KRI) | AV6: 21 | AW6: 46371 | AX6: Manutenção + Qualidade | AY6: =IF(OR($AW6="",IF(AND($AN6="Eficaz",$AS6<>""),$AS6,IF($W6<>"",$W6,$Q6))=""),"",EDATE($AW6,INDEX(MesesRev,MATCH(IF(AND($AN6="Eficaz",$AS6<>""),$AS6,IF($W6<>"",$W6,$Q6)),Niveis,0)))) -> 46553 | AZ6: =IF($C6="","",IF($AD6="","Sem dono",IF($W6="","Falta avaliação",IF(AND($AI6<>"",COUNTIF(PlanosCod,$AI6)=0),"Código não encontrado",IF(AND($AI6<>"",IFERROR(INDEX(PlanosIdRef,MATCH($AI6,PlanosCod,0))&"","")<>"",ISERROR(SEARCH(";"&$A6&";",";"&SUBSTITUTE(SUBSTITUTE(IFERROR(INDEX(PlanosIdRef,MATCH($AI6,PlanosCod,0))&"","")," ",""),",",";")&";"))),"Vínculo divergente",IF(AND(ISNUMBER($P6),ISNUMBER($V6),$V6<$P6,OR($S6="",$S6="Inexistente")),"Redução s/ controle",IF(AND(ISNUMBER($AR6),ISNUMBER($V6),$AR6<$V6,NOT(OR($Z6="Prevenir",$Z6="Mitigar",$Z6="Transferir / compartilhar")),$AC6="",$AI6=""),"Residual s/ tratamento",IF(AND(LEFT($AI6,3)="RNC",N(IFERROR(INDEX(PlanosAbertura,MATCH($AI6,PlanosCod,0)),0))>N($AW6)),"Reavaliar após RNC",IF(AND(N($AV6)>=1,ISNUMBER($T6),$T6<=2),"Recalibrar probabilidade",IF(AND($Z6="Aceitar",$BA6=""),"Aceite sem justificativa",IF(AND($Z6="Aceitar",ISNUMBER($AB6),$AB6<TODAY()),"Aceite vencido",IF(AND(OR($Z6="Aceitar",$Z6="Monitorar"),$Y6<>"Monitorar",$Y6<>""),"Aprovar aceite",IF(AND($Z6<>"Aceitar",$Z6<>"Monitorar",$Z6<>"Aprofundar análise",$AC6="",$AI6="",IFERROR(MATCH(IF($W6<>"",$W6,$Q6),Niveis,0),0)>IF(N(IFERROR(INDEX(ApetIdx,MATCH($M6,ListaCatRisco,0)),0))=0,IdxExige-1,INDEX(ApetIdx,MATCH($M6,ListaCatRisco,0)))),"Sem ação",IF($Z6="Aprofundar análise","Aprofundar análise",IF(AND(OR($Z6="Prevenir",$Z6="Mitigar",$Z6="Transferir / compartilhar"),$AH6=""),"Definir critério de eficácia",IF(AND(OR($Z6="Prevenir",$Z6="Mitigar",$Z6="Transferir / compartilhar"),OR($AA6="Controle administrativo",$AA6="EPI"),IFERROR(MATCH(IF($W6<>"",$W6,$Q6),Niveis,0),0)>=3),"Rever hierarquia de controle",IF(COUNTIFS(KriId,$A6,KriSit,"Estourou")+COUNTIFS(KriId,$A6,KriSit,"Atenção")>0,"KRI em alerta",IF(COUNTIFS(BtId,$A6,BtEf,"Baixa")+COUNTIFS(BtId,$A6,BtEf,"Inexistente")>0,"Barreira fraca",IF($AN6="Não eficaz","Ação ineficaz",IF(AND($AL6<>"",$AL6<TODAY(),$AK6<>"Concluído",$AK6<>"Cancelado"),"Ação vencida",IF(AND($AN6<>"Eficaz",OR($AK6="Concluído",AND(ISNUMBER($AM6),$AM6<TODAY()))),"Avaliar eficácia",IF(AND($AN6="Eficaz",OR($AS6="",$AT6="")),"Concluir residual",IF($AT6="Não","Tratamento adicional",IF(AND($AT6="Sim",$AS6<>"",IFERROR(MATCH($AS6,Niveis,0),0)>IF(N(IFERROR(INDEX(ApetIdx,MATCH($M6,ListaCatRisco,0)),0))=0,IdxExige-1,INDEX(ApetIdx,MATCH($M6,ListaCatRisco,0)))),"Aceite fora do apetite",IF(AND(COUNTIF(BtId,$A6)=0,OR(IFERROR(MATCH(IF($W6<>"",$W6,$Q6),Niveis,0),0)>=3,AND(OR($S6="Baixa",$S6="Inexistente"),IFERROR(MATCH(IF($W6<>"",$W6,$Q6),Niveis,0),0)>=2))),"Sem BowTie",IF(AND($AY6<>"",$AY6<TODAY()),"Revisão vencida",IF(AND($AL6<>"",N($AL6)-TODAY()<=DiasAlerta,$AK6<>"Concluído",$AK6<>"Cancelado"),"Vence em breve","OK"))))))))))))))))))))))))))) -> KRI em alerta | BA6: Defeitos Flash/Leakage por lote no M-SOP-007: pico de 1,68 em 2026-04, queda após a reforma de 15/06/2026 e nova subida lenta. Limite de ciclos provisório: calibrar pela curva defeito × ciclos. | BB6: R1;R19 | BC6: =IF($V6="","",1+COUNTIF($V$5:$V$154,">"&$V6)+COUNTIFS($V$5:$V$154,$V6,$U$5:$U$154,">"&$U6)+COUNTIFS($V$4:$V5,$V6,$U$4:$U5,$U6)) -> 21 | BD6: Média — semanas | BE6: Moderada | BF6: Preventivo | BG6: 25000 | BH6: 75000 | BI6: =IF(OR($BH6="",$T6=""),"",IFERROR($BH6*INDEX(ProbMedia,$T6),"")) -> 37500 | BJ6: =IF(OR($BG6="",$BI6=""),"",IF(OR(LEFT($M6,3)="SST",LEFT($M6,5)="Legal",LEFT($M6,8)="Ambienta"),"SST/Ambiental/Legal: custo não justifica aceitar (apetite e ALARP)",IF($BG6>$BI6,"Custo maior que a perda esperada: reter/aceitar é defensável, com justificativa","Custo menor ou igual à perda esperada: tratar compensa"))) -> Custo menor ou igual à perda esperada: tratar compensa | BW6: =IF($BU6="","",IFERROR(INDEX(SgaProbValor,MATCH($BU6,SgaProbNivel,0)),"")) | BX6: =IF($BV6="","",IFERROR(INDEX(SgaSevRiValor,MATCH($BV6,SgaSevRiNivel,0)),"")) | BY6: =IF(COUNT($BW6:$BX6)=2,$BW6*$BX6,"") | BZ6: =IF($BY6="","",IF($BY6<=SgaLimRiSig,"SIGNIFICATIVO",IF($BY6<=SgaLimRiTol,"TOLERÁVEL","BAIXO"))) | CA6: =IF($BZ6="","",IF($BZ6="SIGNIFICATIVO","NÃO ACEITÁVEL","ACEITÁVEL")) | CG6: =IF(OR($CE6="",$CF6=""),"",IFERROR(INDEX(SgaProbValor,MATCH($CE6,SgaProbNivel,0))*INDEX(SgaSevRiValor,MATCH($CF6,SgaSevRiNivel,0)),"")) | CH6: =IF($CG6="","",IF($CG6<=SgaLimRiSig,"SIGNIFICATIVO",IF($CG6<=SgaLimRiTol,"TOLERÁVEL","BAIXO")))
A7: R3 | B7: Sopro (ISBM) | C7: Paradas não planejadas recorrentes na ISBM-005 por envelhecimento hidráulico reduzem a disponibilidade | D7: Análise de dados / raio-X analítico | E7: Técnico | F7: Operacional | G7: OEE ≥ 81,1% e Disponibilidade ≥ 90% (baseline 79,1% / 87,4%) | H7: Novo | I7: Acionistas / Direção | J7: Envelhecimento do sistema hidráulico: frequência de paradas ≈ 2,3× a base; sem análise de condição por horas de operação | K7: Máquina | L7: Disponibilidade ≈ 80% (planta 87,4%), perda de capacidade e atraso de ordens; qualidade não é afetada | M7: Produção / Ativos | N7: 5 | O7: 3 | P7: =IF(COUNT($N7:$O7)=2,$N7*$O7,"") -> 15 | Q7: =IF($P7="","",INDEX(Niveis,MAX(IFERROR(MATCH($P7,Limites,1),1),IF($O7=5,MinIdx,1)))) -> Alto | R7: Manutenção preventiva calendarizada; reposição reativa de componentes | S7: Baixa | T7: 4 | U7: 3 | V7: =IF(COUNT($T7:$U7)=2,$T7*$U7,"") -> 12 | W7: =IF($V7="","",INDEX(Niveis,MAX(IFERROR(MATCH($V7,Limites,1),1),IF($U7=5,MinIdx,1)))) -> Alto | X7: Alta | Y7: =IF(IF($W7<>"",$W7,$Q7)="","",INDEX(AcaoRisco,MATCH(IF($W7<>"",$W7,$Q7),Niveis,0))) -> Mitigar | Z7: Mitigar | AA7: Controle de engenharia | AC7: Inspeção hidráulica, histórico de componentes críticos e plano por horas de operação (MTBF/MTTR) (RC-06) | AD7: Gerente de Manutenção | AE7: Eng. de Manutenção | AH7: Paradas não planejadas da ISBM-005 ≤ 80 h/mês e disponibilidade ≥ 85% por 3 meses | AI7: PAC 202611 | AJ7: =IF(OR($AI7="",PlanoUrl=""),"",HYPERLINK(SUBSTITUTE(PlanoUrl,"{COD}",SUBSTITUTE($AI7," ","%20")),"↗")) | AK7: =IF($C7="","",IF($AI7="",$AG7&"",IFERROR(IF(INDEX(PlanosStatus,MATCH($AI7,PlanosCod,0))="",$AG7&"",INDEX(PlanosStatus,MATCH($AI7,PlanosCod,0))),$AG7&""))) -> Em andamento | AL7: =IF($C7="","",IF($AI7="",IF($AF7="","",$AF7),IFERROR(IF(INDEX(PlanosPrazo,MATCH($AI7,PlanosCod,0))="",IF($AF7="","",$AF7),INDEX(PlanosPrazo,MATCH($AI7,PlanosCod,0))),IF($AF7="","",$AF7)))) -> 46461 | AM7: 46568 | AP7: 3 | AQ7: 3 | AR7: =IF(COUNT($AP7:$AQ7)=2,$AP7*$AQ7,"") -> 9 | AS7: =IF($AR7="","",INDEX(Niveis,MAX(IFERROR(MATCH($AR7,Limites,1),1),IF($AQ7=5,MinIdx,1)))) -> Médio | AT7: Sim | AU7: Horas de parada não planejada/mês na ISBM-005 (aba KRI) | AV7: 3946 | AW7: 46371 | AX7: Manutenção + Produção | AY7: =IF(OR($AW7="",IF(AND($AN7="Eficaz",$AS7<>""),$AS7,IF($W7<>"",$W7,$Q7))=""),"",EDATE($AW7,INDEX(MesesRev,MATCH(IF(AND($AN7="Eficaz",$AS7<>""),$AS7,IF($W7<>"",$W7,$Q7)),Niveis,0)))) -> 46461 | AZ7: =IF($C7="","",IF($AD7="","Sem dono",IF($W7="","Falta avaliação",IF(AND($AI7<>"",COUNTIF(PlanosCod,$AI7)=0),"Código não encontrado",IF(AND($AI7<>"",IFERROR(INDEX(PlanosIdRef,MATCH($AI7,PlanosCod,0))&"","")<>"",ISERROR(SEARCH(";"&$A7&";",";"&SUBSTITUTE(SUBSTITUTE(IFERROR(INDEX(PlanosIdRef,MATCH($AI7,PlanosCod,0))&"","")," ",""),",",";")&";"))),"Vínculo divergente",IF(AND(ISNUMBER($P7),ISNUMBER($V7),$V7<$P7,OR($S7="",$S7="Inexistente")),"Redução s/ controle",IF(AND(ISNUMBER($AR7),ISNUMBER($V7),$AR7<$V7,NOT(OR($Z7="Prevenir",$Z7="Mitigar",$Z7="Transferir / compartilhar")),$AC7="",$AI7=""),"Residual s/ tratamento",IF(AND(LEFT($AI7,3)="RNC",N(IFERROR(INDEX(PlanosAbertura,MATCH($AI7,PlanosCod,0)),0))>N($AW7)),"Reavaliar após RNC",IF(AND(N($AV7)>=1,ISNUMBER($T7),$T7<=2),"Recalibrar probabilidade",IF(AND($Z7="Aceitar",$BA7=""),"Aceite sem justificativa",IF(AND($Z7="Aceitar",ISNUMBER($AB7),$AB7<TODAY()),"Aceite vencido",IF(AND(OR($Z7="Aceitar",$Z7="Monitorar"),$Y7<>"Monitorar",$Y7<>""),"Aprovar aceite",IF(AND($Z7<>"Aceitar",$Z7<>"Monitorar",$Z7<>"Aprofundar análise",$AC7="",$AI7="",IFERROR(MATCH(IF($W7<>"",$W7,$Q7),Niveis,0),0)>IF(N(IFERROR(INDEX(ApetIdx,MATCH($M7,ListaCatRisco,0)),0))=0,IdxExige-1,INDEX(ApetIdx,MATCH($M7,ListaCatRisco,0)))),"Sem ação",IF($Z7="Aprofundar análise","Aprofundar análise",IF(AND(OR($Z7="Prevenir",$Z7="Mitigar",$Z7="Transferir / compartilhar"),$AH7=""),"Definir critério de eficácia",IF(AND(OR($Z7="Prevenir",$Z7="Mitigar",$Z7="Transferir / compartilhar"),OR($AA7="Controle administrativo",$AA7="EPI"),IFERROR(MATCH(IF($W7<>"",$W7,$Q7),Niveis,0),0)>=3),"Rever hierarquia de controle",IF(COUNTIFS(KriId,$A7,KriSit,"Estourou")+COUNTIFS(KriId,$A7,KriSit,"Atenção")>0,"KRI em alerta",IF(COUNTIFS(BtId,$A7,BtEf,"Baixa")+COUNTIFS(BtId,$A7,BtEf,"Inexistente")>0,"Barreira fraca",IF($AN7="Não eficaz","Ação ineficaz",IF(AND($AL7<>"",$AL7<TODAY(),$AK7<>"Concluído",$AK7<>"Cancelado"),"Ação vencida",IF(AND($AN7<>"Eficaz",OR($AK7="Concluído",AND(ISNUMBER($AM7),$AM7<TODAY()))),"Avaliar eficácia",IF(AND($AN7="Eficaz",OR($AS7="",$AT7="")),"Concluir residual",IF($AT7="Não","Tratamento adicional",IF(AND($AT7="Sim",$AS7<>"",IFERROR(MATCH($AS7,Niveis,0),0)>IF(N(IFERROR(INDEX(ApetIdx,MATCH($M7,ListaCatRisco,0)),0))=0,IdxExige-1,INDEX(ApetIdx,MATCH($M7,ListaCatRisco,0)))),"Aceite fora do apetite",IF(AND(COUNTIF(BtId,$A7)=0,OR(IFERROR(MATCH(IF($W7<>"",$W7,$Q7),Niveis,0),0)>=3,AND(OR($S7="Baixa",$S7="Inexistente"),IFERROR(MATCH(IF($W7<>"",$W7,$Q7),Niveis,0),0)>=2))),"Sem BowTie",IF(AND($AY7<>"",$AY7<TODAY()),"Revisão vencida",IF(AND($AL7<>"",N($AL7)-TODAY()<=DiasAlerta,$AK7<>"Concluído",$AK7<>"Cancelado"),"Vence em breve","OK"))))))))))))))))))))))))))) -> KRI em alerta | BA7: Parada não planejada ISBM-005: ≈ 116 h/mês vs 70 h/mês na média das demais ISBM (custo ilustrativo € 350/h). Não atacar com mais inspeção de produto. | BB7: R23;R22 | BC7: =IF($V7="","",1+COUNTIF($V$5:$V$154,">"&$V7)+COUNTIFS($V$5:$V$154,$V7,$U$5:$U$154,">"&$U7)+COUNTIFS($V$4:$V6,$V7,$U$4:$U6,$U7)) -> 8 | BD7: Rápida — dias | BE7: Moderada | BF7: Preventivo | BG7: 60000 | BH7: 120000 | BI7: =IF(OR($BH7="",$T7=""),"",IFERROR($BH7*INDEX(ProbMedia,$T7),"")) -> 84000 | BJ7: =IF(OR($BG7="",$BI7=""),"",IF(OR(LEFT($M7,3)="SST",LEFT($M7,5)="Legal",LEFT($M7,8)="Ambienta"),"SST/Ambiental/Legal: custo não justifica aceitar (apetite e ALARP)",IF($BG7>$BI7,"Custo maior que a perda esperada: reter/aceitar é defensável, com justificativa","Custo menor ou igual à perda esperada: tratar compensa"))) -> Custo menor ou igual à perda esperada: tratar compensa | BK7: 24 | BL7: PCN-ISBM-01 (transferir ordens para ISBM-004/006) | BW7: =IF($BU7="","",IFERROR(INDEX(SgaProbValor,MATCH($BU7,SgaProbNivel,0)),"")) | BX7: =IF($BV7="","",IFERROR(INDEX(SgaSevRiValor,MATCH($BV7,SgaSevRiNivel,0)),"")) | BY7: =IF(COUNT($BW7:$BX7)=2,$BW7*$BX7,"") | BZ7: =IF($BY7="","",IF($BY7<=SgaLimRiSig,"SIGNIFICATIVO",IF($BY7<=SgaLimRiTol,"TOLERÁVEL","BAIXO"))) | CA7: =IF($BZ7="","",IF($BZ7="SIGNIFICATIVO","NÃO ACEITÁVEL","ACEITÁVEL")) | CG7: =IF(OR($CE7="",$CF7=""),"",IFERROR(INDEX(SgaProbValor,MATCH($CE7,SgaProbNivel,0))*INDEX(SgaSevRiValor,MATCH($CF7,SgaSevRiNivel,0)),"")) | CH7: =IF($CG7="","",IF($CG7<=SgaLimRiSig,"SIGNIFICATIVO",IF($CG7<=SgaLimRiTol,"TOLERÁVEL","BAIXO")))
A8: R4 | B8: Injeção | C8: Short shot e variação de peso na IM-002 causados por banda de aquecimento marginal e janela de parâmetros inadequada | D8: Análise de dados / raio-X analítico | E8: Técnico | F8: Operacional | G8: Taxa de rejeição ≤ 2,0% (baseline 2,39%) | H8: Novo | I8: Clientes de cosmética (marcas UE) | J8: Banda de aquecimento do canhão marginal: interação temperatura × velocidade de injeção fora da janela ótima | K8: Máquina | L8: Short shot (≈ 13,5 mil DPMO, 3,4× as demais), peças fora de peso, rejeição de lote e reclamações | M8: Qualidade / Cliente | N8: 4 | O8: 4 | P8: =IF(COUNT($N8:$O8)=2,$N8*$O8,"") -> 16 | Q8: =IF($P8="","",INDEX(Niveis,MAX(IFERROR(MATCH($P8,Limites,1),1),IF($O8=5,MinIdx,1)))) -> Crítico | R8: AQL por lote; carta de peso; parâmetros do setup padrão | S8: Média | T8: 4 | U8: 3 | V8: =IF(COUNT($T8:$U8)=2,$T8*$U8,"") -> 12 | W8: =IF($V8="","",INDEX(Niveis,MAX(IFERROR(MATCH($V8,Limites,1),1),IF($U8=5,MinIdx,1)))) -> Alto | X8: Alta | Y8: =IF(IF($W8<>"",$W8,$Q8)="","",INDEX(AcaoRisco,MATCH(IF($W8<>"",$W8,$Q8),Niveis,0))) -> Mitigar | Z8: Mitigar | AA8: Controle de engenharia | AC8: Corrida de confirmação independente do DOE (Short Shot 1,35% → 0,11%), atualizar standard work, plano de controle e FMEA (RC-05) | AD8: Gerente da Qualidade | AE8: Eng. da Qualidade | AH8: Short Shot IM-002 ≤ 1 500 DPMO e Cpk do peso ≥ 1,33 por 3 meses após replicação | AI8: PAC 202602 | AJ8: =IF(OR($AI8="",PlanoUrl=""),"",HYPERLINK(SUBSTITUTE(PlanoUrl,"{COD}",SUBSTITUTE($AI8," ","%20")),"↗")) | AK8: =IF($C8="","",IF($AI8="",$AG8&"",IFERROR(IF(INDEX(PlanosStatus,MATCH($AI8,PlanosCod,0))="",$AG8&"",INDEX(PlanosStatus,MATCH($AI8,PlanosCod,0))),$AG8&""))) -> Em andamento | AL8: =IF($C8="","",IF($AI8="",IF($AF8="","",$AF8),IFERROR(IF(INDEX(PlanosPrazo,MATCH($AI8,PlanosCod,0))="",IF($AF8="","",$AF8),INDEX(PlanosPrazo,MATCH($AI8,PlanosCod,0))),IF($AF8="","",$AF8)))) -> 46430 | AM8: 46538 | AP8: 2 | AQ8: 3 | AR8: =IF(COUNT($AP8:$AQ8)=2,$AP8*$AQ8,"") -> 6 | AS8: =IF($AR8="","",INDEX(Niveis,MAX(IFERROR(MATCH($AR8,Limites,1),1),IF($AQ8=5,MinIdx,1)))) -> Baixo | AT8: Sim | AU8: Short Shot DPMO da IM-002 (aba KRI) | AV8: 65 | AW8: 46371 | AX8: Comitê da Qualidade | AY8: =IF(OR($AW8="",IF(AND($AN8="Eficaz",$AS8<>""),$AS8,IF($W8<>"",$W8,$Q8))=""),"",EDATE($AW8,INDEX(MesesRev,MATCH(IF(AND($AN8="Eficaz",$AS8<>""),$AS8,IF($W8<>"",$W8,$Q8)),Niveis,0)))) -> 46461 | AZ8: =IF($C8="","",IF($AD8="","Sem dono",IF($W8="","Falta avaliação",IF(AND($AI8<>"",COUNTIF(PlanosCod,$AI8)=0),"Código não encontrado",IF(AND($AI8<>"",IFERROR(INDEX(PlanosIdRef,MATCH($AI8,PlanosCod,0))&"","")<>"",ISERROR(SEARCH(";"&$A8&";",";"&SUBSTITUTE(SUBSTITUTE(IFERROR(INDEX(PlanosIdRef,MATCH($AI8,PlanosCod,0))&"","")," ",""),",",";")&";"))),"Vínculo divergente",IF(AND(ISNUMBER($P8),ISNUMBER($V8),$V8<$P8,OR($S8="",$S8="Inexistente")),"Redução s/ controle",IF(AND(ISNUMBER($AR8),ISNUMBER($V8),$AR8<$V8,NOT(OR($Z8="Prevenir",$Z8="Mitigar",$Z8="Transferir / compartilhar")),$AC8="",$AI8=""),"Residual s/ tratamento",IF(AND(LEFT($AI8,3)="RNC",N(IFERROR(INDEX(PlanosAbertura,MATCH($AI8,PlanosCod,0)),0))>N($AW8)),"Reavaliar após RNC",IF(AND(N($AV8)>=1,ISNUMBER($T8),$T8<=2),"Recalibrar probabilidade",IF(AND($Z8="Aceitar",$BA8=""),"Aceite sem justificativa",IF(AND($Z8="Aceitar",ISNUMBER($AB8),$AB8<TODAY()),"Aceite vencido",IF(AND(OR($Z8="Aceitar",$Z8="Monitorar"),$Y8<>"Monitorar",$Y8<>""),"Aprovar aceite",IF(AND($Z8<>"Aceitar",$Z8<>"Monitorar",$Z8<>"Aprofundar análise",$AC8="",$AI8="",IFERROR(MATCH(IF($W8<>"",$W8,$Q8),Niveis,0),0)>IF(N(IFERROR(INDEX(ApetIdx,MATCH($M8,ListaCatRisco,0)),0))=0,IdxExige-1,INDEX(ApetIdx,MATCH($M8,ListaCatRisco,0)))),"Sem ação",IF($Z8="Aprofundar análise","Aprofundar análise",IF(AND(OR($Z8="Prevenir",$Z8="Mitigar",$Z8="Transferir / compartilhar"),$AH8=""),"Definir critério de eficácia",IF(AND(OR($Z8="Prevenir",$Z8="Mitigar",$Z8="Transferir / compartilhar"),OR($AA8="Controle administrativo",$AA8="EPI"),IFERROR(MATCH(IF($W8<>"",$W8,$Q8),Niveis,0),0)>=3),"Rever hierarquia de controle",IF(COUNTIFS(KriId,$A8,KriSit,"Estourou")+COUNTIFS(KriId,$A8,KriSit,"Atenção")>0,"KRI em alerta",IF(COUNTIFS(BtId,$A8,BtEf,"Baixa")+COUNTIFS(BtId,$A8,BtEf,"Inexistente")>0,"Barreira fraca",IF($AN8="Não eficaz","Ação ineficaz",IF(AND($AL8<>"",$AL8<TODAY(),$AK8<>"Concluído",$AK8<>"Cancelado"),"Ação vencida",IF(AND($AN8<>"Eficaz",OR($AK8="Concluído",AND(ISNUMBER($AM8),$AM8<TODAY()))),"Avaliar eficácia",IF(AND($AN8="Eficaz",OR($AS8="",$AT8="")),"Concluir residual",IF($AT8="Não","Tratamento adicional",IF(AND($AT8="Sim",$AS8<>"",IFERROR(MATCH($AS8,Niveis,0),0)>IF(N(IFERROR(INDEX(ApetIdx,MATCH($M8,ListaCatRisco,0)),0))=0,IdxExige-1,INDEX(ApetIdx,MATCH($M8,ListaCatRisco,0)))),"Aceite fora do apetite",IF(AND(COUNTIF(BtId,$A8)=0,OR(IFERROR(MATCH(IF($W8<>"",$W8,$Q8),Niveis,0),0)>=3,AND(OR($S8="Baixa",$S8="Inexistente"),IFERROR(MATCH(IF($W8<>"",$W8,$Q8),Niveis,0),0)>=2))),"Sem BowTie",IF(AND($AY8<>"",$AY8<TODAY()),"Revisão vencida",IF(AND($AL8<>"",N($AL8)-TODAY()<=DiasAlerta,$AK8<>"Concluído",$AK8<>"Cancelado"),"Vence em breve","OK"))))))))))))))))))))))))))) -> KRI em alerta | BA8: Caso de maior evidência causal: MSA adequado, efeito de máquina após controle de mix e DOE (temperatura, velocidade e interação). Ainda sem prova de sustentação em produção. | BB8: R10;R19 | BC8: =IF($V8="","",1+COUNTIF($V$5:$V$154,">"&$V8)+COUNTIFS($V$5:$V$154,$V8,$U$5:$U$154,">"&$U8)+COUNTIFS($V$4:$V7,$V8,$U$4:$U7,$U8)) -> 9 | BD8: Média — semanas | BE8: Moderada | BF8: Preventivo | BG8: 15000 | BH8: 48000 | BI8: =IF(OR($BH8="",$T8=""),"",IFERROR($BH8*INDEX(ProbMedia,$T8),"")) -> 33600 | BJ8: =IF(OR($BG8="",$BI8=""),"",IF(OR(LEFT($M8,3)="SST",LEFT($M8,5)="Legal",LEFT($M8,8)="Ambienta"),"SST/Ambiental/Legal: custo não justifica aceitar (apetite e ALARP)",IF($BG8>$BI8,"Custo maior que a perda esperada: reter/aceitar é defensável, com justificativa","Custo menor ou igual à perda esperada: tratar compensa"))) -> Custo menor ou igual à perda esperada: tratar compensa | BW8: =IF($BU8="","",IFERROR(INDEX(SgaProbValor,MATCH($BU8,SgaProbNivel,0)),"")) | BX8: =IF($BV8="","",IFERROR(INDEX(SgaSevRiValor,MATCH($BV8,SgaSevRiNivel,0)),"")) | BY8: =IF(COUNT($BW8:$BX8)=2,$BW8*$BX8,"") | BZ8: =IF($BY8="","",IF($BY8<=SgaLimRiSig,"SIGNIFICATIVO",IF($BY8<=SgaLimRiTol,"TOLERÁVEL","BAIXO"))) | CA8: =IF($BZ8="","",IF($BZ8="SIGNIFICATIVO","NÃO ACEITÁVEL","ACEITÁVEL")) | CG8: =IF(OR($CE8="",$CF8=""),"",IFERROR(INDEX(SgaProbValor,MATCH($CE8,SgaProbNivel,0))*INDEX(SgaSevRiValor,MATCH($CF8,SgaSevRiNivel,0)),"")) | CH8: =IF($CG8="","",IF($CG8<=SgaLimRiSig,"SIGNIFICATIVO",IF($CG8<=SgaLimRiTol,"TOLERÁVEL","BAIXO")))
A9: R5 | B9: Injeção | C9: Flash crescente na IM-004 em campanhas longas entre trocas de molde (acúmulo de ciclos desde o setup) | D9: Análise de dados / raio-X analítico | E9: Técnico | F9: Operacional | G9: Taxa de rejeição ≤ 2,0% (baseline 2,39%) | H9: Novo | I9: Clientes de cosmética (marcas UE) | J9: Campanhas de até 930 mil unidades sem troca; o desgaste do molde cresce com os ciclos e não há contador nem limite de reação | K9: Máquina | L9: Flash em tampas (≈ 15 mil DPMO, 3,8× as demais), lote rejeitado/refeito (NC-01322/01323) e retrabalho | M9: Qualidade / Cliente | N9: 4 | O9: 4 | P9: =IF(COUNT($N9:$O9)=2,$N9*$O9,"") -> 16 | Q9: =IF($P9="","",INDEX(Niveis,MAX(IFERROR(MATCH($P9,Limites,1),1),IF($O9=5,MinIdx,1)))) -> Crítico | R9: AQL de Flash por lote; troca de molde conforme programação | S9: Baixa | T9: 4 | U9: 3 | V9: =IF(COUNT($T9:$U9)=2,$T9*$U9,"") -> 12 | W9: =IF($V9="","",INDEX(Niveis,MAX(IFERROR(MATCH($V9,Limites,1),1),IF($U9=5,MinIdx,1)))) -> Alto | X9: Média | Y9: =IF(IF($W9<>"",$W9,$Q9)="","",INDEX(AcaoRisco,MATCH(IF($W9<>"",$W9,$Q9),Niveis,0))) -> Mitigar | Z9: Mitigar | AA9: Controle de engenharia | AC9: Criar contador de unidades desde o setup com limite validado e inspeção de condição antes do limite (RC-02) | AD9: Gerente de Produção | AE9: Eng. de Manutenção | AH9: Flash IM-004 ≤ 4 000 DPMO; nenhuma campanha acima do limite técnico validado | AI9: PAC 202603 | AJ9: =IF(OR($AI9="",PlanoUrl=""),"",HYPERLINK(SUBSTITUTE(PlanoUrl,"{COD}",SUBSTITUTE($AI9," ","%20")),"↗")) | AK9: =IF($C9="","",IF($AI9="",$AG9&"",IFERROR(IF(INDEX(PlanosStatus,MATCH($AI9,PlanosCod,0))="",$AG9&"",INDEX(PlanosStatus,MATCH($AI9,PlanosCod,0))),$AG9&""))) -> Aberto | AL9: =IF($C9="","",IF($AI9="",IF($AF9="","",$AF9),IFERROR(IF(INDEX(PlanosPrazo,MATCH($AI9,PlanosCod,0))="",IF($AF9="","",$AF9),INDEX(PlanosPrazo,MATCH($AI9,PlanosCod,0))),IF($AF9="","",$AF9)))) -> 46477 | AM9: 46568 | AP9: 2 | AQ9: 3 | AR9: =IF(COUNT($AP9:$AQ9)=2,$AP9*$AQ9,"") -> 6 | AS9: =IF($AR9="","",INDEX(Niveis,MAX(IFERROR(MATCH($AR9,Limites,1),1),IF($AQ9=5,MinIdx,1)))) -> Baixo | AT9: Sim | AU9: Flash DPMO da IM-004 e unidades desde o último setup (aba KRI) | AV9: 40 | AW9: 46371 | AX9: Comitê da Qualidade | AY9: =IF(OR($AW9="",IF(AND($AN9="Eficaz",$AS9<>""),$AS9,IF($W9<>"",$W9,$Q9))=""),"",EDATE($AW9,INDEX(MesesRev,MATCH(IF(AND($AN9="Eficaz",$AS9<>""),$AS9,IF($W9<>"",$W9,$Q9)),Niveis,0)))) -> 46461 | AZ9: =IF($C9="","",IF($AD9="","Sem dono",IF($W9="","Falta avaliação",IF(AND($AI9<>"",COUNTIF(PlanosCod,$AI9)=0),"Código não encontrado",IF(AND($AI9<>"",IFERROR(INDEX(PlanosIdRef,MATCH($AI9,PlanosCod,0))&"","")<>"",ISERROR(SEARCH(";"&$A9&";",";"&SUBSTITUTE(SUBSTITUTE(IFERROR(INDEX(PlanosIdRef,MATCH($AI9,PlanosCod,0))&"","")," ",""),",",";")&";"))),"Vínculo divergente",IF(AND(ISNUMBER($P9),ISNUMBER($V9),$V9<$P9,OR($S9="",$S9="Inexistente")),"Redução s/ controle",IF(AND(ISNUMBER($AR9),ISNUMBER($V9),$AR9<$V9,NOT(OR($Z9="Prevenir",$Z9="Mitigar",$Z9="Transferir / compartilhar")),$AC9="",$AI9=""),"Residual s/ tratamento",IF(AND(LEFT($AI9,3)="RNC",N(IFERROR(INDEX(PlanosAbertura,MATCH($AI9,PlanosCod,0)),0))>N($AW9)),"Reavaliar após RNC",IF(AND(N($AV9)>=1,ISNUMBER($T9),$T9<=2),"Recalibrar probabilidade",IF(AND($Z9="Aceitar",$BA9=""),"Aceite sem justificativa",IF(AND($Z9="Aceitar",ISNUMBER($AB9),$AB9<TODAY()),"Aceite vencido",IF(AND(OR($Z9="Aceitar",$Z9="Monitorar"),$Y9<>"Monitorar",$Y9<>""),"Aprovar aceite",IF(AND($Z9<>"Aceitar",$Z9<>"Monitorar",$Z9<>"Aprofundar análise",$AC9="",$AI9="",IFERROR(MATCH(IF($W9<>"",$W9,$Q9),Niveis,0),0)>IF(N(IFERROR(INDEX(ApetIdx,MATCH($M9,ListaCatRisco,0)),0))=0,IdxExige-1,INDEX(ApetIdx,MATCH($M9,ListaCatRisco,0)))),"Sem ação",IF($Z9="Aprofundar análise","Aprofundar análise",IF(AND(OR($Z9="Prevenir",$Z9="Mitigar",$Z9="Transferir / compartilhar"),$AH9=""),"Definir critério de eficácia",IF(AND(OR($Z9="Prevenir",$Z9="Mitigar",$Z9="Transferir / compartilhar"),OR($AA9="Controle administrativo",$AA9="EPI"),IFERROR(MATCH(IF($W9<>"",$W9,$Q9),Niveis,0),0)>=3),"Rever hierarquia de controle",IF(COUNTIFS(KriId,$A9,KriSit,"Estourou")+COUNTIFS(KriId,$A9,KriSit,"Atenção")>0,"KRI em alerta",IF(COUNTIFS(BtId,$A9,BtEf,"Baixa")+COUNTIFS(BtId,$A9,BtEf,"Inexistente")>0,"Barreira fraca",IF($AN9="Não eficaz","Ação ineficaz",IF(AND($AL9<>"",$AL9<TODAY(),$AK9<>"Concluído",$AK9<>"Cancelado"),"Ação vencida",IF(AND($AN9<>"Eficaz",OR($AK9="Concluído",AND(ISNUMBER($AM9),$AM9<TODAY()))),"Avaliar eficácia",IF(AND($AN9="Eficaz",OR($AS9="",$AT9="")),"Concluir residual",IF($AT9="Não","Tratamento adicional",IF(AND($AT9="Sim",$AS9<>"",IFERROR(MATCH($AS9,Niveis,0),0)>IF(N(IFERROR(INDEX(ApetIdx,MATCH($M9,ListaCatRisco,0)),0))=0,IdxExige-1,INDEX(ApetIdx,MATCH($M9,ListaCatRisco,0)))),"Aceite fora do apetite",IF(AND(COUNTIF(BtId,$A9)=0,OR(IFERROR(MATCH(IF($W9<>"",$W9,$Q9),Niveis,0),0)>=3,AND(OR($S9="Baixa",$S9="Inexistente"),IFERROR(MATCH(IF($W9<>"",$W9,$Q9),Niveis,0),0)>=2))),"Sem BowTie",IF(AND($AY9<>"",$AY9<TODAY()),"Revisão vencida",IF(AND($AL9<>"",N($AL9)-TODAY()<=DiasAlerta,$AK9<>"Concluído",$AK9<>"Cancelado"),"Vence em breve","OK"))))))))))))))))))))))))))) -> KRI em alerta | BA9: Indicador correto é unidades/ciclos desde o setup, não o mês. Limite técnico não escolhido por conveniência: estimar da curva defeito × ciclos e confirmar em campo. | BB9: R2;R19 | BC9: =IF($V9="","",1+COUNTIF($V$5:$V$154,">"&$V9)+COUNTIFS($V$5:$V$154,$V9,$U$5:$U$154,">"&$U9)+COUNTIFS($V$4:$V8,$V9,$U$4:$U8,$U9)) -> 10 | BD9: Média — semanas | BE9: Moderada | BF9: Detectivo | BG9: 12000 | BH9: 38000 | BI9: =IF(OR($BH9="",$T9=""),"",IFERROR($BH9*INDEX(ProbMedia,$T9),"")) -> 26600 | BJ9: =IF(OR($BG9="",$BI9=""),"",IF(OR(LEFT($M9,3)="SST",LEFT($M9,5)="Legal",LEFT($M9,8)="Ambienta"),"SST/Ambiental/Legal: custo não justifica aceitar (apetite e ALARP)",IF($BG9>$BI9,"Custo maior que a perda esperada: reter/aceitar é defensável, com justificativa","Custo menor ou igual à perda esperada: tratar compensa"))) -> Custo menor ou igual à perda esperada: tratar compensa | BW9: =IF($BU9="","",IFERROR(INDEX(SgaProbValor,MATCH($BU9,SgaProbNivel,0)),"")) | BX9: =IF($BV9="","",IFERROR(INDEX(SgaSevRiValor,MATCH($BV9,SgaSevRiNivel,0)),"")) | BY9: =IF(COUNT($BW9:$BX9)=2,$BW9*$BX9,"") | BZ9: =IF($BY9="","",IF($BY9<=SgaLimRiSig,"SIGNIFICATIVO",IF($BY9<=SgaLimRiTol,"TOLERÁVEL","BAIXO"))) | CA9: =IF($BZ9="","",IF($BZ9="SIGNIFICATIVO","NÃO ACEITÁVEL","ACEITÁVEL")) | CG9: =IF(OR($CE9="",$CF9=""),"",IFERROR(INDEX(SgaProbValor,MATCH($CE9,SgaProbNivel,0))*INDEX(SgaSevRiValor,MATCH($CF9,SgaSevRiNivel,0)),"")) | CH9: =IF($CG9="","",IF($CG9<=SgaLimRiSig,"SIGNIFICATIVO",IF($CG9<=SgaLimRiTol,"TOLERÁVEL","BAIXO")))
A10: R6 | B10: Serigrafia | C10: Pico de falha de adesão de tinta em FR-007-PP-350 (SS-002) ligado a lote de resina PP marginal | D10: RNC / reclamação | E10: Externo | F10: Operacional | G10: Taxa de rejeição ≤ 2,0% (baseline 2,39%) | H10: Mantido | I10: Clientes de cosmética (marcas UE) | J10: Interação entrada × processo: lote de PP do fornecedor SUP-005 na janela marginal + sensibilidade do processo de decoração | K10: Material | L10: Lote rejeitado e refeito (NC-01324), adesão ≈ 1 090 DPMO na janela vs 0 fora dela, reclamações de tinta | M10: Qualidade / Cliente | N10: 3 | O10: 4 | P10: =IF(COUNT($N10:$O10)=2,$N10*$O10,"") -> 12 | Q10: =IF($P10="","",INDEX(Niveis,MAX(IFERROR(MATCH($P10,Limites,1),1),IF($O10=5,MinIdx,1)))) -> Alto | R10: Inspeção de recebimento de PP; AQL de adesão; teste de aderência no setup | S10: Média | T10: 3 | U10: 4 | V10: =IF(COUNT($T10:$U10)=2,$T10*$U10,"") -> 12 | W10: =IF($V10="","",INDEX(Niveis,MAX(IFERROR(MATCH($V10,Limites,1),1),IF($U10=5,MinIdx,1)))) -> Alto | X10: Média | Y10: =IF(IF($W10<>"",$W10,$Q10)="","",INDEX(AcaoRisco,MATCH(IF($W10<>"",$W10,$Q10),Niveis,0))) -> Mitigar | Z10: Mitigar | AA10: Controle de engenharia | AC10: Segregar lotes de risco, confirmar o efeito do lote de PP na adesão e fixar a janela de parâmetros da serigrafia (RC-03) | AD10: Gerente da Qualidade | AE10: Eng. da Qualidade | AH10: Adesão ≤ 300 DPMO por material/lote e nenhum lote de PP liberado sem confirmação | AI10: PAC 202607 | AJ10: =IF(OR($AI10="",PlanoUrl=""),"",HYPERLINK(SUBSTITUTE(PlanoUrl,"{COD}",SUBSTITUTE($AI10," ","%20")),"↗")) | AK10: =IF($C10="","",IF($AI10="",$AG10&"",IFERROR(IF(INDEX(PlanosStatus,MATCH($AI10,PlanosCod,0))="",$AG10&"",INDEX(PlanosStatus,MATCH($AI10,PlanosCod,0))),$AG10&""))) -> Aberto | AL10: =IF($C10="","",IF($AI10="",IF($AF10="","",$AF10),IFERROR(IF(INDEX(PlanosPrazo,MATCH($AI10,PlanosCod,0))="",IF($AF10="","",$AF10),INDEX(PlanosPrazo,MATCH($AI10,PlanosCod,0))),IF($AF10="","",$AF10)))) -> 46461 | AM10: 46538 | AP10: 2 | AQ10: 3 | AR10: =IF(COUNT($AP10:$AQ10)=2,$AP10*$AQ10,"") -> 6 | AS10: =IF($AR10="","",INDEX(Niveis,MAX(IFERROR(MATCH($AR10,Limites,1),1),IF($AQ10=5,MinIdx,1)))) -> Baixo | AT10: Sim | AU10: Adesão DPMO na serigrafia (aba KRI) | AV10: 52 | AW10: 46371 | AX10: Comitê da Qualidade | AY10: =IF(OR($AW10="",IF(AND($AN10="Eficaz",$AS10<>""),$AS10,IF($W10<>"",$W10,$Q10))=""),"",EDATE($AW10,INDEX(MesesRev,MATCH(IF(AND($AN10="Eficaz",$AS10<>""),$AS10,IF($W10<>"",$W10,$Q10)),Niveis,0)))) -> 46461 | AZ10: =IF($C10="","",IF($AD10="","Sem dono",IF($W10="","Falta avaliação",IF(AND($AI10<>"",COUNTIF(PlanosCod,$AI10)=0),"Código não encontrado",IF(AND($AI10<>"",IFERROR(INDEX(PlanosIdRef,MATCH($AI10,PlanosCod,0))&"","")<>"",ISERROR(SEARCH(";"&$A10&";",";"&SUBSTITUTE(SUBSTITUTE(IFERROR(INDEX(PlanosIdRef,MATCH($AI10,PlanosCod,0))&"","")," ",""),",",";")&";"))),"Vínculo divergente",IF(AND(ISNUMBER($P10),ISNUMBER($V10),$V10<$P10,OR($S10="",$S10="Inexistente")),"Redução s/ controle",IF(AND(ISNUMBER($AR10),ISNUMBER($V10),$AR10<$V10,NOT(OR($Z10="Prevenir",$Z10="Mitigar",$Z10="Transferir / compartilhar")),$AC10="",$AI10=""),"Residual s/ tratamento",IF(AND(LEFT($AI10,3)="RNC",N(IFERROR(INDEX(PlanosAbertura,MATCH($AI10,PlanosCod,0)),0))>N($AW10)),"Reavaliar após RNC",IF(AND(N($AV10)>=1,ISNUMBER($T10),$T10<=2),"Recalibrar probabilidade",IF(AND($Z10="Aceitar",$BA10=""),"Aceite sem justificativa",IF(AND($Z10="Aceitar",ISNUMBER($AB10),$AB10<TODAY()),"Aceite vencido",IF(AND(OR($Z10="Aceitar",$Z10="Monitorar"),$Y10<>"Monitorar",$Y10<>""),"Aprovar aceite",IF(AND($Z10<>"Aceitar",$Z10<>"Monitorar",$Z10<>"Aprofundar análise",$AC10="",$AI10="",IFERROR(MATCH(IF($W10<>"",$W10,$Q10),Niveis,0),0)>IF(N(IFERROR(INDEX(ApetIdx,MATCH($M10,ListaCatRisco,0)),0))=0,IdxExige-1,INDEX(ApetIdx,MATCH($M10,ListaCatRisco,0)))),"Sem ação",IF($Z10="Aprofundar análise","Aprofundar análise",IF(AND(OR($Z10="Prevenir",$Z10="Mitigar",$Z10="Transferir / compartilhar"),$AH10=""),"Definir critério de eficácia",IF(AND(OR($Z10="Prevenir",$Z10="Mitigar",$Z10="Transferir / compartilhar"),OR($AA10="Controle administrativo",$AA10="EPI"),IFERROR(MATCH(IF($W10<>"",$W10,$Q10),Niveis,0),0)>=3),"Rever hierarquia de controle",IF(COUNTIFS(KriId,$A10,KriSit,"Estourou")+COUNTIFS(KriId,$A10,KriSit,"Atenção")>0,"KRI em alerta",IF(COUNTIFS(BtId,$A10,BtEf,"Baixa")+COUNTIFS(BtId,$A10,BtEf,"Inexistente")>0,"Barreira fraca",IF($AN10="Não eficaz","Ação ineficaz",IF(AND($AL10<>"",$AL10<TODAY(),$AK10<>"Concluído",$AK10<>"Cancelado"),"Ação vencida",IF(AND($AN10<>"Eficaz",OR($AK10="Concluído",AND(ISNUMBER($AM10),$AM10<TODAY()))),"Avaliar eficácia",IF(AND($AN10="Eficaz",OR($AS10="",$AT10="")),"Concluir residual",IF($AT10="Não","Tratamento adicional",IF(AND($AT10="Sim",$AS10<>"",IFERROR(MATCH($AS10,Niveis,0),0)>IF(N(IFERROR(INDEX(ApetIdx,MATCH($M10,ListaCatRisco,0)),0))=0,IdxExige-1,INDEX(ApetIdx,MATCH($M10,ListaCatRisco,0)))),"Aceite fora do apetite",IF(AND(COUNTIF(BtId,$A10)=0,OR(IFERROR(MATCH(IF($W10<>"",$W10,$Q10),Niveis,0),0)>=3,AND(OR($S10="Baixa",$S10="Inexistente"),IFERROR(MATCH(IF($W10<>"",$W10,$Q10),Niveis,0),0)>=2))),"Sem BowTie",IF(AND($AY10<>"",$AY10<TODAY()),"Revisão vencida",IF(AND($AL10<>"",N($AL10)-TODAY()<=DiasAlerta,$AK10<>"Concluído",$AK10<>"Cancelado"),"Vence em breve","OK"))))))))))))))))))))))))))) -> KRI em alerta | BA10: Janela 2026-02-20 a 2026-03-13. Não concluir que a serigrafia é ruim: a evidência aponta para interação com o lote de resina. Ligado a R13. | BB10: R13;R14 | BC10: =IF($V10="","",1+COUNTIF($V$5:$V$154,">"&$V10)+COUNTIFS($V$5:$V$154,$V10,$U$5:$U$154,">"&$U10)+COUNTIFS($V$4:$V9,$V10,$U$4:$U9,$U10)) -> 3 | BD10: Média — semanas | BE10: Alta — muda rápido | BF10: Detectivo | BG10: 14000 | BH10: 36000 | BI10: =IF(OR($BH10="",$T10=""),"",IFERROR($BH10*INDEX(ProbMedia,$T10),"")) -> 18000 | BJ10: =IF(OR($BG10="",$BI10=""),"",IF(OR(LEFT($M10,3)="SST",LEFT($M10,5)="Legal",LEFT($M10,8)="Ambienta"),"SST/Ambiental/Legal: custo não justifica aceitar (apetite e ALARP)",IF($BG10>$BI10,"Custo maior que a perda esperada: reter/aceitar é defensável, com justificativa","Custo menor ou igual à perda esperada: tratar compensa"))) -> Custo menor ou igual à perda esperada: tratar compensa | BW10: =IF($BU10="","",IFERROR(INDEX(SgaProbValor,MATCH($BU10,SgaProbNivel,0)),"")) | BX10: =IF($BV10="","",IFERROR(INDEX(SgaSevRiValor,MATCH($BV10,SgaSevRiNivel,0)),"")) | BY10: =IF(COUNT($BW10:$BX10)=2,$BW10*$BX10,"") | BZ10: =IF($BY10="","",IF($BY10<=SgaLimRiSig,"SIGNIFICATIVO",IF($BY10<=SgaLimRiTol,"TOLERÁVEL","BAIXO"))) | CA10: =IF($BZ10="","",IF($BZ10="SIGNIFICATIVO","NÃO ACEITÁVEL","ACEITÁVEL")) | CG10: =IF(OR($CE10="",$CF10=""),"",IFERROR(INDEX(SgaProbValor,MATCH($CE10,SgaProbNivel,0))*INDEX(SgaSevRiValor,MATCH($CF10,SgaSevRiNivel,0)),"")) | CH10: =IF($CG10="","",IF($CG10<=SgaLimRiSig,"SIGNIFICATIVO",IF($CG10<=SgaLimRiTol,"TOLERÁVEL","BAIXO")))
A11: R7 | B11: Serigrafia | C11: Degradação de confiabilidade da SS-001 (desgaste de rolete/rasqueta e backlog de manutenção) eleva falhas e tempo de reparo | D11: Análise de dados / raio-X analítico | E11: Técnico | F11: Operacional | G11: OEE ≥ 81,1% e Disponibilidade ≥ 90% (baseline 79,1% / 87,4%) | H11: Alterado | I11: Acionistas / Direção | J11: Desgaste de rolete/rasqueta com backlog de manutenção: MTTR subiu de ≈ 1,7 h para ≈ 3,5 h até jun/2026 | K11: Máquina | L11: Paradas longas, atraso de ordens, lote refeito (NC-01326) e perda de disponibilidade | M11: Produção / Ativos | N11: 4 | O11: 4 | P11: =IF(COUNT($N11:$O11)=2,$N11*$O11,"") -> 16 | Q11: =IF($P11="","",INDEX(Niveis,MAX(IFERROR(MATCH($P11,Limites,1),1),IF($O11=5,MinIdx,1)))) -> Crítico | R11: Overhaul executado em 07/2026 (PAC 202609); PM calendarizada genérica | S11: Média | T11: 3 | U11: 3 | V11: =IF(COUNT($T11:$U11)=2,$T11*$U11,"") -> 9 | W11: =IF($V11="","",INDEX(Niveis,MAX(IFERROR(MATCH($V11,Limites,1),1),IF($U11=5,MinIdx,1)))) -> Médio | X11: Alta | Y11: =IF(IF($W11<>"",$W11,$Q11)="","",INDEX(AcaoRisco,MATCH(IF($W11<>"",$W11,$Q11),Niveis,0))) -> Mitigar | Z11: Mitigar | AA11: Controle de engenharia | AC11: Overhaul concluído; falta PM orientada ao modo de falha e acompanhamento de falhas por 100 h (PAC 202610) | AD11: Gerente de Manutenção | AE11: Eng. de Manutenção | AH11: MTTR SS-001 ≤ 1,5 h por 6 meses após o overhaul | AI11: PAC 202609 | AJ11: =IF(OR($AI11="",PlanoUrl=""),"",HYPERLINK(SUBSTITUTE(PlanoUrl,"{COD}",SUBSTITUTE($AI11," ","%20")),"↗")) | AK11: =IF($C11="","",IF($AI11="",$AG11&"",IFERROR(IF(INDEX(PlanosStatus,MATCH($AI11,PlanosCod,0))="",$AG11&"",INDEX(PlanosStatus,MATCH($AI11,PlanosCod,0))),$AG11&""))) -> Concluído | AL11: =IF($C11="","",IF($AI11="",IF($AF11="","",$AF11),IFERROR(IF(INDEX(PlanosPrazo,MATCH($AI11,PlanosCod,0))="",IF($AF11="","",$AF11),INDEX(PlanosPrazo,MATCH($AI11,PlanosCod,0))),IF($AF11="","",$AF11)))) -> 46223 | AM11: 46371 | AN11: Eficaz | AO11: 46371 | AP11: 2 | AQ11: 3 | AR11: =IF(COUNT($AP11:$AQ11)=2,$AP11*$AQ11,"") -> 6 | AS11: =IF($AR11="","",INDEX(Niveis,MAX(IFERROR(MATCH($AR11,Limites,1),1),IF($AQ11=5,MinIdx,1)))) -> Baixo | AT11: Sim | AU11: MTTR e falhas por 100 h da SS-001 (aba KRI) | AV11: 224 | AW11: 46371 | AX11: Manutenção + Produção | AY11: =IF(OR($AW11="",IF(AND($AN11="Eficaz",$AS11<>""),$AS11,IF($W11<>"",$W11,$Q11))=""),"",EDATE($AW11,INDEX(MesesRev,MATCH(IF(AND($AN11="Eficaz",$AS11<>""),$AS11,IF($W11<>"",$W11,$Q11)),Niveis,0)))) -> 46736 | AZ11: =IF($C11="","",IF($AD11="","Sem dono",IF($W11="","Falta avaliação",IF(AND($AI11<>"",COUNTIF(PlanosCod,$AI11)=0),"Código não encontrado",IF(AND($AI11<>"",IFERROR(INDEX(PlanosIdRef,MATCH($AI11,PlanosCod,0))&"","")<>"",ISERROR(SEARCH(";"&$A11&";",";"&SUBSTITUTE(SUBSTITUTE(IFERROR(INDEX(PlanosIdRef,MATCH($AI11,PlanosCod,0))&"","")," ",""),",",";")&";"))),"Vínculo divergente",IF(AND(ISNUMBER($P11),ISNUMBER($V11),$V11<$P11,OR($S11="",$S11="Inexistente")),"Redução s/ controle",IF(AND(ISNUMBER($AR11),ISNUMBER($V11),$AR11<$V11,NOT(OR($Z11="Prevenir",$Z11="Mitigar",$Z11="Transferir / compartilhar")),$AC11="",$AI11=""),"Residual s/ tratamento",IF(AND(LEFT($AI11,3)="RNC",N(IFERROR(INDEX(PlanosAbertura,MATCH($AI11,PlanosCod,0)),0))>N($AW11)),"Reavaliar após RNC",IF(AND(N($AV11)>=1,ISNUMBER($T11),$T11<=2),"Recalibrar probabilidade",IF(AND($Z11="Aceitar",$BA11=""),"Aceite sem justificativa",IF(AND($Z11="Aceitar",ISNUMBER($AB11),$AB11<TODAY()),"Aceite vencido",IF(AND(OR($Z11="Aceitar",$Z11="Monitorar"),$Y11<>"Monitorar",$Y11<>""),"Aprovar aceite",IF(AND($Z11<>"Aceitar",$Z11<>"Monitorar",$Z11<>"Aprofundar análise",$AC11="",$AI11="",IFERROR(MATCH(IF($W11<>"",$W11,$Q11),Niveis,0),0)>IF(N(IFERROR(INDEX(ApetIdx,MATCH($M11,ListaCatRisco,0)),0))=0,IdxExige-1,INDEX(ApetIdx,MATCH($M11,ListaCatRisco,0)))),"Sem ação",IF($Z11="Aprofundar análise","Aprofundar análise",IF(AND(OR($Z11="Prevenir",$Z11="Mitigar",$Z11="Transferir / compartilhar"),$AH11=""),"Definir critério de eficácia",IF(AND(OR($Z11="Prevenir",$Z11="Mitigar",$Z11="Transferir / compartilhar"),OR($AA11="Controle administrativo",$AA11="EPI"),IFERROR(MATCH(IF($W11<>"",$W11,$Q11),Niveis,0),0)>=3),"Rever hierarquia de controle",IF(COUNTIFS(KriId,$A11,KriSit,"Estourou")+COUNTIFS(KriId,$A11,KriSit,"Atenção")>0,"KRI em alerta",IF(COUNTIFS(BtId,$A11,BtEf,"Baixa")+COUNTIFS(BtId,$A11,BtEf,"Inexistente")>0,"Barreira fraca",IF($AN11="Não eficaz","Ação ineficaz",IF(AND($AL11<>"",$AL11<TODAY(),$AK11<>"Concluído",$AK11<>"Cancelado"),"Ação vencida",IF(AND($AN11<>"Eficaz",OR($AK11="Concluído",AND(ISNUMBER($AM11),$AM11<TODAY()))),"Avaliar eficácia",IF(AND($AN11="Eficaz",OR($AS11="",$AT11="")),"Concluir residual",IF($AT11="Não","Tratamento adicional",IF(AND($AT11="Sim",$AS11<>"",IFERROR(MATCH($AS11,Niveis,0),0)>IF(N(IFERROR(INDEX(ApetIdx,MATCH($M11,ListaCatRisco,0)),0))=0,IdxExige-1,INDEX(ApetIdx,MATCH($M11,ListaCatRisco,0)))),"Aceite fora do apetite",IF(AND(COUNTIF(BtId,$A11)=0,OR(IFERROR(MATCH(IF($W11<>"",$W11,$Q11),Niveis,0),0)>=3,AND(OR($S11="Baixa",$S11="Inexistente"),IFERROR(MATCH(IF($W11<>"",$W11,$Q11),Niveis,0),0)>=2))),"Sem BowTie",IF(AND($AY11<>"",$AY11<TODAY()),"Revisão vencida",IF(AND($AL11<>"",N($AL11)-TODAY()<=DiasAlerta,$AK11<>"Concluído",$AK11<>"Cancelado"),"Vence em breve","OK"))))))))))))))))))))))))))) -> OK | BA11: MTTR unplanned SS-001: 2,82 h (jan–jun/2026) → 1,20 h em média (jul–dez/2026). A média de dez/2026 ainda sobe (1,17 h) — manter monitoramento. A análise de DaysSincePM não provou efeito; isso não prova que PM seja inútil. | BB11: R3 | BC11: =IF($V11="","",1+COUNTIF($V$5:$V$154,">"&$V11)+COUNTIFS($V$5:$V$154,$V11,$U$5:$U$154,">"&$U11)+COUNTIFS($V$4:$V10,$V11,$U$4:$U10,$U11)) -> 22 | BD11: Rápida — dias | BE11: Moderada | BF11: Corretivo | BG11: 35000 | BH11: 100000 | BI11: =IF(OR($BH11="",$T11=""),"",IFERROR($BH11*INDEX(ProbMedia,$T11),"")) -> 50000 | BJ11: =IF(OR($BG11="",$BI11=""),"",IF(OR(LEFT($M11,3)="SST",LEFT($M11,5)="Legal",LEFT($M11,8)="Ambienta"),"SST/Ambiental/Legal: custo não justifica aceitar (apetite e ALARP)",IF($BG11>$BI11,"Custo maior que a perda esperada: reter/aceitar é defensável, com justificativa","Custo menor ou igual à perda esperada: tratar compensa"))) -> Custo menor ou igual à perda esperada: tratar compensa | BK11: 16 | BL11: PCN-SS-01 (redistribuir ordens para SS-002) | BW11: =IF($BU11="","",IFERROR(INDEX(SgaProbValor,MATCH($BU11,SgaProbNivel,0)),"")) | BX11: =IF($BV11="","",IFERROR(INDEX(SgaSevRiValor,MATCH($BV11,SgaSevRiNivel,0)),"")) | BY11: =IF(COUNT($BW11:$BX11)=2,$BW11*$BX11,"") | BZ11: =IF($BY11="","",IF($BY11<=SgaLimRiSig,"SIGNIFICATIVO",IF($BY11<=SgaLimRiTol,"TOLERÁVEL","BAIXO"))) | CA11: =IF($BZ11="","",IF($BZ11="SIGNIFICATIVO","NÃO ACEITÁVEL","ACEITÁVEL")) | CG11: =IF(OR($CE11="",$CF11=""),"",IFERROR(INDEX(SgaProbValor,MATCH($CE11,SgaProbNivel,0))*INDEX(SgaSevRiValor,MATCH($CF11,SgaSevRiNivel,0)),"")) | CH11: =IF($CG11="","",IF($CG11<=SgaLimRiSig,"SIGNIFICATIVO",IF($CG11<=SgaLimRiTol,"TOLERÁVEL","BAIXO")))
A12: R8 | B12: Hot Foil | C12: Transferência incompleta de foil na HF-001 em alta velocidade, com velocidade real de linha não registrada | D12: Análise de dados / raio-X analítico | E12: Técnico | F12: Operacional | G12: Taxa de rejeição ≤ 2,0% (baseline 2,39%) | H12: Novo | I12: Clientes de cosmética (marcas UE) | J12: Velocidade elevada estreita a janela do processo; o parâmetro não é registrado por ordem (só recuperado por ActualCycleTimeSec) | K12: Método | L12: Foil Transfer ≈ 416 DPMO (HF-002 ≈ 330), rejeição 3,63% vs 2,99% da HF-002, lote refeito (NC-01325) | M12: Qualidade / Cliente | N12: 4 | O12: 3 | P12: =IF(COUNT($N12:$O12)=2,$N12*$O12,"") -> 12 | Q12: =IF($P12="","",INDEX(Niveis,MAX(IFERROR(MATCH($P12,Limites,1),1),IF($O12=5,MinIdx,1)))) -> Alto | R12: AQL de Foil Transfer por lote; ajuste manual do operador | S12: Baixa | T12: 4 | U12: 3 | V12: =IF(COUNT($T12:$U12)=2,$T12*$U12,"") -> 12 | W12: =IF($V12="","",INDEX(Niveis,MAX(IFERROR(MATCH($V12,Limites,1),1),IF($U12=5,MinIdx,1)))) -> Alto | X12: Média | Y12: =IF(IF($W12<>"",$W12,$Q12)="","",INDEX(AcaoRisco,MATCH(IF($W12<>"",$W12,$Q12),Niveis,0))) -> Mitigar | Z12: Mitigar | AA12: Controle de engenharia | AC12: Instrumentar a velocidade real por ordem, definir janela operacional validada e alarme de limite (RC-04, RC-13) | AD12: Gerente de Produção | AE12: Eng. de Processo | AH12: Foil Transfer HF-001 ≤ 330 DPMO (igual à HF-002) e 100% das ordens com velocidade registrada | AI12: PAC 202608 | AJ12: =IF(OR($AI12="",PlanoUrl=""),"",HYPERLINK(SUBSTITUTE(PlanoUrl,"{COD}",SUBSTITUTE($AI12," ","%20")),"↗")) | AK12: =IF($C12="","",IF($AI12="",$AG12&"",IFERROR(IF(INDEX(PlanosStatus,MATCH($AI12,PlanosCod,0))="",$AG12&"",INDEX(PlanosStatus,MATCH($AI12,PlanosCod,0))),$AG12&""))) -> Aberto | AL12: =IF($C12="","",IF($AI12="",IF($AF12="","",$AF12),IFERROR(IF(INDEX(PlanosPrazo,MATCH($AI12,PlanosCod,0))="",IF($AF12="","",$AF12),INDEX(PlanosPrazo,MATCH($AI12,PlanosCod,0))),IF($AF12="","",$AF12)))) -> 46477 | AM12: 46568 | AP12: 2 | AQ12: 3 | AR12: =IF(COUNT($AP12:$AQ12)=2,$AP12*$AQ12,"") -> 6 | AS12: =IF($AR12="","",INDEX(Niveis,MAX(IFERROR(MATCH($AR12,Limites,1),1),IF($AQ12=5,MinIdx,1)))) -> Baixo | AT12: Sim | AU12: Foil Transfer DPMO da HF-001 (aba KRI) | AV12: 37 | AW12: 46371 | AX12: Produção + Qualidade | AY12: =IF(OR($AW12="",IF(AND($AN12="Eficaz",$AS12<>""),$AS12,IF($W12<>"",$W12,$Q12))=""),"",EDATE($AW12,INDEX(MesesRev,MATCH(IF(AND($AN12="Eficaz",$AS12<>""),$AS12,IF($W12<>"",$W12,$Q12)),Niveis,0)))) -> 46461 | AZ12: =IF($C12="","",IF($AD12="","Sem dono",IF($W12="","Falta avaliação",IF(AND($AI12<>"",COUNTIF(PlanosCod,$AI12)=0),"Código não encontrado",IF(AND($AI12<>"",IFERROR(INDEX(PlanosIdRef,MATCH($AI12,PlanosCod,0))&"","")<>"",ISERROR(SEARCH(";"&$A12&";",";"&SUBSTITUTE(SUBSTITUTE(IFERROR(INDEX(PlanosIdRef,MATCH($AI12,PlanosCod,0))&"","")," ",""),",",";")&";"))),"Vínculo divergente",IF(AND(ISNUMBER($P12),ISNUMBER($V12),$V12<$P12,OR($S12="",$S12="Inexistente")),"Redução s/ controle",IF(AND(ISNUMBER($AR12),ISNUMBER($V12),$AR12<$V12,NOT(OR($Z12="Prevenir",$Z12="Mitigar",$Z12="Transferir / compartilhar")),$AC12="",$AI12=""),"Residual s/ tratamento",IF(AND(LEFT($AI12,3)="RNC",N(IFERROR(INDEX(PlanosAbertura,MATCH($AI12,PlanosCod,0)),0))>N($AW12)),"Reavaliar após RNC",IF(AND(N($AV12)>=1,ISNUMBER($T12),$T12<=2),"Recalibrar probabilidade",IF(AND($Z12="Aceitar",$BA12=""),"Aceite sem justificativa",IF(AND($Z12="Aceitar",ISNUMBER($AB12),$AB12<TODAY()),"Aceite vencido",IF(AND(OR($Z12="Aceitar",$Z12="Monitorar"),$Y12<>"Monitorar",$Y12<>""),"Aprovar aceite",IF(AND($Z12<>"Aceitar",$Z12<>"Monitorar",$Z12<>"Aprofundar análise",$AC12="",$AI12="",IFERROR(MATCH(IF($W12<>"",$W12,$Q12),Niveis,0),0)>IF(N(IFERROR(INDEX(ApetIdx,MATCH($M12,ListaCatRisco,0)),0))=0,IdxExige-1,INDEX(ApetIdx,MATCH($M12,ListaCatRisco,0)))),"Sem ação",IF($Z12="Aprofundar análise","Aprofundar análise",IF(AND(OR($Z12="Prevenir",$Z12="Mitigar",$Z12="Transferir / compartilhar"),$AH12=""),"Definir critério de eficácia",IF(AND(OR($Z12="Prevenir",$Z12="Mitigar",$Z12="Transferir / compartilhar"),OR($AA12="Controle administrativo",$AA12="EPI"),IFERROR(MATCH(IF($W12<>"",$W12,$Q12),Niveis,0),0)>=3),"Rever hierarquia de controle",IF(COUNTIFS(KriId,$A12,KriSit,"Estourou")+COUNTIFS(KriId,$A12,KriSit,"Atenção")>0,"KRI em alerta",IF(COUNTIFS(BtId,$A12,BtEf,"Baixa")+COUNTIFS(BtId,$A12,BtEf,"Inexistente")>0,"Barreira fraca",IF($AN12="Não eficaz","Ação ineficaz",IF(AND($AL12<>"",$AL12<TODAY(),$AK12<>"Concluído",$AK12<>"Cancelado"),"Ação vencida",IF(AND($AN12<>"Eficaz",OR($AK12="Concluído",AND(ISNUMBER($AM12),$AM12<TODAY()))),"Avaliar eficácia",IF(AND($AN12="Eficaz",OR($AS12="",$AT12="")),"Concluir residual",IF($AT12="Não","Tratamento adicional",IF(AND($AT12="Sim",$AS12<>"",IFERROR(MATCH($AS12,Niveis,0),0)>IF(N(IFERROR(INDEX(ApetIdx,MATCH($M12,ListaCatRisco,0)),0))=0,IdxExige-1,INDEX(ApetIdx,MATCH($M12,ListaCatRisco,0)))),"Aceite fora do apetite",IF(AND(COUNTIF(BtId,$A12)=0,OR(IFERROR(MATCH(IF($W12<>"",$W12,$Q12),Niveis,0),0)>=3,AND(OR($S12="Baixa",$S12="Inexistente"),IFERROR(MATCH(IF($W12<>"",$W12,$Q12),Niveis,0),0)>=2))),"Sem BowTie",IF(AND($AY12<>"",$AY12<TODAY()),"Revisão vencida",IF(AND($AL12<>"",N($AL12)-TODAY()<=DiasAlerta,$AK12<>"Concluído",$AK12<>"Cancelado"),"Vence em breve","OK"))))))))))))))))))))))))))) -> KRI em alerta | BA12: Evidência experimental/sintética: confirmar o parâmetro em linha antes de padronizar. | BB12: R19 | BC12: =IF($V12="","",1+COUNTIF($V$5:$V$154,">"&$V12)+COUNTIFS($V$5:$V$154,$V12,$U$5:$U$154,">"&$U12)+COUNTIFS($V$4:$V11,$V12,$U$4:$U11,$U12)) -> 11 | BD12: Média — semanas | BE12: Moderada | BF12: Detectivo | BG12: 16000 | BH12: 30000 | BI12: =IF(OR($BH12="",$T12=""),"",IFERROR($BH12*INDEX(ProbMedia,$T12),"")) -> 21000 | BJ12: =IF(OR($BG12="",$BI12=""),"",IF(OR(LEFT($M12,3)="SST",LEFT($M12,5)="Legal",LEFT($M12,8)="Ambienta"),"SST/Ambiental/Legal: custo não justifica aceitar (apetite e ALARP)",IF($BG12>$BI12,"Custo maior que a perda esperada: reter/aceitar é defensável, com justificativa","Custo menor ou igual à perda esperada: tratar compensa"))) -> Custo menor ou igual à perda esperada: tratar compensa | BW12: =IF($BU12="","",IFERROR(INDEX(SgaProbValor,MATCH($BU12,SgaProbNivel,0)),"")) | BX12: =IF($BV12="","",IFERROR(INDEX(SgaSevRiValor,MATCH($BV12,SgaSevRiNivel,0)),"")) | BY12: =IF(COUNT($BW12:$BX12)=2,$BW12*$BX12,"") | BZ12: =IF($BY12="","",IF($BY12<=SgaLimRiSig,"SIGNIFICATIVO",IF($BY12<=SgaLimRiTol,"TOLERÁVEL","BAIXO"))) | CA12: =IF($BZ12="","",IF($BZ12="SIGNIFICATIVO","NÃO ACEITÁVEL","ACEITÁVEL")) | CG12: =IF(OR($CE12="",$CF12=""),"",IFERROR(INDEX(SgaProbValor,MATCH($CE12,SgaProbNivel,0))*INDEX(SgaSevRiValor,MATCH($CF12,SgaSevRiNivel,0)),"")) | CH12: =IF($CG12="","",IF($CG12<=SgaLimRiSig,"SIGNIFICATIVO",IF($CG12<=SgaLimRiTol,"TOLERÁVEL","BAIXO")))
A13: R9 | B13: Produção (transversal) | C13: Prêmio de defeito no turno 2 (fadiga/handover) eleva a rejeição em todos os processos | D13: Análise de dados / raio-X analítico | E13: Organizacional | F13: Gerencial (processo) | G13: Taxa de rejeição ≤ 2,0% (baseline 2,39%) | H13: Novo | I13: Colaboradores | J13: Fadiga e passagem de turno (handover); carga e supervisão diferentes no turno 14h–22h | K13: Mão de obra | L13: Rejeição de 2,82% no turno 2 vs 2,09% no turno 1 (+35%), mais refugo e retrabalho | M13: Qualidade / Cliente | N13: 4 | O13: 3 | P13: =IF(COUNT($N13:$O13)=2,$N13*$O13,"") -> 12 | Q13: =IF($P13="","",INDEX(Niveis,MAX(IFERROR(MATCH($P13,Limites,1),1),IF($O13=5,MinIdx,1)))) -> Alto | R13: Supervisão de turno; passagem de turno informal | S13: Baixa | T13: 4 | U13: 2 | V13: =IF(COUNT($T13:$U13)=2,$T13*$U13,"") -> 8 | W13: =IF($V13="","",INDEX(Niveis,MAX(IFERROR(MATCH($V13,Limites,1),1),IF($U13=5,MinIdx,1)))) -> Médio | X13: Média | Y13: =IF(IF($W13<>"",$W13,$Q13)="","",INDEX(AcaoRisco,MATCH(IF($W13<>"",$W13,$Q13),Niveis,0))) -> Mitigar | Z13: Mitigar | AA13: Controle administrativo | AC13: Estudar handover, carga, pausas, staffing e parâmetros do turno 2; não culpar operador sem estudo (RC-08) | AD13: Gerente de Produção | AE13: Supervisor de Turno | AH13: Diferença de rejeição turno 2 vs turno 1 ≤ 0,3 p.p. ajustada por produto/máquina | AI13: PAC 202612 | AJ13: =IF(OR($AI13="",PlanoUrl=""),"",HYPERLINK(SUBSTITUTE(PlanoUrl,"{COD}",SUBSTITUTE($AI13," ","%20")),"↗")) | AK13: =IF($C13="","",IF($AI13="",$AG13&"",IFERROR(IF(INDEX(PlanosStatus,MATCH($AI13,PlanosCod,0))="",$AG13&"",INDEX(PlanosStatus,MATCH($AI13,PlanosCod,0))),$AG13&""))) -> Aberto | AL13: =IF($C13="","",IF($AI13="",IF($AF13="","",$AF13),IFERROR(IF(INDEX(PlanosPrazo,MATCH($AI13,PlanosCod,0))="",IF($AF13="","",$AF13),INDEX(PlanosPrazo,MATCH($AI13,PlanosCod,0))),IF($AF13="","",$AF13)))) -> 46507 | AM13: 46568 | AP13: 3 | AQ13: 2 | AR13: =IF(COUNT($AP13:$AQ13)=2,$AP13*$AQ13,"") -> 6 | AS13: =IF($AR13="","",INDEX(Niveis,MAX(IFERROR(MATCH($AR13,Limites,1),1),IF($AQ13=5,MinIdx,1)))) -> Baixo | AT13: Sim | AU13: Rejeição do turno 2 (aba KRI) | AV13: 12 | AW13: 46371 | AX13: Produção | AY13: =IF(OR($AW13="",IF(AND($AN13="Eficaz",$AS13<>""),$AS13,IF($W13<>"",$W13,$Q13))=""),"",EDATE($AW13,INDEX(MesesRev,MATCH(IF(AND($AN13="Eficaz",$AS13<>""),$AS13,IF($W13<>"",$W13,$Q13)),Niveis,0)))) -> 46553 | AZ13: =IF($C13="","",IF($AD13="","Sem dono",IF($W13="","Falta avaliação",IF(AND($AI13<>"",COUNTIF(PlanosCod,$AI13)=0),"Código não encontrado",IF(AND($AI13<>"",IFERROR(INDEX(PlanosIdRef,MATCH($AI13,PlanosCod,0))&"","")<>"",ISERROR(SEARCH(";"&$A13&";",";"&SUBSTITUTE(SUBSTITUTE(IFERROR(INDEX(PlanosIdRef,MATCH($AI13,PlanosCod,0))&"","")," ",""),",",";")&";"))),"Vínculo divergente",IF(AND(ISNUMBER($P13),ISNUMBER($V13),$V13<$P13,OR($S13="",$S13="Inexistente")),"Redução s/ controle",IF(AND(ISNUMBER($AR13),ISNUMBER($V13),$AR13<$V13,NOT(OR($Z13="Prevenir",$Z13="Mitigar",$Z13="Transferir / compartilhar")),$AC13="",$AI13=""),"Residual s/ tratamento",IF(AND(LEFT($AI13,3)="RNC",N(IFERROR(INDEX(PlanosAbertura,MATCH($AI13,PlanosCod,0)),0))>N($AW13)),"Reavaliar após RNC",IF(AND(N($AV13)>=1,ISNUMBER($T13),$T13<=2),"Recalibrar probabilidade",IF(AND($Z13="Aceitar",$BA13=""),"Aceite sem justificativa",IF(AND($Z13="Aceitar",ISNUMBER($AB13),$AB13<TODAY()),"Aceite vencido",IF(AND(OR($Z13="Aceitar",$Z13="Monitorar"),$Y13<>"Monitorar",$Y13<>""),"Aprovar aceite",IF(AND($Z13<>"Aceitar",$Z13<>"Monitorar",$Z13<>"Aprofundar análise",$AC13="",$AI13="",IFERROR(MATCH(IF($W13<>"",$W13,$Q13),Niveis,0),0)>IF(N(IFERROR(INDEX(ApetIdx,MATCH($M13,ListaCatRisco,0)),0))=0,IdxExige-1,INDEX(ApetIdx,MATCH($M13,ListaCatRisco,0)))),"Sem ação",IF($Z13="Aprofundar análise","Aprofundar análise",IF(AND(OR($Z13="Prevenir",$Z13="Mitigar",$Z13="Transferir / compartilhar"),$AH13=""),"Definir critério de eficácia",IF(AND(OR($Z13="Prevenir",$Z13="Mitigar",$Z13="Transferir / compartilhar"),OR($AA13="Controle administrativo",$AA13="EPI"),IFERROR(MATCH(IF($W13<>"",$W13,$Q13),Niveis,0),0)>=3),"Rever hierarquia de controle",IF(COUNTIFS(KriId,$A13,KriSit,"Estourou")+COUNTIFS(KriId,$A13,KriSit,"Atenção")>0,"KRI em alerta",IF(COUNTIFS(BtId,$A13,BtEf,"Baixa")+COUNTIFS(BtId,$A13,BtEf,"Inexistente")>0,"Barreira fraca",IF($AN13="Não eficaz","Ação ineficaz",IF(AND($AL13<>"",$AL13<TODAY(),$AK13<>"Concluído",$AK13<>"Cancelado"),"Ação vencida",IF(AND($AN13<>"Eficaz",OR($AK13="Concluído",AND(ISNUMBER($AM13),$AM13<TODAY()))),"Avaliar eficácia",IF(AND($AN13="Eficaz",OR($AS13="",$AT13="")),"Concluir residual",IF($AT13="Não","Tratamento adicional",IF(AND($AT13="Sim",$AS13<>"",IFERROR(MATCH($AS13,Niveis,0),0)>IF(N(IFERROR(INDEX(ApetIdx,MATCH($M13,ListaCatRisco,0)),0))=0,IdxExige-1,INDEX(ApetIdx,MATCH($M13,ListaCatRisco,0)))),"Aceite fora do apetite",IF(AND(COUNTIF(BtId,$A13)=0,OR(IFERROR(MATCH(IF($W13<>"",$W13,$Q13),Niveis,0),0)>=3,AND(OR($S13="Baixa",$S13="Inexistente"),IFERROR(MATCH(IF($W13<>"",$W13,$Q13),Niveis,0),0)>=2))),"Sem BowTie",IF(AND($AY13<>"",$AY13<TODAY()),"Revisão vencida",IF(AND($AL13<>"",N($AL13)-TODAY()<=DiasAlerta,$AK13<>"Concluído",$AK13<>"Cancelado"),"Vence em breve","OK"))))))))))))))))))))))))))) -> KRI em alerta | BA13: Associação: mecanismo operacional requer validação. Ajustar por produto e máquina antes de concluir. | BB13: R10;R23 | BC13: =IF($V13="","",1+COUNTIF($V$5:$V$154,">"&$V13)+COUNTIFS($V$5:$V$154,$V13,$U$5:$U$154,">"&$U13)+COUNTIFS($V$4:$V12,$V13,$U$4:$U12,$U13)) -> 35 | BD13: Lenta — meses | BE13: Estável | BF13: Preventivo | BG13: 8000 | BH13: 28000 | BI13: =IF(OR($BH13="",$T13=""),"",IFERROR($BH13*INDEX(ProbMedia,$T13),"")) -> 19600 | BJ13: =IF(OR($BG13="",$BI13=""),"",IF(OR(LEFT($M13,3)="SST",LEFT($M13,5)="Legal",LEFT($M13,8)="Ambienta"),"SST/Ambiental/Legal: custo não justifica aceitar (apetite e ALARP)",IF($BG13>$BI13,"Custo maior que a perda esperada: reter/aceitar é defensável, com justificativa","Custo menor ou igual à perda esperada: tratar compensa"))) -> Custo menor ou igual à perda esperada: tratar compensa | BW13: =IF($BU13="","",IFERROR(INDEX(SgaProbValor,MATCH($BU13,SgaProbNivel,0)),"")) | BX13: =IF($BV13="","",IFERROR(INDEX(SgaSevRiValor,MATCH($BV13,SgaSevRiNivel,0)),"")) | BY13: =IF(COUNT($BW13:$BX13)=2,$BW13*$BX13,"") | BZ13: =IF($BY13="","",IF($BY13<=SgaLimRiSig,"SIGNIFICATIVO",IF($BY13<=SgaLimRiTol,"TOLERÁVEL","BAIXO"))) | CA13: =IF($BZ13="","",IF($BZ13="SIGNIFICATIVO","NÃO ACEITÁVEL","ACEITÁVEL")) | CG13: =IF(OR($CE13="",$CF13=""),"",IFERROR(INDEX(SgaProbValor,MATCH($CE13,SgaProbNivel,0))*INDEX(SgaSevRiValor,MATCH($CF13,SgaSevRiNivel,0)),"")) | CH13: =IF($CG13="","",IF($CG13<=SgaLimRiSig,"SIGNIFICATIVO",IF($CG13<=SgaLimRiTol,"TOLERÁVEL","BAIXO")))
A14: R10 | B14: Injeção | C14: Alta variabilidade de execução do operador OP-INJ-003 (dispersão 2× os pares, sem viés de média) | D14: Análise de dados / raio-X analítico | E14: Organizacional | F14: Operacional | G14: Cpk ≥ 1,33 nas características críticas | H14: Novo | I14: Colaboradores | J14: Método de execução/medição inconsistente e possível ergonomia; RangeR ≈ 5,0 vs ≈ 2,5 dos pares com média semelhante | K14: Método | L14: Maior variabilidade intrassubgrupo e menor Cpk; não é viés do operador | M14: Qualidade / Cliente | N14: 3 | O14: 3 | P14: =IF(COUNT($N14:$O14)=2,$N14*$O14,"") -> 9 | Q14: =IF($P14="","",INDEX(Niveis,MAX(IFERROR(MATCH($P14,Limites,1),1),IF($O14=5,MinIdx,1)))) -> Médio | R14: Cartas X-barra/R; standard work escrito | S14: Média | T14: 3 | U14: 2 | V14: =IF(COUNT($T14:$U14)=2,$T14*$U14,"") -> 6 | W14: =IF($V14="","",INDEX(Niveis,MAX(IFERROR(MATCH($V14,Limites,1),1),IF($U14=5,MinIdx,1)))) -> Baixo | X14: Média | Y14: =IF(IF($W14<>"",$W14,$Q14)="","",INDEX(AcaoRisco,MATCH(IF($W14<>"",$W14,$Q14),Niveis,0))) -> Monitorar | Z14: Mitigar | AA14: Controle administrativo | AC14: Observar o standard work, revisar método/ergonomia e treinar sem culpabilizar; repetir Gage R&R por característica (RC-10) | AD14: Gerente de Produção | AE14: Supervisor de Turno | AH14: RangeR do peso ≤ 3,0 sem deslocar a média do processo | AI14: PAC 202613 | AJ14: =IF(OR($AI14="",PlanoUrl=""),"",HYPERLINK(SUBSTITUTE(PlanoUrl,"{COD}",SUBSTITUTE($AI14," ","%20")),"↗")) | AK14: =IF($C14="","",IF($AI14="",$AG14&"",IFERROR(IF(INDEX(PlanosStatus,MATCH($AI14,PlanosCod,0))="",$AG14&"",INDEX(PlanosStatus,MATCH($AI14,PlanosCod,0))),$AG14&""))) -> Aberto | AL14: =IF($C14="","",IF($AI14="",IF($AF14="","",$AF14),IFERROR(IF(INDEX(PlanosPrazo,MATCH($AI14,PlanosCod,0))="",IF($AF14="","",$AF14),INDEX(PlanosPrazo,MATCH($AI14,PlanosCod,0))),IF($AF14="","",$AF14)))) -> 46477 | AM14: 46538 | AP14: 2 | AQ14: 2 | AR14: =IF(COUNT($AP14:$AQ14)=2,$AP14*$AQ14,"") -> 4 | AS14: =IF($AR14="","",INDEX(Niveis,MAX(IFERROR(MATCH($AR14,Limites,1),1),IF($AQ14=5,MinIdx,1)))) -> Baixo | AT14: Sim | AW14: 46371 | AX14: Produção + Qualidade | AY14: =IF(OR($AW14="",IF(AND($AN14="Eficaz",$AS14<>""),$AS14,IF($W14<>"",$W14,$Q14))=""),"",EDATE($AW14,INDEX(MesesRev,MATCH(IF(AND($AN14="Eficaz",$AS14<>""),$AS14,IF($W14<>"",$W14,$Q14)),Niveis,0)))) -> 46736 | AZ14: =IF($C14="","",IF($AD14="","Sem dono",IF($W14="","Falta avaliação",IF(AND($AI14<>"",COUNTIF(PlanosCod,$AI14)=0),"Código não encontrado",IF(AND($AI14<>"",IFERROR(INDEX(PlanosIdRef,MATCH($AI14,PlanosCod,0))&"","")<>"",ISERROR(SEARCH(";"&$A14&";",";"&SUBSTITUTE(SUBSTITUTE(IFERROR(INDEX(PlanosIdRef,MATCH($AI14,PlanosCod,0))&"","")," ",""),",",";")&";"))),"Vínculo divergente",IF(AND(ISNUMBER($P14),ISNUMBER($V14),$V14<$P14,OR($S14="",$S14="Inexistente")),"Redução s/ controle",IF(AND(ISNUMBER($AR14),ISNUMBER($V14),$AR14<$V14,NOT(OR($Z14="Prevenir",$Z14="Mitigar",$Z14="Transferir / compartilhar")),$AC14="",$AI14=""),"Residual s/ tratamento",IF(AND(LEFT($AI14,3)="RNC",N(IFERROR(INDEX(PlanosAbertura,MATCH($AI14,PlanosCod,0)),0))>N($AW14)),"Reavaliar após RNC",IF(AND(N($AV14)>=1,ISNUMBER($T14),$T14<=2),"Recalibrar probabilidade",IF(AND($Z14="Aceitar",$BA14=""),"Aceite sem justificativa",IF(AND($Z14="Aceitar",ISNUMBER($AB14),$AB14<TODAY()),"Aceite vencido",IF(AND(OR($Z14="Aceitar",$Z14="Monitorar"),$Y14<>"Monitorar",$Y14<>""),"Aprovar aceite",IF(AND($Z14<>"Aceitar",$Z14<>"Monitorar",$Z14<>"Aprofundar análise",$AC14="",$AI14="",IFERROR(MATCH(IF($W14<>"",$W14,$Q14),Niveis,0),0)>IF(N(IFERROR(INDEX(ApetIdx,MATCH($M14,ListaCatRisco,0)),0))=0,IdxExige-1,INDEX(ApetIdx,MATCH($M14,ListaCatRisco,0)))),"Sem ação",IF($Z14="Aprofundar análise","Aprofundar análise",IF(AND(OR($Z14="Prevenir",$Z14="Mitigar",$Z14="Transferir / compartilhar"),$AH14=""),"Definir critério de eficácia",IF(AND(OR($Z14="Prevenir",$Z14="Mitigar",$Z14="Transferir / compartilhar"),OR($AA14="Controle administrativo",$AA14="EPI"),IFERROR(MATCH(IF($W14<>"",$W14,$Q14),Niveis,0),0)>=3),"Rever hierarquia de controle",IF(COUNTIFS(KriId,$A14,KriSit,"Estourou")+COUNTIFS(KriId,$A14,KriSit,"Atenção")>0,"KRI em alerta",IF(COUNTIFS(BtId,$A14,BtEf,"Baixa")+COUNTIFS(BtId,$A14,BtEf,"Inexistente")>0,"Barreira fraca",IF($AN14="Não eficaz","Ação ineficaz",IF(AND($AL14<>"",$AL14<TODAY(),$AK14<>"Concluído",$AK14<>"Cancelado"),"Ação vencida",IF(AND($AN14<>"Eficaz",OR($AK14="Concluído",AND(ISNUMBER($AM14),$AM14<TODAY()))),"Avaliar eficácia",IF(AND($AN14="Eficaz",OR($AS14="",$AT14="")),"Concluir residual",IF($AT14="Não","Tratamento adicional",IF(AND($AT14="Sim",$AS14<>"",IFERROR(MATCH($AS14,Niveis,0),0)>IF(N(IFERROR(INDEX(ApetIdx,MATCH($M14,ListaCatRisco,0)),0))=0,IdxExige-1,INDEX(ApetIdx,MATCH($M14,ListaCatRisco,0)))),"Aceite fora do apetite",IF(AND(COUNTIF(BtId,$A14)=0,OR(IFERROR(MATCH(IF($W14<>"",$W14,$Q14),Niveis,0),0)>=3,AND(OR($S14="Baixa",$S14="Inexistente"),IFERROR(MATCH(IF($W14<>"",$W14,$Q14),Niveis,0),0)>=2))),"Sem BowTie",IF(AND($AY14<>"",$AY14<TODAY()),"Revisão vencida",IF(AND($AL14<>"",N($AL14)-TODAY()<=DiasAlerta,$AK14<>"Concluído",$AK14<>"Cancelado"),"Vence em breve","OK"))))))))))))))))))))))))))) -> OK | BA14: A carta X-barra sozinha não detecta este sinal: usar carta R. Tratar como variação de método, não como defeito do operador. | BB14: R4;R9 | BC14: =IF($V14="","",1+COUNTIF($V$5:$V$154,">"&$V14)+COUNTIFS($V$5:$V$154,$V14,$U$5:$U$154,">"&$U14)+COUNTIFS($V$4:$V13,$V14,$U$4:$U13,$U14)) -> 38 | BD14: Lenta — meses | BE14: Estável | BF14: Preventivo | BG14: 4000 | BH14: 12000 | BI14: =IF(OR($BH14="",$T14=""),"",IFERROR($BH14*INDEX(ProbMedia,$T14),"")) -> 6000 | BJ14: =IF(OR($BG14="",$BI14=""),"",IF(OR(LEFT($M14,3)="SST",LEFT($M14,5)="Legal",LEFT($M14,8)="Ambienta"),"SST/Ambiental/Legal: custo não justifica aceitar (apetite e ALARP)",IF($BG14>$BI14,"Custo maior que a perda esperada: reter/aceitar é defensável, com justificativa","Custo menor ou igual à perda esperada: tratar compensa"))) -> Custo menor ou igual à perda esperada: tratar compensa | BW14: =IF($BU14="","",IFERROR(INDEX(SgaProbValor,MATCH($BU14,SgaProbNivel,0)),"")) | BX14: =IF($BV14="","",IFERROR(INDEX(SgaSevRiValor,MATCH($BV14,SgaSevRiNivel,0)),"")) | BY14: =IF(COUNT($BW14:$BX14)=2,$BW14*$BX14,"") | BZ14: =IF($BY14="","",IF($BY14<=SgaLimRiSig,"SIGNIFICATIVO",IF($BY14<=SgaLimRiTol,"TOLERÁVEL","BAIXO"))) | CA14: =IF($BZ14="","",IF($BZ14="SIGNIFICATIVO","NÃO ACEITÁVEL","ACEITÁVEL")) | CG14: =IF(OR($CE14="",$CF14=""),"",IFERROR(INDEX(SgaProbValor,MATCH($CE14,SgaProbNivel,0))*INDEX(SgaSevRiValor,MATCH($CF14,SgaSevRiNivel,0)),"")) | CH14: =IF($CG14="","",IF($CG14<=SgaLimRiSig,"SIGNIFICATIVO",IF($CG14<=SgaLimRiTol,"TOLERÁVEL","BAIXO")))
A15: R11 | B15: Sopro (ISBM) | C15: Contaminação (black specks) em frascos soprados ligada a lote de masterbatch/cor | D15: RNC / reclamação | E15: Externo | F15: Operacional | G15: Reclamações ≤ 3 por milhão de unidades (baseline 4,76) | H15: Mantido | I15: Clientes de cosmética (marcas UE) | J15: Lote de masterbatch com contaminação e purga insuficiente na troca de cor | K15: Material | L15: Pico de black specks (≈ 1,5× a base) em 02–09/02/2026, lote refeito (NC-01320, CAPA-4805) e reclamações de corpo estranho | M15: Qualidade / Cliente | N15: 3 | O15: 4 | P15: =IF(COUNT($N15:$O15)=2,$N15*$O15,"") -> 12 | Q15: =IF($P15="","",INDEX(Niveis,MAX(IFERROR(MATCH($P15,Limites,1),1),IF($O15=5,MinIdx,1)))) -> Alto | R15: Inspeção visual de black specks; controle de lote de masterbatch; CAPA-4805 concluída e eficaz | S15: Média | T15: 3 | U15: 3 | V15: =IF(COUNT($T15:$U15)=2,$T15*$U15,"") -> 9 | W15: =IF($V15="","",INDEX(Niveis,MAX(IFERROR(MATCH($V15,Limites,1),1),IF($U15=5,MinIdx,1)))) -> Médio | X15: Média | Y15: =IF(IF($W15<>"",$W15,$Q15)="","",INDEX(AcaoRisco,MATCH(IF($W15<>"",$W15,$Q15),Niveis,0))) -> Mitigar | Z15: Mitigar | AA15: Controle de engenharia | AC15: Reforçar controle de lote de masterbatch (fornecedor SUP-008) e padrão de purga/limpeza na troca de cor | AD15: Gerente da Qualidade | AE15: Eng. da Qualidade | AH15: Zero lotes rejeitados por black specks por 6 meses | AI15: PAC 202617 | AJ15: =IF(OR($AI15="",PlanoUrl=""),"",HYPERLINK(SUBSTITUTE(PlanoUrl,"{COD}",SUBSTITUTE($AI15," ","%20")),"↗")) | AK15: =IF($C15="","",IF($AI15="",$AG15&"",IFERROR(IF(INDEX(PlanosStatus,MATCH($AI15,PlanosCod,0))="",$AG15&"",INDEX(PlanosStatus,MATCH($AI15,PlanosCod,0))),$AG15&""))) -> Aberto | AL15: =IF($C15="","",IF($AI15="",IF($AF15="","",$AF15),IFERROR(IF(INDEX(PlanosPrazo,MATCH($AI15,PlanosCod,0))="",IF($AF15="","",$AF15),INDEX(PlanosPrazo,MATCH($AI15,PlanosCod,0))),IF($AF15="","",$AF15)))) -> 46461 | AM15: 46568 | AP15: 2 | AQ15: 3 | AR15: =IF(COUNT($AP15:$AQ15)=2,$AP15*$AQ15,"") -> 6 | AS15: =IF($AR15="","",INDEX(Niveis,MAX(IFERROR(MATCH($AR15,Limites,1),1),IF($AQ15=5,MinIdx,1)))) -> Baixo | AT15: Sim | AV15: 1 | AW15: 46371 | AX15: Comitê da Qualidade | AY15: =IF(OR($AW15="",IF(AND($AN15="Eficaz",$AS15<>""),$AS15,IF($W15<>"",$W15,$Q15))=""),"",EDATE($AW15,INDEX(MesesRev,MATCH(IF(AND($AN15="Eficaz",$AS15<>""),$AS15,IF($W15<>"",$W15,$Q15)),Niveis,0)))) -> 46553 | AZ15: =IF($C15="","",IF($AD15="","Sem dono",IF($W15="","Falta avaliação",IF(AND($AI15<>"",COUNTIF(PlanosCod,$AI15)=0),"Código não encontrado",IF(AND($AI15<>"",IFERROR(INDEX(PlanosIdRef,MATCH($AI15,PlanosCod,0))&"","")<>"",ISERROR(SEARCH(";"&$A15&";",";"&SUBSTITUTE(SUBSTITUTE(IFERROR(INDEX(PlanosIdRef,MATCH($AI15,PlanosCod,0))&"","")," ",""),",",";")&";"))),"Vínculo divergente",IF(AND(ISNUMBER($P15),ISNUMBER($V15),$V15<$P15,OR($S15="",$S15="Inexistente")),"Redução s/ controle",IF(AND(ISNUMBER($AR15),ISNUMBER($V15),$AR15<$V15,NOT(OR($Z15="Prevenir",$Z15="Mitigar",$Z15="Transferir / compartilhar")),$AC15="",$AI15=""),"Residual s/ tratamento",IF(AND(LEFT($AI15,3)="RNC",N(IFERROR(INDEX(PlanosAbertura,MATCH($AI15,PlanosCod,0)),0))>N($AW15)),"Reavaliar após RNC",IF(AND(N($AV15)>=1,ISNUMBER($T15),$T15<=2),"Recalibrar probabilidade",IF(AND($Z15="Aceitar",$BA15=""),"Aceite sem justificativa",IF(AND($Z15="Aceitar",ISNUMBER($AB15),$AB15<TODAY()),"Aceite vencido",IF(AND(OR($Z15="Aceitar",$Z15="Monitorar"),$Y15<>"Monitorar",$Y15<>""),"Aprovar aceite",IF(AND($Z15<>"Aceitar",$Z15<>"Monitorar",$Z15<>"Aprofundar análise",$AC15="",$AI15="",IFERROR(MATCH(IF($W15<>"",$W15,$Q15),Niveis,0),0)>IF(N(IFERROR(INDEX(ApetIdx,MATCH($M15,ListaCatRisco,0)),0))=0,IdxExige-1,INDEX(ApetIdx,MATCH($M15,ListaCatRisco,0)))),"Sem ação",IF($Z15="Aprofundar análise","Aprofundar análise",IF(AND(OR($Z15="Prevenir",$Z15="Mitigar",$Z15="Transferir / compartilhar"),$AH15=""),"Definir critério de eficácia",IF(AND(OR($Z15="Prevenir",$Z15="Mitigar",$Z15="Transferir / compartilhar"),OR($AA15="Controle administrativo",$AA15="EPI"),IFERROR(MATCH(IF($W15<>"",$W15,$Q15),Niveis,0),0)>=3),"Rever hierarquia de controle",IF(COUNTIFS(KriId,$A15,KriSit,"Estourou")+COUNTIFS(KriId,$A15,KriSit,"Atenção")>0,"KRI em alerta",IF(COUNTIFS(BtId,$A15,BtEf,"Baixa")+COUNTIFS(BtId,$A15,BtEf,"Inexistente")>0,"Barreira fraca",IF($AN15="Não eficaz","Ação ineficaz",IF(AND($AL15<>"",$AL15<TODAY(),$AK15<>"Concluído",$AK15<>"Cancelado"),"Ação vencida",IF(AND($AN15<>"Eficaz",OR($AK15="Concluído",AND(ISNUMBER($AM15),$AM15<TODAY()))),"Avaliar eficácia",IF(AND($AN15="Eficaz",OR($AS15="",$AT15="")),"Concluir residual",IF($AT15="Não","Tratamento adicional",IF(AND($AT15="Sim",$AS15<>"",IFERROR(MATCH($AS15,Niveis,0),0)>IF(N(IFERROR(INDEX(ApetIdx,MATCH($M15,ListaCatRisco,0)),0))=0,IdxExige-1,INDEX(ApetIdx,MATCH($M15,ListaCatRisco,0)))),"Aceite fora do apetite",IF(AND(COUNTIF(BtId,$A15)=0,OR(IFERROR(MATCH(IF($W15<>"",$W15,$Q15),Niveis,0),0)>=3,AND(OR($S15="Baixa",$S15="Inexistente"),IFERROR(MATCH(IF($W15<>"",$W15,$Q15),Niveis,0),0)>=2))),"Sem BowTie",IF(AND($AY15<>"",$AY15<TODAY()),"Revisão vencida",IF(AND($AL15<>"",N($AL15)-TODAY()<=DiasAlerta,$AK15<>"Concluído",$AK15<>"Cancelado"),"Vence em breve","OK"))))))))))))))))))))))))))) -> OK | BA15: Evento de uma semana, fev/2026, no sopro; a refação ocorreu na ISBM-007 (dados). | BB15: R14 | BC15: =IF($V15="","",1+COUNTIF($V$5:$V$154,">"&$V15)+COUNTIFS($V$5:$V$154,$V15,$U$5:$U$154,">"&$U15)+COUNTIFS($V$4:$V14,$V15,$U$4:$U14,$U15)) -> 23 | BD15: Média — semanas | BE15: Moderada | BF15: Preventivo | BG15: 9000 | BH15: 26000 | BI15: =IF(OR($BH15="",$T15=""),"",IFERROR($BH15*INDEX(ProbMedia,$T15),"")) -> 13000 | BJ15: =IF(OR($BG15="",$BI15=""),"",IF(OR(LEFT($M15,3)="SST",LEFT($M15,5)="Legal",LEFT($M15,8)="Ambienta"),"SST/Ambiental/Legal: custo não justifica aceitar (apetite e ALARP)",IF($BG15>$BI15,"Custo maior que a perda esperada: reter/aceitar é defensável, com justificativa","Custo menor ou igual à perda esperada: tratar compensa"))) -> Custo menor ou igual à perda esperada: tratar compensa | BW15: =IF($BU15="","",IFERROR(INDEX(SgaProbValor,MATCH($BU15,SgaProbNivel,0)),"")) | BX15: =IF($BV15="","",IFERROR(INDEX(SgaSevRiValor,MATCH($BV15,SgaSevRiNivel,0)),"")) | BY15: =IF(COUNT($BW15:$BX15)=2,$BW15*$BX15,"") | BZ15: =IF($BY15="","",IF($BY15<=SgaLimRiSig,"SIGNIFICATIVO",IF($BY15<=SgaLimRiTol,"TOLERÁVEL","BAIXO"))) | CA15: =IF($BZ15="","",IF($BZ15="SIGNIFICATIVO","NÃO ACEITÁVEL","ACEITÁVEL")) | CG15: =IF(OR($CE15="",$CF15=""),"",IFERROR(INDEX(SgaProbValor,MATCH($CE15,SgaProbNivel,0))*INDEX(SgaSevRiValor,MATCH($CF15,SgaSevRiNivel,0)),"")) | CH15: =IF($CG15="","",IF($CG15<=SgaLimRiSig,"SIGNIFICATIVO",IF($CG15<=SgaLimRiTol,"TOLERÁVEL","BAIXO")))
A16: R12 | B16: Engenharia de Processo | C16: Lançamento de novos produtos (FR-011/012-PET-400) com curva de aprendizado e defeitos elevados nas primeiras semanas | D16: Alteração (gestão de mudança) | E16: Práticas de gerenciamento | F16: Projeto | G16: Taxa de rejeição ≤ 2,0% (baseline 2,39%) | H16: Mantido | I16: Clientes de cosmética (marcas UE) | J16: Parâmetros e plano de controle ainda não estabilizados no lançamento; efeito de aprendizado de ~6 semanas | K16: Método | L16: Defeito elevado no lançamento (+80% no modelo), sucata e possíveis reclamações | M16: Qualidade / Cliente | N16: 3 | O16: 2 | P16: =IF(COUNT($N16:$O16)=2,$N16*$O16,"") -> 6 | Q16: =IF($P16="","",INDEX(Niveis,MAX(IFERROR(MATCH($P16,Limites,1),1),IF($O16=5,MinIdx,1)))) -> Baixo | R16: Plano de controle de lançamento; inspeção reforçada nas primeiras semanas | S16: Média | T16: 2 | U16: 2 | V16: =IF(COUNT($T16:$U16)=2,$T16*$U16,"") -> 4 | W16: =IF($V16="","",INDEX(Niveis,MAX(IFERROR(MATCH($V16,Limites,1),1),IF($U16=5,MinIdx,1)))) -> Baixo | X16: Média | Y16: =IF(IF($W16<>"",$W16,$Q16)="","",INDEX(AcaoRisco,MATCH(IF($W16<>"",$W16,$Q16),Niveis,0))) -> Monitorar | Z16: Monitorar | AA16: Controle administrativo | AC16: Manter revisão de riscos de lançamento (APQP simplificado) antes de cada novo SKU | AD16: Gerente da Qualidade | AE16: Eng. da Qualidade | AJ16: =IF(OR($AI16="",PlanoUrl=""),"",HYPERLINK(SUBSTITUTE(PlanoUrl,"{COD}",SUBSTITUTE($AI16," ","%20")),"↗")) | AK16: =IF($C16="","",IF($AI16="",$AG16&"",IFERROR(IF(INDEX(PlanosStatus,MATCH($AI16,PlanosCod,0))="",$AG16&"",INDEX(PlanosStatus,MATCH($AI16,PlanosCod,0))),$AG16&""))) | AL16: =IF($C16="","",IF($AI16="",IF($AF16="","",$AF16),IFERROR(IF(INDEX(PlanosPrazo,MATCH($AI16,PlanosCod,0))="",IF($AF16="","",$AF16),INDEX(PlanosPrazo,MATCH($AI16,PlanosCod,0))),IF($AF16="","",$AF16)))) | AR16: =IF(COUNT($AP16:$AQ16)=2,$AP16*$AQ16,"") | AS16: =IF($AR16="","",INDEX(Niveis,MAX(IFERROR(MATCH($AR16,Limites,1),1),IF($AQ16=5,MinIdx,1)))) | AV16: 0 | AW16: 46371 | AX16: Comitê da Qualidade | AY16: =IF(OR($AW16="",IF(AND($AN16="Eficaz",$AS16<>""),$AS16,IF($W16<>"",$W16,$Q16))=""),"",EDATE($AW16,INDEX(MesesRev,MATCH(IF(AND($AN16="Eficaz",$AS16<>""),$AS16,IF($W16<>"",$W16,$Q16)),Niveis,0)))) -> 46736 | AZ16: =IF($C16="","",IF($AD16="","Sem dono",IF($W16="","Falta avaliação",IF(AND($AI16<>"",COUNTIF(PlanosCod,$AI16)=0),"Código não encontrado",IF(AND($AI16<>"",IFERROR(INDEX(PlanosIdRef,MATCH($AI16,PlanosCod,0))&"","")<>"",ISERROR(SEARCH(";"&$A16&";",";"&SUBSTITUTE(SUBSTITUTE(IFERROR(INDEX(PlanosIdRef,MATCH($AI16,PlanosCod,0))&"","")," ",""),",",";")&";"))),"Vínculo divergente",IF(AND(ISNUMBER($P16),ISNUMBER($V16),$V16<$P16,OR($S16="",$S16="Inexistente")),"Redução s/ controle",IF(AND(ISNUMBER($AR16),ISNUMBER($V16),$AR16<$V16,NOT(OR($Z16="Prevenir",$Z16="Mitigar",$Z16="Transferir / compartilhar")),$AC16="",$AI16=""),"Residual s/ tratamento",IF(AND(LEFT($AI16,3)="RNC",N(IFERROR(INDEX(PlanosAbertura,MATCH($AI16,PlanosCod,0)),0))>N($AW16)),"Reavaliar após RNC",IF(AND(N($AV16)>=1,ISNUMBER($T16),$T16<=2),"Recalibrar probabilidade",IF(AND($Z16="Aceitar",$BA16=""),"Aceite sem justificativa",IF(AND($Z16="Aceitar",ISNUMBER($AB16),$AB16<TODAY()),"Aceite vencido",IF(AND(OR($Z16="Aceitar",$Z16="Monitorar"),$Y16<>"Monitorar",$Y16<>""),"Aprovar aceite",IF(AND($Z16<>"Aceitar",$Z16<>"Monitorar",$Z16<>"Aprofundar análise",$AC16="",$AI16="",IFERROR(MATCH(IF($W16<>"",$W16,$Q16),Niveis,0),0)>IF(N(IFERROR(INDEX(ApetIdx,MATCH($M16,ListaCatRisco,0)),0))=0,IdxExige-1,INDEX(ApetIdx,MATCH($M16,ListaCatRisco,0)))),"Sem ação",IF($Z16="Aprofundar análise","Aprofundar análise",IF(AND(OR($Z16="Prevenir",$Z16="Mitigar",$Z16="Transferir / compartilhar"),$AH16=""),"Definir critério de eficácia",IF(AND(OR($Z16="Prevenir",$Z16="Mitigar",$Z16="Transferir / compartilhar"),OR($AA16="Controle administrativo",$AA16="EPI"),IFERROR(MATCH(IF($W16<>"",$W16,$Q16),Niveis,0),0)>=3),"Rever hierarquia de controle",IF(COUNTIFS(KriId,$A16,KriSit,"Estourou")+COUNTIFS(KriId,$A16,KriSit,"Atenção")>0,"KRI em alerta",IF(COUNTIFS(BtId,$A16,BtEf,"Baixa")+COUNTIFS(BtId,$A16,BtEf,"Inexistente")>0,"Barreira fraca",IF($AN16="Não eficaz","Ação ineficaz",IF(AND($AL16<>"",$AL16<TODAY(),$AK16<>"Concluído",$AK16<>"Cancelado"),"Ação vencida",IF(AND($AN16<>"Eficaz",OR($AK16="Concluído",AND(ISNUMBER($AM16),$AM16<TODAY()))),"Avaliar eficácia",IF(AND($AN16="Eficaz",OR($AS16="",$AT16="")),"Concluir residual",IF($AT16="Não","Tratamento adicional",IF(AND($AT16="Sim",$AS16<>"",IFERROR(MATCH($AS16,Niveis,0),0)>IF(N(IFERROR(INDEX(ApetIdx,MATCH($M16,ListaCatRisco,0)),0))=0,IdxExige-1,INDEX(ApetIdx,MATCH($M16,ListaCatRisco,0)))),"Aceite fora do apetite",IF(AND(COUNTIF(BtId,$A16)=0,OR(IFERROR(MATCH(IF($W16<>"",$W16,$Q16),Niveis,0),0)>=3,AND(OR($S16="Baixa",$S16="Inexistente"),IFERROR(MATCH(IF($W16<>"",$W16,$Q16),Niveis,0),0)>=2))),"Sem BowTie",IF(AND($AY16<>"",$AY16<TODAY()),"Revisão vencida",IF(AND($AL16<>"",N($AL16)-TODAY()<=DiasAlerta,$AK16<>"Concluído",$AK16<>"Cancelado"),"Vence em breve","OK"))))))))))))))))))))))))))) -> OK | BA16: Nos dados, a rejeição dos SKUs lançados em 06/04/2026 foi de 2,54% nas primeiras 6 semanas vs 2,43% depois — efeito pequeno e dentro do apetite (Baixo). | BC16: =IF($V16="","",1+COUNTIF($V$5:$V$154,">"&$V16)+COUNTIFS($V$5:$V$154,$V16,$U$5:$U$154,">"&$U16)+COUNTIFS($V$4:$V15,$V16,$U$4:$U15,$U16)) -> 39 | BD16: Lenta — meses | BE16: Estável | BF16: Preventivo | BI16: =IF(OR($BH16="",$T16=""),"",IFERROR($BH16*INDEX(ProbMedia,$T16),"")) | BJ16: =IF(OR($BG16="",$BI16=""),"",IF(OR(LEFT($M16,3)="SST",LEFT($M16,5)="Legal",LEFT($M16,8)="Ambienta"),"SST/Ambiental/Legal: custo não justifica aceitar (apetite e ALARP)",IF($BG16>$BI16,"Custo maior que a perda esperada: reter/aceitar é defensável, com justificativa","Custo menor ou igual à perda esperada: tratar compensa"))) | BW16: =IF($BU16="","",IFERROR(INDEX(SgaProbValor,MATCH($BU16,SgaProbNivel,0)),"")) | BX16: =IF($BV16="","",IFERROR(INDEX(SgaSevRiValor,MATCH($BV16,SgaSevRiNivel,0)),"")) | BY16: =IF(COUNT($BW16:$BX16)=2,$BW16*$BX16,"") | BZ16: =IF($BY16="","",IF($BY16<=SgaLimRiSig,"SIGNIFICATIVO",IF($BY16<=SgaLimRiTol,"TOLERÁVEL","BAIXO"))) | CA16: =IF($BZ16="","",IF($BZ16="SIGNIFICATIVO","NÃO ACEITÁVEL","ACEITÁVEL")) | CG16: =IF(OR($CE16="",$CF16=""),"",IFERROR(INDEX(SgaProbValor,MATCH($CE16,SgaProbNivel,0))*INDEX(SgaSevRiValor,MATCH($CF16,SgaSevRiNivel,0)),"")) | CH16: =IF($CG16="","",IF($CG16<=SgaLimRiSig,"SIGNIFICATIVO",IF($CG16<=SgaLimRiTol,"TOLERÁVEL","BAIXO")))
A17: R13 | B17: Compras / Fornecedores | C17: Lotes de matéria-prima fora de especificação do fornecedor SUP-005 (compra spot, PP/PVC) chegam à produção | D17: RNC / reclamação | E17: Externo | F17: Gerencial (processo) | G17: Lotes de matéria-prima não aceitos ≤ 5% | H17: Alterado | I17: Fornecedores de polímero e PCR | J17: Fornecedor spot (4 anos, sem contrato de longo prazo) com processo de fornecimento de maior taxa de lote fora de especificação | K17: Material | L17: Lotes não aceitos (25,5% vs 4–9% dos demais; 50% em nov e dez/2026), 29 reclamações ao fornecedor, defeitos a jusante (adesão, refações) | M17: Qualidade / Cliente | N17: 5 | O17: 4 | P17: =IF(COUNT($N17:$O17)=2,$N17*$O17,"") -> 20 | Q17: =IF($P17="","",INDEX(Niveis,MAX(IFERROR(MATCH($P17,Limites,1),1),IF($O17=5,MinIdx,1)))) -> Crítico | R17: Inspeção de recebimento (Melt Index, densidade); segregação de lotes reprovados | S17: Média | T17: 4 | U17: 4 | V17: =IF(COUNT($T17:$U17)=2,$T17*$U17,"") -> 16 | W17: =IF($V17="","",INDEX(Niveis,MAX(IFERROR(MATCH($V17,Limites,1),1),IF($U17=5,MinIdx,1)))) -> Crítico | X17: Alta | Y17: =IF(IF($W17<>"",$W17,$Q17)="","",INDEX(AcaoRisco,MATCH(IF($W17<>"",$W17,$Q17),Niveis,0))) -> Prevenir | Z17: Prevenir | AA17: Substituição | AC17: CAPA de fornecedor, auditoria de processo, critério de aprovação/descredenciamento e plano de contingência de segunda fonte (RC-11) | AD17: Gerente de Compras | AE17: Comprador Sênior | AH17: Lotes SUP-005 não aceitos ≤ 8% por 3 meses ou fornecedor substituído | AI17: PAC 202606 | AJ17: =IF(OR($AI17="",PlanoUrl=""),"",HYPERLINK(SUBSTITUTE(PlanoUrl,"{COD}",SUBSTITUTE($AI17," ","%20")),"↗")) | AK17: =IF($C17="","",IF($AI17="",$AG17&"",IFERROR(IF(INDEX(PlanosStatus,MATCH($AI17,PlanosCod,0))="",$AG17&"",INDEX(PlanosStatus,MATCH($AI17,PlanosCod,0))),$AG17&""))) -> Em andamento | AL17: =IF($C17="","",IF($AI17="",IF($AF17="","",$AF17),IFERROR(IF(INDEX(PlanosPrazo,MATCH($AI17,PlanosCod,0))="",IF($AF17="","",$AF17),INDEX(PlanosPrazo,MATCH($AI17,PlanosCod,0))),IF($AF17="","",$AF17)))) -> 46444 | AM17: 46507 | AP17: 2 | AQ17: 3 | AR17: =IF(COUNT($AP17:$AQ17)=2,$AP17*$AQ17,"") -> 6 | AS17: =IF($AR17="","",INDEX(Niveis,MAX(IFERROR(MATCH($AR17,Limites,1),1),IF($AQ17=5,MinIdx,1)))) -> Baixo | AT17: Sim | AU17: % de lotes não aceitos do SUP-005 (aba KRI) | AV17: 46 | AW17: 46371 | AX17: Compras + Qualidade | AY17: =IF(OR($AW17="",IF(AND($AN17="Eficaz",$AS17<>""),$AS17,IF($W17<>"",$W17,$Q17))=""),"",EDATE($AW17,INDEX(MesesRev,MATCH(IF(AND($AN17="Eficaz",$AS17<>""),$AS17,IF($W17<>"",$W17,$Q17)),Niveis,0)))) -> 46402 | AZ17: =IF($C17="","",IF($AD17="","Sem dono",IF($W17="","Falta avaliação",IF(AND($AI17<>"",COUNTIF(PlanosCod,$AI17)=0),"Código não encontrado",IF(AND($AI17<>"",IFERROR(INDEX(PlanosIdRef,MATCH($AI17,PlanosCod,0))&"","")<>"",ISERROR(SEARCH(";"&$A17&";",";"&SUBSTITUTE(SUBSTITUTE(IFERROR(INDEX(PlanosIdRef,MATCH($AI17,PlanosCod,0))&"","")," ",""),",",";")&";"))),"Vínculo divergente",IF(AND(ISNUMBER($P17),ISNUMBER($V17),$V17<$P17,OR($S17="",$S17="Inexistente")),"Redução s/ controle",IF(AND(ISNUMBER($AR17),ISNUMBER($V17),$AR17<$V17,NOT(OR($Z17="Prevenir",$Z17="Mitigar",$Z17="Transferir / compartilhar")),$AC17="",$AI17=""),"Residual s/ tratamento",IF(AND(LEFT($AI17,3)="RNC",N(IFERROR(INDEX(PlanosAbertura,MATCH($AI17,PlanosCod,0)),0))>N($AW17)),"Reavaliar após RNC",IF(AND(N($AV17)>=1,ISNUMBER($T17),$T17<=2),"Recalibrar probabilidade",IF(AND($Z17="Aceitar",$BA17=""),"Aceite sem justificativa",IF(AND($Z17="Aceitar",ISNUMBER($AB17),$AB17<TODAY()),"Aceite vencido",IF(AND(OR($Z17="Aceitar",$Z17="Monitorar"),$Y17<>"Monitorar",$Y17<>""),"Aprovar aceite",IF(AND($Z17<>"Aceitar",$Z17<>"Monitorar",$Z17<>"Aprofundar análise",$AC17="",$AI17="",IFERROR(MATCH(IF($W17<>"",$W17,$Q17),Niveis,0),0)>IF(N(IFERROR(INDEX(ApetIdx,MATCH($M17,ListaCatRisco,0)),0))=0,IdxExige-1,INDEX(ApetIdx,MATCH($M17,ListaCatRisco,0)))),"Sem ação",IF($Z17="Aprofundar análise","Aprofundar análise",IF(AND(OR($Z17="Prevenir",$Z17="Mitigar",$Z17="Transferir / compartilhar"),$AH17=""),"Definir critério de eficácia",IF(AND(OR($Z17="Prevenir",$Z17="Mitigar",$Z17="Transferir / compartilhar"),OR($AA17="Controle administrativo",$AA17="EPI"),IFERROR(MATCH(IF($W17<>"",$W17,$Q17),Niveis,0),0)>=3),"Rever hierarquia de controle",IF(COUNTIFS(KriId,$A17,KriSit,"Estourou")+COUNTIFS(KriId,$A17,KriSit,"Atenção")>0,"KRI em alerta",IF(COUNTIFS(BtId,$A17,BtEf,"Baixa")+COUNTIFS(BtId,$A17,BtEf,"Inexistente")>0,"Barreira fraca",IF($AN17="Não eficaz","Ação ineficaz",IF(AND($AL17<>"",$AL17<TODAY(),$AK17<>"Concluído",$AK17<>"Cancelado"),"Ação vencida",IF(AND($AN17<>"Eficaz",OR($AK17="Concluído",AND(ISNUMBER($AM17),$AM17<TODAY()))),"Avaliar eficácia",IF(AND($AN17="Eficaz",OR($AS17="",$AT17="")),"Concluir residual",IF($AT17="Não","Tratamento adicional",IF(AND($AT17="Sim",$AS17<>"",IFERROR(MATCH($AS17,Niveis,0),0)>IF(N(IFERROR(INDEX(ApetIdx,MATCH($M17,ListaCatRisco,0)),0))=0,IdxExige-1,INDEX(ApetIdx,MATCH($M17,ListaCatRisco,0)))),"Aceite fora do apetite",IF(AND(COUNTIF(BtId,$A17)=0,OR(IFERROR(MATCH(IF($W17<>"",$W17,$Q17),Niveis,0),0)>=3,AND(OR($S17="Baixa",$S17="Inexistente"),IFERROR(MATCH(IF($W17<>"",$W17,$Q17),Niveis,0),0)>=2))),"Sem BowTie",IF(AND($AY17<>"",$AY17<TODAY()),"Revisão vencida",IF(AND($AL17<>"",N($AL17)-TODAY()<=DiasAlerta,$AK17<>"Concluído",$AK17<>"Cancelado"),"Vence em breve","OK"))))))))))))))))))))))))))) -> KRI em alerta | BA17: Fornecedor spot; n mensal de 13–18 lotes: usar leitura de tendência, não de um mês. O descredenciamento exige critérios aprovados e amostra suficiente. | BB17: R6;R14;R15 | BC17: =IF($V17="","",1+COUNTIF($V$5:$V$154,">"&$V17)+COUNTIFS($V$5:$V$154,$V17,$U$5:$U$154,">"&$U17)+COUNTIFS($V$4:$V16,$V17,$U$4:$U16,$U17)) -> 1 | BD17: Rápida — dias | BE17: Alta — muda rápido | BF17: Preventivo | BG17: 20000 | BH17: 95000 | BI17: =IF(OR($BH17="",$T17=""),"",IFERROR($BH17*INDEX(ProbMedia,$T17),"")) -> 66500 | BJ17: =IF(OR($BG17="",$BI17=""),"",IF(OR(LEFT($M17,3)="SST",LEFT($M17,5)="Legal",LEFT($M17,8)="Ambienta"),"SST/Ambiental/Legal: custo não justifica aceitar (apetite e ALARP)",IF($BG17>$BI17,"Custo maior que a perda esperada: reter/aceitar é defensável, com justificativa","Custo menor ou igual à perda esperada: tratar compensa"))) -> Custo menor ou igual à perda esperada: tratar compensa | BL17: PCN-COMPRAS-01 (segunda fonte PP: SUP-002/SUP-007) | BW17: =IF($BU17="","",IFERROR(INDEX(SgaProbValor,MATCH($BU17,SgaProbNivel,0)),"")) | BX17: =IF($BV17="","",IFERROR(INDEX(SgaSevRiValor,MATCH($BV17,SgaSevRiNivel,0)),"")) | BY17: =IF(COUNT($BW17:$BX17)=2,$BW17*$BX17,"") | BZ17: =IF($BY17="","",IF($BY17<=SgaLimRiSig,"SIGNIFICATIVO",IF($BY17<=SgaLimRiTol,"TOLERÁVEL","BAIXO"))) | CA17: =IF($BZ17="","",IF($BZ17="SIGNIFICATIVO","NÃO ACEITÁVEL","ACEITÁVEL")) | CG17: =IF(OR($CE17="",$CF17=""),"",IFERROR(INDEX(SgaProbValor,MATCH($CE17,SgaProbNivel,0))*INDEX(SgaSevRiValor,MATCH($CF17,SgaSevRiNivel,0)),"")) | CH17: =IF($CG17="","",IF($CG17<=SgaLimRiSig,"SIGNIFICATIVO",IF($CG17<=SgaLimRiTol,"TOLERÁVEL","BAIXO")))
A18: R14 | B18: Compras / Fornecedores | C18: Volatilidade de qualidade e disponibilidade de PCR/rPET e troca de fornecedor de HDPE-PCR | D18: SWOT / contexto | E18: Externo | F18: Estratégico | G18: Lotes de matéria-prima não aceitos ≤ 5% | H18: Alterado | I18: Fornecedores de polímero e PCR | J18: Dependência de poucas fontes de material reciclado; transição SUP-001 → SUP-004 (mai–jun/2026) com curva de aprendizado | K18: Material | L18: Lotes não aceitos (18,2% na transição vs 9,4% fora dela), mais scrap e limitação das metas de conteúdo reciclado | M18: Produção / Ativos | N18: 4 | O18: 3 | P18: =IF(COUNT($N18:$O18)=2,$N18*$O18,"") -> 12 | Q18: =IF($P18="","",INDEX(Niveis,MAX(IFERROR(MATCH($P18,Limites,1),1),IF($O18=5,MinIdx,1)))) -> Alto | R18: Inspeção de recebimento; especificação técnica de PCR | S18: Média | T18: 3 | U18: 3 | V18: =IF(COUNT($T18:$U18)=2,$T18*$U18,"") -> 9 | W18: =IF($V18="","",INDEX(Niveis,MAX(IFERROR(MATCH($V18,Limites,1),1),IF($U18=5,MinIdx,1)))) -> Médio | X18: Média | Y18: =IF(IF($W18<>"",$W18,$Q18)="","",INDEX(AcaoRisco,MATCH(IF($W18<>"",$W18,$Q18),Niveis,0))) -> Mitigar | Z18: Mitigar | AA18: Substituição | AC18: Qualificar fontes múltiplas de PCR/rPET e executar DOE de materiais antes de mudar fornecedor | AD18: Gerente de Compras | AE18: Comprador Sênior | AH18: ≥ 2 fornecedores aprovados por material reciclado e não aceitação ≤ 8% | AI18: PAC 202615 | AJ18: =IF(OR($AI18="",PlanoUrl=""),"",HYPERLINK(SUBSTITUTE(PlanoUrl,"{COD}",SUBSTITUTE($AI18," ","%20")),"↗")) | AK18: =IF($C18="","",IF($AI18="",$AG18&"",IFERROR(IF(INDEX(PlanosStatus,MATCH($AI18,PlanosCod,0))="",$AG18&"",INDEX(PlanosStatus,MATCH($AI18,PlanosCod,0))),$AG18&""))) -> Aberto | AL18: =IF($C18="","",IF($AI18="",IF($AF18="","",$AF18),IFERROR(IF(INDEX(PlanosPrazo,MATCH($AI18,PlanosCod,0))="",IF($AF18="","",$AF18),INDEX(PlanosPrazo,MATCH($AI18,PlanosCod,0))),IF($AF18="","",$AF18)))) -> 46538 | AM18: 46568 | AP18: 2 | AQ18: 3 | AR18: =IF(COUNT($AP18:$AQ18)=2,$AP18*$AQ18,"") -> 6 | AS18: =IF($AR18="","",INDEX(Niveis,MAX(IFERROR(MATCH($AR18,Limites,1),1),IF($AQ18=5,MinIdx,1)))) -> Baixo | AT18: Sim | AU18: % de lotes de MP não aceitos — todos os fornecedores (aba KRI) | AV18: 8 | AW18: 46371 | AX18: Compras + Qualidade | AY18: =IF(OR($AW18="",IF(AND($AN18="Eficaz",$AS18<>""),$AS18,IF($W18<>"",$W18,$Q18))=""),"",EDATE($AW18,INDEX(MesesRev,MATCH(IF(AND($AN18="Eficaz",$AS18<>""),$AS18,IF($W18<>"",$W18,$Q18)),Niveis,0)))) -> 46553 | AZ18: =IF($C18="","",IF($AD18="","Sem dono",IF($W18="","Falta avaliação",IF(AND($AI18<>"",COUNTIF(PlanosCod,$AI18)=0),"Código não encontrado",IF(AND($AI18<>"",IFERROR(INDEX(PlanosIdRef,MATCH($AI18,PlanosCod,0))&"","")<>"",ISERROR(SEARCH(";"&$A18&";",";"&SUBSTITUTE(SUBSTITUTE(IFERROR(INDEX(PlanosIdRef,MATCH($AI18,PlanosCod,0))&"","")," ",""),",",";")&";"))),"Vínculo divergente",IF(AND(ISNUMBER($P18),ISNUMBER($V18),$V18<$P18,OR($S18="",$S18="Inexistente")),"Redução s/ controle",IF(AND(ISNUMBER($AR18),ISNUMBER($V18),$AR18<$V18,NOT(OR($Z18="Prevenir",$Z18="Mitigar",$Z18="Transferir / compartilhar")),$AC18="",$AI18=""),"Residual s/ tratamento",IF(AND(LEFT($AI18,3)="RNC",N(IFERROR(INDEX(PlanosAbertura,MATCH($AI18,PlanosCod,0)),0))>N($AW18)),"Reavaliar após RNC",IF(AND(N($AV18)>=1,ISNUMBER($T18),$T18<=2),"Recalibrar probabilidade",IF(AND($Z18="Aceitar",$BA18=""),"Aceite sem justificativa",IF(AND($Z18="Aceitar",ISNUMBER($AB18),$AB18<TODAY()),"Aceite vencido",IF(AND(OR($Z18="Aceitar",$Z18="Monitorar"),$Y18<>"Monitorar",$Y18<>""),"Aprovar aceite",IF(AND($Z18<>"Aceitar",$Z18<>"Monitorar",$Z18<>"Aprofundar análise",$AC18="",$AI18="",IFERROR(MATCH(IF($W18<>"",$W18,$Q18),Niveis,0),0)>IF(N(IFERROR(INDEX(ApetIdx,MATCH($M18,ListaCatRisco,0)),0))=0,IdxExige-1,INDEX(ApetIdx,MATCH($M18,ListaCatRisco,0)))),"Sem ação",IF($Z18="Aprofundar análise","Aprofundar análise",IF(AND(OR($Z18="Prevenir",$Z18="Mitigar",$Z18="Transferir / compartilhar"),$AH18=""),"Definir critério de eficácia",IF(AND(OR($Z18="Prevenir",$Z18="Mitigar",$Z18="Transferir / compartilhar"),OR($AA18="Controle administrativo",$AA18="EPI"),IFERROR(MATCH(IF($W18<>"",$W18,$Q18),Niveis,0),0)>=3),"Rever hierarquia de controle",IF(COUNTIFS(KriId,$A18,KriSit,"Estourou")+COUNTIFS(KriId,$A18,KriSit,"Atenção")>0,"KRI em alerta",IF(COUNTIFS(BtId,$A18,BtEf,"Baixa")+COUNTIFS(BtId,$A18,BtEf,"Inexistente")>0,"Barreira fraca",IF($AN18="Não eficaz","Ação ineficaz",IF(AND($AL18<>"",$AL18<TODAY(),$AK18<>"Concluído",$AK18<>"Cancelado"),"Ação vencida",IF(AND($AN18<>"Eficaz",OR($AK18="Concluído",AND(ISNUMBER($AM18),$AM18<TODAY()))),"Avaliar eficácia",IF(AND($AN18="Eficaz",OR($AS18="",$AT18="")),"Concluir residual",IF($AT18="Não","Tratamento adicional",IF(AND($AT18="Sim",$AS18<>"",IFERROR(MATCH($AS18,Niveis,0),0)>IF(N(IFERROR(INDEX(ApetIdx,MATCH($M18,ListaCatRisco,0)),0))=0,IdxExige-1,INDEX(ApetIdx,MATCH($M18,ListaCatRisco,0)))),"Aceite fora do apetite",IF(AND(COUNTIF(BtId,$A18)=0,OR(IFERROR(MATCH(IF($W18<>"",$W18,$Q18),Niveis,0),0)>=3,AND(OR($S18="Baixa",$S18="Inexistente"),IFERROR(MATCH(IF($W18<>"",$W18,$Q18),Niveis,0),0)>=2))),"Sem BowTie",IF(AND($AY18<>"",$AY18<TODAY()),"Revisão vencida",IF(AND($AL18<>"",N($AL18)-TODAY()<=DiasAlerta,$AK18<>"Concluído",$AK18<>"Cancelado"),"Vence em breve","OK"))))))))))))))))))))))))))) -> KRI em alerta | BA18: Origem SWOT (Ameaça): custo e disponibilidade de material reciclado. Transição de fornecedor 2026-05-01 a 2026-06-15. | BB18: R13;R25;O5 | BC18: =IF($V18="","",1+COUNTIF($V$5:$V$154,">"&$V18)+COUNTIFS($V$5:$V$154,$V18,$U$5:$U$154,">"&$U18)+COUNTIFS($V$4:$V17,$V18,$U$4:$U17,$U18)) -> 24 | BD18: Média — semanas | BE18: Alta — muda rápido | BF18: Preventivo | BG18: 15000 | BH18: 40000 | BI18: =IF(OR($BH18="",$T18=""),"",IFERROR($BH18*INDEX(ProbMedia,$T18),"")) -> 20000 | BJ18: =IF(OR($BG18="",$BI18=""),"",IF(OR(LEFT($M18,3)="SST",LEFT($M18,5)="Legal",LEFT($M18,8)="Ambienta"),"SST/Ambiental/Legal: custo não justifica aceitar (apetite e ALARP)",IF($BG18>$BI18,"Custo maior que a perda esperada: reter/aceitar é defensável, com justificativa","Custo menor ou igual à perda esperada: tratar compensa"))) -> Custo menor ou igual à perda esperada: tratar compensa | BW18: =IF($BU18="","",IFERROR(INDEX(SgaProbValor,MATCH($BU18,SgaProbNivel,0)),"")) | BX18: =IF($BV18="","",IFERROR(INDEX(SgaSevRiValor,MATCH($BV18,SgaSevRiNivel,0)),"")) | BY18: =IF(COUNT($BW18:$BX18)=2,$BW18*$BX18,"") | BZ18: =IF($BY18="","",IF($BY18<=SgaLimRiSig,"SIGNIFICATIVO",IF($BY18<=SgaLimRiTol,"TOLERÁVEL","BAIXO"))) | CA18: =IF($BZ18="","",IF($BZ18="SIGNIFICATIVO","NÃO ACEITÁVEL","ACEITÁVEL")) | CG18: =IF(OR($CE18="",$CF18=""),"",IFERROR(INDEX(SgaProbValor,MATCH($CE18,SgaProbNivel,0))*INDEX(SgaSevRiValor,MATCH($CF18,SgaSevRiNivel,0)),"")) | CH18: =IF($CG18="","",IF($CG18<=SgaLimRiSig,"SIGNIFICATIVO",IF($CG18<=SgaLimRiTol,"TOLERÁVEL","BAIXO")))
A19: R15 | B19: PCP / Planejamento | C19: Falta de matéria-prima interrompe ordens de produção (parada por Raw Material Shortage) | D19: Monitoramento de itens críticos | E19: Práticas de gerenciamento | F19: Gerencial (processo) | G19: Continuidade da produção e entregas no prazo | H19: Novo | I19: Clientes de cosmética (marcas UE) | J19: Planejamento de compras sem cobertura mínima por material crítico e dependência de fornecedores spot | K19: Método | L19: ≈ 2 680 h de parada em 18 meses (≈ 149 h/mês), ordens atrasadas e mais reclamações de entrega | M19: Produção / Ativos | N19: 4 | O19: 3 | P19: =IF(COUNT($N19:$O19)=2,$N19*$O19,"") -> 12 | Q19: =IF($P19="","",INDEX(Niveis,MAX(IFERROR(MATCH($P19,Limites,1),1),IF($O19=5,MinIdx,1)))) -> Alto | R19: Reposição por ponto de pedido manual; reunião semanal de compras | S19: Média | T19: 3 | U19: 3 | V19: =IF(COUNT($T19:$U19)=2,$T19*$U19,"") -> 9 | W19: =IF($V19="","",INDEX(Niveis,MAX(IFERROR(MATCH($V19,Limites,1),1),IF($U19=5,MinIdx,1)))) -> Médio | X19: Alta | Y19: =IF(IF($W19<>"",$W19,$Q19)="","",INDEX(AcaoRisco,MATCH(IF($W19<>"",$W19,$Q19),Niveis,0))) -> Mitigar | Z19: Mitigar | AA19: Controle administrativo | AC19: Estoque de segurança por material crítico, ponto de pedido automático e alerta de cobertura no PCP | AD19: Gerente de Produção | AE19: Planejador de PCP | AF19: 46477 | AG19: Aberto | AH19: Horas de parada por falta de matéria-prima ≤ 100 h/mês | AJ19: =IF(OR($AI19="",PlanoUrl=""),"",HYPERLINK(SUBSTITUTE(PlanoUrl,"{COD}",SUBSTITUTE($AI19," ","%20")),"↗")) | AK19: =IF($C19="","",IF($AI19="",$AG19&"",IFERROR(IF(INDEX(PlanosStatus,MATCH($AI19,PlanosCod,0))="",$AG19&"",INDEX(PlanosStatus,MATCH($AI19,PlanosCod,0))),$AG19&""))) -> Aberto | AL19: =IF($C19="","",IF($AI19="",IF($AF19="","",$AF19),IFERROR(IF(INDEX(PlanosPrazo,MATCH($AI19,PlanosCod,0))="",IF($AF19="","",$AF19),INDEX(PlanosPrazo,MATCH($AI19,PlanosCod,0))),IF($AF19="","",$AF19)))) -> 46477 | AP19: 2 | AQ19: 3 | AR19: =IF(COUNT($AP19:$AQ19)=2,$AP19*$AQ19,"") -> 6 | AS19: =IF($AR19="","",INDEX(Niveis,MAX(IFERROR(MATCH($AR19,Limites,1),1),IF($AQ19=5,MinIdx,1)))) -> Baixo | AT19: Sim | AU19: Horas de parada por falta de matéria-prima/mês (aba KRI) | AV19: 1114 | AW19: 46371 | AX19: PCP + Compras | AY19: =IF(OR($AW19="",IF(AND($AN19="Eficaz",$AS19<>""),$AS19,IF($W19<>"",$W19,$Q19))=""),"",EDATE($AW19,INDEX(MesesRev,MATCH(IF(AND($AN19="Eficaz",$AS19<>""),$AS19,IF($W19<>"",$W19,$Q19)),Niveis,0)))) -> 46553 | AZ19: =IF($C19="","",IF($AD19="","Sem dono",IF($W19="","Falta avaliação",IF(AND($AI19<>"",COUNTIF(PlanosCod,$AI19)=0),"Código não encontrado",IF(AND($AI19<>"",IFERROR(INDEX(PlanosIdRef,MATCH($AI19,PlanosCod,0))&"","")<>"",ISERROR(SEARCH(";"&$A19&";",";"&SUBSTITUTE(SUBSTITUTE(IFERROR(INDEX(PlanosIdRef,MATCH($AI19,PlanosCod,0))&"","")," ",""),",",";")&";"))),"Vínculo divergente",IF(AND(ISNUMBER($P19),ISNUMBER($V19),$V19<$P19,OR($S19="",$S19="Inexistente")),"Redução s/ controle",IF(AND(ISNUMBER($AR19),ISNUMBER($V19),$AR19<$V19,NOT(OR($Z19="Prevenir",$Z19="Mitigar",$Z19="Transferir / compartilhar")),$AC19="",$AI19=""),"Residual s/ tratamento",IF(AND(LEFT($AI19,3)="RNC",N(IFERROR(INDEX(PlanosAbertura,MATCH($AI19,PlanosCod,0)),0))>N($AW19)),"Reavaliar após RNC",IF(AND(N($AV19)>=1,ISNUMBER($T19),$T19<=2),"Recalibrar probabilidade",IF(AND($Z19="Aceitar",$BA19=""),"Aceite sem justificativa",IF(AND($Z19="Aceitar",ISNUMBER($AB19),$AB19<TODAY()),"Aceite vencido",IF(AND(OR($Z19="Aceitar",$Z19="Monitorar"),$Y19<>"Monitorar",$Y19<>""),"Aprovar aceite",IF(AND($Z19<>"Aceitar",$Z19<>"Monitorar",$Z19<>"Aprofundar análise",$AC19="",$AI19="",IFERROR(MATCH(IF($W19<>"",$W19,$Q19),Niveis,0),0)>IF(N(IFERROR(INDEX(ApetIdx,MATCH($M19,ListaCatRisco,0)),0))=0,IdxExige-1,INDEX(ApetIdx,MATCH($M19,ListaCatRisco,0)))),"Sem ação",IF($Z19="Aprofundar análise","Aprofundar análise",IF(AND(OR($Z19="Prevenir",$Z19="Mitigar",$Z19="Transferir / compartilhar"),$AH19=""),"Definir critério de eficácia",IF(AND(OR($Z19="Prevenir",$Z19="Mitigar",$Z19="Transferir / compartilhar"),OR($AA19="Controle administrativo",$AA19="EPI"),IFERROR(MATCH(IF($W19<>"",$W19,$Q19),Niveis,0),0)>=3),"Rever hierarquia de controle",IF(COUNTIFS(KriId,$A19,KriSit,"Estourou")+COUNTIFS(KriId,$A19,KriSit,"Atenção")>0,"KRI em alerta",IF(COUNTIFS(BtId,$A19,BtEf,"Baixa")+COUNTIFS(BtId,$A19,BtEf,"Inexistente")>0,"Barreira fraca",IF($AN19="Não eficaz","Ação ineficaz",IF(AND($AL19<>"",$AL19<TODAY(),$AK19<>"Concluído",$AK19<>"Cancelado"),"Ação vencida",IF(AND($AN19<>"Eficaz",OR($AK19="Concluído",AND(ISNUMBER($AM19),$AM19<TODAY()))),"Avaliar eficácia",IF(AND($AN19="Eficaz",OR($AS19="",$AT19="")),"Concluir residual",IF($AT19="Não","Tratamento adicional",IF(AND($AT19="Sim",$AS19<>"",IFERROR(MATCH($AS19,Niveis,0),0)>IF(N(IFERROR(INDEX(ApetIdx,MATCH($M19,ListaCatRisco,0)),0))=0,IdxExige-1,INDEX(ApetIdx,MATCH($M19,ListaCatRisco,0)))),"Aceite fora do apetite",IF(AND(COUNTIF(BtId,$A19)=0,OR(IFERROR(MATCH(IF($W19<>"",$W19,$Q19),Niveis,0),0)>=3,AND(OR($S19="Baixa",$S19="Inexistente"),IFERROR(MATCH(IF($W19<>"",$W19,$Q19),Niveis,0),0)>=2))),"Sem BowTie",IF(AND($AY19<>"",$AY19<TODAY()),"Revisão vencida",IF(AND($AL19<>"",N($AL19)-TODAY()<=DiasAlerta,$AK19<>"Concluído",$AK19<>"Cancelado"),"Vence em breve","OK"))))))))))))))))))))))))))) -> KRI em alerta | BA19: Perda ≈ € 350/h × 149 h/mês ≈ € 52 mil/mês (premissa ilustrativa do projeto). | BB19: R13 | BC19: =IF($V19="","",1+COUNTIF($V$5:$V$154,">"&$V19)+COUNTIFS($V$5:$V$154,$V19,$U$5:$U$154,">"&$U19)+COUNTIFS($V$4:$V18,$V19,$U$4:$U18,$U19)) -> 25 | BD19: Rápida — dias | BE19: Moderada | BF19: Preventivo | BG19: 10000 | BH19: 52000 | BI19: =IF(OR($BH19="",$T19=""),"",IFERROR($BH19*INDEX(ProbMedia,$T19),"")) -> 26000 | BJ19: =IF(OR($BG19="",$BI19=""),"",IF(OR(LEFT($M19,3)="SST",LEFT($M19,5)="Legal",LEFT($M19,8)="Ambienta"),"SST/Ambiental/Legal: custo não justifica aceitar (apetite e ALARP)",IF($BG19>$BI19,"Custo maior que a perda esperada: reter/aceitar é defensável, com justificativa","Custo menor ou igual à perda esperada: tratar compensa"))) -> Custo menor ou igual à perda esperada: tratar compensa | BK19: 8 | BW19: =IF($BU19="","",IFERROR(INDEX(SgaProbValor,MATCH($BU19,SgaProbNivel,0)),"")) | BX19: =IF($BV19="","",IFERROR(INDEX(SgaSevRiValor,MATCH($BV19,SgaSevRiNivel,0)),"")) | BY19: =IF(COUNT($BW19:$BX19)=2,$BW19*$BX19,"") | BZ19: =IF($BY19="","",IF($BY19<=SgaLimRiSig,"SIGNIFICATIVO",IF($BY19<=SgaLimRiTol,"TOLERÁVEL","BAIXO"))) | CA19: =IF($BZ19="","",IF($BZ19="SIGNIFICATIVO","NÃO ACEITÁVEL","ACEITÁVEL")) | CG19: =IF(OR($CE19="",$CF19=""),"",IFERROR(INDEX(SgaProbValor,MATCH($CE19,SgaProbNivel,0))*INDEX(SgaSevRiValor,MATCH($CF19,SgaSevRiNivel,0)),"")) | CH19: =IF($CG19="","",IF($CG19<=SgaLimRiSig,"SIGNIFICATIVO",IF($CG19<=SgaLimRiTol,"TOLERÁVEL","BAIXO")))
A20: R16 | B20: Qualidade | C20: Escape de lote marginal ao cliente: passa na amostragem AQL, mas gera reclamação | D20: RNC / reclamação | E20: Práticas de gerenciamento | F20: Gerencial (processo) | G20: Reclamações ≤ 3 por milhão de unidades (baseline 4,76) | H20: Mantido | I20: Clientes de cosmética (marcas UE) | J20: AQL decide o lote, mas não substitui indicadores antecedentes de processo; controle reativo em vez de detecção antecipada | K20: Medida | L20: 208 reclamações em 18 meses (54 críticas; 39 abertas), CPMU 4,76, devolução de lote e perda de confiança | M20: Qualidade / Cliente | N20: 4 | O20: 4 | P20: =IF(COUNT($N20:$O20)=2,$N20*$O20,"") -> 16 | Q20: =IF($P20="","",INDEX(Niveis,MAX(IFERROR(MATCH($P20,Limites,1),1),IF($O20=5,MinIdx,1)))) -> Crítico | R20: Plano de amostragem AQL; inspeção final; tratativa de reclamações | S20: Média | T20: 4 | U20: 3 | V20: =IF(COUNT($T20:$U20)=2,$T20*$U20,"") -> 12 | W20: =IF($V20="","",INDEX(Niveis,MAX(IFERROR(MATCH($V20,Limites,1),1),IF($U20=5,MinIdx,1)))) -> Alto | X20: Alta | Y20: =IF(IF($W20<>"",$W20,$Q20)="","",INDEX(AcaoRisco,MATCH(IF($W20<>"",$W20,$Q20),Niveis,0))) -> Mitigar | Z20: Mitigar | AA20: Controle de engenharia | AC20: Adicionar indicadores antecedentes (KRI/SPC) ao plano de controle e classificar taxonomia de reclamações por lote/defeito (RC-14) | AD20: Gerente da Qualidade | AE20: Eng. da Qualidade | AH20: CPMU ≤ 3,0 e 100% das reclamações rastreadas a lote/ordem | AI20: PAC 202616 | AJ20: =IF(OR($AI20="",PlanoUrl=""),"",HYPERLINK(SUBSTITUTE(PlanoUrl,"{COD}",SUBSTITUTE($AI20," ","%20")),"↗")) | AK20: =IF($C20="","",IF($AI20="",$AG20&"",IFERROR(IF(INDEX(PlanosStatus,MATCH($AI20,PlanosCod,0))="",$AG20&"",INDEX(PlanosStatus,MATCH($AI20,PlanosCod,0))),$AG20&""))) -> Aberto | AL20: =IF($C20="","",IF($AI20="",IF($AF20="","",$AF20),IFERROR(IF(INDEX(PlanosPrazo,MATCH($AI20,PlanosCod,0))="",IF($AF20="","",$AF20),INDEX(PlanosPrazo,MATCH($AI20,PlanosCod,0))),IF($AF20="","",$AF20)))) -> 46477 | AM20: 46568 | AP20: 3 | AQ20: 3 | AR20: =IF(COUNT($AP20:$AQ20)=2,$AP20*$AQ20,"") -> 9 | AS20: =IF($AR20="","",INDEX(Niveis,MAX(IFERROR(MATCH($AR20,Limites,1),1),IF($AQ20=5,MinIdx,1)))) -> Médio | AT20: Sim | AU20: CPMU — reclamações por milhão de unidades (aba KRI) | AV20: 137 | AW20: 46371 | AX20: Comitê da Qualidade | AY20: =IF(OR($AW20="",IF(AND($AN20="Eficaz",$AS20<>""),$AS20,IF($W20<>"",$W20,$Q20))=""),"",EDATE($AW20,INDEX(MesesRev,MATCH(IF(AND($AN20="Eficaz",$AS20<>""),$AS20,IF($W20<>"",$W20,$Q20)),Niveis,0)))) -> 46461 | AZ20: =IF($C20="","",IF($AD20="","Sem dono",IF($W20="","Falta avaliação",IF(AND($AI20<>"",COUNTIF(PlanosCod,$AI20)=0),"Código não encontrado",IF(AND($AI20<>"",IFERROR(INDEX(PlanosIdRef,MATCH($AI20,PlanosCod,0))&"","")<>"",ISERROR(SEARCH(";"&$A20&";",";"&SUBSTITUTE(SUBSTITUTE(IFERROR(INDEX(PlanosIdRef,MATCH($AI20,PlanosCod,0))&"","")," ",""),",",";")&";"))),"Vínculo divergente",IF(AND(ISNUMBER($P20),ISNUMBER($V20),$V20<$P20,OR($S20="",$S20="Inexistente")),"Redução s/ controle",IF(AND(ISNUMBER($AR20),ISNUMBER($V20),$AR20<$V20,NOT(OR($Z20="Prevenir",$Z20="Mitigar",$Z20="Transferir / compartilhar")),$AC20="",$AI20=""),"Residual s/ tratamento",IF(AND(LEFT($AI20,3)="RNC",N(IFERROR(INDEX(PlanosAbertura,MATCH($AI20,PlanosCod,0)),0))>N($AW20)),"Reavaliar após RNC",IF(AND(N($AV20)>=1,ISNUMBER($T20),$T20<=2),"Recalibrar probabilidade",IF(AND($Z20="Aceitar",$BA20=""),"Aceite sem justificativa",IF(AND($Z20="Aceitar",ISNUMBER($AB20),$AB20<TODAY()),"Aceite vencido",IF(AND(OR($Z20="Aceitar",$Z20="Monitorar"),$Y20<>"Monitorar",$Y20<>""),"Aprovar aceite",IF(AND($Z20<>"Aceitar",$Z20<>"Monitorar",$Z20<>"Aprofundar análise",$AC20="",$AI20="",IFERROR(MATCH(IF($W20<>"",$W20,$Q20),Niveis,0),0)>IF(N(IFERROR(INDEX(ApetIdx,MATCH($M20,ListaCatRisco,0)),0))=0,IdxExige-1,INDEX(ApetIdx,MATCH($M20,ListaCatRisco,0)))),"Sem ação",IF($Z20="Aprofundar análise","Aprofundar análise",IF(AND(OR($Z20="Prevenir",$Z20="Mitigar",$Z20="Transferir / compartilhar"),$AH20=""),"Definir critério de eficácia",IF(AND(OR($Z20="Prevenir",$Z20="Mitigar",$Z20="Transferir / compartilhar"),OR($AA20="Controle administrativo",$AA20="EPI"),IFERROR(MATCH(IF($W20<>"",$W20,$Q20),Niveis,0),0)>=3),"Rever hierarquia de controle",IF(COUNTIFS(KriId,$A20,KriSit,"Estourou")+COUNTIFS(KriId,$A20,KriSit,"Atenção")>0,"KRI em alerta",IF(COUNTIFS(BtId,$A20,BtEf,"Baixa")+COUNTIFS(BtId,$A20,BtEf,"Inexistente")>0,"Barreira fraca",IF($AN20="Não eficaz","Ação ineficaz",IF(AND($AL20<>"",$AL20<TODAY(),$AK20<>"Concluído",$AK20<>"Cancelado"),"Ação vencida",IF(AND($AN20<>"Eficaz",OR($AK20="Concluído",AND(ISNUMBER($AM20),$AM20<TODAY()))),"Avaliar eficácia",IF(AND($AN20="Eficaz",OR($AS20="",$AT20="")),"Concluir residual",IF($AT20="Não","Tratamento adicional",IF(AND($AT20="Sim",$AS20<>"",IFERROR(MATCH($AS20,Niveis,0),0)>IF(N(IFERROR(INDEX(ApetIdx,MATCH($M20,ListaCatRisco,0)),0))=0,IdxExige-1,INDEX(ApetIdx,MATCH($M20,ListaCatRisco,0)))),"Aceite fora do apetite",IF(AND(COUNTIF(BtId,$A20)=0,OR(IFERROR(MATCH(IF($W20<>"",$W20,$Q20),Niveis,0),0)>=3,AND(OR($S20="Baixa",$S20="Inexistente"),IFERROR(MATCH(IF($W20<>"",$W20,$Q20),Niveis,0),0)>=2))),"Sem BowTie",IF(AND($AY20<>"",$AY20<TODAY()),"Revisão vencida",IF(AND($AL20<>"",N($AL20)-TODAY()<=DiasAlerta,$AK20<>"Concluído",$AK20<>"Cancelado"),"Vence em breve","OK"))))))))))))))))))))))))))) -> KRI em alerta | BA20: ≈ 67% das reclamações rastreáveis vêm de ordem com qualidade interna abaixo da mediana; o sinal é real, mas fraco: alerta baseado só em rejeição interna captura pouco. | BB20: R18;R21 | BC20: =IF($V20="","",1+COUNTIF($V$5:$V$154,">"&$V20)+COUNTIFS($V$5:$V$154,$V20,$U$5:$U$154,">"&$U20)+COUNTIFS($V$4:$V19,$V20,$U$4:$U19,$U20)) -> 12 | BD20: Rápida — dias | BE20: Moderada | BF20: Detectivo | BG20: 22000 | BH20: 45000 | BI20: =IF(OR($BH20="",$T20=""),"",IFERROR($BH20*INDEX(ProbMedia,$T20),"")) -> 31500 | BJ20: =IF(OR($BG20="",$BI20=""),"",IF(OR(LEFT($M20,3)="SST",LEFT($M20,5)="Legal",LEFT($M20,8)="Ambienta"),"SST/Ambiental/Legal: custo não justifica aceitar (apetite e ALARP)",IF($BG20>$BI20,"Custo maior que a perda esperada: reter/aceitar é defensável, com justificativa","Custo menor ou igual à perda esperada: tratar compensa"))) -> Custo menor ou igual à perda esperada: tratar compensa | BW20: =IF($BU20="","",IFERROR(INDEX(SgaProbValor,MATCH($BU20,SgaProbNivel,0)),"")) | BX20: =IF($BV20="","",IFERROR(INDEX(SgaSevRiValor,MATCH($BV20,SgaSevRiNivel,0)),"")) | BY20: =IF(COUNT($BW20:$BX20)=2,$BW20*$BX20,"") | BZ20: =IF($BY20="","",IF($BY20<=SgaLimRiSig,"SIGNIFICATIVO",IF($BY20<=SgaLimRiTol,"TOLERÁVEL","BAIXO"))) | CA20: =IF($BZ20="","",IF($BZ20="SIGNIFICATIVO","NÃO ACEITÁVEL","ACEITÁVEL")) | CG20: =IF(OR($CE20="",$CF20=""),"",IFERROR(INDEX(SgaProbValor,MATCH($CE20,SgaProbNivel,0))*INDEX(SgaSevRiValor,MATCH($CF20,SgaSevRiNivel,0)),"")) | CH20: =IF($CG20="","",IF($CG20<=SgaLimRiSig,"SIGNIFICATIVO",IF($CG20<=SgaLimRiTol,"TOLERÁVEL","BAIXO")))
A21: R17 | B21: Qualidade | C21: Capacidade de processo marginal: 0% dos 190 grupos máquina×molde×característica atingem Cpk ≥ 1,33 | D21: Análise de dados / raio-X analítico | E21: Técnico | F21: Estratégico | G21: Cpk ≥ 1,33 nas características críticas | H21: Novo | I21: Clientes de cosmética (marcas UE) | J21: Centralização e dispersão inadequadas de forma generalizada; máquinas nomeadas (IM-002, ISBM-003) pioram uma base já modesta | K21: Máquina | L21: Risco de não atender exigência de Cpk de clientes, mais inspeção e maior custo de avaliação | M21: Qualidade / Cliente | N21: 5 | O21: 3 | P21: =IF(COUNT($N21:$O21)=2,$N21*$O21,"") -> 15 | Q21: =IF($P21="","",INDEX(Niveis,MAX(IFERROR(MATCH($P21,Limites,1),1),IF($O21=5,MinIdx,1)))) -> Alto | R21: Cartas de controle; auditoria de processo; inspeção por amostragem | S21: Média | T21: 4 | U21: 3 | V21: =IF(COUNT($T21:$U21)=2,$T21*$U21,"") -> 12 | W21: =IF($V21="","",INDEX(Niveis,MAX(IFERROR(MATCH($V21,Limites,1),1),IF($U21=5,MinIdx,1)))) -> Alto | X21: Alta | Y21: =IF(IF($W21<>"",$W21,$Q21)="","",INDEX(AcaoRisco,MATCH(IF($W21<>"",$W21,$Q21),Niveis,0))) -> Mitigar | Z21: Mitigar | AA21: Controle de engenharia | AC21: Priorizar por Pareto de Cpk × volume × criticidade e conduzir projetos DMAIC nos casos mais fracos | AD21: Gerente da Qualidade | AE21: Black Belt | AH21: ≥ 50% dos grupos priorizados com Cpk ≥ 1,33 em 12 meses | AI21: PAC 202618 | AJ21: =IF(OR($AI21="",PlanoUrl=""),"",HYPERLINK(SUBSTITUTE(PlanoUrl,"{COD}",SUBSTITUTE($AI21," ","%20")),"↗")) | AK21: =IF($C21="","",IF($AI21="",$AG21&"",IFERROR(IF(INDEX(PlanosStatus,MATCH($AI21,PlanosCod,0))="",$AG21&"",INDEX(PlanosStatus,MATCH($AI21,PlanosCod,0))),$AG21&""))) -> Aberto | AL21: =IF($C21="","",IF($AI21="",IF($AF21="","",$AF21),IFERROR(IF(INDEX(PlanosPrazo,MATCH($AI21,PlanosCod,0))="",IF($AF21="","",$AF21),INDEX(PlanosPrazo,MATCH($AI21,PlanosCod,0))),IF($AF21="","",$AF21)))) -> 46741 | AM21: 46741 | AP21: 3 | AQ21: 3 | AR21: =IF(COUNT($AP21:$AQ21)=2,$AP21*$AQ21,"") -> 9 | AS21: =IF($AR21="","",INDEX(Niveis,MAX(IFERROR(MATCH($AR21,Limites,1),1),IF($AQ21=5,MinIdx,1)))) -> Médio | AT21: Sim | AW21: 46371 | AX21: Comitê da Qualidade | AY21: =IF(OR($AW21="",IF(AND($AN21="Eficaz",$AS21<>""),$AS21,IF($W21<>"",$W21,$Q21))=""),"",EDATE($AW21,INDEX(MesesRev,MATCH(IF(AND($AN21="Eficaz",$AS21<>""),$AS21,IF($W21<>"",$W21,$Q21)),Niveis,0)))) -> 46461 | AZ21: =IF($C21="","",IF($AD21="","Sem dono",IF($W21="","Falta avaliação",IF(AND($AI21<>"",COUNTIF(PlanosCod,$AI21)=0),"Código não encontrado",IF(AND($AI21<>"",IFERROR(INDEX(PlanosIdRef,MATCH($AI21,PlanosCod,0))&"","")<>"",ISERROR(SEARCH(";"&$A21&";",";"&SUBSTITUTE(SUBSTITUTE(IFERROR(INDEX(PlanosIdRef,MATCH($AI21,PlanosCod,0))&"","")," ",""),",",";")&";"))),"Vínculo divergente",IF(AND(ISNUMBER($P21),ISNUMBER($V21),$V21<$P21,OR($S21="",$S21="Inexistente")),"Redução s/ controle",IF(AND(ISNUMBER($AR21),ISNUMBER($V21),$AR21<$V21,NOT(OR($Z21="Prevenir",$Z21="Mitigar",$Z21="Transferir / compartilhar")),$AC21="",$AI21=""),"Residual s/ tratamento",IF(AND(LEFT($AI21,3)="RNC",N(IFERROR(INDEX(PlanosAbertura,MATCH($AI21,PlanosCod,0)),0))>N($AW21)),"Reavaliar após RNC",IF(AND(N($AV21)>=1,ISNUMBER($T21),$T21<=2),"Recalibrar probabilidade",IF(AND($Z21="Aceitar",$BA21=""),"Aceite sem justificativa",IF(AND($Z21="Aceitar",ISNUMBER($AB21),$AB21<TODAY()),"Aceite vencido",IF(AND(OR($Z21="Aceitar",$Z21="Monitorar"),$Y21<>"Monitorar",$Y21<>""),"Aprovar aceite",IF(AND($Z21<>"Aceitar",$Z21<>"Monitorar",$Z21<>"Aprofundar análise",$AC21="",$AI21="",IFERROR(MATCH(IF($W21<>"",$W21,$Q21),Niveis,0),0)>IF(N(IFERROR(INDEX(ApetIdx,MATCH($M21,ListaCatRisco,0)),0))=0,IdxExige-1,INDEX(ApetIdx,MATCH($M21,ListaCatRisco,0)))),"Sem ação",IF($Z21="Aprofundar análise","Aprofundar análise",IF(AND(OR($Z21="Prevenir",$Z21="Mitigar",$Z21="Transferir / compartilhar"),$AH21=""),"Definir critério de eficácia",IF(AND(OR($Z21="Prevenir",$Z21="Mitigar",$Z21="Transferir / compartilhar"),OR($AA21="Controle administrativo",$AA21="EPI"),IFERROR(MATCH(IF($W21<>"",$W21,$Q21),Niveis,0),0)>=3),"Rever hierarquia de controle",IF(COUNTIFS(KriId,$A21,KriSit,"Estourou")+COUNTIFS(KriId,$A21,KriSit,"Atenção")>0,"KRI em alerta",IF(COUNTIFS(BtId,$A21,BtEf,"Baixa")+COUNTIFS(BtId,$A21,BtEf,"Inexistente")>0,"Barreira fraca",IF($AN21="Não eficaz","Ação ineficaz",IF(AND($AL21<>"",$AL21<TODAY(),$AK21<>"Concluído",$AK21<>"Cancelado"),"Ação vencida",IF(AND($AN21<>"Eficaz",OR($AK21="Concluído",AND(ISNUMBER($AM21),$AM21<TODAY()))),"Avaliar eficácia",IF(AND($AN21="Eficaz",OR($AS21="",$AT21="")),"Concluir residual",IF($AT21="Não","Tratamento adicional",IF(AND($AT21="Sim",$AS21<>"",IFERROR(MATCH($AS21,Niveis,0),0)>IF(N(IFERROR(INDEX(ApetIdx,MATCH($M21,ListaCatRisco,0)),0))=0,IdxExige-1,INDEX(ApetIdx,MATCH($M21,ListaCatRisco,0)))),"Aceite fora do apetite",IF(AND(COUNTIF(BtId,$A21)=0,OR(IFERROR(MATCH(IF($W21<>"",$W21,$Q21),Niveis,0),0)>=3,AND(OR($S21="Baixa",$S21="Inexistente"),IFERROR(MATCH(IF($W21<>"",$W21,$Q21),Niveis,0),0)>=2))),"Sem BowTie",IF(AND($AY21<>"",$AY21<TODAY()),"Revisão vencida",IF(AND($AL21<>"",N($AL21)-TODAY()<=DiasAlerta,$AK21<>"Concluído",$AK21<>"Cancelado"),"Vence em breve","OK"))))))))))))))))))))))))))) -> Barreira fraca | BA21: Planta estatisticamente marginal como um todo; o Cpk máximo observado fica abaixo de 1,33 mesmo entre grupos estáveis. | BB21: R1;R4 | BC21: =IF($V21="","",1+COUNTIF($V$5:$V$154,">"&$V21)+COUNTIFS($V$5:$V$154,$V21,$U$5:$U$154,">"&$U21)+COUNTIFS($V$4:$V20,$V21,$U$4:$U20,$U21)) -> 13 | BD21: Lenta — meses | BE21: Estável | BF21: Preventivo | BG21: 30000 | BH21: 60000 | BI21: =IF(OR($BH21="",$T21=""),"",IFERROR($BH21*INDEX(ProbMedia,$T21),"")) -> 42000 | BJ21: =IF(OR($BG21="",$BI21=""),"",IF(OR(LEFT($M21,3)="SST",LEFT($M21,5)="Legal",LEFT($M21,8)="Ambienta"),"SST/Ambiental/Legal: custo não justifica aceitar (apetite e ALARP)",IF($BG21>$BI21,"Custo maior que a perda esperada: reter/aceitar é defensável, com justificativa","Custo menor ou igual à perda esperada: tratar compensa"))) -> Custo menor ou igual à perda esperada: tratar compensa | BW21: =IF($BU21="","",IFERROR(INDEX(SgaProbValor,MATCH($BU21,SgaProbNivel,0)),"")) | BX21: =IF($BV21="","",IFERROR(INDEX(SgaSevRiValor,MATCH($BV21,SgaSevRiNivel,0)),"")) | BY21: =IF(COUNT($BW21:$BX21)=2,$BW21*$BX21,"") | BZ21: =IF($BY21="","",IF($BY21<=SgaLimRiSig,"SIGNIFICATIVO",IF($BY21<=SgaLimRiTol,"TOLERÁVEL","BAIXO"))) | CA21: =IF($BZ21="","",IF($BZ21="SIGNIFICATIVO","NÃO ACEITÁVEL","ACEITÁVEL")) | CG21: =IF(OR($CE21="",$CF21=""),"",IFERROR(INDEX(SgaProbValor,MATCH($CE21,SgaProbNivel,0))*INDEX(SgaSevRiValor,MATCH($CF21,SgaSevRiNivel,0)),"")) | CH21: =IF($CG21="","",IF($CG21<=SgaLimRiSig,"SIGNIFICATIVO",IF($CG21<=SgaLimRiTol,"TOLERÁVEL","BAIXO")))
A22: R18 | B22: Qualidade | C22: Rastreabilidade incompleta lote → ordem → produto final impede contenção rápida e RTY real | D22: Análise de dados / raio-X analítico | E22: Práticas de gerenciamento | F22: Gerencial (processo) | G22: Reclamações ≤ 3 por milhão de unidades (baseline 4,76) | H22: Novo | I22: Clientes de cosmética (marcas UE) | J22: Sem rota rastreável sopro → decoração → tampa → produto final; RTY hoje é proxy; parte das reclamações não liga a lote | K22: Método | L22: Contenção lenta, recall mais amplo que o necessário e custo de reclamação maior | M22: Qualidade / Cliente | N22: 4 | O22: 4 | P22: =IF(COUNT($N22:$O22)=2,$N22*$O22,"") -> 16 | Q22: =IF($P22="","",INDEX(Niveis,MAX(IFERROR(MATCH($P22,Limites,1),1),IF($O22=5,MinIdx,1)))) -> Crítico | R22: Rastreabilidade por LotId e ProductBatch; registro de ordem | S22: Baixa | T22: 3 | U22: 4 | V22: =IF(COUNT($T22:$U22)=2,$T22*$U22,"") -> 12 | W22: =IF($V22="","",INDEX(Niveis,MAX(IFERROR(MATCH($V22,Limites,1),1),IF($U22=5,MinIdx,1)))) -> Alto | X22: Média | Y22: =IF(IF($W22<>"",$W22,$Q22)="","",INDEX(AcaoRisco,MATCH(IF($W22<>"",$W22,$Q22),Niveis,0))) -> Mitigar | Z22: Mitigar | AA22: Controle de engenharia | AC22: Amarrar lote/unidade entre processos e ao pedido de venda, com taxonomia de reclamações (RC-14) | AD22: Gerente da Qualidade | AE22: Analista de Dados | AH22: ≥ 95% das reclamações rastreáveis a lote de origem e RTY físico medido | AI22: PAC 202620 | AJ22: =IF(OR($AI22="",PlanoUrl=""),"",HYPERLINK(SUBSTITUTE(PlanoUrl,"{COD}",SUBSTITUTE($AI22," ","%20")),"↗")) | AK22: =IF($C22="","",IF($AI22="",$AG22&"",IFERROR(IF(INDEX(PlanosStatus,MATCH($AI22,PlanosCod,0))="",$AG22&"",INDEX(PlanosStatus,MATCH($AI22,PlanosCod,0))),$AG22&""))) -> Aberto | AL22: =IF($C22="","",IF($AI22="",IF($AF22="","",$AF22),IFERROR(IF(INDEX(PlanosPrazo,MATCH($AI22,PlanosCod,0))="",IF($AF22="","",$AF22),INDEX(PlanosPrazo,MATCH($AI22,PlanosCod,0))),IF($AF22="","",$AF22)))) -> 46538 | AM22: 46568 | AP22: 2 | AQ22: 3 | AR22: =IF(COUNT($AP22:$AQ22)=2,$AP22*$AQ22,"") -> 6 | AS22: =IF($AR22="","",INDEX(Niveis,MAX(IFERROR(MATCH($AR22,Limites,1),1),IF($AQ22=5,MinIdx,1)))) -> Baixo | AT22: Sim | AW22: 46371 | AX22: Qualidade + Dados | AY22: =IF(OR($AW22="",IF(AND($AN22="Eficaz",$AS22<>""),$AS22,IF($W22<>"",$W22,$Q22))=""),"",EDATE($AW22,INDEX(MesesRev,MATCH(IF(AND($AN22="Eficaz",$AS22<>""),$AS22,IF($W22<>"",$W22,$Q22)),Niveis,0)))) -> 46461 | AZ22: =IF($C22="","",IF($AD22="","Sem dono",IF($W22="","Falta avaliação",IF(AND($AI22<>"",COUNTIF(PlanosCod,$AI22)=0),"Código não encontrado",IF(AND($AI22<>"",IFERROR(INDEX(PlanosIdRef,MATCH($AI22,PlanosCod,0))&"","")<>"",ISERROR(SEARCH(";"&$A22&";",";"&SUBSTITUTE(SUBSTITUTE(IFERROR(INDEX(PlanosIdRef,MATCH($AI22,PlanosCod,0))&"","")," ",""),",",";")&";"))),"Vínculo divergente",IF(AND(ISNUMBER($P22),ISNUMBER($V22),$V22<$P22,OR($S22="",$S22="Inexistente")),"Redução s/ controle",IF(AND(ISNUMBER($AR22),ISNUMBER($V22),$AR22<$V22,NOT(OR($Z22="Prevenir",$Z22="Mitigar",$Z22="Transferir / compartilhar")),$AC22="",$AI22=""),"Residual s/ tratamento",IF(AND(LEFT($AI22,3)="RNC",N(IFERROR(INDEX(PlanosAbertura,MATCH($AI22,PlanosCod,0)),0))>N($AW22)),"Reavaliar após RNC",IF(AND(N($AV22)>=1,ISNUMBER($T22),$T22<=2),"Recalibrar probabilidade",IF(AND($Z22="Aceitar",$BA22=""),"Aceite sem justificativa",IF(AND($Z22="Aceitar",ISNUMBER($AB22),$AB22<TODAY()),"Aceite vencido",IF(AND(OR($Z22="Aceitar",$Z22="Monitorar"),$Y22<>"Monitorar",$Y22<>""),"Aprovar aceite",IF(AND($Z22<>"Aceitar",$Z22<>"Monitorar",$Z22<>"Aprofundar análise",$AC22="",$AI22="",IFERROR(MATCH(IF($W22<>"",$W22,$Q22),Niveis,0),0)>IF(N(IFERROR(INDEX(ApetIdx,MATCH($M22,ListaCatRisco,0)),0))=0,IdxExige-1,INDEX(ApetIdx,MATCH($M22,ListaCatRisco,0)))),"Sem ação",IF($Z22="Aprofundar análise","Aprofundar análise",IF(AND(OR($Z22="Prevenir",$Z22="Mitigar",$Z22="Transferir / compartilhar"),$AH22=""),"Definir critério de eficácia",IF(AND(OR($Z22="Prevenir",$Z22="Mitigar",$Z22="Transferir / compartilhar"),OR($AA22="Controle administrativo",$AA22="EPI"),IFERROR(MATCH(IF($W22<>"",$W22,$Q22),Niveis,0),0)>=3),"Rever hierarquia de controle",IF(COUNTIFS(KriId,$A22,KriSit,"Estourou")+COUNTIFS(KriId,$A22,KriSit,"Atenção")>0,"KRI em alerta",IF(COUNTIFS(BtId,$A22,BtEf,"Baixa")+COUNTIFS(BtId,$A22,BtEf,"Inexistente")>0,"Barreira fraca",IF($AN22="Não eficaz","Ação ineficaz",IF(AND($AL22<>"",$AL22<TODAY(),$AK22<>"Concluído",$AK22<>"Cancelado"),"Ação vencida",IF(AND($AN22<>"Eficaz",OR($AK22="Concluído",AND(ISNUMBER($AM22),$AM22<TODAY()))),"Avaliar eficácia",IF(AND($AN22="Eficaz",OR($AS22="",$AT22="")),"Concluir residual",IF($AT22="Não","Tratamento adicional",IF(AND($AT22="Sim",$AS22<>"",IFERROR(MATCH($AS22,Niveis,0),0)>IF(N(IFERROR(INDEX(ApetIdx,MATCH($M22,ListaCatRisco,0)),0))=0,IdxExige-1,INDEX(ApetIdx,MATCH($M22,ListaCatRisco,0)))),"Aceite fora do apetite",IF(AND(COUNTIF(BtId,$A22)=0,OR(IFERROR(MATCH(IF($W22<>"",$W22,$Q22),Niveis,0),0)>=3,AND(OR($S22="Baixa",$S22="Inexistente"),IFERROR(MATCH(IF($W22<>"",$W22,$Q22),Niveis,0),0)>=2))),"Sem BowTie",IF(AND($AY22<>"",$AY22<TODAY()),"Revisão vencida",IF(AND($AL22<>"",N($AL22)-TODAY()<=DiasAlerta,$AK22<>"Concluído",$AK22<>"Cancelado"),"Vence em breve","OK"))))))))))))))))))))))))))) -> Barreira fraca | BA22: O RTY calculado é proxy/teórico; transformar em RTY operacional exige rastreabilidade consistente. | BB22: R16;R19 | BC22: =IF($V22="","",1+COUNTIF($V$5:$V$154,">"&$V22)+COUNTIFS($V$5:$V$154,$V22,$U$5:$U$154,">"&$U22)+COUNTIFS($V$4:$V21,$V22,$U$4:$U21,$U22)) -> 4 | BD22: Rápida — dias | BE22: Estável | BF22: Detectivo | BG22: 28000 | BH22: 60000 | BI22: =IF(OR($BH22="",$T22=""),"",IFERROR($BH22*INDEX(ProbMedia,$T22),"")) -> 30000 | BJ22: =IF(OR($BG22="",$BI22=""),"",IF(OR(LEFT($M22,3)="SST",LEFT($M22,5)="Legal",LEFT($M22,8)="Ambienta"),"SST/Ambiental/Legal: custo não justifica aceitar (apetite e ALARP)",IF($BG22>$BI22,"Custo maior que a perda esperada: reter/aceitar é defensável, com justificativa","Custo menor ou igual à perda esperada: tratar compensa"))) -> Custo menor ou igual à perda esperada: tratar compensa | BW22: =IF($BU22="","",IFERROR(INDEX(SgaProbValor,MATCH($BU22,SgaProbNivel,0)),"")) | BX22: =IF($BV22="","",IFERROR(INDEX(SgaSevRiValor,MATCH($BV22,SgaSevRiNivel,0)),"")) | BY22: =IF(COUNT($BW22:$BX22)=2,$BW22*$BX22,"") | BZ22: =IF($BY22="","",IF($BY22<=SgaLimRiSig,"SIGNIFICATIVO",IF($BY22<=SgaLimRiTol,"TOLERÁVEL","BAIXO"))) | CA22: =IF($BZ22="","",IF($BZ22="SIGNIFICATIVO","NÃO ACEITÁVEL","ACEITÁVEL")) | CG22: =IF(OR($CE22="",$CF22=""),"",IFERROR(INDEX(SgaProbValor,MATCH($CE22,SgaProbNivel,0))*INDEX(SgaSevRiValor,MATCH($CF22,SgaSevRiNivel,0)),"")) | CH22: =IF($CG22="","",IF($CG22<=SgaLimRiSig,"SIGNIFICATIVO",IF($CG22<=SgaLimRiTol,"TOLERÁVEL","BAIXO")))
A23: R19 | B23: Dados / TI | C23: Parâmetros críticos (velocidade, ciclos, pressão, temperatura) não são registrados na hora, impedindo detecção antecipada | D23: Análise de dados / raio-X analítico | E23: Técnico | F23: Gerencial (processo) | G23: Cpk ≥ 1,33 nas características críticas | H23: Novo | I23: Acionistas / Direção | J23: Parâmetros ocultos (velocidade de linha, ciclos desde setup/reforma) são inferidos retrospectivamente por proxy | K23: Medida | L23: Causas só descobertas após o lote falhar; indicador antecedente impossível; diagnóstico dependente de proxies | M23: Qualidade / Cliente | N23: 5 | O23: 3 | P23: =IF(COUNT($N23:$O23)=2,$N23*$O23,"") -> 15 | Q23: =IF($P23="","",INDEX(Niveis,MAX(IFERROR(MATCH($P23,Limites,1),1),IF($O23=5,MinIdx,1)))) -> Alto | R23: Registro parcial de parâmetros de injeção; proxy ActualCycleTimeSec | S23: Baixa | T23: 4 | U23: 3 | V23: =IF(COUNT($T23:$U23)=2,$T23*$U23,"") -> 12 | W23: =IF($V23="","",INDEX(Niveis,MAX(IFERROR(MATCH($V23,Limites,1),1),IF($U23=5,MinIdx,1)))) -> Alto | X23: Alta | Y23: =IF(IF($W23<>"",$W23,$Q23)="","",INDEX(AcaoRisco,MATCH(IF($W23<>"",$W23,$Q23),Niveis,0))) -> Mitigar | Z23: Mitigar | AA23: Controle de engenharia | AC23: Instrumentar velocidade, pressão e temperatura por ordem com timestamp e reset automático dos contadores (RC-13) | AD23: Gerente de Dados / TI | AE23: Analista de Dados | AH23: ≥ 90% das ordens com parâmetros críticos registrados e alarmes de limite ativos | AI23: PAC 202619 | AJ23: =IF(OR($AI23="",PlanoUrl=""),"",HYPERLINK(SUBSTITUTE(PlanoUrl,"{COD}",SUBSTITUTE($AI23," ","%20")),"↗")) | AK23: =IF($C23="","",IF($AI23="",$AG23&"",IFERROR(IF(INDEX(PlanosStatus,MATCH($AI23,PlanosCod,0))="",$AG23&"",INDEX(PlanosStatus,MATCH($AI23,PlanosCod,0))),$AG23&""))) -> Em andamento | AL23: =IF($C23="","",IF($AI23="",IF($AF23="","",$AF23),IFERROR(IF(INDEX(PlanosPrazo,MATCH($AI23,PlanosCod,0))="",IF($AF23="","",$AF23),INDEX(PlanosPrazo,MATCH($AI23,PlanosCod,0))),IF($AF23="","",$AF23)))) -> 46538 | AM23: 46568 | AP23: 2 | AQ23: 3 | AR23: =IF(COUNT($AP23:$AQ23)=2,$AP23*$AQ23,"") -> 6 | AS23: =IF($AR23="","",INDEX(Niveis,MAX(IFERROR(MATCH($AR23,Limites,1),1),IF($AQ23=5,MinIdx,1)))) -> Baixo | AT23: Sim | AU23: Cobertura de parâmetros críticos registrados (aba KRI) | AW23: 46371 | AX23: Dados + Processo | AY23: =IF(OR($AW23="",IF(AND($AN23="Eficaz",$AS23<>""),$AS23,IF($W23<>"",$W23,$Q23))=""),"",EDATE($AW23,INDEX(MesesRev,MATCH(IF(AND($AN23="Eficaz",$AS23<>""),$AS23,IF($W23<>"",$W23,$Q23)),Niveis,0)))) -> 46461 | AZ23: =IF($C23="","",IF($AD23="","Sem dono",IF($W23="","Falta avaliação",IF(AND($AI23<>"",COUNTIF(PlanosCod,$AI23)=0),"Código não encontrado",IF(AND($AI23<>"",IFERROR(INDEX(PlanosIdRef,MATCH($AI23,PlanosCod,0))&"","")<>"",ISERROR(SEARCH(";"&$A23&";",";"&SUBSTITUTE(SUBSTITUTE(IFERROR(INDEX(PlanosIdRef,MATCH($AI23,PlanosCod,0))&"","")," ",""),",",";")&";"))),"Vínculo divergente",IF(AND(ISNUMBER($P23),ISNUMBER($V23),$V23<$P23,OR($S23="",$S23="Inexistente")),"Redução s/ controle",IF(AND(ISNUMBER($AR23),ISNUMBER($V23),$AR23<$V23,NOT(OR($Z23="Prevenir",$Z23="Mitigar",$Z23="Transferir / compartilhar")),$AC23="",$AI23=""),"Residual s/ tratamento",IF(AND(LEFT($AI23,3)="RNC",N(IFERROR(INDEX(PlanosAbertura,MATCH($AI23,PlanosCod,0)),0))>N($AW23)),"Reavaliar após RNC",IF(AND(N($AV23)>=1,ISNUMBER($T23),$T23<=2),"Recalibrar probabilidade",IF(AND($Z23="Aceitar",$BA23=""),"Aceite sem justificativa",IF(AND($Z23="Aceitar",ISNUMBER($AB23),$AB23<TODAY()),"Aceite vencido",IF(AND(OR($Z23="Aceitar",$Z23="Monitorar"),$Y23<>"Monitorar",$Y23<>""),"Aprovar aceite",IF(AND($Z23<>"Aceitar",$Z23<>"Monitorar",$Z23<>"Aprofundar análise",$AC23="",$AI23="",IFERROR(MATCH(IF($W23<>"",$W23,$Q23),Niveis,0),0)>IF(N(IFERROR(INDEX(ApetIdx,MATCH($M23,ListaCatRisco,0)),0))=0,IdxExige-1,INDEX(ApetIdx,MATCH($M23,ListaCatRisco,0)))),"Sem ação",IF($Z23="Aprofundar análise","Aprofundar análise",IF(AND(OR($Z23="Prevenir",$Z23="Mitigar",$Z23="Transferir / compartilhar"),$AH23=""),"Definir critério de eficácia",IF(AND(OR($Z23="Prevenir",$Z23="Mitigar",$Z23="Transferir / compartilhar"),OR($AA23="Controle administrativo",$AA23="EPI"),IFERROR(MATCH(IF($W23<>"",$W23,$Q23),Niveis,0),0)>=3),"Rever hierarquia de controle",IF(COUNTIFS(KriId,$A23,KriSit,"Estourou")+COUNTIFS(KriId,$A23,KriSit,"Atenção")>0,"KRI em alerta",IF(COUNTIFS(BtId,$A23,BtEf,"Baixa")+COUNTIFS(BtId,$A23,BtEf,"Inexistente")>0,"Barreira fraca",IF($AN23="Não eficaz","Ação ineficaz",IF(AND($AL23<>"",$AL23<TODAY(),$AK23<>"Concluído",$AK23<>"Cancelado"),"Ação vencida",IF(AND($AN23<>"Eficaz",OR($AK23="Concluído",AND(ISNUMBER($AM23),$AM23<TODAY()))),"Avaliar eficácia",IF(AND($AN23="Eficaz",OR($AS23="",$AT23="")),"Concluir residual",IF($AT23="Não","Tratamento adicional",IF(AND($AT23="Sim",$AS23<>"",IFERROR(MATCH($AS23,Niveis,0),0)>IF(N(IFERROR(INDEX(ApetIdx,MATCH($M23,ListaCatRisco,0)),0))=0,IdxExige-1,INDEX(ApetIdx,MATCH($M23,ListaCatRisco,0)))),"Aceite fora do apetite",IF(AND(COUNTIF(BtId,$A23)=0,OR(IFERROR(MATCH(IF($W23<>"",$W23,$Q23),Niveis,0),0)>=3,AND(OR($S23="Baixa",$S23="Inexistente"),IFERROR(MATCH(IF($W23<>"",$W23,$Q23),Niveis,0),0)>=2))),"Sem BowTie",IF(AND($AY23<>"",$AY23<TODAY()),"Revisão vencida",IF(AND($AL23<>"",N($AL23)-TODAY()<=DiasAlerta,$AK23<>"Concluído",$AK23<>"Cancelado"),"Vence em breve","OK"))))))))))))))))))))))))))) -> KRI em alerta | BA23: Governança de dados: causa comum de R2, R4, R5, R8. Habilita dashboards e indicadores antecedentes. | BB23: R2;R4;R5;R8 | BC23: =IF($V23="","",1+COUNTIF($V$5:$V$154,">"&$V23)+COUNTIFS($V$5:$V$154,$V23,$U$5:$U$154,">"&$U23)+COUNTIFS($V$4:$V22,$V23,$U$4:$U22,$U23)) -> 14 | BD23: Lenta — meses | BE23: Estável | BF23: Preventivo | BG23: 45000 | BH23: 80000 | BI23: =IF(OR($BH23="",$T23=""),"",IFERROR($BH23*INDEX(ProbMedia,$T23),"")) -> 56000 | BJ23: =IF(OR($BG23="",$BI23=""),"",IF(OR(LEFT($M23,3)="SST",LEFT($M23,5)="Legal",LEFT($M23,8)="Ambienta"),"SST/Ambiental/Legal: custo não justifica aceitar (apetite e ALARP)",IF($BG23>$BI23,"Custo maior que a perda esperada: reter/aceitar é defensável, com justificativa","Custo menor ou igual à perda esperada: tratar compensa"))) -> Custo menor ou igual à perda esperada: tratar compensa | BW23: =IF($BU23="","",IFERROR(INDEX(SgaProbValor,MATCH($BU23,SgaProbNivel,0)),"")) | BX23: =IF($BV23="","",IFERROR(INDEX(SgaSevRiValor,MATCH($BV23,SgaSevRiNivel,0)),"")) | BY23: =IF(COUNT($BW23:$BX23)=2,$BW23*$BX23,"") | BZ23: =IF($BY23="","",IF($BY23<=SgaLimRiSig,"SIGNIFICATIVO",IF($BY23<=SgaLimRiTol,"TOLERÁVEL","BAIXO"))) | CA23: =IF($BZ23="","",IF($BZ23="SIGNIFICATIVO","NÃO ACEITÁVEL","ACEITÁVEL")) | CG23: =IF(OR($CE23="",$CF23=""),"",IFERROR(INDEX(SgaProbValor,MATCH($CE23,SgaProbNivel,0))*INDEX(SgaSevRiValor,MATCH($CF23,SgaSevRiNivel,0)),"")) | CH23: =IF($CG23="","",IF($CG23<=SgaLimRiSig,"SIGNIFICATIVO",IF($CG23<=SgaLimRiTol,"TOLERÁVEL","BAIXO")))
A24: R20 | B24: Qualidade | C24: Backlog de CAPAs vencidas e baixa eficácia (31% não eficazes) permitem recorrência das não conformidades | D24: Auditoria de riscos | E24: Práticas de gerenciamento | F24: Gerencial (processo) | G24: CAPAs vencidas ≤ 15% do total aberto | H24: Novo | I24: Clientes de cosmética (marcas UE) | J24: Sem priorização por risco, prazos irrealistas e verificação de eficácia não exigida antes do fechamento | K24: Método | L24: 187 CAPAs vencidas (23% das 811); 253 não eficazes e 258 com eficácia pendente; recorrência de NC e achados de auditoria | M24: Qualidade / Cliente | N24: 5 | O24: 3 | P24: =IF(COUNT($N24:$O24)=2,$N24*$O24,"") -> 15 | Q24: =IF($P24="","",INDEX(Niveis,MAX(IFERROR(MATCH($P24,Limites,1),1),IF($O24=5,MinIdx,1)))) -> Alto | R24: Registro de CAPA com prazo e responsável; revisão mensal | S24: Baixa | T24: 5 | U24: 3 | V24: =IF(COUNT($T24:$U24)=2,$T24*$U24,"") -> 15 | W24: =IF($V24="","",INDEX(Niveis,MAX(IFERROR(MATCH($V24,Limites,1),1),IF($U24=5,MinIdx,1)))) -> Alto | X24: Alta | Y24: =IF(IF($W24<>"",$W24,$Q24)="","",INDEX(AcaoRisco,MATCH(IF($W24<>"",$W24,$Q24),Niveis,0))) -> Mitigar | Z24: Mitigar | AA24: Controle administrativo | AC24: Mutirão de fechamento, priorização por severidade e regra: nenhuma CAPA encerra sem verificação de eficácia | AD24: Gerente da Qualidade | AE24: Coordenação do SGI | AH24: CAPAs vencidas ≤ 15% do total aberto e ≥ 80% das encerradas com eficácia verificada | AI24: PAC 202622 | AJ24: =IF(OR($AI24="",PlanoUrl=""),"",HYPERLINK(SUBSTITUTE(PlanoUrl,"{COD}",SUBSTITUTE($AI24," ","%20")),"↗")) | AK24: =IF($C24="","",IF($AI24="",$AG24&"",IFERROR(IF(INDEX(PlanosStatus,MATCH($AI24,PlanosCod,0))="",$AG24&"",INDEX(PlanosStatus,MATCH($AI24,PlanosCod,0))),$AG24&""))) -> Em andamento | AL24: =IF($C24="","",IF($AI24="",IF($AF24="","",$AF24),IFERROR(IF(INDEX(PlanosPrazo,MATCH($AI24,PlanosCod,0))="",IF($AF24="","",$AF24),INDEX(PlanosPrazo,MATCH($AI24,PlanosCod,0))),IF($AF24="","",$AF24)))) -> 46477 | AM24: 46568 | AP24: 3 | AQ24: 3 | AR24: =IF(COUNT($AP24:$AQ24)=2,$AP24*$AQ24,"") -> 9 | AS24: =IF($AR24="","",INDEX(Niveis,MAX(IFERROR(MATCH($AR24,Limites,1),1),IF($AQ24=5,MinIdx,1)))) -> Médio | AT24: Sim | AU24: CAPAs vencidas em aberto no fim do mês (aba KRI) | AV24: 126 | AW24: 46371 | AX24: Comitê da Qualidade | AY24: =IF(OR($AW24="",IF(AND($AN24="Eficaz",$AS24<>""),$AS24,IF($W24<>"",$W24,$Q24))=""),"",EDATE($AW24,INDEX(MesesRev,MATCH(IF(AND($AN24="Eficaz",$AS24<>""),$AS24,IF($W24<>"",$W24,$Q24)),Niveis,0)))) -> 46461 | AZ24: =IF($C24="","",IF($AD24="","Sem dono",IF($W24="","Falta avaliação",IF(AND($AI24<>"",COUNTIF(PlanosCod,$AI24)=0),"Código não encontrado",IF(AND($AI24<>"",IFERROR(INDEX(PlanosIdRef,MATCH($AI24,PlanosCod,0))&"","")<>"",ISERROR(SEARCH(";"&$A24&";",";"&SUBSTITUTE(SUBSTITUTE(IFERROR(INDEX(PlanosIdRef,MATCH($AI24,PlanosCod,0))&"","")," ",""),",",";")&";"))),"Vínculo divergente",IF(AND(ISNUMBER($P24),ISNUMBER($V24),$V24<$P24,OR($S24="",$S24="Inexistente")),"Redução s/ controle",IF(AND(ISNUMBER($AR24),ISNUMBER($V24),$AR24<$V24,NOT(OR($Z24="Prevenir",$Z24="Mitigar",$Z24="Transferir / compartilhar")),$AC24="",$AI24=""),"Residual s/ tratamento",IF(AND(LEFT($AI24,3)="RNC",N(IFERROR(INDEX(PlanosAbertura,MATCH($AI24,PlanosCod,0)),0))>N($AW24)),"Reavaliar após RNC",IF(AND(N($AV24)>=1,ISNUMBER($T24),$T24<=2),"Recalibrar probabilidade",IF(AND($Z24="Aceitar",$BA24=""),"Aceite sem justificativa",IF(AND($Z24="Aceitar",ISNUMBER($AB24),$AB24<TODAY()),"Aceite vencido",IF(AND(OR($Z24="Aceitar",$Z24="Monitorar"),$Y24<>"Monitorar",$Y24<>""),"Aprovar aceite",IF(AND($Z24<>"Aceitar",$Z24<>"Monitorar",$Z24<>"Aprofundar análise",$AC24="",$AI24="",IFERROR(MATCH(IF($W24<>"",$W24,$Q24),Niveis,0),0)>IF(N(IFERROR(INDEX(ApetIdx,MATCH($M24,ListaCatRisco,0)),0))=0,IdxExige-1,INDEX(ApetIdx,MATCH($M24,ListaCatRisco,0)))),"Sem ação",IF($Z24="Aprofundar análise","Aprofundar análise",IF(AND(OR($Z24="Prevenir",$Z24="Mitigar",$Z24="Transferir / compartilhar"),$AH24=""),"Definir critério de eficácia",IF(AND(OR($Z24="Prevenir",$Z24="Mitigar",$Z24="Transferir / compartilhar"),OR($AA24="Controle administrativo",$AA24="EPI"),IFERROR(MATCH(IF($W24<>"",$W24,$Q24),Niveis,0),0)>=3),"Rever hierarquia de controle",IF(COUNTIFS(KriId,$A24,KriSit,"Estourou")+COUNTIFS(KriId,$A24,KriSit,"Atenção")>0,"KRI em alerta",IF(COUNTIFS(BtId,$A24,BtEf,"Baixa")+COUNTIFS(BtId,$A24,BtEf,"Inexistente")>0,"Barreira fraca",IF($AN24="Não eficaz","Ação ineficaz",IF(AND($AL24<>"",$AL24<TODAY(),$AK24<>"Concluído",$AK24<>"Cancelado"),"Ação vencida",IF(AND($AN24<>"Eficaz",OR($AK24="Concluído",AND(ISNUMBER($AM24),$AM24<TODAY()))),"Avaliar eficácia",IF(AND($AN24="Eficaz",OR($AS24="",$AT24="")),"Concluir residual",IF($AT24="Não","Tratamento adicional",IF(AND($AT24="Sim",$AS24<>"",IFERROR(MATCH($AS24,Niveis,0),0)>IF(N(IFERROR(INDEX(ApetIdx,MATCH($M24,ListaCatRisco,0)),0))=0,IdxExige-1,INDEX(ApetIdx,MATCH($M24,ListaCatRisco,0)))),"Aceite fora do apetite",IF(AND(COUNTIF(BtId,$A24)=0,OR(IFERROR(MATCH(IF($W24<>"",$W24,$Q24),Niveis,0),0)>=3,AND(OR($S24="Baixa",$S24="Inexistente"),IFERROR(MATCH(IF($W24<>"",$W24,$Q24),Niveis,0),0)>=2))),"Sem BowTie",IF(AND($AY24<>"",$AY24<TODAY()),"Revisão vencida",IF(AND($AL24<>"",N($AL24)-TODAY()<=DiasAlerta,$AK24<>"Concluído",$AK24<>"Cancelado"),"Vence em breve","OK"))))))))))))))))))))))))))) -> Rever hierarquia de controle | BA24: CAPAs vencidas em aberto crescem a cada mês (132 → 191 de jul a dez/2026). Hierarquia é administrativa por natureza do risco; risco de reincidência exige BowTie. | BB24: R16 | BC24: =IF($V24="","",1+COUNTIF($V$5:$V$154,">"&$V24)+COUNTIFS($V$5:$V$154,$V24,$U$5:$U$154,">"&$U24)+COUNTIFS($V$4:$V23,$V24,$U$4:$U23,$U24)) -> 2 | BD24: Lenta — meses | BE24: Moderada | BF24: Corretivo | BG24: 12000 | BH24: 40000 | BI24: =IF(OR($BH24="",$T24=""),"",IFERROR($BH24*INDEX(ProbMedia,$T24),"")) -> 36000 | BJ24: =IF(OR($BG24="",$BI24=""),"",IF(OR(LEFT($M24,3)="SST",LEFT($M24,5)="Legal",LEFT($M24,8)="Ambienta"),"SST/Ambiental/Legal: custo não justifica aceitar (apetite e ALARP)",IF($BG24>$BI24,"Custo maior que a perda esperada: reter/aceitar é defensável, com justificativa","Custo menor ou igual à perda esperada: tratar compensa"))) -> Custo menor ou igual à perda esperada: tratar compensa | BW24: =IF($BU24="","",IFERROR(INDEX(SgaProbValor,MATCH($BU24,SgaProbNivel,0)),"")) | BX24: =IF($BV24="","",IFERROR(INDEX(SgaSevRiValor,MATCH($BV24,SgaSevRiNivel,0)),"")) | BY24: =IF(COUNT($BW24:$BX24)=2,$BW24*$BX24,"") | BZ24: =IF($BY24="","",IF($BY24<=SgaLimRiSig,"SIGNIFICATIVO",IF($BY24<=SgaLimRiTol,"TOLERÁVEL","BAIXO"))) | CA24: =IF($BZ24="","",IF($BZ24="SIGNIFICATIVO","NÃO ACEITÁVEL","ACEITÁVEL")) | CG24: =IF(OR($CE24="",$CF24=""),"",IFERROR(INDEX(SgaProbValor,MATCH($CE24,SgaProbNivel,0))*INDEX(SgaSevRiValor,MATCH($CF24,SgaSevRiNivel,0)),"")) | CH24: =IF($CG24="","",IF($CG24<=SgaLimRiSig,"SIGNIFICATIVO",IF($CG24<=SgaLimRiTol,"TOLERÁVEL","BAIXO")))
A25: R21 | B25: Logística / Expedição | C25: Falhas logísticas (atraso, quantidade menor, produto errado) geram reclamações de cliente sem relação com a qualidade do produto | D25: RNC / reclamação | E25: Práticas de gerenciamento | F25: Operacional | G25: Reclamações ≤ 3 por milhão de unidades (baseline 4,76) | H25: Novo | I25: Clientes de cosmética (marcas UE) | J25: Conferência de expedição e planejamento de carga insuficientes; falta de confirmação do pedido antes do envio | K25: Método | L25: ≈ 37% das reclamações (atraso, falta de quantidade e produto errado) e custo de atendimento | M25: Qualidade / Cliente | N25: 4 | O25: 2 | P25: =IF(COUNT($N25:$O25)=2,$N25*$O25,"") -> 8 | Q25: =IF($P25="","",INDEX(Niveis,MAX(IFERROR(MATCH($P25,Limites,1),1),IF($O25=5,MinIdx,1)))) -> Médio | R25: Conferência manual da expedição; acompanhamento de pedidos | S25: Média | T25: 4 | U25: 2 | V25: =IF(COUNT($T25:$U25)=2,$T25*$U25,"") -> 8 | W25: =IF($V25="","",INDEX(Niveis,MAX(IFERROR(MATCH($V25,Limites,1),1),IF($U25=5,MinIdx,1)))) -> Médio | X25: Alta | Y25: =IF(IF($W25<>"",$W25,$Q25)="","",INDEX(AcaoRisco,MATCH(IF($W25<>"",$W25,$Q25),Niveis,0))) -> Mitigar | Z25: Mitigar | AA25: Controle administrativo | AC25: Conferência por leitura de código na expedição e checklist de carga; acompanhar OTIF | AD25: Gerente de Logística | AE25: Coordenador de Expedição | AF25: 46477 | AG25: Aberto | AH25: Reclamações logísticas ≤ 2 por mês | AJ25: =IF(OR($AI25="",PlanoUrl=""),"",HYPERLINK(SUBSTITUTE(PlanoUrl,"{COD}",SUBSTITUTE($AI25," ","%20")),"↗")) | AK25: =IF($C25="","",IF($AI25="",$AG25&"",IFERROR(IF(INDEX(PlanosStatus,MATCH($AI25,PlanosCod,0))="",$AG25&"",INDEX(PlanosStatus,MATCH($AI25,PlanosCod,0))),$AG25&""))) -> Aberto | AL25: =IF($C25="","",IF($AI25="",IF($AF25="","",$AF25),IFERROR(IF(INDEX(PlanosPrazo,MATCH($AI25,PlanosCod,0))="",IF($AF25="","",$AF25),INDEX(PlanosPrazo,MATCH($AI25,PlanosCod,0))),IF($AF25="","",$AF25)))) -> 46477 | AP25: 3 | AQ25: 2 | AR25: =IF(COUNT($AP25:$AQ25)=2,$AP25*$AQ25,"") -> 6 | AS25: =IF($AR25="","",INDEX(Niveis,MAX(IFERROR(MATCH($AR25,Limites,1),1),IF($AQ25=5,MinIdx,1)))) -> Baixo | AT25: Sim | AU25: Reclamações logísticas/mês (aba KRI) | AV25: 50 | AW25: 46371 | AX25: Logística | AY25: =IF(OR($AW25="",IF(AND($AN25="Eficaz",$AS25<>""),$AS25,IF($W25<>"",$W25,$Q25))=""),"",EDATE($AW25,INDEX(MesesRev,MATCH(IF(AND($AN25="Eficaz",$AS25<>""),$AS25,IF($W25<>"",$W25,$Q25)),Niveis,0)))) -> 46553 | AZ25: =IF($C25="","",IF($AD25="","Sem dono",IF($W25="","Falta avaliação",IF(AND($AI25<>"",COUNTIF(PlanosCod,$AI25)=0),"Código não encontrado",IF(AND($AI25<>"",IFERROR(INDEX(PlanosIdRef,MATCH($AI25,PlanosCod,0))&"","")<>"",ISERROR(SEARCH(";"&$A25&";",";"&SUBSTITUTE(SUBSTITUTE(IFERROR(INDEX(PlanosIdRef,MATCH($AI25,PlanosCod,0))&"","")," ",""),",",";")&";"))),"Vínculo divergente",IF(AND(ISNUMBER($P25),ISNUMBER($V25),$V25<$P25,OR($S25="",$S25="Inexistente")),"Redução s/ controle",IF(AND(ISNUMBER($AR25),ISNUMBER($V25),$AR25<$V25,NOT(OR($Z25="Prevenir",$Z25="Mitigar",$Z25="Transferir / compartilhar")),$AC25="",$AI25=""),"Residual s/ tratamento",IF(AND(LEFT($AI25,3)="RNC",N(IFERROR(INDEX(PlanosAbertura,MATCH($AI25,PlanosCod,0)),0))>N($AW25)),"Reavaliar após RNC",IF(AND(N($AV25)>=1,ISNUMBER($T25),$T25<=2),"Recalibrar probabilidade",IF(AND($Z25="Aceitar",$BA25=""),"Aceite sem justificativa",IF(AND($Z25="Aceitar",ISNUMBER($AB25),$AB25<TODAY()),"Aceite vencido",IF(AND(OR($Z25="Aceitar",$Z25="Monitorar"),$Y25<>"Monitorar",$Y25<>""),"Aprovar aceite",IF(AND($Z25<>"Aceitar",$Z25<>"Monitorar",$Z25<>"Aprofundar análise",$AC25="",$AI25="",IFERROR(MATCH(IF($W25<>"",$W25,$Q25),Niveis,0),0)>IF(N(IFERROR(INDEX(ApetIdx,MATCH($M25,ListaCatRisco,0)),0))=0,IdxExige-1,INDEX(ApetIdx,MATCH($M25,ListaCatRisco,0)))),"Sem ação",IF($Z25="Aprofundar análise","Aprofundar análise",IF(AND(OR($Z25="Prevenir",$Z25="Mitigar",$Z25="Transferir / compartilhar"),$AH25=""),"Definir critério de eficácia",IF(AND(OR($Z25="Prevenir",$Z25="Mitigar",$Z25="Transferir / compartilhar"),OR($AA25="Controle administrativo",$AA25="EPI"),IFERROR(MATCH(IF($W25<>"",$W25,$Q25),Niveis,0),0)>=3),"Rever hierarquia de controle",IF(COUNTIFS(KriId,$A25,KriSit,"Estourou")+COUNTIFS(KriId,$A25,KriSit,"Atenção")>0,"KRI em alerta",IF(COUNTIFS(BtId,$A25,BtEf,"Baixa")+COUNTIFS(BtId,$A25,BtEf,"Inexistente")>0,"Barreira fraca",IF($AN25="Não eficaz","Ação ineficaz",IF(AND($AL25<>"",$AL25<TODAY(),$AK25<>"Concluído",$AK25<>"Cancelado"),"Ação vencida",IF(AND($AN25<>"Eficaz",OR($AK25="Concluído",AND(ISNUMBER($AM25),$AM25<TODAY()))),"Avaliar eficácia",IF(AND($AN25="Eficaz",OR($AS25="",$AT25="")),"Concluir residual",IF($AT25="Não","Tratamento adicional",IF(AND($AT25="Sim",$AS25<>"",IFERROR(MATCH($AS25,Niveis,0),0)>IF(N(IFERROR(INDEX(ApetIdx,MATCH($M25,ListaCatRisco,0)),0))=0,IdxExige-1,INDEX(ApetIdx,MATCH($M25,ListaCatRisco,0)))),"Aceite fora do apetite",IF(AND(COUNTIF(BtId,$A25)=0,OR(IFERROR(MATCH(IF($W25<>"",$W25,$Q25),Niveis,0),0)>=3,AND(OR($S25="Baixa",$S25="Inexistente"),IFERROR(MATCH(IF($W25<>"",$W25,$Q25),Niveis,0),0)>=2))),"Sem BowTie",IF(AND($AY25<>"",$AY25<TODAY()),"Revisão vencida",IF(AND($AL25<>"",N($AL25)-TODAY()<=DiasAlerta,$AK25<>"Concluído",$AK25<>"Cancelado"),"Vence em breve","OK"))))))))))))))))))))))))))) -> KRI em alerta | BA25: Metade das reclamações é logística/independente (dados): sem sinal interno de qualidade — tratar com taxonomia própria. | BB25: R16 | BC25: =IF($V25="","",1+COUNTIF($V$5:$V$154,">"&$V25)+COUNTIFS($V$5:$V$154,$V25,$U$5:$U$154,">"&$U25)+COUNTIFS($V$4:$V24,$V25,$U$4:$U24,$U25)) -> 36 | BD25: Rápida — dias | BE25: Moderada | BF25: Preventivo | BG25: 7000 | BH25: 15000 | BI25: =IF(OR($BH25="",$T25=""),"",IFERROR($BH25*INDEX(ProbMedia,$T25),"")) -> 10500 | BJ25: =IF(OR($BG25="",$BI25=""),"",IF(OR(LEFT($M25,3)="SST",LEFT($M25,5)="Legal",LEFT($M25,8)="Ambienta"),"SST/Ambiental/Legal: custo não justifica aceitar (apetite e ALARP)",IF($BG25>$BI25,"Custo maior que a perda esperada: reter/aceitar é defensável, com justificativa","Custo menor ou igual à perda esperada: tratar compensa"))) -> Custo menor ou igual à perda esperada: tratar compensa | BW25: =IF($BU25="","",IFERROR(INDEX(SgaProbValor,MATCH($BU25,SgaProbNivel,0)),"")) | BX25: =IF($BV25="","",IFERROR(INDEX(SgaSevRiValor,MATCH($BV25,SgaSevRiNivel,0)),"")) | BY25: =IF(COUNT($BW25:$BX25)=2,$BW25*$BX25,"") | BZ25: =IF($BY25="","",IF($BY25<=SgaLimRiSig,"SIGNIFICATIVO",IF($BY25<=SgaLimRiTol,"TOLERÁVEL","BAIXO"))) | CA25: =IF($BZ25="","",IF($BZ25="SIGNIFICATIVO","NÃO ACEITÁVEL","ACEITÁVEL")) | CG25: =IF(OR($CE25="",$CF25=""),"",IFERROR(INDEX(SgaProbValor,MATCH($CE25,SgaProbNivel,0))*INDEX(SgaSevRiValor,MATCH($CF25,SgaSevRiNivel,0)),"")) | CH25: =IF($CG25="","",IF($CG25<=SgaLimRiSig,"SIGNIFICATIVO",IF($CG25<=SgaLimRiTol,"TOLERÁVEL","BAIXO")))
A26: R22 | B26: Utilidades (energia, água, ar) | C26: Falta de ar comprimido interrompe máquinas de injeção, sopro e decoração | D26: Monitoramento de itens críticos | E26: Técnico | F26: Operacional | G26: OEE ≥ 81,1% e Disponibilidade ≥ 90% (baseline 79,1% / 87,4%) | H26: Novo | I26: Acionistas / Direção | J26: Compressores no limite, vazamentos na rede e sem monitoramento de pressão | K26: Máquina | L26: ≈ 2 580 h de parada em 18 meses (≈ 143 h/mês), perda de disponibilidade e custo de energia | M26: Produção / Ativos | N26: 4 | O26: 3 | P26: =IF(COUNT($N26:$O26)=2,$N26*$O26,"") -> 12 | Q26: =IF($P26="","",INDEX(Niveis,MAX(IFERROR(MATCH($P26,Limites,1),1),IF($O26=5,MinIdx,1)))) -> Alto | R26: Manutenção dos compressores; inspeção visual | S26: Baixa | T26: 4 | U26: 3 | V26: =IF(COUNT($T26:$U26)=2,$T26*$U26,"") -> 12 | W26: =IF($V26="","",INDEX(Niveis,MAX(IFERROR(MATCH($V26,Limites,1),1),IF($U26=5,MinIdx,1)))) -> Alto | X26: Alta | Y26: =IF(IF($W26<>"",$W26,$Q26)="","",INDEX(AcaoRisco,MATCH(IF($W26<>"",$W26,$Q26),Niveis,0))) -> Mitigar | Z26: Mitigar | AA26: Controle de engenharia | AC26: Ações no PAM (RG-SGA-06): PAM-26-01. Detecção de vazamentos, monitoramento de pressão com alarme e avaliação de redundância de compressor | AD26: Gerente de Manutenção | AE26: Eng. de Manutenção | AF26: 46387 | AG26: Em andamento | AH26: Paradas por ar comprimido ≤ 90 h/mês | AJ26: =IF(OR($AI26="",PlanoUrl=""),"",HYPERLINK(SUBSTITUTE(PlanoUrl,"{COD}",SUBSTITUTE($AI26," ","%20")),"↗")) | AK26: =IF($C26="","",IF($AI26="",$AG26&"",IFERROR(IF(INDEX(PlanosStatus,MATCH($AI26,PlanosCod,0))="",$AG26&"",INDEX(PlanosStatus,MATCH($AI26,PlanosCod,0))),$AG26&""))) -> Em andamento | AL26: =IF($C26="","",IF($AI26="",IF($AF26="","",$AF26),IFERROR(IF(INDEX(PlanosPrazo,MATCH($AI26,PlanosCod,0))="",IF($AF26="","",$AF26),INDEX(PlanosPrazo,MATCH($AI26,PlanosCod,0))),IF($AF26="","",$AF26)))) -> 46387 | AM26: 46568 | AP26: 3 | AQ26: 2 | AR26: =IF(COUNT($AP26:$AQ26)=2,$AP26*$AQ26,"") -> 6 | AS26: =IF($AR26="","",INDEX(Niveis,MAX(IFERROR(MATCH($AR26,Limites,1),1),IF($AQ26=5,MinIdx,1)))) -> Baixo | AT26: Sim | AU26: Horas de parada por falta de ar comprimido/mês (aba KRI) | AV26: 1053 | AW26: 46371 | AX26: Manutenção | AY26: =IF(OR($AW26="",IF(AND($AN26="Eficaz",$AS26<>""),$AS26,IF($W26<>"",$W26,$Q26))=""),"",EDATE($AW26,INDEX(MesesRev,MATCH(IF(AND($AN26="Eficaz",$AS26<>""),$AS26,IF($W26<>"",$W26,$Q26)),Niveis,0)))) -> 46461 | AZ26: =IF($C26="","",IF($AD26="","Sem dono",IF($W26="","Falta avaliação",IF(AND($AI26<>"",COUNTIF(PlanosCod,$AI26)=0),"Código não encontrado",IF(AND($AI26<>"",IFERROR(INDEX(PlanosIdRef,MATCH($AI26,PlanosCod,0))&"","")<>"",ISERROR(SEARCH(";"&$A26&";",";"&SUBSTITUTE(SUBSTITUTE(IFERROR(INDEX(PlanosIdRef,MATCH($AI26,PlanosCod,0))&"","")," ",""),",",";")&";"))),"Vínculo divergente",IF(AND(ISNUMBER($P26),ISNUMBER($V26),$V26<$P26,OR($S26="",$S26="Inexistente")),"Redução s/ controle",IF(AND(ISNUMBER($AR26),ISNUMBER($V26),$AR26<$V26,NOT(OR($Z26="Prevenir",$Z26="Mitigar",$Z26="Transferir / compartilhar")),$AC26="",$AI26=""),"Residual s/ tratamento",IF(AND(LEFT($AI26,3)="RNC",N(IFERROR(INDEX(PlanosAbertura,MATCH($AI26,PlanosCod,0)),0))>N($AW26)),"Reavaliar após RNC",IF(AND(N($AV26)>=1,ISNUMBER($T26),$T26<=2),"Recalibrar probabilidade",IF(AND($Z26="Aceitar",$BA26=""),"Aceite sem justificativa",IF(AND($Z26="Aceitar",ISNUMBER($AB26),$AB26<TODAY()),"Aceite vencido",IF(AND(OR($Z26="Aceitar",$Z26="Monitorar"),$Y26<>"Monitorar",$Y26<>""),"Aprovar aceite",IF(AND($Z26<>"Aceitar",$Z26<>"Monitorar",$Z26<>"Aprofundar análise",$AC26="",$AI26="",IFERROR(MATCH(IF($W26<>"",$W26,$Q26),Niveis,0),0)>IF(N(IFERROR(INDEX(ApetIdx,MATCH($M26,ListaCatRisco,0)),0))=0,IdxExige-1,INDEX(ApetIdx,MATCH($M26,ListaCatRisco,0)))),"Sem ação",IF($Z26="Aprofundar análise","Aprofundar análise",IF(AND(OR($Z26="Prevenir",$Z26="Mitigar",$Z26="Transferir / compartilhar"),$AH26=""),"Definir critério de eficácia",IF(AND(OR($Z26="Prevenir",$Z26="Mitigar",$Z26="Transferir / compartilhar"),OR($AA26="Controle administrativo",$AA26="EPI"),IFERROR(MATCH(IF($W26<>"",$W26,$Q26),Niveis,0),0)>=3),"Rever hierarquia de controle",IF(COUNTIFS(KriId,$A26,KriSit,"Estourou")+COUNTIFS(KriId,$A26,KriSit,"Atenção")>0,"KRI em alerta",IF(COUNTIFS(BtId,$A26,BtEf,"Baixa")+COUNTIFS(BtId,$A26,BtEf,"Inexistente")>0,"Barreira fraca",IF($AN26="Não eficaz","Ação ineficaz",IF(AND($AL26<>"",$AL26<TODAY(),$AK26<>"Concluído",$AK26<>"Cancelado"),"Ação vencida",IF(AND($AN26<>"Eficaz",OR($AK26="Concluído",AND(ISNUMBER($AM26),$AM26<TODAY()))),"Avaliar eficácia",IF(AND($AN26="Eficaz",OR($AS26="",$AT26="")),"Concluir residual",IF($AT26="Não","Tratamento adicional",IF(AND($AT26="Sim",$AS26<>"",IFERROR(MATCH($AS26,Niveis,0),0)>IF(N(IFERROR(INDEX(ApetIdx,MATCH($M26,ListaCatRisco,0)),0))=0,IdxExige-1,INDEX(ApetIdx,MATCH($M26,ListaCatRisco,0)))),"Aceite fora do apetite",IF(AND(COUNTIF(BtId,$A26)=0,OR(IFERROR(MATCH(IF($W26<>"",$W26,$Q26),Niveis,0),0)>=3,AND(OR($S26="Baixa",$S26="Inexistente"),IFERROR(MATCH(IF($W26<>"",$W26,$Q26),Niveis,0),0)>=2))),"Sem BowTie",IF(AND($AY26<>"",$AY26<TODAY()),"Revisão vencida",IF(AND($AL26<>"",N($AL26)-TODAY()<=DiasAlerta,$AK26<>"Concluído",$AK26<>"Cancelado"),"Vence em breve","OK"))))))))))))))))))))))))))) -> KRI em alerta | BA26: O SGA identifica ar comprimido como consumo energético indireto relevante; benefício duplo (disponibilidade e energia). | BB26: O6;R3 | BC26: =IF($V26="","",1+COUNTIF($V$5:$V$154,">"&$V26)+COUNTIFS($V$5:$V$154,$V26,$U$5:$U$154,">"&$U26)+COUNTIFS($V$4:$V25,$V26,$U$4:$U25,$U26)) -> 15 | BD26: Imediata — horas | BE26: Moderada | BF26: Preventivo | BG26: 38000 | BH26: 70000 | BI26: =IF(OR($BH26="",$T26=""),"",IFERROR($BH26*INDEX(ProbMedia,$T26),"")) -> 49000 | BJ26: =IF(OR($BG26="",$BI26=""),"",IF(OR(LEFT($M26,3)="SST",LEFT($M26,5)="Legal",LEFT($M26,8)="Ambienta"),"SST/Ambiental/Legal: custo não justifica aceitar (apetite e ALARP)",IF($BG26>$BI26,"Custo maior que a perda esperada: reter/aceitar é defensável, com justificativa","Custo menor ou igual à perda esperada: tratar compensa"))) -> Custo menor ou igual à perda esperada: tratar compensa | BK26: 4 | BL26: PCN-UTIL-01 (compressor reserva) | BW26: =IF($BU26="","",IFERROR(INDEX(SgaProbValor,MATCH($BU26,SgaProbNivel,0)),"")) | BX26: =IF($BV26="","",IFERROR(INDEX(SgaSevRiValor,MATCH($BV26,SgaSevRiNivel,0)),"")) | BY26: =IF(COUNT($BW26:$BX26)=2,$BW26*$BX26,"") | BZ26: =IF($BY26="","",IF($BY26<=SgaLimRiSig,"SIGNIFICATIVO",IF($BY26<=SgaLimRiTol,"TOLERÁVEL","BAIXO"))) | CA26: =IF($BZ26="","",IF($BZ26="SIGNIFICATIVO","NÃO ACEITÁVEL","ACEITÁVEL")) | CD26: PAM-26-01 | CG26: =IF(OR($CE26="",$CF26=""),"",IFERROR(INDEX(SgaProbValor,MATCH($CE26,SgaProbNivel,0))*INDEX(SgaSevRiValor,MATCH($CF26,SgaSevRiNivel,0)),"")) | CH26: =IF($CG26="","",IF($CG26<=SgaLimRiSig,"SIGNIFICATIVO",IF($CG26<=SgaLimRiTol,"TOLERÁVEL","BAIXO")))
A27: R23 | B27: Recursos Humanos | C27: Indisponibilidade de operadores (maior causa de parada não planejada) reduz a utilização das máquinas | D27: Monitoramento de itens críticos | E27: Organizacional | F27: Gerencial (processo) | G27: OEE ≥ 81,1% e Disponibilidade ≥ 90% (baseline 79,1% / 87,4%) | H27: Novo | I27: Colaboradores | J27: Escala rígida, absentismo, baixa polivalência e turnos com cobertura mínima | K27: Mão de obra | L27: ≈ 3 606 h de parada em 18 meses (≈ 200 h/mês) — a maior causa isolada de parada | M27: Produção / Ativos | N27: 5 | O27: 3 | P27: =IF(COUNT($N27:$O27)=2,$N27*$O27,"") -> 15 | Q27: =IF($P27="","",INDEX(Niveis,MAX(IFERROR(MATCH($P27,Limites,1),1),IF($O27=5,MinIdx,1)))) -> Alto | R27: Banco de horas; cobertura por supervisor | S27: Baixa | T27: 4 | U27: 3 | V27: =IF(COUNT($T27:$U27)=2,$T27*$U27,"") -> 12 | W27: =IF($V27="","",INDEX(Niveis,MAX(IFERROR(MATCH($V27,Limites,1),1),IF($U27=5,MinIdx,1)))) -> Alto | X27: Alta | Y27: =IF(IF($W27<>"",$W27,$Q27)="","",INDEX(AcaoRisco,MATCH(IF($W27<>"",$W27,$Q27),Niveis,0))) -> Mitigar | Z27: Mitigar | AA27: Controle administrativo | AC27: Matriz de polivalência, escala por demanda e plano de cobertura de ausência | AD27: Gerente de RH | AE27: Supervisor de Turno | AF27: 46507 | AG27: Aberto | AH27: Paradas por operador indisponível ≤ 150 h/mês | AJ27: =IF(OR($AI27="",PlanoUrl=""),"",HYPERLINK(SUBSTITUTE(PlanoUrl,"{COD}",SUBSTITUTE($AI27," ","%20")),"↗")) | AK27: =IF($C27="","",IF($AI27="",$AG27&"",IFERROR(IF(INDEX(PlanosStatus,MATCH($AI27,PlanosCod,0))="",$AG27&"",INDEX(PlanosStatus,MATCH($AI27,PlanosCod,0))),$AG27&""))) -> Aberto | AL27: =IF($C27="","",IF($AI27="",IF($AF27="","",$AF27),IFERROR(IF(INDEX(PlanosPrazo,MATCH($AI27,PlanosCod,0))="",IF($AF27="","",$AF27),INDEX(PlanosPrazo,MATCH($AI27,PlanosCod,0))),IF($AF27="","",$AF27)))) -> 46507 | AP27: 3 | AQ27: 3 | AR27: =IF(COUNT($AP27:$AQ27)=2,$AP27*$AQ27,"") -> 9 | AS27: =IF($AR27="","",INDEX(Niveis,MAX(IFERROR(MATCH($AR27,Limites,1),1),IF($AQ27=5,MinIdx,1)))) -> Médio | AT27: Sim | AU27: Horas de parada por operador indisponível/mês (aba KRI) | AV27: 1435 | AW27: 46371 | AX27: RH + Produção | AY27: =IF(OR($AW27="",IF(AND($AN27="Eficaz",$AS27<>""),$AS27,IF($W27<>"",$W27,$Q27))=""),"",EDATE($AW27,INDEX(MesesRev,MATCH(IF(AND($AN27="Eficaz",$AS27<>""),$AS27,IF($W27<>"",$W27,$Q27)),Niveis,0)))) -> 46461 | AZ27: =IF($C27="","",IF($AD27="","Sem dono",IF($W27="","Falta avaliação",IF(AND($AI27<>"",COUNTIF(PlanosCod,$AI27)=0),"Código não encontrado",IF(AND($AI27<>"",IFERROR(INDEX(PlanosIdRef,MATCH($AI27,PlanosCod,0))&"","")<>"",ISERROR(SEARCH(";"&$A27&";",";"&SUBSTITUTE(SUBSTITUTE(IFERROR(INDEX(PlanosIdRef,MATCH($AI27,PlanosCod,0))&"","")," ",""),",",";")&";"))),"Vínculo divergente",IF(AND(ISNUMBER($P27),ISNUMBER($V27),$V27<$P27,OR($S27="",$S27="Inexistente")),"Redução s/ controle",IF(AND(ISNUMBER($AR27),ISNUMBER($V27),$AR27<$V27,NOT(OR($Z27="Prevenir",$Z27="Mitigar",$Z27="Transferir / compartilhar")),$AC27="",$AI27=""),"Residual s/ tratamento",IF(AND(LEFT($AI27,3)="RNC",N(IFERROR(INDEX(PlanosAbertura,MATCH($AI27,PlanosCod,0)),0))>N($AW27)),"Reavaliar após RNC",IF(AND(N($AV27)>=1,ISNUMBER($T27),$T27<=2),"Recalibrar probabilidade",IF(AND($Z27="Aceitar",$BA27=""),"Aceite sem justificativa",IF(AND($Z27="Aceitar",ISNUMBER($AB27),$AB27<TODAY()),"Aceite vencido",IF(AND(OR($Z27="Aceitar",$Z27="Monitorar"),$Y27<>"Monitorar",$Y27<>""),"Aprovar aceite",IF(AND($Z27<>"Aceitar",$Z27<>"Monitorar",$Z27<>"Aprofundar análise",$AC27="",$AI27="",IFERROR(MATCH(IF($W27<>"",$W27,$Q27),Niveis,0),0)>IF(N(IFERROR(INDEX(ApetIdx,MATCH($M27,ListaCatRisco,0)),0))=0,IdxExige-1,INDEX(ApetIdx,MATCH($M27,ListaCatRisco,0)))),"Sem ação",IF($Z27="Aprofundar análise","Aprofundar análise",IF(AND(OR($Z27="Prevenir",$Z27="Mitigar",$Z27="Transferir / compartilhar"),$AH27=""),"Definir critério de eficácia",IF(AND(OR($Z27="Prevenir",$Z27="Mitigar",$Z27="Transferir / compartilhar"),OR($AA27="Controle administrativo",$AA27="EPI"),IFERROR(MATCH(IF($W27<>"",$W27,$Q27),Niveis,0),0)>=3),"Rever hierarquia de controle",IF(COUNTIFS(KriId,$A27,KriSit,"Estourou")+COUNTIFS(KriId,$A27,KriSit,"Atenção")>0,"KRI em alerta",IF(COUNTIFS(BtId,$A27,BtEf,"Baixa")+COUNTIFS(BtId,$A27,BtEf,"Inexistente")>0,"Barreira fraca",IF($AN27="Não eficaz","Ação ineficaz",IF(AND($AL27<>"",$AL27<TODAY(),$AK27<>"Concluído",$AK27<>"Cancelado"),"Ação vencida",IF(AND($AN27<>"Eficaz",OR($AK27="Concluído",AND(ISNUMBER($AM27),$AM27<TODAY()))),"Avaliar eficácia",IF(AND($AN27="Eficaz",OR($AS27="",$AT27="")),"Concluir residual",IF($AT27="Não","Tratamento adicional",IF(AND($AT27="Sim",$AS27<>"",IFERROR(MATCH($AS27,Niveis,0),0)>IF(N(IFERROR(INDEX(ApetIdx,MATCH($M27,ListaCatRisco,0)),0))=0,IdxExige-1,INDEX(ApetIdx,MATCH($M27,ListaCatRisco,0)))),"Aceite fora do apetite",IF(AND(COUNTIF(BtId,$A27)=0,OR(IFERROR(MATCH(IF($W27<>"",$W27,$Q27),Niveis,0),0)>=3,AND(OR($S27="Baixa",$S27="Inexistente"),IFERROR(MATCH(IF($W27<>"",$W27,$Q27),Niveis,0),0)>=2))),"Sem BowTie",IF(AND($AY27<>"",$AY27<TODAY()),"Revisão vencida",IF(AND($AL27<>"",N($AL27)-TODAY()<=DiasAlerta,$AK27<>"Concluído",$AK27<>"Cancelado"),"Vence em breve","OK"))))))))))))))))))))))))))) -> Rever hierarquia de controle | BA27: Hierarquia administrativa aceitável: não há alternativa de engenharia para ausência. Rever se o nível subir para Crítico. | BB27: R9 | BC27: =IF($V27="","",1+COUNTIF($V$5:$V$154,">"&$V27)+COUNTIFS($V$5:$V$154,$V27,$U$5:$U$154,">"&$U27)+COUNTIFS($V$4:$V26,$V27,$U$4:$U26,$U27)) -> 16 | BD27: Imediata — horas | BE27: Moderada | BF27: Preventivo | BG27: 15000 | BH27: 70000 | BI27: =IF(OR($BH27="",$T27=""),"",IFERROR($BH27*INDEX(ProbMedia,$T27),"")) -> 49000 | BJ27: =IF(OR($BG27="",$BI27=""),"",IF(OR(LEFT($M27,3)="SST",LEFT($M27,5)="Legal",LEFT($M27,8)="Ambienta"),"SST/Ambiental/Legal: custo não justifica aceitar (apetite e ALARP)",IF($BG27>$BI27,"Custo maior que a perda esperada: reter/aceitar é defensável, com justificativa","Custo menor ou igual à perda esperada: tratar compensa"))) -> Custo menor ou igual à perda esperada: tratar compensa | BW27: =IF($BU27="","",IFERROR(INDEX(SgaProbValor,MATCH($BU27,SgaProbNivel,0)),"")) | BX27: =IF($BV27="","",IFERROR(INDEX(SgaSevRiValor,MATCH($BV27,SgaSevRiNivel,0)),"")) | BY27: =IF(COUNT($BW27:$BX27)=2,$BW27*$BX27,"") | BZ27: =IF($BY27="","",IF($BY27<=SgaLimRiSig,"SIGNIFICATIVO",IF($BY27<=SgaLimRiTol,"TOLERÁVEL","BAIXO"))) | CA27: =IF($BZ27="","",IF($BZ27="SIGNIFICATIVO","NÃO ACEITÁVEL","ACEITÁVEL")) | CG27: =IF(OR($CE27="",$CF27=""),"",IFERROR(INDEX(SgaProbValor,MATCH($CE27,SgaProbNivel,0))*INDEX(SgaSevRiValor,MATCH($CF27,SgaSevRiNivel,0)),"")) | CH27: =IF($CG27="","",IF($CG27<=SgaLimRiSig,"SIGNIFICATIVO",IF($CG27<=SgaLimRiTol,"TOLERÁVEL","BAIXO")))
A28: R24 | B28: Gestão Financeira | C28: Erosão de margem por perdas de qualidade (scrap, refação, reclamações) acima da meta | D28: Análise crítica | E28: Práticas de gerenciamento | F28: Estratégico | G28: Custo da não-qualidade −15% vs baseline | H28: Novo | I28: Acionistas / Direção | J28: Perdas dominantes por processo sem priorização financeira; foco no KPI em vez do mecanismo | K28: Método | L28: Scrap de 2,62 milhões de peças (≈ € 131 mil, premissa de € 0,05/un); 8 refações (181 806 peças); falha externa ≈ € 419 mil (premissas) | M28: Financeiro | N28: 4 | O28: 3 | P28: =IF(COUNT($N28:$O28)=2,$N28*$O28,"") -> 12 | Q28: =IF($P28="","",INDEX(Niveis,MAX(IFERROR(MATCH($P28,Limites,1),1),IF($O28=5,MinIdx,1)))) -> Alto | R28: Acompanhamento mensal de rejeição; painel de KPIs | S28: Média | T28: 3 | U28: 3 | V28: =IF(COUNT($T28:$U28)=2,$T28*$U28,"") -> 9 | W28: =IF($V28="","",INDEX(Niveis,MAX(IFERROR(MATCH($V28,Limites,1),1),IF($U28=5,MinIdx,1)))) -> Médio | X28: Média | Y28: =IF(IF($W28<>"",$W28,$Q28)="","",INDEX(AcaoRisco,MATCH(IF($W28<>"",$W28,$Q28),Niveis,0))) -> Mitigar | Z28: Mitigar | AA28: Controle administrativo | AC28: Priorizar por Manufacturing Loss Pareto financeiro (perda × frequência × facilidade × efeito no cliente) | AD28: Gerente Financeiro | AE28: Controller Industrial | AF28: 46477 | AG28: Aberto | AH28: Falha interna + externa −15% vs baseline em 12 meses | AJ28: =IF(OR($AI28="",PlanoUrl=""),"",HYPERLINK(SUBSTITUTE(PlanoUrl,"{COD}",SUBSTITUTE($AI28," ","%20")),"↗")) | AK28: =IF($C28="","",IF($AI28="",$AG28&"",IFERROR(IF(INDEX(PlanosStatus,MATCH($AI28,PlanosCod,0))="",$AG28&"",INDEX(PlanosStatus,MATCH($AI28,PlanosCod,0))),$AG28&""))) -> Aberto | AL28: =IF($C28="","",IF($AI28="",IF($AF28="","",$AF28),IFERROR(IF(INDEX(PlanosPrazo,MATCH($AI28,PlanosCod,0))="",IF($AF28="","",$AF28),INDEX(PlanosPrazo,MATCH($AI28,PlanosCod,0))),IF($AF28="","",$AF28)))) -> 46477 | AP28: 3 | AQ28: 2 | AR28: =IF(COUNT($AP28:$AQ28)=2,$AP28*$AQ28,"") -> 6 | AS28: =IF($AR28="","",INDEX(Niveis,MAX(IFERROR(MATCH($AR28,Limites,1),1),IF($AQ28=5,MinIdx,1)))) -> Baixo | AT28: Sim | AU28: Taxa de rejeição da planta (aba KRI) | AW28: 46371 | AX28: Direção + Finanças | AY28: =IF(OR($AW28="",IF(AND($AN28="Eficaz",$AS28<>""),$AS28,IF($W28<>"",$W28,$Q28))=""),"",EDATE($AW28,INDEX(MesesRev,MATCH(IF(AND($AN28="Eficaz",$AS28<>""),$AS28,IF($W28<>"",$W28,$Q28)),Niveis,0)))) -> 46553 | AZ28: =IF($C28="","",IF($AD28="","Sem dono",IF($W28="","Falta avaliação",IF(AND($AI28<>"",COUNTIF(PlanosCod,$AI28)=0),"Código não encontrado",IF(AND($AI28<>"",IFERROR(INDEX(PlanosIdRef,MATCH($AI28,PlanosCod,0))&"","")<>"",ISERROR(SEARCH(";"&$A28&";",";"&SUBSTITUTE(SUBSTITUTE(IFERROR(INDEX(PlanosIdRef,MATCH($AI28,PlanosCod,0))&"","")," ",""),",",";")&";"))),"Vínculo divergente",IF(AND(ISNUMBER($P28),ISNUMBER($V28),$V28<$P28,OR($S28="",$S28="Inexistente")),"Redução s/ controle",IF(AND(ISNUMBER($AR28),ISNUMBER($V28),$AR28<$V28,NOT(OR($Z28="Prevenir",$Z28="Mitigar",$Z28="Transferir / compartilhar")),$AC28="",$AI28=""),"Residual s/ tratamento",IF(AND(LEFT($AI28,3)="RNC",N(IFERROR(INDEX(PlanosAbertura,MATCH($AI28,PlanosCod,0)),0))>N($AW28)),"Reavaliar após RNC",IF(AND(N($AV28)>=1,ISNUMBER($T28),$T28<=2),"Recalibrar probabilidade",IF(AND($Z28="Aceitar",$BA28=""),"Aceite sem justificativa",IF(AND($Z28="Aceitar",ISNUMBER($AB28),$AB28<TODAY()),"Aceite vencido",IF(AND(OR($Z28="Aceitar",$Z28="Monitorar"),$Y28<>"Monitorar",$Y28<>""),"Aprovar aceite",IF(AND($Z28<>"Aceitar",$Z28<>"Monitorar",$Z28<>"Aprofundar análise",$AC28="",$AI28="",IFERROR(MATCH(IF($W28<>"",$W28,$Q28),Niveis,0),0)>IF(N(IFERROR(INDEX(ApetIdx,MATCH($M28,ListaCatRisco,0)),0))=0,IdxExige-1,INDEX(ApetIdx,MATCH($M28,ListaCatRisco,0)))),"Sem ação",IF($Z28="Aprofundar análise","Aprofundar análise",IF(AND(OR($Z28="Prevenir",$Z28="Mitigar",$Z28="Transferir / compartilhar"),$AH28=""),"Definir critério de eficácia",IF(AND(OR($Z28="Prevenir",$Z28="Mitigar",$Z28="Transferir / compartilhar"),OR($AA28="Controle administrativo",$AA28="EPI"),IFERROR(MATCH(IF($W28<>"",$W28,$Q28),Niveis,0),0)>=3),"Rever hierarquia de controle",IF(COUNTIFS(KriId,$A28,KriSit,"Estourou")+COUNTIFS(KriId,$A28,KriSit,"Atenção")>0,"KRI em alerta",IF(COUNTIFS(BtId,$A28,BtEf,"Baixa")+COUNTIFS(BtId,$A28,BtEf,"Inexistente")>0,"Barreira fraca",IF($AN28="Não eficaz","Ação ineficaz",IF(AND($AL28<>"",$AL28<TODAY(),$AK28<>"Concluído",$AK28<>"Cancelado"),"Ação vencida",IF(AND($AN28<>"Eficaz",OR($AK28="Concluído",AND(ISNUMBER($AM28),$AM28<TODAY()))),"Avaliar eficácia",IF(AND($AN28="Eficaz",OR($AS28="",$AT28="")),"Concluir residual",IF($AT28="Não","Tratamento adicional",IF(AND($AT28="Sim",$AS28<>"",IFERROR(MATCH($AS28,Niveis,0),0)>IF(N(IFERROR(INDEX(ApetIdx,MATCH($M28,ListaCatRisco,0)),0))=0,IdxExige-1,INDEX(ApetIdx,MATCH($M28,ListaCatRisco,0)))),"Aceite fora do apetite",IF(AND(COUNTIF(BtId,$A28)=0,OR(IFERROR(MATCH(IF($W28<>"",$W28,$Q28),Niveis,0),0)>=3,AND(OR($S28="Baixa",$S28="Inexistente"),IFERROR(MATCH(IF($W28<>"",$W28,$Q28),Niveis,0),0)>=2))),"Sem BowTie",IF(AND($AY28<>"",$AY28<TODAY()),"Revisão vencida",IF(AND($AL28<>"",N($AL28)-TODAY()<=DiasAlerta,$AK28<>"Concluído",$AK28<>"Cancelado"),"Vence em breve","OK"))))))))))))))))))))))))))) -> OK | BA28: Valores de custo são modelo ilustrativo sob premissas (scrap € 0,05/un; reclamação € 5 000/€ 1 500/€ 300; parada € 350/h), não custo contábil. | BB28: R16;R20 | BC28: =IF($V28="","",1+COUNTIF($V$5:$V$154,">"&$V28)+COUNTIFS($V$5:$V$154,$V28,$U$5:$U$154,">"&$U28)+COUNTIFS($V$4:$V27,$V28,$U$4:$U27,$U28)) -> 26 | BD28: Lenta — meses | BE28: Moderada | BF28: Preventivo | BG28: 8000 | BH28: 120000 | BI28: =IF(OR($BH28="",$T28=""),"",IFERROR($BH28*INDEX(ProbMedia,$T28),"")) -> 60000 | BJ28: =IF(OR($BG28="",$BI28=""),"",IF(OR(LEFT($M28,3)="SST",LEFT($M28,5)="Legal",LEFT($M28,8)="Ambienta"),"SST/Ambiental/Legal: custo não justifica aceitar (apetite e ALARP)",IF($BG28>$BI28,"Custo maior que a perda esperada: reter/aceitar é defensável, com justificativa","Custo menor ou igual à perda esperada: tratar compensa"))) -> Custo menor ou igual à perda esperada: tratar compensa | BW28: =IF($BU28="","",IFERROR(INDEX(SgaProbValor,MATCH($BU28,SgaProbNivel,0)),"")) | BX28: =IF($BV28="","",IFERROR(INDEX(SgaSevRiValor,MATCH($BV28,SgaSevRiNivel,0)),"")) | BY28: =IF(COUNT($BW28:$BX28)=2,$BW28*$BX28,"") | BZ28: =IF($BY28="","",IF($BY28<=SgaLimRiSig,"SIGNIFICATIVO",IF($BY28<=SgaLimRiTol,"TOLERÁVEL","BAIXO"))) | CA28: =IF($BZ28="","",IF($BZ28="SIGNIFICATIVO","NÃO ACEITÁVEL","ACEITÁVEL")) | CG28: =IF(OR($CE28="",$CF28=""),"",IFERROR(INDEX(SgaProbValor,MATCH($CE28,SgaProbNivel,0))*INDEX(SgaSevRiValor,MATCH($CF28,SgaSevRiNivel,0)),"")) | CH28: =IF($CG28="","",IF($CG28<=SgaLimRiSig,"SIGNIFICATIVO",IF($CG28<=SgaLimRiTol,"TOLERÁVEL","BAIXO")))
A29: R25 | B29: Gestão Financeira | C29: Volatilidade do preço de energia e de polímeros (virgens e reciclados) comprime a margem | D29: PESTEL / cenário externo | E29: Externo | F29: Estratégico | G29: Custo da não-qualidade −15% vs baseline | H29: Mantido | I29: Acionistas / Direção | J29: Preços de energia e resinas voláteis e contratos de fornecimento anuais sem cobertura | K29: Meio ambiente | L29: Aumento do custo por unidade e menor retorno de projetos de eficiência | M29: Financeiro | N29: 4 | O29: 3 | P29: =IF(COUNT($N29:$O29)=2,$N29*$O29,"") -> 12 | Q29: =IF($P29="","",INDEX(Niveis,MAX(IFERROR(MATCH($P29,Limites,1),1),IF($O29=5,MinIdx,1)))) -> Alto | R29: Contratos anuais de resina; acompanhamento de compras | S29: Média | T29: 4 | U29: 3 | V29: =IF(COUNT($T29:$U29)=2,$T29*$U29,"") -> 12 | W29: =IF($V29="","",INDEX(Niveis,MAX(IFERROR(MATCH($V29,Limites,1),1),IF($U29=5,MinIdx,1)))) -> Alto | X29: Baixa | Y29: =IF(IF($W29<>"",$W29,$Q29)="","",INDEX(AcaoRisco,MATCH(IF($W29<>"",$W29,$Q29),Niveis,0))) -> Mitigar | Z29: Transferir / compartilhar | AA29: Não se aplica | AC29: Cláusulas de indexação de preço, contratos de energia a prazo e avaliação de custo total (TCO) | AD29: Gerente Financeiro | AE29: Gerente de Compras | AF29: 46477 | AG29: Aberto | AH29: Variação de custo de material ≤ 5% vs orçamento | AJ29: =IF(OR($AI29="",PlanoUrl=""),"",HYPERLINK(SUBSTITUTE(PlanoUrl,"{COD}",SUBSTITUTE($AI29," ","%20")),"↗")) | AK29: =IF($C29="","",IF($AI29="",$AG29&"",IFERROR(IF(INDEX(PlanosStatus,MATCH($AI29,PlanosCod,0))="",$AG29&"",INDEX(PlanosStatus,MATCH($AI29,PlanosCod,0))),$AG29&""))) -> Aberto | AL29: =IF($C29="","",IF($AI29="",IF($AF29="","",$AF29),IFERROR(IF(INDEX(PlanosPrazo,MATCH($AI29,PlanosCod,0))="",IF($AF29="","",$AF29),INDEX(PlanosPrazo,MATCH($AI29,PlanosCod,0))),IF($AF29="","",$AF29)))) -> 46477 | AP29: 3 | AQ29: 3 | AR29: =IF(COUNT($AP29:$AQ29)=2,$AP29*$AQ29,"") -> 9 | AS29: =IF($AR29="","",INDEX(Niveis,MAX(IFERROR(MATCH($AR29,Limites,1),1),IF($AQ29=5,MinIdx,1)))) -> Médio | AT29: Sim | AW29: 46371 | AX29: Direção + Finanças | AY29: =IF(OR($AW29="",IF(AND($AN29="Eficaz",$AS29<>""),$AS29,IF($W29<>"",$W29,$Q29))=""),"",EDATE($AW29,INDEX(MesesRev,MATCH(IF(AND($AN29="Eficaz",$AS29<>""),$AS29,IF($W29<>"",$W29,$Q29)),Niveis,0)))) -> 46461 | AZ29: =IF($C29="","",IF($AD29="","Sem dono",IF($W29="","Falta avaliação",IF(AND($AI29<>"",COUNTIF(PlanosCod,$AI29)=0),"Código não encontrado",IF(AND($AI29<>"",IFERROR(INDEX(PlanosIdRef,MATCH($AI29,PlanosCod,0))&"","")<>"",ISERROR(SEARCH(";"&$A29&";",";"&SUBSTITUTE(SUBSTITUTE(IFERROR(INDEX(PlanosIdRef,MATCH($AI29,PlanosCod,0))&"","")," ",""),",",";")&";"))),"Vínculo divergente",IF(AND(ISNUMBER($P29),ISNUMBER($V29),$V29<$P29,OR($S29="",$S29="Inexistente")),"Redução s/ controle",IF(AND(ISNUMBER($AR29),ISNUMBER($V29),$AR29<$V29,NOT(OR($Z29="Prevenir",$Z29="Mitigar",$Z29="Transferir / compartilhar")),$AC29="",$AI29=""),"Residual s/ tratamento",IF(AND(LEFT($AI29,3)="RNC",N(IFERROR(INDEX(PlanosAbertura,MATCH($AI29,PlanosCod,0)),0))>N($AW29)),"Reavaliar após RNC",IF(AND(N($AV29)>=1,ISNUMBER($T29),$T29<=2),"Recalibrar probabilidade",IF(AND($Z29="Aceitar",$BA29=""),"Aceite sem justificativa",IF(AND($Z29="Aceitar",ISNUMBER($AB29),$AB29<TODAY()),"Aceite vencido",IF(AND(OR($Z29="Aceitar",$Z29="Monitorar"),$Y29<>"Monitorar",$Y29<>""),"Aprovar aceite",IF(AND($Z29<>"Aceitar",$Z29<>"Monitorar",$Z29<>"Aprofundar análise",$AC29="",$AI29="",IFERROR(MATCH(IF($W29<>"",$W29,$Q29),Niveis,0),0)>IF(N(IFERROR(INDEX(ApetIdx,MATCH($M29,ListaCatRisco,0)),0))=0,IdxExige-1,INDEX(ApetIdx,MATCH($M29,ListaCatRisco,0)))),"Sem ação",IF($Z29="Aprofundar análise","Aprofundar análise",IF(AND(OR($Z29="Prevenir",$Z29="Mitigar",$Z29="Transferir / compartilhar"),$AH29=""),"Definir critério de eficácia",IF(AND(OR($Z29="Prevenir",$Z29="Mitigar",$Z29="Transferir / compartilhar"),OR($AA29="Controle administrativo",$AA29="EPI"),IFERROR(MATCH(IF($W29<>"",$W29,$Q29),Niveis,0),0)>=3),"Rever hierarquia de controle",IF(COUNTIFS(KriId,$A29,KriSit,"Estourou")+COUNTIFS(KriId,$A29,KriSit,"Atenção")>0,"KRI em alerta",IF(COUNTIFS(BtId,$A29,BtEf,"Baixa")+COUNTIFS(BtId,$A29,BtEf,"Inexistente")>0,"Barreira fraca",IF($AN29="Não eficaz","Ação ineficaz",IF(AND($AL29<>"",$AL29<TODAY(),$AK29<>"Concluído",$AK29<>"Cancelado"),"Ação vencida",IF(AND($AN29<>"Eficaz",OR($AK29="Concluído",AND(ISNUMBER($AM29),$AM29<TODAY()))),"Avaliar eficácia",IF(AND($AN29="Eficaz",OR($AS29="",$AT29="")),"Concluir residual",IF($AT29="Não","Tratamento adicional",IF(AND($AT29="Sim",$AS29<>"",IFERROR(MATCH($AS29,Niveis,0),0)>IF(N(IFERROR(INDEX(ApetIdx,MATCH($M29,ListaCatRisco,0)),0))=0,IdxExige-1,INDEX(ApetIdx,MATCH($M29,ListaCatRisco,0)))),"Aceite fora do apetite",IF(AND(COUNTIF(BtId,$A29)=0,OR(IFERROR(MATCH(IF($W29<>"",$W29,$Q29),Niveis,0),0)>=3,AND(OR($S29="Baixa",$S29="Inexistente"),IFERROR(MATCH(IF($W29<>"",$W29,$Q29),Niveis,0),0)>=2))),"Sem BowTie",IF(AND($AY29<>"",$AY29<TODAY()),"Revisão vencida",IF(AND($AL29<>"",N($AL29)-TODAY()<=DiasAlerta,$AK29<>"Concluído",$AK29<>"Cancelado"),"Vence em breve","OK"))))))))))))))))))))))))))) -> Barreira fraca | BA29: Fonte: PESTLE (Econômico) do SGA. Exposição estratégica; indicador de preço a definir com Compras. | BB29: R14;O6 | BC29: =IF($V29="","",1+COUNTIF($V$5:$V$154,">"&$V29)+COUNTIFS($V$5:$V$154,$V29,$U$5:$U$154,">"&$U29)+COUNTIFS($V$4:$V28,$V29,$U$4:$U28,$U29)) -> 17 | BD29: Lenta — meses | BE29: Alta — muda rápido | BF29: Compartilhamento (seguro/contrato) | BG29: 6000 | BH29: 90000 | BI29: =IF(OR($BH29="",$T29=""),"",IFERROR($BH29*INDEX(ProbMedia,$T29),"")) -> 63000 | BJ29: =IF(OR($BG29="",$BI29=""),"",IF(OR(LEFT($M29,3)="SST",LEFT($M29,5)="Legal",LEFT($M29,8)="Ambienta"),"SST/Ambiental/Legal: custo não justifica aceitar (apetite e ALARP)",IF($BG29>$BI29,"Custo maior que a perda esperada: reter/aceitar é defensável, com justificativa","Custo menor ou igual à perda esperada: tratar compensa"))) -> Custo menor ou igual à perda esperada: tratar compensa | BW29: =IF($BU29="","",IFERROR(INDEX(SgaProbValor,MATCH($BU29,SgaProbNivel,0)),"")) | BX29: =IF($BV29="","",IFERROR(INDEX(SgaSevRiValor,MATCH($BV29,SgaSevRiNivel,0)),"")) | BY29: =IF(COUNT($BW29:$BX29)=2,$BW29*$BX29,"") | BZ29: =IF($BY29="","",IF($BY29<=SgaLimRiSig,"SIGNIFICATIVO",IF($BY29<=SgaLimRiTol,"TOLERÁVEL","BAIXO"))) | CA29: =IF($BZ29="","",IF($BZ29="SIGNIFICATIVO","NÃO ACEITÁVEL","ACEITÁVEL")) | CG29: =IF(OR($CE29="",$CF29=""),"",IFERROR(INDEX(SgaProbValor,MATCH($CE29,SgaProbNivel,0))*INDEX(SgaSevRiValor,MATCH($CF29,SgaSevRiNivel,0)),"")) | CH29: =IF($CG29="","",IF($CG29<=SgaLimRiSig,"SIGNIFICATIVO",IF($CG29<=SgaLimRiTol,"TOLERÁVEL","BAIXO")))
A30: R26 | B30: Dados / TI | C30: Indisponibilidade ou corrupção do warehouse/pipeline de dados que sustenta os KPIs e as decisões | D30: Processo (atividades) | E30: Técnico | F30: Gerencial (processo) | G30: Continuidade da produção e entregas no prazo | H30: Novo | I30: Acionistas / Direção | J30: Carga bronze → silver → gold sem monitoramento de qualidade nem plano de recuperação testado | K30: Método | L30: Decisões sem dados ou com dados errados (ex.: erro de dupla contagem nas Seis Grandes Perdas já ocorrido); perda de rastreabilidade | M30: Produção / Ativos | N30: 3 | O30: 3 | P30: =IF(COUNT($N30:$O30)=2,$N30*$O30,"") -> 9 | Q30: =IF($P30="","",INDEX(Niveis,MAX(IFERROR(MATCH($P30,Limites,1),1),IF($O30=5,MinIdx,1)))) -> Médio | R30: Backup do banco; testes de invariantes analíticas | S30: Média | T30: 3 | U30: 3 | V30: =IF(COUNT($T30:$U30)=2,$T30*$U30,"") -> 9 | W30: =IF($V30="","",INDEX(Niveis,MAX(IFERROR(MATCH($V30,Limites,1),1),IF($U30=5,MinIdx,1)))) -> Médio | X30: Média | Y30: =IF(IF($W30<>"",$W30,$Q30)="","",INDEX(AcaoRisco,MATCH(IF($W30<>"",$W30,$Q30),Niveis,0))) -> Mitigar | Z30: Mitigar | AA30: Controle de engenharia | AC30: Monitorar carga com testes de qualidade de dados e ensaiar a restauração do banco | AD30: Gerente de Dados / TI | AE30: Engenheiro de Dados | AH30: Restauração testada em ≤ 4 h e 100% dos testes de invariantes no CI | AI30: PAC 202623 | AJ30: =IF(OR($AI30="",PlanoUrl=""),"",HYPERLINK(SUBSTITUTE(PlanoUrl,"{COD}",SUBSTITUTE($AI30," ","%20")),"↗")) | AK30: =IF($C30="","",IF($AI30="",$AG30&"",IFERROR(IF(INDEX(PlanosStatus,MATCH($AI30,PlanosCod,0))="",$AG30&"",INDEX(PlanosStatus,MATCH($AI30,PlanosCod,0))),$AG30&""))) -> Aberto | AL30: =IF($C30="","",IF($AI30="",IF($AF30="","",$AF30),IFERROR(IF(INDEX(PlanosPrazo,MATCH($AI30,PlanosCod,0))="",IF($AF30="","",$AF30),INDEX(PlanosPrazo,MATCH($AI30,PlanosCod,0))),IF($AF30="","",$AF30)))) -> 46477 | AM30: 46568 | AP30: 1 | AQ30: 3 | AR30: =IF(COUNT($AP30:$AQ30)=2,$AP30*$AQ30,"") -> 3 | AS30: =IF($AR30="","",INDEX(Niveis,MAX(IFERROR(MATCH($AR30,Limites,1),1),IF($AQ30=5,MinIdx,1)))) -> Baixo | AT30: Sim | AV30: 1 | AW30: 46371 | AX30: Dados | AY30: =IF(OR($AW30="",IF(AND($AN30="Eficaz",$AS30<>""),$AS30,IF($W30<>"",$W30,$Q30))=""),"",EDATE($AW30,INDEX(MesesRev,MATCH(IF(AND($AN30="Eficaz",$AS30<>""),$AS30,IF($W30<>"",$W30,$Q30)),Niveis,0)))) -> 46553 | AZ30: =IF($C30="","",IF($AD30="","Sem dono",IF($W30="","Falta avaliação",IF(AND($AI30<>"",COUNTIF(PlanosCod,$AI30)=0),"Código não encontrado",IF(AND($AI30<>"",IFERROR(INDEX(PlanosIdRef,MATCH($AI30,PlanosCod,0))&"","")<>"",ISERROR(SEARCH(";"&$A30&";",";"&SUBSTITUTE(SUBSTITUTE(IFERROR(INDEX(PlanosIdRef,MATCH($AI30,PlanosCod,0))&"","")," ",""),",",";")&";"))),"Vínculo divergente",IF(AND(ISNUMBER($P30),ISNUMBER($V30),$V30<$P30,OR($S30="",$S30="Inexistente")),"Redução s/ controle",IF(AND(ISNUMBER($AR30),ISNUMBER($V30),$AR30<$V30,NOT(OR($Z30="Prevenir",$Z30="Mitigar",$Z30="Transferir / compartilhar")),$AC30="",$AI30=""),"Residual s/ tratamento",IF(AND(LEFT($AI30,3)="RNC",N(IFERROR(INDEX(PlanosAbertura,MATCH($AI30,PlanosCod,0)),0))>N($AW30)),"Reavaliar após RNC",IF(AND(N($AV30)>=1,ISNUMBER($T30),$T30<=2),"Recalibrar probabilidade",IF(AND($Z30="Aceitar",$BA30=""),"Aceite sem justificativa",IF(AND($Z30="Aceitar",ISNUMBER($AB30),$AB30<TODAY()),"Aceite vencido",IF(AND(OR($Z30="Aceitar",$Z30="Monitorar"),$Y30<>"Monitorar",$Y30<>""),"Aprovar aceite",IF(AND($Z30<>"Aceitar",$Z30<>"Monitorar",$Z30<>"Aprofundar análise",$AC30="",$AI30="",IFERROR(MATCH(IF($W30<>"",$W30,$Q30),Niveis,0),0)>IF(N(IFERROR(INDEX(ApetIdx,MATCH($M30,ListaCatRisco,0)),0))=0,IdxExige-1,INDEX(ApetIdx,MATCH($M30,ListaCatRisco,0)))),"Sem ação",IF($Z30="Aprofundar análise","Aprofundar análise",IF(AND(OR($Z30="Prevenir",$Z30="Mitigar",$Z30="Transferir / compartilhar"),$AH30=""),"Definir critério de eficácia",IF(AND(OR($Z30="Prevenir",$Z30="Mitigar",$Z30="Transferir / compartilhar"),OR($AA30="Controle administrativo",$AA30="EPI"),IFERROR(MATCH(IF($W30<>"",$W30,$Q30),Niveis,0),0)>=3),"Rever hierarquia de controle",IF(COUNTIFS(KriId,$A30,KriSit,"Estourou")+COUNTIFS(KriId,$A30,KriSit,"Atenção")>0,"KRI em alerta",IF(COUNTIFS(BtId,$A30,BtEf,"Baixa")+COUNTIFS(BtId,$A30,BtEf,"Inexistente")>0,"Barreira fraca",IF($AN30="Não eficaz","Ação ineficaz",IF(AND($AL30<>"",$AL30<TODAY(),$AK30<>"Concluído",$AK30<>"Cancelado"),"Ação vencida",IF(AND($AN30<>"Eficaz",OR($AK30="Concluído",AND(ISNUMBER($AM30),$AM30<TODAY()))),"Avaliar eficácia",IF(AND($AN30="Eficaz",OR($AS30="",$AT30="")),"Concluir residual",IF($AT30="Não","Tratamento adicional",IF(AND($AT30="Sim",$AS30<>"",IFERROR(MATCH($AS30,Niveis,0),0)>IF(N(IFERROR(INDEX(ApetIdx,MATCH($M30,ListaCatRisco,0)),0))=0,IdxExige-1,INDEX(ApetIdx,MATCH($M30,ListaCatRisco,0)))),"Aceite fora do apetite",IF(AND(COUNTIF(BtId,$A30)=0,OR(IFERROR(MATCH(IF($W30<>"",$W30,$Q30),Niveis,0),0)>=3,AND(OR($S30="Baixa",$S30="Inexistente"),IFERROR(MATCH(IF($W30<>"",$W30,$Q30),Niveis,0),0)>=2))),"Sem BowTie",IF(AND($AY30<>"",$AY30<TODAY()),"Revisão vencida",IF(AND($AL30<>"",N($AL30)-TODAY()<=DiasAlerta,$AK30<>"Concluído",$AK30<>"Cancelado"),"Vence em breve","OK"))))))))))))))))))))))))))) -> OK | BA30: Ocorrência real: dupla contagem em gold.six_big_losses_monthly corrigida na auditoria pós-correção. | BB30: R19 | BC30: =IF($V30="","",1+COUNTIF($V$5:$V$154,">"&$V30)+COUNTIFS($V$5:$V$154,$V30,$U$5:$U$154,">"&$U30)+COUNTIFS($V$4:$V29,$V30,$U$4:$U29,$U30)) -> 27 | BD30: Rápida — dias | BE30: Estável | BF30: Preventivo | BG30: 9000 | BH30: 25000 | BI30: =IF(OR($BH30="",$T30=""),"",IFERROR($BH30*INDEX(ProbMedia,$T30),"")) -> 12500 | BJ30: =IF(OR($BG30="",$BI30=""),"",IF(OR(LEFT($M30,3)="SST",LEFT($M30,5)="Legal",LEFT($M30,8)="Ambienta"),"SST/Ambiental/Legal: custo não justifica aceitar (apetite e ALARP)",IF($BG30>$BI30,"Custo maior que a perda esperada: reter/aceitar é defensável, com justificativa","Custo menor ou igual à perda esperada: tratar compensa"))) -> Custo menor ou igual à perda esperada: tratar compensa | BK30: 8 | BL30: PCN-DADOS-01 (restauração do DW) | BW30: =IF($BU30="","",IFERROR(INDEX(SgaProbValor,MATCH($BU30,SgaProbNivel,0)),"")) | BX30: =IF($BV30="","",IFERROR(INDEX(SgaSevRiValor,MATCH($BV30,SgaSevRiNivel,0)),"")) | BY30: =IF(COUNT($BW30:$BX30)=2,$BW30*$BX30,"") | BZ30: =IF($BY30="","",IF($BY30<=SgaLimRiSig,"SIGNIFICATIVO",IF($BY30<=SgaLimRiTol,"TOLERÁVEL","BAIXO"))) | CA30: =IF($BZ30="","",IF($BZ30="SIGNIFICATIVO","NÃO ACEITÁVEL","ACEITÁVEL")) | CG30: =IF(OR($CE30="",$CF30=""),"",IFERROR(INDEX(SgaProbValor,MATCH($CE30,SgaProbNivel,0))*INDEX(SgaSevRiValor,MATCH($CF30,SgaSevRiNivel,0)),"")) | CH30: =IF($CG30="","",IF($CG30<=SgaLimRiSig,"SIGNIFICATIVO",IF($CG30<=SgaLimRiTol,"TOLERÁVEL","BAIXO")))
A31: R27 | B31: Dados / TI | C31: Uso de modelos de Machine Learning de baixa capacidade preditiva como bloqueio automático ou base de decisão | D31: Análise de dados / raio-X analítico | E31: Práticas de gerenciamento | F31: Projeto | G31: Reclamações ≤ 3 por milhão de unidades (baseline 4,76) | H31: Novo | I31: Acionistas / Direção | J31: Modelos com ROC-AUC 0,59 (manutenção) e 0,69 (qualidade de lote) usados sem baseline, limiar econômico nem monitoramento de drift | K31: Método | L31: Falsos positivos/negativos, decisões equivocadas de parada ou liberação | M31: Qualidade / Cliente | N31: 3 | O31: 3 | P31: =IF(COUNT($N31:$O31)=2,$N31*$O31,"") -> 9 | Q31: =IF($P31="","",INDEX(Niveis,MAX(IFERROR(MATCH($P31,Limites,1),1),IF($O31=5,MinIdx,1)))) -> Médio | R31: Validação temporal (TimeSeriesSplit); auditoria de vazamento | S31: Média | T31: 2 | U31: 3 | V31: =IF(COUNT($T31:$U31)=2,$T31*$U31,"") -> 6 | W31: =IF($V31="","",INDEX(Niveis,MAX(IFERROR(MATCH($V31,Limites,1),1),IF($U31=5,MinIdx,1)))) -> Baixo | X31: Média | Y31: =IF(IF($W31<>"",$W31,$Q31)="","",INDEX(AcaoRisco,MATCH(IF($W31<>"",$W31,$Q31),Niveis,0))) -> Monitorar | Z31: Monitorar | AA31: Controle administrativo | AC31: Operar em shadow mode, definir limiar econômico e revisar recalibração antes de qualquer uso operacional | AD31: Gerente de Dados / TI | AE31: Cientista de Dados | AI31: PAC 202621 | AJ31: =IF(OR($AI31="",PlanoUrl=""),"",HYPERLINK(SUBSTITUTE(PlanoUrl,"{COD}",SUBSTITUTE($AI31," ","%20")),"↗")) | AK31: =IF($C31="","",IF($AI31="",$AG31&"",IFERROR(IF(INDEX(PlanosStatus,MATCH($AI31,PlanosCod,0))="",$AG31&"",INDEX(PlanosStatus,MATCH($AI31,PlanosCod,0))),$AG31&""))) -> Aberto | AL31: =IF($C31="","",IF($AI31="",IF($AF31="","",$AF31),IFERROR(IF(INDEX(PlanosPrazo,MATCH($AI31,PlanosCod,0))="",IF($AF31="","",$AF31),INDEX(PlanosPrazo,MATCH($AI31,PlanosCod,0))),IF($AF31="","",$AF31)))) -> 46477 | AM31: 46568 | AR31: =IF(COUNT($AP31:$AQ31)=2,$AP31*$AQ31,"") | AS31: =IF($AR31="","",INDEX(Niveis,MAX(IFERROR(MATCH($AR31,Limites,1),1),IF($AQ31=5,MinIdx,1)))) | AV31: 0 | AW31: 46371 | AX31: Dados | AY31: =IF(OR($AW31="",IF(AND($AN31="Eficaz",$AS31<>""),$AS31,IF($W31<>"",$W31,$Q31))=""),"",EDATE($AW31,INDEX(MesesRev,MATCH(IF(AND($AN31="Eficaz",$AS31<>""),$AS31,IF($W31<>"",$W31,$Q31)),Niveis,0)))) -> 46736 | AZ31: =IF($C31="","",IF($AD31="","Sem dono",IF($W31="","Falta avaliação",IF(AND($AI31<>"",COUNTIF(PlanosCod,$AI31)=0),"Código não encontrado",IF(AND($AI31<>"",IFERROR(INDEX(PlanosIdRef,MATCH($AI31,PlanosCod,0))&"","")<>"",ISERROR(SEARCH(";"&$A31&";",";"&SUBSTITUTE(SUBSTITUTE(IFERROR(INDEX(PlanosIdRef,MATCH($AI31,PlanosCod,0))&"","")," ",""),",",";")&";"))),"Vínculo divergente",IF(AND(ISNUMBER($P31),ISNUMBER($V31),$V31<$P31,OR($S31="",$S31="Inexistente")),"Redução s/ controle",IF(AND(ISNUMBER($AR31),ISNUMBER($V31),$AR31<$V31,NOT(OR($Z31="Prevenir",$Z31="Mitigar",$Z31="Transferir / compartilhar")),$AC31="",$AI31=""),"Residual s/ tratamento",IF(AND(LEFT($AI31,3)="RNC",N(IFERROR(INDEX(PlanosAbertura,MATCH($AI31,PlanosCod,0)),0))>N($AW31)),"Reavaliar após RNC",IF(AND(N($AV31)>=1,ISNUMBER($T31),$T31<=2),"Recalibrar probabilidade",IF(AND($Z31="Aceitar",$BA31=""),"Aceite sem justificativa",IF(AND($Z31="Aceitar",ISNUMBER($AB31),$AB31<TODAY()),"Aceite vencido",IF(AND(OR($Z31="Aceitar",$Z31="Monitorar"),$Y31<>"Monitorar",$Y31<>""),"Aprovar aceite",IF(AND($Z31<>"Aceitar",$Z31<>"Monitorar",$Z31<>"Aprofundar análise",$AC31="",$AI31="",IFERROR(MATCH(IF($W31<>"",$W31,$Q31),Niveis,0),0)>IF(N(IFERROR(INDEX(ApetIdx,MATCH($M31,ListaCatRisco,0)),0))=0,IdxExige-1,INDEX(ApetIdx,MATCH($M31,ListaCatRisco,0)))),"Sem ação",IF($Z31="Aprofundar análise","Aprofundar análise",IF(AND(OR($Z31="Prevenir",$Z31="Mitigar",$Z31="Transferir / compartilhar"),$AH31=""),"Definir critério de eficácia",IF(AND(OR($Z31="Prevenir",$Z31="Mitigar",$Z31="Transferir / compartilhar"),OR($AA31="Controle administrativo",$AA31="EPI"),IFERROR(MATCH(IF($W31<>"",$W31,$Q31),Niveis,0),0)>=3),"Rever hierarquia de controle",IF(COUNTIFS(KriId,$A31,KriSit,"Estourou")+COUNTIFS(KriId,$A31,KriSit,"Atenção")>0,"KRI em alerta",IF(COUNTIFS(BtId,$A31,BtEf,"Baixa")+COUNTIFS(BtId,$A31,BtEf,"Inexistente")>0,"Barreira fraca",IF($AN31="Não eficaz","Ação ineficaz",IF(AND($AL31<>"",$AL31<TODAY(),$AK31<>"Concluído",$AK31<>"Cancelado"),"Ação vencida",IF(AND($AN31<>"Eficaz",OR($AK31="Concluído",AND(ISNUMBER($AM31),$AM31<TODAY()))),"Avaliar eficácia",IF(AND($AN31="Eficaz",OR($AS31="",$AT31="")),"Concluir residual",IF($AT31="Não","Tratamento adicional",IF(AND($AT31="Sim",$AS31<>"",IFERROR(MATCH($AS31,Niveis,0),0)>IF(N(IFERROR(INDEX(ApetIdx,MATCH($M31,ListaCatRisco,0)),0))=0,IdxExige-1,INDEX(ApetIdx,MATCH($M31,ListaCatRisco,0)))),"Aceite fora do apetite",IF(AND(COUNTIF(BtId,$A31)=0,OR(IFERROR(MATCH(IF($W31<>"",$W31,$Q31),Niveis,0),0)>=3,AND(OR($S31="Baixa",$S31="Inexistente"),IFERROR(MATCH(IF($W31<>"",$W31,$Q31),Niveis,0),0)>=2))),"Sem BowTie",IF(AND($AY31<>"",$AY31<TODAY()),"Revisão vencida",IF(AND($AL31<>"",N($AL31)-TODAY()<=DiasAlerta,$AK31<>"Concluído",$AK31<>"Cancelado"),"Vence em breve","OK"))))))))))))))))))))))))))) -> OK | BA31: Modelos tratados como apoio à decisão, não substitutos da engenharia. R² alto de produção é condicional ao plano. | BB31: R19 | BC31: =IF($V31="","",1+COUNTIF($V$5:$V$154,">"&$V31)+COUNTIFS($V$5:$V$154,$V31,$U$5:$U$154,">"&$U31)+COUNTIFS($V$4:$V30,$V31,$U$4:$U30,$U31)) -> 37 | BD31: Lenta — meses | BE31: Estável | BF31: Diretivo (política/procedimento) | BI31: =IF(OR($BH31="",$T31=""),"",IFERROR($BH31*INDEX(ProbMedia,$T31),"")) | BJ31: =IF(OR($BG31="",$BI31=""),"",IF(OR(LEFT($M31,3)="SST",LEFT($M31,5)="Legal",LEFT($M31,8)="Ambienta"),"SST/Ambiental/Legal: custo não justifica aceitar (apetite e ALARP)",IF($BG31>$BI31,"Custo maior que a perda esperada: reter/aceitar é defensável, com justificativa","Custo menor ou igual à perda esperada: tratar compensa"))) | BW31: =IF($BU31="","",IFERROR(INDEX(SgaProbValor,MATCH($BU31,SgaProbNivel,0)),"")) | BX31: =IF($BV31="","",IFERROR(INDEX(SgaSevRiValor,MATCH($BV31,SgaSevRiNivel,0)),"")) | BY31: =IF(COUNT($BW31:$BX31)=2,$BW31*$BX31,"") | BZ31: =IF($BY31="","",IF($BY31<=SgaLimRiSig,"SIGNIFICATIVO",IF($BY31<=SgaLimRiTol,"TOLERÁVEL","BAIXO"))) | CA31: =IF($BZ31="","",IF($BZ31="SIGNIFICATIVO","NÃO ACEITÁVEL","ACEITÁVEL")) | CG31: =IF(OR($CE31="",$CF31=""),"",IFERROR(INDEX(SgaProbValor,MATCH($CE31,SgaProbNivel,0))*INDEX(SgaSevRiValor,MATCH($CF31,SgaSevRiNivel,0)),"")) | CH31: =IF($CG31="","",IF($CG31<=SgaLimRiSig,"SIGNIFICATIVO",IF($CG31<=SgaLimRiTol,"TOLERÁVEL","BAIXO")))
