Workbook
Name DataRef: Listas!$A$3
Name lst_Adesivo: Listas!$G$3:$G$6
Name lst_Aplicabilidade: Listas!$L$3:$L$6
Name lst_Barreira: Listas!$D$3:$D$6
Name lst_Classe: Listas!$J$3:$J$8
Name lst_CorCorpo: Listas!$C$3:$C$8
Name lst_DataReferencia: Listas!$A$3:$A$3
Name lst_Decoracao: Listas!$H$3:$H$6
Name lst_EstadoAlegacao: Listas!$Q$3:$Q$7
Name lst_EstadoAval: Listas!$T$3:$T$5
Name lst_EstadoReq: Listas!$M$3:$M$8
Name lst_Funcao: Listas!$S$3:$S$24
Name lst_Material: Listas!$B$3:$B$16
Name lst_Maturidade: Listas!$R$3:$R$5
Name lst_Natureza: Listas!$K$3:$K$7
Name lst_Risco: Listas!$N$3:$N$5
Name lst_Rotulo: Listas!$F$3:$F$8
Name lst_Segmento: Listas!$I$3:$I$5
Name lst_SimNao: Listas!$P$3:$P$4
Name lst_Vedante: Listas!$E$3:$E$5
Name lst_Verificacao: Listas!$O$3:$O$6
Name SegmentaçãoDeDados_Conforme_PPWR_2030: #N/A
Name SegmentaçãoDeDados_Cor_Corpo: #N/A
Name SegmentaçãoDeDados_Decoracao_Tipo: #N/A
Name SegmentaçãoDeDados_Estrutura_Material: #N/A
Name SegmentaçãoDeDados_Grau_PPWR_Indicativo: #N/A
Name SegmentaçãoDeDados_Segmento: #N/A

Sheet 00_LEIA-ME
A1: RG-SGA-20 — Reciclabilidade e Conformidade de Embalagens (RecyClass / PPWR)
A2: Sistema de Gestão Ambiental NP EN ISO 14001:2026 · Plasticom — Unidade 1 (Marinha Grande, Portugal) · Registo do SGA (fábrica simulada)
A4: CONTROLO DO DOCUMENTO (7.5 — informação documentada)
A5: Código do registo | B5: RG-SGA-20
A6: Título | B6: Reciclabilidade e Conformidade de Embalagens (RecyClass / PPWR)
A7: Versão / Revisão | B7: 00
A8: Data de emissão | B8: 46289
A9: Elaborado por | B9: Gestor(a) do SGA / EHS
A10: Aprovado por | B10: Diretor Geral
A11: Estado | B11: Em vigor
A12: Retenção | B12: 5 anos após substituição
A13: Localização | B13: Repositório controlado do SGA > Registos_SGA_Plasticom (versão eletrónica é a versão controlada; cópias impressas são não controladas)
A15: FINALIDADE E ÂMBITO
A16: Finalidade | B16: Registo de conformidade de produto das embalagens da Plasticom. A folha Avaliacao_RecyClass tem uma linha por SKU com todos os campos a introduzir na ferramenta online da RecyClass e calcula a classe (A–F), a taxa de reciclabilidade em massa e o grau PPWR indicativo com as regras de tbl_regras_dfr. Liga cada SKU aos requisitos legais aplicáveis (tbl_aplicabilidade), às famílias com declaração UE (tbl_familias_ppwr), aos certificados de reciclado e às vendas por país. A classificação é uma AUTOAVALIAÇÃO com regras simplificadas: o resultado oficial só vem da ferramenta RecyClass / certificação e dos atos delegados do PPWR (critérios de DfR previstos até 2028).
A17: Atividades do curso | B17: Complemento — reciclagem e reciclabilidade de embalagens: classificação RecyClass por SKU, graus PPWR, conteúdo reciclado, matriz legal e normativa de produto, países de destino e alegações.
A18: Requisitos ISO 14001:2026 | B18: 4.3 e) e 6.1.2 (perspetiva de ciclo de vida); 6.1.3 e 9.1.2 (obrigações de conformidade de produto); 8.1 (conceção e requisitos para fornecedores); 7.4 (alegações)
A20: ESTRUTURA DO FICHEIRO
A21: Parametros | B21: Parâmetros dos cálculos (limiares PPWR, massas de rótulo e decoração, logística, imposto espanhol, prestações RAP indicativas).
A22: Metas_Art7 | B22: Metas de conteúdo reciclado do PPWR por categoria (média por instalação de fabrico e por ano).
A23: Materiais | B23: Dimensão material: polímero, fluxo de reciclagem, densidade, teor de reciclado e marcação.
A24: Regras_DfR | B24: Regras de design para reciclagem (interpretação simplificada das diretrizes RecyClass para PE/PP rígidos e garrafas de PET).
A25: Tampas | B25: Componentes de fecho (tampas) com material, massa e comportamento na reciclagem.
A26: Avaliacao_RecyClass | B26: Uma linha por SKU: campos da ferramenta RecyClass, classe A–F, taxa de reciclabilidade, grau PPWR, reciclado e mercado.
A27: Compat_Tampas | B27: Compatibilidade de cada tampa com cada fluxo de corpo (guia comercial de combinação frasco + tampa).
A28: Familias_PPWR | B28: Famílias de embalagem para a documentação técnica e declaração UE de conformidade (base do KPI-12).
A29: Requisitos_Embalagem | B29: Matriz legal e normativa integrada de embalagens (UE, contacto alimentar, cosméticos, farmacêutico, ISO/EN, Portugal) com natureza da obrigação, papel da Plasticom, evidência e verificação da resposta do ChatGPT.
A30: Aplicabilidade_Produto | B30: Fact_Aplicabilidade: produto × requisito com aplicabilidade, motivo, estado calculado e evidência.
A31: Vendas_Pais | B31: Plástico colocado no mercado por SKU e país (base para RAP, imposto espanhol e metas do art. 7.º).
A32: Embalagens_Expedicao | B32: Embalagens de expedição colocadas no mercado por mês, país e material — base da declaração RAP (DL 152-D/2017).
... A40: Dicionario_Dados | B40: Descrição de cada coluna de cada tabela: tipo, origem (entrada/calculado), domínio, obrigatoriedade e chaves.
A42: CONVENÇÕES (prontas para análise de dados e machine learning)
A43: Tabelas | B43: Cada registo é uma Tabela Excel com nome próprio (tbl_*): uma linha = um registo, cabeçalho único, sem células mescladas. Ler com pandas (pd.read_excel(ficheiro, sheet_name=folha, header=<linha do cabeçalho - 1>)) ou Power BI (Obter Dados > Tabela).
A44: Cabeçalho cinzento | B44: Coluna CALCULADA por fórmula — não escrever por cima. As restantes colunas são de entrada.
A45: Validação | B45: Colunas com lista controlada só aceitam valores da folha Listas (evita categorias duplicadas por grafia diferente).
A46: Chaves | B46: IDs estáveis e únicos (PK) e referências a IDs de outros registos (FK) permitem juntar tabelas entre ficheiros — ver SGA-00_Indice_Modelo_Dados.xlsx.
A47: Datas e unidades | B47: Datas em formato data (aaaa-mm-dd); números como números; a unidade está no nome da coluna ou no dicionário. Data de referência do SGA: 2026-12-31 (fecho do ano).
A48: Dados simulados | B48: Fábrica simulada Plasticom. Dados operacionais derivados do dataset do projeto (datasets/silver); dados ambientais e de conformidade são simulação didática — confirmar aplicabilidade legal e números antes de uso real.
A50: LIGAÇÕES A OUTROS REGISTOS
A51: RG-SGA-04 Legal | B51: ID_Legal liga os requisitos a tbl_legal (LEG-09, LEG-16 a LEG-21).
A52: RG-SGA-05 KPI | B52: KPI-12 e KPI-17 a KPI-21 são calculados a partir deste registo.
A53: RG-SGA-06 PAM | B53: Ações PAM-26-10 e PAM-26-22 a PAM-26-27.
A54: RG-SGA-11 Fornecedores | B54: tbl_certificados_pcr[ID_Fornecedor] → tbl_fornecedores.
A55: RG-SGA-17 / RG-SGA-19 | B55: Evidências do tema DM-11 e indicador ESG-E29 (produtos recicláveis).
A56: Dataset | B56: Produtos, cores, masterbatch, decoração e vendas: datasets/silver (dim_bottle, dim_cap, dim_ink, fact_production, fact_sales).

Sheet Painel
A1: PAINEL DE RECICLABILIDADE E CONFORMIDADE DE EMBALAGENS — PLASTICOM
A2: Autoavaliação RecyClass (regras simplificadas) e graus PPWR indicativos · vendas de 2026 · atualiza com as tabelas
A4: Indicador | B4: Valor
A5: SKUs avaliados (frascos e potes) | B5: =COUNTA(tbl_recyclass[ProductId]) -> 113
A6: SKUs com grau PPWR A–C (não isentos) — KPI-18 | B6: =COUNTIFS(tbl_recyclass[Conforme_PPWR_2030],"Sim")/(COUNTA(tbl_recyclass[ProductId])-COUNTIF(tbl_recyclass[Segmento],"Farmacêutico")) -> 0.6635514
A7: Massa vendida com grau A–C (não isentos) — KPI-20 | B7: =SUMIFS(tbl_recyclass[Massa_Vendida_kg],tbl_recyclass[Conforme_PPWR_2030],"Sim")/SUMIFS(tbl_recyclass[Massa_Vendida_kg],tbl_recyclass[Segmento],"<>Farmacêutico") -> 0.59745288
A8: SKUs classe F (não recicláveis) | B8: =COUNTIF(tbl_recyclass[Classe_RecyClass],"F") -> 19
A9: SKUs isentos até 2035 (farmacêuticos) | B9: =COUNTIF(tbl_recyclass[Isencao_Art6],"Isento até 2035") -> 6
A10: Taxa média de reciclabilidade ponderada pela massa vendida | B10: =SUMPRODUCT(tbl_recyclass[Taxa_Reciclabilidade],tbl_recyclass[Massa_Vendida_kg])/SUM(tbl_recyclass[Massa_Vendida_kg]) -> 0.84411001
A11: Conteúdo reciclado ponderado (corpos + tampas vendidos) — KPI-19 | B11: =SUM(tbl_vendas_embalagem[Massa_Reciclado_kg])/SUM(tbl_vendas_embalagem[Massa_kg]) -> 0.11877847
A12: Famílias com declaração UE de conformidade — KPI-12 | B12: =COUNTIF(tbl_familias_ppwr[Declaracao_UE],"Sim")/COUNTA(tbl_familias_ppwr[ID_Familia]) -> 0.77272727
A13: Certificados de reciclado válidos — KPI-21 | B13: =(COUNTIF(tbl_certificados_pcr[Estado],"Válido")+COUNTIF(tbl_certificados_pcr[Estado],"Expira*"))/COUNTIFS(tbl_certificados_pcr[Pct_PCR_Declarado],">0") -> 1
A14: Imposto espanhol estimado (pago pelos clientes ES, €/ano) | B14: =SUM(tbl_vendas_embalagem[Imposto_ES_EUR]) -> 39016.803
A15: Requisitos da matriz em lacuna / parcial | B15: =COUNTIF(tbl_requisitos_emb[Estado],"Lacuna")&" / "&COUNTIF(tbl_requisitos_emb[Estado],"Parcial") -> 1 / 23
A16: Checklist de maturidade implementado | B16: =COUNTIF(tbl_maturidade_emb[Estado],"Implementado")/COUNTA(tbl_maturidade_emb[ID_Item]) -> 0.75
A17: Alegações a retirar / proibidas / suspensas | B17: =COUNTIF(tbl_alegacoes[Estado],"Retirar")+COUNTIF(tbl_alegacoes[Estado],"Proibida")+COUNTIF(tbl_alegacoes[Estado],"Suspensa") -> 4
A19: DISTRIBUIÇÃO POR CLASSE RECYCLASS
A20: Classe | B20: N.º SKUs | C20: Massa vendida (kg) | D20: % SKUs | E20: % massa
A21: A | B21: =COUNTIF(tbl_recyclass[Classe_RecyClass],A21) -> 26 | C21: =SUMIFS(tbl_recyclass[Massa_Vendida_kg],tbl_recyclass[Classe_RecyClass],A21) -> 82511.909 | D21: =B21/SUM($B$21:$B$26) -> 0.2300885 | E21: =C21/SUM($C$21:$C$26) -> 0.17634634
A22: B | B22: =COUNTIF(tbl_recyclass[Classe_RecyClass],A22) -> 25 | C22: =SUMIFS(tbl_recyclass[Massa_Vendida_kg],tbl_recyclass[Classe_RecyClass],A22) -> 109345.5 | D22: =B22/SUM($B$21:$B$26) -> 0.22123894 | E22: =C22/SUM($C$21:$C$26) -> 0.23369569
A23: C | B23: =COUNTIF(tbl_recyclass[Classe_RecyClass],A23) -> 26 | C23: =SUMIFS(tbl_recyclass[Massa_Vendida_kg],tbl_recyclass[Classe_RecyClass],A23) -> 92488.846 | D23: =B23/SUM($B$21:$B$26) -> 0.2300885 | E23: =C23/SUM($C$21:$C$26) -> 0.19766927
A24: D | B24: =COUNTIF(tbl_recyclass[Classe_RecyClass],A24) -> 17 | C24: =SUMIFS(tbl_recyclass[Massa_Vendida_kg],tbl_recyclass[Classe_RecyClass],A24) -> 111035.16 | D24: =B24/SUM($B$21:$B$26) -> 0.15044248 | E24: =C24/SUM($C$21:$C$26) -> 0.23730689
A25: E | B25: =COUNTIF(tbl_recyclass[Classe_RecyClass],A25) -> 0 | C25: =SUMIFS(tbl_recyclass[Massa_Vendida_kg],tbl_recyclass[Classe_RecyClass],A25) -> 0 | D25: =B25/SUM($B$21:$B$26) -> 0 | E25: =C25/SUM($C$21:$C$26) -> 0
A26: F | B26: =COUNTIF(tbl_recyclass[Classe_RecyClass],A26) -> 19 | C26: =SUMIFS(tbl_recyclass[Massa_Vendida_kg],tbl_recyclass[Classe_RecyClass],A26) -> 72515.513 | D26: =B26/SUM($B$21:$B$26) -> 0.16814159 | E26: =C26/SUM($C$21:$C$26) -> 0.15498181
A29: GRAU PPWR INDICATIVO × CONFORMIDADE 2030/2038
A30: Grau PPWR | B30: N.º SKUs | C30: Massa vendida (kg)
A31: A | B31: =COUNTIF(tbl_recyclass[Grau_PPWR_Indicativo],A31) -> 26 | C31: =SUMIFS(tbl_recyclass[Massa_Vendida_kg],tbl_recyclass[Grau_PPWR_Indicativo],A31) -> 82511.909
A32: B | B32: =COUNTIF(tbl_recyclass[Grau_PPWR_Indicativo],A32) -> 25 | C32: =SUMIFS(tbl_recyclass[Massa_Vendida_kg],tbl_recyclass[Grau_PPWR_Indicativo],A32) -> 109345.5
A33: C | B33: =COUNTIF(tbl_recyclass[Grau_PPWR_Indicativo],A33) -> 26 | C33: =SUMIFS(tbl_recyclass[Massa_Vendida_kg],tbl_recyclass[Grau_PPWR_Indicativo],A33) -> 92488.846
A34: Abaixo de C | B34: =COUNTIF(tbl_recyclass[Grau_PPWR_Indicativo],A34) -> 17 | C34: =SUMIFS(tbl_recyclass[Massa_Vendida_kg],tbl_recyclass[Grau_PPWR_Indicativo],A34) -> 111035.16
A35: Não reciclável (F) | B35: =COUNTIF(tbl_recyclass[Grau_PPWR_Indicativo],A35) -> 19 | C35: =SUMIFS(tbl_recyclass[Massa_Vendida_kg],tbl_recyclass[Grau_PPWR_Indicativo],A35) -> 72515.513
A38: CONTEÚDO RECICLADO FACE ÀS METAS DO ART. 7.º (média da instalação, ponderada pela massa vendida)
A39: Categoria art. 7.º | B39: Massa vendida (kg) | C39: Reciclado (%) | D39: Meta 2030 | E39: Gap (p.p.)
A40: Sensível ao contacto — PET | B40: =SUMIFS(tbl_recyclass[Massa_Vendida_kg],tbl_recyclass[Categoria_Art7],A40) -> 0 | C40: =IFERROR(SUMPRODUCT((tbl_recyclass[Categoria_Art7]=A40)*tbl_recyclass[Massa_Vendida_kg]*tbl_recyclass[Conteudo_Reciclado_Pct])/B40,"") | D40: =IFERROR(IF(INDEX(tbl_metas_art7[Meta_2030],MATCH(A40,tbl_metas_art7[Categoria_Art7],0))="","",INDEX(tbl_metas_art7[Meta_2030],MATCH(A40,tbl_metas_art7[Categoria_Art7],0))),"") -> 0.3 | E40: =IF(OR(C40="",D40=""),"",MAX(0,D40-C40))
A41: Sensível ao contacto — outros plásticos | B41: =SUMIFS(tbl_recyclass[Massa_Vendida_kg],tbl_recyclass[Categoria_Art7],A41) -> 21019.797 | C41: =IFERROR(SUMPRODUCT((tbl_recyclass[Categoria_Art7]=A41)*tbl_recyclass[Massa_Vendida_kg]*tbl_recyclass[Conteudo_Reciclado_Pct])/B41,"") -> 0 | D41: =IFERROR(IF(INDEX(tbl_metas_art7[Meta_2030],MATCH(A41,tbl_metas_art7[Categoria_Art7],0))="","",INDEX(tbl_metas_art7[Meta_2030],MATCH(A41,tbl_metas_art7[Categoria_Art7],0))),"") -> 0.1 | E41: =IF(OR(C41="",D41=""),"",MAX(0,D41-C41)) -> 0.1
A42: Garrafas de bebidas de utilização única | B42: =SUMIFS(tbl_recyclass[Massa_Vendida_kg],tbl_recyclass[Categoria_Art7],A42) -> 0 | C42: =IFERROR(SUMPRODUCT((tbl_recyclass[Categoria_Art7]=A42)*tbl_recyclass[Massa_Vendida_kg]*tbl_recyclass[Conteudo_Reciclado_Pct])/B42,"") | D42: =IFERROR(IF(INDEX(tbl_metas_art7[Meta_2030],MATCH(A42,tbl_metas_art7[Categoria_Art7],0))="","",INDEX(tbl_metas_art7[Meta_2030],MATCH(A42,tbl_metas_art7[Categoria_Art7],0))),"") -> 0.3 | E42: =IF(OR(C42="",D42=""),"",MAX(0,D42-C42))
A43: Outras embalagens de plástico | B43: =SUMIFS(tbl_recyclass[Massa_Vendida_kg],tbl_recyclass[Categoria_Art7],A43) -> 434953.35 | C43: =IFERROR(SUMPRODUCT((tbl_recyclass[Categoria_Art7]=A43)*tbl_recyclass[Massa_Vendida_kg]*tbl_recyclass[Conteudo_Reciclado_Pct])/B43,"") -> 0.1220339 | D43: =IFERROR(IF(INDEX(tbl_metas_art7[Meta_2030],MATCH(A43,tbl_metas_art7[Categoria_Art7],0))="","",INDEX(tbl_metas_art7[Meta_2030],MATCH(A43,tbl_metas_art7[Categoria_Art7],0))),"") -> 0.35 | E43: =IF(OR(C43="",D43=""),"",MAX(0,D43-C43)) -> 0.2279661
A44: Isenta — medicamentos (art. 7.º) | B44: =SUMIFS(tbl_recyclass[Massa_Vendida_kg],tbl_recyclass[Categoria_Art7],A44) -> 11923.777 | C44: =IFERROR(SUMPRODUCT((tbl_recyclass[Categoria_Art7]=A44)*tbl_recyclass[Massa_Vendida_kg]*tbl_recyclass[Conteudo_Reciclado_Pct])/B44,"") -> 0 | D44: =IFERROR(IF(INDEX(tbl_metas_art7[Meta_2030],MATCH(A44,tbl_metas_art7[Categoria_Art7],0))="","",INDEX(tbl_metas_art7[Meta_2030],MATCH(A44,tbl_metas_art7[Categoria_Art7],0))),"") | E44: =IF(OR(C44="",D44=""),"",MAX(0,D44-C44))
A47: ANÁLISE DINÂMICA (tabela dinâmica e segmentações — atualizar com Dados > Atualizar tudo)
A50: N.º de SKUs | C50: Classe_RecyClass
A51: Fluxo_Reciclagem | B51: Material_Corpo | C51: A | D51: B | E51: C | F51: D | G51: F | H51: Total Geral
A52: PE rígido | B52: HDPE | C52: 3 | D52: 7 | E52: 6 | G52: 3 | H52: 19
B53: HDPE-FG | C53: 2 | H53: 2
B54: HDPE-PCR | C54: 1 | D54: 10 | E54: 2 | H54: 13
B55: LDPE | D55: 1 | E55: 2 | H55: 3
B56: MDPE | D56: 1 | E56: 3 | G56: 1 | H56: 5
A57: PE rígido Total | C57: 6 | D57: 19 | E57: 13 | G57: 4 | H57: 42
A58: PET frascos e garrafas | B58: PET | C58: 3 | E58: 4 | F58: 6 | H58: 13
B59: PET-PG | E59: 2 | H59: 2
B60: rPET | C60: 8 | F60: 11 | H60: 19
A61: PET frascos e garrafas Total | C61: 11 | E61: 6 | F61: 17 | H61: 34
A62: PP rígido | B62: PP | C62: 6 | D62: 2 | E62: 1 | G62: 2 | H62: 11
B63: PP-FG | C63: 2 | H63: 2
B64: PP-PCR | C64: 1 | D64: 4 | E64: 2 | G64: 1 | H64: 8
B65: PP-PG | E65: 4 | H65: 4
A66: PP rígido Total | C66: 9 | D66: 6 | E66: 7 | G66: 3 | H66: 25
A67: Sem fluxo (PETG) | B67: PETG | G67: 8 | H67: 8
A68: Sem fluxo (PETG) Total | G68: 8 | H68: 8
A69: Sem fluxo (PVC) | B69: PVC | G69: 4 | H69: 4
A70: Sem fluxo (PVC) Total | G70: 4 | H70: 4
A71: Total Geral | C71: 26 | D71: 25 | E71: 26 | F71: 17 | G71: 19 | H71: 113

Sheet Parametros
A1: PARÂMETROS DE CÁLCULO
A2: Editar a coluna Valor; as fórmulas das outras folhas atualizam-se
A4: ID_Parametro | B4: Parametro | C4: Valor | D4: Unidade | E4: Fonte
A5: P-01 | B5: Imposto espanhol sobre embalagens de plástico não reutilizáveis (Lei 7/2022) | C5: 0.45 | D5: €/kg de plástico não reciclado | E5: BOE — Ley 7/2022, art. 81.º (confirmar taxa em vigor)
A6: P-02 | B6: Gramagem de rótulo de filme PE/PP/PET | C6: 55 | D6: g/m² | E6: Estimativa técnica (filme 60 µm + adesivo)
A7: P-03 | B7: Gramagem de rótulo de papel | C7: 75 | D7: g/m² | E7: Estimativa técnica
A8: P-04 | B8: Tinta de serigrafia depositada por cor | C8: 0.08 | D8: g/un | E8: RG-SGA-13 (0,24 kg/1.000 peças para ≈ 3 cores)
A9: P-05 | B9: Metalização de hot foil transferida para a peça | C9: 0.03 | D9: g/un | E9: Estimativa (foil consumido 1,9 kg/1.000; filme de suporte vai para resíduo)
A10: P-06 | B10: Limiar do grau PPWR A (taxa de reciclabilidade em massa) | C10: 0.95 | D10: fração | E10: Reg. (UE) 2025/40, anexo II, quadro 3
A11: P-07 | B11: Limiar do grau PPWR B | C11: 0.8 | D11: fração | E11: Reg. (UE) 2025/40, anexo II, quadro 3
A12: P-08 | B12: Limiar do grau PPWR C | C12: 0.7 | D12: fração | E12: Reg. (UE) 2025/40, anexo II, quadro 3
A13: P-09 | B13: Cartão por caixa de expedição | C13: 0.45 | D13: kg/caixa | E13: Especificação logística Plasticom
A14: P-10 | B14: Frascos por caixa | C14: 250 | D14: un/caixa | E14: Especificação logística (média)
A15: P-11 | B15: Tampas por caixa | C15: 1000 | D15: un/caixa | E15: Especificação logística (média)
A16: P-12 | B16: Caixas por palete | C16: 40 | D16: caixas/palete | E16: Especificação logística
... A21: P-17 | B21: Prestação financeira — madeira (embalagens não urbanas, PT) | C21: 0.01 | D21: €/kg | E21: Valor INDICATIVO — substituir pela tabela da entidade gestora em vigor
A23: Metas de teor mínimo de plástico reciclado — PPWR art. 7.º (tabela tbl_metas_art7 na folha Metas_Art7)

Sheet Metas_Art7
A1: Categoria_Art7 | B1: Meta_2030 | C1: Meta_2040 | D1: Base_Legal | E1: Nota
A2: Sensível ao contacto — PET | B2: 0.3 | C2: 0.5 | D2: Art. 7.º, n.º 1, al. a) e n.º 2, al. a) | E2: Inclui embalagens alimentares de PET (exceto garrafas de bebidas).
A3: Sensível ao contacto — outros plásticos | B3: 0.1 | C3: 0.25 | D3: Art. 7.º, n.º 1, al. b) e n.º 2, al. b) | E3: Embalagens alimentares de PE/PP: o reciclado tem de cumprir o Reg. (UE) 2022/1616.
A4: Garrafas de bebidas de utilização única | B4: 0.3 | C4: 0.65 | D4: Art. 7.º, n.º 1, al. c) e n.º 2, al. c) | E4: Sem SKUs atuais (confirmar uso de FA-030/031).
A5: Outras embalagens de plástico | B5: 0.35 | C5: 0.65 | D5: Art. 7.º, n.º 1, al. d) e n.º 2, al. d) | E5: Cosmética e higiene: pressupõe-se que NÃO é 'sensível ao contacto' (confirmar a definição do art. 3.º) — cenário conservador.
A6: Isenta — medicamentos (art. 7.º) | D6: Art. 7.º (isenções) | E6: Embalagem sensível ao contacto de medicamentos para uso humano e veterinário.

Sheet Materiais
A1: Material | B1: Polimero_Base | C1: Fluxo_Reciclagem | D1: Densidade_g_cm3 | E1: Grau | F1: Pct_PCR | G1: Codigo_Identificacao | H1: ID_Fornecedor | I1: N_SKUs_Corpo | J1: Massa_Vendida_kg
A2: HDPE | B2: PE | C2: PE rígido | D2: 0.955 | E2: Virgem | F2: 0 | G2: >PE-HD< (2) | H2: SUP-001 | I2: =COUNTIF(tbl_recyclass[Material_Corpo],A2) -> 19 | J2: =SUMIFS(tbl_recyclass[Massa_Vendida_kg],tbl_recyclass[Material_Corpo],A2) -> 116243.82
A3: HDPE-PCR | B3: PE | C3: PE rígido | D3: 0.96 | E3: Reciclado pós-consumo | F3: 0.3 | G3: >PE-HD< (2) | H3: SUP-004 | I3: =COUNTIF(tbl_recyclass[Material_Corpo],A3) -> 13 | J3: =SUMIFS(tbl_recyclass[Massa_Vendida_kg],tbl_recyclass[Material_Corpo],A3) -> 62714.338
A4: MDPE | B4: PE | C4: PE rígido | D4: 0.935 | E4: Virgem | F4: 0 | G4: >PE-MD< (4) | H4: SUP-001 | I4: =COUNTIF(tbl_recyclass[Material_Corpo],A4) -> 5 | J4: =SUMIFS(tbl_recyclass[Massa_Vendida_kg],tbl_recyclass[Material_Corpo],A4) -> 18154.214
A5: LDPE | B5: PE | C5: PE rígido | D5: 0.92 | E5: Virgem | F5: 0 | G5: >PE-LD< (4) | H5: SUP-007 | I5: =COUNTIF(tbl_recyclass[Material_Corpo],A5) -> 3 | J5: =SUMIFS(tbl_recyclass[Massa_Vendida_kg],tbl_recyclass[Material_Corpo],A5) -> 4869.9023
A6: HDPE-FG | B6: PE | C6: PE rígido | D6: 0.955 | E6: Grau alimentar (FCM) | F6: 0 | G6: >PE-HD< (2) | H6: SUP-010 | I6: =COUNTIF(tbl_recyclass[Material_Corpo],A6) -> 2 | J6: =SUMIFS(tbl_recyclass[Massa_Vendida_kg],tbl_recyclass[Material_Corpo],A6) -> 10553.735
A7: PP | B7: PP | C7: PP rígido | D7: 0.905 | E7: Virgem | F7: 0 | G7: >PP< (5) | H7: SUP-002 | I7: =COUNTIF(tbl_recyclass[Material_Corpo],A7) -> 11 | J7: =SUMIFS(tbl_recyclass[Massa_Vendida_kg],tbl_recyclass[Material_Corpo],A7) -> 25144.037
A8: PP-PCR | B8: PP | C8: PP rígido | D8: 0.91 | E8: Reciclado pós-consumo | F8: 0.3 | G8: >PP< (5) | H8: SUP-002 | I8: =COUNTIF(tbl_recyclass[Material_Corpo],A8) -> 8 | J8: =SUMIFS(tbl_recyclass[Massa_Vendida_kg],tbl_recyclass[Material_Corpo],A8) -> 18727.65
A9: PP-FG | B9: PP | C9: PP rígido | D9: 0.905 | E9: Grau alimentar (FCM) | F9: 0 | G9: >PP< (5) | H9: SUP-010 | I9: =COUNTIF(tbl_recyclass[Material_Corpo],A9) -> 2 | J9: =SUMIFS(tbl_recyclass[Massa_Vendida_kg],tbl_recyclass[Material_Corpo],A9) -> 10466.062
A10: PP-PG | B10: PP | C10: PP rígido | D10: 0.905 | E10: Grau farmacêutico | F10: 0 | G10: >PP< (5) | H10: SUP-009 | I10: =COUNTIF(tbl_recyclass[Material_Corpo],A10) -> 4 | J10: =SUMIFS(tbl_recyclass[Massa_Vendida_kg],tbl_recyclass[Material_Corpo],A10) -> 7385.1153
A11: PET | B11: PET | C11: PET frascos e garrafas | D11: 1.38 | E11: Virgem | F11: 0 | G11: >PET< (1) | H11: SUP-003 | I11: =COUNTIF(tbl_recyclass[Material_Corpo],A11) -> 13 | J11: =SUMIFS(tbl_recyclass[Massa_Vendida_kg],tbl_recyclass[Material_Corpo],A11) -> 76802.716
A12: rPET | B12: PET | C12: PET frascos e garrafas | D12: 1.38 | E12: Reciclado pós-consumo | F12: 0.5 | G12: >PET< (1) | H12: SUP-004 | I12: =COUNTIF(tbl_recyclass[Material_Corpo],A12) -> 19 | J12: =SUMIFS(tbl_recyclass[Massa_Vendida_kg],tbl_recyclass[Material_Corpo],A12) -> 83695.046
A13: PET-PG | B13: PET | C13: PET frascos e garrafas | D13: 1.38 | E13: Grau farmacêutico | F13: 0 | G13: >PET< (1) | H13: SUP-009 | I13: =COUNTIF(tbl_recyclass[Material_Corpo],A13) -> 2 | J13: =SUMIFS(tbl_recyclass[Massa_Vendida_kg],tbl_recyclass[Material_Corpo],A13) -> 4538.6619
... A15: PVC | B15: PVC | C15: Sem fluxo (PVC) | D15: 1.35 | E15: Virgem | F15: 0 | G15: >PVC< (3) | H15: SUP-005 | I15: =COUNTIF(tbl_recyclass[Material_Corpo],A15) -> 4 | J15: =SUMIFS(tbl_recyclass[Massa_Vendida_kg],tbl_recyclass[Material_Corpo],A15) -> 10112.811

Sheet Regras_DfR
A1: REGRAS DE DESIGN PARA RECICLAGEM (DfR) — BASE DO CÁLCULO RECYCLASS
A2: Interpretação simplificada das diretrizes RecyClass (HDPE/PP containers, PET bottles) · Classe final = pior característica · Editar Classe/Fração para recalibrar
A4: Chave | B4: Fluxo | C4: Caracteristica | D4: Valor | E4: Classe | F4: Compatibilidade | G4: Fracao_Reciclavel | H4: Fundamentacao | I4: Recomendacao
A5: =B5&"|"&C5&"|"&D5 -> PE rígido|Fluxo de reciclagem|PE rígido | B5: PE rígido | C5: Fluxo de reciclagem | D5: PE rígido | E5: A | F5: =CHOOSE(MATCH(E5,{"A","B","C","D","E","F"},0),"Totalmente compatível","Compatibilidade limitada","Compatibilidade limitada (afeta a qualidade)","Problemas significativos","Problemas graves","Não reciclável / não compatível") -> Totalmente compatível | G5: 1 | H5: Fluxo de triagem e reciclagem mecânica estabelecido na Europa. | I5: Sem ação — manter.
A6: =B6&"|"&C6&"|"&D6 -> PP rígido|Fluxo de reciclagem|PP rígido | B6: PP rígido | C6: Fluxo de reciclagem | D6: PP rígido | E6: A | F6: =CHOOSE(MATCH(E6,{"A","B","C","D","E","F"},0),"Totalmente compatível","Compatibilidade limitada","Compatibilidade limitada (afeta a qualidade)","Problemas significativos","Problemas graves","Não reciclável / não compatível") -> Totalmente compatível | G6: 1 | H6: Fluxo de triagem e reciclagem mecânica estabelecido na Europa. | I6: Sem ação — manter.
A7: =B7&"|"&C7&"|"&D7 -> PET frascos e garrafas|Fluxo de reciclagem|PET frascos e garrafas | B7: PET frascos e garrafas | C7: Fluxo de reciclagem | D7: PET frascos e garrafas | E7: A | F7: =CHOOSE(MATCH(E7,{"A","B","C","D","E","F"},0),"Totalmente compatível","Compatibilidade limitada","Compatibilidade limitada (afeta a qualidade)","Problemas significativos","Problemas graves","Não reciclável / não compatível") -> Totalmente compatível | G7: 1 | H7: Fluxo de triagem e reciclagem mecânica estabelecido na Europa. | I7: Sem ação — manter.
A8: =B8&"|"&C8&"|"&D8 -> Sem fluxo (PETG)|Fluxo de reciclagem|Sem fluxo (PETG) | B8: Sem fluxo (PETG) | C8: Fluxo de reciclagem | D8: Sem fluxo (PETG) | E8: F | F8: =CHOOSE(MATCH(E8,{"A","B","C","D","E","F"},0),"Totalmente compatível","Compatibilidade limitada","Compatibilidade limitada (afeta a qualidade)","Problemas significativos","Problemas graves","Não reciclável / não compatível") -> Não reciclável / não compatível | G8: 0 | H8: PETG não tem fluxo de reciclagem dedicado; é triado com o PET e perturba o processo (amolece a temperaturas de secagem do PET). | I8: Mudar o corpo para PET (ou PP/PE) — PETG não passa a grau C em 2030.
A9: =B9&"|"&C9&"|"&D9 -> Sem fluxo (PVC)|Fluxo de reciclagem|Sem fluxo (PVC) | B9: Sem fluxo (PVC) | C9: Fluxo de reciclagem | D9: Sem fluxo (PVC) | E9: F | F9: =CHOOSE(MATCH(E9,{"A","B","C","D","E","F"},0),"Totalmente compatível","Compatibilidade limitada","Compatibilidade limitada (afeta a qualidade)","Problemas significativos","Problemas graves","Não reciclável / não compatível") -> Não reciclável / não compatível | G9: 0 | H9: Sem fluxo de reciclagem de embalagens domésticas de PVC; contamina o PET (HCl na extrusão). | I9: Eliminar o PVC do portfólio (substituir por PET ou PP).
A10: =B10&"|"&C10&"|"&D10 -> PE rígido|Cor do corpo|Natural / incolor | B10: PE rígido | C10: Cor do corpo | D10: Natural / incolor | E10: A | F10: =CHOOSE(MATCH(E10,{"A","B","C","D","E","F"},0),"Totalmente compatível","Compatibilidade limitada","Compatibilidade limitada (afeta a qualidade)","Problemas significativos","Problemas graves","Não reciclável / não compatível") -> Totalmente compatível | G10: 1 | H10: Reciclado incolor de maior valor. | I10: Sem ação — manter.
A11: =B11&"|"&C11&"|"&D11 -> PE rígido|Cor do corpo|Branco (TiO2) | B11: PE rígido | C11: Cor do corpo | D11: Branco (TiO2) | E11: A | F11: =CHOOSE(MATCH(E11,{"A","B","C","D","E","F"},0),"Totalmente compatível","Compatibilidade limitada","Compatibilidade limitada (afeta a qualidade)","Problemas significativos","Problemas graves","Não reciclável / não compatível") -> Totalmente compatível | G11: 1 | H11: Cores claras/brancas totalmente compatíveis. | I11: Sem ação — manter.
A12: =B12&"|"&C12&"|"&D12 -> PE rígido|Cor do corpo|Colorido (claro ou transparente) | B12: PE rígido | C12: Cor do corpo | D12: Colorido (claro ou transparente) | E12: B | F12: =CHOOSE(MATCH(E12,{"A","B","C","D","E","F"},0),"Totalmente compatível","Compatibilidade limitada","Compatibilidade limitada (afeta a qualidade)","Problemas significativos","Problemas graves","Não reciclável / não compatível") -> Compatibilidade limitada | G12: 1 | H12: Reciclado de PE colorido — valor e aplicações mais limitados. | I12: Preferir natural, branco ou cores claras.
A13: =B13&"|"&C13&"|"&D13 -> PE rígido|Cor do corpo|Colorido escuro / opaco | B13: PE rígido | C13: Cor do corpo | D13: Colorido escuro / opaco | E13: B | F13: =CHOOSE(MATCH(E13,{"A","B","C","D","E","F"},0),"Totalmente compatível","Compatibilidade limitada","Compatibilidade limitada (afeta a qualidade)","Problemas significativos","Problemas graves","Não reciclável / não compatível") -> Compatibilidade limitada | G13: 1 | H13: Reciclado de PE escuro — só aplicações escuras. | I13: Preferir cores claras.
A14: =B14&"|"&C14&"|"&D14 -> PE rígido|Cor do corpo|Preto (negro de carbono) | B14: PE rígido | C14: Cor do corpo | D14: Preto (negro de carbono) | E14: F | F14: =CHOOSE(MATCH(E14,{"A","B","C","D","E","F"},0),"Totalmente compatível","Compatibilidade limitada","Compatibilidade limitada (afeta a qualidade)","Problemas significativos","Problemas graves","Não reciclável / não compatível") -> Não reciclável / não compatível | G14: 0 | H14: Negro de carbono absorve o infravermelho próximo: a embalagem não é identificada na triagem NIR e vai para refugo. | I14: Substituir o masterbatch por preto detetável por NIR (pigmentos sem negro de carbono).
A15: =B15&"|"&C15&"|"&D15 -> PE rígido|Cor do corpo|Preto detetável por NIR | B15: PE rígido | C15: Cor do corpo | D15: Preto detetável por NIR | E15: B | F15: =CHOOSE(MATCH(E15,{"A","B","C","D","E","F"},0),"Totalmente compatível","Compatibilidade limitada","Compatibilidade limitada (afeta a qualidade)","Problemas significativos","Problemas graves","Não reciclável / não compatível") -> Compatibilidade limitada | G15: 1 | H15: Detetável na triagem; reciclado escuro. | I15: Manter pigmento detetável por NIR e validar com teste de triagem.
A16: =B16&"|"&C16&"|"&D16 -> PE rígido|Densidade do corpo|< 1,0 g/cm³ | B16: PE rígido | C16: Densidade do corpo | D16: < 1,0 g/cm³ | E16: A | F16: =CHOOSE(MATCH(E16,{"A","B","C","D","E","F"},0),"Totalmente compatível","Compatibilidade limitada","Compatibilidade limitada (afeta a qualidade)","Problemas significativos","Problemas graves","Não reciclável / não compatível") -> Totalmente compatível | G16: 1 | H16: Flutua em água: separado corretamente das impurezas no tanque de afunda-flutua. | I16: Sem ação — manter.
... A117: =B117&"|"&C117&"|"&D117 -> PET frascos e garrafas|Decoração direta|Hot foil metalizado | B117: PET frascos e garrafas | C117: Decoração direta | D117: Hot foil metalizado | E117: D | F117: =CHOOSE(MATCH(E117,{"A","B","C","D","E","F"},0),"Totalmente compatível","Compatibilidade limitada","Compatibilidade limitada (afeta a qualidade)","Problemas significativos","Problemas graves","Não reciclável / não compatível") -> Problemas significativos | G117: 0 | H117: Metalização e verniz não removíveis contaminam os flocos. | I117: Rótulo metalizado de PE/PP destacável.

Sheet Tampas
A1: CapId | B1: Descricao | C1: Tipo_Abertura | D1: Material | E1: Polimero_Base | F1: Massa_g | G1: Densidade_g_cm3 | H1: Flutua_Agua | I1: Rosca | J1: Vedante | K1: Pct_PCR | L1: Familia_PPWR | M1: Unid_Vendidas_P12 | N1: Paises_Venda | O1: Massa_Vendida_kg
A2: TR-001-HDPE-24410 | B2: Tampa rosca comum 24/410 HDPE | C2: Screw Cap | D2: HDPE | E2: =IFERROR(INDEX(tbl_materiais[Polimero_Base],MATCH(D2,tbl_materiais[Material],0)),"") -> PE | F2: 11.5 | G2: =IFERROR(INDEX(tbl_materiais[Densidade_g_cm3],MATCH(D2,tbl_materiais[Material],0)),"") -> 0.955 | H2: =IF(G2="","",IF(G2<1,"Sim","Não")) -> Sim | I2: 24/410 | J2: Sem vedante | K2: =IFERROR(INDEX(tbl_materiais[Pct_PCR],MATCH(D2,tbl_materiais[Material],0)),0) -> 0 | L2: FAM-18 | M2: 1595447 | N2: DE; ES; FR; IT; PL; PT | O2: =M2*F2/1000 -> 18347.641
A3: TR-001-PP-24410 | B3: Tampa rosca comum 24/410 PP | C3: Screw Cap | D3: PP | E3: =IFERROR(INDEX(tbl_materiais[Polimero_Base],MATCH(D3,tbl_materiais[Material],0)),"") -> PP | F3: 10.3 | G3: =IFERROR(INDEX(tbl_materiais[Densidade_g_cm3],MATCH(D3,tbl_materiais[Material],0)),"") -> 0.905 | H3: =IF(G3="","",IF(G3<1,"Sim","Não")) -> Sim | I3: 24/410 | J3: Sem vedante | K3: =IFERROR(INDEX(tbl_materiais[Pct_PCR],MATCH(D3,tbl_materiais[Material],0)),0) -> 0 | L3: FAM-16 | M3: 1539973 | N3: DE; ES; FR; IT; PL; PT | O3: =M3*F3/1000 -> 15861.722
A4: TR-001-PP-PCR-24410 | B4: Tampa rosca comum 24/410 PP-PCR | C4: Screw Cap | D4: PP-PCR | E4: =IFERROR(INDEX(tbl_materiais[Polimero_Base],MATCH(D4,tbl_materiais[Material],0)),"") -> PP | F4: 10.3 | G4: =IFERROR(INDEX(tbl_materiais[Densidade_g_cm3],MATCH(D4,tbl_materiais[Material],0)),"") -> 0.91 | H4: =IF(G4="","",IF(G4<1,"Sim","Não")) -> Sim | I4: 24/410 | J4: Sem vedante | K4: =IFERROR(INDEX(tbl_materiais[Pct_PCR],MATCH(D4,tbl_materiais[Material],0)),0) -> 0.3 | L4: FAM-17 | M4: 1197253 | N4: DE; ES; FR; IT; PL; PT | O4: =M4*F4/1000 -> 12331.706
A5: TR-001-PETG-24410 | B5: Tampa rosca comum 24/410 PETG | C5: Screw Cap | D5: PETG | E5: =IFERROR(INDEX(tbl_materiais[Polimero_Base],MATCH(D5,tbl_materiais[Material],0)),"") -> PETG | F5: 12.1 | G5: =IFERROR(INDEX(tbl_materiais[Densidade_g_cm3],MATCH(D5,tbl_materiais[Material],0)),"") -> 1.27 | H5: =IF(G5="","",IF(G5<1,"Sim","Não")) -> Não | I5: 24/410 | J5: Sem vedante | K5: =IFERROR(INDEX(tbl_materiais[Pct_PCR],MATCH(D5,tbl_materiais[Material],0)),0) -> 0 | L5: FAM-19 | M5: 1380640 | N5: DE; ES; FR; IT; PL; PT | O5: =M5*F5/1000 -> 16705.744
A6: TR-002-HDPE-24410 | B6: Tampa rosca comum 24/410 HDPE | C6: Screw Cap | D6: HDPE | E6: =IFERROR(INDEX(tbl_materiais[Polimero_Base],MATCH(D6,tbl_materiais[Material],0)),"") -> PE | F6: 11.5 | G6: =IFERROR(INDEX(tbl_materiais[Densidade_g_cm3],MATCH(D6,tbl_materiais[Material],0)),"") -> 0.955 | H6: =IF(G6="","",IF(G6<1,"Sim","Não")) -> Sim | I6: 24/410 | J6: Sem vedante | K6: =IFERROR(INDEX(tbl_materiais[Pct_PCR],MATCH(D6,tbl_materiais[Material],0)),0) -> 0 | L6: FAM-18 | M6: 617081 | N6: DE; ES; FR; IT; PL; PT | O6: =M6*F6/1000 -> 7096.4315
A7: TR-002-PP-24410 | B7: Tampa rosca comum 24/410 PP | C7: Screw Cap | D7: PP | E7: =IFERROR(INDEX(tbl_materiais[Polimero_Base],MATCH(D7,tbl_materiais[Material],0)),"") -> PP | F7: 10.3 | G7: =IFERROR(INDEX(tbl_materiais[Densidade_g_cm3],MATCH(D7,tbl_materiais[Material],0)),"") -> 0.905 | H7: =IF(G7="","",IF(G7<1,"Sim","Não")) -> Sim | I7: 24/410 | J7: Sem vedante | K7: =IFERROR(INDEX(tbl_materiais[Pct_PCR],MATCH(D7,tbl_materiais[Material],0)),0) -> 0 | L7: FAM-16 | M7: 507368 | N7: DE; ES; FR; IT; PL; PT | O7: =M7*F7/1000 -> 5225.8904
A8: TR-002-PP-PCR-24410 | B8: Tampa rosca comum 24/410 PP-PCR | C8: Screw Cap | D8: PP-PCR | E8: =IFERROR(INDEX(tbl_materiais[Polimero_Base],MATCH(D8,tbl_materiais[Material],0)),"") -> PP | F8: 10.3 | G8: =IFERROR(INDEX(tbl_materiais[Densidade_g_cm3],MATCH(D8,tbl_materiais[Material],0)),"") -> 0.91 | H8: =IF(G8="","",IF(G8<1,"Sim","Não")) -> Sim | I8: 24/410 | J8: Sem vedante | K8: =IFERROR(INDEX(tbl_materiais[Pct_PCR],MATCH(D8,tbl_materiais[Material],0)),0) -> 0.3 | L8: FAM-17 | M8: 488734 | N8: DE; ES; FR; IT; PL; PT | O8: =M8*F8/1000 -> 5033.9602
A9: TR-002-PETG-24410 | B9: Tampa rosca comum 24/410 PETG | C9: Screw Cap | D9: PETG | E9: =IFERROR(INDEX(tbl_materiais[Polimero_Base],MATCH(D9,tbl_materiais[Material],0)),"") -> PETG | F9: 12.1 | G9: =IFERROR(INDEX(tbl_materiais[Densidade_g_cm3],MATCH(D9,tbl_materiais[Material],0)),"") -> 1.27 | H9: =IF(G9="","",IF(G9<1,"Sim","Não")) -> Não | I9: 24/410 | J9: Sem vedante | K9: =IFERROR(INDEX(tbl_materiais[Pct_PCR],MATCH(D9,tbl_materiais[Material],0)),0) -> 0 | L9: FAM-19 | M9: 533504 | N9: DE; ES; FR; IT; PL; PT | O9: =M9*F9/1000 -> 6455.3984
A10: TR-003-HDPE-24415 | B10: Tampa rosca comum 24/415 HDPE | C10: Screw Cap | D10: HDPE | E10: =IFERROR(INDEX(tbl_materiais[Polimero_Base],MATCH(D10,tbl_materiais[Material],0)),"") -> PE | F10: 11.5 | G10: =IFERROR(INDEX(tbl_materiais[Densidade_g_cm3],MATCH(D10,tbl_materiais[Material],0)),"") -> 0.955 | H10: =IF(G10="","",IF(G10<1,"Sim","Não")) -> Sim | I10: 24/415 | J10: Sem vedante | K10: =IFERROR(INDEX(tbl_materiais[Pct_PCR],MATCH(D10,tbl_materiais[Material],0)),0) -> 0 | L10: FAM-18 | M10: 656567 | N10: DE; ES; FR; IT; PL; PT | O10: =M10*F10/1000 -> 7550.5205
A11: TR-003-PP-24415 | B11: Tampa rosca comum 24/415 PP | C11: Screw Cap | D11: PP | E11: =IFERROR(INDEX(tbl_materiais[Polimero_Base],MATCH(D11,tbl_materiais[Material],0)),"") -> PP | F11: 10.3 | G11: =IFERROR(INDEX(tbl_materiais[Densidade_g_cm3],MATCH(D11,tbl_materiais[Material],0)),"") -> 0.905 | H11: =IF(G11="","",IF(G11<1,"Sim","Não")) -> Sim | I11: 24/415 | J11: Sem vedante | K11: =IFERROR(INDEX(tbl_materiais[Pct_PCR],MATCH(D11,tbl_materiais[Material],0)),0) -> 0 | L11: FAM-16 | M11: 668908 | N11: DE; ES; FR; IT; PL; PT | O11: =M11*F11/1000 -> 6889.7524
A12: TR-003-PP-PCR-24415 | B12: Tampa rosca comum 24/415 PP-PCR | C12: Screw Cap | D12: PP-PCR | E12: =IFERROR(INDEX(tbl_materiais[Polimero_Base],MATCH(D12,tbl_materiais[Material],0)),"") -> PP | F12: 10.3 | G12: =IFERROR(INDEX(tbl_materiais[Densidade_g_cm3],MATCH(D12,tbl_materiais[Material],0)),"") -> 0.91 | H12: =IF(G12="","",IF(G12<1,"Sim","Não")) -> Sim | I12: 24/415 | J12: Sem vedante | K12: =IFERROR(INDEX(tbl_materiais[Pct_PCR],MATCH(D12,tbl_materiais[Material],0)),0) -> 0.3 | L12: FAM-17 | M12: 705915 | N12: DE; ES; FR; IT; PL; PT | O12: =M12*F12/1000 -> 7270.9245
A13: TR-003-PETG-24415 | B13: Tampa rosca comum 24/415 PETG | C13: Screw Cap | D13: PETG | E13: =IFERROR(INDEX(tbl_materiais[Polimero_Base],MATCH(D13,tbl_materiais[Material],0)),"") -> PETG | F13: 12.1 | G13: =IFERROR(INDEX(tbl_materiais[Densidade_g_cm3],MATCH(D13,tbl_materiais[Material],0)),"") -> 1.27 | H13: =IF(G13="","",IF(G13<1,"Sim","Não")) -> Não | I13: 24/415 | J13: Sem vedante | K13: =IFERROR(INDEX(tbl_materiais[Pct_PCR],MATCH(D13,tbl_materiais[Material],0)),0) -> 0 | L13: FAM-19 | M13: 775757 | N13: DE; ES; FR; IT; PL; PT | O13: =M13*F13/1000 -> 9386.6597
... A35: TP-013-PP-PG-070 | B35: Tampa de pote 70mm PP-PG | C35: Snap Lid | D35: PP-PG | E35: =IFERROR(INDEX(tbl_materiais[Polimero_Base],MATCH(D35,tbl_materiais[Material],0)),"") -> PP | F35: 16.5 | G35: =IFERROR(INDEX(tbl_materiais[Densidade_g_cm3],MATCH(D35,tbl_materiais[Material],0)),"") -> 0.905 | H35: =IF(G35="","",IF(G35<1,"Sim","Não")) -> Sim | I35: Snap 70mm | J35: Sem vedante | K35: =IFERROR(INDEX(tbl_materiais[Pct_PCR],MATCH(D35,tbl_materiais[Material],0)),0) -> 0 | L35: FAM-20 | M35: 218005 | N35: ES; PT | O35: =M35*F35/1000 -> 3597.0825
A36: TA-014-HDPE-FG-28410 | B36: Tampa rosca alimentícia 28/410 HDPE-FG | C36: Screw Cap | D36: HDPE-FG | E36: =IFERROR(INDEX(tbl_materiais[Polimero_Base],MATCH(D36,tbl_materiais[Material],0)),"") -> PE | F36: 15.9 | G36: =IFERROR(INDEX(tbl_materiais[Densidade_g_cm3],MATCH(D36,tbl_materiais[Material],0)),"") -> 0.955 | H36: =IF(G36="","",IF(G36<1,"Sim","Não")) -> Sim | I36: 28/410 | J36: Sem vedante | K36: =IFERROR(INDEX(tbl_materiais[Pct_PCR],MATCH(D36,tbl_materiais[Material],0)),0) -> 0 | L36: FAM-21 | M36: 0 | O36: =M36*F36/1000 -> 0
A37: TA-014-PP-FG-28410 | B37: Tampa rosca alimentícia 28/410 PP-FG | C37: Screw Cap | D37: PP-FG | E37: =IFERROR(INDEX(tbl_materiais[Polimero_Base],MATCH(D37,tbl_materiais[Material],0)),"") -> PP | F37: 15.9 | G37: =IFERROR(INDEX(tbl_materiais[Densidade_g_cm3],MATCH(D37,tbl_materiais[Material],0)),"") -> 0.905 | H37: =IF(G37="","",IF(G37<1,"Sim","Não")) -> Sim | I37: 28/410 | J37: Sem vedante | K37: =IFERROR(INDEX(tbl_materiais[Pct_PCR],MATCH(D37,tbl_materiais[Material],0)),0) -> 0 | L37: FAM-22 | M37: 0 | O37: =M37*F37/1000 -> 0

Sheet Avaliacao_RecyClass
A1: AVALIAÇÃO DE RECICLABILIDADE POR SKU — MODELO RECYCLASS + GRAU PPWR (AUTOAVALIAÇÃO)
A2: Colunas brancas = campos a introduzir na ferramenta online RecyClass · cinzentas = cálculo · Rótulos: cenário típico do cliente (confirmar) · Massas estimadas · Não substitui a certificação RecyClass
A4: ID_Avaliacao | B4: ProductId | C4: Formato | D4: Segmento | E4: Contacto | F4: Processo_Fabrico | G4: Familia_PPWR | H4: Volume_ml | I4: Dimensao_Max_mm | J4: Material_Corpo | K4: Polimero_Corpo | L4: Fluxo_Reciclagem | M4: Categoria_RecyClass | N4: Cor_Dataset | O4: Cor_Corpo | P4: Masterbatch_Tipo | Q4: Masterbatch_Pct | R4: Densidade_Corpo_g_cm3 | S4: Barreira_Revestimento | T4: Massa_Corpo_g | U4: Origem_Massa | V4: ID_Tampa | W4: Material_Tampa | X4: Polimero_Tampa | Y4: Massa_Tampa_g | Z4: Vedante_Tampa | AA4: Rotulo_Tipo | AB4: Rotulo_Adesivo | AC4: Rotulo_Cobertura_Pct | AD4: Massa_Rotulo_g | AE4: Origem_Rotulo | AF4: Decoracao_Tipo | AG4: Decoracao_N_Cores | AH4: Decoracao_Valor | AI4: Massa_Decoracao_g | AJ4: Classe_Fluxo | AK4: Classe_Cor | AL4: Classe_Densidade | AM4: Classe_Barreira | AN4: Classe_Tampa | AO4: Classe_Vedante | AP4: Classe_Rotulo | AQ4: Classe_Adesivo | AR4: Classe_Cobertura | AS4: Classe_Decoracao | AT4: Classe_N_Max | AU4: Classe_RecyClass | AV4: Regras_em_Falta | AW4: Ponto_Critico | AX4: Recomendacao | AY4: Massa_Total_g | AZ4: Frac_Corpo | BA4: Frac_Tampa | BB4: Frac_Rotulo | BC4: Massa_Reciclavel_g | BD4: Taxa_Reciclabilidade | BE4: Grau_Taxa | BF4: Grau_PPWR_Indicativo | BG4: Isencao_Art6 | BH4: Conforme_PPWR_2030 | BI4: Conforme_PPWR_2038 | BJ4: Pct_PCR_Corpo | BK4: Pct_PCR_Tampa | BL4: Conteudo_Reciclado_Pct | BM4: Categoria_Art7 | BN4: Meta_2030 | BO4: Gap_2030 | BP4: Conforme_Art7_2030 | BQ4: Estrutura_Material | BR4: Unid_Vendidas_P12 | BS4: N_Clientes_P12 | BT4: Paises_Venda | BU4: Massa_Vendida_kg | BV4: N_Requisitos_Aplicaveis | BW4: N_Lacunas | BX4: Data_Avaliacao | BY4: Proxima_Revisao | BZ4: Avaliador | CA4: Estado_Avaliacao | CB4: Metodo
A5: RCA-001 | B5: FR-001-HDPE-300 | C5: Frasco | D5: Cosmética e higiene pessoal | E5: Contacto direto com cosmético/higiene | F5: Injeção-sopro (ISBM) | G5: FAM-01 | H5: 300 | I5: 115 | J5: HDPE | K5: =IFERROR(INDEX(tbl_materiais[Polimero_Base],MATCH(J5,tbl_materiais[Material],0)),"") -> PE | L5: =IFERROR(INDEX(tbl_materiais[Fluxo_Reciclagem],MATCH(J5,tbl_materiais[Material],0)),"") -> PE rígido | M5: =IF(L5="PE rígido","PE rígido — frascos e contentores (HDPE/LDPE)",IF(L5="PP rígido","PP rígido — frascos, potes e contentores",IF(L5="PET frascos e garrafas",IF(O5="Natural / incolor","PET — garrafas/frascos transparentes incolores","PET — garrafas/frascos coloridos ou opacos"),"Sem categoria RecyClass ("&K5&")"))) -> PE rígido — frascos e contentores (HDPE/LDPE) | N5: Cardinal Red | O5: Colorido (claro ou transparente) | P5: Red Masterbatch | Q5: 0.02 | R5: =IFERROR(ROUND(INDEX(tbl_materiais[Densidade_g_cm3],MATCH(J5,tbl_materiais[Material],0))+Q5*1.2,3),"") -> 0.979 | S5: Nenhuma | T5: 22 | U5: Estimada (22 g a 300 ml, escala ^2/3) | V5: TR-001-HDPE-24410 | W5: =IF(V5="","",IFERROR(INDEX(tbl_tampas[Material],MATCH(V5,tbl_tampas[CapId],0)),"")) -> HDPE | X5: =IF(V5="","Sem tampa",IFERROR(INDEX(tbl_materiais[Polimero_Base],MATCH(W5,tbl_materiais[Material],0)),"")) -> PE | Y5: =IF(V5="",0,IFERROR(INDEX(tbl_tampas[Massa_g],MATCH(V5,tbl_tampas[CapId],0)),0)) -> 11.5 | Z5: Sem vedante | AA5: Sem rótulo | AB5: Sem adesivo | AC5: 0 | AD5: 0 | AE5: Sem rótulo (decoração direta Plasticom) | AF5: Serigrafia | AG5: 1 | AH5: =IF(AF5="Serigrafia",IF(AG5>=3,"Serigrafia ≥ 3 cores","Serigrafia 1–2 cores"),AF5) -> Serigrafia 1–2 cores | AI5: 0.08 | AJ5: =IFERROR(INDEX(tbl_regras_dfr[Classe],MATCH(L5&"|Fluxo de reciclagem|"&L5,tbl_regras_dfr[Chave],0)),"Sem regra") -> A | AK5: =IF(LEFT(L5,9)="Sem fluxo","—",IFERROR(INDEX(tbl_regras_dfr[Classe],MATCH(L5&"|Cor do corpo|"&O5,tbl_regras_dfr[Chave],0)),"Sem regra")) -> B | AL5: =IF(LEFT(L5,9)="Sem fluxo","—",IFERROR(INDEX(tbl_regras_dfr[Classe],MATCH(L5&"|Densidade do corpo|"&IF(R5<1,"< 1,0 g/cm³","≥ 1,0 g/cm³"),tbl_regras_dfr[Chave],0)),"Sem regra")) -> A | AM5: =IF(LEFT(L5,9)="Sem fluxo","—",IFERROR(INDEX(tbl_regras_dfr[Classe],MATCH(L5&"|Barreira / revestimento|"&S5,tbl_regras_dfr[Chave],0)),"Sem regra")) -> A | AN5: =IF(LEFT(L5,9)="Sem fluxo","—",IFERROR(INDEX(tbl_regras_dfr[Classe],MATCH(L5&"|Material da tampa|"&X5,tbl_regras_dfr[Chave],0)),"Sem regra")) -> A | AO5: =IF(LEFT(L5,9)="Sem fluxo","—",IFERROR(INDEX(tbl_regras_dfr[Classe],MATCH(L5&"|Vedante / liner|"&Z5,tbl_regras_dfr[Chave],0)),"Sem regra")) -> A | AP5: =IF(LEFT(L5,9)="Sem fluxo","—",IFERROR(INDEX(tbl_regras_dfr[Classe],MATCH(L5&"|Tipo de rótulo|"&AA5,tbl_regras_dfr[Chave],0)),"Sem regra")) -> A | AQ5: =IF(LEFT(L5,9)="Sem fluxo","—",IFERROR(INDEX(tbl_regras_dfr[Classe],MATCH(L5&"|Adesivo do rótulo|"&AB5,tbl_regras_dfr[Chave],0)),"Sem regra")) -> A | AR5: =IF(LEFT(L5,9)="Sem fluxo","—",IFERROR(INDEX(tbl_regras_dfr[Classe],MATCH(L5&"|Cobertura do rótulo|"&IF(AC5>0.7,"> 70% da superfície","≤ 70% da superfície"),tbl_regras_dfr[Chave],0)),"Sem regra")) -> A | AS5: =IF(LEFT(L5,9)="Sem fluxo","—",IFERROR(INDEX(tbl_regras_dfr[Classe],MATCH(L5&"|Decoração direta|"&AH5,tbl_regras_dfr[Chave],0)),"Sem regra")) -> B | AT5: =IF(COUNTIF(AJ5:AS5,"F"),6,IF(COUNTIF(AJ5:AS5,"E"),5,IF(COUNTIF(AJ5:AS5,"D"),4,IF(COUNTIF(AJ5:AS5,"C"),3,IF(COUNTIF(AJ5:AS5,"B"),2,IF(COUNTIF(AJ5:AS5,"A"),1,0)))))) -> 2 | AU5: =IF(AT5=0,"",INDEX({"A","B","C","D","E","F"},AT5)) -> B | AV5: =COUNTIF(AJ5:AS5,"Sem regra") -> 0 | AW5: =IF(OR(AU5="",AU5="A"),"—",SUBSTITUTE(INDEX($AJ$4:$AS$4,MATCH(AU5,AJ5:AS5,0)),"Classe_","")) -> Cor | AX5: =IF(AU5="A","Sem ação — manter o design.",IFERROR(INDEX(tbl_regras_dfr[Recomendacao],MATCH(CHOOSE(MATCH(AU5,AJ5:AS5,0),L5&"|Fluxo de reciclagem|"&L5,L5&"|Cor do corpo|"&O5,L5&"|Densidade do corpo|"&IF(R5<1,"< 1,0 g/cm³","≥ 1,0 g/cm³"),L5&"|Barreira / revestimento|"&S5,L5&"|Material da tampa|"&X5,L5&"|Vedante / liner|"&Z5,L5&"|Tipo de rótulo|"&AA5,L5&"|Adesivo do rótulo|"&AB5,L5&"|Cobertura do rótulo|"&IF(AC5>0.7,"> 70% da superfície","≤ 70% da superfície"),L5&"|Decoração direta|"&AH5),tbl_regras_dfr[Chave],0)),"")) -> Preferir natural, branco ou cores claras. | AY5: =T5+Y5+AD5+AI5 -> 33.58 | AZ5: =MIN(IFERROR(INDEX(tbl_regras_dfr[Fracao_Reciclavel],MATCH(L5&"|Fluxo de reciclagem|"&L5,tbl_regras_dfr[Chave],0)),0),IFERROR(INDEX(tbl_regras_dfr[Fracao_Reciclavel],MATCH(L5&"|Cor do corpo|"&O5,tbl_regras_dfr[Chave],0)),0)) -> 1 | BA5: =IFERROR(INDEX(tbl_regras_dfr[Fracao_Reciclavel],MATCH(L5&"|Material da tampa|"&X5,tbl_regras_dfr[Chave],0)),0) -> 1 | BB5: =IFERROR(INDEX(tbl_regras_dfr[Fracao_Reciclavel],MATCH(L5&"|Tipo de rótulo|"&AA5,tbl_regras_dfr[Chave],0)),0) -> 1 | BC5: =AZ5*(T5+Y5*BA5+AD5*BB5) -> 33.5 | BD5: =IFERROR(BC5/AY5,0) -> 0.99761763 | BE5: =IF(BD5>=INDEX(tbl_param_emb[Valor],MATCH("P-06",tbl_param_emb[ID_Parametro],0)),"A",IF(BD5>=INDEX(tbl_param_emb[Valor],MATCH("P-07",tbl_param_emb[ID_Parametro],0)),"B",IF(BD5>=INDEX(tbl_param_emb[Valor],MATCH("P-08",tbl_param_emb[ID_Parametro],0)),"C","< 70%"))) -> A | BF5: =IF(AU5="F","Não reciclável (F)",INDEX({"A","B","C","Abaixo de C"},MAX(MIN(AT5,4),IF(BE5="A",1,IF(BE5="B",2,IF(BE5="C",3,4)))))) -> B | BG5: =IF(D5="Farmacêutico","Isento até 2035","—") -> — | BH5: =IF(BG5<>"—",BG5,IF(OR(BF5="A",BF5="B",BF5="C"),"Sim","Não")) -> Sim | BI5: =IF(BG5<>"—",BG5,IF(OR(BF5="A",BF5="B"),"Sim","Não")) -> Sim | BJ5: =IFERROR(INDEX(tbl_materiais[Pct_PCR],MATCH(J5,tbl_materiais[Material],0)),0) -> 0 | BK5: =IF(V5="",0,IFERROR(INDEX(tbl_tampas[Pct_PCR],MATCH(V5,tbl_tampas[CapId],0)),0)) -> 0 | BL5: =IFERROR((T5*BJ5+Y5*BK5)/(T5+Y5),0) -> 0 | BM5: =IF(D5="Farmacêutico","Isenta — medicamentos (art. 7.º)",IF(D5="Alimentar",IF(K5="PET","Sensível ao contacto — PET","Sensível ao contacto — outros plásticos"),"Outras embalagens de plástico")) -> Outras embalagens de plástico | BN5: =IFERROR(IF(INDEX(tbl_metas_art7[Meta_2030],MATCH(BM5,tbl_metas_art7[Categoria_Art7],0))="","",INDEX(tbl_metas_art7[Meta_2030],MATCH(BM5,tbl_metas_art7[Categoria_Art7],0))),"") -> 0.35 | BO5: =IF(BN5="","",MAX(0,BN5-BL5)) -> 0.35 | BP5: =IF(BN5="","Isento",IF(BO5=0,"Sim","Não")) -> Não | BQ5: =IF(AND(OR(X5=K5,X5="Sem tampa",AND(OR(X5="PE",X5="PP"),OR(K5="PE",K5="PP"))),OR(AA5="Sem rótulo",AND(ISNUMBER(SEARCH("PE/PP",AA5)),OR(K5="PE",K5="PP")))),"Monomaterial (mesma família)","Multimaterial") -> Monomaterial (mesma família) | BR5: 363211 | BS5: 14 | BT5: DE; ES; FR; IT; PL; PT | BU5: =BR5*T5/1000 -> 7990.642 | BV5: =COUNTIFS(tbl_aplicabilidade[ProductId],B5,tbl_aplicabilidade[Aplicavel],"Sim") -> 12 | BW5: =COUNTIFS(tbl_aplicabilidade[ProductId],B5,tbl_aplicabilidade[Estado_Resumo],"Lacuna")+COUNTIFS(tbl_aplicabilidade[ProductId],B5,tbl_aplicabilidade[Estado_Resumo],"Não conforme") -> 1 | BX5: 46287 | BY5: =EDATE(BX5,12) -> 46652 | BZ5: Responsável de R&D | CA5: Autoavaliação (não certificada) | CB5: Regras simplificadas SGA-20 v1 (diretrizes DfR RecyClass) — confirmar na ferramenta online
A6: RCA-002 | B6: FR-002-HDPE-PCR-300 | C6: Frasco | D6: Cosmética e higiene pessoal | E6: Contacto direto com cosmético/higiene | F6: Injeção-sopro (ISBM) | G6: FAM-02 | H6: 300 | I6: 115 | J6: HDPE-PCR | K6: =IFERROR(INDEX(tbl_materiais[Polimero_Base],MATCH(J6,tbl_materiais[Material],0)),"") -> PE | L6: =IFERROR(INDEX(tbl_materiais[Fluxo_Reciclagem],MATCH(J6,tbl_materiais[Material],0)),"") -> PE rígido | M6: =IF(L6="PE rígido","PE rígido — frascos e contentores (HDPE/LDPE)",IF(L6="PP rígido","PP rígido — frascos, potes e contentores",IF(L6="PET frascos e garrafas",IF(O6="Natural / incolor","PET — garrafas/frascos transparentes incolores","PET — garrafas/frascos coloridos ou opacos"),"Sem categoria RecyClass ("&K6&")"))) -> PE rígido — frascos e contentores (HDPE/LDPE) | N6: Cobalt Blue | O6: Colorido (claro ou transparente) | P6: Blue Masterbatch | Q6: 0.02 | R6: =IFERROR(ROUND(INDEX(tbl_materiais[Densidade_g_cm3],MATCH(J6,tbl_materiais[Material],0))+Q6*1.2,3),"") -> 0.984 | S6: Nenhuma | T6: 22 | U6: Estimada (22 g a 300 ml, escala ^2/3) | V6: TF-005-PP-PCR-24410 | W6: =IF(V6="","",IFERROR(INDEX(tbl_tampas[Material],MATCH(V6,tbl_tampas[CapId],0)),"")) -> PP-PCR | X6: =IF(V6="","Sem tampa",IFERROR(INDEX(tbl_materiais[Polimero_Base],MATCH(W6,tbl_materiais[Material],0)),"")) -> PP | Y6: =IF(V6="",0,IFERROR(INDEX(tbl_tampas[Massa_g],MATCH(V6,tbl_tampas[CapId],0)),0)) -> 13.9 | Z6: Sem vedante | AA6: Autoadesivo PE/PP | AB6: Acrílico permanente | AC6: 0.4 | AD6: 0.46 | AE6: Cenário típico do cliente — confirmar especificação | AF6: Nenhuma | AG6: 0 | AH6: =IF(AF6="Serigrafia",IF(AG6>=3,"Serigrafia ≥ 3 cores","Serigrafia 1–2 cores"),AF6) -> Nenhuma | AI6: 0 | AJ6: =IFERROR(INDEX(tbl_regras_dfr[Classe],MATCH(L6&"|Fluxo de reciclagem|"&L6,tbl_regras_dfr[Chave],0)),"Sem regra") -> A | AK6: =IF(LEFT(L6,9)="Sem fluxo","—",IFERROR(INDEX(tbl_regras_dfr[Classe],MATCH(L6&"|Cor do corpo|"&O6,tbl_regras_dfr[Chave],0)),"Sem regra")) -> B | AL6: =IF(LEFT(L6,9)="Sem fluxo","—",IFERROR(INDEX(tbl_regras_dfr[Classe],MATCH(L6&"|Densidade do corpo|"&IF(R6<1,"< 1,0 g/cm³","≥ 1,0 g/cm³"),tbl_regras_dfr[Chave],0)),"Sem regra")) -> A | AM6: =IF(LEFT(L6,9)="Sem fluxo","—",IFERROR(INDEX(tbl_regras_dfr[Classe],MATCH(L6&"|Barreira / revestimento|"&S6,tbl_regras_dfr[Chave],0)),"Sem regra")) -> A | AN6: =IF(LEFT(L6,9)="Sem fluxo","—",IFERROR(INDEX(tbl_regras_dfr[Classe],MATCH(L6&"|Material da tampa|"&X6,tbl_regras_dfr[Chave],0)),"Sem regra")) -> A | AO6: =IF(LEFT(L6,9)="Sem fluxo","—",IFERROR(INDEX(tbl_regras_dfr[Classe],MATCH(L6&"|Vedante / liner|"&Z6,tbl_regras_dfr[Chave],0)),"Sem regra")) -> A | AP6: =IF(LEFT(L6,9)="Sem fluxo","—",IFERROR(INDEX(tbl_regras_dfr[Classe],MATCH(L6&"|Tipo de rótulo|"&AA6,tbl_regras_dfr[Chave],0)),"Sem regra")) -> A | AQ6: =IF(LEFT(L6,9)="Sem fluxo","—",IFERROR(INDEX(tbl_regras_dfr[Classe],MATCH(L6&"|Adesivo do rótulo|"&AB6,tbl_regras_dfr[Chave],0)),"Sem regra")) -> A | AR6: =IF(LEFT(L6,9)="Sem fluxo","—",IFERROR(INDEX(tbl_regras_dfr[Classe],MATCH(L6&"|Cobertura do rótulo|"&IF(AC6>0.7,"> 70% da superfície","≤ 70% da superfície"),tbl_regras_dfr[Chave],0)),"Sem regra")) -> A | AS6: =IF(LEFT(L6,9)="Sem fluxo","—",IFERROR(INDEX(tbl_regras_dfr[Classe],MATCH(L6&"|Decoração direta|"&AH6,tbl_regras_dfr[Chave],0)),"Sem regra")) -> A | AT6: =IF(COUNTIF(AJ6:AS6,"F"),6,IF(COUNTIF(AJ6:AS6,"E"),5,IF(COUNTIF(AJ6:AS6,"D"),4,IF(COUNTIF(AJ6:AS6,"C"),3,IF(COUNTIF(AJ6:AS6,"B"),2,IF(COUNTIF(AJ6:AS6,"A"),1,0)))))) -> 2 | AU6: =IF(AT6=0,"",INDEX({"A","B","C","D","E","F"},AT6)) -> B | AV6: =COUNTIF(AJ6:AS6,"Sem regra") -> 0 | AW6: =IF(OR(AU6="",AU6="A"),"—",SUBSTITUTE(INDEX($AJ$4:$AS$4,MATCH(AU6,AJ6:AS6,0)),"Classe_","")) -> Cor | AX6: =IF(AU6="A","Sem ação — manter o design.",IFERROR(INDEX(tbl_regras_dfr[Recomendacao],MATCH(CHOOSE(MATCH(AU6,AJ6:AS6,0),L6&"|Fluxo de reciclagem|"&L6,L6&"|Cor do corpo|"&O6,L6&"|Densidade do corpo|"&IF(R6<1,"< 1,0 g/cm³","≥ 1,0 g/cm³"),L6&"|Barreira / revestimento|"&S6,L6&"|Material da tampa|"&X6,L6&"|Vedante / liner|"&Z6,L6&"|Tipo de rótulo|"&AA6,L6&"|Adesivo do rótulo|"&AB6,L6&"|Cobertura do rótulo|"&IF(AC6>0.7,"> 70% da superfície","≤ 70% da superfície"),L6&"|Decoração direta|"&AH6),tbl_regras_dfr[Chave],0)),"")) -> Preferir natural, branco ou cores claras. | AY6: =T6+Y6+AD6+AI6 -> 36.36 | AZ6: =MIN(IFERROR(INDEX(tbl_regras_dfr[Fracao_Reciclavel],MATCH(L6&"|Fluxo de reciclagem|"&L6,tbl_regras_dfr[Chave],0)),0),IFERROR(INDEX(tbl_regras_dfr[Fracao_Reciclavel],MATCH(L6&"|Cor do corpo|"&O6,tbl_regras_dfr[Chave],0)),0)) -> 1 | BA6: =IFERROR(INDEX(tbl_regras_dfr[Fracao_Reciclavel],MATCH(L6&"|Material da tampa|"&X6,tbl_regras_dfr[Chave],0)),0) -> 1 | BB6: =IFERROR(INDEX(tbl_regras_dfr[Fracao_Reciclavel],MATCH(L6&"|Tipo de rótulo|"&AA6,tbl_regras_dfr[Chave],0)),0) -> 1 | BC6: =AZ6*(T6+Y6*BA6+AD6*BB6) -> 36.36 | BD6: =IFERROR(BC6/AY6,0) -> 1 | BE6: =IF(BD6>=INDEX(tbl_param_emb[Valor],MATCH("P-06",tbl_param_emb[ID_Parametro],0)),"A",IF(BD6>=INDEX(tbl_param_emb[Valor],MATCH("P-07",tbl_param_emb[ID_Parametro],0)),"B",IF(BD6>=INDEX(tbl_param_emb[Valor],MATCH("P-08",tbl_param_emb[ID_Parametro],0)),"C","< 70%"))) -> A | BF6: =IF(AU6="F","Não reciclável (F)",INDEX({"A","B","C","Abaixo de C"},MAX(MIN(AT6,4),IF(BE6="A",1,IF(BE6="B",2,IF(BE6="C",3,4)))))) -> B | BG6: =IF(D6="Farmacêutico","Isento até 2035","—") -> — | BH6: =IF(BG6<>"—",BG6,IF(OR(BF6="A",BF6="B",BF6="C"),"Sim","Não")) -> Sim | BI6: =IF(BG6<>"—",BG6,IF(OR(BF6="A",BF6="B"),"Sim","Não")) -> Sim | BJ6: =IFERROR(INDEX(tbl_materiais[Pct_PCR],MATCH(J6,tbl_materiais[Material],0)),0) -> 0.3 | BK6: =IF(V6="",0,IFERROR(INDEX(tbl_tampas[Pct_PCR],MATCH(V6,tbl_tampas[CapId],0)),0)) -> 0.3 | BL6: =IFERROR((T6*BJ6+Y6*BK6)/(T6+Y6),0) -> 0.3 | BM6: =IF(D6="Farmacêutico","Isenta — medicamentos (art. 7.º)",IF(D6="Alimentar",IF(K6="PET","Sensível ao contacto — PET","Sensível ao contacto — outros plásticos"),"Outras embalagens de plástico")) -> Outras embalagens de plástico | BN6: =IFERROR(IF(INDEX(tbl_metas_art7[Meta_2030],MATCH(BM6,tbl_metas_art7[Categoria_Art7],0))="","",INDEX(tbl_metas_art7[Meta_2030],MATCH(BM6,tbl_metas_art7[Categoria_Art7],0))),"") -> 0.35 | BO6: =IF(BN6="","",MAX(0,BN6-BL6)) -> 0.05 | BP6: =IF(BN6="","Isento",IF(BO6=0,"Sim","Não")) -> Não | BQ6: =IF(AND(OR(X6=K6,X6="Sem tampa",AND(OR(X6="PE",X6="PP"),OR(K6="PE",K6="PP"))),OR(AA6="Sem rótulo",AND(ISNUMBER(SEARCH("PE/PP",AA6)),OR(K6="PE",K6="PP")))),"Monomaterial (mesma família)","Multimaterial") -> Monomaterial (mesma família) | BR6: 1236361 | BS6: 14 | BT6: DE; ES; FR; IT; PL; PT | BU6: =BR6*T6/1000 -> 27199.942 | BV6: =COUNTIFS(tbl_aplicabilidade[ProductId],B6,tbl_aplicabilidade[Aplicavel],"Sim") -> 12 | BW6: =COUNTIFS(tbl_aplicabilidade[ProductId],B6,tbl_aplicabilidade[Estado_Resumo],"Lacuna")+COUNTIFS(tbl_aplicabilidade[ProductId],B6,tbl_aplicabilidade[Estado_Resumo],"Não conforme") -> 1 | BX6: 46287 | BY6: =EDATE(BX6,12) -> 46652 | BZ6: Responsável de R&D | CA6: Autoavaliação (não certificada) | CB6: Regras simplificadas SGA-20 v1 (diretrizes DfR RecyClass) — confirmar na ferramenta online
A7: RCA-003 | B7: FR-001-HDPE-PCR-300 | C7: Frasco | D7: Cosmética e higiene pessoal | E7: Contacto direto com cosmético/higiene | F7: Injeção-sopro (ISBM) | G7: FAM-02 | H7: 300 | I7: 115 | J7: HDPE-PCR | K7: =IFERROR(INDEX(tbl_materiais[Polimero_Base],MATCH(J7,tbl_materiais[Material],0)),"") -> PE | L7: =IFERROR(INDEX(tbl_materiais[Fluxo_Reciclagem],MATCH(J7,tbl_materiais[Material],0)),"") -> PE rígido | M7: =IF(L7="PE rígido","PE rígido — frascos e contentores (HDPE/LDPE)",IF(L7="PP rígido","PP rígido — frascos, potes e contentores",IF(L7="PET frascos e garrafas",IF(O7="Natural / incolor","PET — garrafas/frascos transparentes incolores","PET — garrafas/frascos coloridos ou opacos"),"Sem categoria RecyClass ("&K7&")"))) -> PE rígido — frascos e contentores (HDPE/LDPE) | N7: Cardinal Red | O7: Colorido (claro ou transparente) | P7: Red Masterbatch | Q7: 0.02 | R7: =IFERROR(ROUND(INDEX(tbl_materiais[Densidade_g_cm3],MATCH(J7,tbl_materiais[Material],0))+Q7*1.2,3),"") -> 0.984 | S7: Nenhuma | T7: 22 | U7: Estimada (22 g a 300 ml, escala ^2/3) | V7: TR-001-PP-PCR-24410 | W7: =IF(V7="","",IFERROR(INDEX(tbl_tampas[Material],MATCH(V7,tbl_tampas[CapId],0)),"")) -> PP-PCR | X7: =IF(V7="","Sem tampa",IFERROR(INDEX(tbl_materiais[Polimero_Base],MATCH(W7,tbl_materiais[Material],0)),"")) -> PP | Y7: =IF(V7="",0,IFERROR(INDEX(tbl_tampas[Massa_g],MATCH(V7,tbl_tampas[CapId],0)),0)) -> 10.3 | Z7: Sem vedante | AA7: Autoadesivo PE/PP | AB7: Acrílico permanente | AC7: 0.4 | AD7: 0.46 | AE7: Cenário típico do cliente — confirmar especificação | AF7: Nenhuma | AG7: 0 | AH7: =IF(AF7="Serigrafia",IF(AG7>=3,"Serigrafia ≥ 3 cores","Serigrafia 1–2 cores"),AF7) -> Nenhuma | AI7: 0 | AJ7: =IFERROR(INDEX(tbl_regras_dfr[Classe],MATCH(L7&"|Fluxo de reciclagem|"&L7,tbl_regras_dfr[Chave],0)),"Sem regra") -> A | AK7: =IF(LEFT(L7,9)="Sem fluxo","—",IFERROR(INDEX(tbl_regras_dfr[Classe],MATCH(L7&"|Cor do corpo|"&O7,tbl_regras_dfr[Chave],0)),"Sem regra")) -> B | AL7: =IF(LEFT(L7,9)="Sem fluxo","—",IFERROR(INDEX(tbl_regras_dfr[Classe],MATCH(L7&"|Densidade do corpo|"&IF(R7<1,"< 1,0 g/cm³","≥ 1,0 g/cm³"),tbl_regras_dfr[Chave],0)),"Sem regra")) -> A | AM7: =IF(LEFT(L7,9)="Sem fluxo","—",IFERROR(INDEX(tbl_regras_dfr[Classe],MATCH(L7&"|Barreira / revestimento|"&S7,tbl_regras_dfr[Chave],0)),"Sem regra")) -> A | AN7: =IF(LEFT(L7,9)="Sem fluxo","—",IFERROR(INDEX(tbl_regras_dfr[Classe],MATCH(L7&"|Material da tampa|"&X7,tbl_regras_dfr[Chave],0)),"Sem regra")) -> A | AO7: =IF(LEFT(L7,9)="Sem fluxo","—",IFERROR(INDEX(tbl_regras_dfr[Classe],MATCH(L7&"|Vedante / liner|"&Z7,tbl_regras_dfr[Chave],0)),"Sem regra")) -> A | AP7: =IF(LEFT(L7,9)="Sem fluxo","—",IFERROR(INDEX(tbl_regras_dfr[Classe],MATCH(L7&"|Tipo de rótulo|"&AA7,tbl_regras_dfr[Chave],0)),"Sem regra")) -> A | AQ7: =IF(LEFT(L7,9)="Sem fluxo","—",IFERROR(INDEX(tbl_regras_dfr[Classe],MATCH(L7&"|Adesivo do rótulo|"&AB7,tbl_regras_dfr[Chave],0)),"Sem regra")) -> A | AR7: =IF(LEFT(L7,9)="Sem fluxo","—",IFERROR(INDEX(tbl_regras_dfr[Classe],MATCH(L7&"|Cobertura do rótulo|"&IF(AC7>0.7,"> 70% da superfície","≤ 70% da superfície"),tbl_regras_dfr[Chave],0)),"Sem regra")) -> A | AS7: =IF(LEFT(L7,9)="Sem fluxo","—",IFERROR(INDEX(tbl_regras_dfr[Classe],MATCH(L7&"|Decoração direta|"&AH7,tbl_regras_dfr[Chave],0)),"Sem regra")) -> A | AT7: =IF(COUNTIF(AJ7:AS7,"F"),6,IF(COUNTIF(AJ7:AS7,"E"),5,IF(COUNTIF(AJ7:AS7,"D"),4,IF(COUNTIF(AJ7:AS7,"C"),3,IF(COUNTIF(AJ7:AS7,"B"),2,IF(COUNTIF(AJ7:AS7,"A"),1,0)))))) -> 2 | AU7: =IF(AT7=0,"",INDEX({"A","B","C","D","E","F"},AT7)) -> B | AV7: =COUNTIF(AJ7:AS7,"Sem regra") -> 0 | AW7: =IF(OR(AU7="",AU7="A"),"—",SUBSTITUTE(INDEX($AJ$4:$AS$4,MATCH(AU7,AJ7:AS7,0)),"Classe_","")) -> Cor | AX7: =IF(AU7="A","Sem ação — manter o design.",IFERROR(INDEX(tbl_regras_dfr[Recomendacao],MATCH(CHOOSE(MATCH(AU7,AJ7:AS7,0),L7&"|Fluxo de reciclagem|"&L7,L7&"|Cor do corpo|"&O7,L7&"|Densidade do corpo|"&IF(R7<1,"< 1,0 g/cm³","≥ 1,0 g/cm³"),L7&"|Barreira / revestimento|"&S7,L7&"|Material da tampa|"&X7,L7&"|Vedante / liner|"&Z7,L7&"|Tipo de rótulo|"&AA7,L7&"|Adesivo do rótulo|"&AB7,L7&"|Cobertura do rótulo|"&IF(AC7>0.7,"> 70% da superfície","≤ 70% da superfície"),L7&"|Decoração direta|"&AH7),tbl_regras_dfr[Chave],0)),"")) -> Preferir natural, branco ou cores claras. | AY7: =T7+Y7+AD7+AI7 -> 32.76 | AZ7: =MIN(IFERROR(INDEX(tbl_regras_dfr[Fracao_Reciclavel],MATCH(L7&"|Fluxo de reciclagem|"&L7,tbl_regras_dfr[Chave],0)),0),IFERROR(INDEX(tbl_regras_dfr[Fracao_Reciclavel],MATCH(L7&"|Cor do corpo|"&O7,tbl_regras_dfr[Chave],0)),0)) -> 1 | BA7: =IFERROR(INDEX(tbl_regras_dfr[Fracao_Reciclavel],MATCH(L7&"|Material da tampa|"&X7,tbl_regras_dfr[Chave],0)),0) -> 1 | BB7: =IFERROR(INDEX(tbl_regras_dfr[Fracao_Reciclavel],MATCH(L7&"|Tipo de rótulo|"&AA7,tbl_regras_dfr[Chave],0)),0) -> 1 | BC7: =AZ7*(T7+Y7*BA7+AD7*BB7) -> 32.76 | BD7: =IFERROR(BC7/AY7,0) -> 1 | BE7: =IF(BD7>=INDEX(tbl_param_emb[Valor],MATCH("P-06",tbl_param_emb[ID_Parametro],0)),"A",IF(BD7>=INDEX(tbl_param_emb[Valor],MATCH("P-07",tbl_param_emb[ID_Parametro],0)),"B",IF(BD7>=INDEX(tbl_param_emb[Valor],MATCH("P-08",tbl_param_emb[ID_Parametro],0)),"C","< 70%"))) -> A | BF7: =IF(AU7="F","Não reciclável (F)",INDEX({"A","B","C","Abaixo de C"},MAX(MIN(AT7,4),IF(BE7="A",1,IF(BE7="B",2,IF(BE7="C",3,4)))))) -> B | BG7: =IF(D7="Farmacêutico","Isento até 2035","—") -> — | BH7: =IF(BG7<>"—",BG7,IF(OR(BF7="A",BF7="B",BF7="C"),"Sim","Não")) -> Sim | BI7: =IF(BG7<>"—",BG7,IF(OR(BF7="A",BF7="B"),"Sim","Não")) -> Sim | BJ7: =IFERROR(INDEX(tbl_materiais[Pct_PCR],MATCH(J7,tbl_materiais[Material],0)),0) -> 0.3 | BK7: =IF(V7="",0,IFERROR(INDEX(tbl_tampas[Pct_PCR],MATCH(V7,tbl_tampas[CapId],0)),0)) -> 0.3 | BL7: =IFERROR((T7*BJ7+Y7*BK7)/(T7+Y7),0) -> 0.3 | BM7: =IF(D7="Farmacêutico","Isenta — medicamentos (art. 7.º)",IF(D7="Alimentar",IF(K7="PET","Sensível ao contacto — PET","Sensível ao contacto — outros plásticos"),"Outras embalagens de plástico")) -> Outras embalagens de plástico | BN7: =IFERROR(IF(INDEX(tbl_metas_art7[Meta_2030],MATCH(BM7,tbl_metas_art7[Categoria_Art7],0))="","",INDEX(tbl_metas_art7[Meta_2030],MATCH(BM7,tbl_metas_art7[Categoria_Art7],0))),"") -> 0.35 | BO7: =IF(BN7="","",MAX(0,BN7-BL7)) -> 0.05 | BP7: =IF(BN7="","Isento",IF(BO7=0,"Sim","Não")) -> Não | BQ7: =IF(AND(OR(X7=K7,X7="Sem tampa",AND(OR(X7="PE",X7="PP"),OR(K7="PE",K7="PP"))),OR(AA7="Sem rótulo",AND(ISNUMBER(SEARCH("PE/PP",AA7)),OR(K7="PE",K7="PP")))),"Monomaterial (mesma família)","Multimaterial") -> Monomaterial (mesma família) | BR7: 423949 | BS7: 14 | BT7: DE; ES; FR; IT; PL; PT | BU7: =BR7*T7/1000 -> 9326.878 | BV7: =COUNTIFS(tbl_aplicabilidade[ProductId],B7,tbl_aplicabilidade[Aplicavel],"Sim") -> 12 | BW7: =COUNTIFS(tbl_aplicabilidade[ProductId],B7,tbl_aplicabilidade[Estado_Resumo],"Lacuna")+COUNTIFS(tbl_aplicabilidade[ProductId],B7,tbl_aplicabilidade[Estado_Resumo],"Não conforme") -> 1 | BX7: 46287 | BY7: =EDATE(BX7,12) -> 46652 | BZ7: Responsável de R&D | CA7: Autoavaliação (não certificada) | CB7: Regras simplificadas SGA-20 v1 (diretrizes DfR RecyClass) — confirmar na ferramenta online
A8: RCA-004 | B8: FR-001-rPET-300 | C8: Frasco | D8: Cosmética e higiene pessoal | E8: Contacto direto com cosmético/higiene | F8: Injeção-sopro (ISBM) | G8: FAM-11 | H8: 300 | I8: 115 | J8: rPET | K8: =IFERROR(INDEX(tbl_materiais[Polimero_Base],MATCH(J8,tbl_materiais[Material],0)),"") -> PET | L8: =IFERROR(INDEX(tbl_materiais[Fluxo_Reciclagem],MATCH(J8,tbl_materiais[Material],0)),"") -> PET frascos e garrafas | M8: =IF(L8="PE rígido","PE rígido — frascos e contentores (HDPE/LDPE)",IF(L8="PP rígido","PP rígido — frascos, potes e contentores",IF(L8="PET frascos e garrafas",IF(O8="Natural / incolor","PET — garrafas/frascos transparentes incolores","PET — garrafas/frascos coloridos ou opacos"),"Sem categoria RecyClass ("&K8&")"))) -> PET — garrafas/frascos transparentes incolores | N8: Natural (Uncolored) | O8: Natural / incolor | P8: No Masterbatch | Q8: 0 | R8: =IFERROR(ROUND(INDEX(tbl_materiais[Densidade_g_cm3],MATCH(J8,tbl_materiais[Material],0))+Q8*1.2,3),"") -> 1.38 | S8: Nenhuma | T8: 22 | U8: Estimada (22 g a 300 ml, escala ^2/3) | V8: TR-001-PP-24410 | W8: =IF(V8="","",IFERROR(INDEX(tbl_tampas[Material],MATCH(V8,tbl_tampas[CapId],0)),"")) -> PP | X8: =IF(V8="","Sem tampa",IFERROR(INDEX(tbl_materiais[Polimero_Base],MATCH(W8,tbl_materiais[Material],0)),"")) -> PP | Y8: =IF(V8="",0,IFERROR(INDEX(tbl_tampas[Massa_g],MATCH(V8,tbl_tampas[CapId],0)),0)) -> 10.3 | Z8: Sem vedante | AA8: Sem rótulo | AB8: Sem adesivo | AC8: 0 | AD8: 0 | AE8: Sem rótulo (decoração direta Plasticom) | AF8: Hot foil metalizado | AG8: 1 | AH8: =IF(AF8="Serigrafia",IF(AG8>=3,"Serigrafia ≥ 3 cores","Serigrafia 1–2 cores"),AF8) -> Hot foil metalizado | AI8: 0.03 | AJ8: =IFERROR(INDEX(tbl_regras_dfr[Classe],MATCH(L8&"|Fluxo de reciclagem|"&L8,tbl_regras_dfr[Chave],0)),"Sem regra") -> A | AK8: =IF(LEFT(L8,9)="Sem fluxo","—",IFERROR(INDEX(tbl_regras_dfr[Classe],MATCH(L8&"|Cor do corpo|"&O8,tbl_regras_dfr[Chave],0)),"Sem regra")) -> A | AL8: =IF(LEFT(L8,9)="Sem fluxo","—",IFERROR(INDEX(tbl_regras_dfr[Classe],MATCH(L8&"|Densidade do corpo|"&IF(R8<1,"< 1,0 g/cm³","≥ 1,0 g/cm³"),tbl_regras_dfr[Chave],0)),"Sem regra")) -> A | AM8: =IF(LEFT(L8,9)="Sem fluxo","—",IFERROR(INDEX(tbl_regras_dfr[Classe],MATCH(L8&"|Barreira / revestimento|"&S8,tbl_regras_dfr[Chave],0)),"Sem regra")) -> A | AN8: =IF(LEFT(L8,9)="Sem fluxo","—",IFERROR(INDEX(tbl_regras_dfr[Classe],MATCH(L8&"|Material da tampa|"&X8,tbl_regras_dfr[Chave],0)),"Sem regra")) -> A | AO8: =IF(LEFT(L8,9)="Sem fluxo","—",IFERROR(INDEX(tbl_regras_dfr[Classe],MATCH(L8&"|Vedante / liner|"&Z8,tbl_regras_dfr[Chave],0)),"Sem regra")) -> A | AP8: =IF(LEFT(L8,9)="Sem fluxo","—",IFERROR(INDEX(tbl_regras_dfr[Classe],MATCH(L8&"|Tipo de rótulo|"&AA8,tbl_regras_dfr[Chave],0)),"Sem regra")) -> A | AQ8: =IF(LEFT(L8,9)="Sem fluxo","—",IFERROR(INDEX(tbl_regras_dfr[Classe],MATCH(L8&"|Adesivo do rótulo|"&AB8,tbl_regras_dfr[Chave],0)),"Sem regra")) -> A | AR8: =IF(LEFT(L8,9)="Sem fluxo","—",IFERROR(INDEX(tbl_regras_dfr[Classe],MATCH(L8&"|Cobertura do rótulo|"&IF(AC8>0.7,"> 70% da superfície","≤ 70% da superfície"),tbl_regras_dfr[Chave],0)),"Sem regra")) -> A | AS8: =IF(LEFT(L8,9)="Sem fluxo","—",IFERROR(INDEX(tbl_regras_dfr[Classe],MATCH(L8&"|Decoração direta|"&AH8,tbl_regras_dfr[Chave],0)),"Sem regra")) -> D | AT8: =IF(COUNTIF(AJ8:AS8,"F"),6,IF(COUNTIF(AJ8:AS8,"E"),5,IF(COUNTIF(AJ8:AS8,"D"),4,IF(COUNTIF(AJ8:AS8,"C"),3,IF(COUNTIF(AJ8:AS8,"B"),2,IF(COUNTIF(AJ8:AS8,"A"),1,0)))))) -> 4 | AU8: =IF(AT8=0,"",INDEX({"A","B","C","D","E","F"},AT8)) -> D | AV8: =COUNTIF(AJ8:AS8,"Sem regra") -> 0 | AW8: =IF(OR(AU8="",AU8="A"),"—",SUBSTITUTE(INDEX($AJ$4:$AS$4,MATCH(AU8,AJ8:AS8,0)),"Classe_","")) -> Decoracao | AX8: =IF(AU8="A","Sem ação — manter o design.",IFERROR(INDEX(tbl_regras_dfr[Recomendacao],MATCH(CHOOSE(MATCH(AU8,AJ8:AS8,0),L8&"|Fluxo de reciclagem|"&L8,L8&"|Cor do corpo|"&O8,L8&"|Densidade do corpo|"&IF(R8<1,"< 1,0 g/cm³","≥ 1,0 g/cm³"),L8&"|Barreira / revestimento|"&S8,L8&"|Material da tampa|"&X8,L8&"|Vedante / liner|"&Z8,L8&"|Tipo de rótulo|"&AA8,L8&"|Adesivo do rótulo|"&AB8,L8&"|Cobertura do rótulo|"&IF(AC8>0.7,"> 70% da superfície","≤ 70% da superfície"),L8&"|Decoração direta|"&AH8),tbl_regras_dfr[Chave],0)),"")) -> Rótulo metalizado de PE/PP destacável. | AY8: =T8+Y8+AD8+AI8 -> 32.33 | AZ8: =MIN(IFERROR(INDEX(tbl_regras_dfr[Fracao_Reciclavel],MATCH(L8&"|Fluxo de reciclagem|"&L8,tbl_regras_dfr[Chave],0)),0),IFERROR(INDEX(tbl_regras_dfr[Fracao_Reciclavel],MATCH(L8&"|Cor do corpo|"&O8,tbl_regras_dfr[Chave],0)),0)) -> 1 | BA8: =IFERROR(INDEX(tbl_regras_dfr[Fracao_Reciclavel],MATCH(L8&"|Material da tampa|"&X8,tbl_regras_dfr[Chave],0)),0) -> 1 | BB8: =IFERROR(INDEX(tbl_regras_dfr[Fracao_Reciclavel],MATCH(L8&"|Tipo de rótulo|"&AA8,tbl_regras_dfr[Chave],0)),0) -> 1 | BC8: =AZ8*(T8+Y8*BA8+AD8*BB8) -> 32.3 | BD8: =IFERROR(BC8/AY8,0) -> 0.99907207 | BE8: =IF(BD8>=INDEX(tbl_param_emb[Valor],MATCH("P-06",tbl_param_emb[ID_Parametro],0)),"A",IF(BD8>=INDEX(tbl_param_emb[Valor],MATCH("P-07",tbl_param_emb[ID_Parametro],0)),"B",IF(BD8>=INDEX(tbl_param_emb[Valor],MATCH("P-08",tbl_param_emb[ID_Parametro],0)),"C","< 70%"))) -> A | BF8: =IF(AU8="F","Não reciclável (F)",INDEX({"A","B","C","Abaixo de C"},MAX(MIN(AT8,4),IF(BE8="A",1,IF(BE8="B",2,IF(BE8="C",3,4)))))) -> Abaixo de C | BG8: =IF(D8="Farmacêutico","Isento até 2035","—") -> — | BH8: =IF(BG8<>"—",BG8,IF(OR(BF8="A",BF8="B",BF8="C"),"Sim","Não")) -> Não | BI8: =IF(BG8<>"—",BG8,IF(OR(BF8="A",BF8="B"),"Sim","Não")) -> Não | BJ8: =IFERROR(INDEX(tbl_materiais[Pct_PCR],MATCH(J8,tbl_materiais[Material],0)),0) -> 0.5 | BK8: =IF(V8="",0,IFERROR(INDEX(tbl_tampas[Pct_PCR],MATCH(V8,tbl_tampas[CapId],0)),0)) -> 0 | BL8: =IFERROR((T8*BJ8+Y8*BK8)/(T8+Y8),0) -> 0.34055728 | BM8: =IF(D8="Farmacêutico","Isenta — medicamentos (art. 7.º)",IF(D8="Alimentar",IF(K8="PET","Sensível ao contacto — PET","Sensível ao contacto — outros plásticos"),"Outras embalagens de plástico")) -> Outras embalagens de plástico | BN8: =IFERROR(IF(INDEX(tbl_metas_art7[Meta_2030],MATCH(BM8,tbl_metas_art7[Categoria_Art7],0))="","",INDEX(tbl_metas_art7[Meta_2030],MATCH(BM8,tbl_metas_art7[Categoria_Art7],0))),"") -> 0.35 | BO8: =IF(BN8="","",MAX(0,BN8-BL8)) -> 0.0094427245 | BP8: =IF(BN8="","Isento",IF(BO8=0,"Sim","Não")) -> Não | BQ8: =IF(AND(OR(X8=K8,X8="Sem tampa",AND(OR(X8="PE",X8="PP"),OR(K8="PE",K8="PP"))),OR(AA8="Sem rótulo",AND(ISNUMBER(SEARCH("PE/PP",AA8)),OR(K8="PE",K8="PP")))),"Monomaterial (mesma família)","Multimaterial") -> Multimaterial | BR8: 311456 | BS8: 13 | BT8: DE; ES; FR; IT; PL; PT | BU8: =BR8*T8/1000 -> 6852.032 | BV8: =COUNTIFS(tbl_aplicabilidade[ProductId],B8,tbl_aplicabilidade[Aplicavel],"Sim") -> 12 | BW8: =COUNTIFS(tbl_aplicabilidade[ProductId],B8,tbl_aplicabilidade[Estado_Resumo],"Lacuna")+COUNTIFS(tbl_aplicabilidade[ProductId],B8,tbl_aplicabilidade[Estado_Resumo],"Não conforme") -> 3 | BX8: 46287 | BY8: =EDATE(BX8,12) -> 46652 | BZ8: Responsável de R&D | CA8: Autoavaliação (não certificada) | CB8: Regras simplificadas SGA-20 v1 (diretrizes DfR RecyClass) — confirmar na ferramenta online
A9: RCA-005 | B9: FR-003-rPET-300 | C9: Frasco | D9: Cosmética e higiene pessoal | E9: Contacto direto com cosmético/higiene | F9: Injeção-sopro (ISBM) | G9: FAM-11 | H9: 300 | I9: 115 | J9: rPET | K9: =IFERROR(INDEX(tbl_materiais[Polimero_Base],MATCH(J9,tbl_materiais[Material],0)),"") -> PET | L9: =IFERROR(INDEX(tbl_materiais[Fluxo_Reciclagem],MATCH(J9,tbl_materiais[Material],0)),"") -> PET frascos e garrafas | M9: =IF(L9="PE rígido","PE rígido — frascos e contentores (HDPE/LDPE)",IF(L9="PP rígido","PP rígido — frascos, potes e contentores",IF(L9="PET frascos e garrafas",IF(O9="Natural / incolor","PET — garrafas/frascos transparentes incolores","PET — garrafas/frascos coloridos ou opacos"),"Sem categoria RecyClass ("&K9&")"))) -> PET — garrafas/frascos transparentes incolores | N9: Natural (Uncolored) | O9: Natural / incolor | P9: No Masterbatch | Q9: 0 | R9: =IFERROR(ROUND(INDEX(tbl_materiais[Densidade_g_cm3],MATCH(J9,tbl_materiais[Material],0))+Q9*1.2,3),"") -> 1.38 | S9: Nenhuma | T9: 22 | U9: Estimada (22 g a 300 ml, escala ^2/3) | V9: TR-001-PP-24410 | W9: =IF(V9="","",IFERROR(INDEX(tbl_tampas[Material],MATCH(V9,tbl_tampas[CapId],0)),"")) -> PP | X9: =IF(V9="","Sem tampa",IFERROR(INDEX(tbl_materiais[Polimero_Base],MATCH(W9,tbl_materiais[Material],0)),"")) -> PP | Y9: =IF(V9="",0,IFERROR(INDEX(tbl_tampas[Massa_g],MATCH(V9,tbl_tampas[CapId],0)),0)) -> 10.3 | Z9: Sem vedante | AA9: Sem rótulo | AB9: Sem adesivo | AC9: 0 | AD9: 0 | AE9: Sem rótulo (decoração direta Plasticom) | AF9: Hot foil metalizado | AG9: 1 | AH9: =IF(AF9="Serigrafia",IF(AG9>=3,"Serigrafia ≥ 3 cores","Serigrafia 1–2 cores"),AF9) -> Hot foil metalizado | AI9: 0.03 | AJ9: =IFERROR(INDEX(tbl_regras_dfr[Classe],MATCH(L9&"|Fluxo de reciclagem|"&L9,tbl_regras_dfr[Chave],0)),"Sem regra") -> A | AK9: =IF(LEFT(L9,9)="Sem fluxo","—",IFERROR(INDEX(tbl_regras_dfr[Classe],MATCH(L9&"|Cor do corpo|"&O9,tbl_regras_dfr[Chave],0)),"Sem regra")) -> A | AL9: =IF(LEFT(L9,9)="Sem fluxo","—",IFERROR(INDEX(tbl_regras_dfr[Classe],MATCH(L9&"|Densidade do corpo|"&IF(R9<1,"< 1,0 g/cm³","≥ 1,0 g/cm³"),tbl_regras_dfr[Chave],0)),"Sem regra")) -> A | AM9: =IF(LEFT(L9,9)="Sem fluxo","—",IFERROR(INDEX(tbl_regras_dfr[Classe],MATCH(L9&"|Barreira / revestimento|"&S9,tbl_regras_dfr[Chave],0)),"Sem regra")) -> A | AN9: =IF(LEFT(L9,9)="Sem fluxo","—",IFERROR(INDEX(tbl_regras_dfr[Classe],MATCH(L9&"|Material da tampa|"&X9,tbl_regras_dfr[Chave],0)),"Sem regra")) -> A | AO9: =IF(LEFT(L9,9)="Sem fluxo","—",IFERROR(INDEX(tbl_regras_dfr[Classe],MATCH(L9&"|Vedante / liner|"&Z9,tbl_regras_dfr[Chave],0)),"Sem regra")) -> A | AP9: =IF(LEFT(L9,9)="Sem fluxo","—",IFERROR(INDEX(tbl_regras_dfr[Classe],MATCH(L9&"|Tipo de rótulo|"&AA9,tbl_regras_dfr[Chave],0)),"Sem regra")) -> A | AQ9: =IF(LEFT(L9,9)="Sem fluxo","—",IFERROR(INDEX(tbl_regras_dfr[Classe],MATCH(L9&"|Adesivo do rótulo|"&AB9,tbl_regras_dfr[Chave],0)),"Sem regra")) -> A | AR9: =IF(LEFT(L9,9)="Sem fluxo","—",IFERROR(INDEX(tbl_regras_dfr[Classe],MATCH(L9&"|Cobertura do rótulo|"&IF(AC9>0.7,"> 70% da superfície","≤ 70% da superfície"),tbl_regras_dfr[Chave],0)),"Sem regra")) -> A | AS9: =IF(LEFT(L9,9)="Sem fluxo","—",IFERROR(INDEX(tbl_regras_dfr[Classe],MATCH(L9&"|Decoração direta|"&AH9,tbl_regras_dfr[Chave],0)),"Sem regra")) -> D | AT9: =IF(COUNTIF(AJ9:AS9,"F"),6,IF(COUNTIF(AJ9:AS9,"E"),5,IF(COUNTIF(AJ9:AS9,"D"),4,IF(COUNTIF(AJ9:AS9,"C"),3,IF(COUNTIF(AJ9:AS9,"B"),2,IF(COUNTIF(AJ9:AS9,"A"),1,0)))))) -> 4 | AU9: =IF(AT9=0,"",INDEX({"A","B","C","D","E","F"},AT9)) -> D | AV9: =COUNTIF(AJ9:AS9,"Sem regra") -> 0 | AW9: =IF(OR(AU9="",AU9="A"),"—",SUBSTITUTE(INDEX($AJ$4:$AS$4,MATCH(AU9,AJ9:AS9,0)),"Classe_","")) -> Decoracao | AX9: =IF(AU9="A","Sem ação — manter o design.",IFERROR(INDEX(tbl_regras_dfr[Recomendacao],MATCH(CHOOSE(MATCH(AU9,AJ9:AS9,0),L9&"|Fluxo de reciclagem|"&L9,L9&"|Cor do corpo|"&O9,L9&"|Densidade do corpo|"&IF(R9<1,"< 1,0 g/cm³","≥ 1,0 g/cm³"),L9&"|Barreira / revestimento|"&S9,L9&"|Material da tampa|"&X9,L9&"|Vedante / liner|"&Z9,L9&"|Tipo de rótulo|"&AA9,L9&"|Adesivo do rótulo|"&AB9,L9&"|Cobertura do rótulo|"&IF(AC9>0.7,"> 70% da superfície","≤ 70% da superfície"),L9&"|Decoração direta|"&AH9),tbl_regras_dfr[Chave],0)),"")) -> Rótulo metalizado de PE/PP destacável. | AY9: =T9+Y9+AD9+AI9 -> 32.33 | AZ9: =MIN(IFERROR(INDEX(tbl_regras_dfr[Fracao_Reciclavel],MATCH(L9&"|Fluxo de reciclagem|"&L9,tbl_regras_dfr[Chave],0)),0),IFERROR(INDEX(tbl_regras_dfr[Fracao_Reciclavel],MATCH(L9&"|Cor do corpo|"&O9,tbl_regras_dfr[Chave],0)),0)) -> 1 | BA9: =IFERROR(INDEX(tbl_regras_dfr[Fracao_Reciclavel],MATCH(L9&"|Material da tampa|"&X9,tbl_regras_dfr[Chave],0)),0) -> 1 | BB9: =IFERROR(INDEX(tbl_regras_dfr[Fracao_Reciclavel],MATCH(L9&"|Tipo de rótulo|"&AA9,tbl_regras_dfr[Chave],0)),0) -> 1 | BC9: =AZ9*(T9+Y9*BA9+AD9*BB9) -> 32.3 | BD9: =IFERROR(BC9/AY9,0) -> 0.99907207 | BE9: =IF(BD9>=INDEX(tbl_param_emb[Valor],MATCH("P-06",tbl_param_emb[ID_Parametro],0)),"A",IF(BD9>=INDEX(tbl_param_emb[Valor],MATCH("P-07",tbl_param_emb[ID_Parametro],0)),"B",IF(BD9>=INDEX(tbl_param_emb[Valor],MATCH("P-08",tbl_param_emb[ID_Parametro],0)),"C","< 70%"))) -> A | BF9: =IF(AU9="F","Não reciclável (F)",INDEX({"A","B","C","Abaixo de C"},MAX(MIN(AT9,4),IF(BE9="A",1,IF(BE9="B",2,IF(BE9="C",3,4)))))) -> Abaixo de C | BG9: =IF(D9="Farmacêutico","Isento até 2035","—") -> — | BH9: =IF(BG9<>"—",BG9,IF(OR(BF9="A",BF9="B",BF9="C"),"Sim","Não")) -> Não | BI9: =IF(BG9<>"—",BG9,IF(OR(BF9="A",BF9="B"),"Sim","Não")) -> Não | BJ9: =IFERROR(INDEX(tbl_materiais[Pct_PCR],MATCH(J9,tbl_materiais[Material],0)),0) -> 0.5 | BK9: =IF(V9="",0,IFERROR(INDEX(tbl_tampas[Pct_PCR],MATCH(V9,tbl_tampas[CapId],0)),0)) -> 0 | BL9: =IFERROR((T9*BJ9+Y9*BK9)/(T9+Y9),0) -> 0.34055728 | BM9: =IF(D9="Farmacêutico","Isenta — medicamentos (art. 7.º)",IF(D9="Alimentar",IF(K9="PET","Sensível ao contacto — PET","Sensível ao contacto — outros plásticos"),"Outras embalagens de plástico")) -> Outras embalagens de plástico | BN9: =IFERROR(IF(INDEX(tbl_metas_art7[Meta_2030],MATCH(BM9,tbl_metas_art7[Categoria_Art7],0))="","",INDEX(tbl_metas_art7[Meta_2030],MATCH(BM9,tbl_metas_art7[Categoria_Art7],0))),"") -> 0.35 | BO9: =IF(BN9="","",MAX(0,BN9-BL9)) -> 0.0094427245 | BP9: =IF(BN9="","Isento",IF(BO9=0,"Sim","Não")) -> Não | BQ9: =IF(AND(OR(X9=K9,X9="Sem tampa",AND(OR(X9="PE",X9="PP"),OR(K9="PE",K9="PP"))),OR(AA9="Sem rótulo",AND(ISNUMBER(SEARCH("PE/PP",AA9)),OR(K9="PE",K9="PP")))),"Monomaterial (mesma família)","Multimaterial") -> Multimaterial | BR9: 222782 | BS9: 14 | BT9: DE; ES; FR; IT; PL; PT | BU9: =BR9*T9/1000 -> 4901.204 | BV9: =COUNTIFS(tbl_aplicabilidade[ProductId],B9,tbl_aplicabilidade[Aplicavel],"Sim") -> 12 | BW9: =COUNTIFS(tbl_aplicabilidade[ProductId],B9,tbl_aplicabilidade[Estado_Resumo],"Lacuna")+COUNTIFS(tbl_aplicabilidade[ProductId],B9,tbl_aplicabilidade[Estado_Resumo],"Não conforme") -> 3 | BX9: 46287 | BY9: =EDATE(BX9,12) -> 46652 | BZ9: Responsável de R&D | CA9: Autoavaliação (não certificada) | CB9: Regras simplificadas SGA-20 v1 (diretrizes DfR RecyClass) — confirmar na ferramenta online
A10: RCA-006 | B10: FR-004-rPET-330 | C10: Frasco | D10: Cosmética e higiene pessoal | E10: Contacto direto com cosmético/higiene | F10: Injeção-sopro (ISBM) | G10: FAM-11 | H10: 330 | I10: 119 | J10: rPET | K10: =IFERROR(INDEX(tbl_materiais[Polimero_Base],MATCH(J10,tbl_materiais[Material],0)),"") -> PET | L10: =IFERROR(INDEX(tbl_materiais[Fluxo_Reciclagem],MATCH(J10,tbl_materiais[Material],0)),"") -> PET frascos e garrafas | M10: =IF(L10="PE rígido","PE rígido — frascos e contentores (HDPE/LDPE)",IF(L10="PP rígido","PP rígido — frascos, potes e contentores",IF(L10="PET frascos e garrafas",IF(O10="Natural / incolor","PET — garrafas/frascos transparentes incolores","PET — garrafas/frascos coloridos ou opacos"),"Sem categoria RecyClass ("&K10&")"))) -> PET — garrafas/frascos transparentes incolores | N10: Natural (Uncolored) | O10: Natural / incolor | P10: No Masterbatch | Q10: 0 | R10: =IFERROR(ROUND(INDEX(tbl_materiais[Densidade_g_cm3],MATCH(J10,tbl_materiais[Material],0))+Q10*1.2,3),"") -> 1.38 | S10: Nenhuma | T10: 23.4 | U10: Estimada (22 g a 300 ml, escala ^2/3) | V10: TF-005-PP-24410 | W10: =IF(V10="","",IFERROR(INDEX(tbl_tampas[Material],MATCH(V10,tbl_tampas[CapId],0)),"")) -> PP | X10: =IF(V10="","Sem tampa",IFERROR(INDEX(tbl_materiais[Polimero_Base],MATCH(W10,tbl_materiais[Material],0)),"")) -> PP | Y10: =IF(V10="",0,IFERROR(INDEX(tbl_tampas[Massa_g],MATCH(V10,tbl_tampas[CapId],0)),0)) -> 13.9 | Z10: Sem vedante | AA10: Sem rótulo | AB10: Sem adesivo | AC10: 0 | AD10: 0 | AE10: Sem rótulo (decoração direta Plasticom) | AF10: Hot foil metalizado | AG10: 1 | AH10: =IF(AF10="Serigrafia",IF(AG10>=3,"Serigrafia ≥ 3 cores","Serigrafia 1–2 cores"),AF10) -> Hot foil metalizado | AI10: 0.03 | AJ10: =IFERROR(INDEX(tbl_regras_dfr[Classe],MATCH(L10&"|Fluxo de reciclagem|"&L10,tbl_regras_dfr[Chave],0)),"Sem regra") -> A | AK10: =IF(LEFT(L10,9)="Sem fluxo","—",IFERROR(INDEX(tbl_regras_dfr[Classe],MATCH(L10&"|Cor do corpo|"&O10,tbl_regras_dfr[Chave],0)),"Sem regra")) -> A | AL10: =IF(LEFT(L10,9)="Sem fluxo","—",IFERROR(INDEX(tbl_regras_dfr[Classe],MATCH(L10&"|Densidade do corpo|"&IF(R10<1,"< 1,0 g/cm³","≥ 1,0 g/cm³"),tbl_regras_dfr[Chave],0)),"Sem regra")) -> A | AM10: =IF(LEFT(L10,9)="Sem fluxo","—",IFERROR(INDEX(tbl_regras_dfr[Classe],MATCH(L10&"|Barreira / revestimento|"&S10,tbl_regras_dfr[Chave],0)),"Sem regra")) -> A | AN10: =IF(LEFT(L10,9)="Sem fluxo","—",IFERROR(INDEX(tbl_regras_dfr[Classe],MATCH(L10&"|Material da tampa|"&X10,tbl_regras_dfr[Chave],0)),"Sem regra")) -> A | AO10: =IF(LEFT(L10,9)="Sem fluxo","—",IFERROR(INDEX(tbl_regras_dfr[Classe],MATCH(L10&"|Vedante / liner|"&Z10,tbl_regras_dfr[Chave],0)),"Sem regra")) -> A | AP10: =IF(LEFT(L10,9)="Sem fluxo","—",IFERROR(INDEX(tbl_regras_dfr[Classe],MATCH(L10&"|Tipo de rótulo|"&AA10,tbl_regras_dfr[Chave],0)),"Sem regra")) -> A | AQ10: =IF(LEFT(L10,9)="Sem fluxo","—",IFERROR(INDEX(tbl_regras_dfr[Classe],MATCH(L10&"|Adesivo do rótulo|"&AB10,tbl_regras_dfr[Chave],0)),"Sem regra")) -> A | AR10: =IF(LEFT(L10,9)="Sem fluxo","—",IFERROR(INDEX(tbl_regras_dfr[Classe],MATCH(L10&"|Cobertura do rótulo|"&IF(AC10>0.7,"> 70% da superfície","≤ 70% da superfície"),tbl_regras_dfr[Chave],0)),"Sem regra")) -> A | AS10: =IF(LEFT(L10,9)="Sem fluxo","—",IFERROR(INDEX(tbl_regras_dfr[Classe],MATCH(L10&"|Decoração direta|"&AH10,tbl_regras_dfr[Chave],0)),"Sem regra")) -> D | AT10: =IF(COUNTIF(AJ10:AS10,"F"),6,IF(COUNTIF(AJ10:AS10,"E"),5,IF(COUNTIF(AJ10:AS10,"D"),4,IF(COUNTIF(AJ10:AS10,"C"),3,IF(COUNTIF(AJ10:AS10,"B"),2,IF(COUNTIF(AJ10:AS10,"A"),1,0)))))) -> 4 | AU10: =IF(AT10=0,"",INDEX({"A","B","C","D","E","F"},AT10)) -> D | AV10: =COUNTIF(AJ10:AS10,"Sem regra") -> 0 | AW10: =IF(OR(AU10="",AU10="A"),"—",SUBSTITUTE(INDEX($AJ$4:$AS$4,MATCH(AU10,AJ10:AS10,0)),"Classe_","")) -> Decoracao | AX10: =IF(AU10="A","Sem ação — manter o design.",IFERROR(INDEX(tbl_regras_dfr[Recomendacao],MATCH(CHOOSE(MATCH(AU10,AJ10:AS10,0),L10&"|Fluxo de reciclagem|"&L10,L10&"|Cor do corpo|"&O10,L10&"|Densidade do corpo|"&IF(R10<1,"< 1,0 g/cm³","≥ 1,0 g/cm³"),L10&"|Barreira / revestimento|"&S10,L10&"|Material da tampa|"&X10,L10&"|Vedante / liner|"&Z10,L10&"|Tipo de rótulo|"&AA10,L10&"|Adesivo do rótulo|"&AB10,L10&"|Cobertura do rótulo|"&IF(AC10>0.7,"> 70% da superfície","≤ 70% da superfície"),L10&"|Decoração direta|"&AH10),tbl_regras_dfr[Chave],0)),"")) -> Rótulo metalizado de PE/PP destacável. | AY10: =T10+Y10+AD10+AI10 -> 37.33 | AZ10: =MIN(IFERROR(INDEX(tbl_regras_dfr[Fracao_Reciclavel],MATCH(L10&"|Fluxo de reciclagem|"&L10,tbl_regras_dfr[Chave],0)),0),IFERROR(INDEX(tbl_regras_dfr[Fracao_Reciclavel],MATCH(L10&"|Cor do corpo|"&O10,tbl_regras_dfr[Chave],0)),0)) -> 1 | BA10: =IFERROR(INDEX(tbl_regras_dfr[Fracao_Reciclavel],MATCH(L10&"|Material da tampa|"&X10,tbl_regras_dfr[Chave],0)),0) -> 1 | BB10: =IFERROR(INDEX(tbl_regras_dfr[Fracao_Reciclavel],MATCH(L10&"|Tipo de rótulo|"&AA10,tbl_regras_dfr[Chave],0)),0) -> 1 | BC10: =AZ10*(T10+Y10*BA10+AD10*BB10) -> 37.3 | BD10: =IFERROR(BC10/AY10,0) -> 0.99919636 | BE10: =IF(BD10>=INDEX(tbl_param_emb[Valor],MATCH("P-06",tbl_param_emb[ID_Parametro],0)),"A",IF(BD10>=INDEX(tbl_param_emb[Valor],MATCH("P-07",tbl_param_emb[ID_Parametro],0)),"B",IF(BD10>=INDEX(tbl_param_emb[Valor],MATCH("P-08",tbl_param_emb[ID_Parametro],0)),"C","< 70%"))) -> A | BF10: =IF(AU10="F","Não reciclável (F)",INDEX({"A","B","C","Abaixo de C"},MAX(MIN(AT10,4),IF(BE10="A",1,IF(BE10="B",2,IF(BE10="C",3,4)))))) -> Abaixo de C | BG10: =IF(D10="Farmacêutico","Isento até 2035","—") -> — | BH10: =IF(BG10<>"—",BG10,IF(OR(BF10="A",BF10="B",BF10="C"),"Sim","Não")) -> Não | BI10: =IF(BG10<>"—",BG10,IF(OR(BF10="A",BF10="B"),"Sim","Não")) -> Não | BJ10: =IFERROR(INDEX(tbl_materiais[Pct_PCR],MATCH(J10,tbl_materiais[Material],0)),0) -> 0.5 | BK10: =IF(V10="",0,IFERROR(INDEX(tbl_tampas[Pct_PCR],MATCH(V10,tbl_tampas[CapId],0)),0)) -> 0 | BL10: =IFERROR((T10*BJ10+Y10*BK10)/(T10+Y10),0) -> 0.31367292 | BM10: =IF(D10="Farmacêutico","Isenta — medicamentos (art. 7.º)",IF(D10="Alimentar",IF(K10="PET","Sensível ao contacto — PET","Sensível ao contacto — outros plásticos"),"Outras embalagens de plástico")) -> Outras embalagens de plástico | BN10: =IFERROR(IF(INDEX(tbl_metas_art7[Meta_2030],MATCH(BM10,tbl_metas_art7[Categoria_Art7],0))="","",INDEX(tbl_metas_art7[Meta_2030],MATCH(BM10,tbl_metas_art7[Categoria_Art7],0))),"") -> 0.35 | BO10: =IF(BN10="","",MAX(0,BN10-BL10)) -> 0.036327078 | BP10: =IF(BN10="","Isento",IF(BO10=0,"Sim","Não")) -> Não | BQ10: =IF(AND(OR(X10=K10,X10="Sem tampa",AND(OR(X10="PE",X10="PP"),OR(K10="PE",K10="PP"))),OR(AA10="Sem rótulo",AND(ISNUMBER(SEARCH("PE/PP",AA10)),OR(K10="PE",K10="PP")))),"Monomaterial (mesma família)","Multimaterial") -> Multimaterial | BR10: 491905 | BS10: 14 | BT10: DE; ES; FR; IT; PL; PT | BU10: =BR10*T10/1000 -> 11510.577 | BV10: =COUNTIFS(tbl_aplicabilidade[ProductId],B10,tbl_aplicabilidade[Aplicavel],"Sim") -> 12 | BW10: =COUNTIFS(tbl_aplicabilidade[ProductId],B10,tbl_aplicabilidade[Estado_Resumo],"Lacuna")+COUNTIFS(tbl_aplicabilidade[ProductId],B10,tbl_aplicabilidade[Estado_Resumo],"Não conforme") -> 3 | BX10: 46287 | BY10: =EDATE(BX10,12) -> 46652 | BZ10: Responsável de R&D | CA10: Autoavaliação (não certificada) | CB10: Regras simplificadas SGA-20 v1 (diretrizes DfR RecyClass) — confirmar na ferramenta online
A11: RCA-007 | B11: FR-008-HDPE-350 | C11: Frasco | D11: Cosmética e higiene pessoal | E11: Contacto direto com cosmético/higiene | F11: Injeção-sopro (ISBM) | G11: FAM-01 | H11: 350 | I11: 121 | J11: HDPE | K11: =IFERROR(INDEX(tbl_materiais[Polimero_Base],MATCH(J11,tbl_materiais[Material],0)),"") -> PE | L11: =IFERROR(INDEX(tbl_materiais[Fluxo_Reciclagem],MATCH(J11,tbl_materiais[Material],0)),"") -> PE rígido | M11: =IF(L11="PE rígido","PE rígido — frascos e contentores (HDPE/LDPE)",IF(L11="PP rígido","PP rígido — frascos, potes e contentores",IF(L11="PET frascos e garrafas",IF(O11="Natural / incolor","PET — garrafas/frascos transparentes incolores","PET — garrafas/frascos coloridos ou opacos"),"Sem categoria RecyClass ("&K11&")"))) -> PE rígido — frascos e contentores (HDPE/LDPE) | N11: Graphite Gray | O11: Colorido escuro / opaco | P11: Gray Masterbatch | Q11: 0.02 | R11: =IFERROR(ROUND(INDEX(tbl_materiais[Densidade_g_cm3],MATCH(J11,tbl_materiais[Material],0))+Q11*1.2,3),"") -> 0.979 | S11: Nenhuma | T11: 24.4 | U11: Estimada (22 g a 300 ml, escala ^2/3) | V11: TF-005-HDPE-24410 | W11: =IF(V11="","",IFERROR(INDEX(tbl_tampas[Material],MATCH(V11,tbl_tampas[CapId],0)),"")) -> HDPE | X11: =IF(V11="","Sem tampa",IFERROR(INDEX(tbl_materiais[Polimero_Base],MATCH(W11,tbl_materiais[Material],0)),"")) -> PE | Y11: =IF(V11="",0,IFERROR(INDEX(tbl_tampas[Massa_g],MATCH(V11,tbl_tampas[CapId],0)),0)) -> 15.5 | Z11: Sem vedante | AA11: Sem rótulo | AB11: Sem adesivo | AC11: 0 | AD11: 0 | AE11: Sem rótulo (decoração direta Plasticom) | AF11: Serigrafia | AG11: 2 | AH11: =IF(AF11="Serigrafia",IF(AG11>=3,"Serigrafia ≥ 3 cores","Serigrafia 1–2 cores"),AF11) -> Serigrafia 1–2 cores | AI11: 0.16 | AJ11: =IFERROR(INDEX(tbl_regras_dfr[Classe],MATCH(L11&"|Fluxo de reciclagem|"&L11,tbl_regras_dfr[Chave],0)),"Sem regra") -> A | AK11: =IF(LEFT(L11,9)="Sem fluxo","—",IFERROR(INDEX(tbl_regras_dfr[Classe],MATCH(L11&"|Cor do corpo|"&O11,tbl_regras_dfr[Chave],0)),"Sem regra")) -> B | AL11: =IF(LEFT(L11,9)="Sem fluxo","—",IFERROR(INDEX(tbl_regras_dfr[Classe],MATCH(L11&"|Densidade do corpo|"&IF(R11<1,"< 1,0 g/cm³","≥ 1,0 g/cm³"),tbl_regras_dfr[Chave],0)),"Sem regra")) -> A | AM11: =IF(LEFT(L11,9)="Sem fluxo","—",IFERROR(INDEX(tbl_regras_dfr[Classe],MATCH(L11&"|Barreira / revestimento|"&S11,tbl_regras_dfr[Chave],0)),"Sem regra")) -> A | AN11: =IF(LEFT(L11,9)="Sem fluxo","—",IFERROR(INDEX(tbl_regras_dfr[Classe],MATCH(L11&"|Material da tampa|"&X11,tbl_regras_dfr[Chave],0)),"Sem regra")) -> A | AO11: =IF(LEFT(L11,9)="Sem fluxo","—",IFERROR(INDEX(tbl_regras_dfr[Classe],MATCH(L11&"|Vedante / liner|"&Z11,tbl_regras_dfr[Chave],0)),"Sem regra")) -> A | AP11: =IF(LEFT(L11,9)="Sem fluxo","—",IFERROR(INDEX(tbl_regras_dfr[Classe],MATCH(L11&"|Tipo de rótulo|"&AA11,tbl_regras_dfr[Chave],0)),"Sem regra")) -> A | AQ11: =IF(LEFT(L11,9)="Sem fluxo","—",IFERROR(INDEX(tbl_regras_dfr[Classe],MATCH(L11&"|Adesivo do rótulo|"&AB11,tbl_regras_dfr[Chave],0)),"Sem regra")) -> A | AR11: =IF(LEFT(L11,9)="Sem fluxo","—",IFERROR(INDEX(tbl_regras_dfr[Classe],MATCH(L11&"|Cobertura do rótulo|"&IF(AC11>0.7,"> 70% da superfície","≤ 70% da superfície"),tbl_regras_dfr[Chave],0)),"Sem regra")) -> A | AS11: =IF(LEFT(L11,9)="Sem fluxo","—",IFERROR(INDEX(tbl_regras_dfr[Classe],MATCH(L11&"|Decoração direta|"&AH11,tbl_regras_dfr[Chave],0)),"Sem regra")) -> B | AT11: =IF(COUNTIF(AJ11:AS11,"F"),6,IF(COUNTIF(AJ11:AS11,"E"),5,IF(COUNTIF(AJ11:AS11,"D"),4,IF(COUNTIF(AJ11:AS11,"C"),3,IF(COUNTIF(AJ11:AS11,"B"),2,IF(COUNTIF(AJ11:AS11,"A"),1,0)))))) -> 2 | AU11: =IF(AT11=0,"",INDEX({"A","B","C","D","E","F"},AT11)) -> B | AV11: =COUNTIF(AJ11:AS11,"Sem regra") -> 0 | AW11: =IF(OR(AU11="",AU11="A"),"—",SUBSTITUTE(INDEX($AJ$4:$AS$4,MATCH(AU11,AJ11:AS11,0)),"Classe_","")) -> Cor | AX11: =IF(AU11="A","Sem ação — manter o design.",IFERROR(INDEX(tbl_regras_dfr[Recomendacao],MATCH(CHOOSE(MATCH(AU11,AJ11:AS11,0),L11&"|Fluxo de reciclagem|"&L11,L11&"|Cor do corpo|"&O11,L11&"|Densidade do corpo|"&IF(R11<1,"< 1,0 g/cm³","≥ 1,0 g/cm³"),L11&"|Barreira / revestimento|"&S11,L11&"|Material da tampa|"&X11,L11&"|Vedante / liner|"&Z11,L11&"|Tipo de rótulo|"&AA11,L11&"|Adesivo do rótulo|"&AB11,L11&"|Cobertura do rótulo|"&IF(AC11>0.7,"> 70% da superfície","≤ 70% da superfície"),L11&"|Decoração direta|"&AH11),tbl_regras_dfr[Chave],0)),"")) -> Preferir cores claras. | AY11: =T11+Y11+AD11+AI11 -> 40.06 | AZ11: =MIN(IFERROR(INDEX(tbl_regras_dfr[Fracao_Reciclavel],MATCH(L11&"|Fluxo de reciclagem|"&L11,tbl_regras_dfr[Chave],0)),0),IFERROR(INDEX(tbl_regras_dfr[Fracao_Reciclavel],MATCH(L11&"|Cor do corpo|"&O11,tbl_regras_dfr[Chave],0)),0)) -> 1 | BA11: =IFERROR(INDEX(tbl_regras_dfr[Fracao_Reciclavel],MATCH(L11&"|Material da tampa|"&X11,tbl_regras_dfr[Chave],0)),0) -> 1 | BB11: =IFERROR(INDEX(tbl_regras_dfr[Fracao_Reciclavel],MATCH(L11&"|Tipo de rótulo|"&AA11,tbl_regras_dfr[Chave],0)),0) -> 1 | BC11: =AZ11*(T11+Y11*BA11+AD11*BB11) -> 39.9 | BD11: =IFERROR(BC11/AY11,0) -> 0.99600599 | BE11: =IF(BD11>=INDEX(tbl_param_emb[Valor],MATCH("P-06",tbl_param_emb[ID_Parametro],0)),"A",IF(BD11>=INDEX(tbl_param_emb[Valor],MATCH("P-07",tbl_param_emb[ID_Parametro],0)),"B",IF(BD11>=INDEX(tbl_param_emb[Valor],MATCH("P-08",tbl_param_emb[ID_Parametro],0)),"C","< 70%"))) -> A | BF11: =IF(AU11="F","Não reciclável (F)",INDEX({"A","B","C","Abaixo de C"},MAX(MIN(AT11,4),IF(BE11="A",1,IF(BE11="B",2,IF(BE11="C",3,4)))))) -> B | BG11: =IF(D11="Farmacêutico","Isento até 2035","—") -> — | BH11: =IF(BG11<>"—",BG11,IF(OR(BF11="A",BF11="B",BF11="C"),"Sim","Não")) -> Sim | BI11: =IF(BG11<>"—",BG11,IF(OR(BF11="A",BF11="B"),"Sim","Não")) -> Sim | BJ11: =IFERROR(INDEX(tbl_materiais[Pct_PCR],MATCH(J11,tbl_materiais[Material],0)),0) -> 0 | BK11: =IF(V11="",0,IFERROR(INDEX(tbl_tampas[Pct_PCR],MATCH(V11,tbl_tampas[CapId],0)),0)) -> 0 | BL11: =IFERROR((T11*BJ11+Y11*BK11)/(T11+Y11),0) -> 0 | BM11: =IF(D11="Farmacêutico","Isenta — medicamentos (art. 7.º)",IF(D11="Alimentar",IF(K11="PET","Sensível ao contacto — PET","Sensível ao contacto — outros plásticos"),"Outras embalagens de plástico")) -> Outras embalagens de plástico | BN11: =IFERROR(IF(INDEX(tbl_metas_art7[Meta_2030],MATCH(BM11,tbl_metas_art7[Categoria_Art7],0))="","",INDEX(tbl_metas_art7[Meta_2030],MATCH(BM11,tbl_metas_art7[Categoria_Art7],0))),"") -> 0.35 | BO11: =IF(BN11="","",MAX(0,BN11-BL11)) -> 0.35 | BP11: =IF(BN11="","Isento",IF(BO11=0,"Sim","Não")) -> Não | BQ11: =IF(AND(OR(X11=K11,X11="Sem tampa",AND(OR(X11="PE",X11="PP"),OR(K11="PE",K11="PP"))),OR(AA11="Sem rótulo",AND(ISNUMBER(SEARCH("PE/PP",AA11)),OR(K11="PE",K11="PP")))),"Monomaterial (mesma família)","Multimaterial") -> Monomaterial (mesma família) | BR11: 90151 | BS11: 10 | BT11: DE; ES; FR; IT; PT | BU11: =BR11*T11/1000 -> 2199.6844 | BV11: =COUNTIFS(tbl_aplicabilidade[ProductId],B11,tbl_aplicabilidade[Aplicavel],"Sim") -> 12 | BW11: =COUNTIFS(tbl_aplicabilidade[ProductId],B11,tbl_aplicabilidade[Estado_Resumo],"Lacuna")+COUNTIFS(tbl_aplicabilidade[ProductId],B11,tbl_aplicabilidade[Estado_Resumo],"Não conforme") -> 1 | BX11: 46287 | BY11: =EDATE(BX11,12) -> 46652 | BZ11: Responsável de R&D | CA11: Autoavaliação (não certificada) | CB11: Regras simplificadas SGA-20 v1 (diretrizes DfR RecyClass) — confirmar na ferramenta online
A12: RCA-008 | B12: FR-007-HDPE-350 | C12: Frasco | D12: Cosmética e higiene pessoal | E12: Contacto direto com cosmético/higiene | F12: Injeção-sopro (ISBM) | G12: FAM-01 | H12: 350 | I12: 121 | J12: HDPE | K12: =IFERROR(INDEX(tbl_materiais[Polimero_Base],MATCH(J12,tbl_materiais[Material],0)),"") -> PE | L12: =IFERROR(INDEX(tbl_materiais[Fluxo_Reciclagem],MATCH(J12,tbl_materiais[Material],0)),"") -> PE rígido | M12: =IF(L12="PE rígido","PE rígido — frascos e contentores (HDPE/LDPE)",IF(L12="PP rígido","PP rígido — frascos, potes e contentores",IF(L12="PET frascos e garrafas",IF(O12="Natural / incolor","PET — garrafas/frascos transparentes incolores","PET — garrafas/frascos coloridos ou opacos"),"Sem categoria RecyClass ("&K12&")"))) -> PE rígido — frascos e contentores (HDPE/LDPE) | N12: Translucent Amber | O12: Colorido (claro ou transparente) | P12: Amber Masterbatch | Q12: 0.015 | R12: =IFERROR(ROUND(INDEX(tbl_materiais[Densidade_g_cm3],MATCH(J12,tbl_materiais[Material],0))+Q12*1.2,3),"") -> 0.973 | S12: Nenhuma | T12: 24.4 | U12: Estimada (22 g a 300 ml, escala ^2/3) | V12: TR-001-HDPE-24410 | W12: =IF(V12="","",IFERROR(INDEX(tbl_tampas[Material],MATCH(V12,tbl_tampas[CapId],0)),"")) -> HDPE | X12: =IF(V12="","Sem tampa",IFERROR(INDEX(tbl_materiais[Polimero_Base],MATCH(W12,tbl_materiais[Material],0)),"")) -> PE | Y12: =IF(V12="",0,IFERROR(INDEX(tbl_tampas[Massa_g],MATCH(V12,tbl_tampas[CapId],0)),0)) -> 11.5 | Z12: Sem vedante | AA12: Sem rótulo | AB12: Sem adesivo | AC12: 0 | AD12: 0 | AE12: Sem rótulo (decoração direta Plasticom) | AF12: Serigrafia | AG12: 3 | AH12: =IF(AF12="Serigrafia",IF(AG12>=3,"Serigrafia ≥ 3 cores","Serigrafia 1–2 cores"),AF12) -> Serigrafia ≥ 3 cores | AI12: 0.24 | AJ12: =IFERROR(INDEX(tbl_regras_dfr[Classe],MATCH(L12&"|Fluxo de reciclagem|"&L12,tbl_regras_dfr[Chave],0)),"Sem regra") -> A | AK12: =IF(LEFT(L12,9)="Sem fluxo","—",IFERROR(INDEX(tbl_regras_dfr[Classe],MATCH(L12&"|Cor do corpo|"&O12,tbl_regras_dfr[Chave],0)),"Sem regra")) -> B | AL12: =IF(LEFT(L12,9)="Sem fluxo","—",IFERROR(INDEX(tbl_regras_dfr[Classe],MATCH(L12&"|Densidade do corpo|"&IF(R12<1,"< 1,0 g/cm³","≥ 1,0 g/cm³"),tbl_regras_dfr[Chave],0)),"Sem regra")) -> A | AM12: =IF(LEFT(L12,9)="Sem fluxo","—",IFERROR(INDEX(tbl_regras_dfr[Classe],MATCH(L12&"|Barreira / revestimento|"&S12,tbl_regras_dfr[Chave],0)),"Sem regra")) -> A | AN12: =IF(LEFT(L12,9)="Sem fluxo","—",IFERROR(INDEX(tbl_regras_dfr[Classe],MATCH(L12&"|Material da tampa|"&X12,tbl_regras_dfr[Chave],0)),"Sem regra")) -> A | AO12: =IF(LEFT(L12,9)="Sem fluxo","—",IFERROR(INDEX(tbl_regras_dfr[Classe],MATCH(L12&"|Vedante / liner|"&Z12,tbl_regras_dfr[Chave],0)),"Sem regra")) -> A | AP12: =IF(LEFT(L12,9)="Sem fluxo","—",IFERROR(INDEX(tbl_regras_dfr[Classe],MATCH(L12&"|Tipo de rótulo|"&AA12,tbl_regras_dfr[Chave],0)),"Sem regra")) -> A | AQ12: =IF(LEFT(L12,9)="Sem fluxo","—",IFERROR(INDEX(tbl_regras_dfr[Classe],MATCH(L12&"|Adesivo do rótulo|"&AB12,tbl_regras_dfr[Chave],0)),"Sem regra")) -> A | AR12: =IF(LEFT(L12,9)="Sem fluxo","—",IFERROR(INDEX(tbl_regras_dfr[Classe],MATCH(L12&"|Cobertura do rótulo|"&IF(AC12>0.7,"> 70% da superfície","≤ 70% da superfície"),tbl_regras_dfr[Chave],0)),"Sem regra")) -> A | AS12: =IF(LEFT(L12,9)="Sem fluxo","—",IFERROR(INDEX(tbl_regras_dfr[Classe],MATCH(L12&"|Decoração direta|"&AH12,tbl_regras_dfr[Chave],0)),"Sem regra")) -> C | AT12: =IF(COUNTIF(AJ12:AS12,"F"),6,IF(COUNTIF(AJ12:AS12,"E"),5,IF(COUNTIF(AJ12:AS12,"D"),4,IF(COUNTIF(AJ12:AS12,"C"),3,IF(COUNTIF(AJ12:AS12,"B"),2,IF(COUNTIF(AJ12:AS12,"A"),1,0)))))) -> 3 | AU12: =IF(AT12=0,"",INDEX({"A","B","C","D","E","F"},AT12)) -> C | AV12: =COUNTIF(AJ12:AS12,"Sem regra") -> 0 | AW12: =IF(OR(AU12="",AU12="A"),"—",SUBSTITUTE(INDEX($AJ$4:$AS$4,MATCH(AU12,AJ12:AS12,0)),"Classe_","")) -> Decoracao | AX12: =IF(AU12="A","Sem ação — manter o design.",IFERROR(INDEX(tbl_regras_dfr[Recomendacao],MATCH(CHOOSE(MATCH(AU12,AJ12:AS12,0),L12&"|Fluxo de reciclagem|"&L12,L12&"|Cor do corpo|"&O12,L12&"|Densidade do corpo|"&IF(R12<1,"< 1,0 g/cm³","≥ 1,0 g/cm³"),L12&"|Barreira / revestimento|"&S12,L12&"|Material da tampa|"&X12,L12&"|Vedante / liner|"&Z12,L12&"|Tipo de rótulo|"&AA12,L12&"|Adesivo do rótulo|"&AB12,L12&"|Cobertura do rótulo|"&IF(AC12>0.7,"> 70% da superfície","≤ 70% da superfície"),L12&"|Decoração direta|"&AH12),tbl_regras_dfr[Chave],0)),"")) -> Reduzir cores/área ou passar a rótulo de PE/PP. | AY12: =T12+Y12+AD12+AI12 -> 36.14 | AZ12: =MIN(IFERROR(INDEX(tbl_regras_dfr[Fracao_Reciclavel],MATCH(L12&"|Fluxo de reciclagem|"&L12,tbl_regras_dfr[Chave],0)),0),IFERROR(INDEX(tbl_regras_dfr[Fracao_Reciclavel],MATCH(L12&"|Cor do corpo|"&O12,tbl_regras_dfr[Chave],0)),0)) -> 1 | BA12: =IFERROR(INDEX(tbl_regras_dfr[Fracao_Reciclavel],MATCH(L12&"|Material da tampa|"&X12,tbl_regras_dfr[Chave],0)),0) -> 1 | BB12: =IFERROR(INDEX(tbl_regras_dfr[Fracao_Reciclavel],MATCH(L12&"|Tipo de rótulo|"&AA12,tbl_regras_dfr[Chave],0)),0) -> 1 | BC12: =AZ12*(T12+Y12*BA12+AD12*BB12) -> 35.9 | BD12: =IFERROR(BC12/AY12,0) -> 0.99335916 | BE12: =IF(BD12>=INDEX(tbl_param_emb[Valor],MATCH("P-06",tbl_param_emb[ID_Parametro],0)),"A",IF(BD12>=INDEX(tbl_param_emb[Valor],MATCH("P-07",tbl_param_emb[ID_Parametro],0)),"B",IF(BD12>=INDEX(tbl_param_emb[Valor],MATCH("P-08",tbl_param_emb[ID_Parametro],0)),"C","< 70%"))) -> A | BF12: =IF(AU12="F","Não reciclável (F)",INDEX({"A","B","C","Abaixo de C"},MAX(MIN(AT12,4),IF(BE12="A",1,IF(BE12="B",2,IF(BE12="C",3,4)))))) -> C | BG12: =IF(D12="Farmacêutico","Isento até 2035","—") -> — | BH12: =IF(BG12<>"—",BG12,IF(OR(BF12="A",BF12="B",BF12="C"),"Sim","Não")) -> Sim | BI12: =IF(BG12<>"—",BG12,IF(OR(BF12="A",BF12="B"),"Sim","Não")) -> Não | BJ12: =IFERROR(INDEX(tbl_materiais[Pct_PCR],MATCH(J12,tbl_materiais[Material],0)),0) -> 0 | BK12: =IF(V12="",0,IFERROR(INDEX(tbl_tampas[Pct_PCR],MATCH(V12,tbl_tampas[CapId],0)),0)) -> 0 | BL12: =IFERROR((T12*BJ12+Y12*BK12)/(T12+Y12),0) -> 0 | BM12: =IF(D12="Farmacêutico","Isenta — medicamentos (art. 7.º)",IF(D12="Alimentar",IF(K12="PET","Sensível ao contacto — PET","Sensível ao contacto — outros plásticos"),"Outras embalagens de plástico")) -> Outras embalagens de plástico | BN12: =IFERROR(IF(INDEX(tbl_metas_art7[Meta_2030],MATCH(BM12,tbl_metas_art7[Categoria_Art7],0))="","",INDEX(tbl_metas_art7[Meta_2030],MATCH(BM12,tbl_metas_art7[Categoria_Art7],0))),"") -> 0.35 | BO12: =IF(BN12="","",MAX(0,BN12-BL12)) -> 0.35 | BP12: =IF(BN12="","Isento",IF(BO12=0,"Sim","Não")) -> Não | BQ12: =IF(AND(OR(X12=K12,X12="Sem tampa",AND(OR(X12="PE",X12="PP"),OR(K12="PE",K12="PP"))),OR(AA12="Sem rótulo",AND(ISNUMBER(SEARCH("PE/PP",AA12)),OR(K12="PE",K12="PP")))),"Monomaterial (mesma família)","Multimaterial") -> Monomaterial (mesma família) | BR12: 108196 | BS12: 11 | BT12: DE; ES; FR; IT; PL; PT | BU12: =BR12*T12/1000 -> 2639.9824 | BV12: =COUNTIFS(tbl_aplicabilidade[ProductId],B12,tbl_aplicabilidade[Aplicavel],"Sim") -> 12 | BW12: =COUNTIFS(tbl_aplicabilidade[ProductId],B12,tbl_aplicabilidade[Estado_Resumo],"Lacuna")+COUNTIFS(tbl_aplicabilidade[ProductId],B12,tbl_aplicabilidade[Estado_Resumo],"Não conforme") -> 1 | BX12: 46287 | BY12: =EDATE(BX12,12) -> 46652 | BZ12: Responsável de R&D | CA12: Autoavaliação (não certificada) | CB12: Regras simplificadas SGA-20 v1 (diretrizes DfR RecyClass) — confirmar na ferramenta online
A13: RCA-009 | B13: FR-009-HDPE-350 | C13: Frasco | D13: Cosmética e higiene pessoal | E13: Contacto direto com cosmético/higiene | F13: Injeção-sopro (ISBM) | G13: FAM-01 | H13: 350 | I13: 121 | J13: HDPE | K13: =IFERROR(INDEX(tbl_materiais[Polimero_Base],MATCH(J13,tbl_materiais[Material],0)),"") -> PE | L13: =IFERROR(INDEX(tbl_materiais[Fluxo_Reciclagem],MATCH(J13,tbl_materiais[Material],0)),"") -> PE rígido | M13: =IF(L13="PE rígido","PE rígido — frascos e contentores (HDPE/LDPE)",IF(L13="PP rígido","PP rígido — frascos, potes e contentores",IF(L13="PET frascos e garrafas",IF(O13="Natural / incolor","PET — garrafas/frascos transparentes incolores","PET — garrafas/frascos coloridos ou opacos"),"Sem categoria RecyClass ("&K13&")"))) -> PE rígido — frascos e contentores (HDPE/LDPE) | N13: Cardinal Red | O13: Colorido (claro ou transparente) | P13: Red Masterbatch | Q13: 0.02 | R13: =IFERROR(ROUND(INDEX(tbl_materiais[Densidade_g_cm3],MATCH(J13,tbl_materiais[Material],0))+Q13*1.2,3),"") -> 0.979 | S13: Nenhuma | T13: 24.4 | U13: Estimada (22 g a 300 ml, escala ^2/3) | V13: TR-001-HDPE-24410 | W13: =IF(V13="","",IFERROR(INDEX(tbl_tampas[Material],MATCH(V13,tbl_tampas[CapId],0)),"")) -> HDPE | X13: =IF(V13="","Sem tampa",IFERROR(INDEX(tbl_materiais[Polimero_Base],MATCH(W13,tbl_materiais[Material],0)),"")) -> PE | Y13: =IF(V13="",0,IFERROR(INDEX(tbl_tampas[Massa_g],MATCH(V13,tbl_tampas[CapId],0)),0)) -> 11.5 | Z13: Sem vedante | AA13: Autoadesivo PE/PP | AB13: Acrílico permanente | AC13: 0.4 | AD13: 0.51 | AE13: Cenário típico do cliente — confirmar especificação | AF13: Nenhuma | AG13: 0 | AH13: =IF(AF13="Serigrafia",IF(AG13>=3,"Serigrafia ≥ 3 cores","Serigrafia 1–2 cores"),AF13) -> Nenhuma | AI13: 0 | AJ13: =IFERROR(INDEX(tbl_regras_dfr[Classe],MATCH(L13&"|Fluxo de reciclagem|"&L13,tbl_regras_dfr[Chave],0)),"Sem regra") -> A | AK13: =IF(LEFT(L13,9)="Sem fluxo","—",IFERROR(INDEX(tbl_regras_dfr[Classe],MATCH(L13&"|Cor do corpo|"&O13,tbl_regras_dfr[Chave],0)),"Sem regra")) -> B | AL13: =IF(LEFT(L13,9)="Sem fluxo","—",IFERROR(INDEX(tbl_regras_dfr[Classe],MATCH(L13&"|Densidade do corpo|"&IF(R13<1,"< 1,0 g/cm³","≥ 1,0 g/cm³"),tbl_regras_dfr[Chave],0)),"Sem regra")) -> A | AM13: =IF(LEFT(L13,9)="Sem fluxo","—",IFERROR(INDEX(tbl_regras_dfr[Classe],MATCH(L13&"|Barreira / revestimento|"&S13,tbl_regras_dfr[Chave],0)),"Sem regra")) -> A | AN13: =IF(LEFT(L13,9)="Sem fluxo","—",IFERROR(INDEX(tbl_regras_dfr[Classe],MATCH(L13&"|Material da tampa|"&X13,tbl_regras_dfr[Chave],0)),"Sem regra")) -> A | AO13: =IF(LEFT(L13,9)="Sem fluxo","—",IFERROR(INDEX(tbl_regras_dfr[Classe],MATCH(L13&"|Vedante / liner|"&Z13,tbl_regras_dfr[Chave],0)),"Sem regra")) -> A | AP13: =IF(LEFT(L13,9)="Sem fluxo","—",IFERROR(INDEX(tbl_regras_dfr[Classe],MATCH(L13&"|Tipo de rótulo|"&AA13,tbl_regras_dfr[Chave],0)),"Sem regra")) -> A | AQ13: =IF(LEFT(L13,9)="Sem fluxo","—",IFERROR(INDEX(tbl_regras_dfr[Classe],MATCH(L13&"|Adesivo do rótulo|"&AB13,tbl_regras_dfr[Chave],0)),"Sem regra")) -> A | AR13: =IF(LEFT(L13,9)="Sem fluxo","—",IFERROR(INDEX(tbl_regras_dfr[Classe],MATCH(L13&"|Cobertura do rótulo|"&IF(AC13>0.7,"> 70% da superfície","≤ 70% da superfície"),tbl_regras_dfr[Chave],0)),"Sem regra")) -> A | AS13: =IF(LEFT(L13,9)="Sem fluxo","—",IFERROR(INDEX(tbl_regras_dfr[Classe],MATCH(L13&"|Decoração direta|"&AH13,tbl_regras_dfr[Chave],0)),"Sem regra")) -> A | AT13: =IF(COUNTIF(AJ13:AS13,"F"),6,IF(COUNTIF(AJ13:AS13,"E"),5,IF(COUNTIF(AJ13:AS13,"D"),4,IF(COUNTIF(AJ13:AS13,"C"),3,IF(COUNTIF(AJ13:AS13,"B"),2,IF(COUNTIF(AJ13:AS13,"A"),1,0)))))) -> 2 | AU13: =IF(AT13=0,"",INDEX({"A","B","C","D","E","F"},AT13)) -> B | AV13: =COUNTIF(AJ13:AS13,"Sem regra") -> 0 | AW13: =IF(OR(AU13="",AU13="A"),"—",SUBSTITUTE(INDEX($AJ$4:$AS$4,MATCH(AU13,AJ13:AS13,0)),"Classe_","")) -> Cor | AX13: =IF(AU13="A","Sem ação — manter o design.",IFERROR(INDEX(tbl_regras_dfr[Recomendacao],MATCH(CHOOSE(MATCH(AU13,AJ13:AS13,0),L13&"|Fluxo de reciclagem|"&L13,L13&"|Cor do corpo|"&O13,L13&"|Densidade do corpo|"&IF(R13<1,"< 1,0 g/cm³","≥ 1,0 g/cm³"),L13&"|Barreira / revestimento|"&S13,L13&"|Material da tampa|"&X13,L13&"|Vedante / liner|"&Z13,L13&"|Tipo de rótulo|"&AA13,L13&"|Adesivo do rótulo|"&AB13,L13&"|Cobertura do rótulo|"&IF(AC13>0.7,"> 70% da superfície","≤ 70% da superfície"),L13&"|Decoração direta|"&AH13),tbl_regras_dfr[Chave],0)),"")) -> Preferir natural, branco ou cores claras. | AY13: =T13+Y13+AD13+AI13 -> 36.41 | AZ13: =MIN(IFERROR(INDEX(tbl_regras_dfr[Fracao_Reciclavel],MATCH(L13&"|Fluxo de reciclagem|"&L13,tbl_regras_dfr[Chave],0)),0),IFERROR(INDEX(tbl_regras_dfr[Fracao_Reciclavel],MATCH(L13&"|Cor do corpo|"&O13,tbl_regras_dfr[Chave],0)),0)) -> 1 | BA13: =IFERROR(INDEX(tbl_regras_dfr[Fracao_Reciclavel],MATCH(L13&"|Material da tampa|"&X13,tbl_regras_dfr[Chave],0)),0) -> 1 | BB13: =IFERROR(INDEX(tbl_regras_dfr[Fracao_Reciclavel],MATCH(L13&"|Tipo de rótulo|"&AA13,tbl_regras_dfr[Chave],0)),0) -> 1 | BC13: =AZ13*(T13+Y13*BA13+AD13*BB13) -> 36.41 | BD13: =IFERROR(BC13/AY13,0) -> 1 | BE13: =IF(BD13>=INDEX(tbl_param_emb[Valor],MATCH("P-06",tbl_param_emb[ID_Parametro],0)),"A",IF(BD13>=INDEX(tbl_param_emb[Valor],MATCH("P-07",tbl_param_emb[ID_Parametro],0)),"B",IF(BD13>=INDEX(tbl_param_emb[Valor],MATCH("P-08",tbl_param_emb[ID_Parametro],0)),"C","< 70%"))) -> A | BF13: =IF(AU13="F","Não reciclável (F)",INDEX({"A","B","C","Abaixo de C"},MAX(MIN(AT13,4),IF(BE13="A",1,IF(BE13="B",2,IF(BE13="C",3,4)))))) -> B | BG13: =IF(D13="Farmacêutico","Isento até 2035","—") -> — | BH13: =IF(BG13<>"—",BG13,IF(OR(BF13="A",BF13="B",BF13="C"),"Sim","Não")) -> Sim | BI13: =IF(BG13<>"—",BG13,IF(OR(BF13="A",BF13="B"),"Sim","Não")) -> Sim | BJ13: =IFERROR(INDEX(tbl_materiais[Pct_PCR],MATCH(J13,tbl_materiais[Material],0)),0) -> 0 | BK13: =IF(V13="",0,IFERROR(INDEX(tbl_tampas[Pct_PCR],MATCH(V13,tbl_tampas[CapId],0)),0)) -> 0 | BL13: =IFERROR((T13*BJ13+Y13*BK13)/(T13+Y13),0) -> 0 | BM13: =IF(D13="Farmacêutico","Isenta — medicamentos (art. 7.º)",IF(D13="Alimentar",IF(K13="PET","Sensível ao contacto — PET","Sensível ao contacto — outros plásticos"),"Outras embalagens de plástico")) -> Outras embalagens de plástico | BN13: =IFERROR(IF(INDEX(tbl_metas_art7[Meta_2030],MATCH(BM13,tbl_metas_art7[Categoria_Art7],0))="","",INDEX(tbl_metas_art7[Meta_2030],MATCH(BM13,tbl_metas_art7[Categoria_Art7],0))),"") -> 0.35 | BO13: =IF(BN13="","",MAX(0,BN13-BL13)) -> 0.35 | BP13: =IF(BN13="","Isento",IF(BO13=0,"Sim","Não")) -> Não | BQ13: =IF(AND(OR(X13=K13,X13="Sem tampa",AND(OR(X13="PE",X13="PP"),OR(K13="PE",K13="PP"))),OR(AA13="Sem rótulo",AND(ISNUMBER(SEARCH("PE/PP",AA13)),OR(K13="PE",K13="PP")))),"Monomaterial (mesma família)","Multimaterial") -> Monomaterial (mesma família) | BR13: 71912 | BS13: 11 | BT13: DE; ES; FR; PL; PT | BU13: =BR13*T13/1000 -> 1754.6528 | BV13: =COUNTIFS(tbl_aplicabilidade[ProductId],B13,tbl_aplicabilidade[Aplicavel],"Sim") -> 12 | BW13: =COUNTIFS(tbl_aplicabilidade[ProductId],B13,tbl_aplicabilidade[Estado_Resumo],"Lacuna")+COUNTIFS(tbl_aplicabilidade[ProductId],B13,tbl_aplicabilidade[Estado_Resumo],"Não conforme") -> 1 | BX13: 46287 | BY13: =EDATE(BX13,12) -> 46652 | BZ13: Responsável de R&D | CA13: Autoavaliação (não certificada) | CB13: Regras simplificadas SGA-20 v1 (diretrizes DfR RecyClass) — confirmar na ferramenta online
A14: RCA-010 | B14: FR-008-HDPE-PCR-350 | C14: Frasco | D14: Cosmética e higiene pessoal | E14: Contacto direto com cosmético/higiene | F14: Injeção-sopro (ISBM) | G14: FAM-02 | H14: 350 | I14: 121 | J14: HDPE-PCR | K14: =IFERROR(INDEX(tbl_materiais[Polimero_Base],MATCH(J14,tbl_materiais[Material],0)),"") -> PE | L14: =IFERROR(INDEX(tbl_materiais[Fluxo_Reciclagem],MATCH(J14,tbl_materiais[Material],0)),"") -> PE rígido | M14: =IF(L14="PE rígido","PE rígido — frascos e contentores (HDPE/LDPE)",IF(L14="PP rígido","PP rígido — frascos, potes e contentores",IF(L14="PET frascos e garrafas",IF(O14="Natural / incolor","PET — garrafas/frascos transparentes incolores","PET — garrafas/frascos coloridos ou opacos"),"Sem categoria RecyClass ("&K14&")"))) -> PE rígido — frascos e contentores (HDPE/LDPE) | N14: Cobalt Blue | O14: Colorido (claro ou transparente) | P14: Blue Masterbatch | Q14: 0.02 | R14: =IFERROR(ROUND(INDEX(tbl_materiais[Densidade_g_cm3],MATCH(J14,tbl_materiais[Material],0))+Q14*1.2,3),"") -> 0.984 | S14: Nenhuma | T14: 24.4 | U14: Estimada (22 g a 300 ml, escala ^2/3) | V14: TF-005-PP-PCR-24410 | W14: =IF(V14="","",IFERROR(INDEX(tbl_tampas[Material],MATCH(V14,tbl_tampas[CapId],0)),"")) -> PP-PCR | X14: =IF(V14="","Sem tampa",IFERROR(INDEX(tbl_materiais[Polimero_Base],MATCH(W14,tbl_materiais[Material],0)),"")) -> PP | Y14: =IF(V14="",0,IFERROR(INDEX(tbl_tampas[Massa_g],MATCH(V14,tbl_tampas[CapId],0)),0)) -> 13.9 | Z14: Sem vedante | AA14: Sem rótulo | AB14: Sem adesivo | AC14: 0 | AD14: 0 | AE14: Sem rótulo (decoração direta Plasticom) | AF14: Hot foil metalizado | AG14: 1 | AH14: =IF(AF14="Serigrafia",IF(AG14>=3,"Serigrafia ≥ 3 cores","Serigrafia 1–2 cores"),AF14) -> Hot foil metalizado | AI14: 0.03 | AJ14: =IFERROR(INDEX(tbl_regras_dfr[Classe],MATCH(L14&"|Fluxo de reciclagem|"&L14,tbl_regras_dfr[Chave],0)),"Sem regra") -> A | AK14: =IF(LEFT(L14,9)="Sem fluxo","—",IFERROR(INDEX(tbl_regras_dfr[Classe],MATCH(L14&"|Cor do corpo|"&O14,tbl_regras_dfr[Chave],0)),"Sem regra")) -> B | AL14: =IF(LEFT(L14,9)="Sem fluxo","—",IFERROR(INDEX(tbl_regras_dfr[Classe],MATCH(L14&"|Densidade do corpo|"&IF(R14<1,"< 1,0 g/cm³","≥ 1,0 g/cm³"),tbl_regras_dfr[Chave],0)),"Sem regra")) -> A | AM14: =IF(LEFT(L14,9)="Sem fluxo","—",IFERROR(INDEX(tbl_regras_dfr[Classe],MATCH(L14&"|Barreira / revestimento|"&S14,tbl_regras_dfr[Chave],0)),"Sem regra")) -> A | AN14: =IF(LEFT(L14,9)="Sem fluxo","—",IFERROR(INDEX(tbl_regras_dfr[Classe],MATCH(L14&"|Material da tampa|"&X14,tbl_regras_dfr[Chave],0)),"Sem regra")) -> A | AO14: =IF(LEFT(L14,9)="Sem fluxo","—",IFERROR(INDEX(tbl_regras_dfr[Classe],MATCH(L14&"|Vedante / liner|"&Z14,tbl_regras_dfr[Chave],0)),"Sem regra")) -> A | AP14: =IF(LEFT(L14,9)="Sem fluxo","—",IFERROR(INDEX(tbl_regras_dfr[Classe],MATCH(L14&"|Tipo de rótulo|"&AA14,tbl_regras_dfr[Chave],0)),"Sem regra")) -> A | AQ14: =IF(LEFT(L14,9)="Sem fluxo","—",IFERROR(INDEX(tbl_regras_dfr[Classe],MATCH(L14&"|Adesivo do rótulo|"&AB14,tbl_regras_dfr[Chave],0)),"Sem regra")) -> A | AR14: =IF(LEFT(L14,9)="Sem fluxo","—",IFERROR(INDEX(tbl_regras_dfr[Classe],MATCH(L14&"|Cobertura do rótulo|"&IF(AC14>0.7,"> 70% da superfície","≤ 70% da superfície"),tbl_regras_dfr[Chave],0)),"Sem regra")) -> A | AS14: =IF(LEFT(L14,9)="Sem fluxo","—",IFERROR(INDEX(tbl_regras_dfr[Classe],MATCH(L14&"|Decoração direta|"&AH14,tbl_regras_dfr[Chave],0)),"Sem regra")) -> C | AT14: =IF(COUNTIF(AJ14:AS14,"F"),6,IF(COUNTIF(AJ14:AS14,"E"),5,IF(COUNTIF(AJ14:AS14,"D"),4,IF(COUNTIF(AJ14:AS14,"C"),3,IF(COUNTIF(AJ14:AS14,"B"),2,IF(COUNTIF(AJ14:AS14,"A"),1,0)))))) -> 3 | AU14: =IF(AT14=0,"",INDEX({"A","B","C","D","E","F"},AT14)) -> C | AV14: =COUNTIF(AJ14:AS14,"Sem regra") -> 0 | AW14: =IF(OR(AU14="",AU14="A"),"—",SUBSTITUTE(INDEX($AJ$4:$AS$4,MATCH(AU14,AJ14:AS14,0)),"Classe_","")) -> Decoracao | AX14: =IF(AU14="A","Sem ação — manter o design.",IFERROR(INDEX(tbl_regras_dfr[Recomendacao],MATCH(CHOOSE(MATCH(AU14,AJ14:AS14,0),L14&"|Fluxo de reciclagem|"&L14,L14&"|Cor do corpo|"&O14,L14&"|Densidade do corpo|"&IF(R14<1,"< 1,0 g/cm³","≥ 1,0 g/cm³"),L14&"|Barreira / revestimento|"&S14,L14&"|Material da tampa|"&X14,L14&"|Vedante / liner|"&Z14,L14&"|Tipo de rótulo|"&AA14,L14&"|Adesivo do rótulo|"&AB14,L14&"|Cobertura do rótulo|"&IF(AC14>0.7,"> 70% da superfície","≤ 70% da superfície"),L14&"|Decoração direta|"&AH14),tbl_regras_dfr[Chave],0)),"")) -> Reduzir a área de hot foil ou usar rótulo metalizado destacável. | AY14: =T14+Y14+AD14+AI14 -> 38.33 | AZ14: =MIN(IFERROR(INDEX(tbl_regras_dfr[Fracao_Reciclavel],MATCH(L14&"|Fluxo de reciclagem|"&L14,tbl_regras_dfr[Chave],0)),0),IFERROR(INDEX(tbl_regras_dfr[Fracao_Reciclavel],MATCH(L14&"|Cor do corpo|"&O14,tbl_regras_dfr[Chave],0)),0)) -> 1 | BA14: =IFERROR(INDEX(tbl_regras_dfr[Fracao_Reciclavel],MATCH(L14&"|Material da tampa|"&X14,tbl_regras_dfr[Chave],0)),0) -> 1 | BB14: =IFERROR(INDEX(tbl_regras_dfr[Fracao_Reciclavel],MATCH(L14&"|Tipo de rótulo|"&AA14,tbl_regras_dfr[Chave],0)),0) -> 1 | BC14: =AZ14*(T14+Y14*BA14+AD14*BB14) -> 38.3 | BD14: =IFERROR(BC14/AY14,0) -> 0.99921732 | BE14: =IF(BD14>=INDEX(tbl_param_emb[Valor],MATCH("P-06",tbl_param_emb[ID_Parametro],0)),"A",IF(BD14>=INDEX(tbl_param_emb[Valor],MATCH("P-07",tbl_param_emb[ID_Parametro],0)),"B",IF(BD14>=INDEX(tbl_param_emb[Valor],MATCH("P-08",tbl_param_emb[ID_Parametro],0)),"C","< 70%"))) -> A | BF14: =IF(AU14="F","Não reciclável (F)",INDEX({"A","B","C","Abaixo de C"},MAX(MIN(AT14,4),IF(BE14="A",1,IF(BE14="B",2,IF(BE14="C",3,4)))))) -> C | BG14: =IF(D14="Farmacêutico","Isento até 2035","—") -> — | BH14: =IF(BG14<>"—",BG14,IF(OR(BF14="A",BF14="B",BF14="C"),"Sim","Não")) -> Sim | BI14: =IF(BG14<>"—",BG14,IF(OR(BF14="A",BF14="B"),"Sim","Não")) -> Não | BJ14: =IFERROR(INDEX(tbl_materiais[Pct_PCR],MATCH(J14,tbl_materiais[Material],0)),0) -> 0.3 | BK14: =IF(V14="",0,IFERROR(INDEX(tbl_tampas[Pct_PCR],MATCH(V14,tbl_tampas[CapId],0)),0)) -> 0.3 | BL14: =IFERROR((T14*BJ14+Y14*BK14)/(T14+Y14),0) -> 0.3 | BM14: =IF(D14="Farmacêutico","Isenta — medicamentos (art. 7.º)",IF(D14="Alimentar",IF(K14="PET","Sensível ao contacto — PET","Sensível ao contacto — outros plásticos"),"Outras embalagens de plástico")) -> Outras embalagens de plástico | BN14: =IFERROR(IF(INDEX(tbl_metas_art7[Meta_2030],MATCH(BM14,tbl_metas_art7[Categoria_Art7],0))="","",INDEX(tbl_metas_art7[Meta_2030],MATCH(BM14,tbl_metas_art7[Categoria_Art7],0))),"") -> 0.35 | BO14: =IF(BN14="","",MAX(0,BN14-BL14)) -> 0.05 | BP14: =IF(BN14="","Isento",IF(BO14=0,"Sim","Não")) -> Não | BQ14: =IF(AND(OR(X14=K14,X14="Sem tampa",AND(OR(X14="PE",X14="PP"),OR(K14="PE",K14="PP"))),OR(AA14="Sem rótulo",AND(ISNUMBER(SEARCH("PE/PP",AA14)),OR(K14="PE",K14="PP")))),"Monomaterial (mesma família)","Multimaterial") -> Monomaterial (mesma família) | BR14: 109845 | BS14: 11 | BT14: DE; ES; IT; PL; PT | BU14: =BR14*T14/1000 -> 2680.218 | BV14: =COUNTIFS(tbl_aplicabilidade[ProductId],B14,tbl_aplicabilidade[Aplicavel],"Sim") -> 12 | BW14: =COUNTIFS(tbl_aplicabilidade[ProductId],B14,tbl_aplicabilidade[Estado_Resumo],"Lacuna")+COUNTIFS(tbl_aplicabilidade[ProductId],B14,tbl_aplicabilidade[Estado_Resumo],"Não conforme") -> 1 | BX14: 46287 | BY14: =EDATE(BX14,12) -> 46652 | BZ14: Responsável de R&D | CA14: Autoavaliação (não certificada) | CB14: Regras simplificadas SGA-20 v1 (diretrizes DfR RecyClass) — confirmar na ferramenta online
A15: RCA-011 | B15: FR-007-HDPE-PCR-350 | C15: Frasco | D15: Cosmética e higiene pessoal | E15: Contacto direto com cosmético/higiene | F15: Injeção-sopro (ISBM) | G15: FAM-02 | H15: 350 | I15: 121 | J15: HDPE-PCR | K15: =IFERROR(INDEX(tbl_materiais[Polimero_Base],MATCH(J15,tbl_materiais[Material],0)),"") -> PE | L15: =IFERROR(INDEX(tbl_materiais[Fluxo_Reciclagem],MATCH(J15,tbl_materiais[Material],0)),"") -> PE rígido | M15: =IF(L15="PE rígido","PE rígido — frascos e contentores (HDPE/LDPE)",IF(L15="PP rígido","PP rígido — frascos, potes e contentores",IF(L15="PET frascos e garrafas",IF(O15="Natural / incolor","PET — garrafas/frascos transparentes incolores","PET — garrafas/frascos coloridos ou opacos"),"Sem categoria RecyClass ("&K15&")"))) -> PE rígido — frascos e contentores (HDPE/LDPE) | N15: Cobalt Blue | O15: Colorido (claro ou transparente) | P15: Blue Masterbatch | Q15: 0.02 | R15: =IFERROR(ROUND(INDEX(tbl_materiais[Densidade_g_cm3],MATCH(J15,tbl_materiais[Material],0))+Q15*1.2,3),"") -> 0.984 | S15: Nenhuma | T15: 24.4 | U15: Estimada (22 g a 300 ml, escala ^2/3) | V15: TR-001-PP-PCR-24410 | W15: =IF(V15="","",IFERROR(INDEX(tbl_tampas[Material],MATCH(V15,tbl_tampas[CapId],0)),"")) -> PP-PCR | X15: =IF(V15="","Sem tampa",IFERROR(INDEX(tbl_materiais[Polimero_Base],MATCH(W15,tbl_materiais[Material],0)),"")) -> PP | Y15: =IF(V15="",0,IFERROR(INDEX(tbl_tampas[Massa_g],MATCH(V15,tbl_tampas[CapId],0)),0)) -> 10.3 | Z15: Sem vedante | AA15: Autoadesivo PE/PP | AB15: Acrílico permanente | AC15: 0.4 | AD15: 0.51 | AE15: Cenário típico do cliente — confirmar especificação | AF15: Nenhuma | AG15: 0 | AH15: =IF(AF15="Serigrafia",IF(AG15>=3,"Serigrafia ≥ 3 cores","Serigrafia 1–2 cores"),AF15) -> Nenhuma | AI15: 0 | AJ15: =IFERROR(INDEX(tbl_regras_dfr[Classe],MATCH(L15&"|Fluxo de reciclagem|"&L15,tbl_regras_dfr[Chave],0)),"Sem regra") -> A | AK15: =IF(LEFT(L15,9)="Sem fluxo","—",IFERROR(INDEX(tbl_regras_dfr[Classe],MATCH(L15&"|Cor do corpo|"&O15,tbl_regras_dfr[Chave],0)),"Sem regra")) -> B | AL15: =IF(LEFT(L15,9)="Sem fluxo","—",IFERROR(INDEX(tbl_regras_dfr[Classe],MATCH(L15&"|Densidade do corpo|"&IF(R15<1,"< 1,0 g/cm³","≥ 1,0 g/cm³"),tbl_regras_dfr[Chave],0)),"Sem regra")) -> A | AM15: =IF(LEFT(L15,9)="Sem fluxo","—",IFERROR(INDEX(tbl_regras_dfr[Classe],MATCH(L15&"|Barreira / revestimento|"&S15,tbl_regras_dfr[Chave],0)),"Sem regra")) -> A | AN15: =IF(LEFT(L15,9)="Sem fluxo","—",IFERROR(INDEX(tbl_regras_dfr[Classe],MATCH(L15&"|Material da tampa|"&X15,tbl_regras_dfr[Chave],0)),"Sem regra")) -> A | AO15: =IF(LEFT(L15,9)="Sem fluxo","—",IFERROR(INDEX(tbl_regras_dfr[Classe],MATCH(L15&"|Vedante / liner|"&Z15,tbl_regras_dfr[Chave],0)),"Sem regra")) -> A | AP15: =IF(LEFT(L15,9)="Sem fluxo","—",IFERROR(INDEX(tbl_regras_dfr[Classe],MATCH(L15&"|Tipo de rótulo|"&AA15,tbl_regras_dfr[Chave],0)),"Sem regra")) -> A | AQ15: =IF(LEFT(L15,9)="Sem fluxo","—",IFERROR(INDEX(tbl_regras_dfr[Classe],MATCH(L15&"|Adesivo do rótulo|"&AB15,tbl_regras_dfr[Chave],0)),"Sem regra")) -> A | AR15: =IF(LEFT(L15,9)="Sem fluxo","—",IFERROR(INDEX(tbl_regras_dfr[Classe],MATCH(L15&"|Cobertura do rótulo|"&IF(AC15>0.7,"> 70% da superfície","≤ 70% da superfície"),tbl_regras_dfr[Chave],0)),"Sem regra")) -> A | AS15: =IF(LEFT(L15,9)="Sem fluxo","—",IFERROR(INDEX(tbl_regras_dfr[Classe],MATCH(L15&"|Decoração direta|"&AH15,tbl_regras_dfr[Chave],0)),"Sem regra")) -> A | AT15: =IF(COUNTIF(AJ15:AS15,"F"),6,IF(COUNTIF(AJ15:AS15,"E"),5,IF(COUNTIF(AJ15:AS15,"D"),4,IF(COUNTIF(AJ15:AS15,"C"),3,IF(COUNTIF(AJ15:AS15,"B"),2,IF(COUNTIF(AJ15:AS15,"A"),1,0)))))) -> 2 | AU15: =IF(AT15=0,"",INDEX({"A","B","C","D","E","F"},AT15)) -> B | AV15: =COUNTIF(AJ15:AS15,"Sem regra") -> 0 | AW15: =IF(OR(AU15="",AU15="A"),"—",SUBSTITUTE(INDEX($AJ$4:$AS$4,MATCH(AU15,AJ15:AS15,0)),"Classe_","")) -> Cor | AX15: =IF(AU15="A","Sem ação — manter o design.",IFERROR(INDEX(tbl_regras_dfr[Recomendacao],MATCH(CHOOSE(MATCH(AU15,AJ15:AS15,0),L15&"|Fluxo de reciclagem|"&L15,L15&"|Cor do corpo|"&O15,L15&"|Densidade do corpo|"&IF(R15<1,"< 1,0 g/cm³","≥ 1,0 g/cm³"),L15&"|Barreira / revestimento|"&S15,L15&"|Material da tampa|"&X15,L15&"|Vedante / liner|"&Z15,L15&"|Tipo de rótulo|"&AA15,L15&"|Adesivo do rótulo|"&AB15,L15&"|Cobertura do rótulo|"&IF(AC15>0.7,"> 70% da superfície","≤ 70% da superfície"),L15&"|Decoração direta|"&AH15),tbl_regras_dfr[Chave],0)),"")) -> Preferir natural, branco ou cores claras. | AY15: =T15+Y15+AD15+AI15 -> 35.21 | AZ15: =MIN(IFERROR(INDEX(tbl_regras_dfr[Fracao_Reciclavel],MATCH(L15&"|Fluxo de reciclagem|"&L15,tbl_regras_dfr[Chave],0)),0),IFERROR(INDEX(tbl_regras_dfr[Fracao_Reciclavel],MATCH(L15&"|Cor do corpo|"&O15,tbl_regras_dfr[Chave],0)),0)) -> 1 | BA15: =IFERROR(INDEX(tbl_regras_dfr[Fracao_Reciclavel],MATCH(L15&"|Material da tampa|"&X15,tbl_regras_dfr[Chave],0)),0) -> 1 | BB15: =IFERROR(INDEX(tbl_regras_dfr[Fracao_Reciclavel],MATCH(L15&"|Tipo de rótulo|"&AA15,tbl_regras_dfr[Chave],0)),0) -> 1 | BC15: =AZ15*(T15+Y15*BA15+AD15*BB15) -> 35.21 | BD15: =IFERROR(BC15/AY15,0) -> 1 | BE15: =IF(BD15>=INDEX(tbl_param_emb[Valor],MATCH("P-06",tbl_param_emb[ID_Parametro],0)),"A",IF(BD15>=INDEX(tbl_param_emb[Valor],MATCH("P-07",tbl_param_emb[ID_Parametro],0)),"B",IF(BD15>=INDEX(tbl_param_emb[Valor],MATCH("P-08",tbl_param_emb[ID_Parametro],0)),"C","< 70%"))) -> A | BF15: =IF(AU15="F","Não reciclável (F)",INDEX({"A","B","C","Abaixo de C"},MAX(MIN(AT15,4),IF(BE15="A",1,IF(BE15="B",2,IF(BE15="C",3,4)))))) -> B | BG15: =IF(D15="Farmacêutico","Isento até 2035","—") -> — | BH15: =IF(BG15<>"—",BG15,IF(OR(BF15="A",BF15="B",BF15="C"),"Sim","Não")) -> Sim | BI15: =IF(BG15<>"—",BG15,IF(OR(BF15="A",BF15="B"),"Sim","Não")) -> Sim | BJ15: =IFERROR(INDEX(tbl_materiais[Pct_PCR],MATCH(J15,tbl_materiais[Material],0)),0) -> 0.3 | BK15: =IF(V15="",0,IFERROR(INDEX(tbl_tampas[Pct_PCR],MATCH(V15,tbl_tampas[CapId],0)),0)) -> 0.3 | BL15: =IFERROR((T15*BJ15+Y15*BK15)/(T15+Y15),0) -> 0.3 | BM15: =IF(D15="Farmacêutico","Isenta — medicamentos (art. 7.º)",IF(D15="Alimentar",IF(K15="PET","Sensível ao contacto — PET","Sensível ao contacto — outros plásticos"),"Outras embalagens de plástico")) -> Outras embalagens de plástico | BN15: =IFERROR(IF(INDEX(tbl_metas_art7[Meta_2030],MATCH(BM15,tbl_metas_art7[Categoria_Art7],0))="","",INDEX(tbl_metas_art7[Meta_2030],MATCH(BM15,tbl_metas_art7[Categoria_Art7],0))),"") -> 0.35 | BO15: =IF(BN15="","",MAX(0,BN15-BL15)) -> 0.05 | BP15: =IF(BN15="","Isento",IF(BO15=0,"Sim","Não")) -> Não | BQ15: =IF(AND(OR(X15=K15,X15="Sem tampa",AND(OR(X15="PE",X15="PP"),OR(K15="PE",K15="PP"))),OR(AA15="Sem rótulo",AND(ISNUMBER(SEARCH("PE/PP",AA15)),OR(K15="PE",K15="PP")))),"Monomaterial (mesma família)","Multimaterial") -> Monomaterial (mesma família) | BR15: 160805 | BS15: 12 | BT15: ES; FR; IT; PL; PT | BU15: =BR15*T15/1000 -> 3923.642 | BV15: =COUNTIFS(tbl_aplicabilidade[ProductId],B15,tbl_aplicabilidade[Aplicavel],"Sim") -> 12 | BW15: =COUNTIFS(tbl_aplicabilidade[ProductId],B15,tbl_aplicabilidade[Estado_Resumo],"Lacuna")+COUNTIFS(tbl_aplicabilidade[ProductId],B15,tbl_aplicabilidade[Estado_Resumo],"Não conforme") -> 1 | BX15: 46287 | BY15: =EDATE(BX15,12) -> 46652 | BZ15: Responsável de R&D | CA15: Autoavaliação (não certificada) | CB15: Regras simplificadas SGA-20 v1 (diretrizes DfR RecyClass) — confirmar na ferramenta online
A16: RCA-012 | B16: FR-009-HDPE-PCR-350 | C16: Frasco | D16: Cosmética e higiene pessoal | E16: Contacto direto com cosmético/higiene | F16: Injeção-sopro (ISBM) | G16: FAM-02 | H16: 350 | I16: 121 | J16: HDPE-PCR | K16: =IFERROR(INDEX(tbl_materiais[Polimero_Base],MATCH(J16,tbl_materiais[Material],0)),"") -> PE | L16: =IFERROR(INDEX(tbl_materiais[Fluxo_Reciclagem],MATCH(J16,tbl_materiais[Material],0)),"") -> PE rígido | M16: =IF(L16="PE rígido","PE rígido — frascos e contentores (HDPE/LDPE)",IF(L16="PP rígido","PP rígido — frascos, potes e contentores",IF(L16="PET frascos e garrafas",IF(O16="Natural / incolor","PET — garrafas/frascos transparentes incolores","PET — garrafas/frascos coloridos ou opacos"),"Sem categoria RecyClass ("&K16&")"))) -> PE rígido — frascos e contentores (HDPE/LDPE) | N16: Translucent Amber | O16: Colorido (claro ou transparente) | P16: Amber Masterbatch | Q16: 0.015 | R16: =IFERROR(ROUND(INDEX(tbl_materiais[Densidade_g_cm3],MATCH(J16,tbl_materiais[Material],0))+Q16*1.2,3),"") -> 0.978 | S16: Nenhuma | T16: 24.4 | U16: Estimada (22 g a 300 ml, escala ^2/3) | V16: TR-001-PP-PCR-24410 | W16: =IF(V16="","",IFERROR(INDEX(tbl_tampas[Material],MATCH(V16,tbl_tampas[CapId],0)),"")) -> PP-PCR | X16: =IF(V16="","Sem tampa",IFERROR(INDEX(tbl_materiais[Polimero_Base],MATCH(W16,tbl_materiais[Material],0)),"")) -> PP | Y16: =IF(V16="",0,IFERROR(INDEX(tbl_tampas[Massa_g],MATCH(V16,tbl_tampas[CapId],0)),0)) -> 10.3 | Z16: Sem vedante | AA16: Autoadesivo PE/PP | AB16: Acrílico permanente | AC16: 0.4 | AD16: 0.51 | AE16: Cenário típico do cliente — confirmar especificação | AF16: Nenhuma | AG16: 0 | AH16: =IF(AF16="Serigrafia",IF(AG16>=3,"Serigrafia ≥ 3 cores","Serigrafia 1–2 cores"),AF16) -> Nenhuma | AI16: 0 | AJ16: =IFERROR(INDEX(tbl_regras_dfr[Classe],MATCH(L16&"|Fluxo de reciclagem|"&L16,tbl_regras_dfr[Chave],0)),"Sem regra") -> A | AK16: =IF(LEFT(L16,9)="Sem fluxo","—",IFERROR(INDEX(tbl_regras_dfr[Classe],MATCH(L16&"|Cor do corpo|"&O16,tbl_regras_dfr[Chave],0)),"Sem regra")) -> B | AL16: =IF(LEFT(L16,9)="Sem fluxo","—",IFERROR(INDEX(tbl_regras_dfr[Classe],MATCH(L16&"|Densidade do corpo|"&IF(R16<1,"< 1,0 g/cm³","≥ 1,0 g/cm³"),tbl_regras_dfr[Chave],0)),"Sem regra")) -> A | AM16: =IF(LEFT(L16,9)="Sem fluxo","—",IFERROR(INDEX(tbl_regras_dfr[Classe],MATCH(L16&"|Barreira / revestimento|"&S16,tbl_regras_dfr[Chave],0)),"Sem regra")) -> A | AN16: =IF(LEFT(L16,9)="Sem fluxo","—",IFERROR(INDEX(tbl_regras_dfr[Classe],MATCH(L16&"|Material da tampa|"&X16,tbl_regras_dfr[Chave],0)),"Sem regra")) -> A | AO16: =IF(LEFT(L16,9)="Sem fluxo","—",IFERROR(INDEX(tbl_regras_dfr[Classe],MATCH(L16&"|Vedante / liner|"&Z16,tbl_regras_dfr[Chave],0)),"Sem regra")) -> A | AP16: =IF(LEFT(L16,9)="Sem fluxo","—",IFERROR(INDEX(tbl_regras_dfr[Classe],MATCH(L16&"|Tipo de rótulo|"&AA16,tbl_regras_dfr[Chave],0)),"Sem regra")) -> A | AQ16: =IF(LEFT(L16,9)="Sem fluxo","—",IFERROR(INDEX(tbl_regras_dfr[Classe],MATCH(L16&"|Adesivo do rótulo|"&AB16,tbl_regras_dfr[Chave],0)),"Sem regra")) -> A | AR16: =IF(LEFT(L16,9)="Sem fluxo","—",IFERROR(INDEX(tbl_regras_dfr[Classe],MATCH(L16&"|Cobertura do rótulo|"&IF(AC16>0.7,"> 70% da superfície","≤ 70% da superfície"),tbl_regras_dfr[Chave],0)),"Sem regra")) -> A | AS16: =IF(LEFT(L16,9)="Sem fluxo","—",IFERROR(INDEX(tbl_regras_dfr[Classe],MATCH(L16&"|Decoração direta|"&AH16,tbl_regras_dfr[Chave],0)),"Sem regra")) -> A | AT16: =IF(COUNTIF(AJ16:AS16,"F"),6,IF(COUNTIF(AJ16:AS16,"E"),5,IF(COUNTIF(AJ16:AS16,"D"),4,IF(COUNTIF(AJ16:AS16,"C"),3,IF(COUNTIF(AJ16:AS16,"B"),2,IF(COUNTIF(AJ16:AS16,"A"),1,0)))))) -> 2 | AU16: =IF(AT16=0,"",INDEX({"A","B","C","D","E","F"},AT16)) -> B | AV16: =COUNTIF(AJ16:AS16,"Sem regra") -> 0 | AW16: =IF(OR(AU16="",AU16="A"),"—",SUBSTITUTE(INDEX($AJ$4:$AS$4,MATCH(AU16,AJ16:AS16,0)),"Classe_","")) -> Cor | AX16: =IF(AU16="A","Sem ação — manter o design.",IFERROR(INDEX(tbl_regras_dfr[Recomendacao],MATCH(CHOOSE(MATCH(AU16,AJ16:AS16,0),L16&"|Fluxo de reciclagem|"&L16,L16&"|Cor do corpo|"&O16,L16&"|Densidade do corpo|"&IF(R16<1,"< 1,0 g/cm³","≥ 1,0 g/cm³"),L16&"|Barreira / revestimento|"&S16,L16&"|Material da tampa|"&X16,L16&"|Vedante / liner|"&Z16,L16&"|Tipo de rótulo|"&AA16,L16&"|Adesivo do rótulo|"&AB16,L16&"|Cobertura do rótulo|"&IF(AC16>0.7,"> 70% da superfície","≤ 70% da superfície"),L16&"|Decoração direta|"&AH16),tbl_regras_dfr[Chave],0)),"")) -> Preferir natural, branco ou cores claras. | AY16: =T16+Y16+AD16+AI16 -> 35.21 | AZ16: =MIN(IFERROR(INDEX(tbl_regras_dfr[Fracao_Reciclavel],MATCH(L16&"|Fluxo de reciclagem|"&L16,tbl_regras_dfr[Chave],0)),0),IFERROR(INDEX(tbl_regras_dfr[Fracao_Reciclavel],MATCH(L16&"|Cor do corpo|"&O16,tbl_regras_dfr[Chave],0)),0)) -> 1 | BA16: =IFERROR(INDEX(tbl_regras_dfr[Fracao_Reciclavel],MATCH(L16&"|Material da tampa|"&X16,tbl_regras_dfr[Chave],0)),0) -> 1 | BB16: =IFERROR(INDEX(tbl_regras_dfr[Fracao_Reciclavel],MATCH(L16&"|Tipo de rótulo|"&AA16,tbl_regras_dfr[Chave],0)),0) -> 1 | BC16: =AZ16*(T16+Y16*BA16+AD16*BB16) -> 35.21 | BD16: =IFERROR(BC16/AY16,0) -> 1 | BE16: =IF(BD16>=INDEX(tbl_param_emb[Valor],MATCH("P-06",tbl_param_emb[ID_Parametro],0)),"A",IF(BD16>=INDEX(tbl_param_emb[Valor],MATCH("P-07",tbl_param_emb[ID_Parametro],0)),"B",IF(BD16>=INDEX(tbl_param_emb[Valor],MATCH("P-08",tbl_param_emb[ID_Parametro],0)),"C","< 70%"))) -> A | BF16: =IF(AU16="F","Não reciclável (F)",INDEX({"A","B","C","Abaixo de C"},MAX(MIN(AT16,4),IF(BE16="A",1,IF(BE16="B",2,IF(BE16="C",3,4)))))) -> B | BG16: =IF(D16="Farmacêutico","Isento até 2035","—") -> — | BH16: =IF(BG16<>"—",BG16,IF(OR(BF16="A",BF16="B",BF16="C"),"Sim","Não")) -> Sim | BI16: =IF(BG16<>"—",BG16,IF(OR(BF16="A",BF16="B"),"Sim","Não")) -> Sim | BJ16: =IFERROR(INDEX(tbl_materiais[Pct_PCR],MATCH(J16,tbl_materiais[Material],0)),0) -> 0.3 | BK16: =IF(V16="",0,IFERROR(INDEX(tbl_tampas[Pct_PCR],MATCH(V16,tbl_tampas[CapId],0)),0)) -> 0.3 | BL16: =IFERROR((T16*BJ16+Y16*BK16)/(T16+Y16),0) -> 0.3 | BM16: =IF(D16="Farmacêutico","Isenta — medicamentos (art. 7.º)",IF(D16="Alimentar",IF(K16="PET","Sensível ao contacto — PET","Sensível ao contacto — outros plásticos"),"Outras embalagens de plástico")) -> Outras embalagens de plástico | BN16: =IFERROR(IF(INDEX(tbl_metas_art7[Meta_2030],MATCH(BM16,tbl_metas_art7[Categoria_Art7],0))="","",INDEX(tbl_metas_art7[Meta_2030],MATCH(BM16,tbl_metas_art7[Categoria_Art7],0))),"") -> 0.35 | BO16: =IF(BN16="","",MAX(0,BN16-BL16)) -> 0.05 | BP16: =IF(BN16="","Isento",IF(BO16=0,"Sim","Não")) -> Não | BQ16: =IF(AND(OR(X16=K16,X16="Sem tampa",AND(OR(X16="PE",X16="PP"),OR(K16="PE",K16="PP"))),OR(AA16="Sem rótulo",AND(ISNUMBER(SEARCH("PE/PP",AA16)),OR(K16="PE",K16="PP")))),"Monomaterial (mesma família)","Multimaterial") -> Monomaterial (mesma família) | BR16: 30788 | BS16: 7 | BT16: DE; ES; FR; PT | BU16: =BR16*T16/1000 -> 751.2272 | BV16: =COUNTIFS(tbl_aplicabilidade[ProductId],B16,tbl_aplicabilidade[Aplicavel],"Sim") -> 12 | BW16: =COUNTIFS(tbl_aplicabilidade[ProductId],B16,tbl_aplicabilidade[Estado_Resumo],"Lacuna")+COUNTIFS(tbl_aplicabilidade[ProductId],B16,tbl_aplicabilidade[Estado_Resumo],"Não conforme") -> 1 | BX16: 46287 | BY16: =EDATE(BX16,12) -> 46652 | BZ16: Responsável de R&D | CA16: Autoavaliação (não certificada) | CB16: Regras simplificadas SGA-20 v1 (diretrizes DfR RecyClass) — confirmar na ferramenta online
... A117: RCA-113 | B117: PT-011-PP-PG-100 | C117: Pote | D117: Farmacêutico | E117: Contacto direto com medicamento | F117: Injeção | G117: FAM-15 | H117: 100 | I117: 54 | J117: PP-PG | K117: =IFERROR(INDEX(tbl_materiais[Polimero_Base],MATCH(J117,tbl_materiais[Material],0)),"") -> PP | L117: =IFERROR(INDEX(tbl_materiais[Fluxo_Reciclagem],MATCH(J117,tbl_materiais[Material],0)),"") -> PP rígido | M117: =IF(L117="PE rígido","PE rígido — frascos e contentores (HDPE/LDPE)",IF(L117="PP rígido","PP rígido — frascos, potes e contentores",IF(L117="PET frascos e garrafas",IF(O117="Natural / incolor","PET — garrafas/frascos transparentes incolores","PET — garrafas/frascos coloridos ou opacos"),"Sem categoria RecyClass ("&K117&")"))) -> PP rígido — frascos, potes e contentores | N117: Pharma White | O117: Branco (TiO2) | P117: Pharma Masterbatch | Q117: 0.02 | R117: =IFERROR(ROUND(INDEX(tbl_materiais[Densidade_g_cm3],MATCH(J117,tbl_materiais[Material],0))+Q117*1.2,3),"") -> 0.929 | S117: Nenhuma | T117: 10.6 | U117: Estimada (22 g a 300 ml, escala ^2/3) | V117: TP-013-PP-PG-070 | W117: =IF(V117="","",IFERROR(INDEX(tbl_tampas[Material],MATCH(V117,tbl_tampas[CapId],0)),"")) -> PP-PG | X117: =IF(V117="","Sem tampa",IFERROR(INDEX(tbl_materiais[Polimero_Base],MATCH(W117,tbl_materiais[Material],0)),"")) -> PP | Y117: =IF(V117="",0,IFERROR(INDEX(tbl_tampas[Massa_g],MATCH(V117,tbl_tampas[CapId],0)),0)) -> 16.5 | Z117: Sem vedante | AA117: Autoadesivo papel | AB117: Acrílico permanente | AC117: 0.35 | AD117: 0.19 | AE117: Cenário típico do cliente — confirmar especificação | AF117: Nenhuma | AG117: 0 | AH117: =IF(AF117="Serigrafia",IF(AG117>=3,"Serigrafia ≥ 3 cores","Serigrafia 1–2 cores"),AF117) -> Nenhuma | AI117: 0 | AJ117: =IFERROR(INDEX(tbl_regras_dfr[Classe],MATCH(L117&"|Fluxo de reciclagem|"&L117,tbl_regras_dfr[Chave],0)),"Sem regra") -> A | AK117: =IF(LEFT(L117,9)="Sem fluxo","—",IFERROR(INDEX(tbl_regras_dfr[Classe],MATCH(L117&"|Cor do corpo|"&O117,tbl_regras_dfr[Chave],0)),"Sem regra")) -> A | AL117: =IF(LEFT(L117,9)="Sem fluxo","—",IFERROR(INDEX(tbl_regras_dfr[Classe],MATCH(L117&"|Densidade do corpo|"&IF(R117<1,"< 1,0 g/cm³","≥ 1,0 g/cm³"),tbl_regras_dfr[Chave],0)),"Sem regra")) -> A | AM117: =IF(LEFT(L117,9)="Sem fluxo","—",IFERROR(INDEX(tbl_regras_dfr[Classe],MATCH(L117&"|Barreira / revestimento|"&S117,tbl_regras_dfr[Chave],0)),"Sem regra")) -> A | AN117: =IF(LEFT(L117,9)="Sem fluxo","—",IFERROR(INDEX(tbl_regras_dfr[Classe],MATCH(L117&"|Material da tampa|"&X117,tbl_regras_dfr[Chave],0)),"Sem regra")) -> A | AO117: =IF(LEFT(L117,9)="Sem fluxo","—",IFERROR(INDEX(tbl_regras_dfr[Classe],MATCH(L117&"|Vedante / liner|"&Z117,tbl_regras_dfr[Chave],0)),"Sem regra")) -> A | AP117: =IF(LEFT(L117,9)="Sem fluxo","—",IFERROR(INDEX(tbl_regras_dfr[Classe],MATCH(L117&"|Tipo de rótulo|"&AA117,tbl_regras_dfr[Chave],0)),"Sem regra")) -> C | AQ117: =IF(LEFT(L117,9)="Sem fluxo","—",IFERROR(INDEX(tbl_regras_dfr[Classe],MATCH(L117&"|Adesivo do rótulo|"&AB117,tbl_regras_dfr[Chave],0)),"Sem regra")) -> A | AR117: =IF(LEFT(L117,9)="Sem fluxo","—",IFERROR(INDEX(tbl_regras_dfr[Classe],MATCH(L117&"|Cobertura do rótulo|"&IF(AC117>0.7,"> 70% da superfície","≤ 70% da superfície"),tbl_regras_dfr[Chave],0)),"Sem regra")) -> A | AS117: =IF(LEFT(L117,9)="Sem fluxo","—",IFERROR(INDEX(tbl_regras_dfr[Classe],MATCH(L117&"|Decoração direta|"&AH117,tbl_regras_dfr[Chave],0)),"Sem regra")) -> A | AT117: =IF(COUNTIF(AJ117:AS117,"F"),6,IF(COUNTIF(AJ117:AS117,"E"),5,IF(COUNTIF(AJ117:AS117,"D"),4,IF(COUNTIF(AJ117:AS117,"C"),3,IF(COUNTIF(AJ117:AS117,"B"),2,IF(COUNTIF(AJ117:AS117,"A"),1,0)))))) -> 3 | AU117: =IF(AT117=0,"",INDEX({"A","B","C","D","E","F"},AT117)) -> C | AV117: =COUNTIF(AJ117:AS117,"Sem regra") -> 0 | AW117: =IF(OR(AU117="",AU117="A"),"—",SUBSTITUTE(INDEX($AJ$4:$AS$4,MATCH(AU117,AJ117:AS117,0)),"Classe_","")) -> Rotulo | AX117: =IF(AU117="A","Sem ação — manter o design.",IFERROR(INDEX(tbl_regras_dfr[Recomendacao],MATCH(CHOOSE(MATCH(AU117,AJ117:AS117,0),L117&"|Fluxo de reciclagem|"&L117,L117&"|Cor do corpo|"&O117,L117&"|Densidade do corpo|"&IF(R117<1,"< 1,0 g/cm³","≥ 1,0 g/cm³"),L117&"|Barreira / revestimento|"&S117,L117&"|Material da tampa|"&X117,L117&"|Vedante / liner|"&Z117,L117&"|Tipo de rótulo|"&AA117,L117&"|Adesivo do rótulo|"&AB117,L117&"|Cobertura do rótulo|"&IF(AC117>0.7,"> 70% da superfície","≤ 70% da superfície"),L117&"|Decoração direta|"&AH117),tbl_regras_dfr[Chave],0)),"")) -> Usar rótulo de PE/PP. | AY117: =T117+Y117+AD117+AI117 -> 27.29 | AZ117: =MIN(IFERROR(INDEX(tbl_regras_dfr[Fracao_Reciclavel],MATCH(L117&"|Fluxo de reciclagem|"&L117,tbl_regras_dfr[Chave],0)),0),IFERROR(INDEX(tbl_regras_dfr[Fracao_Reciclavel],MATCH(L117&"|Cor do corpo|"&O117,tbl_regras_dfr[Chave],0)),0)) -> 1 | BA117: =IFERROR(INDEX(tbl_regras_dfr[Fracao_Reciclavel],MATCH(L117&"|Material da tampa|"&X117,tbl_regras_dfr[Chave],0)),0) -> 1 | BB117: =IFERROR(INDEX(tbl_regras_dfr[Fracao_Reciclavel],MATCH(L117&"|Tipo de rótulo|"&AA117,tbl_regras_dfr[Chave],0)),0) -> 0 | BC117: =AZ117*(T117+Y117*BA117+AD117*BB117) -> 27.1 | BD117: =IFERROR(BC117/AY117,0) -> 0.99303774 | BE117: =IF(BD117>=INDEX(tbl_param_emb[Valor],MATCH("P-06",tbl_param_emb[ID_Parametro],0)),"A",IF(BD117>=INDEX(tbl_param_emb[Valor],MATCH("P-07",tbl_param_emb[ID_Parametro],0)),"B",IF(BD117>=INDEX(tbl_param_emb[Valor],MATCH("P-08",tbl_param_emb[ID_Parametro],0)),"C","< 70%"))) -> A | BF117: =IF(AU117="F","Não reciclável (F)",INDEX({"A","B","C","Abaixo de C"},MAX(MIN(AT117,4),IF(BE117="A",1,IF(BE117="B",2,IF(BE117="C",3,4)))))) -> C | BG117: =IF(D117="Farmacêutico","Isento até 2035","—") -> Isento até 2035 | BH117: =IF(BG117<>"—",BG117,IF(OR(BF117="A",BF117="B",BF117="C"),"Sim","Não")) -> Isento até 2035 | BI117: =IF(BG117<>"—",BG117,IF(OR(BF117="A",BF117="B"),"Sim","Não")) -> Isento até 2035 | BJ117: =IFERROR(INDEX(tbl_materiais[Pct_PCR],MATCH(J117,tbl_materiais[Material],0)),0) -> 0 | BK117: =IF(V117="",0,IFERROR(INDEX(tbl_tampas[Pct_PCR],MATCH(V117,tbl_tampas[CapId],0)),0)) -> 0 | BL117: =IFERROR((T117*BJ117+Y117*BK117)/(T117+Y117),0) -> 0 | BM117: =IF(D117="Farmacêutico","Isenta — medicamentos (art. 7.º)",IF(D117="Alimentar",IF(K117="PET","Sensível ao contacto — PET","Sensível ao contacto — outros plásticos"),"Outras embalagens de plástico")) -> Isenta — medicamentos (art. 7.º) | BN117: =IFERROR(IF(INDEX(tbl_metas_art7[Meta_2030],MATCH(BM117,tbl_metas_art7[Categoria_Art7],0))="","",INDEX(tbl_metas_art7[Meta_2030],MATCH(BM117,tbl_metas_art7[Categoria_Art7],0))),"") | BO117: =IF(BN117="","",MAX(0,BN117-BL117)) | BP117: =IF(BN117="","Isento",IF(BO117=0,"Sim","Não")) -> Isento | BQ117: =IF(AND(OR(X117=K117,X117="Sem tampa",AND(OR(X117="PE",X117="PP"),OR(K117="PE",K117="PP"))),OR(AA117="Sem rótulo",AND(ISNUMBER(SEARCH("PE/PP",AA117)),OR(K117="PE",K117="PP")))),"Monomaterial (mesma família)","Multimaterial") -> Multimaterial | BR117: 202596 | BS117: 3 | BT117: ES; PT | BU117: =BR117*T117/1000 -> 2147.5176 | BV117: =COUNTIFS(tbl_aplicabilidade[ProductId],B117,tbl_aplicabilidade[Aplicavel],"Sim") -> 12 | BW117: =COUNTIFS(tbl_aplicabilidade[ProductId],B117,tbl_aplicabilidade[Estado_Resumo],"Lacuna")+COUNTIFS(tbl_aplicabilidade[ProductId],B117,tbl_aplicabilidade[Estado_Resumo],"Não conforme") -> 1 | BX117: 46287 | BY117: =EDATE(BX117,12) -> 46652 | BZ117: Responsável de R&D | CA117: Autoavaliação (não certificada) | CB117: Regras simplificadas SGA-20 v1 (diretrizes DfR RecyClass) — confirmar na ferramenta online

Sheet Compat_Tampas
A1: CapId | B1: Fluxo_Corpo | C1: Polimero_Tampa | D1: Classe | E1: Fracao_Reciclavel | F1: Fundamentacao | G1: Recomendacao_Comercial
A2: TR-001-HDPE-24410 | B2: PE rígido | C2: =IFERROR(INDEX(tbl_tampas[Polimero_Base],MATCH(A2,tbl_tampas[CapId],0)),"") -> PE | D2: =IFERROR(INDEX(tbl_regras_dfr[Classe],MATCH(B2&"|Material da tampa|"&C2,tbl_regras_dfr[Chave],0)),"Sem regra") -> A | E2: =IFERROR(INDEX(tbl_regras_dfr[Fracao_Reciclavel],MATCH(B2&"|Material da tampa|"&C2,tbl_regras_dfr[Chave],0)),0) -> 1 | F2: =IFERROR(INDEX(tbl_regras_dfr[Fundamentacao],MATCH(B2&"|Material da tampa|"&C2,tbl_regras_dfr[Chave],0)),"") -> Poliolefina: reciclada com o corpo ou no fluxo de poliolefinas. | G2: =IF(D2="A","Recomendada",IF(D2="B","Aceitável (perda de massa)","Evitar neste fluxo")) -> Recomendada
A3: TR-001-HDPE-24410 | B3: PP rígido | C3: =IFERROR(INDEX(tbl_tampas[Polimero_Base],MATCH(A3,tbl_tampas[CapId],0)),"") -> PE | D3: =IFERROR(INDEX(tbl_regras_dfr[Classe],MATCH(B3&"|Material da tampa|"&C3,tbl_regras_dfr[Chave],0)),"Sem regra") -> A | E3: =IFERROR(INDEX(tbl_regras_dfr[Fracao_Reciclavel],MATCH(B3&"|Material da tampa|"&C3,tbl_regras_dfr[Chave],0)),0) -> 1 | F3: =IFERROR(INDEX(tbl_regras_dfr[Fundamentacao],MATCH(B3&"|Material da tampa|"&C3,tbl_regras_dfr[Chave],0)),"") -> Poliolefina: reciclada com o corpo ou no fluxo de poliolefinas. | G3: =IF(D3="A","Recomendada",IF(D3="B","Aceitável (perda de massa)","Evitar neste fluxo")) -> Recomendada
A4: TR-001-HDPE-24410 | B4: PET frascos e garrafas | C4: =IFERROR(INDEX(tbl_tampas[Polimero_Base],MATCH(A4,tbl_tampas[CapId],0)),"") -> PE | D4: =IFERROR(INDEX(tbl_regras_dfr[Classe],MATCH(B4&"|Material da tampa|"&C4,tbl_regras_dfr[Chave],0)),"Sem regra") -> A | E4: =IFERROR(INDEX(tbl_regras_dfr[Fracao_Reciclavel],MATCH(B4&"|Material da tampa|"&C4,tbl_regras_dfr[Chave],0)),0) -> 1 | F4: =IFERROR(INDEX(tbl_regras_dfr[Fundamentacao],MATCH(B4&"|Material da tampa|"&C4,tbl_regras_dfr[Chave],0)),"") -> Flutua e é separada; reciclada no fluxo de poliolefinas. | G4: =IF(D4="A","Recomendada",IF(D4="B","Aceitável (perda de massa)","Evitar neste fluxo")) -> Recomendada
A5: TR-001-PP-24410 | B5: PE rígido | C5: =IFERROR(INDEX(tbl_tampas[Polimero_Base],MATCH(A5,tbl_tampas[CapId],0)),"") -> PP | D5: =IFERROR(INDEX(tbl_regras_dfr[Classe],MATCH(B5&"|Material da tampa|"&C5,tbl_regras_dfr[Chave],0)),"Sem regra") -> A | E5: =IFERROR(INDEX(tbl_regras_dfr[Fracao_Reciclavel],MATCH(B5&"|Material da tampa|"&C5,tbl_regras_dfr[Chave],0)),0) -> 1 | F5: =IFERROR(INDEX(tbl_regras_dfr[Fundamentacao],MATCH(B5&"|Material da tampa|"&C5,tbl_regras_dfr[Chave],0)),"") -> Poliolefina: flutua e é reciclada no fluxo de poliolefinas. | G5: =IF(D5="A","Recomendada",IF(D5="B","Aceitável (perda de massa)","Evitar neste fluxo")) -> Recomendada
A6: TR-001-PP-24410 | B6: PP rígido | C6: =IFERROR(INDEX(tbl_tampas[Polimero_Base],MATCH(A6,tbl_tampas[CapId],0)),"") -> PP | D6: =IFERROR(INDEX(tbl_regras_dfr[Classe],MATCH(B6&"|Material da tampa|"&C6,tbl_regras_dfr[Chave],0)),"Sem regra") -> A | E6: =IFERROR(INDEX(tbl_regras_dfr[Fracao_Reciclavel],MATCH(B6&"|Material da tampa|"&C6,tbl_regras_dfr[Chave],0)),0) -> 1 | F6: =IFERROR(INDEX(tbl_regras_dfr[Fundamentacao],MATCH(B6&"|Material da tampa|"&C6,tbl_regras_dfr[Chave],0)),"") -> Poliolefina: flutua e é reciclada no fluxo de poliolefinas. | G6: =IF(D6="A","Recomendada",IF(D6="B","Aceitável (perda de massa)","Evitar neste fluxo")) -> Recomendada
A7: TR-001-PP-24410 | B7: PET frascos e garrafas | C7: =IFERROR(INDEX(tbl_tampas[Polimero_Base],MATCH(A7,tbl_tampas[CapId],0)),"") -> PP | D7: =IFERROR(INDEX(tbl_regras_dfr[Classe],MATCH(B7&"|Material da tampa|"&C7,tbl_regras_dfr[Chave],0)),"Sem regra") -> A | E7: =IFERROR(INDEX(tbl_regras_dfr[Fracao_Reciclavel],MATCH(B7&"|Material da tampa|"&C7,tbl_regras_dfr[Chave],0)),0) -> 1 | F7: =IFERROR(INDEX(tbl_regras_dfr[Fundamentacao],MATCH(B7&"|Material da tampa|"&C7,tbl_regras_dfr[Chave],0)),"") -> Flutua e é separada; reciclada no fluxo de poliolefinas. | G7: =IF(D7="A","Recomendada",IF(D7="B","Aceitável (perda de massa)","Evitar neste fluxo")) -> Recomendada
A8: TR-001-PP-PCR-24410 | B8: PE rígido | C8: =IFERROR(INDEX(tbl_tampas[Polimero_Base],MATCH(A8,tbl_tampas[CapId],0)),"") -> PP | D8: =IFERROR(INDEX(tbl_regras_dfr[Classe],MATCH(B8&"|Material da tampa|"&C8,tbl_regras_dfr[Chave],0)),"Sem regra") -> A | E8: =IFERROR(INDEX(tbl_regras_dfr[Fracao_Reciclavel],MATCH(B8&"|Material da tampa|"&C8,tbl_regras_dfr[Chave],0)),0) -> 1 | F8: =IFERROR(INDEX(tbl_regras_dfr[Fundamentacao],MATCH(B8&"|Material da tampa|"&C8,tbl_regras_dfr[Chave],0)),"") -> Poliolefina: flutua e é reciclada no fluxo de poliolefinas. | G8: =IF(D8="A","Recomendada",IF(D8="B","Aceitável (perda de massa)","Evitar neste fluxo")) -> Recomendada
A9: TR-001-PP-PCR-24410 | B9: PP rígido | C9: =IFERROR(INDEX(tbl_tampas[Polimero_Base],MATCH(A9,tbl_tampas[CapId],0)),"") -> PP | D9: =IFERROR(INDEX(tbl_regras_dfr[Classe],MATCH(B9&"|Material da tampa|"&C9,tbl_regras_dfr[Chave],0)),"Sem regra") -> A | E9: =IFERROR(INDEX(tbl_regras_dfr[Fracao_Reciclavel],MATCH(B9&"|Material da tampa|"&C9,tbl_regras_dfr[Chave],0)),0) -> 1 | F9: =IFERROR(INDEX(tbl_regras_dfr[Fundamentacao],MATCH(B9&"|Material da tampa|"&C9,tbl_regras_dfr[Chave],0)),"") -> Poliolefina: flutua e é reciclada no fluxo de poliolefinas. | G9: =IF(D9="A","Recomendada",IF(D9="B","Aceitável (perda de massa)","Evitar neste fluxo")) -> Recomendada
A10: TR-001-PP-PCR-24410 | B10: PET frascos e garrafas | C10: =IFERROR(INDEX(tbl_tampas[Polimero_Base],MATCH(A10,tbl_tampas[CapId],0)),"") -> PP | D10: =IFERROR(INDEX(tbl_regras_dfr[Classe],MATCH(B10&"|Material da tampa|"&C10,tbl_regras_dfr[Chave],0)),"Sem regra") -> A | E10: =IFERROR(INDEX(tbl_regras_dfr[Fracao_Reciclavel],MATCH(B10&"|Material da tampa|"&C10,tbl_regras_dfr[Chave],0)),0) -> 1 | F10: =IFERROR(INDEX(tbl_regras_dfr[Fundamentacao],MATCH(B10&"|Material da tampa|"&C10,tbl_regras_dfr[Chave],0)),"") -> Flutua e é separada; reciclada no fluxo de poliolefinas. | G10: =IF(D10="A","Recomendada",IF(D10="B","Aceitável (perda de massa)","Evitar neste fluxo")) -> Recomendada
A11: TR-001-PETG-24410 | B11: PE rígido | C11: =IFERROR(INDEX(tbl_tampas[Polimero_Base],MATCH(A11,tbl_tampas[CapId],0)),"") -> PETG | D11: =IFERROR(INDEX(tbl_regras_dfr[Classe],MATCH(B11&"|Material da tampa|"&C11,tbl_regras_dfr[Chave],0)),"Sem regra") -> B | E11: =IFERROR(INDEX(tbl_regras_dfr[Fracao_Reciclavel],MATCH(B11&"|Material da tampa|"&C11,tbl_regras_dfr[Chave],0)),0) -> 0 | F11: =IFERROR(INDEX(tbl_regras_dfr[Fundamentacao],MATCH(B11&"|Material da tampa|"&C11,tbl_regras_dfr[Chave],0)),"") -> Afunda e é separada no afunda-flutua; massa perdida. | G11: =IF(D11="A","Recomendada",IF(D11="B","Aceitável (perda de massa)","Evitar neste fluxo")) -> Aceitável (perda de massa)
A12: TR-001-PETG-24410 | B12: PP rígido | C12: =IFERROR(INDEX(tbl_tampas[Polimero_Base],MATCH(A12,tbl_tampas[CapId],0)),"") -> PETG | D12: =IFERROR(INDEX(tbl_regras_dfr[Classe],MATCH(B12&"|Material da tampa|"&C12,tbl_regras_dfr[Chave],0)),"Sem regra") -> B | E12: =IFERROR(INDEX(tbl_regras_dfr[Fracao_Reciclavel],MATCH(B12&"|Material da tampa|"&C12,tbl_regras_dfr[Chave],0)),0) -> 0 | F12: =IFERROR(INDEX(tbl_regras_dfr[Fundamentacao],MATCH(B12&"|Material da tampa|"&C12,tbl_regras_dfr[Chave],0)),"") -> Afunda e é separada no afunda-flutua; massa perdida. | G12: =IF(D12="A","Recomendada",IF(D12="B","Aceitável (perda de massa)","Evitar neste fluxo")) -> Aceitável (perda de massa)
A13: TR-001-PETG-24410 | B13: PET frascos e garrafas | C13: =IFERROR(INDEX(tbl_tampas[Polimero_Base],MATCH(A13,tbl_tampas[CapId],0)),"") -> PETG | D13: =IFERROR(INDEX(tbl_regras_dfr[Classe],MATCH(B13&"|Material da tampa|"&C13,tbl_regras_dfr[Chave],0)),"Sem regra") -> D | E13: =IFERROR(INDEX(tbl_regras_dfr[Fracao_Reciclavel],MATCH(B13&"|Material da tampa|"&C13,tbl_regras_dfr[Chave],0)),0) -> 0 | F13: =IFERROR(INDEX(tbl_regras_dfr[Fundamentacao],MATCH(B13&"|Material da tampa|"&C13,tbl_regras_dfr[Chave],0)),"") -> Afunda com os flocos de PET e contamina-os (aglomera na secagem). | G13: =IF(D13="A","Recomendada",IF(D13="B","Aceitável (perda de massa)","Evitar neste fluxo")) -> Evitar neste fluxo
... A109: TA-014-PP-FG-28410 | B109: PET frascos e garrafas | C109: =IFERROR(INDEX(tbl_tampas[Polimero_Base],MATCH(A109,tbl_tampas[CapId],0)),"") -> PP | D109: =IFERROR(INDEX(tbl_regras_dfr[Classe],MATCH(B109&"|Material da tampa|"&C109,tbl_regras_dfr[Chave],0)),"Sem regra") -> A | E109: =IFERROR(INDEX(tbl_regras_dfr[Fracao_Reciclavel],MATCH(B109&"|Material da tampa|"&C109,tbl_regras_dfr[Chave],0)),0) -> 1 | F109: =IFERROR(INDEX(tbl_regras_dfr[Fundamentacao],MATCH(B109&"|Material da tampa|"&C109,tbl_regras_dfr[Chave],0)),"") -> Flutua e é separada; reciclada no fluxo de poliolefinas. | G109: =IF(D109="A","Recomendada",IF(D109="B","Aceitável (perda de massa)","Evitar neste fluxo")) -> Recomendada

Sheet Familias_PPWR
A1: ID_Familia | B1: Familia | C1: Tipo | D1: Material | E1: N_SKUs | F1: Documentacao_Tecnica | G1: Declaracao_UE | H1: Data_DoC | I1: Metais_Pesados_Evidencia | J1: Metais_mg_kg | K1: PFAS_Evidencia | L1: SVHC_Artigo | M1: SVHC_Evidencia | N1: Obrigacao_SVHC | O1: Pior_Classe_RecyClass | P1: SKUs_Nao_Conformes_2030 | Q1: Estado | R1: Prazo | S1: ID_PAM
A2: FAM-01 | B2: Frascos HDPE | C2: Frasco | D2: HDPE | E2: =COUNTIF(tbl_recyclass[Familia_PPWR],A2)+COUNTIF(tbl_tampas[Familia_PPWR],A2) -> 19 | F2: Sim | G2: Sim | H2: 46244 | I2: RM-2026-07 (laboratório acreditado) | J2: 18 | K2: Não aplicável (sem contacto alimentar) | L2: Não | M2: Declarações dos fornecedores do polímero e do masterbatch (RG-SGA-21 tbl_declaracoes). | N2: =IF(L2="Sim","Art. 33.º + SCIP (+ art. 7.º, n.º 2 se > 1 t/ano)",IF(L2="Por confirmar","Não expedir sem confirmação","Nenhuma")) -> Nenhuma | O2: =IF(COUNTIF(tbl_recyclass[Familia_PPWR],A2)=0,"(componente)",INDEX({"A","B","C","D","E","F"},_xlfn.MAXIFS(tbl_recyclass[Classe_N_Max],tbl_recyclass[Familia_PPWR],A2))) -> F | P2: =COUNTIFS(tbl_recyclass[Familia_PPWR],A2,tbl_recyclass[Conforme_PPWR_2030],"Não") -> 3 | Q2: =IF(AND(G2="Sim",I2<>"Em falta"),"Conforme","Lacuna") -> Conforme | R2: 46387 | S2: PAM-26-10
A3: FAM-02 | B3: Frascos HDPE-PCR | C3: Frasco | D3: HDPE-PCR | E3: =COUNTIF(tbl_recyclass[Familia_PPWR],A3)+COUNTIF(tbl_tampas[Familia_PPWR],A3) -> 13 | F3: Sim | G3: Sim | H3: 46244 | I3: RM-2026-07 (laboratório acreditado) | J3: 18 | K3: Não aplicável (sem contacto alimentar) | L3: Não | M3: Declarações dos fornecedores do polímero e do masterbatch (RG-SGA-21 tbl_declaracoes). | N3: =IF(L3="Sim","Art. 33.º + SCIP (+ art. 7.º, n.º 2 se > 1 t/ano)",IF(L3="Por confirmar","Não expedir sem confirmação","Nenhuma")) -> Nenhuma | O3: =IF(COUNTIF(tbl_recyclass[Familia_PPWR],A3)=0,"(componente)",INDEX({"A","B","C","D","E","F"},_xlfn.MAXIFS(tbl_recyclass[Classe_N_Max],tbl_recyclass[Familia_PPWR],A3))) -> C | P3: =COUNTIFS(tbl_recyclass[Familia_PPWR],A3,tbl_recyclass[Conforme_PPWR_2030],"Não") -> 0 | Q3: =IF(AND(G3="Sim",I3<>"Em falta"),"Conforme","Lacuna") -> Conforme | R3: 46387 | S3: PAM-26-10
A4: FAM-03 | B4: Frascos MDPE | C4: Frasco | D4: MDPE | E4: =COUNTIF(tbl_recyclass[Familia_PPWR],A4)+COUNTIF(tbl_tampas[Familia_PPWR],A4) -> 5 | F4: Sim | G4: Sim | H4: 46244 | I4: RM-2026-07 (laboratório acreditado) | J4: 18 | K4: Não aplicável (sem contacto alimentar) | L4: Não | M4: Declarações dos fornecedores do polímero e do masterbatch (RG-SGA-21 tbl_declaracoes). | N4: =IF(L4="Sim","Art. 33.º + SCIP (+ art. 7.º, n.º 2 se > 1 t/ano)",IF(L4="Por confirmar","Não expedir sem confirmação","Nenhuma")) -> Nenhuma | O4: =IF(COUNTIF(tbl_recyclass[Familia_PPWR],A4)=0,"(componente)",INDEX({"A","B","C","D","E","F"},_xlfn.MAXIFS(tbl_recyclass[Classe_N_Max],tbl_recyclass[Familia_PPWR],A4))) -> F | P4: =COUNTIFS(tbl_recyclass[Familia_PPWR],A4,tbl_recyclass[Conforme_PPWR_2030],"Não") -> 1 | Q4: =IF(AND(G4="Sim",I4<>"Em falta"),"Conforme","Lacuna") -> Conforme | R4: 46387 | S4: PAM-26-10
A5: FAM-04 | B5: Frascos LDPE | C5: Frasco | D5: LDPE | E5: =COUNTIF(tbl_recyclass[Familia_PPWR],A5)+COUNTIF(tbl_tampas[Familia_PPWR],A5) -> 3 | F5: Sim | G5: Sim | H5: 46244 | I5: Declaração do fornecedor | K5: Não aplicável (sem contacto alimentar) | L5: Não | M5: Declarações dos fornecedores do polímero e do masterbatch (RG-SGA-21 tbl_declaracoes). | N5: =IF(L5="Sim","Art. 33.º + SCIP (+ art. 7.º, n.º 2 se > 1 t/ano)",IF(L5="Por confirmar","Não expedir sem confirmação","Nenhuma")) -> Nenhuma | O5: =IF(COUNTIF(tbl_recyclass[Familia_PPWR],A5)=0,"(componente)",INDEX({"A","B","C","D","E","F"},_xlfn.MAXIFS(tbl_recyclass[Classe_N_Max],tbl_recyclass[Familia_PPWR],A5))) -> C | P5: =COUNTIFS(tbl_recyclass[Familia_PPWR],A5,tbl_recyclass[Conforme_PPWR_2030],"Não") -> 0 | Q5: =IF(AND(G5="Sim",I5<>"Em falta"),"Conforme","Lacuna") -> Conforme | R5: 46387 | S5: PAM-26-10
A6: FAM-05 | B6: Frascos HDPE-FG | C6: Frasco | D6: HDPE-FG | E6: =COUNTIF(tbl_recyclass[Familia_PPWR],A6)+COUNTIF(tbl_tampas[Familia_PPWR],A6) -> 2 | F6: Sim | G6: Sim | H6: 46244 | I6: RM-2026-07 (laboratório acreditado) | J6: 18 | K6: Declaração SUP-010 (07/2026) + flúor total < 50 ppm | L6: Não | M6: Declarações dos fornecedores do polímero e do masterbatch (RG-SGA-21 tbl_declaracoes). | N6: =IF(L6="Sim","Art. 33.º + SCIP (+ art. 7.º, n.º 2 se > 1 t/ano)",IF(L6="Por confirmar","Não expedir sem confirmação","Nenhuma")) -> Nenhuma | O6: =IF(COUNTIF(tbl_recyclass[Familia_PPWR],A6)=0,"(componente)",INDEX({"A","B","C","D","E","F"},_xlfn.MAXIFS(tbl_recyclass[Classe_N_Max],tbl_recyclass[Familia_PPWR],A6))) -> A | P6: =COUNTIFS(tbl_recyclass[Familia_PPWR],A6,tbl_recyclass[Conforme_PPWR_2030],"Não") -> 0 | Q6: =IF(AND(G6="Sim",I6<>"Em falta"),"Conforme","Lacuna") -> Conforme | R6: 46387 | S6: PAM-26-10
A7: FAM-06 | B7: Frascos PP | C7: Frasco | D7: PP | E7: =COUNTIF(tbl_recyclass[Familia_PPWR],A7)+COUNTIF(tbl_tampas[Familia_PPWR],A7) -> 9 | F7: Sim | G7: Sim | H7: 46244 | I7: Declaração do fornecedor | K7: Não aplicável (sem contacto alimentar) | L7: Não | M7: Declarações dos fornecedores do polímero e do masterbatch (RG-SGA-21 tbl_declaracoes). | N7: =IF(L7="Sim","Art. 33.º + SCIP (+ art. 7.º, n.º 2 se > 1 t/ano)",IF(L7="Por confirmar","Não expedir sem confirmação","Nenhuma")) -> Nenhuma | O7: =IF(COUNTIF(tbl_recyclass[Familia_PPWR],A7)=0,"(componente)",INDEX({"A","B","C","D","E","F"},_xlfn.MAXIFS(tbl_recyclass[Classe_N_Max],tbl_recyclass[Familia_PPWR],A7))) -> F | P7: =COUNTIFS(tbl_recyclass[Familia_PPWR],A7,tbl_recyclass[Conforme_PPWR_2030],"Não") -> 2 | Q7: =IF(AND(G7="Sim",I7<>"Em falta"),"Conforme","Lacuna") -> Conforme | R7: 46387 | S7: PAM-26-10
A8: FAM-07 | B8: Frascos PP-PCR | C8: Frasco | D8: PP-PCR | E8: =COUNTIF(tbl_recyclass[Familia_PPWR],A8)+COUNTIF(tbl_tampas[Familia_PPWR],A8) -> 8 | F8: Sim | G8: Sim | H8: 46315 | I8: Declaração do fornecedor | K8: Não aplicável (sem contacto alimentar) | L8: Não | M8: Declarações dos fornecedores do polímero e do masterbatch (RG-SGA-21 tbl_declaracoes). | N8: =IF(L8="Sim","Art. 33.º + SCIP (+ art. 7.º, n.º 2 se > 1 t/ano)",IF(L8="Por confirmar","Não expedir sem confirmação","Nenhuma")) -> Nenhuma | O8: =IF(COUNTIF(tbl_recyclass[Familia_PPWR],A8)=0,"(componente)",INDEX({"A","B","C","D","E","F"},_xlfn.MAXIFS(tbl_recyclass[Classe_N_Max],tbl_recyclass[Familia_PPWR],A8))) -> F | P8: =COUNTIFS(tbl_recyclass[Familia_PPWR],A8,tbl_recyclass[Conforme_PPWR_2030],"Não") -> 1 | Q8: =IF(AND(G8="Sim",I8<>"Em falta"),"Conforme","Lacuna") -> Conforme | R8: 46387 | S8: PAM-26-10
A9: FAM-08 | B9: Frascos PP-FG | C9: Frasco | D9: PP-FG | E9: =COUNTIF(tbl_recyclass[Familia_PPWR],A9)+COUNTIF(tbl_tampas[Familia_PPWR],A9) -> 2 | F9: Sim | G9: Sim | H9: 46315 | I9: Declaração do fornecedor | K9: Declaração SUP-010 (07/2026) + flúor total < 50 ppm | L9: Não | M9: Declarações dos fornecedores do polímero e do masterbatch (RG-SGA-21 tbl_declaracoes). | N9: =IF(L9="Sim","Art. 33.º + SCIP (+ art. 7.º, n.º 2 se > 1 t/ano)",IF(L9="Por confirmar","Não expedir sem confirmação","Nenhuma")) -> Nenhuma | O9: =IF(COUNTIF(tbl_recyclass[Familia_PPWR],A9)=0,"(componente)",INDEX({"A","B","C","D","E","F"},_xlfn.MAXIFS(tbl_recyclass[Classe_N_Max],tbl_recyclass[Familia_PPWR],A9))) -> A | P9: =COUNTIFS(tbl_recyclass[Familia_PPWR],A9,tbl_recyclass[Conforme_PPWR_2030],"Não") -> 0 | Q9: =IF(AND(G9="Sim",I9<>"Em falta"),"Conforme","Lacuna") -> Conforme | R9: 46387 | S9: PAM-26-10
A10: FAM-09 | B10: Frascos PP-PG | C10: Frasco | D10: PP-PG | E10: =COUNTIF(tbl_recyclass[Familia_PPWR],A10)+COUNTIF(tbl_tampas[Familia_PPWR],A10) -> 2 | F10: Não | G10: Não | I10: Em falta | K10: Não aplicável (sem contacto alimentar) | L10: Não | M10: Declarações dos fornecedores do polímero e do masterbatch (RG-SGA-21 tbl_declaracoes). | N10: =IF(L10="Sim","Art. 33.º + SCIP (+ art. 7.º, n.º 2 se > 1 t/ano)",IF(L10="Por confirmar","Não expedir sem confirmação","Nenhuma")) -> Nenhuma | O10: =IF(COUNTIF(tbl_recyclass[Familia_PPWR],A10)=0,"(componente)",INDEX({"A","B","C","D","E","F"},_xlfn.MAXIFS(tbl_recyclass[Classe_N_Max],tbl_recyclass[Familia_PPWR],A10))) -> C | P10: =COUNTIFS(tbl_recyclass[Familia_PPWR],A10,tbl_recyclass[Conforme_PPWR_2030],"Não") -> 0 | Q10: =IF(AND(G10="Sim",I10<>"Em falta"),"Conforme","Lacuna") -> Lacuna | R10: 46387 | S10: PAM-26-10
A11: FAM-10 | B11: Frascos PET | C11: Frasco | D11: PET | E11: =COUNTIF(tbl_recyclass[Familia_PPWR],A11)+COUNTIF(tbl_tampas[Familia_PPWR],A11) -> 13 | F11: Sim | G11: Sim | H11: 46332 | I11: Declaração do fornecedor | K11: Não aplicável (sem contacto alimentar) | L11: Não | M11: DEC-03; tinta UV: fotoiniciador 71868-10-5 = 0,018% m/m no frasco decorado (< 0,1%). | N11: =IF(L11="Sim","Art. 33.º + SCIP (+ art. 7.º, n.º 2 se > 1 t/ano)",IF(L11="Por confirmar","Não expedir sem confirmação","Nenhuma")) -> Nenhuma | O11: =IF(COUNTIF(tbl_recyclass[Familia_PPWR],A11)=0,"(componente)",INDEX({"A","B","C","D","E","F"},_xlfn.MAXIFS(tbl_recyclass[Classe_N_Max],tbl_recyclass[Familia_PPWR],A11))) -> D | P11: =COUNTIFS(tbl_recyclass[Familia_PPWR],A11,tbl_recyclass[Conforme_PPWR_2030],"Não") -> 6 | Q11: =IF(AND(G11="Sim",I11<>"Em falta"),"Conforme","Lacuna") -> Conforme | R11: 46387 | S11: PAM-26-10
A12: FAM-11 | B12: Frascos rPET | C12: Frasco | D12: rPET | E12: =COUNTIF(tbl_recyclass[Familia_PPWR],A12)+COUNTIF(tbl_tampas[Familia_PPWR],A12) -> 19 | F12: Sim | G12: Sim | H12: 46353 | I12: Em falta | K12: Não aplicável (sem contacto alimentar) | L12: Não | M12: DEC-04 (desatualizada — pedir nova, PAM-26-34); tinta UV 0,018% m/m (< 0,1%). | N12: =IF(L12="Sim","Art. 33.º + SCIP (+ art. 7.º, n.º 2 se > 1 t/ano)",IF(L12="Por confirmar","Não expedir sem confirmação","Nenhuma")) -> Nenhuma | O12: =IF(COUNTIF(tbl_recyclass[Familia_PPWR],A12)=0,"(componente)",INDEX({"A","B","C","D","E","F"},_xlfn.MAXIFS(tbl_recyclass[Classe_N_Max],tbl_recyclass[Familia_PPWR],A12))) -> D | P12: =COUNTIFS(tbl_recyclass[Familia_PPWR],A12,tbl_recyclass[Conforme_PPWR_2030],"Não") -> 11 | Q12: =IF(AND(G12="Sim",I12<>"Em falta"),"Conforme","Lacuna") -> Lacuna | R12: 46387 | S12: PAM-26-10
A13: FAM-12 | B13: Frascos PET-PG | C13: Frasco | D13: PET-PG | E13: =COUNTIF(tbl_recyclass[Familia_PPWR],A13)+COUNTIF(tbl_tampas[Familia_PPWR],A13) -> 2 | F13: Não | G13: Não | I13: Em falta | K13: Não aplicável (sem contacto alimentar) | L13: Não | M13: DEC-11. | N13: =IF(L13="Sim","Art. 33.º + SCIP (+ art. 7.º, n.º 2 se > 1 t/ano)",IF(L13="Por confirmar","Não expedir sem confirmação","Nenhuma")) -> Nenhuma | O13: =IF(COUNTIF(tbl_recyclass[Familia_PPWR],A13)=0,"(componente)",INDEX({"A","B","C","D","E","F"},_xlfn.MAXIFS(tbl_recyclass[Classe_N_Max],tbl_recyclass[Familia_PPWR],A13))) -> C | P13: =COUNTIFS(tbl_recyclass[Familia_PPWR],A13,tbl_recyclass[Conforme_PPWR_2030],"Não") -> 0 | Q13: =IF(AND(G13="Sim",I13<>"Em falta"),"Conforme","Lacuna") -> Lacuna | R13: 46387 | S13: PAM-26-10
A14: FAM-13 | B14: Frascos PETG | C14: Frasco | D14: PETG | E14: =COUNTIF(tbl_recyclass[Familia_PPWR],A14)+COUNTIF(tbl_tampas[Familia_PPWR],A14) -> 8 | F14: Não | G14: Não | I14: Em falta | K14: Não aplicável (sem contacto alimentar) | L14: Não | M14: DEC-03; tinta UV 0,018% m/m (< 0,1%). | N14: =IF(L14="Sim","Art. 33.º + SCIP (+ art. 7.º, n.º 2 se > 1 t/ano)",IF(L14="Por confirmar","Não expedir sem confirmação","Nenhuma")) -> Nenhuma | O14: =IF(COUNTIF(tbl_recyclass[Familia_PPWR],A14)=0,"(componente)",INDEX({"A","B","C","D","E","F"},_xlfn.MAXIFS(tbl_recyclass[Classe_N_Max],tbl_recyclass[Familia_PPWR],A14))) -> F | P14: =COUNTIFS(tbl_recyclass[Familia_PPWR],A14,tbl_recyclass[Conforme_PPWR_2030],"Não") -> 8 | Q14: =IF(AND(G14="Sim",I14<>"Em falta"),"Conforme","Lacuna") -> Lacuna | R14: 46387 | S14: PAM-26-10
A15: FAM-14 | B15: Frascos PVC | C15: Frasco | D15: PVC | E15: =COUNTIF(tbl_recyclass[Familia_PPWR],A15)+COUNTIF(tbl_tampas[Familia_PPWR],A15) -> 4 | F15: Não | G15: Não | I15: Em falta | K15: Não aplicável (sem contacto alimentar) | L15: Por confirmar | M15: Sem declaração do SUP-005 (plastificante e estabilizante desconhecidos); análise GC-MS/XRF antes de expedir (PAM-26-28). | N15: =IF(L15="Sim","Art. 33.º + SCIP (+ art. 7.º, n.º 2 se > 1 t/ano)",IF(L15="Por confirmar","Não expedir sem confirmação","Nenhuma")) -> Não expedir sem confirmação | O15: =IF(COUNTIF(tbl_recyclass[Familia_PPWR],A15)=0,"(componente)",INDEX({"A","B","C","D","E","F"},_xlfn.MAXIFS(tbl_recyclass[Classe_N_Max],tbl_recyclass[Familia_PPWR],A15))) -> F | P15: =COUNTIFS(tbl_recyclass[Familia_PPWR],A15,tbl_recyclass[Conforme_PPWR_2030],"Não") -> 4 | Q15: =IF(AND(G15="Sim",I15<>"Em falta"),"Conforme","Lacuna") -> Lacuna | R15: 46387 | S15: PAM-26-10
A16: FAM-15 | B16: Potes PP (inclui PP-PG) | C16: Pote | D16: PP | E16: =COUNTIF(tbl_recyclass[Familia_PPWR],A16)+COUNTIF(tbl_tampas[Familia_PPWR],A16) -> 4 | F16: Sim | G16: Sim | H16: 46339 | I16: Em falta | K16: Não aplicável (sem contacto alimentar) | L16: Não | M16: Declarações dos fornecedores do polímero e do masterbatch (RG-SGA-21 tbl_declaracoes). | N16: =IF(L16="Sim","Art. 33.º + SCIP (+ art. 7.º, n.º 2 se > 1 t/ano)",IF(L16="Por confirmar","Não expedir sem confirmação","Nenhuma")) -> Nenhuma | O16: =IF(COUNTIF(tbl_recyclass[Familia_PPWR],A16)=0,"(componente)",INDEX({"A","B","C","D","E","F"},_xlfn.MAXIFS(tbl_recyclass[Classe_N_Max],tbl_recyclass[Familia_PPWR],A16))) -> C | P16: =COUNTIFS(tbl_recyclass[Familia_PPWR],A16,tbl_recyclass[Conforme_PPWR_2030],"Não") -> 0 | Q16: =IF(AND(G16="Sim",I16<>"Em falta"),"Conforme","Lacuna") -> Lacuna | R16: 46387 | S16: PAM-26-10
A17: FAM-16 | B17: Tampas PP | C17: Tampa | D17: PP | E17: =COUNTIF(tbl_recyclass[Familia_PPWR],A17)+COUNTIF(tbl_tampas[Familia_PPWR],A17) -> 10 | F17: Sim | G17: Sim | H17: 46244 | I17: Declaração do fornecedor | K17: Não aplicável (sem contacto alimentar) | L17: Por confirmar | M17: Masterbatch deslizante/antiestático sem declaração SVHC (DEC-09, PAM-26-34). | N17: =IF(L17="Sim","Art. 33.º + SCIP (+ art. 7.º, n.º 2 se > 1 t/ano)",IF(L17="Por confirmar","Não expedir sem confirmação","Nenhuma")) -> Não expedir sem confirmação | O17: =IF(COUNTIF(tbl_recyclass[Familia_PPWR],A17)=0,"(componente)",INDEX({"A","B","C","D","E","F"},_xlfn.MAXIFS(tbl_recyclass[Classe_N_Max],tbl_recyclass[Familia_PPWR],A17))) -> (componente) | P17: =COUNTIFS(tbl_recyclass[Familia_PPWR],A17,tbl_recyclass[Conforme_PPWR_2030],"Não") -> 0 | Q17: =IF(AND(G17="Sim",I17<>"Em falta"),"Conforme","Lacuna") -> Conforme | R17: 46387 | S17: PAM-26-10
A18: FAM-17 | B18: Tampas PP-PCR | C18: Tampa | D18: PP-PCR | E18: =COUNTIF(tbl_recyclass[Familia_PPWR],A18)+COUNTIF(tbl_tampas[Familia_PPWR],A18) -> 9 | F18: Sim | G18: Sim | H18: 46315 | I18: Declaração do fornecedor | K18: Não aplicável (sem contacto alimentar) | L18: Por confirmar | M18: Masterbatch deslizante/antiestático sem declaração SVHC (DEC-09, PAM-26-34). | N18: =IF(L18="Sim","Art. 33.º + SCIP (+ art. 7.º, n.º 2 se > 1 t/ano)",IF(L18="Por confirmar","Não expedir sem confirmação","Nenhuma")) -> Não expedir sem confirmação | O18: =IF(COUNTIF(tbl_recyclass[Familia_PPWR],A18)=0,"(componente)",INDEX({"A","B","C","D","E","F"},_xlfn.MAXIFS(tbl_recyclass[Classe_N_Max],tbl_recyclass[Familia_PPWR],A18))) -> (componente) | P18: =COUNTIFS(tbl_recyclass[Familia_PPWR],A18,tbl_recyclass[Conforme_PPWR_2030],"Não") -> 0 | Q18: =IF(AND(G18="Sim",I18<>"Em falta"),"Conforme","Lacuna") -> Conforme | R18: 46387 | S18: PAM-26-10
A19: FAM-18 | B19: Tampas HDPE | C19: Tampa | D19: HDPE | E19: =COUNTIF(tbl_recyclass[Familia_PPWR],A19)+COUNTIF(tbl_tampas[Familia_PPWR],A19) -> 9 | F19: Sim | G19: Sim | H19: 46244 | I19: RM-2026-07 (laboratório acreditado) | J19: 18 | K19: Não aplicável (sem contacto alimentar) | L19: Não | M19: Declarações dos fornecedores do polímero e do masterbatch (RG-SGA-21 tbl_declaracoes). | N19: =IF(L19="Sim","Art. 33.º + SCIP (+ art. 7.º, n.º 2 se > 1 t/ano)",IF(L19="Por confirmar","Não expedir sem confirmação","Nenhuma")) -> Nenhuma | O19: =IF(COUNTIF(tbl_recyclass[Familia_PPWR],A19)=0,"(componente)",INDEX({"A","B","C","D","E","F"},_xlfn.MAXIFS(tbl_recyclass[Classe_N_Max],tbl_recyclass[Familia_PPWR],A19))) -> (componente) | P19: =COUNTIFS(tbl_recyclass[Familia_PPWR],A19,tbl_recyclass[Conforme_PPWR_2030],"Não") -> 0 | Q19: =IF(AND(G19="Sim",I19<>"Em falta"),"Conforme","Lacuna") -> Conforme | R19: 46387 | S19: PAM-26-10
A20: FAM-19 | B20: Tampas PETG | C20: Tampa | D20: PETG | E20: =COUNTIF(tbl_recyclass[Familia_PPWR],A20)+COUNTIF(tbl_tampas[Familia_PPWR],A20) -> 4 | F20: Não | G20: Não | I20: Em falta | K20: Não aplicável (sem contacto alimentar) | L20: Não | M20: DEC-03; tinta UV 0,018% m/m (< 0,1%). | N20: =IF(L20="Sim","Art. 33.º + SCIP (+ art. 7.º, n.º 2 se > 1 t/ano)",IF(L20="Por confirmar","Não expedir sem confirmação","Nenhuma")) -> Nenhuma | O20: =IF(COUNTIF(tbl_recyclass[Familia_PPWR],A20)=0,"(componente)",INDEX({"A","B","C","D","E","F"},_xlfn.MAXIFS(tbl_recyclass[Classe_N_Max],tbl_recyclass[Familia_PPWR],A20))) -> (componente) | P20: =COUNTIFS(tbl_recyclass[Familia_PPWR],A20,tbl_recyclass[Conforme_PPWR_2030],"Não") -> 0 | Q20: =IF(AND(G20="Sim",I20<>"Em falta"),"Conforme","Lacuna") -> Lacuna | R20: 46387 | S20: PAM-26-10
A21: FAM-20 | B21: Tampas PP-PG (farmacêuticas) | C21: Tampa | D21: PP-PG | E21: =COUNTIF(tbl_recyclass[Familia_PPWR],A21)+COUNTIF(tbl_tampas[Familia_PPWR],A21) -> 2 | F21: Sim | G21: Sim | H21: 46378 | I21: Em falta | K21: Não aplicável (sem contacto alimentar) | L21: Não | M21: Declarações dos fornecedores do polímero e do masterbatch (RG-SGA-21 tbl_declaracoes). | N21: =IF(L21="Sim","Art. 33.º + SCIP (+ art. 7.º, n.º 2 se > 1 t/ano)",IF(L21="Por confirmar","Não expedir sem confirmação","Nenhuma")) -> Nenhuma | O21: =IF(COUNTIF(tbl_recyclass[Familia_PPWR],A21)=0,"(componente)",INDEX({"A","B","C","D","E","F"},_xlfn.MAXIFS(tbl_recyclass[Classe_N_Max],tbl_recyclass[Familia_PPWR],A21))) -> (componente) | P21: =COUNTIFS(tbl_recyclass[Familia_PPWR],A21,tbl_recyclass[Conforme_PPWR_2030],"Não") -> 0 | Q21: =IF(AND(G21="Sim",I21<>"Em falta"),"Conforme","Lacuna") -> Lacuna | R21: 46387 | S21: PAM-26-10
A22: FAM-21 | B22: Tampas HDPE-FG (alimentares) | C22: Tampa | D22: HDPE-FG | E22: =COUNTIF(tbl_recyclass[Familia_PPWR],A22)+COUNTIF(tbl_tampas[Familia_PPWR],A22) -> 1 | F22: Sim | G22: Sim | H22: 46244 | I22: RM-2026-07 (laboratório acreditado) | J22: 18 | K22: Declaração SUP-010 (07/2026) + flúor total < 50 ppm | L22: Não | M22: Declarações dos fornecedores do polímero e do masterbatch (RG-SGA-21 tbl_declaracoes). | N22: =IF(L22="Sim","Art. 33.º + SCIP (+ art. 7.º, n.º 2 se > 1 t/ano)",IF(L22="Por confirmar","Não expedir sem confirmação","Nenhuma")) -> Nenhuma | O22: =IF(COUNTIF(tbl_recyclass[Familia_PPWR],A22)=0,"(componente)",INDEX({"A","B","C","D","E","F"},_xlfn.MAXIFS(tbl_recyclass[Classe_N_Max],tbl_recyclass[Familia_PPWR],A22))) -> (componente) | P22: =COUNTIFS(tbl_recyclass[Familia_PPWR],A22,tbl_recyclass[Conforme_PPWR_2030],"Não") -> 0 | Q22: =IF(AND(G22="Sim",I22<>"Em falta"),"Conforme","Lacuna") -> Conforme | R22: 46387 | S22: PAM-26-10
A23: FAM-22 | B23: Tampas PP-FG (alimentares) | C23: Tampa | D23: PP-FG | E23: =COUNTIF(tbl_recyclass[Familia_PPWR],A23)+COUNTIF(tbl_tampas[Familia_PPWR],A23) -> 1 | F23: Sim | G23: Sim | H23: 46360 | I23: Declaração do fornecedor | K23: Declaração SUP-010 (07/2026) + flúor total < 50 ppm | L23: Não | M23: Declarações dos fornecedores do polímero e do masterbatch (RG-SGA-21 tbl_declaracoes). | N23: =IF(L23="Sim","Art. 33.º + SCIP (+ art. 7.º, n.º 2 se > 1 t/ano)",IF(L23="Por confirmar","Não expedir sem confirmação","Nenhuma")) -> Nenhuma | O23: =IF(COUNTIF(tbl_recyclass[Familia_PPWR],A23)=0,"(componente)",INDEX({"A","B","C","D","E","F"},_xlfn.MAXIFS(tbl_recyclass[Classe_N_Max],tbl_recyclass[Familia_PPWR],A23))) -> (componente) | P23: =COUNTIFS(tbl_recyclass[Familia_PPWR],A23,tbl_recyclass[Conforme_PPWR_2030],"Não") -> 0 | Q23: =IF(AND(G23="Sim",I23<>"Em falta"),"Conforme","Lacuna") -> Conforme | R23: 46387 | S23: PAM-26-10

Sheet Requisitos_Embalagem
A1: MATRIZ LEGAL E NORMATIVA DE EMBALAGENS — RECICLAGEM, RECICLABILIDADE E SEGURANÇA DOS MATERIAIS
A2: IDs EU-ENV/FCM/COS/PHAR/ISO/PT da matriz proposta (ChatGPT), verificados e completados · Não é parecer jurídico — confirmar artigos na versão consolidada (EUR-Lex/DRE)
A4: ID_Req | B4: Grupo | C4: Fonte | D4: Artigo_Anexo | E4: Tema | F4: Requisito | G4: Natureza_Obrigacao | H4: Papel_Plasticom | I4: Nivel | J4: Ambito_Produtos | K4: Data_Aplicacao | L4: Aplicabilidade | M4: Evidencia_SGA | N4: Metodo_Verificacao | O4: Frequencia | P4: Estado | Q4: Risco | R4: ID_Legal | S4: ID_PAM | T4: Responsavel | U4: Prazo | V4: Verificacao_ChatGPT | W4: Nota_Verificacao | X4: Fonte_Oficial | Y4: Data_Revisao | Z4: N_SKUs_Aplicaveis | AA4: N_SKUs_Conformes | AB4: Alerta
A5: EU-ENV-001 | B5: UE — embalagens | C5: Reg. (UE) 2025/40 (PPWR) | D5: Arts. 1.º–4.º; aplicação geral (art. 71.º) | E5: Âmbito PPWR | F5: Todas as embalagens colocadas no mercado da UE têm de cumprir os requisitos de sustentabilidade, rotulagem e informação do PPWR, aplicável desde 12/08/2026 (aplicação faseada). | G5: Obrigação legal | H5: Fabricante de embalagens e fornecedor a fabricantes de produtos embalados | I5: Empresa | J5: Todos | K5: 46246 | L5: Sim | M5: RG-SGA-04 LEG-09; RG-SGA-20 tbl_recyclass, tbl_familias_ppwr | N5: Análise documental | O5: Semestral | P5: Parcial | Q5: Alto | R5: LEG-09 | S5: PAM-26-10 | T5: Responsável de R&D | U5: 46387 | V5: Confirmado | W5: Data de início de aplicação confirmada (12/08/2026). Papel da Plasticom precisado: fabricante das embalagens vazias que vende em nome próprio. | X5: https://eur-lex.europa.eu/eli/reg/2025/40/oj | Y5: 46287 | Z5: =COUNTIFS(tbl_aplicabilidade[ID_Req],A5,tbl_aplicabilidade[Aplicavel],"Sim") -> 0 | AA5: =COUNTIFS(tbl_aplicabilidade[ID_Req],A5,tbl_aplicabilidade[Estado_Resumo],"Conforme")+COUNTIFS(tbl_aplicabilidade[ID_Req],A5,tbl_aplicabilidade[Estado_Resumo],"Isento") -> 0 | AB5: =IF(AND(OR(P5="Lacuna",P5="Parcial"),S5=""),"Lacuna sem ação",IF(AND(U5<>"",U5<DataRef,P5<>"Conforme"),"Prazo vencido",IF(G5="Necessita verificação","Confirmar aplicabilidade","OK"))) -> OK
A6: EU-ENV-002 | B6: UE — embalagens | C6: Reg. (UE) 2025/40 (PPWR) | D6: Art. 6.º e anexo II (graus de desempenho) | E6: Conceção para reciclagem | F6: A partir de 01/01/2030 só embalagens recicláveis com grau A, B ou C; a partir de 01/01/2038 só A ou B. Critérios de DfR por atos delegados (até 01/01/2028). Isenção até 2035 para embalagem imediata de medicamentos e dispositivos médicos. | G6: Obrigação legal | H6: Fabricante de embalagens | I6: Produto | J6: Todos | K6: 47484 | L6: Futuro | M6: RG-SGA-20 tbl_recyclass (Classe_RecyClass, Grau_PPWR_Indicativo), tbl_regras_dfr | N6: Avaliação técnica por SKU (autoavaliação RecyClass) | O6: Anual e em cada alteração de design | P6: Parcial | Q6: Alto | R6: LEG-09 | S6: PAM-26-22 | T6: Responsável de R&D | U6: 47118 | V6: Complementado | W6: Correto quanto a 2030 (A–C) e 2038 (A–B). Acrescentado: atos delegados de DfR ainda por publicar (grau atual é indicativo), isenção farmacêutica até 2035 e 'reciclado à escala' (EU-ENV-010). | X6: https://eur-lex.europa.eu/eli/reg/2025/40/oj | Y6: 46287 | Z6: =COUNTIFS(tbl_aplicabilidade[ID_Req],A6,tbl_aplicabilidade[Aplicavel],"Sim") -> 113 | AA6: =COUNTIFS(tbl_aplicabilidade[ID_Req],A6,tbl_aplicabilidade[Estado_Resumo],"Conforme")+COUNTIFS(tbl_aplicabilidade[ID_Req],A6,tbl_aplicabilidade[Estado_Resumo],"Isento") -> 77 | AB6: =IF(AND(OR(P6="Lacuna",P6="Parcial"),S6=""),"Lacuna sem ação",IF(AND(U6<>"",U6<DataRef,P6<>"Conforme"),"Prazo vencido",IF(G6="Necessita verificação","Confirmar aplicabilidade","OK"))) -> OK
A7: EU-ENV-003 | B7: UE — embalagens | C7: Reg. (UE) 2025/40 (PPWR) | D7: Art. 7.º (teor mínimo de reciclado) | E7: Conteúdo reciclado | F7: A partir de 01/01/2030, teor mínimo de plástico reciclado pós-consumo por unidade de embalagem (média por instalação de fabrico e por ano): 30% PET sensível ao contacto; 10% outros plásticos sensíveis ao contacto; 30% garrafas de bebidas; 35% outras. Em 2040: 50% / 25% / 65% / 65%. | G7: Obrigação legal | H7: Fabricante de embalagens | I7: Produto | J7: Todos | K7: 47484 | L7: Futuro | M7: RG-SGA-20 tbl_recyclass (Conteudo_Reciclado_Pct, Gap_2030), tbl_metas_art7, tbl_certificados_pcr; RG-SGA-13 PCR_KG | N7: Balanço de massa anual + certificados EN 15343 | O7: Anual | P7: Parcial | Q7: Alto | R7: LEG-09 | S7: PAM-26-25 | T7: Responsável de Compras | U7: 47483 | V7: Complementado | W7: Acrescentadas as metas numéricas 2030/2040, a regra de cálculo por instalação/ano e as isenções (medicamentos, dispositivos médicos, componentes < 5% da massa). Método de cálculo por ato de execução — confirmar publicação. | X7: https://eur-lex.europa.eu/eli/reg/2025/40/oj | Y7: 46287 | Z7: =COUNTIFS(tbl_aplicabilidade[ID_Req],A7,tbl_aplicabilidade[Aplicavel],"Sim") -> 113 | AA7: =COUNTIFS(tbl_aplicabilidade[ID_Req],A7,tbl_aplicabilidade[Estado_Resumo],"Conforme")+COUNTIFS(tbl_aplicabilidade[ID_Req],A7,tbl_aplicabilidade[Estado_Resumo],"Isento") -> 14 | AB7: =IF(AND(OR(P7="Lacuna",P7="Parcial"),S7=""),"Lacuna sem ação",IF(AND(U7<>"",U7<DataRef,P7<>"Conforme"),"Prazo vencido",IF(G7="Necessita verificação","Confirmar aplicabilidade","OK"))) -> OK
A8: EU-ENV-004 | B8: UE — embalagens | C8: Reg. (UE) 2025/40 (PPWR) | D8: Art. 10.º (minimização) | E8: Minimização | F8: A partir de 2030, peso e volume reduzidos ao mínimo necessário para a função; a documentação técnica deve demonstrar a minimização. | G8: Obrigação legal | H8: Fabricante de embalagens (e produtor do produto embalado) | I8: Produto | J8: Todos | K8: 47484 | L8: Futuro | M8: RG-SGA-20 tbl_recyclass (Massa_Corpo_g); RG-SGA-19 tbl_pegada_produto | N8: Análise documental da documentação técnica | O8: Anual | P8: Parcial | Q8: Médio | R8: LEG-09 | S8: PAM-26-10 | T8: Responsável de R&D | U8: 47483 | V8: Confirmado | W8: Massas dos frascos ainda estimadas (escala de volume) — substituir por massas medidas por molde. | X8: https://eur-lex.europa.eu/eli/reg/2025/40/oj | Y8: 46287 | Z8: =COUNTIFS(tbl_aplicabilidade[ID_Req],A8,tbl_aplicabilidade[Aplicavel],"Sim") -> 113 | AA8: =COUNTIFS(tbl_aplicabilidade[ID_Req],A8,tbl_aplicabilidade[Estado_Resumo],"Conforme")+COUNTIFS(tbl_aplicabilidade[ID_Req],A8,tbl_aplicabilidade[Estado_Resumo],"Isento") -> 0 | AB8: =IF(AND(OR(P8="Lacuna",P8="Parcial"),S8=""),"Lacuna sem ação",IF(AND(U8<>"",U8<DataRef,P8<>"Conforme"),"Prazo vencido",IF(G8="Necessita verificação","Confirmar aplicabilidade","OK"))) -> OK
A9: EU-ENV-005 | B9: UE — embalagens | C9: Reg. (UE) 2025/40 (PPWR) | D9: Art. 12.º (rotulagem harmonizada) | E9: Rotulagem | F9: Rótulo harmonizado de composição material a partir de 12/08/2028 (ou 24 meses após o ato de execução); rótulo de conteúdo reciclado facultativo com regras próprias. | G9: Obrigação legal | H9: Produtor do produto embalado (cliente); a Plasticom fornece a informação de material e pode marcar o código no molde (ISO 11469) | I9: Produto | J9: Todos | K9: 46977 | L9: Futuro | M9: RG-SGA-20 tbl_materiais (Codigo_Identificacao); fichas técnicas | N9: Verificação de amostras e fichas técnicas | O9: Anual | P9: Futuro | Q9: Médio | R9: LEG-09 | T9: Responsável de R&D | U9: 46977 | V9: Complementado | W9: Distinguido o responsável (cliente) do contributo da Plasticom (informação e marcação no molde). | X9: https://eur-lex.europa.eu/eli/reg/2025/40/oj | Y9: 46287 | Z9: =COUNTIFS(tbl_aplicabilidade[ID_Req],A9,tbl_aplicabilidade[Aplicavel],"Sim") -> 113 | AA9: =COUNTIFS(tbl_aplicabilidade[ID_Req],A9,tbl_aplicabilidade[Estado_Resumo],"Conforme")+COUNTIFS(tbl_aplicabilidade[ID_Req],A9,tbl_aplicabilidade[Estado_Resumo],"Isento") -> 0 | AB9: =IF(AND(OR(P9="Lacuna",P9="Parcial"),S9=""),"Lacuna sem ação",IF(AND(U9<>"",U9<DataRef,P9<>"Conforme"),"Prazo vencido",IF(G9="Necessita verificação","Confirmar aplicabilidade","OK"))) -> OK
A10: EU-ENV-006 | B10: UE — resíduos | C10: Diretiva 2008/98/CE (quadro dos resíduos), transposta pelo DL 102-D/2020 | D10: Arts. 4.º (hierarquia), 15.º | E10: Resíduos internos | F10: Aplicar a hierarquia dos resíduos, separar, encaminhar para operadores licenciados e registar (MIRR, e-GAR). | G10: Obrigação legal | H10: Produtor de resíduos | I10: Empresa | J10: Empresa | K10: 44175 | L10: Sim | M10: RG-SGA-04 LEG-01, LEG-13; RG-SGA-13 tbl_residuos; RG-SGA-05 KPI-05 | N10: Auditoria / análise documental | O10: Anual | P10: Conforme | Q10: Médio | R10: LEG-01 | T10: Gestor do SGA / EHS (Responsável Ambiental) | V10: Confirmado | W10: Já coberto no SGA (LEG-01, LEG-13). | X10: https://eur-lex.europa.eu/eli/dir/2008/98/oj | Y10: 46287 | Z10: =COUNTIFS(tbl_aplicabilidade[ID_Req],A10,tbl_aplicabilidade[Aplicavel],"Sim") -> 0 | AA10: =COUNTIFS(tbl_aplicabilidade[ID_Req],A10,tbl_aplicabilidade[Estado_Resumo],"Conforme")+COUNTIFS(tbl_aplicabilidade[ID_Req],A10,tbl_aplicabilidade[Estado_Resumo],"Isento") -> 0 | AB10: =IF(AND(OR(P10="Lacuna",P10="Parcial"),S10=""),"Lacuna sem ação",IF(AND(U10<>"",U10<DataRef,P10<>"Conforme"),"Prazo vencido",IF(G10="Necessita verificação","Confirmar aplicabilidade","OK"))) -> OK
A11: EU-ENV-007 | B11: UE — embalagens | C11: Diretiva (UE) 2019/904 (SUP), transposta pelo DL 78/2021 | D11: Arts. 5.º–7.º e anexo (tampas presas, recipientes para alimentos) | E11: Plásticos de utilização única | F11: Recipientes para bebidas até 3 L com tampas de plástico têm de ter tampas presas; recipientes para alimentos de consumo imediato sujeitos a redução de consumo e RAP. | G11: Necessita verificação | H11: Fabricante de embalagens (tampas) — obrigação de colocação no mercado do produtor do produto | I11: Produto | J11: Alimentar | K11: 45476 | L11: Condicional | M11: RG-SGA-20 tbl_aplicabilidade (FA-030/031); confirmação de uso pelos clientes CUST-015/016 | N11: Declaração de utilização do cliente | O11: Por ocorrência | P11: Conforme | Q11: Médio | R11: LEG-19 | S11: PAM-26-26 | T11: Responsável de R&D | U11: 46356 | V11: Complementado | W11: Condicional confirmado. Ponto crítico novo: se os frascos alimentares FA-030/031 forem usados para bebidas, as tampas TA-014 têm de ser presas (tethered). | X11: https://eur-lex.europa.eu/eli/dir/2019/904/oj | Y11: 46287 | Z11: =COUNTIFS(tbl_aplicabilidade[ID_Req],A11,tbl_aplicabilidade[Aplicavel],"Sim") -> 4 | AA11: =COUNTIFS(tbl_aplicabilidade[ID_Req],A11,tbl_aplicabilidade[Estado_Resumo],"Conforme")+COUNTIFS(tbl_aplicabilidade[ID_Req],A11,tbl_aplicabilidade[Estado_Resumo],"Isento") -> 4 | AB11: =IF(AND(OR(P11="Lacuna",P11="Parcial"),S11=""),"Lacuna sem ação",IF(AND(U11<>"",U11<DataRef,P11<>"Conforme"),"Prazo vencido",IF(G11="Necessita verificação","Confirmar aplicabilidade","OK"))) -> Confirmar aplicabilidade
A12: EU-ENV-008 | B12: UE — químicos | C12: Reg. (CE) 1907/2006 (REACH) | D12: Art. 33.º (SVHC em artigos > 0,1%); anexo XVII | E12: Substâncias na cadeia | F12: Comunicar aos clientes SVHC > 0,1% (m/m) nos artigos (art. 33.º); notificar a SCIP e, se > 1 t/ano, a ECHA (art. 7.º, n.º 2); cumprir as restrições do anexo XVII aplicáveis aos artigos. | G12: Obrigação legal | H12: Utilizador a jusante (misturas) e fornecedor de artigos (embalagens) | I12: Empresa | J12: Todos | K12: 39234 | L12: Sim | M12: RG-SGA-20 tbl_familias_ppwr (SVHC_Artigo); RG-SGA-21 tbl_declaracoes | N12: Declarações de fornecedores e cálculo por artigo | O12: Semestral | P12: Parcial | Q12: Médio | R12: LEG-06 | S12: PAM-26-34 | T12: Responsável de Compras | U12: 46387 | V12: Confirmado | W12: Por confirmar: PVC (FAM-14) e tampas PP com aditivo antiestático (FAM-16/17). | X12: https://eur-lex.europa.eu/eli/reg/2006/1907/oj | Y12: 46287 | Z12: =COUNTIFS(tbl_aplicabilidade[ID_Req],A12,tbl_aplicabilidade[Aplicavel],"Sim") -> 0 | AA12: =COUNTIFS(tbl_aplicabilidade[ID_Req],A12,tbl_aplicabilidade[Estado_Resumo],"Conforme")+COUNTIFS(tbl_aplicabilidade[ID_Req],A12,tbl_aplicabilidade[Estado_Resumo],"Isento") -> 0 | AB12: =IF(AND(OR(P12="Lacuna",P12="Parcial"),S12=""),"Lacuna sem ação",IF(AND(U12<>"",U12<DataRef,P12<>"Conforme"),"Prazo vencido",IF(G12="Necessita verificação","Confirmar aplicabilidade","OK"))) -> OK
A13: EU-ENV-009 | B13: UE — químicos | C13: Reg. (CE) 1272/2008 (CLP) | D13: Arts. 17.º e 31.º | E13: Classificação e rotulagem de misturas | F13: Aplica-se às misturas usadas (tintas, solventes, óleos), não às embalagens vendidas. | G13: Obrigação legal | H13: Utilizador a jusante | I13: Empresa | J13: Empresa | K13: 39833 | L13: Sim | M13: RG-SGA-04 LEG-06 (FDS e rotulagem CLP) | N13: Inspeção de rótulos e FDS | O13: Anual | P13: Conforme | Q13: Baixo | R13: LEG-06 | T13: Responsável de Armazém e Logística | V13: Confirmado | W13: Correto: o CLP não equivale à rotulagem das embalagens de consumo. | X13: https://eur-lex.europa.eu/eli/reg/2008/1272/oj | Y13: 46287 | Z13: =COUNTIFS(tbl_aplicabilidade[ID_Req],A13,tbl_aplicabilidade[Aplicavel],"Sim") -> 0 | AA13: =COUNTIFS(tbl_aplicabilidade[ID_Req],A13,tbl_aplicabilidade[Estado_Resumo],"Conforme")+COUNTIFS(tbl_aplicabilidade[ID_Req],A13,tbl_aplicabilidade[Estado_Resumo],"Isento") -> 0 | AB13: =IF(AND(OR(P13="Lacuna",P13="Parcial"),S13=""),"Lacuna sem ação",IF(AND(U13<>"",U13<DataRef,P13<>"Conforme"),"Prazo vencido",IF(G13="Necessita verificação","Confirmar aplicabilidade","OK"))) -> OK
A14: EU-ENV-010 | B14: UE — embalagens | C14: Reg. (UE) 2025/40 (PPWR) | D14: Art. 6.º (reciclado à escala) | E14: Reciclado à escala | F14: A partir de 2035 as embalagens têm também de ser 'recicladas à escala' (recolha, triagem e reciclagem com capacidade na UE, metodologia por ato de execução). | G14: Obrigação legal | H14: Fabricante de embalagens | I14: Produto | J14: Todos | K14: 49310 | L14: Futuro | M14: RG-SGA-20 tbl_recyclass (Fluxo_Reciclagem) | N14: Avaliação técnica | O14: Anual | P14: Futuro | Q14: Médio | R14: LEG-09 | T14: Responsável de R&D | U14: 49309 | V14: Adicionado | W14: Não referido explicitamente na matriz do ChatGPT (apenas 'reciclagem em escala' como evidência). | X14: https://eur-lex.europa.eu/eli/reg/2025/40/oj | Y14: 46287 | Z14: =COUNTIFS(tbl_aplicabilidade[ID_Req],A14,tbl_aplicabilidade[Aplicavel],"Sim") -> 113 | AA14: =COUNTIFS(tbl_aplicabilidade[ID_Req],A14,tbl_aplicabilidade[Estado_Resumo],"Conforme")+COUNTIFS(tbl_aplicabilidade[ID_Req],A14,tbl_aplicabilidade[Estado_Resumo],"Isento") -> 0 | AB14: =IF(AND(OR(P14="Lacuna",P14="Parcial"),S14=""),"Lacuna sem ação",IF(AND(U14<>"",U14<DataRef,P14<>"Conforme"),"Prazo vencido",IF(G14="Necessita verificação","Confirmar aplicabilidade","OK"))) -> OK
A15: EU-ENV-011 | B15: UE — embalagens | C15: Reg. (UE) 2025/40 (PPWR) | D15: Art. 5.º (metais pesados) | E15: Metais pesados | F15: Soma de chumbo, cádmio, mercúrio e crómio hexavalente ≤ 100 mg/kg na embalagem ou nos seus componentes. | G15: Obrigação legal | H15: Fabricante de embalagens | I15: Produto | J15: Todos | K15: 46246 | L15: Sim | M15: RG-SGA-20 tbl_familias_ppwr (Metais_Pesados_Evidencia); relatório RM-2026-07 | N15: Ensaio laboratorial por família / declaração do fornecedor | O15: Anual | P15: Parcial | Q15: Alto | R15: LEG-09 | S15: PAM-26-10 | T15: Gerente da Qualidade | U15: 46387 | V15: Adicionado | W15: A matriz do ChatGPT só fala em 'restrições de substâncias' em geral. | X15: https://eur-lex.europa.eu/eli/reg/2025/40/oj | Y15: 46287 | Z15: =COUNTIFS(tbl_aplicabilidade[ID_Req],A15,tbl_aplicabilidade[Aplicavel],"Sim") -> 113 | AA15: =COUNTIFS(tbl_aplicabilidade[ID_Req],A15,tbl_aplicabilidade[Estado_Resumo],"Conforme")+COUNTIFS(tbl_aplicabilidade[ID_Req],A15,tbl_aplicabilidade[Estado_Resumo],"Isento") -> 74 | AB15: =IF(AND(OR(P15="Lacuna",P15="Parcial"),S15=""),"Lacuna sem ação",IF(AND(U15<>"",U15<DataRef,P15<>"Conforme"),"Prazo vencido",IF(G15="Necessita verificação","Confirmar aplicabilidade","OK"))) -> OK
A16: EU-ENV-012 | B16: UE — embalagens | C16: Reg. (UE) 2025/40 (PPWR) | D16: Art. 5.º, n.º 5 (PFAS em contacto alimentar) | E16: PFAS | F16: Desde 12/08/2026 as embalagens em contacto com alimentos não podem conter PFAS acima de 25 ppb (cada PFAS), 250 ppb (soma) ou 50 ppm (flúor total). | G16: Obrigação legal | H16: Fabricante de embalagens | I16: Produto | J16: Alimentar | K16: 46246 | L16: Sim | M16: Declaração PFAS SUP-010 (07/2026); RG-SGA-21 tbl_declaracoes; RG-SGA-20 tbl_alegacoes ALG-10 | N16: Declaração do fornecedor + ensaio de flúor total | O16: Anual | P16: Conforme | Q16: Alto | R16: LEG-17 | T16: Gerente da Qualidade | V16: Adicionado | W16: Requisito com aplicação imediata não identificado na matriz do ChatGPT. | X16: https://eur-lex.europa.eu/eli/reg/2025/40/oj | Y16: 46287 | Z16: =COUNTIFS(tbl_aplicabilidade[ID_Req],A16,tbl_aplicabilidade[Aplicavel],"Sim") -> 4 | AA16: =COUNTIFS(tbl_aplicabilidade[ID_Req],A16,tbl_aplicabilidade[Estado_Resumo],"Conforme")+COUNTIFS(tbl_aplicabilidade[ID_Req],A16,tbl_aplicabilidade[Estado_Resumo],"Isento") -> 4 | AB16: =IF(AND(OR(P16="Lacuna",P16="Parcial"),S16=""),"Lacuna sem ação",IF(AND(U16<>"",U16<DataRef,P16<>"Conforme"),"Prazo vencido",IF(G16="Necessita verificação","Confirmar aplicabilidade","OK"))) -> OK
A17: EU-ENV-013 | B17: UE — embalagens | C17: Reg. (UE) 2025/40 (PPWR) | D17: Arts. 15.º e 38.º–39.º, anexo VII (confirmar numeração na versão consolidada) | E17: Documentação técnica e declaração UE | F17: Avaliação da conformidade (controlo interno da produção), documentação técnica e declaração UE de conformidade antes da colocação no mercado; conservar 5 anos (10 se reutilizável). | G17: Obrigação legal | H17: Fabricante de embalagens | I17: Produto | J17: Todos | K17: 46246 | L17: Sim | M17: RG-SGA-20 tbl_familias_ppwr (17/22 em 22/12/2026); RG-SGA-05 KPI-12; RG-SGA-04 OBR-12 | N17: Análise documental do dossier | O17: Semestral | P17: Parcial | Q17: Alto | R17: LEG-09 | S17: PAM-26-10 | T17: Responsável de R&D | U17: 46387 | V17: Complementado | W17: O ChatGPT refere 'documentação técnica'; faltava a declaração UE e o prazo de conservação. | X17: https://eur-lex.europa.eu/eli/reg/2025/40/oj | Y17: 46287 | Z17: =COUNTIFS(tbl_aplicabilidade[ID_Req],A17,tbl_aplicabilidade[Aplicavel],"Sim") -> 113 | AA17: =COUNTIFS(tbl_aplicabilidade[ID_Req],A17,tbl_aplicabilidade[Estado_Resumo],"Conforme")+COUNTIFS(tbl_aplicabilidade[ID_Req],A17,tbl_aplicabilidade[Estado_Resumo],"Isento") -> 97 | AB17: =IF(AND(OR(P17="Lacuna",P17="Parcial"),S17=""),"Lacuna sem ação",IF(AND(U17<>"",U17<DataRef,P17<>"Conforme"),"Prazo vencido",IF(G17="Necessita verificação","Confirmar aplicabilidade","OK"))) -> OK
A18: EU-ENV-014 | B18: UE — embalagens | C18: Reg. (UE) 2025/40 (PPWR) | D18: Obrigações de informação na cadeia (fornecedor → fabricante do produto embalado) | E18: Informação ao cliente | F18: Fornecer ao fabricante do produto embalado a informação e documentos necessários para demonstrar a conformidade (material, reciclabilidade, reciclado, substâncias). | G18: Obrigação legal | H18: Fornecedor de embalagens a fabricantes de produtos embalados | I18: Empresa | J18: Todos | K18: 46246 | L18: Sim | M18: RG-SGA-20 Formulario_RecyClass e tbl_recyclass (ficha por SKU) | N18: Amostragem de fichas enviadas aos clientes | O18: Anual | P18: Parcial | Q18: Médio | R18: LEG-09 | S18: PAM-26-10 | T18: Responsável de R&D | U18: 46387 | V18: Adicionado | W18: Os clientes (7 de 9 grandes) já pedem classe de reciclabilidade — DM-11 do RG-SGA-17. | X18: https://eur-lex.europa.eu/eli/reg/2025/40/oj | Y18: 46287 | Z18: =COUNTIFS(tbl_aplicabilidade[ID_Req],A18,tbl_aplicabilidade[Aplicavel],"Sim") -> 0 | AA18: =COUNTIFS(tbl_aplicabilidade[ID_Req],A18,tbl_aplicabilidade[Estado_Resumo],"Conforme")+COUNTIFS(tbl_aplicabilidade[ID_Req],A18,tbl_aplicabilidade[Estado_Resumo],"Isento") -> 0 | AB18: =IF(AND(OR(P18="Lacuna",P18="Parcial"),S18=""),"Lacuna sem ação",IF(AND(U18<>"",U18<DataRef,P18<>"Conforme"),"Prazo vencido",IF(G18="Necessita verificação","Confirmar aplicabilidade","OK"))) -> OK
A19: EU-ENV-015 | B19: UE — embalagens | C19: Reg. (UE) 2025/40 (PPWR) | D19: Art. 29.º (embalagens de transporte reutilizáveis) | E19: Reutilização — expedição | F19: A partir de 2030, paletes, grades e caixas de plástico usadas no transporte entre instalações próprias ou para parceiros no mesmo Estado-Membro têm de ser reutilizáveis (caixas de cartão excluídas). | G19: Necessita verificação | H19: Utilizador de embalagens de transporte (expedição) | I19: Empresa | J19: Expedição | K19: 47484 | L19: Futuro | M19: RG-SGA-20 tbl_emb_expedicao (paletes sem retorno) | N19: Análise documental | O19: Anual | P19: Lacuna | Q19: Médio | R19: LEG-09 | S19: PAM-26-26 | T19: Responsável de Armazém e Logística | U19: 47299 | V19: Adicionado | W19: Paletes de madeira sem retorno nas entregas em Portugal — estudar pool/retorno. | X19: https://eur-lex.europa.eu/eli/reg/2025/40/oj | Y19: 46287 | Z19: =COUNTIFS(tbl_aplicabilidade[ID_Req],A19,tbl_aplicabilidade[Aplicavel],"Sim") -> 0 | AA19: =COUNTIFS(tbl_aplicabilidade[ID_Req],A19,tbl_aplicabilidade[Estado_Resumo],"Conforme")+COUNTIFS(tbl_aplicabilidade[ID_Req],A19,tbl_aplicabilidade[Estado_Resumo],"Isento") -> 0 | AB19: =IF(AND(OR(P19="Lacuna",P19="Parcial"),S19=""),"Lacuna sem ação",IF(AND(U19<>"",U19<DataRef,P19<>"Conforme"),"Prazo vencido",IF(G19="Necessita verificação","Confirmar aplicabilidade","OK"))) -> Confirmar aplicabilidade
A20: EU-ENV-016 | B20: UE — embalagens | C20: Reg. (UE) 2025/40 (PPWR) | D20: Arts. 44.º–45.º (RAP e modulação das prestações) | E20: RAP e ecomodulação | F20: Os produtores (clientes) pagam prestações moduladas pelo grau de reciclabilidade; grau mais baixo = custo maior. | G20: Obrigação legal | H20: Produtor do produto embalado (cliente) — impacto comercial para a Plasticom | I20: Empresa | J20: Todos | K20: 46977 | L20: Futuro | M20: RG-SGA-20 tbl_recyclass (grau por SKU) e tbl_requisitos_pais | N20: Análise documental | O20: Anual | P20: Futuro | Q20: Médio | R20: LEG-16 | T20: Diretor Financeiro | V20: Adicionado | W20: Datas da modulação por grau a confirmar nos atos de execução. | X20: https://eur-lex.europa.eu/eli/reg/2025/40/oj | Y20: 46287 | Z20: =COUNTIFS(tbl_aplicabilidade[ID_Req],A20,tbl_aplicabilidade[Aplicavel],"Sim") -> 0 | AA20: =COUNTIFS(tbl_aplicabilidade[ID_Req],A20,tbl_aplicabilidade[Estado_Resumo],"Conforme")+COUNTIFS(tbl_aplicabilidade[ID_Req],A20,tbl_aplicabilidade[Estado_Resumo],"Isento") -> 0 | AB20: =IF(AND(OR(P20="Lacuna",P20="Parcial"),S20=""),"Lacuna sem ação",IF(AND(U20<>"",U20<DataRef,P20<>"Conforme"),"Prazo vencido",IF(G20="Necessita verificação","Confirmar aplicabilidade","OK"))) -> OK
A21: EU-ENV-017 | B21: UE — embalagens | C21: Diretiva 94/62/CE (embalagens e resíduos de embalagens) | D21: Revogada pelo PPWR (com disposições transitórias) | E21: Regime anterior | F21: Base histórica dos requisitos essenciais e das normas EN 13427–13432; mantém efeitos só nas disposições transitórias. | G21: Necessita verificação | H21: — | I21: Empresa | J21: Nenhum | K21: 34699 | L21: Não | M21: RG-SGA-04 (histórico) | N21: Análise documental | O21: Por ocorrência | P21: Não aplicável | Q21: Baixo | T21: Gestor do SGA / EHS (Responsável Ambiental) | V21: Corrigido | W21: O ChatGPT lista-a como referência; foi substituída pelo PPWR a partir de 12/08/2026 — manter apenas para rastrear disposições transitórias. | X21: https://eur-lex.europa.eu/eli/dir/1994/62/oj | Y21: 46287 | Z21: =COUNTIFS(tbl_aplicabilidade[ID_Req],A21,tbl_aplicabilidade[Aplicavel],"Sim") -> 0 | AA21: =COUNTIFS(tbl_aplicabilidade[ID_Req],A21,tbl_aplicabilidade[Estado_Resumo],"Conforme")+COUNTIFS(tbl_aplicabilidade[ID_Req],A21,tbl_aplicabilidade[Estado_Resumo],"Isento") -> 0 | AB21: =IF(AND(OR(P21="Lacuna",P21="Parcial"),S21=""),"Lacuna sem ação",IF(AND(U21<>"",U21<DataRef,P21<>"Conforme"),"Prazo vencido",IF(G21="Necessita verificação","Confirmar aplicabilidade","OK"))) -> Confirmar aplicabilidade
A22: EU-ENV-018 | B22: UE — consumidores | C22: Diretiva (UE) 2024/825 (capacitação dos consumidores para a transição ecológica) | D22: Alterações à Diretiva 2005/29/CE (anexo I) | E22: Alegações ambientais | F22: A partir de 27/09/2026 são proibidas alegações ambientais genéricas sem desempenho reconhecido e alegações baseadas em compensações; as alegações têm de ser específicas e comprovadas. | G22: Obrigação legal | H22: Autor de comunicações comerciais (site, catálogos, fichas) | I22: Empresa | J22: Todos | K22: 46292 | L22: Sim | M22: PR-SGA-14; RG-SGA-20 tbl_alegacoes | N22: Revisão das comunicações | O22: Semestral | P22: Conforme | Q22: Alto | R22: LEG-18 | S22: PAM-26-27 | T22: Diretor Geral (Gestão de Topo) | U22: 46292 | V22: Adicionado | W22: Na matriz do ChatGPT aparece só como COS-005; tem aplicação transversal e prazo imediato. | X22: https://eur-lex.europa.eu/eli/dir/2024/825/oj | Y22: 46287 | Z22: =COUNTIFS(tbl_aplicabilidade[ID_Req],A22,tbl_aplicabilidade[Aplicavel],"Sim") -> 0 | AA22: =COUNTIFS(tbl_aplicabilidade[ID_Req],A22,tbl_aplicabilidade[Estado_Resumo],"Conforme")+COUNTIFS(tbl_aplicabilidade[ID_Req],A22,tbl_aplicabilidade[Estado_Resumo],"Isento") -> 0 | AB22: =IF(AND(OR(P22="Lacuna",P22="Parcial"),S22=""),"Lacuna sem ação",IF(AND(U22<>"",U22<DataRef,P22<>"Conforme"),"Prazo vencido",IF(G22="Necessita verificação","Confirmar aplicabilidade","OK"))) -> OK
A23: FCM-001 | B23: UE — contacto alimentar | C23: Reg. (CE) 1935/2004 | D23: Arts. 3.º, 16.º, 17.º | E23: Materiais em contacto com alimentos | F23: Materiais inertes nas condições de uso, rastreabilidade e declaração de conformidade. | G23: Obrigação legal | H23: Fabricante de materiais em contacto com alimentos | I23: Produto | J23: Alimentar | K23: 38324 | L23: Sim | M23: RG-SGA-04 LEG-17; dossier FCM dos SKUs FA | N23: Análise documental | O23: Anual | P23: Conforme | Q23: Alto | R23: LEG-17 | T23: Gerente da Qualidade | V23: Confirmado | X23: https://eur-lex.europa.eu/eli/reg/2004/1935/oj | Y23: 46287 | Z23: =COUNTIFS(tbl_aplicabilidade[ID_Req],A23,tbl_aplicabilidade[Aplicavel],"Sim") -> 4 | AA23: =COUNTIFS(tbl_aplicabilidade[ID_Req],A23,tbl_aplicabilidade[Estado_Resumo],"Conforme")+COUNTIFS(tbl_aplicabilidade[ID_Req],A23,tbl_aplicabilidade[Estado_Resumo],"Isento") -> 4 | AB23: =IF(AND(OR(P23="Lacuna",P23="Parcial"),S23=""),"Lacuna sem ação",IF(AND(U23<>"",U23<DataRef,P23<>"Conforme"),"Prazo vencido",IF(G23="Necessita verificação","Confirmar aplicabilidade","OK"))) -> OK
A24: FCM-002 | B24: UE — contacto alimentar | C24: Reg. (CE) 2023/2006 (BPF) | D24: Arts. 5.º–7.º | E24: Boas práticas de fabrico FCM | F24: Sistema de garantia e controlo da qualidade e documentação das BPF. | G24: Obrigação legal | H24: Fabricante de materiais em contacto com alimentos | I24: Produto | J24: Alimentar | K24: 39661 | L24: Sim | M24: Procedimentos de qualidade da linha alimentar | N24: Auditoria interna BPF | O24: Anual | P24: Parcial | Q24: Médio | R24: LEG-17 | T24: Gerente da Qualidade | U24: 46477 | V24: Confirmado | W24: Falta auditoria interna específica de BPF (2023/2006). | X24: https://eur-lex.europa.eu/eli/reg/2006/2023/oj | Y24: 46287 | Z24: =COUNTIFS(tbl_aplicabilidade[ID_Req],A24,tbl_aplicabilidade[Aplicavel],"Sim") -> 4 | AA24: =COUNTIFS(tbl_aplicabilidade[ID_Req],A24,tbl_aplicabilidade[Estado_Resumo],"Conforme")+COUNTIFS(tbl_aplicabilidade[ID_Req],A24,tbl_aplicabilidade[Estado_Resumo],"Isento") -> 0 | AB24: =IF(AND(OR(P24="Lacuna",P24="Parcial"),S24=""),"Lacuna sem ação",IF(AND(U24<>"",U24<DataRef,P24<>"Conforme"),"Prazo vencido",IF(G24="Necessita verificação","Confirmar aplicabilidade","OK"))) -> Lacuna sem ação
A25: FCM-006 | B25: UE — contacto alimentar | C25: Reg. (UE) 2024/3190 | D25: Arts. 3.º–5.º | E25: Bisfenol A e bisfenóis perigosos | F25: Proibição de BPA e de outros bisfenóis perigosos em materiais e objetos em contacto com alimentos (incl. vernizes e tintas), com períodos de transição. | G25: Obrigação legal | H25: Fabricante de materiais plásticos em contacto com alimentos | I25: Produto | J25: Alimentar | K25: 45677 | L25: Sim | M25: RG-SGA-21 tbl_declaracoes (BPA = Não em todos os polímeros FCM) | N25: Declaração do fornecedor | O25: Anual | P25: Conforme | Q25: Médio | R25: LEG-17 | T25: Gerente da Qualidade | V25: Adicionado | W25: Antes estava só na matriz de químicos (RG-SGA-21); é requisito de produto. | X25: https://eur-lex.europa.eu/eli/reg/2024/3190/oj | Y25: 46287 | Z25: =COUNTIFS(tbl_aplicabilidade[ID_Req],A25,tbl_aplicabilidade[Aplicavel],"Sim") -> 4 | AA25: =COUNTIFS(tbl_aplicabilidade[ID_Req],A25,tbl_aplicabilidade[Estado_Resumo],"Conforme")+COUNTIFS(tbl_aplicabilidade[ID_Req],A25,tbl_aplicabilidade[Estado_Resumo],"Isento") -> 4 | AB25: =IF(AND(OR(P25="Lacuna",P25="Parcial"),S25=""),"Lacuna sem ação",IF(AND(U25<>"",U25<DataRef,P25<>"Conforme"),"Prazo vencido",IF(G25="Necessita verificação","Confirmar aplicabilidade","OK"))) -> OK
A26: FCM-003 | B26: UE — contacto alimentar | C26: Reg. (UE) 10/2011 | D26: Arts. 11.º–12.º, 15.º, anexo IV | E26: Plásticos em contacto com alimentos | F26: Lista da União de substâncias, limites de migração global e específica e declaração de conformidade (anexo IV). | G26: Obrigação legal | H26: Fabricante de materiais plásticos em contacto com alimentos | I26: Produto | J26: Alimentar | K26: 40664 | L26: Sim | M26: Ensaios de migração 2026-03 (HDPE-FG, PP-FG); DoC anexo IV | N26: Ensaio + análise documental | O26: Por ocorrência (alteração de material) | P26: Conforme | Q26: Alto | R26: LEG-17 | T26: Gerente da Qualidade | V26: Confirmado | X26: https://eur-lex.europa.eu/eli/reg/2011/10/oj | Y26: 46287 | Z26: =COUNTIFS(tbl_aplicabilidade[ID_Req],A26,tbl_aplicabilidade[Aplicavel],"Sim") -> 4 | AA26: =COUNTIFS(tbl_aplicabilidade[ID_Req],A26,tbl_aplicabilidade[Estado_Resumo],"Conforme")+COUNTIFS(tbl_aplicabilidade[ID_Req],A26,tbl_aplicabilidade[Estado_Resumo],"Isento") -> 4 | AB26: =IF(AND(OR(P26="Lacuna",P26="Parcial"),S26=""),"Lacuna sem ação",IF(AND(U26<>"",U26<DataRef,P26<>"Conforme"),"Prazo vencido",IF(G26="Necessita verificação","Confirmar aplicabilidade","OK"))) -> OK
A27: FCM-004 | B27: UE — contacto alimentar | C27: Reg. (UE) 2022/1616 (plásticos reciclados em contacto com alimentos) | D27: Arts. 4.º–6.º | E27: Reciclado em contacto alimentar | F27: Plástico reciclado só de processos com tecnologia adequada/autorizada. Hoje sem reciclado nos SKUs alimentares; condiciona a meta de 10% do PPWR para PE/PP alimentar. | G27: Obrigação legal | H27: Fabricante de materiais em contacto com alimentos | I27: Material | J27: Alimentar | K27: 44844 | L27: Condicional | M27: RG-SGA-20 tbl_certificados_pcr (CERT-04, reciclado químico em avaliação) | N27: Análise documental | O27: Por ocorrência | P27: Não aplicável | Q27: Médio | R27: LEG-17 | S27: PAM-26-25 | T27: Gerente da Qualidade | U27: 47483 | V27: Complementado | W27: Acrescentada a ligação à meta de 10% (art. 7.º do PPWR) para PE/PP alimentar. | X27: https://eur-lex.europa.eu/eli/reg/2022/1616/oj | Y27: 46287 | Z27: =COUNTIFS(tbl_aplicabilidade[ID_Req],A27,tbl_aplicabilidade[Aplicavel],"Sim") -> 0 | AA27: =COUNTIFS(tbl_aplicabilidade[ID_Req],A27,tbl_aplicabilidade[Estado_Resumo],"Conforme")+COUNTIFS(tbl_aplicabilidade[ID_Req],A27,tbl_aplicabilidade[Estado_Resumo],"Isento") -> 0 | AB27: =IF(AND(OR(P27="Lacuna",P27="Parcial"),S27=""),"Lacuna sem ação",IF(AND(U27<>"",U27<DataRef,P27<>"Conforme"),"Prazo vencido",IF(G27="Necessita verificação","Confirmar aplicabilidade","OK"))) -> OK
A28: FCM-005 | B28: UE — contacto alimentar | C28: Reg. (UE) 2025/40 (PPWR) × segurança alimentar | D28: Arts. 5.º e 7.º | E28: Interação segurança × ambiente | F28: Avaliar em conjunto PFAS, reciclado e reciclabilidade nas embalagens alimentares. | G28: Obrigação legal | H28: Fabricante de embalagens | I28: Empresa | J28: Alimentar | K28: 46246 | L28: Sim | M28: EU-ENV-012 e FCM-004 | N28: Análise documental | O28: Anual | P28: Conforme | Q28: Médio | R28: LEG-17 | T28: Gerente da Qualidade | V28: Confirmado | W28: Operacionalizado em EU-ENV-012 (PFAS) e FCM-004. | X28: https://eur-lex.europa.eu/eli/reg/2025/40/oj | Y28: 46287 | Z28: =COUNTIFS(tbl_aplicabilidade[ID_Req],A28,tbl_aplicabilidade[Aplicavel],"Sim") -> 0 | AA28: =COUNTIFS(tbl_aplicabilidade[ID_Req],A28,tbl_aplicabilidade[Estado_Resumo],"Conforme")+COUNTIFS(tbl_aplicabilidade[ID_Req],A28,tbl_aplicabilidade[Estado_Resumo],"Isento") -> 0 | AB28: =IF(AND(OR(P28="Lacuna",P28="Parcial"),S28=""),"Lacuna sem ação",IF(AND(U28<>"",U28<DataRef,P28<>"Conforme"),"Prazo vencido",IF(G28="Necessita verificação","Confirmar aplicabilidade","OK"))) -> OK
A29: COS-001 | B29: UE — cosméticos | C29: Reg. (CE) 1223/2009 | D29: Art. 3.º; anexo I (relatório de segurança) | E29: Segurança do produto cosmético | F29: A pessoa responsável (cliente) avalia a segurança incluindo o material de embalagem; a Plasticom fornece especificações e composição. | G29: Requisito contratual | H29: Fornecedor de embalagem primária | I29: Produto | J29: Cosmética | K29: 41466 | L29: Sim | M29: Especificações aprovadas e acordos de qualidade com clientes | N29: Análise documental | O29: Anual | P29: Conforme | Q29: Médio | R29: LEG-20 | T29: Gerente da Qualidade | V29: Confirmado | X29: https://eur-lex.europa.eu/eli/reg/2009/1223/oj | Y29: 46287 | Z29: =COUNTIFS(tbl_aplicabilidade[ID_Req],A29,tbl_aplicabilidade[Aplicavel],"Sim") -> 103 | AA29: =COUNTIFS(tbl_aplicabilidade[ID_Req],A29,tbl_aplicabilidade[Estado_Resumo],"Conforme")+COUNTIFS(tbl_aplicabilidade[ID_Req],A29,tbl_aplicabilidade[Estado_Resumo],"Isento") -> 103 | AB29: =IF(AND(OR(P29="Lacuna",P29="Parcial"),S29=""),"Lacuna sem ação",IF(AND(U29<>"",U29<DataRef,P29<>"Conforme"),"Prazo vencido",IF(G29="Necessita verificação","Confirmar aplicabilidade","OK"))) -> OK
A30: COS-002 | B30: UE — cosméticos | C30: Reg. (CE) 1223/2009 | D30: Anexo I, parte A, ponto 4 (material de embalagem) | E30: Materiais e impurezas | F30: Informação sobre o material de embalagem e possíveis migrações/impurezas para o relatório de segurança do cliente. | G30: Requisito contratual | H30: Fornecedor de embalagem primária | I30: Produto | J30: Cosmética | K30: 41466 | L30: Sim | M30: Declarações de composição por SKU (ficha RecyClass) | N30: Análise documental | O30: Anual | P30: Parcial | Q30: Médio | R30: LEG-20 | T30: Gerente da Qualidade | U30: 46387 | V30: Confirmado | W30: Declarações de composição ainda não enviadas a todos os clientes. | X30: https://eur-lex.europa.eu/eli/reg/2009/1223/oj | Y30: 46287 | Z30: =COUNTIFS(tbl_aplicabilidade[ID_Req],A30,tbl_aplicabilidade[Aplicavel],"Sim") -> 103 | AA30: =COUNTIFS(tbl_aplicabilidade[ID_Req],A30,tbl_aplicabilidade[Estado_Resumo],"Conforme")+COUNTIFS(tbl_aplicabilidade[ID_Req],A30,tbl_aplicabilidade[Estado_Resumo],"Isento") -> 0 | AB30: =IF(AND(OR(P30="Lacuna",P30="Parcial"),S30=""),"Lacuna sem ação",IF(AND(U30<>"",U30<DataRef,P30<>"Conforme"),"Prazo vencido",IF(G30="Necessita verificação","Confirmar aplicabilidade","OK"))) -> Lacuna sem ação
A31: COS-003 | B31: UE — cosméticos | C31: EN ISO 22716:2007 (BPF de cosméticos) | D31: Norma harmonizada | E31: Boas práticas de fabrico | F31: Aplica-se ao fabrico do cosmético; para a Plasticom só por exigência contratual. | G31: Norma técnica de suporte | H31: Fornecedor (só se contratado) | I31: Empresa | J31: Cosmética | K31: 39401 | L31: Condicional | M31: Acordos de qualidade | N31: Auditoria de cliente | O31: Por ocorrência | P31: Conforme | Q31: Baixo | R31: LEG-20 | T31: Gerente da Qualidade | V31: Confirmado | X31: https://single-market-economy.ec.europa.eu/sectors/cosmetics_en | Y31: 46287 | Z31: =COUNTIFS(tbl_aplicabilidade[ID_Req],A31,tbl_aplicabilidade[Aplicavel],"Sim") -> 0 | AA31: =COUNTIFS(tbl_aplicabilidade[ID_Req],A31,tbl_aplicabilidade[Estado_Resumo],"Conforme")+COUNTIFS(tbl_aplicabilidade[ID_Req],A31,tbl_aplicabilidade[Estado_Resumo],"Isento") -> 0 | AB31: =IF(AND(OR(P31="Lacuna",P31="Parcial"),S31=""),"Lacuna sem ação",IF(AND(U31<>"",U31<DataRef,P31<>"Conforme"),"Prazo vencido",IF(G31="Necessita verificação","Confirmar aplicabilidade","OK"))) -> OK
A32: COS-004 | B32: UE — cosméticos | C32: Reg. (CE) 1223/2009 / requisitos do cliente | D32: — | E32: Compatibilidade embalagem–produto | F32: Ensaios de compatibilidade e estabilidade feitos pelo cliente com especificação da Plasticom. | G32: Requisito contratual | H32: Fornecedor de embalagem primária | I32: Produto | J32: Cosmética | K32: 41466 | L32: Sim | M32: Fichas técnicas e amostras aprovadas | N32: Análise documental | O32: Por ocorrência | P32: Conforme | Q32: Médio | R32: LEG-20 | T32: Gerente da Qualidade | V32: Confirmado | Y32: 46287 | Z32: =COUNTIFS(tbl_aplicabilidade[ID_Req],A32,tbl_aplicabilidade[Aplicavel],"Sim") -> 103 | AA32: =COUNTIFS(tbl_aplicabilidade[ID_Req],A32,tbl_aplicabilidade[Estado_Resumo],"Conforme")+COUNTIFS(tbl_aplicabilidade[ID_Req],A32,tbl_aplicabilidade[Estado_Resumo],"Isento") -> 103 | AB32: =IF(AND(OR(P32="Lacuna",P32="Parcial"),S32=""),"Lacuna sem ação",IF(AND(U32<>"",U32<DataRef,P32<>"Conforme"),"Prazo vencido",IF(G32="Necessita verificação","Confirmar aplicabilidade","OK"))) -> OK
