Workbook
Name DataRef: Listas!$A$3
Name lst_Categoria: Listas!$D$3:$D$11
Name lst_Condicao: Listas!$F$3:$F$5
Name lst_DataReferencia: Listas!$A$3:$A$3
Name lst_F15: Listas!$I$3:$I$7
Name lst_Fase: Listas!$C$3:$C$8
Name lst_G: Listas!$K$3:$K$9
Name lst_Impacte: Listas!$H$3:$H$14
Name lst_L: Listas!$L$3:$L$4
Name lst_M15: Listas!$J$3:$J$7
Name lst_Processo: Listas!$B$3:$B$18
Name lst_SimNao: Listas!$M$3:$M$4
Name lst_Temporalidade: Listas!$G$3:$G$5
Name lst_TipoAspeto: Listas!$E$3:$E$4

Sheet 00_LEIA-ME
A1: RG-SGA-03 — Matriz de Identificação e Avaliação de Aspetos e Impactes Ambientais (Mod.G.07.00)
A2: Sistema de Gestão Ambiental NP EN ISO 14001:2026 · Plasticom — Unidade 1 (Marinha Grande, Portugal) · Registo do SGA (fábrica simulada)
A4: CONTROLO DO DOCUMENTO (7.5 — informação documentada)
A5: Código do registo | B5: RG-SGA-03
A6: Título | B6: Matriz de Identificação e Avaliação de Aspetos e Impactes Ambientais (Mod.G.07.00)
A7: Versão / Revisão | B7: 01
A8: Data de emissão | B8: 46387
A9: Elaborado por | B9: Gestor(a) do SGA / EHS
A10: Aprovado por | B10: Diretor Geral
A11: Estado | B11: Em vigor
A12: Retenção | B12: 5 anos após substituição
A13: Localização | B13: Repositório controlado do SGA > Registos_SGA_Plasticom (versão eletrónica é a versão controlada; cópias impressas são não controladas)
A15: FINALIDADE E ÂMBITO
A16: Finalidade | B16: Identificar, para todas as atividades da Plasticom e em todas as fases do ciclo de vida, os aspetos ambientais (causa) e os impactes (efeito), e avaliar a significância pelo IRA = (F + M) × G × L segundo o PR.G.01.01. Ponto de partida: folha 03_Aspectos_Impactes do Plasticom_SGA_ISO14001_2026_ESG_com_Dupla_Materialidade.xlsx, revista e alargada.
A17: Atividades do curso | B17: Atividade 3.2 — Identificação e Avaliação de Aspetos e Impactes Ambientais (aspetos selecionados: AA-005 e AA-014).
A18: Requisitos ISO 14001:2026 | B18: 6.1.2 Aspetos ambientais (perspetiva de ciclo de vida; situações de emergência distinguidas das anormais — ISO 14001:2026); 6.1.5; 8.1; 8.2
A20: ESTRUTURA DO FICHEIRO
A21: Impactes | B21: Catálogo de impactes ambientais (dimensão).
A22: Aspetos_Impactes | B22: Registo de aspetos e impactes (1 linha por aspeto) com avaliação IRA e gestão.
A23: Aspeto_Impacte | B23: Relação N:N aspeto × impacte (formato longo, para análise e para os 'X' da matriz Mod.G.07.00).
A24: Mod.G.07.00_Matriz | B24: Matriz no formato do modelo do curso (Mod.G.07.00), com 'X' calculados a partir das tabelas. Para impressão; editar em Aspetos_Impactes.
A25: Resumo_Atividade_3_2 | B25: Ficha dos 2 aspetos selecionados para a Atividade 3.2 (campos do enunciado, calculados).
A26: Analise | B26: Distribuição dos aspetos por classificação, processo, condição e fase (calculado).
A27: Criterios | B27: Critérios F, M, G, L e tabela de significância (PR.G.01.01).
A28: Listas | B28: Domínios (listas de valores) usados na validação de dados das tabelas.
A29: Dicionario_Dados | B29: Descrição de cada coluna de cada tabela: tipo, origem (entrada/calculado), domínio, obrigatoriedade e chaves.
A31: CONVENÇÕES (prontas para análise de dados e machine learning)
A32: Tabelas | B32: Cada registo é uma Tabela Excel com nome próprio (tbl_*): uma linha = um registo, cabeçalho único, sem células mescladas. Ler com pandas (pd.read_excel(ficheiro, sheet_name=folha, header=<linha do cabeçalho - 1>)) ou Power BI (Obter Dados > Tabela).
A33: Cabeçalho cinzento | B33: Coluna CALCULADA por fórmula — não escrever por cima. As restantes colunas são de entrada.
A34: Validação | B34: Colunas com lista controlada só aceitam valores da folha Listas (evita categorias duplicadas por grafia diferente).
A35: Chaves | B35: IDs estáveis e únicos (PK) e referências a IDs de outros registos (FK) permitem juntar tabelas entre ficheiros — ver SGA-00_Indice_Modelo_Dados.xlsx.
A36: Datas e unidades | B36: Datas em formato data (aaaa-mm-dd); números como números; a unidade está no nome da coluna ou no dicionário. Data de referência do SGA: 2026-12-31 (fecho do ano).
A37: Dados simulados | B37: Fábrica simulada Plasticom. Dados operacionais derivados do dataset do projeto (datasets/silver); dados ambientais e de conformidade são simulação didática — confirmar aplicabilidade legal e números antes de uso real.
A39: LIGAÇÕES A OUTROS REGISTOS
A40: RG-SGA-04 Requisitos legais | B40: ID_Legal liga o aspeto à obrigação de conformidade.
A41: RG-SGA-05 Objetivos | B41: ID_Objetivo liga aspetos significativos a objetivos.
A42: RG-SGA-06 PAM | B42: ID_PAM liga a ação de controlo/melhoria.
A43: RG-SGA-13 Monitorização | B43: ID_Monitorizacao liga ao plano de medição (MED-xx). Quantidade_Anual vem dos dados de monitorização ano civil de 2026.

Sheet Impactes
A1: ID_Impacte | B1: Impacte | C1: Natureza | D1: N_Aspetos | E1: N_AAS
A2: IMP-01 | B2: Esgotamento de Recursos Naturais / Recursos | C2: Adverso | D2: =COUNTIF(tbl_aspeto_impacte[ID_Impacte],A2) -> 17 | E2: =COUNTIFS(tbl_aspeto_impacte[ID_Impacte],A2,tbl_aspeto_impacte[Classificacao],"ASPETO*") -> 1
A3: IMP-02 | B3: Contaminação do Solo e/ou Recursos Hídricos | C3: Adverso | D3: =COUNTIF(tbl_aspeto_impacte[ID_Impacte],A3) -> 13 | E3: =COUNTIFS(tbl_aspeto_impacte[ID_Impacte],A3,tbl_aspeto_impacte[Classificacao],"ASPETO*") -> 0
A4: IMP-03 | B4: Poluição do Ar | C4: Adverso | D4: =COUNTIF(tbl_aspeto_impacte[ID_Impacte],A4) -> 8 | E4: =COUNTIFS(tbl_aspeto_impacte[ID_Impacte],A4,tbl_aspeto_impacte[Classificacao],"ASPETO*") -> 1
A5: IMP-04 | B5: Mudanças Climáticas | C5: Adverso | D5: =COUNTIF(tbl_aspeto_impacte[ID_Impacte],A5) -> 13 | E5: =COUNTIFS(tbl_aspeto_impacte[ID_Impacte],A5,tbl_aspeto_impacte[Classificacao],"ASPETO*") -> 2
A6: IMP-05 | B6: Incomodidade da Vizinhança | C6: Adverso | D6: =COUNTIF(tbl_aspeto_impacte[ID_Impacte],A6) -> 2 | E6: =COUNTIFS(tbl_aspeto_impacte[ID_Impacte],A6,tbl_aspeto_impacte[Classificacao],"ASPETO*") -> 1
A7: IMP-06 | B7: Perturbação da Fauna / Flora / Paisagem | C7: Adverso | D7: =COUNTIF(tbl_aspeto_impacte[ID_Impacte],A7) -> 4 | E7: =COUNTIFS(tbl_aspeto_impacte[ID_Impacte],A7,tbl_aspeto_impacte[Classificacao],"ASPETO*") -> 0
A8: IMP-07 | B8: Redução da vida útil de aterros e passivos ambientais | C8: Adverso | D8: =COUNTIF(tbl_aspeto_impacte[ID_Impacte],A8) -> 14 | E8: =COUNTIFS(tbl_aspeto_impacte[ID_Impacte],A8,tbl_aspeto_impacte[Classificacao],"ASPETO*") -> 1
A9: IMP-08 | B9: Degradação da saúde dos ecossistemas aquáticos (microplásticos) | C9: Adverso | D9: =COUNTIF(tbl_aspeto_impacte[ID_Impacte],A9) -> 2 | E9: =COUNTIFS(tbl_aspeto_impacte[ID_Impacte],A9,tbl_aspeto_impacte[Classificacao],"ASPETO*") -> 0
A10: IMP-09 | B10: Promoção da Eficiência Hídrica e Circularidade (valorização interna de resíduos/águas) | C10: Benéfico | D10: =COUNTIF(tbl_aspeto_impacte[ID_Impacte],A10) -> 1 | E10: =COUNTIFS(tbl_aspeto_impacte[ID_Impacte],A10,tbl_aspeto_impacte[Classificacao],"ASPETO*") -> 0
A11: IMP-10 | B11: Otimização do Consumo de Matérias-Primas (poupança ou geração de novos recursos) | C11: Benéfico | D11: =COUNTIF(tbl_aspeto_impacte[ID_Impacte],A11) -> 2 | E11: =COUNTIFS(tbl_aspeto_impacte[ID_Impacte],A11,tbl_aspeto_impacte[Classificacao],"ASPETO*") -> 0
A12: IMP-11 | B12: Extensão do ciclo de vida de materiais (conversão de resíduos em subprodutos) | C12: Benéfico | D12: =COUNTIF(tbl_aspeto_impacte[ID_Impacte],A12) -> 2 | E12: =COUNTIFS(tbl_aspeto_impacte[ID_Impacte],A12,tbl_aspeto_impacte[Classificacao],"ASPETO*") -> 0
A13: IMP-12 | B13: Minimização da Pressão Ecológica (materiais recicláveis ou de origem sustentável) | C13: Benéfico | D13: =COUNTIF(tbl_aspeto_impacte[ID_Impacte],A13) -> 3 | E13: =COUNTIFS(tbl_aspeto_impacte[ID_Impacte],A13,tbl_aspeto_impacte[Classificacao],"ASPETO*") -> 1

Sheet Aspetos_Impactes
A1: MATRIZ DE AVALIAÇÃO DE ASPETOS E IMPACTES AMBIENTAIS — PLASTICOM (registo de dados)
A2: IRA = (F + M) × G × L · AAS se IRA ≥ 40 ou L = 2 · Moderado 20-39 · Não significativo 0-19 · Oportunidade tática -1 a -14 · AAS benéfico ≤ -15 · Filtrar Selecionado_Atv_3_2 = Sim
A4: ID_Aspeto | B4: Processo | C4: Area_Atividade | D4: Atividade | E4: Fase_Ciclo_Vida | F4: Categoria_Aspeto | G4: Descricao_Aspeto | H4: Tipo_Aspeto | I4: Condicao_Operacao | J4: Temporalidade | K4: ID_Impacte_Principal | L4: Impacte_Principal | M4: IDs_Impactes_Secundarios | N4: F | O4: M | P4: G | Q4: L | R4: Tipo_Efeito | S4: IRA | T4: Classificacao | U4: Motivo_Classificacao | V4: Ranking_IRA | W4: Acao_Plano_Melhoria | X4: Medidas_Controlo_Acao | Y4: Controlo_Existente | Z4: Quantidade_Anual | AA4: Unidade_Quantidade | AB4: Fonte_Dado | AC4: Justificacao_Criterios | AD4: ID_Legal | AE4: ID_RO | AF4: ID_Objetivo | AG4: ID_PAM | AH4: ID_Monitorizacao | AI4: Verificacao_Gestao | AJ4: Selecionado_Atv_3_2 | AK4: Data_Avaliacao | AL4: Proxima_Revisao | AM4: Avaliador
A5: AA-001 | B5: CMP | C5: Compras e fornecedores | D5: Aquisição de polímeros (PP, HDPE, PET) | E5: Aquisição | F5: Consumo de recursos | G5: Consumo de polímeros virgens de origem fóssil | H5: Indireto | I5: Normal | J5: Presente | K5: IMP-01 | L5: =IFERROR(INDEX(tbl_impactes[Impacte],MATCH(K5,tbl_impactes[ID_Impacte],0)),"") -> Esgotamento de Recursos Naturais / Recursos | M5: IMP-04 | N5: 5 | O5: 5 | P5: 2 | Q5: 1 | R5: =IF(P5="","",IF(P5<0,"(-) Benéfico","(+) Adverso")) -> (+) Adverso | S5: =IF(COUNT(N5,O5,P5,Q5)<4,"",(N5+O5)*P5*Q5) -> 20 | T5: =IF(S5="","",IF(OR(Q5=2,S5>=40),"ASPETO AMBIENTAL SIGNIFICATIVO (AAS)",IF(S5>=20,"Moderado",IF(S5>=0,"Não Significativo",IF(S5>=-14,"Oportunidade Tática","ASPETO AMBIENTAL SIGNIFICATIVO (AAS) BENÉFICO"))))) -> Moderado | U5: =IF(S5="","",IF(Q5=2,"Regra de ouro (L=2)",IF(S5>=40,"IRA ≥ 40",IF(S5>=20,"IRA 20-39",IF(S5>=0,"IRA 0-19",IF(S5>=-14,"IRA -1 a -14","IRA ≤ -15")))))) -> IRA 20-39 | V5: =IF(S5="","",RANK(S5,$S$5:$S$47,0)) -> 24 | W5: =IF(T5="","",IF(OR(T5="ASPETO AMBIENTAL SIGNIFICATIVO (AAS)",T5="Moderado"),"SIM","NÃO")) -> SIM | X5: Critérios de compra com conteúdo reciclado certificado; lightweighting. | Y5: Especificação técnica de compra. | Z5: 782.9 | AA5: t/ano | AB5: Inventário de matérias-primas (12 meses) | AC5: F5 contínuo; M5 maior fluxo de matéria da fábrica; G2 material inerte mas não renovável. | AE5: RO-05 | AF5: OBJ-02 | AG5: PAM-26-16 | AH5: MED-05 | AI5: =IF(W5="SIM",IF(X5="","FALTA medida de controlo",IF(AND(LEFT(T5,6)="ASPETO",Q5=2,AG5=""),"FALTA ação corretiva (L=2)",IF(AND(LEFT(T5,6)="ASPETO",AH5=""),"Sugestão: definir monitorização","OK"))),"OK") -> OK | AJ5: Não | AK5: 46162 | AL5: =IF(AK5="","",EDATE(AK5,12)) -> 46527 | AM5: Gestor do SGA + responsável do setor
A6: AA-002 | B6: CMP | C6: Compras e fornecedores | D6: Transporte de matérias-primas pelos fornecedores | E6: Aquisição | F6: Emissões atmosféricas | G6: Emissões de gases de escape (CO2, NOx, partículas) no transporte rodoviário e marítimo de resinas | H6: Indireto | I6: Normal | J6: Presente | K6: IMP-04 | L6: =IFERROR(INDEX(tbl_impactes[Impacte],MATCH(K6,tbl_impactes[ID_Impacte],0)),"") -> Mudanças Climáticas | M6: IMP-03 | N6: 4 | O6: 4 | P6: 3 | Q6: 1 | R6: =IF(P6="","",IF(P6<0,"(-) Benéfico","(+) Adverso")) -> (+) Adverso | S6: =IF(COUNT(N6,O6,P6,Q6)<4,"",(N6+O6)*P6*Q6) -> 24 | T6: =IF(S6="","",IF(OR(Q6=2,S6>=40),"ASPETO AMBIENTAL SIGNIFICATIVO (AAS)",IF(S6>=20,"Moderado",IF(S6>=0,"Não Significativo",IF(S6>=-14,"Oportunidade Tática","ASPETO AMBIENTAL SIGNIFICATIVO (AAS) BENÉFICO"))))) -> Moderado | U6: =IF(S6="","",IF(Q6=2,"Regra de ouro (L=2)",IF(S6>=40,"IRA ≥ 40",IF(S6>=20,"IRA 20-39",IF(S6>=0,"IRA 0-19",IF(S6>=-14,"IRA -1 a -14","IRA ≤ -15")))))) -> IRA 20-39 | V6: =IF(S6="","",RANK(S6,$S$5:$S$47,0)) -> 18 | W6: =IF(T6="","",IF(OR(T6="ASPETO AMBIENTAL SIGNIFICATIVO (AAS)",T6="Moderado"),"SIM","NÃO")) -> SIM | X6: Preferir fornecedores ibéricos e cargas completas. | Y6: — | AB6: Guias de remessa; origem dos fornecedores | AC6: F4 entregas diárias; M4 ≈ 810 t/ano transportadas; G3 poluente convencional. | AI6: =IF(W6="SIM",IF(X6="","FALTA medida de controlo",IF(AND(LEFT(T6,6)="ASPETO",Q6=2,AG6=""),"FALTA ação corretiva (L=2)",IF(AND(LEFT(T6,6)="ASPETO",AH6=""),"Sugestão: definir monitorização","OK"))),"OK") -> OK | AJ6: Não | AK6: 46162 | AL6: =IF(AK6="","",EDATE(AK6,12)) -> 46527 | AM6: Gestor do SGA + responsável do setor
A7: AA-003 | B7: REC | C7: Receção e silos | D7: Descarga de big bags e transferência pneumática para silos | E7: Produção | F7: Perdas de granulado | G7: Perda de granulado de plástico para o pavimento e a rede de águas pluviais | H7: Direto | I7: Normal | J7: Presente | K7: IMP-08 | L7: =IFERROR(INDEX(tbl_impactes[Impacte],MATCH(K7,tbl_impactes[ID_Impacte],0)),"") -> Degradação da saúde dos ecossistemas aquáticos (microplásticos) | M7: IMP-02; IMP-06 | N7: 4 | O7: 3 | P7: 4 | Q7: 1 | R7: =IF(P7="","",IF(P7<0,"(-) Benéfico","(+) Adverso")) -> (+) Adverso | S7: =IF(COUNT(N7,O7,P7,Q7)<4,"",(N7+O7)*P7*Q7) -> 28 | T7: =IF(S7="","",IF(OR(Q7=2,S7>=40),"ASPETO AMBIENTAL SIGNIFICATIVO (AAS)",IF(S7>=20,"Moderado",IF(S7>=0,"Não Significativo",IF(S7>=-14,"Oportunidade Tática","ASPETO AMBIENTAL SIGNIFICATIVO (AAS) BENÉFICO"))))) -> Moderado | U7: =IF(S7="","",IF(Q7=2,"Regra de ouro (L=2)",IF(S7>=40,"IRA ≥ 40",IF(S7>=20,"IRA 20-39",IF(S7>=0,"IRA 0-19",IF(S7>=-14,"IRA -1 a -14","IRA ≤ -15")))))) -> IRA 20-39 | V7: =IF(S7="","",RANK(S7,$S$5:$S$47,0)) -> 9 | W7: =IF(T7="","",IF(OR(T7="ASPETO AMBIENTAL SIGNIFICATIVO (AAS)",T7="Moderado"),"SIM","NÃO")) -> SIM | X7: Operation Clean Sweep: filtros nas sarjetas, tabuleiros de descarga, aspiração, inspeção semanal. | Y7: Varrimento diário. | Z7: 100 | AA7: kg/ano recolhidos | AB7: Pesagem do granulado recolhido | AC7: F4 diário; M3 perdas de kg/mês; G4 microplásticos persistentes e nocivos para a fauna aquática. | AD7: LEG-10 | AE7: RO-07 | AF7: OBJ-06 | AG7: PAM-26-11 | AH7: MED-09 | AI7: =IF(W7="SIM",IF(X7="","FALTA medida de controlo",IF(AND(LEFT(T7,6)="ASPETO",Q7=2,AG7=""),"FALTA ação corretiva (L=2)",IF(AND(LEFT(T7,6)="ASPETO",AH7=""),"Sugestão: definir monitorização","OK"))),"OK") -> OK | AJ7: Não | AK7: 46162 | AL7: =IF(AK7="","",EDATE(AK7,12)) -> 46527 | AM7: Gestor do SGA + responsável do setor
A8: AA-004 | B8: REC | C8: Receção e silos | D8: Desembalagem de matérias-primas | E8: Produção | F8: Resíduos | G8: Geração de resíduos de embalagem de matérias-primas (big bags, sacos, paletes, cartão) | H8: Direto | I8: Normal | J8: Presente | K8: IMP-07 | L8: =IFERROR(INDEX(tbl_impactes[Impacte],MATCH(K8,tbl_impactes[ID_Impacte],0)),"") -> Redução da vida útil de aterros e passivos ambientais | M8: IMP-01 | N8: 4 | O8: 3 | P8: 2 | Q8: 1 | R8: =IF(P8="","",IF(P8<0,"(-) Benéfico","(+) Adverso")) -> (+) Adverso | S8: =IF(COUNT(N8,O8,P8,Q8)<4,"",(N8+O8)*P8*Q8) -> 14 | T8: =IF(S8="","",IF(OR(Q8=2,S8>=40),"ASPETO AMBIENTAL SIGNIFICATIVO (AAS)",IF(S8>=20,"Moderado",IF(S8>=0,"Não Significativo",IF(S8>=-14,"Oportunidade Tática","ASPETO AMBIENTAL SIGNIFICATIVO (AAS) BENÉFICO"))))) -> Não Significativo | U8: =IF(S8="","",IF(Q8=2,"Regra de ouro (L=2)",IF(S8>=40,"IRA ≥ 40",IF(S8>=20,"IRA 20-39",IF(S8>=0,"IRA 0-19",IF(S8>=-14,"IRA -1 a -14","IRA ≤ -15")))))) -> IRA 0-19 | V8: =IF(S8="","",RANK(S8,$S$5:$S$47,0)) -> 34 | W8: =IF(T8="","",IF(OR(T8="ASPETO AMBIENTAL SIGNIFICATIVO (AAS)",T8="Moderado"),"SIM","NÃO")) -> NÃO | X8: Segregação por fluxo; big bags retornáveis com fornecedor. | Y8: Contentores identificados no parque de resíduos. | AB8: Pesagens por código LER | AC8: F4 diário; M3; G2 resíduos não perigosos recicláveis. | AD8: LEG-01 | AH8: MED-04 | AI8: =IF(W8="SIM",IF(X8="","FALTA medida de controlo",IF(AND(LEFT(T8,6)="ASPETO",Q8=2,AG8=""),"FALTA ação corretiva (L=2)",IF(AND(LEFT(T8,6)="ASPETO",AH8=""),"Sugestão: definir monitorização","OK"))),"OK") -> OK | AJ8: Não | AK8: 46162 | AL8: =IF(AK8="","",EDATE(AK8,12)) -> 46527 | AM8: Gestor do SGA + responsável do setor
A9: AA-005 | B9: ARQ | C9: Armazém de químicos | D9: Armazenagem de tintas, solventes e óleos | E9: Produção | F9: Contaminação do solo | G9: Derrame acidental de tintas, solventes ou óleos (rutura de embalagem, queda na movimentação) | H9: Direto | I9: Emergência | J9: Futuro | K9: IMP-02 | L9: =IFERROR(INDEX(tbl_impactes[Impacte],MATCH(K9,tbl_impactes[ID_Impacte],0)),"") -> Contaminação do Solo e/ou Recursos Hídricos | M9: IMP-03 | N9: 1 | O9: 3 | P9: 5 | Q9: 1 | R9: =IF(P9="","",IF(P9<0,"(-) Benéfico","(+) Adverso")) -> (+) Adverso | S9: =IF(COUNT(N9,O9,P9,Q9)<4,"",(N9+O9)*P9*Q9) -> 20 | T9: =IF(S9="","",IF(OR(Q9=2,S9>=40),"ASPETO AMBIENTAL SIGNIFICATIVO (AAS)",IF(S9>=20,"Moderado",IF(S9>=0,"Não Significativo",IF(S9>=-14,"Oportunidade Tática","ASPETO AMBIENTAL SIGNIFICATIVO (AAS) BENÉFICO"))))) -> Moderado | U9: =IF(S9="","",IF(Q9=2,"Regra de ouro (L=2)",IF(S9>=40,"IRA ≥ 40",IF(S9>=20,"IRA 20-39",IF(S9>=0,"IRA 0-19",IF(S9>=-14,"IRA -1 a -14","IRA ≤ -15")))))) -> IRA 20-39 | V9: =IF(S9="","",RANK(S9,$S$5:$S$47,0)) -> 24 | W9: =IF(T9="","",IF(OR(T9="ASPETO AMBIENTAL SIGNIFICATIVO (AAS)",T9="Moderado"),"SIM","NÃO")) -> SIM | X9: Bacias de retenção, kits de derrame completos e selados, IT-SGA-01, simulacro semestral. | Y9: Kits de derrame; FDS; parte dos bidões em bacia. | AB9: Inventário do armazém (≈ 1,5 m³ de líquidos perigosos) | AC9: F1 emergência improvável; M3 até 200 L; G5 solventes com H336/H225 e tintas com H411. | AD9: LEG-06 | AE9: RO-10 | AG9: PAM-26-05 | AH9: MED-10 | AI9: =IF(W9="SIM",IF(X9="","FALTA medida de controlo",IF(AND(LEFT(T9,6)="ASPETO",Q9=2,AG9=""),"FALTA ação corretiva (L=2)",IF(AND(LEFT(T9,6)="ASPETO",AH9=""),"Sugestão: definir monitorização","OK"))),"OK") -> OK | AJ9: Sim | AK9: 46162 | AL9: =IF(AK9="","",EDATE(AK9,12)) -> 46527 | AM9: Gestor do SGA + responsável do setor
A10: AA-006 | B10: ARQ | C10: Armazém de químicos | D10: Manuseamento e trasfega de solventes | E10: Produção | F10: Emissões atmosféricas | G10: Evaporação de COV de recipientes abertos ou mal fechados | H10: Direto | I10: Anormal | J10: Presente | K10: IMP-03 | L10: =IFERROR(INDEX(tbl_impactes[Impacte],MATCH(K10,tbl_impactes[ID_Impacte],0)),"") -> Poluição do Ar | M10: IMP-04 | N10: 3 | O10: 2 | P10: 5 | Q10: 1 | R10: =IF(P10="","",IF(P10<0,"(-) Benéfico","(+) Adverso")) -> (+) Adverso | S10: =IF(COUNT(N10,O10,P10,Q10)<4,"",(N10+O10)*P10*Q10) -> 25 | T10: =IF(S10="","",IF(OR(Q10=2,S10>=40),"ASPETO AMBIENTAL SIGNIFICATIVO (AAS)",IF(S10>=20,"Moderado",IF(S10>=0,"Não Significativo",IF(S10>=-14,"Oportunidade Tática","ASPETO AMBIENTAL SIGNIFICATIVO (AAS) BENÉFICO"))))) -> Moderado | U10: =IF(S10="","",IF(Q10=2,"Regra de ouro (L=2)",IF(S10>=40,"IRA ≥ 40",IF(S10>=20,"IRA 20-39",IF(S10>=0,"IRA 0-19",IF(S10>=-14,"IRA -1 a -14","IRA ≤ -15")))))) -> IRA 20-39 | V10: =IF(S10="","",RANK(S10,$S$5:$S$47,0)) -> 17 | W10: =IF(T10="","",IF(OR(T10="ASPETO AMBIENTAL SIGNIFICATIVO (AAS)",T10="Moderado"),"SIM","NÃO")) -> SIM | X10: Recipientes fechados, dispensadores de segurança, regra 'tampa fechada'. | Y10: Instrução verbal. | AB10: Ronda ambiental | AC10: F3 semanal; M2 pequenas quantidades; G5 COV sem tratamento. | AD10: LEG-06 | AF10: OBJ-03 | AG10: PAM-26-08 | AH10: MED-06 | AI10: =IF(W10="SIM",IF(X10="","FALTA medida de controlo",IF(AND(LEFT(T10,6)="ASPETO",Q10=2,AG10=""),"FALTA ação corretiva (L=2)",IF(AND(LEFT(T10,6)="ASPETO",AH10=""),"Sugestão: definir monitorização","OK"))),"OK") -> OK | AJ10: Não | AK10: 46162 | AL10: =IF(AK10="","",EDATE(AK10,12)) -> 46527 | AM10: Gestor do SGA + responsável do setor
A11: AA-007 | B11: INJ | C11: Injeção de tampas | D11: Moldação por injeção (IM-001 a IM-009) | E11: Produção | F11: Consumo de recursos | G11: Consumo de energia elétrica (aquecimento do canhão, hidráulica, extração) | H11: Direto | I11: Normal | J11: Presente | K11: IMP-01 | L11: =IFERROR(INDEX(tbl_impactes[Impacte],MATCH(K11,tbl_impactes[ID_Impacte],0)),"") -> Esgotamento de Recursos Naturais / Recursos | M11: IMP-04 | N11: 5 | O11: 5 | P11: 3 | Q11: 1 | R11: =IF(P11="","",IF(P11<0,"(-) Benéfico","(+) Adverso")) -> (+) Adverso | S11: =IF(COUNT(N11,O11,P11,Q11)<4,"",(N11+O11)*P11*Q11) -> 30 | T11: =IF(S11="","",IF(OR(Q11=2,S11>=40),"ASPETO AMBIENTAL SIGNIFICATIVO (AAS)",IF(S11>=20,"Moderado",IF(S11>=0,"Não Significativo",IF(S11>=-14,"Oportunidade Tática","ASPETO AMBIENTAL SIGNIFICATIVO (AAS) BENÉFICO"))))) -> Moderado | U11: =IF(S11="","",IF(Q11=2,"Regra de ouro (L=2)",IF(S11>=40,"IRA ≥ 40",IF(S11>=20,"IRA 20-39",IF(S11>=0,"IRA 0-19",IF(S11>=-14,"IRA -1 a -14","IRA ≤ -15")))))) -> IRA 20-39 | V11: =IF(S11="","",RANK(S11,$S$5:$S$47,0)) -> 5 | W11: =IF(T11="","",IF(OR(T11="ASPETO AMBIENTAL SIGNIFICATIVO (AAS)",T11="Moderado"),"SIM","NÃO")) -> SIM | X11: Standby nas pausas (Kaizen KZ-01), manutenção de resistências e isolamento do canhão, submedição. | Y11: Manutenção preventiva. | Z11: 2186.1 | AA11: MWh/ano | AB11: Rateio da fatura por horas de marcha (sem submedição) | AC11: F5 contínuo; M5 um dos maiores consumos; G3 emissões indiretas convencionais. | AD11: LEG-08 | AE11: RO-02 | AF11: OBJ-01 | AG11: PAM-26-06 | AH11: MED-01 | AI11: =IF(W11="SIM",IF(X11="","FALTA medida de controlo",IF(AND(LEFT(T11,6)="ASPETO",Q11=2,AG11=""),"FALTA ação corretiva (L=2)",IF(AND(LEFT(T11,6)="ASPETO",AH11=""),"Sugestão: definir monitorização","OK"))),"OK") -> OK | AJ11: Não | AK11: 46162 | AL11: =IF(AK11="","",EDATE(AK11,12)) -> 46527 | AM11: Gestor do SGA + responsável do setor
A12: AA-008 | B12: INJ | C12: Injeção de tampas | D12: Moldação por injeção (IM-001 a IM-009) | E12: Produção | F12: Resíduos | G12: Geração de scrap plástico (peças rejeitadas, jitos e purgas de arranque) | H12: Direto | I12: Normal | J12: Presente | K12: IMP-01 | L12: =IFERROR(INDEX(tbl_impactes[Impacte],MATCH(K12,tbl_impactes[ID_Impacte],0)),"") -> Esgotamento de Recursos Naturais / Recursos | M12: IMP-07 | N12: 5 | O12: 3 | P12: 3 | Q12: 1 | R12: =IF(P12="","",IF(P12<0,"(-) Benéfico","(+) Adverso")) -> (+) Adverso | S12: =IF(COUNT(N12,O12,P12,Q12)<4,"",(N12+O12)*P12*Q12) -> 24 | T12: =IF(S12="","",IF(OR(Q12=2,S12>=40),"ASPETO AMBIENTAL SIGNIFICATIVO (AAS)",IF(S12>=20,"Moderado",IF(S12>=0,"Não Significativo",IF(S12>=-14,"Oportunidade Tática","ASPETO AMBIENTAL SIGNIFICATIVO (AAS) BENÉFICO"))))) -> Moderado | U12: =IF(S12="","",IF(Q12=2,"Regra de ouro (L=2)",IF(S12>=40,"IRA ≥ 40",IF(S12>=20,"IRA 20-39",IF(S12>=0,"IRA 0-19",IF(S12>=-14,"IRA -1 a -14","IRA ≤ -15")))))) -> IRA 20-39 | V12: =IF(S12="","",RANK(S12,$S$5:$S$47,0)) -> 18 | W12: =IF(T12="","",IF(OR(T12="ASPETO AMBIENTAL SIGNIFICATIVO (AAS)",T12="Moderado"),"SIM","NÃO")) -> SIM | X12: Controlo de processo (DOE IM-002), segregação por cor e reintegração. | Y12: Moinhos junto às máquinas. | AB12: Pesagem de scrap | AC12: F5 contínuo; M3; G3 resíduo não perigoso em grande quantidade. | AD12: LEG-01 | AE12: RO-11 | AF12: OBJ-02 | AH12: MED-03 | AI12: =IF(W12="SIM",IF(X12="","FALTA medida de controlo",IF(AND(LEFT(T12,6)="ASPETO",Q12=2,AG12=""),"FALTA ação corretiva (L=2)",IF(AND(LEFT(T12,6)="ASPETO",AH12=""),"Sugestão: definir monitorização","OK"))),"OK") -> OK | AJ12: Não | AK12: 46162 | AL12: =IF(AK12="","",EDATE(AK12,12)) -> 46527 | AM12: Gestor do SGA + responsável do setor
A13: AA-009 | B13: INJ | C13: Injeção de tampas | D13: Mudança de óleo hidráulico e fugas em mangueiras | E13: Produção | F13: Contaminação do solo | G13: Fuga de óleo hidráulico durante manutenção ou por rotura de mangueira | H13: Direto | I13: Anormal | J13: Presente | K13: IMP-02 | L13: =IFERROR(INDEX(tbl_impactes[Impacte],MATCH(K13,tbl_impactes[ID_Impacte],0)),"") -> Contaminação do Solo e/ou Recursos Hídricos | N13: 2 | O13: 2 | P13: 4 | Q13: 1 | R13: =IF(P13="","",IF(P13<0,"(-) Benéfico","(+) Adverso")) -> (+) Adverso | S13: =IF(COUNT(N13,O13,P13,Q13)<4,"",(N13+O13)*P13*Q13) -> 16 | T13: =IF(S13="","",IF(OR(Q13=2,S13>=40),"ASPETO AMBIENTAL SIGNIFICATIVO (AAS)",IF(S13>=20,"Moderado",IF(S13>=0,"Não Significativo",IF(S13>=-14,"Oportunidade Tática","ASPETO AMBIENTAL SIGNIFICATIVO (AAS) BENÉFICO"))))) -> Não Significativo | U13: =IF(S13="","",IF(Q13=2,"Regra de ouro (L=2)",IF(S13>=40,"IRA ≥ 40",IF(S13>=20,"IRA 20-39",IF(S13>=0,"IRA 0-19",IF(S13>=-14,"IRA -1 a -14","IRA ≤ -15")))))) -> IRA 0-19 | V13: =IF(S13="","",RANK(S13,$S$5:$S$47,0)) -> 28 | W13: =IF(T13="","",IF(OR(T13="ASPETO AMBIENTAL SIGNIFICATIVO (AAS)",T13="Moderado"),"SIM","NÃO")) -> NÃO | X13: Tabuleiros de retenção sob a hidráulica; inspeção de mangueiras. | Y13: Absorventes na oficina. | AB13: Registos de manutenção | AC13: F2 trimestral; M2 litros; G4 óleo usado (resíduo perigoso standard). | AD13: LEG-01 | AE13: RO-10 | AI13: =IF(W13="SIM",IF(X13="","FALTA medida de controlo",IF(AND(LEFT(T13,6)="ASPETO",Q13=2,AG13=""),"FALTA ação corretiva (L=2)",IF(AND(LEFT(T13,6)="ASPETO",AH13=""),"Sugestão: definir monitorização","OK"))),"OK") -> OK | AJ13: Não | AK13: 46162 | AL13: =IF(AK13="","",EDATE(AK13,12)) -> 46527 | AM13: Gestor do SGA + responsável do setor
A14: AA-010 | B14: SOP | C14: Sopro de frascos (ISBM) | D14: Moldação por injeção-sopro (ISBM-001 a 010) | E14: Produção | F14: Consumo de recursos | G14: Consumo de energia elétrica (aquecimento de pré-formas, sopro, hidráulica) | H14: Direto | I14: Normal | J14: Presente | K14: IMP-01 | L14: =IFERROR(INDEX(tbl_impactes[Impacte],MATCH(K14,tbl_impactes[ID_Impacte],0)),"") -> Esgotamento de Recursos Naturais / Recursos | M14: IMP-04 | N14: 5 | O14: 5 | P14: 3 | Q14: 1 | R14: =IF(P14="","",IF(P14<0,"(-) Benéfico","(+) Adverso")) -> (+) Adverso | S14: =IF(COUNT(N14,O14,P14,Q14)<4,"",(N14+O14)*P14*Q14) -> 30 | T14: =IF(S14="","",IF(OR(Q14=2,S14>=40),"ASPETO AMBIENTAL SIGNIFICATIVO (AAS)",IF(S14>=20,"Moderado",IF(S14>=0,"Não Significativo",IF(S14>=-14,"Oportunidade Tática","ASPETO AMBIENTAL SIGNIFICATIVO (AAS) BENÉFICO"))))) -> Moderado | U14: =IF(S14="","",IF(Q14=2,"Regra de ouro (L=2)",IF(S14>=40,"IRA ≥ 40",IF(S14>=20,"IRA 20-39",IF(S14>=0,"IRA 0-19",IF(S14>=-14,"IRA -1 a -14","IRA ≤ -15")))))) -> IRA 20-39 | V14: =IF(S14="","",RANK(S14,$S$5:$S$47,0)) -> 5 | W14: =IF(T14="","",IF(OR(T14="ASPETO AMBIENTAL SIGNIFICATIVO (AAS)",T14="Moderado"),"SIM","NÃO")) -> SIM | X14: Submedição, ajuste de temperaturas de condicionamento, standby nas pausas. | Y14: Manutenção preventiva. | Z14: 3137.2 | AA14: MWh/ano | AB14: Rateio da fatura por horas de marcha (sem submedição) | AC14: F5 contínuo; M5 maior consumo de energia; G3. | AD14: LEG-08 | AE14: RO-02 | AF14: OBJ-01 | AG14: PAM-26-02 | AH14: MED-01 | AI14: =IF(W14="SIM",IF(X14="","FALTA medida de controlo",IF(AND(LEFT(T14,6)="ASPETO",Q14=2,AG14=""),"FALTA ação corretiva (L=2)",IF(AND(LEFT(T14,6)="ASPETO",AH14=""),"Sugestão: definir monitorização","OK"))),"OK") -> OK | AJ14: Não | AK14: 46162 | AL14: =IF(AK14="","",EDATE(AK14,12)) -> 46527 | AM14: Gestor do SGA + responsável do setor
A15: AA-011 | B15: SOP | C15: Sopro de frascos (ISBM) | D15: Moldação por injeção-sopro (ISBM-001 a 010) | E15: Produção | F15: Resíduos | G15: Geração de scrap plástico (frascos rejeitados e purgas) | H15: Direto | I15: Normal | J15: Presente | K15: IMP-01 | L15: =IFERROR(INDEX(tbl_impactes[Impacte],MATCH(K15,tbl_impactes[ID_Impacte],0)),"") -> Esgotamento de Recursos Naturais / Recursos | M15: IMP-07 | N15: 5 | O15: 4 | P15: 3 | Q15: 1 | R15: =IF(P15="","",IF(P15<0,"(-) Benéfico","(+) Adverso")) -> (+) Adverso | S15: =IF(COUNT(N15,O15,P15,Q15)<4,"",(N15+O15)*P15*Q15) -> 27 | T15: =IF(S15="","",IF(OR(Q15=2,S15>=40),"ASPETO AMBIENTAL SIGNIFICATIVO (AAS)",IF(S15>=20,"Moderado",IF(S15>=0,"Não Significativo",IF(S15>=-14,"Oportunidade Tática","ASPETO AMBIENTAL SIGNIFICATIVO (AAS) BENÉFICO"))))) -> Moderado | U15: =IF(S15="","",IF(Q15=2,"Regra de ouro (L=2)",IF(S15>=40,"IRA ≥ 40",IF(S15>=20,"IRA 20-39",IF(S15>=0,"IRA 0-19",IF(S15>=-14,"IRA -1 a -14","IRA ≤ -15")))))) -> IRA 20-39 | V15: =IF(S15="","",RANK(S15,$S$5:$S$47,0)) -> 12 | W15: =IF(T15="","",IF(OR(T15="ASPETO AMBIENTAL SIGNIFICATIVO (AAS)",T15="Moderado"),"SIM","NÃO")) -> SIM | X15: Controlo da espessura de parede (ISBM-003), manutenção de moldes, reintegração. | Y15: Cartas de controlo. | Z15: 33.6 | AA15: t/ano (todos os processos) | AB15: Pesagem de scrap | AC15: F5; M4 maior fluxo de scrap; G3. | AD15: LEG-01 | AE15: RO-11 | AF15: OBJ-02 | AH15: MED-03 | AI15: =IF(W15="SIM",IF(X15="","FALTA medida de controlo",IF(AND(LEFT(T15,6)="ASPETO",Q15=2,AG15=""),"FALTA ação corretiva (L=2)",IF(AND(LEFT(T15,6)="ASPETO",AH15=""),"Sugestão: definir monitorização","OK"))),"OK") -> OK | AJ15: Não | AK15: 46162 | AL15: =IF(AK15="","",EDATE(AK15,12)) -> 46527 | AM15: Gestor do SGA + responsável do setor
A16: AA-012 | B16: SOP | C16: Sopro de frascos (ISBM) | D16: Arranque e paragem de máquinas / mudança de molde | E16: Produção | F16: Resíduos | G16: Purgas e peças de arranque após mudança de molde ou paragem | H16: Direto | I16: Anormal | J16: Presente | K16: IMP-01 | L16: =IFERROR(INDEX(tbl_impactes[Impacte],MATCH(K16,tbl_impactes[ID_Impacte],0)),"") -> Esgotamento de Recursos Naturais / Recursos | M16: IMP-07 | N16: 4 | O16: 3 | P16: 3 | Q16: 1 | R16: =IF(P16="","",IF(P16<0,"(-) Benéfico","(+) Adverso")) -> (+) Adverso | S16: =IF(COUNT(N16,O16,P16,Q16)<4,"",(N16+O16)*P16*Q16) -> 21 | T16: =IF(S16="","",IF(OR(Q16=2,S16>=40),"ASPETO AMBIENTAL SIGNIFICATIVO (AAS)",IF(S16>=20,"Moderado",IF(S16>=0,"Não Significativo",IF(S16>=-14,"Oportunidade Tática","ASPETO AMBIENTAL SIGNIFICATIVO (AAS) BENÉFICO"))))) -> Moderado | U16: =IF(S16="","",IF(Q16=2,"Regra de ouro (L=2)",IF(S16>=40,"IRA ≥ 40",IF(S16>=20,"IRA 20-39",IF(S16>=0,"IRA 0-19",IF(S16>=-14,"IRA -1 a -14","IRA ≤ -15")))))) -> IRA 20-39 | V16: =IF(S16="","",RANK(S16,$S$5:$S$47,0)) -> 22 | W16: =IF(T16="","",IF(OR(T16="ASPETO AMBIENTAL SIGNIFICATIVO (AAS)",T16="Moderado"),"SIM","NÃO")) -> SIM | X16: SMED e receitas de arranque validadas. | Y16: Setup padrão. | AB16: Registos de setup | AC16: F4 diário; M3; G3. | AF16: OBJ-02 | AH16: MED-03 | AI16: =IF(W16="SIM",IF(X16="","FALTA medida de controlo",IF(AND(LEFT(T16,6)="ASPETO",Q16=2,AG16=""),"FALTA ação corretiva (L=2)",IF(AND(LEFT(T16,6)="ASPETO",AH16=""),"Sugestão: definir monitorização","OK"))),"OK") -> OK | AJ16: Não | AK16: 46162 | AL16: =IF(AK16="","",EDATE(AK16,12)) -> 46527 | AM16: Gestor do SGA + responsável do setor
A17: AA-013 | B17: SOP | C17: Sopro de frascos (ISBM) | D17: Hidráulica envelhecida da ISBM-005 | E17: Produção | F17: Contaminação do solo | G17: Fugas de óleo hidráulico na ISBM-005 (paragens não planeadas 2,3× a média) | H17: Direto | I17: Anormal | J17: Presente | K17: IMP-02 | L17: =IFERROR(INDEX(tbl_impactes[Impacte],MATCH(K17,tbl_impactes[ID_Impacte],0)),"") -> Contaminação do Solo e/ou Recursos Hídricos | N17: 4 | O17: 2 | P17: 4 | Q17: 1 | R17: =IF(P17="","",IF(P17<0,"(-) Benéfico","(+) Adverso")) -> (+) Adverso | S17: =IF(COUNT(N17,O17,P17,Q17)<4,"",(N17+O17)*P17*Q17) -> 24 | T17: =IF(S17="","",IF(OR(Q17=2,S17>=40),"ASPETO AMBIENTAL SIGNIFICATIVO (AAS)",IF(S17>=20,"Moderado",IF(S17>=0,"Não Significativo",IF(S17>=-14,"Oportunidade Tática","ASPETO AMBIENTAL SIGNIFICATIVO (AAS) BENÉFICO"))))) -> Moderado | U17: =IF(S17="","",IF(Q17=2,"Regra de ouro (L=2)",IF(S17>=40,"IRA ≥ 40",IF(S17>=20,"IRA 20-39",IF(S17>=0,"IRA 0-19",IF(S17>=-14,"IRA -1 a -14","IRA ≤ -15")))))) -> IRA 20-39 | V17: =IF(S17="","",RANK(S17,$S$5:$S$47,0)) -> 18 | W17: =IF(T17="","",IF(OR(T17="ASPETO AMBIENTAL SIGNIFICATIVO (AAS)",T17="Moderado"),"SIM","NÃO")) -> SIM | X17: Plano de manutenção por horas de operação; tabuleiro de retenção. | Y17: Absorventes. | AB17: fact_downtime (ISBM-005) | AC17: F4 semanal; M2; G4 óleo. | AD17: LEG-01 | AE17: RO-10 | AI17: =IF(W17="SIM",IF(X17="","FALTA medida de controlo",IF(AND(LEFT(T17,6)="ASPETO",Q17=2,AG17=""),"FALTA ação corretiva (L=2)",IF(AND(LEFT(T17,6)="ASPETO",AH17=""),"Sugestão: definir monitorização","OK"))),"OK") -> OK | AJ17: Não | AK17: 46162 | AL17: =IF(AK17="","",EDATE(AK17,12)) -> 46527 | AM17: Gestor do SGA + responsável do setor
A18: AA-014 | B18: SER | C18: Serigrafia | D18: Limpeza de ecrãs e rodos com solvente | E18: Produção | F18: Emissões atmosféricas | G18: Emissão difusa de COV na limpeza de ecrãs e rodos com solvente | H18: Direto | I18: Normal | J18: Presente | K18: IMP-03 | L18: =IFERROR(INDEX(tbl_impactes[Impacte],MATCH(K18,tbl_impactes[ID_Impacte],0)),"") -> Poluição do Ar | M18: IMP-04 | N18: 5 | O18: 3 | P18: 5 | Q18: 1 | R18: =IF(P18="","",IF(P18<0,"(-) Benéfico","(+) Adverso")) -> (+) Adverso | S18: =IF(COUNT(N18,O18,P18,Q18)<4,"",(N18+O18)*P18*Q18) -> 40 | T18: =IF(S18="","",IF(OR(Q18=2,S18>=40),"ASPETO AMBIENTAL SIGNIFICATIVO (AAS)",IF(S18>=20,"Moderado",IF(S18>=0,"Não Significativo",IF(S18>=-14,"Oportunidade Tática","ASPETO AMBIENTAL SIGNIFICATIVO (AAS) BENÉFICO"))))) -> ASPETO AMBIENTAL SIGNIFICATIVO (AAS) | U18: =IF(S18="","",IF(Q18=2,"Regra de ouro (L=2)",IF(S18>=40,"IRA ≥ 40",IF(S18>=20,"IRA 20-39",IF(S18>=0,"IRA 0-19",IF(S18>=-14,"IRA -1 a -14","IRA ≤ -15")))))) -> IRA ≥ 40 | V18: =IF(S18="","",RANK(S18,$S$5:$S$47,0)) -> 2 | W18: =IF(T18="","",IF(OR(T18="ASPETO AMBIENTAL SIGNIFICATIVO (AAS)",T18="Moderado"),"SIM","NÃO")) -> SIM | X18: Dispensadores de segurança, panos pré-dosados, limpeza por necessidade, avaliação de solvente de menor volatilidade. | Y18: Exaustão localizada; FDS no posto. | Z18: 759 | AA18: kg solvente/ano | AB18: Inventário de solvente (compras - stock) | AC18: F5 em cada mudança de cor/turno; M3; G5 COV sem tratamento (PR.G.01.01). | AD18: LEG-04 | AF18: OBJ-03 | AG18: PAM-26-08 | AH18: MED-06 | AI18: =IF(W18="SIM",IF(X18="","FALTA medida de controlo",IF(AND(LEFT(T18,6)="ASPETO",Q18=2,AG18=""),"FALTA ação corretiva (L=2)",IF(AND(LEFT(T18,6)="ASPETO",AH18=""),"Sugestão: definir monitorização","OK"))),"OK") -> OK | AJ18: Sim | AK18: 46162 | AL18: =IF(AK18="","",EDATE(AK18,12)) -> 46527 | AM18: Gestor do SGA + responsável do setor
A19: AA-015 | B19: SER | C19: Serigrafia | D19: Impressão serigráfica (SS-001, SS-002) | E19: Produção | F19: Consumo de recursos | G19: Consumo de tintas de serigrafia | H19: Direto | I19: Normal | J19: Presente | K19: IMP-01 | L19: =IFERROR(INDEX(tbl_impactes[Impacte],MATCH(K19,tbl_impactes[ID_Impacte],0)),"") -> Esgotamento de Recursos Naturais / Recursos | M19: IMP-03 | N19: 5 | O19: 3 | P19: 4 | Q19: 1 | R19: =IF(P19="","",IF(P19<0,"(-) Benéfico","(+) Adverso")) -> (+) Adverso | S19: =IF(COUNT(N19,O19,P19,Q19)<4,"",(N19+O19)*P19*Q19) -> 32 | T19: =IF(S19="","",IF(OR(Q19=2,S19>=40),"ASPETO AMBIENTAL SIGNIFICATIVO (AAS)",IF(S19>=20,"Moderado",IF(S19>=0,"Não Significativo",IF(S19>=-14,"Oportunidade Tática","ASPETO AMBIENTAL SIGNIFICATIVO (AAS) BENÉFICO"))))) -> Moderado | U19: =IF(S19="","",IF(Q19=2,"Regra de ouro (L=2)",IF(S19>=40,"IRA ≥ 40",IF(S19>=20,"IRA 20-39",IF(S19>=0,"IRA 0-19",IF(S19>=-14,"IRA -1 a -14","IRA ≤ -15")))))) -> IRA 20-39 | V19: =IF(S19="","",RANK(S19,$S$5:$S$47,0)) -> 3 | W19: =IF(T19="","",IF(OR(T19="ASPETO AMBIENTAL SIGNIFICATIVO (AAS)",T19="Moderado"),"SIM","NÃO")) -> SIM | X19: Dosagem controlada; recuperação de tinta do ecrã. | Y19: — | Z19: 1099 | AA19: kg/ano | AB19: Inventário | AC19: F5; M3; G4 tintas classificadas. | AD19: LEG-06 | AF19: OBJ-03 | AH19: MED-06 | AI19: =IF(W19="SIM",IF(X19="","FALTA medida de controlo",IF(AND(LEFT(T19,6)="ASPETO",Q19=2,AG19=""),"FALTA ação corretiva (L=2)",IF(AND(LEFT(T19,6)="ASPETO",AH19=""),"Sugestão: definir monitorização","OK"))),"OK") -> OK | AJ19: Não | AK19: 46162 | AL19: =IF(AK19="","",EDATE(AK19,12)) -> 46527 | AM19: Gestor do SGA + responsável do setor
A20: AA-016 | B20: SER | C20: Serigrafia | D20: Limpeza e troca de tintas | E20: Produção | F20: Resíduos | G20: Resíduos perigosos: tinta residual (08 03 12*), panos/absorventes (15 02 02*) e embalagens contaminadas (15 01 10*) | H20: Direto | I20: Normal | J20: Presente | K20: IMP-02 | L20: =IFERROR(INDEX(tbl_impactes[Impacte],MATCH(K20,tbl_impactes[ID_Impacte],0)),"") -> Contaminação do Solo e/ou Recursos Hídricos | M20: IMP-07 | N20: 4 | O20: 3 | P20: 4 | Q20: 1 | R20: =IF(P20="","",IF(P20<0,"(-) Benéfico","(+) Adverso")) -> (+) Adverso | S20: =IF(COUNT(N20,O20,P20,Q20)<4,"",(N20+O20)*P20*Q20) -> 28 | T20: =IF(S20="","",IF(OR(Q20=2,S20>=40),"ASPETO AMBIENTAL SIGNIFICATIVO (AAS)",IF(S20>=20,"Moderado",IF(S20>=0,"Não Significativo",IF(S20>=-14,"Oportunidade Tática","ASPETO AMBIENTAL SIGNIFICATIVO (AAS) BENÉFICO"))))) -> Moderado | U20: =IF(S20="","",IF(Q20=2,"Regra de ouro (L=2)",IF(S20>=40,"IRA ≥ 40",IF(S20>=20,"IRA 20-39",IF(S20>=0,"IRA 0-19",IF(S20>=-14,"IRA -1 a -14","IRA ≤ -15")))))) -> IRA 20-39 | V20: =IF(S20="","",RANK(S20,$S$5:$S$47,0)) -> 9 | W20: =IF(T20="","",IF(OR(T20="ASPETO AMBIENTAL SIGNIFICATIVO (AAS)",T20="Moderado"),"SIM","NÃO")) -> SIM | X20: Recipientes fechados e identificados; encaminhamento por operador licenciado; e-GAR. | Y20: Contentores na área. | Z20: 2145 | AA20: kg/ano (todos os perigosos) | AB20: Pesagens e e-GAR | AC20: F4; M3; G4 resíduos perigosos standard. | AD20: LEG-01 | AE20: RO-10 | AH20: MED-04 | AI20: =IF(W20="SIM",IF(X20="","FALTA medida de controlo",IF(AND(LEFT(T20,6)="ASPETO",Q20=2,AG20=""),"FALTA ação corretiva (L=2)",IF(AND(LEFT(T20,6)="ASPETO",AH20=""),"Sugestão: definir monitorização","OK"))),"OK") -> OK | AJ20: Não | AK20: 46162 | AL20: =IF(AK20="","",EDATE(AK20,12)) -> 46527 | AM20: Gestor do SGA + responsável do setor
A21: AA-017 | B21: SER | C21: Serigrafia | D21: Mudança de tinta na linha | E21: Produção | F21: Contaminação do solo | G21: Derrame de tinta ou solvente na linha de serigrafia | H21: Direto | I21: Emergência | J21: Futuro | K21: IMP-02 | L21: =IFERROR(INDEX(tbl_impactes[Impacte],MATCH(K21,tbl_impactes[ID_Impacte],0)),"") -> Contaminação do Solo e/ou Recursos Hídricos | M21: IMP-03 | N21: 1 | O21: 2 | P21: 5 | Q21: 1 | R21: =IF(P21="","",IF(P21<0,"(-) Benéfico","(+) Adverso")) -> (+) Adverso | S21: =IF(COUNT(N21,O21,P21,Q21)<4,"",(N21+O21)*P21*Q21) -> 15 | T21: =IF(S21="","",IF(OR(Q21=2,S21>=40),"ASPETO AMBIENTAL SIGNIFICATIVO (AAS)",IF(S21>=20,"Moderado",IF(S21>=0,"Não Significativo",IF(S21>=-14,"Oportunidade Tática","ASPETO AMBIENTAL SIGNIFICATIVO (AAS) BENÉFICO"))))) -> Não Significativo | U21: =IF(S21="","",IF(Q21=2,"Regra de ouro (L=2)",IF(S21>=40,"IRA ≥ 40",IF(S21>=20,"IRA 20-39",IF(S21>=0,"IRA 0-19",IF(S21>=-14,"IRA -1 a -14","IRA ≤ -15")))))) -> IRA 0-19 | V21: =IF(S21="","",RANK(S21,$S$5:$S$47,0)) -> 33 | W21: =IF(T21="","",IF(OR(T21="ASPETO AMBIENTAL SIGNIFICATIVO (AAS)",T21="Moderado"),"SIM","NÃO")) -> NÃO | X21: Kit de derrame junto à linha; IT-SGA-01. | Y21: Kit de derrame. | AB21: Registo de incidentes | AC21: F1; M2 poucos litros; G5. | AD21: LEG-06 | AE21: RO-10 | AG21: PAM-26-05 | AI21: =IF(W21="SIM",IF(X21="","FALTA medida de controlo",IF(AND(LEFT(T21,6)="ASPETO",Q21=2,AG21=""),"FALTA ação corretiva (L=2)",IF(AND(LEFT(T21,6)="ASPETO",AH21=""),"Sugestão: definir monitorização","OK"))),"OK") -> OK | AJ21: Não | AK21: 46162 | AL21: =IF(AK21="","",EDATE(AK21,12)) -> 46527 | AM21: Gestor do SGA + responsável do setor
A22: AA-018 | B22: HFS | C22: Hot foil stamping | D22: Decoração por hot foil (HF-001, HF-002) | E22: Produção | F22: Resíduos | G22: Resíduo de foil (filme de suporte com restos de metalização) | H22: Direto | I22: Normal | J22: Presente | K22: IMP-07 | L22: =IFERROR(INDEX(tbl_impactes[Impacte],MATCH(K22,tbl_impactes[ID_Impacte],0)),"") -> Redução da vida útil de aterros e passivos ambientais | M22: IMP-01 | N22: 5 | O22: 3 | P22: 2 | Q22: 1 | R22: =IF(P22="","",IF(P22<0,"(-) Benéfico","(+) Adverso")) -> (+) Adverso | S22: =IF(COUNT(N22,O22,P22,Q22)<4,"",(N22+O22)*P22*Q22) -> 16 | T22: =IF(S22="","",IF(OR(Q22=2,S22>=40),"ASPETO AMBIENTAL SIGNIFICATIVO (AAS)",IF(S22>=20,"Moderado",IF(S22>=0,"Não Significativo",IF(S22>=-14,"Oportunidade Tática","ASPETO AMBIENTAL SIGNIFICATIVO (AAS) BENÉFICO"))))) -> Não Significativo | U22: =IF(S22="","",IF(Q22=2,"Regra de ouro (L=2)",IF(S22>=40,"IRA ≥ 40",IF(S22>=20,"IRA 20-39",IF(S22>=0,"IRA 0-19",IF(S22>=-14,"IRA -1 a -14","IRA ≤ -15")))))) -> IRA 0-19 | V22: =IF(S22="","",RANK(S22,$S$5:$S$47,0)) -> 28 | W22: =IF(T22="","",IF(OR(T22="ASPETO AMBIENTAL SIGNIFICATIVO (AAS)",T22="Moderado"),"SIM","NÃO")) -> NÃO | X22: Otimizar passo do foil; valorizar filme como plástico. | Y22: — | AB22: Pesagens | AC22: F5; M3; G2 não perigoso. | AD22: LEG-01 | AH22: MED-04 | AI22: =IF(W22="SIM",IF(X22="","FALTA medida de controlo",IF(AND(LEFT(T22,6)="ASPETO",Q22=2,AG22=""),"FALTA ação corretiva (L=2)",IF(AND(LEFT(T22,6)="ASPETO",AH22=""),"Sugestão: definir monitorização","OK"))),"OK") -> OK | AJ22: Não | AK22: 46162 | AL22: =IF(AK22="","",EDATE(AK22,12)) -> 46527 | AM22: Gestor do SGA + responsável do setor
A23: AA-019 | B23: HFS | C23: Hot foil stamping | D23: Decoração por hot foil (HF-001, HF-002) | E23: Produção | F23: Consumo de recursos | G23: Consumo de energia elétrica (placas aquecidas) | H23: Direto | I23: Normal | J23: Presente | K23: IMP-01 | L23: =IFERROR(INDEX(tbl_impactes[Impacte],MATCH(K23,tbl_impactes[ID_Impacte],0)),"") -> Esgotamento de Recursos Naturais / Recursos | M23: IMP-04 | N23: 5 | O23: 2 | P23: 3 | Q23: 1 | R23: =IF(P23="","",IF(P23<0,"(-) Benéfico","(+) Adverso")) -> (+) Adverso | S23: =IF(COUNT(N23,O23,P23,Q23)<4,"",(N23+O23)*P23*Q23) -> 21 | T23: =IF(S23="","",IF(OR(Q23=2,S23>=40),"ASPETO AMBIENTAL SIGNIFICATIVO (AAS)",IF(S23>=20,"Moderado",IF(S23>=0,"Não Significativo",IF(S23>=-14,"Oportunidade Tática","ASPETO AMBIENTAL SIGNIFICATIVO (AAS) BENÉFICO"))))) -> Moderado | U23: =IF(S23="","",IF(Q23=2,"Regra de ouro (L=2)",IF(S23>=40,"IRA ≥ 40",IF(S23>=20,"IRA 20-39",IF(S23>=0,"IRA 0-19",IF(S23>=-14,"IRA -1 a -14","IRA ≤ -15")))))) -> IRA 20-39 | V23: =IF(S23="","",RANK(S23,$S$5:$S$47,0)) -> 22 | W23: =IF(T23="","",IF(OR(T23="ASPETO AMBIENTAL SIGNIFICATIVO (AAS)",T23="Moderado"),"SIM","NÃO")) -> SIM | X23: Desligar placas nas paragens. | Y23: — | Z23: 120.1 | AA23: MWh/ano | AB23: Rateio da fatura | AC23: F5; M2; G3. | AF23: OBJ-01 | AH23: MED-01 | AI23: =IF(W23="SIM",IF(X23="","FALTA medida de controlo",IF(AND(LEFT(T23,6)="ASPETO",Q23=2,AG23=""),"FALTA ação corretiva (L=2)",IF(AND(LEFT(T23,6)="ASPETO",AH23=""),"Sugestão: definir monitorização","OK"))),"OK") -> OK | AJ23: Não | AK23: 46162 | AL23: =IF(AK23="","",EDATE(AK23,12)) -> 46527 | AM23: Gestor do SGA + responsável do setor
A24: AA-020 | B24: MOA | C24: Moagem de scrap | D24: Moagem e reintegração de rebarbas | E24: Produção | F24: Consumo de recursos | G24: Reintegração de scrap limpo (regrind) em substituição de polímero novo | H24: Direto | I24: Normal | J24: Presente | K24: IMP-10 | L24: =IFERROR(INDEX(tbl_impactes[Impacte],MATCH(K24,tbl_impactes[ID_Impacte],0)),"") -> Otimização do Consumo de Matérias-Primas (poupança ou geração de novos recursos) | M24: IMP-09 | N24: 5 | O24: 4 | P24: -1 | Q24: 1 | R24: =IF(P24="","",IF(P24<0,"(-) Benéfico","(+) Adverso")) -> (-) Benéfico | S24: =IF(COUNT(N24,O24,P24,Q24)<4,"",(N24+O24)*P24*Q24) -> -9 | T24: =IF(S24="","",IF(OR(Q24=2,S24>=40),"ASPETO AMBIENTAL SIGNIFICATIVO (AAS)",IF(S24>=20,"Moderado",IF(S24>=0,"Não Significativo",IF(S24>=-14,"Oportunidade Tática","ASPETO AMBIENTAL SIGNIFICATIVO (AAS) BENÉFICO"))))) -> Oportunidade Tática | U24: =IF(S24="","",IF(Q24=2,"Regra de ouro (L=2)",IF(S24>=40,"IRA ≥ 40",IF(S24>=20,"IRA 20-39",IF(S24>=0,"IRA 0-19",IF(S24>=-14,"IRA -1 a -14","IRA ≤ -15")))))) -> IRA -1 a -14 | V24: =IF(S24="","",RANK(S24,$S$5:$S$47,0)) -> 41 | W24: =IF(T24="","",IF(OR(T24="ASPETO AMBIENTAL SIGNIFICATIVO (AAS)",T24="Moderado"),"SIM","NÃO")) -> NÃO | X24: Segregar por polímero/cor para aumentar a taxa. | Y24: Moinhos junto às máquinas. | Z24: 12.8 | AA24: t/ano | AB24: Pesagem nos moinhos | AC24: Aspeto benéfico: G -1 circularidade interna (evita compra de matéria-prima). | AE24: RO-11 | AF24: OBJ-02 | AH24: MED-03 | AI24: =IF(W24="SIM",IF(X24="","FALTA medida de controlo",IF(AND(LEFT(T24,6)="ASPETO",Q24=2,AG24=""),"FALTA ação corretiva (L=2)",IF(AND(LEFT(T24,6)="ASPETO",AH24=""),"Sugestão: definir monitorização","OK"))),"OK") -> OK | AJ24: Não | AK24: 46162 | AL24: =IF(AK24="","",EDATE(AK24,12)) -> 46527 | AM24: Gestor do SGA + responsável do setor
A25: AA-021 | B25: UTL | C25: Utilidades | D25: Produção de ar comprimido (CMP-01/02) | E25: Produção | F25: Consumo de recursos | G25: Consumo de energia dos compressores, agravado por fugas na rede de ar comprimido | H25: Direto | I25: Normal | J25: Presente | K25: IMP-01 | L25: =IFERROR(INDEX(tbl_impactes[Impacte],MATCH(K25,tbl_impactes[ID_Impacte],0)),"") -> Esgotamento de Recursos Naturais / Recursos | M25: IMP-04 | N25: 5 | O25: 4 | P25: 3 | Q25: 1 | R25: =IF(P25="","",IF(P25<0,"(-) Benéfico","(+) Adverso")) -> (+) Adverso | S25: =IF(COUNT(N25,O25,P25,Q25)<4,"",(N25+O25)*P25*Q25) -> 27 | T25: =IF(S25="","",IF(OR(Q25=2,S25>=40),"ASPETO AMBIENTAL SIGNIFICATIVO (AAS)",IF(S25>=20,"Moderado",IF(S25>=0,"Não Significativo",IF(S25>=-14,"Oportunidade Tática","ASPETO AMBIENTAL SIGNIFICATIVO (AAS) BENÉFICO"))))) -> Moderado | U25: =IF(S25="","",IF(Q25=2,"Regra de ouro (L=2)",IF(S25>=40,"IRA ≥ 40",IF(S25>=20,"IRA 20-39",IF(S25>=0,"IRA 0-19",IF(S25>=-14,"IRA -1 a -14","IRA ≤ -15")))))) -> IRA 20-39 | V25: =IF(S25="","",RANK(S25,$S$5:$S$47,0)) -> 12 | W25: =IF(T25="","",IF(OR(T25="ASPETO AMBIENTAL SIGNIFICATIVO (AAS)",T25="Moderado"),"SIM","NÃO")) -> SIM | X25: Caça a fugas por ultrassom; reduzir pressão de 7,5 para 6,8 bar. | Y25: Manutenção dos compressores. | Z25: 1035.2 | AA25: MWh/ano | AB25: Rateio da fatura | AC25: F5; M4; G3. | AD25: LEG-08 | AE25: RO-02 | AF25: OBJ-01 | AG25: PAM-26-01 | AH25: MED-02 | AI25: =IF(W25="SIM",IF(X25="","FALTA medida de controlo",IF(AND(LEFT(T25,6)="ASPETO",Q25=2,AG25=""),"FALTA ação corretiva (L=2)",IF(AND(LEFT(T25,6)="ASPETO",AH25=""),"Sugestão: definir monitorização","OK"))),"OK") -> OK | AJ25: Não | AK25: 46162 | AL25: =IF(AK25="","",EDATE(AK25,12)) -> 46527 | AM25: Gestor do SGA + responsável do setor
A26: AA-022 | B26: UTL | C26: Utilidades | D26: Operação dos compressores novos (2026) | E26: Produção | F26: Ruído e vibrações | G26: Emissão de ruído para o exterior pelos compressores e torre de arrefecimento | H26: Direto | I26: Normal | J26: Presente | K26: IMP-05 | L26: =IFERROR(INDEX(tbl_impactes[Impacte],MATCH(K26,tbl_impactes[ID_Impacte],0)),"") -> Incomodidade da Vizinhança | N26: 5 | O26: 3 | P26: 2 | Q26: 2 | R26: =IF(P26="","",IF(P26<0,"(-) Benéfico","(+) Adverso")) -> (+) Adverso | S26: =IF(COUNT(N26,O26,P26,Q26)<4,"",(N26+O26)*P26*Q26) -> 32 | T26: =IF(S26="","",IF(OR(Q26=2,S26>=40),"ASPETO AMBIENTAL SIGNIFICATIVO (AAS)",IF(S26>=20,"Moderado",IF(S26>=0,"Não Significativo",IF(S26>=-14,"Oportunidade Tática","ASPETO AMBIENTAL SIGNIFICATIVO (AAS) BENÉFICO"))))) -> ASPETO AMBIENTAL SIGNIFICATIVO (AAS) | U26: =IF(S26="","",IF(Q26=2,"Regra de ouro (L=2)",IF(S26>=40,"IRA ≥ 40",IF(S26>=20,"IRA 20-39",IF(S26>=0,"IRA 0-19",IF(S26>=-14,"IRA -1 a -14","IRA ≤ -15")))))) -> Regra de ouro (L=2) | V26: =IF(S26="","",RANK(S26,$S$5:$S$47,0)) -> 3 | W26: =IF(T26="","",IF(OR(T26="ASPETO AMBIENTAL SIGNIFICATIVO (AAS)",T26="Moderado"),"SIM","NÃO")) -> SIM | X26: Avaliação acústica por laboratório acreditado; atenuadores se necessário. | Y26: Compressores em sala fechada. | AB26: Última avaliação acústica: 2023 (antes da troca de compressores) | AC26: L2: falta a medição obrigatória após alteração (RGR) → AAS pela regra de ouro. | AD26: LEG-05 | AE26: RO-12 | AG26: PAM-26-03 | AH26: MED-07 | AI26: =IF(W26="SIM",IF(X26="","FALTA medida de controlo",IF(AND(LEFT(T26,6)="ASPETO",Q26=2,AG26=""),"FALTA ação corretiva (L=2)",IF(AND(LEFT(T26,6)="ASPETO",AH26=""),"Sugestão: definir monitorização","OK"))),"OK") -> OK | AJ26: Não | AK26: 46162 | AL26: =IF(AK26="","",EDATE(AK26,12)) -> 46527 | AM26: Gestor do SGA + responsável do setor
A27: AA-023 | B27: UTL | C27: Utilidades | D27: Torre de arrefecimento TR-01 | E27: Produção | F27: Consumo de recursos | G27: Consumo de água de rede para reposição da torre de arrefecimento (evaporação e purga) | H27: Direto | I27: Normal | J27: Presente | K27: IMP-01 | L27: =IFERROR(INDEX(tbl_impactes[Impacte],MATCH(K27,tbl_impactes[ID_Impacte],0)),"") -> Esgotamento de Recursos Naturais / Recursos | N27: 5 | O27: 4 | P27: 3 | Q27: 1 | R27: =IF(P27="","",IF(P27<0,"(-) Benéfico","(+) Adverso")) -> (+) Adverso | S27: =IF(COUNT(N27,O27,P27,Q27)<4,"",(N27+O27)*P27*Q27) -> 27 | T27: =IF(S27="","",IF(OR(Q27=2,S27>=40),"ASPETO AMBIENTAL SIGNIFICATIVO (AAS)",IF(S27>=20,"Moderado",IF(S27>=0,"Não Significativo",IF(S27>=-14,"Oportunidade Tática","ASPETO AMBIENTAL SIGNIFICATIVO (AAS) BENÉFICO"))))) -> Moderado | U27: =IF(S27="","",IF(Q27=2,"Regra de ouro (L=2)",IF(S27>=40,"IRA ≥ 40",IF(S27>=20,"IRA 20-39",IF(S27>=0,"IRA 0-19",IF(S27>=-14,"IRA -1 a -14","IRA ≤ -15")))))) -> IRA 20-39 | V27: =IF(S27="","",RANK(S27,$S$5:$S$47,0)) -> 12 | W27: =IF(T27="","",IF(OR(T27="ASPETO AMBIENTAL SIGNIFICATIVO (AAS)",T27="Moderado"),"SIM","NÃO")) -> SIM | X27: Circuito fechado / torre adiabática; controlo da purga por condutividade. | Y27: Tratamento de água da torre. | Z27: 8330 | AA27: m³/ano | AB27: Balanço da fatura de água | AC27: F5; M4 principal consumo de água; G3. | AD27: LEG-03 | AE27: RO-04 | AF27: OBJ-05 | AG27: PAM-26-14 | AH27: MED-08 | AI27: =IF(W27="SIM",IF(X27="","FALTA medida de controlo",IF(AND(LEFT(T27,6)="ASPETO",Q27=2,AG27=""),"FALTA ação corretiva (L=2)",IF(AND(LEFT(T27,6)="ASPETO",AH27=""),"Sugestão: definir monitorização","OK"))),"OK") -> OK | AJ27: Não | AK27: 46162 | AL27: =IF(AK27="","",EDATE(AK27,12)) -> 46527 | AM27: Gestor do SGA + responsável do setor
A28: AA-024 | B28: UTL | C28: Utilidades | D28: Purga da torre de arrefecimento | E28: Produção | F28: Efluentes | G28: Descarga da purga da torre (com biocida e anti-incrustante) no coletor municipal | H28: Direto | I28: Normal | J28: Presente | K28: IMP-02 | L28: =IFERROR(INDEX(tbl_impactes[Impacte],MATCH(K28,tbl_impactes[ID_Impacte],0)),"") -> Contaminação do Solo e/ou Recursos Hídricos | N28: 4 | O28: 3 | P28: 4 | Q28: 1 | R28: =IF(P28="","",IF(P28<0,"(-) Benéfico","(+) Adverso")) -> (+) Adverso | S28: =IF(COUNT(N28,O28,P28,Q28)<4,"",(N28+O28)*P28*Q28) -> 28 | T28: =IF(S28="","",IF(OR(Q28=2,S28>=40),"ASPETO AMBIENTAL SIGNIFICATIVO (AAS)",IF(S28>=20,"Moderado",IF(S28>=0,"Não Significativo",IF(S28>=-14,"Oportunidade Tática","ASPETO AMBIENTAL SIGNIFICATIVO (AAS) BENÉFICO"))))) -> Moderado | U28: =IF(S28="","",IF(Q28=2,"Regra de ouro (L=2)",IF(S28>=40,"IRA ≥ 40",IF(S28>=20,"IRA 20-39",IF(S28>=0,"IRA 0-19",IF(S28>=-14,"IRA -1 a -14","IRA ≤ -15")))))) -> IRA 20-39 | V28: =IF(S28="","",RANK(S28,$S$5:$S$47,0)) -> 9 | W28: =IF(T28="","",IF(OR(T28="ASPETO AMBIENTAL SIGNIFICATIVO (AAS)",T28="Moderado"),"SIM","NÃO")) -> SIM | X28: Dosagem automática; análises; limites do regulamento municipal. | Y28: Autorização de descarga. | AB28: Análises semestrais do efluente | AC28: F4; M3; G4 biocida (H400). | AD28: LEG-03 | AH28: MED-11 | AI28: =IF(W28="SIM",IF(X28="","FALTA medida de controlo",IF(AND(LEFT(T28,6)="ASPETO",Q28=2,AG28=""),"FALTA ação corretiva (L=2)",IF(AND(LEFT(T28,6)="ASPETO",AH28=""),"Sugestão: definir monitorização","OK"))),"OK") -> OK | AJ28: Não | AK28: 46162 | AL28: =IF(AK28="","",EDATE(AK28,12)) -> 46527 | AM28: Gestor do SGA + responsável do setor
A29: AA-025 | B29: UTL | C29: Utilidades | D29: Chiller CH-01 (R410A) | E29: Produção | F29: Fugas | G29: Fuga de gás fluorado R410A do chiller | H29: Direto | I29: Emergência | J29: Passado | K29: IMP-04 | L29: =IFERROR(INDEX(tbl_impactes[Impacte],MATCH(K29,tbl_impactes[ID_Impacte],0)),"") -> Mudanças Climáticas | N29: 1 | O29: 1 | P29: 5 | Q29: 1 | R29: =IF(P29="","",IF(P29<0,"(-) Benéfico","(+) Adverso")) -> (+) Adverso | S29: =IF(COUNT(N29,O29,P29,Q29)<4,"",(N29+O29)*P29*Q29) -> 10 | T29: =IF(S29="","",IF(OR(Q29=2,S29>=40),"ASPETO AMBIENTAL SIGNIFICATIVO (AAS)",IF(S29>=20,"Moderado",IF(S29>=0,"Não Significativo",IF(S29>=-14,"Oportunidade Tática","ASPETO AMBIENTAL SIGNIFICATIVO (AAS) BENÉFICO"))))) -> Não Significativo | U29: =IF(S29="","",IF(Q29=2,"Regra de ouro (L=2)",IF(S29>=40,"IRA ≥ 40",IF(S29>=20,"IRA 20-39",IF(S29>=0,"IRA 0-19",IF(S29>=-14,"IRA -1 a -14","IRA ≤ -15")))))) -> IRA 0-19 | V29: =IF(S29="","",RANK(S29,$S$5:$S$47,0)) -> 37 | W29: =IF(T29="","",IF(OR(T29="ASPETO AMBIENTAL SIGNIFICATIVO (AAS)",T29="Moderado"),"SIM","NÃO")) -> NÃO | X29: Controlo de fugas conforme carga em tCO2e; técnico certificado. | Y29: Registo do equipamento. | Z29: 3.2 | AA29: kg R410A (fuga nov/2025) | AB29: Relatório do técnico certificado | AC29: F1; M1; G5 (GWP 2088). Ocorrência passada em nov/2025. | AD29: LEG-07 | AI29: =IF(W29="SIM",IF(X29="","FALTA medida de controlo",IF(AND(LEFT(T29,6)="ASPETO",Q29=2,AG29=""),"FALTA ação corretiva (L=2)",IF(AND(LEFT(T29,6)="ASPETO",AH29=""),"Sugestão: definir monitorização","OK"))),"OK") -> OK | AJ29: Não | AK29: 46162 | AL29: =IF(AK29="","",EDATE(AK29,12)) -> 46527 | AM29: Gestor do SGA + responsável do setor
A30: AA-026 | B30: MAN | C30: Manutenção | D30: Manutenção mecânica e elétrica | E30: Produção | F30: Resíduos | G30: Geração de óleos usados (13 02 05*), lâmpadas (20 01 21*) e sucata metálica | H30: Direto | I30: Anormal | J30: Presente | K30: IMP-02 | L30: =IFERROR(INDEX(tbl_impactes[Impacte],MATCH(K30,tbl_impactes[ID_Impacte],0)),"") -> Contaminação do Solo e/ou Recursos Hídricos | M30: IMP-07 | N30: 2 | O30: 3 | P30: 4 | Q30: 1 | R30: =IF(P30="","",IF(P30<0,"(-) Benéfico","(+) Adverso")) -> (+) Adverso | S30: =IF(COUNT(N30,O30,P30,Q30)<4,"",(N30+O30)*P30*Q30) -> 20 | T30: =IF(S30="","",IF(OR(Q30=2,S30>=40),"ASPETO AMBIENTAL SIGNIFICATIVO (AAS)",IF(S30>=20,"Moderado",IF(S30>=0,"Não Significativo",IF(S30>=-14,"Oportunidade Tática","ASPETO AMBIENTAL SIGNIFICATIVO (AAS) BENÉFICO"))))) -> Moderado | U30: =IF(S30="","",IF(Q30=2,"Regra de ouro (L=2)",IF(S30>=40,"IRA ≥ 40",IF(S30>=20,"IRA 20-39",IF(S30>=0,"IRA 0-19",IF(S30>=-14,"IRA -1 a -14","IRA ≤ -15")))))) -> IRA 20-39 | V30: =IF(S30="","",RANK(S30,$S$5:$S$47,0)) -> 24 | W30: =IF(T30="","",IF(OR(T30="ASPETO AMBIENTAL SIGNIFICATIVO (AAS)",T30="Moderado"),"SIM","NÃO")) -> SIM | X30: Recolha por operadores licenciados; armazenagem em bacia. | Y30: Bidão de óleo usado em bacia. | AB30: Pesagens e e-GAR | AC30: F2 trimestral; M3; G4. | AD30: LEG-01 | AH30: MED-04 | AI30: =IF(W30="SIM",IF(X30="","FALTA medida de controlo",IF(AND(LEFT(T30,6)="ASPETO",Q30=2,AG30=""),"FALTA ação corretiva (L=2)",IF(AND(LEFT(T30,6)="ASPETO",AH30=""),"Sugestão: definir monitorização","OK"))),"OK") -> OK | AJ30: Não | AK30: 46162 | AL30: =IF(AK30="","",EDATE(AK30,12)) -> 46527 | AM30: Gestor do SGA + responsável do setor
A31: AA-027 | B31: PRS | C31: Parque de resíduos | D31: Armazenagem temporária de resíduos | E31: Fim de Vida | F31: Contaminação do solo | G31: Escorrência de resíduos perigosos armazenados para a rede pluvial em dia de chuva | H31: Direto | I31: Anormal | J31: Presente | K31: IMP-02 | L31: =IFERROR(INDEX(tbl_impactes[Impacte],MATCH(K31,tbl_impactes[ID_Impacte],0)),"") -> Contaminação do Solo e/ou Recursos Hídricos | N31: 2 | O31: 2 | P31: 4 | Q31: 1 | R31: =IF(P31="","",IF(P31<0,"(-) Benéfico","(+) Adverso")) -> (+) Adverso | S31: =IF(COUNT(N31,O31,P31,Q31)<4,"",(N31+O31)*P31*Q31) -> 16 | T31: =IF(S31="","",IF(OR(Q31=2,S31>=40),"ASPETO AMBIENTAL SIGNIFICATIVO (AAS)",IF(S31>=20,"Moderado",IF(S31>=0,"Não Significativo",IF(S31>=-14,"Oportunidade Tática","ASPETO AMBIENTAL SIGNIFICATIVO (AAS) BENÉFICO"))))) -> Não Significativo | U31: =IF(S31="","",IF(Q31=2,"Regra de ouro (L=2)",IF(S31>=40,"IRA ≥ 40",IF(S31>=20,"IRA 20-39",IF(S31>=0,"IRA 0-19",IF(S31>=-14,"IRA -1 a -14","IRA ≤ -15")))))) -> IRA 0-19 | V31: =IF(S31="","",RANK(S31,$S$5:$S$47,0)) -> 28 | W31: =IF(T31="","",IF(OR(T31="ASPETO AMBIENTAL SIGNIFICATIVO (AAS)",T31="Moderado"),"SIM","NÃO")) -> NÃO | X31: Cobertura e bacia no ponto de resíduos perigosos. | Y31: Contentores fechados. | AB31: Ronda ambiental | AC31: F2; M2; G4. | AD31: LEG-01 | AE31: RO-10 | AH31: MED-10 | AI31: =IF(W31="SIM",IF(X31="","FALTA medida de controlo",IF(AND(LEFT(T31,6)="ASPETO",Q31=2,AG31=""),"FALTA ação corretiva (L=2)",IF(AND(LEFT(T31,6)="ASPETO",AH31=""),"Sugestão: definir monitorização","OK"))),"OK") -> OK | AJ31: Não | AK31: 46162 | AL31: =IF(AK31="","",EDATE(AK31,12)) -> 46527 | AM31: Gestor do SGA + responsável do setor
A32: AA-028 | B32: PRS | C32: Parque de resíduos | D32: Encaminhamento de resíduos | E32: Fim de Vida | F32: Resíduos | G32: Envio de scrap sujo e embalagens para reciclagem por operador licenciado (R3) | H32: Indireto | I32: Normal | J32: Presente | K32: IMP-11 | L32: =IFERROR(INDEX(tbl_impactes[Impacte],MATCH(K32,tbl_impactes[ID_Impacte],0)),"") -> Extensão do ciclo de vida de materiais (conversão de resíduos em subprodutos) | M32: IMP-12 | N32: 4 | O32: 3 | P32: -1 | Q32: 1 | R32: =IF(P32="","",IF(P32<0,"(-) Benéfico","(+) Adverso")) -> (-) Benéfico | S32: =IF(COUNT(N32,O32,P32,Q32)<4,"",(N32+O32)*P32*Q32) -> -7 | T32: =IF(S32="","",IF(OR(Q32=2,S32>=40),"ASPETO AMBIENTAL SIGNIFICATIVO (AAS)",IF(S32>=20,"Moderado",IF(S32>=0,"Não Significativo",IF(S32>=-14,"Oportunidade Tática","ASPETO AMBIENTAL SIGNIFICATIVO (AAS) BENÉFICO"))))) -> Oportunidade Tática | U32: =IF(S32="","",IF(Q32=2,"Regra de ouro (L=2)",IF(S32>=40,"IRA ≥ 40",IF(S32>=20,"IRA 20-39",IF(S32>=0,"IRA 0-19",IF(S32>=-14,"IRA -1 a -14","IRA ≤ -15")))))) -> IRA -1 a -14 | V32: =IF(S32="","",RANK(S32,$S$5:$S$47,0)) -> 40 | W32: =IF(T32="","",IF(OR(T32="ASPETO AMBIENTAL SIGNIFICATIVO (AAS)",T32="Moderado"),"SIM","NÃO")) -> NÃO | X32: Aumentar a segregação para subir a taxa de valorização. | Y32: Contratos com operadores. | AB32: e-GAR | AC32: Aspeto benéfico: G -1 (resíduo convertido em matéria-prima secundária). | AD32: LEG-01 | AH32: MED-04 | AI32: =IF(W32="SIM",IF(X32="","FALTA medida de controlo",IF(AND(LEFT(T32,6)="ASPETO",Q32=2,AG32=""),"FALTA ação corretiva (L=2)",IF(AND(LEFT(T32,6)="ASPETO",AH32=""),"Sugestão: definir monitorização","OK"))),"OK") -> OK | AJ32: Não | AK32: 46162 | AL32: =IF(AK32="","",EDATE(AK32,12)) -> 46527 | AM32: Gestor do SGA + responsável do setor
A33: AA-029 | B33: GER | C33: Geral | D33: Funcionamento geral da instalação | E33: Produção | F33: Resíduos | G33: Resíduos indiferenciados (20 03 01) enviados para aterro | H33: Direto | I33: Normal | J33: Presente | K33: IMP-07 | L33: =IFERROR(INDEX(tbl_impactes[Impacte],MATCH(K33,tbl_impactes[ID_Impacte],0)),"") -> Redução da vida útil de aterros e passivos ambientais | N33: 5 | O33: 3 | P33: 2 | Q33: 1 | R33: =IF(P33="","",IF(P33<0,"(-) Benéfico","(+) Adverso")) -> (+) Adverso | S33: =IF(COUNT(N33,O33,P33,Q33)<4,"",(N33+O33)*P33*Q33) -> 16 | T33: =IF(S33="","",IF(OR(Q33=2,S33>=40),"ASPETO AMBIENTAL SIGNIFICATIVO (AAS)",IF(S33>=20,"Moderado",IF(S33>=0,"Não Significativo",IF(S33>=-14,"Oportunidade Tática","ASPETO AMBIENTAL SIGNIFICATIVO (AAS) BENÉFICO"))))) -> Não Significativo | U33: =IF(S33="","",IF(Q33=2,"Regra de ouro (L=2)",IF(S33>=40,"IRA ≥ 40",IF(S33>=20,"IRA 20-39",IF(S33>=0,"IRA 0-19",IF(S33>=-14,"IRA -1 a -14","IRA ≤ -15")))))) -> IRA 0-19 | V33: =IF(S33="","",RANK(S33,$S$5:$S$47,0)) -> 28 | W33: =IF(T33="","",IF(OR(T33="ASPETO AMBIENTAL SIGNIFICATIVO (AAS)",T33="Moderado"),"SIM","NÃO")) -> NÃO | X33: Reduzir contaminação dos fluxos recicláveis. | Y33: Ecopontos. | AB33: Pesagens / e-GAR | AC33: F5; M3; G2. | AD33: LEG-01 | AH33: MED-04 | AI33: =IF(W33="SIM",IF(X33="","FALTA medida de controlo",IF(AND(LEFT(T33,6)="ASPETO",Q33=2,AG33=""),"FALTA ação corretiva (L=2)",IF(AND(LEFT(T33,6)="ASPETO",AH33=""),"Sugestão: definir monitorização","OK"))),"OK") -> OK | AJ33: Não | AK33: 46162 | AL33: =IF(AK33="","",EDATE(AK33,12)) -> 46527 | AM33: Gestor do SGA + responsável do setor
A34: AA-030 | B34: GER | C34: Geral | D34: Iluminação, AVAC, escritórios | E34: Produção | F34: Consumo de recursos | G34: Consumo de energia elétrica geral (iluminação, AVAC, armazéns) | H34: Direto | I34: Normal | J34: Presente | K34: IMP-01 | L34: =IFERROR(INDEX(tbl_impactes[Impacte],MATCH(K34,tbl_impactes[ID_Impacte],0)),"") -> Esgotamento de Recursos Naturais / Recursos | M34: IMP-04 | N34: 5 | O34: 3 | P34: 3 | Q34: 1 | R34: =IF(P34="","",IF(P34<0,"(-) Benéfico","(+) Adverso")) -> (+) Adverso | S34: =IF(COUNT(N34,O34,P34,Q34)<4,"",(N34+O34)*P34*Q34) -> 24 | T34: =IF(S34="","",IF(OR(Q34=2,S34>=40),"ASPETO AMBIENTAL SIGNIFICATIVO (AAS)",IF(S34>=20,"Moderado",IF(S34>=0,"Não Significativo",IF(S34>=-14,"Oportunidade Tática","ASPETO AMBIENTAL SIGNIFICATIVO (AAS) BENÉFICO"))))) -> Moderado | U34: =IF(S34="","",IF(Q34=2,"Regra de ouro (L=2)",IF(S34>=40,"IRA ≥ 40",IF(S34>=20,"IRA 20-39",IF(S34>=0,"IRA 0-19",IF(S34>=-14,"IRA -1 a -14","IRA ≤ -15")))))) -> IRA 20-39 | V34: =IF(S34="","",RANK(S34,$S$5:$S$47,0)) -> 18 | W34: =IF(T34="","",IF(OR(T34="ASPETO AMBIENTAL SIGNIFICATIVO (AAS)",T34="Moderado"),"SIM","NÃO")) -> SIM | X34: LED com sensores; horários de AVAC. | Y34: — | Z34: 553.9 | AA34: MWh/ano | AB34: Rateio da fatura | AC34: F5; M3; G3. | AF34: OBJ-01 | AH34: MED-01 | AI34: =IF(W34="SIM",IF(X34="","FALTA medida de controlo",IF(AND(LEFT(T34,6)="ASPETO",Q34=2,AG34=""),"FALTA ação corretiva (L=2)",IF(AND(LEFT(T34,6)="ASPETO",AH34=""),"Sugestão: definir monitorização","OK"))),"OK") -> OK | AJ34: Não | AK34: 46162 | AL34: =IF(AK34="","",EDATE(AK34,12)) -> 46527 | AM34: Gestor do SGA + responsável do setor
A35: AA-031 | B35: GER | C35: Geral | D35: Contrato de eletricidade | E35: Produção | F35: Consumo de recursos | G35: Consumo de eletricidade com garantia de origem renovável (55% do mix) | H35: Direto | I35: Normal | J35: Presente | K35: IMP-12 | L35: =IFERROR(INDEX(tbl_impactes[Impacte],MATCH(K35,tbl_impactes[ID_Impacte],0)),"") -> Minimização da Pressão Ecológica (materiais recicláveis ou de origem sustentável) | M35: IMP-04 | N35: 5 | O35: 5 | P35: -1 | Q35: 1 | R35: =IF(P35="","",IF(P35<0,"(-) Benéfico","(+) Adverso")) -> (-) Benéfico | S35: =IF(COUNT(N35,O35,P35,Q35)<4,"",(N35+O35)*P35*Q35) -> -10 | T35: =IF(S35="","",IF(OR(Q35=2,S35>=40),"ASPETO AMBIENTAL SIGNIFICATIVO (AAS)",IF(S35>=20,"Moderado",IF(S35>=0,"Não Significativo",IF(S35>=-14,"Oportunidade Tática","ASPETO AMBIENTAL SIGNIFICATIVO (AAS) BENÉFICO"))))) -> Oportunidade Tática | U35: =IF(S35="","",IF(Q35=2,"Regra de ouro (L=2)",IF(S35>=40,"IRA ≥ 40",IF(S35>=20,"IRA 20-39",IF(S35>=0,"IRA 0-19",IF(S35>=-14,"IRA -1 a -14","IRA ≤ -15")))))) -> IRA -1 a -14 | V35: =IF(S35="","",RANK(S35,$S$5:$S$47,0)) -> 42 | W35: =IF(T35="","",IF(OR(T35="ASPETO AMBIENTAL SIGNIFICATIVO (AAS)",T35="Moderado"),"SIM","NÃO")) -> NÃO | X35: Aumentar a quota renovável no próximo contrato. | Y35: Contrato 2026. | Z35: 4280 | AA35: MWh renováveis/ano | AB35: Rótulo de energia do comercializador | AC35: Aspeto benéfico: G -1. | AE35: RO-09 | AH35: MED-01 | AI35: =IF(W35="SIM",IF(X35="","FALTA medida de controlo",IF(AND(LEFT(T35,6)="ASPETO",Q35=2,AG35=""),"FALTA ação corretiva (L=2)",IF(AND(LEFT(T35,6)="ASPETO",AH35=""),"Sugestão: definir monitorização","OK"))),"OK") -> OK | AJ35: Não | AK35: 46162 | AL35: =IF(AK35="","",EDATE(AK35,12)) -> 46527 | AM35: Gestor do SGA + responsável do setor
A36: AA-032 | B36: GER | C36: Geral | D36: Autoconsumo fotovoltaico previsto (UPAC ≈ 1 MWp) | E36: Produção | F36: Consumo de recursos | G36: Produção de energia renovável para autoconsumo | H36: Direto | I36: Normal | J36: Futuro | K36: IMP-12 | L36: =IFERROR(INDEX(tbl_impactes[Impacte],MATCH(K36,tbl_impactes[ID_Impacte],0)),"") -> Minimização da Pressão Ecológica (materiais recicláveis ou de origem sustentável) | M36: IMP-04 | N36: 5 | O36: 4 | P36: -2 | Q36: 1 | R36: =IF(P36="","",IF(P36<0,"(-) Benéfico","(+) Adverso")) -> (-) Benéfico | S36: =IF(COUNT(N36,O36,P36,Q36)<4,"",(N36+O36)*P36*Q36) -> -18 | T36: =IF(S36="","",IF(OR(Q36=2,S36>=40),"ASPETO AMBIENTAL SIGNIFICATIVO (AAS)",IF(S36>=20,"Moderado",IF(S36>=0,"Não Significativo",IF(S36>=-14,"Oportunidade Tática","ASPETO AMBIENTAL SIGNIFICATIVO (AAS) BENÉFICO"))))) -> ASPETO AMBIENTAL SIGNIFICATIVO (AAS) BENÉFICO | U36: =IF(S36="","",IF(Q36=2,"Regra de ouro (L=2)",IF(S36>=40,"IRA ≥ 40",IF(S36>=20,"IRA 20-39",IF(S36>=0,"IRA 0-19",IF(S36>=-14,"IRA -1 a -14","IRA ≤ -15")))))) -> IRA ≤ -15 | V36: =IF(S36="","",RANK(S36,$S$5:$S$47,0)) -> 43 | W36: =IF(T36="","",IF(OR(T36="ASPETO AMBIENTAL SIGNIFICATIVO (AAS)",T36="Moderado"),"SIM","NÃO")) -> NÃO | X36: Estudo de viabilidade e candidatura. | Y36: — | Z36: 1400 | AA36: MWh/ano (estimativa) | AB36: Estudo preliminar | AC36: Aspeto benéfico futuro: G -2 regenerativo/descarbonização. | AE36: RO-09 | AI36: =IF(W36="SIM",IF(X36="","FALTA medida de controlo",IF(AND(LEFT(T36,6)="ASPETO",Q36=2,AG36=""),"FALTA ação corretiva (L=2)",IF(AND(LEFT(T36,6)="ASPETO",AH36=""),"Sugestão: definir monitorização","OK"))),"OK") -> OK | AJ36: Não | AK36: 46162 | AL36: =IF(AK36="","",EDATE(AK36,12)) -> 46527 | AM36: Gestor do SGA + responsável do setor
A37: AA-033 | B37: GER | C37: Geral | D37: Ocupação do terreno industrial | E37: Produção | F37: Ocupação do solo | G37: Impermeabilização do solo (≈ 32.000 m² construídos e pavimentados) e escoamento pluvial | H37: Direto | I37: Normal | J37: Passado | K37: IMP-06 | L37: =IFERROR(INDEX(tbl_impactes[Impacte],MATCH(K37,tbl_impactes[ID_Impacte],0)),"") -> Perturbação da Fauna / Flora / Paisagem | M37: IMP-02 | N37: 5 | O37: 3 | P37: 2 | Q37: 1 | R37: =IF(P37="","",IF(P37<0,"(-) Benéfico","(+) Adverso")) -> (+) Adverso | S37: =IF(COUNT(N37,O37,P37,Q37)<4,"",(N37+O37)*P37*Q37) -> 16 | T37: =IF(S37="","",IF(OR(Q37=2,S37>=40),"ASPETO AMBIENTAL SIGNIFICATIVO (AAS)",IF(S37>=20,"Moderado",IF(S37>=0,"Não Significativo",IF(S37>=-14,"Oportunidade Tática","ASPETO AMBIENTAL SIGNIFICATIVO (AAS) BENÉFICO"))))) -> Não Significativo | U37: =IF(S37="","",IF(Q37=2,"Regra de ouro (L=2)",IF(S37>=40,"IRA ≥ 40",IF(S37>=20,"IRA 20-39",IF(S37>=0,"IRA 0-19",IF(S37>=-14,"IRA -1 a -14","IRA ≤ -15")))))) -> IRA 0-19 | V37: =IF(S37="","",RANK(S37,$S$5:$S$47,0)) -> 28 | W37: =IF(T37="","",IF(OR(T37="ASPETO AMBIENTAL SIGNIFICATIVO (AAS)",T37="Moderado"),"SIM","NÃO")) -> NÃO | X37: Áreas verdes com espécies nativas; pavimento permeável em ampliações. | Y37: — | Z37: 32000 | AA37: m² área impermeabilizada | AB37: Planta da instalação | AC37: Aspeto de biodiversidade (ISO 14001:2026): herdado da construção. | AI37: =IF(W37="SIM",IF(X37="","FALTA medida de controlo",IF(AND(LEFT(T37,6)="ASPETO",Q37=2,AG37=""),"FALTA ação corretiva (L=2)",IF(AND(LEFT(T37,6)="ASPETO",AH37=""),"Sugestão: definir monitorização","OK"))),"OK") -> OK | AJ37: Não | AK37: 46162 | AL37: =IF(AK37="","",EDATE(AK37,12)) -> 46527 | AM37: Gestor do SGA + responsável do setor
A38: AA-034 | B38: GER | C38: Geral | D38: Incêndio na instalação | E38: Produção | F38: Emissões atmosféricas | G38: Fumos de combustão de plástico e águas de combate contaminadas (incêndio) | H38: Direto | I38: Emergência | J38: Futuro | K38: IMP-03 | L38: =IFERROR(INDEX(tbl_impactes[Impacte],MATCH(K38,tbl_impactes[ID_Impacte],0)),"") -> Poluição do Ar | M38: IMP-02; IMP-06 | N38: 1 | O38: 5 | P38: 5 | Q38: 1 | R38: =IF(P38="","",IF(P38<0,"(-) Benéfico","(+) Adverso")) -> (+) Adverso | S38: =IF(COUNT(N38,O38,P38,Q38)<4,"",(N38+O38)*P38*Q38) -> 30 | T38: =IF(S38="","",IF(OR(Q38=2,S38>=40),"ASPETO AMBIENTAL SIGNIFICATIVO (AAS)",IF(S38>=20,"Moderado",IF(S38>=0,"Não Significativo",IF(S38>=-14,"Oportunidade Tática","ASPETO AMBIENTAL SIGNIFICATIVO (AAS) BENÉFICO"))))) -> Moderado | U38: =IF(S38="","",IF(Q38=2,"Regra de ouro (L=2)",IF(S38>=40,"IRA ≥ 40",IF(S38>=20,"IRA 20-39",IF(S38>=0,"IRA 0-19",IF(S38>=-14,"IRA -1 a -14","IRA ≤ -15")))))) -> IRA 20-39 | V38: =IF(S38="","",RANK(S38,$S$5:$S$47,0)) -> 5 | W38: =IF(T38="","",IF(OR(T38="ASPETO AMBIENTAL SIGNIFICATIVO (AAS)",T38="Moderado"),"SIM","NÃO")) -> SIM | X38: Deteção, válvula de corte pluvial, simulacro anual, faixa de gestão de combustível. | Y38: Medidas de autoproteção (SCIE). | AB38: Plano de emergência | AC38: F1; M5 grande carga de incêndio; G5. | AD38: LEG-11 | AE38: RO-08 | AI38: =IF(W38="SIM",IF(X38="","FALTA medida de controlo",IF(AND(LEFT(T38,6)="ASPETO",Q38=2,AG38=""),"FALTA ação corretiva (L=2)",IF(AND(LEFT(T38,6)="ASPETO",AH38=""),"Sugestão: definir monitorização","OK"))),"OK") -> OK | AJ38: Não | AK38: 46162 | AL38: =IF(AK38="","",EDATE(AK38,12)) -> 46527 | AM38: Gestor do SGA + responsável do setor
A39: AA-035 | B39: GER | C39: Geral | D39: Uso de instalações sanitárias | E39: Produção | F39: Efluentes | G39: Águas residuais domésticas descarregadas no coletor municipal | H39: Direto | I39: Normal | J39: Presente | K39: IMP-02 | L39: =IFERROR(INDEX(tbl_impactes[Impacte],MATCH(K39,tbl_impactes[ID_Impacte],0)),"") -> Contaminação do Solo e/ou Recursos Hídricos | N39: 5 | O39: 2 | P39: 2 | Q39: 1 | R39: =IF(P39="","",IF(P39<0,"(-) Benéfico","(+) Adverso")) -> (+) Adverso | S39: =IF(COUNT(N39,O39,P39,Q39)<4,"",(N39+O39)*P39*Q39) -> 14 | T39: =IF(S39="","",IF(OR(Q39=2,S39>=40),"ASPETO AMBIENTAL SIGNIFICATIVO (AAS)",IF(S39>=20,"Moderado",IF(S39>=0,"Não Significativo",IF(S39>=-14,"Oportunidade Tática","ASPETO AMBIENTAL SIGNIFICATIVO (AAS) BENÉFICO"))))) -> Não Significativo | U39: =IF(S39="","",IF(Q39=2,"Regra de ouro (L=2)",IF(S39>=40,"IRA ≥ 40",IF(S39>=20,"IRA 20-39",IF(S39>=0,"IRA 0-19",IF(S39>=-14,"IRA -1 a -14","IRA ≤ -15")))))) -> IRA 0-19 | V39: =IF(S39="","",RANK(S39,$S$5:$S$47,0)) -> 34 | W39: =IF(T39="","",IF(OR(T39="ASPETO AMBIENTAL SIGNIFICATIVO (AAS)",T39="Moderado"),"SIM","NÃO")) -> NÃO | X39: — | Y39: Ligação ao coletor. | Z39: 1849 | AA39: m³/ano | AB39: Estimativa (água sanitária) | AC39: F5; M2; G2. | AD39: LEG-03 | AI39: =IF(W39="SIM",IF(X39="","FALTA medida de controlo",IF(AND(LEFT(T39,6)="ASPETO",Q39=2,AG39=""),"FALTA ação corretiva (L=2)",IF(AND(LEFT(T39,6)="ASPETO",AH39=""),"Sugestão: definir monitorização","OK"))),"OK") -> OK | AJ39: Não | AK39: 46162 | AL39: =IF(AK39="","",EDATE(AK39,12)) -> 46527 | AM39: Gestor do SGA + responsável do setor
A40: AA-036 | B40: ADM | C40: Administrativos | D40: Trabalho de escritório | E40: Produção | F40: Consumo de recursos | G40: Consumo de papel e toners | H40: Direto | I40: Normal | J40: Presente | K40: IMP-01 | L40: =IFERROR(INDEX(tbl_impactes[Impacte],MATCH(K40,tbl_impactes[ID_Impacte],0)),"") -> Esgotamento de Recursos Naturais / Recursos | M40: IMP-07 | N40: 4 | O40: 1 | P40: 1 | Q40: 1 | R40: =IF(P40="","",IF(P40<0,"(-) Benéfico","(+) Adverso")) -> (+) Adverso | S40: =IF(COUNT(N40,O40,P40,Q40)<4,"",(N40+O40)*P40*Q40) -> 5 | T40: =IF(S40="","",IF(OR(Q40=2,S40>=40),"ASPETO AMBIENTAL SIGNIFICATIVO (AAS)",IF(S40>=20,"Moderado",IF(S40>=0,"Não Significativo",IF(S40>=-14,"Oportunidade Tática","ASPETO AMBIENTAL SIGNIFICATIVO (AAS) BENÉFICO"))))) -> Não Significativo | U40: =IF(S40="","",IF(Q40=2,"Regra de ouro (L=2)",IF(S40>=40,"IRA ≥ 40",IF(S40>=20,"IRA 20-39",IF(S40>=0,"IRA 0-19",IF(S40>=-14,"IRA -1 a -14","IRA ≤ -15")))))) -> IRA 0-19 | V40: =IF(S40="","",RANK(S40,$S$5:$S$47,0)) -> 38 | W40: =IF(T40="","",IF(OR(T40="ASPETO AMBIENTAL SIGNIFICATIVO (AAS)",T40="Moderado"),"SIM","NÃO")) -> NÃO | X40: Documentação digital. | Y40: — | AB40: Compras | AC40: F4; M1; G1. | AI40: =IF(W40="SIM",IF(X40="","FALTA medida de controlo",IF(AND(LEFT(T40,6)="ASPETO",Q40=2,AG40=""),"FALTA ação corretiva (L=2)",IF(AND(LEFT(T40,6)="ASPETO",AH40=""),"Sugestão: definir monitorização","OK"))),"OK") -> OK | AJ40: Não | AK40: 46162 | AL40: =IF(AK40="","",EDATE(AK40,12)) -> 46527 | AM40: Gestor do SGA + responsável do setor
A41: AA-037 | B41: RD | C41: R&D | D41: Conceção de novas embalagens | E41: Design e Conceção | F41: Consumo de recursos | G41: Escolha de material, peso e combinação de componentes das embalagens (define impactes a montante e no fim de vida) | H41: Direto | I41: Normal | J41: Presente | K41: IMP-01 | L41: =IFERROR(INDEX(tbl_impactes[Impacte],MATCH(K41,tbl_impactes[ID_Impacte],0)),"") -> Esgotamento de Recursos Naturais / Recursos | M41: IMP-07 | N41: 4 | O41: 5 | P41: 3 | Q41: 1 | R41: =IF(P41="","",IF(P41<0,"(-) Benéfico","(+) Adverso")) -> (+) Adverso | S41: =IF(COUNT(N41,O41,P41,Q41)<4,"",(N41+O41)*P41*Q41) -> 27 | T41: =IF(S41="","",IF(OR(Q41=2,S41>=40),"ASPETO AMBIENTAL SIGNIFICATIVO (AAS)",IF(S41>=20,"Moderado",IF(S41>=0,"Não Significativo",IF(S41>=-14,"Oportunidade Tática","ASPETO AMBIENTAL SIGNIFICATIVO (AAS) BENÉFICO"))))) -> Moderado | U41: =IF(S41="","",IF(Q41=2,"Regra de ouro (L=2)",IF(S41>=40,"IRA ≥ 40",IF(S41>=20,"IRA 20-39",IF(S41>=0,"IRA 0-19",IF(S41>=-14,"IRA -1 a -14","IRA ≤ -15")))))) -> IRA 20-39 | V41: =IF(S41="","",RANK(S41,$S$5:$S$47,0)) -> 12 | W41: =IF(T41="","",IF(OR(T41="ASPETO AMBIENTAL SIGNIFICATIVO (AAS)",T41="Moderado"),"SIM","NÃO")) -> SIM | X41: Checklist Design for Recycling; monomaterial; redução de peso. | Y41: — | AB41: Dossier de desenvolvimento | AC41: F4 cada projeto; M5 afeta todo o volume; G3. | AD41: LEG-09 | AE41: RO-03 | AF41: OBJ-04 | AG41: PAM-26-10 | AI41: =IF(W41="SIM",IF(X41="","FALTA medida de controlo",IF(AND(LEFT(T41,6)="ASPETO",Q41=2,AG41=""),"FALTA ação corretiva (L=2)",IF(AND(LEFT(T41,6)="ASPETO",AH41=""),"Sugestão: definir monitorização","OK"))),"OK") -> OK | AJ41: Não | AK41: 46162 | AL41: =IF(AK41="","",EDATE(AK41,12)) -> 46527 | AM41: Gestor do SGA + responsável do setor
A42: AA-038 | B42: RD | C42: R&D | D42: Colocação de embalagens no mercado UE | E42: Design e Conceção | F42: Consumo de recursos | G42: Embalagens colocadas no mercado sem documentação técnica nem declaração UE de conformidade PPWR | H42: Direto | I42: Normal | J42: Presente | K42: IMP-07 | L42: =IFERROR(INDEX(tbl_impactes[Impacte],MATCH(K42,tbl_impactes[ID_Impacte],0)),"") -> Redução da vida útil de aterros e passivos ambientais | M42: IMP-01 | N42: 5 | O42: 5 | P42: 3 | Q42: 2 | R42: =IF(P42="","",IF(P42<0,"(-) Benéfico","(+) Adverso")) -> (+) Adverso | S42: =IF(COUNT(N42,O42,P42,Q42)<4,"",(N42+O42)*P42*Q42) -> 60 | T42: =IF(S42="","",IF(OR(Q42=2,S42>=40),"ASPETO AMBIENTAL SIGNIFICATIVO (AAS)",IF(S42>=20,"Moderado",IF(S42>=0,"Não Significativo",IF(S42>=-14,"Oportunidade Tática","ASPETO AMBIENTAL SIGNIFICATIVO (AAS) BENÉFICO"))))) -> ASPETO AMBIENTAL SIGNIFICATIVO (AAS) | U42: =IF(S42="","",IF(Q42=2,"Regra de ouro (L=2)",IF(S42>=40,"IRA ≥ 40",IF(S42>=20,"IRA 20-39",IF(S42>=0,"IRA 0-19",IF(S42>=-14,"IRA -1 a -14","IRA ≤ -15")))))) -> Regra de ouro (L=2) | V42: =IF(S42="","",RANK(S42,$S$5:$S$47,0)) -> 1 | W42: =IF(T42="","",IF(OR(T42="ASPETO AMBIENTAL SIGNIFICATIVO (AAS)",T42="Moderado"),"SIM","NÃO")) -> SIM | X42: Dossier técnico por família (OBJ-04). | Y42: Fichas técnicas. | AB42: Avaliação de conformidade LEG-09 | AC42: L2: incumprimento do Reg. (UE) 2025/40 desde 12/08/2026 → AAS pela regra de ouro. | AD42: LEG-09 | AE42: RO-06 | AF42: OBJ-04 | AG42: PAM-26-10 | AH42: MED-12 | AI42: =IF(W42="SIM",IF(X42="","FALTA medida de controlo",IF(AND(LEFT(T42,6)="ASPETO",Q42=2,AG42=""),"FALTA ação corretiva (L=2)",IF(AND(LEFT(T42,6)="ASPETO",AH42=""),"Sugestão: definir monitorização","OK"))),"OK") -> OK | AJ42: Não | AK42: 46162 | AL42: =IF(AK42="","",EDATE(AK42,12)) -> 46527 | AM42: Gestor do SGA + responsável do setor
A43: AA-039 | B43: EXP | C43: Expedição | D43: Embalagem de produto acabado | E43: Distribuição | F43: Consumo de recursos | G43: Consumo de cartão, filme estirável e paletes | H43: Direto | I43: Normal | J43: Presente | K43: IMP-01 | L43: =IFERROR(INDEX(tbl_impactes[Impacte],MATCH(K43,tbl_impactes[ID_Impacte],0)),"") -> Esgotamento de Recursos Naturais / Recursos | M43: IMP-07 | N43: 5 | O43: 4 | P43: 2 | Q43: 1 | R43: =IF(P43="","",IF(P43<0,"(-) Benéfico","(+) Adverso")) -> (+) Adverso | S43: =IF(COUNT(N43,O43,P43,Q43)<4,"",(N43+O43)*P43*Q43) -> 18 | T43: =IF(S43="","",IF(OR(Q43=2,S43>=40),"ASPETO AMBIENTAL SIGNIFICATIVO (AAS)",IF(S43>=20,"Moderado",IF(S43>=0,"Não Significativo",IF(S43>=-14,"Oportunidade Tática","ASPETO AMBIENTAL SIGNIFICATIVO (AAS) BENÉFICO"))))) -> Não Significativo | U43: =IF(S43="","",IF(Q43=2,"Regra de ouro (L=2)",IF(S43>=40,"IRA ≥ 40",IF(S43>=20,"IRA 20-39",IF(S43>=0,"IRA 0-19",IF(S43>=-14,"IRA -1 a -14","IRA ≤ -15")))))) -> IRA 0-19 | V43: =IF(S43="","",RANK(S43,$S$5:$S$47,0)) -> 27 | W43: =IF(T43="","",IF(OR(T43="ASPETO AMBIENTAL SIGNIFICATIVO (AAS)",T43="Moderado"),"SIM","NÃO")) -> NÃO | X43: Caixas e paletes retornáveis com clientes ibéricos. | Y43: — | AB43: Compras | AC43: F5; M4; G2. | AI43: =IF(W43="SIM",IF(X43="","FALTA medida de controlo",IF(AND(LEFT(T43,6)="ASPETO",Q43=2,AG43=""),"FALTA ação corretiva (L=2)",IF(AND(LEFT(T43,6)="ASPETO",AH43=""),"Sugestão: definir monitorização","OK"))),"OK") -> OK | AJ43: Não | AK43: 46162 | AL43: =IF(AK43="","",EDATE(AK43,12)) -> 46527 | AM43: Gestor do SGA + responsável do setor
A44: AA-040 | B44: EXP | C44: Expedição | D44: Transporte de produto a clientes | E44: Distribuição | F44: Emissões atmosféricas | G44: Emissões do transporte rodoviário de produto acabado (Península Ibérica e UE) | H44: Indireto | I44: Normal | J44: Presente | K44: IMP-04 | L44: =IFERROR(INDEX(tbl_impactes[Impacte],MATCH(K44,tbl_impactes[ID_Impacte],0)),"") -> Mudanças Climáticas | M44: IMP-03; IMP-05 | N44: 5 | O44: 4 | P44: 3 | Q44: 1 | R44: =IF(P44="","",IF(P44<0,"(-) Benéfico","(+) Adverso")) -> (+) Adverso | S44: =IF(COUNT(N44,O44,P44,Q44)<4,"",(N44+O44)*P44*Q44) -> 27 | T44: =IF(S44="","",IF(OR(Q44=2,S44>=40),"ASPETO AMBIENTAL SIGNIFICATIVO (AAS)",IF(S44>=20,"Moderado",IF(S44>=0,"Não Significativo",IF(S44>=-14,"Oportunidade Tática","ASPETO AMBIENTAL SIGNIFICATIVO (AAS) BENÉFICO"))))) -> Moderado | U44: =IF(S44="","",IF(Q44=2,"Regra de ouro (L=2)",IF(S44>=40,"IRA ≥ 40",IF(S44>=20,"IRA 20-39",IF(S44>=0,"IRA 0-19",IF(S44>=-14,"IRA -1 a -14","IRA ≤ -15")))))) -> IRA 20-39 | V44: =IF(S44="","",RANK(S44,$S$5:$S$47,0)) -> 12 | W44: =IF(T44="","",IF(OR(T44="ASPETO AMBIENTAL SIGNIFICATIVO (AAS)",T44="Moderado"),"SIM","NÃO")) -> SIM | X44: Consolidação de cargas; critérios ambientais para transportadores. | Y44: — | AB44: Guias de transporte | AC44: F5; M4; G3. | AI44: =IF(W44="SIM",IF(X44="","FALTA medida de controlo",IF(AND(LEFT(T44,6)="ASPETO",Q44=2,AG44=""),"FALTA ação corretiva (L=2)",IF(AND(LEFT(T44,6)="ASPETO",AH44=""),"Sugestão: definir monitorização","OK"))),"OK") -> OK | AJ44: Não | AK44: 46162 | AL44: =IF(AK44="","",EDATE(AK44,12)) -> 46527 | AM44: Gestor do SGA + responsável do setor
A45: AA-041 | B45: EXP | C45: Expedição | D45: Embalagens de transporte retornáveis (piloto) | E45: Distribuição | F45: Resíduos | G45: Reutilização de caixas e paletes com clientes ibéricos | H45: Direto | I45: Normal | J45: Futuro | K45: IMP-11 | L45: =IFERROR(INDEX(tbl_impactes[Impacte],MATCH(K45,tbl_impactes[ID_Impacte],0)),"") -> Extensão do ciclo de vida de materiais (conversão de resíduos em subprodutos) | M45: IMP-10 | N45: 3 | O45: 3 | P45: -1 | Q45: 1 | R45: =IF(P45="","",IF(P45<0,"(-) Benéfico","(+) Adverso")) -> (-) Benéfico | S45: =IF(COUNT(N45,O45,P45,Q45)<4,"",(N45+O45)*P45*Q45) -> -6 | T45: =IF(S45="","",IF(OR(Q45=2,S45>=40),"ASPETO AMBIENTAL SIGNIFICATIVO (AAS)",IF(S45>=20,"Moderado",IF(S45>=0,"Não Significativo",IF(S45>=-14,"Oportunidade Tática","ASPETO AMBIENTAL SIGNIFICATIVO (AAS) BENÉFICO"))))) -> Oportunidade Tática | U45: =IF(S45="","",IF(Q45=2,"Regra de ouro (L=2)",IF(S45>=40,"IRA ≥ 40",IF(S45>=20,"IRA 20-39",IF(S45>=0,"IRA 0-19",IF(S45>=-14,"IRA -1 a -14","IRA ≤ -15")))))) -> IRA -1 a -14 | V45: =IF(S45="","",RANK(S45,$S$5:$S$47,0)) -> 39 | W45: =IF(T45="","",IF(OR(T45="ASPETO AMBIENTAL SIGNIFICATIVO (AAS)",T45="Moderado"),"SIM","NÃO")) -> NÃO | X45: Alargar a 3 clientes. | Y45: — | AB45: Piloto previsto 2027 | AC45: Aspeto benéfico: G -1. | AI45: =IF(W45="SIM",IF(X45="","FALTA medida de controlo",IF(AND(LEFT(T45,6)="ASPETO",Q45=2,AG45=""),"FALTA ação corretiva (L=2)",IF(AND(LEFT(T45,6)="ASPETO",AH45=""),"Sugestão: definir monitorização","OK"))),"OK") -> OK | AJ45: Não | AK45: 46162 | AL45: =IF(AK45="","",EDATE(AK45,12)) -> 46527 | AM45: Gestor do SGA + responsável do setor
A46: AA-042 | B46: GER | C46: Uso pelo cliente | D46: Enchimento e uso da embalagem pelo cliente e consumidor | E46: Uso (Consumidor Final) | F46: Resíduos | G46: Restos de produto cosmético/alimentar na embalagem usada | H46: Indireto | I46: Normal | J46: Presente | K46: IMP-02 | L46: =IFERROR(INDEX(tbl_impactes[Impacte],MATCH(K46,tbl_impactes[ID_Impacte],0)),"") -> Contaminação do Solo e/ou Recursos Hídricos | M46: IMP-07 | N46: 5 | O46: 2 | P46: 2 | Q46: 1 | R46: =IF(P46="","",IF(P46<0,"(-) Benéfico","(+) Adverso")) -> (+) Adverso | S46: =IF(COUNT(N46,O46,P46,Q46)<4,"",(N46+O46)*P46*Q46) -> 14 | T46: =IF(S46="","",IF(OR(Q46=2,S46>=40),"ASPETO AMBIENTAL SIGNIFICATIVO (AAS)",IF(S46>=20,"Moderado",IF(S46>=0,"Não Significativo",IF(S46>=-14,"Oportunidade Tática","ASPETO AMBIENTAL SIGNIFICATIVO (AAS) BENÉFICO"))))) -> Não Significativo | U46: =IF(S46="","",IF(Q46=2,"Regra de ouro (L=2)",IF(S46>=40,"IRA ≥ 40",IF(S46>=20,"IRA 20-39",IF(S46>=0,"IRA 0-19",IF(S46>=-14,"IRA -1 a -14","IRA ≤ -15")))))) -> IRA 0-19 | V46: =IF(S46="","",RANK(S46,$S$5:$S$47,0)) -> 34 | W46: =IF(T46="","",IF(OR(T46="ASPETO AMBIENTAL SIGNIFICATIVO (AAS)",T46="Moderado"),"SIM","NÃO")) -> NÃO | X46: Design que facilita o esvaziamento total. | Y46: — | AB46: — | AC46: F5; M2; G2. | AI46: =IF(W46="SIM",IF(X46="","FALTA medida de controlo",IF(AND(LEFT(T46,6)="ASPETO",Q46=2,AG46=""),"FALTA ação corretiva (L=2)",IF(AND(LEFT(T46,6)="ASPETO",AH46=""),"Sugestão: definir monitorização","OK"))),"OK") -> OK | AJ46: Não | AK46: 46162 | AL46: =IF(AK46="","",EDATE(AK46,12)) -> 46527 | AM46: Gestor do SGA + responsável do setor
A47: AA-043 | B47: GER | C47: Fim de vida | D47: Embalagem pós-consumo | E47: Fim de Vida | F47: Resíduos | G47: Embalagens pós-consumo não recicladas (aterro, incineração ou abandono) | H47: Indireto | I47: Normal | J47: Presente | K47: IMP-07 | L47: =IFERROR(INDEX(tbl_impactes[Impacte],MATCH(K47,tbl_impactes[ID_Impacte],0)),"") -> Redução da vida útil de aterros e passivos ambientais | M47: IMP-08; IMP-06 | N47: 5 | O47: 5 | P47: 3 | Q47: 1 | R47: =IF(P47="","",IF(P47<0,"(-) Benéfico","(+) Adverso")) -> (+) Adverso | S47: =IF(COUNT(N47,O47,P47,Q47)<4,"",(N47+O47)*P47*Q47) -> 30 | T47: =IF(S47="","",IF(OR(Q47=2,S47>=40),"ASPETO AMBIENTAL SIGNIFICATIVO (AAS)",IF(S47>=20,"Moderado",IF(S47>=0,"Não Significativo",IF(S47>=-14,"Oportunidade Tática","ASPETO AMBIENTAL SIGNIFICATIVO (AAS) BENÉFICO"))))) -> Moderado | U47: =IF(S47="","",IF(Q47=2,"Regra de ouro (L=2)",IF(S47>=40,"IRA ≥ 40",IF(S47>=20,"IRA 20-39",IF(S47>=0,"IRA 0-19",IF(S47>=-14,"IRA -1 a -14","IRA ≤ -15")))))) -> IRA 20-39 | V47: =IF(S47="","",RANK(S47,$S$5:$S$47,0)) -> 5 | W47: =IF(T47="","",IF(OR(T47="ASPETO AMBIENTAL SIGNIFICATIVO (AAS)",T47="Moderado"),"SIM","NÃO")) -> SIM | X47: Design for Recycling; informação ao cliente sobre reciclagem. | Y47: — | AB47: Taxas de reciclagem de embalagens plásticas (UE) | AC47: F5; M5 todo o volume vendido; G3. | AD47: LEG-09 | AE47: RO-03 | AF47: OBJ-04 | AI47: =IF(W47="SIM",IF(X47="","FALTA medida de controlo",IF(AND(LEFT(T47,6)="ASPETO",Q47=2,AG47=""),"FALTA ação corretiva (L=2)",IF(AND(LEFT(T47,6)="ASPETO",AH47=""),"Sugestão: definir monitorização","OK"))),"OK") -> OK | AJ47: Não | AK47: 46162 | AL47: =IF(AK47="","",EDATE(AK47,12)) -> 46527 | AM47: Gestor do SGA + responsável do setor

Sheet Aspeto_Impacte
A1: ID_Aspeto | B1: ID_Impacte | C1: Principal | D1: Impacte | E1: Classificacao | F1: IRA
A2: AA-001 | B2: IMP-01 | C2: Sim | D2: =IFERROR(INDEX(tbl_impactes[Impacte],MATCH(B2,tbl_impactes[ID_Impacte],0)),"") -> Esgotamento de Recursos Naturais / Recursos | E2: =IFERROR(INDEX(tbl_aspetos[Classificacao],MATCH(A2,tbl_aspetos[ID_Aspeto],0)),"") -> Moderado | F2: =IFERROR(INDEX(tbl_aspetos[IRA],MATCH(A2,tbl_aspetos[ID_Aspeto],0)),"") -> 20
A3: AA-001 | B3: IMP-04 | C3: Não | D3: =IFERROR(INDEX(tbl_impactes[Impacte],MATCH(B3,tbl_impactes[ID_Impacte],0)),"") -> Mudanças Climáticas | E3: =IFERROR(INDEX(tbl_aspetos[Classificacao],MATCH(A3,tbl_aspetos[ID_Aspeto],0)),"") -> Moderado | F3: =IFERROR(INDEX(tbl_aspetos[IRA],MATCH(A3,tbl_aspetos[ID_Aspeto],0)),"") -> 20
A4: AA-002 | B4: IMP-04 | C4: Sim | D4: =IFERROR(INDEX(tbl_impactes[Impacte],MATCH(B4,tbl_impactes[ID_Impacte],0)),"") -> Mudanças Climáticas | E4: =IFERROR(INDEX(tbl_aspetos[Classificacao],MATCH(A4,tbl_aspetos[ID_Aspeto],0)),"") -> Moderado | F4: =IFERROR(INDEX(tbl_aspetos[IRA],MATCH(A4,tbl_aspetos[ID_Aspeto],0)),"") -> 24
A5: AA-002 | B5: IMP-03 | C5: Não | D5: =IFERROR(INDEX(tbl_impactes[Impacte],MATCH(B5,tbl_impactes[ID_Impacte],0)),"") -> Poluição do Ar | E5: =IFERROR(INDEX(tbl_aspetos[Classificacao],MATCH(A5,tbl_aspetos[ID_Aspeto],0)),"") -> Moderado | F5: =IFERROR(INDEX(tbl_aspetos[IRA],MATCH(A5,tbl_aspetos[ID_Aspeto],0)),"") -> 24
A6: AA-003 | B6: IMP-08 | C6: Sim | D6: =IFERROR(INDEX(tbl_impactes[Impacte],MATCH(B6,tbl_impactes[ID_Impacte],0)),"") -> Degradação da saúde dos ecossistemas aquáticos (microplásticos) | E6: =IFERROR(INDEX(tbl_aspetos[Classificacao],MATCH(A6,tbl_aspetos[ID_Aspeto],0)),"") -> Moderado | F6: =IFERROR(INDEX(tbl_aspetos[IRA],MATCH(A6,tbl_aspetos[ID_Aspeto],0)),"") -> 28
A7: AA-003 | B7: IMP-02 | C7: Não | D7: =IFERROR(INDEX(tbl_impactes[Impacte],MATCH(B7,tbl_impactes[ID_Impacte],0)),"") -> Contaminação do Solo e/ou Recursos Hídricos | E7: =IFERROR(INDEX(tbl_aspetos[Classificacao],MATCH(A7,tbl_aspetos[ID_Aspeto],0)),"") -> Moderado | F7: =IFERROR(INDEX(tbl_aspetos[IRA],MATCH(A7,tbl_aspetos[ID_Aspeto],0)),"") -> 28
A8: AA-003 | B8: IMP-06 | C8: Não | D8: =IFERROR(INDEX(tbl_impactes[Impacte],MATCH(B8,tbl_impactes[ID_Impacte],0)),"") -> Perturbação da Fauna / Flora / Paisagem | E8: =IFERROR(INDEX(tbl_aspetos[Classificacao],MATCH(A8,tbl_aspetos[ID_Aspeto],0)),"") -> Moderado | F8: =IFERROR(INDEX(tbl_aspetos[IRA],MATCH(A8,tbl_aspetos[ID_Aspeto],0)),"") -> 28
A9: AA-004 | B9: IMP-07 | C9: Sim | D9: =IFERROR(INDEX(tbl_impactes[Impacte],MATCH(B9,tbl_impactes[ID_Impacte],0)),"") -> Redução da vida útil de aterros e passivos ambientais | E9: =IFERROR(INDEX(tbl_aspetos[Classificacao],MATCH(A9,tbl_aspetos[ID_Aspeto],0)),"") -> Não Significativo | F9: =IFERROR(INDEX(tbl_aspetos[IRA],MATCH(A9,tbl_aspetos[ID_Aspeto],0)),"") -> 14
A10: AA-004 | B10: IMP-01 | C10: Não | D10: =IFERROR(INDEX(tbl_impactes[Impacte],MATCH(B10,tbl_impactes[ID_Impacte],0)),"") -> Esgotamento de Recursos Naturais / Recursos | E10: =IFERROR(INDEX(tbl_aspetos[Classificacao],MATCH(A10,tbl_aspetos[ID_Aspeto],0)),"") -> Não Significativo | F10: =IFERROR(INDEX(tbl_aspetos[IRA],MATCH(A10,tbl_aspetos[ID_Aspeto],0)),"") -> 14
A11: AA-005 | B11: IMP-02 | C11: Sim | D11: =IFERROR(INDEX(tbl_impactes[Impacte],MATCH(B11,tbl_impactes[ID_Impacte],0)),"") -> Contaminação do Solo e/ou Recursos Hídricos | E11: =IFERROR(INDEX(tbl_aspetos[Classificacao],MATCH(A11,tbl_aspetos[ID_Aspeto],0)),"") -> Moderado | F11: =IFERROR(INDEX(tbl_aspetos[IRA],MATCH(A11,tbl_aspetos[ID_Aspeto],0)),"") -> 20
A12: AA-005 | B12: IMP-03 | C12: Não | D12: =IFERROR(INDEX(tbl_impactes[Impacte],MATCH(B12,tbl_impactes[ID_Impacte],0)),"") -> Poluição do Ar | E12: =IFERROR(INDEX(tbl_aspetos[Classificacao],MATCH(A12,tbl_aspetos[ID_Aspeto],0)),"") -> Moderado | F12: =IFERROR(INDEX(tbl_aspetos[IRA],MATCH(A12,tbl_aspetos[ID_Aspeto],0)),"") -> 20
A13: AA-006 | B13: IMP-03 | C13: Sim | D13: =IFERROR(INDEX(tbl_impactes[Impacte],MATCH(B13,tbl_impactes[ID_Impacte],0)),"") -> Poluição do Ar | E13: =IFERROR(INDEX(tbl_aspetos[Classificacao],MATCH(A13,tbl_aspetos[ID_Aspeto],0)),"") -> Moderado | F13: =IFERROR(INDEX(tbl_aspetos[IRA],MATCH(A13,tbl_aspetos[ID_Aspeto],0)),"") -> 25
... A82: AA-043 | B82: IMP-06 | C82: Não | D82: =IFERROR(INDEX(tbl_impactes[Impacte],MATCH(B82,tbl_impactes[ID_Impacte],0)),"") -> Perturbação da Fauna / Flora / Paisagem | E82: =IFERROR(INDEX(tbl_aspetos[Classificacao],MATCH(A82,tbl_aspetos[ID_Aspeto],0)),"") -> Moderado | F82: =IFERROR(INDEX(tbl_aspetos[IRA],MATCH(A82,tbl_aspetos[ID_Aspeto],0)),"") -> 30

Sheet Mod.G.07.00_Matriz
A1: PLASTICOM | O1: MATRIZ DE AVALIAÇÃO DE ASPETOS E IMPACTES AMBIENTAIS | AF1: Mod. G.07.00
O2: Plasticom — Unidade 1 (Marinha Grande, Portugal) · NP EN ISO 14001:2026 | AF2: Rev. 01 · 31/12/2026
A5: Área / Atividade | C5: Ciclo de Vida | I5: Aspeto | J5: Natureza do aspeto | M5: Potenciais Impactes Ambientais | Y5: Avaliação | AF5: Gestão
A6: Área / Atividade | B6: ID | C6: Aquisição | D6: Design e Conceção | E6: Produção | F6: Distribuição | G6: Uso (Consumidor Final) | H6: Fim de Vida | I6: Descrição do Aspeto Ambiental | J6: Tipo de Aspeto | K6: Condição de Operação | L6: Temporalidade | M6: Esgotamento de Recursos Naturais / Recursos | N6: Contaminação do Solo e/ou Recursos Hídricos | O6: Poluição do Ar | P6: Mudanças Climáticas | Q6: Incomodidade da Vizinhança | R6: Perturbação da Fauna / Flora / Paisagem | S6: Redução da vida útil de aterros e passivos ambientais | T6: Degradação da saúde dos ecossistemas aquáticos (microplásticos) | U6: Promoção da Eficiência Hídrica e Circularidade (valorização interna de resíduos/águas) | V6: Otimização do Consumo de Matérias-Primas (poupança ou geração de novos recursos) | W6: Extensão do ciclo de vida de materiais (conversão de resíduos em subprodutos) | X6: Minimização da Pressão Ecológica (materiais recicláveis ou de origem sustentável) | Y6: Tipo (+/-) | Z6: F | AA6: M | AB6: G | AC6: L | AD6: IRA | AE6: Classificação | AF6: Ação em Plano de Melhoria | AG6: Medidas de Controlo / Ação
A7: =INDEX(Aspetos_Impactes!$C$5:$C$47,1)&" — "&INDEX(Aspetos_Impactes!$D$5:$D$47,1) -> Compras e fornecedores — Aquisição de polímeros (PP, HDPE, PET) | B7: =INDEX(Aspetos_Impactes!$A$5:$A$47,1) -> AA-001 | C7: =IF(INDEX(Aspetos_Impactes!$E$5:$E$47,1)="Aquisição","X","") -> X | D7: =IF(INDEX(Aspetos_Impactes!$E$5:$E$47,1)="Design e Conceção","X","") | E7: =IF(INDEX(Aspetos_Impactes!$E$5:$E$47,1)="Produção","X","") | F7: =IF(INDEX(Aspetos_Impactes!$E$5:$E$47,1)="Distribuição","X","") | G7: =IF(INDEX(Aspetos_Impactes!$E$5:$E$47,1)="Uso (Consumidor Final)","X","") | H7: =IF(INDEX(Aspetos_Impactes!$E$5:$E$47,1)="Fim de Vida","X","") | I7: =INDEX(Aspetos_Impactes!$G$5:$G$47,1) -> Consumo de polímeros virgens de origem fóssil | J7: =INDEX(Aspetos_Impactes!$H$5:$H$47,1) -> Indireto | K7: =INDEX(Aspetos_Impactes!$I$5:$I$47,1) -> Normal | L7: =INDEX(Aspetos_Impactes!$J$5:$J$47,1) -> Presente | M7: =IF(COUNTIFS(tbl_aspeto_impacte[ID_Aspeto],$B7,tbl_aspeto_impacte[ID_Impacte],"IMP-01")>0,"X","") -> X | N7: =IF(COUNTIFS(tbl_aspeto_impacte[ID_Aspeto],$B7,tbl_aspeto_impacte[ID_Impacte],"IMP-02")>0,"X","") | O7: =IF(COUNTIFS(tbl_aspeto_impacte[ID_Aspeto],$B7,tbl_aspeto_impacte[ID_Impacte],"IMP-03")>0,"X","") | P7: =IF(COUNTIFS(tbl_aspeto_impacte[ID_Aspeto],$B7,tbl_aspeto_impacte[ID_Impacte],"IMP-04")>0,"X","") -> X | Q7: =IF(COUNTIFS(tbl_aspeto_impacte[ID_Aspeto],$B7,tbl_aspeto_impacte[ID_Impacte],"IMP-05")>0,"X","") | R7: =IF(COUNTIFS(tbl_aspeto_impacte[ID_Aspeto],$B7,tbl_aspeto_impacte[ID_Impacte],"IMP-06")>0,"X","") | S7: =IF(COUNTIFS(tbl_aspeto_impacte[ID_Aspeto],$B7,tbl_aspeto_impacte[ID_Impacte],"IMP-07")>0,"X","") | T7: =IF(COUNTIFS(tbl_aspeto_impacte[ID_Aspeto],$B7,tbl_aspeto_impacte[ID_Impacte],"IMP-08")>0,"X","") | U7: =IF(COUNTIFS(tbl_aspeto_impacte[ID_Aspeto],$B7,tbl_aspeto_impacte[ID_Impacte],"IMP-09")>0,"X","") | V7: =IF(COUNTIFS(tbl_aspeto_impacte[ID_Aspeto],$B7,tbl_aspeto_impacte[ID_Impacte],"IMP-10")>0,"X","") | W7: =IF(COUNTIFS(tbl_aspeto_impacte[ID_Aspeto],$B7,tbl_aspeto_impacte[ID_Impacte],"IMP-11")>0,"X","") | X7: =IF(COUNTIFS(tbl_aspeto_impacte[ID_Aspeto],$B7,tbl_aspeto_impacte[ID_Impacte],"IMP-12")>0,"X","") | Y7: =LEFT(INDEX(Aspetos_Impactes!$R$5:$R$47,1),3) -> (+) | Z7: =INDEX(Aspetos_Impactes!$N$5:$N$47,1) -> 5 | AA7: =INDEX(Aspetos_Impactes!$O$5:$O$47,1) -> 5 | AB7: =INDEX(Aspetos_Impactes!$P$5:$P$47,1) -> 2 | AC7: =INDEX(Aspetos_Impactes!$Q$5:$Q$47,1) -> 1 | AD7: =INDEX(Aspetos_Impactes!$S$5:$S$47,1) -> 20 | AE7: =INDEX(Aspetos_Impactes!$T$5:$T$47,1) -> Moderado | AF7: =INDEX(Aspetos_Impactes!$W$5:$W$47,1) -> SIM | AG7: =INDEX(Aspetos_Impactes!$X$5:$X$47,1) -> Critérios de compra com conteúdo reciclado certificado; lightweighting.
A8: =INDEX(Aspetos_Impactes!$C$5:$C$47,2)&" — "&INDEX(Aspetos_Impactes!$D$5:$D$47,2) -> Compras e fornecedores — Transporte de matérias-primas pelos fornecedores | B8: =INDEX(Aspetos_Impactes!$A$5:$A$47,2) -> AA-002 | C8: =IF(INDEX(Aspetos_Impactes!$E$5:$E$47,2)="Aquisição","X","") -> X | D8: =IF(INDEX(Aspetos_Impactes!$E$5:$E$47,2)="Design e Conceção","X","") | E8: =IF(INDEX(Aspetos_Impactes!$E$5:$E$47,2)="Produção","X","") | F8: =IF(INDEX(Aspetos_Impactes!$E$5:$E$47,2)="Distribuição","X","") | G8: =IF(INDEX(Aspetos_Impactes!$E$5:$E$47,2)="Uso (Consumidor Final)","X","") | H8: =IF(INDEX(Aspetos_Impactes!$E$5:$E$47,2)="Fim de Vida","X","") | I8: =INDEX(Aspetos_Impactes!$G$5:$G$47,2) -> Emissões de gases de escape (CO2, NOx, partículas) no transporte rodoviário e marítimo de resinas | J8: =INDEX(Aspetos_Impactes!$H$5:$H$47,2) -> Indireto | K8: =INDEX(Aspetos_Impactes!$I$5:$I$47,2) -> Normal | L8: =INDEX(Aspetos_Impactes!$J$5:$J$47,2) -> Presente | M8: =IF(COUNTIFS(tbl_aspeto_impacte[ID_Aspeto],$B8,tbl_aspeto_impacte[ID_Impacte],"IMP-01")>0,"X","") | N8: =IF(COUNTIFS(tbl_aspeto_impacte[ID_Aspeto],$B8,tbl_aspeto_impacte[ID_Impacte],"IMP-02")>0,"X","") | O8: =IF(COUNTIFS(tbl_aspeto_impacte[ID_Aspeto],$B8,tbl_aspeto_impacte[ID_Impacte],"IMP-03")>0,"X","") -> X | P8: =IF(COUNTIFS(tbl_aspeto_impacte[ID_Aspeto],$B8,tbl_aspeto_impacte[ID_Impacte],"IMP-04")>0,"X","") -> X | Q8: =IF(COUNTIFS(tbl_aspeto_impacte[ID_Aspeto],$B8,tbl_aspeto_impacte[ID_Impacte],"IMP-05")>0,"X","") | R8: =IF(COUNTIFS(tbl_aspeto_impacte[ID_Aspeto],$B8,tbl_aspeto_impacte[ID_Impacte],"IMP-06")>0,"X","") | S8: =IF(COUNTIFS(tbl_aspeto_impacte[ID_Aspeto],$B8,tbl_aspeto_impacte[ID_Impacte],"IMP-07")>0,"X","") | T8: =IF(COUNTIFS(tbl_aspeto_impacte[ID_Aspeto],$B8,tbl_aspeto_impacte[ID_Impacte],"IMP-08")>0,"X","") | U8: =IF(COUNTIFS(tbl_aspeto_impacte[ID_Aspeto],$B8,tbl_aspeto_impacte[ID_Impacte],"IMP-09")>0,"X","") | V8: =IF(COUNTIFS(tbl_aspeto_impacte[ID_Aspeto],$B8,tbl_aspeto_impacte[ID_Impacte],"IMP-10")>0,"X","") | W8: =IF(COUNTIFS(tbl_aspeto_impacte[ID_Aspeto],$B8,tbl_aspeto_impacte[ID_Impacte],"IMP-11")>0,"X","") | X8: =IF(COUNTIFS(tbl_aspeto_impacte[ID_Aspeto],$B8,tbl_aspeto_impacte[ID_Impacte],"IMP-12")>0,"X","") | Y8: =LEFT(INDEX(Aspetos_Impactes!$R$5:$R$47,2),3) -> (+) | Z8: =INDEX(Aspetos_Impactes!$N$5:$N$47,2) -> 4 | AA8: =INDEX(Aspetos_Impactes!$O$5:$O$47,2) -> 4 | AB8: =INDEX(Aspetos_Impactes!$P$5:$P$47,2) -> 3 | AC8: =INDEX(Aspetos_Impactes!$Q$5:$Q$47,2) -> 1 | AD8: =INDEX(Aspetos_Impactes!$S$5:$S$47,2) -> 24 | AE8: =INDEX(Aspetos_Impactes!$T$5:$T$47,2) -> Moderado | AF8: =INDEX(Aspetos_Impactes!$W$5:$W$47,2) -> SIM | AG8: =INDEX(Aspetos_Impactes!$X$5:$X$47,2) -> Preferir fornecedores ibéricos e cargas completas.
A9: =INDEX(Aspetos_Impactes!$C$5:$C$47,3)&" — "&INDEX(Aspetos_Impactes!$D$5:$D$47,3) -> Receção e silos — Descarga de big bags e transferência pneumática para silos | B9: =INDEX(Aspetos_Impactes!$A$5:$A$47,3) -> AA-003 | C9: =IF(INDEX(Aspetos_Impactes!$E$5:$E$47,3)="Aquisição","X","") | D9: =IF(INDEX(Aspetos_Impactes!$E$5:$E$47,3)="Design e Conceção","X","") | E9: =IF(INDEX(Aspetos_Impactes!$E$5:$E$47,3)="Produção","X","") -> X | F9: =IF(INDEX(Aspetos_Impactes!$E$5:$E$47,3)="Distribuição","X","") | G9: =IF(INDEX(Aspetos_Impactes!$E$5:$E$47,3)="Uso (Consumidor Final)","X","") | H9: =IF(INDEX(Aspetos_Impactes!$E$5:$E$47,3)="Fim de Vida","X","") | I9: =INDEX(Aspetos_Impactes!$G$5:$G$47,3) -> Perda de granulado de plástico para o pavimento e a rede de águas pluviais | J9: =INDEX(Aspetos_Impactes!$H$5:$H$47,3) -> Direto | K9: =INDEX(Aspetos_Impactes!$I$5:$I$47,3) -> Normal | L9: =INDEX(Aspetos_Impactes!$J$5:$J$47,3) -> Presente | M9: =IF(COUNTIFS(tbl_aspeto_impacte[ID_Aspeto],$B9,tbl_aspeto_impacte[ID_Impacte],"IMP-01")>0,"X","") | N9: =IF(COUNTIFS(tbl_aspeto_impacte[ID_Aspeto],$B9,tbl_aspeto_impacte[ID_Impacte],"IMP-02")>0,"X","") -> X | O9: =IF(COUNTIFS(tbl_aspeto_impacte[ID_Aspeto],$B9,tbl_aspeto_impacte[ID_Impacte],"IMP-03")>0,"X","") | P9: =IF(COUNTIFS(tbl_aspeto_impacte[ID_Aspeto],$B9,tbl_aspeto_impacte[ID_Impacte],"IMP-04")>0,"X","") | Q9: =IF(COUNTIFS(tbl_aspeto_impacte[ID_Aspeto],$B9,tbl_aspeto_impacte[ID_Impacte],"IMP-05")>0,"X","") | R9: =IF(COUNTIFS(tbl_aspeto_impacte[ID_Aspeto],$B9,tbl_aspeto_impacte[ID_Impacte],"IMP-06")>0,"X","") -> X | S9: =IF(COUNTIFS(tbl_aspeto_impacte[ID_Aspeto],$B9,tbl_aspeto_impacte[ID_Impacte],"IMP-07")>0,"X","") | T9: =IF(COUNTIFS(tbl_aspeto_impacte[ID_Aspeto],$B9,tbl_aspeto_impacte[ID_Impacte],"IMP-08")>0,"X","") -> X | U9: =IF(COUNTIFS(tbl_aspeto_impacte[ID_Aspeto],$B9,tbl_aspeto_impacte[ID_Impacte],"IMP-09")>0,"X","") | V9: =IF(COUNTIFS(tbl_aspeto_impacte[ID_Aspeto],$B9,tbl_aspeto_impacte[ID_Impacte],"IMP-10")>0,"X","") | W9: =IF(COUNTIFS(tbl_aspeto_impacte[ID_Aspeto],$B9,tbl_aspeto_impacte[ID_Impacte],"IMP-11")>0,"X","") | X9: =IF(COUNTIFS(tbl_aspeto_impacte[ID_Aspeto],$B9,tbl_aspeto_impacte[ID_Impacte],"IMP-12")>0,"X","") | Y9: =LEFT(INDEX(Aspetos_Impactes!$R$5:$R$47,3),3) -> (+) | Z9: =INDEX(Aspetos_Impactes!$N$5:$N$47,3) -> 4 | AA9: =INDEX(Aspetos_Impactes!$O$5:$O$47,3) -> 3 | AB9: =INDEX(Aspetos_Impactes!$P$5:$P$47,3) -> 4 | AC9: =INDEX(Aspetos_Impactes!$Q$5:$Q$47,3) -> 1 | AD9: =INDEX(Aspetos_Impactes!$S$5:$S$47,3) -> 28 | AE9: =INDEX(Aspetos_Impactes!$T$5:$T$47,3) -> Moderado | AF9: =INDEX(Aspetos_Impactes!$W$5:$W$47,3) -> SIM | AG9: =INDEX(Aspetos_Impactes!$X$5:$X$47,3) -> Operation Clean Sweep: filtros nas sarjetas, tabuleiros de descarga, aspiração, inspeção semanal.
A10: =INDEX(Aspetos_Impactes!$C$5:$C$47,4)&" — "&INDEX(Aspetos_Impactes!$D$5:$D$47,4) -> Receção e silos — Desembalagem de matérias-primas | B10: =INDEX(Aspetos_Impactes!$A$5:$A$47,4) -> AA-004 | C10: =IF(INDEX(Aspetos_Impactes!$E$5:$E$47,4)="Aquisição","X","") | D10: =IF(INDEX(Aspetos_Impactes!$E$5:$E$47,4)="Design e Conceção","X","") | E10: =IF(INDEX(Aspetos_Impactes!$E$5:$E$47,4)="Produção","X","") -> X | F10: =IF(INDEX(Aspetos_Impactes!$E$5:$E$47,4)="Distribuição","X","") | G10: =IF(INDEX(Aspetos_Impactes!$E$5:$E$47,4)="Uso (Consumidor Final)","X","") | H10: =IF(INDEX(Aspetos_Impactes!$E$5:$E$47,4)="Fim de Vida","X","") | I10: =INDEX(Aspetos_Impactes!$G$5:$G$47,4) -> Geração de resíduos de embalagem de matérias-primas (big bags, sacos, paletes, cartão) | J10: =INDEX(Aspetos_Impactes!$H$5:$H$47,4) -> Direto | K10: =INDEX(Aspetos_Impactes!$I$5:$I$47,4) -> Normal | L10: =INDEX(Aspetos_Impactes!$J$5:$J$47,4) -> Presente | M10: =IF(COUNTIFS(tbl_aspeto_impacte[ID_Aspeto],$B10,tbl_aspeto_impacte[ID_Impacte],"IMP-01")>0,"X","") -> X | N10: =IF(COUNTIFS(tbl_aspeto_impacte[ID_Aspeto],$B10,tbl_aspeto_impacte[ID_Impacte],"IMP-02")>0,"X","") | O10: =IF(COUNTIFS(tbl_aspeto_impacte[ID_Aspeto],$B10,tbl_aspeto_impacte[ID_Impacte],"IMP-03")>0,"X","") | P10: =IF(COUNTIFS(tbl_aspeto_impacte[ID_Aspeto],$B10,tbl_aspeto_impacte[ID_Impacte],"IMP-04")>0,"X","") | Q10: =IF(COUNTIFS(tbl_aspeto_impacte[ID_Aspeto],$B10,tbl_aspeto_impacte[ID_Impacte],"IMP-05")>0,"X","") | R10: =IF(COUNTIFS(tbl_aspeto_impacte[ID_Aspeto],$B10,tbl_aspeto_impacte[ID_Impacte],"IMP-06")>0,"X","") | S10: =IF(COUNTIFS(tbl_aspeto_impacte[ID_Aspeto],$B10,tbl_aspeto_impacte[ID_Impacte],"IMP-07")>0,"X","") -> X | T10: =IF(COUNTIFS(tbl_aspeto_impacte[ID_Aspeto],$B10,tbl_aspeto_impacte[ID_Impacte],"IMP-08")>0,"X","") | U10: =IF(COUNTIFS(tbl_aspeto_impacte[ID_Aspeto],$B10,tbl_aspeto_impacte[ID_Impacte],"IMP-09")>0,"X","") | V10: =IF(COUNTIFS(tbl_aspeto_impacte[ID_Aspeto],$B10,tbl_aspeto_impacte[ID_Impacte],"IMP-10")>0,"X","") | W10: =IF(COUNTIFS(tbl_aspeto_impacte[ID_Aspeto],$B10,tbl_aspeto_impacte[ID_Impacte],"IMP-11")>0,"X","") | X10: =IF(COUNTIFS(tbl_aspeto_impacte[ID_Aspeto],$B10,tbl_aspeto_impacte[ID_Impacte],"IMP-12")>0,"X","") | Y10: =LEFT(INDEX(Aspetos_Impactes!$R$5:$R$47,4),3) -> (+) | Z10: =INDEX(Aspetos_Impactes!$N$5:$N$47,4) -> 4 | AA10: =INDEX(Aspetos_Impactes!$O$5:$O$47,4) -> 3 | AB10: =INDEX(Aspetos_Impactes!$P$5:$P$47,4) -> 2 | AC10: =INDEX(Aspetos_Impactes!$Q$5:$Q$47,4) -> 1 | AD10: =INDEX(Aspetos_Impactes!$S$5:$S$47,4) -> 14 | AE10: =INDEX(Aspetos_Impactes!$T$5:$T$47,4) -> Não Significativo | AF10: =INDEX(Aspetos_Impactes!$W$5:$W$47,4) -> NÃO | AG10: =INDEX(Aspetos_Impactes!$X$5:$X$47,4) -> Segregação por fluxo; big bags retornáveis com fornecedor.
A11: =INDEX(Aspetos_Impactes!$C$5:$C$47,5)&" — "&INDEX(Aspetos_Impactes!$D$5:$D$47,5) -> Armazém de químicos — Armazenagem de tintas, solventes e óleos | B11: =INDEX(Aspetos_Impactes!$A$5:$A$47,5) -> AA-005 | C11: =IF(INDEX(Aspetos_Impactes!$E$5:$E$47,5)="Aquisição","X","") | D11: =IF(INDEX(Aspetos_Impactes!$E$5:$E$47,5)="Design e Conceção","X","") | E11: =IF(INDEX(Aspetos_Impactes!$E$5:$E$47,5)="Produção","X","") -> X | F11: =IF(INDEX(Aspetos_Impactes!$E$5:$E$47,5)="Distribuição","X","") | G11: =IF(INDEX(Aspetos_Impactes!$E$5:$E$47,5)="Uso (Consumidor Final)","X","") | H11: =IF(INDEX(Aspetos_Impactes!$E$5:$E$47,5)="Fim de Vida","X","") | I11: =INDEX(Aspetos_Impactes!$G$5:$G$47,5) -> Derrame acidental de tintas, solventes ou óleos (rutura de embalagem, queda na movimentação) | J11: =INDEX(Aspetos_Impactes!$H$5:$H$47,5) -> Direto | K11: =INDEX(Aspetos_Impactes!$I$5:$I$47,5) -> Emergência | L11: =INDEX(Aspetos_Impactes!$J$5:$J$47,5) -> Futuro | M11: =IF(COUNTIFS(tbl_aspeto_impacte[ID_Aspeto],$B11,tbl_aspeto_impacte[ID_Impacte],"IMP-01")>0,"X","") | N11: =IF(COUNTIFS(tbl_aspeto_impacte[ID_Aspeto],$B11,tbl_aspeto_impacte[ID_Impacte],"IMP-02")>0,"X","") -> X | O11: =IF(COUNTIFS(tbl_aspeto_impacte[ID_Aspeto],$B11,tbl_aspeto_impacte[ID_Impacte],"IMP-03")>0,"X","") -> X | P11: =IF(COUNTIFS(tbl_aspeto_impacte[ID_Aspeto],$B11,tbl_aspeto_impacte[ID_Impacte],"IMP-04")>0,"X","") | Q11: =IF(COUNTIFS(tbl_aspeto_impacte[ID_Aspeto],$B11,tbl_aspeto_impacte[ID_Impacte],"IMP-05")>0,"X","") | R11: =IF(COUNTIFS(tbl_aspeto_impacte[ID_Aspeto],$B11,tbl_aspeto_impacte[ID_Impacte],"IMP-06")>0,"X","") | S11: =IF(COUNTIFS(tbl_aspeto_impacte[ID_Aspeto],$B11,tbl_aspeto_impacte[ID_Impacte],"IMP-07")>0,"X","") | T11: =IF(COUNTIFS(tbl_aspeto_impacte[ID_Aspeto],$B11,tbl_aspeto_impacte[ID_Impacte],"IMP-08")>0,"X","") | U11: =IF(COUNTIFS(tbl_aspeto_impacte[ID_Aspeto],$B11,tbl_aspeto_impacte[ID_Impacte],"IMP-09")>0,"X","") | V11: =IF(COUNTIFS(tbl_aspeto_impacte[ID_Aspeto],$B11,tbl_aspeto_impacte[ID_Impacte],"IMP-10")>0,"X","") | W11: =IF(COUNTIFS(tbl_aspeto_impacte[ID_Aspeto],$B11,tbl_aspeto_impacte[ID_Impacte],"IMP-11")>0,"X","") | X11: =IF(COUNTIFS(tbl_aspeto_impacte[ID_Aspeto],$B11,tbl_aspeto_impacte[ID_Impacte],"IMP-12")>0,"X","") | Y11: =LEFT(INDEX(Aspetos_Impactes!$R$5:$R$47,5),3) -> (+) | Z11: =INDEX(Aspetos_Impactes!$N$5:$N$47,5) -> 1 | AA11: =INDEX(Aspetos_Impactes!$O$5:$O$47,5) -> 3 | AB11: =INDEX(Aspetos_Impactes!$P$5:$P$47,5) -> 5 | AC11: =INDEX(Aspetos_Impactes!$Q$5:$Q$47,5) -> 1 | AD11: =INDEX(Aspetos_Impactes!$S$5:$S$47,5) -> 20 | AE11: =INDEX(Aspetos_Impactes!$T$5:$T$47,5) -> Moderado | AF11: =INDEX(Aspetos_Impactes!$W$5:$W$47,5) -> SIM | AG11: =INDEX(Aspetos_Impactes!$X$5:$X$47,5) -> Bacias de retenção, kits de derrame completos e selados, IT-SGA-01, simulacro semestral.
A12: =INDEX(Aspetos_Impactes!$C$5:$C$47,6)&" — "&INDEX(Aspetos_Impactes!$D$5:$D$47,6) -> Armazém de químicos — Manuseamento e trasfega de solventes | B12: =INDEX(Aspetos_Impactes!$A$5:$A$47,6) -> AA-006 | C12: =IF(INDEX(Aspetos_Impactes!$E$5:$E$47,6)="Aquisição","X","") | D12: =IF(INDEX(Aspetos_Impactes!$E$5:$E$47,6)="Design e Conceção","X","") | E12: =IF(INDEX(Aspetos_Impactes!$E$5:$E$47,6)="Produção","X","") -> X | F12: =IF(INDEX(Aspetos_Impactes!$E$5:$E$47,6)="Distribuição","X","") | G12: =IF(INDEX(Aspetos_Impactes!$E$5:$E$47,6)="Uso (Consumidor Final)","X","") | H12: =IF(INDEX(Aspetos_Impactes!$E$5:$E$47,6)="Fim de Vida","X","") | I12: =INDEX(Aspetos_Impactes!$G$5:$G$47,6) -> Evaporação de COV de recipientes abertos ou mal fechados | J12: =INDEX(Aspetos_Impactes!$H$5:$H$47,6) -> Direto | K12: =INDEX(Aspetos_Impactes!$I$5:$I$47,6) -> Anormal | L12: =INDEX(Aspetos_Impactes!$J$5:$J$47,6) -> Presente | M12: =IF(COUNTIFS(tbl_aspeto_impacte[ID_Aspeto],$B12,tbl_aspeto_impacte[ID_Impacte],"IMP-01")>0,"X","") | N12: =IF(COUNTIFS(tbl_aspeto_impacte[ID_Aspeto],$B12,tbl_aspeto_impacte[ID_Impacte],"IMP-02")>0,"X","") | O12: =IF(COUNTIFS(tbl_aspeto_impacte[ID_Aspeto],$B12,tbl_aspeto_impacte[ID_Impacte],"IMP-03")>0,"X","") -> X | P12: =IF(COUNTIFS(tbl_aspeto_impacte[ID_Aspeto],$B12,tbl_aspeto_impacte[ID_Impacte],"IMP-04")>0,"X","") -> X | Q12: =IF(COUNTIFS(tbl_aspeto_impacte[ID_Aspeto],$B12,tbl_aspeto_impacte[ID_Impacte],"IMP-05")>0,"X","") | R12: =IF(COUNTIFS(tbl_aspeto_impacte[ID_Aspeto],$B12,tbl_aspeto_impacte[ID_Impacte],"IMP-06")>0,"X","") | S12: =IF(COUNTIFS(tbl_aspeto_impacte[ID_Aspeto],$B12,tbl_aspeto_impacte[ID_Impacte],"IMP-07")>0,"X","") | T12: =IF(COUNTIFS(tbl_aspeto_impacte[ID_Aspeto],$B12,tbl_aspeto_impacte[ID_Impacte],"IMP-08")>0,"X","") | U12: =IF(COUNTIFS(tbl_aspeto_impacte[ID_Aspeto],$B12,tbl_aspeto_impacte[ID_Impacte],"IMP-09")>0,"X","") | V12: =IF(COUNTIFS(tbl_aspeto_impacte[ID_Aspeto],$B12,tbl_aspeto_impacte[ID_Impacte],"IMP-10")>0,"X","") | W12: =IF(COUNTIFS(tbl_aspeto_impacte[ID_Aspeto],$B12,tbl_aspeto_impacte[ID_Impacte],"IMP-11")>0,"X","") | X12: =IF(COUNTIFS(tbl_aspeto_impacte[ID_Aspeto],$B12,tbl_aspeto_impacte[ID_Impacte],"IMP-12")>0,"X","") | Y12: =LEFT(INDEX(Aspetos_Impactes!$R$5:$R$47,6),3) -> (+) | Z12: =INDEX(Aspetos_Impactes!$N$5:$N$47,6) -> 3 | AA12: =INDEX(Aspetos_Impactes!$O$5:$O$47,6) -> 2 | AB12: =INDEX(Aspetos_Impactes!$P$5:$P$47,6) -> 5 | AC12: =INDEX(Aspetos_Impactes!$Q$5:$Q$47,6) -> 1 | AD12: =INDEX(Aspetos_Impactes!$S$5:$S$47,6) -> 25 | AE12: =INDEX(Aspetos_Impactes!$T$5:$T$47,6) -> Moderado | AF12: =INDEX(Aspetos_Impactes!$W$5:$W$47,6) -> SIM | AG12: =INDEX(Aspetos_Impactes!$X$5:$X$47,6) -> Recipientes fechados, dispensadores de segurança, regra 'tampa fechada'.
A13: =INDEX(Aspetos_Impactes!$C$5:$C$47,7)&" — "&INDEX(Aspetos_Impactes!$D$5:$D$47,7) -> Injeção de tampas — Moldação por injeção (IM-001 a IM-009) | B13: =INDEX(Aspetos_Impactes!$A$5:$A$47,7) -> AA-007 | C13: =IF(INDEX(Aspetos_Impactes!$E$5:$E$47,7)="Aquisição","X","") | D13: =IF(INDEX(Aspetos_Impactes!$E$5:$E$47,7)="Design e Conceção","X","") | E13: =IF(INDEX(Aspetos_Impactes!$E$5:$E$47,7)="Produção","X","") -> X | F13: =IF(INDEX(Aspetos_Impactes!$E$5:$E$47,7)="Distribuição","X","") | G13: =IF(INDEX(Aspetos_Impactes!$E$5:$E$47,7)="Uso (Consumidor Final)","X","") | H13: =IF(INDEX(Aspetos_Impactes!$E$5:$E$47,7)="Fim de Vida","X","") | I13: =INDEX(Aspetos_Impactes!$G$5:$G$47,7) -> Consumo de energia elétrica (aquecimento do canhão, hidráulica, extração) | J13: =INDEX(Aspetos_Impactes!$H$5:$H$47,7) -> Direto | K13: =INDEX(Aspetos_Impactes!$I$5:$I$47,7) -> Normal | L13: =INDEX(Aspetos_Impactes!$J$5:$J$47,7) -> Presente | M13: =IF(COUNTIFS(tbl_aspeto_impacte[ID_Aspeto],$B13,tbl_aspeto_impacte[ID_Impacte],"IMP-01")>0,"X","") -> X | N13: =IF(COUNTIFS(tbl_aspeto_impacte[ID_Aspeto],$B13,tbl_aspeto_impacte[ID_Impacte],"IMP-02")>0,"X","") | O13: =IF(COUNTIFS(tbl_aspeto_impacte[ID_Aspeto],$B13,tbl_aspeto_impacte[ID_Impacte],"IMP-03")>0,"X","") | P13: =IF(COUNTIFS(tbl_aspeto_impacte[ID_Aspeto],$B13,tbl_aspeto_impacte[ID_Impacte],"IMP-04")>0,"X","") -> X | Q13: =IF(COUNTIFS(tbl_aspeto_impacte[ID_Aspeto],$B13,tbl_aspeto_impacte[ID_Impacte],"IMP-05")>0,"X","") | R13: =IF(COUNTIFS(tbl_aspeto_impacte[ID_Aspeto],$B13,tbl_aspeto_impacte[ID_Impacte],"IMP-06")>0,"X","") | S13: =IF(COUNTIFS(tbl_aspeto_impacte[ID_Aspeto],$B13,tbl_aspeto_impacte[ID_Impacte],"IMP-07")>0,"X","") | T13: =IF(COUNTIFS(tbl_aspeto_impacte[ID_Aspeto],$B13,tbl_aspeto_impacte[ID_Impacte],"IMP-08")>0,"X","") | U13: =IF(COUNTIFS(tbl_aspeto_impacte[ID_Aspeto],$B13,tbl_aspeto_impacte[ID_Impacte],"IMP-09")>0,"X","") | V13: =IF(COUNTIFS(tbl_aspeto_impacte[ID_Aspeto],$B13,tbl_aspeto_impacte[ID_Impacte],"IMP-10")>0,"X","") | W13: =IF(COUNTIFS(tbl_aspeto_impacte[ID_Aspeto],$B13,tbl_aspeto_impacte[ID_Impacte],"IMP-11")>0,"X","") | X13: =IF(COUNTIFS(tbl_aspeto_impacte[ID_Aspeto],$B13,tbl_aspeto_impacte[ID_Impacte],"IMP-12")>0,"X","") | Y13: =LEFT(INDEX(Aspetos_Impactes!$R$5:$R$47,7),3) -> (+) | Z13: =INDEX(Aspetos_Impactes!$N$5:$N$47,7) -> 5 | AA13: =INDEX(Aspetos_Impactes!$O$5:$O$47,7) -> 5 | AB13: =INDEX(Aspetos_Impactes!$P$5:$P$47,7) -> 3 | AC13: =INDEX(Aspetos_Impactes!$Q$5:$Q$47,7) -> 1 | AD13: =INDEX(Aspetos_Impactes!$S$5:$S$47,7) -> 30 | AE13: =INDEX(Aspetos_Impactes!$T$5:$T$47,7) -> Moderado | AF13: =INDEX(Aspetos_Impactes!$W$5:$W$47,7) -> SIM | AG13: =INDEX(Aspetos_Impactes!$X$5:$X$47,7) -> Standby nas pausas (Kaizen KZ-01), manutenção de resistências e isolamento do canhão, submedição.
A14: =INDEX(Aspetos_Impactes!$C$5:$C$47,8)&" — "&INDEX(Aspetos_Impactes!$D$5:$D$47,8) -> Injeção de tampas — Moldação por injeção (IM-001 a IM-009) | B14: =INDEX(Aspetos_Impactes!$A$5:$A$47,8) -> AA-008 | C14: =IF(INDEX(Aspetos_Impactes!$E$5:$E$47,8)="Aquisição","X","") | D14: =IF(INDEX(Aspetos_Impactes!$E$5:$E$47,8)="Design e Conceção","X","") | E14: =IF(INDEX(Aspetos_Impactes!$E$5:$E$47,8)="Produção","X","") -> X | F14: =IF(INDEX(Aspetos_Impactes!$E$5:$E$47,8)="Distribuição","X","") | G14: =IF(INDEX(Aspetos_Impactes!$E$5:$E$47,8)="Uso (Consumidor Final)","X","") | H14: =IF(INDEX(Aspetos_Impactes!$E$5:$E$47,8)="Fim de Vida","X","") | I14: =INDEX(Aspetos_Impactes!$G$5:$G$47,8) -> Geração de scrap plástico (peças rejeitadas, jitos e purgas de arranque) | J14: =INDEX(Aspetos_Impactes!$H$5:$H$47,8) -> Direto | K14: =INDEX(Aspetos_Impactes!$I$5:$I$47,8) -> Normal | L14: =INDEX(Aspetos_Impactes!$J$5:$J$47,8) -> Presente | M14: =IF(COUNTIFS(tbl_aspeto_impacte[ID_Aspeto],$B14,tbl_aspeto_impacte[ID_Impacte],"IMP-01")>0,"X","") -> X | N14: =IF(COUNTIFS(tbl_aspeto_impacte[ID_Aspeto],$B14,tbl_aspeto_impacte[ID_Impacte],"IMP-02")>0,"X","") | O14: =IF(COUNTIFS(tbl_aspeto_impacte[ID_Aspeto],$B14,tbl_aspeto_impacte[ID_Impacte],"IMP-03")>0,"X","") | P14: =IF(COUNTIFS(tbl_aspeto_impacte[ID_Aspeto],$B14,tbl_aspeto_impacte[ID_Impacte],"IMP-04")>0,"X","") | Q14: =IF(COUNTIFS(tbl_aspeto_impacte[ID_Aspeto],$B14,tbl_aspeto_impacte[ID_Impacte],"IMP-05")>0,"X","") | R14: =IF(COUNTIFS(tbl_aspeto_impacte[ID_Aspeto],$B14,tbl_aspeto_impacte[ID_Impacte],"IMP-06")>0,"X","") | S14: =IF(COUNTIFS(tbl_aspeto_impacte[ID_Aspeto],$B14,tbl_aspeto_impacte[ID_Impacte],"IMP-07")>0,"X","") -> X | T14: =IF(COUNTIFS(tbl_aspeto_impacte[ID_Aspeto],$B14,tbl_aspeto_impacte[ID_Impacte],"IMP-08")>0,"X","") | U14: =IF(COUNTIFS(tbl_aspeto_impacte[ID_Aspeto],$B14,tbl_aspeto_impacte[ID_Impacte],"IMP-09")>0,"X","") | V14: =IF(COUNTIFS(tbl_aspeto_impacte[ID_Aspeto],$B14,tbl_aspeto_impacte[ID_Impacte],"IMP-10")>0,"X","") | W14: =IF(COUNTIFS(tbl_aspeto_impacte[ID_Aspeto],$B14,tbl_aspeto_impacte[ID_Impacte],"IMP-11")>0,"X","") | X14: =IF(COUNTIFS(tbl_aspeto_impacte[ID_Aspeto],$B14,tbl_aspeto_impacte[ID_Impacte],"IMP-12")>0,"X","") | Y14: =LEFT(INDEX(Aspetos_Impactes!$R$5:$R$47,8),3) -> (+) | Z14: =INDEX(Aspetos_Impactes!$N$5:$N$47,8) -> 5 | AA14: =INDEX(Aspetos_Impactes!$O$5:$O$47,8) -> 3 | AB14: =INDEX(Aspetos_Impactes!$P$5:$P$47,8) -> 3 | AC14: =INDEX(Aspetos_Impactes!$Q$5:$Q$47,8) -> 1 | AD14: =INDEX(Aspetos_Impactes!$S$5:$S$47,8) -> 24 | AE14: =INDEX(Aspetos_Impactes!$T$5:$T$47,8) -> Moderado | AF14: =INDEX(Aspetos_Impactes!$W$5:$W$47,8) -> SIM | AG14: =INDEX(Aspetos_Impactes!$X$5:$X$47,8) -> Controlo de processo (DOE IM-002), segregação por cor e reintegração.
A15: =INDEX(Aspetos_Impactes!$C$5:$C$47,9)&" — "&INDEX(Aspetos_Impactes!$D$5:$D$47,9) -> Injeção de tampas — Mudança de óleo hidráulico e fugas em mangueiras | B15: =INDEX(Aspetos_Impactes!$A$5:$A$47,9) -> AA-009 | C15: =IF(INDEX(Aspetos_Impactes!$E$5:$E$47,9)="Aquisição","X","") | D15: =IF(INDEX(Aspetos_Impactes!$E$5:$E$47,9)="Design e Conceção","X","") | E15: =IF(INDEX(Aspetos_Impactes!$E$5:$E$47,9)="Produção","X","") -> X | F15: =IF(INDEX(Aspetos_Impactes!$E$5:$E$47,9)="Distribuição","X","") | G15: =IF(INDEX(Aspetos_Impactes!$E$5:$E$47,9)="Uso (Consumidor Final)","X","") | H15: =IF(INDEX(Aspetos_Impactes!$E$5:$E$47,9)="Fim de Vida","X","") | I15: =INDEX(Aspetos_Impactes!$G$5:$G$47,9) -> Fuga de óleo hidráulico durante manutenção ou por rotura de mangueira | J15: =INDEX(Aspetos_Impactes!$H$5:$H$47,9) -> Direto | K15: =INDEX(Aspetos_Impactes!$I$5:$I$47,9) -> Anormal | L15: =INDEX(Aspetos_Impactes!$J$5:$J$47,9) -> Presente | M15: =IF(COUNTIFS(tbl_aspeto_impacte[ID_Aspeto],$B15,tbl_aspeto_impacte[ID_Impacte],"IMP-01")>0,"X","") | N15: =IF(COUNTIFS(tbl_aspeto_impacte[ID_Aspeto],$B15,tbl_aspeto_impacte[ID_Impacte],"IMP-02")>0,"X","") -> X | O15: =IF(COUNTIFS(tbl_aspeto_impacte[ID_Aspeto],$B15,tbl_aspeto_impacte[ID_Impacte],"IMP-03")>0,"X","") | P15: =IF(COUNTIFS(tbl_aspeto_impacte[ID_Aspeto],$B15,tbl_aspeto_impacte[ID_Impacte],"IMP-04")>0,"X","") | Q15: =IF(COUNTIFS(tbl_aspeto_impacte[ID_Aspeto],$B15,tbl_aspeto_impacte[ID_Impacte],"IMP-05")>0,"X","") | R15: =IF(COUNTIFS(tbl_aspeto_impacte[ID_Aspeto],$B15,tbl_aspeto_impacte[ID_Impacte],"IMP-06")>0,"X","") | S15: =IF(COUNTIFS(tbl_aspeto_impacte[ID_Aspeto],$B15,tbl_aspeto_impacte[ID_Impacte],"IMP-07")>0,"X","") | T15: =IF(COUNTIFS(tbl_aspeto_impacte[ID_Aspeto],$B15,tbl_aspeto_impacte[ID_Impacte],"IMP-08")>0,"X","") | U15: =IF(COUNTIFS(tbl_aspeto_impacte[ID_Aspeto],$B15,tbl_aspeto_impacte[ID_Impacte],"IMP-09")>0,"X","") | V15: =IF(COUNTIFS(tbl_aspeto_impacte[ID_Aspeto],$B15,tbl_aspeto_impacte[ID_Impacte],"IMP-10")>0,"X","") | W15: =IF(COUNTIFS(tbl_aspeto_impacte[ID_Aspeto],$B15,tbl_aspeto_impacte[ID_Impacte],"IMP-11")>0,"X","") | X15: =IF(COUNTIFS(tbl_aspeto_impacte[ID_Aspeto],$B15,tbl_aspeto_impacte[ID_Impacte],"IMP-12")>0,"X","") | Y15: =LEFT(INDEX(Aspetos_Impactes!$R$5:$R$47,9),3) -> (+) | Z15: =INDEX(Aspetos_Impactes!$N$5:$N$47,9) -> 2 | AA15: =INDEX(Aspetos_Impactes!$O$5:$O$47,9) -> 2 | AB15: =INDEX(Aspetos_Impactes!$P$5:$P$47,9) -> 4 | AC15: =INDEX(Aspetos_Impactes!$Q$5:$Q$47,9) -> 1 | AD15: =INDEX(Aspetos_Impactes!$S$5:$S$47,9) -> 16 | AE15: =INDEX(Aspetos_Impactes!$T$5:$T$47,9) -> Não Significativo | AF15: =INDEX(Aspetos_Impactes!$W$5:$W$47,9) -> NÃO | AG15: =INDEX(Aspetos_Impactes!$X$5:$X$47,9) -> Tabuleiros de retenção sob a hidráulica; inspeção de mangueiras.
A16: =INDEX(Aspetos_Impactes!$C$5:$C$47,10)&" — "&INDEX(Aspetos_Impactes!$D$5:$D$47,10) -> Sopro de frascos (ISBM) — Moldação por injeção-sopro (ISBM-001 a 010) | B16: =INDEX(Aspetos_Impactes!$A$5:$A$47,10) -> AA-010 | C16: =IF(INDEX(Aspetos_Impactes!$E$5:$E$47,10)="Aquisição","X","") | D16: =IF(INDEX(Aspetos_Impactes!$E$5:$E$47,10)="Design e Conceção","X","") | E16: =IF(INDEX(Aspetos_Impactes!$E$5:$E$47,10)="Produção","X","") -> X | F16: =IF(INDEX(Aspetos_Impactes!$E$5:$E$47,10)="Distribuição","X","") | G16: =IF(INDEX(Aspetos_Impactes!$E$5:$E$47,10)="Uso (Consumidor Final)","X","") | H16: =IF(INDEX(Aspetos_Impactes!$E$5:$E$47,10)="Fim de Vida","X","") | I16: =INDEX(Aspetos_Impactes!$G$5:$G$47,10) -> Consumo de energia elétrica (aquecimento de pré-formas, sopro, hidráulica) | J16: =INDEX(Aspetos_Impactes!$H$5:$H$47,10) -> Direto | K16: =INDEX(Aspetos_Impactes!$I$5:$I$47,10) -> Normal | L16: =INDEX(Aspetos_Impactes!$J$5:$J$47,10) -> Presente | M16: =IF(COUNTIFS(tbl_aspeto_impacte[ID_Aspeto],$B16,tbl_aspeto_impacte[ID_Impacte],"IMP-01")>0,"X","") -> X | N16: =IF(COUNTIFS(tbl_aspeto_impacte[ID_Aspeto],$B16,tbl_aspeto_impacte[ID_Impacte],"IMP-02")>0,"X","") | O16: =IF(COUNTIFS(tbl_aspeto_impacte[ID_Aspeto],$B16,tbl_aspeto_impacte[ID_Impacte],"IMP-03")>0,"X","") | P16: =IF(COUNTIFS(tbl_aspeto_impacte[ID_Aspeto],$B16,tbl_aspeto_impacte[ID_Impacte],"IMP-04")>0,"X","") -> X | Q16: =IF(COUNTIFS(tbl_aspeto_impacte[ID_Aspeto],$B16,tbl_aspeto_impacte[ID_Impacte],"IMP-05")>0,"X","") | R16: =IF(COUNTIFS(tbl_aspeto_impacte[ID_Aspeto],$B16,tbl_aspeto_impacte[ID_Impacte],"IMP-06")>0,"X","") | S16: =IF(COUNTIFS(tbl_aspeto_impacte[ID_Aspeto],$B16,tbl_aspeto_impacte[ID_Impacte],"IMP-07")>0,"X","") | T16: =IF(COUNTIFS(tbl_aspeto_impacte[ID_Aspeto],$B16,tbl_aspeto_impacte[ID_Impacte],"IMP-08")>0,"X","") | U16: =IF(COUNTIFS(tbl_aspeto_impacte[ID_Aspeto],$B16,tbl_aspeto_impacte[ID_Impacte],"IMP-09")>0,"X","") | V16: =IF(COUNTIFS(tbl_aspeto_impacte[ID_Aspeto],$B16,tbl_aspeto_impacte[ID_Impacte],"IMP-10")>0,"X","") | W16: =IF(COUNTIFS(tbl_aspeto_impacte[ID_Aspeto],$B16,tbl_aspeto_impacte[ID_Impacte],"IMP-11")>0,"X","") | X16: =IF(COUNTIFS(tbl_aspeto_impacte[ID_Aspeto],$B16,tbl_aspeto_impacte[ID_Impacte],"IMP-12")>0,"X","") | Y16: =LEFT(INDEX(Aspetos_Impactes!$R$5:$R$47,10),3) -> (+) | Z16: =INDEX(Aspetos_Impactes!$N$5:$N$47,10) -> 5 | AA16: =INDEX(Aspetos_Impactes!$O$5:$O$47,10) -> 5 | AB16: =INDEX(Aspetos_Impactes!$P$5:$P$47,10) -> 3 | AC16: =INDEX(Aspetos_Impactes!$Q$5:$Q$47,10) -> 1 | AD16: =INDEX(Aspetos_Impactes!$S$5:$S$47,10) -> 30 | AE16: =INDEX(Aspetos_Impactes!$T$5:$T$47,10) -> Moderado | AF16: =INDEX(Aspetos_Impactes!$W$5:$W$47,10) -> SIM | AG16: =INDEX(Aspetos_Impactes!$X$5:$X$47,10) -> Submedição, ajuste de temperaturas de condicionamento, standby nas pausas.
A17: =INDEX(Aspetos_Impactes!$C$5:$C$47,11)&" — "&INDEX(Aspetos_Impactes!$D$5:$D$47,11) -> Sopro de frascos (ISBM) — Moldação por injeção-sopro (ISBM-001 a 010) | B17: =INDEX(Aspetos_Impactes!$A$5:$A$47,11) -> AA-011 | C17: =IF(INDEX(Aspetos_Impactes!$E$5:$E$47,11)="Aquisição","X","") | D17: =IF(INDEX(Aspetos_Impactes!$E$5:$E$47,11)="Design e Conceção","X","") | E17: =IF(INDEX(Aspetos_Impactes!$E$5:$E$47,11)="Produção","X","") -> X | F17: =IF(INDEX(Aspetos_Impactes!$E$5:$E$47,11)="Distribuição","X","") | G17: =IF(INDEX(Aspetos_Impactes!$E$5:$E$47,11)="Uso (Consumidor Final)","X","") | H17: =IF(INDEX(Aspetos_Impactes!$E$5:$E$47,11)="Fim de Vida","X","") | I17: =INDEX(Aspetos_Impactes!$G$5:$G$47,11) -> Geração de scrap plástico (frascos rejeitados e purgas) | J17: =INDEX(Aspetos_Impactes!$H$5:$H$47,11) -> Direto | K17: =INDEX(Aspetos_Impactes!$I$5:$I$47,11) -> Normal | L17: =INDEX(Aspetos_Impactes!$J$5:$J$47,11) -> Presente | M17: =IF(COUNTIFS(tbl_aspeto_impacte[ID_Aspeto],$B17,tbl_aspeto_impacte[ID_Impacte],"IMP-01")>0,"X","") -> X | N17: =IF(COUNTIFS(tbl_aspeto_impacte[ID_Aspeto],$B17,tbl_aspeto_impacte[ID_Impacte],"IMP-02")>0,"X","") | O17: =IF(COUNTIFS(tbl_aspeto_impacte[ID_Aspeto],$B17,tbl_aspeto_impacte[ID_Impacte],"IMP-03")>0,"X","") | P17: =IF(COUNTIFS(tbl_aspeto_impacte[ID_Aspeto],$B17,tbl_aspeto_impacte[ID_Impacte],"IMP-04")>0,"X","") | Q17: =IF(COUNTIFS(tbl_aspeto_impacte[ID_Aspeto],$B17,tbl_aspeto_impacte[ID_Impacte],"IMP-05")>0,"X","") | R17: =IF(COUNTIFS(tbl_aspeto_impacte[ID_Aspeto],$B17,tbl_aspeto_impacte[ID_Impacte],"IMP-06")>0,"X","") | S17: =IF(COUNTIFS(tbl_aspeto_impacte[ID_Aspeto],$B17,tbl_aspeto_impacte[ID_Impacte],"IMP-07")>0,"X","") -> X | T17: =IF(COUNTIFS(tbl_aspeto_impacte[ID_Aspeto],$B17,tbl_aspeto_impacte[ID_Impacte],"IMP-08")>0,"X","") | U17: =IF(COUNTIFS(tbl_aspeto_impacte[ID_Aspeto],$B17,tbl_aspeto_impacte[ID_Impacte],"IMP-09")>0,"X","") | V17: =IF(COUNTIFS(tbl_aspeto_impacte[ID_Aspeto],$B17,tbl_aspeto_impacte[ID_Impacte],"IMP-10")>0,"X","") | W17: =IF(COUNTIFS(tbl_aspeto_impacte[ID_Aspeto],$B17,tbl_aspeto_impacte[ID_Impacte],"IMP-11")>0,"X","") | X17: =IF(COUNTIFS(tbl_aspeto_impacte[ID_Aspeto],$B17,tbl_aspeto_impacte[ID_Impacte],"IMP-12")>0,"X","") | Y17: =LEFT(INDEX(Aspetos_Impactes!$R$5:$R$47,11),3) -> (+) | Z17: =INDEX(Aspetos_Impactes!$N$5:$N$47,11) -> 5 | AA17: =INDEX(Aspetos_Impactes!$O$5:$O$47,11) -> 4 | AB17: =INDEX(Aspetos_Impactes!$P$5:$P$47,11) -> 3 | AC17: =INDEX(Aspetos_Impactes!$Q$5:$Q$47,11) -> 1 | AD17: =INDEX(Aspetos_Impactes!$S$5:$S$47,11) -> 27 | AE17: =INDEX(Aspetos_Impactes!$T$5:$T$47,11) -> Moderado | AF17: =INDEX(Aspetos_Impactes!$W$5:$W$47,11) -> SIM | AG17: =INDEX(Aspetos_Impactes!$X$5:$X$47,11) -> Controlo da espessura de parede (ISBM-003), manutenção de moldes, reintegração.
A18: =INDEX(Aspetos_Impactes!$C$5:$C$47,12)&" — "&INDEX(Aspetos_Impactes!$D$5:$D$47,12) -> Sopro de frascos (ISBM) — Arranque e paragem de máquinas / mudança de molde | B18: =INDEX(Aspetos_Impactes!$A$5:$A$47,12) -> AA-012 | C18: =IF(INDEX(Aspetos_Impactes!$E$5:$E$47,12)="Aquisição","X","") | D18: =IF(INDEX(Aspetos_Impactes!$E$5:$E$47,12)="Design e Conceção","X","") | E18: =IF(INDEX(Aspetos_Impactes!$E$5:$E$47,12)="Produção","X","") -> X | F18: =IF(INDEX(Aspetos_Impactes!$E$5:$E$47,12)="Distribuição","X","") | G18: =IF(INDEX(Aspetos_Impactes!$E$5:$E$47,12)="Uso (Consumidor Final)","X","") | H18: =IF(INDEX(Aspetos_Impactes!$E$5:$E$47,12)="Fim de Vida","X","") | I18: =INDEX(Aspetos_Impactes!$G$5:$G$47,12) -> Purgas e peças de arranque após mudança de molde ou paragem | J18: =INDEX(Aspetos_Impactes!$H$5:$H$47,12) -> Direto | K18: =INDEX(Aspetos_Impactes!$I$5:$I$47,12) -> Anormal | L18: =INDEX(Aspetos_Impactes!$J$5:$J$47,12) -> Presente | M18: =IF(COUNTIFS(tbl_aspeto_impacte[ID_Aspeto],$B18,tbl_aspeto_impacte[ID_Impacte],"IMP-01")>0,"X","") -> X | N18: =IF(COUNTIFS(tbl_aspeto_impacte[ID_Aspeto],$B18,tbl_aspeto_impacte[ID_Impacte],"IMP-02")>0,"X","") | O18: =IF(COUNTIFS(tbl_aspeto_impacte[ID_Aspeto],$B18,tbl_aspeto_impacte[ID_Impacte],"IMP-03")>0,"X","") | P18: =IF(COUNTIFS(tbl_aspeto_impacte[ID_Aspeto],$B18,tbl_aspeto_impacte[ID_Impacte],"IMP-04")>0,"X","") | Q18: =IF(COUNTIFS(tbl_aspeto_impacte[ID_Aspeto],$B18,tbl_aspeto_impacte[ID_Impacte],"IMP-05")>0,"X","") | R18: =IF(COUNTIFS(tbl_aspeto_impacte[ID_Aspeto],$B18,tbl_aspeto_impacte[ID_Impacte],"IMP-06")>0,"X","") | S18: =IF(COUNTIFS(tbl_aspeto_impacte[ID_Aspeto],$B18,tbl_aspeto_impacte[ID_Impacte],"IMP-07")>0,"X","") -> X | T18: =IF(COUNTIFS(tbl_aspeto_impacte[ID_Aspeto],$B18,tbl_aspeto_impacte[ID_Impacte],"IMP-08")>0,"X","") | U18: =IF(COUNTIFS(tbl_aspeto_impacte[ID_Aspeto],$B18,tbl_aspeto_impacte[ID_Impacte],"IMP-09")>0,"X","") | V18: =IF(COUNTIFS(tbl_aspeto_impacte[ID_Aspeto],$B18,tbl_aspeto_impacte[ID_Impacte],"IMP-10")>0,"X","") | W18: =IF(COUNTIFS(tbl_aspeto_impacte[ID_Aspeto],$B18,tbl_aspeto_impacte[ID_Impacte],"IMP-11")>0,"X","") | X18: =IF(COUNTIFS(tbl_aspeto_impacte[ID_Aspeto],$B18,tbl_aspeto_impacte[ID_Impacte],"IMP-12")>0,"X","") | Y18: =LEFT(INDEX(Aspetos_Impactes!$R$5:$R$47,12),3) -> (+) | Z18: =INDEX(Aspetos_Impactes!$N$5:$N$47,12) -> 4 | AA18: =INDEX(Aspetos_Impactes!$O$5:$O$47,12) -> 3 | AB18: =INDEX(Aspetos_Impactes!$P$5:$P$47,12) -> 3 | AC18: =INDEX(Aspetos_Impactes!$Q$5:$Q$47,12) -> 1 | AD18: =INDEX(Aspetos_Impactes!$S$5:$S$47,12) -> 21 | AE18: =INDEX(Aspetos_Impactes!$T$5:$T$47,12) -> Moderado | AF18: =INDEX(Aspetos_Impactes!$W$5:$W$47,12) -> SIM | AG18: =INDEX(Aspetos_Impactes!$X$5:$X$47,12) -> SMED e receitas de arranque validadas.
A19: =INDEX(Aspetos_Impactes!$C$5:$C$47,13)&" — "&INDEX(Aspetos_Impactes!$D$5:$D$47,13) -> Sopro de frascos (ISBM) — Hidráulica envelhecida da ISBM-005 | B19: =INDEX(Aspetos_Impactes!$A$5:$A$47,13) -> AA-013 | C19: =IF(INDEX(Aspetos_Impactes!$E$5:$E$47,13)="Aquisição","X","") | D19: =IF(INDEX(Aspetos_Impactes!$E$5:$E$47,13)="Design e Conceção","X","") | E19: =IF(INDEX(Aspetos_Impactes!$E$5:$E$47,13)="Produção","X","") -> X | F19: =IF(INDEX(Aspetos_Impactes!$E$5:$E$47,13)="Distribuição","X","") | G19: =IF(INDEX(Aspetos_Impactes!$E$5:$E$47,13)="Uso (Consumidor Final)","X","") | H19: =IF(INDEX(Aspetos_Impactes!$E$5:$E$47,13)="Fim de Vida","X","") | I19: =INDEX(Aspetos_Impactes!$G$5:$G$47,13) -> Fugas de óleo hidráulico na ISBM-005 (paragens não planeadas 2,3× a média) | J19: =INDEX(Aspetos_Impactes!$H$5:$H$47,13) -> Direto | K19: =INDEX(Aspetos_Impactes!$I$5:$I$47,13) -> Anormal | L19: =INDEX(Aspetos_Impactes!$J$5:$J$47,13) -> Presente | M19: =IF(COUNTIFS(tbl_aspeto_impacte[ID_Aspeto],$B19,tbl_aspeto_impacte[ID_Impacte],"IMP-01")>0,"X","") | N19: =IF(COUNTIFS(tbl_aspeto_impacte[ID_Aspeto],$B19,tbl_aspeto_impacte[ID_Impacte],"IMP-02")>0,"X","") -> X | O19: =IF(COUNTIFS(tbl_aspeto_impacte[ID_Aspeto],$B19,tbl_aspeto_impacte[ID_Impacte],"IMP-03")>0,"X","") | P19: =IF(COUNTIFS(tbl_aspeto_impacte[ID_Aspeto],$B19,tbl_aspeto_impacte[ID_Impacte],"IMP-04")>0,"X","") | Q19: =IF(COUNTIFS(tbl_aspeto_impacte[ID_Aspeto],$B19,tbl_aspeto_impacte[ID_Impacte],"IMP-05")>0,"X","") | R19: =IF(COUNTIFS(tbl_aspeto_impacte[ID_Aspeto],$B19,tbl_aspeto_impacte[ID_Impacte],"IMP-06")>0,"X","") | S19: =IF(COUNTIFS(tbl_aspeto_impacte[ID_Aspeto],$B19,tbl_aspeto_impacte[ID_Impacte],"IMP-07")>0,"X","") | T19: =IF(COUNTIFS(tbl_aspeto_impacte[ID_Aspeto],$B19,tbl_aspeto_impacte[ID_Impacte],"IMP-08")>0,"X","") | U19: =IF(COUNTIFS(tbl_aspeto_impacte[ID_Aspeto],$B19,tbl_aspeto_impacte[ID_Impacte],"IMP-09")>0,"X","") | V19: =IF(COUNTIFS(tbl_aspeto_impacte[ID_Aspeto],$B19,tbl_aspeto_impacte[ID_Impacte],"IMP-10")>0,"X","") | W19: =IF(COUNTIFS(tbl_aspeto_impacte[ID_Aspeto],$B19,tbl_aspeto_impacte[ID_Impacte],"IMP-11")>0,"X","") | X19: =IF(COUNTIFS(tbl_aspeto_impacte[ID_Aspeto],$B19,tbl_aspeto_impacte[ID_Impacte],"IMP-12")>0,"X","") | Y19: =LEFT(INDEX(Aspetos_Impactes!$R$5:$R$47,13),3) -> (+) | Z19: =INDEX(Aspetos_Impactes!$N$5:$N$47,13) -> 4 | AA19: =INDEX(Aspetos_Impactes!$O$5:$O$47,13) -> 2 | AB19: =INDEX(Aspetos_Impactes!$P$5:$P$47,13) -> 4 | AC19: =INDEX(Aspetos_Impactes!$Q$5:$Q$47,13) -> 1 | AD19: =INDEX(Aspetos_Impactes!$S$5:$S$47,13) -> 24 | AE19: =INDEX(Aspetos_Impactes!$T$5:$T$47,13) -> Moderado | AF19: =INDEX(Aspetos_Impactes!$W$5:$W$47,13) -> SIM | AG19: =INDEX(Aspetos_Impactes!$X$5:$X$47,13) -> Plano de manutenção por horas de operação; tabuleiro de retenção.
A20: =INDEX(Aspetos_Impactes!$C$5:$C$47,14)&" — "&INDEX(Aspetos_Impactes!$D$5:$D$47,14) -> Serigrafia — Limpeza de ecrãs e rodos com solvente | B20: =INDEX(Aspetos_Impactes!$A$5:$A$47,14) -> AA-014 | C20: =IF(INDEX(Aspetos_Impactes!$E$5:$E$47,14)="Aquisição","X","") | D20: =IF(INDEX(Aspetos_Impactes!$E$5:$E$47,14)="Design e Conceção","X","") | E20: =IF(INDEX(Aspetos_Impactes!$E$5:$E$47,14)="Produção","X","") -> X | F20: =IF(INDEX(Aspetos_Impactes!$E$5:$E$47,14)="Distribuição","X","") | G20: =IF(INDEX(Aspetos_Impactes!$E$5:$E$47,14)="Uso (Consumidor Final)","X","") | H20: =IF(INDEX(Aspetos_Impactes!$E$5:$E$47,14)="Fim de Vida","X","") | I20: =INDEX(Aspetos_Impactes!$G$5:$G$47,14) -> Emissão difusa de COV na limpeza de ecrãs e rodos com solvente | J20: =INDEX(Aspetos_Impactes!$H$5:$H$47,14) -> Direto | K20: =INDEX(Aspetos_Impactes!$I$5:$I$47,14) -> Normal | L20: =INDEX(Aspetos_Impactes!$J$5:$J$47,14) -> Presente | M20: =IF(COUNTIFS(tbl_aspeto_impacte[ID_Aspeto],$B20,tbl_aspeto_impacte[ID_Impacte],"IMP-01")>0,"X","") | N20: =IF(COUNTIFS(tbl_aspeto_impacte[ID_Aspeto],$B20,tbl_aspeto_impacte[ID_Impacte],"IMP-02")>0,"X","") | O20: =IF(COUNTIFS(tbl_aspeto_impacte[ID_Aspeto],$B20,tbl_aspeto_impacte[ID_Impacte],"IMP-03")>0,"X","") -> X | P20: =IF(COUNTIFS(tbl_aspeto_impacte[ID_Aspeto],$B20,tbl_aspeto_impacte[ID_Impacte],"IMP-04")>0,"X","") -> X | Q20: =IF(COUNTIFS(tbl_aspeto_impacte[ID_Aspeto],$B20,tbl_aspeto_impacte[ID_Impacte],"IMP-05")>0,"X","") | R20: =IF(COUNTIFS(tbl_aspeto_impacte[ID_Aspeto],$B20,tbl_aspeto_impacte[ID_Impacte],"IMP-06")>0,"X","") | S20: =IF(COUNTIFS(tbl_aspeto_impacte[ID_Aspeto],$B20,tbl_aspeto_impacte[ID_Impacte],"IMP-07")>0,"X","") | T20: =IF(COUNTIFS(tbl_aspeto_impacte[ID_Aspeto],$B20,tbl_aspeto_impacte[ID_Impacte],"IMP-08")>0,"X","") | U20: =IF(COUNTIFS(tbl_aspeto_impacte[ID_Aspeto],$B20,tbl_aspeto_impacte[ID_Impacte],"IMP-09")>0,"X","") | V20: =IF(COUNTIFS(tbl_aspeto_impacte[ID_Aspeto],$B20,tbl_aspeto_impacte[ID_Impacte],"IMP-10")>0,"X","") | W20: =IF(COUNTIFS(tbl_aspeto_impacte[ID_Aspeto],$B20,tbl_aspeto_impacte[ID_Impacte],"IMP-11")>0,"X","") | X20: =IF(COUNTIFS(tbl_aspeto_impacte[ID_Aspeto],$B20,tbl_aspeto_impacte[ID_Impacte],"IMP-12")>0,"X","") | Y20: =LEFT(INDEX(Aspetos_Impactes!$R$5:$R$47,14),3) -> (+) | Z20: =INDEX(Aspetos_Impactes!$N$5:$N$47,14) -> 5 | AA20: =INDEX(Aspetos_Impactes!$O$5:$O$47,14) -> 3 | AB20: =INDEX(Aspetos_Impactes!$P$5:$P$47,14) -> 5 | AC20: =INDEX(Aspetos_Impactes!$Q$5:$Q$47,14) -> 1 | AD20: =INDEX(Aspetos_Impactes!$S$5:$S$47,14) -> 40 | AE20: =INDEX(Aspetos_Impactes!$T$5:$T$47,14) -> ASPETO AMBIENTAL SIGNIFICATIVO (AAS) | AF20: =INDEX(Aspetos_Impactes!$W$5:$W$47,14) -> SIM | AG20: =INDEX(Aspetos_Impactes!$X$5:$X$47,14) -> Dispensadores de segurança, panos pré-dosados, limpeza por necessidade, avaliação de solvente de menor volatilidade.
A21: =INDEX(Aspetos_Impactes!$C$5:$C$47,15)&" — "&INDEX(Aspetos_Impactes!$D$5:$D$47,15) -> Serigrafia — Impressão serigráfica (SS-001, SS-002) | B21: =INDEX(Aspetos_Impactes!$A$5:$A$47,15) -> AA-015 | C21: =IF(INDEX(Aspetos_Impactes!$E$5:$E$47,15)="Aquisição","X","") | D21: =IF(INDEX(Aspetos_Impactes!$E$5:$E$47,15)="Design e Conceção","X","") | E21: =IF(INDEX(Aspetos_Impactes!$E$5:$E$47,15)="Produção","X","") -> X | F21: =IF(INDEX(Aspetos_Impactes!$E$5:$E$47,15)="Distribuição","X","") | G21: =IF(INDEX(Aspetos_Impactes!$E$5:$E$47,15)="Uso (Consumidor Final)","X","") | H21: =IF(INDEX(Aspetos_Impactes!$E$5:$E$47,15)="Fim de Vida","X","") | I21: =INDEX(Aspetos_Impactes!$G$5:$G$47,15) -> Consumo de tintas de serigrafia | J21: =INDEX(Aspetos_Impactes!$H$5:$H$47,15) -> Direto | K21: =INDEX(Aspetos_Impactes!$I$5:$I$47,15) -> Normal | L21: =INDEX(Aspetos_Impactes!$J$5:$J$47,15) -> Presente | M21: =IF(COUNTIFS(tbl_aspeto_impacte[ID_Aspeto],$B21,tbl_aspeto_impacte[ID_Impacte],"IMP-01")>0,"X","") -> X | N21: =IF(COUNTIFS(tbl_aspeto_impacte[ID_Aspeto],$B21,tbl_aspeto_impacte[ID_Impacte],"IMP-02")>0,"X","") | O21: =IF(COUNTIFS(tbl_aspeto_impacte[ID_Aspeto],$B21,tbl_aspeto_impacte[ID_Impacte],"IMP-03")>0,"X","") -> X | P21: =IF(COUNTIFS(tbl_aspeto_impacte[ID_Aspeto],$B21,tbl_aspeto_impacte[ID_Impacte],"IMP-04")>0,"X","") | Q21: =IF(COUNTIFS(tbl_aspeto_impacte[ID_Aspeto],$B21,tbl_aspeto_impacte[ID_Impacte],"IMP-05")>0,"X","") | R21: =IF(COUNTIFS(tbl_aspeto_impacte[ID_Aspeto],$B21,tbl_aspeto_impacte[ID_Impacte],"IMP-06")>0,"X","") | S21: =IF(COUNTIFS(tbl_aspeto_impacte[ID_Aspeto],$B21,tbl_aspeto_impacte[ID_Impacte],"IMP-07")>0,"X","") | T21: =IF(COUNTIFS(tbl_aspeto_impacte[ID_Aspeto],$B21,tbl_aspeto_impacte[ID_Impacte],"IMP-08")>0,"X","") | U21: =IF(COUNTIFS(tbl_aspeto_impacte[ID_Aspeto],$B21,tbl_aspeto_impacte[ID_Impacte],"IMP-09")>0,"X","") | V21: =IF(COUNTIFS(tbl_aspeto_impacte[ID_Aspeto],$B21,tbl_aspeto_impacte[ID_Impacte],"IMP-10")>0,"X","") | W21: =IF(COUNTIFS(tbl_aspeto_impacte[ID_Aspeto],$B21,tbl_aspeto_impacte[ID_Impacte],"IMP-11")>0,"X","") | X21: =IF(COUNTIFS(tbl_aspeto_impacte[ID_Aspeto],$B21,tbl_aspeto_impacte[ID_Impacte],"IMP-12")>0,"X","") | Y21: =LEFT(INDEX(Aspetos_Impactes!$R$5:$R$47,15),3) -> (+) | Z21: =INDEX(Aspetos_Impactes!$N$5:$N$47,15) -> 5 | AA21: =INDEX(Aspetos_Impactes!$O$5:$O$47,15) -> 3 | AB21: =INDEX(Aspetos_Impactes!$P$5:$P$47,15) -> 4 | AC21: =INDEX(Aspetos_Impactes!$Q$5:$Q$47,15) -> 1 | AD21: =INDEX(Aspetos_Impactes!$S$5:$S$47,15) -> 32 | AE21: =INDEX(Aspetos_Impactes!$T$5:$T$47,15) -> Moderado | AF21: =INDEX(Aspetos_Impactes!$W$5:$W$47,15) -> SIM | AG21: =INDEX(Aspetos_Impactes!$X$5:$X$47,15) -> Dosagem controlada; recuperação de tinta do ecrã.
A22: =INDEX(Aspetos_Impactes!$C$5:$C$47,16)&" — "&INDEX(Aspetos_Impactes!$D$5:$D$47,16) -> Serigrafia — Limpeza e troca de tintas | B22: =INDEX(Aspetos_Impactes!$A$5:$A$47,16) -> AA-016 | C22: =IF(INDEX(Aspetos_Impactes!$E$5:$E$47,16)="Aquisição","X","") | D22: =IF(INDEX(Aspetos_Impactes!$E$5:$E$47,16)="Design e Conceção","X","") | E22: =IF(INDEX(Aspetos_Impactes!$E$5:$E$47,16)="Produção","X","") -> X | F22: =IF(INDEX(Aspetos_Impactes!$E$5:$E$47,16)="Distribuição","X","") | G22: =IF(INDEX(Aspetos_Impactes!$E$5:$E$47,16)="Uso (Consumidor Final)","X","") | H22: =IF(INDEX(Aspetos_Impactes!$E$5:$E$47,16)="Fim de Vida","X","") | I22: =INDEX(Aspetos_Impactes!$G$5:$G$47,16) -> Resíduos perigosos: tinta residual (08 03 12*), panos/absorventes (15 02 02*) e embalagens contaminadas (15 01 10*) | J22: =INDEX(Aspetos_Impactes!$H$5:$H$47,16) -> Direto | K22: =INDEX(Aspetos_Impactes!$I$5:$I$47,16) -> Normal | L22: =INDEX(Aspetos_Impactes!$J$5:$J$47,16) -> Presente | M22: =IF(COUNTIFS(tbl_aspeto_impacte[ID_Aspeto],$B22,tbl_aspeto_impacte[ID_Impacte],"IMP-01")>0,"X","") | N22: =IF(COUNTIFS(tbl_aspeto_impacte[ID_Aspeto],$B22,tbl_aspeto_impacte[ID_Impacte],"IMP-02")>0,"X","") -> X | O22: =IF(COUNTIFS(tbl_aspeto_impacte[ID_Aspeto],$B22,tbl_aspeto_impacte[ID_Impacte],"IMP-03")>0,"X","") | P22: =IF(COUNTIFS(tbl_aspeto_impacte[ID_Aspeto],$B22,tbl_aspeto_impacte[ID_Impacte],"IMP-04")>0,"X","") | Q22: =IF(COUNTIFS(tbl_aspeto_impacte[ID_Aspeto],$B22,tbl_aspeto_impacte[ID_Impacte],"IMP-05")>0,"X","") | R22: =IF(COUNTIFS(tbl_aspeto_impacte[ID_Aspeto],$B22,tbl_aspeto_impacte[ID_Impacte],"IMP-06")>0,"X","") | S22: =IF(COUNTIFS(tbl_aspeto_impacte[ID_Aspeto],$B22,tbl_aspeto_impacte[ID_Impacte],"IMP-07")>0,"X","") -> X | T22: =IF(COUNTIFS(tbl_aspeto_impacte[ID_Aspeto],$B22,tbl_aspeto_impacte[ID_Impacte],"IMP-08")>0,"X","") | U22: =IF(COUNTIFS(tbl_aspeto_impacte[ID_Aspeto],$B22,tbl_aspeto_impacte[ID_Impacte],"IMP-09")>0,"X","") | V22: =IF(COUNTIFS(tbl_aspeto_impacte[ID_Aspeto],$B22,tbl_aspeto_impacte[ID_Impacte],"IMP-10")>0,"X","") | W22: =IF(COUNTIFS(tbl_aspeto_impacte[ID_Aspeto],$B22,tbl_aspeto_impacte[ID_Impacte],"IMP-11")>0,"X","") | X22: =IF(COUNTIFS(tbl_aspeto_impacte[ID_Aspeto],$B22,tbl_aspeto_impacte[ID_Impacte],"IMP-12")>0,"X","") | Y22: =LEFT(INDEX(Aspetos_Impactes!$R$5:$R$47,16),3) -> (+) | Z22: =INDEX(Aspetos_Impactes!$N$5:$N$47,16) -> 4 | AA22: =INDEX(Aspetos_Impactes!$O$5:$O$47,16) -> 3 | AB22: =INDEX(Aspetos_Impactes!$P$5:$P$47,16) -> 4 | AC22: =INDEX(Aspetos_Impactes!$Q$5:$Q$47,16) -> 1 | AD22: =INDEX(Aspetos_Impactes!$S$5:$S$47,16) -> 28 | AE22: =INDEX(Aspetos_Impactes!$T$5:$T$47,16) -> Moderado | AF22: =INDEX(Aspetos_Impactes!$W$5:$W$47,16) -> SIM | AG22: =INDEX(Aspetos_Impactes!$X$5:$X$47,16) -> Recipientes fechados e identificados; encaminhamento por operador licenciado; e-GAR.
A23: =INDEX(Aspetos_Impactes!$C$5:$C$47,17)&" — "&INDEX(Aspetos_Impactes!$D$5:$D$47,17) -> Serigrafia — Mudança de tinta na linha | B23: =INDEX(Aspetos_Impactes!$A$5:$A$47,17) -> AA-017 | C23: =IF(INDEX(Aspetos_Impactes!$E$5:$E$47,17)="Aquisição","X","") | D23: =IF(INDEX(Aspetos_Impactes!$E$5:$E$47,17)="Design e Conceção","X","") | E23: =IF(INDEX(Aspetos_Impactes!$E$5:$E$47,17)="Produção","X","") -> X | F23: =IF(INDEX(Aspetos_Impactes!$E$5:$E$47,17)="Distribuição","X","") | G23: =IF(INDEX(Aspetos_Impactes!$E$5:$E$47,17)="Uso (Consumidor Final)","X","") | H23: =IF(INDEX(Aspetos_Impactes!$E$5:$E$47,17)="Fim de Vida","X","") | I23: =INDEX(Aspetos_Impactes!$G$5:$G$47,17) -> Derrame de tinta ou solvente na linha de serigrafia | J23: =INDEX(Aspetos_Impactes!$H$5:$H$47,17) -> Direto | K23: =INDEX(Aspetos_Impactes!$I$5:$I$47,17) -> Emergência | L23: =INDEX(Aspetos_Impactes!$J$5:$J$47,17) -> Futuro | M23: =IF(COUNTIFS(tbl_aspeto_impacte[ID_Aspeto],$B23,tbl_aspeto_impacte[ID_Impacte],"IMP-01")>0,"X","") | N23: =IF(COUNTIFS(tbl_aspeto_impacte[ID_Aspeto],$B23,tbl_aspeto_impacte[ID_Impacte],"IMP-02")>0,"X","") -> X | O23: =IF(COUNTIFS(tbl_aspeto_impacte[ID_Aspeto],$B23,tbl_aspeto_impacte[ID_Impacte],"IMP-03")>0,"X","") -> X | P23: =IF(COUNTIFS(tbl_aspeto_impacte[ID_Aspeto],$B23,tbl_aspeto_impacte[ID_Impacte],"IMP-04")>0,"X","") | Q23: =IF(COUNTIFS(tbl_aspeto_impacte[ID_Aspeto],$B23,tbl_aspeto_impacte[ID_Impacte],"IMP-05")>0,"X","") | R23: =IF(COUNTIFS(tbl_aspeto_impacte[ID_Aspeto],$B23,tbl_aspeto_impacte[ID_Impacte],"IMP-06")>0,"X","") | S23: =IF(COUNTIFS(tbl_aspeto_impacte[ID_Aspeto],$B23,tbl_aspeto_impacte[ID_Impacte],"IMP-07")>0,"X","") | T23: =IF(COUNTIFS(tbl_aspeto_impacte[ID_Aspeto],$B23,tbl_aspeto_impacte[ID_Impacte],"IMP-08")>0,"X","") | U23: =IF(COUNTIFS(tbl_aspeto_impacte[ID_Aspeto],$B23,tbl_aspeto_impacte[ID_Impacte],"IMP-09")>0,"X","") | V23: =IF(COUNTIFS(tbl_aspeto_impacte[ID_Aspeto],$B23,tbl_aspeto_impacte[ID_Impacte],"IMP-10")>0,"X","") | W23: =IF(COUNTIFS(tbl_aspeto_impacte[ID_Aspeto],$B23,tbl_aspeto_impacte[ID_Impacte],"IMP-11")>0,"X","") | X23: =IF(COUNTIFS(tbl_aspeto_impacte[ID_Aspeto],$B23,tbl_aspeto_impacte[ID_Impacte],"IMP-12")>0,"X","") | Y23: =LEFT(INDEX(Aspetos_Impactes!$R$5:$R$47,17),3) -> (+) | Z23: =INDEX(Aspetos_Impactes!$N$5:$N$47,17) -> 1 | AA23: =INDEX(Aspetos_Impactes!$O$5:$O$47,17) -> 2 | AB23: =INDEX(Aspetos_Impactes!$P$5:$P$47,17) -> 5 | AC23: =INDEX(Aspetos_Impactes!$Q$5:$Q$47,17) -> 1 | AD23: =INDEX(Aspetos_Impactes!$S$5:$S$47,17) -> 15 | AE23: =INDEX(Aspetos_Impactes!$T$5:$T$47,17) -> Não Significativo | AF23: =INDEX(Aspetos_Impactes!$W$5:$W$47,17) -> NÃO | AG23: =INDEX(Aspetos_Impactes!$X$5:$X$47,17) -> Kit de derrame junto à linha; IT-SGA-01.
A24: =INDEX(Aspetos_Impactes!$C$5:$C$47,18)&" — "&INDEX(Aspetos_Impactes!$D$5:$D$47,18) -> Hot foil stamping — Decoração por hot foil (HF-001, HF-002) | B24: =INDEX(Aspetos_Impactes!$A$5:$A$47,18) -> AA-018 | C24: =IF(INDEX(Aspetos_Impactes!$E$5:$E$47,18)="Aquisição","X","") | D24: =IF(INDEX(Aspetos_Impactes!$E$5:$E$47,18)="Design e Conceção","X","") | E24: =IF(INDEX(Aspetos_Impactes!$E$5:$E$47,18)="Produção","X","") -> X | F24: =IF(INDEX(Aspetos_Impactes!$E$5:$E$47,18)="Distribuição","X","") | G24: =IF(INDEX(Aspetos_Impactes!$E$5:$E$47,18)="Uso (Consumidor Final)","X","") | H24: =IF(INDEX(Aspetos_Impactes!$E$5:$E$47,18)="Fim de Vida","X","") | I24: =INDEX(Aspetos_Impactes!$G$5:$G$47,18) -> Resíduo de foil (filme de suporte com restos de metalização) | J24: =INDEX(Aspetos_Impactes!$H$5:$H$47,18) -> Direto | K24: =INDEX(Aspetos_Impactes!$I$5:$I$47,18) -> Normal | L24: =INDEX(Aspetos_Impactes!$J$5:$J$47,18) -> Presente | M24: =IF(COUNTIFS(tbl_aspeto_impacte[ID_Aspeto],$B24,tbl_aspeto_impacte[ID_Impacte],"IMP-01")>0,"X","") -> X | N24: =IF(COUNTIFS(tbl_aspeto_impacte[ID_Aspeto],$B24,tbl_aspeto_impacte[ID_Impacte],"IMP-02")>0,"X","") | O24: =IF(COUNTIFS(tbl_aspeto_impacte[ID_Aspeto],$B24,tbl_aspeto_impacte[ID_Impacte],"IMP-03")>0,"X","") | P24: =IF(COUNTIFS(tbl_aspeto_impacte[ID_Aspeto],$B24,tbl_aspeto_impacte[ID_Impacte],"IMP-04")>0,"X","") | Q24: =IF(COUNTIFS(tbl_aspeto_impacte[ID_Aspeto],$B24,tbl_aspeto_impacte[ID_Impacte],"IMP-05")>0,"X","") | R24: =IF(COUNTIFS(tbl_aspeto_impacte[ID_Aspeto],$B24,tbl_aspeto_impacte[ID_Impacte],"IMP-06")>0,"X","") | S24: =IF(COUNTIFS(tbl_aspeto_impacte[ID_Aspeto],$B24,tbl_aspeto_impacte[ID_Impacte],"IMP-07")>0,"X","") -> X | T24: =IF(COUNTIFS(tbl_aspeto_impacte[ID_Aspeto],$B24,tbl_aspeto_impacte[ID_Impacte],"IMP-08")>0,"X","") | U24: =IF(COUNTIFS(tbl_aspeto_impacte[ID_Aspeto],$B24,tbl_aspeto_impacte[ID_Impacte],"IMP-09")>0,"X","") | V24: =IF(COUNTIFS(tbl_aspeto_impacte[ID_Aspeto],$B24,tbl_aspeto_impacte[ID_Impacte],"IMP-10")>0,"X","") | W24: =IF(COUNTIFS(tbl_aspeto_impacte[ID_Aspeto],$B24,tbl_aspeto_impacte[ID_Impacte],"IMP-11")>0,"X","") | X24: =IF(COUNTIFS(tbl_aspeto_impacte[ID_Aspeto],$B24,tbl_aspeto_impacte[ID_Impacte],"IMP-12")>0,"X","") | Y24: =LEFT(INDEX(Aspetos_Impactes!$R$5:$R$47,18),3) -> (+) | Z24: =INDEX(Aspetos_Impactes!$N$5:$N$47,18) -> 5 | AA24: =INDEX(Aspetos_Impactes!$O$5:$O$47,18) -> 3 | AB24: =INDEX(Aspetos_Impactes!$P$5:$P$47,18) -> 2 | AC24: =INDEX(Aspetos_Impactes!$Q$5:$Q$47,18) -> 1 | AD24: =INDEX(Aspetos_Impactes!$S$5:$S$47,18) -> 16 | AE24: =INDEX(Aspetos_Impactes!$T$5:$T$47,18) -> Não Significativo | AF24: =INDEX(Aspetos_Impactes!$W$5:$W$47,18) -> NÃO | AG24: =INDEX(Aspetos_Impactes!$X$5:$X$47,18) -> Otimizar passo do foil; valorizar filme como plástico.
A25: =INDEX(Aspetos_Impactes!$C$5:$C$47,19)&" — "&INDEX(Aspetos_Impactes!$D$5:$D$47,19) -> Hot foil stamping — Decoração por hot foil (HF-001, HF-002) | B25: =INDEX(Aspetos_Impactes!$A$5:$A$47,19) -> AA-019 | C25: =IF(INDEX(Aspetos_Impactes!$E$5:$E$47,19)="Aquisição","X","") | D25: =IF(INDEX(Aspetos_Impactes!$E$5:$E$47,19)="Design e Conceção","X","") | E25: =IF(INDEX(Aspetos_Impactes!$E$5:$E$47,19)="Produção","X","") -> X | F25: =IF(INDEX(Aspetos_Impactes!$E$5:$E$47,19)="Distribuição","X","") | G25: =IF(INDEX(Aspetos_Impactes!$E$5:$E$47,19)="Uso (Consumidor Final)","X","") | H25: =IF(INDEX(Aspetos_Impactes!$E$5:$E$47,19)="Fim de Vida","X","") | I25: =INDEX(Aspetos_Impactes!$G$5:$G$47,19) -> Consumo de energia elétrica (placas aquecidas) | J25: =INDEX(Aspetos_Impactes!$H$5:$H$47,19) -> Direto | K25: =INDEX(Aspetos_Impactes!$I$5:$I$47,19) -> Normal | L25: =INDEX(Aspetos_Impactes!$J$5:$J$47,19) -> Presente | M25: =IF(COUNTIFS(tbl_aspeto_impacte[ID_Aspeto],$B25,tbl_aspeto_impacte[ID_Impacte],"IMP-01")>0,"X","") -> X | N25: =IF(COUNTIFS(tbl_aspeto_impacte[ID_Aspeto],$B25,tbl_aspeto_impacte[ID_Impacte],"IMP-02")>0,"X","") | O25: =IF(COUNTIFS(tbl_aspeto_impacte[ID_Aspeto],$B25,tbl_aspeto_impacte[ID_Impacte],"IMP-03")>0,"X","") | P25: =IF(COUNTIFS(tbl_aspeto_impacte[ID_Aspeto],$B25,tbl_aspeto_impacte[ID_Impacte],"IMP-04")>0,"X","") -> X | Q25: =IF(COUNTIFS(tbl_aspeto_impacte[ID_Aspeto],$B25,tbl_aspeto_impacte[ID_Impacte],"IMP-05")>0,"X","") | R25: =IF(COUNTIFS(tbl_aspeto_impacte[ID_Aspeto],$B25,tbl_aspeto_impacte[ID_Impacte],"IMP-06")>0,"X","") | S25: =IF(COUNTIFS(tbl_aspeto_impacte[ID_Aspeto],$B25,tbl_aspeto_impacte[ID_Impacte],"IMP-07")>0,"X","") | T25: =IF(COUNTIFS(tbl_aspeto_impacte[ID_Aspeto],$B25,tbl_aspeto_impacte[ID_Impacte],"IMP-08")>0,"X","") | U25: =IF(COUNTIFS(tbl_aspeto_impacte[ID_Aspeto],$B25,tbl_aspeto_impacte[ID_Impacte],"IMP-09")>0,"X","") | V25: =IF(COUNTIFS(tbl_aspeto_impacte[ID_Aspeto],$B25,tbl_aspeto_impacte[ID_Impacte],"IMP-10")>0,"X","") | W25: =IF(COUNTIFS(tbl_aspeto_impacte[ID_Aspeto],$B25,tbl_aspeto_impacte[ID_Impacte],"IMP-11")>0,"X","") | X25: =IF(COUNTIFS(tbl_aspeto_impacte[ID_Aspeto],$B25,tbl_aspeto_impacte[ID_Impacte],"IMP-12")>0,"X","") | Y25: =LEFT(INDEX(Aspetos_Impactes!$R$5:$R$47,19),3) -> (+) | Z25: =INDEX(Aspetos_Impactes!$N$5:$N$47,19) -> 5 | AA25: =INDEX(Aspetos_Impactes!$O$5:$O$47,19) -> 2 | AB25: =INDEX(Aspetos_Impactes!$P$5:$P$47,19) -> 3 | AC25: =INDEX(Aspetos_Impactes!$Q$5:$Q$47,19) -> 1 | AD25: =INDEX(Aspetos_Impactes!$S$5:$S$47,19) -> 21 | AE25: =INDEX(Aspetos_Impactes!$T$5:$T$47,19) -> Moderado | AF25: =INDEX(Aspetos_Impactes!$W$5:$W$47,19) -> SIM | AG25: =INDEX(Aspetos_Impactes!$X$5:$X$47,19) -> Desligar placas nas paragens.
A26: =INDEX(Aspetos_Impactes!$C$5:$C$47,20)&" — "&INDEX(Aspetos_Impactes!$D$5:$D$47,20) -> Moagem de scrap — Moagem e reintegração de rebarbas | B26: =INDEX(Aspetos_Impactes!$A$5:$A$47,20) -> AA-020 | C26: =IF(INDEX(Aspetos_Impactes!$E$5:$E$47,20)="Aquisição","X","") | D26: =IF(INDEX(Aspetos_Impactes!$E$5:$E$47,20)="Design e Conceção","X","") | E26: =IF(INDEX(Aspetos_Impactes!$E$5:$E$47,20)="Produção","X","") -> X | F26: =IF(INDEX(Aspetos_Impactes!$E$5:$E$47,20)="Distribuição","X","") | G26: =IF(INDEX(Aspetos_Impactes!$E$5:$E$47,20)="Uso (Consumidor Final)","X","") | H26: =IF(INDEX(Aspetos_Impactes!$E$5:$E$47,20)="Fim de Vida","X","") | I26: =INDEX(Aspetos_Impactes!$G$5:$G$47,20) -> Reintegração de scrap limpo (regrind) em substituição de polímero novo | J26: =INDEX(Aspetos_Impactes!$H$5:$H$47,20) -> Direto | K26: =INDEX(Aspetos_Impactes!$I$5:$I$47,20) -> Normal | L26: =INDEX(Aspetos_Impactes!$J$5:$J$47,20) -> Presente | M26: =IF(COUNTIFS(tbl_aspeto_impacte[ID_Aspeto],$B26,tbl_aspeto_impacte[ID_Impacte],"IMP-01")>0,"X","") | N26: =IF(COUNTIFS(tbl_aspeto_impacte[ID_Aspeto],$B26,tbl_aspeto_impacte[ID_Impacte],"IMP-02")>0,"X","") | O26: =IF(COUNTIFS(tbl_aspeto_impacte[ID_Aspeto],$B26,tbl_aspeto_impacte[ID_Impacte],"IMP-03")>0,"X","") | P26: =IF(COUNTIFS(tbl_aspeto_impacte[ID_Aspeto],$B26,tbl_aspeto_impacte[ID_Impacte],"IMP-04")>0,"X","") | Q26: =IF(COUNTIFS(tbl_aspeto_impacte[ID_Aspeto],$B26,tbl_aspeto_impacte[ID_Impacte],"IMP-05")>0,"X","") | R26: =IF(COUNTIFS(tbl_aspeto_impacte[ID_Aspeto],$B26,tbl_aspeto_impacte[ID_Impacte],"IMP-06")>0,"X","") | S26: =IF(COUNTIFS(tbl_aspeto_impacte[ID_Aspeto],$B26,tbl_aspeto_impacte[ID_Impacte],"IMP-07")>0,"X","") | T26: =IF(COUNTIFS(tbl_aspeto_impacte[ID_Aspeto],$B26,tbl_aspeto_impacte[ID_Impacte],"IMP-08")>0,"X","") | U26: =IF(COUNTIFS(tbl_aspeto_impacte[ID_Aspeto],$B26,tbl_aspeto_impacte[ID_Impacte],"IMP-09")>0,"X","") -> X | V26: =IF(COUNTIFS(tbl_aspeto_impacte[ID_Aspeto],$B26,tbl_aspeto_impacte[ID_Impacte],"IMP-10")>0,"X","") -> X | W26: =IF(COUNTIFS(tbl_aspeto_impacte[ID_Aspeto],$B26,tbl_aspeto_impacte[ID_Impacte],"IMP-11")>0,"X","") | X26: =IF(COUNTIFS(tbl_aspeto_impacte[ID_Aspeto],$B26,tbl_aspeto_impacte[ID_Impacte],"IMP-12")>0,"X","") | Y26: =LEFT(INDEX(Aspetos_Impactes!$R$5:$R$47,20),3) -> (-) | Z26: =INDEX(Aspetos_Impactes!$N$5:$N$47,20) -> 5 | AA26: =INDEX(Aspetos_Impactes!$O$5:$O$47,20) -> 4 | AB26: =INDEX(Aspetos_Impactes!$P$5:$P$47,20) -> -1 | AC26: =INDEX(Aspetos_Impactes!$Q$5:$Q$47,20) -> 1 | AD26: =INDEX(Aspetos_Impactes!$S$5:$S$47,20) -> -9 | AE26: =INDEX(Aspetos_Impactes!$T$5:$T$47,20) -> Oportunidade Tática | AF26: =INDEX(Aspetos_Impactes!$W$5:$W$47,20) -> NÃO | AG26: =INDEX(Aspetos_Impactes!$X$5:$X$47,20) -> Segregar por polímero/cor para aumentar a taxa.
A27: =INDEX(Aspetos_Impactes!$C$5:$C$47,21)&" — "&INDEX(Aspetos_Impactes!$D$5:$D$47,21) -> Utilidades — Produção de ar comprimido (CMP-01/02) | B27: =INDEX(Aspetos_Impactes!$A$5:$A$47,21) -> AA-021 | C27: =IF(INDEX(Aspetos_Impactes!$E$5:$E$47,21)="Aquisição","X","") | D27: =IF(INDEX(Aspetos_Impactes!$E$5:$E$47,21)="Design e Conceção","X","") | E27: =IF(INDEX(Aspetos_Impactes!$E$5:$E$47,21)="Produção","X","") -> X | F27: =IF(INDEX(Aspetos_Impactes!$E$5:$E$47,21)="Distribuição","X","") | G27: =IF(INDEX(Aspetos_Impactes!$E$5:$E$47,21)="Uso (Consumidor Final)","X","") | H27: =IF(INDEX(Aspetos_Impactes!$E$5:$E$47,21)="Fim de Vida","X","") | I27: =INDEX(Aspetos_Impactes!$G$5:$G$47,21) -> Consumo de energia dos compressores, agravado por fugas na rede de ar comprimido | J27: =INDEX(Aspetos_Impactes!$H$5:$H$47,21) -> Direto | K27: =INDEX(Aspetos_Impactes!$I$5:$I$47,21) -> Normal | L27: =INDEX(Aspetos_Impactes!$J$5:$J$47,21) -> Presente | M27: =IF(COUNTIFS(tbl_aspeto_impacte[ID_Aspeto],$B27,tbl_aspeto_impacte[ID_Impacte],"IMP-01")>0,"X","") -> X | N27: =IF(COUNTIFS(tbl_aspeto_impacte[ID_Aspeto],$B27,tbl_aspeto_impacte[ID_Impacte],"IMP-02")>0,"X","") | O27: =IF(COUNTIFS(tbl_aspeto_impacte[ID_Aspeto],$B27,tbl_aspeto_impacte[ID_Impacte],"IMP-03")>0,"X","") | P27: =IF(COUNTIFS(tbl_aspeto_impacte[ID_Aspeto],$B27,tbl_aspeto_impacte[ID_Impacte],"IMP-04")>0,"X","") -> X | Q27: =IF(COUNTIFS(tbl_aspeto_impacte[ID_Aspeto],$B27,tbl_aspeto_impacte[ID_Impacte],"IMP-05")>0,"X","") | R27: =IF(COUNTIFS(tbl_aspeto_impacte[ID_Aspeto],$B27,tbl_aspeto_impacte[ID_Impacte],"IMP-06")>0,"X","") | S27: =IF(COUNTIFS(tbl_aspeto_impacte[ID_Aspeto],$B27,tbl_aspeto_impacte[ID_Impacte],"IMP-07")>0,"X","") | T27: =IF(COUNTIFS(tbl_aspeto_impacte[ID_Aspeto],$B27,tbl_aspeto_impacte[ID_Impacte],"IMP-08")>0,"X","") | U27: =IF(COUNTIFS(tbl_aspeto_impacte[ID_Aspeto],$B27,tbl_aspeto_impacte[ID_Impacte],"IMP-09")>0,"X","") | V27: =IF(COUNTIFS(tbl_aspeto_impacte[ID_Aspeto],$B27,tbl_aspeto_impacte[ID_Impacte],"IMP-10")>0,"X","") | W27: =IF(COUNTIFS(tbl_aspeto_impacte[ID_Aspeto],$B27,tbl_aspeto_impacte[ID_Impacte],"IMP-11")>0,"X","") | X27: =IF(COUNTIFS(tbl_aspeto_impacte[ID_Aspeto],$B27,tbl_aspeto_impacte[ID_Impacte],"IMP-12")>0,"X","") | Y27: =LEFT(INDEX(Aspetos_Impactes!$R$5:$R$47,21),3) -> (+) | Z27: =INDEX(Aspetos_Impactes!$N$5:$N$47,21) -> 5 | AA27: =INDEX(Aspetos_Impactes!$O$5:$O$47,21) -> 4 | AB27: =INDEX(Aspetos_Impactes!$P$5:$P$47,21) -> 3 | AC27: =INDEX(Aspetos_Impactes!$Q$5:$Q$47,21) -> 1 | AD27: =INDEX(Aspetos_Impactes!$S$5:$S$47,21) -> 27 | AE27: =INDEX(Aspetos_Impactes!$T$5:$T$47,21) -> Moderado | AF27: =INDEX(Aspetos_Impactes!$W$5:$W$47,21) -> SIM | AG27: =INDEX(Aspetos_Impactes!$X$5:$X$47,21) -> Caça a fugas por ultrassom; reduzir pressão de 7,5 para 6,8 bar.
A28: =INDEX(Aspetos_Impactes!$C$5:$C$47,22)&" — "&INDEX(Aspetos_Impactes!$D$5:$D$47,22) -> Utilidades — Operação dos compressores novos (2026) | B28: =INDEX(Aspetos_Impactes!$A$5:$A$47,22) -> AA-022 | C28: =IF(INDEX(Aspetos_Impactes!$E$5:$E$47,22)="Aquisição","X","") | D28: =IF(INDEX(Aspetos_Impactes!$E$5:$E$47,22)="Design e Conceção","X","") | E28: =IF(INDEX(Aspetos_Impactes!$E$5:$E$47,22)="Produção","X","") -> X | F28: =IF(INDEX(Aspetos_Impactes!$E$5:$E$47,22)="Distribuição","X","") | G28: =IF(INDEX(Aspetos_Impactes!$E$5:$E$47,22)="Uso (Consumidor Final)","X","") | H28: =IF(INDEX(Aspetos_Impactes!$E$5:$E$47,22)="Fim de Vida","X","") | I28: =INDEX(Aspetos_Impactes!$G$5:$G$47,22) -> Emissão de ruído para o exterior pelos compressores e torre de arrefecimento | J28: =INDEX(Aspetos_Impactes!$H$5:$H$47,22) -> Direto | K28: =INDEX(Aspetos_Impactes!$I$5:$I$47,22) -> Normal | L28: =INDEX(Aspetos_Impactes!$J$5:$J$47,22) -> Presente | M28: =IF(COUNTIFS(tbl_aspeto_impacte[ID_Aspeto],$B28,tbl_aspeto_impacte[ID_Impacte],"IMP-01")>0,"X","") | N28: =IF(COUNTIFS(tbl_aspeto_impacte[ID_Aspeto],$B28,tbl_aspeto_impacte[ID_Impacte],"IMP-02")>0,"X","") | O28: =IF(COUNTIFS(tbl_aspeto_impacte[ID_Aspeto],$B28,tbl_aspeto_impacte[ID_Impacte],"IMP-03")>0,"X","") | P28: =IF(COUNTIFS(tbl_aspeto_impacte[ID_Aspeto],$B28,tbl_aspeto_impacte[ID_Impacte],"IMP-04")>0,"X","") | Q28: =IF(COUNTIFS(tbl_aspeto_impacte[ID_Aspeto],$B28,tbl_aspeto_impacte[ID_Impacte],"IMP-05")>0,"X","") -> X | R28: =IF(COUNTIFS(tbl_aspeto_impacte[ID_Aspeto],$B28,tbl_aspeto_impacte[ID_Impacte],"IMP-06")>0,"X","") | S28: =IF(COUNTIFS(tbl_aspeto_impacte[ID_Aspeto],$B28,tbl_aspeto_impacte[ID_Impacte],"IMP-07")>0,"X","") | T28: =IF(COUNTIFS(tbl_aspeto_impacte[ID_Aspeto],$B28,tbl_aspeto_impacte[ID_Impacte],"IMP-08")>0,"X","") | U28: =IF(COUNTIFS(tbl_aspeto_impacte[ID_Aspeto],$B28,tbl_aspeto_impacte[ID_Impacte],"IMP-09")>0,"X","") | V28: =IF(COUNTIFS(tbl_aspeto_impacte[ID_Aspeto],$B28,tbl_aspeto_impacte[ID_Impacte],"IMP-10")>0,"X","") | W28: =IF(COUNTIFS(tbl_aspeto_impacte[ID_Aspeto],$B28,tbl_aspeto_impacte[ID_Impacte],"IMP-11")>0,"X","") | X28: =IF(COUNTIFS(tbl_aspeto_impacte[ID_Aspeto],$B28,tbl_aspeto_impacte[ID_Impacte],"IMP-12")>0,"X","") | Y28: =LEFT(INDEX(Aspetos_Impactes!$R$5:$R$47,22),3) -> (+) | Z28: =INDEX(Aspetos_Impactes!$N$5:$N$47,22) -> 5 | AA28: =INDEX(Aspetos_Impactes!$O$5:$O$47,22) -> 3 | AB28: =INDEX(Aspetos_Impactes!$P$5:$P$47,22) -> 2 | AC28: =INDEX(Aspetos_Impactes!$Q$5:$Q$47,22) -> 2 | AD28: =INDEX(Aspetos_Impactes!$S$5:$S$47,22) -> 32 | AE28: =INDEX(Aspetos_Impactes!$T$5:$T$47,22) -> ASPETO AMBIENTAL SIGNIFICATIVO (AAS) | AF28: =INDEX(Aspetos_Impactes!$W$5:$W$47,22) -> SIM | AG28: =INDEX(Aspetos_Impactes!$X$5:$X$47,22) -> Avaliação acústica por laboratório acreditado; atenuadores se necessário.
A29: =INDEX(Aspetos_Impactes!$C$5:$C$47,23)&" — "&INDEX(Aspetos_Impactes!$D$5:$D$47,23) -> Utilidades — Torre de arrefecimento TR-01 | B29: =INDEX(Aspetos_Impactes!$A$5:$A$47,23) -> AA-023 | C29: =IF(INDEX(Aspetos_Impactes!$E$5:$E$47,23)="Aquisição","X","") | D29: =IF(INDEX(Aspetos_Impactes!$E$5:$E$47,23)="Design e Conceção","X","") | E29: =IF(INDEX(Aspetos_Impactes!$E$5:$E$47,23)="Produção","X","") -> X | F29: =IF(INDEX(Aspetos_Impactes!$E$5:$E$47,23)="Distribuição","X","") | G29: =IF(INDEX(Aspetos_Impactes!$E$5:$E$47,23)="Uso (Consumidor Final)","X","") | H29: =IF(INDEX(Aspetos_Impactes!$E$5:$E$47,23)="Fim de Vida","X","") | I29: =INDEX(Aspetos_Impactes!$G$5:$G$47,23) -> Consumo de água de rede para reposição da torre de arrefecimento (evaporação e purga) | J29: =INDEX(Aspetos_Impactes!$H$5:$H$47,23) -> Direto | K29: =INDEX(Aspetos_Impactes!$I$5:$I$47,23) -> Normal | L29: =INDEX(Aspetos_Impactes!$J$5:$J$47,23) -> Presente | M29: =IF(COUNTIFS(tbl_aspeto_impacte[ID_Aspeto],$B29,tbl_aspeto_impacte[ID_Impacte],"IMP-01")>0,"X","") -> X | N29: =IF(COUNTIFS(tbl_aspeto_impacte[ID_Aspeto],$B29,tbl_aspeto_impacte[ID_Impacte],"IMP-02")>0,"X","") | O29: =IF(COUNTIFS(tbl_aspeto_impacte[ID_Aspeto],$B29,tbl_aspeto_impacte[ID_Impacte],"IMP-03")>0,"X","") | P29: =IF(COUNTIFS(tbl_aspeto_impacte[ID_Aspeto],$B29,tbl_aspeto_impacte[ID_Impacte],"IMP-04")>0,"X","") | Q29: =IF(COUNTIFS(tbl_aspeto_impacte[ID_Aspeto],$B29,tbl_aspeto_impacte[ID_Impacte],"IMP-05")>0,"X","") | R29: =IF(COUNTIFS(tbl_aspeto_impacte[ID_Aspeto],$B29,tbl_aspeto_impacte[ID_Impacte],"IMP-06")>0,"X","") | S29: =IF(COUNTIFS(tbl_aspeto_impacte[ID_Aspeto],$B29,tbl_aspeto_impacte[ID_Impacte],"IMP-07")>0,"X","") | T29: =IF(COUNTIFS(tbl_aspeto_impacte[ID_Aspeto],$B29,tbl_aspeto_impacte[ID_Impacte],"IMP-08")>0,"X","") | U29: =IF(COUNTIFS(tbl_aspeto_impacte[ID_Aspeto],$B29,tbl_aspeto_impacte[ID_Impacte],"IMP-09")>0,"X","") | V29: =IF(COUNTIFS(tbl_aspeto_impacte[ID_Aspeto],$B29,tbl_aspeto_impacte[ID_Impacte],"IMP-10")>0,"X","") | W29: =IF(COUNTIFS(tbl_aspeto_impacte[ID_Aspeto],$B29,tbl_aspeto_impacte[ID_Impacte],"IMP-11")>0,"X","") | X29: =IF(COUNTIFS(tbl_aspeto_impacte[ID_Aspeto],$B29,tbl_aspeto_impacte[ID_Impacte],"IMP-12")>0,"X","") | Y29: =LEFT(INDEX(Aspetos_Impactes!$R$5:$R$47,23),3) -> (+) | Z29: =INDEX(Aspetos_Impactes!$N$5:$N$47,23) -> 5 | AA29: =INDEX(Aspetos_Impactes!$O$5:$O$47,23) -> 4 | AB29: =INDEX(Aspetos_Impactes!$P$5:$P$47,23) -> 3 | AC29: =INDEX(Aspetos_Impactes!$Q$5:$Q$47,23) -> 1 | AD29: =INDEX(Aspetos_Impactes!$S$5:$S$47,23) -> 27 | AE29: =INDEX(Aspetos_Impactes!$T$5:$T$47,23) -> Moderado | AF29: =INDEX(Aspetos_Impactes!$W$5:$W$47,23) -> SIM | AG29: =INDEX(Aspetos_Impactes!$X$5:$X$47,23) -> Circuito fechado / torre adiabática; controlo da purga por condutividade.
A30: =INDEX(Aspetos_Impactes!$C$5:$C$47,24)&" — "&INDEX(Aspetos_Impactes!$D$5:$D$47,24) -> Utilidades — Purga da torre de arrefecimento | B30: =INDEX(Aspetos_Impactes!$A$5:$A$47,24) -> AA-024 | C30: =IF(INDEX(Aspetos_Impactes!$E$5:$E$47,24)="Aquisição","X","") | D30: =IF(INDEX(Aspetos_Impactes!$E$5:$E$47,24)="Design e Conceção","X","") | E30: =IF(INDEX(Aspetos_Impactes!$E$5:$E$47,24)="Produção","X","") -> X | F30: =IF(INDEX(Aspetos_Impactes!$E$5:$E$47,24)="Distribuição","X","") | G30: =IF(INDEX(Aspetos_Impactes!$E$5:$E$47,24)="Uso (Consumidor Final)","X","") | H30: =IF(INDEX(Aspetos_Impactes!$E$5:$E$47,24)="Fim de Vida","X","") | I30: =INDEX(Aspetos_Impactes!$G$5:$G$47,24) -> Descarga da purga da torre (com biocida e anti-incrustante) no coletor municipal | J30: =INDEX(Aspetos_Impactes!$H$5:$H$47,24) -> Direto | K30: =INDEX(Aspetos_Impactes!$I$5:$I$47,24) -> Normal | L30: =INDEX(Aspetos_Impactes!$J$5:$J$47,24) -> Presente | M30: =IF(COUNTIFS(tbl_aspeto_impacte[ID_Aspeto],$B30,tbl_aspeto_impacte[ID_Impacte],"IMP-01")>0,"X","") | N30: =IF(COUNTIFS(tbl_aspeto_impacte[ID_Aspeto],$B30,tbl_aspeto_impacte[ID_Impacte],"IMP-02")>0,"X","") -> X | O30: =IF(COUNTIFS(tbl_aspeto_impacte[ID_Aspeto],$B30,tbl_aspeto_impacte[ID_Impacte],"IMP-03")>0,"X","") | P30: =IF(COUNTIFS(tbl_aspeto_impacte[ID_Aspeto],$B30,tbl_aspeto_impacte[ID_Impacte],"IMP-04")>0,"X","") | Q30: =IF(COUNTIFS(tbl_aspeto_impacte[ID_Aspeto],$B30,tbl_aspeto_impacte[ID_Impacte],"IMP-05")>0,"X","") | R30: =IF(COUNTIFS(tbl_aspeto_impacte[ID_Aspeto],$B30,tbl_aspeto_impacte[ID_Impacte],"IMP-06")>0,"X","") | S30: =IF(COUNTIFS(tbl_aspeto_impacte[ID_Aspeto],$B30,tbl_aspeto_impacte[ID_Impacte],"IMP-07")>0,"X","") | T30: =IF(COUNTIFS(tbl_aspeto_impacte[ID_Aspeto],$B30,tbl_aspeto_impacte[ID_Impacte],"IMP-08")>0,"X","") | U30: =IF(COUNTIFS(tbl_aspeto_impacte[ID_Aspeto],$B30,tbl_aspeto_impacte[ID_Impacte],"IMP-09")>0,"X","") | V30: =IF(COUNTIFS(tbl_aspeto_impacte[ID_Aspeto],$B30,tbl_aspeto_impacte[ID_Impacte],"IMP-10")>0,"X","") | W30: =IF(COUNTIFS(tbl_aspeto_impacte[ID_Aspeto],$B30,tbl_aspeto_impacte[ID_Impacte],"IMP-11")>0,"X","") | X30: =IF(COUNTIFS(tbl_aspeto_impacte[ID_Aspeto],$B30,tbl_aspeto_impacte[ID_Impacte],"IMP-12")>0,"X","") | Y30: =LEFT(INDEX(Aspetos_Impactes!$R$5:$R$47,24),3) -> (+) | Z30: =INDEX(Aspetos_Impactes!$N$5:$N$47,24) -> 4 | AA30: =INDEX(Aspetos_Impactes!$O$5:$O$47,24) -> 3 | AB30: =INDEX(Aspetos_Impactes!$P$5:$P$47,24) -> 4 | AC30: =INDEX(Aspetos_Impactes!$Q$5:$Q$47,24) -> 1 | AD30: =INDEX(Aspetos_Impactes!$S$5:$S$47,24) -> 28 | AE30: =INDEX(Aspetos_Impactes!$T$5:$T$47,24) -> Moderado | AF30: =INDEX(Aspetos_Impactes!$W$5:$W$47,24) -> SIM | AG30: =INDEX(Aspetos_Impactes!$X$5:$X$47,24) -> Dosagem automática; análises; limites do regulamento municipal.
A31: =INDEX(Aspetos_Impactes!$C$5:$C$47,25)&" — "&INDEX(Aspetos_Impactes!$D$5:$D$47,25) -> Utilidades — Chiller CH-01 (R410A) | B31: =INDEX(Aspetos_Impactes!$A$5:$A$47,25) -> AA-025 | C31: =IF(INDEX(Aspetos_Impactes!$E$5:$E$47,25)="Aquisição","X","") | D31: =IF(INDEX(Aspetos_Impactes!$E$5:$E$47,25)="Design e Conceção","X","") | E31: =IF(INDEX(Aspetos_Impactes!$E$5:$E$47,25)="Produção","X","") -> X | F31: =IF(INDEX(Aspetos_Impactes!$E$5:$E$47,25)="Distribuição","X","") | G31: =IF(INDEX(Aspetos_Impactes!$E$5:$E$47,25)="Uso (Consumidor Final)","X","") | H31: =IF(INDEX(Aspetos_Impactes!$E$5:$E$47,25)="Fim de Vida","X","") | I31: =INDEX(Aspetos_Impactes!$G$5:$G$47,25) -> Fuga de gás fluorado R410A do chiller | J31: =INDEX(Aspetos_Impactes!$H$5:$H$47,25) -> Direto | K31: =INDEX(Aspetos_Impactes!$I$5:$I$47,25) -> Emergência | L31: =INDEX(Aspetos_Impactes!$J$5:$J$47,25) -> Passado | M31: =IF(COUNTIFS(tbl_aspeto_impacte[ID_Aspeto],$B31,tbl_aspeto_impacte[ID_Impacte],"IMP-01")>0,"X","") | N31: =IF(COUNTIFS(tbl_aspeto_impacte[ID_Aspeto],$B31,tbl_aspeto_impacte[ID_Impacte],"IMP-02")>0,"X","") | O31: =IF(COUNTIFS(tbl_aspeto_impacte[ID_Aspeto],$B31,tbl_aspeto_impacte[ID_Impacte],"IMP-03")>0,"X","") | P31: =IF(COUNTIFS(tbl_aspeto_impacte[ID_Aspeto],$B31,tbl_aspeto_impacte[ID_Impacte],"IMP-04")>0,"X","") -> X | Q31: =IF(COUNTIFS(tbl_aspeto_impacte[ID_Aspeto],$B31,tbl_aspeto_impacte[ID_Impacte],"IMP-05")>0,"X","") | R31: =IF(COUNTIFS(tbl_aspeto_impacte[ID_Aspeto],$B31,tbl_aspeto_impacte[ID_Impacte],"IMP-06")>0,"X","") | S31: =IF(COUNTIFS(tbl_aspeto_impacte[ID_Aspeto],$B31,tbl_aspeto_impacte[ID_Impacte],"IMP-07")>0,"X","") | T31: =IF(COUNTIFS(tbl_aspeto_impacte[ID_Aspeto],$B31,tbl_aspeto_impacte[ID_Impacte],"IMP-08")>0,"X","") | U31: =IF(COUNTIFS(tbl_aspeto_impacte[ID_Aspeto],$B31,tbl_aspeto_impacte[ID_Impacte],"IMP-09")>0,"X","") | V31: =IF(COUNTIFS(tbl_aspeto_impacte[ID_Aspeto],$B31,tbl_aspeto_impacte[ID_Impacte],"IMP-10")>0,"X","") | W31: =IF(COUNTIFS(tbl_aspeto_impacte[ID_Aspeto],$B31,tbl_aspeto_impacte[ID_Impacte],"IMP-11")>0,"X","") | X31: =IF(COUNTIFS(tbl_aspeto_impacte[ID_Aspeto],$B31,tbl_aspeto_impacte[ID_Impacte],"IMP-12")>0,"X","") | Y31: =LEFT(INDEX(Aspetos_Impactes!$R$5:$R$47,25),3) -> (+) | Z31: =INDEX(Aspetos_Impactes!$N$5:$N$47,25) -> 1 | AA31: =INDEX(Aspetos_Impactes!$O$5:$O$47,25) -> 1 | AB31: =INDEX(Aspetos_Impactes!$P$5:$P$47,25) -> 5 | AC31: =INDEX(Aspetos_Impactes!$Q$5:$Q$47,25) -> 1 | AD31: =INDEX(Aspetos_Impactes!$S$5:$S$47,25) -> 10 | AE31: =INDEX(Aspetos_Impactes!$T$5:$T$47,25) -> Não Significativo | AF31: =INDEX(Aspetos_Impactes!$W$5:$W$47,25) -> NÃO | AG31: =INDEX(Aspetos_Impactes!$X$5:$X$47,25) -> Controlo de fugas conforme carga em tCO2e; técnico certificado.
A32: =INDEX(Aspetos_Impactes!$C$5:$C$47,26)&" — "&INDEX(Aspetos_Impactes!$D$5:$D$47,26) -> Manutenção — Manutenção mecânica e elétrica | B32: =INDEX(Aspetos_Impactes!$A$5:$A$47,26) -> AA-026 | C32: =IF(INDEX(Aspetos_Impactes!$E$5:$E$47,26)="Aquisição","X","") | D32: =IF(INDEX(Aspetos_Impactes!$E$5:$E$47,26)="Design e Conceção","X","") | E32: =IF(INDEX(Aspetos_Impactes!$E$5:$E$47,26)="Produção","X","") -> X | F32: =IF(INDEX(Aspetos_Impactes!$E$5:$E$47,26)="Distribuição","X","") | G32: =IF(INDEX(Aspetos_Impactes!$E$5:$E$47,26)="Uso (Consumidor Final)","X","") | H32: =IF(INDEX(Aspetos_Impactes!$E$5:$E$47,26)="Fim de Vida","X","") | I32: =INDEX(Aspetos_Impactes!$G$5:$G$47,26) -> Geração de óleos usados (13 02 05*), lâmpadas (20 01 21*) e sucata metálica | J32: =INDEX(Aspetos_Impactes!$H$5:$H$47,26) -> Direto | K32: =INDEX(Aspetos_Impactes!$I$5:$I$47,26) -> Anormal | L32: =INDEX(Aspetos_Impactes!$J$5:$J$47,26) -> Presente | M32: =IF(COUNTIFS(tbl_aspeto_impacte[ID_Aspeto],$B32,tbl_aspeto_impacte[ID_Impacte],"IMP-01")>0,"X","") | N32: =IF(COUNTIFS(tbl_aspeto_impacte[ID_Aspeto],$B32,tbl_aspeto_impacte[ID_Impacte],"IMP-02")>0,"X","") -> X | O32: =IF(COUNTIFS(tbl_aspeto_impacte[ID_Aspeto],$B32,tbl_aspeto_impacte[ID_Impacte],"IMP-03")>0,"X","") | P32: =IF(COUNTIFS(tbl_aspeto_impacte[ID_Aspeto],$B32,tbl_aspeto_impacte[ID_Impacte],"IMP-04")>0,"X","") | Q32: =IF(COUNTIFS(tbl_aspeto_impacte[ID_Aspeto],$B32,tbl_aspeto_impacte[ID_Impacte],"IMP-05")>0,"X","") | R32: =IF(COUNTIFS(tbl_aspeto_impacte[ID_Aspeto],$B32,tbl_aspeto_impacte[ID_Impacte],"IMP-06")>0,"X","") | S32: =IF(COUNTIFS(tbl_aspeto_impacte[ID_Aspeto],$B32,tbl_aspeto_impacte[ID_Impacte],"IMP-07")>0,"X","") -> X | T32: =IF(COUNTIFS(tbl_aspeto_impacte[ID_Aspeto],$B32,tbl_aspeto_impacte[ID_Impacte],"IMP-08")>0,"X","") | U32: =IF(COUNTIFS(tbl_aspeto_impacte[ID_Aspeto],$B32,tbl_aspeto_impacte[ID_Impacte],"IMP-09")>0,"X","") | V32: =IF(COUNTIFS(tbl_aspeto_impacte[ID_Aspeto],$B32,tbl_aspeto_impacte[ID_Impacte],"IMP-10")>0,"X","") | W32: =IF(COUNTIFS(tbl_aspeto_impacte[ID_Aspeto],$B32,tbl_aspeto_impacte[ID_Impacte],"IMP-11")>0,"X","") | X32: =IF(COUNTIFS(tbl_aspeto_impacte[ID_Aspeto],$B32,tbl_aspeto_impacte[ID_Impacte],"IMP-12")>0,"X","") | Y32: =LEFT(INDEX(Aspetos_Impactes!$R$5:$R$47,26),3) -> (+) | Z32: =INDEX(Aspetos_Impactes!$N$5:$N$47,26) -> 2 | AA32: =INDEX(Aspetos_Impactes!$O$5:$O$47,26) -> 3 | AB32: =INDEX(Aspetos_Impactes!$P$5:$P$47,26) -> 4 | AC32: =INDEX(Aspetos_Impactes!$Q$5:$Q$47,26) -> 1 | AD32: =INDEX(Aspetos_Impactes!$S$5:$S$47,26) -> 20 | AE32: =INDEX(Aspetos_Impactes!$T$5:$T$47,26) -> Moderado | AF32: =INDEX(Aspetos_Impactes!$W$5:$W$47,26) -> SIM | AG32: =INDEX(Aspetos_Impactes!$X$5:$X$47,26) -> Recolha por operadores licenciados; armazenagem em bacia.
A33: =INDEX(Aspetos_Impactes!$C$5:$C$47,27)&" — "&INDEX(Aspetos_Impactes!$D$5:$D$47,27) -> Parque de resíduos — Armazenagem temporária de resíduos | B33: =INDEX(Aspetos_Impactes!$A$5:$A$47,27) -> AA-027 | C33: =IF(INDEX(Aspetos_Impactes!$E$5:$E$47,27)="Aquisição","X","") | D33: =IF(INDEX(Aspetos_Impactes!$E$5:$E$47,27)="Design e Conceção","X","") | E33: =IF(INDEX(Aspetos_Impactes!$E$5:$E$47,27)="Produção","X","") | F33: =IF(INDEX(Aspetos_Impactes!$E$5:$E$47,27)="Distribuição","X","") | G33: =IF(INDEX(Aspetos_Impactes!$E$5:$E$47,27)="Uso (Consumidor Final)","X","") | H33: =IF(INDEX(Aspetos_Impactes!$E$5:$E$47,27)="Fim de Vida","X","") -> X | I33: =INDEX(Aspetos_Impactes!$G$5:$G$47,27) -> Escorrência de resíduos perigosos armazenados para a rede pluvial em dia de chuva | J33: =INDEX(Aspetos_Impactes!$H$5:$H$47,27) -> Direto | K33: =INDEX(Aspetos_Impactes!$I$5:$I$47,27) -> Anormal | L33: =INDEX(Aspetos_Impactes!$J$5:$J$47,27) -> Presente | M33: =IF(COUNTIFS(tbl_aspeto_impacte[ID_Aspeto],$B33,tbl_aspeto_impacte[ID_Impacte],"IMP-01")>0,"X","") | N33: =IF(COUNTIFS(tbl_aspeto_impacte[ID_Aspeto],$B33,tbl_aspeto_impacte[ID_Impacte],"IMP-02")>0,"X","") -> X | O33: =IF(COUNTIFS(tbl_aspeto_impacte[ID_Aspeto],$B33,tbl_aspeto_impacte[ID_Impacte],"IMP-03")>0,"X","") | P33: =IF(COUNTIFS(tbl_aspeto_impacte[ID_Aspeto],$B33,tbl_aspeto_impacte[ID_Impacte],"IMP-04")>0,"X","") | Q33: =IF(COUNTIFS(tbl_aspeto_impacte[ID_Aspeto],$B33,tbl_aspeto_impacte[ID_Impacte],"IMP-05")>0,"X","") | R33: =IF(COUNTIFS(tbl_aspeto_impacte[ID_Aspeto],$B33,tbl_aspeto_impacte[ID_Impacte],"IMP-06")>0,"X","") | S33: =IF(COUNTIFS(tbl_aspeto_impacte[ID_Aspeto],$B33,tbl_aspeto_impacte[ID_Impacte],"IMP-07")>0,"X","") | T33: =IF(COUNTIFS(tbl_aspeto_impacte[ID_Aspeto],$B33,tbl_aspeto_impacte[ID_Impacte],"IMP-08")>0,"X","") | U33: =IF(COUNTIFS(tbl_aspeto_impacte[ID_Aspeto],$B33,tbl_aspeto_impacte[ID_Impacte],"IMP-09")>0,"X","") | V33: =IF(COUNTIFS(tbl_aspeto_impacte[ID_Aspeto],$B33,tbl_aspeto_impacte[ID_Impacte],"IMP-10")>0,"X","") | W33: =IF(COUNTIFS(tbl_aspeto_impacte[ID_Aspeto],$B33,tbl_aspeto_impacte[ID_Impacte],"IMP-11")>0,"X","") | X33: =IF(COUNTIFS(tbl_aspeto_impacte[ID_Aspeto],$B33,tbl_aspeto_impacte[ID_Impacte],"IMP-12")>0,"X","") | Y33: =LEFT(INDEX(Aspetos_Impactes!$R$5:$R$47,27),3) -> (+) | Z33: =INDEX(Aspetos_Impactes!$N$5:$N$47,27) -> 2 | AA33: =INDEX(Aspetos_Impactes!$O$5:$O$47,27) -> 2 | AB33: =INDEX(Aspetos_Impactes!$P$5:$P$47,27) -> 4 | AC33: =INDEX(Aspetos_Impactes!$Q$5:$Q$47,27) -> 1 | AD33: =INDEX(Aspetos_Impactes!$S$5:$S$47,27) -> 16 | AE33: =INDEX(Aspetos_Impactes!$T$5:$T$47,27) -> Não Significativo | AF33: =INDEX(Aspetos_Impactes!$W$5:$W$47,27) -> NÃO | AG33: =INDEX(Aspetos_Impactes!$X$5:$X$47,27) -> Cobertura e bacia no ponto de resíduos perigosos.
A34: =INDEX(Aspetos_Impactes!$C$5:$C$47,28)&" — "&INDEX(Aspetos_Impactes!$D$5:$D$47,28) -> Parque de resíduos — Encaminhamento de resíduos | B34: =INDEX(Aspetos_Impactes!$A$5:$A$47,28) -> AA-028 | C34: =IF(INDEX(Aspetos_Impactes!$E$5:$E$47,28)="Aquisição","X","") | D34: =IF(INDEX(Aspetos_Impactes!$E$5:$E$47,28)="Design e Conceção","X","") | E34: =IF(INDEX(Aspetos_Impactes!$E$5:$E$47,28)="Produção","X","") | F34: =IF(INDEX(Aspetos_Impactes!$E$5:$E$47,28)="Distribuição","X","") | G34: =IF(INDEX(Aspetos_Impactes!$E$5:$E$47,28)="Uso (Consumidor Final)","X","") | H34: =IF(INDEX(Aspetos_Impactes!$E$5:$E$47,28)="Fim de Vida","X","") -> X | I34: =INDEX(Aspetos_Impactes!$G$5:$G$47,28) -> Envio de scrap sujo e embalagens para reciclagem por operador licenciado (R3) | J34: =INDEX(Aspetos_Impactes!$H$5:$H$47,28) -> Indireto | K34: =INDEX(Aspetos_Impactes!$I$5:$I$47,28) -> Normal | L34: =INDEX(Aspetos_Impactes!$J$5:$J$47,28) -> Presente | M34: =IF(COUNTIFS(tbl_aspeto_impacte[ID_Aspeto],$B34,tbl_aspeto_impacte[ID_Impacte],"IMP-01")>0,"X","") | N34: =IF(COUNTIFS(tbl_aspeto_impacte[ID_Aspeto],$B34,tbl_aspeto_impacte[ID_Impacte],"IMP-02")>0,"X","") | O34: =IF(COUNTIFS(tbl_aspeto_impacte[ID_Aspeto],$B34,tbl_aspeto_impacte[ID_Impacte],"IMP-03")>0,"X","") | P34: =IF(COUNTIFS(tbl_aspeto_impacte[ID_Aspeto],$B34,tbl_aspeto_impacte[ID_Impacte],"IMP-04")>0,"X","") | Q34: =IF(COUNTIFS(tbl_aspeto_impacte[ID_Aspeto],$B34,tbl_aspeto_impacte[ID_Impacte],"IMP-05")>0,"X","") | R34: =IF(COUNTIFS(tbl_aspeto_impacte[ID_Aspeto],$B34,tbl_aspeto_impacte[ID_Impacte],"IMP-06")>0,"X","") | S34: =IF(COUNTIFS(tbl_aspeto_impacte[ID_Aspeto],$B34,tbl_aspeto_impacte[ID_Impacte],"IMP-07")>0,"X","") | T34: =IF(COUNTIFS(tbl_aspeto_impacte[ID_Aspeto],$B34,tbl_aspeto_impacte[ID_Impacte],"IMP-08")>0,"X","") | U34: =IF(COUNTIFS(tbl_aspeto_impacte[ID_Aspeto],$B34,tbl_aspeto_impacte[ID_Impacte],"IMP-09")>0,"X","") | V34: =IF(COUNTIFS(tbl_aspeto_impacte[ID_Aspeto],$B34,tbl_aspeto_impacte[ID_Impacte],"IMP-10")>0,"X","") | W34: =IF(COUNTIFS(tbl_aspeto_impacte[ID_Aspeto],$B34,tbl_aspeto_impacte[ID_Impacte],"IMP-11")>0,"X","") -> X | X34: =IF(COUNTIFS(tbl_aspeto_impacte[ID_Aspeto],$B34,tbl_aspeto_impacte[ID_Impacte],"IMP-12")>0,"X","") -> X | Y34: =LEFT(INDEX(Aspetos_Impactes!$R$5:$R$47,28),3) -> (-) | Z34: =INDEX(Aspetos_Impactes!$N$5:$N$47,28) -> 4 | AA34: =INDEX(Aspetos_Impactes!$O$5:$O$47,28) -> 3 | AB34: =INDEX(Aspetos_Impactes!$P$5:$P$47,28) -> -1 | AC34: =INDEX(Aspetos_Impactes!$Q$5:$Q$47,28) -> 1 | AD34: =INDEX(Aspetos_Impactes!$S$5:$S$47,28) -> -7 | AE34: =INDEX(Aspetos_Impactes!$T$5:$T$47,28) -> Oportunidade Tática | AF34: =INDEX(Aspetos_Impactes!$W$5:$W$47,28) -> NÃO | AG34: =INDEX(Aspetos_Impactes!$X$5:$X$47,28) -> Aumentar a segregação para subir a taxa de valorização.
A35: =INDEX(Aspetos_Impactes!$C$5:$C$47,29)&" — "&INDEX(Aspetos_Impactes!$D$5:$D$47,29) -> Geral — Funcionamento geral da instalação | B35: =INDEX(Aspetos_Impactes!$A$5:$A$47,29) -> AA-029 | C35: =IF(INDEX(Aspetos_Impactes!$E$5:$E$47,29)="Aquisição","X","") | D35: =IF(INDEX(Aspetos_Impactes!$E$5:$E$47,29)="Design e Conceção","X","") | E35: =IF(INDEX(Aspetos_Impactes!$E$5:$E$47,29)="Produção","X","") -> X | F35: =IF(INDEX(Aspetos_Impactes!$E$5:$E$47,29)="Distribuição","X","") | G35: =IF(INDEX(Aspetos_Impactes!$E$5:$E$47,29)="Uso (Consumidor Final)","X","") | H35: =IF(INDEX(Aspetos_Impactes!$E$5:$E$47,29)="Fim de Vida","X","") | I35: =INDEX(Aspetos_Impactes!$G$5:$G$47,29) -> Resíduos indiferenciados (20 03 01) enviados para aterro | J35: =INDEX(Aspetos_Impactes!$H$5:$H$47,29) -> Direto | K35: =INDEX(Aspetos_Impactes!$I$5:$I$47,29) -> Normal | L35: =INDEX(Aspetos_Impactes!$J$5:$J$47,29) -> Presente | M35: =IF(COUNTIFS(tbl_aspeto_impacte[ID_Aspeto],$B35,tbl_aspeto_impacte[ID_Impacte],"IMP-01")>0,"X","") | N35: =IF(COUNTIFS(tbl_aspeto_impacte[ID_Aspeto],$B35,tbl_aspeto_impacte[ID_Impacte],"IMP-02")>0,"X","") | O35: =IF(COUNTIFS(tbl_aspeto_impacte[ID_Aspeto],$B35,tbl_aspeto_impacte[ID_Impacte],"IMP-03")>0,"X","") | P35: =IF(COUNTIFS(tbl_aspeto_impacte[ID_Aspeto],$B35,tbl_aspeto_impacte[ID_Impacte],"IMP-04")>0,"X","") | Q35: =IF(COUNTIFS(tbl_aspeto_impacte[ID_Aspeto],$B35,tbl_aspeto_impacte[ID_Impacte],"IMP-05")>0,"X","") | R35: =IF(COUNTIFS(tbl_aspeto_impacte[ID_Aspeto],$B35,tbl_aspeto_impacte[ID_Impacte],"IMP-06")>0,"X","") | S35: =IF(COUNTIFS(tbl_aspeto_impacte[ID_Aspeto],$B35,tbl_aspeto_impacte[ID_Impacte],"IMP-07")>0,"X","") -> X | T35: =IF(COUNTIFS(tbl_aspeto_impacte[ID_Aspeto],$B35,tbl_aspeto_impacte[ID_Impacte],"IMP-08")>0,"X","") | U35: =IF(COUNTIFS(tbl_aspeto_impacte[ID_Aspeto],$B35,tbl_aspeto_impacte[ID_Impacte],"IMP-09")>0,"X","") | V35: =IF(COUNTIFS(tbl_aspeto_impacte[ID_Aspeto],$B35,tbl_aspeto_impacte[ID_Impacte],"IMP-10")>0,"X","") | W35: =IF(COUNTIFS(tbl_aspeto_impacte[ID_Aspeto],$B35,tbl_aspeto_impacte[ID_Impacte],"IMP-11")>0,"X","") | X35: =IF(COUNTIFS(tbl_aspeto_impacte[ID_Aspeto],$B35,tbl_aspeto_impacte[ID_Impacte],"IMP-12")>0,"X","") | Y35: =LEFT(INDEX(Aspetos_Impactes!$R$5:$R$47,29),3) -> (+) | Z35: =INDEX(Aspetos_Impactes!$N$5:$N$47,29) -> 5 | AA35: =INDEX(Aspetos_Impactes!$O$5:$O$47,29) -> 3 | AB35: =INDEX(Aspetos_Impactes!$P$5:$P$47,29) -> 2 | AC35: =INDEX(Aspetos_Impactes!$Q$5:$Q$47,29) -> 1 | AD35: =INDEX(Aspetos_Impactes!$S$5:$S$47,29) -> 16 | AE35: =INDEX(Aspetos_Impactes!$T$5:$T$47,29) -> Não Significativo | AF35: =INDEX(Aspetos_Impactes!$W$5:$W$47,29) -> NÃO | AG35: =INDEX(Aspetos_Impactes!$X$5:$X$47,29) -> Reduzir contaminação dos fluxos recicláveis.
A36: =INDEX(Aspetos_Impactes!$C$5:$C$47,30)&" — "&INDEX(Aspetos_Impactes!$D$5:$D$47,30) -> Geral — Iluminação, AVAC, escritórios | B36: =INDEX(Aspetos_Impactes!$A$5:$A$47,30) -> AA-030 | C36: =IF(INDEX(Aspetos_Impactes!$E$5:$E$47,30)="Aquisição","X","") | D36: =IF(INDEX(Aspetos_Impactes!$E$5:$E$47,30)="Design e Conceção","X","") | E36: =IF(INDEX(Aspetos_Impactes!$E$5:$E$47,30)="Produção","X","") -> X | F36: =IF(INDEX(Aspetos_Impactes!$E$5:$E$47,30)="Distribuição","X","") | G36: =IF(INDEX(Aspetos_Impactes!$E$5:$E$47,30)="Uso (Consumidor Final)","X","") | H36: =IF(INDEX(Aspetos_Impactes!$E$5:$E$47,30)="Fim de Vida","X","") | I36: =INDEX(Aspetos_Impactes!$G$5:$G$47,30) -> Consumo de energia elétrica geral (iluminação, AVAC, armazéns) | J36: =INDEX(Aspetos_Impactes!$H$5:$H$47,30) -> Direto | K36: =INDEX(Aspetos_Impactes!$I$5:$I$47,30) -> Normal | L36: =INDEX(Aspetos_Impactes!$J$5:$J$47,30) -> Presente | M36: =IF(COUNTIFS(tbl_aspeto_impacte[ID_Aspeto],$B36,tbl_aspeto_impacte[ID_Impacte],"IMP-01")>0,"X","") -> X | N36: =IF(COUNTIFS(tbl_aspeto_impacte[ID_Aspeto],$B36,tbl_aspeto_impacte[ID_Impacte],"IMP-02")>0,"X","") | O36: =IF(COUNTIFS(tbl_aspeto_impacte[ID_Aspeto],$B36,tbl_aspeto_impacte[ID_Impacte],"IMP-03")>0,"X","") | P36: =IF(COUNTIFS(tbl_aspeto_impacte[ID_Aspeto],$B36,tbl_aspeto_impacte[ID_Impacte],"IMP-04")>0,"X","") -> X | Q36: =IF(COUNTIFS(tbl_aspeto_impacte[ID_Aspeto],$B36,tbl_aspeto_impacte[ID_Impacte],"IMP-05")>0,"X","") | R36: =IF(COUNTIFS(tbl_aspeto_impacte[ID_Aspeto],$B36,tbl_aspeto_impacte[ID_Impacte],"IMP-06")>0,"X","") | S36: =IF(COUNTIFS(tbl_aspeto_impacte[ID_Aspeto],$B36,tbl_aspeto_impacte[ID_Impacte],"IMP-07")>0,"X","") | T36: =IF(COUNTIFS(tbl_aspeto_impacte[ID_Aspeto],$B36,tbl_aspeto_impacte[ID_Impacte],"IMP-08")>0,"X","") | U36: =IF(COUNTIFS(tbl_aspeto_impacte[ID_Aspeto],$B36,tbl_aspeto_impacte[ID_Impacte],"IMP-09")>0,"X","") | V36: =IF(COUNTIFS(tbl_aspeto_impacte[ID_Aspeto],$B36,tbl_aspeto_impacte[ID_Impacte],"IMP-10")>0,"X","") | W36: =IF(COUNTIFS(tbl_aspeto_impacte[ID_Aspeto],$B36,tbl_aspeto_impacte[ID_Impacte],"IMP-11")>0,"X","") | X36: =IF(COUNTIFS(tbl_aspeto_impacte[ID_Aspeto],$B36,tbl_aspeto_impacte[ID_Impacte],"IMP-12")>0,"X","") | Y36: =LEFT(INDEX(Aspetos_Impactes!$R$5:$R$47,30),3) -> (+) | Z36: =INDEX(Aspetos_Impactes!$N$5:$N$47,30) -> 5 | AA36: =INDEX(Aspetos_Impactes!$O$5:$O$47,30) -> 3 | AB36: =INDEX(Aspetos_Impactes!$P$5:$P$47,30) -> 3 | AC36: =INDEX(Aspetos_Impactes!$Q$5:$Q$47,30) -> 1 | AD36: =INDEX(Aspetos_Impactes!$S$5:$S$47,30) -> 24 | AE36: =INDEX(Aspetos_Impactes!$T$5:$T$47,30) -> Moderado | AF36: =INDEX(Aspetos_Impactes!$W$5:$W$47,30) -> SIM | AG36: =INDEX(Aspetos_Impactes!$X$5:$X$47,30) -> LED com sensores; horários de AVAC.
A37: =INDEX(Aspetos_Impactes!$C$5:$C$47,31)&" — "&INDEX(Aspetos_Impactes!$D$5:$D$47,31) -> Geral — Contrato de eletricidade | B37: =INDEX(Aspetos_Impactes!$A$5:$A$47,31) -> AA-031 | C37: =IF(INDEX(Aspetos_Impactes!$E$5:$E$47,31)="Aquisição","X","") | D37: =IF(INDEX(Aspetos_Impactes!$E$5:$E$47,31)="Design e Conceção","X","") | E37: =IF(INDEX(Aspetos_Impactes!$E$5:$E$47,31)="Produção","X","") -> X | F37: =IF(INDEX(Aspetos_Impactes!$E$5:$E$47,31)="Distribuição","X","") | G37: =IF(INDEX(Aspetos_Impactes!$E$5:$E$47,31)="Uso (Consumidor Final)","X","") | H37: =IF(INDEX(Aspetos_Impactes!$E$5:$E$47,31)="Fim de Vida","X","") | I37: =INDEX(Aspetos_Impactes!$G$5:$G$47,31) -> Consumo de eletricidade com garantia de origem renovável (55% do mix) | J37: =INDEX(Aspetos_Impactes!$H$5:$H$47,31) -> Direto | K37: =INDEX(Aspetos_Impactes!$I$5:$I$47,31) -> Normal | L37: =INDEX(Aspetos_Impactes!$J$5:$J$47,31) -> Presente | M37: =IF(COUNTIFS(tbl_aspeto_impacte[ID_Aspeto],$B37,tbl_aspeto_impacte[ID_Impacte],"IMP-01")>0,"X","") | N37: =IF(COUNTIFS(tbl_aspeto_impacte[ID_Aspeto],$B37,tbl_aspeto_impacte[ID_Impacte],"IMP-02")>0,"X","") | O37: =IF(COUNTIFS(tbl_aspeto_impacte[ID_Aspeto],$B37,tbl_aspeto_impacte[ID_Impacte],"IMP-03")>0,"X","") | P37: =IF(COUNTIFS(tbl_aspeto_impacte[ID_Aspeto],$B37,tbl_aspeto_impacte[ID_Impacte],"IMP-04")>0,"X","") -> X | Q37: =IF(COUNTIFS(tbl_aspeto_impacte[ID_Aspeto],$B37,tbl_aspeto_impacte[ID_Impacte],"IMP-05")>0,"X","") | R37: =IF(COUNTIFS(tbl_aspeto_impacte[ID_Aspeto],$B37,tbl_aspeto_impacte[ID_Impacte],"IMP-06")>0,"X","") | S37: =IF(COUNTIFS(tbl_aspeto_impacte[ID_Aspeto],$B37,tbl_aspeto_impacte[ID_Impacte],"IMP-07")>0,"X","") | T37: =IF(COUNTIFS(tbl_aspeto_impacte[ID_Aspeto],$B37,tbl_aspeto_impacte[ID_Impacte],"IMP-08")>0,"X","") | U37: =IF(COUNTIFS(tbl_aspeto_impacte[ID_Aspeto],$B37,tbl_aspeto_impacte[ID_Impacte],"IMP-09")>0,"X","") | V37: =IF(COUNTIFS(tbl_aspeto_impacte[ID_Aspeto],$B37,tbl_aspeto_impacte[ID_Impacte],"IMP-10")>0,"X","") | W37: =IF(COUNTIFS(tbl_aspeto_impacte[ID_Aspeto],$B37,tbl_aspeto_impacte[ID_Impacte],"IMP-11")>0,"X","") | X37: =IF(COUNTIFS(tbl_aspeto_impacte[ID_Aspeto],$B37,tbl_aspeto_impacte[ID_Impacte],"IMP-12")>0,"X","") -> X | Y37: =LEFT(INDEX(Aspetos_Impactes!$R$5:$R$47,31),3) -> (-) | Z37: =INDEX(Aspetos_Impactes!$N$5:$N$47,31) -> 5 | AA37: =INDEX(Aspetos_Impactes!$O$5:$O$47,31) -> 5 | AB37: =INDEX(Aspetos_Impactes!$P$5:$P$47,31) -> -1 | AC37: =INDEX(Aspetos_Impactes!$Q$5:$Q$47,31) -> 1 | AD37: =INDEX(Aspetos_Impactes!$S$5:$S$47,31) -> -10 | AE37: =INDEX(Aspetos_Impactes!$T$5:$T$47,31) -> Oportunidade Tática | AF37: =INDEX(Aspetos_Impactes!$W$5:$W$47,31) -> NÃO | AG37: =INDEX(Aspetos_Impactes!$X$5:$X$47,31) -> Aumentar a quota renovável no próximo contrato.
A38: =INDEX(Aspetos_Impactes!$C$5:$C$47,32)&" — "&INDEX(Aspetos_Impactes!$D$5:$D$47,32) -> Geral — Autoconsumo fotovoltaico previsto (UPAC ≈ 1 MWp) | B38: =INDEX(Aspetos_Impactes!$A$5:$A$47,32) -> AA-032 | C38: =IF(INDEX(Aspetos_Impactes!$E$5:$E$47,32)="Aquisição","X","") | D38: =IF(INDEX(Aspetos_Impactes!$E$5:$E$47,32)="Design e Conceção","X","") | E38: =IF(INDEX(Aspetos_Impactes!$E$5:$E$47,32)="Produção","X","") -> X | F38: =IF(INDEX(Aspetos_Impactes!$E$5:$E$47,32)="Distribuição","X","") | G38: =IF(INDEX(Aspetos_Impactes!$E$5:$E$47,32)="Uso (Consumidor Final)","X","") | H38: =IF(INDEX(Aspetos_Impactes!$E$5:$E$47,32)="Fim de Vida","X","") | I38: =INDEX(Aspetos_Impactes!$G$5:$G$47,32) -> Produção de energia renovável para autoconsumo | J38: =INDEX(Aspetos_Impactes!$H$5:$H$47,32) -> Direto | K38: =INDEX(Aspetos_Impactes!$I$5:$I$47,32) -> Normal | L38: =INDEX(Aspetos_Impactes!$J$5:$J$47,32) -> Futuro | M38: =IF(COUNTIFS(tbl_aspeto_impacte[ID_Aspeto],$B38,tbl_aspeto_impacte[ID_Impacte],"IMP-01")>0,"X","") | N38: =IF(COUNTIFS(tbl_aspeto_impacte[ID_Aspeto],$B38,tbl_aspeto_impacte[ID_Impacte],"IMP-02")>0,"X","") | O38: =IF(COUNTIFS(tbl_aspeto_impacte[ID_Aspeto],$B38,tbl_aspeto_impacte[ID_Impacte],"IMP-03")>0,"X","") | P38: =IF(COUNTIFS(tbl_aspeto_impacte[ID_Aspeto],$B38,tbl_aspeto_impacte[ID_Impacte],"IMP-04")>0,"X","") -> X | Q38: =IF(COUNTIFS(tbl_aspeto_impacte[ID_Aspeto],$B38,tbl_aspeto_impacte[ID_Impacte],"IMP-05")>0,"X","") | R38: =IF(COUNTIFS(tbl_aspeto_impacte[ID_Aspeto],$B38,tbl_aspeto_impacte[ID_Impacte],"IMP-06")>0,"X","") | S38: =IF(COUNTIFS(tbl_aspeto_impacte[ID_Aspeto],$B38,tbl_aspeto_impacte[ID_Impacte],"IMP-07")>0,"X","") | T38: =IF(COUNTIFS(tbl_aspeto_impacte[ID_Aspeto],$B38,tbl_aspeto_impacte[ID_Impacte],"IMP-08")>0,"X","") | U38: =IF(COUNTIFS(tbl_aspeto_impacte[ID_Aspeto],$B38,tbl_aspeto_impacte[ID_Impacte],"IMP-09")>0,"X","") | V38: =IF(COUNTIFS(tbl_aspeto_impacte[ID_Aspeto],$B38,tbl_aspeto_impacte[ID_Impacte],"IMP-10")>0,"X","") | W38: =IF(COUNTIFS(tbl_aspeto_impacte[ID_Aspeto],$B38,tbl_aspeto_impacte[ID_Impacte],"IMP-11")>0,"X","") | X38: =IF(COUNTIFS(tbl_aspeto_impacte[ID_Aspeto],$B38,tbl_aspeto_impacte[ID_Impacte],"IMP-12")>0,"X","") -> X | Y38: =LEFT(INDEX(Aspetos_Impactes!$R$5:$R$47,32),3) -> (-) | Z38: =INDEX(Aspetos_Impactes!$N$5:$N$47,32) -> 5 | AA38: =INDEX(Aspetos_Impactes!$O$5:$O$47,32) -> 4 | AB38: =INDEX(Aspetos_Impactes!$P$5:$P$47,32) -> -2 | AC38: =INDEX(Aspetos_Impactes!$Q$5:$Q$47,32) -> 1 | AD38: =INDEX(Aspetos_Impactes!$S$5:$S$47,32) -> -18 | AE38: =INDEX(Aspetos_Impactes!$T$5:$T$47,32) -> ASPETO AMBIENTAL SIGNIFICATIVO (AAS) BENÉFICO | AF38: =INDEX(Aspetos_Impactes!$W$5:$W$47,32) -> NÃO | AG38: =INDEX(Aspetos_Impactes!$X$5:$X$47,32) -> Estudo de viabilidade e candidatura.
A39: =INDEX(Aspetos_Impactes!$C$5:$C$47,33)&" — "&INDEX(Aspetos_Impactes!$D$5:$D$47,33) -> Geral — Ocupação do terreno industrial | B39: =INDEX(Aspetos_Impactes!$A$5:$A$47,33) -> AA-033 | C39: =IF(INDEX(Aspetos_Impactes!$E$5:$E$47,33)="Aquisição","X","") | D39: =IF(INDEX(Aspetos_Impactes!$E$5:$E$47,33)="Design e Conceção","X","") | E39: =IF(INDEX(Aspetos_Impactes!$E$5:$E$47,33)="Produção","X","") -> X | F39: =IF(INDEX(Aspetos_Impactes!$E$5:$E$47,33)="Distribuição","X","") | G39: =IF(INDEX(Aspetos_Impactes!$E$5:$E$47,33)="Uso (Consumidor Final)","X","") | H39: =IF(INDEX(Aspetos_Impactes!$E$5:$E$47,33)="Fim de Vida","X","") | I39: =INDEX(Aspetos_Impactes!$G$5:$G$47,33) -> Impermeabilização do solo (≈ 32.000 m² construídos e pavimentados) e escoamento pluvial | J39: =INDEX(Aspetos_Impactes!$H$5:$H$47,33) -> Direto | K39: =INDEX(Aspetos_Impactes!$I$5:$I$47,33) -> Normal | L39: =INDEX(Aspetos_Impactes!$J$5:$J$47,33) -> Passado | M39: =IF(COUNTIFS(tbl_aspeto_impacte[ID_Aspeto],$B39,tbl_aspeto_impacte[ID_Impacte],"IMP-01")>0,"X","") | N39: =IF(COUNTIFS(tbl_aspeto_impacte[ID_Aspeto],$B39,tbl_aspeto_impacte[ID_Impacte],"IMP-02")>0,"X","") -> X | O39: =IF(COUNTIFS(tbl_aspeto_impacte[ID_Aspeto],$B39,tbl_aspeto_impacte[ID_Impacte],"IMP-03")>0,"X","") | P39: =IF(COUNTIFS(tbl_aspeto_impacte[ID_Aspeto],$B39,tbl_aspeto_impacte[ID_Impacte],"IMP-04")>0,"X","") | Q39: =IF(COUNTIFS(tbl_aspeto_impacte[ID_Aspeto],$B39,tbl_aspeto_impacte[ID_Impacte],"IMP-05")>0,"X","") | R39: =IF(COUNTIFS(tbl_aspeto_impacte[ID_Aspeto],$B39,tbl_aspeto_impacte[ID_Impacte],"IMP-06")>0,"X","") -> X | S39: =IF(COUNTIFS(tbl_aspeto_impacte[ID_Aspeto],$B39,tbl_aspeto_impacte[ID_Impacte],"IMP-07")>0,"X","") | T39: =IF(COUNTIFS(tbl_aspeto_impacte[ID_Aspeto],$B39,tbl_aspeto_impacte[ID_Impacte],"IMP-08")>0,"X","") | U39: =IF(COUNTIFS(tbl_aspeto_impacte[ID_Aspeto],$B39,tbl_aspeto_impacte[ID_Impacte],"IMP-09")>0,"X","") | V39: =IF(COUNTIFS(tbl_aspeto_impacte[ID_Aspeto],$B39,tbl_aspeto_impacte[ID_Impacte],"IMP-10")>0,"X","") | W39: =IF(COUNTIFS(tbl_aspeto_impacte[ID_Aspeto],$B39,tbl_aspeto_impacte[ID_Impacte],"IMP-11")>0,"X","") | X39: =IF(COUNTIFS(tbl_aspeto_impacte[ID_Aspeto],$B39,tbl_aspeto_impacte[ID_Impacte],"IMP-12")>0,"X","") | Y39: =LEFT(INDEX(Aspetos_Impactes!$R$5:$R$47,33),3) -> (+) | Z39: =INDEX(Aspetos_Impactes!$N$5:$N$47,33) -> 5 | AA39: =INDEX(Aspetos_Impactes!$O$5:$O$47,33) -> 3 | AB39: =INDEX(Aspetos_Impactes!$P$5:$P$47,33) -> 2 | AC39: =INDEX(Aspetos_Impactes!$Q$5:$Q$47,33) -> 1 | AD39: =INDEX(Aspetos_Impactes!$S$5:$S$47,33) -> 16 | AE39: =INDEX(Aspetos_Impactes!$T$5:$T$47,33) -> Não Significativo | AF39: =INDEX(Aspetos_Impactes!$W$5:$W$47,33) -> NÃO | AG39: =INDEX(Aspetos_Impactes!$X$5:$X$47,33) -> Áreas verdes com espécies nativas; pavimento permeável em ampliações.
A40: =INDEX(Aspetos_Impactes!$C$5:$C$47,34)&" — "&INDEX(Aspetos_Impactes!$D$5:$D$47,34) -> Geral — Incêndio na instalação | B40: =INDEX(Aspetos_Impactes!$A$5:$A$47,34) -> AA-034 | C40: =IF(INDEX(Aspetos_Impactes!$E$5:$E$47,34)="Aquisição","X","") | D40: =IF(INDEX(Aspetos_Impactes!$E$5:$E$47,34)="Design e Conceção","X","") | E40: =IF(INDEX(Aspetos_Impactes!$E$5:$E$47,34)="Produção","X","") -> X | F40: =IF(INDEX(Aspetos_Impactes!$E$5:$E$47,34)="Distribuição","X","") | G40: =IF(INDEX(Aspetos_Impactes!$E$5:$E$47,34)="Uso (Consumidor Final)","X","") | H40: =IF(INDEX(Aspetos_Impactes!$E$5:$E$47,34)="Fim de Vida","X","") | I40: =INDEX(Aspetos_Impactes!$G$5:$G$47,34) -> Fumos de combustão de plástico e águas de combate contaminadas (incêndio) | J40: =INDEX(Aspetos_Impactes!$H$5:$H$47,34) -> Direto | K40: =INDEX(Aspetos_Impactes!$I$5:$I$47,34) -> Emergência | L40: =INDEX(Aspetos_Impactes!$J$5:$J$47,34) -> Futuro | M40: =IF(COUNTIFS(tbl_aspeto_impacte[ID_Aspeto],$B40,tbl_aspeto_impacte[ID_Impacte],"IMP-01")>0,"X","") | N40: =IF(COUNTIFS(tbl_aspeto_impacte[ID_Aspeto],$B40,tbl_aspeto_impacte[ID_Impacte],"IMP-02")>0,"X","") -> X | O40: =IF(COUNTIFS(tbl_aspeto_impacte[ID_Aspeto],$B40,tbl_aspeto_impacte[ID_Impacte],"IMP-03")>0,"X","") -> X | P40: =IF(COUNTIFS(tbl_aspeto_impacte[ID_Aspeto],$B40,tbl_aspeto_impacte[ID_Impacte],"IMP-04")>0,"X","") | Q40: =IF(COUNTIFS(tbl_aspeto_impacte[ID_Aspeto],$B40,tbl_aspeto_impacte[ID_Impacte],"IMP-05")>0,"X","") | R40: =IF(COUNTIFS(tbl_aspeto_impacte[ID_Aspeto],$B40,tbl_aspeto_impacte[ID_Impacte],"IMP-06")>0,"X","") -> X | S40: =IF(COUNTIFS(tbl_aspeto_impacte[ID_Aspeto],$B40,tbl_aspeto_impacte[ID_Impacte],"IMP-07")>0,"X","") | T40: =IF(COUNTIFS(tbl_aspeto_impacte[ID_Aspeto],$B40,tbl_aspeto_impacte[ID_Impacte],"IMP-08")>0,"X","") | U40: =IF(COUNTIFS(tbl_aspeto_impacte[ID_Aspeto],$B40,tbl_aspeto_impacte[ID_Impacte],"IMP-09")>0,"X","") | V40: =IF(COUNTIFS(tbl_aspeto_impacte[ID_Aspeto],$B40,tbl_aspeto_impacte[ID_Impacte],"IMP-10")>0,"X","") | W40: =IF(COUNTIFS(tbl_aspeto_impacte[ID_Aspeto],$B40,tbl_aspeto_impacte[ID_Impacte],"IMP-11")>0,"X","") | X40: =IF(COUNTIFS(tbl_aspeto_impacte[ID_Aspeto],$B40,tbl_aspeto_impacte[ID_Impacte],"IMP-12")>0,"X","") | Y40: =LEFT(INDEX(Aspetos_Impactes!$R$5:$R$47,34),3) -> (+) | Z40: =INDEX(Aspetos_Impactes!$N$5:$N$47,34) -> 1 | AA40: =INDEX(Aspetos_Impactes!$O$5:$O$47,34) -> 5 | AB40: =INDEX(Aspetos_Impactes!$P$5:$P$47,34) -> 5 | AC40: =INDEX(Aspetos_Impactes!$Q$5:$Q$47,34) -> 1 | AD40: =INDEX(Aspetos_Impactes!$S$5:$S$47,34) -> 30 | AE40: =INDEX(Aspetos_Impactes!$T$5:$T$47,34) -> Moderado | AF40: =INDEX(Aspetos_Impactes!$W$5:$W$47,34) -> SIM | AG40: =INDEX(Aspetos_Impactes!$X$5:$X$47,34) -> Deteção, válvula de corte pluvial, simulacro anual, faixa de gestão de combustível.
A41: =INDEX(Aspetos_Impactes!$C$5:$C$47,35)&" — "&INDEX(Aspetos_Impactes!$D$5:$D$47,35) -> Geral — Uso de instalações sanitárias | B41: =INDEX(Aspetos_Impactes!$A$5:$A$47,35) -> AA-035 | C41: =IF(INDEX(Aspetos_Impactes!$E$5:$E$47,35)="Aquisição","X","") | D41: =IF(INDEX(Aspetos_Impactes!$E$5:$E$47,35)="Design e Conceção","X","") | E41: =IF(INDEX(Aspetos_Impactes!$E$5:$E$47,35)="Produção","X","") -> X | F41: =IF(INDEX(Aspetos_Impactes!$E$5:$E$47,35)="Distribuição","X","") | G41: =IF(INDEX(Aspetos_Impactes!$E$5:$E$47,35)="Uso (Consumidor Final)","X","") | H41: =IF(INDEX(Aspetos_Impactes!$E$5:$E$47,35)="Fim de Vida","X","") | I41: =INDEX(Aspetos_Impactes!$G$5:$G$47,35) -> Águas residuais domésticas descarregadas no coletor municipal | J41: =INDEX(Aspetos_Impactes!$H$5:$H$47,35) -> Direto | K41: =INDEX(Aspetos_Impactes!$I$5:$I$47,35) -> Normal | L41: =INDEX(Aspetos_Impactes!$J$5:$J$47,35) -> Presente | M41: =IF(COUNTIFS(tbl_aspeto_impacte[ID_Aspeto],$B41,tbl_aspeto_impacte[ID_Impacte],"IMP-01")>0,"X","") | N41: =IF(COUNTIFS(tbl_aspeto_impacte[ID_Aspeto],$B41,tbl_aspeto_impacte[ID_Impacte],"IMP-02")>0,"X","") -> X | O41: =IF(COUNTIFS(tbl_aspeto_impacte[ID_Aspeto],$B41,tbl_aspeto_impacte[ID_Impacte],"IMP-03")>0,"X","") | P41: =IF(COUNTIFS(tbl_aspeto_impacte[ID_Aspeto],$B41,tbl_aspeto_impacte[ID_Impacte],"IMP-04")>0,"X","") | Q41: =IF(COUNTIFS(tbl_aspeto_impacte[ID_Aspeto],$B41,tbl_aspeto_impacte[ID_Impacte],"IMP-05")>0,"X","") | R41: =IF(COUNTIFS(tbl_aspeto_impacte[ID_Aspeto],$B41,tbl_aspeto_impacte[ID_Impacte],"IMP-06")>0,"X","") | S41: =IF(COUNTIFS(tbl_aspeto_impacte[ID_Aspeto],$B41,tbl_aspeto_impacte[ID_Impacte],"IMP-07")>0,"X","") | T41: =IF(COUNTIFS(tbl_aspeto_impacte[ID_Aspeto],$B41,tbl_aspeto_impacte[ID_Impacte],"IMP-08")>0,"X","") | U41: =IF(COUNTIFS(tbl_aspeto_impacte[ID_Aspeto],$B41,tbl_aspeto_impacte[ID_Impacte],"IMP-09")>0,"X","") | V41: =IF(COUNTIFS(tbl_aspeto_impacte[ID_Aspeto],$B41,tbl_aspeto_impacte[ID_Impacte],"IMP-10")>0,"X","") | W41: =IF(COUNTIFS(tbl_aspeto_impacte[ID_Aspeto],$B41,tbl_aspeto_impacte[ID_Impacte],"IMP-11")>0,"X","") | X41: =IF(COUNTIFS(tbl_aspeto_impacte[ID_Aspeto],$B41,tbl_aspeto_impacte[ID_Impacte],"IMP-12")>0,"X","") | Y41: =LEFT(INDEX(Aspetos_Impactes!$R$5:$R$47,35),3) -> (+) | Z41: =INDEX(Aspetos_Impactes!$N$5:$N$47,35) -> 5 | AA41: =INDEX(Aspetos_Impactes!$O$5:$O$47,35) -> 2 | AB41: =INDEX(Aspetos_Impactes!$P$5:$P$47,35) -> 2 | AC41: =INDEX(Aspetos_Impactes!$Q$5:$Q$47,35) -> 1 | AD41: =INDEX(Aspetos_Impactes!$S$5:$S$47,35) -> 14 | AE41: =INDEX(Aspetos_Impactes!$T$5:$T$47,35) -> Não Significativo | AF41: =INDEX(Aspetos_Impactes!$W$5:$W$47,35) -> NÃO | AG41: =INDEX(Aspetos_Impactes!$X$5:$X$47,35) -> —
A42: =INDEX(Aspetos_Impactes!$C$5:$C$47,36)&" — "&INDEX(Aspetos_Impactes!$D$5:$D$47,36) -> Administrativos — Trabalho de escritório | B42: =INDEX(Aspetos_Impactes!$A$5:$A$47,36) -> AA-036 | C42: =IF(INDEX(Aspetos_Impactes!$E$5:$E$47,36)="Aquisição","X","") | D42: =IF(INDEX(Aspetos_Impactes!$E$5:$E$47,36)="Design e Conceção","X","") | E42: =IF(INDEX(Aspetos_Impactes!$E$5:$E$47,36)="Produção","X","") -> X | F42: =IF(INDEX(Aspetos_Impactes!$E$5:$E$47,36)="Distribuição","X","") | G42: =IF(INDEX(Aspetos_Impactes!$E$5:$E$47,36)="Uso (Consumidor Final)","X","") | H42: =IF(INDEX(Aspetos_Impactes!$E$5:$E$47,36)="Fim de Vida","X","") | I42: =INDEX(Aspetos_Impactes!$G$5:$G$47,36) -> Consumo de papel e toners | J42: =INDEX(Aspetos_Impactes!$H$5:$H$47,36) -> Direto | K42: =INDEX(Aspetos_Impactes!$I$5:$I$47,36) -> Normal | L42: =INDEX(Aspetos_Impactes!$J$5:$J$47,36) -> Presente | M42: =IF(COUNTIFS(tbl_aspeto_impacte[ID_Aspeto],$B42,tbl_aspeto_impacte[ID_Impacte],"IMP-01")>0,"X","") -> X | N42: =IF(COUNTIFS(tbl_aspeto_impacte[ID_Aspeto],$B42,tbl_aspeto_impacte[ID_Impacte],"IMP-02")>0,"X","") | O42: =IF(COUNTIFS(tbl_aspeto_impacte[ID_Aspeto],$B42,tbl_aspeto_impacte[ID_Impacte],"IMP-03")>0,"X","") | P42: =IF(COUNTIFS(tbl_aspeto_impacte[ID_Aspeto],$B42,tbl_aspeto_impacte[ID_Impacte],"IMP-04")>0,"X","") | Q42: =IF(COUNTIFS(tbl_aspeto_impacte[ID_Aspeto],$B42,tbl_aspeto_impacte[ID_Impacte],"IMP-05")>0,"X","") | R42: =IF(COUNTIFS(tbl_aspeto_impacte[ID_Aspeto],$B42,tbl_aspeto_impacte[ID_Impacte],"IMP-06")>0,"X","") | S42: =IF(COUNTIFS(tbl_aspeto_impacte[ID_Aspeto],$B42,tbl_aspeto_impacte[ID_Impacte],"IMP-07")>0,"X","") -> X | T42: =IF(COUNTIFS(tbl_aspeto_impacte[ID_Aspeto],$B42,tbl_aspeto_impacte[ID_Impacte],"IMP-08")>0,"X","") | U42: =IF(COUNTIFS(tbl_aspeto_impacte[ID_Aspeto],$B42,tbl_aspeto_impacte[ID_Impacte],"IMP-09")>0,"X","") | V42: =IF(COUNTIFS(tbl_aspeto_impacte[ID_Aspeto],$B42,tbl_aspeto_impacte[ID_Impacte],"IMP-10")>0,"X","") | W42: =IF(COUNTIFS(tbl_aspeto_impacte[ID_Aspeto],$B42,tbl_aspeto_impacte[ID_Impacte],"IMP-11")>0,"X","") | X42: =IF(COUNTIFS(tbl_aspeto_impacte[ID_Aspeto],$B42,tbl_aspeto_impacte[ID_Impacte],"IMP-12")>0,"X","") | Y42: =LEFT(INDEX(Aspetos_Impactes!$R$5:$R$47,36),3) -> (+) | Z42: =INDEX(Aspetos_Impactes!$N$5:$N$47,36) -> 4 | AA42: =INDEX(Aspetos_Impactes!$O$5:$O$47,36) -> 1 | AB42: =INDEX(Aspetos_Impactes!$P$5:$P$47,36) -> 1 | AC42: =INDEX(Aspetos_Impactes!$Q$5:$Q$47,36) -> 1 | AD42: =INDEX(Aspetos_Impactes!$S$5:$S$47,36) -> 5 | AE42: =INDEX(Aspetos_Impactes!$T$5:$T$47,36) -> Não Significativo | AF42: =INDEX(Aspetos_Impactes!$W$5:$W$47,36) -> NÃO | AG42: =INDEX(Aspetos_Impactes!$X$5:$X$47,36) -> Documentação digital.
A43: =INDEX(Aspetos_Impactes!$C$5:$C$47,37)&" — "&INDEX(Aspetos_Impactes!$D$5:$D$47,37) -> R&D — Conceção de novas embalagens | B43: =INDEX(Aspetos_Impactes!$A$5:$A$47,37) -> AA-037 | C43: =IF(INDEX(Aspetos_Impactes!$E$5:$E$47,37)="Aquisição","X","") | D43: =IF(INDEX(Aspetos_Impactes!$E$5:$E$47,37)="Design e Conceção","X","") -> X | E43: =IF(INDEX(Aspetos_Impactes!$E$5:$E$47,37)="Produção","X","") | F43: =IF(INDEX(Aspetos_Impactes!$E$5:$E$47,37)="Distribuição","X","") | G43: =IF(INDEX(Aspetos_Impactes!$E$5:$E$47,37)="Uso (Consumidor Final)","X","") | H43: =IF(INDEX(Aspetos_Impactes!$E$5:$E$47,37)="Fim de Vida","X","") | I43: =INDEX(Aspetos_Impactes!$G$5:$G$47,37) -> Escolha de material, peso e combinação de componentes das embalagens (define impactes a montante e no fim de vida) | J43: =INDEX(Aspetos_Impactes!$H$5:$H$47,37) -> Direto | K43: =INDEX(Aspetos_Impactes!$I$5:$I$47,37) -> Normal | L43: =INDEX(Aspetos_Impactes!$J$5:$J$47,37) -> Presente | M43: =IF(COUNTIFS(tbl_aspeto_impacte[ID_Aspeto],$B43,tbl_aspeto_impacte[ID_Impacte],"IMP-01")>0,"X","") -> X | N43: =IF(COUNTIFS(tbl_aspeto_impacte[ID_Aspeto],$B43,tbl_aspeto_impacte[ID_Impacte],"IMP-02")>0,"X","") | O43: =IF(COUNTIFS(tbl_aspeto_impacte[ID_Aspeto],$B43,tbl_aspeto_impacte[ID_Impacte],"IMP-03")>0,"X","") | P43: =IF(COUNTIFS(tbl_aspeto_impacte[ID_Aspeto],$B43,tbl_aspeto_impacte[ID_Impacte],"IMP-04")>0,"X","") | Q43: =IF(COUNTIFS(tbl_aspeto_impacte[ID_Aspeto],$B43,tbl_aspeto_impacte[ID_Impacte],"IMP-05")>0,"X","") | R43: =IF(COUNTIFS(tbl_aspeto_impacte[ID_Aspeto],$B43,tbl_aspeto_impacte[ID_Impacte],"IMP-06")>0,"X","") | S43: =IF(COUNTIFS(tbl_aspeto_impacte[ID_Aspeto],$B43,tbl_aspeto_impacte[ID_Impacte],"IMP-07")>0,"X","") -> X | T43: =IF(COUNTIFS(tbl_aspeto_impacte[ID_Aspeto],$B43,tbl_aspeto_impacte[ID_Impacte],"IMP-08")>0,"X","") | U43: =IF(COUNTIFS(tbl_aspeto_impacte[ID_Aspeto],$B43,tbl_aspeto_impacte[ID_Impacte],"IMP-09")>0,"X","") | V43: =IF(COUNTIFS(tbl_aspeto_impacte[ID_Aspeto],$B43,tbl_aspeto_impacte[ID_Impacte],"IMP-10")>0,"X","") | W43: =IF(COUNTIFS(tbl_aspeto_impacte[ID_Aspeto],$B43,tbl_aspeto_impacte[ID_Impacte],"IMP-11")>0,"X","") | X43: =IF(COUNTIFS(tbl_aspeto_impacte[ID_Aspeto],$B43,tbl_aspeto_impacte[ID_Impacte],"IMP-12")>0,"X","") | Y43: =LEFT(INDEX(Aspetos_Impactes!$R$5:$R$47,37),3) -> (+) | Z43: =INDEX(Aspetos_Impactes!$N$5:$N$47,37) -> 4 | AA43: =INDEX(Aspetos_Impactes!$O$5:$O$47,37) -> 5 | AB43: =INDEX(Aspetos_Impactes!$P$5:$P$47,37) -> 3 | AC43: =INDEX(Aspetos_Impactes!$Q$5:$Q$47,37) -> 1 | AD43: =INDEX(Aspetos_Impactes!$S$5:$S$47,37) -> 27 | AE43: =INDEX(Aspetos_Impactes!$T$5:$T$47,37) -> Moderado | AF43: =INDEX(Aspetos_Impactes!$W$5:$W$47,37) -> SIM | AG43: =INDEX(Aspetos_Impactes!$X$5:$X$47,37) -> Checklist Design for Recycling; monomaterial; redução de peso.
A44: =INDEX(Aspetos_Impactes!$C$5:$C$47,38)&" — "&INDEX(Aspetos_Impactes!$D$5:$D$47,38) -> R&D — Colocação de embalagens no mercado UE | B44: =INDEX(Aspetos_Impactes!$A$5:$A$47,38) -> AA-038 | C44: =IF(INDEX(Aspetos_Impactes!$E$5:$E$47,38)="Aquisição","X","") | D44: =IF(INDEX(Aspetos_Impactes!$E$5:$E$47,38)="Design e Conceção","X","") -> X | E44: =IF(INDEX(Aspetos_Impactes!$E$5:$E$47,38)="Produção","X","") | F44: =IF(INDEX(Aspetos_Impactes!$E$5:$E$47,38)="Distribuição","X","") | G44: =IF(INDEX(Aspetos_Impactes!$E$5:$E$47,38)="Uso (Consumidor Final)","X","") | H44: =IF(INDEX(Aspetos_Impactes!$E$5:$E$47,38)="Fim de Vida","X","") | I44: =INDEX(Aspetos_Impactes!$G$5:$G$47,38) -> Embalagens colocadas no mercado sem documentação técnica nem declaração UE de conformidade PPWR | J44: =INDEX(Aspetos_Impactes!$H$5:$H$47,38) -> Direto | K44: =INDEX(Aspetos_Impactes!$I$5:$I$47,38) -> Normal | L44: =INDEX(Aspetos_Impactes!$J$5:$J$47,38) -> Presente | M44: =IF(COUNTIFS(tbl_aspeto_impacte[ID_Aspeto],$B44,tbl_aspeto_impacte[ID_Impacte],"IMP-01")>0,"X","") -> X | N44: =IF(COUNTIFS(tbl_aspeto_impacte[ID_Aspeto],$B44,tbl_aspeto_impacte[ID_Impacte],"IMP-02")>0,"X","") | O44: =IF(COUNTIFS(tbl_aspeto_impacte[ID_Aspeto],$B44,tbl_aspeto_impacte[ID_Impacte],"IMP-03")>0,"X","") | P44: =IF(COUNTIFS(tbl_aspeto_impacte[ID_Aspeto],$B44,tbl_aspeto_impacte[ID_Impacte],"IMP-04")>0,"X","") | Q44: =IF(COUNTIFS(tbl_aspeto_impacte[ID_Aspeto],$B44,tbl_aspeto_impacte[ID_Impacte],"IMP-05")>0,"X","") | R44: =IF(COUNTIFS(tbl_aspeto_impacte[ID_Aspeto],$B44,tbl_aspeto_impacte[ID_Impacte],"IMP-06")>0,"X","") | S44: =IF(COUNTIFS(tbl_aspeto_impacte[ID_Aspeto],$B44,tbl_aspeto_impacte[ID_Impacte],"IMP-07")>0,"X","") -> X | T44: =IF(COUNTIFS(tbl_aspeto_impacte[ID_Aspeto],$B44,tbl_aspeto_impacte[ID_Impacte],"IMP-08")>0,"X","") | U44: =IF(COUNTIFS(tbl_aspeto_impacte[ID_Aspeto],$B44,tbl_aspeto_impacte[ID_Impacte],"IMP-09")>0,"X","") | V44: =IF(COUNTIFS(tbl_aspeto_impacte[ID_Aspeto],$B44,tbl_aspeto_impacte[ID_Impacte],"IMP-10")>0,"X","") | W44: =IF(COUNTIFS(tbl_aspeto_impacte[ID_Aspeto],$B44,tbl_aspeto_impacte[ID_Impacte],"IMP-11")>0,"X","") | X44: =IF(COUNTIFS(tbl_aspeto_impacte[ID_Aspeto],$B44,tbl_aspeto_impacte[ID_Impacte],"IMP-12")>0,"X","") | Y44: =LEFT(INDEX(Aspetos_Impactes!$R$5:$R$47,38),3) -> (+) | Z44: =INDEX(Aspetos_Impactes!$N$5:$N$47,38) -> 5 | AA44: =INDEX(Aspetos_Impactes!$O$5:$O$47,38) -> 5 | AB44: =INDEX(Aspetos_Impactes!$P$5:$P$47,38) -> 3 | AC44: =INDEX(Aspetos_Impactes!$Q$5:$Q$47,38) -> 2 | AD44: =INDEX(Aspetos_Impactes!$S$5:$S$47,38) -> 60 | AE44: =INDEX(Aspetos_Impactes!$T$5:$T$47,38) -> ASPETO AMBIENTAL SIGNIFICATIVO (AAS) | AF44: =INDEX(Aspetos_Impactes!$W$5:$W$47,38) -> SIM | AG44: =INDEX(Aspetos_Impactes!$X$5:$X$47,38) -> Dossier técnico por família (OBJ-04).
A45: =INDEX(Aspetos_Impactes!$C$5:$C$47,39)&" — "&INDEX(Aspetos_Impactes!$D$5:$D$47,39) -> Expedição — Embalagem de produto acabado | B45: =INDEX(Aspetos_Impactes!$A$5:$A$47,39) -> AA-039 | C45: =IF(INDEX(Aspetos_Impactes!$E$5:$E$47,39)="Aquisição","X","") | D45: =IF(INDEX(Aspetos_Impactes!$E$5:$E$47,39)="Design e Conceção","X","") | E45: =IF(INDEX(Aspetos_Impactes!$E$5:$E$47,39)="Produção","X","") | F45: =IF(INDEX(Aspetos_Impactes!$E$5:$E$47,39)="Distribuição","X","") -> X | G45: =IF(INDEX(Aspetos_Impactes!$E$5:$E$47,39)="Uso (Consumidor Final)","X","") | H45: =IF(INDEX(Aspetos_Impactes!$E$5:$E$47,39)="Fim de Vida","X","") | I45: =INDEX(Aspetos_Impactes!$G$5:$G$47,39) -> Consumo de cartão, filme estirável e paletes | J45: =INDEX(Aspetos_Impactes!$H$5:$H$47,39) -> Direto | K45: =INDEX(Aspetos_Impactes!$I$5:$I$47,39) -> Normal | L45: =INDEX(Aspetos_Impactes!$J$5:$J$47,39) -> Presente | M45: =IF(COUNTIFS(tbl_aspeto_impacte[ID_Aspeto],$B45,tbl_aspeto_impacte[ID_Impacte],"IMP-01")>0,"X","") -> X | N45: =IF(COUNTIFS(tbl_aspeto_impacte[ID_Aspeto],$B45,tbl_aspeto_impacte[ID_Impacte],"IMP-02")>0,"X","") | O45: =IF(COUNTIFS(tbl_aspeto_impacte[ID_Aspeto],$B45,tbl_aspeto_impacte[ID_Impacte],"IMP-03")>0,"X","") | P45: =IF(COUNTIFS(tbl_aspeto_impacte[ID_Aspeto],$B45,tbl_aspeto_impacte[ID_Impacte],"IMP-04")>0,"X","") | Q45: =IF(COUNTIFS(tbl_aspeto_impacte[ID_Aspeto],$B45,tbl_aspeto_impacte[ID_Impacte],"IMP-05")>0,"X","") | R45: =IF(COUNTIFS(tbl_aspeto_impacte[ID_Aspeto],$B45,tbl_aspeto_impacte[ID_Impacte],"IMP-06")>0,"X","") | S45: =IF(COUNTIFS(tbl_aspeto_impacte[ID_Aspeto],$B45,tbl_aspeto_impacte[ID_Impacte],"IMP-07")>0,"X","") -> X | T45: =IF(COUNTIFS(tbl_aspeto_impacte[ID_Aspeto],$B45,tbl_aspeto_impacte[ID_Impacte],"IMP-08")>0,"X","") | U45: =IF(COUNTIFS(tbl_aspeto_impacte[ID_Aspeto],$B45,tbl_aspeto_impacte[ID_Impacte],"IMP-09")>0,"X","") | V45: =IF(COUNTIFS(tbl_aspeto_impacte[ID_Aspeto],$B45,tbl_aspeto_impacte[ID_Impacte],"IMP-10")>0,"X","") | W45: =IF(COUNTIFS(tbl_aspeto_impacte[ID_Aspeto],$B45,tbl_aspeto_impacte[ID_Impacte],"IMP-11")>0,"X","") | X45: =IF(COUNTIFS(tbl_aspeto_impacte[ID_Aspeto],$B45,tbl_aspeto_impacte[ID_Impacte],"IMP-12")>0,"X","") | Y45: =LEFT(INDEX(Aspetos_Impactes!$R$5:$R$47,39),3) -> (+) | Z45: =INDEX(Aspetos_Impactes!$N$5:$N$47,39) -> 5 | AA45: =INDEX(Aspetos_Impactes!$O$5:$O$47,39) -> 4 | AB45: =INDEX(Aspetos_Impactes!$P$5:$P$47,39) -> 2 | AC45: =INDEX(Aspetos_Impactes!$Q$5:$Q$47,39) -> 1 | AD45: =INDEX(Aspetos_Impactes!$S$5:$S$47,39) -> 18 | AE45: =INDEX(Aspetos_Impactes!$T$5:$T$47,39) -> Não Significativo | AF45: =INDEX(Aspetos_Impactes!$W$5:$W$47,39) -> NÃO | AG45: =INDEX(Aspetos_Impactes!$X$5:$X$47,39) -> Caixas e paletes retornáveis com clientes ibéricos.
A46: =INDEX(Aspetos_Impactes!$C$5:$C$47,40)&" — "&INDEX(Aspetos_Impactes!$D$5:$D$47,40) -> Expedição — Transporte de produto a clientes | B46: =INDEX(Aspetos_Impactes!$A$5:$A$47,40) -> AA-040 | C46: =IF(INDEX(Aspetos_Impactes!$E$5:$E$47,40)="Aquisição","X","") | D46: =IF(INDEX(Aspetos_Impactes!$E$5:$E$47,40)="Design e Conceção","X","") | E46: =IF(INDEX(Aspetos_Impactes!$E$5:$E$47,40)="Produção","X","") | F46: =IF(INDEX(Aspetos_Impactes!$E$5:$E$47,40)="Distribuição","X","") -> X | G46: =IF(INDEX(Aspetos_Impactes!$E$5:$E$47,40)="Uso (Consumidor Final)","X","") | H46: =IF(INDEX(Aspetos_Impactes!$E$5:$E$47,40)="Fim de Vida","X","") | I46: =INDEX(Aspetos_Impactes!$G$5:$G$47,40) -> Emissões do transporte rodoviário de produto acabado (Península Ibérica e UE) | J46: =INDEX(Aspetos_Impactes!$H$5:$H$47,40) -> Indireto | K46: =INDEX(Aspetos_Impactes!$I$5:$I$47,40) -> Normal | L46: =INDEX(Aspetos_Impactes!$J$5:$J$47,40) -> Presente | M46: =IF(COUNTIFS(tbl_aspeto_impacte[ID_Aspeto],$B46,tbl_aspeto_impacte[ID_Impacte],"IMP-01")>0,"X","") | N46: =IF(COUNTIFS(tbl_aspeto_impacte[ID_Aspeto],$B46,tbl_aspeto_impacte[ID_Impacte],"IMP-02")>0,"X","") | O46: =IF(COUNTIFS(tbl_aspeto_impacte[ID_Aspeto],$B46,tbl_aspeto_impacte[ID_Impacte],"IMP-03")>0,"X","") -> X | P46: =IF(COUNTIFS(tbl_aspeto_impacte[ID_Aspeto],$B46,tbl_aspeto_impacte[ID_Impacte],"IMP-04")>0,"X","") -> X | Q46: =IF(COUNTIFS(tbl_aspeto_impacte[ID_Aspeto],$B46,tbl_aspeto_impacte[ID_Impacte],"IMP-05")>0,"X","") -> X | R46: =IF(COUNTIFS(tbl_aspeto_impacte[ID_Aspeto],$B46,tbl_aspeto_impacte[ID_Impacte],"IMP-06")>0,"X","") | S46: =IF(COUNTIFS(tbl_aspeto_impacte[ID_Aspeto],$B46,tbl_aspeto_impacte[ID_Impacte],"IMP-07")>0,"X","") | T46: =IF(COUNTIFS(tbl_aspeto_impacte[ID_Aspeto],$B46,tbl_aspeto_impacte[ID_Impacte],"IMP-08")>0,"X","") | U46: =IF(COUNTIFS(tbl_aspeto_impacte[ID_Aspeto],$B46,tbl_aspeto_impacte[ID_Impacte],"IMP-09")>0,"X","") | V46: =IF(COUNTIFS(tbl_aspeto_impacte[ID_Aspeto],$B46,tbl_aspeto_impacte[ID_Impacte],"IMP-10")>0,"X","") | W46: =IF(COUNTIFS(tbl_aspeto_impacte[ID_Aspeto],$B46,tbl_aspeto_impacte[ID_Impacte],"IMP-11")>0,"X","") | X46: =IF(COUNTIFS(tbl_aspeto_impacte[ID_Aspeto],$B46,tbl_aspeto_impacte[ID_Impacte],"IMP-12")>0,"X","") | Y46: =LEFT(INDEX(Aspetos_Impactes!$R$5:$R$47,40),3) -> (+) | Z46: =INDEX(Aspetos_Impactes!$N$5:$N$47,40) -> 5 | AA46: =INDEX(Aspetos_Impactes!$O$5:$O$47,40) -> 4 | AB46: =INDEX(Aspetos_Impactes!$P$5:$P$47,40) -> 3 | AC46: =INDEX(Aspetos_Impactes!$Q$5:$Q$47,40) -> 1 | AD46: =INDEX(Aspetos_Impactes!$S$5:$S$47,40) -> 27 | AE46: =INDEX(Aspetos_Impactes!$T$5:$T$47,40) -> Moderado | AF46: =INDEX(Aspetos_Impactes!$W$5:$W$47,40) -> SIM | AG46: =INDEX(Aspetos_Impactes!$X$5:$X$47,40) -> Consolidação de cargas; critérios ambientais para transportadores.
