Workbook
Name DataRef: Listas!$A$3
Name lst_AN_Limite: Listas!$I$3:$I$5
Name lst_AN_Matriz: Listas!$H$3:$H$7
Name lst_AN_SimNao: Listas!$J$3:$J$4
Name lst_Cat6M: Listas!$E$3:$E$8
Name lst_DataReferencia: Listas!$A$3:$A$3
Name lst_EstadoHip: Listas!$D$3:$D$6
Name lst_Funcao: Listas!$C$3:$C$24
Name lst_Processo: Listas!$F$3:$F$20
Name lst_Qualidade: Listas!$G$3:$G$5
Name lst_Tipo: Listas!$B$3:$B$4

Sheet 00_LEIA-ME
A1: RG-SGA-13 — Plano de Monitorização e Medição e Avaliação do Desempenho Ambiental
A2: Sistema de Gestão Ambiental NP EN ISO 14001:2026 · Plasticom — Unidade 1 (Marinha Grande, Portugal) · Registo do SGA (fábrica simulada)
A4: CONTROLO DO DOCUMENTO (7.5 — informação documentada)
A5: Código do registo | B5: RG-SGA-13
A6: Título | B6: Plano de Monitorização e Medição e Avaliação do Desempenho Ambiental
A7: Versão / Revisão | B7: 01
A8: Data de emissão | B8: 46387
A9: Elaborado por | B9: Gestor(a) do SGA / EHS
A10: Aprovado por | B10: Diretor Geral
A11: Estado | B11: Em vigor
A12: Retenção | B12: 5 anos após substituição
A13: Localização | B13: Repositório controlado do SGA > Registos_SGA_Plasticom (versão eletrónica é a versão controlada; cópias impressas são não controladas)
A15: FINALIDADE E ÂMBITO
A16: Finalidade | B16: Base de dados ambiental mensal de mar/2025 a dez/2026 (22 meses) em formato longo, derivada da produção real da fábrica simulada e de fatores documentados; plano de monitorização com responsáveis e frequências; controlo de calibração; indicadores mensais calculados; e análise do desvio do solvente com hipóteses verificadas por dados.
A17: Atividades do curso | B17: Atividade 5.1 — Plano de Monitorização e Medição (o quê, como, quando, quem) e equipamentos a calibrar/verificar. Atividade 5.2 Parte 1 — análise do desvio de +15% no solvente de limpeza da serigrafia (18 meses de dados).
A18: Requisitos ISO 14001:2026 | B18: 9.1.1 Monitorização, medição, análise e avaliação (avaliar o desempenho ambiental E a eficácia do SGA — ISO 14001:2026); 9.1.2; 7.1 (equipamentos calibrados/verificados)
A20: ESTRUTURA DO FICHEIRO
A21: Plano_Monitorizacao | B21: Plano de monitorização e medição (o quê, como, quando, quem) — Atividade 5.1.
A22: Equipamentos_Calibracao | B22: Equipamentos de monitorização que exigem calibração/verificação (Atividade 5.1, ponto 3).
A23: Parametros | B23: Fatores usados para derivar os dados ambientais a partir da produção (transparência do modelo; alterar aqui não recalcula a base de dados).
A24: Dim_Mes | B24: Dimensão mês com temperatura, dias úteis e faturas de eletricidade e água (consumo, preço, custo, emissões do âmbito 2).
A25: Producao_Mensal | B25: Produção mensal por processo (denominadores dos indicadores).
A26: Dados_Ambientais | B26: Base de dados ambiental mensal em formato longo (1 linha = mês × processo × variável) — pronta para análise e ML.
A27: Residuos_Mensais | B27: Resíduos mensais por código LER, destino e operador (base do MIRR).
A28: Indicadores_Mensais | B28: Indicadores mensais calculados com SUMIFS sobre as tabelas de dados (KPI-01 a KPI-08, KPI-16).
A29: Analise_Desvio_5_2 | B29: Atividade 5.2 Parte 1: cenário de desvio do solvente (+15% nos últimos 3 meses com produção estável), comparações calculadas, hipóteses e ações.
A30: Hipoteses_Desvio | B30: Hipóteses (causas prováveis) do desvio do solvente e resultado da verificação com dados.
A31: Pesagem_Solvente | B31: Pesagem diária de solvente por máquina e turno (investigação PAM-26-07 desde 08/09/2026 e acompanhamento das ações até 31/12/2026).
A32: Analises_Laboratoriais | B32: Resultados de monitorização por ensaio (efluente, águas pluviais, torre/Legionella, ruído, emissões) comparados com os limites (9.1.1, 9.1.2).
... A34: Dicionario_Dados | B34: Descrição de cada coluna de cada tabela: tipo, origem (entrada/calculado), domínio, obrigatoriedade e chaves.
A36: CONVENÇÕES (prontas para análise de dados e machine learning)
A37: Tabelas | B37: Cada registo é uma Tabela Excel com nome próprio (tbl_*): uma linha = um registo, cabeçalho único, sem células mescladas. Ler com pandas (pd.read_excel(ficheiro, sheet_name=folha, header=<linha do cabeçalho - 1>)) ou Power BI (Obter Dados > Tabela).
A38: Cabeçalho cinzento | B38: Coluna CALCULADA por fórmula — não escrever por cima. As restantes colunas são de entrada.
A39: Validação | B39: Colunas com lista controlada só aceitam valores da folha Listas (evita categorias duplicadas por grafia diferente).
A40: Chaves | B40: IDs estáveis e únicos (PK) e referências a IDs de outros registos (FK) permitem juntar tabelas entre ficheiros — ver SGA-00_Indice_Modelo_Dados.xlsx.
A41: Datas e unidades | B41: Datas em formato data (aaaa-mm-dd); números como números; a unidade está no nome da coluna ou no dicionário. Data de referência do SGA: 2026-12-31 (fecho do ano).
A42: Dados simulados | B42: Fábrica simulada Plasticom. Dados operacionais derivados do dataset do projeto (datasets/silver); dados ambientais e de conformidade são simulação didática — confirmar aplicabilidade legal e números antes de uso real.
A44: LIGAÇÕES A OUTROS REGISTOS
A45: Dataset da fábrica | B45: Produção, rejeições, horas de marcha e mudanças de molde de datasets/silver (jul/2025–dez/2026); mar–jun/2025 reconstruídos (marcados).
A46: RG-SGA-05 Objetivos | B46: Os KPI (KPI-xx) estão definidos no catálogo do RG-SGA-05.
A47: RG-SGA-16 EMAS | B47: Os totais anuais alimentam os indicadores principais do EMAS.

Sheet Plano_Monitorizacao
A1: PLANO DE MONITORIZAÇÃO E MEDIÇÃO — PLASTICOM
A2: Monitorizar = verificar o estado · Medir = obter um valor quantitativo com equipamento calibrado/verificado
A4: ID_MED | B4: O_Que_Medir | C4: Unidade | D4: Tipo | E4: Como_Medir | F4: Equipamentos | G4: Quando_Medir | H4: Quem_Mede | I4: ID_KPI | J4: Criterio_Meta | K4: IDs_Aspetos | L4: Estado_Equipamentos
A5: MED-01 | B5: Eletricidade total e por processo | C5: kWh (total e por processo); kWh/1.000 un; tCO2e | D5: Medir | E5: Leitura do contador geral (fatura) + analisadores de energia por quadro (em serviço desde 15/12/2026; até lá rateio por horas de marcha) | F5: EQP-01; EQP-03 | G5: Mensal, no último dia útil (fatura) e diária (analisadores) | H5: Gerente de Manutenção | I5: KPI-01; KPI-08 | J5: Meta OBJ-01: ≤ 101 kWh/1.000 un até 12/2027 | K5: AA-007; AA-010; AA-030 | L5: =IF(F5="—","Não aplicável",IF(SUMPRODUCT(ISNUMBER(SEARCH(tbl_equipamentos[ID_Equipamento],F5))*(tbl_equipamentos[Estado]<>"Válido"))>0,"Equipamento a regularizar","OK")) -> OK
A6: MED-02 | B6: Ar comprimido: caudal e fugas | C6: Nm³/min; % fugas em teste de vazio | D6: Medir | E6: Medidor de caudal na saída dos compressores; teste de vazio ao domingo; detetor ultrassónico | F6: EQP-04; EQP-05 | G6: Mensal (teste de vazio) e trimestral (campanha ultrassom) | H6: Técnico de Manutenção | I6: KPI-01 | J6: Fugas < 10% do caudal | K6: AA-021 | L6: =IF(F6="—","Não aplicável",IF(SUMPRODUCT(ISNUMBER(SEARCH(tbl_equipamentos[ID_Equipamento],F6))*(tbl_equipamentos[Estado]<>"Válido"))>0,"Equipamento a regularizar","OK")) -> OK
A7: MED-03 | B7: Scrap gerado e reintegrado | C7: kg/mês por processo; kg/1.000 un; % reintegração | D7: Medir | E7: Pesagem das caixas de scrap na balança de piso de cada área e dos moinhos | F7: EQP-06 | G7: Diária (registo por turno), consolidação mensal | H7: Gerente de Produção | I7: KPI-03; KPI-04 | J7: Meta OBJ-02: ≤ 0,423 kg/1.000 un até 06/2027 | K7: AA-008; AA-011; AA-020 | L7: =IF(F7="—","Não aplicável",IF(SUMPRODUCT(ISNUMBER(SEARCH(tbl_equipamentos[ID_Equipamento],F7))*(tbl_equipamentos[Estado]<>"Válido"))>0,"Equipamento a regularizar","OK")) -> OK
A8: MED-04 | B8: Resíduos por código LER e destino | C8: kg/mês por LER; % valorização; kg perigosos | D8: Medir | E8: Pesagem na balança de plataforma do parque antes de cada recolha; conferência com e-GAR | F8: EQP-02 | G8: Em cada recolha; consolidação mensal; MIRR anual | H8: Responsável de Armazém e Logística | I8: KPI-05; KPI-07 | J8: Valorização ≥ 80%; 100% e-GAR confirmadas | K8: AA-004; AA-016; AA-029 | L8: =IF(F8="—","Não aplicável",IF(SUMPRODUCT(ISNUMBER(SEARCH(tbl_equipamentos[ID_Equipamento],F8))*(tbl_equipamentos[Estado]<>"Válido"))>0,"Equipamento a regularizar","OK")) -> OK
A9: MED-05 | B9: Polímero consumido e conteúdo reciclado | C9: kg/mês; % PCR | D9: Medir | E9: Inventário de matérias-primas (entradas − stock) e declarações dos fornecedores | F9: EQP-06 | G9: Mensal | H9: Responsável de Compras | I9: — | J9: % PCR a reportar a clientes | K9: AA-001 | L9: =IF(F9="—","Não aplicável",IF(SUMPRODUCT(ISNUMBER(SEARCH(tbl_equipamentos[ID_Equipamento],F9))*(tbl_equipamentos[Estado]<>"Válido"))>0,"Equipamento a regularizar","OK")) -> OK
A10: MED-06 | B10: Solvente de limpeza na serigrafia | C10: kg/mês; kg/1.000 peças serigrafadas | D10: Medir | E10: Balanço de inventário (compras − stock) e, desde 08/09/2026, pesagem diária dos dispensadores por máquina e turno | F10: EQP-07 | G10: Mensal (inventário) e diária (pesagem) | H10: Gestor do SGA / EHS (Responsável Ambiental) | I10: KPI-06 | J10: Meta OBJ-03: ≤ 0,128 kg/1.000 peças até 06/2027 | K10: AA-014; AA-006 | L10: =IF(F10="—","Não aplicável",IF(SUMPRODUCT(ISNUMBER(SEARCH(tbl_equipamentos[ID_Equipamento],F10))*(tbl_equipamentos[Estado]<>"Válido"))>0,"Equipamento a regularizar","OK")) -> OK
A11: MED-07 | B11: Ruído ambiente no recetor sensível | C11: dB(A); critério de incomodidade | D11: Medir | E11: Ensaio acústico por laboratório acreditado (sonómetro classe 1 calibrado) | F11: EXT-01 | G11: Após alterações e trianual | H11: Gestor do SGA / EHS (Responsável Ambiental) | I11: — | J11: Critério de incomodidade noturno ≤ 3 dB(A) | K11: AA-022 | L11: =IF(F11="—","Não aplicável",IF(SUMPRODUCT(ISNUMBER(SEARCH(tbl_equipamentos[ID_Equipamento],F11))*(tbl_equipamentos[Estado]<>"Válido"))>0,"Equipamento a regularizar","OK")) -> OK
A12: MED-08 | B12: Água de rede e água da torre | C12: m³/mês; m³/1.000 un; condutividade da purga | D12: Medir | E12: Contador geral (fatura) + contadores parciais da torre e sanitária (a partir de 12/2026); condutivímetro da purga | F12: EQP-08; EQP-09 | G12: Mensal (fatura); semanal (leitura dos contadores parciais) | H12: Técnico de Utilidades | I12: KPI-02 | J12: Meta OBJ-05: -10% até 12/2027 (normalizado pela temperatura) | K12: AA-023 | L12: =IF(F12="—","Não aplicável",IF(SUMPRODUCT(ISNUMBER(SEARCH(tbl_equipamentos[ID_Equipamento],F12))*(tbl_equipamentos[Estado]<>"Válido"))>0,"Equipamento a regularizar","OK")) -> OK
A13: MED-09 | B13: Perdas de granulado | C13: kg recolhidos/mês; n.º sarjetas com grânulos | D13: Monitorizar | E13: Inspeção visual semanal das sarjetas e pesagem do granulado recolhido | F13: EQP-06 | G13: Semanal | H13: Gestor do SGA / EHS (Responsável Ambiental) | I13: KPI-13 | J13: 0 sarjetas com grânulos | K13: AA-003 | L13: =IF(F13="—","Não aplicável",IF(SUMPRODUCT(ISNUMBER(SEARCH(tbl_equipamentos[ID_Equipamento],F13))*(tbl_equipamentos[Estado]<>"Válido"))>0,"Equipamento a regularizar","OK")) -> OK
A14: MED-10 | B14: Estado dos controlos operacionais | C14: % pontos conformes nas rondas; n.º incidentes | D14: Monitorizar | E14: Ronda ambiental com checklist (RG-SGA-10) | F14: — | G14: Semanal | H14: Gestor do SGA / EHS (Responsável Ambiental) | I14: KPI-10; KPI-11 | J14: ≥ 90% pontos conformes | K14: AA-005; AA-016 | L14: =IF(F14="—","Não aplicável",IF(SUMPRODUCT(ISNUMBER(SEARCH(tbl_equipamentos[ID_Equipamento],F14))*(tbl_equipamentos[Estado]<>"Válido"))>0,"Equipamento a regularizar","OK")) -> Não aplicável
A15: MED-11 | B15: Qualidade do efluente (purga da torre) | C15: pH, CQO, SST (mg/L) | D15: Medir | E15: Colheita e análise por laboratório acreditado | F15: EXT-02 | G15: Semestral | H15: Gerente de Manutenção | I15: — | J15: Abaixo dos VLE do regulamento municipal | K15: AA-024 | L15: =IF(F15="—","Não aplicável",IF(SUMPRODUCT(ISNUMBER(SEARCH(tbl_equipamentos[ID_Equipamento],F15))*(tbl_equipamentos[Estado]<>"Válido"))>0,"Equipamento a regularizar","OK")) -> Equipamento a regularizar
A16: MED-12 | B16: Conformidade PPWR por família | C16: % famílias com declaração UE | D16: Monitorizar | E16: Revisão do dossier técnico de produto | F16: — | G16: Mensal | H16: Responsável de R&D | I16: KPI-12 | J16: 100% até 31/12/2026 | K16: AA-038 | L16: =IF(F16="—","Não aplicável",IF(SUMPRODUCT(ISNUMBER(SEARCH(tbl_equipamentos[ID_Equipamento],F16))*(tbl_equipamentos[Estado]<>"Válido"))>0,"Equipamento a regularizar","OK")) -> Não aplicável

Sheet Equipamentos_Calibracao
A1: ID_Equipamento | B1: Equipamento | C1: IDs_MED | D1: Tipo_Controlo | E1: Ultima_Calibracao | F1: Periodicidade_Meses | G1: Entidade | H1: Evidencia | I1: Proxima_Calibracao | J1: Estado
A2: EQP-01 | B2: Contador geral de eletricidade (operador de rede) | C2: MED-01 | D2: Verificação metrológica pelo operador de rede | E2: 45422 | F2: 60 | G2: Operador de rede | H2: Certificado do operador | I2: =IF(E2="","",EDATE(E2,F2)) -> 47248 | J2: =IF(E2="","Por verificar",IF(I2<DataRef,"Vencido",IF(I2-DataRef<=45,"A vencer","Válido"))) -> Válido
A3: EQP-02 | B3: Balança de plataforma do parque de resíduos (3.000 kg) | C3: MED-04 | D3: Verificação com massas-padrão | E3: 46318 | F3: 12 | G3: Entidade acreditada | H3: Certificado VB-2026-10 (PAM-26-20; NC-SGA-26-07 fechada) | I3: =IF(E3="","",EDATE(E3,F3)) -> 46683 | J3: =IF(E3="","Por verificar",IF(I3<DataRef,"Vencido",IF(I3-DataRef<=45,"A vencer","Válido"))) -> Válido
A4: EQP-03 | B4: Analisadores de energia (6 un.) | C4: MED-01 | D4: Verificação inicial na instalação | E4: 46371 | F4: 24 | G4: Instalador certificado | H4: Relatório de comissionamento RC-2026-12 (PAM-26-02) | I4: =IF(E4="","",EDATE(E4,F4)) -> 47102 | J4: =IF(E4="","Por verificar",IF(I4<DataRef,"Vencido",IF(I4-DataRef<=45,"A vencer","Válido"))) -> Válido
A5: EQP-04 | B5: Medidor de caudal de ar comprimido | C5: MED-02 | D5: Calibração | E5: 45945 | F5: 24 | G5: Laboratório acreditado | H5: Certificado CAL-2025-331 | I5: =IF(E5="","",EDATE(E5,F5)) -> 46675 | J5: =IF(E5="","Por verificar",IF(I5<DataRef,"Vencido",IF(I5-DataRef<=45,"A vencer","Válido"))) -> Válido
A6: EQP-05 | B6: Detetor ultrassónico de fugas | C6: MED-02 | D6: Verificação funcional | E6: 46204 | F6: 12 | G6: Fornecedor | H6: Relatório de verificação | I6: =IF(E6="","",EDATE(E6,F6)) -> 46569 | J6: =IF(E6="","Por verificar",IF(I6<DataRef,"Vencido",IF(I6-DataRef<=45,"A vencer","Válido"))) -> Válido
A7: EQP-06 | B7: Balanças de piso das áreas (5 un.) | C7: MED-03; MED-05; MED-09 | D7: Verificação com massas-padrão | E7: 46344 | F7: 12 | G7: Entidade acreditada | H7: Certificados VB-2026-11 | I7: =IF(E7="","",EDATE(E7,F7)) -> 46709 | J7: =IF(E7="","Por verificar",IF(I7<DataRef,"Vencido",IF(I7-DataRef<=45,"A vencer","Válido"))) -> Válido
A8: EQP-07 | B8: Balança de bancada da serigrafia (30 kg) | C8: MED-06 | D8: Verificação com massas-padrão | E8: 46270 | F8: 12 | G8: Interna (massas-padrão calibradas) | H8: Registo interno VI-2026-09 | I8: =IF(E8="","",EDATE(E8,F8)) -> 46635 | J8: =IF(E8="","Por verificar",IF(I8<DataRef,"Vencido",IF(I8-DataRef<=45,"A vencer","Válido"))) -> Válido
A9: EQP-08 | B9: Contador geral de água (entidade gestora) | C9: MED-08 | D9: Verificação metrológica pela entidade gestora | E9: 44713 | F9: 96 | G9: Entidade gestora | H9: Selo do contador | I9: =IF(E9="","",EDATE(E9,F9)) -> 47635 | J9: =IF(E9="","Por verificar",IF(I9<DataRef,"Vencido",IF(I9-DataRef<=45,"A vencer","Válido"))) -> Válido
A10: EQP-09 | B10: Condutivímetro da purga da torre | C10: MED-08; MED-11 | D10: Calibração com soluções-padrão | E10: 46365 | F10: 6 | G10: Técnico de Utilidades | H10: Registo CAL-TR-2026-12 | I10: =IF(E10="","",EDATE(E10,F10)) -> 46547 | J10: =IF(E10="","Por verificar",IF(I10<DataRef,"Vencido",IF(I10-DataRef<=45,"A vencer","Válido"))) -> Válido
A11: EXT-01 | B11: Sonómetro classe 1 (laboratório externo) | C11: MED-07 | D11: Calibração (responsabilidade do laboratório) | E11: 46071 | F11: 12 | G11: Laboratório acreditado | H11: Certificado anexo ao relatório de ensaio | I11: =IF(E11="","",EDATE(E11,F11)) -> 46436 | J11: =IF(E11="","Por verificar",IF(I11<DataRef,"Vencido",IF(I11-DataRef<=45,"A vencer","Válido"))) -> Válido
A12: EXT-02 | B12: Equipamento analítico do laboratório externo | C12: MED-11 | D12: Acreditação do laboratório | E12: 46032 | F12: 12 | G12: IPAC / laboratório | H12: Anexo técnico de acreditação | I12: =IF(E12="","",EDATE(E12,F12)) -> 46397 | J12: =IF(E12="","Por verificar",IF(I12<DataRef,"Vencido",IF(I12-DataRef<=45,"A vencer","Válido"))) -> A vencer

Sheet Parametros
A1: Codigo | B1: Valor | C1: Unidade | D1: Descricao
A2: KW_INJ | B2: 45 | C2: kW | D2: Potência média absorvida por máquina de injeção em marcha
A3: KW_SOP | B3: 55 | C3: kW | D3: Potência média absorvida por máquina ISBM em marcha
A4: KW_SER | B4: 18 | C4: kW | D4: Potência média por máquina de serigrafia (inclui cura UV/IR)
A5: KW_HFS | B5: 9 | C5: kW | D5: Potência média por máquina de hot foil
A6: AR_FRAC | B6: 0.19 | C6: fração | D6: Energia dos compressores de ar em proporção da energia dos processos
A7: FRIO_FRAC | B7: 0.1 | C7: fração | D7: Energia do chiller/torre em proporção da energia de injeção + sopro, a 15 °C
A8: FRIO_TEMP | B8: 0.05 | C8: 1/°C | D8: Aumento relativo da energia de arrefecimento por °C acima de 15 °C
A9: BASE_KWH | B9: 42000 | C9: kWh/mês | D9: Consumo base (iluminação, escritórios, armazéns, AVAC a 18 °C)
A10: AGUA_TORRE | B10: 1.45 | C10: m³/MWh | D10: Água de reposição da torre por MWh de injeção + sopro, a 15 °C
A11: AGUA_TEMP | B11: 0.045 | C11: 1/°C | D11: Aumento relativo da reposição da torre por °C acima de 15 °C
A12: AGUA_SAN | B12: 150 | C12: m³/mês | D12: Água sanitária e de limpeza (≈ 150 trabalhadores)
A13: G_FRASCO | B13: 22 | C13: g/un | D13: Massa média de um frasco soprado
... A25: GWP_R410A | B25: 2088 | C25: kgCO2e/kg | D25: GWP do R410A (chiller CH-01). CÓPIA do FE-05 do RG-SGA-19 (mestre dos fatores)

Sheet Dim_Mes
A1: Mes | B1: Ano | C1: Mes_Num | D1: Trimestre | E1: Temp_Media_C | F1: Dias_Uteis | G1: Periodo_Dataset | H1: Fatura_Eletricidade | I1: Energia_kWh | J1: Preco_Eletricidade_EUR_kWh | K1: Potencia_Contratada_kW | L1: Custo_Eletricidade_EUR | M1: Fatura_Agua | N1: Agua_m3 | O1: Tarifa_Agua_EUR_m3 | P1: Tarifa_Saneamento_EUR_m3 | Q1: Custo_Agua_EUR | R1: Custo_por_MWh_EUR | S1: Agua_Torre_m3 | T1: Agua_Consumida_m3 | U1: Agua_Descarregada_m3
A2: 45717 | B2: 2025 | C2: 3 | D2: 2025-T1 | E2: 13.2 | F2: 21 | G2: Pré-dataset | H2: FE-202503-8501 | I2: =SUMIFS(tbl_dados_ambientais[Valor],tbl_dados_ambientais[Mes],A2,tbl_dados_ambientais[Variavel],"ENE_TOTAL") -> 568941.28 | J2: 0.1266 | K2: 1350 | L2: =ROUND(I2*J2,0) -> 72028 | M2: FA-202503 | N2: =SUMIFS(tbl_dados_ambientais[Valor],tbl_dados_ambientais[Mes],A2,tbl_dados_ambientais[Variavel],"AGUA_TOTAL") -> 664.72 | O2: 1.62 | P2: 1.05 | Q2: =ROUND(N2*(O2+P2),0) -> 1775 | R2: =IFERROR(ROUND(L2/I2*1000,0),"") -> 127 | S2: =SUMIFS(tbl_dados_ambientais[Valor],tbl_dados_ambientais[Mes],A2,tbl_dados_ambientais[Variavel],"AGUA_USO",tbl_dados_ambientais[Processo],"UTL-FRIO") -> 516.73 | T2: =ROUND(S2*0.8,0) -> 413 | U2: =N2-T2 -> 251.72
A3: 45748 | B3: 2025 | C3: 4 | D3: 2025-T2 | E3: 15.2 | F3: 20 | G3: Pré-dataset | H3: FE-202504-7773 | I3: =SUMIFS(tbl_dados_ambientais[Valor],tbl_dados_ambientais[Mes],A3,tbl_dados_ambientais[Variavel],"ENE_TOTAL") -> 545353.91 | J3: 0.1155 | K3: 1350 | L3: =ROUND(I3*J3,0) -> 62988 | M3: FA-202504 | N3: =SUMIFS(tbl_dados_ambientais[Valor],tbl_dados_ambientais[Mes],A3,tbl_dados_ambientais[Variavel],"AGUA_TOTAL") -> 693.8 | O3: 1.62 | P3: 1.05 | Q3: =ROUND(N3*(O3+P3),0) -> 1852 | R3: =IFERROR(ROUND(L3/I3*1000,0),"") -> 115 | S3: =SUMIFS(tbl_dados_ambientais[Valor],tbl_dados_ambientais[Mes],A3,tbl_dados_ambientais[Variavel],"AGUA_USO",tbl_dados_ambientais[Processo],"UTL-FRIO") -> 544.68 | T3: =ROUND(S3*0.8,0) -> 436 | U3: =N3-T3 -> 257.8
A4: 45778 | B4: 2025 | C4: 5 | D4: 2025-T2 | E4: 16.8 | F4: 21 | G4: Pré-dataset | H4: FE-202505-7293 | I4: =SUMIFS(tbl_dados_ambientais[Valor],tbl_dados_ambientais[Mes],A4,tbl_dados_ambientais[Variavel],"ENE_TOTAL") -> 538026.29 | J4: 0.1094 | K4: 1350 | L4: =ROUND(I4*J4,0) -> 58860 | M4: FA-202505 | N4: =SUMIFS(tbl_dados_ambientais[Valor],tbl_dados_ambientais[Mes],A4,tbl_dados_ambientais[Variavel],"AGUA_TOTAL") -> 704.19 | O4: 1.62 | P4: 1.05 | Q4: =ROUND(N4*(O4+P4),0) -> 1880 | R4: =IFERROR(ROUND(L4/I4*1000,0),"") -> 109 | S4: =SUMIFS(tbl_dados_ambientais[Valor],tbl_dados_ambientais[Mes],A4,tbl_dados_ambientais[Variavel],"AGUA_USO",tbl_dados_ambientais[Processo],"UTL-FRIO") -> 567.25 | T4: =ROUND(S4*0.8,0) -> 454 | U4: =N4-T4 -> 250.19
A5: 45809 | B5: 2025 | C5: 6 | D5: 2025-T2 | E5: 21.2 | F5: 19 | G5: Pré-dataset | H5: FE-202506-8407 | I5: =SUMIFS(tbl_dados_ambientais[Valor],tbl_dados_ambientais[Mes],A5,tbl_dados_ambientais[Variavel],"ENE_TOTAL") -> 515423.14 | J5: 0.107 | K5: 1350 | L5: =ROUND(I5*J5,0) -> 55150 | M5: FA-202506 | N5: =SUMIFS(tbl_dados_ambientais[Valor],tbl_dados_ambientais[Mes],A5,tbl_dados_ambientais[Variavel],"AGUA_TOTAL") -> 724.54 | O5: 1.62 | P5: 1.05 | Q5: =ROUND(N5*(O5+P5),0) -> 1935 | R5: =IFERROR(ROUND(L5/I5*1000,0),"") -> 107 | S5: =SUMIFS(tbl_dados_ambientais[Valor],tbl_dados_ambientais[Mes],A5,tbl_dados_ambientais[Variavel],"AGUA_USO",tbl_dados_ambientais[Processo],"UTL-FRIO") -> 589.02 | T5: =ROUND(S5*0.8,0) -> 471 | U5: =N5-T5 -> 253.54
A6: 45839 | B6: 2025 | C6: 7 | D6: 2025-T3 | E6: 22.2 | F6: 23 | G6: Dataset de produção | H6: FE-202507-4684 | I6: =SUMIFS(tbl_dados_ambientais[Valor],tbl_dados_ambientais[Mes],A6,tbl_dados_ambientais[Variavel],"ENE_TOTAL") -> 620886.12 | J6: 0.1029 | K6: 1350 | L6: =ROUND(I6*J6,0) -> 63889 | M6: FA-202507 | N6: =SUMIFS(tbl_dados_ambientais[Valor],tbl_dados_ambientais[Mes],A6,tbl_dados_ambientais[Variavel],"AGUA_TOTAL") -> 934.86 | O6: 1.62 | P6: 1.05 | Q6: =ROUND(N6*(O6+P6),0) -> 2496 | R6: =IFERROR(ROUND(L6/I6*1000,0),"") -> 103 | S6: =SUMIFS(tbl_dados_ambientais[Valor],tbl_dados_ambientais[Mes],A6,tbl_dados_ambientais[Variavel],"AGUA_USO",tbl_dados_ambientais[Processo],"UTL-FRIO") -> 763.85 | T6: =ROUND(S6*0.8,0) -> 611 | U6: =N6-T6 -> 323.86
A7: 45870 | B7: 2025 | C7: 8 | D7: 2025-T3 | E7: 23.1 | F7: 20 | G7: Dataset de produção | H7: FE-202508-2456 | I7: =SUMIFS(tbl_dados_ambientais[Valor],tbl_dados_ambientais[Mes],A7,tbl_dados_ambientais[Variavel],"ENE_TOTAL") -> 586900.91 | J7: 0.103 | K7: 1350 | L7: =ROUND(I7*J7,0) -> 60451 | M7: FA-202508 | N7: =SUMIFS(tbl_dados_ambientais[Valor],tbl_dados_ambientais[Mes],A7,tbl_dados_ambientais[Variavel],"AGUA_TOTAL") -> 914.2 | O7: 1.62 | P7: 1.05 | Q7: =ROUND(N7*(O7+P7),0) -> 2441 | R7: =IFERROR(ROUND(L7/I7*1000,0),"") -> 103 | S7: =SUMIFS(tbl_dados_ambientais[Valor],tbl_dados_ambientais[Mes],A7,tbl_dados_ambientais[Variavel],"AGUA_USO",tbl_dados_ambientais[Processo],"UTL-FRIO") -> 778.07 | T7: =ROUND(S7*0.8,0) -> 622 | U7: =N7-T7 -> 292.2
A8: 45901 | B8: 2025 | C8: 9 | D8: 2025-T3 | E8: 20.9 | F8: 22 | G8: Dataset de produção | H8: FE-202509-3005 | I8: =SUMIFS(tbl_dados_ambientais[Valor],tbl_dados_ambientais[Mes],A8,tbl_dados_ambientais[Variavel],"ENE_TOTAL") -> 569448.28 | J8: 0.117 | K8: 1350 | L8: =ROUND(I8*J8,0) -> 66625 | M8: FA-202509 | N8: =SUMIFS(tbl_dados_ambientais[Valor],tbl_dados_ambientais[Mes],A8,tbl_dados_ambientais[Variavel],"AGUA_TOTAL") -> 854.7 | O8: 1.62 | P8: 1.05 | Q8: =ROUND(N8*(O8+P8),0) -> 2282 | R8: =IFERROR(ROUND(L8/I8*1000,0),"") -> 117 | S8: =SUMIFS(tbl_dados_ambientais[Valor],tbl_dados_ambientais[Mes],A8,tbl_dados_ambientais[Variavel],"AGUA_USO",tbl_dados_ambientais[Processo],"UTL-FRIO") -> 695.96 | T8: =ROUND(S8*0.8,0) -> 557 | U8: =N8-T8 -> 297.7
A9: 45931 | B9: 2025 | C9: 10 | D9: 2025-T4 | E9: 18.1 | F9: 22 | G9: Dataset de produção | H9: FE-202510-4189 | I9: =SUMIFS(tbl_dados_ambientais[Valor],tbl_dados_ambientais[Mes],A9,tbl_dados_ambientais[Variavel],"ENE_TOTAL") -> 568761.74 | J9: 0.1215 | K9: 1350 | L9: =ROUND(I9*J9,0) -> 69105 | M9: FA-202510 | N9: =SUMIFS(tbl_dados_ambientais[Valor],tbl_dados_ambientais[Mes],A9,tbl_dados_ambientais[Variavel],"AGUA_TOTAL") -> 793.45 | O9: 1.62 | P9: 1.05 | Q9: =ROUND(N9*(O9+P9),0) -> 2119 | R9: =IFERROR(ROUND(L9/I9*1000,0),"") -> 122 | S9: =SUMIFS(tbl_dados_ambientais[Valor],tbl_dados_ambientais[Mes],A9,tbl_dados_ambientais[Variavel],"AGUA_USO",tbl_dados_ambientais[Processo],"UTL-FRIO") -> 637.78 | T9: =ROUND(S9*0.8,0) -> 510 | U9: =N9-T9 -> 283.45
A10: 45962 | B10: 2025 | C10: 11 | D10: 2025-T4 | E10: 13.3 | F10: 19 | G10: Dataset de produção | H10: FE-202511-7676 | I10: =SUMIFS(tbl_dados_ambientais[Valor],tbl_dados_ambientais[Mes],A10,tbl_dados_ambientais[Variavel],"ENE_TOTAL") -> 561642.6 | J10: 0.1253 | K10: 1350 | L10: =ROUND(I10*J10,0) -> 70374 | M10: FA-202511 | N10: =SUMIFS(tbl_dados_ambientais[Valor],tbl_dados_ambientais[Mes],A10,tbl_dados_ambientais[Variavel],"AGUA_TOTAL") -> 629.21 | O10: 1.62 | P10: 1.05 | Q10: =ROUND(N10*(O10+P10),0) -> 1680 | R10: =IFERROR(ROUND(L10/I10*1000,0),"") -> 125 | S10: =SUMIFS(tbl_dados_ambientais[Valor],tbl_dados_ambientais[Mes],A10,tbl_dados_ambientais[Variavel],"AGUA_USO",tbl_dados_ambientais[Processo],"UTL-FRIO") -> 487.84 | T10: =ROUND(S10*0.8,0) -> 390 | U10: =N10-T10 -> 239.21
A11: 45992 | B11: 2025 | C11: 12 | D11: 2025-T4 | E11: 11.4 | F11: 20 | G11: Dataset de produção | H11: FE-202512-6121 | I11: =SUMIFS(tbl_dados_ambientais[Valor],tbl_dados_ambientais[Mes],A11,tbl_dados_ambientais[Variavel],"ENE_TOTAL") -> 582602.49 | J11: 0.1259 | K11: 1350 | L11: =ROUND(I11*J11,0) -> 73350 | M11: FA-202512 | N11: =SUMIFS(tbl_dados_ambientais[Valor],tbl_dados_ambientais[Mes],A11,tbl_dados_ambientais[Variavel],"AGUA_TOTAL") -> 628.99 | O11: 1.62 | P11: 1.05 | Q11: =ROUND(N11*(O11+P11),0) -> 1679 | R11: =IFERROR(ROUND(L11/I11*1000,0),"") -> 126 | S11: =SUMIFS(tbl_dados_ambientais[Valor],tbl_dados_ambientais[Mes],A11,tbl_dados_ambientais[Variavel],"AGUA_USO",tbl_dados_ambientais[Processo],"UTL-FRIO") -> 485.73 | T11: =ROUND(S11*0.8,0) -> 389 | U11: =N11-T11 -> 239.99
A12: 46023 | B12: 2026 | C12: 1 | D12: 2026-T1 | E12: 9.6 | F12: 21 | G12: Dataset de produção | H12: FE-202601-7519 | I12: =SUMIFS(tbl_dados_ambientais[Valor],tbl_dados_ambientais[Mes],A12,tbl_dados_ambientais[Variavel],"ENE_TOTAL") -> 567251.44 | J12: 0.1408 | K12: 1350 | L12: =ROUND(I12*J12,0) -> 79869 | M12: FA-202601 | N12: =SUMIFS(tbl_dados_ambientais[Valor],tbl_dados_ambientais[Mes],A12,tbl_dados_ambientais[Variavel],"AGUA_TOTAL") -> 589.01 | O12: 1.71 | P12: 1.11 | Q12: =ROUND(N12*(O12+P12),0) -> 1661 | R12: =IFERROR(ROUND(L12/I12*1000,0),"") -> 141 | S12: =SUMIFS(tbl_dados_ambientais[Valor],tbl_dados_ambientais[Mes],A12,tbl_dados_ambientais[Variavel],"AGUA_USO",tbl_dados_ambientais[Processo],"UTL-FRIO") -> 432.47 | T12: =ROUND(S12*0.8,0) -> 346 | U12: =N12-T12 -> 243.01
A13: 46054 | B13: 2026 | C13: 2 | D13: 2026-T1 | E13: 11.9 | F13: 20 | G13: Dataset de produção | H13: FE-202602-5999 | I13: =SUMIFS(tbl_dados_ambientais[Valor],tbl_dados_ambientais[Mes],A13,tbl_dados_ambientais[Variavel],"ENE_TOTAL") -> 527748.79 | J13: 0.1396 | K13: 1350 | L13: =ROUND(I13*J13,0) -> 73674 | M13: FA-202602 | N13: =SUMIFS(tbl_dados_ambientais[Valor],tbl_dados_ambientais[Mes],A13,tbl_dados_ambientais[Variavel],"AGUA_TOTAL") -> 565.5 | O13: 1.71 | P13: 1.11 | Q13: =ROUND(N13*(O13+P13),0) -> 1595 | R13: =IFERROR(ROUND(L13/I13*1000,0),"") -> 140 | S13: =SUMIFS(tbl_dados_ambientais[Valor],tbl_dados_ambientais[Mes],A13,tbl_dados_ambientais[Variavel],"AGUA_USO",tbl_dados_ambientais[Processo],"UTL-FRIO") -> 415.36 | T13: =ROUND(S13*0.8,0) -> 332 | U13: =N13-T13 -> 233.5
... A23: 46357 | B23: 2026 | C23: 12 | D23: 2026-T4 | E23: 11.1 | F23: 20 | G23: Dataset de produção | H23: FE-202612-2243 | I23: =SUMIFS(tbl_dados_ambientais[Valor],tbl_dados_ambientais[Mes],A23,tbl_dados_ambientais[Variavel],"ENE_TOTAL") -> 675973.18 | J23: 0.1368 | K23: 1350 | L23: =ROUND(I23*J23,0) -> 92473 | M23: FA-202612 | N23: =SUMIFS(tbl_dados_ambientais[Valor],tbl_dados_ambientais[Mes],A23,tbl_dados_ambientais[Variavel],"AGUA_TOTAL") -> 701.33 | O23: 1.71 | P23: 1.11 | Q23: =ROUND(N23*(O23+P23),0) -> 1978 | R23: =IFERROR(ROUND(L23/I23*1000,0),"") -> 137 | S23: =SUMIFS(tbl_dados_ambientais[Valor],tbl_dados_ambientais[Mes],A23,tbl_dados_ambientais[Variavel],"AGUA_USO",tbl_dados_ambientais[Processo],"UTL-FRIO") -> 554.61 | T23: =ROUND(S23*0.8,0) -> 444 | U23: =N23-T23 -> 257.33

Sheet Producao_Mensal
A1: Mes | B1: Processo | C1: Unid | D1: Rej | E1: Horas | F1: Setups | G1: Taxa_Rejeicao | H1: Fonte
A2: 45717 | B2: HFS | C2: 622911 | D2: 19932 | E2: 1330 | F2: 0 | G2: =IF(C2=0,"",D2/C2) -> 0.031998151 | H2: Reconstruído (pré-dataset, faturas e registos de turno)
A3: 45717 | B3: INJ | C3: 3127150 | D3: 73603 | E3: 3398.2 | F3: 40 | G3: =IF(C3=0,"",D3/C3) -> 0.023536767 | H3: Reconstruído (pré-dataset, faturas e registos de turno)
A4: 45717 | B4: SER | C4: 373701 | D4: 8279 | E4: 745.8 | F4: 0 | G4: =IF(C4=0,"",D4/C4) -> 0.022154075 | H4: Reconstruído (pré-dataset, faturas e registos de turno)
A5: 45717 | B5: SOP | C5: 2074828 | D5: 47637 | E5: 4230.2 | F5: 140 | G5: =IF(C5=0,"",D5/C5) -> 0.022959494 | H5: Reconstruído (pré-dataset, faturas e registos de turno)
A6: 45748 | B6: HFS | C6: 532950 | D6: 17717 | E6: 1137.9 | F6: 0 | G6: =IF(C6=0,"",D6/C6) -> 0.033243269 | H6: Reconstruído (pré-dataset, faturas e registos de turno)
A7: 45748 | B7: INJ | C7: 2949838 | D7: 63947 | E7: 3205.5 | F7: 38 | G7: =IF(C7=0,"",D7/C7) -> 0.02167814 | H7: Reconstruído (pré-dataset, faturas e registos de turno)
A8: 45748 | B8: SER | C8: 352528 | D8: 8115 | E8: 703.6 | F8: 0 | G8: =IF(C8=0,"",D8/C8) -> 0.023019448 | H8: Reconstruído (pré-dataset, faturas e registos de turno)
A9: 45748 | B9: SOP | C9: 1917166 | D9: 43191 | E9: 3908.8 | F9: 129 | G9: =IF(C9=0,"",D9/C9) -> 0.022528566 | H9: Reconstruído (pré-dataset, faturas e registos de turno)
A10: 45778 | B10: HFS | C10: 583006 | D10: 20556 | E10: 1244.8 | F10: 0 | G10: =IF(C10=0,"",D10/C10) -> 0.035258642 | H10: Reconstruído (pré-dataset, faturas e registos de turno)
A11: 45778 | B11: INJ | C11: 3081721 | D11: 70133 | E11: 3348.8 | F11: 39 | G11: =IF(C11=0,"",D11/C11) -> 0.022757738 | H11: Reconstruído (pré-dataset, faturas e registos de turno)
A12: 45778 | B12: SER | C12: 376251 | D12: 8782 | E12: 750.9 | F12: 0 | G12: =IF(C12=0,"",D12/C12) -> 0.023340802 | H12: Reconstruído (pré-dataset, faturas e registos de turno)
A13: 45778 | B13: SOP | C13: 1948876 | D13: 42207 | E13: 3973.4 | F13: 132 | G13: =IF(C13=0,"",D13/C13) -> 0.021657099 | H13: Reconstruído (pré-dataset, faturas e registos de turno)
... A89: 46357 | B89: SOP | C89: 2608256 | D89: 59893 | E89: 5342.6289 | F89: 176 | G89: =IF(C89=0,"",D89/C89) -> 0.022962853 | H89: Dataset de produção (silver)

Sheet Dados_Ambientais
A1: Mes | B1: Processo | C1: Variavel | D1: Descricao | E1: Valor | F1: Unidade | G1: Fonte | H1: Qualidade_Dado
A2: 45717 | B2: GER | C2: ENE_TOTAL | D2: Eletricidade total (fatura) | E2: 568941.28 | F2: kWh | G2: Fatura do comercializador | H2: Medido
A3: 45717 | B3: INJ | C3: ENE_PROC | D3: Eletricidade por processo/uso (rateio por horas de marcha) | E3: 150493.33 | F3: kWh | G3: Rateio por horas de marcha | H3: Estimado
A4: 45717 | B4: SOP | C4: ENE_PROC | D4: Eletricidade por processo/uso (rateio por horas de marcha) | E4: 233780.43 | F4: kWh | G4: Rateio por horas de marcha | H4: Estimado
A5: 45717 | B5: SER | C5: ENE_PROC | D5: Eletricidade por processo/uso (rateio por horas de marcha) | E5: 12915.26 | F5: kWh | G5: Rateio por horas de marcha | H5: Estimado
A6: 45717 | B6: HFS | C6: ENE_PROC | D6: Eletricidade por processo/uso (rateio por horas de marcha) | E6: 12304.15 | F6: kWh | G6: Rateio por horas de marcha | H6: Estimado
A7: 45717 | B7: UTL-AR | C7: ENE_PROC | D7: Eletricidade por processo/uso (rateio por horas de marcha) | E7: 78796.94 | F7: kWh | G7: Rateio por horas de marcha | H7: Estimado
A8: 45717 | B8: UTL-FRIO | C8: ENE_PROC | D8: Eletricidade por processo/uso (rateio por horas de marcha) | E8: 34764.66 | F8: kWh | G8: Rateio por horas de marcha | H8: Estimado
A9: 45717 | B9: GER | C9: ENE_PROC | D9: Eletricidade por processo/uso (rateio por horas de marcha) | E9: 45886.52 | F9: kWh | G9: Rateio por horas de marcha | H9: Estimado
A10: 45717 | B10: GER | C10: AGUA_TOTAL | D10: Água de rede total (fatura) | E10: 664.72 | F10: m³ | G10: Fatura da entidade gestora | H10: Medido
A11: 45717 | B11: UTL-FRIO | C11: AGUA_USO | D11: Água de reposição da torre de arrefecimento (estimativa) | E11: 516.73 | F11: m³ | G11: Balanço (fatura - sanitária) | H11: Estimado
A12: 45717 | B12: GER | C12: AGUA_USO | D12: Água sanitária e limpezas (estimativa) | E12: 147.99 | F12: m³ | G12: Estimativa por n.º de trabalhadores | H12: Estimado
A13: 45717 | B13: SOP | C13: SCRAP_KG | D13: Scrap plástico gerado (rejeitados + purgas de arranque) | E13: 1454.75 | F13: kg | G13: Pesagem na balança da área | H13: Medido
... A486: 45962 | B486: UTL-FRIO | C486: FGAS_KG | D486: Fuga de gás fluorado R410A (reposição após fuga) | E486: 3.2 | F486: kg | G486: Relatório do técnico certificado | H486: Medido

Sheet Residuos_Mensais
A1: Mes | B1: Codigo_LER | C1: Descricao | D1: Perigoso | E1: Quantidade_kg | F1: Operacao_Destino | G1: Operador | H1: Valorizado
A2: 45717 | B2: 07 02 13 | C2: Resíduos de plásticos (scrap não reintegrado) | D2: Não | E2: 1652.1 | F2: R3 | G2: OGR-01 Recicladora de plásticos | H2: =IF(LEFT(F2,1)="R","Sim","Não") -> Sim
A3: 45717 | B3: 15 01 01 | C3: Embalagens de papel e cartão | D3: Não | E3: 3270.2 | F3: R3 | G3: OGR-02 Gestor de papel/cartão | H3: =IF(LEFT(F3,1)="R","Sim","Não") -> Sim
A4: 45717 | B4: 15 01 02 | C4: Embalagens de plástico (filme, big bags, sacos) | D4: Não | E4: 1841.9 | F4: R3 | G4: OGR-01 Recicladora de plásticos | H4: =IF(LEFT(F4,1)="R","Sim","Não") -> Sim
A5: 45717 | B5: 15 01 03 | C5: Embalagens de madeira (paletes) | D5: Não | E5: 1117.9 | F5: R3 | G5: OGR-03 Recuperador de paletes | H5: =IF(LEFT(F5,1)="R","Sim","Não") -> Sim
A6: 45717 | B6: 07 02 13 | C6: Resíduo de foil (filme de suporte) | D6: Não | E6: 445.2 | F6: R13 | G6: OGR-01 Recicladora de plásticos | H6: =IF(LEFT(F6,1)="R","Sim","Não") -> Sim
A7: 45717 | B7: 20 03 01 | C7: Misturas de resíduos urbanos (indiferenciados) | D7: Não | E7: 2246.6 | F7: D1 | G7: OGR-04 Sistema municipal | H7: =IF(LEFT(F7,1)="R","Sim","Não") -> Não
A8: 45717 | B8: 17 04 05 | C8: Ferro e aço (sucata) | D8: Não | E8: 458.8 | F8: R4 | G8: OGR-05 Sucateiro licenciado | H8: =IF(LEFT(F8,1)="R","Sim","Não") -> Sim
A9: 45717 | B9: 08 03 12* | C9: Resíduos de tintas de impressão com substâncias perigosas | D9: Sim | E9: 24.3 | F9: R13 | G9: OGR-06 Operador de resíduos perigosos | H9: =IF(LEFT(F9,1)="R","Sim","Não") -> Sim
A10: 45717 | B10: 15 01 10* | C10: Embalagens contaminadas por substâncias perigosas | D10: Sim | E10: 44.1 | F10: R13 | G10: OGR-06 Operador de resíduos perigosos | H10: =IF(LEFT(F10,1)="R","Sim","Não") -> Sim
A11: 45717 | B11: 15 02 02* | C11: Absorventes e panos contaminados | D11: Sim | E11: 41.2 | F11: D15 | G11: OGR-06 Operador de resíduos perigosos | H11: =IF(LEFT(F11,1)="R","Sim","Não") -> Não
A12: 45717 | B12: 13 02 05* | C12: Óleos minerais de motores e lubrificação usados | D12: Sim | E12: 193.3 | F12: R13 | G12: OGR-07 Regenerador de óleos | H12: =IF(LEFT(F12,1)="R","Sim","Não") -> Sim
A13: 45717 | B13: 20 01 21* | C13: Lâmpadas fluorescentes | D13: Sim | E13: 0 | F13: R13 | G13: OGR-06 Operador de resíduos perigosos | H13: =IF(LEFT(F13,1)="R","Sim","Não") -> Sim
... A265: 46357 | B265: 20 01 21* | C265: Lâmpadas fluorescentes | D265: Sim | E265: 0 | F265: R13 | G265: OGR-06 Operador de resíduos perigosos | H265: =IF(LEFT(F265,1)="R","Sim","Não") -> Sim

Sheet Indicadores_Mensais
A1: INDICADORES AMBIENTAIS MENSAIS — calculados
A3: Mês | B3: Temp. (°C) | C3: Unid. INJ+SOP | D3: kWh total | E3: KPI-01 kWh/1.000 un | F3: m³ água | G3: KPI-02 m³/1.000 un | H3: Scrap (kg) | I3: KPI-03 kg/1.000 un | J3: KPI-04 % reintegração | K3: Resíduos (kg) | L3: KPI-05 % valorização | M3: KPI-07 perigosos (kg) | N3: Peças serigrafadas | O3: Solvente (kg) | P3: KPI-06 kg/1.000 peças | Q3: KPI-08 tCO2e (âmbito 2)
A4: =INDEX(Dim_Mes!$A$2:$A$23,1) -> 45717 | B4: =INDEX(Dim_Mes!$E$2:$E$23,1) -> 13.2 | C4: =SUMIFS(Producao_Mensal!$C$2:$C$89,Producao_Mensal!$A$2:$A$89,$A4,Producao_Mensal!$B$2:$B$89,"INJ")+SUMIFS(Producao_Mensal!$C$2:$C$89,Producao_Mensal!$A$2:$A$89,$A4,Producao_Mensal!$B$2:$B$89,"SOP") -> 5201978 | D4: =SUMIFS(Dados_Ambientais!$E$2:$E$486,Dados_Ambientais!$A$2:$A$486,$A4,Dados_Ambientais!$C$2:$C$486,"ENE_TOTAL") -> 568941.28 | E4: =D4/C4*1000 -> 109.37018 | F4: =SUMIFS(Dados_Ambientais!$E$2:$E$486,Dados_Ambientais!$A$2:$A$486,$A4,Dados_Ambientais!$C$2:$C$486,"AGUA_TOTAL") -> 664.72 | G4: =F4/C4*1000 -> 0.12778216 | H4: =SUMIFS(Dados_Ambientais!$E$2:$E$486,Dados_Ambientais!$A$2:$A$486,$A4,Dados_Ambientais!$C$2:$C$486,"SCRAP_KG") -> 2594.09 | I4: =H4/C4*1000 -> 0.49867377 | J4: =SUMIFS(Dados_Ambientais!$E$2:$E$486,Dados_Ambientais!$A$2:$A$486,$A4,Dados_Ambientais!$C$2:$C$486,"REGRIND_KG")/H4 -> 0.36311385 | K4: =SUMIFS(Residuos_Mensais!$E$2:$E$265,Residuos_Mensais!$A$2:$A$265,$A4) -> 11335.6 | L4: =SUMIFS(Residuos_Mensais!$E$2:$E$265,Residuos_Mensais!$A$2:$A$265,$A4,Residuos_Mensais!$H$2:$H$265,"Sim")/K4 -> 0.79817566 | M4: =SUMIFS(Residuos_Mensais!$E$2:$E$265,Residuos_Mensais!$A$2:$A$265,$A4,Residuos_Mensais!$D$2:$D$265,"Sim") -> 302.9 | N4: =SUMIFS(Producao_Mensal!$C$2:$C$89,Producao_Mensal!$A$2:$A$89,$A4,Producao_Mensal!$B$2:$B$89,"SER") -> 373701 | O4: =SUMIFS(Dados_Ambientais!$E$2:$E$486,Dados_Ambientais!$A$2:$A$486,$A4,Dados_Ambientais!$C$2:$C$486,"SOLVENTE_KG") -> 60.61 | P4: =O4/N4*1000 -> 0.16218849 | Q4: =D4*INDEX(Parametros!$B$2:$B$25,22)/1000 -> 62.583541
A5: =INDEX(Dim_Mes!$A$2:$A$23,2) -> 45748 | B5: =INDEX(Dim_Mes!$E$2:$E$23,2) -> 15.2 | C5: =SUMIFS(Producao_Mensal!$C$2:$C$89,Producao_Mensal!$A$2:$A$89,$A5,Producao_Mensal!$B$2:$B$89,"INJ")+SUMIFS(Producao_Mensal!$C$2:$C$89,Producao_Mensal!$A$2:$A$89,$A5,Producao_Mensal!$B$2:$B$89,"SOP") -> 4867004 | D5: =SUMIFS(Dados_Ambientais!$E$2:$E$486,Dados_Ambientais!$A$2:$A$486,$A5,Dados_Ambientais!$C$2:$C$486,"ENE_TOTAL") -> 545353.91 | E5: =D5/C5*1000 -> 112.05126 | F5: =SUMIFS(Dados_Ambientais!$E$2:$E$486,Dados_Ambientais!$A$2:$A$486,$A5,Dados_Ambientais!$C$2:$C$486,"AGUA_TOTAL") -> 693.8 | G5: =F5/C5*1000 -> 0.14255176 | H5: =SUMIFS(Dados_Ambientais!$E$2:$E$486,Dados_Ambientais!$A$2:$A$486,$A5,Dados_Ambientais!$C$2:$C$486,"SCRAP_KG") -> 2362.67 | I5: =H5/C5*1000 -> 0.48544649 | J5: =SUMIFS(Dados_Ambientais!$E$2:$E$486,Dados_Ambientais!$A$2:$A$486,$A5,Dados_Ambientais!$C$2:$C$486,"REGRIND_KG")/H5 -> 0.37189282 | K5: =SUMIFS(Residuos_Mensais!$E$2:$E$265,Residuos_Mensais!$A$2:$A$265,$A5) -> 10955.4 | L5: =SUMIFS(Residuos_Mensais!$E$2:$E$265,Residuos_Mensais!$A$2:$A$265,$A5,Residuos_Mensais!$H$2:$H$265,"Sim")/K5 -> 0.80010771 | M5: =SUMIFS(Residuos_Mensais!$E$2:$E$265,Residuos_Mensais!$A$2:$A$265,$A5,Residuos_Mensais!$D$2:$D$265,"Sim") -> 128.7 | N5: =SUMIFS(Producao_Mensal!$C$2:$C$89,Producao_Mensal!$A$2:$A$89,$A5,Producao_Mensal!$B$2:$B$89,"SER") -> 352528 | O5: =SUMIFS(Dados_Ambientais!$E$2:$E$486,Dados_Ambientais!$A$2:$A$486,$A5,Dados_Ambientais!$C$2:$C$486,"SOLVENTE_KG") -> 60.01 | P5: =O5/N5*1000 -> 0.17022761 | Q5: =D5*INDEX(Parametros!$B$2:$B$25,22)/1000 -> 59.98893
A6: =INDEX(Dim_Mes!$A$2:$A$23,3) -> 45778 | B6: =INDEX(Dim_Mes!$E$2:$E$23,3) -> 16.8 | C6: =SUMIFS(Producao_Mensal!$C$2:$C$89,Producao_Mensal!$A$2:$A$89,$A6,Producao_Mensal!$B$2:$B$89,"INJ")+SUMIFS(Producao_Mensal!$C$2:$C$89,Producao_Mensal!$A$2:$A$89,$A6,Producao_Mensal!$B$2:$B$89,"SOP") -> 5030597 | D6: =SUMIFS(Dados_Ambientais!$E$2:$E$486,Dados_Ambientais!$A$2:$A$486,$A6,Dados_Ambientais!$C$2:$C$486,"ENE_TOTAL") -> 538026.29 | E6: =D6/C6*1000 -> 106.95078 | F6: =SUMIFS(Dados_Ambientais!$E$2:$E$486,Dados_Ambientais!$A$2:$A$486,$A6,Dados_Ambientais!$C$2:$C$486,"AGUA_TOTAL") -> 704.19 | G6: =F6/C6*1000 -> 0.1399814 | H6: =SUMIFS(Dados_Ambientais!$E$2:$E$486,Dados_Ambientais!$A$2:$A$486,$A6,Dados_Ambientais!$C$2:$C$486,"SCRAP_KG") -> 2471.24 | I6: =H6/C6*1000 -> 0.49124189 | J6: =SUMIFS(Dados_Ambientais!$E$2:$E$486,Dados_Ambientais!$A$2:$A$486,$A6,Dados_Ambientais!$C$2:$C$486,"REGRIND_KG")/H6 -> 0.35957252 | K6: =SUMIFS(Residuos_Mensais!$E$2:$E$265,Residuos_Mensais!$A$2:$A$265,$A6) -> 10841.6 | L6: =SUMIFS(Residuos_Mensais!$E$2:$E$265,Residuos_Mensais!$A$2:$A$265,$A6,Residuos_Mensais!$H$2:$H$265,"Sim")/K6 -> 0.80657836 | M6: =SUMIFS(Residuos_Mensais!$E$2:$E$265,Residuos_Mensais!$A$2:$A$265,$A6,Residuos_Mensais!$D$2:$D$265,"Sim") -> 121.8 | N6: =SUMIFS(Producao_Mensal!$C$2:$C$89,Producao_Mensal!$A$2:$A$89,$A6,Producao_Mensal!$B$2:$B$89,"SER") -> 376251 | O6: =SUMIFS(Dados_Ambientais!$E$2:$E$486,Dados_Ambientais!$A$2:$A$486,$A6,Dados_Ambientais!$C$2:$C$486,"SOLVENTE_KG") -> 59.93 | P6: =O6/N6*1000 -> 0.15928197 | Q6: =D6*INDEX(Parametros!$B$2:$B$25,22)/1000 -> 59.182892
A7: =INDEX(Dim_Mes!$A$2:$A$23,4) -> 45809 | B7: =INDEX(Dim_Mes!$E$2:$E$23,4) -> 21.2 | C7: =SUMIFS(Producao_Mensal!$C$2:$C$89,Producao_Mensal!$A$2:$A$89,$A7,Producao_Mensal!$B$2:$B$89,"INJ")+SUMIFS(Producao_Mensal!$C$2:$C$89,Producao_Mensal!$A$2:$A$89,$A7,Producao_Mensal!$B$2:$B$89,"SOP") -> 4543947 | D7: =SUMIFS(Dados_Ambientais!$E$2:$E$486,Dados_Ambientais!$A$2:$A$486,$A7,Dados_Ambientais!$C$2:$C$486,"ENE_TOTAL") -> 515423.14 | E7: =D7/C7*1000 -> 113.43071 | F7: =SUMIFS(Dados_Ambientais!$E$2:$E$486,Dados_Ambientais!$A$2:$A$486,$A7,Dados_Ambientais!$C$2:$C$486,"AGUA_TOTAL") -> 724.54 | G7: =F7/C7*1000 -> 0.15945168 | H7: =SUMIFS(Dados_Ambientais!$E$2:$E$486,Dados_Ambientais!$A$2:$A$486,$A7,Dados_Ambientais!$C$2:$C$486,"SCRAP_KG") -> 2363.35 | I7: =H7/C7*1000 -> 0.5201095 | J7: =SUMIFS(Dados_Ambientais!$E$2:$E$486,Dados_Ambientais!$A$2:$A$486,$A7,Dados_Ambientais!$C$2:$C$486,"REGRIND_KG")/H7 -> 0.36229082 | K7: =SUMIFS(Residuos_Mensais!$E$2:$E$265,Residuos_Mensais!$A$2:$A$265,$A7) -> 11143.8 | L7: =SUMIFS(Residuos_Mensais!$E$2:$E$265,Residuos_Mensais!$A$2:$A$265,$A7,Residuos_Mensais!$H$2:$H$265,"Sim")/K7 -> 0.79317647 | M7: =SUMIFS(Residuos_Mensais!$E$2:$E$265,Residuos_Mensais!$A$2:$A$265,$A7,Residuos_Mensais!$D$2:$D$265,"Sim") -> 284.6 | N7: =SUMIFS(Producao_Mensal!$C$2:$C$89,Producao_Mensal!$A$2:$A$89,$A7,Producao_Mensal!$B$2:$B$89,"SER") -> 336762 | O7: =SUMIFS(Dados_Ambientais!$E$2:$E$486,Dados_Ambientais!$A$2:$A$486,$A7,Dados_Ambientais!$C$2:$C$486,"SOLVENTE_KG") -> 52.8 | P7: =O7/N7*1000 -> 0.15678729 | Q7: =D7*INDEX(Parametros!$B$2:$B$25,22)/1000 -> 56.696545
A8: =INDEX(Dim_Mes!$A$2:$A$23,5) -> 45839 | B8: =INDEX(Dim_Mes!$E$2:$E$23,5) -> 22.2 | C8: =SUMIFS(Producao_Mensal!$C$2:$C$89,Producao_Mensal!$A$2:$A$89,$A8,Producao_Mensal!$B$2:$B$89,"INJ")+SUMIFS(Producao_Mensal!$C$2:$C$89,Producao_Mensal!$A$2:$A$89,$A8,Producao_Mensal!$B$2:$B$89,"SOP") -> 5273074 | D8: =SUMIFS(Dados_Ambientais!$E$2:$E$486,Dados_Ambientais!$A$2:$A$486,$A8,Dados_Ambientais!$C$2:$C$486,"ENE_TOTAL") -> 620886.12 | E8: =D8/C8*1000 -> 117.74652 | F8: =SUMIFS(Dados_Ambientais!$E$2:$E$486,Dados_Ambientais!$A$2:$A$486,$A8,Dados_Ambientais!$C$2:$C$486,"AGUA_TOTAL") -> 934.86 | G8: =F8/C8*1000 -> 0.17728938 | H8: =SUMIFS(Dados_Ambientais!$E$2:$E$486,Dados_Ambientais!$A$2:$A$486,$A8,Dados_Ambientais!$C$2:$C$486,"SCRAP_KG") -> 2638.73 | I8: =H8/C8*1000 -> 0.50041589 | J8: =SUMIFS(Dados_Ambientais!$E$2:$E$486,Dados_Ambientais!$A$2:$A$486,$A8,Dados_Ambientais!$C$2:$C$486,"REGRIND_KG")/H8 -> 0.38126296 | K8: =SUMIFS(Residuos_Mensais!$E$2:$E$265,Residuos_Mensais!$A$2:$A$265,$A8) -> 11144.1 | L8: =SUMIFS(Residuos_Mensais!$E$2:$E$265,Residuos_Mensais!$A$2:$A$265,$A8,Residuos_Mensais!$H$2:$H$265,"Sim")/K8 -> 0.80305274 | M8: =SUMIFS(Residuos_Mensais!$E$2:$E$265,Residuos_Mensais!$A$2:$A$265,$A8,Residuos_Mensais!$D$2:$D$265,"Sim") -> 124.7 | N8: =SUMIFS(Producao_Mensal!$C$2:$C$89,Producao_Mensal!$A$2:$A$89,$A8,Producao_Mensal!$B$2:$B$89,"SER") -> 443480 | O8: =SUMIFS(Dados_Ambientais!$E$2:$E$486,Dados_Ambientais!$A$2:$A$486,$A8,Dados_Ambientais!$C$2:$C$486,"SOLVENTE_KG") -> 68.44 | P8: =O8/N8*1000 -> 0.15432489 | Q8: =D8*INDEX(Parametros!$B$2:$B$25,22)/1000 -> 68.297473
A9: =INDEX(Dim_Mes!$A$2:$A$23,6) -> 45870 | B9: =INDEX(Dim_Mes!$E$2:$E$23,6) -> 23.1 | C9: =SUMIFS(Producao_Mensal!$C$2:$C$89,Producao_Mensal!$A$2:$A$89,$A9,Producao_Mensal!$B$2:$B$89,"INJ")+SUMIFS(Producao_Mensal!$C$2:$C$89,Producao_Mensal!$A$2:$A$89,$A9,Producao_Mensal!$B$2:$B$89,"SOP") -> 5443656 | D9: =SUMIFS(Dados_Ambientais!$E$2:$E$486,Dados_Ambientais!$A$2:$A$486,$A9,Dados_Ambientais!$C$2:$C$486,"ENE_TOTAL") -> 586900.91 | E9: =D9/C9*1000 -> 107.81374 | F9: =SUMIFS(Dados_Ambientais!$E$2:$E$486,Dados_Ambientais!$A$2:$A$486,$A9,Dados_Ambientais!$C$2:$C$486,"AGUA_TOTAL") -> 914.2 | G9: =F9/C9*1000 -> 0.16793861 | H9: =SUMIFS(Dados_Ambientais!$E$2:$E$486,Dados_Ambientais!$A$2:$A$486,$A9,Dados_Ambientais!$C$2:$C$486,"SCRAP_KG") -> 2732.91 | I9: =H9/C9*1000 -> 0.50203576 | J9: =SUMIFS(Dados_Ambientais!$E$2:$E$486,Dados_Ambientais!$A$2:$A$486,$A9,Dados_Ambientais!$C$2:$C$486,"REGRIND_KG")/H9 -> 0.35900194 | K9: =SUMIFS(Residuos_Mensais!$E$2:$E$265,Residuos_Mensais!$A$2:$A$265,$A9) -> 11135.9 | L9: =SUMIFS(Residuos_Mensais!$E$2:$E$265,Residuos_Mensais!$A$2:$A$265,$A9,Residuos_Mensais!$H$2:$H$265,"Sim")/K9 -> 0.77814995 | M9: =SUMIFS(Residuos_Mensais!$E$2:$E$265,Residuos_Mensais!$A$2:$A$265,$A9,Residuos_Mensais!$D$2:$D$265,"Sim") -> 104.6 | N9: =SUMIFS(Producao_Mensal!$C$2:$C$89,Producao_Mensal!$A$2:$A$89,$A9,Producao_Mensal!$B$2:$B$89,"SER") -> 237760 | O9: =SUMIFS(Dados_Ambientais!$E$2:$E$486,Dados_Ambientais!$A$2:$A$486,$A9,Dados_Ambientais!$C$2:$C$486,"SOLVENTE_KG") -> 37.4 | P9: =O9/N9*1000 -> 0.15730148 | Q9: =D9*INDEX(Parametros!$B$2:$B$25,22)/1000 -> 64.5591
A10: =INDEX(Dim_Mes!$A$2:$A$23,7) -> 45901 | B10: =INDEX(Dim_Mes!$E$2:$E$23,7) -> 20.9 | C10: =SUMIFS(Producao_Mensal!$C$2:$C$89,Producao_Mensal!$A$2:$A$89,$A10,Producao_Mensal!$B$2:$B$89,"INJ")+SUMIFS(Producao_Mensal!$C$2:$C$89,Producao_Mensal!$A$2:$A$89,$A10,Producao_Mensal!$B$2:$B$89,"SOP") -> 5062893 | D10: =SUMIFS(Dados_Ambientais!$E$2:$E$486,Dados_Ambientais!$A$2:$A$486,$A10,Dados_Ambientais!$C$2:$C$486,"ENE_TOTAL") -> 569448.28 | E10: =D10/C10*1000 -> 112.47488 | F10: =SUMIFS(Dados_Ambientais!$E$2:$E$486,Dados_Ambientais!$A$2:$A$486,$A10,Dados_Ambientais!$C$2:$C$486,"AGUA_TOTAL") -> 854.7 | G10: =F10/C10*1000 -> 0.16881652 | H10: =SUMIFS(Dados_Ambientais!$E$2:$E$486,Dados_Ambientais!$A$2:$A$486,$A10,Dados_Ambientais!$C$2:$C$486,"SCRAP_KG") -> 2521.04 | I10: =H10/C10*1000 -> 0.49794455 | J10: =SUMIFS(Dados_Ambientais!$E$2:$E$486,Dados_Ambientais!$A$2:$A$486,$A10,Dados_Ambientais!$C$2:$C$486,"REGRIND_KG")/H10 -> 0.35465126 | K10: =SUMIFS(Residuos_Mensais!$E$2:$E$265,Residuos_Mensais!$A$2:$A$265,$A10) -> 11091.5 | L10: =SUMIFS(Residuos_Mensais!$E$2:$E$265,Residuos_Mensais!$A$2:$A$265,$A10,Residuos_Mensais!$H$2:$H$265,"Sim")/K10 -> 0.80853807 | M10: =SUMIFS(Residuos_Mensais!$E$2:$E$265,Residuos_Mensais!$A$2:$A$265,$A10,Residuos_Mensais!$D$2:$D$265,"Sim") -> 297.7 | N10: =SUMIFS(Producao_Mensal!$C$2:$C$89,Producao_Mensal!$A$2:$A$89,$A10,Producao_Mensal!$B$2:$B$89,"SER") -> 372292 | O10: =SUMIFS(Dados_Ambientais!$E$2:$E$486,Dados_Ambientais!$A$2:$A$486,$A10,Dados_Ambientais!$C$2:$C$486,"SOLVENTE_KG") -> 59.8 | P10: =O10/N10*1000 -> 0.1606266 | Q10: =D10*INDEX(Parametros!$B$2:$B$25,22)/1000 -> 62.639311
A11: =INDEX(Dim_Mes!$A$2:$A$23,8) -> 45931 | B11: =INDEX(Dim_Mes!$E$2:$E$23,8) -> 18.1 | C11: =SUMIFS(Producao_Mensal!$C$2:$C$89,Producao_Mensal!$A$2:$A$89,$A11,Producao_Mensal!$B$2:$B$89,"INJ")+SUMIFS(Producao_Mensal!$C$2:$C$89,Producao_Mensal!$A$2:$A$89,$A11,Producao_Mensal!$B$2:$B$89,"SOP") -> 5158725 | D11: =SUMIFS(Dados_Ambientais!$E$2:$E$486,Dados_Ambientais!$A$2:$A$486,$A11,Dados_Ambientais!$C$2:$C$486,"ENE_TOTAL") -> 568761.74 | E11: =D11/C11*1000 -> 110.25239 | F11: =SUMIFS(Dados_Ambientais!$E$2:$E$486,Dados_Ambientais!$A$2:$A$486,$A11,Dados_Ambientais!$C$2:$C$486,"AGUA_TOTAL") -> 793.45 | G11: =F11/C11*1000 -> 0.15380738 | H11: =SUMIFS(Dados_Ambientais!$E$2:$E$486,Dados_Ambientais!$A$2:$A$486,$A11,Dados_Ambientais!$C$2:$C$486,"SCRAP_KG") -> 2553.13 | I11: =H11/C11*1000 -> 0.49491493 | J11: =SUMIFS(Dados_Ambientais!$E$2:$E$486,Dados_Ambientais!$A$2:$A$486,$A11,Dados_Ambientais!$C$2:$C$486,"REGRIND_KG")/H11 -> 0.35674642 | K11: =SUMIFS(Residuos_Mensais!$E$2:$E$265,Residuos_Mensais!$A$2:$A$265,$A11) -> 11729.1 | L11: =SUMIFS(Residuos_Mensais!$E$2:$E$265,Residuos_Mensais!$A$2:$A$265,$A11,Residuos_Mensais!$H$2:$H$265,"Sim")/K11 -> 0.79946458 | M11: =SUMIFS(Residuos_Mensais!$E$2:$E$265,Residuos_Mensais!$A$2:$A$265,$A11,Residuos_Mensais!$D$2:$D$265,"Sim") -> 131.5 | N11: =SUMIFS(Producao_Mensal!$C$2:$C$89,Producao_Mensal!$A$2:$A$89,$A11,Producao_Mensal!$B$2:$B$89,"SER") -> 431440 | O11: =SUMIFS(Dados_Ambientais!$E$2:$E$486,Dados_Ambientais!$A$2:$A$486,$A11,Dados_Ambientais!$C$2:$C$486,"SOLVENTE_KG") -> 72.62 | P11: =O11/N11*1000 -> 0.16832004 | Q11: =D11*INDEX(Parametros!$B$2:$B$25,22)/1000 -> 62.563791
A12: =INDEX(Dim_Mes!$A$2:$A$23,9) -> 45962 | B12: =INDEX(Dim_Mes!$E$2:$E$23,9) -> 13.3 | C12: =SUMIFS(Producao_Mensal!$C$2:$C$89,Producao_Mensal!$A$2:$A$89,$A12,Producao_Mensal!$B$2:$B$89,"INJ")+SUMIFS(Producao_Mensal!$C$2:$C$89,Producao_Mensal!$A$2:$A$89,$A12,Producao_Mensal!$B$2:$B$89,"SOP") -> 4974090 | D12: =SUMIFS(Dados_Ambientais!$E$2:$E$486,Dados_Ambientais!$A$2:$A$486,$A12,Dados_Ambientais!$C$2:$C$486,"ENE_TOTAL") -> 561642.6 | E12: =D12/C12*1000 -> 112.91364 | F12: =SUMIFS(Dados_Ambientais!$E$2:$E$486,Dados_Ambientais!$A$2:$A$486,$A12,Dados_Ambientais!$C$2:$C$486,"AGUA_TOTAL") -> 629.21 | G12: =F12/C12*1000 -> 0.12649751 | H12: =SUMIFS(Dados_Ambientais!$E$2:$E$486,Dados_Ambientais!$A$2:$A$486,$A12,Dados_Ambientais!$C$2:$C$486,"SCRAP_KG") -> 2691.58 | I12: =H12/C12*1000 -> 0.54112008 | J12: =SUMIFS(Dados_Ambientais!$E$2:$E$486,Dados_Ambientais!$A$2:$A$486,$A12,Dados_Ambientais!$C$2:$C$486,"REGRIND_KG")/H12 -> 0.33164535 | K12: =SUMIFS(Residuos_Mensais!$E$2:$E$265,Residuos_Mensais!$A$2:$A$265,$A12) -> 11222 | L12: =SUMIFS(Residuos_Mensais!$E$2:$E$265,Residuos_Mensais!$A$2:$A$265,$A12,Residuos_Mensais!$H$2:$H$265,"Sim")/K12 -> 0.80852789 | M12: =SUMIFS(Residuos_Mensais!$E$2:$E$265,Residuos_Mensais!$A$2:$A$265,$A12,Residuos_Mensais!$D$2:$D$265,"Sim") -> 129.7 | N12: =SUMIFS(Producao_Mensal!$C$2:$C$89,Producao_Mensal!$A$2:$A$89,$A12,Producao_Mensal!$B$2:$B$89,"SER") -> 448497 | O12: =SUMIFS(Dados_Ambientais!$E$2:$E$486,Dados_Ambientais!$A$2:$A$486,$A12,Dados_Ambientais!$C$2:$C$486,"SOLVENTE_KG") -> 70.53 | P12: =O12/N12*1000 -> 0.15725858 | Q12: =D12*INDEX(Parametros!$B$2:$B$25,22)/1000 -> 61.780686
A13: =INDEX(Dim_Mes!$A$2:$A$23,10) -> 45992 | B13: =INDEX(Dim_Mes!$E$2:$E$23,10) -> 11.4 | C13: =SUMIFS(Producao_Mensal!$C$2:$C$89,Producao_Mensal!$A$2:$A$89,$A13,Producao_Mensal!$B$2:$B$89,"INJ")+SUMIFS(Producao_Mensal!$C$2:$C$89,Producao_Mensal!$A$2:$A$89,$A13,Producao_Mensal!$B$2:$B$89,"SOP") -> 5221940 | D13: =SUMIFS(Dados_Ambientais!$E$2:$E$486,Dados_Ambientais!$A$2:$A$486,$A13,Dados_Ambientais!$C$2:$C$486,"ENE_TOTAL") -> 582602.49 | E13: =D13/C13*1000 -> 111.56821 | F13: =SUMIFS(Dados_Ambientais!$E$2:$E$486,Dados_Ambientais!$A$2:$A$486,$A13,Dados_Ambientais!$C$2:$C$486,"AGUA_TOTAL") -> 628.99 | G13: =F13/C13*1000 -> 0.1204514 | H13: =SUMIFS(Dados_Ambientais!$E$2:$E$486,Dados_Ambientais!$A$2:$A$486,$A13,Dados_Ambientais!$C$2:$C$486,"SCRAP_KG") -> 2561.61 | I13: =H13/C13*1000 -> 0.49054757 | J13: =SUMIFS(Dados_Ambientais!$E$2:$E$486,Dados_Ambientais!$A$2:$A$486,$A13,Dados_Ambientais!$C$2:$C$486,"REGRIND_KG")/H13 -> 0.39097286 | K13: =SUMIFS(Residuos_Mensais!$E$2:$E$265,Residuos_Mensais!$A$2:$A$265,$A13) -> 11187 | L13: =SUMIFS(Residuos_Mensais!$E$2:$E$265,Residuos_Mensais!$A$2:$A$265,$A13,Residuos_Mensais!$H$2:$H$265,"Sim")/K13 -> 0.78297131 | M13: =SUMIFS(Residuos_Mensais!$E$2:$E$265,Residuos_Mensais!$A$2:$A$265,$A13,Residuos_Mensais!$D$2:$D$265,"Sim") -> 279.5 | N13: =SUMIFS(Producao_Mensal!$C$2:$C$89,Producao_Mensal!$A$2:$A$89,$A13,Producao_Mensal!$B$2:$B$89,"SER") -> 338785 | O13: =SUMIFS(Dados_Ambientais!$E$2:$E$486,Dados_Ambientais!$A$2:$A$486,$A13,Dados_Ambientais!$C$2:$C$486,"SOLVENTE_KG") -> 54.57 | P13: =O13/N13*1000 -> 0.16107561 | Q13: =D13*INDEX(Parametros!$B$2:$B$25,22)/1000 -> 64.086274
A14: =INDEX(Dim_Mes!$A$2:$A$23,11) -> 46023 | B14: =INDEX(Dim_Mes!$E$2:$E$23,11) -> 9.6 | C14: =SUMIFS(Producao_Mensal!$C$2:$C$89,Producao_Mensal!$A$2:$A$89,$A14,Producao_Mensal!$B$2:$B$89,"INJ")+SUMIFS(Producao_Mensal!$C$2:$C$89,Producao_Mensal!$A$2:$A$89,$A14,Producao_Mensal!$B$2:$B$89,"SOP") -> 5272284 | D14: =SUMIFS(Dados_Ambientais!$E$2:$E$486,Dados_Ambientais!$A$2:$A$486,$A14,Dados_Ambientais!$C$2:$C$486,"ENE_TOTAL") -> 567251.44 | E14: =D14/C14*1000 -> 107.59121 | F14: =SUMIFS(Dados_Ambientais!$E$2:$E$486,Dados_Ambientais!$A$2:$A$486,$A14,Dados_Ambientais!$C$2:$C$486,"AGUA_TOTAL") -> 589.01 | G14: =F14/C14*1000 -> 0.11171819 | H14: =SUMIFS(Dados_Ambientais!$E$2:$E$486,Dados_Ambientais!$A$2:$A$486,$A14,Dados_Ambientais!$C$2:$C$486,"SCRAP_KG") -> 2387.46 | I14: =H14/C14*1000 -> 0.45283221 | J14: =SUMIFS(Dados_Ambientais!$E$2:$E$486,Dados_Ambientais!$A$2:$A$486,$A14,Dados_Ambientais!$C$2:$C$486,"REGRIND_KG")/H14 -> 0.37455706 | K14: =SUMIFS(Residuos_Mensais!$E$2:$E$265,Residuos_Mensais!$A$2:$A$265,$A14) -> 10388.6 | L14: =SUMIFS(Residuos_Mensais!$E$2:$E$265,Residuos_Mensais!$A$2:$A$265,$A14,Residuos_Mensais!$H$2:$H$265,"Sim")/K14 -> 0.80764492 | M14: =SUMIFS(Residuos_Mensais!$E$2:$E$265,Residuos_Mensais!$A$2:$A$265,$A14,Residuos_Mensais!$D$2:$D$265,"Sim") -> 102.4 | N14: =SUMIFS(Producao_Mensal!$C$2:$C$89,Producao_Mensal!$A$2:$A$89,$A14,Producao_Mensal!$B$2:$B$89,"SER") -> 296927 | O14: =SUMIFS(Dados_Ambientais!$E$2:$E$486,Dados_Ambientais!$A$2:$A$486,$A14,Dados_Ambientais!$C$2:$C$486,"SOLVENTE_KG") -> 47.3 | P14: =O14/N14*1000 -> 0.15929841 | Q14: =D14*INDEX(Parametros!$B$2:$B$25,22)/1000 -> 62.397658
A15: =INDEX(Dim_Mes!$A$2:$A$23,12) -> 46054 | B15: =INDEX(Dim_Mes!$E$2:$E$23,12) -> 11.9 | C15: =SUMIFS(Producao_Mensal!$C$2:$C$89,Producao_Mensal!$A$2:$A$89,$A15,Producao_Mensal!$B$2:$B$89,"INJ")+SUMIFS(Producao_Mensal!$C$2:$C$89,Producao_Mensal!$A$2:$A$89,$A15,Producao_Mensal!$B$2:$B$89,"SOP") -> 4757334 | D15: =SUMIFS(Dados_Ambientais!$E$2:$E$486,Dados_Ambientais!$A$2:$A$486,$A15,Dados_Ambientais!$C$2:$C$486,"ENE_TOTAL") -> 527748.79 | E15: =D15/C15*1000 -> 110.93373 | F15: =SUMIFS(Dados_Ambientais!$E$2:$E$486,Dados_Ambientais!$A$2:$A$486,$A15,Dados_Ambientais!$C$2:$C$486,"AGUA_TOTAL") -> 565.5 | G15: =F15/C15*1000 -> 0.1188691 | H15: =SUMIFS(Dados_Ambientais!$E$2:$E$486,Dados_Ambientais!$A$2:$A$486,$A15,Dados_Ambientais!$C$2:$C$486,"SCRAP_KG") -> 2288.72 | I15: =H15/C15*1000 -> 0.48109298 | J15: =SUMIFS(Dados_Ambientais!$E$2:$E$486,Dados_Ambientais!$A$2:$A$486,$A15,Dados_Ambientais!$C$2:$C$486,"REGRIND_KG")/H15 -> 0.38429777 | K15: =SUMIFS(Residuos_Mensais!$E$2:$E$265,Residuos_Mensais!$A$2:$A$265,$A15) -> 10265.8 | L15: =SUMIFS(Residuos_Mensais!$E$2:$E$265,Residuos_Mensais!$A$2:$A$265,$A15,Residuos_Mensais!$H$2:$H$265,"Sim")/K15 -> 0.79586588 | M15: =SUMIFS(Residuos_Mensais!$E$2:$E$265,Residuos_Mensais!$A$2:$A$265,$A15,Residuos_Mensais!$D$2:$D$265,"Sim") -> 100.3 | N15: =SUMIFS(Producao_Mensal!$C$2:$C$89,Producao_Mensal!$A$2:$A$89,$A15,Producao_Mensal!$B$2:$B$89,"SER") -> 295268 | O15: =SUMIFS(Dados_Ambientais!$E$2:$E$486,Dados_Ambientais!$A$2:$A$486,$A15,Dados_Ambientais!$C$2:$C$486,"SOLVENTE_KG") -> 47.53 | P15: =O15/N15*1000 -> 0.1609724 | Q15: =D15*INDEX(Parametros!$B$2:$B$25,22)/1000 -> 58.052367
A16: =INDEX(Dim_Mes!$A$2:$A$23,13) -> 46082 | B16: =INDEX(Dim_Mes!$E$2:$E$23,13) -> 13.1 | C16: =SUMIFS(Producao_Mensal!$C$2:$C$89,Producao_Mensal!$A$2:$A$89,$A16,Producao_Mensal!$B$2:$B$89,"INJ")+SUMIFS(Producao_Mensal!$C$2:$C$89,Producao_Mensal!$A$2:$A$89,$A16,Producao_Mensal!$B$2:$B$89,"SOP") -> 5427071 | D16: =SUMIFS(Dados_Ambientais!$E$2:$E$486,Dados_Ambientais!$A$2:$A$486,$A16,Dados_Ambientais!$C$2:$C$486,"ENE_TOTAL") -> 590162.4 | E16: =D16/C16*1000 -> 108.74418 | F16: =SUMIFS(Dados_Ambientais!$E$2:$E$486,Dados_Ambientais!$A$2:$A$486,$A16,Dados_Ambientais!$C$2:$C$486,"AGUA_TOTAL") -> 714.87 | G16: =F16/C16*1000 -> 0.13172299 | H16: =SUMIFS(Dados_Ambientais!$E$2:$E$486,Dados_Ambientais!$A$2:$A$486,$A16,Dados_Ambientais!$C$2:$C$486,"SCRAP_KG") -> 2532.15 | I16: =H16/C16*1000 -> 0.46657764 | J16: =SUMIFS(Dados_Ambientais!$E$2:$E$486,Dados_Ambientais!$A$2:$A$486,$A16,Dados_Ambientais!$C$2:$C$486,"REGRIND_KG")/H16 -> 0.37487906 | K16: =SUMIFS(Residuos_Mensais!$E$2:$E$265,Residuos_Mensais!$A$2:$A$265,$A16) -> 10740.8 | L16: =SUMIFS(Residuos_Mensais!$E$2:$E$265,Residuos_Mensais!$A$2:$A$265,$A16,Residuos_Mensais!$H$2:$H$265,"Sim")/K16 -> 0.80002421 | M16: =SUMIFS(Residuos_Mensais!$E$2:$E$265,Residuos_Mensais!$A$2:$A$265,$A16,Residuos_Mensais!$D$2:$D$265,"Sim") -> 270.5 | N16: =SUMIFS(Producao_Mensal!$C$2:$C$89,Producao_Mensal!$A$2:$A$89,$A16,Producao_Mensal!$B$2:$B$89,"SER") -> 380216 | O16: =SUMIFS(Dados_Ambientais!$E$2:$E$486,Dados_Ambientais!$A$2:$A$486,$A16,Dados_Ambientais!$C$2:$C$486,"SOLVENTE_KG") -> 61.77 | P16: =O16/N16*1000 -> 0.16246029 | Q16: =D16*INDEX(Parametros!$B$2:$B$25,22)/1000 -> 64.917864
A17: =INDEX(Dim_Mes!$A$2:$A$23,14) -> 46113 | B17: =INDEX(Dim_Mes!$E$2:$E$23,14) -> 14.9 | C17: =SUMIFS(Producao_Mensal!$C$2:$C$89,Producao_Mensal!$A$2:$A$89,$A17,Producao_Mensal!$B$2:$B$89,"INJ")+SUMIFS(Producao_Mensal!$C$2:$C$89,Producao_Mensal!$A$2:$A$89,$A17,Producao_Mensal!$B$2:$B$89,"SOP") -> 4961953 | D17: =SUMIFS(Dados_Ambientais!$E$2:$E$486,Dados_Ambientais!$A$2:$A$486,$A17,Dados_Ambientais!$C$2:$C$486,"ENE_TOTAL") -> 554352.38 | E17: =D17/C17*1000 -> 111.7206 | F17: =SUMIFS(Dados_Ambientais!$E$2:$E$486,Dados_Ambientais!$A$2:$A$486,$A17,Dados_Ambientais!$C$2:$C$486,"AGUA_TOTAL") -> 673.72 | G17: =F17/C17*1000 -> 0.13577718 | H17: =SUMIFS(Dados_Ambientais!$E$2:$E$486,Dados_Ambientais!$A$2:$A$486,$A17,Dados_Ambientais!$C$2:$C$486,"SCRAP_KG") -> 2606.86 | I17: =H17/C17*1000 -> 0.52536975 | J17: =SUMIFS(Dados_Ambientais!$E$2:$E$486,Dados_Ambientais!$A$2:$A$486,$A17,Dados_Ambientais!$C$2:$C$486,"REGRIND_KG")/H17 -> 0.39404494 | K17: =SUMIFS(Residuos_Mensais!$E$2:$E$265,Residuos_Mensais!$A$2:$A$265,$A17) -> 10411.6 | L17: =SUMIFS(Residuos_Mensais!$E$2:$E$265,Residuos_Mensais!$A$2:$A$265,$A17,Residuos_Mensais!$H$2:$H$265,"Sim")/K17 -> 0.80604326 | M17: =SUMIFS(Residuos_Mensais!$E$2:$E$265,Residuos_Mensais!$A$2:$A$265,$A17,Residuos_Mensais!$D$2:$D$265,"Sim") -> 140.2 | N17: =SUMIFS(Producao_Mensal!$C$2:$C$89,Producao_Mensal!$A$2:$A$89,$A17,Producao_Mensal!$B$2:$B$89,"SER") -> 361694 | O17: =SUMIFS(Dados_Ambientais!$E$2:$E$486,Dados_Ambientais!$A$2:$A$486,$A17,Dados_Ambientais!$C$2:$C$486,"SOLVENTE_KG") -> 56.87 | P17: =O17/N17*1000 -> 0.15723236 | Q17: =D17*INDEX(Parametros!$B$2:$B$25,22)/1000 -> 60.978762
A18: =INDEX(Dim_Mes!$A$2:$A$23,15) -> 46143 | B18: =INDEX(Dim_Mes!$E$2:$E$23,15) -> 17.6 | C18: =SUMIFS(Producao_Mensal!$C$2:$C$89,Producao_Mensal!$A$2:$A$89,$A18,Producao_Mensal!$B$2:$B$89,"INJ")+SUMIFS(Producao_Mensal!$C$2:$C$89,Producao_Mensal!$A$2:$A$89,$A18,Producao_Mensal!$B$2:$B$89,"SOP") -> 5248065 | D18: =SUMIFS(Dados_Ambientais!$E$2:$E$486,Dados_Ambientais!$A$2:$A$486,$A18,Dados_Ambientais!$C$2:$C$486,"ENE_TOTAL") -> 588371.46 | E18: =D18/C18*1000 -> 112.11208 | F18: =SUMIFS(Dados_Ambientais!$E$2:$E$486,Dados_Ambientais!$A$2:$A$486,$A18,Dados_Ambientais!$C$2:$C$486,"AGUA_TOTAL") -> 800.63 | G18: =F18/C18*1000 -> 0.15255718 | H18: =SUMIFS(Dados_Ambientais!$E$2:$E$486,Dados_Ambientais!$A$2:$A$486,$A18,Dados_Ambientais!$C$2:$C$486,"SCRAP_KG") -> 2596.39 | I18: =H18/C18*1000 -> 0.49473282 | J18: =SUMIFS(Dados_Ambientais!$E$2:$E$486,Dados_Ambientais!$A$2:$A$486,$A18,Dados_Ambientais!$C$2:$C$486,"REGRIND_KG")/H18 -> 0.35669141 | K18: =SUMIFS(Residuos_Mensais!$E$2:$E$265,Residuos_Mensais!$A$2:$A$265,$A18) -> 10838.1 | L18: =SUMIFS(Residuos_Mensais!$E$2:$E$265,Residuos_Mensais!$A$2:$A$265,$A18,Residuos_Mensais!$H$2:$H$265,"Sim")/K18 -> 0.79990958 | M18: =SUMIFS(Residuos_Mensais!$E$2:$E$265,Residuos_Mensais!$A$2:$A$265,$A18,Residuos_Mensais!$D$2:$D$265,"Sim") -> 124.7 | N18: =SUMIFS(Producao_Mensal!$C$2:$C$89,Producao_Mensal!$A$2:$A$89,$A18,Producao_Mensal!$B$2:$B$89,"SER") -> 391966 | O18: =SUMIFS(Dados_Ambientais!$E$2:$E$486,Dados_Ambientais!$A$2:$A$486,$A18,Dados_Ambientais!$C$2:$C$486,"SOLVENTE_KG") -> 61.5 | P18: =O18/N18*1000 -> 0.15690136 | Q18: =D18*INDEX(Parametros!$B$2:$B$25,22)/1000 -> 64.720861
A19: =INDEX(Dim_Mes!$A$2:$A$23,16) -> 46174 | B19: =INDEX(Dim_Mes!$E$2:$E$23,16) -> 21.3 | C19: =SUMIFS(Producao_Mensal!$C$2:$C$89,Producao_Mensal!$A$2:$A$89,$A19,Producao_Mensal!$B$2:$B$89,"INJ")+SUMIFS(Producao_Mensal!$C$2:$C$89,Producao_Mensal!$A$2:$A$89,$A19,Producao_Mensal!$B$2:$B$89,"SOP") -> 5074996 | D19: =SUMIFS(Dados_Ambientais!$E$2:$E$486,Dados_Ambientais!$A$2:$A$486,$A19,Dados_Ambientais!$C$2:$C$486,"ENE_TOTAL") -> 568978.72 | E19: =D19/C19*1000 -> 112.11412 | F19: =SUMIFS(Dados_Ambientais!$E$2:$E$486,Dados_Ambientais!$A$2:$A$486,$A19,Dados_Ambientais!$C$2:$C$486,"AGUA_TOTAL") -> 859.14 | G19: =F19/C19*1000 -> 0.1692888 | H19: =SUMIFS(Dados_Ambientais!$E$2:$E$486,Dados_Ambientais!$A$2:$A$486,$A19,Dados_Ambientais!$C$2:$C$486,"SCRAP_KG") -> 2424.82 | I19: =H19/C19*1000 -> 0.47779742 | J19: =SUMIFS(Dados_Ambientais!$E$2:$E$486,Dados_Ambientais!$A$2:$A$486,$A19,Dados_Ambientais!$C$2:$C$486,"REGRIND_KG")/H19 -> 0.36587458 | K19: =SUMIFS(Residuos_Mensais!$E$2:$E$265,Residuos_Mensais!$A$2:$A$265,$A19) -> 11079.3 | L19: =SUMIFS(Residuos_Mensais!$E$2:$E$265,Residuos_Mensais!$A$2:$A$265,$A19,Residuos_Mensais!$H$2:$H$265,"Sim")/K19 -> 0.8174975 | M19: =SUMIFS(Residuos_Mensais!$E$2:$E$265,Residuos_Mensais!$A$2:$A$265,$A19,Residuos_Mensais!$D$2:$D$265,"Sim") -> 285.7 | N19: =SUMIFS(Producao_Mensal!$C$2:$C$89,Producao_Mensal!$A$2:$A$89,$A19,Producao_Mensal!$B$2:$B$89,"SER") -> 254209 | O19: =SUMIFS(Dados_Ambientais!$E$2:$E$486,Dados_Ambientais!$A$2:$A$486,$A19,Dados_Ambientais!$C$2:$C$486,"SOLVENTE_KG") -> 45.09 | P19: =O19/N19*1000 -> 0.17737374 | Q19: =D19*INDEX(Parametros!$B$2:$B$25,22)/1000 -> 62.587659
A20: =INDEX(Dim_Mes!$A$2:$A$23,17) -> 46204 | B20: =INDEX(Dim_Mes!$E$2:$E$23,17) -> 23.3 | C20: =SUMIFS(Producao_Mensal!$C$2:$C$89,Producao_Mensal!$A$2:$A$89,$A20,Producao_Mensal!$B$2:$B$89,"INJ")+SUMIFS(Producao_Mensal!$C$2:$C$89,Producao_Mensal!$A$2:$A$89,$A20,Producao_Mensal!$B$2:$B$89,"SOP") -> 6806783 | D20: =SUMIFS(Dados_Ambientais!$E$2:$E$486,Dados_Ambientais!$A$2:$A$486,$A20,Dados_Ambientais!$C$2:$C$486,"ENE_TOTAL") -> 727698.42 | E20: =D20/C20*1000 -> 106.90783 | F20: =SUMIFS(Dados_Ambientais!$E$2:$E$486,Dados_Ambientais!$A$2:$A$486,$A20,Dados_Ambientais!$C$2:$C$486,"AGUA_TOTAL") -> 1093.08 | G20: =F20/C20*1000 -> 0.16058687 | H20: =SUMIFS(Dados_Ambientais!$E$2:$E$486,Dados_Ambientais!$A$2:$A$486,$A20,Dados_Ambientais!$C$2:$C$486,"SCRAP_KG") -> 2936.72 | I20: =H20/C20*1000 -> 0.43144023 | J20: =SUMIFS(Dados_Ambientais!$E$2:$E$486,Dados_Ambientais!$A$2:$A$486,$A20,Dados_Ambientais!$C$2:$C$486,"REGRIND_KG")/H20 -> 0.41081887 | K20: =SUMIFS(Residuos_Mensais!$E$2:$E$265,Residuos_Mensais!$A$2:$A$265,$A20) -> 10959.5 | L20: =SUMIFS(Residuos_Mensais!$E$2:$E$265,Residuos_Mensais!$A$2:$A$265,$A20,Residuos_Mensais!$H$2:$H$265,"Sim")/K20 -> 0.78582965 | M20: =SUMIFS(Residuos_Mensais!$E$2:$E$265,Residuos_Mensais!$A$2:$A$265,$A20,Residuos_Mensais!$D$2:$D$265,"Sim") -> 145.4 | N20: =SUMIFS(Producao_Mensal!$C$2:$C$89,Producao_Mensal!$A$2:$A$89,$A20,Producao_Mensal!$B$2:$B$89,"SER") -> 437609 | O20: =SUMIFS(Dados_Ambientais!$E$2:$E$486,Dados_Ambientais!$A$2:$A$486,$A20,Dados_Ambientais!$C$2:$C$486,"SOLVENTE_KG") -> 79.18 | P20: =O20/N20*1000 -> 0.18093778 | Q20: =D20*INDEX(Parametros!$B$2:$B$25,22)/1000 -> 80.046826
A21: =INDEX(Dim_Mes!$A$2:$A$23,18) -> 46235 | B21: =INDEX(Dim_Mes!$E$2:$E$23,18) -> 24 | C21: =SUMIFS(Producao_Mensal!$C$2:$C$89,Producao_Mensal!$A$2:$A$89,$A21,Producao_Mensal!$B$2:$B$89,"INJ")+SUMIFS(Producao_Mensal!$C$2:$C$89,Producao_Mensal!$A$2:$A$89,$A21,Producao_Mensal!$B$2:$B$89,"SOP") -> 7413048 | D21: =SUMIFS(Dados_Ambientais!$E$2:$E$486,Dados_Ambientais!$A$2:$A$486,$A21,Dados_Ambientais!$C$2:$C$486,"ENE_TOTAL") -> 804829.55 | E21: =D21/C21*1000 -> 108.56932 | F21: =SUMIFS(Dados_Ambientais!$E$2:$E$486,Dados_Ambientais!$A$2:$A$486,$A21,Dados_Ambientais!$C$2:$C$486,"AGUA_TOTAL") -> 1223.12 | G21: =F21/C21*1000 -> 0.16499556 | H21: =SUMIFS(Dados_Ambientais!$E$2:$E$486,Dados_Ambientais!$A$2:$A$486,$A21,Dados_Ambientais!$C$2:$C$486,"SCRAP_KG") -> 3110.31 | I21: =H21/C21*1000 -> 0.41957235 | J21: =SUMIFS(Dados_Ambientais!$E$2:$E$486,Dados_Ambientais!$A$2:$A$486,$A21,Dados_Ambientais!$C$2:$C$486,"REGRIND_KG")/H21 -> 0.3772132 | K21: =SUMIFS(Residuos_Mensais!$E$2:$E$265,Residuos_Mensais!$A$2:$A$265,$A21) -> 10700.2 | L21: =SUMIFS(Residuos_Mensais!$E$2:$E$265,Residuos_Mensais!$A$2:$A$265,$A21,Residuos_Mensais!$H$2:$H$265,"Sim")/K21 -> 0.8205641 | M21: =SUMIFS(Residuos_Mensais!$E$2:$E$265,Residuos_Mensais!$A$2:$A$265,$A21,Residuos_Mensais!$D$2:$D$265,"Sim") -> 129 | N21: =SUMIFS(Producao_Mensal!$C$2:$C$89,Producao_Mensal!$A$2:$A$89,$A21,Producao_Mensal!$B$2:$B$89,"SER") -> 441790 | O21: =SUMIFS(Dados_Ambientais!$E$2:$E$486,Dados_Ambientais!$A$2:$A$486,$A21,Dados_Ambientais!$C$2:$C$486,"SOLVENTE_KG") -> 84.06 | P21: =O21/N21*1000 -> 0.1902714 | Q21: =D21*INDEX(Parametros!$B$2:$B$25,22)/1000 -> 88.531251
A22: =INDEX(Dim_Mes!$A$2:$A$23,19) -> 46266 | B22: =INDEX(Dim_Mes!$E$2:$E$23,19) -> 21.6 | C22: =SUMIFS(Producao_Mensal!$C$2:$C$89,Producao_Mensal!$A$2:$A$89,$A22,Producao_Mensal!$B$2:$B$89,"INJ")+SUMIFS(Producao_Mensal!$C$2:$C$89,Producao_Mensal!$A$2:$A$89,$A22,Producao_Mensal!$B$2:$B$89,"SOP") -> 6946568 | D22: =SUMIFS(Dados_Ambientais!$E$2:$E$486,Dados_Ambientais!$A$2:$A$486,$A22,Dados_Ambientais!$C$2:$C$486,"ENE_TOTAL") -> 736636.48 | E22: =D22/C22*1000 -> 106.04323 | F22: =SUMIFS(Dados_Ambientais!$E$2:$E$486,Dados_Ambientais!$A$2:$A$486,$A22,Dados_Ambientais!$C$2:$C$486,"AGUA_TOTAL") -> 1106.72 | G22: =F22/C22*1000 -> 0.15931896 | H22: =SUMIFS(Dados_Ambientais!$E$2:$E$486,Dados_Ambientais!$A$2:$A$486,$A22,Dados_Ambientais!$C$2:$C$486,"SCRAP_KG") -> 3284.11 | I22: =H22/C22*1000 -> 0.47276727 | J22: =SUMIFS(Dados_Ambientais!$E$2:$E$486,Dados_Ambientais!$A$2:$A$486,$A22,Dados_Ambientais!$C$2:$C$486,"REGRIND_KG")/H22 -> 0.37959752 | K22: =SUMIFS(Residuos_Mensais!$E$2:$E$265,Residuos_Mensais!$A$2:$A$265,$A22) -> 11339.5 | L22: =SUMIFS(Residuos_Mensais!$E$2:$E$265,Residuos_Mensais!$A$2:$A$265,$A22,Residuos_Mensais!$H$2:$H$265,"Sim")/K22 -> 0.81045901 | M22: =SUMIFS(Residuos_Mensais!$E$2:$E$265,Residuos_Mensais!$A$2:$A$265,$A22,Residuos_Mensais!$D$2:$D$265,"Sim") -> 275.9 | N22: =SUMIFS(Producao_Mensal!$C$2:$C$89,Producao_Mensal!$A$2:$A$89,$A22,Producao_Mensal!$B$2:$B$89,"SER") -> 462346 | O22: =SUMIFS(Dados_Ambientais!$E$2:$E$486,Dados_Ambientais!$A$2:$A$486,$A22,Dados_Ambientais!$C$2:$C$486,"SOLVENTE_KG") -> 78.78 | P22: =O22/N22*1000 -> 0.17039187 | Q22: =D22*INDEX(Parametros!$B$2:$B$25,22)/1000 -> 81.030013
A23: =INDEX(Dim_Mes!$A$2:$A$23,20) -> 46296 | B23: =INDEX(Dim_Mes!$E$2:$E$23,20) -> 18.2 | C23: =SUMIFS(Producao_Mensal!$C$2:$C$89,Producao_Mensal!$A$2:$A$89,$A23,Producao_Mensal!$B$2:$B$89,"INJ")+SUMIFS(Producao_Mensal!$C$2:$C$89,Producao_Mensal!$A$2:$A$89,$A23,Producao_Mensal!$B$2:$B$89,"SOP") -> 7420393 | D23: =SUMIFS(Dados_Ambientais!$E$2:$E$486,Dados_Ambientais!$A$2:$A$486,$A23,Dados_Ambientais!$C$2:$C$486,"ENE_TOTAL") -> 741702.88 | E23: =D23/C23*1000 -> 99.954663 | F23: =SUMIFS(Dados_Ambientais!$E$2:$E$486,Dados_Ambientais!$A$2:$A$486,$A23,Dados_Ambientais!$C$2:$C$486,"AGUA_TOTAL") -> 1031.27 | G23: =F23/C23*1000 -> 0.13897781 | H23: =SUMIFS(Dados_Ambientais!$E$2:$E$486,Dados_Ambientais!$A$2:$A$486,$A23,Dados_Ambientais!$C$2:$C$486,"SCRAP_KG") -> 3249.23 | I23: =H23/C23*1000 -> 0.43787843 | J23: =SUMIFS(Dados_Ambientais!$E$2:$E$486,Dados_Ambientais!$A$2:$A$486,$A23,Dados_Ambientais!$C$2:$C$486,"REGRIND_KG")/H23 -> 0.39628466 | K23: =SUMIFS(Residuos_Mensais!$E$2:$E$265,Residuos_Mensais!$A$2:$A$265,$A23) -> 11420.1 | L23: =SUMIFS(Residuos_Mensais!$E$2:$E$265,Residuos_Mensais!$A$2:$A$265,$A23,Residuos_Mensais!$H$2:$H$265,"Sim")/K23 -> 0.77579005 | M23: =SUMIFS(Residuos_Mensais!$E$2:$E$265,Residuos_Mensais!$A$2:$A$265,$A23,Residuos_Mensais!$D$2:$D$265,"Sim") -> 149.9 | N23: =SUMIFS(Producao_Mensal!$C$2:$C$89,Producao_Mensal!$A$2:$A$89,$A23,Producao_Mensal!$B$2:$B$89,"SER") -> 461147 | O23: =SUMIFS(Dados_Ambientais!$E$2:$E$486,Dados_Ambientais!$A$2:$A$486,$A23,Dados_Ambientais!$C$2:$C$486,"SOLVENTE_KG") -> 76.71 | P23: =O23/N23*1000 -> 0.16634609 | Q23: =D23*INDEX(Parametros!$B$2:$B$25,22)/1000 -> 81.587317
A24: =INDEX(Dim_Mes!$A$2:$A$23,21) -> 46327 | B24: =INDEX(Dim_Mes!$E$2:$E$23,21) -> 13.8 | C24: =SUMIFS(Producao_Mensal!$C$2:$C$89,Producao_Mensal!$A$2:$A$89,$A24,Producao_Mensal!$B$2:$B$89,"INJ")+SUMIFS(Producao_Mensal!$C$2:$C$89,Producao_Mensal!$A$2:$A$89,$A24,Producao_Mensal!$B$2:$B$89,"SOP") -> 6825788 | D24: =SUMIFS(Dados_Ambientais!$E$2:$E$486,Dados_Ambientais!$A$2:$A$486,$A24,Dados_Ambientais!$C$2:$C$486,"ENE_TOTAL") -> 697660.72 | E24: =D24/C24*1000 -> 102.20955 | F24: =SUMIFS(Dados_Ambientais!$E$2:$E$486,Dados_Ambientais!$A$2:$A$486,$A24,Dados_Ambientais!$C$2:$C$486,"AGUA_TOTAL") -> 820.48 | G24: =F24/C24*1000 -> 0.12020297 | H24: =SUMIFS(Dados_Ambientais!$E$2:$E$486,Dados_Ambientais!$A$2:$A$486,$A24,Dados_Ambientais!$C$2:$C$486,"SCRAP_KG") -> 3116.49 | I24: =H24/C24*1000 -> 0.45657586 | J24: =SUMIFS(Dados_Ambientais!$E$2:$E$486,Dados_Ambientais!$A$2:$A$486,$A24,Dados_Ambientais!$C$2:$C$486,"REGRIND_KG")/H24 -> 0.38212861 | K24: =SUMIFS(Residuos_Mensais!$E$2:$E$265,Residuos_Mensais!$A$2:$A$265,$A24) -> 10823.1 | L24: =SUMIFS(Residuos_Mensais!$E$2:$E$265,Residuos_Mensais!$A$2:$A$265,$A24,Residuos_Mensais!$H$2:$H$265,"Sim")/K24 -> 0.80463084 | M24: =SUMIFS(Residuos_Mensais!$E$2:$E$265,Residuos_Mensais!$A$2:$A$265,$A24,Residuos_Mensais!$D$2:$D$265,"Sim") -> 117 | N24: =SUMIFS(Producao_Mensal!$C$2:$C$89,Producao_Mensal!$A$2:$A$89,$A24,Producao_Mensal!$B$2:$B$89,"SER") -> 383074 | O24: =SUMIFS(Dados_Ambientais!$E$2:$E$486,Dados_Ambientais!$A$2:$A$486,$A24,Dados_Ambientais!$C$2:$C$486,"SOLVENTE_KG") -> 62.82 | P24: =O24/N24*1000 -> 0.1639892 | Q24: =D24*INDEX(Parametros!$B$2:$B$25,22)/1000 -> 76.742679
A25: =INDEX(Dim_Mes!$A$2:$A$23,22) -> 46357 | B25: =INDEX(Dim_Mes!$E$2:$E$23,22) -> 11.1 | C25: =SUMIFS(Producao_Mensal!$C$2:$C$89,Producao_Mensal!$A$2:$A$89,$A25,Producao_Mensal!$B$2:$B$89,"INJ")+SUMIFS(Producao_Mensal!$C$2:$C$89,Producao_Mensal!$A$2:$A$89,$A25,Producao_Mensal!$B$2:$B$89,"SOP") -> 6914348 | D25: =SUMIFS(Dados_Ambientais!$E$2:$E$486,Dados_Ambientais!$A$2:$A$486,$A25,Dados_Ambientais!$C$2:$C$486,"ENE_TOTAL") -> 675973.18 | E25: =D25/C25*1000 -> 97.763835 | F25: =SUMIFS(Dados_Ambientais!$E$2:$E$486,Dados_Ambientais!$A$2:$A$486,$A25,Dados_Ambientais!$C$2:$C$486,"AGUA_TOTAL") -> 701.33 | G25: =F25/C25*1000 -> 0.10143111 | H25: =SUMIFS(Dados_Ambientais!$E$2:$E$486,Dados_Ambientais!$A$2:$A$486,$A25,Dados_Ambientais!$C$2:$C$486,"SCRAP_KG") -> 3032.67 | I25: =H25/C25*1000 -> 0.43860535 | J25: =SUMIFS(Dados_Ambientais!$E$2:$E$486,Dados_Ambientais!$A$2:$A$486,$A25,Dados_Ambientais!$C$2:$C$486,"REGRIND_KG")/H25 -> 0.37972809 | K25: =SUMIFS(Residuos_Mensais!$E$2:$E$265,Residuos_Mensais!$A$2:$A$265,$A25) -> 10504.7 | L25: =SUMIFS(Residuos_Mensais!$E$2:$E$265,Residuos_Mensais!$A$2:$A$265,$A25,Residuos_Mensais!$H$2:$H$265,"Sim")/K25 -> 0.8254686 | M25: =SUMIFS(Residuos_Mensais!$E$2:$E$265,Residuos_Mensais!$A$2:$A$265,$A25,Residuos_Mensais!$D$2:$D$265,"Sim") -> 304.2 | N25: =SUMIFS(Producao_Mensal!$C$2:$C$89,Producao_Mensal!$A$2:$A$89,$A25,Producao_Mensal!$B$2:$B$89,"SER") -> 359103 | O25: =SUMIFS(Dados_Ambientais!$E$2:$E$486,Dados_Ambientais!$A$2:$A$486,$A25,Dados_Ambientais!$C$2:$C$486,"SOLVENTE_KG") -> 57.56 | P25: =O25/N25*1000 -> 0.16028827 | Q25: =D25*INDEX(Parametros!$B$2:$B$25,22)/1000 -> 74.35705

Sheet Analise_Desvio_5_2
A1: ATIVIDADE 5.2 — ANÁLISE DE DESVIO: SOLVENTE DE LIMPEZA NA SERIGRAFIA (KPI-06)
A3: Indicador crítico escolhido: KPI-06 — kg de solvente de limpeza por 1.000 peças serigrafadas (aspeto AA-014, AAS de COV; objetivo OBJ-03).
A5: Média do KPI-06 — jun–ago/2026 (últimos 3 meses) | B5: =AVERAGE(Indicadores_Mensais!P19:P21) -> 0.18286097
A6: Média do KPI-06 — mar–mai/2026 (3 meses anteriores) | B6: =AVERAGE(Indicadores_Mensais!P16:P18) -> 0.15886467
A7: Variação do indicador (últimos 3 vs anteriores) | B7: =B5/B6-1 -> 0.1510487
A8: Peças serigrafadas — jun–ago/2026 | B8: =SUM(Indicadores_Mensais!N19:N21) -> 1133608
A9: Peças serigrafadas — mar–mai/2026 | B9: =SUM(Indicadores_Mensais!N16:N18) -> 1133876
A10: Variação da produção | B10: =B8/B9-1 -> -0.00023635741
A11: Média do KPI-06 — jun–ago/2025 (mesma estação do ano anterior) | B11: =AVERAGE(Indicadores_Mensais!P7:P9) -> 0.15613788
A12: Variação face ao mesmo período de 2025 | B12: =B5/B11-1 -> 0.17115056
A13: Solvente em excesso no período (kg) | B13: =SUM(Indicadores_Mensais!O19:O21)-B6*B8/1000 -> 28.239741
A14: Média do KPI-06 — out–dez/2026 (após PAM-26-07 e PAM-26-08) | B14: =AVERAGE(Indicadores_Mensais!P23:P25) -> 0.16354119
A15: Variação out–dez/2026 face a mar–mai/2026 (antes do desvio) | B15: =B14/B6-1 -> 0.02943713
A16: Leitura automática | B16: =IF(AND(B7>=0.1,ABS(B10)<0.05),"DESVIO REAL: o indicador subiu "&FIXED(B7*100,1)&"% com a produção estável ("&FIXED(B10*100,2)&"%) → investigar causas operacionais/técnicas.",IF(B7>=0.1,"Subida acompanhada de variação de produção: normalizar antes de concluir.","Sem desvio relevante.")) -> DESVIO REAL: o indicador subiu 15,1% com a produção estável (-0,02%) → investigar causas operacionais/técnicas.
A18: Cenário (enunciado) | B18: Os dados de mar/2025 a ago/2026 (18 meses) mostraram que o consumo específico de solvente de limpeza na serigrafia subiu cerca de 15% em jun–ago/2026 face aos 3 meses anteriores, com a produção de peças serigrafadas estável. A Gestão de Topo pediu justificação e soluções. A investigação (PAM-26-07) testou 7 hipóteses: 3 confirmadas, 1 parcial e 3 descartadas (folha Hipoteses_Desvio).
A20: Ações imediatas
B21: • PAM-26-07 (C1): pesagem diária por máquina e turno, fechar e identificar todos os recipientes, observar a limpeza nos 3 turnos, reconciliar o inventário.
B22: • PAM-26-08 (C2): dispensadores de segurança, norma de limpeza, afinação da rasqueta da SS-001 e formação dos operadores (incl. temporários).
B23: • PAM-26-13 (M, decisão da Revisão pela Gestão): unidade de recuperação de solvente.
B24: • COM-03: toolbox com os operadores para partilhar o desvio e recolher as causas prováveis.

Sheet Hipoteses_Desvio
A1: ID_Hipotese | B1: Categoria_6M | C1: Hipotese | D1: Como_Verificar | E1: Evidencia_Obtida | F1: Estado | G1: ID_PAM
A2: H1 | B2: Método | C2: Latas e recipientes de solvente deixados abertos no posto (evaporação). | D2: Rondas RON-01 de jun–ago; observação nos 3 turnos. | E2: RON-01 não conforme em 45% das rondas de jun–ago/2026 (vs 12% no resto do ano). | F2: Confirmada | G2: PAM-26-08
A3: H2 | B3: Máquina | C3: Após o overhaul da SS-001 (jul/2026) a nova rasqueta/tela obriga a mais limpezas. | D3: Pesagem diária do solvente por máquina (8–22/09). | E3: SS-001 consome ≈ 30% mais solvente por 1.000 peças do que a SS-002 (ver Pesagem_Solvente). | F3: Confirmada | G3: PAM-26-08
A4: H3 | B4: Mão de obra | C4: Operador temporário no turno 2 sem formação na IT de limpeza. | D4: Matriz de competências; pesagem por turno. | E4: Operador OP-SK-T01 sem FOR-02 (NC-SGA-26-08); turno 2 com o maior consumo por 1.000 peças. | F4: Confirmada | G4: PAM-26-08
A5: H4 | B5: Material | C5: Novo lote/tinta de secagem mais rápida exige mais limpezas. | D5: Lotes e fornecedor da tinta; consumo de tinta por 1.000 peças. | E5: Mesmo fornecedor e referência desde abril; consumo de tinta por 1.000 peças estável (±3%). | F5: Descartada
A6: H5 | B6: Medição | C6: Erro de inventário (compra de junho lançada em duplicado). | D6: Reconciliação faturas × entradas × stock físico. | E6: Reconciliação sem diferenças. | F6: Descartada
A7: H6 | B7: Meio ambiente | C7: Calor de verão aumenta a evaporação do solvente. | D7: Comparar jun–ago/2026 com jun–ago/2025 (mesma estação). | E7: Temperatura +1,6 °C face a 2025; efeito estimado 3-4% — não explica +15%. A subida também existe face ao verão de 2025. | F7: Parcial
A8: H7 | B8: Método | C8: Mais mudanças de cor (mix com mais cores) → mais limpezas. | D8: N.º de ordens e de cores por ordem na serigrafia (dataset). | E8: N.º de ordens e de cores por peça estável em jun–ago. | F8: Descartada

Sheet Pesagem_Solvente
A1: Data | B1: Maquina | C1: Turno | D1: Pecas_Serigrafadas | E1: Solvente_kg | F1: kg_por_1000 | I1: Resumo (kg por 1.000 peças)
A2: 46273 | B2: SS-001 | C2: 1 | D2: 5787 | E2: 1.206 | F2: =E2/D2*1000 -> 0.20839813 | J2: Turno 1 | K2: Turno 2 | L2: Turno 3 | M2: Total
A3: 46273 | B3: SS-001 | C3: 2 | D3: 6168 | E3: 1.486 | F3: =E3/D3*1000 -> 0.24092088 | I3: SS-001 | J3: =SUMIFS($E$2:$E$475,$B$2:$B$475,"SS-001",$C$2:$C$475,1)/SUMIFS($D$2:$D$475,$B$2:$B$475,"SS-001",$C$2:$C$475,1)*1000 -> 0.18722413 | K3: =SUMIFS($E$2:$E$475,$B$2:$B$475,"SS-001",$C$2:$C$475,2)/SUMIFS($D$2:$D$475,$B$2:$B$475,"SS-001",$C$2:$C$475,2)*1000 -> 0.2137986 | L3: =SUMIFS($E$2:$E$475,$B$2:$B$475,"SS-001",$C$2:$C$475,3)/SUMIFS($D$2:$D$475,$B$2:$B$475,"SS-001",$C$2:$C$475,3)*1000 -> 0.18417437 | M3: =SUMIFS($E$2:$E$475,$B$2:$B$475,"SS-001")/SUMIFS($D$2:$D$475,$B$2:$B$475,"SS-001")*1000 -> 0.19511979
A4: 46273 | B4: SS-001 | C4: 3 | D4: 6361 | E4: 1.359 | F4: =E4/D4*1000 -> 0.21364565 | I4: SS-002 | J4: =SUMIFS($E$2:$E$475,$B$2:$B$475,"SS-002",$C$2:$C$475,1)/SUMIFS($D$2:$D$475,$B$2:$B$475,"SS-002",$C$2:$C$475,1)*1000 -> 0.14567651 | K4: =SUMIFS($E$2:$E$475,$B$2:$B$475,"SS-002",$C$2:$C$475,2)/SUMIFS($D$2:$D$475,$B$2:$B$475,"SS-002",$C$2:$C$475,2)*1000 -> 0.16336446 | L4: =SUMIFS($E$2:$E$475,$B$2:$B$475,"SS-002",$C$2:$C$475,3)/SUMIFS($D$2:$D$475,$B$2:$B$475,"SS-002",$C$2:$C$475,3)*1000 -> 0.14549916 | M4: =SUMIFS($E$2:$E$475,$B$2:$B$475,"SS-002")/SUMIFS($D$2:$D$475,$B$2:$B$475,"SS-002")*1000 -> 0.1514987
A5: 46273 | B5: SS-002 | C5: 1 | D5: 6294 | E5: 1.005 | F5: =E5/D5*1000 -> 0.15967588
A6: 46273 | B6: SS-002 | C6: 2 | D6: 5631 | E6: 1.086 | F6: =E6/D6*1000 -> 0.19286095
A7: 46273 | B7: SS-002 | C7: 3 | D7: 6037 | E7: 1.011 | F7: =E7/D7*1000 -> 0.16746729
A8: 46274 | B8: SS-001 | C8: 1 | D8: 6856 | E8: 1.27 | F8: =E8/D8*1000 -> 0.18523921
A9: 46274 | B9: SS-001 | C9: 2 | D9: 6864 | E9: 1.596 | F9: =E9/D9*1000 -> 0.23251748
A10: 46274 | B10: SS-001 | C10: 3 | D10: 5681 | E10: 1.151 | F10: =E10/D10*1000 -> 0.20260518
A11: 46274 | B11: SS-002 | C11: 1 | D11: 6349 | E11: 1.064 | F11: =E11/D11*1000 -> 0.16758545
A12: 46274 | B12: SS-002 | C12: 2 | D12: 7611 | E12: 1.294 | F12: =E12/D12*1000 -> 0.17001708
A13: 46274 | B13: SS-002 | C13: 3 | D13: 6016 | E13: 0.972 | F13: =E13/D13*1000 -> 0.16156915
A14: 46275 | B14: SS-001 | C14: 1 | D14: 5933 | E14: 1.093 | F14: =E14/D14*1000 -> 0.18422383
A15: 46275 | B15: SS-001 | C15: 2 | D15: 6086 | E15: 1.473 | F15: =E15/D15*1000 -> 0.24203089
A16: 46275 | B16: SS-001 | C16: 3 | D16: 6396 | E16: 1.283 | F16: =E16/D16*1000 -> 0.20059412
... A475: 46387 | B475: SS-002 | C475: 3 | D475: 6679 | E475: 0.939 | F475: =E475/D475*1000 -> 0.14058991

Sheet Analises_Laboratoriais
A1: RESULTADOS DE MONITORIZAÇÃO — ENSAIOS E MEDIÇÕES vs. LIMITES
A2: Formato longo (1 linha = 1 parâmetro) · Limites indicativos a confirmar na autorização de descarga, RGR e DL 39/2018 · Medições internas não substituem ensaios acreditados
A4: ID_Analise | B4: Data | C4: Matriz | D4: Ponto_Amostragem | E4: Parametro | F4: Valor | G4: Unidade | H4: Limite_Min | I4: Limite_Max | J4: Tipo_Limite | K4: Laboratorio | L4: Acreditado | M4: N_Relatorio | N4: ID_Legal | O4: Pct_do_Limite | P4: Conformidade
A5: AN-001 | B5: 45006 | C5: Emissões — chaminé FP1 | D5: Chaminé FP1 (estufa de cura) | E5: COVT | F5: 27 | G5: mg C/Nm³ | I5: 200 | J5: VLE legal | K5: Laboratório acreditado (IPAC L0xxx) | L5: Sim | M5: 2023/03-EF | N5: LEG-12 | O5: =IF(OR(F5="",I5=""),"",F5/I5) -> 0.135 | P5: =IF(F5="","",IF(OR(AND(H5<>"",F5<H5),F5>I5),"Não conforme","Conforme")) -> Conforme
A6: AN-002 | B6: 45006 | C6: Emissões — chaminé FP1 | D6: Chaminé FP1 (estufa de cura) | E6: Caudal mássico COVT | F6: 0.05 | G6: kg C/h | I6: 2 | J6: Limiar legal de ação | K6: Laboratório acreditado (IPAC L0xxx) | L6: Sim | M6: 2023/03-EF | N6: LEG-12 | O6: =IF(OR(F6="",I6=""),"",F6/I6) -> 0.025 | P6: =IF(F6="","",IF(OR(AND(H6<>"",F6<H6),F6>I6),"Não conforme","Conforme")) -> Conforme
A7: AN-003 | B7: 45183 | C7: Ruído ambiente | D7: Recetor R1 (habitação a sul, 250 m) | E7: Ln (recetor R1) | F7: 47 | G7: dB(A) | I7: 55 | J7: VLE legal | K7: Laboratório acreditado (IPAC L0xxx) | L7: Sim | M7: AC-2023-041 | N7: LEG-05 | O7: =IF(OR(F7="",I7=""),"",F7/I7) -> 0.85454545 | P7: =IF(F7="","",IF(OR(AND(H7<>"",F7<H7),F7>I7),"Não conforme","Conforme")) -> Conforme
A8: AN-004 | B8: 45183 | C8: Ruído ambiente | D8: Recetor R1 (habitação a sul, 250 m) | E8: Incomodidade noturna ΔLA (R1) | F8: 2 | G8: dB(A) | I8: 3 | J8: VLE legal | K8: Laboratório acreditado (IPAC L0xxx) | L8: Sim | M8: AC-2023-041 | N8: LEG-05 | O8: =IF(OR(F8="",I8=""),"",F8/I8) -> 0.66666667 | P8: =IF(F8="","",IF(OR(AND(H8<>"",F8<H8),F8>I8),"Não conforme","Conforme")) -> Conforme
A9: AN-005 | B9: 45728 | C9: Água da torre | D9: Bacia da torre TR-01 | E9: Legionella spp. | F9: 50 | G9: UFC/L | I9: 1000 | J9: Limiar legal de ação | K9: Laboratório acreditado (IPAC L0xxx) | L9: Sim | M9: L25-0311 | N9: LEG-15 | O9: =IF(OR(F9="",I9=""),"",F9/I9) -> 0.05 | P9: =IF(F9="","",IF(OR(AND(H9<>"",F9<H9),F9>I9),"Não conforme","Conforme")) -> Conforme
A10: AN-006 | B10: 45818 | C10: Água da torre | D10: Bacia da torre TR-01 | E10: Legionella spp. | F10: 100 | G10: UFC/L | I10: 1000 | J10: Limiar legal de ação | K10: Laboratório acreditado (IPAC L0xxx) | L10: Sim | M10: L25-0610 | N10: LEG-15 | O10: =IF(OR(F10="",I10=""),"",F10/I10) -> 0.1 | P10: =IF(F10="","",IF(OR(AND(H10<>"",F10<H10),F10>I10),"Não conforme","Conforme")) -> Conforme
A11: AN-007 | B11: 45819 | C11: Efluente (coletor municipal) | D11: Caixa de visita final | E11: pH | F11: 7.6 | G11: Escala Sørensen | H11: 5.5 | I11: 9.5 | J11: VLE legal | K11: Laboratório acreditado (IPAC L0xxx) | L11: Sim | M11: 25/1033 | N11: LEG-03 | O11: =IF(OR(F11="",I11=""),"",F11/I11) -> 0.8 | P11: =IF(F11="","",IF(OR(AND(H11<>"",F11<H11),F11>I11),"Não conforme","Conforme")) -> Conforme
A12: AN-008 | B12: 45819 | C12: Efluente (coletor municipal) | D12: Caixa de visita final | E12: CQO | F12: 162 | G12: mg/L O2 | I12: 1000 | J12: VLE legal | K12: Laboratório acreditado (IPAC L0xxx) | L12: Sim | M12: 25/1033 | N12: LEG-03 | O12: =IF(OR(F12="",I12=""),"",F12/I12) -> 0.162 | P12: =IF(F12="","",IF(OR(AND(H12<>"",F12<H12),F12>I12),"Não conforme","Conforme")) -> Conforme
A13: AN-009 | B13: 45819 | C13: Efluente (coletor municipal) | D13: Caixa de visita final | E13: SST | F13: 44 | G13: mg/L | I13: 1000 | J13: VLE legal | K13: Laboratório acreditado (IPAC L0xxx) | L13: Sim | M13: 25/1033 | N13: LEG-03 | O13: =IF(OR(F13="",I13=""),"",F13/I13) -> 0.044 | P13: =IF(F13="","",IF(OR(AND(H13<>"",F13<H13),F13>I13),"Não conforme","Conforme")) -> Conforme
A14: AN-010 | B14: 45819 | C14: Efluente (coletor municipal) | D14: Caixa de visita final | E14: CBO5 | F14: 61 | G14: mg/L O2 | I14: 500 | J14: VLE legal | K14: Laboratório acreditado (IPAC L0xxx) | L14: Sim | M14: 25/1033 | N14: LEG-03 | O14: =IF(OR(F14="",I14=""),"",F14/I14) -> 0.122 | P14: =IF(F14="","",IF(OR(AND(H14<>"",F14<H14),F14>I14),"Não conforme","Conforme")) -> Conforme
A15: AN-011 | B15: 45819 | C15: Efluente (coletor municipal) | D15: Caixa de visita final | E15: Óleos e gorduras | F15: 12 | G15: mg/L | I15: 100 | J15: VLE legal | K15: Laboratório acreditado (IPAC L0xxx) | L15: Sim | M15: 25/1033 | N15: LEG-03 | O15: =IF(OR(F15="",I15=""),"",F15/I15) -> 0.12 | P15: =IF(F15="","",IF(OR(AND(H15<>"",F15<H15),F15>I15),"Não conforme","Conforme")) -> Conforme
A16: AN-012 | B16: 45882 | C16: Efluente (coletor municipal) | D16: Caixa de visita final | E16: Isotiazolinonas (biocida) | F16: 2.8 | G16: mg/L | I16: 1 | J16: Valor de referência interno | K16: Laboratório acreditado (IPAC L0xxx) | L16: Sim | M16: 25/1520 | N16: LEG-03 | O16: =IF(OR(F16="",I16=""),"",F16/I16) -> 2.8 | P16: =IF(F16="","",IF(OR(AND(H16<>"",F16<H16),F16>I16),"Não conforme","Conforme")) -> Não conforme
A17: AN-013 | B17: 45883 | C17: Água da torre | D17: Bacia da torre TR-01 | E17: Legionella spp. | F17: 1200 | G17: UFC/L | I17: 1000 | J17: Limiar legal de ação | K17: Laboratório acreditado (IPAC L0xxx) | L17: Sim | M17: L25-0814 | N17: LEG-15 | O17: =IF(OR(F17="",I17=""),"",F17/I17) -> 1.2 | P17: =IF(F17="","",IF(OR(AND(H17<>"",F17<H17),F17>I17),"Não conforme","Conforme")) -> Não conforme
A18: AN-014 | B18: 45909 | C18: Água da torre | D18: Bacia da torre TR-01 | E18: Legionella spp. | F18: 50 | G18: UFC/L | I18: 1000 | J18: Limiar legal de ação | K18: Laboratório acreditado (IPAC L0xxx) | L18: Sim | M18: L25-0909 | N18: LEG-15 | O18: =IF(OR(F18="",I18=""),"",F18/I18) -> 0.05 | P18: =IF(F18="","",IF(OR(AND(H18<>"",F18<H18),F18>I18),"Não conforme","Conforme")) -> Conforme
A19: AN-015 | B19: 45981 | C19: Águas pluviais | D19: Caixa de saída pluvial (portão sul) | E19: SST | F19: 48 | G19: mg/L | I19: 60 | J19: Valor de referência interno | K19: Laboratório acreditado (IPAC L0xxx) | L19: Sim | M19: 25/2101 | N19: LEG-03 | O19: =IF(OR(F19="",I19=""),"",F19/I19) -> 0.8 | P19: =IF(F19="","",IF(OR(AND(H19<>"",F19<H19),F19>I19),"Não conforme","Conforme")) -> Conforme
A20: AN-016 | B20: 45981 | C20: Águas pluviais | D20: Caixa de saída pluvial (portão sul) | E20: Hidrocarbonetos totais | F20: 0.6 | G20: mg/L | I20: 10 | J20: Valor de referência interno | K20: Laboratório acreditado (IPAC L0xxx) | L20: Sim | M20: 25/2101 | N20: LEG-03 | O20: =IF(OR(F20="",I20=""),"",F20/I20) -> 0.06 | P20: =IF(F20="","",IF(OR(AND(H20<>"",F20<H20),F20>I20),"Não conforme","Conforme")) -> Conforme
A21: AN-017 | B21: 46001 | C21: Efluente (coletor municipal) | D21: Caixa de visita final | E21: pH | F21: 7.9 | G21: Escala Sørensen | H21: 5.5 | I21: 9.5 | J21: VLE legal | K21: Laboratório acreditado (IPAC L0xxx) | L21: Sim | M21: 25/2210 | N21: LEG-03 | O21: =IF(OR(F21="",I21=""),"",F21/I21) -> 0.83157895 | P21: =IF(F21="","",IF(OR(AND(H21<>"",F21<H21),F21>I21),"Não conforme","Conforme")) -> Conforme
A22: AN-018 | B22: 46001 | C22: Efluente (coletor municipal) | D22: Caixa de visita final | E22: CQO | F22: 131 | G22: mg/L O2 | I22: 1000 | J22: VLE legal | K22: Laboratório acreditado (IPAC L0xxx) | L22: Sim | M22: 25/2210 | N22: LEG-03 | O22: =IF(OR(F22="",I22=""),"",F22/I22) -> 0.131 | P22: =IF(F22="","",IF(OR(AND(H22<>"",F22<H22),F22>I22),"Não conforme","Conforme")) -> Conforme
A23: AN-019 | B23: 46001 | C23: Efluente (coletor municipal) | D23: Caixa de visita final | E23: SST | F23: 35 | G23: mg/L | I23: 1000 | J23: VLE legal | K23: Laboratório acreditado (IPAC L0xxx) | L23: Sim | M23: 25/2210 | N23: LEG-03 | O23: =IF(OR(F23="",I23=""),"",F23/I23) -> 0.035 | P23: =IF(F23="","",IF(OR(AND(H23<>"",F23<H23),F23>I23),"Não conforme","Conforme")) -> Conforme
A24: AN-020 | B24: 46001 | C24: Efluente (coletor municipal) | D24: Caixa de visita final | E24: CBO5 | F24: 48 | G24: mg/L O2 | I24: 500 | J24: VLE legal | K24: Laboratório acreditado (IPAC L0xxx) | L24: Sim | M24: 25/2210 | N24: LEG-03 | O24: =IF(OR(F24="",I24=""),"",F24/I24) -> 0.096 | P24: =IF(F24="","",IF(OR(AND(H24<>"",F24<H24),F24>I24),"Não conforme","Conforme")) -> Conforme
A25: AN-021 | B25: 46001 | C25: Efluente (coletor municipal) | D25: Caixa de visita final | E25: Óleos e gorduras | F25: 9 | G25: mg/L | I25: 100 | J25: VLE legal | K25: Laboratório acreditado (IPAC L0xxx) | L25: Sim | M25: 25/2210 | N25: LEG-03 | O25: =IF(OR(F25="",I25=""),"",F25/I25) -> 0.09 | P25: =IF(F25="","",IF(OR(AND(H25<>"",F25<H25),F25>I25),"Não conforme","Conforme")) -> Conforme
A26: AN-022 | B26: 46001 | C26: Água da torre | D26: Bacia da torre TR-01 | E26: Legionella spp. | F26: 50 | G26: UFC/L | I26: 1000 | J26: Limiar legal de ação | K26: Laboratório acreditado (IPAC L0xxx) | L26: Sim | M26: L25-1210 | N26: LEG-15 | O26: =IF(OR(F26="",I26=""),"",F26/I26) -> 0.05 | P26: =IF(F26="","",IF(OR(AND(H26<>"",F26<H26),F26>I26),"Não conforme","Conforme")) -> Conforme
A27: AN-023 | B27: 46092 | C27: Água da torre | D27: Bacia da torre TR-01 | E27: Legionella spp. | F27: 100 | G27: UFC/L | I27: 1000 | J27: Limiar legal de ação | K27: Laboratório acreditado (IPAC L0xxx) | L27: Sim | M27: L26-0311 | N27: LEG-15 | O27: =IF(OR(F27="",I27=""),"",F27/I27) -> 0.1 | P27: =IF(F27="","",IF(OR(AND(H27<>"",F27<H27),F27>I27),"Não conforme","Conforme")) -> Conforme
A28: AN-024 | B28: 46099 | C28: Emissões — chaminé FP1 | D28: Chaminé FP1 (estufa de cura) | E28: COVT | F28: 22 | G28: mg C/Nm³ | I28: 200 | J28: VLE legal | K28: Laboratório acreditado (IPAC L0xxx) | L28: Sim | M28: 2026/03-EF | N28: LEG-12 | O28: =IF(OR(F28="",I28=""),"",F28/I28) -> 0.11 | P28: =IF(F28="","",IF(OR(AND(H28<>"",F28<H28),F28>I28),"Não conforme","Conforme")) -> Conforme
A29: AN-025 | B29: 46099 | C29: Emissões — chaminé FP1 | D29: Chaminé FP1 (estufa de cura) | E29: Caudal mássico COVT | F29: 0.04 | G29: kg C/h | I29: 2 | J29: Limiar legal de ação | K29: Laboratório acreditado (IPAC L0xxx) | L29: Sim | M29: 2026/03-EF | N29: LEG-12 | O29: =IF(OR(F29="",I29=""),"",F29/I29) -> 0.02 | P29: =IF(F29="","",IF(OR(AND(H29<>"",F29<H29),F29>I29),"Não conforme","Conforme")) -> Conforme
A30: AN-026 | B30: 46134 | C30: Águas pluviais | D30: Caixa de saída pluvial (portão sul) | E30: SST | F30: 31 | G30: mg/L | I30: 60 | J30: Valor de referência interno | K30: Laboratório acreditado (IPAC L0xxx) | L30: Sim | M30: 26/0907 | N30: LEG-03 | O30: =IF(OR(F30="",I30=""),"",F30/I30) -> 0.51666667 | P30: =IF(F30="","",IF(OR(AND(H30<>"",F30<H30),F30>I30),"Não conforme","Conforme")) -> Conforme
A31: AN-027 | B31: 46134 | C31: Águas pluviais | D31: Caixa de saída pluvial (portão sul) | E31: Hidrocarbonetos totais | F31: 0.4 | G31: mg/L | I31: 10 | J31: Valor de referência interno | K31: Laboratório acreditado (IPAC L0xxx) | L31: Sim | M31: 26/0907 | N31: LEG-03 | O31: =IF(OR(F31="",I31=""),"",F31/I31) -> 0.04 | P31: =IF(F31="","",IF(OR(AND(H31<>"",F31<H31),F31>I31),"Não conforme","Conforme")) -> Conforme
A32: AN-028 | B32: 46182 | C32: Água da torre | D32: Bacia da torre TR-01 | E32: Legionella spp. | F32: 150 | G32: UFC/L | I32: 1000 | J32: Limiar legal de ação | K32: Laboratório acreditado (IPAC L0xxx) | L32: Sim | M32: L26-0609 | N32: LEG-15 | O32: =IF(OR(F32="",I32=""),"",F32/I32) -> 0.15 | P32: =IF(F32="","",IF(OR(AND(H32<>"",F32<H32),F32>I32),"Não conforme","Conforme")) -> Conforme
A33: AN-029 | B33: 46185 | C33: Efluente (coletor municipal) | D33: Caixa de visita final | E33: pH | F33: 7.8 | G33: Escala Sørensen | H33: 5.5 | I33: 9.5 | J33: VLE legal | K33: Laboratório acreditado (IPAC L0xxx) | L33: Sim | M33: 26/1187 | N33: LEG-03 | O33: =IF(OR(F33="",I33=""),"",F33/I33) -> 0.82105263 | P33: =IF(F33="","",IF(OR(AND(H33<>"",F33<H33),F33>I33),"Não conforme","Conforme")) -> Conforme
A34: AN-030 | B34: 46185 | C34: Efluente (coletor municipal) | D34: Caixa de visita final | E34: CQO | F34: 145 | G34: mg/L O2 | I34: 1000 | J34: VLE legal | K34: Laboratório acreditado (IPAC L0xxx) | L34: Sim | M34: 26/1187 | N34: LEG-03 | O34: =IF(OR(F34="",I34=""),"",F34/I34) -> 0.145 | P34: =IF(F34="","",IF(OR(AND(H34<>"",F34<H34),F34>I34),"Não conforme","Conforme")) -> Conforme
A35: AN-031 | B35: 46185 | C35: Efluente (coletor municipal) | D35: Caixa de visita final | E35: SST | F35: 38 | G35: mg/L | I35: 1000 | J35: VLE legal | K35: Laboratório acreditado (IPAC L0xxx) | L35: Sim | M35: 26/1187 | N35: LEG-03 | O35: =IF(OR(F35="",I35=""),"",F35/I35) -> 0.038 | P35: =IF(F35="","",IF(OR(AND(H35<>"",F35<H35),F35>I35),"Não conforme","Conforme")) -> Conforme
A36: AN-032 | B36: 46185 | C36: Efluente (coletor municipal) | D36: Caixa de visita final | E36: CBO5 | F36: 55 | G36: mg/L O2 | I36: 500 | J36: VLE legal | K36: Laboratório acreditado (IPAC L0xxx) | L36: Sim | M36: 26/1187 | N36: LEG-03 | O36: =IF(OR(F36="",I36=""),"",F36/I36) -> 0.11 | P36: =IF(F36="","",IF(OR(AND(H36<>"",F36<H36),F36>I36),"Não conforme","Conforme")) -> Conforme
A37: AN-033 | B37: 46185 | C37: Efluente (coletor municipal) | D37: Caixa de visita final | E37: Óleos e gorduras | F37: 10 | G37: mg/L | I37: 100 | J37: VLE legal | K37: Laboratório acreditado (IPAC L0xxx) | L37: Sim | M37: 26/1187 | N37: LEG-03 | O37: =IF(OR(F37="",I37=""),"",F37/I37) -> 0.1 | P37: =IF(F37="","",IF(OR(AND(H37<>"",F37<H37),F37>I37),"Não conforme","Conforme")) -> Conforme
A38: AN-034 | B38: 46213 | C38: Ruído ambiente | D38: Recetor R1 (habitação a sul, 250 m) | E38: Ln (recetor R1) | F38: 51 | G38: dB(A) | I38: 55 | J38: Valor de referência interno | K38: Medição interna (sonómetro classe 2) | L38: Não | M38: MI-2026-07 | N38: LEG-05 | O38: =IF(OR(F38="",I38=""),"",F38/I38) -> 0.92727273 | P38: =IF(F38="","",IF(OR(AND(H38<>"",F38<H38),F38>I38),"Não conforme","Conforme")) -> Conforme
A39: AN-035 | B39: 46213 | C39: Ruído ambiente | D39: Recetor R1 (habitação a sul, 250 m) | E39: Incomodidade noturna ΔLA (R1) | F39: 5 | G39: dB(A) | I39: 3 | J39: Valor de referência interno | K39: Medição interna (sonómetro classe 2) | L39: Não | M39: MI-2026-07 | N39: LEG-05 | O39: =IF(OR(F39="",I39=""),"",F39/I39) -> 1.6666667 | P39: =IF(F39="","",IF(OR(AND(H39<>"",F39<H39),F39>I39),"Não conforme","Conforme")) -> Não conforme
A40: AN-036 | B40: 46273 | C40: Água da torre | D40: Bacia da torre TR-01 | E40: Legionella spp. | F40: 100 | G40: UFC/L | I40: 1000 | J40: Limiar legal de ação | K40: Laboratório acreditado (IPAC L0xxx) | L40: Sim | M40: L26-0908 | N40: LEG-15 | O40: =IF(OR(F40="",I40=""),"",F40/I40) -> 0.1 | P40: =IF(F40="","",IF(OR(AND(H40<>"",F40<H40),F40>I40),"Não conforme","Conforme")) -> Conforme
A41: AN-037 | B41: 46323 | C41: Ruído ambiente | D41: Recetor R1 (habitação a sul, 250 m) | E41: Ln (recetor R1) | F41: 48 | G41: dB(A) | I41: 55 | J41: VLE legal | K41: Laboratório acreditado (IPAC L0xxx) | L41: Sim | M41: AC-2026-112 | N41: LEG-05 | O41: =IF(OR(F41="",I41=""),"",F41/I41) -> 0.87272727 | P41: =IF(F41="","",IF(OR(AND(H41<>"",F41<H41),F41>I41),"Não conforme","Conforme")) -> Conforme
A42: AN-038 | B42: 46323 | C42: Ruído ambiente | D42: Recetor R1 (habitação a sul, 250 m) | E42: Incomodidade noturna ΔLA (R1) | F42: 2 | G42: dB(A) | I42: 3 | J42: VLE legal | K42: Laboratório acreditado (IPAC L0xxx) | L42: Sim | M42: AC-2026-112 | N42: LEG-05 | O42: =IF(OR(F42="",I42=""),"",F42/I42) -> 0.66666667 | P42: =IF(F42="","",IF(OR(AND(H42<>"",F42<H42),F42>I42),"Não conforme","Conforme")) -> Conforme
A43: AN-039 | B43: 46345 | C43: Águas pluviais | D43: Caixa de saída pluvial (portão sul) | E43: SST | F43: 29 | G43: mg/L | I43: 60 | J43: Valor de referência interno | K43: Laboratório acreditado (IPAC L0xxx) | L43: Sim | M43: 26/2288 | N43: LEG-03 | O43: =IF(OR(F43="",I43=""),"",F43/I43) -> 0.48333333 | P43: =IF(F43="","",IF(OR(AND(H43<>"",F43<H43),F43>I43),"Não conforme","Conforme")) -> Conforme
A44: AN-040 | B44: 46345 | C44: Águas pluviais | D44: Caixa de saída pluvial (portão sul) | E44: Hidrocarbonetos totais | F44: 0.3 | G44: mg/L | I44: 10 | J44: Valor de referência interno | K44: Laboratório acreditado (IPAC L0xxx) | L44: Sim | M44: 26/2288 | N44: LEG-03 | O44: =IF(OR(F44="",I44=""),"",F44/I44) -> 0.03 | P44: =IF(F44="","",IF(OR(AND(H44<>"",F44<H44),F44>I44),"Não conforme","Conforme")) -> Conforme
A45: AN-041 | B45: 46363 | C45: Água da torre | D45: Bacia da torre TR-01 | E45: Legionella spp. | F45: 50 | G45: UFC/L | I45: 1000 | J45: Limiar legal de ação | K45: Laboratório acreditado (IPAC L0xxx) | L45: Sim | M45: L26-1207 | N45: LEG-15 | O45: =IF(OR(F45="",I45=""),"",F45/I45) -> 0.05 | P45: =IF(F45="","",IF(OR(AND(H45<>"",F45<H45),F45>I45),"Não conforme","Conforme")) -> Conforme
A46: AN-042 | B46: 46366 | C46: Efluente (coletor municipal) | D46: Caixa de visita final | E46: pH | F46: 7.6 | G46: Escala Sørensen | H46: 5.5 | I46: 9.5 | J46: VLE legal | K46: Laboratório acreditado (IPAC L0xxx) | L46: Sim | M46: 26/2410 | N46: LEG-03 | O46: =IF(OR(F46="",I46=""),"",F46/I46) -> 0.8 | P46: =IF(F46="","",IF(OR(AND(H46<>"",F46<H46),F46>I46),"Não conforme","Conforme")) -> Conforme
A47: AN-043 | B47: 46366 | C47: Efluente (coletor municipal) | D47: Caixa de visita final | E47: CQO | F47: 132 | G47: mg/L O2 | I47: 1000 | J47: VLE legal | K47: Laboratório acreditado (IPAC L0xxx) | L47: Sim | M47: 26/2410 | N47: LEG-03 | O47: =IF(OR(F47="",I47=""),"",F47/I47) -> 0.132 | P47: =IF(F47="","",IF(OR(AND(H47<>"",F47<H47),F47>I47),"Não conforme","Conforme")) -> Conforme
A48: AN-044 | B48: 46366 | C48: Efluente (coletor municipal) | D48: Caixa de visita final | E48: SST | F48: 31 | G48: mg/L | I48: 1000 | J48: VLE legal | K48: Laboratório acreditado (IPAC L0xxx) | L48: Sim | M48: 26/2410 | N48: LEG-03 | O48: =IF(OR(F48="",I48=""),"",F48/I48) -> 0.031 | P48: =IF(F48="","",IF(OR(AND(H48<>"",F48<H48),F48>I48),"Não conforme","Conforme")) -> Conforme
A49: AN-045 | B49: 46366 | C49: Efluente (coletor municipal) | D49: Caixa de visita final | E49: CBO5 | F49: 45 | G49: mg/L O2 | I49: 500 | J49: VLE legal | K49: Laboratório acreditado (IPAC L0xxx) | L49: Sim | M49: 26/2410 | N49: LEG-03 | O49: =IF(OR(F49="",I49=""),"",F49/I49) -> 0.09 | P49: =IF(F49="","",IF(OR(AND(H49<>"",F49<H49),F49>I49),"Não conforme","Conforme")) -> Conforme
A50: AN-046 | B50: 46366 | C50: Efluente (coletor municipal) | D50: Caixa de visita final | E50: Óleos e gorduras | F50: 8 | G50: mg/L | I50: 100 | J50: VLE legal | K50: Laboratório acreditado (IPAC L0xxx) | L50: Sim | M50: 26/2410 | N50: LEG-03 | O50: =IF(OR(F50="",I50=""),"",F50/I50) -> 0.08 | P50: =IF(F50="","",IF(OR(AND(H50<>"",F50<H50),F50>I50),"Não conforme","Conforme")) -> Conforme
O51: =IF(OR(F51="",I51=""),"",F51/I51) | P51: =IF(F51="","",IF(OR(AND(H51<>"",F51<H51),F51>I51),"Não conforme","Conforme"))
O52: =IF(OR(F52="",I52=""),"",F52/I52) | P52: =IF(F52="","",IF(OR(AND(H52<>"",F52<H52),F52>I52),"Não conforme","Conforme"))
O53: =IF(OR(F53="",I53=""),"",F53/I53) | P53: =IF(F53="","",IF(OR(AND(H53<>"",F53<H53),F53>I53),"Não conforme","Conforme"))
O54: =IF(OR(F54="",I54=""),"",F54/I54) | P54: =IF(F54="","",IF(OR(AND(H54<>"",F54<H54),F54>I54),"Não conforme","Conforme"))
O55: =IF(OR(F55="",I55=""),"",F55/I55) | P55: =IF(F55="","",IF(OR(AND(H55<>"",F55<H55),F55>I55),"Não conforme","Conforme"))
O56: =IF(OR(F56="",I56=""),"",F56/I56) | P56: =IF(F56="","",IF(OR(AND(H56<>"",F56<H56),F56>I56),"Não conforme","Conforme"))
O57: =IF(OR(F57="",I57=""),"",F57/I57) | P57: =IF(F57="","",IF(OR(AND(H57<>"",F57<H57),F57>I57),"Não conforme","Conforme"))
O58: =IF(OR(F58="",I58=""),"",F58/I58) | P58: =IF(F58="","",IF(OR(AND(H58<>"",F58<H58),F58>I58),"Não conforme","Conforme"))
O59: =IF(OR(F59="",I59=""),"",F59/I59) | P59: =IF(F59="","",IF(OR(AND(H59<>"",F59<H59),F59>I59),"Não conforme","Conforme"))
O60: =IF(OR(F60="",I60=""),"",F60/I60) | P60: =IF(F60="","",IF(OR(AND(H60<>"",F60<H60),F60>I60),"Não conforme","Conforme"))
O61: =IF(OR(F61="",I61=""),"",F61/I61) | P61: =IF(F61="","",IF(OR(AND(H61<>"",F61<H61),F61>I61),"Não conforme","Conforme"))
O62: =IF(OR(F62="",I62=""),"",F62/I62) | P62: =IF(F62="","",IF(OR(AND(H62<>"",F62<H62),F62>I62),"Não conforme","Conforme"))
... O110: =IF(OR(F110="",I110=""),"",F110/I110) | P110: =IF(F110="","",IF(OR(AND(H110<>"",F110<H110),F110>I110),"Não conforme","Conforme"))

Sheet Listas
A1: LISTAS CONTROLADAS (domínios de validação de dados) — editar aqui para alterar opções
A2: DataReferencia | B2: Tipo | C2: Funcao | D2: EstadoHip | E2: Cat6M | F2: Processo | G2: Qualidade | H2: AN_Matriz | I2: AN_Limite | J2: AN_SimNao
A3: 46387 | B3: Medir | C3: Diretor Geral (Gestão de Topo) | D3: Confirmada | E3: Método | F3: REC | G3: Medido | H3: Efluente (coletor municipal) | I3: VLE legal | J3: Sim
B4: Monitorizar | C4: Diretor Industrial | D4: Parcial | E4: Máquina | F4: ARQ | G4: Estimado | H4: Água da torre | I4: Limiar legal de ação | J4: Não
C5: Gestor do SGA / EHS (Responsável Ambiental) | D5: Descartada | E5: Material | F5: INJ | G5: Calculado | H5: Águas pluviais | I5: Valor de referência interno
C6: Gerente de Produção | D6: Em verificação | E6: Mão de obra | F6: SOP | H6: Ruído ambiente
C7: Gerente de Manutenção | E7: Medição | F7: SER | H7: Emissões — chaminé FP1
C8: Gerente da Qualidade | E8: Meio ambiente | F8: HFS
C9: Responsável de Armazém e Logística | F9: MOA
C10: Responsável de Compras | F10: UTL
C11: Responsável de R&D | F11: MAN
C12: Responsável de Recursos Humanos | F12: PRS
C13: Diretor Financeiro | F13: EXP
C14: Operador de Serigrafia | F14: LAB
C15: Operador de Injeção | F15: RD
C16: Operador de Sopro (ISBM) | F16: CMP
C17: Operador de Hot Foil | F17: ADM
C18: Técnico de Manutenção | F18: GER
C19: Técnico de Utilidades | F19: UTL-AR
C20: Operador de Armazém / Empilhador | F20: UTL-FRIO
C21: Chefe de Turno
C22: Auditor Interno do SGA
C23: Representante dos Trabalhadores (SST/Ambiente)
C24: Técnico de Qualidade/Ambiente

Sheet Dicionario_Dados
A1: Folha | B1: Tabela | C1: Coluna | D1: Tipo | E1: Origem | F1: Descricao | G1: Dominio_Unidade | H1: Obrigatorio | I1: Chave
A2: Plano_Monitorizacao | B2: tbl_plano_monitorizacao | C2: ID_MED | D2: Texto | E2: Entrada | F2: Parâmetro monitorizado. | H2: Sim | I2: PK
A3: Plano_Monitorizacao | B3: tbl_plano_monitorizacao | C3: O_Que_Medir | D3: Texto | E3: Entrada | F3: O quê medir (indicador exato). | H3: Sim
A4: Plano_Monitorizacao | B4: tbl_plano_monitorizacao | C4: Unidade | D4: Texto | E4: Entrada | F4: Unidade. | H4: Sim
A5: Plano_Monitorizacao | B5: tbl_plano_monitorizacao | C5: Tipo | D5: Texto | E5: Entrada | F5: Medir (valor quantitativo) ou Monitorizar (verificação de estado). | G5: Lista lst_Tipo | H5: Sim
A6: Plano_Monitorizacao | B6: tbl_plano_monitorizacao | C6: Como_Medir | D6: Texto | E6: Entrada | F6: Método/equipamento. | H6: Sim
A7: Plano_Monitorizacao | B7: tbl_plano_monitorizacao | C7: Equipamentos | D7: Texto | E7: Entrada | F7: Equipamentos usados. | H7: Sim | I7: FK → tbl_equipamentos
A8: Plano_Monitorizacao | B8: tbl_plano_monitorizacao | C8: Quando_Medir | D8: Texto | E8: Entrada | F8: Frequência. | H8: Sim
A9: Plano_Monitorizacao | B9: tbl_plano_monitorizacao | C9: Quem_Mede | D9: Texto | E9: Entrada | F9: Responsável pela recolha. | G9: Lista lst_Funcao | H9: Sim
A10: Plano_Monitorizacao | B10: tbl_plano_monitorizacao | C10: ID_KPI | D10: Texto | E10: Entrada | F10: KPI alimentado. | H10: Sim | I10: FK → RG-SGA-05
A11: Plano_Monitorizacao | B11: tbl_plano_monitorizacao | C11: Criterio_Meta | D11: Texto | E11: Entrada | F11: Critério/meta. | H11: Sim
A12: Plano_Monitorizacao | B12: tbl_plano_monitorizacao | C12: IDs_Aspetos | D12: Texto | E12: Entrada | F12: Aspetos ambientais monitorizados. | H12: Sim | I12: FK → RG-SGA-03
A13: Plano_Monitorizacao | B13: tbl_plano_monitorizacao | C13: Estado_Equipamentos | D13: Texto | E13: Calculado (fórmula) | F13: Alerta se algum equipamento associado não está válido. | H13: Sim
A14: Equipamentos_Calibracao | B14: tbl_equipamentos | C14: ID_Equipamento | D14: Texto | E14: Entrada | F14: Equipamento. | H14: Sim | I14: PK
A15: Equipamentos_Calibracao | B15: tbl_equipamentos | C15: Equipamento | D15: Texto | E15: Entrada | F15: Descrição. | H15: Sim
A16: Equipamentos_Calibracao | B16: tbl_equipamentos | C16: IDs_MED | D16: Texto | E16: Entrada | F16: Parâmetros em que é usado. | H16: Sim
A17: Equipamentos_Calibracao | B17: tbl_equipamentos | C17: Tipo_Controlo | D17: Texto | E17: Entrada | F17: Calibração ou verificação. | H17: Sim
A18: Equipamentos_Calibracao | B18: tbl_equipamentos | C18: Ultima_Calibracao | D18: Data (aaaa-mm-dd) | E18: Entrada | F18: Data da última calibração/verificação. | H18: Não
A19: Equipamentos_Calibracao | B19: tbl_equipamentos | C19: Periodicidade_Meses | D19: Inteiro | E19: Entrada | F19: Periodicidade. | H19: Sim
A20: Equipamentos_Calibracao | B20: tbl_equipamentos | C20: Entidade | D20: Texto | E20: Entrada | F20: Quem calibra/verifica. | H20: Sim
A21: Equipamentos_Calibracao | B21: tbl_equipamentos | C21: Evidencia | D21: Texto | E21: Entrada | F21: Certificado/registo. | H21: Sim
A22: Equipamentos_Calibracao | B22: tbl_equipamentos | C22: Proxima_Calibracao | D22: Data (aaaa-mm-dd) | E22: Calculado (fórmula) | F22: Data da próxima. | H22: Sim
A23: Equipamentos_Calibracao | B23: tbl_equipamentos | C23: Estado | D23: Texto | E23: Calculado (fórmula) | F23: Estado calculado. | H23: Sim
A24: Parametros | B24: tbl_parametros | C24: Codigo | D24: Texto | E24: Entrada | F24: Parâmetro. | H24: Sim | I24: PK
A25: Parametros | B25: tbl_parametros | C25: Valor | D25: Decimal | E25: Entrada | F25: Valor. | H25: Sim
A26: Parametros | B26: tbl_parametros | C26: Unidade | D26: Texto | E26: Entrada | F26: Unidade. | H26: Sim
A27: Parametros | B27: tbl_parametros | C27: Descricao | D27: Texto | E27: Entrada | F27: Descrição e origem. | H27: Sim
A28: Dim_Mes | B28: tbl_meses | C28: Mes | D28: Data (aaaa-mm-dd) | E28: Entrada | F28: Mês (1.º dia). | H28: Sim | I28: PK
A29: Dim_Mes | B29: tbl_meses | C29: Ano | D29: Inteiro | E29: Entrada | F29: Ano. | H29: Sim
A30: Dim_Mes | B30: tbl_meses | C30: Mes_Num | D30: Inteiro | E30: Entrada | F30: Mês (1-12). | H30: Sim
A31: Dim_Mes | B31: tbl_meses | C31: Trimestre | D31: Texto | E31: Entrada | F31: Trimestre. | H31: Sim
A32: Dim_Mes | B32: tbl_meses | C32: Temp_Media_C | D32: Decimal | E32: Entrada | F32: Temperatura média exterior (°C) — variável explicativa (KPI-16). | H32: Sim
A33: Dim_Mes | B33: tbl_meses | C33: Dias_Uteis | D33: Inteiro | E33: Entrada | F33: Dias úteis. | H33: Sim
A34: Dim_Mes | B34: tbl_meses | C34: Periodo_Dataset | D34: Texto | E34: Entrada | F34: Origem dos dados de produção. | H34: Sim
A35: Dim_Mes | B35: tbl_meses | C35: Fatura_Eletricidade | D35: Texto | E35: Entrada | F35: N.º da fatura de eletricidade do mês. | H35: Sim
A36: Dim_Mes | B36: tbl_meses | C36: Energia_kWh | D36: Decimal | E36: Calculado (fórmula) | F36: Eletricidade faturada (ENE_TOTAL de tbl_dados_ambientais). | H36: Sim
A37: Dim_Mes | B37: tbl_meses | C37: Preco_Eletricidade_EUR_kWh | D37: Decimal | E37: Entrada | F37: Preço médio (energia + redes + impostos, sem IVA) — simulado; validar com a fatura. | H37: Sim
A38: Dim_Mes | B38: tbl_meses | C38: Potencia_Contratada_kW | D38: Decimal | E38: Entrada | F38: Potência contratada. | H38: Sim
A39: Dim_Mes | B39: tbl_meses | C39: Custo_Eletricidade_EUR | D39: Moeda (EUR) | E39: Calculado (fórmula) | F39: Custo da eletricidade. | H39: Sim
A40: Dim_Mes | B40: tbl_meses | C40: Fatura_Agua | D40: Texto | E40: Entrada | F40: N.º da fatura de água do mês. | H40: Sim
... A48: Dim_Mes | B48: tbl_meses | C48: Agua_Descarregada_m3 | D48: Decimal | E48: Calculado (fórmula) | F48: Descarga no coletor (sanitária + purga) = captação − consumo — GRI 303-4. | H48: Sim
A49: Producao_Mensal | B49: tbl_producao_mensal | C49: Mes | D49: Data (aaaa-mm-dd) | E49: Entrada | F49: Mês. | H49: Sim | I49: PK (com Processo)
A50: Producao_Mensal | B50: tbl_producao_mensal | C50: Processo | D50: Texto | E50: Entrada | F50: Processo. | G50: Lista lst_Processo | H50: Sim
A51: Producao_Mensal | B51: tbl_producao_mensal | C51: Unid | D51: Decimal | E51: Entrada | F51: Unidades produzidas. | H51: Sim
A52: Producao_Mensal | B52: tbl_producao_mensal | C52: Rej | D52: Decimal | E52: Entrada | F52: Unidades rejeitadas. | H52: Sim
A53: Producao_Mensal | B53: tbl_producao_mensal | C53: Horas | D53: Decimal | E53: Entrada | F53: Horas de marcha (soma das máquinas). | H53: Sim
A54: Producao_Mensal | B54: tbl_producao_mensal | C54: Setups | D54: Decimal | E54: Entrada | F54: Mudanças de molde. | H54: Sim
A55: Producao_Mensal | B55: tbl_producao_mensal | C55: Taxa_Rejeicao | D55: Percentagem (fração 0-1) | E55: Calculado (fórmula) | F55: Rejeitadas ÷ produzidas. | H55: Sim
A56: Producao_Mensal | B56: tbl_producao_mensal | C56: Fonte | D56: Texto | E56: Entrada | F56: Origem. | H56: Sim
A57: Dados_Ambientais | B57: tbl_dados_ambientais | C57: Mes | D57: Data (aaaa-mm-dd) | E57: Entrada | F57: Mês. | H57: Sim | I57: PK (com Processo, Variavel)
A58: Dados_Ambientais | B58: tbl_dados_ambientais | C58: Processo | D58: Texto | E58: Entrada | F58: Processo/uso. | G58: Lista lst_Processo | H58: Sim
A59: Dados_Ambientais | B59: tbl_dados_ambientais | C59: Variavel | D59: Texto | E59: Entrada | F59: Código da variável (ENE_TOTAL, ENE_PROC, AGUA_TOTAL, AGUA_USO, SCRAP_KG, REGRIND_KG, POLIMERO_KG, PCR_KG, TINTA_KG, SOLVENTE_KG, FOIL_KG, GRANULADO_KG, FGAS_KG). | H59: Sim
A60: Dados_Ambientais | B60: tbl_dados_ambientais | C60: Descricao | D60: Texto | E60: Entrada | F60: Descrição. | H60: Sim
A61: Dados_Ambientais | B61: tbl_dados_ambientais | C61: Valor | D61: Decimal | E61: Entrada | F61: Valor. | H61: Sim
A62: Dados_Ambientais | B62: tbl_dados_ambientais | C62: Unidade | D62: Texto | E62: Entrada | F62: Unidade. | H62: Sim
A63: Dados_Ambientais | B63: tbl_dados_ambientais | C63: Fonte | D63: Texto | E63: Entrada | F63: Fonte do dado. | H63: Sim
A64: Dados_Ambientais | B64: tbl_dados_ambientais | C64: Qualidade_Dado | D64: Texto | E64: Entrada | F64: Medido / Estimado / Calculado. | G64: Lista lst_Qualidade | H64: Sim
A65: Residuos_Mensais | B65: tbl_residuos | C65: Mes | D65: Data (aaaa-mm-dd) | E65: Entrada | F65: Mês. | H65: Sim
A66: Residuos_Mensais | B66: tbl_residuos | C66: Codigo_LER | D66: Texto | E66: Entrada | F66: Código LER (* = perigoso). | H66: Sim
A67: Residuos_Mensais | B67: tbl_residuos | C67: Descricao | D67: Texto | E67: Entrada | F67: Descrição. | H67: Sim
A68: Residuos_Mensais | B68: tbl_residuos | C68: Perigoso | D68: Texto | E68: Entrada | F68: Sim/Não. | H68: Sim
A69: Residuos_Mensais | B69: tbl_residuos | C69: Quantidade_kg | D69: Decimal | E69: Entrada | F69: Quantidade (kg). | H69: Sim
A70: Residuos_Mensais | B70: tbl_residuos | C70: Operacao_Destino | D70: Texto | E70: Entrada | F70: Operação R/D. | H70: Sim
A71: Residuos_Mensais | B71: tbl_residuos | C71: Operador | D71: Texto | E71: Entrada | F71: Operador de gestão de resíduos. | H71: Sim
A72: Residuos_Mensais | B72: tbl_residuos | C72: Valorizado | D72: Texto | E72: Calculado (fórmula) | F72: Destino de valorização (operação R). | H72: Sim
A73: Hipoteses_Desvio | B73: tbl_hipoteses | C73: ID_Hipotese | D73: Texto | E73: Entrada | F73: Hipótese. | H73: Sim | I73: PK
A74: Hipoteses_Desvio | B74: tbl_hipoteses | C74: Categoria_6M | D74: Texto | E74: Entrada | F74: Categoria Ishikawa. | G74: Lista lst_Cat6M | H74: Sim
A75: Hipoteses_Desvio | B75: tbl_hipoteses | C75: Hipotese | D75: Texto | E75: Entrada | F75: Causa provável. | H75: Sim
A76: Hipoteses_Desvio | B76: tbl_hipoteses | C76: Como_Verificar | D76: Texto | E76: Entrada | F76: Teste/dado usado para verificar. | H76: Sim
A77: Hipoteses_Desvio | B77: tbl_hipoteses | C77: Evidencia_Obtida | D77: Texto | E77: Entrada | F77: Resultado da verificação. | H77: Sim
A78: Hipoteses_Desvio | B78: tbl_hipoteses | C78: Estado | D78: Texto | E78: Entrada | F78: Confirmada / Parcial / Descartada. | G78: Lista lst_EstadoHip | H78: Sim
A79: Hipoteses_Desvio | B79: tbl_hipoteses | C79: ID_PAM | D79: Texto | E79: Entrada | F79: Ação. | H79: Não | I79: FK → RG-SGA-06
A80: Pesagem_Solvente | B80: tbl_pesagem_solvente | C80: Data | D80: Data (aaaa-mm-dd) | E80: Entrada | F80: Dia. | H80: Sim
A81: Pesagem_Solvente | B81: tbl_pesagem_solvente | C81: Maquina | D81: Texto | E81: Entrada | F81: Máquina (SS-001/SS-002). | H81: Sim
A82: Pesagem_Solvente | B82: tbl_pesagem_solvente | C82: Turno | D82: Inteiro | E82: Entrada | F82: Turno. | H82: Sim
A83: Pesagem_Solvente | B83: tbl_pesagem_solvente | C83: Pecas_Serigrafadas | D83: Decimal | E83: Entrada | F83: Peças. | H83: Sim
A84: Pesagem_Solvente | B84: tbl_pesagem_solvente | C84: Solvente_kg | D84: Decimal | E84: Entrada | F84: Solvente pesado (kg). | H84: Sim
A85: Pesagem_Solvente | B85: tbl_pesagem_solvente | C85: kg_por_1000 | D85: Decimal | E85: Calculado (fórmula) | F85: kg por 1.000 peças. | H85: Sim
A86: Analises_Laboratoriais | B86: tbl_analises | C86: ID_Analise | D86: Texto | E86: Entrada | F86: Identificador do resultado. | H86: Sim | I86: PK
A87: Analises_Laboratoriais | B87: tbl_analises | C87: Data | D87: Data (aaaa-mm-dd) | E87: Entrada | F87: Data da colheita/medição. | H87: Sim
A88: Analises_Laboratoriais | B88: tbl_analises | C88: Matriz | D88: Texto | E88: Entrada | F88: Matriz ambiental. | G88: Lista lst_AN_Matriz | H88: Sim
A89: Analises_Laboratoriais | B89: tbl_analises | C89: Ponto_Amostragem | D89: Texto | E89: Entrada | F89: Ponto de amostragem / recetor. | H89: Sim
A90: Analises_Laboratoriais | B90: tbl_analises | C90: Parametro | D90: Texto | E90: Entrada | F90: Parâmetro. | H90: Sim
A91: Analises_Laboratoriais | B91: tbl_analises | C91: Valor | D91: Decimal | E91: Entrada | F91: Resultado. | H91: Sim
A92: Analises_Laboratoriais | B92: tbl_analises | C92: Unidade | D92: Texto | E92: Entrada | F92: Unidade. | H92: Sim
A93: Analises_Laboratoriais | B93: tbl_analises | C93: Limite_Min | D93: Decimal | E93: Entrada | F93: Limite inferior (ex.: pH). | H93: Não
A94: Analises_Laboratoriais | B94: tbl_analises | C94: Limite_Max | D94: Decimal | E94: Entrada | F94: Limite superior (VLE ou referência). | H94: Sim
A95: Analises_Laboratoriais | B95: tbl_analises | C95: Tipo_Limite | D95: Texto | E95: Entrada | F95: Origem do limite (confirmar valores na licença/regulamento aplicável). | G95: Lista lst_AN_Limite | H95: Sim
A96: Analises_Laboratoriais | B96: tbl_analises | C96: Laboratorio | D96: Texto | E96: Entrada | F96: Laboratório ou medição interna. | H96: Sim
A97: Analises_Laboratoriais | B97: tbl_analises | C97: Acreditado | D97: Texto | E97: Entrada | F97: Ensaio acreditado (ISO/IEC 17025). | G97: Lista lst_AN_SimNao | H97: Sim
A98: Analises_Laboratoriais | B98: tbl_analises | C98: N_Relatorio | D98: Texto | E98: Entrada | F98: N.º do relatório/boletim. | H98: Sim
A99: Analises_Laboratoriais | B99: tbl_analises | C99: ID_Legal | D99: Texto | E99: Entrada | F99: Requisito legal. | H99: Sim | I99: FK → tbl_legal (RG-SGA-04)
A100: Analises_Laboratoriais | B100: tbl_analises | C100: Pct_do_Limite | D100: Percentagem (fração 0-1) | E100: Calculado (fórmula) | F100: Resultado em % do limite superior. | H100: Sim
A101: Analises_Laboratoriais | B101: tbl_analises | C101: Conformidade | D101: Texto | E101: Calculado (fórmula) | F101: Automático. | H101: Sim
